Workbook
Name __DdeLink__2326_2541265958: 'Двери Kapelli'!#REF!
Name __DdeLink__294_2844460511: 'Двери Kapelli'!#REF!
Name __DdeLink__960_1832848366: 'Двери Kapelli'!#REF!
Name Print_Area: 'Дерев. гл. двери в проем'!$A$1:$H$44
Name Print_Area: 'Дерев. гл. скр. двери в проем'!$A$1:$H$51

Sheet Смета ЕР (общ) 
F1: Формат объекта | H1: ККО | P1: курс $ | Q1: 85.25
F2: дверной | G2: Адрес объекта: | H2: заполняется конкретный адрес | P2: курс Евро | Q2: 98.85
F3: Плoщадь объекта (м.кв.): | G3: Плащадь объекта: | H3: 500 | P3: Дисконт по тендеру | Q3: 0
F4: Срок проведения работ | G4: Срок проведения работ | H4: Согласно план-графику производства работ | P4: курс Юань | Q4: 12.64
F5: ПОДРЯДЧИК: | G5: ПОДРЯДЧИК: | H5: !!! ЗАПОЛНИТЬ !!!
F6: Юридический адрес: | G6: Юридический адрес: | H6: !!! ЗАПОЛНИТЬ !!!
F7: Электронный адрес: | G7: Электронный адрес: | H7: !!! ЗАПОЛНИТЬ !!!
F8: Контактное лицо (Ф.И.О.) : | G8: Контактное лицо (Ф.И.О.) : | H8: !!! ЗАПОЛНИТЬ !!!
F9: Контактный телефон: | G9: Контактный телефон: | H9: !!! ЗАПОЛНИТЬ !!!
F10: Реквизиты: | G10: Реквизиты: | H10: !!! ЗАПОЛНИТЬ !!!
F11: Сумма по смете: | G11: Сумма по смете: | H11: =N1666 -> 0
A14: Раздел | B14: Подраздел | C14: Подраздел подраздела | D14: Пункт подраздела | E14: Новый номенклатурный номер | F14: № | G14: Наименование работ и затрат | H14: Един. изм. | I14: Кол - во. (объем) | J14: ЕР цена работ, руб.* | K14: ЕР цена материалов и оборудования, руб.* | L14: Цена работ, руб. * | M14: Цена материалов и оборудования, руб. * | N14: Стоимость работ, руб. * | O14: Стоимость материалов и оборудования руб. * | P14: Примечание | R14: ККО/ИНФРАСТРУКТУРА
A15: Р1 | B15: 0 | D15: 0 | E15: =CONCATENATE('Смета ЕР (общ) '!$A15,".",'Смета ЕР (общ) '!$B15,".",'Смета ЕР (общ) '!$D15) -> Р1.0.0 | F15: 1 | G15: Раздел №1. Проектные работы и согласования | I15: =I16 -> 0 | N15: =ROUND(N16,2) -> 0 | O15: =ROUND(O16,2) -> 0
A16: Р1 | B16: 1 | D16: 0 | E16: =CONCATENATE('Смета ЕР (общ) '!$A16,".",'Смета ЕР (общ) '!$B16,".",'Смета ЕР (общ) '!$D16) -> Р1.1.0 | F16: =IF(I16>0,F15+1,F15) -> 1 | G16: 1.1.0 Проектные работы и согласования | I16: =SUM(I17:I108) -> 0 | N16: =SUM(N17:N108) -> 0 | O16: =SUM(O17:O108) -> 0
A17: Р1 | B17: 1 | D17: 1 | E17: =CONCATENATE('Смета ЕР (общ) '!$A17,".",'Смета ЕР (общ) '!$B17,".",'Смета ЕР (общ) '!$D17) -> Р1.1.1 | F17: =IF(I17>0,F16+1,F16) -> 1 | G17: Техническое обследование состояния несущих конструкций помещения с подготовкой рекомендаций по усилению (Техничесекое заключение о конструктиве - "ТЗК") (для помещений от 100 до 450 м.кв) | H17: м2 | J17: ='Проектирование 100-450'!E36*1.05 -> 3675 | K17: 0 | L17: =ROUND(J17-J17*$Q$3,2) -> 3675 | M17: =ROUND(K17-K17*$Q$3,2) -> 0 | N17: =ROUND('Смета ЕР (общ) '!$I17*'Смета ЕР (общ) '!$L17,2) -> 0 | O17: =ROUND('Смета ЕР (общ) '!$I17*'Смета ЕР (общ) '!$M17,2) -> 0
A18: Р1 | B18: 1 | D18: 44 | E18: =CONCATENATE('Смета ЕР (общ) '!$A18,".",'Смета ЕР (общ) '!$B18,".",'Смета ЕР (общ) '!$D18) -> Р1.1.44 | F18: =IF(I18>0,F17+1,F17) -> 1 | G18: Эскизный проект фасада и Колористический паспорт с указанием ведомости отделки и проектным решением со спецификацией элементов (крыльцо, пандус, навесы, колонны и т.д.)(для фасадов от 100 до 450 м.кв) | H18: м2 | J18: ='Проектирование 100-450'!E37*1.05 -> 7822.5 | K18: 0 | L18: =ROUND(J18-J18*$Q$3,2) -> 7822.5 | M18: =ROUND(K18-K18*$Q$3,2) -> 0 | N18: =ROUND('Смета ЕР (общ) '!$I18*'Смета ЕР (общ) '!$L18,2) -> 0 | O18: =ROUND('Смета ЕР (общ) '!$I18*'Смета ЕР (общ) '!$M18,2) -> 0
A19: Р1 | B19: 1 | D19: 2 | E19: =CONCATENATE('Смета ЕР (общ) '!$A19,".",'Смета ЕР (общ) '!$B19,".",'Смета ЕР (общ) '!$D19) -> Р1.1.2 | F19: =IF(I19>0,F18+1,F18) -> 1 | G19: Рабочая документация по усилению/устройству несущих конструкций ("КР"), включая пояснительную записку (для помещений от 100 до 450 м.кв) | H19: м2 | J19: ='Проектирование 100-450'!E18*1.05 -> 135.45 | K19: 0 | L19: =ROUND(J19-J19*$Q$3,2) -> 135.45 | M19: =ROUND(K19-K19*$Q$3,2) -> 0 | N19: =ROUND('Смета ЕР (общ) '!$I19*'Смета ЕР (общ) '!$L19,2) -> 0 | O19: =ROUND('Смета ЕР (общ) '!$I19*'Смета ЕР (общ) '!$M19,2) -> 0
A20: Р1 | B20: 1 | D20: 3 | E20: =CONCATENATE('Смета ЕР (общ) '!$A20,".",'Смета ЕР (общ) '!$B20,".",'Смета ЕР (общ) '!$D20) -> Р1.1.3 | F20: =IF(I20>0,F19+1,F19) -> 1 | G20: Рабочая документация "Архитектурные решения" ("АР"), включая пояснительную записку (для помещений от 100 до 450 м.кв) | H20: м2 | J20: ='Проектирование 100-450'!E19*1.05 -> 389.55 | K20: 0 | L20: =ROUND(J20-J20*$Q$3,2) -> 389.55 | M20: =ROUND(K20-K20*$Q$3,2) -> 0 | N20: =ROUND('Смета ЕР (общ) '!$I20*'Смета ЕР (общ) '!$L20,2) -> 0 | O20: =ROUND('Смета ЕР (общ) '!$I20*'Смета ЕР (общ) '!$M20,2) -> 0
A21: Р1 | B21: 1 | D21: 4 | E21: =CONCATENATE('Смета ЕР (общ) '!$A21,".",'Смета ЕР (общ) '!$B21,".",'Смета ЕР (общ) '!$D21) -> Р1.1.4 | F21: =IF(I21>0,F20+1,F20) -> 1 | G21: Рабочая документация по электроснабжению и электроосвещению ("ЭОМ"), включая пояснительную записку (для помещений от 100 до 450 м.кв) | H21: м2 | J21: ='Проектирование 100-450'!E20*1.05 -> 258.3 | K21: 0 | L21: =ROUND(J21-J21*$Q$3,2) -> 258.3 | M21: =ROUND(K21-K21*$Q$3,2) -> 0 | N21: =ROUND('Смета ЕР (общ) '!$I21*'Смета ЕР (общ) '!$L21,2) -> 0 | O21: =ROUND('Смета ЕР (общ) '!$I21*'Смета ЕР (общ) '!$M21,2) -> 0
A22: Р1 | B22: 1 | D22: 5 | E22: =CONCATENATE('Смета ЕР (общ) '!$A22,".",'Смета ЕР (общ) '!$B22,".",'Смета ЕР (общ) '!$D22) -> Р1.1.5 | F22: =IF(I22>0,F21+1,F21) -> 1 | G22: Рабочая документация Системы вентиляции ("ОВиК-В"), включая пояснительную записку (для помещений от 100 до 450 м.кв) | H22: м2 | J22: ='Проектирование 100-450'!E21*1.05 -> 202.65 | K22: 0 | L22: =ROUND(J22-J22*$Q$3,2) -> 202.65 | M22: =ROUND(K22-K22*$Q$3,2) -> 0 | N22: =ROUND('Смета ЕР (общ) '!$I22*'Смета ЕР (общ) '!$L22,2) -> 0 | O22: =ROUND('Смета ЕР (общ) '!$I22*'Смета ЕР (общ) '!$M22,2) -> 0
A23: Р1 | B23: 1 | D23: 6 | E23: =CONCATENATE('Смета ЕР (общ) '!$A23,".",'Смета ЕР (общ) '!$B23,".",'Смета ЕР (общ) '!$D23) -> Р1.1.6 | F23: =IF(I23>0,F22+1,F22) -> 1 | G23: Рабочая документация Системы кондиционирования ("ОВиК-К"), включая пояснительную записку (для помещений от 100 до 450 м.кв) | H23: м2 | J23: ='Проектирование 100-450'!E22*1.05 -> 159.4845 | K23: 0 | L23: =ROUND(J23-J23*$Q$3,2) -> 159.48 | M23: =ROUND(K23-K23*$Q$3,2) -> 0 | N23: =ROUND('Смета ЕР (общ) '!$I23*'Смета ЕР (общ) '!$L23,2) -> 0 | O23: =ROUND('Смета ЕР (общ) '!$I23*'Смета ЕР (общ) '!$M23,2) -> 0
A24: Р1 | B24: 1 | D24: 7 | E24: =CONCATENATE('Смета ЕР (общ) '!$A24,".",'Смета ЕР (общ) '!$B24,".",'Смета ЕР (общ) '!$D24) -> Р1.1.7 | F24: =IF(I24>0,F23+1,F23) -> 1 | G24: Рабочая документация Системы отопления ("ОВиК-О"), включая Пояснительную записку и Теплотехнический расчет (для помещений от 100 до 450 м.кв) | H24: м2 | J24: ='Проектирование 100-450'!E23*1.05 -> 123.9 | K24: 0 | L24: =ROUND(J24-J24*$Q$3,2) -> 123.9 | M24: =ROUND(K24-K24*$Q$3,2) -> 0 | N24: =ROUND('Смета ЕР (общ) '!$I24*'Смета ЕР (общ) '!$L24,2) -> 0 | O24: =ROUND('Смета ЕР (общ) '!$I24*'Смета ЕР (общ) '!$M24,2) -> 0
A25: Р1 | B25: 1 | D25: 8 | E25: =CONCATENATE('Смета ЕР (общ) '!$A25,".",'Смета ЕР (общ) '!$B25,".",'Смета ЕР (общ) '!$D25) -> Р1.1.8 | F25: =IF(I25>0,F24+1,F24) -> 1 | G25: Рабочая документация Системы водоснабжения и канализации ("ВК"), включая пояснительную записку (для помещений от 100 до 450 м.кв) | H25: м2 | J25: ='Проектирование 100-450'!E24*1.05 -> 130.2 | K25: 0 | L25: =ROUND(J25-J25*$Q$3,2) -> 130.2 | M25: =ROUND(K25-K25*$Q$3,2) -> 0 | N25: =ROUND('Смета ЕР (общ) '!$I25*'Смета ЕР (общ) '!$L25,2) -> 0 | O25: =ROUND('Смета ЕР (общ) '!$I25*'Смета ЕР (общ) '!$M25,2) -> 0
A26: Р1 | B26: 1 | D26: 9 | E26: =CONCATENATE('Смета ЕР (общ) '!$A26,".",'Смета ЕР (общ) '!$B26,".",'Смета ЕР (общ) '!$D26) -> Р1.1.9 | F26: =IF(I26>0,F25+1,F25) -> 1 | G26: Рабочая документация Системы автоматической установки водяного пожаротушения ("АУВПТ"), (спринкерная, дренчерная, модульная система), включая пояснительную записку (для помещений от 100 до 450 м.кв) | H26: м2 | J26: ='Проектирование 100-450'!E25*1.05 -> 91.6755 | K26: 0 | L26: =ROUND(J26-J26*$Q$3,2) -> 91.68 | M26: =ROUND(K26-K26*$Q$3,2) -> 0 | N26: =ROUND('Смета ЕР (общ) '!$I26*'Смета ЕР (общ) '!$L26,2) -> 0 | O26: =ROUND('Смета ЕР (общ) '!$I26*'Смета ЕР (общ) '!$M26,2) -> 0
A27: Р1 | B27: 1 | D27: 43 | E27: =CONCATENATE('Смета ЕР (общ) '!$A27,".",'Смета ЕР (общ) '!$B27,".",'Смета ЕР (общ) '!$D27) -> Р1.1.43 | F27: =IF(I27>0,F26+1,F26) -> 1 | G27: Рабочая документация Системы Внутреннего противопожарного водопровода ("ВПВ"), включая пояснительную записку (для помещений от 100 до 450 м.кв) | H27: м2 | J27: ='Проектирование 100-450'!E26*1.05 -> 91.6755 | K27: 0 | L27: =ROUND(J27-J27*$Q$3,2) -> 91.68 | M27: =ROUND(K27-K27*$Q$3,2) -> 0 | N27: =ROUND('Смета ЕР (общ) '!$I27*'Смета ЕР (общ) '!$L27,2) -> 0 | O27: =ROUND('Смета ЕР (общ) '!$I27*'Смета ЕР (общ) '!$M27,2) -> 0
A28: Р1 | B28: 1 | D28: 10 | E28: =CONCATENATE('Смета ЕР (общ) '!$A28,".",'Смета ЕР (общ) '!$B28,".",'Смета ЕР (общ) '!$D28) -> Р1.1.10 | F28: =IF(I28>0,F27+1,F27) -> 1 | G28: Рабочая документация Системы дымоудаления ("ДУ"), включая пояснительную записку (для помещений от 100 до 450 м.кв) | H28: м2 | J28: ='Проектирование 100-450'!E27*1.05 -> 103.95 | K28: 0 | L28: =ROUND(J28-J28*$Q$3,2) -> 103.95 | M28: =ROUND(K28-K28*$Q$3,2) -> 0 | N28: =ROUND('Смета ЕР (общ) '!$I28*'Смета ЕР (общ) '!$L28,2) -> 0 | O28: =ROUND('Смета ЕР (общ) '!$I28*'Смета ЕР (общ) '!$M28,2) -> 0
A29: Р1 | B29: 1 | D29: 11 | E29: =CONCATENATE('Смета ЕР (общ) '!$A29,".",'Смета ЕР (общ) '!$B29,".",'Смета ЕР (общ) '!$D29) -> Р1.1.11 | F29: =IF(I29>0,F28+1,F28) -> 1 | G29: Рабочая документация "Автоматическая пожарная сигнализация" (АПС) | H29: м2 | J29: ='АПС, СОУЭ, ППА'!F13*1.05*0.1 -> 7.035 | K29: 0 | L29: =ROUND(J29-J29*$Q$3,2) -> 7.04 | M29: =ROUND(K29-K29*$Q$3,2) -> 0 | N29: =ROUND('Смета ЕР (общ) '!$I29*'Смета ЕР (общ) '!$L29,2) -> 0 | O29: =ROUND('Смета ЕР (общ) '!$I29*'Смета ЕР (общ) '!$M29,2) -> 0 | P29: см. лист "АПС, СОУЭ, ППА"
A30: Р1 | B30: 1 | D30: 25 | E30: =CONCATENATE('Смета ЕР (общ) '!$A30,".",'Смета ЕР (общ) '!$B30,".",'Смета ЕР (общ) '!$D30) -> Р1.1.25 | F30: =IF(I30>0,F29+1,F29) -> 1 | G30: Рабочая документация "Система оповещения и управления эвакуацией людей при пожаре" (СОУЭ) | H30: м2 | J30: ='АПС, СОУЭ, ППА'!F14*1.05*0.1 -> 4.095 | K30: 0 | L30: =ROUND(J30-J30*$Q$3,2) -> 4.1 | M30: =ROUND(K30-K30*$Q$3,2) -> 0 | N30: =ROUND('Смета ЕР (общ) '!$I30*'Смета ЕР (общ) '!$L30,2) -> 0 | O30: =ROUND('Смета ЕР (общ) '!$I30*'Смета ЕР (общ) '!$M30,2) -> 0 | P30: см. лист "АПС, СОУЭ, ППА"
A31: Р1 | B31: 1 | D31: 26 | E31: =CONCATENATE('Смета ЕР (общ) '!$A31,".",'Смета ЕР (общ) '!$B31,".",'Смета ЕР (общ) '!$D31) -> Р1.1.26 | F31: =IF(I31>0,F30+1,F30) -> 1 | G31: Рабочая документация "Автоматизация системы внутреннего противопожарного водопровода (ВПВ) | H31: м2 | J31: ='АПС, СОУЭ, ППА'!F16*1.05*0.1 -> 0.84 | K31: 0 | L31: =ROUND(J31-J31*$Q$3,2) -> 0.84 | M31: =ROUND(K31-K31*$Q$3,2) -> 0 | N31: =ROUND('Смета ЕР (общ) '!$I31*'Смета ЕР (общ) '!$L31,2) -> 0 | O31: =ROUND('Смета ЕР (общ) '!$I31*'Смета ЕР (общ) '!$M31,2) -> 0
A32: Р1 | B32: 1 | D32: 29 | E32: =CONCATENATE('Смета ЕР (общ) '!$A32,".",'Смета ЕР (общ) '!$B32,".",'Смета ЕР (общ) '!$D32) -> Р1.1.29 | F32: =IF(I32>0,F31+1,F31) -> 1 | G32: Рабочая документация "Автоматизация системы противодымной вентиляции (ПДВ")" | H32: м2 | J32: ='АПС, СОУЭ, ППА'!F17*1.05*0.1 -> 2.625 | K32: 0 | L32: =ROUND(J32-J32*$Q$3,2) -> 2.63 | M32: =ROUND(K32-K32*$Q$3,2) -> 0 | N32: =ROUND('Смета ЕР (общ) '!$I32*'Смета ЕР (общ) '!$L32,2) -> 0 | O32: =ROUND('Смета ЕР (общ) '!$I32*'Смета ЕР (общ) '!$M32,2) -> 0
A33: Р1 | B33: 1 | D33: 30 | E33: =CONCATENATE('Смета ЕР (общ) '!$A33,".",'Смета ЕР (общ) '!$B33,".",'Смета ЕР (общ) '!$D33) -> Р1.1.30 | F33: =IF(I33>0,F32+1,F32) -> 1 | G33: Рабочая документация "Автоматизация Системы отопления, вентиляции и кондиционирования (ОВиК)" | H33: м2 | J33: ='АПС, СОУЭ, ППА'!F18*1.05*0.1 -> 0.315 | K33: 0 | L33: =ROUND(J33-J33*$Q$3,2) -> 0.32 | M33: =ROUND(K33-K33*$Q$3,2) -> 0 | N33: =ROUND('Смета ЕР (общ) '!$I33*'Смета ЕР (общ) '!$L33,2) -> 0 | O33: =ROUND('Смета ЕР (общ) '!$I33*'Смета ЕР (общ) '!$M33,2) -> 0
A34: Р1 | B34: 1 | D34: 31 | E34: =CONCATENATE('Смета ЕР (общ) '!$A34,".",'Смета ЕР (общ) '!$B34,".",'Смета ЕР (общ) '!$D34) -> Р1.1.31 | F34: =IF(I34>0,F33+1,F33) -> 1 | G34: Рабочая документация "Автоматизация Системы аварийного освещения (АО)" | H34: м2 | J34: ='АПС, СОУЭ, ППА'!F19*1.05*0.1 -> 0.105 | K34: 0 | L34: =ROUND(J34-J34*$Q$3,2) -> 0.11 | M34: =ROUND(K34-K34*$Q$3,2) -> 0 | N34: =ROUND('Смета ЕР (общ) '!$I34*'Смета ЕР (общ) '!$L34,2) -> 0 | O34: =ROUND('Смета ЕР (общ) '!$I34*'Смета ЕР (общ) '!$M34,2) -> 0
A35: Р1 | B35: 1 | D35: 33 | E35: =CONCATENATE('Смета ЕР (общ) '!$A35,".",'Смета ЕР (общ) '!$B35,".",'Смета ЕР (общ) '!$D35) -> Р1.1.33 | F35: =IF(I35>0,F34+1,F34) -> 1 | G35: Рабочая документация "Автоматизации лифтовового хозяйства" | H35: м2 | J35: ='АПС, СОУЭ, ППА'!F20*1.05*0.1 -> 0.105 | K35: 0 | L35: =ROUND(J35-J35*$Q$3,2) -> 0.11 | M35: =ROUND(K35-K35*$Q$3,2) -> 0 | N35: =ROUND('Смета ЕР (общ) '!$I35*'Смета ЕР (общ) '!$L35,2) -> 0 | O35: =ROUND('Смета ЕР (общ) '!$I35*'Смета ЕР (общ) '!$M35,2) -> 0
A36: Р1 | B36: 1 | D36: 36 | E36: =CONCATENATE('Смета ЕР (общ) '!$A36,".",'Смета ЕР (общ) '!$B36,".",'Смета ЕР (общ) '!$D36) -> Р1.1.36 | F36: =IF(I36>0,F35+1,F35) -> 1 | G36: Рабочая документация "Автоматизации Системы контроля управления доступом (СКУД)" | H36: м2 | J36: ='АПС, СОУЭ, ППА'!F21*1.05*0.1 -> 0.105 | K36: 0 | L36: =ROUND(J36-J36*$Q$3,2) -> 0.11 | M36: =ROUND(K36-K36*$Q$3,2) -> 0 | N36: =ROUND('Смета ЕР (общ) '!$I36*'Смета ЕР (общ) '!$L36,2) -> 0 | O36: =ROUND('Смета ЕР (общ) '!$I36*'Смета ЕР (общ) '!$M36,2) -> 0
A37: Р1 | B37: 1 | D37: 37 | E37: =CONCATENATE('Смета ЕР (общ) '!$A37,".",'Смета ЕР (общ) '!$B37,".",'Смета ЕР (общ) '!$D37) -> Р1.1.37 | F37: =IF(I37>0,F36+1,F36) -> 1 | G37: Техническое обследование состояния несущих конструкций помещения с подготовкой рекомендаций по усилению в зоне расположения депозитария, кассового узла и банкоматов (Техничесекое заключение о конструктиве - "ТЗК")(для помещений менее 100 м.кв) | H37: м2 | J37: ='Проектирование до 100'!E35*1.05 -> 3675 | K37: 0 | L37: =ROUND(J37-J37*$Q$3,2) -> 3675 | M37: =ROUND(K37-K37*$Q$3,2) -> 0 | N37: =ROUND('Смета ЕР (общ) '!$I37*'Смета ЕР (общ) '!$L37,2) -> 0 | O37: =ROUND('Смета ЕР (общ) '!$I37*'Смета ЕР (общ) '!$M37,2) -> 0
A38: Р1 | B38: 1 | D38: 45 | E38: =CONCATENATE('Смета ЕР (общ) '!$A38,".",'Смета ЕР (общ) '!$B38,".",'Смета ЕР (общ) '!$D38) -> Р1.1.45 | F38: =IF(I38>0,F37+1,F37) -> 1 | G38: Эскизный проект фасада и колористический паспорт с указанием ведомости отделки и проектным решением со спецификацией элементов (крыльцо, пандус, навесы, колонны и т.д.)(для фасадов менее 100 м.кв) | H38: кв.м.площади фасада | J38: ='Проектирование до 100'!E36*1.05 -> 7822.5 | K38: 0 | L38: =ROUND(J38-J38*$Q$3,2) -> 7822.5 | M38: =ROUND(K38-K38*$Q$3,2) -> 0 | N38: =ROUND('Смета ЕР (общ) '!$I38*'Смета ЕР (общ) '!$L38,2) -> 0 | O38: =ROUND('Смета ЕР (общ) '!$I38*'Смета ЕР (общ) '!$M38,2) -> 0
A39: Р1 | B39: 1 | D39: 46 | E39: =CONCATENATE('Смета ЕР (общ) '!$A39,".",'Смета ЕР (общ) '!$B39,".",'Смета ЕР (общ) '!$D39) -> Р1.1.46 | F39: =IF(I39>0,F38+1,F38) -> 1 | G39: Рабочая документация по усилению/устройству несущих конструкций ("КР"), включая пояснительную записку (для помещений менее 100 м.кв) | H39: компл. | J39: ='Проектирование до 100'!E17*1.05 -> 10500 | K39: 0 | L39: =ROUND(J39-J39*$Q$3,2) -> 10500 | M39: =ROUND(K39-K39*$Q$3,2) -> 0 | N39: =ROUND('Смета ЕР (общ) '!$I39*'Смета ЕР (общ) '!$L39,2) -> 0 | O39: =ROUND('Смета ЕР (общ) '!$I39*'Смета ЕР (общ) '!$M39,2) -> 0
A40: Р1 | B40: 1 | D40: 47 | E40: =CONCATENATE('Смета ЕР (общ) '!$A40,".",'Смета ЕР (общ) '!$B40,".",'Смета ЕР (общ) '!$D40) -> Р1.1.47 | F40: =IF(I40>0,F39+1,F39) -> 1 | G40: Рабочая документация "Архитектурные решения" ("АР"), включая пояснительную записку (для помещений менее 100 м.кв) | H40: компл. | J40: ='Проектирование до 100'!E18*1.05 -> 20737.5 | K40: 0 | L40: =ROUND(J40-J40*$Q$3,2) -> 20737.5 | M40: =ROUND(K40-K40*$Q$3,2) -> 0 | N40: =ROUND('Смета ЕР (общ) '!$I40*'Смета ЕР (общ) '!$L40,2) -> 0 | O40: =ROUND('Смета ЕР (общ) '!$I40*'Смета ЕР (общ) '!$M40,2) -> 0
A41: Р1 | B41: 1 | D41: 48 | E41: =CONCATENATE('Смета ЕР (общ) '!$A41,".",'Смета ЕР (общ) '!$B41,".",'Смета ЕР (общ) '!$D41) -> Р1.1.48 | F41: =IF(I41>0,F40+1,F40) -> 1 | G41: Рабочая документация по электроснабжению и электроосвещению ("ЭОМ"), включая пояснительную записку (для помещений менее 100 м.кв) | H41: компл. | J41: ='Проектирование до 100'!E19*1.05 -> 20737.5 | K41: 0 | L41: =ROUND(J41-J41*$Q$3,2) -> 20737.5 | M41: =ROUND(K41-K41*$Q$3,2) -> 0 | N41: =ROUND('Смета ЕР (общ) '!$I41*'Смета ЕР (общ) '!$L41,2) -> 0 | O41: =ROUND('Смета ЕР (общ) '!$I41*'Смета ЕР (общ) '!$M41,2) -> 0
A42: Р1 | B42: 1 | D42: 49 | E42: =CONCATENATE('Смета ЕР (общ) '!$A42,".",'Смета ЕР (общ) '!$B42,".",'Смета ЕР (общ) '!$D42) -> Р1.1.49 | F42: =IF(I42>0,F41+1,F41) -> 1 | G42: Рабочая документация Системы вентиляции ("ОВиК-В"), включая пояснительную записку (для помещений менее 100 м.кв) | H42: компл. | J42: ='Проектирование до 100'!E20*1.05 -> 15592.5 | K42: 0 | L42: =ROUND(J42-J42*$Q$3,2) -> 15592.5 | M42: =ROUND(K42-K42*$Q$3,2) -> 0 | N42: =ROUND('Смета ЕР (общ) '!$I42*'Смета ЕР (общ) '!$L42,2) -> 0 | O42: =ROUND('Смета ЕР (общ) '!$I42*'Смета ЕР (общ) '!$M42,2) -> 0
A43: Р1 | B43: 1 | D43: 50 | E43: =CONCATENATE('Смета ЕР (общ) '!$A43,".",'Смета ЕР (общ) '!$B43,".",'Смета ЕР (общ) '!$D43) -> Р1.1.50 | F43: =IF(I43>0,F42+1,F42) -> 1 | G43: Рабочая документация Системы кондиционирования ("ОВиК-К"), включая пояснительную записку (для помещений менее 100 м.кв) | H43: компл. | J43: ='Проектирование до 100'!E21*1.05 -> 10395 | K43: 0 | L43: =ROUND(J43-J43*$Q$3,2) -> 10395 | M43: =ROUND(K43-K43*$Q$3,2) -> 0 | N43: =ROUND('Смета ЕР (общ) '!$I43*'Смета ЕР (общ) '!$L43,2) -> 0 | O43: =ROUND('Смета ЕР (общ) '!$I43*'Смета ЕР (общ) '!$M43,2) -> 0
A44: Р1 | B44: 1 | D44: 51 | E44: =CONCATENATE('Смета ЕР (общ) '!$A44,".",'Смета ЕР (общ) '!$B44,".",'Смета ЕР (общ) '!$D44) -> Р1.1.51 | F44: =IF(I44>0,F43+1,F43) -> 1 | G44: Рабочая документация Системы отопления ("ОВиК-О"), включая Пояснительную записку и Теплотехнический расчет (для помещений менее 100 м.кв) | H44: компл. | J44: ='Проектирование до 100'!E22*1.05 -> 10395 | K44: 0 | L44: =ROUND(J44-J44*$Q$3,2) -> 10395 | M44: =ROUND(K44-K44*$Q$3,2) -> 0 | N44: =ROUND('Смета ЕР (общ) '!$I44*'Смета ЕР (общ) '!$L44,2) -> 0 | O44: =ROUND('Смета ЕР (общ) '!$I44*'Смета ЕР (общ) '!$M44,2) -> 0
A45: Р1 | B45: 1 | D45: 52 | E45: =CONCATENATE('Смета ЕР (общ) '!$A45,".",'Смета ЕР (общ) '!$B45,".",'Смета ЕР (общ) '!$D45) -> Р1.1.52 | F45: =IF(I45>0,F44+1,F44) -> 1 | G45: Рабочая документация Системы водоснабжения и канализации ("ВК"), включая пояснительную записку (для помещений менее 100 м.кв) | H45: компл. | J45: ='Проектирование до 100'!E23*1.05 -> 10395 | K45: 0 | L45: =ROUND(J45-J45*$Q$3,2) -> 10395 | M45: =ROUND(K45-K45*$Q$3,2) -> 0 | N45: =ROUND('Смета ЕР (общ) '!$I45*'Смета ЕР (общ) '!$L45,2) -> 0 | O45: =ROUND('Смета ЕР (общ) '!$I45*'Смета ЕР (общ) '!$M45,2) -> 0
A46: Р1 | B46: 1 | D46: 53 | E46: =CONCATENATE('Смета ЕР (общ) '!$A46,".",'Смета ЕР (общ) '!$B46,".",'Смета ЕР (общ) '!$D46) -> Р1.1.53 | F46: =IF(I46>0,F45+1,F45) -> 1 | G46: Рабочая документация Системы автоматической установки водяного пожаротушения ("АУВПТ"), (спринкерная, дренчерная, модульная система), включая пояснительную записку (для помещений менее 100 м.кв) | H46: компл. | J46: ='Проектирование до 100'!E24*1.05 -> 15592.5 | K46: 0 | L46: =ROUND(J46-J46*$Q$3,2) -> 15592.5 | M46: =ROUND(K46-K46*$Q$3,2) -> 0 | N46: =ROUND('Смета ЕР (общ) '!$I46*'Смета ЕР (общ) '!$L46,2) -> 0 | O46: =ROUND('Смета ЕР (общ) '!$I46*'Смета ЕР (общ) '!$M46,2) -> 0
A47: Р1 | B47: 1 | D47: 54 | E47: =CONCATENATE('Смета ЕР (общ) '!$A47,".",'Смета ЕР (общ) '!$B47,".",'Смета ЕР (общ) '!$D47) -> Р1.1.54 | F47: =IF(I47>0,F46+1,F46) -> 1 | G47: Рабочая документация Системы Внутреннего противопожарного водопровода ("ВПВ"), включая пояснительную записку (для помещений менее 100 м.кв) | H47: компл. | J47: ='Проектирование до 100'!E25*1.05 -> 10395 | K47: 0 | L47: =ROUND(J47-J47*$Q$3,2) -> 10395 | M47: =ROUND(K47-K47*$Q$3,2) -> 0 | N47: =ROUND('Смета ЕР (общ) '!$I47*'Смета ЕР (общ) '!$L47,2) -> 0 | O47: =ROUND('Смета ЕР (общ) '!$I47*'Смета ЕР (общ) '!$M47,2) -> 0
A48: Р1 | B48: 1 | D48: 55 | E48: =CONCATENATE('Смета ЕР (общ) '!$A48,".",'Смета ЕР (общ) '!$B48,".",'Смета ЕР (общ) '!$D48) -> Р1.1.55 | F48: =IF(I48>0,F47+1,F47) -> 1 | G48: Рабочая документация Системы дымоудаления ("ДУ"), включая пояснительную записку (для помещений менее 100 м.кв) | H48: компл. | J48: ='Проектирование до 100'!E26*1.05 -> 15592.5 | K48: 0 | L48: =ROUND(J48-J48*$Q$3,2) -> 15592.5 | M48: =ROUND(K48-K48*$Q$3,2) -> 0 | N48: =ROUND('Смета ЕР (общ) '!$I48*'Смета ЕР (общ) '!$L48,2) -> 0 | O48: =ROUND('Смета ЕР (общ) '!$I48*'Смета ЕР (общ) '!$M48,2) -> 0
A49: Р1 | B49: 1 | D49: 56 | E49: =CONCATENATE('Смета ЕР (общ) '!$A49,".",'Смета ЕР (общ) '!$B49,".",'Смета ЕР (общ) '!$D49) -> Р1.1.56 | F49: =IF(I49>0,F48+1,F48) -> 1 | G49: Исполнительная документация по усилению/устройству несущих конструкций ("КР"), включая пояснительную записку (для объектов более 100 кв.м.) | H49: м2 | J49: ='Проектирование 100-450'!E18*1.05*0.1 -> 13.545 | K49: 0 | L49: =ROUND(J49-J49*$Q$3,2) -> 13.55 | M49: =ROUND(K49-K49*$Q$3,2) -> 0 | N49: =ROUND('Смета ЕР (общ) '!$I49*'Смета ЕР (общ) '!$L49,2) -> 0 | O49: =ROUND('Смета ЕР (общ) '!$I49*'Смета ЕР (общ) '!$M49,2) -> 0
A50: Р1 | B50: 1 | D50: 57 | E50: =CONCATENATE('Смета ЕР (общ) '!$A50,".",'Смета ЕР (общ) '!$B50,".",'Смета ЕР (общ) '!$D50) -> Р1.1.57 | F50: =IF(I50>0,F49+1,F49) -> 1 | G50: Исполнительная документация "Архитектурные решения" ("АР"), включая пояснительную записку (для объектов более 100 кв.м.) | H50: м2 | J50: ='Проектирование 100-450'!E19*1.05*0.1 -> 38.955 | K50: 0 | L50: =ROUND(J50-J50*$Q$3,2) -> 38.96 | M50: =ROUND(K50-K50*$Q$3,2) -> 0 | N50: =ROUND('Смета ЕР (общ) '!$I50*'Смета ЕР (общ) '!$L50,2) -> 0 | O50: =ROUND('Смета ЕР (общ) '!$I50*'Смета ЕР (общ) '!$M50,2) -> 0
A51: Р1 | B51: 1 | D51: 58 | E51: =CONCATENATE('Смета ЕР (общ) '!$A51,".",'Смета ЕР (общ) '!$B51,".",'Смета ЕР (общ) '!$D51) -> Р1.1.58 | F51: =IF(I51>0,F50+1,F50) -> 1 | G51: Исполнительная документация по электроснабжению и электроосвещению ("ЭОМ"), включая пояснительную записку (для объектов более 100 кв.м.) | H51: м2 | J51: ='Проектирование 100-450'!E20*1.05*0.1 -> 25.83 | K51: 0 | L51: =ROUND(J51-J51*$Q$3,2) -> 25.83 | M51: =ROUND(K51-K51*$Q$3,2) -> 0 | N51: =ROUND('Смета ЕР (общ) '!$I51*'Смета ЕР (общ) '!$L51,2) -> 0 | O51: =ROUND('Смета ЕР (общ) '!$I51*'Смета ЕР (общ) '!$M51,2) -> 0
A52: Р1 | B52: 1 | D52: 59 | E52: =CONCATENATE('Смета ЕР (общ) '!$A52,".",'Смета ЕР (общ) '!$B52,".",'Смета ЕР (общ) '!$D52) -> Р1.1.59 | F52: =IF(I52>0,F51+1,F51) -> 1 | G52: Исполнительная документация Системы вентиляции ("ОВиК-В"), включая пояснительную записку (для объектов более 100 кв.м.) | H52: м2 | J52: ='Проектирование 100-450'!E21*1.05*0.1 -> 20.265 | K52: 0 | L52: =ROUND(J52-J52*$Q$3,2) -> 20.27 | M52: =ROUND(K52-K52*$Q$3,2) -> 0 | N52: =ROUND('Смета ЕР (общ) '!$I52*'Смета ЕР (общ) '!$L52,2) -> 0 | O52: =ROUND('Смета ЕР (общ) '!$I52*'Смета ЕР (общ) '!$M52,2) -> 0
A53: Р1 | B53: 1 | D53: 60 | E53: =CONCATENATE('Смета ЕР (общ) '!$A53,".",'Смета ЕР (общ) '!$B53,".",'Смета ЕР (общ) '!$D53) -> Р1.1.60 | F53: =IF(I53>0,F52+1,F52) -> 1 | G53: Исполнительная документация Системы кондиционирования ("ОВиК-К"), включая пояснительную записку (для объектов более 100 кв.м.) | H53: м2 | J53: ='Проектирование 100-450'!E22*1.05*0.1 -> 15.94845 | K53: 0 | L53: =ROUND(J53-J53*$Q$3,2) -> 15.95 | M53: =ROUND(K53-K53*$Q$3,2) -> 0 | N53: =ROUND('Смета ЕР (общ) '!$I53*'Смета ЕР (общ) '!$L53,2) -> 0 | O53: =ROUND('Смета ЕР (общ) '!$I53*'Смета ЕР (общ) '!$M53,2) -> 0
A54: Р1 | B54: 1 | D54: 61 | E54: =CONCATENATE('Смета ЕР (общ) '!$A54,".",'Смета ЕР (общ) '!$B54,".",'Смета ЕР (общ) '!$D54) -> Р1.1.61 | F54: =IF(I54>0,F53+1,F53) -> 1 | G54: Исполнительная документация Системы отопления ("ОВиК-О"), включая Пояснительную записку и Теплотехнический расчет (для объектов более 100 кв.м.) | H54: м2 | J54: ='Проектирование 100-450'!E23*1.05*0.1 -> 12.39 | K54: 0 | L54: =ROUND(J54-J54*$Q$3,2) -> 12.39 | M54: =ROUND(K54-K54*$Q$3,2) -> 0 | N54: =ROUND('Смета ЕР (общ) '!$I54*'Смета ЕР (общ) '!$L54,2) -> 0 | O54: =ROUND('Смета ЕР (общ) '!$I54*'Смета ЕР (общ) '!$M54,2) -> 0
A55: Р1 | B55: 1 | D55: 62 | E55: =CONCATENATE('Смета ЕР (общ) '!$A55,".",'Смета ЕР (общ) '!$B55,".",'Смета ЕР (общ) '!$D55) -> Р1.1.62 | F55: =IF(I55>0,F54+1,F54) -> 1 | G55: Исполнительная документация Системы водоснабжения и канализации ("ВК"), включая пояснительную записку (для объектов более 100 кв.м.) | H55: м2 | J55: ='Проектирование 100-450'!E24*1.05*0.1 -> 13.02 | K55: 0 | L55: =ROUND(J55-J55*$Q$3,2) -> 13.02 | M55: =ROUND(K55-K55*$Q$3,2) -> 0 | N55: =ROUND('Смета ЕР (общ) '!$I55*'Смета ЕР (общ) '!$L55,2) -> 0 | O55: =ROUND('Смета ЕР (общ) '!$I55*'Смета ЕР (общ) '!$M55,2) -> 0
A56: Р1 | B56: 1 | D56: 63 | E56: =CONCATENATE('Смета ЕР (общ) '!$A56,".",'Смета ЕР (общ) '!$B56,".",'Смета ЕР (общ) '!$D56) -> Р1.1.63 | F56: =IF(I56>0,F55+1,F55) -> 1 | G56: Исполнительная документация Системы автматической установки водяного пожаротушения ("АУВПТ"), (спринкерная, дренчерная, модульная система), включая пояснительную записку (для объектов более 100 кв.м.) | H56: м2 | J56: ='Проектирование 100-450'!E25*1.05*0.1 -> 9.16755 | K56: 0 | L56: =ROUND(J56-J56*$Q$3,2) -> 9.17 | M56: =ROUND(K56-K56*$Q$3,2) -> 0 | N56: =ROUND('Смета ЕР (общ) '!$I56*'Смета ЕР (общ) '!$L56,2) -> 0 | O56: =ROUND('Смета ЕР (общ) '!$I56*'Смета ЕР (общ) '!$M56,2) -> 0
A57: Р1 | B57: 1 | D57: 64 | E57: =CONCATENATE('Смета ЕР (общ) '!$A57,".",'Смета ЕР (общ) '!$B57,".",'Смета ЕР (общ) '!$D57) -> Р1.1.64 | F57: =IF(I57>0,F56+1,F56) -> 1 | G57: Исполнительная документация Системы Внутреннего противопожарного водопровода ("ВПВ"), включая пояснительную записку (для объектов более 100 кв.м.) | H57: м2 | J57: ='Проектирование 100-450'!E26*1.05*0.1 -> 9.16755 | K57: 0 | L57: =ROUND(J57-J57*$Q$3,2) -> 9.17 | M57: =ROUND(K57-K57*$Q$3,2) -> 0 | N57: =ROUND('Смета ЕР (общ) '!$I57*'Смета ЕР (общ) '!$L57,2) -> 0 | O57: =ROUND('Смета ЕР (общ) '!$I57*'Смета ЕР (общ) '!$M57,2) -> 0
A58: Р1 | B58: 1 | D58: 65 | E58: =CONCATENATE('Смета ЕР (общ) '!$A58,".",'Смета ЕР (общ) '!$B58,".",'Смета ЕР (общ) '!$D58) -> Р1.1.65 | F58: =IF(I58>0,F57+1,F57) -> 1 | G58: Исполнительная документация Системы дымоудаления ("ДУ"), включая пояснительную записку (для объектов более 100 кв.м.) | H58: м2 | J58: ='Проектирование 100-450'!E27*1.05*0.1 -> 10.395 | K58: 0 | L58: =ROUND(J58-J58*$Q$3,2) -> 10.4 | M58: =ROUND(K58-K58*$Q$3,2) -> 0 | N58: =ROUND('Смета ЕР (общ) '!$I58*'Смета ЕР (общ) '!$L58,2) -> 0 | O58: =ROUND('Смета ЕР (общ) '!$I58*'Смета ЕР (общ) '!$M58,2) -> 0
A59: Р1 | B59: 1 | D59: 66 | E59: =CONCATENATE('Смета ЕР (общ) '!$A59,".",'Смета ЕР (общ) '!$B59,".",'Смета ЕР (общ) '!$D59) -> Р1.1.66 | F59: =IF(I59>0,F58+1,F58) -> 1 | G59: Исполнительная документация по усилению/устройству несущих конструкций ("КР"), включая пояснительную записку (для объектов менее 100 кв.м.) | H59: компл. | J59: ='Проектирование до 100'!E17*1.05*0.1 -> 1050 | K59: 0 | L59: =ROUND(J59-J59*$Q$3,2) -> 1050 | M59: =ROUND(K59-K59*$Q$3,2) -> 0 | N59: =ROUND('Смета ЕР (общ) '!$I59*'Смета ЕР (общ) '!$L59,2) -> 0 | O59: =ROUND('Смета ЕР (общ) '!$I59*'Смета ЕР (общ) '!$M59,2) -> 0
A60: Р1 | B60: 1 | D60: 67 | E60: =CONCATENATE('Смета ЕР (общ) '!$A60,".",'Смета ЕР (общ) '!$B60,".",'Смета ЕР (общ) '!$D60) -> Р1.1.67 | F60: =IF(I60>0,F59+1,F59) -> 1 | G60: Исполнительная документация "Архитектурные решения" ("АР"), включая пояснительную записку (для объектов менее 100 кв.м.) | H60: компл. | J60: ='Проектирование до 100'!E18*1.05*0.1 -> 2073.75 | K60: 0 | L60: =ROUND(J60-J60*$Q$3,2) -> 2073.75 | M60: =ROUND(K60-K60*$Q$3,2) -> 0 | N60: =ROUND('Смета ЕР (общ) '!$I60*'Смета ЕР (общ) '!$L60,2) -> 0 | O60: =ROUND('Смета ЕР (общ) '!$I60*'Смета ЕР (общ) '!$M60,2) -> 0
A61: Р1 | B61: 1 | D61: 68 | E61: =CONCATENATE('Смета ЕР (общ) '!$A61,".",'Смета ЕР (общ) '!$B61,".",'Смета ЕР (общ) '!$D61) -> Р1.1.68 | F61: =IF(I61>0,F60+1,F60) -> 1 | G61: Исполнительная документация по электроснабжению и электроосвещению ("ЭОМ"), включая пояснительную записку (для объектов менее 100 кв.м.) | H61: компл. | J61: ='Проектирование до 100'!E19*1.05*0.1 -> 2073.75 | K61: 0 | L61: =ROUND(J61-J61*$Q$3,2) -> 2073.75 | M61: =ROUND(K61-K61*$Q$3,2) -> 0 | N61: =ROUND('Смета ЕР (общ) '!$I61*'Смета ЕР (общ) '!$L61,2) -> 0 | O61: =ROUND('Смета ЕР (общ) '!$I61*'Смета ЕР (общ) '!$M61,2) -> 0
A62: Р1 | B62: 1 | D62: 69 | E62: =CONCATENATE('Смета ЕР (общ) '!$A62,".",'Смета ЕР (общ) '!$B62,".",'Смета ЕР (общ) '!$D62) -> Р1.1.69 | F62: =IF(I62>0,F61+1,F61) -> 1 | G62: Исполнительная документация Системы вентиляции ("ОВиК-В"), включая пояснительную записку (для объектов менее 100 кв.м.) | H62: компл. | J62: ='Проектирование до 100'!E20*1.05*0.1 -> 1559.25 | K62: 0 | L62: =ROUND(J62-J62*$Q$3,2) -> 1559.25 | M62: =ROUND(K62-K62*$Q$3,2) -> 0 | N62: =ROUND('Смета ЕР (общ) '!$I62*'Смета ЕР (общ) '!$L62,2) -> 0 | O62: =ROUND('Смета ЕР (общ) '!$I62*'Смета ЕР (общ) '!$M62,2) -> 0
A63: Р1 | B63: 1 | D63: 70 | E63: =CONCATENATE('Смета ЕР (общ) '!$A63,".",'Смета ЕР (общ) '!$B63,".",'Смета ЕР (общ) '!$D63) -> Р1.1.70 | F63: =IF(I63>0,F62+1,F62) -> 1 | G63: Исполнительная документация Системы кондиционирования ("ОВиК-К"), включая пояснительную записку (для объектов менее 100 кв.м.) | H63: компл. | J63: ='Проектирование до 100'!E21*1.05*0.1 -> 1039.5 | K63: 0 | L63: =ROUND(J63-J63*$Q$3,2) -> 1039.5 | M63: =ROUND(K63-K63*$Q$3,2) -> 0 | N63: =ROUND('Смета ЕР (общ) '!$I63*'Смета ЕР (общ) '!$L63,2) -> 0 | O63: =ROUND('Смета ЕР (общ) '!$I63*'Смета ЕР (общ) '!$M63,2) -> 0
A64: Р1 | B64: 1 | D64: 71 | E64: =CONCATENATE('Смета ЕР (общ) '!$A64,".",'Смета ЕР (общ) '!$B64,".",'Смета ЕР (общ) '!$D64) -> Р1.1.71 | F64: =IF(I64>0,F63+1,F63) -> 1 | G64: Исполнительная документация Системы отопления ("ОВиК-О"), включая Пояснительную записку и Теплотехнический расчет (для объектов менее 100 кв.м.) | H64: компл. | J64: ='Проектирование до 100'!E22*1.05*0.1 -> 1039.5 | K64: 0 | L64: =ROUND(J64-J64*$Q$3,2) -> 1039.5 | M64: =ROUND(K64-K64*$Q$3,2) -> 0 | N64: =ROUND('Смета ЕР (общ) '!$I64*'Смета ЕР (общ) '!$L64,2) -> 0 | O64: =ROUND('Смета ЕР (общ) '!$I64*'Смета ЕР (общ) '!$M64,2) -> 0
A65: Р1 | B65: 1 | D65: 72 | E65: =CONCATENATE('Смета ЕР (общ) '!$A65,".",'Смета ЕР (общ) '!$B65,".",'Смета ЕР (общ) '!$D65) -> Р1.1.72 | F65: =IF(I65>0,F64+1,F64) -> 1 | G65: Исполнительная документация Системы водоснабжения и канализации ("ВК"), включая пояснительную записку (для объектов менее 100 кв.м.) | H65: компл. | J65: ='Проектирование до 100'!E23*1.05*0.1 -> 1039.5 | K65: 0 | L65: =ROUND(J65-J65*$Q$3,2) -> 1039.5 | M65: =ROUND(K65-K65*$Q$3,2) -> 0 | N65: =ROUND('Смета ЕР (общ) '!$I65*'Смета ЕР (общ) '!$L65,2) -> 0 | O65: =ROUND('Смета ЕР (общ) '!$I65*'Смета ЕР (общ) '!$M65,2) -> 0
A66: Р1 | B66: 1 | D66: 73 | E66: =CONCATENATE('Смета ЕР (общ) '!$A66,".",'Смета ЕР (общ) '!$B66,".",'Смета ЕР (общ) '!$D66) -> Р1.1.73 | F66: =IF(I66>0,F65+1,F65) -> 1 | G66: Исполнительная документация Системы автматической установки водяного пожаротушения ("АУВПТ"), (спринкерная, дренчерная, модульная система), включая пояснительную записку (для объектов менее 100 кв.м.) | H66: компл. | J66: ='Проектирование до 100'!E24*1.05*0.1 -> 1559.25 | K66: 0 | L66: =ROUND(J66-J66*$Q$3,2) -> 1559.25 | M66: =ROUND(K66-K66*$Q$3,2) -> 0 | N66: =ROUND('Смета ЕР (общ) '!$I66*'Смета ЕР (общ) '!$L66,2) -> 0 | O66: =ROUND('Смета ЕР (общ) '!$I66*'Смета ЕР (общ) '!$M66,2) -> 0
A67: Р1 | B67: 1 | D67: 74 | E67: =CONCATENATE('Смета ЕР (общ) '!$A67,".",'Смета ЕР (общ) '!$B67,".",'Смета ЕР (общ) '!$D67) -> Р1.1.74 | F67: =IF(I67>0,F66+1,F66) -> 1 | G67: Исполнительная документация Системы Внутреннего противопожарного водопровода ("ВПВ"), включая пояснительную записку (для объектов менее 100 кв.м.) | H67: компл. | J67: ='Проектирование до 100'!E25*1.05*0.1 -> 1039.5 | K67: 0 | L67: =ROUND(J67-J67*$Q$3,2) -> 1039.5 | M67: =ROUND(K67-K67*$Q$3,2) -> 0 | N67: =ROUND('Смета ЕР (общ) '!$I67*'Смета ЕР (общ) '!$L67,2) -> 0 | O67: =ROUND('Смета ЕР (общ) '!$I67*'Смета ЕР (общ) '!$M67,2) -> 0
A68: Р1 | B68: 1 | D68: 75 | E68: =CONCATENATE('Смета ЕР (общ) '!$A68,".",'Смета ЕР (общ) '!$B68,".",'Смета ЕР (общ) '!$D68) -> Р1.1.75 | F68: =IF(I68>0,F67+1,F67) -> 1 | G68: Исполнительная документация Системы дымоудаления ("ДУ"), включая пояснительную записку (для объектов менее 100 кв.м.) | H68: компл. | J68: ='Проектирование до 100'!E26*1.05*0.1 -> 1559.25 | K68: 0 | L68: =ROUND(J68-J68*$Q$3,2) -> 1559.25 | M68: =ROUND(K68-K68*$Q$3,2) -> 0 | N68: =ROUND('Смета ЕР (общ) '!$I68*'Смета ЕР (общ) '!$L68,2) -> 0 | O68: =ROUND('Смета ЕР (общ) '!$I68*'Смета ЕР (общ) '!$M68,2) -> 0
A69: Р1 | B69: 1 | D69: 76 | E69: =CONCATENATE('Смета ЕР (общ) '!$A69,".",'Смета ЕР (общ) '!$B69,".",'Смета ЕР (общ) '!$D69) -> Р1.1.76 | F69: =IF(I69>0,F68+1,F68) -> 1 | G69: Рабочая документация "Автоматическая пожарная сигнализация" (АПС) | H69: м2 | J69: ='АПС, СОУЭ, ППА'!F13*1.05 -> 70.35 | K69: 1 | L69: =ROUND(J69-J69*$Q$3,2) -> 70.35 | M69: =ROUND(K69-K69*$Q$3,2) -> 1 | N69: =ROUND('Смета ЕР (общ) '!$I69*'Смета ЕР (общ) '!$L69,2) -> 0 | O69: =ROUND('Смета ЕР (общ) '!$I69*'Смета ЕР (общ) '!$M69,2) -> 0 | P69: см. лист "АПС, СОУЭ, ППА"
A70: Р1 | B70: 1 | D70: 77 | E70: =CONCATENATE('Смета ЕР (общ) '!$A70,".",'Смета ЕР (общ) '!$B70,".",'Смета ЕР (общ) '!$D70) -> Р1.1.77 | F70: =IF(I70>0,F69+1,F69) -> 1 | G70: Рабочая документация "Система оповещения и управления эвакуацией людей при пожаре" (СОУЭ) | H70: м2 | J70: ='АПС, СОУЭ, ППА'!F14*1.05 -> 40.95 | K70: 2 | L70: =ROUND(J70-J70*$Q$3,2) -> 40.95 | M70: =ROUND(K70-K70*$Q$3,2) -> 2 | N70: =ROUND('Смета ЕР (общ) '!$I70*'Смета ЕР (общ) '!$L70,2) -> 0 | O70: =ROUND('Смета ЕР (общ) '!$I70*'Смета ЕР (общ) '!$M70,2) -> 0 | P70: см. лист "АПС, СОУЭ, ППА"
A71: Р1 | B71: 1 | D71: 78 | E71: =CONCATENATE('Смета ЕР (общ) '!$A71,".",'Смета ЕР (общ) '!$B71,".",'Смета ЕР (общ) '!$D71) -> Р1.1.78 | F71: =IF(I71>0,F70+1,F70) -> 1 | G71: Рабочая документация "Автоматизация системы внутреннего противопожарного водопровода (ВПВ) | H71: м2 | J71: ='АПС, СОУЭ, ППА'!F16*1.05 -> 8.4 | K71: 3 | L71: =ROUND(J71-J71*$Q$3,2) -> 8.4 | M71: =ROUND(K71-K71*$Q$3,2) -> 3 | N71: =ROUND('Смета ЕР (общ) '!$I71*'Смета ЕР (общ) '!$L71,2) -> 0 | O71: =ROUND('Смета ЕР (общ) '!$I71*'Смета ЕР (общ) '!$M71,2) -> 0
A72: Р1 | B72: 1 | D72: 79 | E72: =CONCATENATE('Смета ЕР (общ) '!$A72,".",'Смета ЕР (общ) '!$B72,".",'Смета ЕР (общ) '!$D72) -> Р1.1.79 | F72: =IF(I72>0,F71+1,F71) -> 1 | G72: Рабочая документация "Автоматизация системы противодымной вентиляции (ПДВ")" | H72: м2 | J72: ='АПС, СОУЭ, ППА'!F17*1.05 -> 26.25 | K72: 4 | L72: =ROUND(J72-J72*$Q$3,2) -> 26.25 | M72: =ROUND(K72-K72*$Q$3,2) -> 4 | N72: =ROUND('Смета ЕР (общ) '!$I72*'Смета ЕР (общ) '!$L72,2) -> 0 | O72: =ROUND('Смета ЕР (общ) '!$I72*'Смета ЕР (общ) '!$M72,2) -> 0
A73: Р1 | B73: 1 | D73: 80 | E73: =CONCATENATE('Смета ЕР (общ) '!$A73,".",'Смета ЕР (общ) '!$B73,".",'Смета ЕР (общ) '!$D73) -> Р1.1.80 | F73: =IF(I73>0,F72+1,F72) -> 1 | G73: Рабочая документация "Автоматизация Системы отопления, вентиляции и кондиционирования (ОВиК)" | H73: м2 | J73: ='АПС, СОУЭ, ППА'!F18*1.05 -> 3.15 | K73: 5 | L73: =ROUND(J73-J73*$Q$3,2) -> 3.15 | M73: =ROUND(K73-K73*$Q$3,2) -> 5 | N73: =ROUND('Смета ЕР (общ) '!$I73*'Смета ЕР (общ) '!$L73,2) -> 0 | O73: =ROUND('Смета ЕР (общ) '!$I73*'Смета ЕР (общ) '!$M73,2) -> 0
A74: Р1 | B74: 1 | D74: 81 | E74: =CONCATENATE('Смета ЕР (общ) '!$A74,".",'Смета ЕР (общ) '!$B74,".",'Смета ЕР (общ) '!$D74) -> Р1.1.81 | F74: =IF(I74>0,F73+1,F73) -> 1 | G74: Рабочая документация "Автоматизация Системы аварийного освещения (АО)" | H74: м2 | J74: ='АПС, СОУЭ, ППА'!F19*1.05 -> 1.05 | K74: 6 | L74: =ROUND(J74-J74*$Q$3,2) -> 1.05 | M74: =ROUND(K74-K74*$Q$3,2) -> 6 | N74: =ROUND('Смета ЕР (общ) '!$I74*'Смета ЕР (общ) '!$L74,2) -> 0 | O74: =ROUND('Смета ЕР (общ) '!$I74*'Смета ЕР (общ) '!$M74,2) -> 0
A75: Р1 | B75: 1 | D75: 82 | E75: =CONCATENATE('Смета ЕР (общ) '!$A75,".",'Смета ЕР (общ) '!$B75,".",'Смета ЕР (общ) '!$D75) -> Р1.1.82 | F75: =IF(I75>0,F74+1,F74) -> 1 | G75: Рабочая документация "Автоматизации лифтовового хозяйства" | H75: м2 | J75: ='АПС, СОУЭ, ППА'!F20*1.05 -> 1.05 | K75: 7 | L75: =ROUND(J75-J75*$Q$3,2) -> 1.05 | M75: =ROUND(K75-K75*$Q$3,2) -> 7 | N75: =ROUND('Смета ЕР (общ) '!$I75*'Смета ЕР (общ) '!$L75,2) -> 0 | O75: =ROUND('Смета ЕР (общ) '!$I75*'Смета ЕР (общ) '!$M75,2) -> 0
A76: Р1 | B76: 1 | D76: 83 | E76: =CONCATENATE('Смета ЕР (общ) '!$A76,".",'Смета ЕР (общ) '!$B76,".",'Смета ЕР (общ) '!$D76) -> Р1.1.83 | F76: =IF(I76>0,F75+1,F75) -> 1 | G76: Рабочая документация "Автоматизации Системы контроля управления доступом (СКУД)" | H76: м2 | J76: ='АПС, СОУЭ, ППА'!F21*1.05 -> 1.05 | K76: 8 | L76: =ROUND(J76-J76*$Q$3,2) -> 1.05 | M76: =ROUND(K76-K76*$Q$3,2) -> 8 | N76: =ROUND('Смета ЕР (общ) '!$I76*'Смета ЕР (общ) '!$L76,2) -> 0 | O76: =ROUND('Смета ЕР (общ) '!$I76*'Смета ЕР (общ) '!$M76,2) -> 0
A77: Р1 | B77: 1 | D77: 12 | E77: =CONCATENATE('Смета ЕР (общ) '!$A77,".",'Смета ЕР (общ) '!$B77,".",'Смета ЕР (общ) '!$D77) -> Р1.1.12 | F77: =IF(I77>0,F76+1,F76) -> 1 | G77: Стоимость согласования проекта перепланировки/реставрации объекта культурного наследия в соответствии с нормативными актами г.______________. | H77: м2 | J77: 0 | K77: 0 | L77: =ROUND(J77-J77*$Q$3,2) -> 0 | M77: =ROUND(K77-K77*$Q$3,2) -> 0 | N77: =ROUND('Смета ЕР (общ) '!$I77*'Смета ЕР (общ) '!$L77,2) -> 0 | O77: =ROUND('Смета ЕР (общ) '!$I77*'Смета ЕР (общ) '!$M77,2) -> 0 | P77: цена по КП
A78: Р1 | B78: 1 | D78: 13 | E78: =CONCATENATE('Смета ЕР (общ) '!$A78,".",'Смета ЕР (общ) '!$B78,".",'Смета ЕР (общ) '!$D78) -> Р1.1.13 | F78: =IF(I78>0,F77+1,F77) -> 1 | G78: Стоимость согласования проекта перепланировки/реконструкции объекта в соответствии с нормативными актами г.______________. | H78: м2 | J78: 0 | K78: 0 | L78: =ROUND(J78-J78*$Q$3,2) -> 0 | M78: =ROUND(K78-K78*$Q$3,2) -> 0 | N78: =ROUND('Смета ЕР (общ) '!$I78*'Смета ЕР (общ) '!$L78,2) -> 0 | O78: =ROUND('Смета ЕР (общ) '!$I78*'Смета ЕР (общ) '!$M78,2) -> 0 | P78: цена по КП
A79: Р1 | B79: 1 | D79: 14 | E79: =CONCATENATE('Смета ЕР (общ) '!$A79,".",'Смета ЕР (общ) '!$B79,".",'Смета ЕР (общ) '!$D79) -> Р1.1.14 | F79: =IF(I79>0,F78+1,F78) -> 1 | G79: Получение паспорта БТИ (в черных линиях) | H79: м2 | J79: 0 | K79: 0 | L79: =ROUND(J79-J79*$Q$3,2) -> 0 | M79: =ROUND(K79-K79*$Q$3,2) -> 0 | N79: =ROUND('Смета ЕР (общ) '!$I79*'Смета ЕР (общ) '!$L79,2) -> 0 | O79: =ROUND('Смета ЕР (общ) '!$I79*'Смета ЕР (общ) '!$M79,2) -> 0 | P79: цена по КП
A80: Р1 | B80: 1 | D80: 15 | E80: =CONCATENATE('Смета ЕР (общ) '!$A80,".",'Смета ЕР (общ) '!$B80,".",'Смета ЕР (общ) '!$D80) -> Р1.1.15 | F80: =IF(I80>0,F79+1,F79) -> 1 | G80: Сертификация помещения для совершения операций с ценностями, хранение ценностей по (2) классу вломостойкости и (3) классу пулестойкости | H80: м2 | J80: 88.99 | K80: 0 | L80: =ROUND(J80-J80*$Q$3,2) -> 88.99 | M80: =ROUND(K80-K80*$Q$3,2) -> 0 | N80: =ROUND('Смета ЕР (общ) '!$I80*'Смета ЕР (общ) '!$L80,2) -> 0 | O80: =ROUND('Смета ЕР (общ) '!$I80*'Смета ЕР (общ) '!$M80,2) -> 0
A81: Р1 | B81: 1 | D81: 16 | E81: =CONCATENATE('Смета ЕР (общ) '!$A81,".",'Смета ЕР (общ) '!$B81,".",'Смета ЕР (общ) '!$D81) -> Р1.1.16 | F81: =IF(I81>0,F80+1,F80) -> 1 | G81: Сертификация помещения для совершения операций с ценностями, хранение ценностей по 3 классу вломостойкости и 3 классу пулестойкости | H81: м2 | J81: 149.82 | K81: 0 | L81: =ROUND(J81-J81*$Q$3,2) -> 149.82 | M81: =ROUND(K81-K81*$Q$3,2) -> 0 | N81: =ROUND('Смета ЕР (общ) '!$I81*'Смета ЕР (общ) '!$L81,2) -> 0 | O81: =ROUND('Смета ЕР (общ) '!$I81*'Смета ЕР (общ) '!$M81,2) -> 0
A82: Р1 | B82: 1 | D82: 17 | E82: =CONCATENATE('Смета ЕР (общ) '!$A82,".",'Смета ЕР (общ) '!$B82,".",'Смета ЕР (общ) '!$D82) -> Р1.1.17 | F82: =IF(I82>0,F81+1,F81) -> 1 | G82: Сертификация помещения для совершения операций с ценностями, хранение ценностей по (5) классу вломостойкости | H82: м2 | J82: 96.48 | K82: 0 | L82: =ROUND(J82-J82*$Q$3,2) -> 96.48 | M82: =ROUND(K82-K82*$Q$3,2) -> 0 | N82: =ROUND('Смета ЕР (общ) '!$I82*'Смета ЕР (общ) '!$L82,2) -> 0 | O82: =ROUND('Смета ЕР (общ) '!$I82*'Смета ЕР (общ) '!$M82,2) -> 0
A83: Р1 | B83: 1 | D83: 18 | E83: =CONCATENATE('Смета ЕР (общ) '!$A83,".",'Смета ЕР (общ) '!$B83,".",'Смета ЕР (общ) '!$D83) -> Р1.1.18 | F83: =IF(I83>0,F82+1,F82) -> 1 | G83: Технический отчет электролаборатории для помещений более 100 м.кв. | H83: м2 | J83: 123.58 | K83: 0 | L83: =ROUND(J83-J83*$Q$3,2) -> 123.58 | M83: =ROUND(K83-K83*$Q$3,2) -> 0 | N83: =ROUND('Смета ЕР (общ) '!$I83*'Смета ЕР (общ) '!$L83,2) -> 0 | O83: =ROUND('Смета ЕР (общ) '!$I83*'Смета ЕР (общ) '!$M83,2) -> 0
A84: Р1 | B84: 1 | D84: 84 | E84: =CONCATENATE('Смета ЕР (общ) '!$A84,".",'Смета ЕР (общ) '!$B84,".",'Смета ЕР (общ) '!$D84) -> Р1.1.84 | F84: =IF(I84>0,F83+1,F83) -> 1 | G84: Технический отчет электролаборатории для помещений менее 100 м.кв. | H84: компл. | J84: 13074.35 | K84: 0 | L84: =ROUND(J84-J84*$Q$3,2) -> 13074.35 | M84: =ROUND(K84-K84*$Q$3,2) -> 0 | N84: =ROUND('Смета ЕР (общ) '!$I84*'Смета ЕР (общ) '!$L84,2) -> 0 | O84: =ROUND('Смета ЕР (общ) '!$I84*'Смета ЕР (общ) '!$M84,2) -> 0
A85: Р1 | B85: 1 | D85: 19 | E85: =CONCATENATE('Смета ЕР (общ) '!$A85,".",'Смета ЕР (общ) '!$B85,".",'Смета ЕР (общ) '!$D85) -> Р1.1.19 | F85: =IF(I85>0,F84+1,F84) -> 1 | G85: Стоимость согласования проекта изменения фасада согласно нормативных и законодательных актов г. ___________ и РФ. | H85: м2 | J85: 190.9 | K85: 0 | L85: =ROUND(J85-J85*$Q$3,2) -> 190.9 | M85: =ROUND(K85-K85*$Q$3,2) -> 0 | N85: =ROUND('Смета ЕР (общ) '!$I85*'Смета ЕР (общ) '!$L85,2) -> 0 | O85: =ROUND('Смета ЕР (общ) '!$I85*'Смета ЕР (общ) '!$M85,2) -> 0
A86: Р1 | B86: 1 | D86: 20 | E86: =CONCATENATE('Смета ЕР (общ) '!$A86,".",'Смета ЕР (общ) '!$B86,".",'Смета ЕР (общ) '!$D86) -> Р1.1.20 | F86: =IF(I86>0,F85+1,F85) -> 1 | G86: Разработка дизайн-проекта интерьера | H86: м2 | J86: 0 | K86: 0 | L86: =ROUND(J86-J86*$Q$3,2) -> 0 | M86: =ROUND(K86-K86*$Q$3,2) -> 0 | N86: =ROUND('Смета ЕР (общ) '!$I86*'Смета ЕР (общ) '!$L86,2) -> 0 | O86: =ROUND('Смета ЕР (общ) '!$I86*'Смета ЕР (общ) '!$M86,2) -> 0 | P86: цена по КП
A87: Р1 | B87: 1 | D87: 21 | E87: =CONCATENATE('Смета ЕР (общ) '!$A87,".",'Смета ЕР (общ) '!$B87,".",'Смета ЕР (общ) '!$D87) -> Р1.1.21 | F87: =IF(I87>0,F86+1,F86) -> 1 | G87: Экспертиза и согласование проекта ЭОМ в Ростехнадзоре | H87: м2 | J87: 98.96 | K87: 0 | L87: =ROUND(J87-J87*$Q$3,2) -> 98.96 | M87: =ROUND(K87-K87*$Q$3,2) -> 0 | N87: =ROUND('Смета ЕР (общ) '!$I87*'Смета ЕР (общ) '!$L87,2) -> 0 | O87: =ROUND('Смета ЕР (общ) '!$I87*'Смета ЕР (общ) '!$M87,2) -> 0
A88: Р1 | B88: 1 | D88: 22 | E88: =CONCATENATE('Смета ЕР (общ) '!$A88,".",'Смета ЕР (общ) '!$B88,".",'Смета ЕР (общ) '!$D88) -> Р1.1.22 | F88: =IF(I88>0,F87+1,F87) -> 1 | G88: Проект системы водоотведения | H88: м2 | J88: 0 | K88: 0 | L88: =ROUND(J88-J88*$Q$3,2) -> 0 | M88: =ROUND(K88-K88*$Q$3,2) -> 0 | N88: =ROUND('Смета ЕР (общ) '!$I88*'Смета ЕР (общ) '!$L88,2) -> 0 | O88: =ROUND('Смета ЕР (общ) '!$I88*'Смета ЕР (общ) '!$M88,2) -> 0 | P88: цена по КП
A89: Р1 | B89: 1 | D89: 23 | E89: =CONCATENATE('Смета ЕР (общ) '!$A89,".",'Смета ЕР (общ) '!$B89,".",'Смета ЕР (общ) '!$D89) -> Р1.1.23 | F89: =IF(I89>0,F88+1,F88) -> 1 | G89: Рабочая документация Системы ливневой канализации | H89: м2 | J89: 0 | K89: 0 | L89: =ROUND(J89-J89*$Q$3,2) -> 0 | M89: =ROUND(K89-K89*$Q$3,2) -> 0 | N89: =ROUND('Смета ЕР (общ) '!$I89*'Смета ЕР (общ) '!$L89,2) -> 0 | O89: =ROUND('Смета ЕР (общ) '!$I89*'Смета ЕР (общ) '!$M89,2) -> 0 | P89: цена по КП
A90: Р1 | B90: 1 | D90: 24 | E90: =CONCATENATE('Смета ЕР (общ) '!$A90,".",'Смета ЕР (общ) '!$B90,".",'Смета ЕР (общ) '!$D90) -> Р1.1.24 | F90: =IF(I90>0,F89+1,F89) -> 1 | G90: Получение Технических условий (при необходимости) | H90: м2 | J90: 0 | K90: 0 | L90: =ROUND(J90-J90*$Q$3,2) -> 0 | M90: =ROUND(K90-K90*$Q$3,2) -> 0 | N90: =ROUND('Смета ЕР (общ) '!$I90*'Смета ЕР (общ) '!$L90,2) -> 0 | O90: =ROUND('Смета ЕР (общ) '!$I90*'Смета ЕР (общ) '!$M90,2) -> 0 | P90: цена по КП
A91: Р1 | B91: 1 | D91: 27 | E91: =CONCATENATE('Смета ЕР (общ) '!$A91,".",'Смета ЕР (общ) '!$B91,".",'Смета ЕР (общ) '!$D91) -> Р1.1.27 | F91: =IF(I91>0,F90+1,F90) -> 1 | G91: Расчет категории пожарной опасности помещений | H91: м2 | J91: 114.84 | K91: 0 | L91: =ROUND(J91-J91*$Q$3,2) -> 114.84 | M91: =ROUND(K91-K91*$Q$3,2) -> 0 | N91: =ROUND('Смета ЕР (общ) '!$I91*'Смета ЕР (общ) '!$L91,2) -> 0 | O91: =ROUND('Смета ЕР (общ) '!$I91*'Смета ЕР (общ) '!$M91,2) -> 0
A92: Р1 | B92: 1 | D92: 28 | E92: =CONCATENATE('Смета ЕР (общ) '!$A92,".",'Смета ЕР (общ) '!$B92,".",'Смета ЕР (общ) '!$D92) -> Р1.1.28 | F92: =IF(I92>0,F91+1,F91) -> 1 | G92: Рабочая документация Системы оповещения и управления эвакуацией в части световых указателей ("СОУЭ") | H92: м2 | J92: 52.25 | K92: 0 | L92: =ROUND(J92-J92*$Q$3,2) -> 52.25 | M92: =ROUND(K92-K92*$Q$3,2) -> 0 | N92: =ROUND('Смета ЕР (общ) '!$I92*'Смета ЕР (общ) '!$L92,2) -> 0 | O92: =ROUND('Смета ЕР (общ) '!$I92*'Смета ЕР (общ) '!$M92,2) -> 0
A93: Р1 | B93: 1 | D93: 32 | E93: =CONCATENATE('Смета ЕР (общ) '!$A93,".",'Смета ЕР (общ) '!$B93,".",'Смета ЕР (общ) '!$D93) -> Р1.1.32 | F93: =IF(I93>0,F92+1,F92) -> 1 | G93: Согласование проекта Системы водоотведения и получения тех условий (при необходимости) | H93: м2 | J93: 0 | K93: 0 | L93: =ROUND(J93-J93*$Q$3,2) -> 0 | M93: =ROUND(K93-K93*$Q$3,2) -> 0 | N93: =ROUND('Смета ЕР (общ) '!$I93*'Смета ЕР (общ) '!$L93,2) -> 0 | O93: =ROUND('Смета ЕР (общ) '!$I93*'Смета ЕР (общ) '!$M93,2) -> 0 | P93: цена по КП
A94: Р1 | B94: 1 | D94: 34 | E94: =CONCATENATE('Смета ЕР (общ) '!$A94,".",'Смета ЕР (общ) '!$B94,".",'Смета ЕР (общ) '!$D94) -> Р1.1.34 | F94: =IF(I94>0,F93+1,F93) -> 1 | G94: Испытание лестниц 3 типа с предоставлением актов | H94: м2 | J94: 30.63 | K94: 0 | L94: =ROUND(J94-J94*$Q$3,2) -> 30.63 | M94: =ROUND(K94-K94*$Q$3,2) -> 0 | N94: =ROUND('Смета ЕР (общ) '!$I94*'Смета ЕР (общ) '!$L94,2) -> 0 | O94: =ROUND('Смета ЕР (общ) '!$I94*'Смета ЕР (общ) '!$M94,2) -> 0
A95: Р1 | B95: 1 | D95: 92 | E95: =CONCATENATE('Смета ЕР (общ) '!$A95,".",'Смета ЕР (общ) '!$B95,".",'Смета ЕР (общ) '!$D95) -> Р1.1.92 | F95: =IF(I95>0,F94+1,F94) -> 1 | G95: Испытания системы внутреннего противопожарного водопровода аккредитованной организацией (ВПВ и АУПТ). | H95: компл. | J95: 10207.56 | K95: 0 | L95: =ROUND(J95-J95*$Q$3,2) -> 10207.56 | M95: =ROUND(K95-K95*$Q$3,2) -> 0 | N95: =ROUND('Смета ЕР (общ) '!$I95*'Смета ЕР (общ) '!$L95,2) -> 0 | O95: =ROUND('Смета ЕР (общ) '!$I95*'Смета ЕР (общ) '!$M95,2) -> 0
A96: Р1 | B96: 1 | D96: 35 | E96: =CONCATENATE('Смета ЕР (общ) '!$A96,".",'Смета ЕР (общ) '!$B96,".",'Смета ЕР (общ) '!$D96) -> Р1.1.35 | F96: =IF(I96>0,F94+1,F94) -> 1 | G96: Мероприятия по обеспечению доступа инвалидов | H96: м2 | J96: 76.52 | K96: 0 | L96: =ROUND(J96-J96*$Q$3,2) -> 76.52 | M96: =ROUND(K96-K96*$Q$3,2) -> 0 | N96: =ROUND('Смета ЕР (общ) '!$I96*'Смета ЕР (общ) '!$L96,2) -> 0 | O96: =ROUND('Смета ЕР (общ) '!$I96*'Смета ЕР (общ) '!$M96,2) -> 0
A97: Р1 | B97: 1 | D97: 38 | E97: =CONCATENATE('Смета ЕР (общ) '!$A97,".",'Смета ЕР (общ) '!$B97,".",'Смета ЕР (общ) '!$D97) -> Р1.1.38 | F97: =IF(I97>0,F96+1,F96) -> 1 | G97: Расчет пожарного риска | H97: м2 | J97: 0 | K97: 0 | L97: =ROUND(J97-J97*$Q$3,2) -> 0 | M97: =ROUND(K97-K97*$Q$3,2) -> 0 | N97: =ROUND('Смета ЕР (общ) '!$I97*'Смета ЕР (общ) '!$L97,2) -> 0 | O97: =ROUND('Смета ЕР (общ) '!$I97*'Смета ЕР (общ) '!$M97,2) -> 0 | P97: цена по КП
A98: Р1 | B98: 1 | D98: 39 | E98: =CONCATENATE('Смета ЕР (общ) '!$A98,".",'Смета ЕР (общ) '!$B98,".",'Смета ЕР (общ) '!$D98) -> Р1.1.39 | F98: =IF(I98>0,F97+1,F97) -> 1 | G98: Подготовка и постановка на учет Независимой оценки пожарного риска (пожарный аудит), включая Расчет пожарного риска | H98: м2 | J98: 0 | K98: 0 | L98: =ROUND(J98-J98*$Q$3,2) -> 0 | M98: =ROUND(K98-K98*$Q$3,2) -> 0 | N98: =ROUND('Смета ЕР (общ) '!$I98*'Смета ЕР (общ) '!$L98,2) -> 0 | O98: =ROUND('Смета ЕР (общ) '!$I98*'Смета ЕР (общ) '!$M98,2) -> 0 | P98: цена по КП
A99: Р1 | B99: 1 | D99: 40 | E99: =CONCATENATE('Смета ЕР (общ) '!$A99,".",'Смета ЕР (общ) '!$B99,".",'Смета ЕР (общ) '!$D99) -> Р1.1.40 | F99: =IF(I99>0,F98+1,F98) -> 1 | G99: Разработка проекта огнезащиты | H99: шт. | J99: 16168.42 | K99: 0 | L99: =ROUND(J99-J99*$Q$3,2) -> 16168.42 | M99: =ROUND(K99-K99*$Q$3,2) -> 0 | N99: =ROUND('Смета ЕР (общ) '!$I99*'Смета ЕР (общ) '!$L99,2) -> 0 | O99: =ROUND('Смета ЕР (общ) '!$I99*'Смета ЕР (общ) '!$M99,2) -> 0
A100: Р1 | B100: 1 | D100: 41 | E100: =CONCATENATE('Смета ЕР (общ) '!$A100,".",'Смета ЕР (общ) '!$B100,".",'Смета ЕР (общ) '!$D100) -> Р1.1.41 | F100: =IF(I100>0,F99+1,F99) -> 1 | G100: Предоставление заключения пожарной испытательной лаборатории для контроля качества огнезащитных работ с предоставлением заключения о соответствии (до 1000 м кв. металлоконструкций) | H100: компл. | J100: 23438.15 | K100: 0 | L100: =ROUND(J100-J100*$Q$3,2) -> 23438.15 | M100: =ROUND(K100-K100*$Q$3,2) -> 0 | N100: =ROUND('Смета ЕР (общ) '!$I100*'Смета ЕР (общ) '!$L100,2) -> 0 | O100: =ROUND('Смета ЕР (общ) '!$I100*'Смета ЕР (общ) '!$M100,2) -> 0
A101: Р1 | B101: 1 | D101: 85 | E101: =CONCATENATE('Смета ЕР (общ) '!$A101,".",'Смета ЕР (общ) '!$B101,".",'Смета ЕР (общ) '!$D101) -> Р1.1.85 | F101: =IF(I101>0,F100+1,F100) -> 1 | G101: Предоставление заключения пожарной испытательной лаборатории для контроля качества огнезащитных работ с предоставлением заключения о соответствии (более 1000 м кв. металлоконструкций) | H101: м2 | J101: 17.8 | K101: 0 | L101: =ROUND(J101-J101*$Q$3,2) -> 17.8 | M101: =ROUND(K101-K101*$Q$3,2) -> 0 | N101: =ROUND('Смета ЕР (общ) '!$I101*'Смета ЕР (общ) '!$L101,2) -> 0 | O101: =ROUND('Смета ЕР (общ) '!$I101*'Смета ЕР (общ) '!$M101,2) -> 0
A102: Р1 | B102: 1 | D102: 86 | E102: =CONCATENATE('Смета ЕР (общ) '!$A102,".",'Смета ЕР (общ) '!$B102,".",'Смета ЕР (общ) '!$D102) -> Р1.1.86 | F102: =IF(I102>0,F101+1,F101) -> 1 | G102: Акустический расчет инженерных систем ОВиК (предоставление в Роспотребнадзор) электронный и бумажный вариант | H102: компл. | J102: 132501.92 | K102: 0 | L102: =ROUND(J102-J102*$Q$3,2) -> 132501.92 | M102: =ROUND(K102-K102*$Q$3,2) -> 0 | N102: =ROUND('Смета ЕР (общ) '!$I102*'Смета ЕР (общ) '!$L102,2) -> 0 | O102: =ROUND('Смета ЕР (общ) '!$I102*'Смета ЕР (общ) '!$M102,2) -> 0 | P102: согласование памятников архитектуры
...

Sheet ЭУИ
C2: Электроустановочные изделия | D2: Ед.изм. | E2: Цена для подрядчика | F2: Цена для Заказчика
C3: ВЫКЛЮЧАТЕЛЬ ОДНОКЛАВИШНЫЙ, серия - ETIKA, цвет черный Антрацит | D3: шт. | E3: 167.03 | F3: =ROUND(E3*1.05,2)+H8 -> 175.38
C4: ВЫКЛЮЧАТЕЛЬ ДВУХКЛАВИШНЫЙ, серия - ETIKA, цвет черный Антрацит | D4: шт. | E4: 248.09 | F4: =ROUND(E4*1.05,2)+H9 -> 260.49
C5: ПЕРЕКЛЮЧАТЕЛЬ ОДНОКЛАВИШНЫЙ, серия - ETIKA, цвет черный Антрацит | D5: шт. | E5: 253.16 | F5: =ROUND(E5*1.05,2)+H10 -> 346.84333
C6: ПЕРЕКЛЮЧАТЕЛЬ ДВУХКЛАВИШНЫЙ, серия - ETIKA, цвет черный Антрацит | D6: шт. | E6: 468.36 | F6: =ROUND(E6*1.05,2)+H10 -> 572.80333
C7: Рамка 1 пост, цвет - черный | D7: шт. | E7: 69.39 | F7: =ROUND(E7*1.05,2) -> 72.86 | G7: =F7 -> 72.86
C8: Рамка 2 поста, цвет - черный | D8: шт. | E8: 132.61 | F8: =ROUND(E8*1.05,2) -> 139.24 | G8: =F8/2 -> 69.62
C9: Рамка 3 поста, цвет -черный | D9: шт. | E9: 202.03 | F9: =ROUND(E9*1.05,2) -> 212.13 | G9: =F9/3 -> 70.71
C10: Рамка 4 поста, цвет - черный | D10: шт. | E10: 310.6 | F10: =ROUND(E10*1.05,2) -> 326.13 | G10: =SUM(G7:G9)/3 -> 71.063333 | H10: =G10+F17 -> 81.023333
C11: Рамка 5 постов, цвет - черный | D11: шт. | E11: 412.62 | F11: =ROUND(E11*1.05,2) -> 433.25
C12: Розетка 1-местная с заземлением с защитными шторками 16А антрацит ETIKA | D12: шт. | E12: 228.6 | F12: =ROUND(E12*1.05,2)+H10 -> 321.05333
C13: РКС-20-32-П-К Розетка с з/к 2к (на 2 модуля) ПРАЙМЕР красная IEK | D13: шт. | E13: 283.49 | F13: =ROUND(E13*1.05,2)+H10 -> 378.68333
C14: РКС-20-30-П-К Розетка с з/к 2к (на 2 модуля) ПРАЙМЕР белая IEK | D14: шт. | E14: 283.49 | F14: =ROUND(E14*1.05,2)+H10 -> 378.68333
C15: РКС-20-32-П-К Розетка с з/к 2к (на 2 модуля) ПРАЙМЕР красная IEK (для лючка) | D15: шт. | E15: 283.49 | F15: =ROUND(E15*1.05,2) -> 297.66
C16: РКС-20-30-П-К Розетка с з/к 2к (на 2 модуля) ПРАЙМЕР белая IEK (для лючка) | D16: шт. | E16: 283.49 | F16: =ROUND(E16*1.05,2) -> 297.66
C17: Коробка установочная СЗ для твердых стен D=68х45мм GENERICA | D17: шт. | E17: 9.49 | F17: =ROUND(E17*1.05,2) -> 9.96
C18: Штепсельная розетка с заземлением в стену, 2P+E, с з/ш, "Avanti", "Белое облако" (арт. 4400003), с суппоротом и рамкой | D18: шт. | E18: 408.33 | F18: =ROUND(E18*1.05,2)+G26 -> 506.89333
C19: Штепсельная розетка с заземлением в стену, 2P+E, с з/ш, "Avanti", "Красный квадрат" (арт. 4401003), с суппортом и рамкой | D19: шт. | E19: 551.22 | F19: =ROUND(E19*1.05,2)+G26 -> 656.92333
C20: Розетка модульная, 2P+E, с з/ш, "Avanti", "Белое облако", 2 модуля 4400002 | D20: шт. | E20: 195.73 | F20: =ROUND(E20*1.05,2) -> 205.52
C21: Розетка модульная, 2P+E, с з/ш, "Avanti", "Красный квадрат", 2 модуля 4401002 | D21: шт. | E21: 264.24 | F21: =ROUND(E21*1.05,2) -> 277.45
C22: Рамка "Avanti", "Белое облако", 1 пост (2 мод.) 4400902 | D22: шт. | E22: 63.38 | F22: =ROUND(E22*1.05,2) -> 66.55 | G22: =F22 -> 66.55
C23: Рамка "Avanti", "Белое облако", 2 поста (4 мод.) 4400904 | D23: шт. | E23: 140.82 | F23: =ROUND(E23*1.05,2) -> 147.86 | G23: =F23/2 -> 73.93
C24: Рамка "Avanti", "Белое облако", 3 поста (6 мод.) 4400906 | D24: шт. | E24: 183.06 | F24: =ROUND(E24*1.05,2) -> 192.21 | G24: =F24/3 -> 64.07
C25: Рамка "Avanti", "Белое облако", 4 поста (8 мод.) 4400908 | D25: шт. | E25: 309.77 | F25: =ROUND(E25*1.05,2) -> 325.26 | G25: =(SUM(G22:G24))/3 -> 68.183333
C26: Выключатель одноклавишный в стену, "Avanti", "Белое облако" 4400103 | D26: шт. | E26: 422.39 | F26: =ROUND(E26*1.05,2)+G26 -> 521.65333 | G26: =G25+F17 -> 78.143333
C27: Выключатель двухклавишный в стену, "Avanti", "Белое облако" 4400104 | D27: шт. | E27: 563.18 | F27: =ROUND(E27*1.05,2)+G26 -> 669.48333
L32: www.etm.ru
E34: Коммерческое предложение / Спецификация № | F34: 973/30916552 | I34: от | J34: 24.07.2026
D35: АО ''АЛЬФА-БАНК''
A36: Представляем Вашему вниманию цены на продукцию, которая может быть Вам интересна:
A37: Примечание:
A38: N | B38: Код товара | C38: Имя товара | D38: Производитель | E38: Артикул | F38: Кол-во | G38: Ед.изм. | H38: Цена без НДС | I38: Цена с НДС | J38: Сумма без НДС | K38: Сумма с НДС
A39: 1 | B39: 4977704 | C39: Выключатель 1-клавишный 10А безвинтовое крепление антрацит ETIKA | D39: IEK | E39: 672601 | F39: 800 | G39: шт | H39: 136.91 | I39: 167.03 | J39: 109528 | K39: 133624.16
A40: 2 | B40: 5915539 | C40: Выключатель 2-клавишный 10А безвинтовое крепление антрацит ETIKA | D40: IEK | E40: 672602 | F40: 500 | G40: шт | H40: 203.35 | I40: 248.09 | J40: 101675 | K40: 124043.5
A41: 3 | B41: 4981597 | C41: Выключатель 1-клавишный проходной 10А безвинтовое крепление антрацит ETIKA | D41: IEK | E41: 672605 | F41: 300 | G41: шт | H41: 207.51 | I41: 253.16 | J41: 62253 | K41: 75948.66
A42: 4 | B42: 6617473 | C42: Выключатель 2-клавишный проходной 10А безвинтовое крепление антрацит ETIKA | D42: IEK | E42: 672612 | F42: 100 | G42: шт | H42: 383.9 | I42: 468.36 | J42: 38390 | K42: 46835.8
A43: 5 | B43: 5971424 | C43: Рамка 1-местная антрацит ETIKA | D43: IEK | E43: 672581 | F43: 2000 | G43: шт | H43: 56.88 | I43: 69.39 | J43: 113760 | K43: 138787.2
A44: 6 | B44: 4651309 | C44: Рамка 2-местная антрацит ETIKA | D44: IEK | E44: 672582 | F44: 2000 | G44: шт | H44: 108.7 | I44: 132.61 | J44: 217400 | K44: 265228
A45: 7 | B45: 2160796 | C45: Рамка 3-местная антрацит ETIKA | D45: IEK | E45: 672583 | F45: 1000 | G45: шт | H45: 165.6 | I45: 202.03 | J45: 165600 | K45: 202032
A46: 8 | B46: 7834922 | C46: Рамка 4-местная антрацит ETIKA | D46: IEK | E46: 672584 | F46: 1000 | G46: шт | H46: 254.59 | I46: 310.6 | J46: 254590 | K46: 310599.8
A47: 9 | B47: 1284380 | C47: Рамка 5-местная антрацит ETIKA | D47: IEK | E47: 672585 | F47: 1000 | G47: шт | H47: 338.21 | I47: 412.62 | J47: 338210 | K47: 412616.2
A48: 10 | B48: 4719888 | C48: Розетка 1-местная с заземлением с защитными шторками 16А антрацит ETIKA | D48: IEK | E48: 672622 | F48: 1600 | G48: шт | H48: 187.38 | I48: 228.6 | J48: 299808 | K48: 365765.76
A49: 11 | B49: 2122554 | C49: РКС-20-32-П-К Розетка с з/к 2к (на 2 модуля) ПРАЙМЕР красная IEK | D49: IEK | E49: CKK-40D-RSZK2-K04-K | F49: 800 | G49: шт | H49: 232.37 | I49: 283.49 | J49: 185896 | K49: 226793.12 | L49: ПРЕДЛОЖЕНА ЗАМЕНА НА ИЕК
A50: 12 | B50: 4412942 | C50: РКС-20-30-П-К Розетка с з/к 2к (на 2 модуля) ПРАЙМЕР белая IEK | D50: IEK | E50: CKK-40D-RSZB2-K01-K | F50: 800 | G50: шт | H50: 232.37 | I50: 283.49 | J50: 185896 | K50: 226793.12 | L50: ПРЕДЛОЖЕНА ЗАМЕНА НА ИЕК
A51: 13 | B51: 8698998 | C51: Avanti Выключатель одноклавишный, в стену Белое облако | D51: DKC | E51: 4400103 | F51: 300 | G51: шт | H51: 346.22 | I51: 422.39 | J51: 103866 | K51: 126716.52
A52: 14 | B52: 2322919 | C52: Avanti Выключатель двухклавишный в стену, Белое облако | D52: DKC | E52: 4400104 | F52: 200 | G52: шт | H52: 461.62 | I52: 563.18 | J52: 92324 | K52: 112635.28
A53: 15 | B53: 3702304 | C53: Avanti Розетка в стену, 2P+E, с защитными шторками, ''Белое облако'' | D53: DKC | E53: 4400003 | F53: 500 | G53: шт | H53: 334.7 | I53: 408.33 | J53: 167350 | K53: 204167
A54: 16 | B54: 2821537 | C54: Avanti Розетка в стену, 2P+E, с защитными шторками, ''Красный квадрат'' | D54: DKC | E54: 4401003 | F54: 500 | G54: шт | H54: 451.82 | I54: 551.22 | J54: 225910 | K54: 275610.2
A55: 17 | B55: 1889860 | C55: Коробка установочная СЗ для твердых стен D=68х45мм GENERICA | D55: GENERICA | E55: UKT10-068-045-000-A-N-UO | F55: 3000 | G55: шт | H55: 7.78 | I55: 9.49 | J55: 23340 | K55: 28474.8 | L55: ПРЕДЛОЖЕНА ЗАМЕНА НА ИЕК
A56: 18 | B56: 9828538 | C56: Коробка распаячная КМ41234 для открытой проводки безгалогенная (HF) 100х100х50мм IP55 6 гермовводов серая IEK | D56: IEK | E56: UKO11-100-100-050-K41-55 | F56: 13000 | G56: шт | H56: 87.36 | I56: 106.58 | J56: 1135680 | K56: 1385529.6 | L56: ПРЕДЛОЖЕНА ЗАМЕНА НА ИЕК
A57: 19 | B57: 7521639 | C57: Avanti Рамка ARTLEBEDEV ''Белое облако'' 2 модульная | D57: DKC | E57: 4400902 | F57: 2000 | G57: шт | H57: 51.95 | I57: 63.38 | J57: 103900 | K57: 126758
A58: 20 | B58: 53548 | C58: Avanti Рамка ARTLEBEDEV ''Белое облако'' 4 модульная | D58: DKC | E58: 4400904 | F58: 2000 | G58: шт | H58: 115.43 | I58: 140.82 | J58: 230860 | K58: 281649.2
A59: 21 | B59: 2055776 | C59: Avanti Рамка ARTLEBEDEV ''Белое облако'' 6 модульная | D59: DKC | E59: 4400906 | F59: 1000 | G59: шт | H59: 150.05 | I59: 183.06 | J59: 150050 | K59: 183061
A60: 22 | B60: 9229704 | C60: Avanti Рамка ARTLEBEDEV ''Белое облако'' 8 модульная | D60: DKC | E60: 4400908 | F60: 1000 | G60: шт | H60: 253.91 | I60: 309.77 | J60: 253910 | K60: 309770.2
A61: 23 | B61: 4333164 | C61: Avanti Рамка ARTLEBEDEV ''Белое облако'' 10 модульная | D61: DKC | E61: 4400900 | F61: 1000 | G61: шт | H61: 403.92 | I61: 492.78 | J61: 403920 | K61: 492782.4
I62: Всего | J62: 4906996 | K62: 5986535.1

Sheet Радиаторы
C1: Адрес Склада: | N1: 111672, Москва г, Суздальская ул, дом № 46
C2: Время работы Центрального Офиса:
C3: Время работы Склада: | N3: Пн-Чт 10:30–19:00, Пт 10:30-17:00 (Обмен и Возврат товара с 13 до 17 часов)
C5: Менеджер: | H5: Савелов Андрей | N5: +7 (495) 258-93-88, доб.212 моб. +7 (926) 716-43-58, sam@teplonet.ru | AM5: www.teplonet.ru
C6: Выписал счет: | H6: Савелов Андрей | N6: +7 (495) 258-93-88, доб.212 моб. +7 (926) 716-43-58, sam@teplonet.ru
C12: Филиал "Корпоративный" ПАО "Совкомбанк" г. Москва | U12: БИК | X12: 044525360
U13: Сч. № | X13: 30101810445250000360
C14: Банк получателя
C15: ИНН | E15: 7720712565 | L15: КПП | N15: 772001001 | U15: Сч. № | X15: 40702810500140620906
C16: ООО "ТМ Инвест" | U16: Вид оп. | X16: 01 | AA16: Срок плат.
U17: Наз. пл. | AA17: Очер. плат. | AE17: 5
U18: Код | X18: ЗК2603ТМ000070570007 | AA18: Рез. поле
C19: Получатель
C20: Оплата по заказу клиента №7057
C22: Назначение платежа | AM22: Оплатите, отсканировав код в платежном терминале или передав сотруднику банка
C24: Цена МРЦ
C26: Поставщик: | G26: ООО "ТМ Инвест", ИНН 7720712565, КПП 772001001, 111672, г. Москва, ул. Суздальская, дом № 46, тел.: (495) 545-05-40
C28: Покупатель:
C30: № | E30: Артикул | H30: Товары (работы, услуги) | U30: Количество | Z30: Цена с НДС | AD30: Ставка НДС | AL30: Сумма НДС | AT30: Сумма | BC30: Цена с НДС для Банка
C32: 1 | E32: R-BA-200-10 | H32: Радиатор биметаллический RIFAR BASE 200 10 секц. бок. | U32: 1 | W32: шт | Z32: 9250 | AD32: 22 | AL32: 1668.03 | AT32: 9250 | BC32: =ROUNDUP(Z32*1.05,2) -> 9712.5
C33: 2 | E33: R-BA-350-10 | H33: Радиатор биметаллический RIFAR BASE 350 10 секц. бок. | U33: 1 | W33: шт | Z33: 9460 | AD33: 22 | AL33: 1705.9 | AT33: 9460 | BC33: =ROUNDUP(Z33*1.05,2) -> 9933
C34: 3 | E34: R-BA-500-10 | H34: Радиатор биметаллический RIFAR BASE 500 10 секц. бок. | U34: 1 | W34: шт | Z34: 9660 | AD34: 22 | AL34: 1741.97 | AT34: 9660 | BC34: =ROUNDUP(Z34*1.05,2) -> 10143
C35: 4 | E35: R-EB-300-10 | H35: Радиатор биметаллический RIFAR ECOBUILD 300 10 секц. бок. | U35: 1 | W35: шт | Z35: 9460 | AD35: 22 | AL35: 1705.9 | AT35: 9460 | BC35: =ROUNDUP(Z35*1.05,2) -> 9933
C36: 5 | E36: R-EB-500-10 | H36: Радиатор биметаллический RIFAR ECOBUILD 500 10 секц. бок. | U36: 1 | W36: шт | Z36: 9660 | AD36: 22 | AL36: 1741.97 | AT36: 9660 | BC36: =ROUNDUP(Z36*1.05,2) -> 10143
C37: 6 | E37: R-MN-300-10 | H37: Радиатор биметаллический RIFAR MONOLIT 300 10 секц. бок. | U37: 1 | W37: шт | Z37: 10570 | AD37: 22 | AL37: 1906.07 | AT37: 10570 | BC37: =ROUNDUP(Z37*1.05,2) -> 11098.5
C38: 7 | E38: R-MN-350-10 | H38: Радиатор биметаллический RIFAR MONOLIT 350 10 секц. бок. | U38: 1 | W38: шт | Z38: 10780 | AD38: 22 | AL38: 1943.93 | AT38: 10780 | BC38: =ROUNDUP(Z38*1.05,2) -> 11319
C39: 8 | E39: R-MN-500-10 | H39: Радиатор биметаллический RIFAR MONOLIT 500 10 секц. бок. | U39: 1 | W39: шт | Z39: 10980 | AD39: 22 | AL39: 1980 | AT39: 10980 | BC39: =ROUNDUP(Z39*1.05,2) -> 11529
C40: 9 | E40: R-SU-350-10 | H40: Радиатор биметаллический RIFAR SUPReMO 350 10 секц. бок. | U40: 1 | W40: шт | Z40: 13420 | AD40: 22 | AL40: 2420 | AT40: 13420 | BC40: =ROUNDUP(Z40*1.05,2) -> 14091
C41: 10 | E41: R-SU-500-10 | H41: Радиатор биметаллический RIFAR SUPReMO 500 10 секц. бок. | U41: 1 | W41: шт | Z41: 13620 | AD41: 22 | AL41: 2456.07 | AT41: 13620 | BC41: =ROUNDUP(Z41*1.05,2) -> 14301
C42: 11 | E42: R-SU-800-10 | H42: Радиатор биметаллический RIFAR SUPReMO 800 10 секц. бок. | U42: 1 | W42: шт | Z42: 22370 | AD42: 22 | AL42: 4033.93 | AT42: 22370 | BC42: =ROUNDUP(Z42*1.05,2) -> 23488.5
C43: 12 | E43: TUB 2057-10 | H43: Радиатор трубчатый RIFAR TUBOG 2057 10 секц. бок. | U43: 1 | W43: шт | Z43: 12830.5 | AD43: 22 | AL43: 2313.7 | AT43: 12830.5 | BC43: =ROUNDUP(Z43*1.05,2) -> 13472.03
... C46: 15 | E46: R-BA-200-04-VR | H46: Радиатор биметаллический RIFAR BASE Ventil 200 04 секц. нижн. прав. | U46: 1 | W46: шт | Z46: 5459 | AD46: 22 | AL46: 984.41 | AT46: 5459 | BC46: =ROUNDUP(Z46*1.05,2) -> 5731.95
C47: № | E47: Артикул | H47: Товары (работы, услуги) | U47: Количество | Z47: Цена с НДС | AD47: Ставка НДС | AL47: Сумма НДС | AT47: Сумма | BC47: Цена с НДС для Банка
C49: 16 | E49: R-BA-200-05-VR | H49: Радиатор биметаллический RIFAR BASE Ventil 200 05 секц. нижн. прав. | U49: 2 | W49: шт | Z49: 6384 | AD49: 22 | AL49: 2302.43 | AT49: 12768 | BC49: =ROUNDUP(Z49*1.05,2) -> 6703.2
C50: 17 | E50: R-BA-200-07-VR | H50: Радиатор биметаллический RIFAR BASE Ventil 200 07 секц. нижн. прав. | U50: 1 | W50: шт | Z50: 8234 | AD50: 22 | AL50: 1484.82 | AT50: 8234 | BC50: =ROUNDUP(Z50*1.05,2) -> 8645.7
C51: 18 | E51: R-BA-200-08-VR | H51: Радиатор биметаллический RIFAR BASE Ventil 200 08 секц. нижн. прав. | U51: 1 | W51: шт | Z51: 9159 | AD51: 22 | AL51: 1651.62 | AT51: 9159 | BC51: =ROUNDUP(Z51*1.05,2) -> 9616.95
C52: 19 | E52: R-BA-200-10-VR | H52: Радиатор биметаллический RIFAR BASE Ventil 200 10 секц. нижн. прав. | U52: 1 | W52: шт | Z52: 11009 | AD52: 22 | AL52: 1985.23 | AT52: 11009 | BC52: =ROUNDUP(Z52*1.05,2) -> 11559.45
C53: 20 | E53: R-BA-200-11-VR | H53: Радиатор биметаллический RIFAR BASE Ventil 200 11 секц. нижн. прав. | U53: 1 | W53: шт | Z53: 11934 | AD53: 22 | AL53: 2152.03 | AT53: 11934 | BC53: =ROUNDUP(Z53*1.05,2) -> 12530.7
C54: 21 | E54: R-BA-200-12-VR | H54: Радиатор биметаллический RIFAR BASE Ventil 200 12 секц. нижн. прав. | U54: 1 | W54: шт | Z54: 12859 | AD54: 22 | AL54: 2318.84 | AT54: 12859 | BC54: =ROUNDUP(Z54*1.05,2) -> 13501.95
C55: 22 | E55: R-BA-200-13-VR | H55: Радиатор биметаллический RIFAR BASE Ventil 200 13 секц. нижн. прав. | U55: 1 | W55: шт | Z55: 13784 | AD55: 22 | AL55: 2485.64 | AT55: 13784 | BC55: =ROUNDUP(Z55*1.05,2) -> 14473.2
C56: 23 | E56: R-BA-200-14-VR | H56: Радиатор биметаллический RIFAR BASE Ventil 200 14 секц. нижн. прав. | U56: 1 | W56: шт | Z56: 14709 | AD56: 22 | AL56: 2652.44 | AT56: 14709 | BC56: =ROUNDUP(Z56*1.05,2) -> 15444.45
C57: 24 | E57: R-BA-350-04-VR | H57: Радиатор биметаллический RIFAR BASE Ventil 350 04 секц. нижн. прав. | U57: 1 | W57: шт | Z57: 5543 | AD57: 22 | AL57: 999.56 | AT57: 5543 | BC57: =ROUNDUP(Z57*1.05,2) -> 5820.15
C58: 25 | E58: R-BA-350-05-VR | H58: Радиатор биметаллический RIFAR BASE Ventil 350 05 секц. нижн. прав. | U58: 1 | W58: шт | Z58: 6489 | AD58: 22 | AL58: 1170.15 | AT58: 6489 | BC58: =ROUNDUP(Z58*1.05,2) -> 6813.45
C59: 26 | E59: R-BA-350-06-VR | H59: Радиатор биметаллический RIFAR BASE Ventil 350 06 секц. нижн. прав. | U59: 1 | W59: шт | Z59: 7435 | AD59: 22 | AL59: 1340.74 | AT59: 7435 | BC59: =ROUNDUP(Z59*1.05,2) -> 7806.75
C60: 27 | E60: R-BA-350-07-VR | H60: Радиатор биметаллический RIFAR BASE Ventil 350 07 секц. нижн. прав. | U60: 1 | W60: шт | Z60: 8381 | AD60: 22 | AL60: 1511.33 | AT60: 8381 | BC60: =ROUNDUP(Z60*1.05,2) -> 8800.05
... C92: 59 | E92: R-EB-500-06-VR | H92: Радиатор биметаллический RIFAR ECOBUILD Ventil 500 06 секц. нижн. прав. | U92: 1 | W92: шт | Z92: 7555 | AD92: 22 | AL92: 1362.38 | AT92: 7555 | BC92: =ROUNDUP(Z92*1.05,2) -> 7932.75
C93: № | E93: Артикул | H93: Товары (работы, услуги) | U93: Количество | Z93: Цена | AD93: Ставка НДС | AL93: Сумма НДС | AT93: Сумма | BC93: Цена с НДС для Банка
C95: 60 | E95: R-EB-500-07-VR | H95: Радиатор биметаллический RIFAR ECOBUILD Ventil 500 07 секц. нижн. прав. | U95: 1 | W95: шт | Z95: 8521 | AD95: 22 | AL95: 1536.57 | AT95: 8521 | BC95: =ROUNDUP(Z95*1.05,2) -> 8947.05
C96: 61 | E96: R-EB-500-08-VR | H96: Радиатор биметаллический RIFAR ECOBUILD Ventil 500 08 секц. нижн. прав. | U96: 1 | W96: шт | Z96: 9487 | AD96: 22 | AL96: 1710.77 | AT96: 9487 | BC96: =ROUNDUP(Z96*1.05,2) -> 9961.35
C97: 62 | E97: R-EB-500-09-VR | H97: Радиатор биметаллический RIFAR ECOBUILD Ventil 500 09 секц. нижн. прав. | U97: 1 | W97: шт | Z97: 10453 | AD97: 22 | AL97: 1884.97 | AT97: 10453 | BC97: =ROUNDUP(Z97*1.05,2) -> 10975.65
C98: 63 | E98: R-EB-500-10-VR | H98: Радиатор биметаллический RIFAR ECOBUILD Ventil 500 10 секц. нижн. прав. | U98: 1 | W98: шт | Z98: 11419 | AD98: 22 | AL98: 2059.16 | AT98: 11419 | BC98: =ROUNDUP(Z98*1.05,2) -> 11989.95
C99: 64 | E99: R-EB-500-11-VR | H99: Радиатор биметаллический RIFAR ECOBUILD Ventil 500 11 секц. нижн. прав. | U99: 1 | W99: шт | Z99: 12385 | AD99: 22 | AL99: 2233.36 | AT99: 12385 | BC99: =ROUNDUP(Z99*1.05,2) -> 13004.25
C100: 65 | E100: R-EB-500-12-VR | H100: Радиатор биметаллический RIFAR ECOBUILD Ventil 500 12 секц. нижн. прав. | U100: 1 | W100: шт | Z100: 13351 | AD100: 22 | AL100: 2407.56 | AT100: 13351 | BC100: =ROUNDUP(Z100*1.05,2) -> 14018.55
C101: 66 | E101: R-EB-500-13-VR | H101: Радиатор биметаллический RIFAR ECOBUILD Ventil 500 13 секц. нижн. прав. | U101: 1 | W101: шт | Z101: 14317 | AD101: 22 | AL101: 2581.75 | AT101: 14317 | BC101: =ROUNDUP(Z101*1.05,2) -> 15032.85
C102: 67 | E102: R-EB-500-14-VR | H102: Радиатор биметаллический RIFAR ECOBUILD Ventil 500 14 секц. нижн. прав. | U102: 1 | W102: шт | Z102: 15283 | AD102: 22 | AL102: 2755.95 | AT102: 15283 | BC102: =ROUNDUP(Z102*1.05,2) -> 16047.15
C103: 68 | E103: R-MN-300-04-VR | H103: Радиатор биметаллический RIFAR MONOLIT Ventil 300 04 секц. нижн. прав. | U103: 1 | W103: шт | Z103: 6272 | AD103: 22 | AL103: 1131.02 | AT103: 6272 | BC103: =ROUNDUP(Z103*1.05,2) -> 6585.6
C104: 69 | E104: R-MN-300-05-VR | H104: Радиатор биметаллический RIFAR MONOLIT Ventil 300 05 секц. нижн. прав. | U104: 1 | W104: шт | Z104: 7329 | AD104: 22 | AL104: 1321.62 | AT104: 7329 | BC104: =ROUNDUP(Z104*1.05,2) -> 7695.45
C105: 70 | E105: R-MN-300-06-VR | H105: Радиатор биметаллический RIFAR MONOLIT Ventil 300 06 секц. нижн. прав. | U105: 1 | W105: шт | Z105: 8386 | AD105: 22 | AL105: 1512.23 | AT105: 8386 | BC105: =ROUNDUP(Z105*1.05,2) -> 8805.3
C106: 71 | E106: R-MN-300-07-VR | H106: Радиатор биметаллический RIFAR MONOLIT Ventil 300 07 секц. нижн. прав. | U106: 1 | W106: шт | Z106: 9443 | AD106: 22 | AL106: 1702.84 | AT106: 9443 | BC106: =ROUNDUP(Z106*1.05,2) -> 9915.15
... C138: 103 | E138: R-SU-350-06-VR | H138: Радиатор биметаллический RIFAR SUPReMO Ventil 350 06 секц. нижн. прав. | U138: 1 | W138: шт | Z138: 10096 | AD138: 22 | AL138: 1820.59 | AT138: 10096 | BC138: =ROUNDUP(Z138*1.05,2) -> 10600.8
C139: № | E139: Артикул | H139: Товары (работы, услуги) | U139: Количество | Z139: Цена | AD139: Ставка НДС | AL139: Сумма НДС | AT139: Сумма | BC139: Цена с НДС для Банка
C141: 104 | E141: R-SU-350-07-VR | H141: Радиатор биметаллический RIFAR SUPReMO Ventil 350 07 секц. нижн. прав. | U141: 1 | W141: шт | Z141: 11438 | AD141: 22 | AL141: 2062.59 | AT141: 11438 | BC141: =ROUNDUP(Z141*1.05,2) -> 12009.9
C142: 105 | E142: R-SU-350-08-VR | H142: Радиатор биметаллический RIFAR SUPReMO Ventil 350 08 секц. нижн. прав. | U142: 1 | W142: шт | Z142: 12780 | AD142: 22 | AL142: 2304.59 | AT142: 12780 | BC142: =ROUNDUP(Z142*1.05,2) -> 13419
C143: 106 | E143: R-SU-350-09-VR | H143: Радиатор биметаллический RIFAR SUPReMO Ventil 350 09 секц. нижн. прав. | U143: 1 | W143: шт | Z143: 14122 | AD143: 22 | AL143: 2546.59 | AT143: 14122 | BC143: =ROUNDUP(Z143*1.05,2) -> 14828.1
C144: 107 | E144: R-SU-350-10-VR | H144: Радиатор биметаллический RIFAR SUPReMO Ventil 350 10 секц. нижн. прав. | U144: 1 | W144: шт | Z144: 15464 | AD144: 22 | AL144: 2788.59 | AT144: 15464 | BC144: =ROUNDUP(Z144*1.05,2) -> 16237.2
C145: 108 | E145: R-SU-350-11-VR | H145: Радиатор биметаллический RIFAR SUPReMO Ventil 350 11 секц. нижн. прав. | U145: 1 | W145: шт | Z145: 16806 | AD145: 22 | AL145: 3030.59 | AT145: 16806 | BC145: =ROUNDUP(Z145*1.05,2) -> 17646.3
C146: 109 | E146: R-SU-350-12-VR | H146: Радиатор биметаллический RIFAR SUPReMO Ventil 350 12 секц. нижн. прав. | U146: 1 | W146: шт | Z146: 18148 | AD146: 22 | AL146: 3272.59 | AT146: 18148 | BC146: =ROUNDUP(Z146*1.05,2) -> 19055.4
C147: 110 | E147: R-SU-350-13-VR | H147: Радиатор биметаллический RIFAR SUPReMO Ventil 350 13 секц. нижн. прав. | U147: 1 | W147: шт | Z147: 19490 | AD147: 22 | AL147: 3514.59 | AT147: 19490 | BC147: =ROUNDUP(Z147*1.05,2) -> 20464.5
C148: 111 | E148: R-SU-350-14-VR | H148: Радиатор биметаллический RIFAR SUPReMO Ventil 350 14 секц. нижн. прав. | U148: 1 | W148: шт | Z148: 20832 | AD148: 22 | AL148: 3756.59 | AT148: 20832 | BC148: =ROUNDUP(Z148*1.05,2) -> 21873.6
C149: 112 | E149: R-SU-500-04-VR | H149: Радиатор биметаллический RIFAR SUPReMO Ventil 500 04 секц. нижн. прав. | U149: 1 | W149: шт | Z149: 7492 | AD149: 22 | AL149: 1351.02 | AT149: 7492 | BC149: =ROUNDUP(Z149*1.05,2) -> 7866.6
C150: 113 | E150: R-SU-500-05-VR | H150: Радиатор биметаллический RIFAR SUPReMO Ventil 500 05 секц. нижн. прав. | U150: 1 | W150: шт | Z150: 8854 | AD150: 22 | AL150: 1596.62 | AT150: 8854 | BC150: =ROUNDUP(Z150*1.05,2) -> 9296.7
C151: 114 | E151: R-SU-500-06-VR | H151: Радиатор биметаллический RIFAR SUPReMO Ventil 500 06 секц. нижн. прав. | U151: 1 | W151: шт | Z151: 10216 | AD151: 22 | AL151: 1842.23 | AT151: 10216 | BC151: =ROUNDUP(Z151*1.05,2) -> 10726.8
C152: 115 | E152: R-SU-500-07-VR | H152: Радиатор биметаллический RIFAR SUPReMO Ventil 500 07 секц. нижн. прав. | U152: 1 | W152: шт | Z152: 11578 | AD152: 22 | AL152: 2087.84 | AT152: 11578 | BC152: =ROUNDUP(Z152*1.05,2) -> 12156.9
... C187: 150 | E187: КМУ12 | H187: КОМПЛЕКТ МОНТАЖНЫЙ 1/2 универсальный белый без кронштейнов | U187: 1 | W187: шт | Z187: 679 | AD187: 22 | AL187: 122.44 | AT187: 679 | BC187: =ROUNDUP(Z187*1.05,2) -> 712.95
C188: № | E188: Артикул | H188: Товары (работы, услуги) | U188: Количество | Z188: Цена | AD188: Ставка НДС | AL188: Сумма НДС | AT188: Сумма | BC188: Цена с НДС для Банка
C190: 151 | E190: КМУ34 | H190: КОМПЛЕКТ МОНТАЖНЫЙ 3/4 универсальный белый без кронштейнов | U190: 1 | W190: шт | Z190: 649 | AD190: 22 | AL190: 117.03 | AT190: 649 | BC190: =ROUNDUP(Z190*1.05,2) -> 681.45
H191: Наценка на радиатор с нп Комплектация для радиатора с НП ( клапан термостатический с комплектующими , монтажный комплект | U191: 1 | W191: шт | Z191: 1759 | AD191: 22 | AL191: 117.03 | AT191: 649 | BC191: =ROUNDUP(Z191*1.05,2) -> 1846.95
E192: 216033 | H192: Узел подключения радиатора H-образный Arrowhead Element, прямой, 3/4"- 3/4" (без ниппелей) | U192: 1 | W192: шт | Z192: 597 | AD192: 22 | AL192: 117.03 | AT192: 649 | BC192: =ROUNDUP(Z192*1.05,2) -> 626.85
E193: 11096641002 | H193: Трубка РЕХАУ из. нерж. стали для подкл. радиатора, Г-образная 16/250 | U193: 2 | W193: шт | Z193: 1187.5 | AD193: 22 | AL193: 117.03 | AT193: 649 | BC193: =ROUNDUP(Z193*1.05,2) -> 1246.88
E194: 12406013003 | H194: Резьбозажимное соединение РЕХАУ для металлической трубки G 3/4 -15 | U194: 2 | W194: шт | Z194: 392.35 | AD194: 22 | AL194: 117.03 | AT194: 649 | BC194: =ROUNDUP(Z194*1.05,2) -> 411.97
C218: Продавец: ___________________________________________

Sheet Стекл двери в алюм. (2)
A1: Наименование компании | B1: ООО "ФАСАДСТРОЙ"
A2: контактная информация | B2: 398050,г.Липецк, ул.Ленина 11/2 , оф.408
A3: эл.почта | B3: svetlanal80@mail.ru
A4: тел | B4: 79155597559 | F4: 46246
A5: Двери входные | B5: Ед. изм. | C5: Цена (руб./ед.) | D5: Цена для Альфа-Банка
A6: однопольный дверной блок (алюминиевый теплый профиль 3 петли, два врезных замка цилиндрического типа, имеющих с внутренней стороны запорные устройства типа «вертушок» (количество ключей не менее 4 шт.) без защелки , ручка из нержавеющей стали типа «труба» со смещением креплений диаметром 32 мм, длиной 1000 мм, цвет «хром». Размер "в свету" 900*2100. однокамерный стеклопакет. | B6: шт. | C6: 55730 | D6: =ROUNDUP(C6*1.05,2) -> 58516.5
A7: полуторапольный дверной блок (алюминиевый теплый профиль 3 петли, два врезных замка цилиндрического типа, имеющих с внутренней стороны запорные устройства типа «вертушок» (количество ключей не менее 4 шт.) без защелки , ручка из нержавеющей стали типа «труба» со смещением креплений диаметром 32 мм, длиной 1000 мм, цвет «хром». Размер "в свету" 1200*2100. однокамерный стеклопакет, | B7: шт. | C7: 83772 | D7: =ROUNDUP(C7*1.05,2) -> 87960.6
A8: двупольноый дверной блок (алюминиевый теплый профиль 3 петли, два врезных замка цилиндрического типа, имеющих с внутренней стороны запорные устройства типа «вертушок» без защелки , ручка из нержавеющей стали типа «труба» со смещением креплений диаметром 32 мм, длиной 1000 мм, цвет «хром»). Размер "в свету" 1800*2100.однокамерный стеклопакет стекла закаленные и/или трипликс 6 мм | B8: шт. | C8: 96100 | D8: =ROUNDUP(C8*1.05,2) -> 100905
A9: Установка дверного доводчика штанга рычажная на входные двери (210 кг) | B9: шт. | C9: 5500 | D9: =ROUNDUP(C9*1.05,2) -> 5775
A10: Двери стеклянные в алюминиевом профиле внутренние
A11: однопольный дверной блок в алюминиевом корпусе. Размер в "свету" 900х2100 мм. Два врезных замка цилиндрического типа, имеющих с внутренней стороны запорные устройства типа «вертушок» (количество ключей не менее 4 шт.). Ручка из нержавеющей стали типа «труба» со смещением креплений диаметром 32 мм, длиной 1000 мм, цвет «хром»). Однокамерный стеклопакет, стекла закаленные 8 мм /или трипликс | B11: шт. | C11: 44790 | D11: =ROUNDUP(C11*1.05,2) -> 47029.5
A12: полуторапольный дверной блок в алюминиевом корпусе.Размер в "свету" 1200х2100 мм . Два врезных замка цилиндрического типа, имеющих с внутренней стороны запорные устройства типа «вертушок» (количество ключей не менее 4 шт.) Ручка из нержавеющей стали типа «труба» со смещением креплений диаметром 32 мм, длиной 1000 мм, цвет «хром»). Однокамерный стеклопакет, стекла закаленные 8 мм /или трипликс | B12: шт. | C12: 65100 | D12: =ROUNDUP(C12*1.05,2) -> 68355
A13: двупольный дверной блок в алюминиевом корпусе.Размер в "свету" 1800х2100 мм . Два врезных замка цилиндрического типа, имеющих с внутренней стороны запорные устройства типа «вертушок» (количество ключей не менее 4 шт.) Ручка из нержавеющей стали типа «труба» со смещением креплений диаметром 32 мм, длиной 1000 мм, цвет «хром»). Однокамерный стеклопакет, стекла закаленные 8 мм /или трипликс | B13: шт. | C13: 75900 | D13: =ROUNDUP(C13*1.05,2) -> 79695

Sheet Проектирование до 100
B2: Диапазон площади проекта, S | C2: кв.м. | D2: 0 < S <100
B3: Количество проектов в данном диапазоне | C3: шт. | D3: =[15]Объекты!C48 -> 17
B4: Общая площадь проектирования в данном диапазоне | C4: кв.м. | D4: =[15]Объекты!B48 -> 890
B5: Средняя площадь проекта | C5: кв.м. | D5: =ROUND(D4/D3,0) -> 52
B6: Средний срок Авторского надзора при РСР | C6: месяц | D6: 1
B7: Доля авторского надзора в стоимости основных проектных работ | D7: 0.3
B8: Стоимость основных проектных работ по КП | C8: руб. | G8: =SUM(G17:G26)*D3 -> 1590435
B9: Стоимость авторского надзора | C9: руб. | G9: =G27*D3 -> 681615
B10: Стоимость опциональных проектных работ по КП | C10: руб. | G10: =G34*D32 -> 76650
B11: ВСЕГО стоимость по КП | C11: руб. | G11: =G8+G9+G10 -> 2348700
B13: ОСНОВНЫЕ ПРОЕКТНЫЕ РАБОТЫ
A14: № | B14: Наименование работ и затрат | C14: Един. изм. | D14: Кол - во. (объем) | E14: Цена работ с АН, руб., в т.ч. НДС | F14: Цена работ без АН, руб., в т.ч. НДС | G14: Стоимость работ, руб., в т.ч. НДС | H14: Стоимость материалов и оборудования руб., в т.ч. НДС | K14: ПОДРЯДЧИК: | L14: ООО "ЛИБГОТ"
B15: Раздел №1. Проектные работы и согласования | D15: =D16 -> 9 | G15: =ROUND(G16,2) -> 133650 | K15: Юридический адрес: | L15: 115114, г. Москва, вн.тер.г. муниципальный округ Замоскворечье, ул. Летниковская, д. 10, стр. 2, помещ. 18/10
B16: Проектные работы и согласования | D16: =SUM(D17:D25) -> 9 | G16: =SUM(G17:G27) -> 133650 | K16: Электронный адрес: | L16: libgotstroy@mail.ru
A17: 1 | B17: Рабочая документация по усилению/устройству несущих конструкций ("КР"), включая пояснительную записку (для помещений менее 100 м.кв) | C17: компл. | D17: 1 | E17: 10000 | F17: =E17*(1-$D$7) -> 7000 | G17: =D17*F17 -> 7000 | K17: Контактное лицо (Ф.И.О.) : | L17: Либгот Андрей Дмитриевич
A18: 2 | B18: Рабочая документация "Архитектурные решения" ("АР"), включая пояснительную записку (для помещений менее 100 м.кв) | C18: компл. | D18: 1 | E18: 19750 | F18: =E18*(1-$D$7) -> 13825 | G18: =D18*F18 -> 13825 | K18: Контактный телефон: | L18: 8-977-330-33-10
A19: 3 | B19: Рабочая документация по электроснабжению и электроосвещению ("ЭОМ"), включая пояснительную записку (для помещений менее 100 м.кв) | C19: компл. | D19: 1 | E19: 19750 | F19: =E19*(1-$D$7) -> 13825 | G19: =D19*F19 -> 13825 | K19: Реквизиты: | L19: ИНН 9705229621, КПП 770501001, ОГРН 1247700560238
A20: 4 | B20: Рабочая документация Системы вентиляции ("ОВиК-В"), включая пояснительную записку (для помещений менее 100 м.кв) | C20: компл. | D20: 1 | E20: 14850 | F20: =E20*(1-$D$7) -> 10395 | G20: =D20*F20 -> 10395
A21: 5 | B21: Рабочая документация Системы кондиционирования ("ОВиК-К"), включая пояснительную записку (для помещений менее 100 м.кв) | C21: компл. | D21: 1 | E21: 9900 | F21: =E21*(1-$D$7) -> 6930 | G21: =D21*F21 -> 6930
A22: 6 | B22: Рабочая документация Системы отопления ("ОВиК-О"), включая Пояснительную записку и Теплотехнический расчет (для помещений менее 100 м.кв) | C22: компл. | D22: 1 | E22: 9900 | F22: =E22*(1-$D$7) -> 6930 | G22: =D22*F22 -> 6930
A23: 7 | B23: Рабочая документация Системы водоснабжения и канализации ("ВК"), включая пояснительную записку (для помещений менее 100 м.кв) | C23: компл. | D23: 1 | E23: 9900 | F23: =E23*(1-$D$7) -> 6930 | G23: =D23*F23 -> 6930
A24: 8 | B24: Рабочая документация Системы автоматической установки водяного пожаротушения ("АУВПТ"), (спринкерная, дренчерная, модульная система), включая пояснительную записку (для помещений менее 100 м.кв) | C24: компл. | D24: 1 | E24: 14850 | F24: =E24*(1-$D$7) -> 10395 | G24: =D24*F24 -> 10395
A25: 9 | B25: Рабочая документация Системы Внутреннего противопожарного водопровода ("ВПВ"), включая пояснительную записку (для помещений менее 100 м.кв) | C25: компл. | D25: 1 | E25: 9900 | F25: =E25*(1-$D$7) -> 6930 | G25: =D25*F25 -> 6930
A26: 10 | B26: Рабочая документация Системы дымоудаления ("ДУ"), включая пояснительную записку (для помещений менее 100 м.кв) | C26: компл. | D26: 1 | E26: 14850 | F26: =E26*(1-$D$7) -> 10395 | G26: =D26*F26 -> 10395
A27: 11 | B27: Авторский надзор (без учета услуги по выездам представителя Подрядчика на Объект) | C27: месяц | D27: =D6 -> 1 | E27: =SUMPRODUCT(D17:D26,E17:E26)*D7/D27 -> 40095 | F27: 0 | G27: =D27*E27 -> 40095
B30: ОПЦИОНАЛЬНЫЕ ПРОЕКТНЫЕ РАБОТЫ
B31: =B5 -> Средняя площадь проекта | C31: кв.м. | D31: =ROUND(D5/10,0) -> 5
B32: =B3 -> Количество проектов в данном диапазоне | C32: шт. | D32: =ROUND(D3/10,0) -> 2
B33: =B4 -> Общая площадь проектирования в данном диапазоне | C33: кв.м. | D33: =D31*D32 -> 10
B34: Проектные работы и согласования | D34: =SUM(D35:D41) -> 10 | G34: =SUM(G35:G36) -> 38325
A35: 1 | B35: Техническое обследование состояния несущих конструкций помещения с подготовкой рекомендаций по усилению в зоне расположения депозитария, кассового узла и банкоматов (Техничесекое заключение о конструктиве - "ТЗК")(для помещений менее 100 м.кв) | C35: кв.м. | D35: =D31 -> 5 | E35: 3500 | F35: =E35*(1-$D$7) -> 2450 | G35: =D35*F35 -> 12250
A36: 2 | B36: Эскизный проект фасада и колористический паспорт с указанием ведомости отделки и проектным решением со спецификацией элементов (крыльцо, пандус, навесы, колонны и т.д.)(для фасадов менее 100 м.кв) | C36: кв.м.площади фасада | D36: =D31 -> 5 | E36: 7450 | F36: =E36*(1-$D$7) -> 5215 | G36: =D36*F36 -> 26075
B40: Примечание: Услуги по выездам представителя Подрядчика на Объект в цену Работ не включены и оплачиваются дополнительно. При необходимости выезда представителя Подрядчика на Объект Заказчик несет расходы по оплате авиабилетов (эконом класс), ж/д билетов (купе, класс обслуживания 2С, 2В) до города и обратно, проживание в гостинице (стандартный номер стоимостью не более 4500 рублей в сутки), трансфер (2000 руб.) на каждого представителя Подрядчика. Возмещение расходов по оплате услуг раннего въезда\ позднего выезда производится согласно отчетным документам в полном объеме (в норму по оплате проживания данные услуги не включены). Необходимость выезда Подрядчика на объект должна быть подтверждена Заказчиком.
B41: Примечание: В течении производства Ремонтно-строительных работ Объекта вести авторский надзор (с присутствием на еженедельных рабочих группах в режиме on/off лайн), в соответствии с положением об авторском надзоре и другими нормативными требованиями в этой области. Вести журнал авторского надзора, своевременно занося в него выявленные при строительстве отступления от ПД, строительных норм и правил, технических условий по производству работ. Проводить работы по внесению всех изменений в проектную документацию всех разделов документации согласно требованиям представителей Технического надзора, Представителей служб Заказчика, авторов дизайн-проекта в течение 3-х рабочих дней.
B42: Примечание: Производство Ремонтно-строительных работ Объекта 1-2 месяца. Выезд на объект по согласованию с Заказчиком.

Sheet Проектирование 100-450
B2: Диапазон площади проекта, S | C2: кв.м. | D2: 100 < S < 450
B3: Количество проектов в данном диапазоне | C3: шт. | D3: =[15]Объекты!C49 -> 59
B4: Общая площадь проектирования в данном диапазоне | C4: кв.м. | D4: =[15]Объекты!B49 -> 14317.4
B5: Средняя площадь проекта | C5: кв.м. | D5: =ROUND(D4/D3,0) -> 243
B6: Средний срок Авторского надзора при РСР | C6: месяц | D6: 2
B7: Доля авторского надзора в стоимости основных проектных работ | D7: 0.3
B8: Стоимость основных проектных работ по КП | C8: руб. | H8: =SUM(H18:H27)*D3 -> 16122774
B9: Стоимость авторского надзора | C9: руб. | H9: =H28*D3 -> 6909760.2
B10: Стоимость опциональных проектных работ по КП | C10: руб. | H10: =H35*D33 -> 1103760
B11: ВСЕГО стоимость по КП | C11: руб. | H11: =H8+H9+H10 -> 24136294
B12: Цена за 1 кв.м. проектирования | C12: руб. за 1 кв.м. | H12: =H11/D4 -> 1685.8015
B14: ОСНОВНЫЕ ПРОЕКТНЫЕ РАБОТЫ
A15: № | B15: Наименование работ и затрат | C15: Един. изм. | D15: Кол - во. (объем) | E15: Цена работ с АН, руб., в т.ч. НДС | F15: Цена работ без АН, руб., в т.ч. НДС | G15: Цена материалов и оборудования, руб., в т.ч. НДС | H15: Стоимость работ, руб., в т.ч. НДС | I15: Стоимость материалов и оборудования руб., в т.ч. НДС | N15: ПОДРЯДЧИК: | O15: ООО "ЛИБГОТ"
B16: Раздел №1. Проектные работы и согласования | D16: =D17 -> 2187 | H16: =ROUND(H17,2) -> 390381.93 | N16: Юридический адрес: | O16: 115114, г. Москва, вн.тер.г. муниципальный округ Замоскворечье, ул. Летниковская, д. 10, стр. 2, помещ. 18/10
B17: Проектные работы и согласования | D17: =SUM(D18:D26) -> 2187 | H17: =SUM(H18:H28) -> 390381.93 | N17: Электронный адрес: | O17: libgotstroy@mail.ru
A18: 1 | B18: Рабочая документация по усилению/устройству несущих конструкций ("КР"), включая пояснительную записку (для помещений от 100 до 450 м.кв) | C18: кв.м.площади офиса | D18: =$D$5 -> 243 | E18: 129 | F18: =E18*(1-$D$7) -> 90.3 | G18: =ROUND(#REF!-#REF!*$Q$17,2) -> #REF! | H18: =D18*F18 -> 21942.9 | N18: Контактное лицо (Ф.И.О.) : | O18: Либгот Андрей Дмитриевич
A19: 2 | B19: Рабочая документация "Архитектурные решения" ("АР"), включая пояснительную записку (для помещений от 100 до 450 м.кв) | C19: кв.м.площади офиса | D19: =$D$5 -> 243 | E19: 371 | F19: =E19*(1-$D$7) -> 259.7 | G19: =ROUND(#REF!-#REF!*$Q$17,2) -> #REF! | H19: =D19*F19 -> 63107.1 | N19: Контактный телефон: | O19: 8-977-330-33-10
A20: 3 | B20: Рабочая документация по электроснабжению и электроосвещению ("ЭОМ"), включая пояснительную записку (для помещений от 100 до 450 м.кв) | C20: кв.м.площади офиса | D20: =$D$5 -> 243 | E20: 246 | F20: =E20*(1-$D$7) -> 172.2 | G20: =ROUND(#REF!-#REF!*$Q$17,2) -> #REF! | H20: =D20*F20 -> 41844.6 | N20: Реквизиты: | O20: ИНН 9705229621, КПП 770501001, ОГРН 1247700560238
A21: 4 | B21: Рабочая документация Системы вентиляции ("ОВиК-В"), включая пояснительную записку (для помещений от 100 до 450 м.кв) | C21: кв.м.площади офиса | D21: =$D$5 -> 243 | E21: 193 | F21: =E21*(1-$D$7) -> 135.1 | G21: =ROUND(#REF!-#REF!*$Q$17,2) -> #REF! | H21: =D21*F21 -> 32829.3
A22: 5 | B22: Рабочая документация Системы кондиционирования ("ОВиК-К"), включая пояснительную записку (для помещений от 100 до 450 м.кв) | C22: кв.м.площади офиса | D22: =$D$5 -> 243 | E22: 151.89 | F22: =E22*(1-$D$7) -> 106.323 | G22: =ROUND(#REF!-#REF!*$Q$17,2) -> #REF! | H22: =D22*F22 -> 25836.489
A23: 6 | B23: Рабочая документация Системы отопления ("ОВиК-О"), включая Пояснительную записку и Теплотехнический расчет (для помещений от 100 до 450 м.кв) | C23: кв.м.площади офиса | D23: =$D$5 -> 243 | E23: 118 | F23: =E23*(1-$D$7) -> 82.6 | G23: =ROUND(#REF!-#REF!*$Q$17,2) -> #REF! | H23: =D23*F23 -> 20071.8
A24: 7 | B24: Рабочая документация Системы водоснабжения и канализации ("ВК"), включая пояснительную записку (для помещений от 100 до 450 м.кв) | C24: кв.м.площади офиса | D24: =$D$5 -> 243 | E24: 124 | F24: =E24*(1-$D$7) -> 86.8 | G24: =ROUND(#REF!-#REF!*$Q$17,2) -> #REF! | H24: =D24*F24 -> 21092.4
A25: 8 | B25: Рабочая документация Системы автоматической установки водяного пожаротушения ("АУВПТ"), (спринкерная, дренчерная, модульная система), включая пояснительную записку (для помещений от 100 до 450 м.кв) | C25: кв.м.площади офиса | D25: =$D$5 -> 243 | E25: 87.31 | F25: =E25*(1-$D$7) -> 61.117 | G25: =ROUND(#REF!-#REF!*$Q$17,2) -> #REF! | H25: =D25*F25 -> 14851.431
A26: 9 | B26: Рабочая документация Системы Внутреннего противопожарного водопровода ("ВПВ"), включая пояснительную записку (для помещений от 100 до 450 м.кв) | C26: кв.м.площади офиса | D26: =$D$5 -> 243 | E26: 87.31 | F26: =E26*(1-$D$7) -> 61.117 | G26: =ROUND(#REF!-#REF!*$Q$17,2) -> #REF! | H26: =D26*F26 -> 14851.431
A27: 10 | B27: Рабочая документация Системы дымоудаления ("ДУ"), включая пояснительную записку (для помещений от 100 до 450 м.кв) | C27: кв.м.площади офиса | D27: =$D$5 -> 243 | E27: 99 | F27: =E27*(1-$D$7) -> 69.3 | G27: =ROUND(#REF!-#REF!*$Q$17,2) -> #REF! | H27: =D27*F27 -> 16839.9
A28: 11 | B28: Авторский надзор (без учета услуги по выездам представителя Подрядчика на Объект) | C28: месяц | D28: =D6 -> 2 | E28: =SUMPRODUCT(D18:D27,E18:E27)*D7/D28 -> 58557.29 | G28: =ROUND(#REF!-#REF!*$Q$17,2) -> #REF! | H28: =D28*E28 -> 117114.58
B31: ОПЦИОНАЛЬНЫЕ ПРОЕКТНЫЕ РАБОТЫ
B32: =B5 -> Средняя площадь проекта | C32: кв.м. | D32: =ROUND(D5/10,0) -> 24
B33: =B3 -> Количество проектов в данном диапазоне | C33: шт. | D33: =ROUND(D3/10,0) -> 6
B34: =B4 -> Общая площадь проектирования в данном диапазоне | C34: кв.м. | D34: =D32*D33 -> 144
B35: Проектные работы и согласования | D35: =SUM(D36:D42) -> 48 | H35: =SUM(H36:H37) -> 183960
A36: 1 | B36: Техническое обследование состояния несущих конструкций помещения с подготовкой рекомендаций по усилению (Техничесекое заключение о конструктиве - "ТЗК") (для помещений от 100 до 450 м.кв) | C36: кв.м. | D36: =D32 -> 24 | E36: 3500 | F36: =E36*(1-$D$7) -> 2450 | G36: =ROUND(#REF!-#REF!*$Q$17,2) -> #REF! | H36: =D36*F36 -> 58800
A37: 2 | B37: Эскизный проект фасада и Колористический паспорт с указанием ведомости отделки и проектным решением со спецификацией элементов (крыльцо, пандус, навесы, колонны и т.д.)(для фасадов от 100 до 450 м.кв) | C37: кв.м.площади фасада | D37: =D32 -> 24 | E37: 7450 | F37: =E37*(1-$D$7) -> 5215 | G37: =ROUND(#REF!-#REF!*$Q$17,2) -> #REF! | H37: =D37*F37 -> 125160
B41: Примечание: Услуги по выездам представителя Подрядчика на Объект в цену Работ не включены и оплачиваются дополнительно. При необходимости выезда представителя Подрядчика на Объект Заказчик несет расходы по оплате авиабилетов (эконом класс), ж/д билетов (купе, класс обслуживания 2С, 2В) до города и обратно, проживание в гостинице (стандартный номер стоимостью не более 4500 рублей в сутки), трансфер (2000 руб.) на каждого представителя Подрядчика. Возмещение расходов по оплате услуг раннего въезда\ позднего выезда производится согласно отчетным документам в полном объеме (в норму по оплате проживания данные услуги не включены). Необходимость выезда Подрядчика на объект должна быть подтверждена Заказчиком.
B42: Примечание: В течении производства Ремонтно-строительных работ Объекта вести авторский надзор (с присутствием на еженедельных рабочих группах в режиме on/off лайн), в соответствии с положением об авторском надзоре и другими нормативными требованиями в этой области. Вести журнал авторского надзора, своевременно занося в него выявленные при строительстве отступления от ПД, строительных норм и правил, технических условий по производству работ. Проводить работы по внесению всех изменений в проектную документацию всех разделов документации согласно требованиям представителей Технического надзора, Представителей служб Заказчика, авторов дизайн-проекта в течение 3-х рабочих дней.
B43: Примечание: Производство Ремонтно-строительных работ Объекта 2-3 месяца. Выезд на объект по согласованию с Заказчиком.

Sheet Список и контакты поставщиков
A1: ККО
A2: Инфраструктура
B3: Материал | C3: Производитель | D3: ФИО | E3: Телефон | F3: Электронная почта | G3: Наличие меморандума | H3: Срок окончания
B4: Керамогранит | C4: Kerama-Marazzi | D4: Александр Зуев | E4: +7 (926) 376-55-56 | F4: a.zuev@grestyle.ru | G4: да | H4: 45290
D5: Алексей Лукашов | E5: +7 (926) 376-53-70 | F5: a.lukashov@grestyle.ru
B6: Кондиционеры | C6: «Haier» | D6: Владимир Власенко | E6: 8 (926) 466-81-78 | F6: vladimir.vlasenko@haierrussia.ru | G6: да | H6: 45352
D7: Песин Андрей Олегович | E7: 8 (919) 991-27-22 | F7: andrey.pesin@haierrussia.ru
D8: Дмитриев Е.В. | E8: +7(916) 922-22-20 | F8: Evgeniy.Dmitriev@haierrussia.ru
C9: MDV («Дженерал-Трейд»)/ Mitsubishi Heavy | D9: Карпов Александр | E9: 8 (977) 477-19-97 | F9: akarpov@jac-company.com
D10: Комарова Наталья | F10: nkomarova@jac-company.com
C11: Daikin | D11: Ведущий специалист Куценко Екатерина Васильевна | E11: 7-495-73-73-73-3 (доб. 1786) | F11: Kutsenko@daichi.ru
D12: Заместитель генерального директора по работе с ключевыми клиентами Минаев Андрей Евгеньевич | E12: 7-495-73-73-73-3 (доб. 1702) | F12: Aminaev@daichi.ru
B13: Трансформируемая стеклянная перегородка | C13: ООО "Ктисис" | D13: Дубовицкая Ольга Юрьевна | E13: 8 913 774 32 31 | F13: rperegorodki@yandex.ru | G13: да | H13: 45291
B14: Вентиляция | C14: Globalvent | D14: Алейник Алена | E14: 8 985 270 67 65 | F14: aleinik.alena@gmail.com | G14: да | H14: 45291
C15: VTS | D15: Хусяинов Марат | E15: 8 926 281 00 51 | F15: Marat.Khusainov@vtsrussia.ru | G15: нет | H15: временно не ставим
B16: Бризер | C16: ТИОН | E16: 8 (800) 500-6029
D17: Васильева Наталья | E17: 8 913 915 18 85 | G17: нет | H17: договоренности по цене | I17: (находится в головном офисе в г. Новосибирск +4 часа от Москвы) .
B18: Проектирование | C18: ООО "Ронко" | D18: Романенко Евгений | E18: 8 916 833 86 48 | F18: romanenko@roncogroup.ru | G18: нет | H18: договоренности по цене
C19: ООО "ЛИБГОТ" | D19: Либгот Андрей Дмитриевич | E19: 8-977-330-33-10 | F19: libgotstroy@mail.ru
C20: ООО «ИНТЕЛЛЕКТ-СТРОЙПРОЕКТ» | D20: Шумова Алла Алексеевна. | E20: +7 (903) 587-10-40 | F20: archont15@yandex.ru | G20: нет | H20: договоренности по цене
B21: Лайтбоксы | C21: ООО «ЛЕД ДИЗАЙН» (ТД ПРОФЛЕД) | D21: Тишкова Алие Энверовна | E21: Моб.: 8-963-634-89-88 | F21: E-mail: tae@prof-led.ru | G21: да | H21: 45428
B22: Светильники | C22: ООО "ЭТМ" | D22: Шитов Михаил | E22: 8 (926) 208-37-90 | F22: shitov_ma@etm.ru, | G22: да | H22: 45427
B23: Сантехника, | C23: ООО "Дом мечты" | D23: Шихов Сергей | E23: 8 925 088 35 55 | F23: 17935@mail.ru | G23: нет | H23: договоренности по цене. Проводился выбор. Параллельный импорт. Оперативная замена с согласия ДУС.
B24: Керамическая плитка стены СУ (основной поставщик) | C24: ООО "Отделкино" | D24: Руев Сергей Викторович | E24: 8 920 859 42 13 | F24: ruev@otdelkino.ru | G24: да | H24: 45352
B25: Керамическая плитка стены СУ (резерв) | C25: ООО «Промлес» | D25: Коваленко Галина | E25: +7 (926) 820-03-26, | F25: kovalenko_gn@mosplitka.ru. | G25: да | H25: 45046
B26: Двери Kapelli | C26: Фабрика Kapelli (г. Ростов-на-Дону) | D26: Журавлёва Елена | E26: (863) 261-89-82 доб. 172., моб. 8950-843-15-45 | G26: да | H26: 45368 | I26: периодически корректируют по КП
B27: Щиты | C27: ООО "АВВ-электрощит" | D27: Александр Семенихин | E27: тел.: 8(495)152-25-52 моб. тел.: 8(966)666-24-92 | F27: aleksandr.s@abb-electro.ru www.abb-electro.ru | G27: да | H27: 45374
B28: ПВХ | C28: ООО "Опус-контаркт" | D28: Карнелия | E28: Моб. +7 (965) 209-57-09 , | F28: ksimonova@opuscontract.ru
B29: Тепловые завесы | C29: ООО "Тепломаш-Центр" | D29: Полунин Валерий Викторович | E29: 8(499)504-04-24, 8(916)850-11-40 | F29: polunin@teplomash.ru | G29: да | H29: 45291
B30: Радиаторы REFAR | C30: ООО "ТМ Инвест" | D30: Савелов Андрей | E30: +7 (495) 258-93-88, доб.212 моб. +7 (926) 716-43-58 | F30: sam@teplonet.ru | G30: да | H30: срок вышел нужен новый тендер
B31: Бронеизделия (лотки, панели, передаточный узел, бронедвери) и ПП двери | C31: ООО "СПЕЦ Прожект групп" | D31: Семихин Алексей Николаевич | E31: 8(904) 037-44-57 | F31: 4457@apit-kovrov.ru | G31: да | H31: отказ, идет конкурс
B32: Формат МИКРО (коробочное решение электрика), ЭУИ | C32: ООО "ТД "Электромонтаж" (ЭТМ) | D32: Шафигулин Рузил Рустемович | E32: 7 (926) 528-89-50 +7 (495) 668-70-10 (доб. 360) | F32: shafigulin_rr@etm.ru | G32: да | H32: 45449
D33: Шитов Михаил Александрович | E33: 7(926)208-37-90 | F33: shitov_ma@etm.ru
B34: ЭУИ | C34: ООО "Русский свет" | D34: Дмитрий Варданян | E34: +7 (495) 981-49-21, +7 (962) 985-51-88 | F34: mpp3@skm.russvet.ru | G34: да | H34: 45117
B35: Потолки грильято | C35: ООО "Профиль С" | E35: 8 495 221 31 31 доб. 104 , 8 985 300 35 87 | F35: potolki@griliato.ru | G35: да | H35: 45274 | I35: не используют
B36: Стеклянные двери в алюминиевом корпусе | C36: ООО "ФАСАДСТРОЙ" | D36: Светлана | E36: 79155597559 | F36: svetlanal80@mail.ru | G36: да | H36: срок вышел нужен новый тендер
B37: Бескаркасные двери и перегородки | C37: ООО "Вертикальный транспорт" | D37: Дегтярев С.Д. | E37: +7(903)-622-74-45. | F37: degtyarev.s.str@gmail.com
B38: Стеклянные двери и перегородки инфраструктура | C38: ООО "Вертикальный транспорт" | D38: Дегтярев С.Д. | E38: +7(903)-622-74-45. | F38: degtyarev.s.str@gmail.com
B39: Деревянные двери инфраструктура | C39: ООО "Вертикальный транспорт" | D39: Дегтярев С.Д. | E39: +7(903)-622-74-45. | F39: degtyarev.s.str@gmail.com
B40: Светильники инфраструктура | C40: ООО "Рефлекта" | E40: +7 (499) 755 95 87 | F40: info@reflectalight.ru
B41: Лючок напольный | C41: ООО "РусТрэйд" | D41: Брусник Алексей | E41: 89266597618 | F41: rustrade077@gmail.com; brusnic1@mail.ru
B42: ЭУИ | C42: ООО "ЭТМ" | D42: Шитов Михаил | E42: 8 (926) 208-37-90 | F42: shitov_ma@etm.ru,

Sheet АПС, СОУЭ, ППА
A1: Формат объекта | C1: Инфраструктура
A2: Адрес объекта: | B2: Адрес объекта: | C2: г. Москва, ул. Каланчевская, д. 29, стр. 2
A3: Плoщадь объекта (м.кв.): | B3: Плащадь объекта: | C3: =B37 -> 0
A4: Срок проведения работ | B4: Срок проведения работ
A5: ПОДРЯДЧИК: | B5: ПОДРЯДЧИК:
A6: Юридический адрес: | B6: Юридический адрес:
A7: Электронный адрес: | B7: Электронный адрес:
A8: Контактное лицо (Ф.И.О.) : | B8: Контактное лицо (Ф.И.О.) :
A9: Контактный телефон: | B9: Контактный телефон:
A10: Реквизиты: | B10: Реквизиты:
A11: Сумма по смете: | B11: Сумма по смете: | C11: =D38 -> 0
A12: Поз № | B12: Наименование помещений | D12: Ед.изм. | E12: Объем | F12: Цена за 1 кв.м. руб. с НДС руб.
A13: 1 | B13: Рабочая документация "Автоматическая пожарная сигнализация" (АПС) | D13: кв.м площади офиса | E13: 1 | F13: 67
A14: 2 | B14: Рабочая документация "Система оповещения и управления эвакуацией людей при пожаре" (СОУЭ) | D14: кв.м площади офиса | E14: 1 | F14: 39
A15: 3 | B15: Рабочая документация "Противопожарная автоматика (ППА), включая: | D15: кв.м площади офиса | E15: 1 | F15: =SUM(F16:F21) -> 39
A16: 3.1 | B16: Автоматизация системы внутреннего противопожарного водопровода (ВПВ) | D16: кв.м площади офиса | E16: 1 | F16: 8
A17: 3.2 | B17: Автоматизация системы противодымной вентиляции (ПДВ) | D17: кв.м площади офиса | E17: 1 | F17: 25
A18: 3.3 | B18: Автоматизация Системы отопления, вентиляции и кондиционирования (ОВиК) | D18: кв.м площади офиса | E18: 1 | F18: 3
A19: 3.4 | B19: Автоматизация Системы аварийного освещения (АО) | D19: кв.м площади офиса | E19: 1 | F19: 1
A20: 3.5 | B20: Автоматизации лифтовового хозяйства | D20: кв.м площади офиса | E20: 1 | F20: 1
A21: 3.6 | B21: Автоматизации Системы контроля управления доступом (СКУД) | D21: кв.м площади офиса | E21: 1 | F21: 1
A22: 4 | B22: Сметная документация на АПС, СОУЭ и ППА | D22: кв.м площади офиса | E22: 1 | F22: 5
B23: Базовая цена проектирования за 1 кв.м. | D23: кв.м площади офиса | E23: 1 | F23: =SUM(F13:F15)+F22 -> 150

Sheet Освещение Рефлекта
B2: Russia, Moscow region, 143902
B3: Balashikha, Sovetskaya str, 36, build.13
B4: tel/fax: +7 (495) 740-55-69
B5: E-mail: info@reflectalight.ru
A8: Спецификация № 194 /_01_07_2025_
A11: * - на предзаказе длины и прочие размеры согласовываются отдельно с конструктором +/- см
A14: Вид | B14: Тип | C14: Наименование | D14: Артикул | E14: Размеры, мм | F14: Цена, вкл. НДС, ₽ | G14: Цена, вкл. НДС, ₽ с ГП | H14: Сумма, ₽ | I14: Производитель | J14: Готовность к отгрузке | K14: Примечания
B15: L1 | C15: Rota D1000 MP ECO 42W-4000K CRI 90 Susp WHI - Светильник | D15: 2206905_ WHI | E15: D1000, H107 | F15: 32428.62 | G15: =F15*1.05 -> 34050.051 | H15: =F15*G15 -> 1.1041962e+09 | I15: REFLECTA
B16: L1 | C16: Rota D1000 MP ECO 42W-4000K CRI 90 Susp BLK - Светильник | D16: 2206905_ BLK | E16: D1000, H107 | F16: 32428.62 | G16: =F16*1.05 -> 34050.051 | H16: =F16*G16 -> 1.1041962e+09 | I16: REFLECTA
B17: L1A | C17: Rota D1000 MP ECO 42W-4000K CRI 90 Susp WHI Emerg- Светильник | D17: 2206905_ WHI Emg | E17: D1000, H107 | F17: 37564.695 | G17: =F17*1.05 -> 39442.93 | H17: =F17*G17 -> 1.4816616e+09 | I17: REFLECTA
B18: L1A | C18: Rota D1000 MP ECO 42W-4000K CRI 90 Susp BLK Emerg- Светильник | D18: 2206905_ BLK Emg | E18: D1000, H107 | F18: 37564.695 | G18: =F18*1.05 -> 39442.93 | H18: =F18*G18 -> 1.4816616e+09 | I18: REFLECTA
B19: L1.1 | C19: Rota D1000 MP ECO 54W-4000K CRI 90 L24 270mA Susp WHI - Светильник | D19: 2206911_ WHI | E19: D1000, H107 | F19: 33572.07 | G19: =F19*1.05 -> 35250.674 | H19: =F19*G19 -> 1.1834381e+09 | I19: REFLECTA
B20: L1.1 | C20: Rota D1000 MP ECO 54W-4000K CRI 90 L24 270mA Susp BLK - Светильник | D20: 2206911_ BLK | E20: D1000, H107 | F20: 33572.07 | G20: =F20*1.05 -> 35250.674 | H20: =F20*G20 -> 1.1834381e+09 | I20: REFLECTA
B21: L1.1A | C21: Rota D1000 MP ECO 54W-4000K CRI 90 L24 270mA Susp WHI Emerg- Светильник | D21: 2206911_ WHI Emerg | E21: D1000, H107 | F21: 38708.145 | G21: =F21*1.05 -> 40643.552 | H21: =F21*G21 -> 1.5732365e+09 | I21: REFLECTA
B22: L1.1A | C22: Rota D1000 MP ECO 54W-4000K CRI 90 L24 270mA Susp BLK Emerg- Светильник | D22: 2206911_ BLK Emg | E22: D1000, H107 | F22: 38708.145 | G22: =F22*1.05 -> 40643.552 | H22: =F22*G22 -> 1.5732365e+09 | I22: REFLECTA
B23: L1.2 | C23: Rota D1000 MP ECO 28W-4000K CRI 90 270mA Susp WHI - Светильник | D23: 2208013_ WHI | E23: D1000, H107 | F23: 32428.62 | G23: =F23*1.05 -> 34050.051 | H23: =F23*G23 -> 1.1041962e+09 | I23: REFLECTA
B24: L1.2 | C24: Rota D1000 MP ECO 28W-4000K CRI 90 270mA Susp BLK - Светильник | D24: 2208013_ BLK | E24: D1000, H107 | F24: 32428.62 | G24: =F24*1.05 -> 34050.051 | H24: =F24*G24 -> 1.1041962e+09 | I24: REFLECTA
B25: L1.2 | C25: Rota D1000 MP ECO 77W-4000K CRI 90 L24 Susp WHI - Светильник | D25: 2400467_ WHI | E25: D1000, H107 | F25: 33572.07 | G25: =F25*1.05 -> 35250.674 | H25: =F25*G25 -> 1.1834381e+09 | I25: REFLECTA
B26: L1.2 | C26: Rota D1000 MP ECO 77W-4000K CRI 90 L24 Susp BLK - Светильник | D26: 2400467_ BLK | E26: D1000, H107 | F26: 33572.07 | G26: =F26*1.05 -> 35250.674 | H26: =F26*G26 -> 1.1834381e+09 | I26: REFLECTA
... B75: C2.1 A | C75: MICA System D330 27W-4000K CRI 90 MP ECO BLK Emerg - Светильник | D75: 2206251 BLK Emg | E75: D330 | F75: 22532.58 | G75: =F75*1.05 -> 23659.209 | H75: =F75*G75 -> 5.3310302e+08 | I75: REFLECTA
B76: С2.1 | C76: MICA System Base Kit, ROW Susp BLK, L=XXXXmm - База | D76: 2100369_XXXX BLK | E76: 1000 | F76: 5958.225 | G76: =F76*1.05 -> 6256.1363 | H76: =F76*G76 -> 37275467 | I76: REFLECTA
B77: L4 | C77: Calida MP ECO 16W/mt-4000K CRI 90 R-8620 Line_2500 ROW Susp BLK | D77: 2204401_2500x60_ BLK | E77: 2500 | F77: 42521.22 | G77: =F77*1.05 -> 44647.281 | H77: =F77*G77 -> 1.8984569e+09 | I77: REFLECTA
C78: Calida MP ECO 16W/mt-4000K CRI 90 R-2850 Line_3575 ROW Susp BLK | D78: 2204401_3575x60_ BLK | E78: 3575 | F78: 60805.08 | G78: =F78*1.05 -> 63845.334 | H78: =F78*G78 -> 3.8821206e+09 | I78: REFLECTA
C79: Calida MP ECO 16W/mt-4000K CRI 90 R-8620 Line_5764 ROW Susp BLK | D79: 2204401_5764x60_ BLK | E79: 5764 | F79: 98037.135 | G79: =F79*1.05 -> 102938.99 | H79: =F79*G79 -> 1.0091844e+10 | I79: REFLECTA
B80: L4 | C80: Calida MP ECO 16W/mt-4000K CRI 90 R-XXX Line_XXXX ROW Susp WHI | D80: 2204401_XXXXx60_ WHI | E80: 1000 | F80: 17008.425 | G80: =F80*1.05 -> 17858.846 | H80: =F80*G80 -> 3.0375085e+08 | I80: REFLECTA
B81: L4 | C81: Calida MP ECO 16W/mt-4000K CRI 90 R-XXX Line_XXXX ROW Susp BLK | D81: 2204401_XXXXx60_ BLK | E81: 1000 | F81: 17008.425 | G81: =F81*1.05 -> 17858.846 | H81: =F81*G81 -> 3.0375085e+08 | I81: REFLECTA
B82: C15 | C82: Quark ON HE MP D30 8W-4000K CRI 90 H630 Ceil BLK - Светильник (драйвер выносной) | D82: 2202647 BLK | E82: D30, H630 | F82: 5465.1765 | G82: =F82*1.05 -> 5738.4353 | H82: =F82*G82 -> 31361562 | I82: REFLECTA
B83: C15.1 | C83: Quark ON HE MP D30 8W-4000K CRI 90 H420 Ceil BLK - Светильник (драйвер выносной) | D83: 2202635_ BLK | E83: D30, H420 | F83: 5063.121 | G83: =F83*1.05 -> 5316.2771 | H83: =F83*G83 -> 26916954 | I83: REFLECTA
B84: L3 | C84: Quark AIR HE D30 Lens 10` 2W-4000K CRI 90 H200 Susp BLK - Светильник | D84: 2503487 BLK | E84: D30, H200 | F84: 5013.687 | G84: =F84*1.05 -> 5264.3714 | H84: =F84*G84 -> 26393910 | I84: REFLECTA | J84: 4-6 недель
B85: L4 | C85: Quark AIR HE D30 Lens 10` 2W-4000K CRI 90 H300 Susp - Светильник | D85: 2503488 | E85: D30, H300 | F85: 5286.204 | G85: =F85*1.05 -> 5550.5142 | H85: =F85*G85 -> 29341150 | I85: REFLECTA
B86: L1 | C86: Quark AIR HE D30 Lens 10` 2W-4000K CRI 90 H500 Susp BLK - Светильник | D86: 2503489 BLK | E86: D30, H500 | F86: 5817.777 | G86: =F86*1.05 -> 6108.6659 | H86: =F86*G86 -> 35538856 | I86: REFLECTA | J86: 4-6 недель
B87: L2 | C87: Quark AIR HE D30 Lens 10` 2W-4000K CRI 90 H500 Susp Gold - Светильник | D87: 2503489 Gold | E87: D30, H500 | F87: 5817.777 | G87: =F87*1.05 -> 6108.6659 | H87: =F87*G87 -> 35538856 | I87: REFLECTA | J87: 4-6 недель
B88: L16 | C88: Quark ON IT D70 45` 8W-4000K CRI 90 H210 Ceil RAL3028 - Светильник | D88: 2308932 RAL3028 | E88: D70, H210 | F88: 7827.435 | G88: =F88*1.05 -> 8218.8068 | H88: =F88*G88 -> 64332176 | I88: REFLECTA
B89: L16A | C89: Quark ON IT D70 45` 8W-4000K CRI 90 H210 Ceil RAL3028 Emerg - Светильник | D89: 2308932 RAL3028 Emg | E89: D70, H210 | F89: 13691.16 | G89: =F89*1.05 -> 14375.718 | H89: =F89*G89 -> 1.9682026e+08 | I89: REFLECTA
B90: C12 | C90: Quark AIR IT MP D30 8W-4000K CRI 90 H420 Susp WHI - Светильник (драйвер выносной) | D90: 2201739_ WHI | E90: D30 H420 | F90: 6505.38 | G90: =F90*1.05 -> 6830.649 | H90: =F90*G90 -> 44435967 | I90: REFLECTA
B91: C12 | C91: Quark AIR IT MP D30 8W-4000K CRI 90 H420 Susp BLK - Светильник (драйвер выносной) | D91: 2201739_ BLK | E91: D30 H420 | F91: 6505.38 | G91: =F91*1.05 -> 6830.649 | H91: =F91*G91 -> 44435967 | I91: REFLECTA
B92: L3 | C92: Quark AIR HE MP D30 8W-4000K CRI 90 H420 Susp WHI - Светильник | D92: 2201251_ BLK | E92: D30 H420 | F92: 6505.38 | G92: =F92*1.05 -> 6830.649 | H92: =F92*G92 -> 44435967 | I92: REFLECTA
B93: L3 | C93: Quark AIR HE MP D30 8W-4000K CRI 90 H420 Susp BLK - Светильник | D93: 2201251_ BLK | E93: D30 H420 | F93: 6505.38 | G93: =F93*1.05 -> 6830.649 | H93: =F93*G93 -> 44435967 | I93: REFLECTA
B94: C14 | C94: Quark AIR HE D45 MP 8W-4000K CRI 90 H110 Susp BLK - Светильник | D94: 2503425_ BLK | E94: D45, H110 | F94: 5257.6755 | G94: =F94*1.05 -> 5520.5593 | H94: =F94*G94 -> 29025309 | I94: REFLECTA
B95: C14A | C95: Quark AIR HE D45 MP 8W-4000K CRI 90 H110 Susp BLK Emerg - Светильник | D95: 2503425_ BLK Emg | E95: D45, H110 | F95: 11121.4 | G95: =F95*1.05 -> 11677.471 | H95: =F95*G95 -> 1.2986983e+08 | I95: REFLECTA
C96: Quark AIR IT MP D45 12W-4000K CRI 90 H210 Susp WHI - Светильник + NECK Q45 IT - Декоративная насадка | D96: 2201786_ WHI + 2200018 | E96: D45 H210 | F96: 8383.095 | G96: =F96*1.05 -> 8802.2497 | H96: =F96*G96 -> 73790096 | I96: REFLECTA
C97: Quark AIR IT MP D45 12W-4000K CRI 90 H210 Susp BLK - Светильник + NECK Q45 IT - Декоративная насадка | D97: 2201786_ BLK + 2200018 | E97: D45 H210 | F97: 8383.095 | G97: =F97*1.05 -> 8802.2497 | H97: =F97*G97 -> 73790096 | I97: REFLECTA
B98: L8 | C98: Quark AIR IT MP D70 8W-4000K CRI 90 H210 Susp WHI - Светильник | D98: 2201851_ WHI | E98: D70 H210 | F98: 7143.255 | G98: =F98*1.05 -> 7500.4178 | H98: =F98*G98 -> 53577397 | I98: REFLECTA
B99: L8 | C99: Quark AIR IT MP D70 8W-4000K CRI 90 H210 Susp BLK - Светильник | D99: 2201851_ BLK | E99: D70 H210 | F99: 7143.255 | G99: =F99*1.05 -> 7500.4178 | H99: =F99*G99 -> 53577397 | I99: REFLECTA
B100: L9 | C100: Quark AIR IT MP D70 12W-4000K CRI 90 H210 Susp WHI - Светильник | D100: 2201857_ WHI | E100: D70 H210 | F100: 8103.375 | G100: =F100*1.05 -> 8508.5438 | H100: =F100*G100 -> 68947921 | I100: REFLECTA
B101: L9 | C101: Quark AIR IT MP D70 12W-4000K CRI 90 H210 Susp BLK - Светильник | D101: 2201857_ BLK | E101: D70 H210 | F101: 8103.375 | G101: =F101*1.05 -> 8508.5438 | H101: =F101*G101 -> 68947921 | I101: REFLECTA
B102: L9A | C102: Quark AIR IT MP D70 12W-4000K CRI 90 H210 Susp WHI Emerg - Светильник | D102: 2201857_ WHI Emg | E102: D70 H210 | F102: 13967.1 | G102: =F102*1.05 -> 14665.455 | H102: =F102*G102 -> 2.0483388e+08 | I102: REFLECTA
B103: L9A | C103: Quark AIR IT MP D70 12W-4000K CRI 90 H210 Susp BLK Emerg - Светильник | D103: 2201857_ BLK Emg | E103: D70 H210 | F103: 13967.1 | G103: =F103*1.05 -> 14665.455 | H103: =F103*G103 -> 2.0483388e+08 | I103: REFLECTA
B104: L11.1 | C104: Quark AIR HE MP D70 12W-4000K CRI 90 H210 Susp WHI - Светильник | D104: 2201293_ WHI | E104: D70 H210 | F104: 8103.375 | G104: =F104*1.05 -> 8508.5438 | H104: =F104*G104 -> 68947921 | I104: REFLECTA
B105: L11.1 | C105: Quark AIR HE MP D70 12W-4000K CRI 90 H210 Susp BLK - Светильник | D105: 2201293_ BLK | E105: D70 H210 | F105: 8103.375 | G105: =F105*1.05 -> 8508.5438 | H105: =F105*G105 -> 68947921 | I105: REFLECTA
B106: L11.1A | C106: Quark AIR HE MP D70 12W-4000K CRI 90 H210 Susp WHI Emerg- Светильник | D106: 2201293_ WHI Emg | E106: D70 H210 | F106: 13967.1 | G106: =F106*1.05 -> 14665.455 | H106: =F106*G106 -> 2.0483388e+08 | I106: REFLECTA
B107: L11.1A | C107: Quark AIR HE MP D70 12W-4000K CRI 90 H210 Susp BLK Emerg- Светильник | D107: 2201293_ BLK Emg | E107: D70 H210 | F107: 13967.1 | G107: =F107*1.05 -> 14665.455 | H107: =F107*G107 -> 2.0483388e+08 | I107: REFLECTA
B108: L4.1 | C108: Quark AIR IT Ref 45` D70 6W-4000K CRI 90 H210 Susp WHI - Светильник | D108: 2407161_ WHI | E108: D70 H210 | F108: 8103.375 | G108: =F108*1.05 -> 8508.5438 | H108: =F108*G108 -> 68947921 | I108: REFLECTA
B109: L4.1 | C109: Quark AIR IT Ref 45` D70 6W-4000K CRI 90 H210 Susp BLK - Светильник | D109: 2407161_ BLK | E109: D70 H210 | F109: 8103.375 | G109: =F109*1.05 -> 8508.5438 | H109: =F109*G109 -> 68947921 | I109: REFLECTA
... B153: L6.1 | C153: Quark IN HE D70 MP 8W-4000K CRI 90 Recess IP44 BLK - Светильник | D153: 2202126 IP44_ BLK | E153: D70 | F153: 7004.34 | G153: =F153*1.05 -> 7354.557 | H153: =F153*G153 -> 51513818 | I153: REFLECTA
B154: L5.1 | C154: AURA ALFA 49W-4000K CRI 90 M1200x800 EDG (Triangle) - Светильник | D154: 2204325 | E154: 1162x744 | F154: 36547.875 | G154: =F154*1.05 -> 38375.269 | H154: =F154*G154 -> 1.4025345e+09 | I154: REFLECTA
B155: L7.2 | C155: Longa 40 DI/IN 20W-4000K CRI 90 M700 270mA WALL RAL3028 - Светильник | D155: 2205875_ Reduced RAL3028 | E155: 701 | F155: 8053.29 | G155: =F155*1.05 -> 8455.9545 | H155: =F155*G155 -> 68098254 | I155: REFLECTA
B156: L17 | C156: Longa 40 DI 26W-4000K CRI 90 M900 WALL WHI - Светильник | D156: 2205838_ WHI | E156: 931 | F156: 12010.005 | G156: =F156*1.05 -> 12610.505 | H156: =F156*G156 -> 1.5145223e+08 | I156: REFLECTA
B157: L17A | C157: Longa 40 DI 26W-4000K CRI 90 M900 WALL WHI Emerg - Светильник | D157: 2205838_ WHI Emg | E157: 931 | F157: 17146.08 | G157: =F157*1.05 -> 18003.384 | H157: =F157*G157 -> 3.0868746e+08 | I157: REFLECTA
B158: L7.1 | C158: Longa 40 DI_IN 33W-4000K CRI 90 M1200 270mA WALL RAL3028 - Светильник | D158: 2205883_Reduced RAL3028 | E158: 1162 | F158: 14291.235 | G158: =F158*1.05 -> 15005.797 | H158: =F158*G158 -> 2.1445137e+08 | I158: REFLECTA
B159: L7.2A | C159: Longa 40 DI_IN 45W-4000K CRI 90 M1200 WALL RAL3028 Emerg - Светильник | D159: 2205883_RAL3028 Emg | E159: 1162 | F159: 19427.31 | G159: =F159*1.05 -> 20398.676 | H159: =F159*G159 -> 3.9629139e+08 | I159: REFLECTA
B160: L7.3 | C160: Longa 40 DI 33W-4000K CRI 90 M1200 WALL WHI - Светильник | D160: 2205842_ WHI | E160: 1162 | F160: 14291.235 | G160: =F160*1.05 -> 15005.797 | H160: =F160*G160 -> 2.1445137e+08 | I160: REFLECTA
B161: C8 | C161: Longa 40 DI 39W-4000K CRI 90 M1400 WALL BLK, L=1392mm - Светильник | D161: 2205846_ BLK | E161: 1392 | F161: 12298.829 | G161: =F161*1.05 -> 12913.77 | H161: =F161*G161 -> 1.5882424e+08 | I161: REFLECTA
B162: C8A | C162: Longa 40 DI 39W-4000K CRI 90 M1400 WALL BLK Emerg, L=1392mm - Светильник | D162: 2205846_ BLK Emg | E162: 1392 | F162: 17434.904 | G162: =F162*1.05 -> 18306.649 | H162: =F162*G162 -> 3.1917465e+08 | I162: REFLECTA
B163: L7.4 | C163: Longa 40 DI 29W/mt-4000K CRI 90 ROW WALL WHI - Светильник | D163: 2205850_XXX_ WHI | E163: 1000 | F163: 11040.677 | G163: =F163*1.05 -> 11592.71 | H163: =F163*G163 -> 1.2799136e+08 | I163: REFLECTA
B164: L13 | C164: Longa 40 DI ADJ 14W-4000K CRI 90 M500 WALL - Светильник | D164: 2205820 | E164: M500 | F164: 9216.585 | G164: =F164*1.05 -> 9677.4143 | H164: =F164*G164 -> 89192711 | I164: REFLECTA
B165: L6 | C165: FAT 8W-4000K CRI 90 H95 MP Ceil WHI - Светильник потолочный. Предусмотреть выход кабеля сбоку | D165: 2200576_ WHI | E165: D125 H95 | F165: 7351.155 | G165: =F165*1.05 -> 7718.7128 | H165: =F165*G165 -> 56741454 | I165: REFLECTA
B166: L6 | C166: FAT 8W-4000K CRI 90 H95 MP Ceil BLK - Светильник потолочный. Предусмотреть выход кабеля сбоку | D166: 2200576_ BLK | E166: D125 H95 | F166: 7351.155 | G166: =F166*1.05 -> 7718.7128 | H166: =F166*G166 -> 56741454 | I166: REFLECTA
B167: L6A | C167: FAT 8W-4000K CRI 90 H95 MP Ceil WHI Emerg - Светильник потолочный. Предусмотреть выход кабеля сбоку | D167: 2200576_ WHI Emerg | E167: D125 H95 | F167: 13214.88 | G167: =F167*1.05 -> 13875.624 | H167: =F167*G167 -> 1.8336471e+08 | I167: REFLECTA
B168: L6A | C168: FAT 8W-4000K CRI 90 H95 MP Ceil BLK Emerg - Светильник потолочный. Предусмотреть выход кабеля сбоку | D168: 2200576_ BLK Emerg | E168: D125 H95 | F168: 13214.88 | G168: =F168*1.05 -> 13875.624 | H168: =F168*G168 -> 1.8336471e+08 | I168: REFLECTA
B169: L6.1 | C169: FAT 12W-4000K CRI 90 H95 MP Ceil WHI - Светильник потолочный. Предусмотреть выход кабеля сбоку | D169: 2200580_ WHI | E169: D125 H95 | F169: 8143.065 | G169: =F169*1.05 -> 8550.2183 | H169: =F169*G169 -> 69624983 | I169: REFLECTA
B170: L6.1 | C170: FAT 12W-4000K CRI 90 H95 MP Ceil BLK - Светильник потолочный. Предусмотреть выход кабеля сбоку | D170: 2200580_ BLK | E170: D125 H95 | F170: 8143.065 | G170: =F170*1.05 -> 8550.2183 | H170: =F170*G170 -> 69624983 | I170: REFLECTA
B171: L15 | C171: FAT 12W-4000K CRI 90 H95 REF 45`Ceil WHI - Светильник | D171: 2309088_ WHI | E171: D125 H95 | F171: 9660.735 | G171: =F171*1.05 -> 10143.772 | H171: =F171*G171 -> 97996291 | I171: REFLECTA
B172: L15 | C172: FAT 12W-4000K CRI 90 H95 REF 45`Ceil BLK - Светильник | D172: 2309088_ BLK | E172: D125 H95 | F172: 9660.735 | G172: =F172*1.05 -> 10143.772 | H172: =F172*G172 -> 97996291 | I172: REFLECTA
B173: L15A | C173: FAT 12W-4000K CRI 90 H95 REF 45`Ceil WHI - Светильник. Аварийный блок выносной | D173: 2309088_ WHI Emg | E173: D125 H95 | F173: 15524.46 | G173: =F173*1.05 -> 16300.683 | H173: =F173*G173 -> 2.530593e+08 | I173: REFLECTA
B174: L15A | C174: FAT 12W-4000K CRI 90 H95 REF 45`Ceil BLK - Светильник. Аварийный блок выносной | D174: 2309088_ BLK Emg | E174: D125 H95 | F174: 15524.46 | G174: =F174*1.05 -> 16300.683 | H174: =F174*G174 -> 2.530593e+08 | I174: REFLECTA
B175: C3.4 | C175: FAT 8W-4000K CRI 90 H180 REF 45`Ceil WHI - Светильник | D175: 2502602_ WHI | E175: D125 H180 | F175: 8553.048 | G175: =F175*1.05 -> 8980.7004 | H175: =F175*G175 -> 76812362 | I175: REFLECTA
B176: C3.4 | C176: FAT 8W-4000K CRI 90 H180 REF 45`Ceil BLK - Светильник | D176: 2502602_ BLK | E176: D125 H180 | F176: 8553.048 | G176: =F176*1.05 -> 8980.7004 | H176: =F176*G176 -> 76812362 | I176: REFLECTA
... B212: L11.1A | C212: IEK Светильник ДСП 1304 18Вт 4000К IP65 600мм Emerg - Светильник | D212: 2409705 Emg | E212: 600x66 | F212: 7769.79 | G212: =F212*1.05 -> 8158.2795 | H212: =F212*G212 -> 63388118 | I212: Поставка REFLECTA
C213: Acc. Wire ↓ suspension 1500mm - Тросовый подвес с регулировкой внизу, 1 шт. | D213: 1400140 | F213: 917.595 | G213: =F213*1.05 -> 963.47475 | H213: =F213*G213 -> 884079.61 | I213: REFLECTA
C214: O-Brant D600, L1750 25W-4000K CRI 90 Susp BLK - Светильник | D214: 2503502_ BLK | E214: D600, L1750 | F214: 38701.372 | G214: =F214*1.05 -> 40636.441 | H214: =F214*G214 -> 1.572686e+09 | I214: REFLECTA
B215: L9 | C215: Ray IN D750 69W-4000K CRI 90 Susp WHI - Светильник | D215: 2206334_ WHI | E215: D750, H40 | F215: 25462.08 | G215: =F215*1.05 -> 26735.184 | H215: =F215*G215 -> 6.8073339e+08 | I215: REFLECTA
B216: L9 | C216: Ray IN D750 69W-4000K CRI 90 Susp BLK - Светильник | D216: 2206334_ BLK | E216: D750, H40 | F216: 25462.08 | G216: =F216*1.05 -> 26735.184 | H216: =F216*G216 -> 6.8073339e+08 | I216: REFLECTA
B217: L9A | C217: Ray IN D750 69W-4000K CRI 90 Susp WHI Emerg - Светильник | D217: 2206334_ WHI Emg | E217: D750, H40 | F217: 30598.155 | G217: =F217*1.05 -> 32128.063 | H217: =F217*G217 -> 9.8305944e+08 | I217: REFLECTA
B218: L9A | C218: Ray IN D750 69W-4000K CRI 90 Susp BLK Emerg - Светильник | D218: 2206334_ BLK Emg | E218: D750, H40 | F218: 30598.155 | G218: =F218*1.05 -> 32128.063 | H218: =F218*G218 -> 9.8305944e+08 | I218: REFLECTA
B219: L16.2 | C219: Ray IN D1000 69W-4000K CRI 90 270mA Susp WHI - Светильник | D219: 2206388_ Reduced WHI | E219: D1000, H40 | F219: 35442.225 | G219: =F219*1.05 -> 37214.336 | H219: =F219*G219 -> 1.3189589e+09 | I219: REFLECTA
B220: L16.2 | C220: Ray IN D1000 69W-4000K CRI 90 270mA Susp BLK - Светильник | D220: 2206388_ Reduced BLK | E220: D1000, H40 | F220: 35442.225 | G220: =F220*1.05 -> 37214.336 | H220: =F220*G220 -> 1.3189589e+09 | I220: REFLECTA
B221: L11 | C221: Agat Vertical D80 12W-4000K CRI 90 H200 Susp (ceiling rose incl.) WHI - Светильник | D221: 2409707_ WHI | E221: D80 H200 | F221: 11498.76 | G221: =F221*1.05 -> 12073.698 | H221: =F221*G221 -> 1.3883256e+08 | I221: REFLECTA
B222: L11A | C222: Agat Vertical D80 12W-4000K CRI 90 H200 Susp (ceiling rose incl.) WHI Emerg - Светильник | D222: 2409707_ WHI Emg | E222: D80 H200 | F222: 17362.485 | G222: =F222*1.05 -> 18230.609 | H222: =F222*G222 -> 3.1652868e+08 | I222: REFLECTA
B223: L6 | C223: Agat D80 35W-4000K CRI 90 M1200 Susp (драйвер выносной) WHI - Светильник | D223: 2309027_ WHI | E223: 1214 | F223: 18185.58 | G223: =F223*1.05 -> 19094.859 | H223: =F223*G223 -> 3.4725109e+08 | I223: REFLECTA
B224: L6A | C224: Agat D80 35W-4000K CRI 90 M1200 Susp (драйвер выносной) WHI Emerg - Светильник | D224: 2309027_ WHI Emg | E224: 1214 | F224: 24049.305 | G224: =F224*1.05 -> 25251.77 | H224: =F224*G224 -> 6.0728752e+08 | I224: REFLECTA
B225: L10 | C225: Agat D80 31W/mt-4000K CRI 90 ROW Susp WHI - Светильник | D225: 2309053_ WHI | E225: 2135 | F225: 31982.58 | G225: =F225*1.05 -> 33581.709 | H225: =F225*G225 -> 1.0740297e+09 | I225: REFLECTA
B226: L9.1 | C226: Agat D80 37W/mt-4000K CRI 90 2xL24 270mA ROW Susp WHI, L=2135mm - Светильник | D226: 2309054_2135 WHI | E226: 2135 | F226: 35180.46 | G226: =F226*1.05 -> 36939.483 | H226: =F226*G226 -> 1.299548e+09 | I226: REFLECTA
C227: Шинопровод подвесной цвет черный для светильников LXX: XXXX + XXXX + XXXX + XXXX + XXXX + XXXX | F227: 0 | G227: =F227*1.05 -> 0 | H227: =F227*G227 -> 0 | I227: Поставка REFLECTA
C228: Шинопровод черный 1м. | E228: 1000 | F228: 1507.275 | G228: =F228*1.05 -> 1582.6388 | H228: =F228*G228 -> 2385471.8 | I228: Поставка REFLECTA
C229: Шинопровод черный 2м. | E229: 2000 | F229: 3014.55 | G229: =F229*1.05 -> 3165.2775 | H229: =F229*G229 -> 9541887.3 | I229: Поставка REFLECTA
C230: Шинопровод черный 3м. | E230: 3000 | F230: 4521.825 | G230: =F230*1.05 -> 4747.9163 | H230: =F230*G230 -> 21469246 | I230: Поставка REFLECTA
C231: Токоподвод д/шинопровода Левый, черный | F231: 388.395 | G231: =F231*1.05 -> 407.81475 | H231: =F231*G231 -> 158393.21 | I231: Поставка REFLECTA
C232: Токоподвод д/шинопровода Правый, черный | F232: 388.395 | G232: =F232*1.05 -> 407.81475 | H232: =F232*G232 -> 158393.21 | I232: Поставка REFLECTA
C233: Заглушка, черная | F233: 40.635 | G233: =F233*1.05 -> 42.66675 | H233: =F233*G233 -> 1733.7634 | I233: Поставка REFLECTA
...

Sheet  Кондиционеры бытовые
B1: Тип | C1: Инвертор | D1: Мощность охлаждения, кВт | E1: Шум, не более, Дб | F1: Макс. длина трубопровода, м | G1: Кол-во внутр. блоков | H1: Доп. требования | I1: ООО "Хайер Электрикал Эпплаенсис РУС" | L1: Дженерал-Трейд (АЯК) - оборудование MDV (GD Midea)
I2: Модель | J2: Цена для Подрядчика Заказчика с НДС, в USD | K2: Цена для Заказчика с НДС, в USD | L2: Модель | M2: Цена для Подрядчика Заказчика с НДС, в USD | N2: Цена для Заказчика с НДС, в USD
P4: Уполномоченным лицом от «Haier» является:
A5: 1 | B5: Настенный 7 | C5: нет | D5: 2,0 - 2,3 | E5: 40 | H5: включая пульт | I5: HSU-07HSL103/R3-W(IN)/HSU-07HSL103/R3(OUT) | J5: 209 | K5: =J5*1.05 -> 219.45 | L5: MDSAJ-07HRN8 / MDOAJ-07HN8 | M5: 228 | N5: =M5*1.05 -> 239.4 | P5: Управляющий директор Фомичев С.Ю.
A6: 2 | B6: Настенный 9 | C6: нет | D6: 2,5 - 2,8 | E6: 40 | H6: включая пульт | I6: HSU-09HSL103/R3-W(IN)/HSU-09HSL103/R3(OUT) | J6: 231 | K6: =J6*1.05 -> 242.55 | L6: MDSAJ-09HRN8 / MDOAJ-09HN8 | M6: 254 | N6: =M6*1.05 -> 266.7 | P6: E-mail: info@haierrussia.ru
A7: 3 | B7: Настенный 12 | C7: нет | D7: 3,2 - 3,6 | E7: 42 | H7: включая пульт | I7: HSU-12HSL103/R3-W(IN)/HSU-12HSL103/R3(OUT) | J7: 292 | K7: =J7*1.05 -> 306.6 | L7: MDSAJ-12HRN8 / MDOAJ-12HN8 | M7: 313 | N7: =M7*1.05 -> 328.65 | P7: тел.: +7(495) 782-10-20
A8: 4 | B8: Настенный 18 | C8: нет | D8: 4,8 - 5,4 | E8: 45 | H8: включая пульт | I8: HSU-18HSL103/R3-W(IN)/HSU-18HSL103/R3(OUT) | J8: 478 | K8: =J8*1.05 -> 501.9 | L8: MDSAJ-18HRN8 / MDOAJ-18HN8 | M8: 498 | N8: =M8*1.05 -> 522.9 | P8: Для заказа оборудования:
A9: 5 | B9: Настенный 24 | C9: нет | D9: 6,1 - 7,1 | E9: 49 | H9: включая пульт | I9: HSU-24HSL103/R3-W(IN)/HSU-24HSL103/R3(OUT) | J9: 635 | K9: =J9*1.05 -> 666.75 | L9: MDSAJ-24HRN8 / MDOAJ-24HN8 | M9: 668 | N9: =M9*1.05 -> 701.4 | P9: Менеджер проектов направления систем кондиционирования Власенко В.
A10: 6 | B10: Кассетный 12 | C10: нет | D10: 3,3 - 3,7 | E10: 38 | H10: включая пульт | K10: =J10*1.05 -> 0 | L10: MDCA6-12HRN1 / T-MBQ4-03B / MDOU3-12HN1-L | M10: 537 | N10: =M10*1.05 -> 563.85 | P10: тел.: +7(495) 782-10-20 доб.129
A11: 7 | B11: Кассетный 18 | C11: нет | D11: 4,6 - 5,4 | E11: 49 | H11: включая пульт | K11: =J11*1.05 -> 0 | L11: MDCA6-18HRN1 / T-MBQ4-03B / MDOU3-18HN1-L | M11: 587 | N11: =M11*1.05 -> 616.35 | P11: моб.: +7(926) 466-81-78
A12: 8 | B12: Кассетный 24 | C12: нет | D12: 6,8 - 7,5 | E12: 48 | H12: включая пульт | K12: =J12*1.05 -> 0 | L12: MDCF-24HRN1 / T-MBQ4-04B / MDOU3-24HN1-L | M12: 769 | N12: =M12*1.05 -> 807.45 | P12: E-mail: vladimir.vlasenko@haierrussia.ru
A13: 9 | B13: Кассетный 30 | C13: нет | D13: 7,1 - 8,5 | E13: 50 | H13: включая пульт | K13: =J13*1.05 -> 0 | L13: MDCF-24HRN1 / T-MBQ4-04B / MDOU3-24HN1-L | M13: 769 | N13: =M13*1.05 -> 807.45
A14: 10 | B14: Кассетный 36 | C14: нет | D14: 9,7 - 11 | E14: 53 | H14: включая пульт | K14: =J14*1.05 -> 0 | L14: MDCF2-36HRN1 / T-MBQ4-04B / MDOU3-36HN1-L | M14: 1064 | N14: =M14*1.05 -> 1117.2
A15: 11 | B15: Кассетный 48 | C15: нет | D15: 13,5 - 14,1 | E15: 52 | H15: включая пульт | K15: =J15*1.05 -> 0 | L15: MDCF-48HRN1 / T-MBQ4-04B / MDOU3-48HN1-L | M15: 1215 | N15: =M15*1.05 -> 1275.75 | P15: Уполномоченным лицом от «Дженерал-Трейд» является:
A16: 12 | B16: Кассетный 54 | C16: нет | D16: 14,3 - 16,2 | E16: 52 | H16: включая пульт | K16: =J16*1.05 -> 0 | L16: MDCF2-60HRN1 / T-MBQ4-04B / MDOU3-60HN1-L | M16: 1554 | N16: =M16*1.05 -> 1631.7 | P16: Директор по развитию Нуждин Владимир Юрьевич
A17: 13 | B17: Напольно - потолочный 18 | C17: нет | D17: 5,0 - 5,5 | E17: 46 | H17: включая пульт | K17: =J17*1.05 -> 0 | P17: E-mail: vnuzhdin@profcond.com
A18: 14 | B18: Напольно - потолочный 24 | C18: нет | D18: 6,5 - 7,7 | E18: 52 | H18: включая пульт | K18: =J18*1.05 -> 0 | L18: MDUE-24HRN1 / MDOU3-24HN1-L | M18: 748 | N18: =M18*1.05 -> 785.4 | P18: Тел.: +7 (800) 234-56-05, добавочный номер 271
A19: 15 | B19: Напольно - потолочный 36 | C19: нет | D19: 10,0 - 11,5 | E19: 54 | H19: включая пульт | K19: =J19*1.05 -> 0 | L19: MDUE2-36HRN1 / MDOU3-36HN1-L | M19: 1079 | N19: =M19*1.05 -> 1132.95 | P19: Моб.: +7 (903)7110106(WhatsApp)
A20: 16 | B20: Напольно - потолочный 48 | C20: нет | D20: 13,4 - 14,2 | E20: 55 | H20: включая пульт | K20: =J20*1.05 -> 0 | L20: MDUE-48HRN1 / MDOU3-48HN1-L | M20: 1313 | N20: =M20*1.05 -> 1378.65 | P20: Для заказа оборудования:
A21: 17 | B21: Напольно - потолочный 60 | C21: нет | D21: 15,0 - 17,6 | E21: 56 | H21: включая пульт | K21: =J21*1.05 -> 0 | L21: MDUE-60HRN1 / MDOU3-60HN1-L | M21: 1505 | N21: =M21*1.05 -> 1580.25 | P21: Карпов Александр
A22: 18 | B22: Канальный 18 | C22: нет | D22: 4,8 - 5,3 | E22: 44 | H22: включая пульт и раздаточный пленум | K22: =J22*1.05 -> 0 | P22: Тел.: +7 (800) 234-56-05, добавочный номер 285
A23: 19 | B23: Канальный 24 | C23: нет | D23: 7,0 - 7,4 | E23: 49 | H23: включая пульт и раздаточный пленум | K23: =J23*1.05 -> 0 | L23: MDTJ2-24HWN1 / MDOU3-24HN1-L | M23: 757 | N23: =M23*1.05 -> 794.85 | P23: моб.: +7 (9776) 477-19-97
A24: 20 | B24: Канальный 36 | C24: нет | D24: 10,0 - 10,6 | E24: 50 | H24: включая пульт и раздаточный пленум | K24: =J24*1.05 -> 0 | L24: MDTJ2-36HWN1 / MDOU3-36HN1-L | M24: 1091 | N24: =M24*1.05 -> 1145.55 | P24: E-mail: akarpov@jac-company.com
A25: 21 | B25: Канальный 48 | C25: нет | D25: 13,4 - 14,1 | E25: 53 | H25: включая пульт и раздаточный пленум | K25: =J25*1.05 -> 0 | L25: MDTJ2-48HWN1 / MDOU3-48HN1-L | M25: 1332 | N25: =M25*1.05 -> 1398.6 | P25: Комарова Наталья
A26: 22 | B26: Канальный 60 | C26: нет | D26: 15,0 - 16,2 | E26: 53 | H26: включая пульт и раздаточный пленум | K26: =J26*1.05 -> 0 | L26: MDTJ2-60HWN1 / MDOU3-60HN1-L | M26: 1543 | N26: =M26*1.05 -> 1620.15 | P26: Тел.: +7 (800) 234-56-05
A27: 23 | B27: Настенный 7 | C27: да | D27: 2,0 - 2,3 | E27: 40 | H27: включая пульт | I27: AS20HQJ2HRA-W/1U20HQJ2FRA | J27: 292 | K27: =J27*1.05 -> 306.6 | L27: MDSI-07HRDN8 (WF) / MDOI-07HDN8 | M27: 327 | N27: =M27*1.05 -> 343.35 | P27: моб.:
A28: 24 | B28: Настенный 9 | C28: да | D28: 2,5 - 2,8 | E28: 40 | H28: включая пульт | I28: AS25HQJ2HRA-W/1U25HQJ2FRA | J28: 316 | K28: =J28*1.05 -> 331.8 | L28: MDSI-09HRDN8 (WF) / MDOI-09HDN8 | M28: 345 | N28: =M28*1.05 -> 362.25
A29: 25 | B29: Настенный 12 | C29: да | D29: 3,2 - 3,6 | E29: 42 | H29: включая пульт | I29: AS35HQJ2HRA-W/1U35HQJ2FRA | J29: 363 | K29: =J29*1.05 -> 381.15 | L29: MDSI-12HRDN8 (WF) / MDOI-12HDN8 | M29: 426 | N29: =M29*1.05 -> 447.3
A30: 26 | B30: Настенный 18 | C30: да | D30: 4,8 - 5,4 | E30: 45 | H30: включая пульт | I30: AS50HQJ2HRA-W/1U50HQJ2FRA | J30: 556 | K30: =J30*1.05 -> 583.8 | L30: MDSI2-18HRFN8 / MDOI2-18HFN8 | M30: 708 | N30: =M30*1.05 -> 743.4
A31: 27 | B31: Настенный 24 | C31: да | D31: 6,1 - 7,1 | E31: 49 | H31: включая пульт | I31: AS70HQJ2HRA-W/1U70HQJ2FRA | J31: 696 | K31: =J31*1.05 -> 730.8 | L31: MDSI2-24HRFN8 / MDOI2-24HFN8 | M31: 860 | N31: =M31*1.05 -> 903
A32: 28 | B32: Кассетный 12 | C32: да | D32: 3,3 - 3,7 | E32: 38 | H32: включая пульт | I32: AB35S2SC1FA/1U35S2SM4FA/PB-700KB | J32: 761 | K32: =J32*1.05 -> 799.05 | L32: MDCAC4I-12HRFN8 / T-MBQ4-03BD / MDOAG-12HFN8 | M32: 611 | N32: =M32*1.05 -> 641.55
A33: 29 | B33: Кассетный 18 | C33: да | D33: 4,6 - 5,4 | E33: 49 | H33: включая пульт | I33: AB50S2SC1FA/1U50S2SJ3FA/PB-700KB | J33: 970 | K33: =J33*1.05 -> 1018.5 | L33: MDCAC4I-18HRFN8 / T-MBQ4-03BD / MDOAG-18HFN8 | M33: 851 | N33: =M33*1.05 -> 893.55
A34: 30 | B34: Кассетный 24 | C34: да | D34: 6,8 - 7,5 | E34: 48 | H34: включая пульт | I34: AB71S2LR2FA/1U71S1LR2FA/PB-950QB(P) | J34: 759 | K34: =J34*1.05 -> 796.95 | L34: MDCD-24HRFN8 / T-MBQ4-04BD / MDOUN-24HFN8 | M34: 1207 | N34: =M34*1.05 -> 1267.35
A35: 31 | B35: Кассетный 30 | C35: да | D35: 7,1 - 8,5 | E35: 50 | H35: включая пульт | I35: AB71S2LR2FA/1U71S1LR2FA/PB-950QB(P) | J35: 759 | K35: =J35*1.05 -> 796.95 | L35: MDCD-24HRFN8 / T-MBQ4-04BD / MDOUN-24HFN8 | M35: 1207 | N35: =M35*1.05 -> 1267.35
A36: 32 | B36: Кассетный 36 | C36: да | D36: 9,7 - 11 | E36: 53 | H36: включая пульт | I36: AB105S2LR2FA/1U105S1LS2FB/PB-950QB(P) | J36: 1026 | K36: =J36*1.05 -> 1077.3 | L36: MDCD-36HRFN8 / T-MBQ4-04BD / MDOU-36HFN8 | M36: 1819 | N36: =M36*1.05 -> 1909.95
A37: 33 | B37: Кассетный 48 | C37: да | D37: 13,5 - 14,1 | E37: 52 | H37: включая пульт | I37: AB140S2LR2FA/1U140S2LN2FB/PB-950QB(P) | J37: 1160 | K37: =J37*1.05 -> 1218 | L37: MDCD-48HRFN8 / T-MBQ4-04BD / MDOUN-48HFN8 | M37: 2004 | N37: =M37*1.05 -> 2104.2
A38: 34 | B38: Кассетный 54 | C38: да | D38: 14,3 - 16,2 | E38: 52 | H38: включая пульт | I38: AB160S2LR2FA/1U160S2LN2FB/PB-950QB(P) | J38: 1350 | K38: =J38*1.05 -> 1417.5 | L38: MDCD-60HRFN8 / T-MBQ4-04BD / MDOUN-60HFN8 | M38: 2516 | N38: =M38*1.05 -> 2641.8
A39: 35 | B39: Напольно - потолочный 18 | C39: да | D39: 5,0 - 5,5 | E39: 46 | H39: включая пульт | I39: AC50S1LG2FA/1U50S1LM2FA | J39: 655 | K39: =J39*1.05 -> 687.75 | L39: MDUE-18HRFN8 / MDOU-18HFN8 | M39: 909 | N39: =M39*1.05 -> 954.45
... A48: 44 | B48: Канальный 60 | C48: да | D48: 15,0 - 16,2 | E48: 53 | H48: включая пульт и раздаточный пленум | I48: AD160S2LM1FA/1U160S1LN1FB | J48: 1623 | K48: =J48*1.05 -> 1704.15 | L48: MDT2I-60HWFN8 / MDOUN-60HFN8 | M48: 2470 | N48: =M48*1.05 -> 2593.5
A49: 45 | B49: Мульти-сплит внешн. блок | C49: да | D49: 4,7 - 5,3 | E49: 57 | F49: 20 - 40 | G49: 2 | H49: включая пульт | I49: 2U50S2SM1FA-3 | J49: 630 | K49: =J49*1.05 -> 661.5 | L49: MD2O-18HFN8 | M49: 1049 | N49: =M49*1.05 -> 1101.45
A50: 46 | B50: Мульти-сплит внешн. блок | C50: да | D50: 5,4 - 7,1 | E50: 62 | F50: 30 - 60 | G50: 2 | H50: включая пульт | I50: 3U55S2SR5FA | J50: 920 | K50: =J50*1.05 -> 966 | L50: MD3O-21HFN8 | M50: 1110 | N50: =M50*1.05 -> 1165.5
A51: 47 | B51: Мульти-сплит внешн. блок | C51: да | D51: 7,2 - 8,3 | E51: 65 | F51: 45 - 80 | G51: 3 - 4 | H51: включая пульт | I51: 4U75S2SR5FA | J51: 1150 | K51: =J51*1.05 -> 1207.5 | L51: MD4O-28HFN8 | M51: 1216 | N51: =M51*1.05 -> 1276.8
A52: 48 | B52: Мульти-сплит внешн. блок | C52: да | D52: 9,0 - 11,7 | E52: 67 | F52: 60 - 85 | G52: 4 - 5 | H52: включая пульт | I52: 5U90S2SS5FA | J52: 1277 | K52: =J52*1.05 -> 1340.85 | L52: MD4O-36HFN8 | M52: 2137 | N52: =M52*1.05 -> 2243.85
A53: 49 | B53: Мульти-сплит внешн. блок | C53: да | D53: 10,7 - 14,7 | E53: 67 | F53: 60 - 135 | G53: 4 - 8 | H53: включая пульт | I53: 5U105S2SS5FA | J53: 1458 | K53: =J53*1.05 -> 1530.9 | L53: MD5OB-42HFN8 | M53: 2199 | N53: =M53*1.05 -> 2308.95
A54: 50 | B54: Мульти-сплит внешн. блок | C54: да | D54: 13,5 - 16,7 | E54: 69 | F54: 75 - 145 | G54: 5 - 9 | H54: включая пульт | I54: 5U125S2SN1FA | J54: 1747 | K54: =J54*1.05 -> 1834.35
A55: 51 | B55: Мульти-сплит настенный внутр. блок | C55: да | D55: 1,5 - 2,0 | E55: 28 | H55: включая беспроводной пульт | I55: AS20PS1HRA-M | J55: 156 | K55: =J55*1.05 -> 163.8 | L55: MDSAJ-07HRFN8 | M55: 123 | N55: =M55*1.05 -> 129.15
A56: 52 | B56: Мульти-сплит настенный внутр. блок | C56: да | D56: 2,0 - 2,2 | E56: 29 | H56: включая беспроводной пульт | I56: AS20PS1HRA-M | J56: 156 | K56: =J56*1.05 -> 163.8 | L56: MDSAJ-09HRFN8 | M56: 136 | N56: =M56*1.05 -> 142.8
A57: 53 | B57: Мульти-сплит настенный внутр. блок | C57: да | D57: 2,6 - 2,8 | E57: 29 | H57: включая беспроводной пульт | I57: AS25PS1HRA-M | J57: 164 | K57: =J57*1.05 -> 172.2 | L57: MDSAJ-12HRFN8 | M57: 164 | N57: =M57*1.05 -> 172.2
A58: 54 | B58: Мульти-сплит настенный внутр. блок | C58: да | D58: 3,5 - 3,6 | E58: 34 | H58: включая беспроводной пульт | I58: AS35PS1HRA-M | J58: 176 | K58: =J58*1.05 -> 184.8 | L58: MDSAJ-18HRFN8 | M58: 226 | N58: =M58*1.05 -> 237.3
A59: 55 | B59: Мульти-сплит настенный внутр. блок | C59: да | D59: 5,1 - 5,6 | E59: 42 | H59: включая беспроводной пульт | I59: AS50PS1HRA-M | J59: 211 | K59: =J59*1.05 -> 221.55 | L59: MDSAJ-24HRFN8 | M59: 272 | N59: =M59*1.05 -> 285.6
A60: 56 | B60: Мульти-сплит настенный внутр. блок | C60: да | D60: 6,7 - 7,1 | E60: 45 | H60: включая беспроводной пульт | I60: AS70PS1HRA-M | J60: 276 | K60: =J60*1.05 -> 289.8 | L60: MDSAJ-24HRFN8 | M60: 272 | N60: =M60*1.05 -> 285.6
A61: 57 | B61: Мульти-сплит кассетный внутр. блок | C61: да | D61: 1,5 - 2,0 | E61: 32 | H61: включая беспроводной пульт и декоративную панель | I61: AB25S2SC1FA/PB-700KB | J61: 318 | K61: =J61*1.05 -> 333.9 | L61: MDCAC4I-07HRFN8 / T-MBQ4-03BD | M61: 321 | N61: =M61*1.05 -> 337.05
A62: 58 | B62: Мульти-сплит кассетный внутр. блок | C62: да | D62: 2,0 - 2,2 | E62: 34 | H62: включая беспроводной пульт и декоративную панель | I62: AB25S2SC1FA/PB-700KB | J62: 318 | K62: =J62*1.05 -> 333.9 | L62: MDCAC4I-07HRFN8 / T-MBQ4-03BD | M62: 321 | N62: =M62*1.05 -> 337.05
A63: 59 | B63: Мульти-сплит кассетный внутр. блок | C63: да | D63: 2,6 - 2,8 | E63: 36 | H63: включая беспроводной пульт и декоративную панель | I63: AB25S2SC1FA/PB-700KB | J63: 318 | K63: =J63*1.05 -> 333.9 | L63: MDCAC4I-09HRFN8 / T-MBQ4-03BD | M63: 329 | N63: =M63*1.05 -> 345.45
A64: 60 | B64: Мульти-сплит кассетный внутр. блок | C64: да | D64: 3,5 - 3,6 | E64: 38 | H64: включая беспроводной пульт и декоративную панель | I64: AB35S2SC1FA/PB-700KB | J64: 329 | K64: =J64*1.05 -> 345.45 | L64: MDCAC4I-12HRFN8 / T-MBQ4-03BD | M64: 339 | N64: =M64*1.05 -> 355.95
A65: 61 | B65: Мульти-сплит кассетный внутр. блок | C65: да | D65: 4,5 - 5,6 | E65: 42 | H65: включая беспроводной пульт и декоративную панель | I65: AB50S2SC1FA/PB-700KB | J65: 338 | K65: =J65*1.05 -> 354.9 | L65: MDCAC4I-18HRFN8 / T-MBQ4-03BD | M65: 377 | N65: =M65*1.05 -> 395.85
A66: 62 | B66: Мульти-сплит кассетный внутр. блок | C66: да | D66: 6,5 - 7,1 | E66: 44 | H66: включая беспроводной пульт и декоративную панель | I66: AB71S2SG1FA/PB-950KB | J66: 475 | K66: =J66*1.05 -> 498.75
A67: 63 | B67: Мульти-сплит канальный внутр. блок | C67: да | D67: 2,2 - 2,7 | E67: 35 | H67: включая беспроводной пульт | I67: AD25S2SS1FA | J67: 309 | K67: =J67*1.05 -> 324.45 | L67: MDT2II-09HWFN8 | M67: 295 | N67: =M67*1.05 -> 309.75
A68: 64 | B68: Мульти-сплит канальный внутр. блок | C68: да | D68: 3,2 - 3,6 | E68: 35 | H68: включая беспроводной пульт | I68: AD35S2SS1FA | J68: 315 | K68: =J68*1.05 -> 330.75 | L68: MDT2II-12HWFN8 | M68: 323 | N68: =M68*1.05 -> 339.15
A69: 65 | B69: Мульти-сплит канальный внутр. блок | C69: да | D69: 5,0 - 5,6 | E69: 40 | H69: включая беспроводной пульт | I69: AD50S2SS1FA | J69: 367 | K69: =J69*1.05 -> 385.35 | L69: MDT2II-18HWFN8 | M69: 375 | N69: =M69*1.05 -> 393.75
A70: 66 | B70: Мульти-сплит канальный внутр. блок | C70: да | D70: 6,5 - 7,2 | E70: 42 | H70: включая беспроводной пульт | I70: AD71S2SS1FA | J70: 406 | K70: =J70*1.05 -> 426.3 | L70: MDT2II-24HWFN8 | M70: 403 | N70: =M70*1.05 -> 423.15
A71: 67 | B71: Мульти-сплит напольно-потолочный внутр. блок | C71: да | D71: 2,5 - 2,8 | E71: 38 | H71: включая беспроводной пульт | I71: AC35S2SG1FA | J71: 408 | K71: =J71*1.05 -> 428.4
A72: 68 | B72: Мульти-сплит напольно-потолочный внутр. блок | C72: да | D72: 3,5 - 4,5 | E72: 42 | H72: включая беспроводной пульт | I72: AC35S2SG1FA | J72: 408 | K72: =J72*1.05 -> 428.4
A73: 69 | B73: Мульти-сплит напольно-потолочный внутр. блок | C73: да | D73: 5,0 - 5,6 | E73: 45 | H73: включая беспроводной пульт | I73: AC50S2SG1FA | J73: 430 | K73: =J73*1.05 -> 451.5
A74: 70 | B74: Мульти-сплит напольно-потолочный внутр. блок | C74: да | D74: 6,5 - 7,5 | E74: 46 | H74: включая беспроводной пульт | I74: AC71S2SG1FA | J74: 478 | K74: =J74*1.05 -> 501.9
B75: Настенный 24 | I75: AS70S2SF3FA-W/1U70S2SJ2FA | J75: 1360 | K75: =J75*1.05 -> 1428
B76: Обязательные требования: | C76: Хладагент R-410A
C77: Цвет оборудования - белый
C78: Все оборудование должно быть с режимами работы тепло - холод.
C79: Во всех внутренних блоках должны быть установлены фильтры тонкой очистки.

Sheet Сантехника
B1: Наименование | C1: Фабрика | D1: Артикул | E1: Старая цена | G1: Кол-во, шт. | H1: Новая цена | I1: Техническая информация | J1: Стоимость для Альфа-Банка | K1: Замена | L1: Старая цена | M1: 46206 | N1: письмо УЦЗ
A2: 1 | B2: Унитаз подвесной SantiLine SL-5007 безободковый, с микролифтом | C2: SantiLine | D2: SL-5007 | E2: 13750 | G2: 1 | H2: 12180 | J2: =ROUNDUP(H2*1.05,2) -> 12789 | L2: 12180
A3: 3 | B3: Раковина SantiLine SL-2005 | C3: SantiLine | D3: SL-2005 | E3: 5168 | G3: 1 | H3: 6900 | J3: =ROUNDUP(H3*1.05,2) -> 7245 | L3: 7200
B4: CN6014 Умывальник Ceramicanova чаша накладная круглая Element 435*435*135мм | C4: Ceramicanova | D4: CN6014 | G4: 1 | H4: 7890 | J4: =ROUNDUP(H4*1.05,2) -> 8284.5 | L4: 6409
A5: 5 | B5: Смеситель для раковины IDEAL STANDARD CERALINE BC193AA однорычажный, хром | C5: Ideal Standard | E5: 7550 | G5: 1 | H5: 10900 | J5: =ROUNDUP(H5*1.05,2) -> 11445 | L5: 9290
A6: 6 | B6: Сифон для раковины Viega 100674 Хром | C6: Viega | D6: 100674 | E6: 3392 | G6: 1 | H6: 3070 | J6: =ROUNDUP(H6*1.05,2) -> 3223.5 | K6: Сифон, GROHE, 1 1/4 заменен 21.11.23 | L6: 2800
A7: 7 | B7: Инсталляция для подвесного унитаза Aquatek Standart 37 INS-0000017, кнопка Акватек KDI-0000016 хром | C7: Aquatek | D7: 366527 | E7: 14342 | G7: 1 | H7: 13126 | J7: =ROUNDUP(H7*1.05,2) -> 13782.3
A8: 8 | B8: Смеситель гигиенический Ideal Standart DB130AA | C8: Ideal Standard | D8: DB130AA | E8: 15400 | G8: 1 | H8: 11540 | J8: =ROUNDUP(H8*1.05,2) -> 12117 | L8: 10990
B9: Зеркало с встроенным светильником и сенсорным выключателем 12W, 220-240V, 600x30 | C9: belbagno | D9: SPC-RNG-600-LED-TCH | E9: 8300 | G9: 1 | H9: 8900 | J9: =ROUNDUP(H9*1.05,2) -> 9345 | L9: 8300
B10: Рама для монтажа PROSYS R016367 писсуара с задней подводкой | D10: R016367 | E10: =SUM(E2:E9) -> 67902 | G10: 1 | H10: 19390 | J10: =ROUNDUP(H10*1.05,2) -> 20359.5
B11: LEMARK Смывное устройство для писсуара, сенсорное, встраиваемое | C11: LEMARK | D11: LM4657CE | G11: 1 | H11: 14890 | J11: =ROUNDUP(H11*1.05,2) -> 15634.5
B12: Душевая дверь в нишу River SUEZ 80 МТ 10000000740 | C12: River | D12: 10000000740 | G12: 1 | H12: 11520 | J12: =ROUNDUP(H12*1.05,2) -> 12096
B13: Душевая дверь в нишу Allen Brau Приорити (Priority) 3.31003.BBA 90 | C13: Allen Brau | D13: 3.31003.BBA | G13: 1 | H13: 26300 | J13: =ROUNDUP(H13*1.05,2) -> 27615
B14: AQ2060MB ВЕГА душевая система AQUATEK (смеситель для душа) 3jet 250мм, матовый черный | C14: AQUATEK | D14: AQ2060MB | G14: 1 | H14: 19600 | J14: =ROUNDUP(H14*1.05,2) -> 20580
B15: Комплект TECElinus для монтажа дренажного канала с основой для плитки “tile” и панелью “steel” 2 в 1 Комплект поставки: Дренажный канал из нержавеющей стали; Сифон DN 50, выход вбок, производительность (согласно DIN EN 1253) при уровне воды 10/20 мм над решеткой: 0,7/0,8 л/с; высота гидрозатвора = 25 мм согласно DIN EN 1253; Гидроизоляционная манжета; Стакан гидрозатвора с мембраной; Комплект опор, высота до 125 мм (до уровня чистового пола); Двухсторонняя вставка 2 в 1: основа для плитки “tile” и панель “steel” | C15: TECElinus | D15: 15103079 | G15: 1 | H15: 26190 | J15: =ROUNDUP(H15*1.05,2) -> 27499.5
B16: Ванна моечная моповая КОБОР ВМБ/1-50/50 | C16: КОБОР | D16: ВМБ/1-50/50 | G16: 1 | H16: 16730 | J16: =ROUNDUP(H16*1.05,2) -> 17566.5
B17: Смеситель для ванны Rossinka S35-33 универсальный | C17: Rossinka | D17: S35-33 | G17: 1 | H17: 5900 | J17: =ROUNDUP(H17*1.05,2) -> 6195
B18: Сифон для умывальника бутылочный 1 1/4"x40 с гофрой 40х40/50 выпуск с нержавеющей решёткой D=65мм АНИ Пласт C1015 | C18: АНИ пласт | D18: C1015 | G18: 1 | H18: 410 | J18: =ROUNDUP(H18*1.05,2) -> 430.5
B19: FR212X300R1BM Верхний душ, Splendy, Feeling R, тип установки-настенный, потолочный, размер душевого диска, мм-300*300, форма-круглая, количество режимов-1, тип струи-дождь (Rain), держатель-необходимо заказать, материал-латунь, цвет-черный матовый | C19: Splendy | D19: FR212X300R1BM | G19: 1 | H19: 13200 | J19: =ROUNDUP(H19*1.05,2) -> 13860
B20: AA213N380RBM Держатель верхнего душа, Splendy, вид-настенный, вынос, мм-380, круглый отражатель, материал-латунь, цвет-черный матовый | C20: Splendy | D20: AA213N380RBM | G20: 1 | H20: 4300 | J20: =ROUNDUP(H20*1.05,2) -> 4515
B21: Термостатический смеситель встраиваемый Splendy Passion PA204U2T3BM С ВНУТРЕННЕЙ ЧАСТЬЮ, черный матовый | C21: Splendy | D21: PA204U2T3BM | G21: 1 | H21: 30600 | J21: =ROUNDUP(H21*1.05,2) -> 32130
B22: Мойка для кухни Granula 4445U графит матовый, 44х45 см, квадратная | C22: Granula | D22: Granula | G22: 1 | H22: 21870 | J22: =ROUNDUP(H22*1.05,2) -> 22963.5
B23: Смеситель для кухни Omoikiri Kanto PVD-GM с гибким изливом | C23: Omoikiri | D23: Kanto PVD-GM | G23: 1 | H23: 39960 | J23: =ROUNDUP(H23*1.05,2) -> 41958
B24: Поручень для инсталляции Aquatek POR-0000004, хром, 800 мм | C24: Aquatek | D24: POR-0000004 | G24: 1 | H24: 7930 | J24: =ROUNDUP(H24*1.05,2) -> 8326.5
B25: Поручень AQUATEK AQ4996CR латунь, хром, настенный 650 мм | C25: AQUATEK | D25: AQ4996CR | G25: 1 | H25: 4150 | J25: =ROUNDUP(H25*1.05,2) -> 4357.5
B26: Комплект AQ1905-MB ВЕГА Унитаз подвесной безободковый 525*360*320мм, тонкое сиденье с механизмом плавного закрывания, крепеж, цвет матовый черный, INS-0000017 Aquatek Инсталляция для подвесного унитаза узкая Aquatek Standart 37, 1130*370*150 мм, +звукоизоляционная прокладка, KDI-0000012 (001D) Панель смыва Черная матовая (клавиши квадрат) | C26: AQUATEK | G26: 1 | H26: 28160 | J26: =ROUNDUP(H26*1.05,2) -> 29568
B27: торговая сеть, смеситель для раковины Allen Brau Priority 5.31001-31, цвет черный матовый | C27: Allen Brau | D27: 5.31001-31 | G27: 1 | H27: 13080 | J27: =ROUNDUP(H27*1.05,2) -> 13734
B28: смеситель с гигиеническим душем Allen Brau Priority 5.31A29-31 (с внутренней частью), цвет черный матовый | C28: Allen Brau | D28: 5.31A29-31 | G28: 1 | H28: 11880 | J28: =ROUNDUP(H28*1.05,2) -> 12474
B29: Донный клапан для раковины Splendy AA3071NORMBM без перелива, матовый черный | C29: Splendy | D29: AA3071NORMBM | G29: 1 | H29: 1820 | J29: =ROUNDUP(H29*1.05,2) -> 1911
B30: Смеситель сенсорный Swedbe Europe 6000-220 | C30: Swedbe | D30: 6000-220 | G30: 1 | H30: 14760 | J30: =ROUNDUP(H30*1.05,2) -> 15498 | L30: 14064
B31: ES3300 CREAVIT Кран для писсуара сенсорный | C31: CREAVIT | D31: ES3300 | H31: 28030 | J31: =ROUNDUP(H31*1.05,2) -> 29431.5 | L31: 27571
B32: Раковина Creavit Next NX242-00CB00E-0000 белая (Ширина: 500 мм, Высота: 130 мм, Глубина: 400 мм) | C32: Creavit | D32: NX242-00CB00E-0000 | H32: 10390 | J32: =ROUNDUP(H32*1.05,2) -> 10909.5 | L32: 9460
B33: HB66 Донный клапан для раковины Haiba без перелива, хром | C33: Haiba | D33: HB66 | H33: 980 | J33: =ROUNDUP(H33*1.05,2) -> 1029 | L33: 660
B34: HB80 Сифон для раковины Haiba хром | C34: Haiba | D34: HB80 | H34: 1290 | J34: =ROUNDUP(H34*1.05,2) -> 1354.5 | L34: 1085
B35: E253701 i.life Писсуар Ideal Standard, задняя подводка, с крепежами и фитингами в комплекте. Безободковая чаша без | C35: Ideal Standard | D35: E253701 | H35: 22360 | J35: =ROUNDUP(H35*1.05,2) -> 23478 | L35: 20370
B36: W00750 Унитаз напольный безободковый торнадо с быстросъемным дюропласт сиденьем микролифт Watersense Aurora TORNADO | D36: W00750 | H36: 11800 | J36: =ROUNDUP(H36*1.05,2) -> 12390 | K36: взамен Jika Baltic 2428.6 - снят с производства | M36: 46223 | N36: уточнение от 06.07.26
B37: 770230001 Damixa Jupiter смеситель для раковины с гигиеническим душем | C37: Damixa | D37: 770230001 | H37: 9800 | J37: =ROUNDUP(H37*1.05,2) -> 10290 | M37: 46223
B49: Поставщик: Шихов Сергей тел.89250883555 E-mail: 17935@mail.ru

Sheet Тепловые завесы
J2: СПИСОК ФИЛИАЛОВ И ПРЕДСТАВИТЕЛЬСТВ ПОСТАВЩИКА:
B3: Наименование | C3: Артикул | D3: Единица измерения | E3: Цена за ед. с НДС, руб. для подрядчика | F3: Цена за ед. с НДС, руб. для Заказчика | J3: №№ | K3: Регион/город | L3: Адрес | M3: Контактная информация | P3: цены до 18.04.
B4: Компактная воздушно-тепловая завеса КЭВ-3П1154Е | C4: 121021 | D4: шт | E4: 11482.5 | F4: =ROUND(E4*1.05,2) -> 12056.63 | J4: 1 | K4: Центральный | L4: г. Москва, Батюнинский проезд, д. 10, строение 3 | M4: Телефон: +7 (499) 504-04-24 | P4: 9185.4
B5: Компактная воздушно-тепловая завеса КЭВ-6П2212E | C5: 122002 | D5: шт | E5: 24240 | F5: =ROUND(E5*1.05,2) -> 25452 | M5: E-mail: mos@teplomash.ru | P5: 20723.85
B6: Компактная воздушно-тепловая завеса КЭВ-9П3012E | C6: 123037 | D6: шт | E6: 42600 | F6: =ROUND(E6*1.05,2) -> 44730 | J6: 2 | K6: Северо-Западный | L6: г. Санкт-Петербург, ш. Революции, д.90 | M6: +7 (812) 380-13-27 | P6: 36364.2
B7: Компактная воздушно-тепловая завеса КЭВ-12П3042E | C7: 123040 | D7: шт | E7: 47512.5 | F7: =ROUND(E7*1.05,2) -> 49888.13 | M7: toh@teplomash.ru | P7: 41580
E8: цены с 01.09.25 | J8: 3 | K8: Урал | L8: г. Екатеринбург, ул. Шефская, 2а | M8: +7 (343) 385-68-98
B9: Уполномоченным лицом Поставщика является: | M9: ural@teplomash.ru
B10: Генеральный директор Козин Алексей Витальевич, | J10: 4 | K10: Сибирь | L10: г. Новосибирск, ул. Н.Островского, 49 | M10: +7 (383) 363-00-23
B11: контактный телефон: +7(499)504-04-24, моб.: +7(916)324-04-24, | M11: nsk@teplomash.ru
B12: эл.почта: kozin@teplomash.ru
B13: Общая эл.почта отдела продаж: mos@teplomash.ru
B15: Главный специалист отдела продаж Полунин Валерий Викторович,
B16: контактный телефон: +7(499)504-04-24, моб.:+7(916)850-11-40, эл.почта: polunin@teplomash.ru

Sheet Светильники ЭТМ
A1: название компании | B1: ООО "СИЛЕД" | G1: АО "ТД "ЭЛЕКТРОТЕХМОНТАЖ"
A2: адрес электронной почты | B2: faa@siled.ru | G2: Шитов Михаил Александрович <shitov_ma@etm.ru> Шафигуллин Рузил Рустемович" <shafigulin_rr@etm.ru>
A3: контактное лицо | B3: Фролов Алексей | G3: Шитов Михаил Александрович, Шафигуллин Рузил Рустемович
A4: производитель | B4: https://siled.ru/ | G4: Арлайт/Центрстройсвет
B5: 8 (977) 950-91-05
A6: Производство SILED | B6: Аналог МДМ | C6: Един. изм. | D6: приблиз кол-во в год | E6: Цена за ед. с НДС, руб | F6: Цена за ед с НДС для Банка | G6: Наименование ЭТМ | H6: Артикул | I6: Един. изм. | J6: приблиз кол-во в год | K6: Цена за ед. с НДС, руб | L6: Цена за ед с НДС для Банка | O6: 46262
A7: Комплект подвеса для шинопровода 3000 мм (SILED)КРАСНЫЙ ГЛАДКИЙ 3020 | B7: NS.1705.22.05/RU-TRACK / LINE Комплект подвеса для шинопровода 3000 мм (БОСМА)КРАСНЫЙ ГЛАДКИЙ 3020 | C7: шт | D7: 176 | E7: 490 | F7: =ROUND(E7*1.09,2) -> 534.1 | G7: Подвес LGD-4TR-HANG-2-WH © | H7: 024280 | I7: шт | J7: 176 | K7: 516.78 | L7: =ROUND(K7*1.05,2) -> 542.62
A8: Комплект линейного соединения для св-ка LA LINEA SILED | B8: Комплект линейного соединения для св-ка RETA (БОСМА) | C8: шт | D8: 24 | E8: 279 | F8: =ROUND(E8*1.09,2) -> 304.11 | G8: Коннектор прямой LGD-4TR-CON-LONG-WH © | H8: 028836 | I8: шт | J8: 24 | K8: 828.22 | L8: =ROUND(K8*1.05,2) -> 869.63
A9: Светильник светодиодный трековый SILED LINE SPOT 20W 4000K/CRI80 45 гр КРАСНЫЙ RAL3020 | B9: NS.0076.21.133/TUNIC LED spot II 18W 4000K/CRI80 45 гр/Пр-р(Evercore)(БОСМА)КРАСНЫЙ RAL3020 | C9: шт | D9: 140 | E9: 3728 | F9: =ROUND(E9*1.09,2) -> 4063.52 | G9: Светильник LGD-GERA-4TR-R74-20W Day4000 (WH, 24 deg, 230V) | H9: 024085(2) | I9: шт | J9: 140 | K9: 2453.31 | L9: =ROUND(K9*1.05,2) -> 2575.98
A10: SILED Шинопровод 3000 мм КРАСНЫЙ | B10: RU-TRACK / LINE 4300 Шинопровод 3000 мм КРАСНЫЙ | C10: шт | D10: 32 | E10: 4680 | F10: =ROUND(E10*1.09,2) -> 5101.2 | G10: Трек LGD-4TR-TRACK-3000-WH-M © | H10: 046092 | I10: шт | J10: 32 | K10: 6545.42 | L10: =ROUND(K10*1.05,2) -> 6872.69
A11: SILED Шинопровод 2000 мм КРАСНЫЙ | B11: RU-TRACK / LINE 4200 Шинопровод 2000 мм КРАСНЫЙ | C11: шт | D11: 12 | E11: 3120 | F11: =ROUND(E11*1.09,2) -> 3400.8 | G11: Трек LGD-4TR-TRACK-2000-WH-M © | H11: 026140(2) | I11: шт | J11: 12 | K11: 4044.08 | L11: =ROUND(K11*1.05,2) -> 4246.28
A12: SILED Шинопровод 1000 мм КРАСНЫЙ | B12: RU-TRACK / LINE 4100 Шинопровод 1000 мм КРАСНЫЙ | C12: шт | D12: 24 | E12: 1560 | F12: =ROUND(E12*1.09,2) -> 1700.4 | G12: Трек LGD-4TR-TRACK-1000-WH-M © | H12: 030562(2) | I12: шт | J12: 24 | K12: 2286.61 | L12: =ROUND(K12*1.05,2) -> 2400.94
A13: SILED Шинопровод 2500 мм КРАСНЫЙ | B13: RU-TRACK / LINE 4250 Шинопровод 2500 мм КРАСНЫЙ | C13: шт | D13: 4 | E13: 3900 | F13: =ROUND(E13*1.09,2) -> 4251 | G13: Трек LGD-4TR-TRACK-3000-WH-M © | H13: 046092 | I13: шт | J13: 4 | K13: 6545.42 | L13: =ROUND(K13*1.05,2) -> 6872.69
A14: SILED Шинопровод 1500 мм КРАСНЫЙ | B14: RU-TRACK / LINE 4150 Шинопровод 1500 мм КРАСНЫЙ | C14: шт | D14: 4 | E14: 2340 | F14: =ROUND(E14*1.09,2) -> 2550.6 | G14: Трек LGD-4TR-TRACK-2000-WH-M © | H14: 026140(2) | I14: шт | J14: 4 | K14: 4044.08 | L14: =ROUND(K14*1.05,2) -> 4246.28
A15: SILED / XTS 11-3 Токоподвод левый КРАСНЫЙ ГЛАДКИЙ МАТОВЫЙ RAL3020 | B15: NS.1705.22.01/RU-TRACK / LINE 11-3 Токоподвод левый (БОСМА)КРАСНЫЙ ГЛАДКИЙ МАТОВЫЙ RAL3020 | C15: шт | D15: 48 | E15: 465 | F15: =ROUND(E15*1.09,2) -> 506.85 | G15: Коннектор питания LGD-4TR-CON-POWER-L-WH © | H15: 024714 | I15: шт | J15: 48 | K15: 422.07 | L15: =ROUND(K15*1.05,2) -> 443.17
A16: SILED / XTS 41-3 Заглушка для шинопровода КРАСНЫЙ ГЛАДКИЙ МАТОВЫЙ RAL3020 | B16: NS.1705.22.02/RU-TRACK / LINE 41-3 Заглушка для шинопровода (БОСМА)КРАСНЫЙ ГЛАДКИЙ МАТОВЫЙ RAL3020 | C16: шт | D16: 48 | E16: 89 | F16: =ROUND(E16*1.09,2) -> 97.01 | G16: Заглушка LGD-4TR-CAP-WH © | H16: 024729 | I16: шт | J16: 48 | K16: 70 | L16: =ROUND(K16*1.05,2) -> 73.5
A17: SILED / XTS 21 Cтык внутренний КРАСНЫЙ ГЛАДКИЙ МАТОВЫЙ RAL3020 | B17: NS.1705.22.03/RU-TRACK / LINE 21 Cтык внутренний (БОСМА)КРАСНЫЙ ГЛАДКИЙ МАТОВЫЙ RAL3020 | C17: шт | D17: 24 | E17: 465 | F17: =ROUND(E17*1.09,2) -> 506.85 | G17: Коннектор внутренний LGD-4TR-CON-MINI-WH © | H17: 042557 | I17: шт | J17: 24 | K17: 482.95 | L17: =ROUND(K17*1.05,2) -> 507.1
A18: SILED / SKB 18-3 Усилитель стыка для шинопровода КРАСНЫЙ ГЛАДКИЙ 3020 | B18: NS.1705.22.04/RU-TRACK / LINE 18-3 Усилитель стыка для шинопровода (БОСМА)КРАСНЫЙ ГЛАДКИЙ 3020 | C18: шт | D18: 24 | E18: 348 | F18: =ROUND(E18*1.09,2) -> 379.32 | G18: Зажим LGD-4TR-CLIP-WH © | H18: 024727 | I18: шт | J18: 24 | K18: 482.95 | L18: =ROUND(K18*1.05,2) -> 507.1
... A22: Светильник светодиодный SILED LA LINEA 3000 75W 4000K Ra80, МИКРОПРИЗМА, 2968 мм КРАСНЫЙ ГЛАДКИЙ 3020 в комплекте с подвесом и заглушками | B22: NS.0076.21.163/RETA SN 84W 4000K Ra80/Св-к LED,МИКРОПРИЗМА,3000мм(подв)(БОСМА)КРАСНЫЙ ГЛАДКИЙ 3020 в комплекте с подвесом и заглушками | C22: шт | D22: 165 | E22: 8395 | F22: =ROUND(E22*1.09,2) -> 9150.55 | G22: CSVT FLORA-50 70 3040х50х70 CRI80 4000 microprisma IP40 красный AB (в комплекте с подвесом и заглушками) | H22: ЦБ-00009023 | I22: шт | J22: 165 | K22: 7052 | L22: =ROUND(K22*1.05,2) -> 7404.6
G23: Светильник светодиодный CSVT FLORA-50 27 993х50х70 CRI80 4000 microprisma-opal IP40 черный RAL9005 подвесной/накладной met AB SW-007 | H23: ЦБ-00013391 | I23: шт | K23: 2998 | L23: =ROUND(K23*1.05,2) -> 3147.9
G24: Светильник светодиодный CSVT FLORA-50 36 1540х50х70 CRI80 4000 microprisma-opal IP40 черный RAL9005 подвесной/накладной met AB SW-007 | H24: ЦБ-00013392 | I24: шт | K24: 4183 | L24: =ROUND(K24*1.05,2) -> 4392.15
G25: Светильник светодиодный CSVT SLIM 32 1262х124х85 CRI80 4000 milky IP65 II серый подвесной/накладной | H25: ЦБ-00010703 | I25: шт | K25: 1464 | L25: =ROUND(K25*1.05,2) -> 1537.2
G27: Требования: | H27: ДА/НЕТ
G28: "единое окно" для подачи заказа | H28: ДА
G29: бесплатный светотехнический расчет всех площадок | H29: ДА
G30: бесплатный "несгораемый" складской запас на 5 отделений | H30: ДА
G31: срок отправки не более 15 календарных дней с момента заказа | H31: ДА
G32: адрес склада отгрузки | H32: Отгрузка с ближайшего склада к отделению

Sheet Светильники Профдед н
B2: № | C2: № по смете | D2: Аналог | E2: Наименование аналога Профлед(артикул) | F2: Един. изм. | G2: Кол - во. (объем) | H2: Цена материалов и оборудования для подрядчика. руб., в т.ч. НДС | I2: Цена материалов и оборудования для Банка. руб., в т.ч. НДС с учетом генподрядных | K2: письмо ДЦЗ 12.08.26
E3: наименование аналога | F3: Цена за ед. с НДС, руб | H3: Цена за ед. с НДС, руб | I3: Цена Для Заказчика с учетом генподрядных
E4: ORTUS SORES 650 св-к накладной LED 53W/4000K (СЕРЫЙ RAL 7047 МАТОВЫЙ) | F4: шт. | H4: 29455 | I4: =ROUND(H4*1.05,2) -> 30927.75
E5: ORTUS SORES 650 св-к подвесной LED 53W/4000K подвес 1,5м (СЕРЫЙ RAL 7047 МАТОВЫЙ) | F5: шт. | H5: 29455 | I5: =ROUND(H5*1.05,2) -> 30927.75
E6: ORTUS SORES 1000 св-к подвесной/накладной LED 76W/4000K (КРАСНЫЙ RAL 3020 ШАГРЕНЬ) | F6: шт. | H6: 40945 | I6: =ROUND(H6*1.05,2) -> 42992.25
E7: ORTUS SORES 1000 св-к подвесной/накладной LED 76W/4000K DIMM 0-10V (КРАСНЫЙ RAL 3020 ШАГРЕНЬ) | F7: шт. | H7: 50025 | I7: =ROUND(H7*1.05,2) -> 52526.25
E8: ORTUS SORES 1500 св-к подвесной LED 124W/4000K DIMM 0-10V (КРАСНЫЙ RAL 3020 ШАГРЕНЬ) | F8: шт. | H8: 84555 | I8: =ROUND(H8*1.05,2) -> 88782.75
E9: ORTUS SORES 2000 св-к подвесной LED 192W/4000K DIMM 0-10V (КРАСНЫЙ RAL 3020 ШАГРЕНЬ) | F9: шт. | H9: 121975 | I9: =ROUND(H9*1.05,2) -> 128073.75
E10: ORTUS SORES 2500 св-к подвесной LED 285W/4000K DIMM 0-10V (КРАСНЫЙ RAL 3020 ШАГРЕНЬ) | F10: шт. | H10: 301000 | I10: =ROUND(H10*1.05,2) -> 316050
E11: Пульт SMART-R10-DIM (4 зоны, 2.4G) | F11: шт. | H11: 3824.42 | I11: =ROUND(H11*1.05,2) -> 4015.64

Sheet Двери Kapelli
AB1: Цена до 09.06.22 | AH1: Цена до 18.07.22
B2: Наименование | C2: шт. | D2: Цена | E2: Стоимость | J2: С уважением, Фабрика дверей KAPELLI | Z2: 23960 | AB2: Наименование | AC2: шт. | AD2: Цена | AE2: Стоимость | AH2: Наименование | AI2: шт. | AJ2: Цена | AK2: Стоимость
B3: Блок с усилением под доводчик | C3: 1 | D3: =D17 -> 13025 | E3: =C3*D3 -> 13025 | J3: менеджер отдела сбыта Журавлёва Елена | AB3: Блок с усилением под доводчик | AC3: 1 | AD3: 11340 | AE3: =AC3*AD3 -> 11340 | AH3: Блок с усилением под доводчик | AI3: 1 | AJ3: 10080 | AK3: =AI3*AJ3 -> 10080
B4: Наличник | C4: 5 | D4: 510 | E4: =C4*D4 -> 2550 | J4: 344064, г.Ростов-на-Дону, ул. Вавилова, д.63 А | AB4: Наличник | AC4: 5 | AD4: 590 | AE4: =AC4*AD4 -> 2950 | AH4: Наличник | AI4: 5 | AJ4: 500 | AK4: =AI4*AJ4 -> 2500
B5: Добор | C5: 2.5 | D5: 690 | E5: =C5*D5 -> 1725 | J5: Контакты: (863) 261-89-82 доб. 172. | AB5: Добор | AC5: 2.5 | AD5: 680 | AE5: =AC5*AD5 -> 1700 | AH5: Добор | AI5: 2.5 | AJ5: 590 | AK5: =AI5*AJ5 -> 1475
B6: Ручка V44L-2 (компл) | C6: 1 | D6: 1962 | E6: =C6*D6 -> 1962 | F6: закупается отдельно (не у Капелли). | J6: Моб.тел.: 8950-843-15-45 | AB6: Ручка V44L-2 (компл) | AC6: 1 | AD6: 1500 | AE6: =AC6*AD6 -> 1500 | AF6: закупается отдельно (не у Капелли). | AH6: Ручка V44L-2 (компл) | AI6: 1 | AJ6: 1500 | AK6: =AI6*AJ6 -> 1500 | AL6: закупается отдельно (не у Капелли).
B7: Замок магнитный хром | C7: 1 | D7: =D24 -> 395 | E7: =C7*D7 -> 395 | J7: email: zhuravleva1545@yandex.ru | AB7: Замок магнитный хром | AC7: 1 | AD7: 650 | AE7: =AC7*AD7 -> 650 | AH7: Замок магнитный хром | AI7: 1 | AJ7: 650 | AK7: =AI7*AJ7 -> 650
B8: Петли накладные хром | C8: 2 | D8: =D30 -> 75 | E8: =C8*D8 -> 150 | J8: Skype: zhuravleva.e1 | AB8: Петли накладные хром | AC8: 2 | AD8: 168 | AE8: =AC8*AD8 -> 336 | AH8: Петли накладные хром | AI8: 2 | AJ8: 168 | AK8: =AI8*AJ8 -> 336
B9: Накладка на цилиндр ET-02 L-2/ Накладка сантехническая ВК02 L-2 | C9: 1 | D9: 350 | E9: =C9*D9 -> 350 | F9: закупается отдельно (не у Капелли). | J9: ICQ: 681713269 | AB9: Накладка на цилиндр ET-02 L-2/ Накладка сантехническая ВК02 L-2 | AC9: 1 | AD9: 402 | AE9: =AC9*AD9 -> 402 | AH9: Накладка на цилиндр ET-02 L-2/ Накладка сантехническая ВК02 L-2 | AI9: 1 | AJ9: 402 | AK9: =AI9*AJ9 -> 402
B10: Цилиндр ключ-фиксатор хром | C10: 1 | D10: =D27 -> 280 | E10: =C10*D10 -> 280 | J10: www.kapelli-doors.ru | AB10: Цилиндр ключ-фиксатор хром | AC10: 1 | AD10: 458 | AE10: =AC10*AD10 -> 458 | AH10: Цилиндр ключ-фиксатор хром | AI10: 1 | AJ10: 458 | AK10: =AI10*AJ10 -> 458
B11: Итого цена для подрядчика: | E11: =SUM(E3:E10) -> 20437 | AB11: Итого цена для подрядчика: | AE11: =SUM(AE3:AE10) -> 19336 | AH11: Итого цена для подрядчика: | AK11: =SUM(AK3:AK10) -> 17401
B12: Итого цена для Заказчика с учетом ГП. | E12: =ROUNDUP(E11*1.05,2) -> 21458.85 | AB12: Итого цена для Заказчика с учетом ГП. | AE12: =AE11*1.09 -> 21076.24 | AH12: Итого цена для Заказчика с учетом ГП. | AK12: =AK11*1.09 -> 18967.09
A16: № | B16: Наименование | C16: Единица измерения | D16: Цена за ед. с НДС, руб. | F16: КП от 18.08.26 | H16: ранее КП от 10.06.25
A17: 1 | B17: ДГ 21-10 КАПЕЛЬ Гладкая МС7035 (полотно 2000*900, ДКТ80) УД | C17: компл | D17: 13025
A18: 2 | B18: ДГ 21-9 КАПЕЛЬ Гладкая МС7035 (полотно 2000*800, ДКТ80) УД | C18: компл | D18: 13025
A19: 3 | B19: ДГ 21-8 КАПЕЛЬ Гладкая МС7035 (полотно 2000*700, ДКТ80) УД | C19: компл | D19: 13025
A20: 4 | B20: ДГ 21-7 КАПЕЛЬ Гладкая МС7035 (полотно 2000*600, ДКТ80) УД | C20: компл | D20: 13025
A21: 5 | B21: Наличник F ПВХ 2,17м серый 7035 телескопический | C21: шт | D21: 525
A22: 6 | B22: Добор для F-наличника серый 7035 (5х100х2070мм) | C22: шт | D22: 465
A23: 7 | B23: Добор для F-наличника серый 7035 (5х150х2070мм) | C23: шт | D23: 695
A24: 8 | B24: Замок магнитный (под цилиндр / под фиксатор) | C24: шт | D24: 395 | F24: уточнение цены на фурнитуру 28.02.26
A25: 9 | B25: Замок механический (под цилиндр / под фиксатор) | C25: шт | D25: 415
A26: 10 | B26: Цилиндр (клю-ключ) | C26: шт | D26: 250
A27: 11 | B27: Цилиндр (ключ-фиксатор) | C27: шт | D27: 280
A28: 12 | B28: Накладка под цилиндр | C28: шт | D28: 155
A29: 13 | B29: Завертка WC | C29: шт | D29: нет
A30: 14 | B30: Петля накладная | C30: шт | D30: 75

Sheet Броня
B1: Наименование компании-поставщика | C1: ООО "СПЕЦ Прожект групп"
B2: Контактное лицо (Ф.И.О.): | C2: Семихин Алексей Николаевич
B3: Телефон | C3: 8(904) 037-44-57
B4: Эл. почта | C4: 4457@apit-kovrov.ru
B5: Реквизиты: | C5: ИНН 3305797523, КПП 772501001, ОГРН 1173328011890
A6: №№ | B6: Наименование | C6: ед. изм. | D6: кол-во | E6: цена за ед.(руб с НДС) для подрядчика | F6: цена за ед.(руб с НДС) для Банка | G6: Примечание
A7: 1 | B7: Бронестекло ПУз-Бр3 (1000*1000 мм. Видимая часть). По раме 1090х1090 мм без учета лотка. ЛИСТ 2. | C7: шт. | D7: 100 | E7: 50000 | F7: =E7*1.05 -> 52500 | H7: лист 2 | J7: 46176
A8: 2 | B8: Передаточный (подвижный, двухуровневый) лоток для передачи 5-ти банковских упаковок по 1000 листов Габаритные размеры 415х610х232 мм Ш*В*Д, внутри нижнего лотка 300х160х260 мм Ш*В*Д, внутри верхнего лотка 300х20-185 мм Ш*В*Д . Отделка лотка : лотковые емкости и лицевая накладка - шлифованная или зеркальная нерж.стль, короб - порошковая окрас. RAL7047. ЛИСТ 3. | C8: шт. | D8: 100 | E8: 38000 | F8: =E8*1.05 -> 39900 | H8: лист3
A9: 1 | B9: Бронестекло ПУз-Бр3 (1090*1335 мм. ). С учетом лотка. ЛИСТ 1. | C9: шт. | D9: 100 | E9: 100000 | F9: =E9*1.05 -> 105000 | H9: лист1
A10: 3 | B10: Шлюз инкассаторский кл. Бр-3 по пулестойкости, механический со стеклом, габаритные размеры 910х820х870 мм, ВШхД. внутренние размеры 710х670х750 мм. Открывание кассира левое, инкассатора правое. Порошковая окрас. RAL7047. ЛИСТ 4. | C10: шт. | D10: 50 | E10: 95000 | F10: =E10*1.05 -> 99750 | H10: лист4
A11: 4 | B11: Шлюз инкассаторский кл. Бр-3 по пулестойкости, электро-механический со стеклом, габаритные размеры 910х820х870 мм, ВШхД. внутренние размеры 710х670х750 мм. Открывание кассира левое, инкассатора правое. Порошковая окрас. RAL7047. ЛИСТ 5. | C11: шт. | D11: 5 | E11: 107000 | F11: =E11*1.05 -> 112350
A12: 5 | B12: Шлюз инкассаторский кл. Бр-2 по пулестойкости, механический со стеклом, габаритные размеры 910х820х870 мм, ВШхД. внутренние размеры 710х670х750 мм. Открывание кассира левое, инкассатора правое. Порошковая окрас. RAL7047. ЛИСТ 6. | C12: шт. | D12: 5 | E12: 97700 | F12: =E12*1.05 -> 102585
A13: 6 | B13: Шлюз инкассаторский кл. Бр-3 по пулестойкости, механический со стеклом СЗМ-Бр3, габаритные размеры 750х540х615 мм, ВШхД. внутренние размеры 652х250х471 мм.Открывание кассира левое, инкассатора правое. Способ крепления - на монтажные уголки приваренные посередине к шлюзу.Порошковая окрас. RAL7047. ЛИСТ 7. | C13: шт. | D13: 30 | E13: 75000 | F13: =E13*1.05 -> 78750
A14: 7 | B14: Шлюз инкассаторский кл. Бр-3 по пулестойкости, электромеханический со стеклом СЗМ-Бр3, габаритные размеры 750х540х615 мм, ВШхД. внутренние размеры 652х250х471 мм.Открывание кассира левое, инкассатора правое. Способ крепления - на монтажные уголки приваренные посередине к шлюзу.Порошковая окрас. RAL7048. ЛИСТ 8. | C14: шт. | D14: 5 | E14: 89000 | F14: =E14*1.05 -> 93450
A15: 8 | B15: Шлюз инкассаторский кл. Бр-2 по пулестойкости, механический со стеклом СЗМ-Бр3, габаритные размеры 750х540х615 мм, ВШхД. внутренние размеры 652х250х471 мм.Открывание кассира левое, инкассатора правое. Способ крепления - на монтажные уголки приваренные посередине к шлюзу.Порошковая окрас. RAL7049. ЛИСТ 9. | C15: шт. | D15: 5 | E15: 74400 | F15: =E15*1.05 -> 78120
A16: 9 | B16: Панели защитные, стеновые кл. Бр-2 по пулестойкости и II класс взломостойкости, сварное соединение, облегченные, Покраска грунт | C16: м2 | D16: 1750 | E16: 14000 | F16: =E16*1.05 -> 14700
A17: 10 | B17: Панели защитные, стеновые кл. Бр-2 по пулестойкости и II класс взломостойкости, болтовое соединение, облегченные, Покраска грунт | C17: м2 | D17: 100 | E17: 14500 | F17: =E17*1.05 -> 15225
A18: 11 | B18: Панели защитные, стеновые кл. Бр-3 по пулестойкости и III класс взломостойкости, сварное соединение, облегченные, Покраска грунт | C18: м2 | D18: 1000 | E18: 16700 | F18: =E18*1.05 -> 17535
A19: 12 | B19: Панели защитные, стеновые кл. Бр-3 по пулестойкости и III класс взломостойкости, болтовое соединение, облегченные, Покраска грунт | C19: м2 | D19: 10 | E19: 17200 | F19: =E19*1.05 -> 18060
A20: 13 | B20: Панели защитные, стеновые V класс взломостойкости, сварное соединение, бетонно-заливная. Покраска грунт | C20: м2 | D20: 500 | E20: 15000 | F20: =E20*1.05 -> 15750
A21: 14 | B21: Дверной блок 2-го класса устойчивости к взлому (дверное полотно 858*2110). Размер по раме 950х2200 мм. Цилиндровый механизм с перекодировкой со штоком Securemme K2. Гардиан сувальдный ЗВ 71.14 Т (К-К). Без наличников. ЛИСТ 10. RAL7047. Упаковка изолон (дер.упаковка доп) | C21: шт. | D21: 50 | E21: 84500 | F21: =E21*1.05 -> 88725 | G21: См. ТЗ "Двери 2 кл" | H21: согласовано 25.05.25 замена замка
A22: 14 | B22: Дверной блок 2-го класса устойчивости к взлому (дверное полотно 758*2010). Размер по раме 850х2100 мм. Цилиндровый механизм с перекодировкой со штоком Securemme K2. Гардиан сувальдный ЗВ 71.14 Т (К-К). Без наличников. ЛИСТ 11. RAL7047. Упаковка изолон (дер.упаковка доп) | C22: шт. | D22: 50 | E22: 83000 | F22: =E22*1.05 -> 87150 | G22: См. ТЗ "Двери 2 кл" | H22: согласовано 25.05.25 замена замка
A23: 15 | B23: Дверной блок 3-го класса устойчивости к взлому с решетчатой дверью (дверное полотно 908*2110). Размер по раме 1000х2200 мм. Размер по раме 1000х2200 мм. Два замка Гардиан 71.14Т сувальдного типа на расстоянии не менее 350 мм друг от друга по замочным скважинам + противосъемные механизмы по трем сторонам двери (К-К). ЛИСТ 12. | C23: шт. | D23: 20 | E23: 141500 | F23: =E23*1.05 -> 148575 | G23: См. ТЗ "Двери 3 кл" | H23: новое требование ББ по замку
A24: 16 | B24: Дверной блок 5-го класса устойчивости к взлому с решетчатой дверью . 2 замка СИ600 (дверное полотно 898*1970), 1030х2100 мм по раме. ЛИСТ 13. | C24: шт. | D24: 10 | E24: 213000 | F24: =E24*1.05 -> 223650 | G24: См. ТЗ "Двери 5 кл."
A25: 17 | B25: Противопожарный однопольный дверной блок , min EI60 с фурнитурой 1000х2100мм по раме | C25: шт. | D25: 200 | E25: 105000 | F25: =E25*1.05 -> 110250 | H25: не поставляет
B26: Установка противопожарного однопольного дверного блока, min EI60 с фурнитурой 1200х2100мм | E26: 8000 | H26: не поставляет
B27: Установка противопожарного двухпольного дверного блока , min EI60 с фурнитурой 1300х2100мм | H27: не поставляет
B28: Установка противопожарного двухпольного дверного блока , min EI60 с фурнитурой 1800х2100мм | H28: не поставляет
A29: 18 | B29: Противопожарный двухпольный дверной блока , min EI60 с фурнитурой 1600х2350мм с откидным порожком по раме | C29: шт. | D29: 100 | F29: =E29*1.05 -> 0 | H29: не поставляет
A30: 19 | B30: Дверной блок утепленый, полуторастворчатый размером по раме 2100Нх1400 мм (размер двери в свету 2000Нх1200 мм), полотна из листов металла 2+2 мм (наружный и внутренние листы). Рабочая створка-________, шириной 900 мм, на раб створке 2 замка: оба цилиндровые Гардиан ЗВ.32.01 ключ-вертушок и Гардиан ЗВ.32.11 (с защелкой) ключ-вертушок, на оба замка устанавливается броненакладка КРИТ Бн-13; Ручка: нажимная (нерж.). Вторая створка оборудуется системой Антипаника с фиксацией створки сверху и снизу. Штанги Антипаники внутри створки для разблокирования верхнего и нижнего запоров. Порог 40 мм. Порошковая покраска цвет RAL- _____ включая транспортную упаковку. | C30: шт. | D30: 80 | E30: 105000 | F30: =E30*1.05 -> 110250 | G30: См. ТЗ "Двери запасного выхода"
A31: 20 | B31: Доводчик на рабочую створку NOTEDO DC-025-095 (со скользящим каналом). Доводчик на паразитную створку NOTEDO DC-070 (паук) | C31: шт. | D31: 80 | E31: 8000 | F31: =E31*1.05 -> 8400 | H31: цена за 2 доводчика
B34: Сроки изготовления на данный момент с резким увелечением потребности в зону СВО, составляют 20 раб дней. Так же ежедневно они корректируются.

Sheet Плитка СУ
A1: ОСНОВНОЙ ВАРИАНТ
A2: Наименование | B2: Артикул | C2: Единица измерения | D2: Цена за ед. с НДС, руб. | E2: Цена для Заказчика | F2: 1524 | G2: цена по КП | K2: 46175
A3: Керамическая плитка 200*500 Amsterdam graphite " Ctramica Konskie" | C3: 1 м.кв. | D3: 1524 | E3: =F9 -> 2338.6755 | F3: =F2*0.1 -> 152.4 | G3: подрезка 10% | I3: цена за ед | L3: нет в продаже
F4: =I4*5 -> 315.6 | G4: Церезит | H4: 5 кг,м.кв. | I4: 63.12
F5: =0.33*I5 -> 100.65 | G5: Церезит | H5: 0,33 кг/м.кв | I5: 305
F6: =I6*0.3 -> 43.26 | G6: Грунтовка для пола Litokol Primer | H6: 0,3 л/м.кв | I6: 144.2
A7: СПИСОК ФИЛИАЛОВ И ПРЕДСТАВИТЕЛЬСТВ ПОСТАВЩИКА: | F7: 91.4 | G7: Система выравнивания
F8: =SUBTOTAL(9,F2:F7) -> 2227.31
A9: №№ | B9: Регион/город | C9: Адрес | D9: Контактная информация | F9: =F8*1.05 -> 2338.6755 | G9: генподряд 5%
D10: 8 920 859 42 13
D11: Руев Сергей Викторович
D12: ruev@otdelkino.ru
A19: РЕЗЕРВНЫЕ ВАРИАНТЫ
A20: Наименование | B20: Артикул | C20: Единица измерения | D20: Цена за ед. с НДС, руб. | E20: Цена для Заказчика | G20: цена по КП
A21: Плитка Ganna smoke 20х60 | B21: снята с производства | F21: =D22 -> 1054 | G21: подрезка 10% | I21: цена за ед
A22: Плитка Frida gray 30х60 | B22: 00-00-5-18-01-06-3325 | C22: 1,8 м2 в коробке | D22: 1054 | E22: 1685.1555 | F22: =I22*5 -> 315.6 | G22: Церезит | H22: 5 кг,м.кв. | I22: 63.12
A23: Плитка Mountain silver 25х50 | B23: 00-00-5-10-01-06-2835 | C23: 1,625 м2 в коробке | D23: 994 | E23: 1622.1555 | F23: =0.33*I23 -> 100.65 | G23: Церезит | H23: 0,33 кг/м.кв | I23: 305
F24: =I24*0.3 -> 43.26 | G24: Грунтовка для пола Litokol Primer | H24: 0,3 л/м.кв | I24: 144.2
A25: СПИСОК ФИЛИАЛОВ И ПРЕДСТАВИТЕЛЬСТВ ПОСТАВЩИКА: | F25: 91.4 | G25: Система выравнивания
F26: =SUBTOTAL(9,F20:F25) -> 1604.91
A27: №№ | B27: Регион/город | C27: Адрес | D27: Контактная информация | F27: =F26*1.05 -> 1685.1555 | G27: генподряд 5%
B28: Московская область | C28: г. Подольск, пр-т Юных Ленинцев, д. 41 | D28: (926) 820-03-26 /kovalenko_gn@mosplitka.ru /Галина Коваленко
D29: Менеджер отдела Оптовых продаж

Sheet Бескаркасные двери и перегородк
A1: ПОДРЯДЧИК: | B1: ООО "Вертикальный транспорт"
A2: Юридический адрес:
A3: Реквизиты:
A4: Контактное лицо (Ф.И.О.) : | B4: Дегтярев С.Д. | H4: 46246
A5: Контактный телефон и e-mail: | B5: 8(903)-622-74-45. degtyarev.s.str@gmail.com
A6: Стеклянный однопольный дверной блок 900х2100 мм Стекло 10мм закалённое. Фурнитура цвета матовая нержавеющая сталь Dorma в Universal Light. Кромка стекла полированная. Доводчик Titan N87D SSS с фиксацией 90* вар.№ 1 Запирающаяся ручка-скоба двусторонняя, длина 1225 мм, две точки крепления, в комплекте с запирающим устройством и цилиндром или вар.№2: Studio Rondo нажиманя ручка с запиранием (вариант согласовать с заказчиком) | B6: шт. | C6: 40 | D6: 48725 | E6: =ROUNDUP(D6*1.05,2) -> 51161.25 | F6: 20-25 к.д. | G6: Данная цена указана с учетом доводчика аналогичного указанному в запросе! Если изготавливать данные двери с учетом доводчика Dorma BTS 75V с фиксацией 90*, стоимость дверей увеличтся на 35 000,00 рублей одностворчатых, и на 70 000,00 рублей полуторных и двустворчатых, так как только указанный доводчик стоит 39 695,00 рублей. ссылка ниже!
A7: Стеклянный полуторапольный дверной блок 1400х2100 мм Стекло 10мм закалённое. Фурнитура цвета матовая нержавеющая сталь Dorma в Universal Light. Кромка стекла полированная. Доводчик Tinan N87D SSS с фиксацией 90* вар.№ 1 Запирающаяся ручка-скоба двусторонняя, длина 1225 мм, две точки крепления, в комплекте с запирающим устройством и цилиндром или вар.№2: Studio Rondo нажиманя ручка с запиранием (вариант согласовать с заказчиком) | B7: шт. | C7: 5 | D7: 75795 | E7: =ROUNDUP(D7*1.05,2) -> 79584.75 | F7: 20-25 к.д.
A8: Стеклянный двупольный дверной блок 1800х2400 мм Стекло 10мм закалённое. Фурнитура цвета матовая нержавеющая сталь Dorma в Universal Light. Кромка стекла полированная. Доводчик Tinan N87D SSS с фиксацией 90* вар.№ 1 Запирающаяся ручка-скоба двусторонняя, длина 1225 мм, две точки крепления, в комплекте с запирающим устройством и цилиндром или вар.№2: Studio Rondo нажиманя ручка с запиранием (вариант согласовать с заказчиком) | B8: шт. | C8: 5 | D8: 111370 | E8: =ROUNDUP(D8*1.05,2) -> 116938.5 | F8: 20-25 к.д.
A9: Стеклянные перегородки
A10: Монтаж стеклянных бескаркасных перегородок , стекло 10 мм, закаленное с фурнитурой цвета матовая нержавеющая сталь | B10: м2 | C10: 400 | D10: 7800 | E10: =ROUNDUP(D10*1.05,2) -> 8190 | F10: 20-25 к.д.
A11: Устройство стеклянной перегородки в алюминиевом профиле по RAL. Стекло закаленное 6 мм. | B11: м2 | C11: 400 | D11: 7500 | E11: =ROUNDUP(D11*1.05,2) -> 7875 | F11: 20-25 к.д.
A12: Итого перегородки и бескаркасные двери | E12: =E6+E7+E8+E10+E11 -> 263749.5

Sheet Kerama Marazzi
C2: =E23 -> 1369 | D2: цена по КП | G2: 46239
C3: =C2*0.1 -> 136.9 | D3: подрезка 10% | F3: цена за ед
C4: =F4*5 -> 315.6 | D4: Церезит | E4: 5 кг,м.кв. | F4: 63.12
C5: =0.33*F5 -> 100.65 | D5: Церезит | E5: 0,33 кг/м.кв | F5: 305
C6: =F6*0.3 -> 43.26 | D6: Грунтовка для пола Litokol Primer | E6: 0,3 л/м.кв | F6: 144.2
C7: 91.4 | D7: Система выравнивания
B8: Итого | C8: =SUBTOTAL(9,C2:C7) -> 2056.81
C9: =C8*1.05 -> 2159.6505 | D9: генподряд 5%
B14: Поставщик | C14: Александр Зуев +7 (926) 376-55-56, Алексей Лукашов +7 (926) 376-53-70
B17: Настоящим документом ООО «Керамогрес» закрепляет специальные условия на продукцию KERAMA MARAZZI для АО «Заказчик»:
B19: Фиксация рублевых цен 91156,20 рубля/м2
B22: № п/п | C22: Наименование | D22: Ед. изм. | E22: Цена за ед., руб. с учетом скидки (в т.ч. НДС)
B23: 1. | C23: Терраццо серый светлый обрезной арт. SG632420R | D23: м2 | E23: 1369
B25: Исполнители вправе произвести самовывоз со склада поставщика по фиксированной стоимости Продукции.
B26: Доставка (кроме г. Москва и Московской области) рассчитывается отдельно. Стоимость доставки будет включена в стоимость Продукции.
B102: сечас | C102: было | D102: разница
B103: 1390 | C103: 1982.5 | D103: =C103-B103 -> 592.5

Sheet Трансформируемая перегородка
B2: Наименование | C2: Артикул | D2: Единица измерения | E2: Цена за ед. , в т.ч. НДС 20% | F2: Цена за ед. для Заказчика | G2: Дубовицкая Ольга Юрьевна, контактный | I2: 1.89 | J2: 2.7 | K2: =I2*J2 -> 5.103 | M2: КП от 07.08.26
B3: Система перегородок СТ1 (под заполнение закаленным стеклом М1, прозрачное, 10мм для перегородок высотой до 3000мм) в проем до 5 м² | D3: м2 | E3: 38940 | F3: =ROUND(E3*1.05,2) -> 40887 | G3: телефон: +7-913-774-3231, эл.почта : rperegorodki@yandex.ru. | I3: =C3*E3 -> 0 | J3: =C3*F3 -> 0
B4: Система перегородок СТ1 (под заполнение закаленным стеклом М1, прозрачное, 10мм для перегородок высотой до 3000мм) в проем от 5 до 10 м² | C4: 7.59 | D4: м2 | E4: 35860 | F4: =ROUND(E4*1.05,2) -> 37653 | I4: =C4*E4 -> 272177.4 | J4: =C4*F4 -> 285786.27
B5: Система перегородок СТ1 (под заполнение закаленным стеклом М1, прозрачное, 10мм для перегородок высотой до 3000мм) в проем от 10 до 15 м² | D5: м2 | E5: 34881 | F5: =ROUND(E5*1.05,2) -> 36625.05 | I5: =C5*E5 -> 0 | J5: =C5*F5 -> 0
B6: Система перегородок СТ1 (под заполнение закаленным стеклом М1, прозрачное, 10мм для перегородок высотой до 3000мм) в проем от 15 м² до 20м2 | D6: м2 | E6: 33770 | F6: =ROUND(E6*1.05,2) -> 35458.5 | I6: =C6*E6 -> 0 | J6: =C6*F6 -> 0
B7: Cтекло закаленное М1, прозрачное, 12 мм, кромка полированная, для перегородок высотой 3000-3300мм | D7: м2 | E7: 7865 | F7: =ROUND(E7*1.05,2) -> 8258.25 | I7: =C7*E7 -> 0 | J7: =C7*F7 -> 0
B8: Cтекло закаленное М1, прозрачное, 10 мм, кромка полированная, для перегородок высотой до 3000мм | C8: 7.59 | D8: м2 | E8: 5445 | F8: =ROUND(E8*1.05,2) -> 5717.25 | I8: =C8*E8 -> 41327.55 | J8: =C8*F8 -> 43393.927
B9: Доводчик напольный 840-20-90 (SSS) | D9: шт | E9: 18260 | F9: =ROUND(E9*1.05,2) -> 19173 | I9: =SUM(I3:I8) -> 313504.95 | J9: =SUM(J3:J8) -> 329180.2
B10: Доводчик скрытый 850-25 (SSS) | D10: шт | E10: 18900 | F10: =ROUND(E10*1.05,2) -> 19845
B11: Цилиндр с заверткой для нижнего замка | D11: шт | E11: 1630 | F11: =ROUND(E11*1.05,2) -> 1711.5
B12: Цилиндр с заверткой для среднего замка | D12: шт | E12: 2000 | F12: =ROUND(E12*1.05,2) -> 2100

Sheet Щиты в сборе
C14: Коммерческое предложение от 25.02.2026
A16: № сделки: | D16: 9940-30
A17: Объект: | D17: Заказчик
A18: Заказчик: | D18: Заказчик
A19: Контактное лицо заказчика: | D19: Шапировская Светлана
A20: Способ связи: | D20: тел: | E20: +79169069929
D21: e-mail: | E21: sshapirovskaya@alfabank.ru
A23: № | B23: Наименование изделия | H23: Кол-во | I23: Ед. | J23: Цена для подрядчика | K23: Сумма | M23: Цена для Заказчика
A24: 1 | B24: ГРЩ-0080-54 (ГРЩ1) | H24: 1 | I24: шт. | J24: 118102 | K24: =J24 -> 118102 | M24: =ROUND(J24*1.05,2) -> 124007.1
A25: 2 | B25: ГРЩ-0080-54 (ГРЩ2+АВР) | H25: 1 | I25: шт. | J25: 296290 | K25: =J25 -> 296290 | M25: =ROUND(J25*1.05,2) -> 311104.5 | P25: =K25*1.05 -> 311104.5 | Q25: =ROUND(J25*1.05,1) -> 311104.5
A26: 3 | B26: ЩР-0063-54 (ЩС1) | H26: 1 | I26: шт. | J26: 332273 | K26: =J26 -> 332273 | M26: =ROUND(J26*1.05,2) -> 348886.65
A27: 4 | B27: ЩР-0063-54 (ЩС2) | H27: 1 | I27: шт. | J27: 332016 | K27: =J27 -> 332016 | M27: =ROUND(J27*1.05,2) -> 348616.8
A28: 5 | B28: ЩР-0025-54 (ЩСБ) | H28: 1 | I28: шт. | J28: 11448 | K28: =J28 -> 11448 | M28: =ROUND(J28*1.05,2) -> 12020.4
A29: 6 | B29: ЩР-0025-54 (ЩИБП) | H29: 1 | I29: шт. | J29: 21494 | K29: =J29 -> 21494 | M29: =ROUND(J29*1.05,2) -> 22568.7
A30: 7 | B30: ЩР-0025-54 (ППУ) | H30: 1 | I30: шт. | J30: 23804 | K30: =J30 -> 23804 | M30: =ROUND(J30*1.05,2) -> 24994.2
A31: 8 | B31: ВРЩ микро | H31: 1 | I31: шт. | J31: 179001 | K31: =J31 -> 179001 | M31: =ROUND(J31*1.05,2) -> 187951.05
A32: 9 | B32: ЩППУ(красный) микро | H32: 1 | I32: шт. | J32: 21624 | K32: =J32 -> 21624 | M32: =ROUND(J32*1.05,2) -> 22705.2
A33: 10 | B33: ЩР (НАНО 1-ф) | H33: 1 | I33: шт. | J33: 59758 | K33: =J33 -> 59758 | M33: =ROUND(J33*1.05,2) -> 62745.9
A34: 11 | B34: ЩР (НАНО 3-ф) | H34: 1 | I34: шт. | J34: 130317 | K34: =J34 -> 130317 | M34: =ROUND(J34*1.05,2) -> 136832.85
H37: Итого (с НДС): | J37: =SUM(K24:L34) -> 1526127
A38: Срок изготовления:
B39: 15-17 дней*
A40: *Срок поставки оборудования может отличаться от заявленного в зависимости от наличия комплектации на складах производителей.
A42: Ответственный:
B43: Семенихин Александр Михайлович
H44: aleksandr.s@abb-electro.ru
A45: Комментарии: 1. Оборудование: System Electric; 2. Корпуса: Россия Примечание: 1. Оборудование пр-ва КЭАЗ заменили на оборудование пр-ва SE; 2. Корпуса серии TwinLine и ComfortLine заменили на корпуса ЩМП и ЩРн пр-ва ИЭК соответственно
A46: Спецификация заказчику для объекта Заказчик по документу расчета для сделки номер 9940, версия расчета 07
A50: Номер щита | D50: Номенклатура | Q50: Кол-во
A51: 1 | D51: ГРЩ-0080-54 (ГРЩ1) | Q51: 1
D52: Панель № 1 | Q52: 1
H53: АВТ.ВЫКЛ SYSTEMEPACT CCB100 36KA 3P3D TMD80 РЫЧАГ | Q53: 1
H54: Меркурий 236 АRT-02 PQRS | Q54: 1
H55: City9 Set Автоматический выключатель (АВ) С 50А 3P 6kA 400В | Q55: 1
H56: City9 Set Автоматический выключатель (АВ) С 32А 3P 6kA 400В | Q56: 1
H57: City9 Set Автоматический выключатель (АВ) С 25А 3P 6kA 400В | Q57: 1
H58: City9 Set Автоматический выключатель (АВ) С 16А 3P 6kA 400В | Q58: 2
H59: City9 Set Автоматический выключатель (АВ) С 16А 1P 6kA 230В | Q59: 4
H60: Шины на DIN-рейку (кросс-модуль) ШНК 4х11 3L+PEN | Q60: 1
H61: Кабель-канал перфорированный 40х40 "ИМПАКТ" | Q61: 2
H62: Фланец мембранный 220х79 мм для шкафа IP54 EKF PROxima | Q62: 2
H63: Провод ПуГВ (ПВ3) 1х10,0 | Q63: 6
H64: Наконечник штыревой втулочный изолированный НШвИ 10,0-12 (50шт.) EKF PROxima | Q64: 0.2
H65: Корпус метал. ЩМП-3-0 (650х500х220) У2 IP54 | Q65: 1
A66: 2 | D66: ГРЩ-0080-54 (ГРЩ2+АВР) | Q66: 1
D67: Панель № 1 | Q67: 1
H68: АВТ.ВЫКЛ SYSTEMEPACT CCB100 36KA 3P3D TMD80 РЫЧАГ | Q68: 2
H69: Меркурий 236 АRT-02 PQRS | Q69: 2
H70: City9 Set Автоматический выключатель (АВ) С 50А 3P 6kA 400В | Q70: 1
H71: City9 Set Автоматический выключатель (АВ) С 32А 3P 6kA 400В | Q71: 3
H72: City9 Set Автоматический выключатель (АВ) С 25А 3P 6kA 400В | Q72: 1
H73: City9 Set Выключатель нагрузки (ВН) 3P 63А 400В | Q73: 1
H74: City9 Set Автоматический выключатель (АВ) С 16А 3P 6kA 400В | Q74: 2
H75: City9 Set Автоматический выключатель (АВ) С 16А 1P 6kA 230В | Q75: 4
H76: City9 Set Автоматический выключатель (АВ) С 6А 1P 6kA 230В | Q76: 5
H77: Реле контроля фаз ЕЛ-11Е 380В 50Гц | Q77: 1
H78: КОНТАКТОР MC1D 3P 40A НО+НЗ 220V 50/60ГЦ | Q78: 2
H79: ДОП. КОНТ. БЛОК MC1D 2НО+2НЗ ФРОНТАЛЬНЫЙ МОНТАЖ | Q79: 2
... H92: Корпус метал. ЩМП-4-0 (800х650х250) У2 IP54 | Q92: 1
A93: 3 | D93: ЩР-0063-54 (ЩС1) | Q93: 1
D94: Панель № 1 | Q94: 1
H95: City9 Set Выключатель нагрузки (ВН) 3P 63А 400В | Q95: 3
H96: City9 Set Автоматический выключатель (АВ) С 32А 3P 6kA 400В | Q96: 1
H97: City9 Set Автоматический выключатель (АВ) С 20А 3P 6kA 400В | Q97: 1
H98: City9 Set Автоматический выключатель (АВ) С 16А 3P 6kA 400В | Q98: 2
H99: City9 Set Автоматический выключатель (АВ) С 16А 1P 6kA 230В | Q99: 3
H100: City9 Set Автоматический выключатель (АВ) С 10А 1P 6kA 230В | Q100: 1
H101: City9 Set Автоматический выключатель (АВ) B 10А 1P 6kA 230В | Q101: 11
H102: City9 Set Автоматический выключатель (АВ) С 6А 1P 6kA 230В | Q102: 5
H103: City9 Set Авт. выкл. диф. тока (АВДТ) 1P+N С 16А 6kA 30мА Тип-AС 230В | Q103: 32
H104: City9 Set Контактор 4P 4НО 40A AC 400В-230В | Q104: 2
H105: City9 Set Контактор 4P 4НО 40A AC 400В-230В | Q105: 1
H106: OptiDin МК63-2011-230AC | Q106: 2
... H112: TITAN 5 Корпус металлический ЩРн-144 IP54 У2 | Q112: 1
A113: 4 | D113: ЩР-0063-54 (ЩС2) | Q113: 1
D114: Панель № 1 | Q114: 1
H115: City9 Set Выключатель нагрузки (ВН) 3P 63А 400В | Q115: 3
H116: City9 Set Автоматический выключатель (АВ) С 32А 3P 6kA 400В | Q116: 1
H117: City9 Set Автоматический выключатель (АВ) С 16А 3P 6kA 400В | Q117: 2
H118: City9 Set Автоматический выключатель (АВ) С 16А 1P 6kA 230В | Q118: 12
H119: City9 Set Автоматический выключатель (АВ) B 10А 1P 6kA 230В | Q119: 11
H120: City9 Set Автоматический выключатель (АВ) С 6А 1P 6kA 230В | Q120: 5
H121: City9 Set Авт. выкл. диф. тока (АВДТ) 1P+N С 16А 6kA 30мА Тип-AС 230В | Q121: 32
H122: City9 Set Контактор 4P 4НО 40A AC 400В-230В | Q122: 2
H123: City9 Set Контактор 4P 4НО 40A AC 400В-230В | Q123: 2
H124: OptiDin МК63-2011-230AC | Q124: 1
H125: Таймер ТЭ15 цифровой 16А 230В на DIN-рейку | Q125: 1
H126: Шина нулевая в корпусе (4х7) EKF PROxima | Q126: 3
... H130: TITAN 5 Корпус металлический ЩРн-144 IP54 У2 | Q130: 1
A131: 5 | D131: ЩР-0025-54 (ЩСБ) | Q131: 1
D132: Панель № 1 | Q132: 1
H133: City9 Set Выключатель нагрузки (ВН) 1P 40А 230В | Q133: 1
H134: City9 Set Автоматический выключатель (АВ) С 10А 1P 6kA 230В | Q134: 1
H135: City9 Set Автоматический выключатель (АВ) С 6А 1P 6kA 230В | Q135: 5
H136: Шина нулевая в корпусе (2х7) EKF PROxima | Q136: 1
H137: TITAN 3 Корпус метал. ЩРн-12 (240х330х120) IP54 | Q137: 1
A138: 6 | D138: ЩР-0025-54 (ЩИБП) | Q138: 1
D139: Панель № 1 | Q139: 1
H140: City9 Set Выключатель нагрузки (ВН) 1P 40А 230В | Q140: 1
H141: City9 Set Авт. выкл. диф. тока (АВДТ) 1P+N С 10А 6kA 30мА Тип-AС 230В | Q141: 2
...

Sheet Кондиционеры Haier VRF
A1: Мультизональные системы MRV
A2: Тип | C2: Ряд | E2: Модель | F2: Панель | G2: Фото | H2: Примечание | I2: Цена для подрядчиков АО "Заказчик" USD с НДС | J2: Цена для АО "Заказчик" USD с НДС
A4: MRV III - S Внешний блок | C4: DC INVERTER | D4: 3HP | E4: AU032FSEUA | I4: 1242 | J4: =I4*1.05 -> 1304.1
D5: 5HP | E5: AU052FPEUA | I5: 2149 | J5: =I5*1.05 -> 2256.45
D6: 6HP | E6: AU07NFPEUA | I6: 2182 | J6: =I6*1.05 -> 2291.1
D7: 4HP | E7: AU042FPERA | I7: 2203 | J7: =I7*1.05 -> 2313.15
D8: 4HP | E8: AU04IFPERA | I8: 2203 | J8: =I8*1.05 -> 2313.15
D9: 5HP | E9: AU052FPERA | I9: 2214 | J9: =I9*1.05 -> 2324.7
D10: 5HP | E10: AU05IFPERA | I10: 2214 | J10: =I10*1.05 -> 2324.7
D11: 6HP | E11: AU062FPERA | I11: 2225 | J11: =I11*1.05 -> 2336.25
D12: 6HP | E12: AU06IFPERA | I12: 2225 | J12: =I12*1.05 -> 2336.25
D13: 4HP | E13: AU042FNERA | I13: 1966 | J13: =I13*1.05 -> 2064.3
D14: 5HP | E14: AU052FNERA | I14: 1976 | J14: =I14*1.05 -> 2074.8
D15: 8HP | E15: AU08NFKERA | I15: 3046 | J15: =I15*1.05 -> 3198.3
D16: 10HP | E16: AU10NFKERA | I16: 3110 | J16: =I16*1.05 -> 3265.5
D17: 12HP | E17: AU12NFKERA | I17: 3218 | J17: =I17*1.05 -> 3378.9
A18: MRV- V Внешний блок | C18: FULL DC INVERTER | D18: 8HP | E18: AV08IMVEVA | I18: 5292 | J18: =I18*1.05 -> 5556.6
D19: 10HP | E19: AV10IMVEVA | I19: 5378 | J19: =I19*1.05 -> 5646.9
D20: 12HP | E20: AV12IMVEVA | I20: 6372 | J20: =I20*1.05 -> 6690.6
D21: 14HP | E21: AV14IMVEVA | I21: 6588 | J21: =I21*1.05 -> 6917.4
D22: 16HP | E22: AV16IMVEVA | I22: 7020 | J22: =I22*1.05 -> 7371
D23: 18HP | E23: AV18IMVEVA | I23: 7992 | J23: =I23*1.05 -> 8391.6
D24: 20HP | E24: AV20IMVEVA | I24: 9288 | J24: =I24*1.05 -> 9752.4
D25: 22HP | E25: AV22IMVEVA | I25: 9936 | J25: =I25*1.05 -> 10432.8
D26: 24HP | E26: AV24IMVEVA | I26: 10152 | J26: =I26*1.05 -> 10659.6
D27: 26HP | E27: AV26IMVEVA | I27: 10368 | J27: =I27*1.05 -> 10886.4
A28: Настенный Family | C28: DC INVERTER | D28: 5K | E28: AS052MNERA | H28: В комплекте с пультом YR-HD | I28: 255 | J28: =I28*1.05 -> 267.75
D29: 7K | E29: AS072MNERA | I29: 257 | J29: =I29*1.05 -> 269.85
D30: 9K | E30: AS092MNERA | I30: 259 | J30: =I30*1.05 -> 271.95
D31: 12K | E31: AS122MNERA | I31: 265 | J31: =I31*1.05 -> 278.25
D32: 16K | E32: AS162MNERA | I32: 291 | J32: =I32*1.05 -> 305.55
D33: 18K | E33: AS182MNERA | I33: 311 | J33: =I33*1.05 -> 326.55
D34: 24K | E34: AS242MNERA | I34: 333 | J34: =I34*1.05 -> 349.65
D35: 28K | E35: AS282MNERA | I35: 376 | J35: =I35*1.05 -> 394.8
D36: 30K | E36: AS302MNERA | I36: 400 | J36: =I36*1.05 -> 420
A37: Настенный Lightera | C37: DC INVERTER | D37: 5K | E37: AS052MFERA | H37: В комплекте с пультом YR-HD | I37: 294 | J37: =I37*1.05 -> 308.7
D38: 7K | E38: AS072MFERA | I38: 296 | J38: =I38*1.05 -> 310.8
D39: 9K | E39: AS092MFERA | I39: 298 | J39: =I39*1.05 -> 312.9
D40: 12K | E40: AS122MFERA | I40: 302 | J40: =I40*1.05 -> 317.1
D41: 16K | E41: AS162MFERA | I41: 340 | J41: =I41*1.05 -> 357
D42: 18K | E42: AS182MFERA | I42: 356 | J42: =I42*1.05 -> 373.8
D43: 24K | E43: AS242MFERA | I43: 378 | J43: =I43*1.05 -> 396.9
A44: Кассетный | C44: 4-х поточный компакт 600х600 | D44: 5K | E44: AB052MCERA(M) | F44: PB-620KB | I44: 276 | J44: =I44*1.05 -> 289.8
D45: 7K | E45: AB072MCERA(M) | I45: 281 | J45: =I45*1.05 -> 295.05
D46: 9K | E46: AB092MCERA(M) | I46: 289 | J46: =I46*1.05 -> 303.45
D47: 12K | E47: AB122MCERA(M) | I47: 302 | J47: =I47*1.05 -> 317.1
D48: 16K | E48: AB162MCERA(M) | I48: 316 | J48: =I48*1.05 -> 331.8
D49: 18K | E49: AB182MCERA(M) | I49: 351 | J49: =I49*1.05 -> 368.55
C50: 4-х поточный | D50: 5K | E50: AB052MCERA | F50: PB-700IB | J50: =I50*1.05 -> 0
D51: 7K | E51: AB072MCERA | J51: =I51*1.05 -> 0
D52: 9K | E52: AB092MCERA | J52: =I52*1.05 -> 0
D53: 12K | E53: AB122MCERA | J53: =I53*1.05 -> 0
D54: 16K | E54: AB162MCERA | J54: =I54*1.05 -> 0
D55: 18K | E55: AB182MCERA © | J55: =I55*1.05 -> 0
D56: 18K | E56: AB182MNERA | F56: PB-950JB | I56: 486 | J56: =I56*1.05 -> 510.3
D57: 24K | E57: AB242MNERA | I57: 508 | J57: =I57*1.05 -> 533.4
D58: 28K | E58: AB282MNERA | I58: 529 | J58: =I58*1.05 -> 555.45
D59: 30K | E59: AB302MNERA | I59: 567 | J59: =I59*1.05 -> 595.35
D60: 38K | E60: AB382MNERA | I60: 594 | J60: =I60*1.05 -> 623.7
D61: 48K | E61: AB482MNERA | I61: 616 | J61: =I61*1.05 -> 646.8
E62: AB602MNERA | I62: 648 | J62: =I62*1.05 -> 680.4
C63: 4-х поточный new | D63: 7K | E63: AB072MRERA | F63: PB-950KB | J63: =I63*1.05 -> 0
D64: 9K | E64: AB092MRERA | J64: =I64*1.05 -> 0
D65: 12K | E65: AB122MRERA | J65: =I65*1.05 -> 0
D66: 16K | E66: AB162MRERA | J66: =I66*1.05 -> 0
D67: 18K | E67: AB182MRERA | J67: =I67*1.05 -> 0
D68: 24K | E68: AB242MRERA | J68: =I68*1.05 -> 0
D69: 28K | E69: AB282MRERA | J69: =I69*1.05 -> 0
D70: 30K | E70: AB302MRERA | J70: =I70*1.05 -> 0
D71: 38K | E71: AB382MRERA | J71: =I71*1.05 -> 0
D72: 48K | E72: AB482MRERA | J72: =I72*1.05 -> 0
D73: 60K | E73: AB602MRERA | J73: =I73*1.05 -> 0
A74: Универсальный | C74: DC INVERTER | D74: 9K | E74: AC092MDERA | H74: без пульта | I74: 529 | J74: =I74*1.05 -> 555.45
D75: 12K | E75: AC122MDERA | I75: 562 | J75: =I75*1.05 -> 590.1
D76: 16K | E76: AC162MDERA | I76: 572 | J76: =I76*1.05 -> 600.6
D77: 18K | E77: AC182MDERA | I77: 594 | J77: =I77*1.05 -> 623.7
D78: 24K | E78: AC242MDERA | I78: 637 | J78: =I78*1.05 -> 668.85
D79: 28K | E79: AC282MDERA | I79: 734 | J79: =I79*1.05 -> 770.7
D80: 30K | E80: AC302MDERA | I80: 756 | J80: =I80*1.05 -> 793.8
D81: 38K | E81: AC382MDERA | I81: 810 | J81: =I81*1.05 -> 850.5
D82: 48K | E82: AC482MDERA | I82: 842 | J82: =I82*1.05 -> 884.1
A83: Канальный | B83: 30 Pa | C83: DC INVERTER | D83: 5K | E83: AD052MSERA | H83: без пульта | I83: 289 | J83: =I83*1.05 -> 303.45
D84: 7K | E84: AD072MSERA | I84: 302 | J84: =I84*1.05 -> 317.1
D85: 9K | E85: AD092MSERA | I85: 313 | J85: =I85*1.05 -> 328.65
D86: 12K | E86: AD122MSERA | I86: 324 | J86: =I86*1.05 -> 340.2
D87: 16K | E87: AD162MSERA | I87: 367 | J87: =I87*1.05 -> 385.35
D88: 18K | E88: AD182MSERA | I88: 421 | J88: =I88*1.05 -> 442.05
D89: 24K | E89: AD242MSERA | I89: 458 | J89: =I89*1.05 -> 480.9
C90: FULL DC INVERTER | D90: 5K | E90: AD052MSERA (D) | H90: без пульта | I90: 389 | J90: =I90*1.05 -> 408.45
D91: 7K | E91: AD072MSERA (D) | I91: 400 | J91: =I91*1.05 -> 420
D92: 9K | E92: AD092MSERA (D) | I92: 410 | J92: =I92*1.05 -> 430.5
D93: 12K | E93: AD122MSERA (D) | I93: 421 | J93: =I93*1.05 -> 442.05
D94: 16K | E94: AD162MSERA (D) | I94: 432 | J94: =I94*1.05 -> 453.6
D95: 18K | E95: AD182MSERA (D) | I95: 486 | J95: =I95*1.05 -> 510.3
D96: 24K | E96: AD242MSERA (D) | I96: 508 | J96: =I96*1.05 -> 533.4
B97: 50/100 Pa | C97: DC INVERTER | D97: 5K | E97: AD052MJERA | H97: без пульта | I97: 497 | J97: =I97*1.05 -> 521.85
D98: 7K | E98: AD072MJERA | I98: 508 | J98: =I98*1.05 -> 533.4
D99: 9K | E99: AD092MJERA | I99: 521 | J99: =I99*1.05 -> 547.05
D100: 12K | E100: AD122MJERA | I100: 540 | J100: =I100*1.05 -> 567
D101: 16K | E101: AD162MJERA | I101: 562 | J101: =I101*1.05 -> 590.1
...

Sheet Кондиционеры MDV VRF
A4: VRF-СИСТЕМЫ V8
A6: Модель | B6: Производительность, кВт | D6: Уровень шума, дБ(A) | E6: Объем брутто, м3 | F6: Вес брутто, кг | G6: Цена, USD без НДС | I6: Цена, USD с НДС 22%
B7: охл. | C7: нагр.
A8: Наружные блоки
A9: Полноразмерные блоки V8 модульного исполнения, R410A
A10: (DC inverter, R410A, 380V) | I10: Цена для Подрядчика Заказчика с НДС, в USD | J10: Цена для Заказчика с НДС, в USD
A11: MDV-V8252V2R1A(MA) | B11: 25.2 | C11: 27 | D11: 56 | E11: 1.74 | F11: 213 | G11: 6073.3333 | I11: =G11*1.22 -> 7409.4667 | J11: =I11*1.05 -> 7779.94
A12: MDV-V8280V2R1A(MA) | B12: 28 | C12: 31.5 | D12: 57 | E12: 1.74 | F12: 213 | G12: 6545.3333 | I12: =G12*1.22 -> 7985.3067 | J12: =I12*1.05 -> 8384.572
A13: MDV-V8335V2R1A(MA) | B13: 33.5 | C13: 37.5 | D13: 59 | E13: 1.74 | F13: 213 | G13: 6965.3333 | I13: =G13*1.22 -> 8497.7067 | J13: =I13*1.05 -> 8922.592
A14: MDV-V8400V2R1A(MA) | B14: 40 | C14: 45 | D14: 59 | E14: 1.74 | F14: 236 | G14: 7974.3333 | I14: =G14*1.22 -> 9728.6867 | J14: =I14*1.05 -> 10215.121
A15: MDV-V8450V2R1A(MA) | B15: 45 | C15: 50 | D15: 60 | E15: 1.74 | F15: 236 | G15: 8368.6667 | I15: =G15*1.22 -> 10209.773 | J15: =I15*1.05 -> 10720.262
A16: MDV-V8500V2R1A(MA) | B16: 50 | C16: 56 | D16: 61 | E16: 1.74 | F16: 236 | G16: 9771 | I16: =G16*1.22 -> 11920.62 | J16: =I16*1.05 -> 12516.651
A17: MDV-V8560V2R1A(MA) | B17: 56 | C17: 63 | D17: 62 | E17: 2.432 | F17: 297 | G17: 10313.667 | I17: =G17*1.22 -> 12582.673 | J17: =I17*1.05 -> 13211.807
A18: MDV-V8615V2R1A(MA) | B18: 61.5 | C18: 69 | D18: 62 | E18: 2.432 | F18: 297 | G18: 11087 | I18: =G18*1.22 -> 13526.14 | J18: =I18*1.05 -> 14202.447
A19: MDV-V8670V2R1A(MA) | B19: 67 | C19: 75 | D19: 62 | E19: 2.432 | F19: 317 | G19: 12512 | I19: =G19*1.22 -> 15264.64 | J19: =I19*1.05 -> 16027.872
A20: MDV-V8730V2R1A(MA) | B20: 73 | C20: 81.5 | D20: 62 | E20: 3.367 | F20: 405 | G20: 13767.667 | I20: =G20*1.22 -> 16796.553 | J20: =I20*1.05 -> 17636.381
A21: MDV-V8785V2R1A(MA) | B21: 78.5 | C21: 87.5 | D21: 63 | E21: 3.367 | F21: 405 | G21: 14204.667 | I21: =G21*1.22 -> 17329.693 | J21: =I21*1.05 -> 18196.178
A22: MDV-V8850V2R1A(MA) | B22: 85 | C22: 95 | D22: 64 | E22: 3.367 | F22: 444 | G22: 15386 | I22: =G22*1.22 -> 18770.92 | J22: =I22*1.05 -> 19709.466
... A27: MDV-V81120V2R1A(MA) | B27: 112 | C27: 123.5 | D27: 67 | E27: 3.367 | F27: 465 | G27: 17970.333 | I27: =G27*1.22 -> 21923.807 | J27: =I27*1.05 -> 23019.997
A28: Полноразмерные блоки V8i индивидуального исполнения, R410A
A29: (DC inverter, R410A, 380V) | G29: 0
A30: MDV-V8i252V2R1A(MA) | B30: 25.2 | C30: 27 | D30: 56 | E30: 1.74 | F30: 213 | G30: 5033 | I30: =G30*1.22 -> 6140.26 | J30: =I30*1.05 -> 6447.273
A31: MDV-V8i280V2R1A(MA) | B31: 28 | C31: 31.5 | D31: 57 | E31: 1.74 | F31: 213 | G31: 5305 | I31: =G31*1.22 -> 6472.1 | J31: =I31*1.05 -> 6795.705
A32: MDV-V8i335V2R1A(MA) | B32: 33.5 | C32: 37.5 | D32: 59 | E32: 1.74 | F32: 213 | G32: 5826.6667 | I32: =G32*1.22 -> 7108.5333 | J32: =I32*1.05 -> 7463.96
A33: MDV-V8i400V2R1A(MA) | B33: 40 | C33: 45 | D33: 59 | E33: 1.74 | F33: 216 | G33: 6671 | I33: =G33*1.22 -> 8138.62 | J33: =I33*1.05 -> 8545.551
A34: MDV-V8i450V2R1A(MA) | B34: 45 | C34: 50 | D34: 60 | E34: 1.74 | F34: 236 | G34: 6845.3333 | I34: =G34*1.22 -> 8351.3067 | J34: =I34*1.05 -> 8768.872
A35: MDV-V8i500V2R1A(MA) | B35: 50 | C35: 56 | D35: 61 | E35: 1.74 | F35: 236 | G35: 7912 | I35: =G35*1.22 -> 9652.64 | J35: =I35*1.05 -> 10135.272
A36: MDV-V8i560V2R1A(MA) | B36: 56 | C36: 63 | D36: 62 | E36: 2.432 | F36: 297 | G36: 8351.6667 | I36: =G36*1.22 -> 10189.033 | J36: =I36*1.05 -> 10698.485
A37: MDV-V8i615V2R1A(MA) | B37: 61.5 | C37: 69 | D37: 62 | E37: 2.432 | F37: 297 | G37: 9061.6667 | I37: =G37*1.22 -> 11055.233 | J37: =I37*1.05 -> 11607.995
A38: MDV-V8i670V2R1A(MA) | B38: 67 | C38: 75 | D38: 62 | E38: 2.432 | F38: 299 | G38: 9793.6667 | I38: =G38*1.22 -> 11948.273 | J38: =I38*1.05 -> 12545.687
A39: MDV-V8i730V2R1A(MA) | B39: 73 | C39: 81.5 | D39: 62 | E39: 3.367 | F39: 405 | G39: 11502.667 | I39: =G39*1.22 -> 14033.253 | J39: =I39*1.05 -> 14734.916
A40: MDV-V8i785V2R1A(MA) | B40: 78.5 | C40: 87.5 | D40: 63 | E40: 3.367 | F40: 405 | G40: 11610 | I40: =G40*1.22 -> 14164.2 | J40: =I40*1.05 -> 14872.41
A41: MDV-V8i850V2R1A(MA) | B41: 85 | C41: 95 | D41: 64 | E41: 3.367 | F41: 444 | G41: 12584.667 | I41: =G41*1.22 -> 15353.293 | J41: =I41*1.05 -> 16120.958
... A47: MDV-V8i1170V2R1A(MA) | B47: 117 | C47: 130 | D47: 68 | E47: 3.367 | F47: 467 | G47: 15737.333 | I47: =G47*1.22 -> 19199.547 | J47: =I47*1.05 -> 20159.524
A48: Полноразмерные блоки серии VCmax (только охлаждение), R410A
A49: (DC inverter, R410A, 380V) | G49: 0
A50: MDVO-VCM224V2R1A | B50: 22.4 | C50: - | D50: 57 | E50: 1.748 | F50: 200 | G50: 2602 | I50: =G50*1.22 -> 3174.44 | J50: =I50*1.05 -> 3333.162
A51: MDVO-VCM280V2R1A | B51: 28 | C51: - | D51: 58 | E51: 1.748 | F51: 200 | G51: 2730.3333 | I51: =G51*1.22 -> 3331.0067 | J51: =I51*1.05 -> 3497.557
A52: MDVO-VCM335V2R1A | B52: 33.5 | C52: - | D52: 60 | E52: 1.748 | F52: 200 | G52: 3360.6667 | I52: =G52*1.22 -> 4100.0133 | J52: =I52*1.05 -> 4305.014
A53: MDVO-VCM400V2R1A | B53: 40 | C53: - | D53: 60 | E53: 1.748 | F53: 215 | G53: 4205 | I53: =G53*1.22 -> 5130.1 | J53: =I53*1.05 -> 5386.605
A54: MDVO-VCM450V2R1A | B54: 45 | C54: - | D54: 61 | E54: 1.748 | F54: 215 | G54: 4437.3333 | I54: =G54*1.22 -> 5413.5467 | J54: =I54*1.05 -> 5684.224
A55: MDVO-VCM500V2R1A | B55: 50 | C55: - | D55: 62 | E55: 1.748 | F55: 232 | G55: 5665 | I55: =G55*1.22 -> 6911.3 | J55: =I55*1.05 -> 7256.865
A56: MDVO-VCM560V2R1A | B56: 56 | C56: - | D56: 63 | E56: 1.748 | F56: 245 | G56: 5844.3333 | I56: =G56*1.22 -> 7130.0867 | J56: =I56*1.05 -> 7486.591
A57: MDVO-VCM615V2R1A | B57: 61.5 | C57: - | D57: 63 | E57: 2.441 | F57: 285 | G57: 6378.6667 | I57: =G57*1.22 -> 7781.9733 | J57: =I57*1.05 -> 8171.072
A58: MDVO-VCM670V2R1A | B58: 67 | C58: - | D58: 64 | E58: 2.441 | F58: 285 | G58: 6748 | I58: =G58*1.22 -> 8232.56 | J58: =I58*1.05 -> 8644.188
A59: MDVO-VCM730V2R1A | B59: 73 | C59: - | D59: 64 | E59: 2.441 | F59: 350 | G59: 7117.3333 | I59: =G59*1.22 -> 8683.1467 | J59: =I59*1.05 -> 9117.304
A60: MDVO-VCM785V2R1A | B60: 78.5 | C60: - | D60: 64 | E60: 2.441 | F60: 350 | G60: 7395.3333 | I60: =G60*1.22 -> 9022.3067 | J60: =I60*1.05 -> 9473.422
A61: MDVO-VCM850V2R1A | B61: 85 | C61: - | D61: 64 | E61: 2.441 | F61: 350 | G61: 7830.6667 | I61: =G61*1.22 -> 9553.4133 | J61: =I61*1.05 -> 10031.084
A62: Блоки V8S с боковым выбросом воздуха модульного исполнения, R410A
A63: (DC inverter, R410A, 380V) | G63: 0
A64: MDV-V8S252V2R1A | B64: 25 | C64: 27 | D64: 56 | E64: 1.384 | F64: 191 | G64: 5606.3333 | I64: =G64*1.22 -> 6839.7267 | J64: =I64*1.05 -> 7181.713
A65: MDV-V8S280V2R1A | B65: 28 | C65: 31.5 | D65: 57 | E65: 1.384 | F65: 191 | G65: 6042 | I65: =G65*1.22 -> 7371.24 | J65: =I65*1.05 -> 7739.802
A66: MDV-V8S335V2R1A | B66: 33.5 | C66: 37.5 | D66: 58 | E66: 1.384 | F66: 194 | G66: 6429 | I66: =G66*1.22 -> 7843.38 | J66: =I66*1.05 -> 8235.549
A67: MDV-V8S400V2R1A | B67: 40 | C67: 45 | D67: 59 | E67: 1.384 | F67: 196 | G67: 7077.6667 | I67: =G67*1.22 -> 8634.7533 | J67: =I67*1.05 -> 9066.491
A68: MDV-V8S450V2R1A | B68: 45 | C68: 50 | D68: 60 | E68: 1.384 | F68: 196 | G68: 7724.6667 | I68: =G68*1.22 -> 9424.0933 | J68: =I68*1.05 -> 9895.298
A69: MDV-V8S500V2R1A | B69: 50 | C69: 56.5 | D69: 61 | E69: 1.521 | F69: 223 | G69: 8672.3333 | I69: =G69*1.22 -> 10580.247 | J69: =I69*1.05 -> 11109.259
A70: MDV-V8S560V2R1A | B70: 56 | C70: 63 | D70: 61 | E70: 1.521 | F70: 243 | G70: 9520.6667 | I70: =G70*1.22 -> 11615.213 | J70: =I70*1.05 -> 12195.974
A71: MDV-V8S615V2R1A | B71: 61.5 | C71: 69 | D71: 62 | E71: 1.521 | F71: 243 | G71: 9148.6667 | I71: =G71*1.22 -> 11161.373 | J71: =I71*1.05 -> 11719.442
A72: MDV-V8S670V2R1A | B72: 67 | C72: 75 | D72: 64 | E72: 1.521 | F72: 248 | G72: 9888 | I72: =G72*1.22 -> 12063.36 | J72: =I72*1.05 -> 12666.528
A73: Блоки V8S-i с боковым выбросом воздуха индивидуального исполнения, R410A
A74: (DC inverter, R410A, 380V) | G74: 0
A75: MDV-Vi252V2R1A | B75: 25.2 | C75: 27 | D75: 56 | E75: 1.384 | F75: 191 | G75: 4839.3333 | I75: =G75*1.22 -> 5903.9867 | J75: =I75*1.05 -> 6199.186
A76: MDV-Vi280V2R1A | B76: 28 | C76: 31.5 | D76: 57 | E76: 1.384 | F76: 191 | G76: 5100.6667 | I76: =G76*1.22 -> 6222.8133 | J76: =I76*1.05 -> 6533.954
A77: MDV-Vi335V2R1A | B77: 33.5 | C77: 37.5 | D77: 58 | E77: 1.384 | F77: 194 | G77: 5602.6667 | I77: =G77*1.22 -> 6835.2533 | J77: =I77*1.05 -> 7177.016
A78: MDV-Vi400V2R1A | B78: 40 | C78: 45 | D78: 59 | E78: 1.384 | F78: 196 | G78: 6414 | I78: =G78*1.22 -> 7825.08 | J78: =I78*1.05 -> 8216.334
A79: MDV-Vi450V2R1A | B79: 45 | C79: 50 | D79: 60 | E79: 1.384 | F79: 196 | G79: 6582 | I79: =G79*1.22 -> 8030.04 | J79: =I79*1.05 -> 8431.542
A80: MDV-Vi500V2R1A | B80: 50 | C80: 57 | D80: 61 | E80: 1.521 | F80: 223 | G80: 7607.6667 | I80: =G80*1.22 -> 9281.3533 | J80: =I80*1.05 -> 9745.421
A81: MDV-Vi560V2R1A | B81: 56 | C81: 63 | D81: 61 | E81: 1.521 | F81: 243 | G81: 8030.6667 | I81: =G81*1.22 -> 9797.4133 | J81: =I81*1.05 -> 10287.284
A82: MDV-Vi615V2R1A | B82: 61.5 | C82: 69 | D82: 62 | E82: 1.521 | F82: 243 | G82: 8713 | I82: =G82*1.22 -> 10629.86 | J82: =I82*1.05 -> 11161.353
A83: MDV-Vi670V2R1A | B83: 67 | C83: 75 | D83: 64 | E83: 1.521 | F83: 248 | G83: 9417 | I83: =G83*1.22 -> 11488.74 | J83: =I83*1.05 -> 12063.177
A84: Мини VRF V8, 1-фазные, R410A
A85: (DC inverter, R410A, 380V) | G85: 0
A86: MDV-V8M80V2R1E | B86: 8 | C86: 9 | D86: 53 | E86: 0.615 | F86: 90 | G86: 1537.3333 | I86: =G86*1.22 -> 1875.5467 | J86: =I86*1.05 -> 1969.324
A87: MDV-V8M100V2R1E | B87: 10 | C87: 12 | D87: 53 | E87: 0.615 | F87: 90 | G87: 1791.3333 | I87: =G87*1.22 -> 2185.4267 | J87: =I87*1.05 -> 2294.698
A88: MDV-V8M120V2R1E | B88: 12 | C88: 14 | D88: 55 | E88: 0.615 | F88: 104 | G88: 2151 | I88: =G88*1.22 -> 2624.22 | J88: =I88*1.05 -> 2755.431
A89: MDV-V8M140V2R1E | B89: 14 | C89: 16 | D89: 56 | E89: 0.615 | F89: 104 | G89: 2348 | I89: =G89*1.22 -> 2864.56 | J89: =I89*1.05 -> 3007.788
A90: MDV-V8M160V2R1E | B90: 16 | C90: 18 | D90: 56 | E90: 0.615 | F90: 104 | G90: 2643.6667 | I90: =G90*1.22 -> 3225.2733 | J90: =I90*1.05 -> 3386.537
A91: Мини VRF V8, 3-фазные, R410A
A92: (DC inverter, R410A, 380V) | G92: 0
A93: MDV-V8M120V2R1B | B93: 12 | C93: 14 | D93: 55 | E93: 0.615 | F93: 119 | G93: 2567.6667 | I93: =G93*1.22 -> 3132.5533 | J93: =I93*1.05 -> 3289.181
A94: MDV-V8M140V2R1B | B94: 14 | C94: 16 | D94: 56 | E94: 0.615 | F94: 119 | G94: 2799 | I94: =G94*1.22 -> 3414.78 | J94: =I94*1.05 -> 3585.519
A95: MDV-V8M160V2R1B | B95: 16 | C95: 18 | D95: 56 | E95: 0.615 | F95: 119 | G95: 3148.3333 | I95: =G95*1.22 -> 3840.9667 | J95: =I95*1.05 -> 4033.015
A97: ВНУТРЕННИЕ БЛОКИ VRF серии V8 DC-inverter
A98: Кассетные компактные четырехпоточные
G99: 0
A100: MDVI3-15C4CVR12D | B100: 1.5 | C100: 1.8 | D100: 25~29 | E100: 0.136 | F100: 15 | G100: 362.66667 | I100: =G100*1.22 -> 442.45333 | J100: =I100*1.05 -> 464.576
A101: MDVI3-22C4CVR12D | B101: 2.2 | C101: 2.4 | D101: 25~29 | E101: 0.136 | F101: 15 | G101: 419.33333 | I101: =G101*1.22 -> 511.58667 | J101: =I101*1.05 -> 537.166
A102: MDVI3-28C4CVR12D | B102: 2.8 | C102: 3.2 | D102: 25~30 | E102: 0.136 | F102: 15 | G102: 425 | I102: =G102*1.22 -> 518.5 | J102: =I102*1.05 -> 544.425
A103: MDVI3-36C4CVR12D | B103: 3.6 | C103: 4 | D103: 25,5~31 | E103: 0.136 | F103: 16 | G103: 452.33333 | I103: =G103*1.22 -> 551.84667 | J103: =I103*1.05 -> 579.439
A104: MDVI3-45C4CVR12D | B104: 4.5 | C104: 5 | D104: 26,5~36,5 | E104: 0.136 | F104: 16 | G104: 494.66667 | I104: =G104*1.22 -> 603.49333 | J104: =I104*1.05 -> 633.668
A105: MDVI3-56C4CVR12D | B105: 5.6 | C105: 6.3 | D105: 32~39 | E105: 0.136 | F105: 17 | G105: 497.33333 | I105: =G105*1.22 -> 606.74667 | J105: =I105*1.05 -> 637.084
A106: MDVI3-63C4CVR12D | B106: 6.3 | C106: 7.1 | D106: 33,5~43 | E106: 0.136 | F106: 17 | G106: 516.66667 | I106: =G106*1.22 -> 630.33333 | J106: =I106*1.05 -> 661.85
A107: Декоративные панели | I107: =G107*1.22 -> 0
A108: MDV-MBQ4C-8PC | B108: панель потолочная для кассетных блоков компактных | E108: 0.036 | F108: 3.2 | G108: 89.666667 | I108: =G108*1.22 -> 109.39333 | J108: =I108*1.05 -> 114.863
A109: Кассетные полноразмерные четырехпоточные
G110: 0
A111: MDVI3-28C4VR12D | B111: 2.8 | C111: 3.2 | D111: 25~30 | E111: 0.221 | F111: 20.5 | G111: 483.66667 | I111: =G111*1.22 -> 590.07333 | J111: =I111*1.05 -> 619.577
A112: MDVI3-36C4VR12D | B112: 3.6 | C112: 4 | D112: 25~30 | E112: 0.221 | F112: 20.5 | G112: 491.66667 | I112: =G112*1.22 -> 599.83333 | J112: =I112*1.05 -> 629.825
A113: MDVI3-45C4VR12D | B113: 4.5 | C113: 5 | D113: 27~37 | E113: 0.221 | F113: 20.5 | G113: 519 | I113: =G113*1.22 -> 633.18 | J113: =I113*1.05 -> 664.839
