Workbook

Sheet Смета ЕР (общ) 
F1: Формат объекта | P1: курс $ | Q1: 81
F2: дверной | G2: Адрес объекта: | H2: г. Москва, ул. Маши Порываевой, д. 34 | P2: курс Евро | Q2: 95
F3: Плoщадь объекта (м.кв.): | G3: Плащадь объекта: | H3: - | P3: Дисконт по тендеру | Q3: 0
F4: Срок проведения работ | G4: Срок проведения работ | H4: Согласно план-графику производства работ | P4: курс Юань | Q4: 10.94
F5: ПОДРЯДЧИК: | G5: ПОДРЯДЧИК:
F6: Юридический адрес: | G6: Юридический адрес:
F7: Электронный адрес: | G7: Электронный адрес:
F8: Контактное лицо (Ф.И.О.) : | G8: Контактное лицо (Ф.И.О.) :
F9: Контактный телефон: | G9: Контактный телефон:
F10: Реквизиты: | G10: Реквизиты:
F11: Сумма по смете: | G11: Сумма по смете: | H11: =N1708 -> 0
A14: Раздел | B14: Подраздел | C14: Подраздел подраздела | D14: Пункт подраздела | E14: Новый номенклатурный номер | F14: № | G14: Наименование работ и затрат | H14: Един. изм. | I14: Кол - во. (объем) | J14: ЕР цена работ, руб.* | K14: ЕР цена материалов и оборудования, руб.* | L14: Цена работ, руб. * | M14: Цена материалов и оборудования, руб. * | N14: Стоимость работ, руб. * | O14: Стоимость материалов и оборудования руб. * | P14: Примечание | T14: Кол - во. (объем)
A15: Р1 | B15: 0 | D15: 0 | E15: =CONCATENATE('Смета ЕР (общ) '!$A15,".",'Смета ЕР (общ) '!$B15,".",'Смета ЕР (общ) '!$D15) -> Р1.0.0 | F15: 1 | G15: Раздел №1. Проектные работы и согласования | N15: =ROUND(N16,2) -> 0 | O15: =ROUND(O16,2) -> 0 | T15: 1498
A16: Р1 | B16: 1 | D16: 0 | E16: =CONCATENATE('Смета ЕР (общ) '!$A16,".",'Смета ЕР (общ) '!$B16,".",'Смета ЕР (общ) '!$D16) -> Р1.1.0 | F16: =IF(I16>0,F15+1,F15) -> 1 | G16: 1.1.0 Проектные работы и согласования | N16: =SUM(N17:N108) -> 0 | O16: =SUM(O17:O108) -> 0 | T16: 1498
A17: Р1 | B17: 1 | D17: 1 | E17: =CONCATENATE('Смета ЕР (общ) '!$A17,".",'Смета ЕР (общ) '!$B17,".",'Смета ЕР (общ) '!$D17) -> Р1.1.1 | F17: =IF(I17>0,F16+1,F16) -> 1 | G17: Техническое обследование состояния несущих конструкций помещения с подготовкой рекомендаций по усилению (Техничесекое заключение о конструктиве - "ТЗК") (для помещений от 100 до 450 м.кв) | H17: м2 | J17: ='[14]Проектирование 100-450'!E36*1.05 -> 3675 | K17: 0 | L17: =ROUND(J17-J17*$Q$3,2) -> 3675 | M17: =ROUND(K17-K17*$Q$3,2) -> 0 | N17: =ROUND('Смета ЕР (общ) '!$I17*'Смета ЕР (общ) '!$L17,2) -> 0 | O17: =ROUND('Смета ЕР (общ) '!$I17*'Смета ЕР (общ) '!$M17,2) -> 0
A18: Р1 | B18: 1 | D18: 44 | E18: =CONCATENATE('Смета ЕР (общ) '!$A18,".",'Смета ЕР (общ) '!$B18,".",'Смета ЕР (общ) '!$D18) -> Р1.1.44 | F18: =IF(I18>0,F17+1,F17) -> 1 | G18: Эскизный проект фасада и Колористический паспорт с указанием ведомости отделки и проектным решением со спецификацией элементов (крыльцо, пандус, навесы, колонны и т.д.)(для фасадов от 100 до 450 м.кв) | H18: м2 | J18: ='[14]Проектирование 100-450'!E37*1.05 -> 7822.5 | K18: 0 | L18: =ROUND(J18-J18*$Q$3,2) -> 7822.5 | M18: =ROUND(K18-K18*$Q$3,2) -> 0 | N18: =ROUND('Смета ЕР (общ) '!$I18*'Смета ЕР (общ) '!$L18,2) -> 0 | O18: =ROUND('Смета ЕР (общ) '!$I18*'Смета ЕР (общ) '!$M18,2) -> 0
A19: Р1 | B19: 1 | D19: 2 | E19: =CONCATENATE('Смета ЕР (общ) '!$A19,".",'Смета ЕР (общ) '!$B19,".",'Смета ЕР (общ) '!$D19) -> Р1.1.2 | F19: =IF(I19>0,F18+1,F18) -> 1 | G19: Рабочая документация по усилению/устройству несущих конструкций ("КР"), включая пояснительную записку (для помещений от 100 до 450 м.кв) | H19: м2 | J19: ='[14]Проектирование 100-450'!E18*1.05 -> 135.45 | K19: 0 | L19: =ROUND(J19-J19*$Q$3,2) -> 135.45 | M19: =ROUND(K19-K19*$Q$3,2) -> 0 | N19: =ROUND('Смета ЕР (общ) '!$I19*'Смета ЕР (общ) '!$L19,2) -> 0 | O19: =ROUND('Смета ЕР (общ) '!$I19*'Смета ЕР (общ) '!$M19,2) -> 0
A20: Р1 | B20: 1 | D20: 3 | E20: =CONCATENATE('Смета ЕР (общ) '!$A20,".",'Смета ЕР (общ) '!$B20,".",'Смета ЕР (общ) '!$D20) -> Р1.1.3 | F20: =IF(I20>0,F19+1,F19) -> 1 | G20: Рабочая документация "Архитектурные решения" ("АР"), включая пояснительную записку (для помещений от 100 до 450 м.кв) | H20: м2 | J20: ='[14]Проектирование 100-450'!E19*1.05 -> 389.55 | K20: 0 | L20: =ROUND(J20-J20*$Q$3,2) -> 389.55 | M20: =ROUND(K20-K20*$Q$3,2) -> 0 | N20: =ROUND('Смета ЕР (общ) '!$I20*'Смета ЕР (общ) '!$L20,2) -> 0 | O20: =ROUND('Смета ЕР (общ) '!$I20*'Смета ЕР (общ) '!$M20,2) -> 0 | T20: 214
A21: Р1 | B21: 1 | D21: 4 | E21: =CONCATENATE('Смета ЕР (общ) '!$A21,".",'Смета ЕР (общ) '!$B21,".",'Смета ЕР (общ) '!$D21) -> Р1.1.4 | F21: =IF(I21>0,F20+1,F20) -> 1 | G21: Рабочая документация по электроснабжению и электроосвещению ("ЭОМ"), включая пояснительную записку (для помещений от 100 до 450 м.кв) | H21: м2 | J21: ='[14]Проектирование 100-450'!E20*1.05 -> 258.3 | K21: 0 | L21: =ROUND(J21-J21*$Q$3,2) -> 258.3 | M21: =ROUND(K21-K21*$Q$3,2) -> 0 | N21: =ROUND('Смета ЕР (общ) '!$I21*'Смета ЕР (общ) '!$L21,2) -> 0 | O21: =ROUND('Смета ЕР (общ) '!$I21*'Смета ЕР (общ) '!$M21,2) -> 0 | T21: 214
A22: Р1 | B22: 1 | D22: 5 | E22: =CONCATENATE('Смета ЕР (общ) '!$A22,".",'Смета ЕР (общ) '!$B22,".",'Смета ЕР (общ) '!$D22) -> Р1.1.5 | F22: =IF(I22>0,F21+1,F21) -> 1 | G22: Рабочая документация Системы вентиляции ("ОВиК-В"), включая пояснительную записку (для помещений от 100 до 450 м.кв) | H22: м2 | J22: ='[14]Проектирование 100-450'!E21*1.05 -> 202.65 | K22: 0 | L22: =ROUND(J22-J22*$Q$3,2) -> 202.65 | M22: =ROUND(K22-K22*$Q$3,2) -> 0 | N22: =ROUND('Смета ЕР (общ) '!$I22*'Смета ЕР (общ) '!$L22,2) -> 0 | O22: =ROUND('Смета ЕР (общ) '!$I22*'Смета ЕР (общ) '!$M22,2) -> 0 | T22: 214
A23: Р1 | B23: 1 | D23: 6 | E23: =CONCATENATE('Смета ЕР (общ) '!$A23,".",'Смета ЕР (общ) '!$B23,".",'Смета ЕР (общ) '!$D23) -> Р1.1.6 | F23: =IF(I23>0,F22+1,F22) -> 1 | G23: Рабочая документация Системы кондиционирования ("ОВиК-К"), включая пояснительную записку (для помещений от 100 до 450 м.кв) | H23: м2 | J23: ='[14]Проектирование 100-450'!E22*1.05 -> 159.4845 | K23: 0 | L23: =ROUND(J23-J23*$Q$3,2) -> 159.48 | M23: =ROUND(K23-K23*$Q$3,2) -> 0 | N23: =ROUND('Смета ЕР (общ) '!$I23*'Смета ЕР (общ) '!$L23,2) -> 0 | O23: =ROUND('Смета ЕР (общ) '!$I23*'Смета ЕР (общ) '!$M23,2) -> 0 | T23: 214
A24: Р1 | B24: 1 | D24: 7 | E24: =CONCATENATE('Смета ЕР (общ) '!$A24,".",'Смета ЕР (общ) '!$B24,".",'Смета ЕР (общ) '!$D24) -> Р1.1.7 | F24: =IF(I24>0,F23+1,F23) -> 1 | G24: Рабочая документация Системы отопления ("ОВиК-О"), включая Пояснительную записку и Теплотехнический расчет (для помещений от 100 до 450 м.кв) | H24: м2 | J24: ='[14]Проектирование 100-450'!E23*1.05 -> 123.9 | K24: 0 | L24: =ROUND(J24-J24*$Q$3,2) -> 123.9 | M24: =ROUND(K24-K24*$Q$3,2) -> 0 | N24: =ROUND('Смета ЕР (общ) '!$I24*'Смета ЕР (общ) '!$L24,2) -> 0 | O24: =ROUND('Смета ЕР (общ) '!$I24*'Смета ЕР (общ) '!$M24,2) -> 0 | T24: 214
A25: Р1 | B25: 1 | D25: 8 | E25: =CONCATENATE('Смета ЕР (общ) '!$A25,".",'Смета ЕР (общ) '!$B25,".",'Смета ЕР (общ) '!$D25) -> Р1.1.8 | F25: =IF(I25>0,F24+1,F24) -> 1 | G25: Рабочая документация Системы водоснабжения и канализации ("ВК"), включая пояснительную записку (для помещений от 100 до 450 м.кв) | H25: м2 | J25: ='[14]Проектирование 100-450'!E24*1.05 -> 130.2 | K25: 0 | L25: =ROUND(J25-J25*$Q$3,2) -> 130.2 | M25: =ROUND(K25-K25*$Q$3,2) -> 0 | N25: =ROUND('Смета ЕР (общ) '!$I25*'Смета ЕР (общ) '!$L25,2) -> 0 | O25: =ROUND('Смета ЕР (общ) '!$I25*'Смета ЕР (общ) '!$M25,2) -> 0 | T25: 214
A26: Р1 | B26: 1 | D26: 9 | E26: =CONCATENATE('Смета ЕР (общ) '!$A26,".",'Смета ЕР (общ) '!$B26,".",'Смета ЕР (общ) '!$D26) -> Р1.1.9 | F26: =IF(I26>0,F25+1,F25) -> 1 | G26: Рабочая документация Системы автоматической установки водяного пожаротушения ("АУВПТ"), (спринкерная, дренчерная, модульная система), включая пояснительную записку (для помещений от 100 до 450 м.кв) | H26: м2 | J26: ='[14]Проектирование 100-450'!E25*1.05 -> 91.6755 | K26: 0 | L26: =ROUND(J26-J26*$Q$3,2) -> 91.68 | M26: =ROUND(K26-K26*$Q$3,2) -> 0 | N26: =ROUND('Смета ЕР (общ) '!$I26*'Смета ЕР (общ) '!$L26,2) -> 0 | O26: =ROUND('Смета ЕР (общ) '!$I26*'Смета ЕР (общ) '!$M26,2) -> 0
A27: Р1 | B27: 1 | D27: 43 | E27: =CONCATENATE('Смета ЕР (общ) '!$A27,".",'Смета ЕР (общ) '!$B27,".",'Смета ЕР (общ) '!$D27) -> Р1.1.43 | F27: =IF(I27>0,F26+1,F26) -> 1 | G27: Рабочая документация Системы Внутреннего противопожарного водопровода ("ВПВ"), включая пояснительную записку (для помещений от 100 до 450 м.кв) | H27: м2 | J27: ='[14]Проектирование 100-450'!E26*1.05 -> 91.6755 | K27: 0 | L27: =ROUND(J27-J27*$Q$3,2) -> 91.68 | M27: =ROUND(K27-K27*$Q$3,2) -> 0 | N27: =ROUND('Смета ЕР (общ) '!$I27*'Смета ЕР (общ) '!$L27,2) -> 0 | O27: =ROUND('Смета ЕР (общ) '!$I27*'Смета ЕР (общ) '!$M27,2) -> 0
A28: Р1 | B28: 1 | D28: 10 | E28: =CONCATENATE('Смета ЕР (общ) '!$A28,".",'Смета ЕР (общ) '!$B28,".",'Смета ЕР (общ) '!$D28) -> Р1.1.10 | F28: =IF(I28>0,F27+1,F27) -> 1 | G28: Рабочая документация Системы дымоудаления ("ДУ"), включая пояснительную записку (для помещений от 100 до 450 м.кв) | H28: м2 | J28: ='[14]Проектирование 100-450'!E27*1.05 -> 103.95 | K28: 0 | L28: =ROUND(J28-J28*$Q$3,2) -> 103.95 | M28: =ROUND(K28-K28*$Q$3,2) -> 0 | N28: =ROUND('Смета ЕР (общ) '!$I28*'Смета ЕР (общ) '!$L28,2) -> 0 | O28: =ROUND('Смета ЕР (общ) '!$I28*'Смета ЕР (общ) '!$M28,2) -> 0
A29: Р1 | B29: 1 | D29: 11 | E29: =CONCATENATE('Смета ЕР (общ) '!$A29,".",'Смета ЕР (общ) '!$B29,".",'Смета ЕР (общ) '!$D29) -> Р1.1.11 | F29: =IF(I29>0,F28+1,F28) -> 1 | G29: Рабочая документация "Автоматическая пожарная сигнализация" (АПС) | H29: м2 | J29: ='[14]АПС, СОУЭ, ППА'!F13*1.05*0.1 -> 7.035 | K29: 0 | L29: =ROUND(J29-J29*$Q$3,2) -> 7.04 | M29: =ROUND(K29-K29*$Q$3,2) -> 0 | N29: =ROUND('Смета ЕР (общ) '!$I29*'Смета ЕР (общ) '!$L29,2) -> 0 | O29: =ROUND('Смета ЕР (общ) '!$I29*'Смета ЕР (общ) '!$M29,2) -> 0
A30: Р1 | B30: 1 | D30: 25 | E30: =CONCATENATE('Смета ЕР (общ) '!$A30,".",'Смета ЕР (общ) '!$B30,".",'Смета ЕР (общ) '!$D30) -> Р1.1.25 | F30: =IF(I30>0,F29+1,F29) -> 1 | G30: Рабочая документация "Система оповещения и управления эвакуацией людей при пожаре" (СОУЭ) | H30: м2 | J30: ='[14]АПС, СОУЭ, ППА'!F14*1.05*0.1 -> 4.095 | K30: 0 | L30: =ROUND(J30-J30*$Q$3,2) -> 4.1 | M30: =ROUND(K30-K30*$Q$3,2) -> 0 | N30: =ROUND('Смета ЕР (общ) '!$I30*'Смета ЕР (общ) '!$L30,2) -> 0 | O30: =ROUND('Смета ЕР (общ) '!$I30*'Смета ЕР (общ) '!$M30,2) -> 0
A31: Р1 | B31: 1 | D31: 26 | E31: =CONCATENATE('Смета ЕР (общ) '!$A31,".",'Смета ЕР (общ) '!$B31,".",'Смета ЕР (общ) '!$D31) -> Р1.1.26 | F31: =IF(I31>0,F30+1,F30) -> 1 | G31: Рабочая документация "Автоматизация системы внутреннего противопожарного водопровода (ВПВ) | H31: м2 | J31: ='[14]АПС, СОУЭ, ППА'!F16*1.05*0.1 -> 0.84 | K31: 0 | L31: =ROUND(J31-J31*$Q$3,2) -> 0.84 | M31: =ROUND(K31-K31*$Q$3,2) -> 0 | N31: =ROUND('Смета ЕР (общ) '!$I31*'Смета ЕР (общ) '!$L31,2) -> 0 | O31: =ROUND('Смета ЕР (общ) '!$I31*'Смета ЕР (общ) '!$M31,2) -> 0
A32: Р1 | B32: 1 | D32: 29 | E32: =CONCATENATE('Смета ЕР (общ) '!$A32,".",'Смета ЕР (общ) '!$B32,".",'Смета ЕР (общ) '!$D32) -> Р1.1.29 | F32: =IF(I32>0,F31+1,F31) -> 1 | G32: Рабочая документация "Автоматизация системы противодымной вентиляции (ПДВ")" | H32: м2 | J32: ='[14]АПС, СОУЭ, ППА'!F17*1.05*0.1 -> 2.625 | K32: 0 | L32: =ROUND(J32-J32*$Q$3,2) -> 2.63 | M32: =ROUND(K32-K32*$Q$3,2) -> 0 | N32: =ROUND('Смета ЕР (общ) '!$I32*'Смета ЕР (общ) '!$L32,2) -> 0 | O32: =ROUND('Смета ЕР (общ) '!$I32*'Смета ЕР (общ) '!$M32,2) -> 0
A33: Р1 | B33: 1 | D33: 30 | E33: =CONCATENATE('Смета ЕР (общ) '!$A33,".",'Смета ЕР (общ) '!$B33,".",'Смета ЕР (общ) '!$D33) -> Р1.1.30 | F33: =IF(I33>0,F32+1,F32) -> 1 | G33: Рабочая документация "Автоматизация Системы отопления, вентиляции и кондиционирования (ОВиК)" | H33: м2 | J33: ='[14]АПС, СОУЭ, ППА'!F18*1.05*0.1 -> 0.315 | K33: 0 | L33: =ROUND(J33-J33*$Q$3,2) -> 0.32 | M33: =ROUND(K33-K33*$Q$3,2) -> 0 | N33: =ROUND('Смета ЕР (общ) '!$I33*'Смета ЕР (общ) '!$L33,2) -> 0 | O33: =ROUND('Смета ЕР (общ) '!$I33*'Смета ЕР (общ) '!$M33,2) -> 0
A34: Р1 | B34: 1 | D34: 31 | E34: =CONCATENATE('Смета ЕР (общ) '!$A34,".",'Смета ЕР (общ) '!$B34,".",'Смета ЕР (общ) '!$D34) -> Р1.1.31 | F34: =IF(I34>0,F33+1,F33) -> 1 | G34: Рабочая документация "Автоматизация Системы аварийного освещения (АО)" | H34: м2 | J34: ='[14]АПС, СОУЭ, ППА'!F19*1.05*0.1 -> 0.105 | K34: 0 | L34: =ROUND(J34-J34*$Q$3,2) -> 0.11 | M34: =ROUND(K34-K34*$Q$3,2) -> 0 | N34: =ROUND('Смета ЕР (общ) '!$I34*'Смета ЕР (общ) '!$L34,2) -> 0 | O34: =ROUND('Смета ЕР (общ) '!$I34*'Смета ЕР (общ) '!$M34,2) -> 0
A35: Р1 | B35: 1 | D35: 33 | E35: =CONCATENATE('Смета ЕР (общ) '!$A35,".",'Смета ЕР (общ) '!$B35,".",'Смета ЕР (общ) '!$D35) -> Р1.1.33 | F35: =IF(I35>0,F34+1,F34) -> 1 | G35: Рабочая документация "Автоматизации лифтовового хозяйства" | H35: м2 | J35: ='[14]АПС, СОУЭ, ППА'!F20*1.05*0.1 -> 0.105 | K35: 0 | L35: =ROUND(J35-J35*$Q$3,2) -> 0.11 | M35: =ROUND(K35-K35*$Q$3,2) -> 0 | N35: =ROUND('Смета ЕР (общ) '!$I35*'Смета ЕР (общ) '!$L35,2) -> 0 | O35: =ROUND('Смета ЕР (общ) '!$I35*'Смета ЕР (общ) '!$M35,2) -> 0
A36: Р1 | B36: 1 | D36: 36 | E36: =CONCATENATE('Смета ЕР (общ) '!$A36,".",'Смета ЕР (общ) '!$B36,".",'Смета ЕР (общ) '!$D36) -> Р1.1.36 | F36: =IF(I36>0,F35+1,F35) -> 1 | G36: Рабочая документация "Автоматизации Системы контроля управления доступом (СКУД)" | H36: м2 | J36: ='[14]АПС, СОУЭ, ППА'!F21*1.05*0.1 -> 0.105 | K36: 0 | L36: =ROUND(J36-J36*$Q$3,2) -> 0.11 | M36: =ROUND(K36-K36*$Q$3,2) -> 0 | N36: =ROUND('Смета ЕР (общ) '!$I36*'Смета ЕР (общ) '!$L36,2) -> 0 | O36: =ROUND('Смета ЕР (общ) '!$I36*'Смета ЕР (общ) '!$M36,2) -> 0
A37: Р1 | B37: 1 | D37: 37 | E37: =CONCATENATE('Смета ЕР (общ) '!$A37,".",'Смета ЕР (общ) '!$B37,".",'Смета ЕР (общ) '!$D37) -> Р1.1.37 | F37: =IF(I37>0,F36+1,F36) -> 1 | G37: Техническое обследование состояния несущих конструкций помещения с подготовкой рекомендаций по усилению в зоне расположения депозитария, кассового узла и банкоматов (Техничесекое заключение о конструктиве - "ТЗК")(для помещений менее 100 м.кв) | H37: м2 | J37: ='[14]Проектирование до 100'!E35*1.05 -> 3675 | K37: 0 | L37: =ROUND(J37-J37*$Q$3,2) -> 3675 | M37: =ROUND(K37-K37*$Q$3,2) -> 0 | N37: =ROUND('Смета ЕР (общ) '!$I37*'Смета ЕР (общ) '!$L37,2) -> 0 | O37: =ROUND('Смета ЕР (общ) '!$I37*'Смета ЕР (общ) '!$M37,2) -> 0
A38: Р1 | B38: 1 | D38: 45 | E38: =CONCATENATE('Смета ЕР (общ) '!$A38,".",'Смета ЕР (общ) '!$B38,".",'Смета ЕР (общ) '!$D38) -> Р1.1.45 | F38: =IF(I38>0,F37+1,F37) -> 1 | G38: Эскизный проект фасада и колористический паспорт с указанием ведомости отделки и проектным решением со спецификацией элементов (крыльцо, пандус, навесы, колонны и т.д.)(для фасадов менее 100 м.кв) | H38: кв.м.площади фасада | J38: ='[14]Проектирование до 100'!E36*1.05 -> 7822.5 | K38: 0 | L38: =ROUND(J38-J38*$Q$3,2) -> 7822.5 | M38: =ROUND(K38-K38*$Q$3,2) -> 0 | N38: =ROUND('Смета ЕР (общ) '!$I38*'Смета ЕР (общ) '!$L38,2) -> 0 | O38: =ROUND('Смета ЕР (общ) '!$I38*'Смета ЕР (общ) '!$M38,2) -> 0
A39: Р1 | B39: 1 | D39: 46 | E39: =CONCATENATE('Смета ЕР (общ) '!$A39,".",'Смета ЕР (общ) '!$B39,".",'Смета ЕР (общ) '!$D39) -> Р1.1.46 | F39: =IF(I39>0,F38+1,F38) -> 1 | G39: Рабочая документация по усилению/устройству несущих конструкций ("КР"), включая пояснительную записку (для помещений менее 100 м.кв) | H39: компл. | J39: ='[14]Проектирование до 100'!E17*1.05 -> 10500 | K39: 0 | L39: =ROUND(J39-J39*$Q$3,2) -> 10500 | M39: =ROUND(K39-K39*$Q$3,2) -> 0 | N39: =ROUND('Смета ЕР (общ) '!$I39*'Смета ЕР (общ) '!$L39,2) -> 0 | O39: =ROUND('Смета ЕР (общ) '!$I39*'Смета ЕР (общ) '!$M39,2) -> 0
A40: Р1 | B40: 1 | D40: 47 | E40: =CONCATENATE('Смета ЕР (общ) '!$A40,".",'Смета ЕР (общ) '!$B40,".",'Смета ЕР (общ) '!$D40) -> Р1.1.47 | F40: =IF(I40>0,F39+1,F39) -> 1 | G40: Рабочая документация "Архитектурные решения" ("АР"), включая пояснительную записку (для помещений менее 100 м.кв) | H40: компл. | J40: ='[14]Проектирование до 100'!E18*1.05 -> 20737.5 | K40: 0 | L40: =ROUND(J40-J40*$Q$3,2) -> 20737.5 | M40: =ROUND(K40-K40*$Q$3,2) -> 0 | N40: =ROUND('Смета ЕР (общ) '!$I40*'Смета ЕР (общ) '!$L40,2) -> 0 | O40: =ROUND('Смета ЕР (общ) '!$I40*'Смета ЕР (общ) '!$M40,2) -> 0
A41: Р1 | B41: 1 | D41: 48 | E41: =CONCATENATE('Смета ЕР (общ) '!$A41,".",'Смета ЕР (общ) '!$B41,".",'Смета ЕР (общ) '!$D41) -> Р1.1.48 | F41: =IF(I41>0,F40+1,F40) -> 1 | G41: Рабочая документация по электроснабжению и электроосвещению ("ЭОМ"), включая пояснительную записку (для помещений менее 100 м.кв) | H41: компл. | J41: ='[14]Проектирование до 100'!E19*1.05 -> 20737.5 | K41: 0 | L41: =ROUND(J41-J41*$Q$3,2) -> 20737.5 | M41: =ROUND(K41-K41*$Q$3,2) -> 0 | N41: =ROUND('Смета ЕР (общ) '!$I41*'Смета ЕР (общ) '!$L41,2) -> 0 | O41: =ROUND('Смета ЕР (общ) '!$I41*'Смета ЕР (общ) '!$M41,2) -> 0
A42: Р1 | B42: 1 | D42: 49 | E42: =CONCATENATE('Смета ЕР (общ) '!$A42,".",'Смета ЕР (общ) '!$B42,".",'Смета ЕР (общ) '!$D42) -> Р1.1.49 | F42: =IF(I42>0,F41+1,F41) -> 1 | G42: Рабочая документация Системы вентиляции ("ОВиК-В"), включая пояснительную записку (для помещений менее 100 м.кв) | H42: компл. | J42: ='[14]Проектирование до 100'!E20*1.05 -> 15592.5 | K42: 0 | L42: =ROUND(J42-J42*$Q$3,2) -> 15592.5 | M42: =ROUND(K42-K42*$Q$3,2) -> 0 | N42: =ROUND('Смета ЕР (общ) '!$I42*'Смета ЕР (общ) '!$L42,2) -> 0 | O42: =ROUND('Смета ЕР (общ) '!$I42*'Смета ЕР (общ) '!$M42,2) -> 0
A43: Р1 | B43: 1 | D43: 50 | E43: =CONCATENATE('Смета ЕР (общ) '!$A43,".",'Смета ЕР (общ) '!$B43,".",'Смета ЕР (общ) '!$D43) -> Р1.1.50 | F43: =IF(I43>0,F42+1,F42) -> 1 | G43: Рабочая документация Системы кондиционирования ("ОВиК-К"), включая пояснительную записку (для помещений менее 100 м.кв) | H43: компл. | J43: ='[14]Проектирование до 100'!E21*1.05 -> 10395 | K43: 0 | L43: =ROUND(J43-J43*$Q$3,2) -> 10395 | M43: =ROUND(K43-K43*$Q$3,2) -> 0 | N43: =ROUND('Смета ЕР (общ) '!$I43*'Смета ЕР (общ) '!$L43,2) -> 0 | O43: =ROUND('Смета ЕР (общ) '!$I43*'Смета ЕР (общ) '!$M43,2) -> 0
A44: Р1 | B44: 1 | D44: 51 | E44: =CONCATENATE('Смета ЕР (общ) '!$A44,".",'Смета ЕР (общ) '!$B44,".",'Смета ЕР (общ) '!$D44) -> Р1.1.51 | F44: =IF(I44>0,F43+1,F43) -> 1 | G44: Рабочая документация Системы отопления ("ОВиК-О"), включая Пояснительную записку и Теплотехнический расчет (для помещений менее 100 м.кв) | H44: компл. | J44: ='[14]Проектирование до 100'!E22*1.05 -> 10395 | K44: 0 | L44: =ROUND(J44-J44*$Q$3,2) -> 10395 | M44: =ROUND(K44-K44*$Q$3,2) -> 0 | N44: =ROUND('Смета ЕР (общ) '!$I44*'Смета ЕР (общ) '!$L44,2) -> 0 | O44: =ROUND('Смета ЕР (общ) '!$I44*'Смета ЕР (общ) '!$M44,2) -> 0
A45: Р1 | B45: 1 | D45: 52 | E45: =CONCATENATE('Смета ЕР (общ) '!$A45,".",'Смета ЕР (общ) '!$B45,".",'Смета ЕР (общ) '!$D45) -> Р1.1.52 | F45: =IF(I45>0,F44+1,F44) -> 1 | G45: Рабочая документация Системы водоснабжения и канализации ("ВК"), включая пояснительную записку (для помещений менее 100 м.кв) | H45: компл. | J45: ='[14]Проектирование до 100'!E23*1.05 -> 10395 | K45: 0 | L45: =ROUND(J45-J45*$Q$3,2) -> 10395 | M45: =ROUND(K45-K45*$Q$3,2) -> 0 | N45: =ROUND('Смета ЕР (общ) '!$I45*'Смета ЕР (общ) '!$L45,2) -> 0 | O45: =ROUND('Смета ЕР (общ) '!$I45*'Смета ЕР (общ) '!$M45,2) -> 0
A46: Р1 | B46: 1 | D46: 53 | E46: =CONCATENATE('Смета ЕР (общ) '!$A46,".",'Смета ЕР (общ) '!$B46,".",'Смета ЕР (общ) '!$D46) -> Р1.1.53 | F46: =IF(I46>0,F45+1,F45) -> 1 | G46: Рабочая документация Системы автоматической установки водяного пожаротушения ("АУВПТ"), (спринкерная, дренчерная, модульная система), включая пояснительную записку (для помещений менее 100 м.кв) | H46: компл. | J46: ='[14]Проектирование до 100'!E24*1.05 -> 15592.5 | K46: 0 | L46: =ROUND(J46-J46*$Q$3,2) -> 15592.5 | M46: =ROUND(K46-K46*$Q$3,2) -> 0 | N46: =ROUND('Смета ЕР (общ) '!$I46*'Смета ЕР (общ) '!$L46,2) -> 0 | O46: =ROUND('Смета ЕР (общ) '!$I46*'Смета ЕР (общ) '!$M46,2) -> 0
A47: Р1 | B47: 1 | D47: 54 | E47: =CONCATENATE('Смета ЕР (общ) '!$A47,".",'Смета ЕР (общ) '!$B47,".",'Смета ЕР (общ) '!$D47) -> Р1.1.54 | F47: =IF(I47>0,F46+1,F46) -> 1 | G47: Рабочая документация Системы Внутреннего противопожарного водопровода ("ВПВ"), включая пояснительную записку (для помещений менее 100 м.кв) | H47: компл. | J47: ='[14]Проектирование до 100'!E25*1.05 -> 10395 | K47: 0 | L47: =ROUND(J47-J47*$Q$3,2) -> 10395 | M47: =ROUND(K47-K47*$Q$3,2) -> 0 | N47: =ROUND('Смета ЕР (общ) '!$I47*'Смета ЕР (общ) '!$L47,2) -> 0 | O47: =ROUND('Смета ЕР (общ) '!$I47*'Смета ЕР (общ) '!$M47,2) -> 0
A48: Р1 | B48: 1 | D48: 55 | E48: =CONCATENATE('Смета ЕР (общ) '!$A48,".",'Смета ЕР (общ) '!$B48,".",'Смета ЕР (общ) '!$D48) -> Р1.1.55 | F48: =IF(I48>0,F47+1,F47) -> 1 | G48: Рабочая документация Системы дымоудаления ("ДУ"), включая пояснительную записку (для помещений менее 100 м.кв) | H48: компл. | J48: ='[14]Проектирование до 100'!E26*1.05 -> 15592.5 | K48: 0 | L48: =ROUND(J48-J48*$Q$3,2) -> 15592.5 | M48: =ROUND(K48-K48*$Q$3,2) -> 0 | N48: =ROUND('Смета ЕР (общ) '!$I48*'Смета ЕР (общ) '!$L48,2) -> 0 | O48: =ROUND('Смета ЕР (общ) '!$I48*'Смета ЕР (общ) '!$M48,2) -> 0
A49: Р1 | B49: 1 | D49: 56 | E49: =CONCATENATE('Смета ЕР (общ) '!$A49,".",'Смета ЕР (общ) '!$B49,".",'Смета ЕР (общ) '!$D49) -> Р1.1.56 | F49: =IF(I49>0,F48+1,F48) -> 1 | G49: Исполнительная документация по усилению/устройству несущих конструкций ("КР"), включая пояснительную записку (для объектов более 100 кв.м.) | H49: м2 | J49: ='[14]Проектирование 100-450'!E18*1.05*0.1 -> 13.545 | K49: 0 | L49: =ROUND(J49-J49*$Q$3,2) -> 13.55 | M49: =ROUND(K49-K49*$Q$3,2) -> 0 | N49: =ROUND('Смета ЕР (общ) '!$I49*'Смета ЕР (общ) '!$L49,2) -> 0 | O49: =ROUND('Смета ЕР (общ) '!$I49*'Смета ЕР (общ) '!$M49,2) -> 0
A50: Р1 | B50: 1 | D50: 57 | E50: =CONCATENATE('Смета ЕР (общ) '!$A50,".",'Смета ЕР (общ) '!$B50,".",'Смета ЕР (общ) '!$D50) -> Р1.1.57 | F50: =IF(I50>0,F49+1,F49) -> 1 | G50: Исполнительная документация "Архитектурные решения" ("АР"), включая пояснительную записку (для объектов более 100 кв.м.) | H50: м2 | J50: ='[14]Проектирование 100-450'!E19*1.05*0.1 -> 38.955 | K50: 0 | L50: =ROUND(J50-J50*$Q$3,2) -> 38.96 | M50: =ROUND(K50-K50*$Q$3,2) -> 0 | N50: =ROUND('Смета ЕР (общ) '!$I50*'Смета ЕР (общ) '!$L50,2) -> 0 | O50: =ROUND('Смета ЕР (общ) '!$I50*'Смета ЕР (общ) '!$M50,2) -> 0
A51: Р1 | B51: 1 | D51: 58 | E51: =CONCATENATE('Смета ЕР (общ) '!$A51,".",'Смета ЕР (общ) '!$B51,".",'Смета ЕР (общ) '!$D51) -> Р1.1.58 | F51: =IF(I51>0,F50+1,F50) -> 1 | G51: Исполнительная документация по электроснабжению и электроосвещению ("ЭОМ"), включая пояснительную записку (для объектов более 100 кв.м.) | H51: м2 | J51: ='[14]Проектирование 100-450'!E20*1.05*0.1 -> 25.83 | K51: 0 | L51: =ROUND(J51-J51*$Q$3,2) -> 25.83 | M51: =ROUND(K51-K51*$Q$3,2) -> 0 | N51: =ROUND('Смета ЕР (общ) '!$I51*'Смета ЕР (общ) '!$L51,2) -> 0 | O51: =ROUND('Смета ЕР (общ) '!$I51*'Смета ЕР (общ) '!$M51,2) -> 0
A52: Р1 | B52: 1 | D52: 59 | E52: =CONCATENATE('Смета ЕР (общ) '!$A52,".",'Смета ЕР (общ) '!$B52,".",'Смета ЕР (общ) '!$D52) -> Р1.1.59 | F52: =IF(I52>0,F51+1,F51) -> 1 | G52: Исполнительная документация Системы вентиляции ("ОВиК-В"), включая пояснительную записку (для объектов более 100 кв.м.) | H52: м2 | J52: ='[14]Проектирование 100-450'!E21*1.05*0.1 -> 20.265 | K52: 0 | L52: =ROUND(J52-J52*$Q$3,2) -> 20.27 | M52: =ROUND(K52-K52*$Q$3,2) -> 0 | N52: =ROUND('Смета ЕР (общ) '!$I52*'Смета ЕР (общ) '!$L52,2) -> 0 | O52: =ROUND('Смета ЕР (общ) '!$I52*'Смета ЕР (общ) '!$M52,2) -> 0
A53: Р1 | B53: 1 | D53: 60 | E53: =CONCATENATE('Смета ЕР (общ) '!$A53,".",'Смета ЕР (общ) '!$B53,".",'Смета ЕР (общ) '!$D53) -> Р1.1.60 | F53: =IF(I53>0,F52+1,F52) -> 1 | G53: Исполнительная документация Системы кондиционирования ("ОВиК-К"), включая пояснительную записку (для объектов более 100 кв.м.) | H53: м2 | J53: ='[14]Проектирование 100-450'!E22*1.05*0.1 -> 15.94845 | K53: 0 | L53: =ROUND(J53-J53*$Q$3,2) -> 15.95 | M53: =ROUND(K53-K53*$Q$3,2) -> 0 | N53: =ROUND('Смета ЕР (общ) '!$I53*'Смета ЕР (общ) '!$L53,2) -> 0 | O53: =ROUND('Смета ЕР (общ) '!$I53*'Смета ЕР (общ) '!$M53,2) -> 0
A54: Р1 | B54: 1 | D54: 61 | E54: =CONCATENATE('Смета ЕР (общ) '!$A54,".",'Смета ЕР (общ) '!$B54,".",'Смета ЕР (общ) '!$D54) -> Р1.1.61 | F54: =IF(I54>0,F53+1,F53) -> 1 | G54: Исполнительная документация Системы отопления ("ОВиК-О"), включая Пояснительную записку и Теплотехнический расчет (для объектов более 100 кв.м.) | H54: м2 | J54: ='[14]Проектирование 100-450'!E23*1.05*0.1 -> 12.39 | K54: 0 | L54: =ROUND(J54-J54*$Q$3,2) -> 12.39 | M54: =ROUND(K54-K54*$Q$3,2) -> 0 | N54: =ROUND('Смета ЕР (общ) '!$I54*'Смета ЕР (общ) '!$L54,2) -> 0 | O54: =ROUND('Смета ЕР (общ) '!$I54*'Смета ЕР (общ) '!$M54,2) -> 0
A55: Р1 | B55: 1 | D55: 62 | E55: =CONCATENATE('Смета ЕР (общ) '!$A55,".",'Смета ЕР (общ) '!$B55,".",'Смета ЕР (общ) '!$D55) -> Р1.1.62 | F55: =IF(I55>0,F54+1,F54) -> 1 | G55: Исполнительная документация Системы водоснабжения и канализации ("ВК"), включая пояснительную записку (для объектов более 100 кв.м.) | H55: м2 | J55: ='[14]Проектирование 100-450'!E24*1.05*0.1 -> 13.02 | K55: 0 | L55: =ROUND(J55-J55*$Q$3,2) -> 13.02 | M55: =ROUND(K55-K55*$Q$3,2) -> 0 | N55: =ROUND('Смета ЕР (общ) '!$I55*'Смета ЕР (общ) '!$L55,2) -> 0 | O55: =ROUND('Смета ЕР (общ) '!$I55*'Смета ЕР (общ) '!$M55,2) -> 0
A56: Р1 | B56: 1 | D56: 63 | E56: =CONCATENATE('Смета ЕР (общ) '!$A56,".",'Смета ЕР (общ) '!$B56,".",'Смета ЕР (общ) '!$D56) -> Р1.1.63 | F56: =IF(I56>0,F55+1,F55) -> 1 | G56: Исполнительная документация Системы автматической установки водяного пожаротушения ("АУВПТ"), (спринкерная, дренчерная, модульная система), включая пояснительную записку (для объектов более 100 кв.м.) | H56: м2 | J56: ='[14]Проектирование 100-450'!E25*1.05*0.1 -> 9.16755 | K56: 0 | L56: =ROUND(J56-J56*$Q$3,2) -> 9.17 | M56: =ROUND(K56-K56*$Q$3,2) -> 0 | N56: =ROUND('Смета ЕР (общ) '!$I56*'Смета ЕР (общ) '!$L56,2) -> 0 | O56: =ROUND('Смета ЕР (общ) '!$I56*'Смета ЕР (общ) '!$M56,2) -> 0
A57: Р1 | B57: 1 | D57: 64 | E57: =CONCATENATE('Смета ЕР (общ) '!$A57,".",'Смета ЕР (общ) '!$B57,".",'Смета ЕР (общ) '!$D57) -> Р1.1.64 | F57: =IF(I57>0,F56+1,F56) -> 1 | G57: Исполнительная документация Системы Внутреннего противопожарного водопровода ("ВПВ"), включая пояснительную записку (для объектов более 100 кв.м.) | H57: м2 | J57: ='[14]Проектирование 100-450'!E26*1.05*0.1 -> 9.16755 | K57: 0 | L57: =ROUND(J57-J57*$Q$3,2) -> 9.17 | M57: =ROUND(K57-K57*$Q$3,2) -> 0 | N57: =ROUND('Смета ЕР (общ) '!$I57*'Смета ЕР (общ) '!$L57,2) -> 0 | O57: =ROUND('Смета ЕР (общ) '!$I57*'Смета ЕР (общ) '!$M57,2) -> 0
A58: Р1 | B58: 1 | D58: 65 | E58: =CONCATENATE('Смета ЕР (общ) '!$A58,".",'Смета ЕР (общ) '!$B58,".",'Смета ЕР (общ) '!$D58) -> Р1.1.65 | F58: =IF(I58>0,F57+1,F57) -> 1 | G58: Исполнительная документация Системы дымоудаления ("ДУ"), включая пояснительную записку (для объектов более 100 кв.м.) | H58: м2 | J58: ='[14]Проектирование 100-450'!E27*1.05*0.1 -> 10.395 | K58: 0 | L58: =ROUND(J58-J58*$Q$3,2) -> 10.4 | M58: =ROUND(K58-K58*$Q$3,2) -> 0 | N58: =ROUND('Смета ЕР (общ) '!$I58*'Смета ЕР (общ) '!$L58,2) -> 0 | O58: =ROUND('Смета ЕР (общ) '!$I58*'Смета ЕР (общ) '!$M58,2) -> 0
A59: Р1 | B59: 1 | D59: 66 | E59: =CONCATENATE('Смета ЕР (общ) '!$A59,".",'Смета ЕР (общ) '!$B59,".",'Смета ЕР (общ) '!$D59) -> Р1.1.66 | F59: =IF(I59>0,F58+1,F58) -> 1 | G59: Исполнительная документация по усилению/устройству несущих конструкций ("КР"), включая пояснительную записку (для объектов менее 100 кв.м.) | H59: компл. | J59: ='[14]Проектирование до 100'!E17*1.05*0.1 -> 1050 | K59: 0 | L59: =ROUND(J59-J59*$Q$3,2) -> 1050 | M59: =ROUND(K59-K59*$Q$3,2) -> 0 | N59: =ROUND('Смета ЕР (общ) '!$I59*'Смета ЕР (общ) '!$L59,2) -> 0 | O59: =ROUND('Смета ЕР (общ) '!$I59*'Смета ЕР (общ) '!$M59,2) -> 0
A60: Р1 | B60: 1 | D60: 67 | E60: =CONCATENATE('Смета ЕР (общ) '!$A60,".",'Смета ЕР (общ) '!$B60,".",'Смета ЕР (общ) '!$D60) -> Р1.1.67 | F60: =IF(I60>0,F59+1,F59) -> 1 | G60: Исполнительная документация "Архитектурные решения" ("АР"), включая пояснительную записку (для объектов менее 100 кв.м.) | H60: компл. | J60: ='[14]Проектирование до 100'!E18*1.05*0.1 -> 2073.75 | K60: 0 | L60: =ROUND(J60-J60*$Q$3,2) -> 2073.75 | M60: =ROUND(K60-K60*$Q$3,2) -> 0 | N60: =ROUND('Смета ЕР (общ) '!$I60*'Смета ЕР (общ) '!$L60,2) -> 0 | O60: =ROUND('Смета ЕР (общ) '!$I60*'Смета ЕР (общ) '!$M60,2) -> 0
A61: Р1 | B61: 1 | D61: 68 | E61: =CONCATENATE('Смета ЕР (общ) '!$A61,".",'Смета ЕР (общ) '!$B61,".",'Смета ЕР (общ) '!$D61) -> Р1.1.68 | F61: =IF(I61>0,F60+1,F60) -> 1 | G61: Исполнительная документация по электроснабжению и электроосвещению ("ЭОМ"), включая пояснительную записку (для объектов менее 100 кв.м.) | H61: компл. | J61: ='[14]Проектирование до 100'!E19*1.05*0.1 -> 2073.75 | K61: 0 | L61: =ROUND(J61-J61*$Q$3,2) -> 2073.75 | M61: =ROUND(K61-K61*$Q$3,2) -> 0 | N61: =ROUND('Смета ЕР (общ) '!$I61*'Смета ЕР (общ) '!$L61,2) -> 0 | O61: =ROUND('Смета ЕР (общ) '!$I61*'Смета ЕР (общ) '!$M61,2) -> 0
A62: Р1 | B62: 1 | D62: 69 | E62: =CONCATENATE('Смета ЕР (общ) '!$A62,".",'Смета ЕР (общ) '!$B62,".",'Смета ЕР (общ) '!$D62) -> Р1.1.69 | F62: =IF(I62>0,F61+1,F61) -> 1 | G62: Исполнительная документация Системы вентиляции ("ОВиК-В"), включая пояснительную записку (для объектов менее 100 кв.м.) | H62: компл. | J62: ='[14]Проектирование до 100'!E20*1.05*0.1 -> 1559.25 | K62: 0 | L62: =ROUND(J62-J62*$Q$3,2) -> 1559.25 | M62: =ROUND(K62-K62*$Q$3,2) -> 0 | N62: =ROUND('Смета ЕР (общ) '!$I62*'Смета ЕР (общ) '!$L62,2) -> 0 | O62: =ROUND('Смета ЕР (общ) '!$I62*'Смета ЕР (общ) '!$M62,2) -> 0
A63: Р1 | B63: 1 | D63: 70 | E63: =CONCATENATE('Смета ЕР (общ) '!$A63,".",'Смета ЕР (общ) '!$B63,".",'Смета ЕР (общ) '!$D63) -> Р1.1.70 | F63: =IF(I63>0,F62+1,F62) -> 1 | G63: Исполнительная документация Системы кондиционирования ("ОВиК-К"), включая пояснительную записку (для объектов менее 100 кв.м.) | H63: компл. | J63: ='[14]Проектирование до 100'!E21*1.05*0.1 -> 1039.5 | K63: 0 | L63: =ROUND(J63-J63*$Q$3,2) -> 1039.5 | M63: =ROUND(K63-K63*$Q$3,2) -> 0 | N63: =ROUND('Смета ЕР (общ) '!$I63*'Смета ЕР (общ) '!$L63,2) -> 0 | O63: =ROUND('Смета ЕР (общ) '!$I63*'Смета ЕР (общ) '!$M63,2) -> 0
A64: Р1 | B64: 1 | D64: 71 | E64: =CONCATENATE('Смета ЕР (общ) '!$A64,".",'Смета ЕР (общ) '!$B64,".",'Смета ЕР (общ) '!$D64) -> Р1.1.71 | F64: =IF(I64>0,F63+1,F63) -> 1 | G64: Исполнительная документация Системы отопления ("ОВиК-О"), включая Пояснительную записку и Теплотехнический расчет (для объектов менее 100 кв.м.) | H64: компл. | J64: ='[14]Проектирование до 100'!E22*1.05*0.1 -> 1039.5 | K64: 0 | L64: =ROUND(J64-J64*$Q$3,2) -> 1039.5 | M64: =ROUND(K64-K64*$Q$3,2) -> 0 | N64: =ROUND('Смета ЕР (общ) '!$I64*'Смета ЕР (общ) '!$L64,2) -> 0 | O64: =ROUND('Смета ЕР (общ) '!$I64*'Смета ЕР (общ) '!$M64,2) -> 0
A65: Р1 | B65: 1 | D65: 72 | E65: =CONCATENATE('Смета ЕР (общ) '!$A65,".",'Смета ЕР (общ) '!$B65,".",'Смета ЕР (общ) '!$D65) -> Р1.1.72 | F65: =IF(I65>0,F64+1,F64) -> 1 | G65: Исполнительная документация Системы водоснабжения и канализации ("ВК"), включая пояснительную записку (для объектов менее 100 кв.м.) | H65: компл. | J65: ='[14]Проектирование до 100'!E23*1.05*0.1 -> 1039.5 | K65: 0 | L65: =ROUND(J65-J65*$Q$3,2) -> 1039.5 | M65: =ROUND(K65-K65*$Q$3,2) -> 0 | N65: =ROUND('Смета ЕР (общ) '!$I65*'Смета ЕР (общ) '!$L65,2) -> 0 | O65: =ROUND('Смета ЕР (общ) '!$I65*'Смета ЕР (общ) '!$M65,2) -> 0
A66: Р1 | B66: 1 | D66: 73 | E66: =CONCATENATE('Смета ЕР (общ) '!$A66,".",'Смета ЕР (общ) '!$B66,".",'Смета ЕР (общ) '!$D66) -> Р1.1.73 | F66: =IF(I66>0,F65+1,F65) -> 1 | G66: Исполнительная документация Системы автматической установки водяного пожаротушения ("АУВПТ"), (спринкерная, дренчерная, модульная система), включая пояснительную записку (для объектов менее 100 кв.м.) | H66: компл. | J66: ='[14]Проектирование до 100'!E24*1.05*0.1 -> 1559.25 | K66: 0 | L66: =ROUND(J66-J66*$Q$3,2) -> 1559.25 | M66: =ROUND(K66-K66*$Q$3,2) -> 0 | N66: =ROUND('Смета ЕР (общ) '!$I66*'Смета ЕР (общ) '!$L66,2) -> 0 | O66: =ROUND('Смета ЕР (общ) '!$I66*'Смета ЕР (общ) '!$M66,2) -> 0
A67: Р1 | B67: 1 | D67: 74 | E67: =CONCATENATE('Смета ЕР (общ) '!$A67,".",'Смета ЕР (общ) '!$B67,".",'Смета ЕР (общ) '!$D67) -> Р1.1.74 | F67: =IF(I67>0,F66+1,F66) -> 1 | G67: Исполнительная документация Системы Внутреннего противопожарного водопровода ("ВПВ"), включая пояснительную записку (для объектов менее 100 кв.м.) | H67: компл. | J67: ='[14]Проектирование до 100'!E25*1.05*0.1 -> 1039.5 | K67: 0 | L67: =ROUND(J67-J67*$Q$3,2) -> 1039.5 | M67: =ROUND(K67-K67*$Q$3,2) -> 0 | N67: =ROUND('Смета ЕР (общ) '!$I67*'Смета ЕР (общ) '!$L67,2) -> 0 | O67: =ROUND('Смета ЕР (общ) '!$I67*'Смета ЕР (общ) '!$M67,2) -> 0
A68: Р1 | B68: 1 | D68: 75 | E68: =CONCATENATE('Смета ЕР (общ) '!$A68,".",'Смета ЕР (общ) '!$B68,".",'Смета ЕР (общ) '!$D68) -> Р1.1.75 | F68: =IF(I68>0,F67+1,F67) -> 1 | G68: Исполнительная документация Системы дымоудаления ("ДУ"), включая пояснительную записку (для объектов менее 100 кв.м.) | H68: компл. | J68: ='[14]Проектирование до 100'!E26*1.05*0.1 -> 1559.25 | K68: 0 | L68: =ROUND(J68-J68*$Q$3,2) -> 1559.25 | M68: =ROUND(K68-K68*$Q$3,2) -> 0 | N68: =ROUND('Смета ЕР (общ) '!$I68*'Смета ЕР (общ) '!$L68,2) -> 0 | O68: =ROUND('Смета ЕР (общ) '!$I68*'Смета ЕР (общ) '!$M68,2) -> 0
A69: Р1 | B69: 1 | D69: 76 | E69: =CONCATENATE('Смета ЕР (общ) '!$A69,".",'Смета ЕР (общ) '!$B69,".",'Смета ЕР (общ) '!$D69) -> Р1.1.76 | F69: =IF(I69>0,F68+1,F68) -> 1 | G69: Рабочая документация "Автоматическая пожарная сигнализация" (АПС) | H69: м2 | J69: ='[14]АПС, СОУЭ, ППА'!F13*1.05 -> 70.35 | K69: 1 | L69: =ROUND(J69-J69*$Q$3,2) -> 70.35 | M69: =ROUND(K69-K69*$Q$3,2) -> 1 | N69: =ROUND('Смета ЕР (общ) '!$I69*'Смета ЕР (общ) '!$L69,2) -> 0 | O69: =ROUND('Смета ЕР (общ) '!$I69*'Смета ЕР (общ) '!$M69,2) -> 0
A70: Р1 | B70: 1 | D70: 77 | E70: =CONCATENATE('Смета ЕР (общ) '!$A70,".",'Смета ЕР (общ) '!$B70,".",'Смета ЕР (общ) '!$D70) -> Р1.1.77 | F70: =IF(I70>0,F69+1,F69) -> 1 | G70: Рабочая документация "Система оповещения и управления эвакуацией людей при пожаре" (СОУЭ) | H70: м2 | J70: ='[14]АПС, СОУЭ, ППА'!F14*1.05 -> 40.95 | K70: 2 | L70: =ROUND(J70-J70*$Q$3,2) -> 40.95 | M70: =ROUND(K70-K70*$Q$3,2) -> 2 | N70: =ROUND('Смета ЕР (общ) '!$I70*'Смета ЕР (общ) '!$L70,2) -> 0 | O70: =ROUND('Смета ЕР (общ) '!$I70*'Смета ЕР (общ) '!$M70,2) -> 0
A71: Р1 | B71: 1 | D71: 78 | E71: =CONCATENATE('Смета ЕР (общ) '!$A71,".",'Смета ЕР (общ) '!$B71,".",'Смета ЕР (общ) '!$D71) -> Р1.1.78 | F71: =IF(I71>0,F70+1,F70) -> 1 | G71: Рабочая документация "Автоматизация системы внутреннего противопожарного водопровода (ВПВ) | H71: м2 | J71: ='[14]АПС, СОУЭ, ППА'!F16*1.05 -> 8.4 | K71: 3 | L71: =ROUND(J71-J71*$Q$3,2) -> 8.4 | M71: =ROUND(K71-K71*$Q$3,2) -> 3 | N71: =ROUND('Смета ЕР (общ) '!$I71*'Смета ЕР (общ) '!$L71,2) -> 0 | O71: =ROUND('Смета ЕР (общ) '!$I71*'Смета ЕР (общ) '!$M71,2) -> 0
A72: Р1 | B72: 1 | D72: 79 | E72: =CONCATENATE('Смета ЕР (общ) '!$A72,".",'Смета ЕР (общ) '!$B72,".",'Смета ЕР (общ) '!$D72) -> Р1.1.79 | F72: =IF(I72>0,F71+1,F71) -> 1 | G72: Рабочая документация "Автоматизация системы противодымной вентиляции (ПДВ")" | H72: м2 | J72: ='[14]АПС, СОУЭ, ППА'!F17*1.05 -> 26.25 | K72: 4 | L72: =ROUND(J72-J72*$Q$3,2) -> 26.25 | M72: =ROUND(K72-K72*$Q$3,2) -> 4 | N72: =ROUND('Смета ЕР (общ) '!$I72*'Смета ЕР (общ) '!$L72,2) -> 0 | O72: =ROUND('Смета ЕР (общ) '!$I72*'Смета ЕР (общ) '!$M72,2) -> 0
A73: Р1 | B73: 1 | D73: 80 | E73: =CONCATENATE('Смета ЕР (общ) '!$A73,".",'Смета ЕР (общ) '!$B73,".",'Смета ЕР (общ) '!$D73) -> Р1.1.80 | F73: =IF(I73>0,F72+1,F72) -> 1 | G73: Рабочая документация "Автоматизация Системы отопления, вентиляции и кондиционирования (ОВиК)" | H73: м2 | J73: ='[14]АПС, СОУЭ, ППА'!F18*1.05 -> 3.15 | K73: 5 | L73: =ROUND(J73-J73*$Q$3,2) -> 3.15 | M73: =ROUND(K73-K73*$Q$3,2) -> 5 | N73: =ROUND('Смета ЕР (общ) '!$I73*'Смета ЕР (общ) '!$L73,2) -> 0 | O73: =ROUND('Смета ЕР (общ) '!$I73*'Смета ЕР (общ) '!$M73,2) -> 0
A74: Р1 | B74: 1 | D74: 81 | E74: =CONCATENATE('Смета ЕР (общ) '!$A74,".",'Смета ЕР (общ) '!$B74,".",'Смета ЕР (общ) '!$D74) -> Р1.1.81 | F74: =IF(I74>0,F73+1,F73) -> 1 | G74: Рабочая документация "Автоматизация Системы аварийного освещения (АО)" | H74: м2 | J74: ='[14]АПС, СОУЭ, ППА'!F19*1.05 -> 1.05 | K74: 6 | L74: =ROUND(J74-J74*$Q$3,2) -> 1.05 | M74: =ROUND(K74-K74*$Q$3,2) -> 6 | N74: =ROUND('Смета ЕР (общ) '!$I74*'Смета ЕР (общ) '!$L74,2) -> 0 | O74: =ROUND('Смета ЕР (общ) '!$I74*'Смета ЕР (общ) '!$M74,2) -> 0
A75: Р1 | B75: 1 | D75: 82 | E75: =CONCATENATE('Смета ЕР (общ) '!$A75,".",'Смета ЕР (общ) '!$B75,".",'Смета ЕР (общ) '!$D75) -> Р1.1.82 | F75: =IF(I75>0,F74+1,F74) -> 1 | G75: Рабочая документация "Автоматизации лифтовового хозяйства" | H75: м2 | J75: ='[14]АПС, СОУЭ, ППА'!F20*1.05 -> 1.05 | K75: 7 | L75: =ROUND(J75-J75*$Q$3,2) -> 1.05 | M75: =ROUND(K75-K75*$Q$3,2) -> 7 | N75: =ROUND('Смета ЕР (общ) '!$I75*'Смета ЕР (общ) '!$L75,2) -> 0 | O75: =ROUND('Смета ЕР (общ) '!$I75*'Смета ЕР (общ) '!$M75,2) -> 0
A76: Р1 | B76: 1 | D76: 83 | E76: =CONCATENATE('Смета ЕР (общ) '!$A76,".",'Смета ЕР (общ) '!$B76,".",'Смета ЕР (общ) '!$D76) -> Р1.1.83 | F76: =IF(I76>0,F75+1,F75) -> 1 | G76: Рабочая документация "Автоматизации Системы контроля управления доступом (СКУД)" | H76: м2 | J76: ='[14]АПС, СОУЭ, ППА'!F21*1.05 -> 1.05 | K76: 8 | L76: =ROUND(J76-J76*$Q$3,2) -> 1.05 | M76: =ROUND(K76-K76*$Q$3,2) -> 8 | N76: =ROUND('Смета ЕР (общ) '!$I76*'Смета ЕР (общ) '!$L76,2) -> 0 | O76: =ROUND('Смета ЕР (общ) '!$I76*'Смета ЕР (общ) '!$M76,2) -> 0
A77: Р1 | B77: 1 | D77: 12 | E77: =CONCATENATE('Смета ЕР (общ) '!$A77,".",'Смета ЕР (общ) '!$B77,".",'Смета ЕР (общ) '!$D77) -> Р1.1.12 | F77: =IF(I77>0,F76+1,F76) -> 1 | G77: Стоимость согласования проекта перепланировки/реставрации объекта культурного наследия в соответствии с нормативными актами г.______________. | H77: м2 | J77: 0 | K77: 0 | L77: =ROUND(J77-J77*$Q$3,2) -> 0 | M77: =ROUND(K77-K77*$Q$3,2) -> 0 | N77: =ROUND('Смета ЕР (общ) '!$I77*'Смета ЕР (общ) '!$L77,2) -> 0 | O77: =ROUND('Смета ЕР (общ) '!$I77*'Смета ЕР (общ) '!$M77,2) -> 0 | P77: цена по КП
A78: Р1 | B78: 1 | D78: 13 | E78: =CONCATENATE('Смета ЕР (общ) '!$A78,".",'Смета ЕР (общ) '!$B78,".",'Смета ЕР (общ) '!$D78) -> Р1.1.13 | F78: =IF(I78>0,F77+1,F77) -> 1 | G78: Стоимость согласования проекта перепланировки/реконструкции объекта в соответствии с нормативными актами г.______________. | H78: м2 | J78: 0 | K78: 0 | L78: =ROUND(J78-J78*$Q$3,2) -> 0 | M78: =ROUND(K78-K78*$Q$3,2) -> 0 | N78: =ROUND('Смета ЕР (общ) '!$I78*'Смета ЕР (общ) '!$L78,2) -> 0 | O78: =ROUND('Смета ЕР (общ) '!$I78*'Смета ЕР (общ) '!$M78,2) -> 0 | P78: цена по КП
A79: Р1 | B79: 1 | D79: 14 | E79: =CONCATENATE('Смета ЕР (общ) '!$A79,".",'Смета ЕР (общ) '!$B79,".",'Смета ЕР (общ) '!$D79) -> Р1.1.14 | F79: =IF(I79>0,F78+1,F78) -> 1 | G79: Получение паспорта БТИ (в черных линиях) | H79: м2 | J79: 0 | K79: 0 | L79: =ROUND(J79-J79*$Q$3,2) -> 0 | M79: =ROUND(K79-K79*$Q$3,2) -> 0 | N79: =ROUND('Смета ЕР (общ) '!$I79*'Смета ЕР (общ) '!$L79,2) -> 0 | O79: =ROUND('Смета ЕР (общ) '!$I79*'Смета ЕР (общ) '!$M79,2) -> 0 | P79: цена по КП
A80: Р1 | B80: 1 | D80: 15 | E80: =CONCATENATE('Смета ЕР (общ) '!$A80,".",'Смета ЕР (общ) '!$B80,".",'Смета ЕР (общ) '!$D80) -> Р1.1.15 | F80: =IF(I80>0,F79+1,F79) -> 1 | G80: Сертификация помещения для совершения операций с ценностями, хранение ценностей по (2) классу вломостойкости и (3) классу пулестойкости | H80: м2 | J80: 88.99 | K80: 0 | L80: =ROUND(J80-J80*$Q$3,2) -> 88.99 | M80: =ROUND(K80-K80*$Q$3,2) -> 0 | N80: =ROUND('Смета ЕР (общ) '!$I80*'Смета ЕР (общ) '!$L80,2) -> 0 | O80: =ROUND('Смета ЕР (общ) '!$I80*'Смета ЕР (общ) '!$M80,2) -> 0
A81: Р1 | B81: 1 | D81: 16 | E81: =CONCATENATE('Смета ЕР (общ) '!$A81,".",'Смета ЕР (общ) '!$B81,".",'Смета ЕР (общ) '!$D81) -> Р1.1.16 | F81: =IF(I81>0,F80+1,F80) -> 1 | G81: Сертификация помещения для совершения операций с ценностями, хранение ценностей по 3 классу вломостойкости и 3 классу пулестойкости | H81: м2 | J81: 149.82 | K81: 0 | L81: =ROUND(J81-J81*$Q$3,2) -> 149.82 | M81: =ROUND(K81-K81*$Q$3,2) -> 0 | N81: =ROUND('Смета ЕР (общ) '!$I81*'Смета ЕР (общ) '!$L81,2) -> 0 | O81: =ROUND('Смета ЕР (общ) '!$I81*'Смета ЕР (общ) '!$M81,2) -> 0
A82: Р1 | B82: 1 | D82: 17 | E82: =CONCATENATE('Смета ЕР (общ) '!$A82,".",'Смета ЕР (общ) '!$B82,".",'Смета ЕР (общ) '!$D82) -> Р1.1.17 | F82: =IF(I82>0,F81+1,F81) -> 1 | G82: Сертификация помещения для совершения операций с ценностями, хранение ценностей по (5) классу вломостойкости | H82: м2 | J82: 96.48 | K82: 0 | L82: =ROUND(J82-J82*$Q$3,2) -> 96.48 | M82: =ROUND(K82-K82*$Q$3,2) -> 0 | N82: =ROUND('Смета ЕР (общ) '!$I82*'Смета ЕР (общ) '!$L82,2) -> 0 | O82: =ROUND('Смета ЕР (общ) '!$I82*'Смета ЕР (общ) '!$M82,2) -> 0
A83: Р1 | B83: 1 | D83: 18 | E83: =CONCATENATE('Смета ЕР (общ) '!$A83,".",'Смета ЕР (общ) '!$B83,".",'Смета ЕР (общ) '!$D83) -> Р1.1.18 | F83: =IF(I83>0,F82+1,F82) -> 1 | G83: Технический отчет электролаборатории для помещений более 100 м.кв. | H83: м2 | J83: 123.58 | K83: 0 | L83: =ROUND(J83-J83*$Q$3,2) -> 123.58 | M83: =ROUND(K83-K83*$Q$3,2) -> 0 | N83: =ROUND('Смета ЕР (общ) '!$I83*'Смета ЕР (общ) '!$L83,2) -> 0 | O83: =ROUND('Смета ЕР (общ) '!$I83*'Смета ЕР (общ) '!$M83,2) -> 0 | T83: 214
A84: Р1 | B84: 1 | D84: 84 | E84: =CONCATENATE('Смета ЕР (общ) '!$A84,".",'Смета ЕР (общ) '!$B84,".",'Смета ЕР (общ) '!$D84) -> Р1.1.84 | F84: =IF(I84>0,F83+1,F83) -> 1 | G84: Технический отчет электролаборатории для помещений менее 100 м.кв. | H84: компл. | J84: 13074.35 | K84: 0 | L84: =ROUND(J84-J84*$Q$3,2) -> 13074.35 | M84: =ROUND(K84-K84*$Q$3,2) -> 0 | N84: =ROUND('Смета ЕР (общ) '!$I84*'Смета ЕР (общ) '!$L84,2) -> 0 | O84: =ROUND('Смета ЕР (общ) '!$I84*'Смета ЕР (общ) '!$M84,2) -> 0
A85: Р1 | B85: 1 | D85: 19 | E85: =CONCATENATE('Смета ЕР (общ) '!$A85,".",'Смета ЕР (общ) '!$B85,".",'Смета ЕР (общ) '!$D85) -> Р1.1.19 | F85: =IF(I85>0,F84+1,F84) -> 1 | G85: Стоимость согласования проекта изменения фасада согласно нормативных и законодательных актов г. ___________ и РФ. | H85: м2 | J85: 190.9 | K85: 0 | L85: =ROUND(J85-J85*$Q$3,2) -> 190.9 | M85: =ROUND(K85-K85*$Q$3,2) -> 0 | N85: =ROUND('Смета ЕР (общ) '!$I85*'Смета ЕР (общ) '!$L85,2) -> 0 | O85: =ROUND('Смета ЕР (общ) '!$I85*'Смета ЕР (общ) '!$M85,2) -> 0
A86: Р1 | B86: 1 | D86: 20 | E86: =CONCATENATE('Смета ЕР (общ) '!$A86,".",'Смета ЕР (общ) '!$B86,".",'Смета ЕР (общ) '!$D86) -> Р1.1.20 | F86: =IF(I86>0,F85+1,F85) -> 1 | G86: Разработка дизайн-проекта интерьера | H86: м2 | J86: 0 | K86: 0 | L86: =ROUND(J86-J86*$Q$3,2) -> 0 | M86: =ROUND(K86-K86*$Q$3,2) -> 0 | N86: =ROUND('Смета ЕР (общ) '!$I86*'Смета ЕР (общ) '!$L86,2) -> 0 | O86: =ROUND('Смета ЕР (общ) '!$I86*'Смета ЕР (общ) '!$M86,2) -> 0 | P86: цена по КП
A87: Р1 | B87: 1 | D87: 21 | E87: =CONCATENATE('Смета ЕР (общ) '!$A87,".",'Смета ЕР (общ) '!$B87,".",'Смета ЕР (общ) '!$D87) -> Р1.1.21 | F87: =IF(I87>0,F86+1,F86) -> 1 | G87: Экспертиза и согласование проекта ЭОМ в Ростехнадзоре | H87: м2 | J87: 98.96 | K87: 0 | L87: =ROUND(J87-J87*$Q$3,2) -> 98.96 | M87: =ROUND(K87-K87*$Q$3,2) -> 0 | N87: =ROUND('Смета ЕР (общ) '!$I87*'Смета ЕР (общ) '!$L87,2) -> 0 | O87: =ROUND('Смета ЕР (общ) '!$I87*'Смета ЕР (общ) '!$M87,2) -> 0
A88: Р1 | B88: 1 | D88: 22 | E88: =CONCATENATE('Смета ЕР (общ) '!$A88,".",'Смета ЕР (общ) '!$B88,".",'Смета ЕР (общ) '!$D88) -> Р1.1.22 | F88: =IF(I88>0,F87+1,F87) -> 1 | G88: Проект системы водоотведения | H88: м2 | J88: 0 | K88: 0 | L88: =ROUND(J88-J88*$Q$3,2) -> 0 | M88: =ROUND(K88-K88*$Q$3,2) -> 0 | N88: =ROUND('Смета ЕР (общ) '!$I88*'Смета ЕР (общ) '!$L88,2) -> 0 | O88: =ROUND('Смета ЕР (общ) '!$I88*'Смета ЕР (общ) '!$M88,2) -> 0 | P88: цена по КП
A89: Р1 | B89: 1 | D89: 23 | E89: =CONCATENATE('Смета ЕР (общ) '!$A89,".",'Смета ЕР (общ) '!$B89,".",'Смета ЕР (общ) '!$D89) -> Р1.1.23 | F89: =IF(I89>0,F88+1,F88) -> 1 | G89: Рабочая документация Системы ливневой канализации | H89: м2 | J89: 0 | K89: 0 | L89: =ROUND(J89-J89*$Q$3,2) -> 0 | M89: =ROUND(K89-K89*$Q$3,2) -> 0 | N89: =ROUND('Смета ЕР (общ) '!$I89*'Смета ЕР (общ) '!$L89,2) -> 0 | O89: =ROUND('Смета ЕР (общ) '!$I89*'Смета ЕР (общ) '!$M89,2) -> 0 | P89: цена по КП
A90: Р1 | B90: 1 | D90: 24 | E90: =CONCATENATE('Смета ЕР (общ) '!$A90,".",'Смета ЕР (общ) '!$B90,".",'Смета ЕР (общ) '!$D90) -> Р1.1.24 | F90: =IF(I90>0,F89+1,F89) -> 1 | G90: Получение Технических условий (при необходимости) | H90: м2 | J90: 0 | K90: 0 | L90: =ROUND(J90-J90*$Q$3,2) -> 0 | M90: =ROUND(K90-K90*$Q$3,2) -> 0 | N90: =ROUND('Смета ЕР (общ) '!$I90*'Смета ЕР (общ) '!$L90,2) -> 0 | O90: =ROUND('Смета ЕР (общ) '!$I90*'Смета ЕР (общ) '!$M90,2) -> 0 | P90: цена по КП
A91: Р1 | B91: 1 | D91: 27 | E91: =CONCATENATE('Смета ЕР (общ) '!$A91,".",'Смета ЕР (общ) '!$B91,".",'Смета ЕР (общ) '!$D91) -> Р1.1.27 | F91: =IF(I91>0,F90+1,F90) -> 1 | G91: Расчет категории пожарной опасности помещений | H91: м2 | J91: 114.84 | K91: 0 | L91: =ROUND(J91-J91*$Q$3,2) -> 114.84 | M91: =ROUND(K91-K91*$Q$3,2) -> 0 | N91: =ROUND('Смета ЕР (общ) '!$I91*'Смета ЕР (общ) '!$L91,2) -> 0 | O91: =ROUND('Смета ЕР (общ) '!$I91*'Смета ЕР (общ) '!$M91,2) -> 0
A92: Р1 | B92: 1 | D92: 28 | E92: =CONCATENATE('Смета ЕР (общ) '!$A92,".",'Смета ЕР (общ) '!$B92,".",'Смета ЕР (общ) '!$D92) -> Р1.1.28 | F92: =IF(I92>0,F91+1,F91) -> 1 | G92: Рабочая документация Системы оповещения и управления эвакуацией в части световых указателей ("СОУЭ") | H92: м2 | J92: 52.25 | K92: 0 | L92: =ROUND(J92-J92*$Q$3,2) -> 52.25 | M92: =ROUND(K92-K92*$Q$3,2) -> 0 | N92: =ROUND('Смета ЕР (общ) '!$I92*'Смета ЕР (общ) '!$L92,2) -> 0 | O92: =ROUND('Смета ЕР (общ) '!$I92*'Смета ЕР (общ) '!$M92,2) -> 0
A93: Р1 | B93: 1 | D93: 32 | E93: =CONCATENATE('Смета ЕР (общ) '!$A93,".",'Смета ЕР (общ) '!$B93,".",'Смета ЕР (общ) '!$D93) -> Р1.1.32 | F93: =IF(I93>0,F92+1,F92) -> 1 | G93: Согласование проекта Системы водоотведения и получения тех условий (при необходимости) | H93: м2 | J93: 0 | K93: 0 | L93: =ROUND(J93-J93*$Q$3,2) -> 0 | M93: =ROUND(K93-K93*$Q$3,2) -> 0 | N93: =ROUND('Смета ЕР (общ) '!$I93*'Смета ЕР (общ) '!$L93,2) -> 0 | O93: =ROUND('Смета ЕР (общ) '!$I93*'Смета ЕР (общ) '!$M93,2) -> 0 | P93: цена по КП
A94: Р1 | B94: 1 | D94: 34 | E94: =CONCATENATE('Смета ЕР (общ) '!$A94,".",'Смета ЕР (общ) '!$B94,".",'Смета ЕР (общ) '!$D94) -> Р1.1.34 | F94: =IF(I94>0,F93+1,F93) -> 1 | G94: Испытание лестниц 3 типа с предоставлением актов | H94: м2 | J94: 30.63 | K94: 0 | L94: =ROUND(J94-J94*$Q$3,2) -> 30.63 | M94: =ROUND(K94-K94*$Q$3,2) -> 0 | N94: =ROUND('Смета ЕР (общ) '!$I94*'Смета ЕР (общ) '!$L94,2) -> 0 | O94: =ROUND('Смета ЕР (общ) '!$I94*'Смета ЕР (общ) '!$M94,2) -> 0
A95: Р1 | B95: 1 | D95: 92 | E95: =CONCATENATE('Смета ЕР (общ) '!$A95,".",'Смета ЕР (общ) '!$B95,".",'Смета ЕР (общ) '!$D95) -> Р1.1.92 | F95: =IF(I95>0,F94+1,F94) -> 1 | G95: Испытания системы внутреннего противопожарного водопровода аккредитованной организацией (ВПВ и АУПТ). | H95: компл. | J95: 10207.56 | K95: 0 | L95: =ROUND(J95-J95*$Q$3,2) -> 10207.56 | M95: =ROUND(K95-K95*$Q$3,2) -> 0 | N95: =ROUND('Смета ЕР (общ) '!$I95*'Смета ЕР (общ) '!$L95,2) -> 0 | O95: =ROUND('Смета ЕР (общ) '!$I95*'Смета ЕР (общ) '!$M95,2) -> 0
A96: Р1 | B96: 1 | D96: 35 | E96: =CONCATENATE('Смета ЕР (общ) '!$A96,".",'Смета ЕР (общ) '!$B96,".",'Смета ЕР (общ) '!$D96) -> Р1.1.35 | F96: =IF(I96>0,F94+1,F94) -> 1 | G96: Мероприятия по обеспечению доступа инвалидов | H96: м2 | J96: 76.52 | K96: 0 | L96: =ROUND(J96-J96*$Q$3,2) -> 76.52 | M96: =ROUND(K96-K96*$Q$3,2) -> 0 | N96: =ROUND('Смета ЕР (общ) '!$I96*'Смета ЕР (общ) '!$L96,2) -> 0 | O96: =ROUND('Смета ЕР (общ) '!$I96*'Смета ЕР (общ) '!$M96,2) -> 0
A97: Р1 | B97: 1 | D97: 38 | E97: =CONCATENATE('Смета ЕР (общ) '!$A97,".",'Смета ЕР (общ) '!$B97,".",'Смета ЕР (общ) '!$D97) -> Р1.1.38 | F97: =IF(I97>0,F96+1,F96) -> 1 | G97: Расчет пожарного риска | H97: м2 | J97: 0 | K97: 0 | L97: =ROUND(J97-J97*$Q$3,2) -> 0 | M97: =ROUND(K97-K97*$Q$3,2) -> 0 | N97: =ROUND('Смета ЕР (общ) '!$I97*'Смета ЕР (общ) '!$L97,2) -> 0 | O97: =ROUND('Смета ЕР (общ) '!$I97*'Смета ЕР (общ) '!$M97,2) -> 0 | P97: цена по КП
A98: Р1 | B98: 1 | D98: 39 | E98: =CONCATENATE('Смета ЕР (общ) '!$A98,".",'Смета ЕР (общ) '!$B98,".",'Смета ЕР (общ) '!$D98) -> Р1.1.39 | F98: =IF(I98>0,F97+1,F97) -> 1 | G98: Подготовка и постановка на учет Независимой оценки пожарного риска (пожарный аудит), включая Расчет пожарного риска | H98: м2 | J98: 0 | K98: 0 | L98: =ROUND(J98-J98*$Q$3,2) -> 0 | M98: =ROUND(K98-K98*$Q$3,2) -> 0 | N98: =ROUND('Смета ЕР (общ) '!$I98*'Смета ЕР (общ) '!$L98,2) -> 0 | O98: =ROUND('Смета ЕР (общ) '!$I98*'Смета ЕР (общ) '!$M98,2) -> 0 | P98: цена по КП
A99: Р1 | B99: 1 | D99: 40 | E99: =CONCATENATE('Смета ЕР (общ) '!$A99,".",'Смета ЕР (общ) '!$B99,".",'Смета ЕР (общ) '!$D99) -> Р1.1.40 | F99: =IF(I99>0,F98+1,F98) -> 1 | G99: Разработка проекта огнезащиты | H99: шт. | J99: 16168.42 | K99: 0 | L99: =ROUND(J99-J99*$Q$3,2) -> 16168.42 | M99: =ROUND(K99-K99*$Q$3,2) -> 0 | N99: =ROUND('Смета ЕР (общ) '!$I99*'Смета ЕР (общ) '!$L99,2) -> 0 | O99: =ROUND('Смета ЕР (общ) '!$I99*'Смета ЕР (общ) '!$M99,2) -> 0
A100: Р1 | B100: 1 | D100: 41 | E100: =CONCATENATE('Смета ЕР (общ) '!$A100,".",'Смета ЕР (общ) '!$B100,".",'Смета ЕР (общ) '!$D100) -> Р1.1.41 | F100: =IF(I100>0,F99+1,F99) -> 1 | G100: Предоставление заключения пожарной испытательной лаборатории для контроля качества огнезащитных работ с предоставлением заключения о соответствии (до 1000 м кв. металлоконструкций) | H100: компл. | J100: 23438.15 | K100: 0 | L100: =ROUND(J100-J100*$Q$3,2) -> 23438.15 | M100: =ROUND(K100-K100*$Q$3,2) -> 0 | N100: =ROUND('Смета ЕР (общ) '!$I100*'Смета ЕР (общ) '!$L100,2) -> 0 | O100: =ROUND('Смета ЕР (общ) '!$I100*'Смета ЕР (общ) '!$M100,2) -> 0
A101: Р1 | B101: 1 | D101: 85 | E101: =CONCATENATE('Смета ЕР (общ) '!$A101,".",'Смета ЕР (общ) '!$B101,".",'Смета ЕР (общ) '!$D101) -> Р1.1.85 | F101: =IF(I101>0,F100+1,F100) -> 1 | G101: Предоставление заключения пожарной испытательной лаборатории для контроля качества огнезащитных работ с предоставлением заключения о соответствии (более 1000 м кв. металлоконструкций) | H101: м2 | J101: 17.8 | K101: 0 | L101: =ROUND(J101-J101*$Q$3,2) -> 17.8 | M101: =ROUND(K101-K101*$Q$3,2) -> 0 | N101: =ROUND('Смета ЕР (общ) '!$I101*'Смета ЕР (общ) '!$L101,2) -> 0 | O101: =ROUND('Смета ЕР (общ) '!$I101*'Смета ЕР (общ) '!$M101,2) -> 0
A102: Р1 | B102: 1 | D102: 86 | E102: =CONCATENATE('Смета ЕР (общ) '!$A102,".",'Смета ЕР (общ) '!$B102,".",'Смета ЕР (общ) '!$D102) -> Р1.1.86 | F102: =IF(I102>0,F101+1,F101) -> 1 | G102: Акустический расчет инженерных систем ОВиК (предоставление в Роспотребнадзор) электронный и бумажный вариант | H102: компл. | J102: 132501.92 | K102: 0 | L102: =ROUND(J102-J102*$Q$3,2) -> 132501.92 | M102: =ROUND(K102-K102*$Q$3,2) -> 0 | N102: =ROUND('Смета ЕР (общ) '!$I102*'Смета ЕР (общ) '!$L102,2) -> 0 | O102: =ROUND('Смета ЕР (общ) '!$I102*'Смета ЕР (общ) '!$M102,2) -> 0 | P102: согласование памятников архитектуры
...
