Workbook

Sheet Смета 1-й этаж
G4: Формат объекта | I4: Инфраструктура | O4: курс $ | P4: 70
G5: Адрес объекта: | H5: Адрес объекта: | S5: Выбрать значение из списка | AP5: не считать электрику
G6: Плoщадь объекта (м.кв.): | H6: Плащадь объекта: | R6: Электрическая мощность объекта | S6: не считать электрику | AP6: до 33 кВт включ., автомат до 63А включ.
G7: Срок проведения работ | H7: Срок проведения работ | AP7: от 33 кВт до 40 кВт включ., автомат от 63А до 80А включ.
G8: ПОДРЯДЧИК: | H8: ПОДРЯДЧИК: | AP8: от 40 кВт до 60 кВт включ., автомат от 80А до 125А включ.
G9: Юридический адрес: | H9: Юридический адрес: | S9: Выбрать значение из списка | AP9: нет
G10: Электронный адрес: | H10: Электронный адрес: | R10: Наличие на объекте АВР | S10: от 40 кВт до 60 кВт включ., автомат от 80А до 125А включ. | AP10: до 33 кВт включ., автомат до 63А включ.
G11: Контактное лицо (Ф.И.О.) : | H11: Контактное лицо (Ф.И.О.) : | AP11: от 33 кВт до 40 кВт включ., автомат от 63А до 80А включ.
G12: Контактный телефон: | H12: Контактный телефон: | S12: Выбрать значение из списка | AP12: от 40 кВт до 60 кВт включ., автомат от 80А до 125А включ.
G13: Реквизиты: | H13: Реквизиты: | R13: Наличие на объекте ИБП | S13: да | AP13: да
G14: Сумма по смете: | H14: Сумма по смете: | AP14: нет
A16: Новый номенклатурный номер | B16: Номер строки | C16: Раздел | D16: Подраздел | E16: Пункт подраздела | F16: Новый номенклатурный номер | G16: № | H16: Наименование работ и затрат | I16: Един. изм. | J16: Кол - во. (объем) | K16: Цена работ, руб., в т.ч. НДС | L16: Цена материалов и оборудования, руб., в т.ч. НДС | M16: Стоимость работ, руб., в т.ч. НДС | N16: Стоимость материалов и оборудования руб., в т.ч. НДС | O16: Уточнение УОС | P16: Уточнение для ПЭУ | S16: Перед отправкой смету фильтровать по Кол-у | AQ16: "Специальные" работы | AR16: Стоимость "специальных" рпбот
A17: =CONCATENATE('Смета 1-й этаж'!$C17,".",'Смета 1-й этаж'!$D17,".",'Смета 1-й этаж'!$E17) -> Р1.0.0 | B17: 1 | C17: Р1 | D17: 0 | E17: 0 | F17: =CONCATENATE('Смета 1-й этаж'!$C17,".",'Смета 1-й этаж'!$D17,".",'Смета 1-й этаж'!$E17) -> Р1.0.0 | G17: 1 | H17: Раздел №1. Проектные работы и согласования | J17: =J18 -> 0 | M17: =ROUND(M18,2) -> 0 | N17: =ROUND(N18,2) -> 0
A18: =CONCATENATE('Смета 1-й этаж'!$C18,".",'Смета 1-й этаж'!$D18,".",'Смета 1-й этаж'!$E18) -> Р1.1.0 | B18: 2 | C18: Р1 | D18: 1 | E18: 0 | F18: =CONCATENATE('Смета 1-й этаж'!$C18,".",'Смета 1-й этаж'!$D18,".",'Смета 1-й этаж'!$E18) -> Р1.1.0 | G18: 2 | H18: Проектные работы и согласования | J18: =SUM(J19:J51) -> 0 | M18: =SUM(M19:M55) -> 0 | N18: =SUM(N19:N55) -> 0 | P18: новый подраздел
A19: =CONCATENATE('Смета 1-й этаж'!$C19,".",'Смета 1-й этаж'!$D19,".",'Смета 1-й этаж'!$E19) -> Р1.0.1 | B19: 3 | C19: Р1 | D19: 0 | E19: 1 | F19: =CONCATENATE('Смета 1-й этаж'!$C19,".",'Смета 1-й этаж'!$D19,".",'Смета 1-й этаж'!$E19) -> Р1.0.1 | G19: =IF(J19>0,G18+1,G18) -> 2 | H19: Техническое обследование состояния несущих конструкций помещения с подготовкой рекомендаций по усилению (Техничесекое заключение о конструктиве - "ТЗК") | I19: кв.м.площади офиса | K19: 350 | M19: =ROUND('Смета 1-й этаж'!$J19*'Смета 1-й этаж'!$K19,2) -> 0 | N19: =ROUND('Смета 1-й этаж'!$J19*'Смета 1-й этаж'!$L19,2) -> 0
C20: Р1 | D20: 0 | E20: 40 | F20: =CONCATENATE('Смета 1-й этаж'!$C20,".",'Смета 1-й этаж'!$D20,".",'Смета 1-й этаж'!$E20) -> Р1.0.40 | G20: =IF(J20>0,G19+1,G19) -> 2 | H20: Техническое обследование состояния несущих конструкций помещения с подготовкой рекомендаций по усилению в зоне расположения депозитария, кассового узла и банкоматов (Техничесекое заключение о конструктиве - "ТЗК") | I20: шт | K20: 65000 | L20: 0 | M20: =ROUND('Смета 1-й этаж'!$J20*'Смета 1-й этаж'!$K20,2) -> 0 | N20: =ROUND('Смета 1-й этаж'!$J20*'Смета 1-й этаж'!$L20,2) -> 0 | P20: новая позиция
A21: =CONCATENATE('Смета 1-й этаж'!$C21,".",'Смета 1-й этаж'!$D21,".",'Смета 1-й этаж'!$E21) -> Р1.0.2 | B21: 4 | C21: Р1 | D21: 0 | E21: 2 | F21: =CONCATENATE('Смета 1-й этаж'!$C21,".",'Смета 1-й этаж'!$D21,".",'Смета 1-й этаж'!$E21) -> Р1.0.2 | G21: =IF(J21>0,G20+1,G20) -> 2 | H21: Рабочая документация по усилению/устройству несущих конструкций ("КР"), включая пояснительную записку | I21: кв.м.площади офиса | K21: 70.5 | M21: =ROUND('Смета 1-й этаж'!$J21*'Смета 1-й этаж'!$K21,2) -> 0 | N21: =ROUND('Смета 1-й этаж'!$J21*'Смета 1-й этаж'!$L21,2) -> 0
A22: =CONCATENATE('Смета 1-й этаж'!$C22,".",'Смета 1-й этаж'!$D22,".",'Смета 1-й этаж'!$E22) -> Р1.0.3 | B22: 5 | C22: Р1 | D22: 0 | E22: 3 | F22: =CONCATENATE('Смета 1-й этаж'!$C22,".",'Смета 1-й этаж'!$D22,".",'Смета 1-й этаж'!$E22) -> Р1.0.3 | G22: =IF(J22>0,G21+1,G21) -> 2 | H22: Рабочая документация "Архитектурные решения" ("АР"), включая пояснительную записку | I22: кв.м.площади офиса | K22: 240 | M22: =ROUND('Смета 1-й этаж'!$J22*'Смета 1-й этаж'!$K22,2) -> 0 | N22: =ROUND('Смета 1-й этаж'!$J22*'Смета 1-й этаж'!$L22,2) -> 0 | AQ22: 57388084
A23: =CONCATENATE('Смета 1-й этаж'!$C23,".",'Смета 1-й этаж'!$D23,".",'Смета 1-й этаж'!$E23) -> Р1.0.4 | B23: 6 | C23: Р1 | D23: 0 | E23: 4 | F23: =CONCATENATE('Смета 1-й этаж'!$C23,".",'Смета 1-й этаж'!$D23,".",'Смета 1-й этаж'!$E23) -> Р1.0.4 | G23: =IF(J23>0,G22+1,G22) -> 2 | H23: Рабочая документация по электроснабжению и электроосвещению ("ЭОМ"), включая пояснительную записку | I23: кв.м.площади офиса | K23: 201.6 | M23: =ROUND('Смета 1-й этаж'!$J23*'Смета 1-й этаж'!$K23,2) -> 0 | N23: =ROUND('Смета 1-й этаж'!$J23*'Смета 1-й этаж'!$L23,2) -> 0 | AQ23: 26471538
A24: =CONCATENATE('Смета 1-й этаж'!$C24,".",'Смета 1-й этаж'!$D24,".",'Смета 1-й этаж'!$E24) -> Р1.0.5 | B24: 7 | C24: Р1 | D24: 0 | E24: 5 | F24: =CONCATENATE('Смета 1-й этаж'!$C24,".",'Смета 1-й этаж'!$D24,".",'Смета 1-й этаж'!$E24) -> Р1.0.5 | G24: =IF(J24>0,G23+1,G23) -> 2 | H24: Рабочая документация Системы вентиляции ("ОВиК-В"), включая пояснительную записку | I24: кв.м.площади офиса | K24: 86.4 | M24: =ROUND('Смета 1-й этаж'!$J24*'Смета 1-й этаж'!$K24,2) -> 0 | N24: =ROUND('Смета 1-й этаж'!$J24*'Смета 1-й этаж'!$L24,2) -> 0 | AQ24: =SUBTOTAL(9,AQ22:AQ23) -> 83859622
A25: =CONCATENATE('Смета 1-й этаж'!$C25,".",'Смета 1-й этаж'!$D25,".",'Смета 1-й этаж'!$E25) -> Р1.0.6 | B25: 8 | C25: Р1 | D25: 0 | E25: 6 | F25: =CONCATENATE('Смета 1-й этаж'!$C25,".",'Смета 1-й этаж'!$D25,".",'Смета 1-й этаж'!$E25) -> Р1.0.6 | G25: =IF(J25>0,G24+1,G24) -> 2 | H25: Рабочая документация Системы кондиционирования ("ОВиК-К"), включая пояснительную записку | I25: кв.м.площади офиса | K25: 79.2 | M25: =ROUND('Смета 1-й этаж'!$J25*'Смета 1-й этаж'!$K25,2) -> 0 | N25: =ROUND('Смета 1-й этаж'!$J25*'Смета 1-й этаж'!$L25,2) -> 0 | AQ25: 82281575
A26: =CONCATENATE('Смета 1-й этаж'!$C26,".",'Смета 1-й этаж'!$D26,".",'Смета 1-й этаж'!$E26) -> Р1.0.7 | B26: 9 | C26: Р1 | D26: 0 | E26: 7 | F26: =CONCATENATE('Смета 1-й этаж'!$C26,".",'Смета 1-й этаж'!$D26,".",'Смета 1-й этаж'!$E26) -> Р1.0.7 | G26: =IF(J26>0,G25+1,G25) -> 2 | H26: Рабочая документация Системы отопления ("ОВиК-О"), включая Пояснительную записку и Теплотехнический расчет | I26: кв.м.площади офиса | K26: 64.8 | M26: =ROUND('Смета 1-й этаж'!$J26*'Смета 1-й этаж'!$K26,2) -> 0 | N26: =ROUND('Смета 1-й этаж'!$J26*'Смета 1-й этаж'!$L26,2) -> 0 | AQ26: =AQ24-AQ25 -> 1578046.9
A27: =CONCATENATE('Смета 1-й этаж'!$C27,".",'Смета 1-й этаж'!$D27,".",'Смета 1-й этаж'!$E27) -> Р1.0.8 | B27: 10 | C27: Р1 | D27: 0 | E27: 8 | F27: =CONCATENATE('Смета 1-й этаж'!$C27,".",'Смета 1-й этаж'!$D27,".",'Смета 1-й этаж'!$E27) -> Р1.0.8 | G27: =IF(J27>0,G26+1,G26) -> 2 | H27: Рабочая документация Системы водоснабжения и канализации ("ВК"), включая пояснительную записку | I27: кв.м.площади офиса | K27: 100.8 | M27: =ROUND('Смета 1-й этаж'!$J27*'Смета 1-й этаж'!$K27,2) -> 0 | N27: =ROUND('Смета 1-й этаж'!$J27*'Смета 1-й этаж'!$L27,2) -> 0
A28: =CONCATENATE('Смета 1-й этаж'!$C28,".",'Смета 1-й этаж'!$D28,".",'Смета 1-й этаж'!$E28) -> Р1.0.9 | B28: 11 | C28: Р1 | D28: 0 | E28: 9 | F28: =CONCATENATE('Смета 1-й этаж'!$C28,".",'Смета 1-й этаж'!$D28,".",'Смета 1-й этаж'!$E28) -> Р1.0.9 | G28: =IF(J28>0,G27+1,G27) -> 2 | H28: Эскизный проект фасада и колористический паспорт с указанием ведомости отделки и проектным решением со спецификацией элементов (крыльцо, пандус, навесы, колонны и т.д.) | I28: кв.м.площади офиса | K28: 69.25 | M28: =ROUND('Смета 1-й этаж'!$J28*'Смета 1-й этаж'!$K28,2) -> 0 | N28: =ROUND('Смета 1-й этаж'!$J28*'Смета 1-й этаж'!$L28,2) -> 0
A29: =CONCATENATE('Смета 1-й этаж'!$C29,".",'Смета 1-й этаж'!$D29,".",'Смета 1-й этаж'!$E29) -> Р1.0.10 | B29: 12 | C29: Р1 | D29: 0 | E29: 10 | F29: =CONCATENATE('Смета 1-й этаж'!$C29,".",'Смета 1-й этаж'!$D29,".",'Смета 1-й этаж'!$E29) -> Р1.0.10 | G29: =IF(J29>0,G28+1,G28) -> 2 | H29: Рабочая документация Системы автматической установки водяного пожаротушения ("АУВПТ"), (сплинкерная, дренчерная, модульная система), включая пояснительную записку | I29: кв.м.площади офиса | K29: 100.8 | M29: =ROUND('Смета 1-й этаж'!$J29*'Смета 1-й этаж'!$K29,2) -> 0 | N29: =ROUND('Смета 1-й этаж'!$J29*'Смета 1-й этаж'!$L29,2) -> 0
B30: 38 | C30: Р2 | D30: 0 | E30: 43 | F30: =CONCATENATE('Смета 1-й этаж'!$C30,".",'Смета 1-й этаж'!$D30,".",'Смета 1-й этаж'!$E30) -> Р2.0.43 | G30: =IF(J30>0,G29+1,G29) -> 2 | H30: Испытания системы внутреннего противопожарного водопровода аккредитованной организацией (ВПВ и АУПТ). | I30: компл. | K30: 7500 | M30: =ROUND('Смета 1-й этаж'!$J30*'Смета 1-й этаж'!$K30,2) -> 0 | N30: =ROUND('Смета 1-й этаж'!$J30*'Смета 1-й этаж'!$L30,2) -> 0 | P30: новая позиция
A31: =CONCATENATE('Смета 1-й этаж'!$C31,".",'Смета 1-й этаж'!$D31,".",'Смета 1-й этаж'!$E31) -> Р1.0.11 | B31: 13 | C31: Р1 | D31: 0 | E31: 11 | F31: =CONCATENATE('Смета 1-й этаж'!$C31,".",'Смета 1-й этаж'!$D31,".",'Смета 1-й этаж'!$E31) -> Р1.0.11 | G31: =IF(J31>0,G30+1,G30) -> 2 | H31: Рабочая документация Системы Внутреннего противопожарного водопровода ("ВПВ"), включая пояснительную записку | I31: кв.м.площади офиса | K31: 43.2 | M31: =ROUND('Смета 1-й этаж'!$J31*'Смета 1-й этаж'!$K31,2) -> 0 | N31: =ROUND('Смета 1-й этаж'!$J31*'Смета 1-й этаж'!$L31,2) -> 0
A32: =CONCATENATE('Смета 1-й этаж'!$C32,".",'Смета 1-й этаж'!$D32,".",'Смета 1-й этаж'!$E32) -> Р1.0.12 | B32: 14 | C32: Р1 | D32: 0 | E32: 12 | F32: =CONCATENATE('Смета 1-й этаж'!$C32,".",'Смета 1-й этаж'!$D32,".",'Смета 1-й этаж'!$E32) -> Р1.0.12 | G32: =IF(J32>0,G31+1,G31) -> 2 | H32: Стоимость согласования проекта перепланировки/реставрации объекта культурного наследия в соответствии с нормативными актами г.______________. | I32: кв.м.площади офиса | K32: 0 | L32: 0 | M32: =ROUND('Смета 1-й этаж'!$J32*'Смета 1-й этаж'!$K32,2) -> 0 | N32: =ROUND('Смета 1-й этаж'!$J32*'Смета 1-й этаж'!$L32,2) -> 0
A33: =CONCATENATE('Смета 1-й этаж'!$C33,".",'Смета 1-й этаж'!$D33,".",'Смета 1-й этаж'!$E33) -> Р1.0.13 | B33: 15 | C33: Р1 | D33: 0 | E33: 13 | F33: =CONCATENATE('Смета 1-й этаж'!$C33,".",'Смета 1-й этаж'!$D33,".",'Смета 1-й этаж'!$E33) -> Р1.0.13 | G33: =IF(J33>0,G32+1,G32) -> 2 | H33: Стоимость согласования проекта перепланировки/реконструкции объекта в соответствии с нормативными актами г.Москва. | I33: кв.м.площади офиса | K33: 150 | M33: =ROUND('Смета 1-й этаж'!$J33*'Смета 1-й этаж'!$K33,2) -> 0 | N33: =ROUND('Смета 1-й этаж'!$J33*'Смета 1-й этаж'!$L33,2) -> 0
A34: =CONCATENATE('Смета 1-й этаж'!$C34,".",'Смета 1-й этаж'!$D34,".",'Смета 1-й этаж'!$E34) -> Р1.0.14 | B34: 16 | C34: Р1 | D34: 0 | E34: 14 | F34: =CONCATENATE('Смета 1-й этаж'!$C34,".",'Смета 1-й этаж'!$D34,".",'Смета 1-й этаж'!$E34) -> Р1.0.14 | G34: =IF(J34>0,G33+1,G33) -> 2 | H34: Получение паспорта БТИ (в черных линиях) | I34: кв.м.площади офиса | K34: 171.924 | M34: =ROUND('Смета 1-й этаж'!$J34*'Смета 1-й этаж'!$K34,2) -> 0 | N34: =ROUND('Смета 1-й этаж'!$J34*'Смета 1-й этаж'!$L34,2) -> 0
A35: =CONCATENATE('Смета 1-й этаж'!$C35,".",'Смета 1-й этаж'!$D35,".",'Смета 1-й этаж'!$E35) -> Р1.0.15 | B35: 17 | C35: Р1 | D35: 0 | E35: 15 | F35: =CONCATENATE('Смета 1-й этаж'!$C35,".",'Смета 1-й этаж'!$D35,".",'Смета 1-й этаж'!$E35) -> Р1.0.15 | G35: =IF(J35>0,G34+1,G34) -> 2 | H35: Сертификация помещения для совершения операций с ценностями, хранение ценностей по (2) классу вломостойкости и (3) классу пулестойкости | I35: кв.м.площади офиса | K35: 60.48 | L35: 0 | M35: =ROUND('Смета 1-й этаж'!$J35*'Смета 1-й этаж'!$K35,2) -> 0 | N35: =ROUND('Смета 1-й этаж'!$J35*'Смета 1-й этаж'!$L35,2) -> 0
A36: =CONCATENATE('Смета 1-й этаж'!$C36,".",'Смета 1-й этаж'!$D36,".",'Смета 1-й этаж'!$E36) -> Р1.0.16 | B36: 18 | C36: Р1 | D36: 0 | E36: 16 | F36: =CONCATENATE('Смета 1-й этаж'!$C36,".",'Смета 1-й этаж'!$D36,".",'Смета 1-й этаж'!$E36) -> Р1.0.16 | G36: =IF(J36>0,G35+1,G35) -> 2 | H36: Сертификация помещения для совершения операций с ценностями, хранение ценностей по 3 классу вломостойкости и 3 классу пулестойкости | I36: кв.м.площади офиса | K36: 108.48 | L36: 0 | M36: =ROUND('Смета 1-й этаж'!$J36*'Смета 1-й этаж'!$K36,2) -> 0 | N36: =ROUND('Смета 1-й этаж'!$J36*'Смета 1-й этаж'!$L36,2) -> 0
A37: =CONCATENATE('Смета 1-й этаж'!$C37,".",'Смета 1-й этаж'!$D37,".",'Смета 1-й этаж'!$E37) -> Р1.0.17 | B37: 19 | C37: Р1 | D37: 0 | E37: 17 | F37: =CONCATENATE('Смета 1-й этаж'!$C37,".",'Смета 1-й этаж'!$D37,".",'Смета 1-й этаж'!$E37) -> Р1.0.17 | G37: =IF(J37>0,G36+1,G36) -> 2 | H37: Сертификация помещения для совершения операций с ценностями, хранение ценностей по (5) классу вломостойкости | I37: кв.м.площади офиса | K37: 62.52 | L37: 0 | M37: =ROUND('Смета 1-й этаж'!$J37*'Смета 1-й этаж'!$K37,2) -> 0 | N37: =ROUND('Смета 1-й этаж'!$J37*'Смета 1-й этаж'!$L37,2) -> 0
A38: =CONCATENATE('Смета 1-й этаж'!$C38,".",'Смета 1-й этаж'!$D38,".",'Смета 1-й этаж'!$E38) -> Р1.0.18 | B38: 20 | C38: Р1 | D38: 0 | E38: 18 | F38: =CONCATENATE('Смета 1-й этаж'!$C38,".",'Смета 1-й этаж'!$D38,".",'Смета 1-й этаж'!$E38) -> Р1.0.18 | G38: =IF(J38>0,G37+1,G37) -> 2 | H38: Технический отчет электролаборатории | I38: кв.м.площади офиса | K38: 83.428138 | M38: =ROUND('Смета 1-й этаж'!$J38*'Смета 1-й этаж'!$K38,2) -> 0 | N38: =ROUND('Смета 1-й этаж'!$J38*'Смета 1-й этаж'!$L38,2) -> 0
A39: =CONCATENATE('Смета 1-й этаж'!$C39,".",'Смета 1-й этаж'!$D39,".",'Смета 1-й этаж'!$E39) -> Р1.0.19 | B39: 21 | C39: Р1 | D39: 0 | E39: 19 | F39: =CONCATENATE('Смета 1-й этаж'!$C39,".",'Смета 1-й этаж'!$D39,".",'Смета 1-й этаж'!$E39) -> Р1.0.19 | G39: =IF(J39>0,G38+1,G38) -> 2 | H39: Стоимость согласования проекта изменения фасада согласно нормативных и законодательных актов г. ___________ и РФ. | I39: кв.м.площади офиса | K39: 131.15 | L39: 0 | M39: =ROUND('Смета 1-й этаж'!$J39*'Смета 1-й этаж'!$K39,2) -> 0 | N39: =ROUND('Смета 1-й этаж'!$J39*'Смета 1-й этаж'!$L39,2) -> 0
A40: =CONCATENATE('Смета 1-й этаж'!$C40,".",'Смета 1-й этаж'!$D40,".",'Смета 1-й этаж'!$E40) -> Р1.0.20 | B40: 22 | C40: Р1 | D40: 0 | E40: 20 | F40: =CONCATENATE('Смета 1-й этаж'!$C40,".",'Смета 1-й этаж'!$D40,".",'Смета 1-й этаж'!$E40) -> Р1.0.20 | G40: =IF(J40>0,G39+1,G39) -> 2 | H40: Разработка дизайн-проекта интерьера | I40: кв.м.площади офиса | K40: 0 | L40: 0 | M40: =ROUND('Смета 1-й этаж'!$J40*'Смета 1-й этаж'!$K40,2) -> 0 | N40: =ROUND('Смета 1-й этаж'!$J40*'Смета 1-й этаж'!$L40,2) -> 0
A41: =CONCATENATE('Смета 1-й этаж'!$C41,".",'Смета 1-й этаж'!$D41,".",'Смета 1-й этаж'!$E41) -> Р1.0.21 | B41: 23 | C41: Р1 | D41: 0 | E41: 21 | F41: =CONCATENATE('Смета 1-й этаж'!$C41,".",'Смета 1-й этаж'!$D41,".",'Смета 1-й этаж'!$E41) -> Р1.0.21 | G41: =IF(J41>0,G40+1,G40) -> 2 | H41: Экспертиза и согласование проекта ЭОМ в Ростехнадзоре | I41: кв.м.площади офиса | K41: 73.65 | L41: 0 | M41: =ROUND('Смета 1-й этаж'!$J41*'Смета 1-й этаж'!$K41,2) -> 0 | N41: =ROUND('Смета 1-й этаж'!$J41*'Смета 1-й этаж'!$L41,2) -> 0
A42: =CONCATENATE('Смета 1-й этаж'!$C42,".",'Смета 1-й этаж'!$D42,".",'Смета 1-й этаж'!$E42) -> Р1.0.22 | B42: 24 | C42: Р1 | D42: 0 | E42: 22 | F42: =CONCATENATE('Смета 1-й этаж'!$C42,".",'Смета 1-й этаж'!$D42,".",'Смета 1-й этаж'!$E42) -> Р1.0.22 | G42: =IF(J42>0,G41+1,G41) -> 2 | H42: Проект системы водоотведения | I42: кв.м.площади офиса | K42: 0 | L42: 0 | M42: =ROUND('Смета 1-й этаж'!$J42*'Смета 1-й этаж'!$K42,2) -> 0 | N42: =ROUND('Смета 1-й этаж'!$J42*'Смета 1-й этаж'!$L42,2) -> 0
A43: =CONCATENATE('Смета 1-й этаж'!$C43,".",'Смета 1-й этаж'!$D43,".",'Смета 1-й этаж'!$E43) -> Р1.0.23 | B43: 25 | C43: Р1 | D43: 0 | E43: 23 | F43: =CONCATENATE('Смета 1-й этаж'!$C43,".",'Смета 1-й этаж'!$D43,".",'Смета 1-й этаж'!$E43) -> Р1.0.23 | G43: =IF(J43>0,G42+1,G42) -> 2 | H43: Рабочая документация Системы ливневой канализации | I43: кв.м.площади офиса | K43: 0 | L43: 0 | M43: =ROUND('Смета 1-й этаж'!$J43*'Смета 1-й этаж'!$K43,2) -> 0 | N43: =ROUND('Смета 1-й этаж'!$J43*'Смета 1-й этаж'!$L43,2) -> 0
A44: =CONCATENATE('Смета 1-й этаж'!$C44,".",'Смета 1-й этаж'!$D44,".",'Смета 1-й этаж'!$E44) -> Р1.0.24 | B44: 26 | C44: Р1 | D44: 0 | E44: 24 | F44: =CONCATENATE('Смета 1-й этаж'!$C44,".",'Смета 1-й этаж'!$D44,".",'Смета 1-й этаж'!$E44) -> Р1.0.24 | G44: =IF(J44>0,G43+1,G43) -> 2 | H44: Получение Технических условий (при необходимости) | I44: кв.м.площади офиса | K44: 0 | L44: 0 | M44: =ROUND('Смета 1-й этаж'!$J44*'Смета 1-й этаж'!$K44,2) -> 0 | N44: =ROUND('Смета 1-й этаж'!$J44*'Смета 1-й этаж'!$L44,2) -> 0
A45: =CONCATENATE('Смета 1-й этаж'!$C45,".",'Смета 1-й этаж'!$D45,".",'Смета 1-й этаж'!$E45) -> Р1.0.25 | B45: 27 | C45: Р1 | D45: 0 | E45: 25 | F45: =CONCATENATE('Смета 1-й этаж'!$C45,".",'Смета 1-й этаж'!$D45,".",'Смета 1-й этаж'!$E45) -> Р1.0.25 | G45: =IF(J45>0,G44+1,G44) -> 2 | H45: Рабочая документация Системы дымоудаления ("ДУ"), включая пояснительную записку | I45: кв.м.площади офиса | K45: 72 | M45: =ROUND('Смета 1-й этаж'!$J45*'Смета 1-й этаж'!$K45,2) -> 0 | N45: =ROUND('Смета 1-й этаж'!$J45*'Смета 1-й этаж'!$L45,2) -> 0
A46: =CONCATENATE('Смета 1-й этаж'!$C46,".",'Смета 1-й этаж'!$D46,".",'Смета 1-й этаж'!$E46) -> Р1.0.27 | B46: 28 | C46: Р1 | D46: 0 | E46: 27 | F46: =CONCATENATE('Смета 1-й этаж'!$C46,".",'Смета 1-й этаж'!$D46,".",'Смета 1-й этаж'!$E46) -> Р1.0.27 | G46: =IF(J46>0,G45+1,G45) -> 2 | H46: Расчет категории пожарной опасности помещений | I46: кв.м.площади офиса | K46: 22.34 | L46: 0 | M46: =ROUND('Смета 1-й этаж'!$J46*'Смета 1-й этаж'!$K46,2) -> 0 | N46: =ROUND('Смета 1-й этаж'!$J46*'Смета 1-й этаж'!$L46,2) -> 0
A47: =CONCATENATE('Смета 1-й этаж'!$C47,".",'Смета 1-й этаж'!$D47,".",'Смета 1-й этаж'!$E47) -> Р1.0.28 | B47: 29 | C47: Р1 | D47: 0 | E47: 28 | F47: =CONCATENATE('Смета 1-й этаж'!$C47,".",'Смета 1-й этаж'!$D47,".",'Смета 1-й этаж'!$E47) -> Р1.0.28 | G47: =IF(J47>0,G46+1,G46) -> 2 | H47: Рабочая документация Системы оповещения и управления эвакуацией в части световых указателей ("СОУЭ") | I47: кв.м.площади офиса | K47: 22.34 | L47: 0 | M47: =ROUND('Смета 1-й этаж'!$J47*'Смета 1-й этаж'!$K47,2) -> 0 | N47: =ROUND('Смета 1-й этаж'!$J47*'Смета 1-й этаж'!$L47,2) -> 0
A48: =CONCATENATE('Смета 1-й этаж'!$C48,".",'Смета 1-й этаж'!$D48,".",'Смета 1-й этаж'!$E48) -> Р1.0.32 | B48: 30 | C48: Р1 | D48: 0 | E48: 32 | F48: =CONCATENATE('Смета 1-й этаж'!$C48,".",'Смета 1-й этаж'!$D48,".",'Смета 1-й этаж'!$E48) -> Р1.0.32 | G48: =IF(J48>0,G47+1,G47) -> 2 | H48: Согласование проекта Системы водоотведения и получения тех условий (при необходимости) | I48: кв.м.площади офиса | K48: 0 | L48: 0 | M48: =ROUND('Смета 1-й этаж'!$J48*'Смета 1-й этаж'!$K48,2) -> 0 | N48: =ROUND('Смета 1-й этаж'!$J48*'Смета 1-й этаж'!$L48,2) -> 0
A49: =CONCATENATE('Смета 1-й этаж'!$C49,".",'Смета 1-й этаж'!$D49,".",'Смета 1-й этаж'!$E49) -> Р1.0.34 | B49: 31 | C49: Р1 | D49: 0 | E49: 34 | F49: =CONCATENATE('Смета 1-й этаж'!$C49,".",'Смета 1-й этаж'!$D49,".",'Смета 1-й этаж'!$E49) -> Р1.0.34 | G49: =IF(J49>0,G48+1,G48) -> 2 | H49: Испытание лестниц 3 типа с предоставлением актов | I49: кв.м.площади офиса | K49: 21.01 | L49: 0 | M49: =ROUND('Смета 1-й этаж'!$J49*'Смета 1-й этаж'!$K49,2) -> 0 | N49: =ROUND('Смета 1-й этаж'!$J49*'Смета 1-й этаж'!$L49,2) -> 0
A50: =CONCATENATE('Смета 1-й этаж'!$C50,".",'Смета 1-й этаж'!$D50,".",'Смета 1-й этаж'!$E50) -> Р1.0.35 | B50: 32 | C50: Р1 | D50: 0 | E50: 35 | F50: =CONCATENATE('Смета 1-й этаж'!$C50,".",'Смета 1-й этаж'!$D50,".",'Смета 1-й этаж'!$E50) -> Р1.0.35 | G50: =IF(J50>0,G49+1,G49) -> 2 | H50: Мероприятия по обеспечению доступа инвалидов | I50: кв.м.площади офиса | K50: 52.11 | L50: 0 | M50: =ROUND('Смета 1-й этаж'!$J50*'Смета 1-й этаж'!$K50,2) -> 0 | N50: =ROUND('Смета 1-й этаж'!$J50*'Смета 1-й этаж'!$L50,2) -> 0
A51: =CONCATENATE('Смета 1-й этаж'!$C51,".",'Смета 1-й этаж'!$D51,".",'Смета 1-й этаж'!$E51) -> Р1.0.38 | B51: 33 | C51: Р1 | D51: 0 | E51: 38 | F51: =CONCATENATE('Смета 1-й этаж'!$C51,".",'Смета 1-й этаж'!$D51,".",'Смета 1-й этаж'!$E51) -> Р1.0.38 | G51: =IF(J51>0,G50+1,G50) -> 2 | H51: Расчет пожарного риска | I51: кв.м.площади офиса | K51: 0 | L51: 0 | M51: =ROUND('Смета 1-й этаж'!$J51*'Смета 1-й этаж'!$K51,2) -> 0 | N51: =ROUND('Смета 1-й этаж'!$J51*'Смета 1-й этаж'!$L51,2) -> 0 | O51: при проведении конкурса позицию не использовать, при включении позиции в ДС использовать данный номер | P51: новая расценка
B52: 34 | C52: Р1 | D52: 0 | E52: 39 | F52: =CONCATENATE('Смета 1-й этаж'!$C52,".",'Смета 1-й этаж'!$D52,".",'Смета 1-й этаж'!$E52) -> Р1.0.39 | G52: =IF(J52>0,G51+1,G51) -> 2 | H52: Подготовка и постановка на учет Независимой оценки пожарного риска (пожарный аудит), включая Расчет пожарного риска | I52: кв.м.площади офиса | K52: 0 | L52: 0 | M52: =ROUND('Смета 1-й этаж'!$J52*'Смета 1-й этаж'!$K52,2) -> 0 | N52: =ROUND('Смета 1-й этаж'!$J52*'Смета 1-й этаж'!$L52,2) -> 0 | O52: при проведении конкурса позицию не использовать, при включении позиции в ДС использовать данный номер | P52: новая расценка
B53: 35 | C53: Р1 | D53: 0 | E53: 40 | F53: =CONCATENATE('Смета 1-й этаж'!$C53,".",'Смета 1-й этаж'!$D53,".",'Смета 1-й этаж'!$E53) -> Р1.0.40 | G53: =IF(J53>0,G52+1,G52) -> 2 | H53: Разработка проекта огнезащиты | I53: шт. | K53: 11500 | M53: =ROUND('Смета 1-й этаж'!$J53*'Смета 1-й этаж'!$K53,2) -> 0 | N53: =ROUND('Смета 1-й этаж'!$J53*'Смета 1-й этаж'!$L53,2) -> 0 | P53: новая расценка
B54: 36 | C54: Р1 | D54: 0 | E54: 41 | F54: =CONCATENATE('Смета 1-й этаж'!$C54,".",'Смета 1-й этаж'!$D54,".",'Смета 1-й этаж'!$E54) -> Р1.0.41 | G54: =IF(J54>0,G53+1,G53) -> 2 | H54: Предоставление заключения пожарной испытательной лаборатории для контроля качества огнезащитных работ | I54: комп. | K54: 13200 | M54: =ROUND('Смета 1-й этаж'!$J54*'Смета 1-й этаж'!$K54,2) -> 0 | N54: =ROUND('Смета 1-й этаж'!$J54*'Смета 1-й этаж'!$L54,2) -> 0 | P54: новая расценка
B55: 37 | C55: Р1 | D55: 0 | E55: 42 | F55: =CONCATENATE('Смета 1-й этаж'!$C55,".",'Смета 1-й этаж'!$D55,".",'Смета 1-й этаж'!$E55) -> Р1.0.42 | G55: =IF(J55>0,G54+1,G54) -> 2 | M55: =ROUND('Смета 1-й этаж'!$J55*'Смета 1-й этаж'!$K55,2) -> 0 | N55: =ROUND('Смета 1-й этаж'!$J55*'Смета 1-й этаж'!$L55,2) -> 0
B56: 38 | C56: Р2 | D56: 0 | E56: 43 | F56: =CONCATENATE('Смета 1-й этаж'!$C56,".",'Смета 1-й этаж'!$D56,".",'Смета 1-й этаж'!$E56) -> Р2.0.43 | G56: =IF(J56>0,G55+1,G55) -> 2 | M56: =ROUND('Смета 1-й этаж'!$J56*'Смета 1-й этаж'!$K56,2) -> 0 | N56: =ROUND('Смета 1-й этаж'!$J56*'Смета 1-й этаж'!$L56,2) -> 0
A57: =CONCATENATE('Смета 1-й этаж'!$C57,".",'Смета 1-й этаж'!$D57,".",'Смета 1-й этаж'!$E57) -> Р2.0.0 | B57: 34 | C57: Р2 | D57: 0 | E57: 0 | F57: =CONCATENATE('Смета 1-й этаж'!$C57,".",'Смета 1-й этаж'!$D57,".",'Смета 1-й этаж'!$E57) -> Р2.0.0 | G57: =IF(J57>0,G56+1,G56) -> 2 | H57: Раздел №2. Демонтажные работы. | J57: =J189+J181+J168+J162+J152+J137+J121+J111+J93+J75+J59+J131+J58 -> 0 | M57: =ROUND(M189+M181+M168+M162+M152+M137+M121+M111+M93+M75+M59+M131+M58,2) -> 0 | N57: =ROUND(N189+N181+N168+N162+N152+N137+N121+N111+N93+N75+N59+N131+N58,2) -> 0
A58: =CONCATENATE('Смета 1-й этаж'!$C58,".",'Смета 1-й этаж'!$D58,".",'Смета 1-й этаж'!$E58) -> Р2.1.16 | B58: 35 | C58: Р2 | D58: 1 | E58: 16 | F58: =CONCATENATE('Смета 1-й этаж'!$C58,".",'Смета 1-й этаж'!$D58,".",'Смета 1-й этаж'!$E58) -> Р2.1.16 | G58: =IF(J58>0,G57+1,G57) -> 2 | H58: Демонтажные работы до состояния shell-and-core | I58: кв.м.площади офиса | K58: 905 | L58: 0 | M58: =ROUND('Смета 1-й этаж'!$J58*'Смета 1-й этаж'!$K58,2) -> 0 | N58: =ROUND('Смета 1-й этаж'!$J58*'Смета 1-й этаж'!$L58,2) -> 0 | O58: Позиция применяется при полном демонтаже. Демонтаж бронированных касс и депозитариев оценивается дополнительно.
A59: =CONCATENATE('Смета 1-й этаж'!$C59,".",'Смета 1-й этаж'!$D59,".",'Смета 1-й этаж'!$E59) -> Р2.1.0 | B59: 36 | C59: Р2 | D59: 1 | E59: 0 | F59: =CONCATENATE('Смета 1-й этаж'!$C59,".",'Смета 1-й этаж'!$D59,".",'Смета 1-й этаж'!$E59) -> Р2.1.0 | G59: =IF(J59>0,G58+1,G58) -> 2 | H59: 2.1.0 Потолки | J59: =SUM(J60:J74) -> 0 | M59: =SUM(M60:M74) -> 0 | N59: =SUM(N60:N74) -> 0
A60: =CONCATENATE('Смета 1-й этаж'!$C60,".",'Смета 1-й этаж'!$D60,".",'Смета 1-й этаж'!$E60) -> Р2.1.1 | B60: 37 | C60: Р2 | D60: 1 | E60: 1 | F60: =CONCATENATE('Смета 1-й этаж'!$C60,".",'Смета 1-й этаж'!$D60,".",'Смета 1-й этаж'!$E60) -> Р2.1.1 | G60: =IF(J60>0,G59+1,G59) -> 2 | H60: Демонтаж подвесных потолков типа "Армстронг" | I60: м2 | K60: 71.68 | L60: 0 | M60: =ROUND('Смета 1-й этаж'!$J60*'Смета 1-й этаж'!$K60,2) -> 0 | N60: =ROUND('Смета 1-й этаж'!$J60*'Смета 1-й этаж'!$L60,2) -> 0
A61: =CONCATENATE('Смета 1-й этаж'!$C61,".",'Смета 1-й этаж'!$D61,".",'Смета 1-й этаж'!$E61) -> Р2.1.2 | B61: 38 | C61: Р2 | D61: 1 | E61: 2 | F61: =CONCATENATE('Смета 1-й этаж'!$C61,".",'Смета 1-й этаж'!$D61,".",'Смета 1-й этаж'!$E61) -> Р2.1.2 | G61: =IF(J61>0,G60+1,G60) -> 2 | H61: Демонтаж подвесных потолков "Армстронг" с сохранением | I61: м2 | K61: 142.5 | L61: 0 | M61: =ROUND('Смета 1-й этаж'!$J61*'Смета 1-й этаж'!$K61,2) -> 0 | N61: =ROUND('Смета 1-й этаж'!$J61*'Смета 1-й этаж'!$L61,2) -> 0
A62: =CONCATENATE('Смета 1-й этаж'!$C62,".",'Смета 1-й этаж'!$D62,".",'Смета 1-й этаж'!$E62) -> Р2.1.3 | B62: 39 | C62: Р2 | D62: 1 | E62: 3 | F62: =CONCATENATE('Смета 1-й этаж'!$C62,".",'Смета 1-й этаж'!$D62,".",'Смета 1-й этаж'!$E62) -> Р2.1.3 | G62: =IF(J62>0,G61+1,G61) -> 2 | H62: Демонтаж одноуровневых потолков из ГКЛ | I62: м2 | K62: 100 | L62: 0 | M62: =ROUND('Смета 1-й этаж'!$J62*'Смета 1-й этаж'!$K62,2) -> 0 | N62: =ROUND('Смета 1-й этаж'!$J62*'Смета 1-й этаж'!$L62,2) -> 0
A63: =CONCATENATE('Смета 1-й этаж'!$C63,".",'Смета 1-й этаж'!$D63,".",'Смета 1-й этаж'!$E63) -> Р2.1.4 | B63: 40 | C63: Р2 | D63: 1 | E63: 4 | F63: =CONCATENATE('Смета 1-й этаж'!$C63,".",'Смета 1-й этаж'!$D63,".",'Смета 1-й этаж'!$E63) -> Р2.1.4 | G63: =IF(J63>0,G62+1,G62) -> 2 | H63: Демонтаж двухуровневых потолков из ГКЛ | I63: м2 | K63: 123 | L63: 0 | M63: =ROUND('Смета 1-й этаж'!$J63*'Смета 1-й этаж'!$K63,2) -> 0 | N63: =ROUND('Смета 1-й этаж'!$J63*'Смета 1-й этаж'!$L63,2) -> 0
A64: =CONCATENATE('Смета 1-й этаж'!$C64,".",'Смета 1-й этаж'!$D64,".",'Смета 1-й этаж'!$E64) -> Р2.1.5 | B64: 41 | C64: Р2 | D64: 1 | E64: 5 | F64: =CONCATENATE('Смета 1-й этаж'!$C64,".",'Смета 1-й этаж'!$D64,".",'Смета 1-й этаж'!$E64) -> Р2.1.5 | G64: =IF(J64>0,G63+1,G63) -> 2 | H64: Демонтаж реечного потолка | I64: м2 | K64: 127.35 | L64: 0 | M64: =ROUND('Смета 1-й этаж'!$J64*'Смета 1-й этаж'!$K64,2) -> 0 | N64: =ROUND('Смета 1-й этаж'!$J64*'Смета 1-й этаж'!$L64,2) -> 0
A65: =CONCATENATE('Смета 1-й этаж'!$C65,".",'Смета 1-й этаж'!$D65,".",'Смета 1-й этаж'!$E65) -> Р2.1.6 | B65: 42 | C65: Р2 | D65: 1 | E65: 6 | F65: =CONCATENATE('Смета 1-й этаж'!$C65,".",'Смета 1-й этаж'!$D65,".",'Смета 1-й этаж'!$E65) -> Р2.1.6 | G65: =IF(J65>0,G64+1,G64) -> 2 | H65: Демонтаж плитки потолочной из экструдированного полистирола. | I65: м2 | K65: 90 | L65: 0 | M65: =ROUND('Смета 1-й этаж'!$J65*'Смета 1-й этаж'!$K65,2) -> 0 | N65: =ROUND('Смета 1-й этаж'!$J65*'Смета 1-й этаж'!$L65,2) -> 0
A66: =CONCATENATE('Смета 1-й этаж'!$C66,".",'Смета 1-й этаж'!$D66,".",'Смета 1-й этаж'!$E66) -> Р2.1.7 | B66: 43 | C66: Р2 | D66: 1 | E66: 7 | F66: =CONCATENATE('Смета 1-й этаж'!$C66,".",'Смета 1-й этаж'!$D66,".",'Смета 1-й этаж'!$E66) -> Р2.1.7 | G66: =IF(J66>0,G65+1,G65) -> 2 | H66: Демонтаж потолков из ПВХ вагонки | I66: м2 | K66: 33.58 | L66: 0 | M66: =ROUND('Смета 1-й этаж'!$J66*'Смета 1-й этаж'!$K66,2) -> 0 | N66: =ROUND('Смета 1-й этаж'!$J66*'Смета 1-й этаж'!$L66,2) -> 0
A67: =CONCATENATE('Смета 1-й этаж'!$C67,".",'Смета 1-й этаж'!$D67,".",'Смета 1-й этаж'!$E67) -> Р2.1.8 | B67: 44 | C67: Р2 | D67: 1 | E67: 8 | F67: =CONCATENATE('Смета 1-й этаж'!$C67,".",'Смета 1-й этаж'!$D67,".",'Смета 1-й этаж'!$E67) -> Р2.1.8 | G67: =IF(J67>0,G66+1,G66) -> 2 | H67: Демонтаж потолков из деревянной вагонки | I67: м2 | K67: 36.79 | L67: 0 | M67: =ROUND('Смета 1-й этаж'!$J67*'Смета 1-й этаж'!$K67,2) -> 0 | N67: =ROUND('Смета 1-й этаж'!$J67*'Смета 1-й этаж'!$L67,2) -> 0
A68: =CONCATENATE('Смета 1-й этаж'!$C68,".",'Смета 1-й этаж'!$D68,".",'Смета 1-й этаж'!$E68) -> Р2.1.9 | B68: 45 | C68: Р2 | D68: 1 | E68: 9 | F68: =CONCATENATE('Смета 1-й этаж'!$C68,".",'Смета 1-й этаж'!$D68,".",'Смета 1-й этаж'!$E68) -> Р2.1.9 | G68: =IF(J68>0,G67+1,G67) -> 2 | H68: Демонтаж утеплителя потолков из минераловатных плит | I68: м3 | K68: 689.17 | L68: 0 | M68: =ROUND('Смета 1-й этаж'!$J68*'Смета 1-й этаж'!$K68,2) -> 0 | N68: =ROUND('Смета 1-й этаж'!$J68*'Смета 1-й этаж'!$L68,2) -> 0
A69: =CONCATENATE('Смета 1-й этаж'!$C69,".",'Смета 1-й этаж'!$D69,".",'Смета 1-й этаж'!$E69) -> Р2.1.10 | B69: 46 | C69: Р2 | D69: 1 | E69: 10 | F69: =CONCATENATE('Смета 1-й этаж'!$C69,".",'Смета 1-й этаж'!$D69,".",'Смета 1-й этаж'!$E69) -> Р2.1.10 | G69: =IF(J69>0,G68+1,G68) -> 2 | H69: Демонтаж утеплителя потолков из пенополистирола | I69: м3 | K69: 630.83 | L69: 0 | M69: =ROUND('Смета 1-й этаж'!$J69*'Смета 1-й этаж'!$K69,2) -> 0 | N69: =ROUND('Смета 1-й этаж'!$J69*'Смета 1-й этаж'!$L69,2) -> 0
A70: =CONCATENATE('Смета 1-й этаж'!$C70,".",'Смета 1-й этаж'!$D70,".",'Смета 1-й этаж'!$E70) -> Р2.1.11 | B70: 47 | C70: Р2 | D70: 1 | E70: 11 | F70: =CONCATENATE('Смета 1-й этаж'!$C70,".",'Смета 1-й этаж'!$D70,".",'Смета 1-й этаж'!$E70) -> Р2.1.11 | G70: =IF(J70>0,G69+1,G69) -> 2 | H70: Демонтаж потолочного плинтуса, карниза, элементов декора. | I70: м.п. | K70: 42.5 | L70: 0 | M70: =ROUND('Смета 1-й этаж'!$J70*'Смета 1-й этаж'!$K70,2) -> 0 | N70: =ROUND('Смета 1-й этаж'!$J70*'Смета 1-й этаж'!$L70,2) -> 0
A71: =CONCATENATE('Смета 1-й этаж'!$C71,".",'Смета 1-й этаж'!$D71,".",'Смета 1-й этаж'!$E71) -> Р2.1.12 | B71: 48 | C71: Р2 | D71: 1 | E71: 12 | F71: =CONCATENATE('Смета 1-й этаж'!$C71,".",'Смета 1-й этаж'!$D71,".",'Смета 1-й этаж'!$E71) -> Р2.1.12 | G71: =IF(J71>0,G70+1,G70) -> 2 | H71: Демонтаж потолочного плинтуса, карниза, элементов декора с сохранением. | I71: м.п. | K71: 114 | L71: 0 | M71: =ROUND('Смета 1-й этаж'!$J71*'Смета 1-й этаж'!$K71,2) -> 0 | N71: =ROUND('Смета 1-й этаж'!$J71*'Смета 1-й этаж'!$L71,2) -> 0
... A74: =CONCATENATE('Смета 1-й этаж'!$C74,".",'Смета 1-й этаж'!$D74,".",'Смета 1-й этаж'!$E74) -> Р2.1.15 | B74: 51 | C74: Р2 | D74: 1 | E74: 15 | F74: =CONCATENATE('Смета 1-й этаж'!$C74,".",'Смета 1-й этаж'!$D74,".",'Смета 1-й этаж'!$E74) -> Р2.1.15 | G74: =IF(J74>0,G73+1,G73) -> 2 | H74: Демонтаж подвесных потолков типа "Грильято" | I74: м2 | K74: 150 | L74: 0 | M74: =ROUND('Смета 1-й этаж'!$J74*'Смета 1-й этаж'!$K74,2) -> 0 | N74: =ROUND('Смета 1-й этаж'!$J74*'Смета 1-й этаж'!$L74,2) -> 0
A75: =CONCATENATE('Смета 1-й этаж'!$C75,".",'Смета 1-й этаж'!$D75,".",'Смета 1-й этаж'!$E75) -> Р2.2.0 | B75: 52 | C75: Р2 | D75: 2 | E75: 0 | F75: =CONCATENATE('Смета 1-й этаж'!$C75,".",'Смета 1-й этаж'!$D75,".",'Смета 1-й этаж'!$E75) -> Р2.2.0 | G75: =IF(J75>0,G74+1,G74) -> 2 | H75: 2.2.0 Полы | J75: =SUM(J76:J92) -> 0 | M75: =SUM(M76:M92) -> 0 | N75: =SUM(N76:N92) -> 0
A76: =CONCATENATE('Смета 1-й этаж'!$C76,".",'Смета 1-й этаж'!$D76,".",'Смета 1-й этаж'!$E76) -> Р2.2.1 | B76: 53 | C76: Р2 | D76: 2 | E76: 1 | F76: =CONCATENATE('Смета 1-й этаж'!$C76,".",'Смета 1-й этаж'!$D76,".",'Смета 1-й этаж'!$E76) -> Р2.2.1 | G76: =IF(J76>0,G75+1,G75) -> 2 | H76: Демонтаж цементно-песчаной стяжки толщиной до 50 мм | I76: м2 | K76: 128.43 | L76: 0 | M76: =ROUND('Смета 1-й этаж'!$J76*'Смета 1-й этаж'!$K76,2) -> 0 | N76: =ROUND('Смета 1-й этаж'!$J76*'Смета 1-й этаж'!$L76,2) -> 0
A77: =CONCATENATE('Смета 1-й этаж'!$C77,".",'Смета 1-й этаж'!$D77,".",'Смета 1-й этаж'!$E77) -> Р2.2.2 | B77: 54 | C77: Р2 | D77: 2 | E77: 2 | F77: =CONCATENATE('Смета 1-й этаж'!$C77,".",'Смета 1-й этаж'!$D77,".",'Смета 1-й этаж'!$E77) -> Р2.2.2 | G77: =IF(J77>0,G76+1,G76) -> 2 | H77: Демонтаж цементно-песчаной стяжки толщиной до 100 мм | I77: м2 | K77: 125 | L77: 0 | M77: =ROUND('Смета 1-й этаж'!$J77*'Смета 1-й этаж'!$K77,2) -> 0 | N77: =ROUND('Смета 1-й этаж'!$J77*'Смета 1-й этаж'!$L77,2) -> 0
A78: =CONCATENATE('Смета 1-й этаж'!$C78,".",'Смета 1-й этаж'!$D78,".",'Смета 1-й этаж'!$E78) -> Р2.2.3 | B78: 55 | C78: Р2 | D78: 2 | E78: 3 | F78: =CONCATENATE('Смета 1-й этаж'!$C78,".",'Смета 1-й этаж'!$D78,".",'Смета 1-й этаж'!$E78) -> Р2.2.3 | G78: =IF(J78>0,G77+1,G77) -> 2 | H78: Демонтаж цементно-песчаной стяжки армированной толщиной до 50 мм | I78: м2 | K78: 232.5 | L78: 0 | M78: =ROUND('Смета 1-й этаж'!$J78*'Смета 1-й этаж'!$K78,2) -> 0 | N78: =ROUND('Смета 1-й этаж'!$J78*'Смета 1-й этаж'!$L78,2) -> 0
A79: =CONCATENATE('Смета 1-й этаж'!$C79,".",'Смета 1-й этаж'!$D79,".",'Смета 1-й этаж'!$E79) -> Р2.2.4 | B79: 56 | C79: Р2 | D79: 2 | E79: 4 | F79: =CONCATENATE('Смета 1-й этаж'!$C79,".",'Смета 1-й этаж'!$D79,".",'Смета 1-й этаж'!$E79) -> Р2.2.4 | G79: =IF(J79>0,G78+1,G78) -> 2 | H79: Демонтаж цементно-песчаной стяжки армированной толщиной до 100 мм | I79: м2 | K79: 298.33 | L79: 0 | M79: =ROUND('Смета 1-й этаж'!$J79*'Смета 1-й этаж'!$K79,2) -> 0 | N79: =ROUND('Смета 1-й этаж'!$J79*'Смета 1-й этаж'!$L79,2) -> 0
A80: =CONCATENATE('Смета 1-й этаж'!$C80,".",'Смета 1-й этаж'!$D80,".",'Смета 1-й этаж'!$E80) -> Р2.2.5 | B80: 57 | C80: Р2 | D80: 2 | E80: 5 | F80: =CONCATENATE('Смета 1-й этаж'!$C80,".",'Смета 1-й этаж'!$D80,".",'Смета 1-й этаж'!$E80) -> Р2.2.5 | G80: =IF(J80>0,G79+1,G79) -> 2 | H80: Демонтаж полов из гранитных и мраморных плит толщиной 30 мм | I80: м2 | K80: 223.33 | L80: 0 | M80: =ROUND('Смета 1-й этаж'!$J80*'Смета 1-й этаж'!$K80,2) -> 0 | N80: =ROUND('Смета 1-й этаж'!$J80*'Смета 1-й этаж'!$L80,2) -> 0
A81: =CONCATENATE('Смета 1-й этаж'!$C81,".",'Смета 1-й этаж'!$D81,".",'Смета 1-й этаж'!$E81) -> Р2.2.6 | B81: 58 | C81: Р2 | D81: 2 | E81: 6 | F81: =CONCATENATE('Смета 1-й этаж'!$C81,".",'Смета 1-й этаж'!$D81,".",'Смета 1-й этаж'!$E81) -> Р2.2.6 | G81: =IF(J81>0,G80+1,G80) -> 2 | H81: Демонтаж покрытия полов из керамогранита и кераимческих плиток | I81: м2 | K81: 102.63 | L81: 0 | M81: =ROUND('Смета 1-й этаж'!$J81*'Смета 1-й этаж'!$K81,2) -> 0 | N81: =ROUND('Смета 1-й этаж'!$J81*'Смета 1-й этаж'!$L81,2) -> 0
A82: =CONCATENATE('Смета 1-й этаж'!$C82,".",'Смета 1-й этаж'!$D82,".",'Смета 1-й этаж'!$E82) -> Р2.2.7 | B82: 59 | C82: Р2 | D82: 2 | E82: 7 | F82: =CONCATENATE('Смета 1-й этаж'!$C82,".",'Смета 1-й этаж'!$D82,".",'Смета 1-й этаж'!$E82) -> Р2.2.7 | G82: =IF(J82>0,G81+1,G81) -> 2 | H82: Демонтаж покрытия полов цементных с мраморной крошкой | I82: м2 | K82: 0 | L82: 0 | M82: =ROUND('Смета 1-й этаж'!$J82*'Смета 1-й этаж'!$K82,2) -> 0 | N82: =ROUND('Смета 1-й этаж'!$J82*'Смета 1-й этаж'!$L82,2) -> 0
A83: =CONCATENATE('Смета 1-й этаж'!$C83,".",'Смета 1-й этаж'!$D83,".",'Смета 1-й этаж'!$E83) -> Р2.2.8 | B83: 60 | C83: Р2 | D83: 2 | E83: 8 | F83: =CONCATENATE('Смета 1-й этаж'!$C83,".",'Смета 1-й этаж'!$D83,".",'Смета 1-й этаж'!$E83) -> Р2.2.8 | G83: =IF(J83>0,G82+1,G82) -> 2 | H83: Расшивка швов поверхности пола из плитки керамической | I83: м2 | K83: 100 | L83: 0 | M83: =ROUND('Смета 1-й этаж'!$J83*'Смета 1-й этаж'!$K83,2) -> 0 | N83: =ROUND('Смета 1-й этаж'!$J83*'Смета 1-й этаж'!$L83,2) -> 0
A84: =CONCATENATE('Смета 1-й этаж'!$C84,".",'Смета 1-й этаж'!$D84,".",'Смета 1-й этаж'!$E84) -> Р2.2.9 | B84: 61 | C84: Р2 | D84: 2 | E84: 9 | F84: =CONCATENATE('Смета 1-й этаж'!$C84,".",'Смета 1-й этаж'!$D84,".",'Смета 1-й этаж'!$E84) -> Р2.2.9 | G84: =IF(J84>0,G83+1,G83) -> 2 | H84: Демонтаж покрытия полов: из линолеума, ковролина | I84: м2 | K84: 85.67 | L84: 0 | M84: =ROUND('Смета 1-й этаж'!$J84*'Смета 1-й этаж'!$K84,2) -> 0 | N84: =ROUND('Смета 1-й этаж'!$J84*'Смета 1-й этаж'!$L84,2) -> 0
A85: =CONCATENATE('Смета 1-й этаж'!$C85,".",'Смета 1-й этаж'!$D85,".",'Смета 1-й этаж'!$E85) -> Р2.2.10 | B85: 62 | C85: Р2 | D85: 2 | E85: 10 | F85: =CONCATENATE('Смета 1-й этаж'!$C85,".",'Смета 1-й этаж'!$D85,".",'Смета 1-й этаж'!$E85) -> Р2.2.10 | G85: =IF(J85>0,G84+1,G84) -> 2 | H85: Демонтаж покрытия полов: из паркетной доски (ламината) | I85: м2 | K85: 28.41 | L85: 0 | M85: =ROUND('Смета 1-й этаж'!$J85*'Смета 1-й этаж'!$K85,2) -> 0 | N85: =ROUND('Смета 1-й этаж'!$J85*'Смета 1-й этаж'!$L85,2) -> 0
A86: =CONCATENATE('Смета 1-й этаж'!$C86,".",'Смета 1-й этаж'!$D86,".",'Смета 1-й этаж'!$E86) -> Р2.2.11 | B86: 63 | C86: Р2 | D86: 2 | E86: 11 | F86: =CONCATENATE('Смета 1-й этаж'!$C86,".",'Смета 1-й этаж'!$D86,".",'Смета 1-й этаж'!$E86) -> Р2.2.11 | G86: =IF(J86>0,G85+1,G85) -> 2 | H86: Демонтаж фальшпола | I86: м2 | K86: 197 | L86: 0 | M86: =ROUND('Смета 1-й этаж'!$J86*'Смета 1-й этаж'!$K86,2) -> 0 | N86: =ROUND('Смета 1-й этаж'!$J86*'Смета 1-й этаж'!$L86,2) -> 0
A87: =CONCATENATE('Смета 1-й этаж'!$C87,".",'Смета 1-й этаж'!$D87,".",'Смета 1-й этаж'!$E87) -> Р2.2.12 | B87: 64 | C87: Р2 | D87: 2 | E87: 12 | F87: =CONCATENATE('Смета 1-й этаж'!$C87,".",'Смета 1-й этаж'!$D87,".",'Смета 1-й этаж'!$E87) -> Р2.2.12 | G87: =IF(J87>0,G86+1,G86) -> 2 | H87: Демонтаж деревянных полов на деревянных лагах | I87: м2 | K87: 208 | L87: 0 | M87: =ROUND('Смета 1-й этаж'!$J87*'Смета 1-й этаж'!$K87,2) -> 0 | N87: =ROUND('Смета 1-й этаж'!$J87*'Смета 1-й этаж'!$L87,2) -> 0
... A89: =CONCATENATE('Смета 1-й этаж'!$C89,".",'Смета 1-й этаж'!$D89,".",'Смета 1-й этаж'!$E89) -> Р2.2.14 | B89: 66 | C89: Р2 | D89: 2 | E89: 14 | F89: =CONCATENATE('Смета 1-й этаж'!$C89,".",'Смета 1-й этаж'!$D89,".",'Смета 1-й этаж'!$E89) -> Р2.2.14 | G89: =IF(J89>0,G88+1,G88) -> 2 | H89: Демонтаж плинтусов: деревянных, пвх | I89: м.п. | K89: 30.25 | L89: 0 | M89: =ROUND('Смета 1-й этаж'!$J89*'Смета 1-й этаж'!$K89,2) -> 0 | N89: =ROUND('Смета 1-й этаж'!$J89*'Смета 1-й этаж'!$L89,2) -> 0
A90: =CONCATENATE('Смета 1-й этаж'!$C90,".",'Смета 1-й этаж'!$D90,".",'Смета 1-й этаж'!$E90) -> Р2.2.15 | B90: 67 | C90: Р2 | D90: 2 | E90: 15 | F90: =CONCATENATE('Смета 1-й этаж'!$C90,".",'Смета 1-й этаж'!$D90,".",'Смета 1-й этаж'!$E90) -> Р2.2.15 | G90: =IF(J90>0,G89+1,G89) -> 2 | H90: Демонтаж ЖБ плит перекрытия. | I90: м2 | J90: 0 | K90: 4595.45 | L90: 0 | M90: =ROUND('Смета 1-й этаж'!$J90*'Смета 1-й этаж'!$K90,2) -> 0 | N90: =ROUND('Смета 1-й этаж'!$J90*'Смета 1-й этаж'!$L90,2) -> 0
A91: =CONCATENATE('Смета 1-й этаж'!$C91,".",'Смета 1-й этаж'!$D91,".",'Смета 1-й этаж'!$E91) -> Р2.2.16 | B91: 68 | C91: Р2 | D91: 2 | E91: 16 | F91: =CONCATENATE('Смета 1-й этаж'!$C91,".",'Смета 1-й этаж'!$D91,".",'Смета 1-й этаж'!$E91) -> Р2.2.16 | G91: =IF(J91>0,G90+1,G90) -> 2 | H91: Демонтаж деревянных балок перекрытия | I91: м.п. | K91: 500 | L91: 0 | M91: =ROUND('Смета 1-й этаж'!$J91*'Смета 1-й этаж'!$K91,2) -> 0 | N91: =ROUND('Смета 1-й этаж'!$J91*'Смета 1-й этаж'!$L91,2) -> 0
A92: =CONCATENATE('Смета 1-й этаж'!$C92,".",'Смета 1-й этаж'!$D92,".",'Смета 1-й этаж'!$E92) -> Р2.2.17 | B92: 69 | C92: Р2 | D92: 2 | E92: 17 | F92: =CONCATENATE('Смета 1-й этаж'!$C92,".",'Смета 1-й этаж'!$D92,".",'Смета 1-й этаж'!$E92) -> Р2.2.17 | G92: =IF(J92>0,G91+1,G91) -> 2 | H92: Демонтаж плиточного клея | I92: м2 | K92: 33.58 | L92: 0 | M92: =ROUND('Смета 1-й этаж'!$J92*'Смета 1-й этаж'!$K92,2) -> 0 | N92: =ROUND('Смета 1-й этаж'!$J92*'Смета 1-й этаж'!$L92,2) -> 0
A93: =CONCATENATE('Смета 1-й этаж'!$C93,".",'Смета 1-й этаж'!$D93,".",'Смета 1-й этаж'!$E93) -> Р2.3.0 | B93: 70 | C93: Р2 | D93: 3 | E93: 0 | F93: =CONCATENATE('Смета 1-й этаж'!$C93,".",'Смета 1-й этаж'!$D93,".",'Смета 1-й этаж'!$E93) -> Р2.3.0 | G93: =IF(J93>0,G92+1,G92) -> 2 | H93: 2.3.0 Стены и перегородки | J93: =SUM(J94:J110) -> 0 | M93: =SUM(M94:M110) -> 0 | N93: =SUM(N94:N110) -> 0
A94: =CONCATENATE('Смета 1-й этаж'!$C94,".",'Смета 1-й этаж'!$D94,".",'Смета 1-й этаж'!$E94) -> Р2.3.1 | B94: 71 | C94: Р2 | D94: 3 | E94: 1 | F94: =CONCATENATE('Смета 1-й этаж'!$C94,".",'Смета 1-й этаж'!$D94,".",'Смета 1-й этаж'!$E94) -> Р2.3.1 | G94: =IF(J94>0,G93+1,G93) -> 2 | H94: Демонтаж кирпичных перегородок (в 1/2 кирпича) | I94: м2 | K94: 926 | L94: 0 | M94: =ROUND('Смета 1-й этаж'!$J94*'Смета 1-й этаж'!$K94,2) -> 0 | N94: =ROUND('Смета 1-й этаж'!$J94*'Смета 1-й этаж'!$L94,2) -> 0
A95: =CONCATENATE('Смета 1-й этаж'!$C95,".",'Смета 1-й этаж'!$D95,".",'Смета 1-й этаж'!$E95) -> Р2.3.2 | B95: 72 | C95: Р2 | D95: 3 | E95: 2 | F95: =CONCATENATE('Смета 1-й этаж'!$C95,".",'Смета 1-й этаж'!$D95,".",'Смета 1-й этаж'!$E95) -> Р2.3.2 | G95: =IF(J95>0,G94+1,G94) -> 2 | H95: Демонтаж кирпичных перегородок (в 1/2 кирпича) с армированием ( d16 яч. 150Х150) | I95: м2 | K95: 660.33 | L95: 0 | M95: =ROUND('Смета 1-й этаж'!$J95*'Смета 1-й этаж'!$K95,2) -> 0 | N95: =ROUND('Смета 1-й этаж'!$J95*'Смета 1-й этаж'!$L95,2) -> 0
A96: =CONCATENATE('Смета 1-й этаж'!$C96,".",'Смета 1-й этаж'!$D96,".",'Смета 1-й этаж'!$E96) -> Р2.3.3 | B96: 73 | C96: Р2 | D96: 3 | E96: 3 | F96: =CONCATENATE('Смета 1-й этаж'!$C96,".",'Смета 1-й этаж'!$D96,".",'Смета 1-й этаж'!$E96) -> Р2.3.3 | G96: =IF(J96>0,G95+1,G95) -> 2 | H96: Демонтаж кирпичных стен | I96: м3 | K96: 4566.66 | L96: 0 | M96: =ROUND('Смета 1-й этаж'!$J96*'Смета 1-й этаж'!$K96,2) -> 0 | N96: =ROUND('Смета 1-й этаж'!$J96*'Смета 1-й этаж'!$L96,2) -> 0
A97: =CONCATENATE('Смета 1-й этаж'!$C97,".",'Смета 1-й этаж'!$D97,".",'Смета 1-й этаж'!$E97) -> Р2.3.7 | B97: 74 | C97: Р2 | D97: 3 | E97: 7 | F97: =CONCATENATE('Смета 1-й этаж'!$C97,".",'Смета 1-й этаж'!$D97,".",'Смета 1-й этаж'!$E97) -> Р2.3.7 | G97: =IF(J97>0,G96+1,G96) -> 2 | H97: Демонтаж стен из пенобетонных блоков | I97: м3 | K97: 0 | L97: 0 | M97: =ROUND('Смета 1-й этаж'!$J97*'Смета 1-й этаж'!$K97,2) -> 0 | N97: =ROUND('Смета 1-й этаж'!$J97*'Смета 1-й этаж'!$L97,2) -> 0
A98: =CONCATENATE('Смета 1-й этаж'!$C98,".",'Смета 1-й этаж'!$D98,".",'Смета 1-й этаж'!$E98) -> Р2.3.8 | B98: 75 | C98: Р2 | D98: 3 | E98: 8 | F98: =CONCATENATE('Смета 1-й этаж'!$C98,".",'Смета 1-й этаж'!$D98,".",'Смета 1-й этаж'!$E98) -> Р2.3.8 | G98: =IF(J98>0,G97+1,G97) -> 2 | H98: Демонтаж утеплителя стен из минераловатных плит | I98: м2 | K98: 43.11 | L98: 0 | M98: =ROUND('Смета 1-й этаж'!$J98*'Смета 1-й этаж'!$K98,2) -> 0 | N98: =ROUND('Смета 1-й этаж'!$J98*'Смета 1-й этаж'!$L98,2) -> 0
A99: =CONCATENATE('Смета 1-й этаж'!$C99,".",'Смета 1-й этаж'!$D99,".",'Смета 1-й этаж'!$E99) -> Р2.3.9 | B99: 76 | C99: Р2 | D99: 3 | E99: 9 | F99: =CONCATENATE('Смета 1-й этаж'!$C99,".",'Смета 1-й этаж'!$D99,".",'Смета 1-й этаж'!$E99) -> Р2.3.9 | G99: =IF(J99>0,G98+1,G98) -> 2 | H99: Демонтаж утеплителя стен из пенополистирола | I99: м3 | K99: 0 | L99: 0 | M99: =ROUND('Смета 1-й этаж'!$J99*'Смета 1-й этаж'!$K99,2) -> 0 | N99: =ROUND('Смета 1-й этаж'!$J99*'Смета 1-й этаж'!$L99,2) -> 0
A100: =CONCATENATE('Смета 1-й этаж'!$C100,".",'Смета 1-й этаж'!$D100,".",'Смета 1-й этаж'!$E100) -> Р2.3.10 | B100: 77 | C100: Р2 | D100: 3 | E100: 10 | F100: =CONCATENATE('Смета 1-й этаж'!$C100,".",'Смета 1-й этаж'!$D100,".",'Смета 1-й этаж'!$E100) -> Р2.3.10 | G100: =IF(J100>0,G99+1,G99) -> 2 | H100: Демонтаж облицовки стен листами ГКЛ по металлическому каркасу | I100: м2 | K100: 78.88 | L100: 0 | M100: =ROUND('Смета 1-й этаж'!$J100*'Смета 1-й этаж'!$K100,2) -> 0 | N100: =ROUND('Смета 1-й этаж'!$J100*'Смета 1-й этаж'!$L100,2) -> 0
A101: =CONCATENATE('Смета 1-й этаж'!$C101,".",'Смета 1-й этаж'!$D101,".",'Смета 1-й этаж'!$E101) -> Р2.3.11 | B101: 78 | C101: Р2 | D101: 3 | E101: 11 | F101: =CONCATENATE('Смета 1-й этаж'!$C101,".",'Смета 1-й этаж'!$D101,".",'Смета 1-й этаж'!$E101) -> Р2.3.11 | G101: =IF(J101>0,G100+1,G100) -> 2 | H101: Демонтаж облицовки стен из МДФ панелей | I101: м2 | K101: 76.41 | L101: 0 | M101: =ROUND('Смета 1-й этаж'!$J101*'Смета 1-й этаж'!$K101,2) -> 0 | N101: =ROUND('Смета 1-й этаж'!$J101*'Смета 1-й этаж'!$L101,2) -> 0
A102: =CONCATENATE('Смета 1-й этаж'!$C102,".",'Смета 1-й этаж'!$D102,".",'Смета 1-й этаж'!$E102) -> Р2.3.12 | B102: 79 | C102: Р2 | D102: 3 | E102: 12 | F102: =CONCATENATE('Смета 1-й этаж'!$C102,".",'Смета 1-й этаж'!$D102,".",'Смета 1-й этаж'!$E102) -> Р2.3.12 | G102: =IF(J102>0,G101+1,G101) -> 2 | H102: Демонтаж каркасных деревянных перегородок с облицовкой панелями МДФ | I102: м2 | K102: 0 | L102: 0 | M102: =ROUND('Смета 1-й этаж'!$J102*'Смета 1-й этаж'!$K102,2) -> 0 | N102: =ROUND('Смета 1-й этаж'!$J102*'Смета 1-й этаж'!$L102,2) -> 0
A103: =CONCATENATE('Смета 1-й этаж'!$C103,".",'Смета 1-й этаж'!$D103,".",'Смета 1-й этаж'!$E103) -> Р2.3.13 | B103: 80 | C103: Р2 | D103: 3 | E103: 13 | F103: =CONCATENATE('Смета 1-й этаж'!$C103,".",'Смета 1-й этаж'!$D103,".",'Смета 1-й этаж'!$E103) -> Р2.3.13 | G103: =IF(J103>0,G102+1,G102) -> 2 | H103: Демонтаж перегородок по металлическому каркасу с облицовкой панелями МДФ | I103: м2 | K103: 144.65 | L103: 0 | M103: =ROUND('Смета 1-й этаж'!$J103*'Смета 1-й этаж'!$K103,2) -> 0 | N103: =ROUND('Смета 1-й этаж'!$J103*'Смета 1-й этаж'!$L103,2) -> 0
A104: =CONCATENATE('Смета 1-й этаж'!$C104,".",'Смета 1-й этаж'!$D104,".",'Смета 1-й этаж'!$E104) -> Р2.3.14 | B104: 81 | C104: Р2 | D104: 3 | E104: 14 | F104: =CONCATENATE('Смета 1-й этаж'!$C104,".",'Смета 1-й этаж'!$D104,".",'Смета 1-й этаж'!$E104) -> Р2.3.14 | G104: =IF(J104>0,G103+1,G103) -> 2 | H104: Отбивка штукатурки стен толщиной до 30 мм | I104: м2 | K104: 156.5 | L104: 0 | M104: =ROUND('Смета 1-й этаж'!$J104*'Смета 1-й этаж'!$K104,2) -> 0 | N104: =ROUND('Смета 1-й этаж'!$J104*'Смета 1-й этаж'!$L104,2) -> 0
A105: =CONCATENATE('Смета 1-й этаж'!$C105,".",'Смета 1-й этаж'!$D105,".",'Смета 1-й этаж'!$E105) -> Р2.3.15 | B105: 82 | C105: Р2 | D105: 3 | E105: 15 | F105: =CONCATENATE('Смета 1-й этаж'!$C105,".",'Смета 1-й этаж'!$D105,".",'Смета 1-й этаж'!$E105) -> Р2.3.15 | G105: =IF(J105>0,G104+1,G104) -> 2 | H105: Снятие обоев | I105: м2 | K105: 36.04 | L105: 0 | M105: =ROUND('Смета 1-й этаж'!$J105*'Смета 1-й этаж'!$K105,2) -> 0 | N105: =ROUND('Смета 1-й этаж'!$J105*'Смета 1-й этаж'!$L105,2) -> 0
... A110: =CONCATENATE('Смета 1-й этаж'!$C110,".",'Смета 1-й этаж'!$D110,".",'Смета 1-й этаж'!$E110) -> Р2.3.20 | B110: 87 | C110: Р2 | D110: 3 | E110: 20 | F110: =CONCATENATE('Смета 1-й этаж'!$C110,".",'Смета 1-й этаж'!$D110,".",'Смета 1-й этаж'!$E110) -> Р2.3.20 | G110: =IF(J110>0,G109+1,G109) -> 2 | H110: Разборка перегородок из ГКЛ по металлическому каркасу | I110: м2 | K110: 115.45 | L110: 0 | M110: =ROUND('Смета 1-й этаж'!$J110*'Смета 1-й этаж'!$K110,2) -> 0 | N110: =ROUND('Смета 1-й этаж'!$J110*'Смета 1-й этаж'!$L110,2) -> 0
A111: =CONCATENATE('Смета 1-й этаж'!$C111,".",'Смета 1-й этаж'!$D111,".",'Смета 1-й этаж'!$E111) -> Р2.4.0 | B111: 88 | C111: Р2 | D111: 4 | E111: 0 | F111: =CONCATENATE('Смета 1-й этаж'!$C111,".",'Смета 1-й этаж'!$D111,".",'Смета 1-й этаж'!$E111) -> Р2.4.0 | G111: =IF(J111>0,G110+1,G110) -> 2 | H111: 2.4.0 Двери | J111: =SUM(J112:J120) -> 0 | M111: =SUM(M112:M120) -> 0 | N111: =SUM(N112:N120) -> 0
...

Sheet Для калькулятора
H2: Общие расценки, зависят от площади офиса. Все значения должны округляться до целых чисел | O2: Коэффициенты зависимости от площади
A4: Р9.0.168 | B4: 801 | C4: Р9 | D4: 0 | E4: 168 | F4: Р9.0.168 | G4: 2 | H4: Светильник эвакуационный с аккумуляторной батареей | I4: шт | K4: 488.86 | L4: 1494.42 | M4: 0 | N4: 0 | O4: 0.025 | P4: 1 шт на 40 м кв площади офиса
A5: Р9.0.171 | B5: 804 | C5: Р9 | D5: 0 | E5: 171 | F5: Р9.0.171 | G5: 2 | H5: Гофрированная ПВХ труба ∅ 20 | I5: м.п. | K5: 68.91 | L5: 18.78 | M5: 0 | N5: 0 | O5: 15.39 | P5: 1 м.п. на 0,065 м кв площади офиса
A6: Р9.0.172 | B6: 805 | C6: Р9 | D6: 0 | E6: 172 | F6: Р9.0.172 | G6: 2 | H6: Гофрированная ПВХ труба ∅ 16 | I6: м.п. | K6: 68.91 | L6: 13.92 | M6: 0 | N6: 0 | O6: 28.57 | P6: 1 м.п. на 0,035 м кв площади офиса
A7: Р9.0.176 | B7: 810 | C7: Р9 | D7: 0 | E7: 176 | F7: Р9.0.176 | G7: 2 | H7: Кабель-канал 105х50 мм. | I7: м.п. | K7: 101.23 | L7: 336.01 | M7: 0 | N7: 0 | O7: 0.066 | P7: 1 м.п. на 15 м кв площади офиса
A8: Р9.0.177 | B8: 811 | C8: Р9 | D8: 0 | E8: 177 | F8: Р9.0.177 | G8: 2 | H8: Лоток металлический перфорированный с фасонными частями, крепежом 200*50 | I8: м.п. | K8: 174.99 | L8: 351.64 | M8: 0 | N8: 0 | O8: 0.1 | P8: 1 м.п. на 10 м кв площади офиса
A9: Р9.0.178 | B9: 812 | C9: Р9 | D9: 0 | E9: 178 | F9: Р9.0.178 | G9: 2 | H9: Зажим 773-302 безвинтовой 6х (0,75-2,5) кв. мм для меди и алюминия (Wago) | I9: шт | K9: 8.66 | L9: 15.39 | M9: 0 | N9: 0 | O9: 1 | P9: 1 шт на 1 м кв площади офиса
A10: Р9.0.179 | B10: 813 | C10: Р9 | D10: 0 | E10: 179 | F10: Р9.0.179 | G10: 2 | H10: Зажим 773-302 безвинтовой 2х (0,75-2,5) кв. мм для меди и алюминия (Wago) | I10: шт | K10: 4.74 | L10: 7.56 | M10: 0 | N10: 0 | O10: 1 | P10: 1 шт на 1 м кв площади офиса
A11: Р9.0.206 | B11: 840 | C11: Р9 | D11: 0 | E11: 206 | F11: Р9.0.206 | G11: 2 | H11: Светильник с люминесцентными лампами встраиваемый PRBLUX -600х600(касса) | I11: шт | K11: 486.25 | L11: 2772.5 | M11: 0 | N11: 0 | O11: 2 шт на офис | P11: 2 шт на офис
A12: Р9.0.207 | B12: 841 | C12: Р9 | D12: 0 | E12: 207 | F12: Р9.0.207 | G12: 2 | H12: Светильник противопожарный с люминесцентными лампами встраиваемый стекло матовое 600х600(серверная) | I12: шт | K12: 410.87 | L12: 4301.26 | M12: 0 | N12: 0 | O12: 2 шт на офис | P12: 2 шт на офис
A13: Р9.0.210 | B13: 844 | C13: Р9 | D13: 0 | E13: 210 | F13: Р9.0.210 | G13: 2 | H13: Пуско-наладочные работы | I13: к-т | K13: 10598.55 | L13: 1118.63 | M13: 0 | N13: 0 | O13: 1 шт на офис | P13: 1 шт на офис
A14: Р9.0.211 | B14: 845 | C14: Р9 | D14: 0 | E14: 211 | F14: Р9.0.211 | G14: 2 | H14: Расходные и крепежные материалы | I14: к-т | K14: 0 | L14: 13608.89 | M14: 0 | N14: 0 | O14: 1 шт на офис | P14: 1 шт на офис
A15: Р9.0.214 | B15: 848 | C15: Р9 | D15: 0 | E15: 214 | F15: Р9.0.214 | G15: 2 | H15: Блок аварийного питания INTERLUX ES-1 ( 6-58Ц) | I15: шт | K15: 184.87 | L15: 3256.59 | M15: 0 | N15: 0 | O15: 0.05 | P15: 1 шт на 20 м кв площади офиса
A16: Р9.0.217 | B16: 851 | C16: Р9 | D16: 0 | E16: 217 | F16: Р9.0.217 | G16: 2 | H16: Распред коробка legrand | I16: шт | K16: 88.48 | L16: 204.67 | M16: 0 | N16: 0 | O16: 0.5 | P16: 1 шт на 2 м кв площади офиса
A17: Р9.0.219 | B17: 854 | C17: Р9 | D17: 0 | E17: 219 | F17: Р9.0.219 | G17: 2 | H17: Установка светильника 94 836 NDL-P1-10W-840-WH-LED (аналог R80 100Вт) Navigator 4607136948365 | I17: шт | K17: 590 | L17: 900 | M17: 0 | N17: 0 | O17: 0.2 | P17: 1 шт на 5 м кв площади офиса
A18: Р9.0.246 | B18: 876 | C18: Р9 | D18: 0 | E18: 246 | F18: Р9.0.246 | G18: 2 | H18: Обработка проходов кабелей через перегородки огнезой с 2 сторон | I18: шт | K18: 150 | L18: 350 | M18: 0 | N18: 0 | O18: 0.066 | P18: 1 шт на 15 м кв площади офиса
A19: Р9.0.261 | B19: 853 | C19: Р9 | D19: 0 | E19: 261 | F19: Р9.0.261 | G19: 2 | H19: Светильник светодиодный 18 Вт, Navigator 71 761 NLP-R1-18W-R220-840-WH-LED | I19: шт | K19: 600 | L19: 1350 | M19: 0 | N19: 0 | O19: 0.29 | P19: 1 шт на 3,5 м кв площади офиса
A20: Р9.0.262 | B20: 855 | C20: Р9 | D20: 0 | E20: 262 | F20: Р9.0.262 | G20: 2 | H20: Светильник светодиодный 5 Вт IP44, Navigator 71 366 NDL-P2-5W-830-CH-LED | I20: шт | K20: 500 | L20: 800 | M20: 0 | N20: 0 | O20: 0.033 | P20: 1 шт на 30 м кв площади офиса
A21: Р9.0.231 | B21: 867 | C21: Р9 | D21: 0 | E21: 231 | F21: Р9.0.231 | G21: 2 | H21: Кабель ППГнг(А)-HF 3х2,5 | I21: м.п. | K21: 36.28 | L21: 57.73 | M21: 0 | N21: 0 | O21: 5,5 если площадь офиса больше 300 м кв | P21: 1 м.п. на 0,18 м кв площади офиса
A22: Р9.0.232 | B22: 868 | C22: Р9 | D22: 0 | E22: 232 | F22: Р9.0.232 | G22: 2 | H22: Кабель ППГнг(А)-HF 3x1,5 | I22: м.п. | K22: 36.28 | L22: 41.51 | M22: 0 | N22: 0 | O22: 3,8 если площадь офиса больше 300 м кв | P22: 1 м.п. на 0,26 м кв площади офиса
A23: Р9.0.228 | B23: 864 | C23: Р9 | D23: 0 | E23: 228 | F23: Р9.0.228 | G23: 2 | H23: Кабель ППГнг(А)-HF 5х2,5 | I23: м.п. | K23: 94.04 | L23: 92.48 | M23: 0 | N23: 0 | O23: 0,066 если площадь офиса больше 300 м кв | P23: 1 м.п. на 15 м кв площади офиса
A24: Р9.0.226 | B24: 862 | C24: Р9 | D24: 0 | E24: 226 | F24: Р9.0.226 | G24: 2 | H24: Кабель ППГнг(А)-HF 5х6 | I24: м.п. | K24: 94.04 | L24: 199.29 | M24: 0 | N24: 0 | O24: 0,025 если площадь офиса больше 300 м кв | P24: 1 м.п. на 40 м кв площади офиса
A25: Р9.0.182 | B25: 816 | C25: Р9 | D25: 0 | E25: 182 | F25: Р9.0.182 | G25: 2 | H25: Кабель ВВГнг-LS 5х6 | I25: м.п. | K25: 94.04 | L25: 194.81 | M25: 0 | N25: 0 | O25: 0,025 если площадь офиса меньше 300 м кв | P25: 1 м.п. на 40 м кв площади офиса
A26: Р9.0.184 | B26: 818 | C26: Р9 | D26: 0 | E26: 184 | F26: Р9.0.184 | G26: 2 | H26: Кабель ВВГнг-LS 5х2,5 | I26: м.п. | K26: 117.69 | L26: 85.02 | M26: 0 | N26: 0 | O26: 0,066 если площадь офиса меньше 300 м кв | P26: 1 м.п. на 15 м кв площади офиса
A27: Р9.0.188 | B27: 822 | C27: Р9 | D27: 0 | E27: 188 | F27: Р9.0.188 | G27: 2 | H27: Кабель ВВГнг-LS 3х2,5 | I27: м.п. | K27: 36.28 | L27: 41.85 | M27: 0 | N27: 0 | O27: 5,5 если площадь офиса меньше 300 м кв | P27: 1 м.п. на 0,18 м кв площади офиса
A28: Р9.0.189 | B28: 823 | C28: Р9 | D28: 0 | E28: 189 | F28: Р9.0.189 | G28: 2 | H28: Кабель ВВГнг-LS 3х1,5 | I28: м.п. | K28: 36.28 | L28: 33.05 | M28: 0 | N28: 0 | O28: 3,8 если площадь офиса меньше 300 м кв | P28: 1 м.п. на 0,26 м кв площади офиса
A29: Р9.0.263 | B29: 870 | C29: Р9 | D29: 0 | E29: 263 | F29: Р9.0.263 | G29: 2 | H29: Кабель ППГнг(А)-FRHF 3х1,5 | I29: м.п. | K29: 36.28 | L29: 66.27 | M29: 0 | N29: 0 | O29: 0.5 | P29: 1 м.п. на 2 м кв площади офиса
A30: Р9.0.195 | B30: 829 | C30: Р9 | D30: 0 | E30: 195 | F30: Р9.0.195 | G30: 2 | H30: Провод ПВ1 1х6 (красный/голубой/желтый/зеленый/желто-зеленый) | I30: м.п. | K30: 30.38 | L30: 35.74 | M30: 0 | N30: 0 | O30: 0.05 | P30: 1 м.п. на 20 м кв площади офиса
A31: Р9.0.196 | B31: 830 | C31: Р9 | D31: 0 | E31: 196 | F31: Р9.0.196 | G31: 2 | H31: Провод ПВ1 1х2,5 (красный/голубой/желтый/зеленый/желто-зеленый) | I31: м.п. | K31: 31.57 | L31: 22.81 | M31: 0 | N31: 0 | O31: 0.1 | P31: 1 м.п. на 10 м кв площади офиса
H35: Нижеследующие расценки разделены на три блока. Выбор блока будет зависеть от электрической мощности выделенной на объект и вводного автомата. К каждому из 3-х блоков возможно ПО два добавления (дабавления разные и зависят от номера блока): в ячейке должен быть вопрос "На объекте будет АВР?" и два варианта ответа да или нет. При ответе да добавляются несколько позиций. В другой ячейке должен быть вопрос "На объекте будет ИБП?" и два варианта ответа да или нет. При ответе да добавляется одна позиция.
H37: Если электрическая мощность меньше, либо равна 33 кВт или вводной автомат меньше либо равен 63А, то 1 блок. IF P<=33 and I<=63 THEN "блок 1"
A39: Р9.0.3 | B39: 627 | C39: Р9 | D39: 0 | E39: 3 | F39: Р9.0.3 | G39: 2 | H39: Щит 72 модулей, IP43, ABB или Legrand, с замком в комплекте с DIN-рейками, перемычками, шинами РЕ и N | I39: шт | J39: 1 | K39: 3289.97 | L39: 14122.98 | M39: 0 | N39: 0
A40: Р9.0.6 | B40: 625 | C40: Р9 | D40: 0 | E40: 6 | F40: Р9.0.6 | G40: 2 | H40: Щит 48 модулей, IP43, ABB или Legrand, с замком в комплекте с DIN-рейками, перемычками, шинами РЕ и N | I40: шт | J40: 3 | K40: 2726.23 | L40: 12171.03 | M40: 0 | N40: 0
A41: Р9.0.7 | B41: 624 | C41: Р9 | D41: 0 | E41: 7 | F41: Р9.0.7 | G41: 2 | H41: Щит 36 модулей, IP43, ABB или Legrand, с замком в комплекте с DIN-рейками, перемычками, шинами РЕ и N | I41: шт | J41: 1 | K41: 2508.08 | L41: 10421.19 | M41: 0 | N41: 0
A42: Р9.0.250 | B42: 622 | C42: Р9 | D42: 0 | E42: 250 | F42: Р9.0.250 | G42: 2 | H42: Щит 12 модулей, IP43, ABB или Legrand, с замком в комплекте с DIN-рейками, перемычками, шинами РЕ и N | I42: шт | J42: 1 | K42: 1800 | L42: 2674 | M42: 0 | N42: 0
A43: Р9.0.245 | B43: 630 | C43: Р9 | D43: 0 | E43: 245 | F43: Р9.0.245 | G43: 2 | H43: Щит ППУ 8-12 мод IP 65 красный металлический | I43: шт | J43: 1 | K43: 1500 | L43: 14600 | M43: 0 | N43: 0
A44: Р9.0.9 | B44: 638 | C44: Р9 | D44: 0 | E44: 9 | F44: Р9.0.9 | G44: 2 | H44: Счетчик электроэнергии, Меркурий 231 АТ 01 (двухтарифный, 3-х фазный, 63А) | I44: шт | J44: 1 | K44: 1856.03 | L44: 3917.46 | M44: 0 | N44: 0
A45: Р9.0.265 | B45: 728 | C45: Р9 | D45: 0 | E45: 265 | F45: Р9.0.265 | G45: 2 | H45: Автомат.выкл-ль АВВ 3-полюсный S203 C63А | I45: шт | J45: 1 | K45: 343.33 | L45: 2100 | M45: 0 | N45: 0
A46: Р9.0.95 | B46: 726 | C46: Р9 | D46: 0 | E46: 95 | F46: Р9.0.95 | G46: 2 | H46: Автомат.выкл-ль АВВ 3-полюсный S203 C40А | I46: шт | J46: 1 | K46: 343.33 | L46: 2094.97 | M46: 0 | N46: 0
A47: Р9.0.94 | B47: 725 | C47: Р9 | D47: 0 | E47: 94 | F47: Р9.0.94 | G47: 2 | H47: Автомат.выкл-ль АВВ 3-полюсный S203 C32А | I47: шт | J47: 4 | K47: 343.33 | L47: 1918.87 | M47: 0 | N47: 0
A48: Р9.0.93 | B48: 724 | C48: Р9 | D48: 0 | E48: 93 | F48: Р9.0.93 | G48: 2 | H48: Автомат.выкл-ль АВВ 3-полюсный S203 C25А | I48: шт | J48: 3 | K48: 233.93 | L48: 659.87 | M48: 0 | N48: 0
A49: Р9.0.91 | B49: 722 | C49: Р9 | D49: 0 | E49: 91 | F49: Р9.0.91 | G49: 2 | H49: Автомат.выкл-ль АВВ 3-полюсный S203 C16А | I49: шт | J49: 1 | K49: 233.93 | L49: 514.62 | M49: 0 | N49: 0
A50: Р9.0.47 | B50: 678 | C50: Р9 | D50: 0 | E50: 47 | F50: Р9.0.47 | G50: 2 | H50: Автомат.выкл-ль АВВ 1-полюсный S201 C25А | I50: шт | J50: 2 | K50: 122.6 | L50: 423.43 | M50: 0 | N50: 0
... A60: Р9.0.158 | B60: 798 | C60: Р9 | D60: 0 | E60: 158 | F60: Р9.0.158 | G60: 2 | H60: Электромеханический недельный таймер ABB | I60: шт | J60: 1 | K60: 525 | L60: 6431.87 | M60: 0 | N60: 0
H63: Если стоит "да" при ответе на вопрос "На объекте будет АВР?", то в блок 1 добавляются следующие позиции
A64: Р9.0.252 | B64: 631 | C64: Р9 | D64: 0 | E64: 252 | F64: Р9.0.252 | G64: 2 | H64: Автоматический ввод резерва 63А, 380В в сборе | I64: шт | J64: 1 | K64: 2500 | L64: 35000 | M64: 0 | N64: 0
A65: Р9.0.9 | B65: 638 | C65: Р9 | D65: 0 | E65: 9 | F65: Р9.0.9 | G65: 2 | H65: Счетчик электроэнергии, Меркурий 231 АТ 01 (двухтарифный, 3-х фазный, 63А) | I65: шт | J65: 1 | K65: 1856.03 | L65: 3917.46 | M65: 0 | N65: 0
A66: Р9.0.265 | B66: 728 | C66: Р9 | D66: 0 | E66: 265 | F66: Р9.0.265 | G66: 2 | H66: Автомат.выкл-ль АВВ 3-полюсный S203 C63А | I66: шт | J66: 1 | K66: 343.33 | L66: 2100 | M66: 0 | N66: 0
H68: Если стоит "да" при ответе на вопрос "На объекте будет ИБП?", то в блок 1 добавляются следующие позиции
A69: Р9.0.256 | B69: 636 | C69: Р9 | D69: 0 | E69: 256 | F69: Р9.0.256 | G69: 2 | H69: Выключатель нагрузки OT63E3, 63А, ABB | I69: шт | J69: 3 | K69: 984.23 | L69: 1600 | M69: 0 | N69: 0
H72: Если электрическая мощность больше 33 кВт но меньше, либо равна 40 кВт или вводной трехполюсный автомат больше 63 А но меньше либо равен 80А, то 2 блок. IF 33<P<=40 and 63<I<=80 THEN "блок 2"
A73: Р9.0.3 | B73: 627 | C73: Р9 | D73: 0 | E73: 3 | F73: Р9.0.3 | G73: 2 | H73: Щит 72 модулей, IP43, ABB или Legrand, с замком в комплекте с DIN-рейками, перемычками, шинами РЕ и N | I73: шт | J73: 1 | K73: 3289.97 | L73: 14122.98 | M73: 0 | N73: 0
A74: Р9.0.6 | B74: 625 | C74: Р9 | D74: 0 | E74: 6 | F74: Р9.0.6 | G74: 2 | H74: Щит 48 модулей, IP43, ABB или Legrand, с замком в комплекте с DIN-рейками, перемычками, шинами РЕ и N | I74: шт | J74: 3 | K74: 2726.23 | L74: 12171.03 | M74: 0 | N74: 0
A75: Р9.0.7 | B75: 624 | C75: Р9 | D75: 0 | E75: 7 | F75: Р9.0.7 | G75: 2 | H75: Щит 36 модулей, IP43, ABB или Legrand, с замком в комплекте с DIN-рейками, перемычками, шинами РЕ и N | I75: шт | J75: 1 | K75: 2508.08 | L75: 10421.19 | M75: 0 | N75: 0
A76: Р9.0.250 | B76: 622 | C76: Р9 | D76: 0 | E76: 250 | F76: Р9.0.250 | G76: 2 | H76: Щит 12 модулей, IP43, ABB или Legrand, с замком в комплекте с DIN-рейками, перемычками, шинами РЕ и N | I76: шт | J76: 1 | K76: 1800 | L76: 2674 | M76: 0 | N76: 0
A77: Р9.0.245 | B77: 630 | C77: Р9 | D77: 0 | E77: 245 | F77: Р9.0.245 | G77: 2 | H77: Щит ППУ 8-12 мод IP 65 красный металлический | I77: шт | J77: 1 | K77: 1500 | L77: 14600 | M77: 0 | N77: 0
A78: Р9.0.259 | B78: 640 | C78: Р9 | D78: 0 | E78: 259 | F78: Р9.0.259 | G78: 2 | H78: Счетчик электроэнергии, Меркурий 230 ART-02 CN (многотарифный, 3-х фазный, 100А) | I78: шт | J78: 1 | K78: 1856.03 | L78: 6000 | M78: 0 | N78: 0
A79: Р9.0.264 | B79: 749 | C79: Р9 | D79: 0 | E79: 264 | F79: Р9.0.264 | G79: 2 | H79: Автомат.выкл-ль АВВ Т1В160 80А | I79: шт | J79: 1 | K79: 350 | L79: 8500 | M79: 0 | N79: 0
A80: Р9.0.243 | B80: 751 | C80: Р9 | D80: 0 | E80: 243 | F80: Р9.0.243 | G80: 2 | H80: Монтажная площадка для Т1В 160 | I80: шт | J80: 1 | K80: 350 | L80: 785 | M80: 0 | N80: 0
A81: Р9.0.96 | B81: 727 | C81: Р9 | D81: 0 | E81: 96 | F81: Р9.0.96 | G81: 2 | H81: Автомат.выкл-ль АВВ 3-полюсный S203 C50А | I81: шт | J81: 1 | K81: 343.33 | L81: 2620.1 | M81: 0 | N81: 0
A82: Р9.0.95 | B82: 726 | C82: Р9 | D82: 0 | E82: 95 | F82: Р9.0.95 | G82: 2 | H82: Автомат.выкл-ль АВВ 3-полюсный S203 C40А | I82: шт | J82: 1 | K82: 343.33 | L82: 2094.97 | M82: 0 | N82: 0
A83: Р9.0.94 | B83: 725 | C83: Р9 | D83: 0 | E83: 94 | F83: Р9.0.94 | G83: 2 | H83: Автомат.выкл-ль АВВ 3-полюсный S203 C32А | I83: шт | J83: 3 | K83: 343.33 | L83: 1918.87 | M83: 0 | N83: 0
A84: Р9.0.93 | B84: 724 | C84: Р9 | D84: 0 | E84: 93 | F84: Р9.0.93 | G84: 2 | H84: Автомат.выкл-ль АВВ 3-полюсный S203 C25А | I84: шт | J84: 3 | K84: 233.93 | L84: 659.87 | M84: 0 | N84: 0
... A98: Р9.0.158 | B98: 798 | C98: Р9 | D98: 0 | E98: 158 | F98: Р9.0.158 | G98: 2 | H98: Электромеханический недельный таймер ABB | I98: шт | J98: 1 | K98: 525 | L98: 6431.87 | M98: 0 | N98: 0
H100: Если стоит "да" при ответе на вопрос "На объекте будет АВР?", то в блок 2 добавляются следующие позиции
A101: Р9.0.253 | B101: 632 | C101: Р9 | D101: 0 | E101: 253 | F101: Р9.0.253 | G101: 2 | H101: Автоматический ввод резерва 80А, 380В в сборе | I101: шт | J101: 1 | K101: 2500 | L101: 60000 | M101: 0 | N101: 0
A102: Р9.0.259 | B102: 640 | C102: Р9 | D102: 0 | E102: 259 | F102: Р9.0.259 | G102: 2 | H102: Счетчик электроэнергии, Меркурий 230 ART-02 CN (многотарифный, 3-х фазный, 100А) | I102: шт | J102: 1 | K102: 1856.03 | L102: 6000 | M102: 0 | N102: 0
A103: Р9.0.264 | B103: 749 | C103: Р9 | D103: 0 | E103: 264 | F103: Р9.0.264 | G103: 2 | H103: Автомат.выкл-ль АВВ Т1В160 80А | I103: шт | J103: 1 | K103: 350 | L103: 8500 | M103: 0 | N103: 0
A104: Р9.0.243 | B104: 751 | C104: Р9 | D104: 0 | E104: 243 | F104: Р9.0.243 | G104: 2 | H104: Монтажная площадка для Т1В 160 | I104: шт | J104: 1 | K104: 350 | L104: 785 | M104: 0 | N104: 0
H106: Если стоит "да" при ответе на вопрос "На объекте будет ИБП?", то в блок 2 добавляются следующие позиции
A107: Р9.0.256 | B107: 636 | C107: Р9 | D107: 0 | E107: 256 | F107: Р9.0.256 | G107: 2 | H107: Выключатель нагрузки OT63E3, 63А, ABB | I107: шт | J107: 3 | K107: 984.23 | L107: 1600 | M107: 0 | N107: 0
H110: Если электрическая мощность больше 40 кВт но меньше, либо равна 60 кВт или вводной трехполюсный автомат больше 80А но меньше либо равен 125А, то 3 блок. IF 40<P<=60 and 80<I<=125 THEN "блок 3"
A112: Р9.0.2 | B112: 628 | C112: Р9 | D112: 0 | E112: 2 | F112: Р9.0.2 | G112: 2 | H112: Щит 96 модулей, IP43, ABB или Legrand, с замком в комплекте с DIN-рейками, перемычками, шинами РЕ и N | I112: шт | J112: 1000 | K112: 2883.31 | L112: 16946.98 | M112: 0 | N112: 0
A113: Р9.0.4 | B113: 626 | C113: Р9 | D113: 0 | E113: 4 | F113: Р9.0.4 | G113: 2 | H113: Щит 54 модулей, IP43, ABB или Legrand, с замком в комплекте с DIN-рейками, перемычками, шинами РЕ и N | I113: шт | J113: 2 | K113: 2962.5 | L113: 8172.34 | M113: 0 | N113: 0
A114: Р9.0.6 | B114: 625 | C114: Р9 | D114: 0 | E114: 6 | F114: Р9.0.6 | G114: 2 | H114: Щит 48 модулей, IP43, ABB или Legrand, с замком в комплекте с DIN-рейками, перемычками, шинами РЕ и N | I114: шт | J114: 1 | K114: 2726.23 | L114: 12171.03 | M114: 0 | N114: 0
A115: Р9.0.7 | B115: 624 | C115: Р9 | D115: 0 | E115: 7 | F115: Р9.0.7 | G115: 2 | H115: Щит 36 модулей, IP43, ABB или Legrand, с замком в комплекте с DIN-рейками, перемычками, шинами РЕ и N | I115: шт | J115: 1 | K115: 2508.08 | L115: 10421.19 | M115: 0 | N115: 0
A116: Р9.0.251 | B116: 623 | C116: Р9 | D116: 0 | E116: 251 | F116: Р9.0.251 | G116: 2 | H116: Щит 18 модулей, IP43, ABB или Legrand, с замком в комплекте с DIN-рейками, перемычками, шинами РЕ и N | I116: шт | J116: 1 | K116: 2000 | L116: 3148 | M116: 0 | N116: 0
A117: Р9.0.245 | B117: 630 | C117: Р9 | D117: 0 | E117: 245 | F117: Р9.0.245 | G117: 2 | H117: Щит ППУ 8-12 мод IP 65 красный металлический | I117: шт | J117: 1 | K117: 1500 | L117: 14600 | M117: 0 | N117: 0
A118: Р9.0.258 | B118: 639 | C118: Р9 | D118: 0 | E118: 258 | F118: Р9.0.258 | G118: 2 | H118: Счетчик электроэнергии, Меркурий 231 АТ 01 с трансформаторами тока (двухтарифный, 3-х фазный, 63А) | I118: шт | J118: 1 | K118: 3000 | L118: 6000 | M118: 0 | N118: 0
H119: Автомат.выкл-ль АВВ Т1В160 125А | I119: шт | J119: 1 | K119: 350 | L119: 12100 | M119: 0 | N119: 0 | P119: добавить позицию
A120: Р9.0.243 | B120: 751 | C120: Р9 | D120: 0 | E120: 243 | F120: Р9.0.243 | G120: 2 | H120: Монтажная площадка для Т1В 160 | I120: шт | J120: 1 | K120: 350 | L120: 785 | M120: 0 | N120: 0
A121: Р9.0.96 | B121: 727 | C121: Р9 | D121: 0 | E121: 96 | F121: Р9.0.96 | G121: 2 | H121: Автомат.выкл-ль АВВ 3-полюсный S203 C50А | I121: шт | J121: 2 | K121: 343.33 | L121: 2620.1 | M121: 0 | N121: 0
A122: Р9.0.95 | B122: 726 | C122: Р9 | D122: 0 | E122: 95 | F122: Р9.0.95 | G122: 2 | H122: Автомат.выкл-ль АВВ 3-полюсный S203 C40А | I122: шт | J122: 1 | K122: 343.33 | L122: 2094.97 | M122: 0 | N122: 0
A123: Р9.0.94 | B123: 725 | C123: Р9 | D123: 0 | E123: 94 | F123: Р9.0.94 | G123: 2 | H123: Автомат.выкл-ль АВВ 3-полюсный S203 C32А | I123: шт | J123: 2 | K123: 343.33 | L123: 1918.87 | M123: 0 | N123: 0
A124: Р9.0.91 | B124: 722 | C124: Р9 | D124: 0 | E124: 91 | F124: Р9.0.91 | G124: 2 | H124: Автомат.выкл-ль АВВ 3-полюсный S203 C16А | I124: шт | J124: 8 | K124: 233.93 | L124: 514.62 | M124: 0 | N124: 0
A125: Р9.0.47 | B125: 678 | C125: Р9 | D125: 0 | E125: 47 | F125: Р9.0.47 | G125: 2 | H125: Автомат.выкл-ль АВВ 1-полюсный S201 C25А | I125: шт | J125: 2 | K125: 122.6 | L125: 423.43 | M125: 0 | N125: 0
A126: Р9.0.46 | B126: 677 | C126: Р9 | D126: 0 | E126: 46 | F126: Р9.0.46 | G126: 2 | H126: Автомат.выкл-ль АВВ 1-полюсный S201 C20А | I126: шт | J126: 6 | K126: 159.71 | L126: 363.98 | M126: 0 | N126: 0
A127: Р9.0.45 | B127: 676 | C127: Р9 | D127: 0 | E127: 45 | F127: Р9.0.45 | G127: 2 | H127: Автомат.выкл-ль АВВ 1-полюсный S201 C16А | I127: шт | J127: 8 | K127: 159.71 | L127: 333.48 | M127: 0 | N127: 0
A128: Р9.0.44 | B128: 675 | C128: Р9 | D128: 0 | E128: 44 | F128: Р9.0.44 | G128: 2 | H128: Автомат.выкл-ль АВВ 1-полюсный S201 C10А | I128: шт | J128: 15 | K128: 171.34 | L128: 260.24 | M128: 0 | N128: 0
A129: Р9.0.43 | B129: 674 | C129: Р9 | D129: 0 | E129: 43 | F129: Р9.0.43 | G129: 2 | H129: Автомат.выкл-ль АВВ 1-полюсный S201 C6А | I129: шт | J129: 8 | K129: 159.71 | L129: 267.39 | M129: 0 | N129: 0
A130: Р9.0.128 | B130: 767 | C130: Р9 | D130: 0 | E130: 128 | F130: Р9.0.128 | G130: 2 | H130: Дифференциальный автомат АВВ DSH941R 1P+N 16A (C) 4,5kA тип AC 30mA (2мод.) | I130: шт | J130: 30 | K130: 333.22 | L130: 2158.27 | M130: 0 | N130: 0
A131: Р9.0.260 | B131: 788 | C131: Р9 | D131: 0 | E131: 260 | F131: Р9.0.260 | G131: 2 | H131: Контактор модульный ABB ESB63-40 | I131: шт | J131: 3 | K131: 400 | L131: 3800 | M131: 0 | N131: 0
... A138: Р9.0.158 | B138: 798 | C138: Р9 | D138: 0 | E138: 158 | F138: Р9.0.158 | G138: 2 | H138: Электромеханический недельный таймер ABB | I138: шт | J138: 1 | K138: 525 | L138: 6431.87 | M138: 0 | N138: 0
H141: Если стоит "да" при ответе на вопрос "На объекте будет АВР?", то в блок 3 добавляются следующие позиции
A142: Р9.0.254 | B142: 633 | C142: Р9 | D142: 0 | E142: 254 | F142: Р9.0.254 | G142: 2 | H142: Автоматический ввод резерва 125А, 380В в сборе | I142: шт | J142: 1 | K142: 2500 | L142: 90000 | M142: 0 | N142: 0
H143: Автомат.выкл-ль АВВ Т1В160 125А | I143: шт | J143: 1 | K143: 350 | L143: 12100 | M143: 0 | N143: 0 | P143: добавить позицию
A144: Р9.0.243 | B144: 751 | C144: Р9 | D144: 0 | E144: 243 | F144: Р9.0.243 | G144: 2 | H144: Монтажная площадка для Т1В 160 | I144: шт | J144: 1 | K144: 350 | L144: 785 | M144: 0 | N144: 0
A145: Р9.0.258 | B145: 639 | C145: Р9 | D145: 0 | E145: 258 | F145: Р9.0.258 | G145: 2 | H145: Счетчик электроэнергии, Меркурий 231 АТ 01 с трансформаторами тока (двухтарифный, 3-х фазный, 63А) | I145: шт | J145: 1 | K145: 3000 | L145: 6000 | M145: 0 | N145: 0
H148: Если стоит "да" при ответе на вопрос "На объекте будет ИБП?", то в блок 3 добавляются следующие позиции
A149: Р9.0.256 | B149: 636 | C149: Р9 | D149: 0 | E149: 256 | F149: Р9.0.256 | G149: 2 | H149: Выключатель нагрузки OT63E3, 63А, ABB | I149: шт | J149: 3 | K149: 984.23 | L149: 1600 | M149: 0 | N149: 0

Sheet Кондиционеры
B1: Тип | C1: Инвертор | D1: Мощность охлаждения, кВт | E1: Шум, не более, Дб | F1: Макс. длина трубопровода, м | G1: Кол-во внутр. блоков | H1: Доп. требования | I1: ООО "Хайер Электрикал Эпплаенсис РУС" | L1: Дженерал-Трейд (АЯК) - оборудование MDV (GD Midea)
I2: Модель | J2: Цена для Подрядчика Альфа-Банка с НДС, в USD | K2: Цена для Альфа-Банка с НДС, в USD | L2: Модель | M2: Цена для Подрядчика Альфа-Банка с НДС, в USD | N2: Цена для Альфа-Банка с НДС, в USD
A5: 1 | B5: Настенный 7 | C5: нет | D5: 2,0 - 2,3 | E5: 40 | H5: включая пульт | I5: HSU-07HT103/R2/HSU-07HUN203/R2 | J5: 157 | K5: =J5*1.1 -> 172.7 | L5: MDSF-07HRN1/MDOF-07HN1 | M5: 175.78 | N5: =M5*1.1 -> 193.358
A6: 2 | B6: Настенный 9 | C6: нет | D6: 2,5 - 2,8 | E6: 40 | H6: включая пульт | I6: HSU-09HT203/R2/HSU-09HUN103/R2 | J6: 168 | K6: =J6*1.1 -> 184.8 | L6: MDSF-09HRN1/MDOF-09HN1 | M6: 183.3 | N6: =M6*1.1 -> 201.63
A7: 3 | B7: Настенный 12 | C7: нет | D7: 3,2 - 3,6 | E7: 42 | H7: включая пульт | I7: HSU-12HT203/R2/HSU-12HUN103/R2 | J7: 216 | K7: =J7*1.1 -> 237.6 | L7: MDSF-12HRN1/MDOF-12HN1 | M7: 244.87 | N7: =M7*1.1 -> 269.357 | O7: =N7*70 -> 18854.99
A8: 4 | B8: Настенный 18 | C8: нет | D8: 4,8 - 5,4 | E8: 45 | H8: включая пульт | I8: HSU-18HT203/R2/HSU-18HUN103/R2 | J8: 330 | K8: =J8*1.1 -> 363 | L8: MDSF-18HRN1/MDOF-18HN1 | M8: 374.12 | N8: =M8*1.1 -> 411.532 | O8: =N8*70 -> 28807.24
A9: 5 | B9: Настенный 24 | C9: нет | D9: 6,1 - 7,1 | E9: 49 | H9: включая пульт | I9: HSU-24HT203/R2/HSU-24HUN103/R2 | J9: 438 | K9: =J9*1.1 -> 481.8 | L9: MDSF-24HRN1/MDOF-24HN1 | M9: 490.68 | N9: =M9*1.1 -> 539.748
A10: 6 | B10: Кассетный 12 | C10: нет | D10: 3,3 - 3,7 | E10: 38 | H10: включая пульт | I10: AB18CS1ERA(S)/1U18DS1EAA/PB-700IB | J10: 543 | K10: =J10*1.1 -> 597.3 | L10: MDCA3-12HN1/MDOU-12HN1/T-MBQ4-03B4 | M10: 547.68 | N10: =M10*1.1 -> 602.448
A11: 7 | B11: Кассетный 18 | C11: нет | D11: 4,6 - 5,4 | E11: 49 | H11: включая пульт | I11: AB18CS1ERA(S)/1U18DS1EAA/PB-700IB | J11: 543 | K11: =J11*1.1 -> 597.3 | L11: MDCA3-18HN1/MDOU-18HN1/T-MBQ4-03B4 | M11: 623.04 | N11: =M11*1.1 -> 685.344
A12: 8 | B12: Кассетный 24 | C12: нет | D12: 6,8 - 7,5 | E12: 48 | H12: включая пульт | I12: AB24ES1ERA(S)/1U24FS1EAA/PB-950JB | J12: 737 | K12: =J12*1.1 -> 810.7 | L12: MDCD-24HRN1/MDOU-24HN1/T-MBQ-02C1 | M12: 779.52 | N12: =M12*1.1 -> 857.472
A13: 9 | B13: Кассетный 30 | C13: нет | D13: 7,1 - 8,5 | E13: 50 | H13: включая пульт | I13: AB24ES1ERA(S)/1U24FS1EAA/PB-950JB | J13: 737 | K13: =J13*1.1 -> 810.7 | L13: MDCD-24HRN1/MDOU-24HN1/T-MBQ-02C1 | M13: 779.52 | N13: =M13*1.1 -> 857.472
A14: 10 | B14: Кассетный 36 | C14: нет | D14: 9,7 - 11 | E14: 53 | H14: включая пульт | I14: AB36ES1ERA(S)/1U36SS1EAB/PB-950JB | J14: 863 | K14: =J14*1.1 -> 949.3 | L14: MDCD-36HRN1/MDOU-36HN1-L/LT-MBQ-02C1 | M14: 1162.08 | N14: =M14*1.1 -> 1278.288
A15: 11 | B15: Кассетный 48 | C15: нет | D15: 13,5 - 14,1 | E15: 52 | H15: включая пульт | I15: AB48ES1ERA(S)/1U48LS1EAB(S)/PB-P50JB | J15: 1046 | K15: =J15*1.1 -> 1150.6 | L15: MDCD-48HRN1/MDOU-48HN1-L/LT-MBQ-02C1 | M15: 1291.2 | N15: =M15*1.1 -> 1420.32
A16: 12 | B16: Кассетный 54 | C16: нет | D16: 14,3 - 16,2 | E16: 52 | H16: включая пульт | I16: AB60CS1ERA(S)/1U60IS1EAB(S)/PB-1340IB | J16: 1215 | K16: =J16*1.1 -> 1336.5 | L16: MDCD-60HRN1/MDOU-60HN1-L/LT-MBQ-02C1 | M16: 1427.52 | N16: =M16*1.1 -> 1570.272
A17: 13 | B17: Напольно - потолочный 18 | C17: нет | D17: 5,0 - 5,5 | E17: 46 | H17: включая пульт | I17: AC18CS1ERA(S)/1U18DS1EAA | J17: 553 | K17: =J17*1.1 -> 608.3 | L17: MDUE-18HRN1/MDOU-18HN1 | M17: 582.24 | N17: =M17*1.1 -> 640.464
A18: 14 | B18: Напольно - потолочный 24 | C18: нет | D18: 6,5 - 7,7 | E18: 52 | H18: включая пульт | I18: AC24CS1ERA(S)/1U24FS1EAA | J18: 744 | K18: =J18*1.1 -> 818.4 | L18: MDUE-24HRN1/MDOU-24HN1 | M18: 775.68 | N18: =M18*1.1 -> 853.248
A19: 15 | B19: Напольно - потолочный 36 | C19: нет | D19: 10,0 - 11,5 | E19: 54 | H19: включая пульт | I19: AC36ES1ERA(S)/1U36SS1EAB | J19: 896 | K19: =J19*1.1 -> 985.6 | L19: MDUE-36HRN1/MDOU-36HN1 | M19: 1158.24 | N19: =M19*1.1 -> 1274.064
A20: 16 | B20: Напольно - потолочный 48 | C20: нет | D20: 13,4 - 14,2 | E20: 55 | H20: включая пульт | I20: AC48FS1ERA(S)/1U48LS1EAB(S) | J20: 1005 | K20: =J20*1.1 -> 1105.5 | L20: MDUE-48HRN1/MDOU-48HN1 | M20: 1294.08 | N20: =M20*1.1 -> 1423.488
... A27: 23 | B27: Настенный 7 | C27: да | D27: 2,0 - 2,3 | E27: 40 | H27: включая пульт | I27: AS07TH3HRA/1U07MR4ERA | J27: 254 | K27: =J27*1.1 -> 279.4 | L27: MDSA-07HRFN1 | M27: 330.88 | N27: =M27*1.1 -> 363.968
A28: 24 | B28: Настенный 9 | C28: да | D28: 2,5 - 2,8 | E28: 40 | H28: включая пульт | I28: AS09TH3HRA/1U09MR4ERA | J28: 264 | K28: =J28*1.1 -> 290.4 | L28: MDSA-09HRFN1 | M28: 347.8 | N28: =M28*1.1 -> 382.58 | O28: =N28*66.56 -> 25464.525
A29: 25 | B29: Настенный 12 | C29: да | D29: 3,2 - 3,6 | E29: 42 | H29: включая пульт | I29: AS12TB3HRA/1U12MR4ERA | J29: 299 | K29: =J29*1.1 -> 328.9 | L29: MDSA-12HRFN1 | M29: 397.15 | N29: =M29*1.1 -> 436.865 | O29: =N29*70 -> 30580.55
A30: 26 | B30: Настенный 18 | C30: да | D30: 4,8 - 5,4 | E30: 45 | H30: включая пульт | I30: AS18TD2HRA/1U18EE8ERA | J30: 446 | K30: =J30*1.1 -> 490.6 | L30: MDSA-18HRFN1 | M30: 622.28 | N30: =M30*1.1 -> 684.508 | O30: =N30*70 -> 47915.56
A31: 27 | B31: Настенный 24 | C31: да | D31: 6,1 - 7,1 | E31: 49 | H31: включая пульт | I31: AS24TD2HRA/1U24RE8ERA | J31: 577 | K31: =J31*1.1 -> 634.7 | L31: MDSA-24HRFN1 | M31: 765.63 | N31: =M31*1.1 -> 842.193
A32: 28 | B32: Кассетный 12 | C32: да | D32: 3,3 - 3,7 | E32: 38 | H32: включая пульт | I32: AB12CS1ERA(S)/1U12BS3ERA/PB-700IB | J32: 586 | K32: =J32*1.1 -> 644.6 | L32: MDCA3-18HRDN1 | M32: 722.86 | N32: =M32*1.1 -> 795.146
A33: 29 | B33: Кассетный 18 | C33: да | D33: 4,6 - 5,4 | E33: 49 | H33: включая пульт | I33: AB18CS1ERA(S)/1U18FS2ERA(S)/PB-700IB | J33: 761 | K33: =J33*1.1 -> 837.1 | L33: MDCA3-18HRDN1 | M33: 722.86 | N33: =M33*1.1 -> 795.146
A34: 30 | B34: Кассетный 24 | C34: да | D34: 6,8 - 7,5 | E34: 48 | H34: включая пульт | I34: AB24ES1ERA(S)/1U24GS1ERA/PB-950JB | J34: 962 | K34: =J34*1.1 -> 1058.2 | L34: MDCD-24HRDN1 | M34: 928.25 | N34: =M34*1.1 -> 1021.075
A35: 31 | B35: Кассетный 30 | C35: да | D35: 7,1 - 8,5 | E35: 50 | H35: включая пульт | I35: AB24ES1ERA(S)/1U24GS1ERA/PB-950JB | J35: 962 | K35: =J35*1.1 -> 1058.2 | L35: MDCD-24HRDN1 | M35: 928.25 | N35: =M35*1.1 -> 1021.075
A36: 32 | B36: Кассетный 36 | C36: да | D36: 9,7 - 11 | E36: 53 | H36: включая пульт | I36: AB36ES1ERA(S)/1U36HS1ERA(S)/PB-950JB | J36: 1433 | K36: =J36*1.1 -> 1576.3 | L36: MDCD-36HRDN1 | M36: 1475.33 | N36: =M36*1.1 -> 1622.863
A37: 33 | B37: Кассетный 48 | C37: да | D37: 13,5 - 14,1 | E37: 52 | H37: включая пульт | I37: AB48ES1ERA(S)/1U48LS1ERB(S)/PB-950JB | J37: 1762 | K37: =J37*1.1 -> 1938.2 | L37: MDCD-48HRDN1 | M37: 1624.32 | N37: =M37*1.1 -> 1786.752
A38: 34 | B38: Кассетный 54 | C38: да | D38: 14,3 - 16,2 | E38: 52 | H38: включая пульт | I38: AB60CS1ERA(S)/1U60IS1ERB(S)/PB-1340IB | J38: 2067 | K38: =J38*1.1 -> 2273.7 | L38: MDCD-60HRDN1 | M38: 1886.58 | N38: =M38*1.1 -> 2075.238
A39: 35 | B39: Напольно - потолочный 18 | C39: да | D39: 5,0 - 5,5 | E39: 46 | H39: включая пульт | I39: AC18CS1ERA(S)/1U18FS2ERA(S) | J39: 765 | K39: =J39*1.1 -> 841.5 | L39: MDUE-18HRDN1 | M39: 713.93 | N39: =M39*1.1 -> 785.323
A40: 36 | B40: Напольно - потолочный 24 | C40: да | D40: 6,5 - 7,7 | E40: 52 | H40: включая пульт | I40: AC24CS1ERA(S)/1U24GS1ERA | J40: 944 | K40: =J40*1.1 -> 1038.4 | L40: MDUE-24HRDN1 | M40: 713.93 | N40: =M40*1.1 -> 785.323
A41: 37 | B41: Напольно - потолочный 36 | C41: да | D41: 10,0 - 11,5 | E41: 54 | H41: включая пульт | I41: AC36ES1ERA(S)/1U36HS1ERA(S) | J41: 1458 | K41: =J41*1.1 -> 1603.8 | L41: MDUE-36HRDN1 | M41: 1458.41 | N41: =M41*1.1 -> 1604.251
A42: 38 | B42: Напольно - потолочный 48 | C42: да | D42: 13,4 - 14,2 | E42: 55 | H42: включая пульт | I42: AC48FS1ERA(S)/1U48LS1ERB(S) | J42: 1722 | K42: =J42*1.1 -> 1894.2 | L42: MDUE-48HRDN1 | M42: 1629.02 | N42: =M42*1.1 -> 1791.922
... A48: 44 | B48: Канальный 60 | C48: да | D48: 15,0 - 16,2 | E48: 53 | H48: включая пульт и раздаточный пленум | I48: AD60HS1ERA(S)/1U60IS1ERB(S) | J48: 2125 | K48: =J48*1.1 -> 2337.5 | L48: MDTB-60HWDN1 | M48: 1848.98 | N48: =M48*1.1 -> 2033.878
A49: 45 | B49: Мульти-сплит внешн. блок | C49: да | D49: 4,7 - 5,3 | E49: 57 | F49: 20 - 40 | G49: 2 | H49: включая пульт | I49: 2U18FS2ERA(S) | J49: 470 | K49: =J49*1.1 -> 517 | L49: MD2O-14HFN1 outdoor | M49: 626.98 | N49: =M49*1.1 -> 689.678
A50: 46 | B50: Мульти-сплит внешн. блок | C50: да | D50: 5,4 - 7,1 | E50: 62 | F50: 30 - 60 | G50: 2 | H50: включая пульт | I50: 3U19FS1ERA(N) | J50: 722 | K50: =J50*1.1 -> 794.2 | L50: MD3O-21HFN1 outdoor | M50: 744.48 | N50: =M50*1.1 -> 818.928
A51: 47 | B51: Мульти-сплит внешн. блок | C51: да | D51: 7,2 - 8,3 | E51: 65 | F51: 45 - 80 | G51: 3 - 4 | H51: включая пульт | I51: 4U26HS1ERA | J51: 966 | K51: =J51*1.1 -> 1062.6 | L51: MD4O-28HFN1 outdoor | M51: 811.22 | N51: =M51*1.1 -> 892.342
A52: 48 | B52: Мульти-сплит внешн. блок | C52: да | D52: 9,0 - 11,7 | E52: 67 | F52: 60 - 85 | G52: 4 - 5 | H52: включая пульт | I52: 4U30HS1ERA | J52: 1082 | K52: =J52*1.1 -> 1190.2 | L52: MD4O-36HFN1 outdoor | M52: 1445.25 | N52: =M52*1.1 -> 1589.775
A53: 49 | B53: Мульти-сплит внешн. блок | C53: да | D53: 10,7 - 14,7 | E53: 67 | F53: 60 - 135 | G53: 4 - 8 | H53: включая пульт | I53: 5U34HS1ERA | J53: 1279 | K53: =J53*1.1 -> 1406.9 | L53: MD5O-42HFN1 outdoor | M53: 1487.55 | N53: =M53*1.1 -> 1636.305
A54: 50 | B54: Мульти-сплит внешн. блок | C54: да | D54: 13,5 - 16,7 | E54: 69 | F54: 75 - 145 | G54: 5 - 9 | H54: включая пульт | I54: 5U45LS1ERA | J54: 1622 | K54: =J54*1.1 -> 1784.2 | L54: MD4O-28HFN1 + MD3O-21HFN1 | M54: 1555.7 | N54: =M54*1.1 -> 1711.27
A55: 51 | B55: Мульти-сплит настенный внутр. блок | C55: да | D55: 1,5 - 2,0 | E55: 28 | H55: включая беспроводной пульт | I55: AS07BS4HRA | J55: 111 | K55: =J55*1.1 -> 122.1 | L55: MDSAI-07HRFN1 indoor | M55: 114.68 | N55: =M55*1.1 -> 126.148
A56: 52 | B56: Мульти-сплит настенный внутр. блок | C56: да | D56: 2,0 - 2,2 | E56: 29 | H56: включая беспроводной пульт | I56: AS07BS4HRA | J56: 111 | K56: =J56*1.1 -> 122.1 | L56: MDSAI-07HRFN1 indoor | M56: 114.68 | N56: =M56*1.1 -> 126.148
A57: 53 | B57: Мульти-сплит настенный внутр. блок | C57: да | D57: 2,6 - 2,8 | E57: 29 | H57: включая беспроводной пульт | I57: AS09BS4HRA | J57: 120 | K57: =J57*1.1 -> 132 | L57: MDSAI-09HRFN1 indoor | M57: 116.56 | N57: =M57*1.1 -> 128.216
A58: 54 | B58: Мульти-сплит настенный внутр. блок | C58: да | D58: 3,5 - 3,6 | E58: 34 | H58: включая беспроводной пульт | I58: AS12BS4HRA | J58: 136 | K58: =J58*1.1 -> 149.6 | L58: MDSAI-12HRFN1 indoor | M58: 117.97 | N58: =M58*1.1 -> 129.767
A59: 55 | B59: Мульти-сплит настенный внутр. блок | C59: да | D59: 5,1 - 5,6 | E59: 42 | H59: включая беспроводной пульт | I59: AS18BS4HRA | J59: 179 | K59: =J59*1.1 -> 196.9 | L59: MDSAI-18HRFN1 indoor | M59: 148.52 | N59: =M59*1.1 -> 163.372
A60: 56 | B60: Мульти-сплит настенный внутр. блок | C60: да | D60: 6,7 - 7,1 | E60: 45 | H60: включая беспроводной пульт | I60: AS24BS4HRA | J60: 204 | K60: =J60*1.1 -> 224.4 | L60: MDSAI-24HRFN1 indoor | M60: 160.27 | N60: =M60*1.1 -> 176.297
A61: 57 | B61: Мульти-сплит кассетный внутр. блок | C61: да | D61: 1,5 - 2,0 | E61: 32 | H61: включая беспроводной пульт и декоративную панель | I61: AB09CS1ERA/PB-700IB | J61: 268 | K61: =J61*1.1 -> 294.8 | L61: MDCA3I-07HRFN1 indoor | M61: 231.24 | N61: =M61*1.1 -> 254.364
A62: 58 | B62: Мульти-сплит кассетный внутр. блок | C62: да | D62: 2,0 - 2,2 | E62: 34 | H62: включая беспроводной пульт и декоративную панель | I62: AB09CS1ERA/PB-700IB | J62: 268 | K62: =J62*1.1 -> 294.8 | L62: MDCA3I-07HRFN1 indoor | M62: 231.24 | N62: =M62*1.1 -> 254.364
A63: 59 | B63: Мульти-сплит кассетный внутр. блок | C63: да | D63: 2,6 - 2,8 | E63: 36 | H63: включая беспроводной пульт и декоративную панель | I63: AB09CS1ERA/PB-700IB | J63: 268 | K63: =J63*1.1 -> 294.8 | L63: MDCA3I-09HRFN1 indoor | M63: 237.35 | N63: =M63*1.1 -> 261.085
A64: 60 | B64: Мульти-сплит кассетный внутр. блок | C64: да | D64: 3,5 - 3,6 | E64: 38 | H64: включая беспроводной пульт и декоративную панель | I64: AB12CS1ERA(S)/PB-700IB | J64: 279 | K64: =J64*1.1 -> 306.9 | L64: MDCA3I-12HRFN1 indoor | M64: 244.87 | N64: =M64*1.1 -> 269.357
A65: 61 | B65: Мульти-сплит кассетный внутр. блок | C65: да | D65: 4,5 - 5,6 | E65: 42 | H65: включая беспроводной пульт и декоративную панель | I65: AB18CS1ERA(S)/PB-700IB | J65: 307 | K65: =J65*1.1 -> 337.7 | L65: MDCA3I-18HRDN1 indoor | M65: 271.66 | N65: =M65*1.1 -> 298.826
A66: 62 | B66: Мульти-сплит кассетный внутр. блок | C66: да | D66: 6,5 - 7,1 | E66: 44 | H66: включая беспроводной пульт и декоративную панель | I66: AB24ES1ERA(S)/PB-950JB | J66: 360 | K66: =J66*1.1 -> 396 | L66: MDCE-24HRDN1 indoor | M66: 366.6 | N66: =M66*1.1 -> 403.26
... A74: 70 | B74: Мульти-сплит напольно-потолочный внутр. блок | C74: да | D74: 6,5 - 7,5 | E74: 46 | H74: включая беспроводной пульт | I74: AC24CS1ERA(S) | J74: 341 | K74: =J74*1.1 -> 375.1 | L74: MDSAI-24HRFN1 indoor | M74: 160.27 | N74: =M74*1.1 -> 176.297
B75: Обязательные требования: | C75: Хладагент R-410A
C76: Цвет оборудования - белый
C77: Все оборудование должно быть с режимами работы тепло - холод.
C78: Во всех внутренних блоках должны быть установлены фильтры тонкой очистки.

Sheet Контакты кондиционеры
A1: Уполномоченным лицом от «Haier» является:
A2: Руководитель филиала Фомичев С.Ю.
A3: E-mail: info@haierrussia.ru
A4: тел.: +7(495) 782-10-20
A5: Для заказа оборудования:
A6: Менеджер проектов направления систем кондиционирования
A7: Вячеслав Оданец
A8: тел.: +7(495) 782-10-20 доб.129
A9: моб.: +7(926) 920-53-77
A10: E-mail: V.odanets@haierrussia.ru
A12: Уполномоченным лицом от «Дженерал-Трейд»/Аяк является:
A13: Директор по развитию Гасин Михаил Юрьевич
... A33: Тарская Кристина

Sheet ККО
A1: Раздел | B1: Подраздел | C1: Пункт подраздела | D1: Новый номенклатурный номер | E1: Наименование работ и затрат | F1: СРЕДНЯЯ Стоимость работ, руб. | G1: СРЕДНЯЯ Стоимость материалов и оборудования руб. | H1: СРЕДНЯЯ стоимость ВСЕГО, руб. | I1: Стоимость работ, руб. | J1: Стоимость материалов и оборудования руб. | K1: ВСЕГО стоимость ВСЕГО, руб. | L1: Отклонение, %
A2: Р1 | B2: 0 | C2: 0 | D2: Р1.0.0 | E2: Раздел №1. Проектные работы и согласования | F2: 1595.7959 | G2: 0 | H2: 1595.7959 | I2: =IF('Смета 1-й этаж'!$I$4="ККО",'Смета 1-й этаж'!$M$17/'Смета 1-й этаж'!$I$6,0) -> 0 | J2: =IF('Смета 1-й этаж'!$I$4="ККО",'Смета 1-й этаж'!$N$17/'Смета 1-й этаж'!$I$6,0) -> 0 | K2: =I2+J2 -> 0 | L2: =K2/H2-1 -> -1
A3: Р2 | B3: 0 | C3: 0 | D3: Р2.0.0 | E3: Раздел №2. Демонтажные работы. | F3: 1504.7928 | G3: 229.02445 | H3: 1733.8173 | I3: =IF('Смета 1-й этаж'!$I$4="ККО",'Смета 1-й этаж'!$M$57/'Смета 1-й этаж'!$I$6,0) -> 0 | J3: =IF('Смета 1-й этаж'!$I$4="ККО",'Смета 1-й этаж'!$N$57/'Смета 1-й этаж'!$I$6,0) -> 0 | K3: =I3+J3 -> 0 | L3: =K3/H3-1 -> -1
A4: Р3 | B4: 0 | C4: 0 | D4: Р3.0.0 | E4: Раздел №3. Внутренние строительные работы | F4: 5234.746 | G4: 10264.199 | H4: 15498.945 | I4: =IF('Смета 1-й этаж'!$I$4="ККО",'Смета 1-й этаж'!$M$196/'Смета 1-й этаж'!$I$6,0) -> 0 | J4: =IF('Смета 1-й этаж'!$I$4="ККО",'Смета 1-й этаж'!$N$196/'Смета 1-й этаж'!$I$6,0) -> 0 | K4: =I4+J4 -> 0 | L4: =K4/H4-1 -> -1
A5: Р4 | B5: 0 | C5: 0 | D5: Р4.0.0 | E5: Раздел №4. Наружные строительные работы | F5: 211.01514 | G5: 485.45572 | H5: 696.47086 | I5: =IF('Смета 1-й этаж'!$I$4="ККО",'Смета 1-й этаж'!$M$472/'Смета 1-й этаж'!$I$6,0) -> 0 | J5: =IF('Смета 1-й этаж'!$I$4="ККО",'Смета 1-й этаж'!$N$472/'Смета 1-й этаж'!$I$6,0) -> 0 | K5: =I5+J5 -> 0 | L5: =K5/H5-1 -> -1
A6: Р5 | B6: 0 | C6: 0 | D6: Р5.0.0 | E6: Раздел №5. Водоснабжение и Канализация | F6: 193.04775 | G6: 592.60376 | H6: 785.65151 | I6: =IF('Смета 1-й этаж'!$I$4="ККО",'Смета 1-й этаж'!$M$534/'Смета 1-й этаж'!$I$6,0) -> 0 | J6: =IF('Смета 1-й этаж'!$I$4="ККО",'Смета 1-й этаж'!$N$534/'Смета 1-й этаж'!$I$6,0) -> 0 | K6: =I6+J6 -> 0 | L6: =K6/H6-1 -> -1
A7: Р6 | B7: 0 | C7: 0 | D7: Р6.0.0 | E7: Раздел №6. Отопление | F7: 418.52736 | G7: 447.62296 | H7: 866.15032 | I7: =IF('Смета 1-й этаж'!$I$4="ККО",'Смета 1-й этаж'!$M$628/'Смета 1-й этаж'!$I$6,0) -> 0 | J7: =IF('Смета 1-й этаж'!$I$4="ККО",'Смета 1-й этаж'!$N$628/'Смета 1-й этаж'!$I$6,0) -> 0 | K7: =I7+J7 -> 0 | L7: =K7/H7-1 -> -1
A8: Р7 | B8: 0 | C8: 0 | D8: Р7.0.0 | E8: Раздел №7. Вентиляция | F8: 440.67248 | G8: 2966.1666 | H8: 3406.8391 | I8: =IF('Смета 1-й этаж'!$I$4="ККО",'Смета 1-й этаж'!$M$686/'Смета 1-й этаж'!$I$6,0) -> 0 | J8: =IF('Смета 1-й этаж'!$I$4="ККО",'Смета 1-й этаж'!$N$686/'Смета 1-й этаж'!$I$6,0) -> 0 | K8: =I8+J8 -> 0 | L8: =K8/H8-1 -> -1
A9: Р8 | B9: 0 | C9: 0 | D9: Р8.0.0 | E9: Раздел №8. Кондиционирование | F9: 615.20973 | G9: 2979.6748 | H9: 3594.8845 | I9: =IF('Смета 1-й этаж'!$I$4="ККО",'Смета 1-й этаж'!M$712/'Смета 1-й этаж'!$I$6,0) -> 0 | J9: =IF('Смета 1-й этаж'!$I$4="ККО",'Смета 1-й этаж'!$N$712/'Смета 1-й этаж'!$I$6,0) -> 0 | K9: =I9+J9 -> 0 | L9: =K9/H9-1 -> -1
A10: Р9 | B10: 0 | C10: 0 | D10: Р9.0.0 | E10: Раздел №9. Электротехнические работы | F10: 1401.4891 | G10: 3655.3367 | H10: 5056.8258 | I10: =IF('Смета 1-й этаж'!$I$4="ККО",'Смета 1-й этаж'!$M$759/'Смета 1-й этаж'!$I$6,0) -> 0 | J10: =IF('Смета 1-й этаж'!$I$4="ККО",'Смета 1-й этаж'!$N$759/'Смета 1-й этаж'!$I$6,0) -> 0 | K10: =I10+J10 -> 0 | L10: =K10/H10-1 -> -1
A11: Р10 | B11: 0 | C11: 0 | D11: Р10.0.0 | E11: Раздел №10. Адаптация объекта для МГН | I11: =IF('Смета 1-й этаж'!$I$4="ККО",'Смета 1-й этаж'!$M$1181/'Смета 1-й этаж'!$I$6,0) -> 0 | J11: =IF('Смета 1-й этаж'!$I$4="ККО",'Смета 1-й этаж'!$N$1181/'Смета 1-й этаж'!$I$6,0) -> 0 | K11: =I11+J11 -> 0 | L11: =K11/H11-1 -> #DIV/0!
E12: Транспортно-накладные расходы (% от стоимости работ и материалов): | F12: 598.41783 | G12: 0 | H12: 598.41783 | I12: =IF('Смета 1-й этаж'!$I$4="ККО",'Смета 1-й этаж'!$M$1212/'Смета 1-й этаж'!$I$6,0) -> 0 | J12: 0 | K12: =I12+J12 -> 0 | L12: =K12/H12-1 -> -1
A13: Итог | B13: 0 | E13: ИТОГО РАЗДЕЛ | F13: =SUM(F2:F12) -> 12213.714 | G13: =SUM(G2:G12) -> 21620.084 | H13: =SUM(H2:H12) -> 33833.798 | I13: =SUM(I2:I12) -> 0 | J13: =SUM(J2:J12) -> 0 | K13: =SUM(K2:K12) -> 0 | L13: =K13/H13-1 -> -1
D16: Работы, выходящие по стоимости из "среднего" проекта
J17: Стоитмость (руб.) | K17: Цена 1 кв.м. (руб.) | N17: Заполняется перечень и стоимость работ, выходящих за рамки "типоывой" площадки. В таблице пример таких работ (могут быть другие)
D18: 1 | E18: Конструктивные работы | J18: ='Смета 1-й этаж'!AR197+'Смета 1-й этаж'!AR357+'Смета 1-й этаж'!AR440 -> 0 | K18: =J18/'Смета 1-й этаж'!$I$6 -> #DIV/0!
D19: 2 | E19: Устройство новых входных групп или запасных выходов (изменение фасадов) | J19: ='Смета 1-й этаж'!AR264 -> 0 | K19: =J19/'Смета 1-й этаж'!$I$6 -> #DIV/0!
D20: 3 | E20: Ремонт фасадов | J20: ='Смета 1-й этаж'!AR486 -> 0 | K20: =J20/'Смета 1-й этаж'!$I$6 -> #DIV/0!
D21: 4 | E21: Ремонт кровли | J21: ='Смета 1-й этаж'!AR473 -> 0 | K21: =J21/'Смета 1-й этаж'!$I$6 -> #DIV/0!
D22: 5 | E22: Противопожарные мероприятия | J22: ='Смета 1-й этаж'!AR606+'Смета 1-й этаж'!AR624+'Смета 1-й этаж'!AR707 -> 0 | K22: =J22/'Смета 1-й этаж'!$I$6 -> #DIV/0!
D23: 6 | E23: Устройство, ремонт лифтов | K23: =J23/'Смета 1-й этаж'!$I$6 -> #DIV/0!
D24: 7 | E24: Диспетчеризация и управление инженерными системами: | K24: =J24/'Смета 1-й этаж'!$I$6 -> #DIV/0!
D25: 8 | E25: Благоустроство территории | J25: ='Смета 1-й этаж'!AR515 -> 0 | K25: =J25/'Смета 1-й этаж'!$I$6 -> #DIV/0!
D26: 9 | E26: Ввод и Резервирование электроснабжения: | K26: =J26/'Смета 1-й этаж'!$I$6 -> #DIV/0!
D27: 10 | E27: Внешние сети | K27: =J27/'Смета 1-й этаж'!$I$6 -> #DIV/0!
D28: 11 | E28: Стеклянные перегородки (больше обычного) | K28: =J28/'Смета 1-й этаж'!$I$6 -> #DIV/0!
D29: 12 | E29: Вентиляция (больше обычного) | K29: =J29/'Смета 1-й этаж'!$I$6 -> #DIV/0!
D30: 13 | E30: Кондиционирование (больше обычного) | K30: =J30/'Смета 1-й этаж'!$I$6 -> #DIV/0!
D31: 14 | K31: =J31/'Смета 1-й этаж'!$I$6 -> #DIV/0!
D32: 15 | K32: =J32/'Смета 1-й этаж'!$I$6 -> #DIV/0!
D33: 16 | K33: =J33/'Смета 1-й этаж'!$I$6 -> #DIV/0!
E34: Итого стоимость "специальных" работ | J34: =SUM(J18:J33) -> 0 | K34: =SUM(K18:K33) -> #DIV/0!
E35: Цена 1 кв м стоимости РСР без учета "специальных" работ | K35: =K13-K34 -> #DIV/0!

Sheet Инфраструктура
A1: Раздел | B1: Подраздел | C1: Пункт подраздела | D1: Новый номенклатурный номер | E1: Наименование работ и затрат | F1: СРЕДНЯЯ Стоимость работ, руб. | G1: СРЕДНЯЯ Стоимость материалов и оборудования руб. | H1: СРЕДНЯЯ стоимость ВСЕГО, руб. | I1: Стоимость работ, руб. | J1: Стоимость материалов и оборудования руб. | K1: ВСЕГО стоимость ВСЕГО, руб. | L1: Отклонение, %
A2: Р1 | B2: 0 | C2: 0 | D2: Р1.0.0 | E2: Раздел №1. Проектные работы и согласования | F2: 1079.0166 | G2: 0 | H2: 1079.0166 | I2: =IF('Смета 1-й этаж'!$I$4="Инфраструктура",'Смета 1-й этаж'!$M$17/'Смета 1-й этаж'!$I$6,0) -> #DIV/0! | J2: =IF('Смета 1-й этаж'!$I$4="Инфраструктура",'Смета 1-й этаж'!$N$17/'Смета 1-й этаж'!$I$6,0) -> #DIV/0! | K2: =I2+J2 -> #DIV/0! | L2: =K2/H2-1 -> #DIV/0!
A3: Р2 | B3: 0 | C3: 0 | D3: Р2.0.0 | E3: Раздел №2. Демонтажные работы. | F3: 1716.883 | G3: 105.7182 | H3: 1822.6012 | I3: =IF('Смета 1-й этаж'!$I$4="Инфраструктура",'Смета 1-й этаж'!$M$57/'Смета 1-й этаж'!$I$6,0) -> #DIV/0! | J3: =IF('Смета 1-й этаж'!$I$4="Инфраструктура",'Смета 1-й этаж'!$N$57/'Смета 1-й этаж'!$I$6,0) -> #DIV/0! | K3: =I3+J3 -> #DIV/0! | L3: =K3/H3-1 -> #DIV/0!
A4: Р3 | B4: 0 | C4: 0 | D4: Р3.0.0 | E4: Раздел №3. Внутренние строительные работы | F4: 6370.3388 | G4: 12428.826 | H4: 18799.165 | I4: =IF('Смета 1-й этаж'!$I$4="Инфраструктура",'Смета 1-й этаж'!$M$196/'Смета 1-й этаж'!$I$6,0) -> #DIV/0! | J4: =IF('Смета 1-й этаж'!$I$4="Инфраструктура",'Смета 1-й этаж'!$N$196/'Смета 1-й этаж'!$I$6,0) -> #DIV/0! | K4: =I4+J4 -> #DIV/0! | L4: =K4/H4-1 -> #DIV/0!
A5: Р4 | B5: 0 | C5: 0 | D5: Р4.0.0 | E5: Раздел №4. Наружные строительные работы | F5: 223.81675 | G5: 759.68777 | H5: 983.50452 | I5: =IF('Смета 1-й этаж'!$I$4="Инфраструктура",'Смета 1-й этаж'!$M$472/'Смета 1-й этаж'!$I$6,0) -> #DIV/0! | J5: =IF('Смета 1-й этаж'!$I$4="Инфраструктура",'Смета 1-й этаж'!$N$472/'Смета 1-й этаж'!$I$6,0) -> #DIV/0! | K5: =I5+J5 -> #DIV/0! | L5: =K5/H5-1 -> #DIV/0!
A6: Р5 | B6: 0 | C6: 0 | D6: Р5.0.0 | E6: Раздел №5. Водоснабжение и Канализация | F6: 191.78339 | G6: 369.50799 | H6: 561.29139 | I6: =IF('Смета 1-й этаж'!$I$4="Инфраструктура",'Смета 1-й этаж'!$M$534/'Смета 1-й этаж'!$I$6,0) -> #DIV/0! | J6: =IF('Смета 1-й этаж'!$I$4="Инфраструктура",'Смета 1-й этаж'!$N$534/'Смета 1-й этаж'!$I$6,0) -> #DIV/0! | K6: =I6+J6 -> #DIV/0! | L6: =K6/H6-1 -> #DIV/0!
A7: Р6 | B7: 0 | C7: 0 | D7: Р6.0.0 | E7: Раздел №6. Отопление | F7: 196.81226 | G7: 249.92222 | H7: 446.73448 | I7: =IF('Смета 1-й этаж'!$I$4="Инфраструктура",'Смета 1-й этаж'!$M$628/'Смета 1-й этаж'!$I$6,0) -> #DIV/0! | J7: =IF('Смета 1-й этаж'!$I$4="Инфраструктура",'Смета 1-й этаж'!$N$628/'Смета 1-й этаж'!$I$6,0) -> #DIV/0! | K7: =I7+J7 -> #DIV/0! | L7: =K7/H7-1 -> #DIV/0!
A8: Р7 | B8: 0 | C8: 0 | D8: Р7.0.0 | E8: Раздел №7. Вентиляция | F8: 657.15384 | G8: 3376.1791 | H8: 4033.3329 | I8: =IF('Смета 1-й этаж'!$I$4="Инфраструктура",'Смета 1-й этаж'!$M$686/'Смета 1-й этаж'!$I$6,0) -> #DIV/0! | J8: =IF('Смета 1-й этаж'!$I$4="Инфраструктура",'Смета 1-й этаж'!$N$686/'Смета 1-й этаж'!$I$6,0) -> #DIV/0! | K8: =I8+J8 -> #DIV/0! | L8: =K8/H8-1 -> #DIV/0!
A9: Р8 | B9: 0 | C9: 0 | D9: Р8.0.0 | E9: Раздел №8. Кондиционирование | F9: 570.71637 | G9: 2786.6431 | H9: 3357.3595 | I9: =IF('Смета 1-й этаж'!$I$4="Инфраструктура",'Смета 1-й этаж'!M$712/'Смета 1-й этаж'!$I$6,0) -> #DIV/0! | J9: =IF('Смета 1-й этаж'!$I$4="Инфраструктура",'Смета 1-й этаж'!$N$712/'Смета 1-й этаж'!$I$6,0) -> #DIV/0! | K9: =I9+J9 -> #DIV/0! | L9: =K9/H9-1 -> #DIV/0!
A10: Р9 | B10: 0 | C10: 0 | D10: Р9.0.0 | E10: Раздел №9. Электротехнические работы | F10: 1497.0422 | G10: 3569.412 | H10: 5066.4542 | I10: =IF('Смета 1-й этаж'!$I$4="Инфраструктура",'Смета 1-й этаж'!$M$759/'Смета 1-й этаж'!$I$6,0) -> #DIV/0! | J10: =IF('Смета 1-й этаж'!$I$4="Инфраструктура",'Смета 1-й этаж'!$N$759/'Смета 1-й этаж'!$I$6,0) -> #DIV/0! | K10: =I10+J10 -> #DIV/0! | L10: =K10/H10-1 -> #DIV/0!
A11: Р10 | B11: 0 | C11: 0 | D11: Р10.0.0 | E11: Раздел №10. Адаптация объекта для МГН | I11: =IF('Смета 1-й этаж'!$I$4="Инфраструктура",'Смета 1-й этаж'!$M$1181/'Смета 1-й этаж'!$I$6,0) -> #DIV/0! | J11: =IF('Смета 1-й этаж'!$I$4="Инфраструктура",'Смета 1-й этаж'!$N$1181/'Смета 1-й этаж'!$I$6,0) -> #DIV/0! | K11: =I11+J11 -> #DIV/0! | L11: =K11/H11-1 -> #DIV/0!
E12: Транспортно-накладные расходы (% от стоимости работ и материалов): | F12: 628.48145 | G12: 0 | H12: 628.48145 | I12: =IF('Смета 1-й этаж'!$I$4="Инфраструктура",'Смета 1-й этаж'!$M$1212/'Смета 1-й этаж'!$I$6,0) -> #DIV/0! | J12: 0 | K12: =I12+J12 -> #DIV/0! | L12: =K12/H12-1 -> #DIV/0!
A13: Итог | B13: 0 | E13: ИТОГО РАЗДЕЛ | F13: =SUM(F2:F12) -> 13132.045 | G13: =SUM(G2:G12) -> 23645.896 | H13: =SUM(H2:H12) -> 36777.941 | I13: =SUM(I2:I12) -> #DIV/0! | J13: =SUM(J2:J12) -> #DIV/0! | K13: =SUM(K2:K12) -> #DIV/0! | L13: =K13/H13-1 -> #DIV/0!

Sheet Список
A1: ККО
A2: Инфраструктура

Sheet свод_исходн
A3: Названия строк | B3: Стоимость работ | C3: Стоимость материалов и оборудования | D3: Итого
A4: Смета_FIFA_Добролюбова | B4: 8242224 | C4: 14557776 | D4: =B4+C4 -> 22800000
A5: Смета_FIFA_Житная | B5: 6023712.9 | C5: 12720312 | D5: =B5+C5 -> 18744025
A6: Смета_FIFA_Проектируемый проезд | B6: 2180901 | C6: 5719099 | D6: =B6+C6 -> 7900000
A7: Смета_Братиславский_5 | B7: 2013600.8 | C7: 4434529.2 | D7: =B7+C7 -> 6448130
A8: Смета_Братиславский_6 | B8: 1360056.9 | C8: 2991813 | D8: =B8+C8 -> 4351869.9
A9: Смета_Володарский | B9: 6922260.7 | C9: 11484249 | D9: =B9+C9 -> 18406510
A10: Смета_Кемерово_Кузбасс | B10: 3325304.8 | C10: 6422661.7 | D10: =B10+C10 -> 9747966.5
A11: Смета_КЦ_МОПР | B11: 7996659.6 | C11: 16238497 | D11: =B11+C11 -> 24235157
A12: Смета_Людмила | B12: 3061831.9 | C12: 6229060.3 | D12: =B12+C12 -> 9290892.1
A13: Смета_Саратовский_Соборная | B13: 5473685 | C13: 8815485.1 | D13: =B13+C13 -> 14289170
A14: Смета_Саратовский_Чернышевского | B14: 3415508 | C14: 5995321.9 | D14: =B14+C14 -> 9410829.9
A15: Смета_Сокольники | B15: 4293844.8 | C15: 7017814.1 | D15: =B15+C15 -> 11311659
... A17: Смета_Ярославский_Чайковского | B17: 939732.31 | C17: 1414657.2 | D17: =B17+C17 -> 2354389.5
A18: Общий итог | B18: 62289122 | C18: 1.1611259e+08 | D18: =SUM(D4:D17) -> 1.7840171e+08
