Workbook
Name S_общая: Параметры!$B$19
Name S_поверхность: Параметры!$B$23
Name S_пол: Параметры!$B$20
Name S_потолок: Параметры!$B$22
Name S_проёмы: Параметры!$B$24
Name S_стены: Параметры!$B$21
Name S_фасад: Параметры!$B$25
Name Адрес: Параметры!$B$6
Name ДатаЦен: Параметры!$B$8
Name ДисконтТендер: Параметры!$B$31
Name КодыРабот: Работы!$A$2:$A$6000
Name КонтЛицо: Параметры!$B$14
Name КонтТел: Параметры!$B$15
Name КурсEUR: Параметры!$B$36
Name КурсUSD: Параметры!$B$35
Name мат_VRF_ВНУТ: OFFSET(Материалы!$A$1,MATCH("VRF.ВНУТ",Материалы!$G:$G,0)-1,0,COUNTIF(Материалы!$G:$G,"VRF.ВНУТ"),1)
Name мат_VRF_НАР: OFFSET(Материалы!$A$1,MATCH("VRF.НАР",Материалы!$G:$G,0)-1,0,COUNTIF(Материалы!$G:$G,"VRF.НАР"),1)
Name мат_БРОНЯ: OFFSET(Материалы!$A$1,MATCH("БРОНЯ",Материалы!$G:$G,0)-1,0,COUNTIF(Материалы!$G:$G,"БРОНЯ"),1)
Name мат_ДВ: OFFSET(Материалы!$A$1,MATCH("ДВ",Материалы!$G:$G,0)-1,0,COUNTIF(Материалы!$G:$G,"ДВ"),1)
Name мат_ДВ_АЛ: OFFSET(Материалы!$A$1,MATCH("ДВ.АЛ",Материалы!$G:$G,0)-1,0,COUNTIF(Материалы!$G:$G,"ДВ.АЛ"),1)
Name мат_ДВ_ДЕР: OFFSET(Материалы!$A$1,MATCH("ДВ.ДЕР",Материалы!$G:$G,0)-1,0,COUNTIF(Материалы!$G:$G,"ДВ.ДЕР"),1)
Name мат_ДВ_СТ: OFFSET(Материалы!$A$1,MATCH("ДВ.СТ",Материалы!$G:$G,0)-1,0,COUNTIF(Материалы!$G:$G,"ДВ.СТ"),1)
Name мат_ЗАВЕСА: OFFSET(Материалы!$A$1,MATCH("ЗАВЕСА",Материалы!$G:$G,0)-1,0,COUNTIF(Материалы!$G:$G,"ЗАВЕСА"),1)
Name мат_ЛЮЧОК: OFFSET(Материалы!$A$1,MATCH("ЛЮЧОК",Материалы!$G:$G,0)-1,0,COUNTIF(Материалы!$G:$G,"ЛЮЧОК"),1)
Name мат_ПВУ: OFFSET(Материалы!$A$1,MATCH("ПВУ",Материалы!$G:$G,0)-1,0,COUNTIF(Материалы!$G:$G,"ПВУ"),1)
Name мат_ПЕРЕГ_СТ: OFFSET(Материалы!$A$1,MATCH("ПЕРЕГ.СТ",Материалы!$G:$G,0)-1,0,COUNTIF(Материалы!$G:$G,"ПЕРЕГ.СТ"),1)
Name мат_ПЕРЕГ_ТР: OFFSET(Материалы!$A$1,MATCH("ПЕРЕГ.ТР",Материалы!$G:$G,0)-1,0,COUNTIF(Материалы!$G:$G,"ПЕРЕГ.ТР"),1)
Name мат_ПОЛ_КГ: OFFSET(Материалы!$A$1,MATCH("ПОЛ.КГ",Материалы!$G:$G,0)-1,0,COUNTIF(Материалы!$G:$G,"ПОЛ.КГ"),1)
Name мат_ПОЛ_МОД: OFFSET(Материалы!$A$1,MATCH("ПОЛ.МОД",Материалы!$G:$G,0)-1,0,COUNTIF(Материалы!$G:$G,"ПОЛ.МОД"),1)
Name мат_ПОТОЛОК: OFFSET(Материалы!$A$1,MATCH("ПОТОЛОК",Материалы!$G:$G,0)-1,0,COUNTIF(Материалы!$G:$G,"ПОТОЛОК"),1)
Name мат_РАД: OFFSET(Материалы!$A$1,MATCH("РАД",Материалы!$G:$G,0)-1,0,COUNTIF(Материалы!$G:$G,"РАД"),1)
Name мат_РАД_КОМПЛ: OFFSET(Материалы!$A$1,MATCH("РАД.КОМПЛ",Материалы!$G:$G,0)-1,0,COUNTIF(Материалы!$G:$G,"РАД.КОМПЛ"),1)
Name мат_СВЕТ: OFFSET(Материалы!$A$1,MATCH("СВЕТ",Материалы!$G:$G,0)-1,0,COUNTIF(Материалы!$G:$G,"СВЕТ"),1)
Name мат_СВЕТ_АВАР: OFFSET(Материалы!$A$1,MATCH("СВЕТ.АВАР",Материалы!$G:$G,0)-1,0,COUNTIF(Материалы!$G:$G,"СВЕТ.АВАР"),1)
Name мат_СПЛИТ: OFFSET(Материалы!$A$1,MATCH("СПЛИТ",Материалы!$G:$G,0)-1,0,COUNTIF(Материалы!$G:$G,"СПЛИТ"),1)
Name мат_СТЕН_ПЛ: OFFSET(Материалы!$A$1,MATCH("СТЕН.ПЛ",Материалы!$G:$G,0)-1,0,COUNTIF(Материалы!$G:$G,"СТЕН.ПЛ"),1)
Name мат_СТП_РАК: OFFSET(Материалы!$A$1,MATCH("СТП.РАК",Материалы!$G:$G,0)-1,0,COUNTIF(Материалы!$G:$G,"СТП.РАК"),1)
Name мат_СТП_СМЕС: OFFSET(Материалы!$A$1,MATCH("СТП.СМЕС",Материалы!$G:$G,0)-1,0,COUNTIF(Материалы!$G:$G,"СТП.СМЕС"),1)
Name мат_СТП_УНИТ: OFFSET(Материалы!$A$1,MATCH("СТП.УНИТ",Материалы!$G:$G,0)-1,0,COUNTIF(Материалы!$G:$G,"СТП.УНИТ"),1)
Name мат_ФАЛЬШПОЛ: OFFSET(Материалы!$A$1,MATCH("ФАЛЬШПОЛ",Материалы!$G:$G,0)-1,0,COUNTIF(Материалы!$G:$G,"ФАЛЬШПОЛ"),1)
Name мат_ЭУИ_ВЫКЛ: OFFSET(Материалы!$A$1,MATCH("ЭУИ.ВЫКЛ",Материалы!$G:$G,0)-1,0,COUNTIF(Материалы!$G:$G,"ЭУИ.ВЫКЛ"),1)
Name мат_ЭУИ_РОЗ: OFFSET(Материалы!$A$1,MATCH("ЭУИ.РОЗ",Материалы!$G:$G,0)-1,0,COUNTIF(Материалы!$G:$G,"ЭУИ.РОЗ"),1)
Name мат_ЭЩ: OFFSET(Материалы!$A$1,MATCH("ЭЩ",Материалы!$G:$G,0)-1,0,COUNTIF(Материалы!$G:$G,"ЭЩ"),1)
Name Периметр_пола: Параметры!$B$26
Name Подрядчик: Параметры!$B$11
Name ПроцРезерв: Параметры!$B$34
Name ПроцТакелаж: Параметры!$B$33
Name ПроцТранспорт: Параметры!$B$32
Name РежимЦены: Параметры!$B$29
Name Реквизиты: Параметры!$B$16
Name Срок: Параметры!$B$7
Name СтавкаНДС: Параметры!$B$30
Name ФорматОбъекта: Параметры!$B$5
Name ЭлАдрес: Параметры!$B$13
Name ЮрАдрес: Параметры!$B$12

Sheet О шаблоне
A1: Смета объекта — единый файл (Excel 2019+)
A3: ТРИ ПРАВИЛА
A4: 1. «Конструктор» — вводишь по нужным строкам: Объём · Код_материала · Вкл. (да/нет).
A5: Подсказка «Драйвер» говорит, откуда объём (S_пол, S_стены, спецификация, замер…).
A6: Список материала — только по группе этой работы. «Гр_ОK» краснеет, если выбран не тот.
A7: 2. «Смета» — готовый документ. После ввода объёмов: встать на таблицу расшифровки →
A8: Данные → «Применить повторно» (Ctrl+Alt+L). Позиции появятся, итоги встанут под ними.
A9: 3. Цены и работы менять — на жёлтых листах «Работы» / «Материалы» в этом же файле.
A10: После ДОБАВЛЕНИЯ материалов — отсортировать лист «Материалы» по колонке «Группа_материалов»
A11: (выделить таблицу → Данные → Сортировка). Иначе список материала по группе будет неполным.
A13: ЛИСТЫ:
A14: Параметры — объект, подрядчик, площади, НДС, %% транспорта/такелажа/резерва, курсы (жёлтые ячейки).
... A24: Сформировано: 2026-08-31. Работ: 911. Материалов: 1218. Буфер Конструктора: 1211. Версия: 1.0 (единый файл).

Sheet Параметры
A1: ПАРАМЕТРЫ ОБЪЕКТА
A3: Параметр | B3: Значение | C3: Пояснение
A4: Объект
A5: Формат объекта | B5: ККО | C5: ККО / Инфраструктура
A6: Адрес объекта
A7: Срок проведения работ | B7: Согласно план-графику производства работ
A8: Дата цен | B8: 46265 | C8: на какую дату актуальны цены КП
A10: Подрядчик
A11: ПОДРЯДЧИК (наименование)
A12: Юридический адрес
A13: Электронный адрес
A14: Контактное лицо (Ф.И.О.)
A15: Контактный телефон
A16: Реквизиты
A18: Площади, м²
A19: S_общая (площадь объекта) | B19: 0 | C19: для ТЭП и проектных расценок
A20: S_пол | B20: 0 | C20: драйвер S_пол
A21: S_стены | B21: 0 | C21: драйвер S_стены (развёртка)
A22: S_потолок | B22: 0 | C22: драйвер S_потолок
A23: S_поверхность | B23: 0 | C23: драйвер S_поверхность
A24: S_проёмы | B24: 0 | C24: драйвер S_проёмы
A25: S_фасад | B25: 0 | C25: драйвер S_фасад
A26: Периметр_пола, м.п. | B26: 0 | C26: драйвер Периметр_пола
A28: Финансы
A29: Режим цены | B29: с НДС в цене | C29: «с НДС в цене» — НДС извлекается; «без НДС» — начисляется сверху
A30: Ставка НДС, % | B30: 20 | C30: 5 / 7 / 20
A31: Дисконт по тендеру, доля | B31: 0 | C31: 0,05 = минус 5% к ЕР
A32: Транспортные, % от стоимости материалов | B32: 3
A33: Такелаж / верт. транспорт, % от (работы+материалы) | B33: 0 | C33: режим ТЦ/БЦ, ночные работы
A34: Резерв на непредвиденные, % от (работы+материалы) | B34: 0 | C34: 0 = не применять
A35: Курс USD | B35: 81 | C35: для валютных материалов
A36: Курс EUR | B36: 95

Sheet Конструктор
A1: Раздел | B1: Подраздел | C1: Код_работы | D1: Наименование работы | E1: Ед | F1: Группа_мат | G1: Драйвер | H1: Объём | I1: Код_материала | J1: Наименование материала | K1: Гр_ОK | L1: Цена работ, ₽ | M1: Цена мат, ₽ | N1: Стоим. работ, ₽ | O1: Стоим. мат, ₽ | P1: Всего, ₽ | Q1: Тип | R1: Вкл. | S1: Примечание | T1: _ранг
A2: =IFERROR(INDEX(Работы!$D$2:$D$6000,MATCH($C2,Работы!$A$2:$A$6000,0)),"") -> Р1 | B2: =IFERROR(INDEX(Работы!$F$2:$F$6000,MATCH($C2,Работы!$A$2:$A$6000,0)),"") -> 1 | C2: =IFERROR(INDEX(Работы!$A$2:$A$6000,1),"") -> РАБ.Р1.1.001 | D2: =IFERROR(INDEX(Работы!$B$2:$B$6000,MATCH($C2,Работы!$A$2:$A$6000,0)),"") -> Техническое обследование состояния несущих конструкций помещения с подготовкой рекомендаций по усилению (Техничесекое заключение о конструктиве - "ТЗК") (для помещений от 100 до 45… | E2: =IFERROR(INDEX(Работы!$C$2:$C$6000,MATCH($C2,Работы!$A$2:$A$6000,0)),"") -> м2 | F2: =IFERROR(INDEX(Работы!$G$2:$G$6000,MATCH($C2,Работы!$A$2:$A$6000,0)),"") -> 0 | G2: =IFERROR(INDEX(Работы!$K$2:$K$6000,MATCH($C2,Работы!$A$2:$A$6000,0)),"") -> S_общая | J2: =IFERROR(INDEX(Материалы!$B$2:$B$9000,MATCH($I2,Материалы!$A$2:$A$9000,0)),"") | K2: =IF($I2="","",IF($F2=IFERROR(INDEX(Материалы!$G$2:$G$9000,MATCH($I2,Материалы!$A$2:$A$9000,0)),""),"OK","!! не та группа")) | L2: =IFERROR(INDEX(Работы!$H$2:$H$6000,MATCH($C2,Работы!$A$2:$A$6000,0))*(1-ДисконтТендер),0) -> 3675 | M2: =IF($I2="",0,IFERROR(INDEX(Материалы!$I$2:$I$9000,MATCH($I2,Материалы!$A$2:$A$9000,0))*IF(INDEX(Материалы!$J$2:$J$9000,MATCH($I2,Материалы!$A$2:$A$9000,0))="USD",КурсUSD,IF(INDEX(Материалы!$J$2:$J$9000,MATCH($I2,Материалы!$A$2:$A$9000,0))="EUR",КурсEUR,1))*INDEX(Материалы!$K$2:$K$9000,MATCH($I2,Материалы!$A$2:$A$9000,0))*(1+IFERROR(INDEX(Работы!$I$2:$I$6000,MATCH($C2,Работы!$A$2:$A$6000,0))/100,0))*(1-ДисконтТендер),0)) -> 0 | N2: =IF(AND($R2="да",$H2<>""),ROUND($H2*$L2,2),0) -> 0 | O2: =IF(AND($R2="да",$H2<>""),ROUND($H2*$M2,2),0) -> 0 | P2: =$N2+$O2 -> 0 | Q2: =IFERROR(INDEX(Работы!$J$2:$J$6000,MATCH($C2,Работы!$A$2:$A$6000,0)),"") -> нетиповая | R2: да | T2: =IF(AND($P2>0,$R2="да"),MAX($T$1:$T1)+1,"")
A3: =IFERROR(INDEX(Работы!$D$2:$D$6000,MATCH($C3,Работы!$A$2:$A$6000,0)),"") -> Р1 | B3: =IFERROR(INDEX(Работы!$F$2:$F$6000,MATCH($C3,Работы!$A$2:$A$6000,0)),"") -> 1 | C3: =IFERROR(INDEX(Работы!$A$2:$A$6000,2),"") -> РАБ.Р1.1.002 | D3: =IFERROR(INDEX(Работы!$B$2:$B$6000,MATCH($C3,Работы!$A$2:$A$6000,0)),"") -> Эскизный проект фасада и Колористический паспорт с указанием ведомости отделки и проектным решением со спецификацией элементов (крыльцо, пандус, навесы, колонны и т.д.)(для фасадов… | E3: =IFERROR(INDEX(Работы!$C$2:$C$6000,MATCH($C3,Работы!$A$2:$A$6000,0)),"") -> м2 | F3: =IFERROR(INDEX(Работы!$G$2:$G$6000,MATCH($C3,Работы!$A$2:$A$6000,0)),"") -> 0 | G3: =IFERROR(INDEX(Работы!$K$2:$K$6000,MATCH($C3,Работы!$A$2:$A$6000,0)),"") -> S_общая | J3: =IFERROR(INDEX(Материалы!$B$2:$B$9000,MATCH($I3,Материалы!$A$2:$A$9000,0)),"") | K3: =IF($I3="","",IF($F3=IFERROR(INDEX(Материалы!$G$2:$G$9000,MATCH($I3,Материалы!$A$2:$A$9000,0)),""),"OK","!! не та группа")) | L3: =IFERROR(INDEX(Работы!$H$2:$H$6000,MATCH($C3,Работы!$A$2:$A$6000,0))*(1-ДисконтТендер),0) -> 7822.5 | M3: =IF($I3="",0,IFERROR(INDEX(Материалы!$I$2:$I$9000,MATCH($I3,Материалы!$A$2:$A$9000,0))*IF(INDEX(Материалы!$J$2:$J$9000,MATCH($I3,Материалы!$A$2:$A$9000,0))="USD",КурсUSD,IF(INDEX(Материалы!$J$2:$J$9000,MATCH($I3,Материалы!$A$2:$A$9000,0))="EUR",КурсEUR,1))*INDEX(Материалы!$K$2:$K$9000,MATCH($I3,Материалы!$A$2:$A$9000,0))*(1+IFERROR(INDEX(Работы!$I$2:$I$6000,MATCH($C3,Работы!$A$2:$A$6000,0))/100,0))*(1-ДисконтТендер),0)) -> 0 | N3: =IF(AND($R3="да",$H3<>""),ROUND($H3*$L3,2),0) -> 0 | O3: =IF(AND($R3="да",$H3<>""),ROUND($H3*$M3,2),0) -> 0 | P3: =$N3+$O3 -> 0 | Q3: =IFERROR(INDEX(Работы!$J$2:$J$6000,MATCH($C3,Работы!$A$2:$A$6000,0)),"") -> нетиповая | R3: да | T3: =IF(AND($P3>0,$R3="да"),MAX($T$1:$T2)+1,"")
A4: =IFERROR(INDEX(Работы!$D$2:$D$6000,MATCH($C4,Работы!$A$2:$A$6000,0)),"") -> Р1 | B4: =IFERROR(INDEX(Работы!$F$2:$F$6000,MATCH($C4,Работы!$A$2:$A$6000,0)),"") -> 1 | C4: =IFERROR(INDEX(Работы!$A$2:$A$6000,3),"") -> РАБ.Р1.1.003 | D4: =IFERROR(INDEX(Работы!$B$2:$B$6000,MATCH($C4,Работы!$A$2:$A$6000,0)),"") -> Рабочая документация по усилению/устройству несущих конструкций ("КР"), включая пояснительную записку (для помещений от 100 до 450 м.кв) | E4: =IFERROR(INDEX(Работы!$C$2:$C$6000,MATCH($C4,Работы!$A$2:$A$6000,0)),"") -> м2 | F4: =IFERROR(INDEX(Работы!$G$2:$G$6000,MATCH($C4,Работы!$A$2:$A$6000,0)),"") -> 0 | G4: =IFERROR(INDEX(Работы!$K$2:$K$6000,MATCH($C4,Работы!$A$2:$A$6000,0)),"") -> S_общая | J4: =IFERROR(INDEX(Материалы!$B$2:$B$9000,MATCH($I4,Материалы!$A$2:$A$9000,0)),"") | K4: =IF($I4="","",IF($F4=IFERROR(INDEX(Материалы!$G$2:$G$9000,MATCH($I4,Материалы!$A$2:$A$9000,0)),""),"OK","!! не та группа")) | L4: =IFERROR(INDEX(Работы!$H$2:$H$6000,MATCH($C4,Работы!$A$2:$A$6000,0))*(1-ДисконтТендер),0) -> 135.45 | M4: =IF($I4="",0,IFERROR(INDEX(Материалы!$I$2:$I$9000,MATCH($I4,Материалы!$A$2:$A$9000,0))*IF(INDEX(Материалы!$J$2:$J$9000,MATCH($I4,Материалы!$A$2:$A$9000,0))="USD",КурсUSD,IF(INDEX(Материалы!$J$2:$J$9000,MATCH($I4,Материалы!$A$2:$A$9000,0))="EUR",КурсEUR,1))*INDEX(Материалы!$K$2:$K$9000,MATCH($I4,Материалы!$A$2:$A$9000,0))*(1+IFERROR(INDEX(Работы!$I$2:$I$6000,MATCH($C4,Работы!$A$2:$A$6000,0))/100,0))*(1-ДисконтТендер),0)) -> 0 | N4: =IF(AND($R4="да",$H4<>""),ROUND($H4*$L4,2),0) -> 0 | O4: =IF(AND($R4="да",$H4<>""),ROUND($H4*$M4,2),0) -> 0 | P4: =$N4+$O4 -> 0 | Q4: =IFERROR(INDEX(Работы!$J$2:$J$6000,MATCH($C4,Работы!$A$2:$A$6000,0)),"") -> нетиповая | R4: да | T4: =IF(AND($P4>0,$R4="да"),MAX($T$1:$T3)+1,"")
A5: =IFERROR(INDEX(Работы!$D$2:$D$6000,MATCH($C5,Работы!$A$2:$A$6000,0)),"") -> Р1 | B5: =IFERROR(INDEX(Работы!$F$2:$F$6000,MATCH($C5,Работы!$A$2:$A$6000,0)),"") -> 1 | C5: =IFERROR(INDEX(Работы!$A$2:$A$6000,4),"") -> РАБ.Р1.1.004 | D5: =IFERROR(INDEX(Работы!$B$2:$B$6000,MATCH($C5,Работы!$A$2:$A$6000,0)),"") -> Рабочая документация "Архитектурные решения" ("АР"), включая пояснительную записку (для помещений от 100 до 450 м.кв) | E5: =IFERROR(INDEX(Работы!$C$2:$C$6000,MATCH($C5,Работы!$A$2:$A$6000,0)),"") -> м2 | F5: =IFERROR(INDEX(Работы!$G$2:$G$6000,MATCH($C5,Работы!$A$2:$A$6000,0)),"") -> 0 | G5: =IFERROR(INDEX(Работы!$K$2:$K$6000,MATCH($C5,Работы!$A$2:$A$6000,0)),"") -> S_общая | J5: =IFERROR(INDEX(Материалы!$B$2:$B$9000,MATCH($I5,Материалы!$A$2:$A$9000,0)),"") | K5: =IF($I5="","",IF($F5=IFERROR(INDEX(Материалы!$G$2:$G$9000,MATCH($I5,Материалы!$A$2:$A$9000,0)),""),"OK","!! не та группа")) | L5: =IFERROR(INDEX(Работы!$H$2:$H$6000,MATCH($C5,Работы!$A$2:$A$6000,0))*(1-ДисконтТендер),0) -> 389.55 | M5: =IF($I5="",0,IFERROR(INDEX(Материалы!$I$2:$I$9000,MATCH($I5,Материалы!$A$2:$A$9000,0))*IF(INDEX(Материалы!$J$2:$J$9000,MATCH($I5,Материалы!$A$2:$A$9000,0))="USD",КурсUSD,IF(INDEX(Материалы!$J$2:$J$9000,MATCH($I5,Материалы!$A$2:$A$9000,0))="EUR",КурсEUR,1))*INDEX(Материалы!$K$2:$K$9000,MATCH($I5,Материалы!$A$2:$A$9000,0))*(1+IFERROR(INDEX(Работы!$I$2:$I$6000,MATCH($C5,Работы!$A$2:$A$6000,0))/100,0))*(1-ДисконтТендер),0)) -> 0 | N5: =IF(AND($R5="да",$H5<>""),ROUND($H5*$L5,2),0) -> 0 | O5: =IF(AND($R5="да",$H5<>""),ROUND($H5*$M5,2),0) -> 0 | P5: =$N5+$O5 -> 0 | Q5: =IFERROR(INDEX(Работы!$J$2:$J$6000,MATCH($C5,Работы!$A$2:$A$6000,0)),"") -> типовая | R5: да | T5: =IF(AND($P5>0,$R5="да"),MAX($T$1:$T4)+1,"")
A6: =IFERROR(INDEX(Работы!$D$2:$D$6000,MATCH($C6,Работы!$A$2:$A$6000,0)),"") -> Р1 | B6: =IFERROR(INDEX(Работы!$F$2:$F$6000,MATCH($C6,Работы!$A$2:$A$6000,0)),"") -> 1 | C6: =IFERROR(INDEX(Работы!$A$2:$A$6000,5),"") -> РАБ.Р1.1.005 | D6: =IFERROR(INDEX(Работы!$B$2:$B$6000,MATCH($C6,Работы!$A$2:$A$6000,0)),"") -> Рабочая документация по электроснабжению и электроосвещению ("ЭОМ"), включая пояснительную записку (для помещений от 100 до 450 м.кв) | E6: =IFERROR(INDEX(Работы!$C$2:$C$6000,MATCH($C6,Работы!$A$2:$A$6000,0)),"") -> м2 | F6: =IFERROR(INDEX(Работы!$G$2:$G$6000,MATCH($C6,Работы!$A$2:$A$6000,0)),"") -> 0 | G6: =IFERROR(INDEX(Работы!$K$2:$K$6000,MATCH($C6,Работы!$A$2:$A$6000,0)),"") -> S_общая | J6: =IFERROR(INDEX(Материалы!$B$2:$B$9000,MATCH($I6,Материалы!$A$2:$A$9000,0)),"") | K6: =IF($I6="","",IF($F6=IFERROR(INDEX(Материалы!$G$2:$G$9000,MATCH($I6,Материалы!$A$2:$A$9000,0)),""),"OK","!! не та группа")) | L6: =IFERROR(INDEX(Работы!$H$2:$H$6000,MATCH($C6,Работы!$A$2:$A$6000,0))*(1-ДисконтТендер),0) -> 258.3 | M6: =IF($I6="",0,IFERROR(INDEX(Материалы!$I$2:$I$9000,MATCH($I6,Материалы!$A$2:$A$9000,0))*IF(INDEX(Материалы!$J$2:$J$9000,MATCH($I6,Материалы!$A$2:$A$9000,0))="USD",КурсUSD,IF(INDEX(Материалы!$J$2:$J$9000,MATCH($I6,Материалы!$A$2:$A$9000,0))="EUR",КурсEUR,1))*INDEX(Материалы!$K$2:$K$9000,MATCH($I6,Материалы!$A$2:$A$9000,0))*(1+IFERROR(INDEX(Работы!$I$2:$I$6000,MATCH($C6,Работы!$A$2:$A$6000,0))/100,0))*(1-ДисконтТендер),0)) -> 0 | N6: =IF(AND($R6="да",$H6<>""),ROUND($H6*$L6,2),0) -> 0 | O6: =IF(AND($R6="да",$H6<>""),ROUND($H6*$M6,2),0) -> 0 | P6: =$N6+$O6 -> 0 | Q6: =IFERROR(INDEX(Работы!$J$2:$J$6000,MATCH($C6,Работы!$A$2:$A$6000,0)),"") -> типовая | R6: да | T6: =IF(AND($P6>0,$R6="да"),MAX($T$1:$T5)+1,"")
A7: =IFERROR(INDEX(Работы!$D$2:$D$6000,MATCH($C7,Работы!$A$2:$A$6000,0)),"") -> Р1 | B7: =IFERROR(INDEX(Работы!$F$2:$F$6000,MATCH($C7,Работы!$A$2:$A$6000,0)),"") -> 1 | C7: =IFERROR(INDEX(Работы!$A$2:$A$6000,6),"") -> РАБ.Р1.1.006 | D7: =IFERROR(INDEX(Работы!$B$2:$B$6000,MATCH($C7,Работы!$A$2:$A$6000,0)),"") -> Рабочая документация Системы вентиляции ("ОВиК-В"), включая пояснительную записку (для помещений от 100 до 450 м.кв) | E7: =IFERROR(INDEX(Работы!$C$2:$C$6000,MATCH($C7,Работы!$A$2:$A$6000,0)),"") -> м2 | F7: =IFERROR(INDEX(Работы!$G$2:$G$6000,MATCH($C7,Работы!$A$2:$A$6000,0)),"") -> 0 | G7: =IFERROR(INDEX(Работы!$K$2:$K$6000,MATCH($C7,Работы!$A$2:$A$6000,0)),"") -> S_общая | J7: =IFERROR(INDEX(Материалы!$B$2:$B$9000,MATCH($I7,Материалы!$A$2:$A$9000,0)),"") | K7: =IF($I7="","",IF($F7=IFERROR(INDEX(Материалы!$G$2:$G$9000,MATCH($I7,Материалы!$A$2:$A$9000,0)),""),"OK","!! не та группа")) | L7: =IFERROR(INDEX(Работы!$H$2:$H$6000,MATCH($C7,Работы!$A$2:$A$6000,0))*(1-ДисконтТендер),0) -> 202.65 | M7: =IF($I7="",0,IFERROR(INDEX(Материалы!$I$2:$I$9000,MATCH($I7,Материалы!$A$2:$A$9000,0))*IF(INDEX(Материалы!$J$2:$J$9000,MATCH($I7,Материалы!$A$2:$A$9000,0))="USD",КурсUSD,IF(INDEX(Материалы!$J$2:$J$9000,MATCH($I7,Материалы!$A$2:$A$9000,0))="EUR",КурсEUR,1))*INDEX(Материалы!$K$2:$K$9000,MATCH($I7,Материалы!$A$2:$A$9000,0))*(1+IFERROR(INDEX(Работы!$I$2:$I$6000,MATCH($C7,Работы!$A$2:$A$6000,0))/100,0))*(1-ДисконтТендер),0)) -> 0 | N7: =IF(AND($R7="да",$H7<>""),ROUND($H7*$L7,2),0) -> 0 | O7: =IF(AND($R7="да",$H7<>""),ROUND($H7*$M7,2),0) -> 0 | P7: =$N7+$O7 -> 0 | Q7: =IFERROR(INDEX(Работы!$J$2:$J$6000,MATCH($C7,Работы!$A$2:$A$6000,0)),"") -> типовая | R7: да | T7: =IF(AND($P7>0,$R7="да"),MAX($T$1:$T6)+1,"")
A8: =IFERROR(INDEX(Работы!$D$2:$D$6000,MATCH($C8,Работы!$A$2:$A$6000,0)),"") -> Р1 | B8: =IFERROR(INDEX(Работы!$F$2:$F$6000,MATCH($C8,Работы!$A$2:$A$6000,0)),"") -> 1 | C8: =IFERROR(INDEX(Работы!$A$2:$A$6000,7),"") -> РАБ.Р1.1.007 | D8: =IFERROR(INDEX(Работы!$B$2:$B$6000,MATCH($C8,Работы!$A$2:$A$6000,0)),"") -> Рабочая документация Системы кондиционирования ("ОВиК-К"), включая пояснительную записку (для помещений от 100 до 450 м.кв) | E8: =IFERROR(INDEX(Работы!$C$2:$C$6000,MATCH($C8,Работы!$A$2:$A$6000,0)),"") -> м2 | F8: =IFERROR(INDEX(Работы!$G$2:$G$6000,MATCH($C8,Работы!$A$2:$A$6000,0)),"") -> 0 | G8: =IFERROR(INDEX(Работы!$K$2:$K$6000,MATCH($C8,Работы!$A$2:$A$6000,0)),"") -> S_общая | J8: =IFERROR(INDEX(Материалы!$B$2:$B$9000,MATCH($I8,Материалы!$A$2:$A$9000,0)),"") | K8: =IF($I8="","",IF($F8=IFERROR(INDEX(Материалы!$G$2:$G$9000,MATCH($I8,Материалы!$A$2:$A$9000,0)),""),"OK","!! не та группа")) | L8: =IFERROR(INDEX(Работы!$H$2:$H$6000,MATCH($C8,Работы!$A$2:$A$6000,0))*(1-ДисконтТендер),0) -> 159.48 | M8: =IF($I8="",0,IFERROR(INDEX(Материалы!$I$2:$I$9000,MATCH($I8,Материалы!$A$2:$A$9000,0))*IF(INDEX(Материалы!$J$2:$J$9000,MATCH($I8,Материалы!$A$2:$A$9000,0))="USD",КурсUSD,IF(INDEX(Материалы!$J$2:$J$9000,MATCH($I8,Материалы!$A$2:$A$9000,0))="EUR",КурсEUR,1))*INDEX(Материалы!$K$2:$K$9000,MATCH($I8,Материалы!$A$2:$A$9000,0))*(1+IFERROR(INDEX(Работы!$I$2:$I$6000,MATCH($C8,Работы!$A$2:$A$6000,0))/100,0))*(1-ДисконтТендер),0)) -> 0 | N8: =IF(AND($R8="да",$H8<>""),ROUND($H8*$L8,2),0) -> 0 | O8: =IF(AND($R8="да",$H8<>""),ROUND($H8*$M8,2),0) -> 0 | P8: =$N8+$O8 -> 0 | Q8: =IFERROR(INDEX(Работы!$J$2:$J$6000,MATCH($C8,Работы!$A$2:$A$6000,0)),"") -> типовая | R8: да | T8: =IF(AND($P8>0,$R8="да"),MAX($T$1:$T7)+1,"")
A9: =IFERROR(INDEX(Работы!$D$2:$D$6000,MATCH($C9,Работы!$A$2:$A$6000,0)),"") -> Р1 | B9: =IFERROR(INDEX(Работы!$F$2:$F$6000,MATCH($C9,Работы!$A$2:$A$6000,0)),"") -> 1 | C9: =IFERROR(INDEX(Работы!$A$2:$A$6000,8),"") -> РАБ.Р1.1.008 | D9: =IFERROR(INDEX(Работы!$B$2:$B$6000,MATCH($C9,Работы!$A$2:$A$6000,0)),"") -> Рабочая документация Системы отопления ("ОВиК-О"), включая Пояснительную записку и Теплотехнический расчет (для помещений от 100 до 450 м.кв) | E9: =IFERROR(INDEX(Работы!$C$2:$C$6000,MATCH($C9,Работы!$A$2:$A$6000,0)),"") -> м2 | F9: =IFERROR(INDEX(Работы!$G$2:$G$6000,MATCH($C9,Работы!$A$2:$A$6000,0)),"") -> 0 | G9: =IFERROR(INDEX(Работы!$K$2:$K$6000,MATCH($C9,Работы!$A$2:$A$6000,0)),"") -> S_общая | J9: =IFERROR(INDEX(Материалы!$B$2:$B$9000,MATCH($I9,Материалы!$A$2:$A$9000,0)),"") | K9: =IF($I9="","",IF($F9=IFERROR(INDEX(Материалы!$G$2:$G$9000,MATCH($I9,Материалы!$A$2:$A$9000,0)),""),"OK","!! не та группа")) | L9: =IFERROR(INDEX(Работы!$H$2:$H$6000,MATCH($C9,Работы!$A$2:$A$6000,0))*(1-ДисконтТендер),0) -> 123.9 | M9: =IF($I9="",0,IFERROR(INDEX(Материалы!$I$2:$I$9000,MATCH($I9,Материалы!$A$2:$A$9000,0))*IF(INDEX(Материалы!$J$2:$J$9000,MATCH($I9,Материалы!$A$2:$A$9000,0))="USD",КурсUSD,IF(INDEX(Материалы!$J$2:$J$9000,MATCH($I9,Материалы!$A$2:$A$9000,0))="EUR",КурсEUR,1))*INDEX(Материалы!$K$2:$K$9000,MATCH($I9,Материалы!$A$2:$A$9000,0))*(1+IFERROR(INDEX(Работы!$I$2:$I$6000,MATCH($C9,Работы!$A$2:$A$6000,0))/100,0))*(1-ДисконтТендер),0)) -> 0 | N9: =IF(AND($R9="да",$H9<>""),ROUND($H9*$L9,2),0) -> 0 | O9: =IF(AND($R9="да",$H9<>""),ROUND($H9*$M9,2),0) -> 0 | P9: =$N9+$O9 -> 0 | Q9: =IFERROR(INDEX(Работы!$J$2:$J$6000,MATCH($C9,Работы!$A$2:$A$6000,0)),"") -> типовая | R9: да | T9: =IF(AND($P9>0,$R9="да"),MAX($T$1:$T8)+1,"")
A10: =IFERROR(INDEX(Работы!$D$2:$D$6000,MATCH($C10,Работы!$A$2:$A$6000,0)),"") -> Р1 | B10: =IFERROR(INDEX(Работы!$F$2:$F$6000,MATCH($C10,Работы!$A$2:$A$6000,0)),"") -> 1 | C10: =IFERROR(INDEX(Работы!$A$2:$A$6000,9),"") -> РАБ.Р1.1.009 | D10: =IFERROR(INDEX(Работы!$B$2:$B$6000,MATCH($C10,Работы!$A$2:$A$6000,0)),"") -> Рабочая документация Системы водоснабжения и канализации ("ВК"), включая пояснительную записку (для помещений от 100 до 450 м.кв) | E10: =IFERROR(INDEX(Работы!$C$2:$C$6000,MATCH($C10,Работы!$A$2:$A$6000,0)),"") -> м2 | F10: =IFERROR(INDEX(Работы!$G$2:$G$6000,MATCH($C10,Работы!$A$2:$A$6000,0)),"") -> 0 | G10: =IFERROR(INDEX(Работы!$K$2:$K$6000,MATCH($C10,Работы!$A$2:$A$6000,0)),"") -> S_общая | J10: =IFERROR(INDEX(Материалы!$B$2:$B$9000,MATCH($I10,Материалы!$A$2:$A$9000,0)),"") | K10: =IF($I10="","",IF($F10=IFERROR(INDEX(Материалы!$G$2:$G$9000,MATCH($I10,Материалы!$A$2:$A$9000,0)),""),"OK","!! не та группа")) | L10: =IFERROR(INDEX(Работы!$H$2:$H$6000,MATCH($C10,Работы!$A$2:$A$6000,0))*(1-ДисконтТендер),0) -> 130.2 | M10: =IF($I10="",0,IFERROR(INDEX(Материалы!$I$2:$I$9000,MATCH($I10,Материалы!$A$2:$A$9000,0))*IF(INDEX(Материалы!$J$2:$J$9000,MATCH($I10,Материалы!$A$2:$A$9000,0))="USD",КурсUSD,IF(INDEX(Материалы!$J$2:$J$9000,MATCH($I10,Материалы!$A$2:$A$9000,0))="EUR",КурсEUR,1))*INDEX(Материалы!$K$2:$K$9000,MATCH($I10,Материалы!$A$2:$A$9000,0))*(1+IFERROR(INDEX(Работы!$I$2:$I$6000,MATCH($C10,Работы!$A$2:$A$6000,0))/100,0))*(1-ДисконтТендер),0)) -> 0 | N10: =IF(AND($R10="да",$H10<>""),ROUND($H10*$L10,2),0) -> 0 | O10: =IF(AND($R10="да",$H10<>""),ROUND($H10*$M10,2),0) -> 0 | P10: =$N10+$O10 -> 0 | Q10: =IFERROR(INDEX(Работы!$J$2:$J$6000,MATCH($C10,Работы!$A$2:$A$6000,0)),"") -> типовая | R10: да | T10: =IF(AND($P10>0,$R10="да"),MAX($T$1:$T9)+1,"")
A11: =IFERROR(INDEX(Работы!$D$2:$D$6000,MATCH($C11,Работы!$A$2:$A$6000,0)),"") -> Р1 | B11: =IFERROR(INDEX(Работы!$F$2:$F$6000,MATCH($C11,Работы!$A$2:$A$6000,0)),"") -> 1 | C11: =IFERROR(INDEX(Работы!$A$2:$A$6000,10),"") -> РАБ.Р1.1.010 | D11: =IFERROR(INDEX(Работы!$B$2:$B$6000,MATCH($C11,Работы!$A$2:$A$6000,0)),"") -> Рабочая документация Системы автоматической установки водяного пожаротушения ("АУВПТ"), (спринкерная, дренчерная, модульная система), включая пояснительную записку (для помещений о… | E11: =IFERROR(INDEX(Работы!$C$2:$C$6000,MATCH($C11,Работы!$A$2:$A$6000,0)),"") -> м2 | F11: =IFERROR(INDEX(Работы!$G$2:$G$6000,MATCH($C11,Работы!$A$2:$A$6000,0)),"") -> 0 | G11: =IFERROR(INDEX(Работы!$K$2:$K$6000,MATCH($C11,Работы!$A$2:$A$6000,0)),"") -> S_общая | J11: =IFERROR(INDEX(Материалы!$B$2:$B$9000,MATCH($I11,Материалы!$A$2:$A$9000,0)),"") | K11: =IF($I11="","",IF($F11=IFERROR(INDEX(Материалы!$G$2:$G$9000,MATCH($I11,Материалы!$A$2:$A$9000,0)),""),"OK","!! не та группа")) | L11: =IFERROR(INDEX(Работы!$H$2:$H$6000,MATCH($C11,Работы!$A$2:$A$6000,0))*(1-ДисконтТендер),0) -> 91.68 | M11: =IF($I11="",0,IFERROR(INDEX(Материалы!$I$2:$I$9000,MATCH($I11,Материалы!$A$2:$A$9000,0))*IF(INDEX(Материалы!$J$2:$J$9000,MATCH($I11,Материалы!$A$2:$A$9000,0))="USD",КурсUSD,IF(INDEX(Материалы!$J$2:$J$9000,MATCH($I11,Материалы!$A$2:$A$9000,0))="EUR",КурсEUR,1))*INDEX(Материалы!$K$2:$K$9000,MATCH($I11,Материалы!$A$2:$A$9000,0))*(1+IFERROR(INDEX(Работы!$I$2:$I$6000,MATCH($C11,Работы!$A$2:$A$6000,0))/100,0))*(1-ДисконтТендер),0)) -> 0 | N11: =IF(AND($R11="да",$H11<>""),ROUND($H11*$L11,2),0) -> 0 | O11: =IF(AND($R11="да",$H11<>""),ROUND($H11*$M11,2),0) -> 0 | P11: =$N11+$O11 -> 0 | Q11: =IFERROR(INDEX(Работы!$J$2:$J$6000,MATCH($C11,Работы!$A$2:$A$6000,0)),"") -> типовая | R11: да | T11: =IF(AND($P11>0,$R11="да"),MAX($T$1:$T10)+1,"")
A12: =IFERROR(INDEX(Работы!$D$2:$D$6000,MATCH($C12,Работы!$A$2:$A$6000,0)),"") -> Р1 | B12: =IFERROR(INDEX(Работы!$F$2:$F$6000,MATCH($C12,Работы!$A$2:$A$6000,0)),"") -> 1 | C12: =IFERROR(INDEX(Работы!$A$2:$A$6000,11),"") -> РАБ.Р1.1.011 | D12: =IFERROR(INDEX(Работы!$B$2:$B$6000,MATCH($C12,Работы!$A$2:$A$6000,0)),"") -> Рабочая документация Системы Внутреннего противопожарного водопровода ("ВПВ"), включая пояснительную записку (для помещений от 100 до 450 м.кв) | E12: =IFERROR(INDEX(Работы!$C$2:$C$6000,MATCH($C12,Работы!$A$2:$A$6000,0)),"") -> м2 | F12: =IFERROR(INDEX(Работы!$G$2:$G$6000,MATCH($C12,Работы!$A$2:$A$6000,0)),"") -> 0 | G12: =IFERROR(INDEX(Работы!$K$2:$K$6000,MATCH($C12,Работы!$A$2:$A$6000,0)),"") -> S_общая | J12: =IFERROR(INDEX(Материалы!$B$2:$B$9000,MATCH($I12,Материалы!$A$2:$A$9000,0)),"") | K12: =IF($I12="","",IF($F12=IFERROR(INDEX(Материалы!$G$2:$G$9000,MATCH($I12,Материалы!$A$2:$A$9000,0)),""),"OK","!! не та группа")) | L12: =IFERROR(INDEX(Работы!$H$2:$H$6000,MATCH($C12,Работы!$A$2:$A$6000,0))*(1-ДисконтТендер),0) -> 91.68 | M12: =IF($I12="",0,IFERROR(INDEX(Материалы!$I$2:$I$9000,MATCH($I12,Материалы!$A$2:$A$9000,0))*IF(INDEX(Материалы!$J$2:$J$9000,MATCH($I12,Материалы!$A$2:$A$9000,0))="USD",КурсUSD,IF(INDEX(Материалы!$J$2:$J$9000,MATCH($I12,Материалы!$A$2:$A$9000,0))="EUR",КурсEUR,1))*INDEX(Материалы!$K$2:$K$9000,MATCH($I12,Материалы!$A$2:$A$9000,0))*(1+IFERROR(INDEX(Работы!$I$2:$I$6000,MATCH($C12,Работы!$A$2:$A$6000,0))/100,0))*(1-ДисконтТендер),0)) -> 0 | N12: =IF(AND($R12="да",$H12<>""),ROUND($H12*$L12,2),0) -> 0 | O12: =IF(AND($R12="да",$H12<>""),ROUND($H12*$M12,2),0) -> 0 | P12: =$N12+$O12 -> 0 | Q12: =IFERROR(INDEX(Работы!$J$2:$J$6000,MATCH($C12,Работы!$A$2:$A$6000,0)),"") -> типовая | R12: да | T12: =IF(AND($P12>0,$R12="да"),MAX($T$1:$T11)+1,"")
A13: =IFERROR(INDEX(Работы!$D$2:$D$6000,MATCH($C13,Работы!$A$2:$A$6000,0)),"") -> Р1 | B13: =IFERROR(INDEX(Работы!$F$2:$F$6000,MATCH($C13,Работы!$A$2:$A$6000,0)),"") -> 1 | C13: =IFERROR(INDEX(Работы!$A$2:$A$6000,12),"") -> РАБ.Р1.1.012 | D13: =IFERROR(INDEX(Работы!$B$2:$B$6000,MATCH($C13,Работы!$A$2:$A$6000,0)),"") -> Рабочая документация Системы дымоудаления ("ДУ"), включая пояснительную записку (для помещений от 100 до 450 м.кв) | E13: =IFERROR(INDEX(Работы!$C$2:$C$6000,MATCH($C13,Работы!$A$2:$A$6000,0)),"") -> м2 | F13: =IFERROR(INDEX(Работы!$G$2:$G$6000,MATCH($C13,Работы!$A$2:$A$6000,0)),"") -> 0 | G13: =IFERROR(INDEX(Работы!$K$2:$K$6000,MATCH($C13,Работы!$A$2:$A$6000,0)),"") -> S_общая | J13: =IFERROR(INDEX(Материалы!$B$2:$B$9000,MATCH($I13,Материалы!$A$2:$A$9000,0)),"") | K13: =IF($I13="","",IF($F13=IFERROR(INDEX(Материалы!$G$2:$G$9000,MATCH($I13,Материалы!$A$2:$A$9000,0)),""),"OK","!! не та группа")) | L13: =IFERROR(INDEX(Работы!$H$2:$H$6000,MATCH($C13,Работы!$A$2:$A$6000,0))*(1-ДисконтТендер),0) -> 103.95 | M13: =IF($I13="",0,IFERROR(INDEX(Материалы!$I$2:$I$9000,MATCH($I13,Материалы!$A$2:$A$9000,0))*IF(INDEX(Материалы!$J$2:$J$9000,MATCH($I13,Материалы!$A$2:$A$9000,0))="USD",КурсUSD,IF(INDEX(Материалы!$J$2:$J$9000,MATCH($I13,Материалы!$A$2:$A$9000,0))="EUR",КурсEUR,1))*INDEX(Материалы!$K$2:$K$9000,MATCH($I13,Материалы!$A$2:$A$9000,0))*(1+IFERROR(INDEX(Работы!$I$2:$I$6000,MATCH($C13,Работы!$A$2:$A$6000,0))/100,0))*(1-ДисконтТендер),0)) -> 0 | N13: =IF(AND($R13="да",$H13<>""),ROUND($H13*$L13,2),0) -> 0 | O13: =IF(AND($R13="да",$H13<>""),ROUND($H13*$M13,2),0) -> 0 | P13: =$N13+$O13 -> 0 | Q13: =IFERROR(INDEX(Работы!$J$2:$J$6000,MATCH($C13,Работы!$A$2:$A$6000,0)),"") -> типовая | R13: да | T13: =IF(AND($P13>0,$R13="да"),MAX($T$1:$T12)+1,"")
A14: =IFERROR(INDEX(Работы!$D$2:$D$6000,MATCH($C14,Работы!$A$2:$A$6000,0)),"") -> Р1 | B14: =IFERROR(INDEX(Работы!$F$2:$F$6000,MATCH($C14,Работы!$A$2:$A$6000,0)),"") -> 1 | C14: =IFERROR(INDEX(Работы!$A$2:$A$6000,13),"") -> РАБ.Р1.1.013 | D14: =IFERROR(INDEX(Работы!$B$2:$B$6000,MATCH($C14,Работы!$A$2:$A$6000,0)),"") -> Рабочая документация "Автоматическая пожарная сигнализация" (АПС) | E14: =IFERROR(INDEX(Работы!$C$2:$C$6000,MATCH($C14,Работы!$A$2:$A$6000,0)),"") -> м2 | F14: =IFERROR(INDEX(Работы!$G$2:$G$6000,MATCH($C14,Работы!$A$2:$A$6000,0)),"") -> 0 | G14: =IFERROR(INDEX(Работы!$K$2:$K$6000,MATCH($C14,Работы!$A$2:$A$6000,0)),"") -> S_общая | J14: =IFERROR(INDEX(Материалы!$B$2:$B$9000,MATCH($I14,Материалы!$A$2:$A$9000,0)),"") | K14: =IF($I14="","",IF($F14=IFERROR(INDEX(Материалы!$G$2:$G$9000,MATCH($I14,Материалы!$A$2:$A$9000,0)),""),"OK","!! не та группа")) | L14: =IFERROR(INDEX(Работы!$H$2:$H$6000,MATCH($C14,Работы!$A$2:$A$6000,0))*(1-ДисконтТендер),0) -> 7.04 | M14: =IF($I14="",0,IFERROR(INDEX(Материалы!$I$2:$I$9000,MATCH($I14,Материалы!$A$2:$A$9000,0))*IF(INDEX(Материалы!$J$2:$J$9000,MATCH($I14,Материалы!$A$2:$A$9000,0))="USD",КурсUSD,IF(INDEX(Материалы!$J$2:$J$9000,MATCH($I14,Материалы!$A$2:$A$9000,0))="EUR",КурсEUR,1))*INDEX(Материалы!$K$2:$K$9000,MATCH($I14,Материалы!$A$2:$A$9000,0))*(1+IFERROR(INDEX(Работы!$I$2:$I$6000,MATCH($C14,Работы!$A$2:$A$6000,0))/100,0))*(1-ДисконтТендер),0)) -> 0 | N14: =IF(AND($R14="да",$H14<>""),ROUND($H14*$L14,2),0) -> 0 | O14: =IF(AND($R14="да",$H14<>""),ROUND($H14*$M14,2),0) -> 0 | P14: =$N14+$O14 -> 0 | Q14: =IFERROR(INDEX(Работы!$J$2:$J$6000,MATCH($C14,Работы!$A$2:$A$6000,0)),"") -> типовая | R14: да | T14: =IF(AND($P14>0,$R14="да"),MAX($T$1:$T13)+1,"")
A15: =IFERROR(INDEX(Работы!$D$2:$D$6000,MATCH($C15,Работы!$A$2:$A$6000,0)),"") -> Р1 | B15: =IFERROR(INDEX(Работы!$F$2:$F$6000,MATCH($C15,Работы!$A$2:$A$6000,0)),"") -> 1 | C15: =IFERROR(INDEX(Работы!$A$2:$A$6000,14),"") -> РАБ.Р1.1.014 | D15: =IFERROR(INDEX(Работы!$B$2:$B$6000,MATCH($C15,Работы!$A$2:$A$6000,0)),"") -> Рабочая документация "Система оповещения и управления эвакуацией людей при пожаре" (СОУЭ) | E15: =IFERROR(INDEX(Работы!$C$2:$C$6000,MATCH($C15,Работы!$A$2:$A$6000,0)),"") -> м2 | F15: =IFERROR(INDEX(Работы!$G$2:$G$6000,MATCH($C15,Работы!$A$2:$A$6000,0)),"") -> 0 | G15: =IFERROR(INDEX(Работы!$K$2:$K$6000,MATCH($C15,Работы!$A$2:$A$6000,0)),"") -> S_общая | J15: =IFERROR(INDEX(Материалы!$B$2:$B$9000,MATCH($I15,Материалы!$A$2:$A$9000,0)),"") | K15: =IF($I15="","",IF($F15=IFERROR(INDEX(Материалы!$G$2:$G$9000,MATCH($I15,Материалы!$A$2:$A$9000,0)),""),"OK","!! не та группа")) | L15: =IFERROR(INDEX(Работы!$H$2:$H$6000,MATCH($C15,Работы!$A$2:$A$6000,0))*(1-ДисконтТендер),0) -> 4.1 | M15: =IF($I15="",0,IFERROR(INDEX(Материалы!$I$2:$I$9000,MATCH($I15,Материалы!$A$2:$A$9000,0))*IF(INDEX(Материалы!$J$2:$J$9000,MATCH($I15,Материалы!$A$2:$A$9000,0))="USD",КурсUSD,IF(INDEX(Материалы!$J$2:$J$9000,MATCH($I15,Материалы!$A$2:$A$9000,0))="EUR",КурсEUR,1))*INDEX(Материалы!$K$2:$K$9000,MATCH($I15,Материалы!$A$2:$A$9000,0))*(1+IFERROR(INDEX(Работы!$I$2:$I$6000,MATCH($C15,Работы!$A$2:$A$6000,0))/100,0))*(1-ДисконтТендер),0)) -> 0 | N15: =IF(AND($R15="да",$H15<>""),ROUND($H15*$L15,2),0) -> 0 | O15: =IF(AND($R15="да",$H15<>""),ROUND($H15*$M15,2),0) -> 0 | P15: =$N15+$O15 -> 0 | Q15: =IFERROR(INDEX(Работы!$J$2:$J$6000,MATCH($C15,Работы!$A$2:$A$6000,0)),"") -> типовая | R15: да | T15: =IF(AND($P15>0,$R15="да"),MAX($T$1:$T14)+1,"")
A16: =IFERROR(INDEX(Работы!$D$2:$D$6000,MATCH($C16,Работы!$A$2:$A$6000,0)),"") -> Р1 | B16: =IFERROR(INDEX(Работы!$F$2:$F$6000,MATCH($C16,Работы!$A$2:$A$6000,0)),"") -> 1 | C16: =IFERROR(INDEX(Работы!$A$2:$A$6000,15),"") -> РАБ.Р1.1.015 | D16: =IFERROR(INDEX(Работы!$B$2:$B$6000,MATCH($C16,Работы!$A$2:$A$6000,0)),"") -> Рабочая документация "Автоматизация системы внутреннего противопожарного водопровода (ВПВ) | E16: =IFERROR(INDEX(Работы!$C$2:$C$6000,MATCH($C16,Работы!$A$2:$A$6000,0)),"") -> м2 | F16: =IFERROR(INDEX(Работы!$G$2:$G$6000,MATCH($C16,Работы!$A$2:$A$6000,0)),"") -> 0 | G16: =IFERROR(INDEX(Работы!$K$2:$K$6000,MATCH($C16,Работы!$A$2:$A$6000,0)),"") -> S_общая | J16: =IFERROR(INDEX(Материалы!$B$2:$B$9000,MATCH($I16,Материалы!$A$2:$A$9000,0)),"") | K16: =IF($I16="","",IF($F16=IFERROR(INDEX(Материалы!$G$2:$G$9000,MATCH($I16,Материалы!$A$2:$A$9000,0)),""),"OK","!! не та группа")) | L16: =IFERROR(INDEX(Работы!$H$2:$H$6000,MATCH($C16,Работы!$A$2:$A$6000,0))*(1-ДисконтТендер),0) -> 0.84 | M16: =IF($I16="",0,IFERROR(INDEX(Материалы!$I$2:$I$9000,MATCH($I16,Материалы!$A$2:$A$9000,0))*IF(INDEX(Материалы!$J$2:$J$9000,MATCH($I16,Материалы!$A$2:$A$9000,0))="USD",КурсUSD,IF(INDEX(Материалы!$J$2:$J$9000,MATCH($I16,Материалы!$A$2:$A$9000,0))="EUR",КурсEUR,1))*INDEX(Материалы!$K$2:$K$9000,MATCH($I16,Материалы!$A$2:$A$9000,0))*(1+IFERROR(INDEX(Работы!$I$2:$I$6000,MATCH($C16,Работы!$A$2:$A$6000,0))/100,0))*(1-ДисконтТендер),0)) -> 0 | N16: =IF(AND($R16="да",$H16<>""),ROUND($H16*$L16,2),0) -> 0 | O16: =IF(AND($R16="да",$H16<>""),ROUND($H16*$M16,2),0) -> 0 | P16: =$N16+$O16 -> 0 | Q16: =IFERROR(INDEX(Работы!$J$2:$J$6000,MATCH($C16,Работы!$A$2:$A$6000,0)),"") -> типовая | R16: да | T16: =IF(AND($P16>0,$R16="да"),MAX($T$1:$T15)+1,"")
A17: =IFERROR(INDEX(Работы!$D$2:$D$6000,MATCH($C17,Работы!$A$2:$A$6000,0)),"") -> Р1 | B17: =IFERROR(INDEX(Работы!$F$2:$F$6000,MATCH($C17,Работы!$A$2:$A$6000,0)),"") -> 1 | C17: =IFERROR(INDEX(Работы!$A$2:$A$6000,16),"") -> РАБ.Р1.1.016 | D17: =IFERROR(INDEX(Работы!$B$2:$B$6000,MATCH($C17,Работы!$A$2:$A$6000,0)),"") -> Рабочая документация "Автоматизация системы противодымной вентиляции (ПДВ")" | E17: =IFERROR(INDEX(Работы!$C$2:$C$6000,MATCH($C17,Работы!$A$2:$A$6000,0)),"") -> м2 | F17: =IFERROR(INDEX(Работы!$G$2:$G$6000,MATCH($C17,Работы!$A$2:$A$6000,0)),"") -> 0 | G17: =IFERROR(INDEX(Работы!$K$2:$K$6000,MATCH($C17,Работы!$A$2:$A$6000,0)),"") -> S_общая | J17: =IFERROR(INDEX(Материалы!$B$2:$B$9000,MATCH($I17,Материалы!$A$2:$A$9000,0)),"") | K17: =IF($I17="","",IF($F17=IFERROR(INDEX(Материалы!$G$2:$G$9000,MATCH($I17,Материалы!$A$2:$A$9000,0)),""),"OK","!! не та группа")) | L17: =IFERROR(INDEX(Работы!$H$2:$H$6000,MATCH($C17,Работы!$A$2:$A$6000,0))*(1-ДисконтТендер),0) -> 2.62 | M17: =IF($I17="",0,IFERROR(INDEX(Материалы!$I$2:$I$9000,MATCH($I17,Материалы!$A$2:$A$9000,0))*IF(INDEX(Материалы!$J$2:$J$9000,MATCH($I17,Материалы!$A$2:$A$9000,0))="USD",КурсUSD,IF(INDEX(Материалы!$J$2:$J$9000,MATCH($I17,Материалы!$A$2:$A$9000,0))="EUR",КурсEUR,1))*INDEX(Материалы!$K$2:$K$9000,MATCH($I17,Материалы!$A$2:$A$9000,0))*(1+IFERROR(INDEX(Работы!$I$2:$I$6000,MATCH($C17,Работы!$A$2:$A$6000,0))/100,0))*(1-ДисконтТендер),0)) -> 0 | N17: =IF(AND($R17="да",$H17<>""),ROUND($H17*$L17,2),0) -> 0 | O17: =IF(AND($R17="да",$H17<>""),ROUND($H17*$M17,2),0) -> 0 | P17: =$N17+$O17 -> 0 | Q17: =IFERROR(INDEX(Работы!$J$2:$J$6000,MATCH($C17,Работы!$A$2:$A$6000,0)),"") -> типовая | R17: да | T17: =IF(AND($P17>0,$R17="да"),MAX($T$1:$T16)+1,"")
A18: =IFERROR(INDEX(Работы!$D$2:$D$6000,MATCH($C18,Работы!$A$2:$A$6000,0)),"") -> Р1 | B18: =IFERROR(INDEX(Работы!$F$2:$F$6000,MATCH($C18,Работы!$A$2:$A$6000,0)),"") -> 1 | C18: =IFERROR(INDEX(Работы!$A$2:$A$6000,17),"") -> РАБ.Р1.1.017 | D18: =IFERROR(INDEX(Работы!$B$2:$B$6000,MATCH($C18,Работы!$A$2:$A$6000,0)),"") -> Рабочая документация "Автоматизация Системы отопления, вентиляции и кондиционирования (ОВиК)" | E18: =IFERROR(INDEX(Работы!$C$2:$C$6000,MATCH($C18,Работы!$A$2:$A$6000,0)),"") -> м2 | F18: =IFERROR(INDEX(Работы!$G$2:$G$6000,MATCH($C18,Работы!$A$2:$A$6000,0)),"") -> 0 | G18: =IFERROR(INDEX(Работы!$K$2:$K$6000,MATCH($C18,Работы!$A$2:$A$6000,0)),"") -> S_общая | J18: =IFERROR(INDEX(Материалы!$B$2:$B$9000,MATCH($I18,Материалы!$A$2:$A$9000,0)),"") | K18: =IF($I18="","",IF($F18=IFERROR(INDEX(Материалы!$G$2:$G$9000,MATCH($I18,Материалы!$A$2:$A$9000,0)),""),"OK","!! не та группа")) | L18: =IFERROR(INDEX(Работы!$H$2:$H$6000,MATCH($C18,Работы!$A$2:$A$6000,0))*(1-ДисконтТендер),0) -> 0.32 | M18: =IF($I18="",0,IFERROR(INDEX(Материалы!$I$2:$I$9000,MATCH($I18,Материалы!$A$2:$A$9000,0))*IF(INDEX(Материалы!$J$2:$J$9000,MATCH($I18,Материалы!$A$2:$A$9000,0))="USD",КурсUSD,IF(INDEX(Материалы!$J$2:$J$9000,MATCH($I18,Материалы!$A$2:$A$9000,0))="EUR",КурсEUR,1))*INDEX(Материалы!$K$2:$K$9000,MATCH($I18,Материалы!$A$2:$A$9000,0))*(1+IFERROR(INDEX(Работы!$I$2:$I$6000,MATCH($C18,Работы!$A$2:$A$6000,0))/100,0))*(1-ДисконтТендер),0)) -> 0 | N18: =IF(AND($R18="да",$H18<>""),ROUND($H18*$L18,2),0) -> 0 | O18: =IF(AND($R18="да",$H18<>""),ROUND($H18*$M18,2),0) -> 0 | P18: =$N18+$O18 -> 0 | Q18: =IFERROR(INDEX(Работы!$J$2:$J$6000,MATCH($C18,Работы!$A$2:$A$6000,0)),"") -> типовая | R18: да | T18: =IF(AND($P18>0,$R18="да"),MAX($T$1:$T17)+1,"")
A19: =IFERROR(INDEX(Работы!$D$2:$D$6000,MATCH($C19,Работы!$A$2:$A$6000,0)),"") -> Р1 | B19: =IFERROR(INDEX(Работы!$F$2:$F$6000,MATCH($C19,Работы!$A$2:$A$6000,0)),"") -> 1 | C19: =IFERROR(INDEX(Работы!$A$2:$A$6000,18),"") -> РАБ.Р1.1.018 | D19: =IFERROR(INDEX(Работы!$B$2:$B$6000,MATCH($C19,Работы!$A$2:$A$6000,0)),"") -> Рабочая документация "Автоматизация Системы аварийного освещения (АО)" | E19: =IFERROR(INDEX(Работы!$C$2:$C$6000,MATCH($C19,Работы!$A$2:$A$6000,0)),"") -> м2 | F19: =IFERROR(INDEX(Работы!$G$2:$G$6000,MATCH($C19,Работы!$A$2:$A$6000,0)),"") -> 0 | G19: =IFERROR(INDEX(Работы!$K$2:$K$6000,MATCH($C19,Работы!$A$2:$A$6000,0)),"") -> S_общая | J19: =IFERROR(INDEX(Материалы!$B$2:$B$9000,MATCH($I19,Материалы!$A$2:$A$9000,0)),"") | K19: =IF($I19="","",IF($F19=IFERROR(INDEX(Материалы!$G$2:$G$9000,MATCH($I19,Материалы!$A$2:$A$9000,0)),""),"OK","!! не та группа")) | L19: =IFERROR(INDEX(Работы!$H$2:$H$6000,MATCH($C19,Работы!$A$2:$A$6000,0))*(1-ДисконтТендер),0) -> 0.11 | M19: =IF($I19="",0,IFERROR(INDEX(Материалы!$I$2:$I$9000,MATCH($I19,Материалы!$A$2:$A$9000,0))*IF(INDEX(Материалы!$J$2:$J$9000,MATCH($I19,Материалы!$A$2:$A$9000,0))="USD",КурсUSD,IF(INDEX(Материалы!$J$2:$J$9000,MATCH($I19,Материалы!$A$2:$A$9000,0))="EUR",КурсEUR,1))*INDEX(Материалы!$K$2:$K$9000,MATCH($I19,Материалы!$A$2:$A$9000,0))*(1+IFERROR(INDEX(Работы!$I$2:$I$6000,MATCH($C19,Работы!$A$2:$A$6000,0))/100,0))*(1-ДисконтТендер),0)) -> 0 | N19: =IF(AND($R19="да",$H19<>""),ROUND($H19*$L19,2),0) -> 0 | O19: =IF(AND($R19="да",$H19<>""),ROUND($H19*$M19,2),0) -> 0 | P19: =$N19+$O19 -> 0 | Q19: =IFERROR(INDEX(Работы!$J$2:$J$6000,MATCH($C19,Работы!$A$2:$A$6000,0)),"") -> типовая | R19: да | T19: =IF(AND($P19>0,$R19="да"),MAX($T$1:$T18)+1,"")
A20: =IFERROR(INDEX(Работы!$D$2:$D$6000,MATCH($C20,Работы!$A$2:$A$6000,0)),"") -> Р1 | B20: =IFERROR(INDEX(Работы!$F$2:$F$6000,MATCH($C20,Работы!$A$2:$A$6000,0)),"") -> 1 | C20: =IFERROR(INDEX(Работы!$A$2:$A$6000,19),"") -> РАБ.Р1.1.019 | D20: =IFERROR(INDEX(Работы!$B$2:$B$6000,MATCH($C20,Работы!$A$2:$A$6000,0)),"") -> Рабочая документация "Автоматизации лифтовового хозяйства" | E20: =IFERROR(INDEX(Работы!$C$2:$C$6000,MATCH($C20,Работы!$A$2:$A$6000,0)),"") -> м2 | F20: =IFERROR(INDEX(Работы!$G$2:$G$6000,MATCH($C20,Работы!$A$2:$A$6000,0)),"") -> 0 | G20: =IFERROR(INDEX(Работы!$K$2:$K$6000,MATCH($C20,Работы!$A$2:$A$6000,0)),"") -> S_общая | J20: =IFERROR(INDEX(Материалы!$B$2:$B$9000,MATCH($I20,Материалы!$A$2:$A$9000,0)),"") | K20: =IF($I20="","",IF($F20=IFERROR(INDEX(Материалы!$G$2:$G$9000,MATCH($I20,Материалы!$A$2:$A$9000,0)),""),"OK","!! не та группа")) | L20: =IFERROR(INDEX(Работы!$H$2:$H$6000,MATCH($C20,Работы!$A$2:$A$6000,0))*(1-ДисконтТендер),0) -> 0.11 | M20: =IF($I20="",0,IFERROR(INDEX(Материалы!$I$2:$I$9000,MATCH($I20,Материалы!$A$2:$A$9000,0))*IF(INDEX(Материалы!$J$2:$J$9000,MATCH($I20,Материалы!$A$2:$A$9000,0))="USD",КурсUSD,IF(INDEX(Материалы!$J$2:$J$9000,MATCH($I20,Материалы!$A$2:$A$9000,0))="EUR",КурсEUR,1))*INDEX(Материалы!$K$2:$K$9000,MATCH($I20,Материалы!$A$2:$A$9000,0))*(1+IFERROR(INDEX(Работы!$I$2:$I$6000,MATCH($C20,Работы!$A$2:$A$6000,0))/100,0))*(1-ДисконтТендер),0)) -> 0 | N20: =IF(AND($R20="да",$H20<>""),ROUND($H20*$L20,2),0) -> 0 | O20: =IF(AND($R20="да",$H20<>""),ROUND($H20*$M20,2),0) -> 0 | P20: =$N20+$O20 -> 0 | Q20: =IFERROR(INDEX(Работы!$J$2:$J$6000,MATCH($C20,Работы!$A$2:$A$6000,0)),"") -> нетиповая | R20: да | T20: =IF(AND($P20>0,$R20="да"),MAX($T$1:$T19)+1,"")
A21: =IFERROR(INDEX(Работы!$D$2:$D$6000,MATCH($C21,Работы!$A$2:$A$6000,0)),"") -> Р1 | B21: =IFERROR(INDEX(Работы!$F$2:$F$6000,MATCH($C21,Работы!$A$2:$A$6000,0)),"") -> 1 | C21: =IFERROR(INDEX(Работы!$A$2:$A$6000,20),"") -> РАБ.Р1.1.020 | D21: =IFERROR(INDEX(Работы!$B$2:$B$6000,MATCH($C21,Работы!$A$2:$A$6000,0)),"") -> Рабочая документация "Автоматизации Системы контроля управления доступом (СКУД)" | E21: =IFERROR(INDEX(Работы!$C$2:$C$6000,MATCH($C21,Работы!$A$2:$A$6000,0)),"") -> м2 | F21: =IFERROR(INDEX(Работы!$G$2:$G$6000,MATCH($C21,Работы!$A$2:$A$6000,0)),"") -> 0 | G21: =IFERROR(INDEX(Работы!$K$2:$K$6000,MATCH($C21,Работы!$A$2:$A$6000,0)),"") -> S_общая | J21: =IFERROR(INDEX(Материалы!$B$2:$B$9000,MATCH($I21,Материалы!$A$2:$A$9000,0)),"") | K21: =IF($I21="","",IF($F21=IFERROR(INDEX(Материалы!$G$2:$G$9000,MATCH($I21,Материалы!$A$2:$A$9000,0)),""),"OK","!! не та группа")) | L21: =IFERROR(INDEX(Работы!$H$2:$H$6000,MATCH($C21,Работы!$A$2:$A$6000,0))*(1-ДисконтТендер),0) -> 0.11 | M21: =IF($I21="",0,IFERROR(INDEX(Материалы!$I$2:$I$9000,MATCH($I21,Материалы!$A$2:$A$9000,0))*IF(INDEX(Материалы!$J$2:$J$9000,MATCH($I21,Материалы!$A$2:$A$9000,0))="USD",КурсUSD,IF(INDEX(Материалы!$J$2:$J$9000,MATCH($I21,Материалы!$A$2:$A$9000,0))="EUR",КурсEUR,1))*INDEX(Материалы!$K$2:$K$9000,MATCH($I21,Материалы!$A$2:$A$9000,0))*(1+IFERROR(INDEX(Работы!$I$2:$I$6000,MATCH($C21,Работы!$A$2:$A$6000,0))/100,0))*(1-ДисконтТендер),0)) -> 0 | N21: =IF(AND($R21="да",$H21<>""),ROUND($H21*$L21,2),0) -> 0 | O21: =IF(AND($R21="да",$H21<>""),ROUND($H21*$M21,2),0) -> 0 | P21: =$N21+$O21 -> 0 | Q21: =IFERROR(INDEX(Работы!$J$2:$J$6000,MATCH($C21,Работы!$A$2:$A$6000,0)),"") -> типовая | R21: да | T21: =IF(AND($P21>0,$R21="да"),MAX($T$1:$T20)+1,"")
A22: =IFERROR(INDEX(Работы!$D$2:$D$6000,MATCH($C22,Работы!$A$2:$A$6000,0)),"") -> Р1 | B22: =IFERROR(INDEX(Работы!$F$2:$F$6000,MATCH($C22,Работы!$A$2:$A$6000,0)),"") -> 1 | C22: =IFERROR(INDEX(Работы!$A$2:$A$6000,21),"") -> РАБ.Р1.1.021 | D22: =IFERROR(INDEX(Работы!$B$2:$B$6000,MATCH($C22,Работы!$A$2:$A$6000,0)),"") -> Техническое обследование состояния несущих конструкций помещения с подготовкой рекомендаций по усилению в зоне расположения депозитария, кассового узла и банкоматов (Техничесекое з… | E22: =IFERROR(INDEX(Работы!$C$2:$C$6000,MATCH($C22,Работы!$A$2:$A$6000,0)),"") -> м2 | F22: =IFERROR(INDEX(Работы!$G$2:$G$6000,MATCH($C22,Работы!$A$2:$A$6000,0)),"") -> 0 | G22: =IFERROR(INDEX(Работы!$K$2:$K$6000,MATCH($C22,Работы!$A$2:$A$6000,0)),"") -> S_общая | J22: =IFERROR(INDEX(Материалы!$B$2:$B$9000,MATCH($I22,Материалы!$A$2:$A$9000,0)),"") | K22: =IF($I22="","",IF($F22=IFERROR(INDEX(Материалы!$G$2:$G$9000,MATCH($I22,Материалы!$A$2:$A$9000,0)),""),"OK","!! не та группа")) | L22: =IFERROR(INDEX(Работы!$H$2:$H$6000,MATCH($C22,Работы!$A$2:$A$6000,0))*(1-ДисконтТендер),0) -> 3675 | M22: =IF($I22="",0,IFERROR(INDEX(Материалы!$I$2:$I$9000,MATCH($I22,Материалы!$A$2:$A$9000,0))*IF(INDEX(Материалы!$J$2:$J$9000,MATCH($I22,Материалы!$A$2:$A$9000,0))="USD",КурсUSD,IF(INDEX(Материалы!$J$2:$J$9000,MATCH($I22,Материалы!$A$2:$A$9000,0))="EUR",КурсEUR,1))*INDEX(Материалы!$K$2:$K$9000,MATCH($I22,Материалы!$A$2:$A$9000,0))*(1+IFERROR(INDEX(Работы!$I$2:$I$6000,MATCH($C22,Работы!$A$2:$A$6000,0))/100,0))*(1-ДисконтТендер),0)) -> 0 | N22: =IF(AND($R22="да",$H22<>""),ROUND($H22*$L22,2),0) -> 0 | O22: =IF(AND($R22="да",$H22<>""),ROUND($H22*$M22,2),0) -> 0 | P22: =$N22+$O22 -> 0 | Q22: =IFERROR(INDEX(Работы!$J$2:$J$6000,MATCH($C22,Работы!$A$2:$A$6000,0)),"") -> нетиповая | R22: да | T22: =IF(AND($P22>0,$R22="да"),MAX($T$1:$T21)+1,"")
A23: =IFERROR(INDEX(Работы!$D$2:$D$6000,MATCH($C23,Работы!$A$2:$A$6000,0)),"") -> Р1 | B23: =IFERROR(INDEX(Работы!$F$2:$F$6000,MATCH($C23,Работы!$A$2:$A$6000,0)),"") -> 1 | C23: =IFERROR(INDEX(Работы!$A$2:$A$6000,22),"") -> РАБ.Р1.1.022 | D23: =IFERROR(INDEX(Работы!$B$2:$B$6000,MATCH($C23,Работы!$A$2:$A$6000,0)),"") -> Эскизный проект фасада и колористический паспорт с указанием ведомости отделки и проектным решением со спецификацией элементов (крыльцо, пандус, навесы, колонны и т.д.)(для фасадов… | E23: =IFERROR(INDEX(Работы!$C$2:$C$6000,MATCH($C23,Работы!$A$2:$A$6000,0)),"") -> кв.м.площади фасада | F23: =IFERROR(INDEX(Работы!$G$2:$G$6000,MATCH($C23,Работы!$A$2:$A$6000,0)),"") -> 0 | G23: =IFERROR(INDEX(Работы!$K$2:$K$6000,MATCH($C23,Работы!$A$2:$A$6000,0)),"") -> S_общая | J23: =IFERROR(INDEX(Материалы!$B$2:$B$9000,MATCH($I23,Материалы!$A$2:$A$9000,0)),"") | K23: =IF($I23="","",IF($F23=IFERROR(INDEX(Материалы!$G$2:$G$9000,MATCH($I23,Материалы!$A$2:$A$9000,0)),""),"OK","!! не та группа")) | L23: =IFERROR(INDEX(Работы!$H$2:$H$6000,MATCH($C23,Работы!$A$2:$A$6000,0))*(1-ДисконтТендер),0) -> 7822.5 | M23: =IF($I23="",0,IFERROR(INDEX(Материалы!$I$2:$I$9000,MATCH($I23,Материалы!$A$2:$A$9000,0))*IF(INDEX(Материалы!$J$2:$J$9000,MATCH($I23,Материалы!$A$2:$A$9000,0))="USD",КурсUSD,IF(INDEX(Материалы!$J$2:$J$9000,MATCH($I23,Материалы!$A$2:$A$9000,0))="EUR",КурсEUR,1))*INDEX(Материалы!$K$2:$K$9000,MATCH($I23,Материалы!$A$2:$A$9000,0))*(1+IFERROR(INDEX(Работы!$I$2:$I$6000,MATCH($C23,Работы!$A$2:$A$6000,0))/100,0))*(1-ДисконтТендер),0)) -> 0 | N23: =IF(AND($R23="да",$H23<>""),ROUND($H23*$L23,2),0) -> 0 | O23: =IF(AND($R23="да",$H23<>""),ROUND($H23*$M23,2),0) -> 0 | P23: =$N23+$O23 -> 0 | Q23: =IFERROR(INDEX(Работы!$J$2:$J$6000,MATCH($C23,Работы!$A$2:$A$6000,0)),"") -> нетиповая | R23: да | T23: =IF(AND($P23>0,$R23="да"),MAX($T$1:$T22)+1,"")
A24: =IFERROR(INDEX(Работы!$D$2:$D$6000,MATCH($C24,Работы!$A$2:$A$6000,0)),"") -> Р1 | B24: =IFERROR(INDEX(Работы!$F$2:$F$6000,MATCH($C24,Работы!$A$2:$A$6000,0)),"") -> 1 | C24: =IFERROR(INDEX(Работы!$A$2:$A$6000,23),"") -> РАБ.Р1.1.023 | D24: =IFERROR(INDEX(Работы!$B$2:$B$6000,MATCH($C24,Работы!$A$2:$A$6000,0)),"") -> Рабочая документация по усилению/устройству несущих конструкций ("КР"), включая пояснительную записку (для помещений менее 100 м.кв) | E24: =IFERROR(INDEX(Работы!$C$2:$C$6000,MATCH($C24,Работы!$A$2:$A$6000,0)),"") -> компл. | F24: =IFERROR(INDEX(Работы!$G$2:$G$6000,MATCH($C24,Работы!$A$2:$A$6000,0)),"") -> 0 | G24: =IFERROR(INDEX(Работы!$K$2:$K$6000,MATCH($C24,Работы!$A$2:$A$6000,0)),"") -> S_общая | J24: =IFERROR(INDEX(Материалы!$B$2:$B$9000,MATCH($I24,Материалы!$A$2:$A$9000,0)),"") | K24: =IF($I24="","",IF($F24=IFERROR(INDEX(Материалы!$G$2:$G$9000,MATCH($I24,Материалы!$A$2:$A$9000,0)),""),"OK","!! не та группа")) | L24: =IFERROR(INDEX(Работы!$H$2:$H$6000,MATCH($C24,Работы!$A$2:$A$6000,0))*(1-ДисконтТендер),0) -> 10500 | M24: =IF($I24="",0,IFERROR(INDEX(Материалы!$I$2:$I$9000,MATCH($I24,Материалы!$A$2:$A$9000,0))*IF(INDEX(Материалы!$J$2:$J$9000,MATCH($I24,Материалы!$A$2:$A$9000,0))="USD",КурсUSD,IF(INDEX(Материалы!$J$2:$J$9000,MATCH($I24,Материалы!$A$2:$A$9000,0))="EUR",КурсEUR,1))*INDEX(Материалы!$K$2:$K$9000,MATCH($I24,Материалы!$A$2:$A$9000,0))*(1+IFERROR(INDEX(Работы!$I$2:$I$6000,MATCH($C24,Работы!$A$2:$A$6000,0))/100,0))*(1-ДисконтТендер),0)) -> 0 | N24: =IF(AND($R24="да",$H24<>""),ROUND($H24*$L24,2),0) -> 0 | O24: =IF(AND($R24="да",$H24<>""),ROUND($H24*$M24,2),0) -> 0 | P24: =$N24+$O24 -> 0 | Q24: =IFERROR(INDEX(Работы!$J$2:$J$6000,MATCH($C24,Работы!$A$2:$A$6000,0)),"") -> нетиповая | R24: да | T24: =IF(AND($P24>0,$R24="да"),MAX($T$1:$T23)+1,"")
A25: =IFERROR(INDEX(Работы!$D$2:$D$6000,MATCH($C25,Работы!$A$2:$A$6000,0)),"") -> Р1 | B25: =IFERROR(INDEX(Работы!$F$2:$F$6000,MATCH($C25,Работы!$A$2:$A$6000,0)),"") -> 1 | C25: =IFERROR(INDEX(Работы!$A$2:$A$6000,24),"") -> РАБ.Р1.1.024 | D25: =IFERROR(INDEX(Работы!$B$2:$B$6000,MATCH($C25,Работы!$A$2:$A$6000,0)),"") -> Рабочая документация "Архитектурные решения" ("АР"), включая пояснительную записку (для помещений менее 100 м.кв) | E25: =IFERROR(INDEX(Работы!$C$2:$C$6000,MATCH($C25,Работы!$A$2:$A$6000,0)),"") -> компл. | F25: =IFERROR(INDEX(Работы!$G$2:$G$6000,MATCH($C25,Работы!$A$2:$A$6000,0)),"") -> 0 | G25: =IFERROR(INDEX(Работы!$K$2:$K$6000,MATCH($C25,Работы!$A$2:$A$6000,0)),"") -> S_общая | J25: =IFERROR(INDEX(Материалы!$B$2:$B$9000,MATCH($I25,Материалы!$A$2:$A$9000,0)),"") | K25: =IF($I25="","",IF($F25=IFERROR(INDEX(Материалы!$G$2:$G$9000,MATCH($I25,Материалы!$A$2:$A$9000,0)),""),"OK","!! не та группа")) | L25: =IFERROR(INDEX(Работы!$H$2:$H$6000,MATCH($C25,Работы!$A$2:$A$6000,0))*(1-ДисконтТендер),0) -> 20737.5 | M25: =IF($I25="",0,IFERROR(INDEX(Материалы!$I$2:$I$9000,MATCH($I25,Материалы!$A$2:$A$9000,0))*IF(INDEX(Материалы!$J$2:$J$9000,MATCH($I25,Материалы!$A$2:$A$9000,0))="USD",КурсUSD,IF(INDEX(Материалы!$J$2:$J$9000,MATCH($I25,Материалы!$A$2:$A$9000,0))="EUR",КурсEUR,1))*INDEX(Материалы!$K$2:$K$9000,MATCH($I25,Материалы!$A$2:$A$9000,0))*(1+IFERROR(INDEX(Работы!$I$2:$I$6000,MATCH($C25,Работы!$A$2:$A$6000,0))/100,0))*(1-ДисконтТендер),0)) -> 0 | N25: =IF(AND($R25="да",$H25<>""),ROUND($H25*$L25,2),0) -> 0 | O25: =IF(AND($R25="да",$H25<>""),ROUND($H25*$M25,2),0) -> 0 | P25: =$N25+$O25 -> 0 | Q25: =IFERROR(INDEX(Работы!$J$2:$J$6000,MATCH($C25,Работы!$A$2:$A$6000,0)),"") -> типовая | R25: да | T25: =IF(AND($P25>0,$R25="да"),MAX($T$1:$T24)+1,"")
A26: =IFERROR(INDEX(Работы!$D$2:$D$6000,MATCH($C26,Работы!$A$2:$A$6000,0)),"") -> Р1 | B26: =IFERROR(INDEX(Работы!$F$2:$F$6000,MATCH($C26,Работы!$A$2:$A$6000,0)),"") -> 1 | C26: =IFERROR(INDEX(Работы!$A$2:$A$6000,25),"") -> РАБ.Р1.1.025 | D26: =IFERROR(INDEX(Работы!$B$2:$B$6000,MATCH($C26,Работы!$A$2:$A$6000,0)),"") -> Рабочая документация по электроснабжению и электроосвещению ("ЭОМ"), включая пояснительную записку (для помещений менее 100 м.кв) | E26: =IFERROR(INDEX(Работы!$C$2:$C$6000,MATCH($C26,Работы!$A$2:$A$6000,0)),"") -> компл. | F26: =IFERROR(INDEX(Работы!$G$2:$G$6000,MATCH($C26,Работы!$A$2:$A$6000,0)),"") -> 0 | G26: =IFERROR(INDEX(Работы!$K$2:$K$6000,MATCH($C26,Работы!$A$2:$A$6000,0)),"") -> S_общая | J26: =IFERROR(INDEX(Материалы!$B$2:$B$9000,MATCH($I26,Материалы!$A$2:$A$9000,0)),"") | K26: =IF($I26="","",IF($F26=IFERROR(INDEX(Материалы!$G$2:$G$9000,MATCH($I26,Материалы!$A$2:$A$9000,0)),""),"OK","!! не та группа")) | L26: =IFERROR(INDEX(Работы!$H$2:$H$6000,MATCH($C26,Работы!$A$2:$A$6000,0))*(1-ДисконтТендер),0) -> 20737.5 | M26: =IF($I26="",0,IFERROR(INDEX(Материалы!$I$2:$I$9000,MATCH($I26,Материалы!$A$2:$A$9000,0))*IF(INDEX(Материалы!$J$2:$J$9000,MATCH($I26,Материалы!$A$2:$A$9000,0))="USD",КурсUSD,IF(INDEX(Материалы!$J$2:$J$9000,MATCH($I26,Материалы!$A$2:$A$9000,0))="EUR",КурсEUR,1))*INDEX(Материалы!$K$2:$K$9000,MATCH($I26,Материалы!$A$2:$A$9000,0))*(1+IFERROR(INDEX(Работы!$I$2:$I$6000,MATCH($C26,Работы!$A$2:$A$6000,0))/100,0))*(1-ДисконтТендер),0)) -> 0 | N26: =IF(AND($R26="да",$H26<>""),ROUND($H26*$L26,2),0) -> 0 | O26: =IF(AND($R26="да",$H26<>""),ROUND($H26*$M26,2),0) -> 0 | P26: =$N26+$O26 -> 0 | Q26: =IFERROR(INDEX(Работы!$J$2:$J$6000,MATCH($C26,Работы!$A$2:$A$6000,0)),"") -> типовая | R26: да | T26: =IF(AND($P26>0,$R26="да"),MAX($T$1:$T25)+1,"")
A27: =IFERROR(INDEX(Работы!$D$2:$D$6000,MATCH($C27,Работы!$A$2:$A$6000,0)),"") -> Р1 | B27: =IFERROR(INDEX(Работы!$F$2:$F$6000,MATCH($C27,Работы!$A$2:$A$6000,0)),"") -> 1 | C27: =IFERROR(INDEX(Работы!$A$2:$A$6000,26),"") -> РАБ.Р1.1.026 | D27: =IFERROR(INDEX(Работы!$B$2:$B$6000,MATCH($C27,Работы!$A$2:$A$6000,0)),"") -> Рабочая документация Системы вентиляции ("ОВиК-В"), включая пояснительную записку (для помещений менее 100 м.кв) | E27: =IFERROR(INDEX(Работы!$C$2:$C$6000,MATCH($C27,Работы!$A$2:$A$6000,0)),"") -> компл. | F27: =IFERROR(INDEX(Работы!$G$2:$G$6000,MATCH($C27,Работы!$A$2:$A$6000,0)),"") -> 0 | G27: =IFERROR(INDEX(Работы!$K$2:$K$6000,MATCH($C27,Работы!$A$2:$A$6000,0)),"") -> S_общая | J27: =IFERROR(INDEX(Материалы!$B$2:$B$9000,MATCH($I27,Материалы!$A$2:$A$9000,0)),"") | K27: =IF($I27="","",IF($F27=IFERROR(INDEX(Материалы!$G$2:$G$9000,MATCH($I27,Материалы!$A$2:$A$9000,0)),""),"OK","!! не та группа")) | L27: =IFERROR(INDEX(Работы!$H$2:$H$6000,MATCH($C27,Работы!$A$2:$A$6000,0))*(1-ДисконтТендер),0) -> 15592.5 | M27: =IF($I27="",0,IFERROR(INDEX(Материалы!$I$2:$I$9000,MATCH($I27,Материалы!$A$2:$A$9000,0))*IF(INDEX(Материалы!$J$2:$J$9000,MATCH($I27,Материалы!$A$2:$A$9000,0))="USD",КурсUSD,IF(INDEX(Материалы!$J$2:$J$9000,MATCH($I27,Материалы!$A$2:$A$9000,0))="EUR",КурсEUR,1))*INDEX(Материалы!$K$2:$K$9000,MATCH($I27,Материалы!$A$2:$A$9000,0))*(1+IFERROR(INDEX(Работы!$I$2:$I$6000,MATCH($C27,Работы!$A$2:$A$6000,0))/100,0))*(1-ДисконтТендер),0)) -> 0 | N27: =IF(AND($R27="да",$H27<>""),ROUND($H27*$L27,2),0) -> 0 | O27: =IF(AND($R27="да",$H27<>""),ROUND($H27*$M27,2),0) -> 0 | P27: =$N27+$O27 -> 0 | Q27: =IFERROR(INDEX(Работы!$J$2:$J$6000,MATCH($C27,Работы!$A$2:$A$6000,0)),"") -> типовая | R27: да | T27: =IF(AND($P27>0,$R27="да"),MAX($T$1:$T26)+1,"")
A28: =IFERROR(INDEX(Работы!$D$2:$D$6000,MATCH($C28,Работы!$A$2:$A$6000,0)),"") -> Р1 | B28: =IFERROR(INDEX(Работы!$F$2:$F$6000,MATCH($C28,Работы!$A$2:$A$6000,0)),"") -> 1 | C28: =IFERROR(INDEX(Работы!$A$2:$A$6000,27),"") -> РАБ.Р1.1.027 | D28: =IFERROR(INDEX(Работы!$B$2:$B$6000,MATCH($C28,Работы!$A$2:$A$6000,0)),"") -> Рабочая документация Системы кондиционирования ("ОВиК-К"), включая пояснительную записку (для помещений менее 100 м.кв) | E28: =IFERROR(INDEX(Работы!$C$2:$C$6000,MATCH($C28,Работы!$A$2:$A$6000,0)),"") -> компл. | F28: =IFERROR(INDEX(Работы!$G$2:$G$6000,MATCH($C28,Работы!$A$2:$A$6000,0)),"") -> 0 | G28: =IFERROR(INDEX(Работы!$K$2:$K$6000,MATCH($C28,Работы!$A$2:$A$6000,0)),"") -> S_общая | J28: =IFERROR(INDEX(Материалы!$B$2:$B$9000,MATCH($I28,Материалы!$A$2:$A$9000,0)),"") | K28: =IF($I28="","",IF($F28=IFERROR(INDEX(Материалы!$G$2:$G$9000,MATCH($I28,Материалы!$A$2:$A$9000,0)),""),"OK","!! не та группа")) | L28: =IFERROR(INDEX(Работы!$H$2:$H$6000,MATCH($C28,Работы!$A$2:$A$6000,0))*(1-ДисконтТендер),0) -> 10395 | M28: =IF($I28="",0,IFERROR(INDEX(Материалы!$I$2:$I$9000,MATCH($I28,Материалы!$A$2:$A$9000,0))*IF(INDEX(Материалы!$J$2:$J$9000,MATCH($I28,Материалы!$A$2:$A$9000,0))="USD",КурсUSD,IF(INDEX(Материалы!$J$2:$J$9000,MATCH($I28,Материалы!$A$2:$A$9000,0))="EUR",КурсEUR,1))*INDEX(Материалы!$K$2:$K$9000,MATCH($I28,Материалы!$A$2:$A$9000,0))*(1+IFERROR(INDEX(Работы!$I$2:$I$6000,MATCH($C28,Работы!$A$2:$A$6000,0))/100,0))*(1-ДисконтТендер),0)) -> 0 | N28: =IF(AND($R28="да",$H28<>""),ROUND($H28*$L28,2),0) -> 0 | O28: =IF(AND($R28="да",$H28<>""),ROUND($H28*$M28,2),0) -> 0 | P28: =$N28+$O28 -> 0 | Q28: =IFERROR(INDEX(Работы!$J$2:$J$6000,MATCH($C28,Работы!$A$2:$A$6000,0)),"") -> типовая | R28: да | T28: =IF(AND($P28>0,$R28="да"),MAX($T$1:$T27)+1,"")
A29: =IFERROR(INDEX(Работы!$D$2:$D$6000,MATCH($C29,Работы!$A$2:$A$6000,0)),"") -> Р1 | B29: =IFERROR(INDEX(Работы!$F$2:$F$6000,MATCH($C29,Работы!$A$2:$A$6000,0)),"") -> 1 | C29: =IFERROR(INDEX(Работы!$A$2:$A$6000,28),"") -> РАБ.Р1.1.028 | D29: =IFERROR(INDEX(Работы!$B$2:$B$6000,MATCH($C29,Работы!$A$2:$A$6000,0)),"") -> Рабочая документация Системы отопления ("ОВиК-О"), включая Пояснительную записку и Теплотехнический расчет (для помещений менее 100 м.кв) | E29: =IFERROR(INDEX(Работы!$C$2:$C$6000,MATCH($C29,Работы!$A$2:$A$6000,0)),"") -> компл. | F29: =IFERROR(INDEX(Работы!$G$2:$G$6000,MATCH($C29,Работы!$A$2:$A$6000,0)),"") -> 0 | G29: =IFERROR(INDEX(Работы!$K$2:$K$6000,MATCH($C29,Работы!$A$2:$A$6000,0)),"") -> S_общая | J29: =IFERROR(INDEX(Материалы!$B$2:$B$9000,MATCH($I29,Материалы!$A$2:$A$9000,0)),"") | K29: =IF($I29="","",IF($F29=IFERROR(INDEX(Материалы!$G$2:$G$9000,MATCH($I29,Материалы!$A$2:$A$9000,0)),""),"OK","!! не та группа")) | L29: =IFERROR(INDEX(Работы!$H$2:$H$6000,MATCH($C29,Работы!$A$2:$A$6000,0))*(1-ДисконтТендер),0) -> 10395 | M29: =IF($I29="",0,IFERROR(INDEX(Материалы!$I$2:$I$9000,MATCH($I29,Материалы!$A$2:$A$9000,0))*IF(INDEX(Материалы!$J$2:$J$9000,MATCH($I29,Материалы!$A$2:$A$9000,0))="USD",КурсUSD,IF(INDEX(Материалы!$J$2:$J$9000,MATCH($I29,Материалы!$A$2:$A$9000,0))="EUR",КурсEUR,1))*INDEX(Материалы!$K$2:$K$9000,MATCH($I29,Материалы!$A$2:$A$9000,0))*(1+IFERROR(INDEX(Работы!$I$2:$I$6000,MATCH($C29,Работы!$A$2:$A$6000,0))/100,0))*(1-ДисконтТендер),0)) -> 0 | N29: =IF(AND($R29="да",$H29<>""),ROUND($H29*$L29,2),0) -> 0 | O29: =IF(AND($R29="да",$H29<>""),ROUND($H29*$M29,2),0) -> 0 | P29: =$N29+$O29 -> 0 | Q29: =IFERROR(INDEX(Работы!$J$2:$J$6000,MATCH($C29,Работы!$A$2:$A$6000,0)),"") -> типовая | R29: да | T29: =IF(AND($P29>0,$R29="да"),MAX($T$1:$T28)+1,"")
A30: =IFERROR(INDEX(Работы!$D$2:$D$6000,MATCH($C30,Работы!$A$2:$A$6000,0)),"") -> Р1 | B30: =IFERROR(INDEX(Работы!$F$2:$F$6000,MATCH($C30,Работы!$A$2:$A$6000,0)),"") -> 1 | C30: =IFERROR(INDEX(Работы!$A$2:$A$6000,29),"") -> РАБ.Р1.1.029 | D30: =IFERROR(INDEX(Работы!$B$2:$B$6000,MATCH($C30,Работы!$A$2:$A$6000,0)),"") -> Рабочая документация Системы водоснабжения и канализации ("ВК"), включая пояснительную записку (для помещений менее 100 м.кв) | E30: =IFERROR(INDEX(Работы!$C$2:$C$6000,MATCH($C30,Работы!$A$2:$A$6000,0)),"") -> компл. | F30: =IFERROR(INDEX(Работы!$G$2:$G$6000,MATCH($C30,Работы!$A$2:$A$6000,0)),"") -> 0 | G30: =IFERROR(INDEX(Работы!$K$2:$K$6000,MATCH($C30,Работы!$A$2:$A$6000,0)),"") -> S_общая | J30: =IFERROR(INDEX(Материалы!$B$2:$B$9000,MATCH($I30,Материалы!$A$2:$A$9000,0)),"") | K30: =IF($I30="","",IF($F30=IFERROR(INDEX(Материалы!$G$2:$G$9000,MATCH($I30,Материалы!$A$2:$A$9000,0)),""),"OK","!! не та группа")) | L30: =IFERROR(INDEX(Работы!$H$2:$H$6000,MATCH($C30,Работы!$A$2:$A$6000,0))*(1-ДисконтТендер),0) -> 10395 | M30: =IF($I30="",0,IFERROR(INDEX(Материалы!$I$2:$I$9000,MATCH($I30,Материалы!$A$2:$A$9000,0))*IF(INDEX(Материалы!$J$2:$J$9000,MATCH($I30,Материалы!$A$2:$A$9000,0))="USD",КурсUSD,IF(INDEX(Материалы!$J$2:$J$9000,MATCH($I30,Материалы!$A$2:$A$9000,0))="EUR",КурсEUR,1))*INDEX(Материалы!$K$2:$K$9000,MATCH($I30,Материалы!$A$2:$A$9000,0))*(1+IFERROR(INDEX(Работы!$I$2:$I$6000,MATCH($C30,Работы!$A$2:$A$6000,0))/100,0))*(1-ДисконтТендер),0)) -> 0 | N30: =IF(AND($R30="да",$H30<>""),ROUND($H30*$L30,2),0) -> 0 | O30: =IF(AND($R30="да",$H30<>""),ROUND($H30*$M30,2),0) -> 0 | P30: =$N30+$O30 -> 0 | Q30: =IFERROR(INDEX(Работы!$J$2:$J$6000,MATCH($C30,Работы!$A$2:$A$6000,0)),"") -> типовая | R30: да | T30: =IF(AND($P30>0,$R30="да"),MAX($T$1:$T29)+1,"")
A31: =IFERROR(INDEX(Работы!$D$2:$D$6000,MATCH($C31,Работы!$A$2:$A$6000,0)),"") -> Р1 | B31: =IFERROR(INDEX(Работы!$F$2:$F$6000,MATCH($C31,Работы!$A$2:$A$6000,0)),"") -> 1 | C31: =IFERROR(INDEX(Работы!$A$2:$A$6000,30),"") -> РАБ.Р1.1.030 | D31: =IFERROR(INDEX(Работы!$B$2:$B$6000,MATCH($C31,Работы!$A$2:$A$6000,0)),"") -> Рабочая документация Системы автоматической установки водяного пожаротушения ("АУВПТ"), (спринкерная, дренчерная, модульная система), включая пояснительную записку (для помещений м… | E31: =IFERROR(INDEX(Работы!$C$2:$C$6000,MATCH($C31,Работы!$A$2:$A$6000,0)),"") -> компл. | F31: =IFERROR(INDEX(Работы!$G$2:$G$6000,MATCH($C31,Работы!$A$2:$A$6000,0)),"") -> 0 | G31: =IFERROR(INDEX(Работы!$K$2:$K$6000,MATCH($C31,Работы!$A$2:$A$6000,0)),"") -> S_общая | J31: =IFERROR(INDEX(Материалы!$B$2:$B$9000,MATCH($I31,Материалы!$A$2:$A$9000,0)),"") | K31: =IF($I31="","",IF($F31=IFERROR(INDEX(Материалы!$G$2:$G$9000,MATCH($I31,Материалы!$A$2:$A$9000,0)),""),"OK","!! не та группа")) | L31: =IFERROR(INDEX(Работы!$H$2:$H$6000,MATCH($C31,Работы!$A$2:$A$6000,0))*(1-ДисконтТендер),0) -> 15592.5 | M31: =IF($I31="",0,IFERROR(INDEX(Материалы!$I$2:$I$9000,MATCH($I31,Материалы!$A$2:$A$9000,0))*IF(INDEX(Материалы!$J$2:$J$9000,MATCH($I31,Материалы!$A$2:$A$9000,0))="USD",КурсUSD,IF(INDEX(Материалы!$J$2:$J$9000,MATCH($I31,Материалы!$A$2:$A$9000,0))="EUR",КурсEUR,1))*INDEX(Материалы!$K$2:$K$9000,MATCH($I31,Материалы!$A$2:$A$9000,0))*(1+IFERROR(INDEX(Работы!$I$2:$I$6000,MATCH($C31,Работы!$A$2:$A$6000,0))/100,0))*(1-ДисконтТендер),0)) -> 0 | N31: =IF(AND($R31="да",$H31<>""),ROUND($H31*$L31,2),0) -> 0 | O31: =IF(AND($R31="да",$H31<>""),ROUND($H31*$M31,2),0) -> 0 | P31: =$N31+$O31 -> 0 | Q31: =IFERROR(INDEX(Работы!$J$2:$J$6000,MATCH($C31,Работы!$A$2:$A$6000,0)),"") -> типовая | R31: да | T31: =IF(AND($P31>0,$R31="да"),MAX($T$1:$T30)+1,"")
A32: =IFERROR(INDEX(Работы!$D$2:$D$6000,MATCH($C32,Работы!$A$2:$A$6000,0)),"") -> Р1 | B32: =IFERROR(INDEX(Работы!$F$2:$F$6000,MATCH($C32,Работы!$A$2:$A$6000,0)),"") -> 1 | C32: =IFERROR(INDEX(Работы!$A$2:$A$6000,31),"") -> РАБ.Р1.1.031 | D32: =IFERROR(INDEX(Работы!$B$2:$B$6000,MATCH($C32,Работы!$A$2:$A$6000,0)),"") -> Рабочая документация Системы Внутреннего противопожарного водопровода ("ВПВ"), включая пояснительную записку (для помещений менее 100 м.кв) | E32: =IFERROR(INDEX(Работы!$C$2:$C$6000,MATCH($C32,Работы!$A$2:$A$6000,0)),"") -> компл. | F32: =IFERROR(INDEX(Работы!$G$2:$G$6000,MATCH($C32,Работы!$A$2:$A$6000,0)),"") -> 0 | G32: =IFERROR(INDEX(Работы!$K$2:$K$6000,MATCH($C32,Работы!$A$2:$A$6000,0)),"") -> S_общая | J32: =IFERROR(INDEX(Материалы!$B$2:$B$9000,MATCH($I32,Материалы!$A$2:$A$9000,0)),"") | K32: =IF($I32="","",IF($F32=IFERROR(INDEX(Материалы!$G$2:$G$9000,MATCH($I32,Материалы!$A$2:$A$9000,0)),""),"OK","!! не та группа")) | L32: =IFERROR(INDEX(Работы!$H$2:$H$6000,MATCH($C32,Работы!$A$2:$A$6000,0))*(1-ДисконтТендер),0) -> 10395 | M32: =IF($I32="",0,IFERROR(INDEX(Материалы!$I$2:$I$9000,MATCH($I32,Материалы!$A$2:$A$9000,0))*IF(INDEX(Материалы!$J$2:$J$9000,MATCH($I32,Материалы!$A$2:$A$9000,0))="USD",КурсUSD,IF(INDEX(Материалы!$J$2:$J$9000,MATCH($I32,Материалы!$A$2:$A$9000,0))="EUR",КурсEUR,1))*INDEX(Материалы!$K$2:$K$9000,MATCH($I32,Материалы!$A$2:$A$9000,0))*(1+IFERROR(INDEX(Работы!$I$2:$I$6000,MATCH($C32,Работы!$A$2:$A$6000,0))/100,0))*(1-ДисконтТендер),0)) -> 0 | N32: =IF(AND($R32="да",$H32<>""),ROUND($H32*$L32,2),0) -> 0 | O32: =IF(AND($R32="да",$H32<>""),ROUND($H32*$M32,2),0) -> 0 | P32: =$N32+$O32 -> 0 | Q32: =IFERROR(INDEX(Работы!$J$2:$J$6000,MATCH($C32,Работы!$A$2:$A$6000,0)),"") -> типовая | R32: да | T32: =IF(AND($P32>0,$R32="да"),MAX($T$1:$T31)+1,"")
A33: =IFERROR(INDEX(Работы!$D$2:$D$6000,MATCH($C33,Работы!$A$2:$A$6000,0)),"") -> Р1 | B33: =IFERROR(INDEX(Работы!$F$2:$F$6000,MATCH($C33,Работы!$A$2:$A$6000,0)),"") -> 1 | C33: =IFERROR(INDEX(Работы!$A$2:$A$6000,32),"") -> РАБ.Р1.1.032 | D33: =IFERROR(INDEX(Работы!$B$2:$B$6000,MATCH($C33,Работы!$A$2:$A$6000,0)),"") -> Рабочая документация Системы дымоудаления ("ДУ"), включая пояснительную записку (для помещений менее 100 м.кв) | E33: =IFERROR(INDEX(Работы!$C$2:$C$6000,MATCH($C33,Работы!$A$2:$A$6000,0)),"") -> компл. | F33: =IFERROR(INDEX(Работы!$G$2:$G$6000,MATCH($C33,Работы!$A$2:$A$6000,0)),"") -> 0 | G33: =IFERROR(INDEX(Работы!$K$2:$K$6000,MATCH($C33,Работы!$A$2:$A$6000,0)),"") -> S_общая | J33: =IFERROR(INDEX(Материалы!$B$2:$B$9000,MATCH($I33,Материалы!$A$2:$A$9000,0)),"") | K33: =IF($I33="","",IF($F33=IFERROR(INDEX(Материалы!$G$2:$G$9000,MATCH($I33,Материалы!$A$2:$A$9000,0)),""),"OK","!! не та группа")) | L33: =IFERROR(INDEX(Работы!$H$2:$H$6000,MATCH($C33,Работы!$A$2:$A$6000,0))*(1-ДисконтТендер),0) -> 15592.5 | M33: =IF($I33="",0,IFERROR(INDEX(Материалы!$I$2:$I$9000,MATCH($I33,Материалы!$A$2:$A$9000,0))*IF(INDEX(Материалы!$J$2:$J$9000,MATCH($I33,Материалы!$A$2:$A$9000,0))="USD",КурсUSD,IF(INDEX(Материалы!$J$2:$J$9000,MATCH($I33,Материалы!$A$2:$A$9000,0))="EUR",КурсEUR,1))*INDEX(Материалы!$K$2:$K$9000,MATCH($I33,Материалы!$A$2:$A$9000,0))*(1+IFERROR(INDEX(Работы!$I$2:$I$6000,MATCH($C33,Работы!$A$2:$A$6000,0))/100,0))*(1-ДисконтТендер),0)) -> 0 | N33: =IF(AND($R33="да",$H33<>""),ROUND($H33*$L33,2),0) -> 0 | O33: =IF(AND($R33="да",$H33<>""),ROUND($H33*$M33,2),0) -> 0 | P33: =$N33+$O33 -> 0 | Q33: =IFERROR(INDEX(Работы!$J$2:$J$6000,MATCH($C33,Работы!$A$2:$A$6000,0)),"") -> типовая | R33: да | T33: =IF(AND($P33>0,$R33="да"),MAX($T$1:$T32)+1,"")
A34: =IFERROR(INDEX(Работы!$D$2:$D$6000,MATCH($C34,Работы!$A$2:$A$6000,0)),"") -> Р1 | B34: =IFERROR(INDEX(Работы!$F$2:$F$6000,MATCH($C34,Работы!$A$2:$A$6000,0)),"") -> 1 | C34: =IFERROR(INDEX(Работы!$A$2:$A$6000,33),"") -> РАБ.Р1.1.033 | D34: =IFERROR(INDEX(Работы!$B$2:$B$6000,MATCH($C34,Работы!$A$2:$A$6000,0)),"") -> Исполнительная документация по усилению/устройству несущих конструкций ("КР"), включая пояснительную записку (для объектов более 100 кв.м.) | E34: =IFERROR(INDEX(Работы!$C$2:$C$6000,MATCH($C34,Работы!$A$2:$A$6000,0)),"") -> м2 | F34: =IFERROR(INDEX(Работы!$G$2:$G$6000,MATCH($C34,Работы!$A$2:$A$6000,0)),"") -> 0 | G34: =IFERROR(INDEX(Работы!$K$2:$K$6000,MATCH($C34,Работы!$A$2:$A$6000,0)),"") -> S_общая | J34: =IFERROR(INDEX(Материалы!$B$2:$B$9000,MATCH($I34,Материалы!$A$2:$A$9000,0)),"") | K34: =IF($I34="","",IF($F34=IFERROR(INDEX(Материалы!$G$2:$G$9000,MATCH($I34,Материалы!$A$2:$A$9000,0)),""),"OK","!! не та группа")) | L34: =IFERROR(INDEX(Работы!$H$2:$H$6000,MATCH($C34,Работы!$A$2:$A$6000,0))*(1-ДисконтТендер),0) -> 13.55 | M34: =IF($I34="",0,IFERROR(INDEX(Материалы!$I$2:$I$9000,MATCH($I34,Материалы!$A$2:$A$9000,0))*IF(INDEX(Материалы!$J$2:$J$9000,MATCH($I34,Материалы!$A$2:$A$9000,0))="USD",КурсUSD,IF(INDEX(Материалы!$J$2:$J$9000,MATCH($I34,Материалы!$A$2:$A$9000,0))="EUR",КурсEUR,1))*INDEX(Материалы!$K$2:$K$9000,MATCH($I34,Материалы!$A$2:$A$9000,0))*(1+IFERROR(INDEX(Работы!$I$2:$I$6000,MATCH($C34,Работы!$A$2:$A$6000,0))/100,0))*(1-ДисконтТендер),0)) -> 0 | N34: =IF(AND($R34="да",$H34<>""),ROUND($H34*$L34,2),0) -> 0 | O34: =IF(AND($R34="да",$H34<>""),ROUND($H34*$M34,2),0) -> 0 | P34: =$N34+$O34 -> 0 | Q34: =IFERROR(INDEX(Работы!$J$2:$J$6000,MATCH($C34,Работы!$A$2:$A$6000,0)),"") -> нетиповая | R34: да | T34: =IF(AND($P34>0,$R34="да"),MAX($T$1:$T33)+1,"")
A35: =IFERROR(INDEX(Работы!$D$2:$D$6000,MATCH($C35,Работы!$A$2:$A$6000,0)),"") -> Р1 | B35: =IFERROR(INDEX(Работы!$F$2:$F$6000,MATCH($C35,Работы!$A$2:$A$6000,0)),"") -> 1 | C35: =IFERROR(INDEX(Работы!$A$2:$A$6000,34),"") -> РАБ.Р1.1.034 | D35: =IFERROR(INDEX(Работы!$B$2:$B$6000,MATCH($C35,Работы!$A$2:$A$6000,0)),"") -> Исполнительная документация "Архитектурные решения" ("АР"), включая пояснительную записку (для объектов более 100 кв.м.) | E35: =IFERROR(INDEX(Работы!$C$2:$C$6000,MATCH($C35,Работы!$A$2:$A$6000,0)),"") -> м2 | F35: =IFERROR(INDEX(Работы!$G$2:$G$6000,MATCH($C35,Работы!$A$2:$A$6000,0)),"") -> 0 | G35: =IFERROR(INDEX(Работы!$K$2:$K$6000,MATCH($C35,Работы!$A$2:$A$6000,0)),"") -> S_общая | J35: =IFERROR(INDEX(Материалы!$B$2:$B$9000,MATCH($I35,Материалы!$A$2:$A$9000,0)),"") | K35: =IF($I35="","",IF($F35=IFERROR(INDEX(Материалы!$G$2:$G$9000,MATCH($I35,Материалы!$A$2:$A$9000,0)),""),"OK","!! не та группа")) | L35: =IFERROR(INDEX(Работы!$H$2:$H$6000,MATCH($C35,Работы!$A$2:$A$6000,0))*(1-ДисконтТендер),0) -> 38.96 | M35: =IF($I35="",0,IFERROR(INDEX(Материалы!$I$2:$I$9000,MATCH($I35,Материалы!$A$2:$A$9000,0))*IF(INDEX(Материалы!$J$2:$J$9000,MATCH($I35,Материалы!$A$2:$A$9000,0))="USD",КурсUSD,IF(INDEX(Материалы!$J$2:$J$9000,MATCH($I35,Материалы!$A$2:$A$9000,0))="EUR",КурсEUR,1))*INDEX(Материалы!$K$2:$K$9000,MATCH($I35,Материалы!$A$2:$A$9000,0))*(1+IFERROR(INDEX(Работы!$I$2:$I$6000,MATCH($C35,Работы!$A$2:$A$6000,0))/100,0))*(1-ДисконтТендер),0)) -> 0 | N35: =IF(AND($R35="да",$H35<>""),ROUND($H35*$L35,2),0) -> 0 | O35: =IF(AND($R35="да",$H35<>""),ROUND($H35*$M35,2),0) -> 0 | P35: =$N35+$O35 -> 0 | Q35: =IFERROR(INDEX(Работы!$J$2:$J$6000,MATCH($C35,Работы!$A$2:$A$6000,0)),"") -> типовая | R35: да | T35: =IF(AND($P35>0,$R35="да"),MAX($T$1:$T34)+1,"")
A36: =IFERROR(INDEX(Работы!$D$2:$D$6000,MATCH($C36,Работы!$A$2:$A$6000,0)),"") -> Р1 | B36: =IFERROR(INDEX(Работы!$F$2:$F$6000,MATCH($C36,Работы!$A$2:$A$6000,0)),"") -> 1 | C36: =IFERROR(INDEX(Работы!$A$2:$A$6000,35),"") -> РАБ.Р1.1.035 | D36: =IFERROR(INDEX(Работы!$B$2:$B$6000,MATCH($C36,Работы!$A$2:$A$6000,0)),"") -> Исполнительная документация по электроснабжению и электроосвещению ("ЭОМ"), включая пояснительную записку (для объектов более 100 кв.м.) | E36: =IFERROR(INDEX(Работы!$C$2:$C$6000,MATCH($C36,Работы!$A$2:$A$6000,0)),"") -> м2 | F36: =IFERROR(INDEX(Работы!$G$2:$G$6000,MATCH($C36,Работы!$A$2:$A$6000,0)),"") -> 0 | G36: =IFERROR(INDEX(Работы!$K$2:$K$6000,MATCH($C36,Работы!$A$2:$A$6000,0)),"") -> S_общая | J36: =IFERROR(INDEX(Материалы!$B$2:$B$9000,MATCH($I36,Материалы!$A$2:$A$9000,0)),"") | K36: =IF($I36="","",IF($F36=IFERROR(INDEX(Материалы!$G$2:$G$9000,MATCH($I36,Материалы!$A$2:$A$9000,0)),""),"OK","!! не та группа")) | L36: =IFERROR(INDEX(Работы!$H$2:$H$6000,MATCH($C36,Работы!$A$2:$A$6000,0))*(1-ДисконтТендер),0) -> 25.83 | M36: =IF($I36="",0,IFERROR(INDEX(Материалы!$I$2:$I$9000,MATCH($I36,Материалы!$A$2:$A$9000,0))*IF(INDEX(Материалы!$J$2:$J$9000,MATCH($I36,Материалы!$A$2:$A$9000,0))="USD",КурсUSD,IF(INDEX(Материалы!$J$2:$J$9000,MATCH($I36,Материалы!$A$2:$A$9000,0))="EUR",КурсEUR,1))*INDEX(Материалы!$K$2:$K$9000,MATCH($I36,Материалы!$A$2:$A$9000,0))*(1+IFERROR(INDEX(Работы!$I$2:$I$6000,MATCH($C36,Работы!$A$2:$A$6000,0))/100,0))*(1-ДисконтТендер),0)) -> 0 | N36: =IF(AND($R36="да",$H36<>""),ROUND($H36*$L36,2),0) -> 0 | O36: =IF(AND($R36="да",$H36<>""),ROUND($H36*$M36,2),0) -> 0 | P36: =$N36+$O36 -> 0 | Q36: =IFERROR(INDEX(Работы!$J$2:$J$6000,MATCH($C36,Работы!$A$2:$A$6000,0)),"") -> типовая | R36: да | T36: =IF(AND($P36>0,$R36="да"),MAX($T$1:$T35)+1,"")
A37: =IFERROR(INDEX(Работы!$D$2:$D$6000,MATCH($C37,Работы!$A$2:$A$6000,0)),"") -> Р1 | B37: =IFERROR(INDEX(Работы!$F$2:$F$6000,MATCH($C37,Работы!$A$2:$A$6000,0)),"") -> 1 | C37: =IFERROR(INDEX(Работы!$A$2:$A$6000,36),"") -> РАБ.Р1.1.036 | D37: =IFERROR(INDEX(Работы!$B$2:$B$6000,MATCH($C37,Работы!$A$2:$A$6000,0)),"") -> Исполнительная документация Системы вентиляции ("ОВиК-В"), включая пояснительную записку (для объектов более 100 кв.м.) | E37: =IFERROR(INDEX(Работы!$C$2:$C$6000,MATCH($C37,Работы!$A$2:$A$6000,0)),"") -> м2 | F37: =IFERROR(INDEX(Работы!$G$2:$G$6000,MATCH($C37,Работы!$A$2:$A$6000,0)),"") -> 0 | G37: =IFERROR(INDEX(Работы!$K$2:$K$6000,MATCH($C37,Работы!$A$2:$A$6000,0)),"") -> S_общая | J37: =IFERROR(INDEX(Материалы!$B$2:$B$9000,MATCH($I37,Материалы!$A$2:$A$9000,0)),"") | K37: =IF($I37="","",IF($F37=IFERROR(INDEX(Материалы!$G$2:$G$9000,MATCH($I37,Материалы!$A$2:$A$9000,0)),""),"OK","!! не та группа")) | L37: =IFERROR(INDEX(Работы!$H$2:$H$6000,MATCH($C37,Работы!$A$2:$A$6000,0))*(1-ДисконтТендер),0) -> 20.27 | M37: =IF($I37="",0,IFERROR(INDEX(Материалы!$I$2:$I$9000,MATCH($I37,Материалы!$A$2:$A$9000,0))*IF(INDEX(Материалы!$J$2:$J$9000,MATCH($I37,Материалы!$A$2:$A$9000,0))="USD",КурсUSD,IF(INDEX(Материалы!$J$2:$J$9000,MATCH($I37,Материалы!$A$2:$A$9000,0))="EUR",КурсEUR,1))*INDEX(Материалы!$K$2:$K$9000,MATCH($I37,Материалы!$A$2:$A$9000,0))*(1+IFERROR(INDEX(Работы!$I$2:$I$6000,MATCH($C37,Работы!$A$2:$A$6000,0))/100,0))*(1-ДисконтТендер),0)) -> 0 | N37: =IF(AND($R37="да",$H37<>""),ROUND($H37*$L37,2),0) -> 0 | O37: =IF(AND($R37="да",$H37<>""),ROUND($H37*$M37,2),0) -> 0 | P37: =$N37+$O37 -> 0 | Q37: =IFERROR(INDEX(Работы!$J$2:$J$6000,MATCH($C37,Работы!$A$2:$A$6000,0)),"") -> типовая | R37: да | T37: =IF(AND($P37>0,$R37="да"),MAX($T$1:$T36)+1,"")
A38: =IFERROR(INDEX(Работы!$D$2:$D$6000,MATCH($C38,Работы!$A$2:$A$6000,0)),"") -> Р1 | B38: =IFERROR(INDEX(Работы!$F$2:$F$6000,MATCH($C38,Работы!$A$2:$A$6000,0)),"") -> 1 | C38: =IFERROR(INDEX(Работы!$A$2:$A$6000,37),"") -> РАБ.Р1.1.037 | D38: =IFERROR(INDEX(Работы!$B$2:$B$6000,MATCH($C38,Работы!$A$2:$A$6000,0)),"") -> Исполнительная документация Системы кондиционирования ("ОВиК-К"), включая пояснительную записку (для объектов более 100 кв.м.) | E38: =IFERROR(INDEX(Работы!$C$2:$C$6000,MATCH($C38,Работы!$A$2:$A$6000,0)),"") -> м2 | F38: =IFERROR(INDEX(Работы!$G$2:$G$6000,MATCH($C38,Работы!$A$2:$A$6000,0)),"") -> 0 | G38: =IFERROR(INDEX(Работы!$K$2:$K$6000,MATCH($C38,Работы!$A$2:$A$6000,0)),"") -> S_общая | J38: =IFERROR(INDEX(Материалы!$B$2:$B$9000,MATCH($I38,Материалы!$A$2:$A$9000,0)),"") | K38: =IF($I38="","",IF($F38=IFERROR(INDEX(Материалы!$G$2:$G$9000,MATCH($I38,Материалы!$A$2:$A$9000,0)),""),"OK","!! не та группа")) | L38: =IFERROR(INDEX(Работы!$H$2:$H$6000,MATCH($C38,Работы!$A$2:$A$6000,0))*(1-ДисконтТендер),0) -> 15.95 | M38: =IF($I38="",0,IFERROR(INDEX(Материалы!$I$2:$I$9000,MATCH($I38,Материалы!$A$2:$A$9000,0))*IF(INDEX(Материалы!$J$2:$J$9000,MATCH($I38,Материалы!$A$2:$A$9000,0))="USD",КурсUSD,IF(INDEX(Материалы!$J$2:$J$9000,MATCH($I38,Материалы!$A$2:$A$9000,0))="EUR",КурсEUR,1))*INDEX(Материалы!$K$2:$K$9000,MATCH($I38,Материалы!$A$2:$A$9000,0))*(1+IFERROR(INDEX(Работы!$I$2:$I$6000,MATCH($C38,Работы!$A$2:$A$6000,0))/100,0))*(1-ДисконтТендер),0)) -> 0 | N38: =IF(AND($R38="да",$H38<>""),ROUND($H38*$L38,2),0) -> 0 | O38: =IF(AND($R38="да",$H38<>""),ROUND($H38*$M38,2),0) -> 0 | P38: =$N38+$O38 -> 0 | Q38: =IFERROR(INDEX(Работы!$J$2:$J$6000,MATCH($C38,Работы!$A$2:$A$6000,0)),"") -> типовая | R38: да | T38: =IF(AND($P38>0,$R38="да"),MAX($T$1:$T37)+1,"")
A39: =IFERROR(INDEX(Работы!$D$2:$D$6000,MATCH($C39,Работы!$A$2:$A$6000,0)),"") -> Р1 | B39: =IFERROR(INDEX(Работы!$F$2:$F$6000,MATCH($C39,Работы!$A$2:$A$6000,0)),"") -> 1 | C39: =IFERROR(INDEX(Работы!$A$2:$A$6000,38),"") -> РАБ.Р1.1.038 | D39: =IFERROR(INDEX(Работы!$B$2:$B$6000,MATCH($C39,Работы!$A$2:$A$6000,0)),"") -> Исполнительная документация Системы отопления ("ОВиК-О"), включая Пояснительную записку и Теплотехнический расчет (для объектов более 100 кв.м.) | E39: =IFERROR(INDEX(Работы!$C$2:$C$6000,MATCH($C39,Работы!$A$2:$A$6000,0)),"") -> м2 | F39: =IFERROR(INDEX(Работы!$G$2:$G$6000,MATCH($C39,Работы!$A$2:$A$6000,0)),"") -> 0 | G39: =IFERROR(INDEX(Работы!$K$2:$K$6000,MATCH($C39,Работы!$A$2:$A$6000,0)),"") -> S_общая | J39: =IFERROR(INDEX(Материалы!$B$2:$B$9000,MATCH($I39,Материалы!$A$2:$A$9000,0)),"") | K39: =IF($I39="","",IF($F39=IFERROR(INDEX(Материалы!$G$2:$G$9000,MATCH($I39,Материалы!$A$2:$A$9000,0)),""),"OK","!! не та группа")) | L39: =IFERROR(INDEX(Работы!$H$2:$H$6000,MATCH($C39,Работы!$A$2:$A$6000,0))*(1-ДисконтТендер),0) -> 12.39 | M39: =IF($I39="",0,IFERROR(INDEX(Материалы!$I$2:$I$9000,MATCH($I39,Материалы!$A$2:$A$9000,0))*IF(INDEX(Материалы!$J$2:$J$9000,MATCH($I39,Материалы!$A$2:$A$9000,0))="USD",КурсUSD,IF(INDEX(Материалы!$J$2:$J$9000,MATCH($I39,Материалы!$A$2:$A$9000,0))="EUR",КурсEUR,1))*INDEX(Материалы!$K$2:$K$9000,MATCH($I39,Материалы!$A$2:$A$9000,0))*(1+IFERROR(INDEX(Работы!$I$2:$I$6000,MATCH($C39,Работы!$A$2:$A$6000,0))/100,0))*(1-ДисконтТендер),0)) -> 0 | N39: =IF(AND($R39="да",$H39<>""),ROUND($H39*$L39,2),0) -> 0 | O39: =IF(AND($R39="да",$H39<>""),ROUND($H39*$M39,2),0) -> 0 | P39: =$N39+$O39 -> 0 | Q39: =IFERROR(INDEX(Работы!$J$2:$J$6000,MATCH($C39,Работы!$A$2:$A$6000,0)),"") -> типовая | R39: да | T39: =IF(AND($P39>0,$R39="да"),MAX($T$1:$T38)+1,"")
A40: =IFERROR(INDEX(Работы!$D$2:$D$6000,MATCH($C40,Работы!$A$2:$A$6000,0)),"") -> Р1 | B40: =IFERROR(INDEX(Работы!$F$2:$F$6000,MATCH($C40,Работы!$A$2:$A$6000,0)),"") -> 1 | C40: =IFERROR(INDEX(Работы!$A$2:$A$6000,39),"") -> РАБ.Р1.1.039 | D40: =IFERROR(INDEX(Работы!$B$2:$B$6000,MATCH($C40,Работы!$A$2:$A$6000,0)),"") -> Исполнительная документация Системы водоснабжения и канализации ("ВК"), включая пояснительную записку (для объектов более 100 кв.м.) | E40: =IFERROR(INDEX(Работы!$C$2:$C$6000,MATCH($C40,Работы!$A$2:$A$6000,0)),"") -> м2 | F40: =IFERROR(INDEX(Работы!$G$2:$G$6000,MATCH($C40,Работы!$A$2:$A$6000,0)),"") -> 0 | G40: =IFERROR(INDEX(Работы!$K$2:$K$6000,MATCH($C40,Работы!$A$2:$A$6000,0)),"") -> S_общая | J40: =IFERROR(INDEX(Материалы!$B$2:$B$9000,MATCH($I40,Материалы!$A$2:$A$9000,0)),"") | K40: =IF($I40="","",IF($F40=IFERROR(INDEX(Материалы!$G$2:$G$9000,MATCH($I40,Материалы!$A$2:$A$9000,0)),""),"OK","!! не та группа")) | L40: =IFERROR(INDEX(Работы!$H$2:$H$6000,MATCH($C40,Работы!$A$2:$A$6000,0))*(1-ДисконтТендер),0) -> 13.02 | M40: =IF($I40="",0,IFERROR(INDEX(Материалы!$I$2:$I$9000,MATCH($I40,Материалы!$A$2:$A$9000,0))*IF(INDEX(Материалы!$J$2:$J$9000,MATCH($I40,Материалы!$A$2:$A$9000,0))="USD",КурсUSD,IF(INDEX(Материалы!$J$2:$J$9000,MATCH($I40,Материалы!$A$2:$A$9000,0))="EUR",КурсEUR,1))*INDEX(Материалы!$K$2:$K$9000,MATCH($I40,Материалы!$A$2:$A$9000,0))*(1+IFERROR(INDEX(Работы!$I$2:$I$6000,MATCH($C40,Работы!$A$2:$A$6000,0))/100,0))*(1-ДисконтТендер),0)) -> 0 | N40: =IF(AND($R40="да",$H40<>""),ROUND($H40*$L40,2),0) -> 0 | O40: =IF(AND($R40="да",$H40<>""),ROUND($H40*$M40,2),0) -> 0 | P40: =$N40+$O40 -> 0 | Q40: =IFERROR(INDEX(Работы!$J$2:$J$6000,MATCH($C40,Работы!$A$2:$A$6000,0)),"") -> типовая | R40: да | T40: =IF(AND($P40>0,$R40="да"),MAX($T$1:$T39)+1,"")
A41: =IFERROR(INDEX(Работы!$D$2:$D$6000,MATCH($C41,Работы!$A$2:$A$6000,0)),"") -> Р1 | B41: =IFERROR(INDEX(Работы!$F$2:$F$6000,MATCH($C41,Работы!$A$2:$A$6000,0)),"") -> 1 | C41: =IFERROR(INDEX(Работы!$A$2:$A$6000,40),"") -> РАБ.Р1.1.040 | D41: =IFERROR(INDEX(Работы!$B$2:$B$6000,MATCH($C41,Работы!$A$2:$A$6000,0)),"") -> Исполнительная документация Системы автматической установки водяного пожаротушения ("АУВПТ"), (спринкерная, дренчерная, модульная система), включая пояснительную записку (для объек… | E41: =IFERROR(INDEX(Работы!$C$2:$C$6000,MATCH($C41,Работы!$A$2:$A$6000,0)),"") -> м2 | F41: =IFERROR(INDEX(Работы!$G$2:$G$6000,MATCH($C41,Работы!$A$2:$A$6000,0)),"") -> 0 | G41: =IFERROR(INDEX(Работы!$K$2:$K$6000,MATCH($C41,Работы!$A$2:$A$6000,0)),"") -> S_общая | J41: =IFERROR(INDEX(Материалы!$B$2:$B$9000,MATCH($I41,Материалы!$A$2:$A$9000,0)),"") | K41: =IF($I41="","",IF($F41=IFERROR(INDEX(Материалы!$G$2:$G$9000,MATCH($I41,Материалы!$A$2:$A$9000,0)),""),"OK","!! не та группа")) | L41: =IFERROR(INDEX(Работы!$H$2:$H$6000,MATCH($C41,Работы!$A$2:$A$6000,0))*(1-ДисконтТендер),0) -> 9.17 | M41: =IF($I41="",0,IFERROR(INDEX(Материалы!$I$2:$I$9000,MATCH($I41,Материалы!$A$2:$A$9000,0))*IF(INDEX(Материалы!$J$2:$J$9000,MATCH($I41,Материалы!$A$2:$A$9000,0))="USD",КурсUSD,IF(INDEX(Материалы!$J$2:$J$9000,MATCH($I41,Материалы!$A$2:$A$9000,0))="EUR",КурсEUR,1))*INDEX(Материалы!$K$2:$K$9000,MATCH($I41,Материалы!$A$2:$A$9000,0))*(1+IFERROR(INDEX(Работы!$I$2:$I$6000,MATCH($C41,Работы!$A$2:$A$6000,0))/100,0))*(1-ДисконтТендер),0)) -> 0 | N41: =IF(AND($R41="да",$H41<>""),ROUND($H41*$L41,2),0) -> 0 | O41: =IF(AND($R41="да",$H41<>""),ROUND($H41*$M41,2),0) -> 0 | P41: =$N41+$O41 -> 0 | Q41: =IFERROR(INDEX(Работы!$J$2:$J$6000,MATCH($C41,Работы!$A$2:$A$6000,0)),"") -> типовая | R41: да | T41: =IF(AND($P41>0,$R41="да"),MAX($T$1:$T40)+1,"")
A42: =IFERROR(INDEX(Работы!$D$2:$D$6000,MATCH($C42,Работы!$A$2:$A$6000,0)),"") -> Р1 | B42: =IFERROR(INDEX(Работы!$F$2:$F$6000,MATCH($C42,Работы!$A$2:$A$6000,0)),"") -> 1 | C42: =IFERROR(INDEX(Работы!$A$2:$A$6000,41),"") -> РАБ.Р1.1.041 | D42: =IFERROR(INDEX(Работы!$B$2:$B$6000,MATCH($C42,Работы!$A$2:$A$6000,0)),"") -> Исполнительная документация Системы Внутреннего противопожарного водопровода ("ВПВ"), включая пояснительную записку (для объектов более 100 кв.м.) | E42: =IFERROR(INDEX(Работы!$C$2:$C$6000,MATCH($C42,Работы!$A$2:$A$6000,0)),"") -> м2 | F42: =IFERROR(INDEX(Работы!$G$2:$G$6000,MATCH($C42,Работы!$A$2:$A$6000,0)),"") -> 0 | G42: =IFERROR(INDEX(Работы!$K$2:$K$6000,MATCH($C42,Работы!$A$2:$A$6000,0)),"") -> S_общая | J42: =IFERROR(INDEX(Материалы!$B$2:$B$9000,MATCH($I42,Материалы!$A$2:$A$9000,0)),"") | K42: =IF($I42="","",IF($F42=IFERROR(INDEX(Материалы!$G$2:$G$9000,MATCH($I42,Материалы!$A$2:$A$9000,0)),""),"OK","!! не та группа")) | L42: =IFERROR(INDEX(Работы!$H$2:$H$6000,MATCH($C42,Работы!$A$2:$A$6000,0))*(1-ДисконтТендер),0) -> 9.17 | M42: =IF($I42="",0,IFERROR(INDEX(Материалы!$I$2:$I$9000,MATCH($I42,Материалы!$A$2:$A$9000,0))*IF(INDEX(Материалы!$J$2:$J$9000,MATCH($I42,Материалы!$A$2:$A$9000,0))="USD",КурсUSD,IF(INDEX(Материалы!$J$2:$J$9000,MATCH($I42,Материалы!$A$2:$A$9000,0))="EUR",КурсEUR,1))*INDEX(Материалы!$K$2:$K$9000,MATCH($I42,Материалы!$A$2:$A$9000,0))*(1+IFERROR(INDEX(Работы!$I$2:$I$6000,MATCH($C42,Работы!$A$2:$A$6000,0))/100,0))*(1-ДисконтТендер),0)) -> 0 | N42: =IF(AND($R42="да",$H42<>""),ROUND($H42*$L42,2),0) -> 0 | O42: =IF(AND($R42="да",$H42<>""),ROUND($H42*$M42,2),0) -> 0 | P42: =$N42+$O42 -> 0 | Q42: =IFERROR(INDEX(Работы!$J$2:$J$6000,MATCH($C42,Работы!$A$2:$A$6000,0)),"") -> типовая | R42: да | T42: =IF(AND($P42>0,$R42="да"),MAX($T$1:$T41)+1,"")
A43: =IFERROR(INDEX(Работы!$D$2:$D$6000,MATCH($C43,Работы!$A$2:$A$6000,0)),"") -> Р1 | B43: =IFERROR(INDEX(Работы!$F$2:$F$6000,MATCH($C43,Работы!$A$2:$A$6000,0)),"") -> 1 | C43: =IFERROR(INDEX(Работы!$A$2:$A$6000,42),"") -> РАБ.Р1.1.042 | D43: =IFERROR(INDEX(Работы!$B$2:$B$6000,MATCH($C43,Работы!$A$2:$A$6000,0)),"") -> Исполнительная документация Системы дымоудаления ("ДУ"), включая пояснительную записку (для объектов более 100 кв.м.) | E43: =IFERROR(INDEX(Работы!$C$2:$C$6000,MATCH($C43,Работы!$A$2:$A$6000,0)),"") -> м2 | F43: =IFERROR(INDEX(Работы!$G$2:$G$6000,MATCH($C43,Работы!$A$2:$A$6000,0)),"") -> 0 | G43: =IFERROR(INDEX(Работы!$K$2:$K$6000,MATCH($C43,Работы!$A$2:$A$6000,0)),"") -> S_общая | J43: =IFERROR(INDEX(Материалы!$B$2:$B$9000,MATCH($I43,Материалы!$A$2:$A$9000,0)),"") | K43: =IF($I43="","",IF($F43=IFERROR(INDEX(Материалы!$G$2:$G$9000,MATCH($I43,Материалы!$A$2:$A$9000,0)),""),"OK","!! не та группа")) | L43: =IFERROR(INDEX(Работы!$H$2:$H$6000,MATCH($C43,Работы!$A$2:$A$6000,0))*(1-ДисконтТендер),0) -> 10.4 | M43: =IF($I43="",0,IFERROR(INDEX(Материалы!$I$2:$I$9000,MATCH($I43,Материалы!$A$2:$A$9000,0))*IF(INDEX(Материалы!$J$2:$J$9000,MATCH($I43,Материалы!$A$2:$A$9000,0))="USD",КурсUSD,IF(INDEX(Материалы!$J$2:$J$9000,MATCH($I43,Материалы!$A$2:$A$9000,0))="EUR",КурсEUR,1))*INDEX(Материалы!$K$2:$K$9000,MATCH($I43,Материалы!$A$2:$A$9000,0))*(1+IFERROR(INDEX(Работы!$I$2:$I$6000,MATCH($C43,Работы!$A$2:$A$6000,0))/100,0))*(1-ДисконтТендер),0)) -> 0 | N43: =IF(AND($R43="да",$H43<>""),ROUND($H43*$L43,2),0) -> 0 | O43: =IF(AND($R43="да",$H43<>""),ROUND($H43*$M43,2),0) -> 0 | P43: =$N43+$O43 -> 0 | Q43: =IFERROR(INDEX(Работы!$J$2:$J$6000,MATCH($C43,Работы!$A$2:$A$6000,0)),"") -> типовая | R43: да | T43: =IF(AND($P43>0,$R43="да"),MAX($T$1:$T42)+1,"")
A44: =IFERROR(INDEX(Работы!$D$2:$D$6000,MATCH($C44,Работы!$A$2:$A$6000,0)),"") -> Р1 | B44: =IFERROR(INDEX(Работы!$F$2:$F$6000,MATCH($C44,Работы!$A$2:$A$6000,0)),"") -> 1 | C44: =IFERROR(INDEX(Работы!$A$2:$A$6000,43),"") -> РАБ.Р1.1.043 | D44: =IFERROR(INDEX(Работы!$B$2:$B$6000,MATCH($C44,Работы!$A$2:$A$6000,0)),"") -> Исполнительная документация по усилению/устройству несущих конструкций ("КР"), включая пояснительную записку (для объектов менее 100 кв.м.) | E44: =IFERROR(INDEX(Работы!$C$2:$C$6000,MATCH($C44,Работы!$A$2:$A$6000,0)),"") -> компл. | F44: =IFERROR(INDEX(Работы!$G$2:$G$6000,MATCH($C44,Работы!$A$2:$A$6000,0)),"") -> 0 | G44: =IFERROR(INDEX(Работы!$K$2:$K$6000,MATCH($C44,Работы!$A$2:$A$6000,0)),"") -> S_общая | J44: =IFERROR(INDEX(Материалы!$B$2:$B$9000,MATCH($I44,Материалы!$A$2:$A$9000,0)),"") | K44: =IF($I44="","",IF($F44=IFERROR(INDEX(Материалы!$G$2:$G$9000,MATCH($I44,Материалы!$A$2:$A$9000,0)),""),"OK","!! не та группа")) | L44: =IFERROR(INDEX(Работы!$H$2:$H$6000,MATCH($C44,Работы!$A$2:$A$6000,0))*(1-ДисконтТендер),0) -> 1050 | M44: =IF($I44="",0,IFERROR(INDEX(Материалы!$I$2:$I$9000,MATCH($I44,Материалы!$A$2:$A$9000,0))*IF(INDEX(Материалы!$J$2:$J$9000,MATCH($I44,Материалы!$A$2:$A$9000,0))="USD",КурсUSD,IF(INDEX(Материалы!$J$2:$J$9000,MATCH($I44,Материалы!$A$2:$A$9000,0))="EUR",КурсEUR,1))*INDEX(Материалы!$K$2:$K$9000,MATCH($I44,Материалы!$A$2:$A$9000,0))*(1+IFERROR(INDEX(Работы!$I$2:$I$6000,MATCH($C44,Работы!$A$2:$A$6000,0))/100,0))*(1-ДисконтТендер),0)) -> 0 | N44: =IF(AND($R44="да",$H44<>""),ROUND($H44*$L44,2),0) -> 0 | O44: =IF(AND($R44="да",$H44<>""),ROUND($H44*$M44,2),0) -> 0 | P44: =$N44+$O44 -> 0 | Q44: =IFERROR(INDEX(Работы!$J$2:$J$6000,MATCH($C44,Работы!$A$2:$A$6000,0)),"") -> нетиповая | R44: да | T44: =IF(AND($P44>0,$R44="да"),MAX($T$1:$T43)+1,"")
A45: =IFERROR(INDEX(Работы!$D$2:$D$6000,MATCH($C45,Работы!$A$2:$A$6000,0)),"") -> Р1 | B45: =IFERROR(INDEX(Работы!$F$2:$F$6000,MATCH($C45,Работы!$A$2:$A$6000,0)),"") -> 1 | C45: =IFERROR(INDEX(Работы!$A$2:$A$6000,44),"") -> РАБ.Р1.1.044 | D45: =IFERROR(INDEX(Работы!$B$2:$B$6000,MATCH($C45,Работы!$A$2:$A$6000,0)),"") -> Исполнительная документация "Архитектурные решения" ("АР"), включая пояснительную записку (для объектов менее 100 кв.м.) | E45: =IFERROR(INDEX(Работы!$C$2:$C$6000,MATCH($C45,Работы!$A$2:$A$6000,0)),"") -> компл. | F45: =IFERROR(INDEX(Работы!$G$2:$G$6000,MATCH($C45,Работы!$A$2:$A$6000,0)),"") -> 0 | G45: =IFERROR(INDEX(Работы!$K$2:$K$6000,MATCH($C45,Работы!$A$2:$A$6000,0)),"") -> S_общая | J45: =IFERROR(INDEX(Материалы!$B$2:$B$9000,MATCH($I45,Материалы!$A$2:$A$9000,0)),"") | K45: =IF($I45="","",IF($F45=IFERROR(INDEX(Материалы!$G$2:$G$9000,MATCH($I45,Материалы!$A$2:$A$9000,0)),""),"OK","!! не та группа")) | L45: =IFERROR(INDEX(Работы!$H$2:$H$6000,MATCH($C45,Работы!$A$2:$A$6000,0))*(1-ДисконтТендер),0) -> 2073.75 | M45: =IF($I45="",0,IFERROR(INDEX(Материалы!$I$2:$I$9000,MATCH($I45,Материалы!$A$2:$A$9000,0))*IF(INDEX(Материалы!$J$2:$J$9000,MATCH($I45,Материалы!$A$2:$A$9000,0))="USD",КурсUSD,IF(INDEX(Материалы!$J$2:$J$9000,MATCH($I45,Материалы!$A$2:$A$9000,0))="EUR",КурсEUR,1))*INDEX(Материалы!$K$2:$K$9000,MATCH($I45,Материалы!$A$2:$A$9000,0))*(1+IFERROR(INDEX(Работы!$I$2:$I$6000,MATCH($C45,Работы!$A$2:$A$6000,0))/100,0))*(1-ДисконтТендер),0)) -> 0 | N45: =IF(AND($R45="да",$H45<>""),ROUND($H45*$L45,2),0) -> 0 | O45: =IF(AND($R45="да",$H45<>""),ROUND($H45*$M45,2),0) -> 0 | P45: =$N45+$O45 -> 0 | Q45: =IFERROR(INDEX(Работы!$J$2:$J$6000,MATCH($C45,Работы!$A$2:$A$6000,0)),"") -> типовая | R45: да | T45: =IF(AND($P45>0,$R45="да"),MAX($T$1:$T44)+1,"")
A46: =IFERROR(INDEX(Работы!$D$2:$D$6000,MATCH($C46,Работы!$A$2:$A$6000,0)),"") -> Р1 | B46: =IFERROR(INDEX(Работы!$F$2:$F$6000,MATCH($C46,Работы!$A$2:$A$6000,0)),"") -> 1 | C46: =IFERROR(INDEX(Работы!$A$2:$A$6000,45),"") -> РАБ.Р1.1.045 | D46: =IFERROR(INDEX(Работы!$B$2:$B$6000,MATCH($C46,Работы!$A$2:$A$6000,0)),"") -> Исполнительная документация по электроснабжению и электроосвещению ("ЭОМ"), включая пояснительную записку (для объектов менее 100 кв.м.) | E46: =IFERROR(INDEX(Работы!$C$2:$C$6000,MATCH($C46,Работы!$A$2:$A$6000,0)),"") -> компл. | F46: =IFERROR(INDEX(Работы!$G$2:$G$6000,MATCH($C46,Работы!$A$2:$A$6000,0)),"") -> 0 | G46: =IFERROR(INDEX(Работы!$K$2:$K$6000,MATCH($C46,Работы!$A$2:$A$6000,0)),"") -> S_общая | J46: =IFERROR(INDEX(Материалы!$B$2:$B$9000,MATCH($I46,Материалы!$A$2:$A$9000,0)),"") | K46: =IF($I46="","",IF($F46=IFERROR(INDEX(Материалы!$G$2:$G$9000,MATCH($I46,Материалы!$A$2:$A$9000,0)),""),"OK","!! не та группа")) | L46: =IFERROR(INDEX(Работы!$H$2:$H$6000,MATCH($C46,Работы!$A$2:$A$6000,0))*(1-ДисконтТендер),0) -> 2073.75 | M46: =IF($I46="",0,IFERROR(INDEX(Материалы!$I$2:$I$9000,MATCH($I46,Материалы!$A$2:$A$9000,0))*IF(INDEX(Материалы!$J$2:$J$9000,MATCH($I46,Материалы!$A$2:$A$9000,0))="USD",КурсUSD,IF(INDEX(Материалы!$J$2:$J$9000,MATCH($I46,Материалы!$A$2:$A$9000,0))="EUR",КурсEUR,1))*INDEX(Материалы!$K$2:$K$9000,MATCH($I46,Материалы!$A$2:$A$9000,0))*(1+IFERROR(INDEX(Работы!$I$2:$I$6000,MATCH($C46,Работы!$A$2:$A$6000,0))/100,0))*(1-ДисконтТендер),0)) -> 0 | N46: =IF(AND($R46="да",$H46<>""),ROUND($H46*$L46,2),0) -> 0 | O46: =IF(AND($R46="да",$H46<>""),ROUND($H46*$M46,2),0) -> 0 | P46: =$N46+$O46 -> 0 | Q46: =IFERROR(INDEX(Работы!$J$2:$J$6000,MATCH($C46,Работы!$A$2:$A$6000,0)),"") -> типовая | R46: да | T46: =IF(AND($P46>0,$R46="да"),MAX($T$1:$T45)+1,"")
A47: =IFERROR(INDEX(Работы!$D$2:$D$6000,MATCH($C47,Работы!$A$2:$A$6000,0)),"") -> Р1 | B47: =IFERROR(INDEX(Работы!$F$2:$F$6000,MATCH($C47,Работы!$A$2:$A$6000,0)),"") -> 1 | C47: =IFERROR(INDEX(Работы!$A$2:$A$6000,46),"") -> РАБ.Р1.1.046 | D47: =IFERROR(INDEX(Работы!$B$2:$B$6000,MATCH($C47,Работы!$A$2:$A$6000,0)),"") -> Исполнительная документация Системы вентиляции ("ОВиК-В"), включая пояснительную записку (для объектов менее 100 кв.м.) | E47: =IFERROR(INDEX(Работы!$C$2:$C$6000,MATCH($C47,Работы!$A$2:$A$6000,0)),"") -> компл. | F47: =IFERROR(INDEX(Работы!$G$2:$G$6000,MATCH($C47,Работы!$A$2:$A$6000,0)),"") -> 0 | G47: =IFERROR(INDEX(Работы!$K$2:$K$6000,MATCH($C47,Работы!$A$2:$A$6000,0)),"") -> S_общая | J47: =IFERROR(INDEX(Материалы!$B$2:$B$9000,MATCH($I47,Материалы!$A$2:$A$9000,0)),"") | K47: =IF($I47="","",IF($F47=IFERROR(INDEX(Материалы!$G$2:$G$9000,MATCH($I47,Материалы!$A$2:$A$9000,0)),""),"OK","!! не та группа")) | L47: =IFERROR(INDEX(Работы!$H$2:$H$6000,MATCH($C47,Работы!$A$2:$A$6000,0))*(1-ДисконтТендер),0) -> 1559.25 | M47: =IF($I47="",0,IFERROR(INDEX(Материалы!$I$2:$I$9000,MATCH($I47,Материалы!$A$2:$A$9000,0))*IF(INDEX(Материалы!$J$2:$J$9000,MATCH($I47,Материалы!$A$2:$A$9000,0))="USD",КурсUSD,IF(INDEX(Материалы!$J$2:$J$9000,MATCH($I47,Материалы!$A$2:$A$9000,0))="EUR",КурсEUR,1))*INDEX(Материалы!$K$2:$K$9000,MATCH($I47,Материалы!$A$2:$A$9000,0))*(1+IFERROR(INDEX(Работы!$I$2:$I$6000,MATCH($C47,Работы!$A$2:$A$6000,0))/100,0))*(1-ДисконтТендер),0)) -> 0 | N47: =IF(AND($R47="да",$H47<>""),ROUND($H47*$L47,2),0) -> 0 | O47: =IF(AND($R47="да",$H47<>""),ROUND($H47*$M47,2),0) -> 0 | P47: =$N47+$O47 -> 0 | Q47: =IFERROR(INDEX(Работы!$J$2:$J$6000,MATCH($C47,Работы!$A$2:$A$6000,0)),"") -> типовая | R47: да | T47: =IF(AND($P47>0,$R47="да"),MAX($T$1:$T46)+1,"")
A48: =IFERROR(INDEX(Работы!$D$2:$D$6000,MATCH($C48,Работы!$A$2:$A$6000,0)),"") -> Р1 | B48: =IFERROR(INDEX(Работы!$F$2:$F$6000,MATCH($C48,Работы!$A$2:$A$6000,0)),"") -> 1 | C48: =IFERROR(INDEX(Работы!$A$2:$A$6000,47),"") -> РАБ.Р1.1.047 | D48: =IFERROR(INDEX(Работы!$B$2:$B$6000,MATCH($C48,Работы!$A$2:$A$6000,0)),"") -> Исполнительная документация Системы кондиционирования ("ОВиК-К"), включая пояснительную записку (для объектов менее 100 кв.м.) | E48: =IFERROR(INDEX(Работы!$C$2:$C$6000,MATCH($C48,Работы!$A$2:$A$6000,0)),"") -> компл. | F48: =IFERROR(INDEX(Работы!$G$2:$G$6000,MATCH($C48,Работы!$A$2:$A$6000,0)),"") -> 0 | G48: =IFERROR(INDEX(Работы!$K$2:$K$6000,MATCH($C48,Работы!$A$2:$A$6000,0)),"") -> S_общая | J48: =IFERROR(INDEX(Материалы!$B$2:$B$9000,MATCH($I48,Материалы!$A$2:$A$9000,0)),"") | K48: =IF($I48="","",IF($F48=IFERROR(INDEX(Материалы!$G$2:$G$9000,MATCH($I48,Материалы!$A$2:$A$9000,0)),""),"OK","!! не та группа")) | L48: =IFERROR(INDEX(Работы!$H$2:$H$6000,MATCH($C48,Работы!$A$2:$A$6000,0))*(1-ДисконтТендер),0) -> 1039.5 | M48: =IF($I48="",0,IFERROR(INDEX(Материалы!$I$2:$I$9000,MATCH($I48,Материалы!$A$2:$A$9000,0))*IF(INDEX(Материалы!$J$2:$J$9000,MATCH($I48,Материалы!$A$2:$A$9000,0))="USD",КурсUSD,IF(INDEX(Материалы!$J$2:$J$9000,MATCH($I48,Материалы!$A$2:$A$9000,0))="EUR",КурсEUR,1))*INDEX(Материалы!$K$2:$K$9000,MATCH($I48,Материалы!$A$2:$A$9000,0))*(1+IFERROR(INDEX(Работы!$I$2:$I$6000,MATCH($C48,Работы!$A$2:$A$6000,0))/100,0))*(1-ДисконтТендер),0)) -> 0 | N48: =IF(AND($R48="да",$H48<>""),ROUND($H48*$L48,2),0) -> 0 | O48: =IF(AND($R48="да",$H48<>""),ROUND($H48*$M48,2),0) -> 0 | P48: =$N48+$O48 -> 0 | Q48: =IFERROR(INDEX(Работы!$J$2:$J$6000,MATCH($C48,Работы!$A$2:$A$6000,0)),"") -> типовая | R48: да | T48: =IF(AND($P48>0,$R48="да"),MAX($T$1:$T47)+1,"")
A49: =IFERROR(INDEX(Работы!$D$2:$D$6000,MATCH($C49,Работы!$A$2:$A$6000,0)),"") -> Р1 | B49: =IFERROR(INDEX(Работы!$F$2:$F$6000,MATCH($C49,Работы!$A$2:$A$6000,0)),"") -> 1 | C49: =IFERROR(INDEX(Работы!$A$2:$A$6000,48),"") -> РАБ.Р1.1.048 | D49: =IFERROR(INDEX(Работы!$B$2:$B$6000,MATCH($C49,Работы!$A$2:$A$6000,0)),"") -> Исполнительная документация Системы отопления ("ОВиК-О"), включая Пояснительную записку и Теплотехнический расчет (для объектов менее 100 кв.м.) | E49: =IFERROR(INDEX(Работы!$C$2:$C$6000,MATCH($C49,Работы!$A$2:$A$6000,0)),"") -> компл. | F49: =IFERROR(INDEX(Работы!$G$2:$G$6000,MATCH($C49,Работы!$A$2:$A$6000,0)),"") -> 0 | G49: =IFERROR(INDEX(Работы!$K$2:$K$6000,MATCH($C49,Работы!$A$2:$A$6000,0)),"") -> S_общая | J49: =IFERROR(INDEX(Материалы!$B$2:$B$9000,MATCH($I49,Материалы!$A$2:$A$9000,0)),"") | K49: =IF($I49="","",IF($F49=IFERROR(INDEX(Материалы!$G$2:$G$9000,MATCH($I49,Материалы!$A$2:$A$9000,0)),""),"OK","!! не та группа")) | L49: =IFERROR(INDEX(Работы!$H$2:$H$6000,MATCH($C49,Работы!$A$2:$A$6000,0))*(1-ДисконтТендер),0) -> 1039.5 | M49: =IF($I49="",0,IFERROR(INDEX(Материалы!$I$2:$I$9000,MATCH($I49,Материалы!$A$2:$A$9000,0))*IF(INDEX(Материалы!$J$2:$J$9000,MATCH($I49,Материалы!$A$2:$A$9000,0))="USD",КурсUSD,IF(INDEX(Материалы!$J$2:$J$9000,MATCH($I49,Материалы!$A$2:$A$9000,0))="EUR",КурсEUR,1))*INDEX(Материалы!$K$2:$K$9000,MATCH($I49,Материалы!$A$2:$A$9000,0))*(1+IFERROR(INDEX(Работы!$I$2:$I$6000,MATCH($C49,Работы!$A$2:$A$6000,0))/100,0))*(1-ДисконтТендер),0)) -> 0 | N49: =IF(AND($R49="да",$H49<>""),ROUND($H49*$L49,2),0) -> 0 | O49: =IF(AND($R49="да",$H49<>""),ROUND($H49*$M49,2),0) -> 0 | P49: =$N49+$O49 -> 0 | Q49: =IFERROR(INDEX(Работы!$J$2:$J$6000,MATCH($C49,Работы!$A$2:$A$6000,0)),"") -> типовая | R49: да | T49: =IF(AND($P49>0,$R49="да"),MAX($T$1:$T48)+1,"")
A50: =IFERROR(INDEX(Работы!$D$2:$D$6000,MATCH($C50,Работы!$A$2:$A$6000,0)),"") -> Р1 | B50: =IFERROR(INDEX(Работы!$F$2:$F$6000,MATCH($C50,Работы!$A$2:$A$6000,0)),"") -> 1 | C50: =IFERROR(INDEX(Работы!$A$2:$A$6000,49),"") -> РАБ.Р1.1.049 | D50: =IFERROR(INDEX(Работы!$B$2:$B$6000,MATCH($C50,Работы!$A$2:$A$6000,0)),"") -> Исполнительная документация Системы водоснабжения и канализации ("ВК"), включая пояснительную записку (для объектов менее 100 кв.м.) | E50: =IFERROR(INDEX(Работы!$C$2:$C$6000,MATCH($C50,Работы!$A$2:$A$6000,0)),"") -> компл. | F50: =IFERROR(INDEX(Работы!$G$2:$G$6000,MATCH($C50,Работы!$A$2:$A$6000,0)),"") -> 0 | G50: =IFERROR(INDEX(Работы!$K$2:$K$6000,MATCH($C50,Работы!$A$2:$A$6000,0)),"") -> S_общая | J50: =IFERROR(INDEX(Материалы!$B$2:$B$9000,MATCH($I50,Материалы!$A$2:$A$9000,0)),"") | K50: =IF($I50="","",IF($F50=IFERROR(INDEX(Материалы!$G$2:$G$9000,MATCH($I50,Материалы!$A$2:$A$9000,0)),""),"OK","!! не та группа")) | L50: =IFERROR(INDEX(Работы!$H$2:$H$6000,MATCH($C50,Работы!$A$2:$A$6000,0))*(1-ДисконтТендер),0) -> 1039.5 | M50: =IF($I50="",0,IFERROR(INDEX(Материалы!$I$2:$I$9000,MATCH($I50,Материалы!$A$2:$A$9000,0))*IF(INDEX(Материалы!$J$2:$J$9000,MATCH($I50,Материалы!$A$2:$A$9000,0))="USD",КурсUSD,IF(INDEX(Материалы!$J$2:$J$9000,MATCH($I50,Материалы!$A$2:$A$9000,0))="EUR",КурсEUR,1))*INDEX(Материалы!$K$2:$K$9000,MATCH($I50,Материалы!$A$2:$A$9000,0))*(1+IFERROR(INDEX(Работы!$I$2:$I$6000,MATCH($C50,Работы!$A$2:$A$6000,0))/100,0))*(1-ДисконтТендер),0)) -> 0 | N50: =IF(AND($R50="да",$H50<>""),ROUND($H50*$L50,2),0) -> 0 | O50: =IF(AND($R50="да",$H50<>""),ROUND($H50*$M50,2),0) -> 0 | P50: =$N50+$O50 -> 0 | Q50: =IFERROR(INDEX(Работы!$J$2:$J$6000,MATCH($C50,Работы!$A$2:$A$6000,0)),"") -> типовая | R50: да | T50: =IF(AND($P50>0,$R50="да"),MAX($T$1:$T49)+1,"")
A51: =IFERROR(INDEX(Работы!$D$2:$D$6000,MATCH($C51,Работы!$A$2:$A$6000,0)),"") -> Р1 | B51: =IFERROR(INDEX(Работы!$F$2:$F$6000,MATCH($C51,Работы!$A$2:$A$6000,0)),"") -> 1 | C51: =IFERROR(INDEX(Работы!$A$2:$A$6000,50),"") -> РАБ.Р1.1.050 | D51: =IFERROR(INDEX(Работы!$B$2:$B$6000,MATCH($C51,Работы!$A$2:$A$6000,0)),"") -> Исполнительная документация Системы автматической установки водяного пожаротушения ("АУВПТ"), (спринкерная, дренчерная, модульная система), включая пояснительную записку (для объек… | E51: =IFERROR(INDEX(Работы!$C$2:$C$6000,MATCH($C51,Работы!$A$2:$A$6000,0)),"") -> компл. | F51: =IFERROR(INDEX(Работы!$G$2:$G$6000,MATCH($C51,Работы!$A$2:$A$6000,0)),"") -> 0 | G51: =IFERROR(INDEX(Работы!$K$2:$K$6000,MATCH($C51,Работы!$A$2:$A$6000,0)),"") -> S_общая | J51: =IFERROR(INDEX(Материалы!$B$2:$B$9000,MATCH($I51,Материалы!$A$2:$A$9000,0)),"") | K51: =IF($I51="","",IF($F51=IFERROR(INDEX(Материалы!$G$2:$G$9000,MATCH($I51,Материалы!$A$2:$A$9000,0)),""),"OK","!! не та группа")) | L51: =IFERROR(INDEX(Работы!$H$2:$H$6000,MATCH($C51,Работы!$A$2:$A$6000,0))*(1-ДисконтТендер),0) -> 1559.25 | M51: =IF($I51="",0,IFERROR(INDEX(Материалы!$I$2:$I$9000,MATCH($I51,Материалы!$A$2:$A$9000,0))*IF(INDEX(Материалы!$J$2:$J$9000,MATCH($I51,Материалы!$A$2:$A$9000,0))="USD",КурсUSD,IF(INDEX(Материалы!$J$2:$J$9000,MATCH($I51,Материалы!$A$2:$A$9000,0))="EUR",КурсEUR,1))*INDEX(Материалы!$K$2:$K$9000,MATCH($I51,Материалы!$A$2:$A$9000,0))*(1+IFERROR(INDEX(Работы!$I$2:$I$6000,MATCH($C51,Работы!$A$2:$A$6000,0))/100,0))*(1-ДисконтТендер),0)) -> 0 | N51: =IF(AND($R51="да",$H51<>""),ROUND($H51*$L51,2),0) -> 0 | O51: =IF(AND($R51="да",$H51<>""),ROUND($H51*$M51,2),0) -> 0 | P51: =$N51+$O51 -> 0 | Q51: =IFERROR(INDEX(Работы!$J$2:$J$6000,MATCH($C51,Работы!$A$2:$A$6000,0)),"") -> типовая | R51: да | T51: =IF(AND($P51>0,$R51="да"),MAX($T$1:$T50)+1,"")
A52: =IFERROR(INDEX(Работы!$D$2:$D$6000,MATCH($C52,Работы!$A$2:$A$6000,0)),"") -> Р1 | B52: =IFERROR(INDEX(Работы!$F$2:$F$6000,MATCH($C52,Работы!$A$2:$A$6000,0)),"") -> 1 | C52: =IFERROR(INDEX(Работы!$A$2:$A$6000,51),"") -> РАБ.Р1.1.051 | D52: =IFERROR(INDEX(Работы!$B$2:$B$6000,MATCH($C52,Работы!$A$2:$A$6000,0)),"") -> Исполнительная документация Системы Внутреннего противопожарного водопровода ("ВПВ"), включая пояснительную записку (для объектов менее 100 кв.м.) | E52: =IFERROR(INDEX(Работы!$C$2:$C$6000,MATCH($C52,Работы!$A$2:$A$6000,0)),"") -> компл. | F52: =IFERROR(INDEX(Работы!$G$2:$G$6000,MATCH($C52,Работы!$A$2:$A$6000,0)),"") -> 0 | G52: =IFERROR(INDEX(Работы!$K$2:$K$6000,MATCH($C52,Работы!$A$2:$A$6000,0)),"") -> S_общая | J52: =IFERROR(INDEX(Материалы!$B$2:$B$9000,MATCH($I52,Материалы!$A$2:$A$9000,0)),"") | K52: =IF($I52="","",IF($F52=IFERROR(INDEX(Материалы!$G$2:$G$9000,MATCH($I52,Материалы!$A$2:$A$9000,0)),""),"OK","!! не та группа")) | L52: =IFERROR(INDEX(Работы!$H$2:$H$6000,MATCH($C52,Работы!$A$2:$A$6000,0))*(1-ДисконтТендер),0) -> 1039.5 | M52: =IF($I52="",0,IFERROR(INDEX(Материалы!$I$2:$I$9000,MATCH($I52,Материалы!$A$2:$A$9000,0))*IF(INDEX(Материалы!$J$2:$J$9000,MATCH($I52,Материалы!$A$2:$A$9000,0))="USD",КурсUSD,IF(INDEX(Материалы!$J$2:$J$9000,MATCH($I52,Материалы!$A$2:$A$9000,0))="EUR",КурсEUR,1))*INDEX(Материалы!$K$2:$K$9000,MATCH($I52,Материалы!$A$2:$A$9000,0))*(1+IFERROR(INDEX(Работы!$I$2:$I$6000,MATCH($C52,Работы!$A$2:$A$6000,0))/100,0))*(1-ДисконтТендер),0)) -> 0 | N52: =IF(AND($R52="да",$H52<>""),ROUND($H52*$L52,2),0) -> 0 | O52: =IF(AND($R52="да",$H52<>""),ROUND($H52*$M52,2),0) -> 0 | P52: =$N52+$O52 -> 0 | Q52: =IFERROR(INDEX(Работы!$J$2:$J$6000,MATCH($C52,Работы!$A$2:$A$6000,0)),"") -> типовая | R52: да | T52: =IF(AND($P52>0,$R52="да"),MAX($T$1:$T51)+1,"")
A53: =IFERROR(INDEX(Работы!$D$2:$D$6000,MATCH($C53,Работы!$A$2:$A$6000,0)),"") -> Р1 | B53: =IFERROR(INDEX(Работы!$F$2:$F$6000,MATCH($C53,Работы!$A$2:$A$6000,0)),"") -> 1 | C53: =IFERROR(INDEX(Работы!$A$2:$A$6000,52),"") -> РАБ.Р1.1.052 | D53: =IFERROR(INDEX(Работы!$B$2:$B$6000,MATCH($C53,Работы!$A$2:$A$6000,0)),"") -> Исполнительная документация Системы дымоудаления ("ДУ"), включая пояснительную записку (для объектов менее 100 кв.м.) | E53: =IFERROR(INDEX(Работы!$C$2:$C$6000,MATCH($C53,Работы!$A$2:$A$6000,0)),"") -> компл. | F53: =IFERROR(INDEX(Работы!$G$2:$G$6000,MATCH($C53,Работы!$A$2:$A$6000,0)),"") -> 0 | G53: =IFERROR(INDEX(Работы!$K$2:$K$6000,MATCH($C53,Работы!$A$2:$A$6000,0)),"") -> S_общая | J53: =IFERROR(INDEX(Материалы!$B$2:$B$9000,MATCH($I53,Материалы!$A$2:$A$9000,0)),"") | K53: =IF($I53="","",IF($F53=IFERROR(INDEX(Материалы!$G$2:$G$9000,MATCH($I53,Материалы!$A$2:$A$9000,0)),""),"OK","!! не та группа")) | L53: =IFERROR(INDEX(Работы!$H$2:$H$6000,MATCH($C53,Работы!$A$2:$A$6000,0))*(1-ДисконтТендер),0) -> 1559.25 | M53: =IF($I53="",0,IFERROR(INDEX(Материалы!$I$2:$I$9000,MATCH($I53,Материалы!$A$2:$A$9000,0))*IF(INDEX(Материалы!$J$2:$J$9000,MATCH($I53,Материалы!$A$2:$A$9000,0))="USD",КурсUSD,IF(INDEX(Материалы!$J$2:$J$9000,MATCH($I53,Материалы!$A$2:$A$9000,0))="EUR",КурсEUR,1))*INDEX(Материалы!$K$2:$K$9000,MATCH($I53,Материалы!$A$2:$A$9000,0))*(1+IFERROR(INDEX(Работы!$I$2:$I$6000,MATCH($C53,Работы!$A$2:$A$6000,0))/100,0))*(1-ДисконтТендер),0)) -> 0 | N53: =IF(AND($R53="да",$H53<>""),ROUND($H53*$L53,2),0) -> 0 | O53: =IF(AND($R53="да",$H53<>""),ROUND($H53*$M53,2),0) -> 0 | P53: =$N53+$O53 -> 0 | Q53: =IFERROR(INDEX(Работы!$J$2:$J$6000,MATCH($C53,Работы!$A$2:$A$6000,0)),"") -> типовая | R53: да | T53: =IF(AND($P53>0,$R53="да"),MAX($T$1:$T52)+1,"")
A54: =IFERROR(INDEX(Работы!$D$2:$D$6000,MATCH($C54,Работы!$A$2:$A$6000,0)),"") -> Р1 | B54: =IFERROR(INDEX(Работы!$F$2:$F$6000,MATCH($C54,Работы!$A$2:$A$6000,0)),"") -> 1 | C54: =IFERROR(INDEX(Работы!$A$2:$A$6000,53),"") -> РАБ.Р1.1.053 | D54: =IFERROR(INDEX(Работы!$B$2:$B$6000,MATCH($C54,Работы!$A$2:$A$6000,0)),"") -> Рабочая документация "Автоматическая пожарная сигнализация" (АПС) | E54: =IFERROR(INDEX(Работы!$C$2:$C$6000,MATCH($C54,Работы!$A$2:$A$6000,0)),"") -> м2 | F54: =IFERROR(INDEX(Работы!$G$2:$G$6000,MATCH($C54,Работы!$A$2:$A$6000,0)),"") -> 0 | G54: =IFERROR(INDEX(Работы!$K$2:$K$6000,MATCH($C54,Работы!$A$2:$A$6000,0)),"") -> S_общая | J54: =IFERROR(INDEX(Материалы!$B$2:$B$9000,MATCH($I54,Материалы!$A$2:$A$9000,0)),"") | K54: =IF($I54="","",IF($F54=IFERROR(INDEX(Материалы!$G$2:$G$9000,MATCH($I54,Материалы!$A$2:$A$9000,0)),""),"OK","!! не та группа")) | L54: =IFERROR(INDEX(Работы!$H$2:$H$6000,MATCH($C54,Работы!$A$2:$A$6000,0))*(1-ДисконтТендер),0) -> 70.35 | M54: =IF($I54="",0,IFERROR(INDEX(Материалы!$I$2:$I$9000,MATCH($I54,Материалы!$A$2:$A$9000,0))*IF(INDEX(Материалы!$J$2:$J$9000,MATCH($I54,Материалы!$A$2:$A$9000,0))="USD",КурсUSD,IF(INDEX(Материалы!$J$2:$J$9000,MATCH($I54,Материалы!$A$2:$A$9000,0))="EUR",КурсEUR,1))*INDEX(Материалы!$K$2:$K$9000,MATCH($I54,Материалы!$A$2:$A$9000,0))*(1+IFERROR(INDEX(Работы!$I$2:$I$6000,MATCH($C54,Работы!$A$2:$A$6000,0))/100,0))*(1-ДисконтТендер),0)) -> 0 | N54: =IF(AND($R54="да",$H54<>""),ROUND($H54*$L54,2),0) -> 0 | O54: =IF(AND($R54="да",$H54<>""),ROUND($H54*$M54,2),0) -> 0 | P54: =$N54+$O54 -> 0 | Q54: =IFERROR(INDEX(Работы!$J$2:$J$6000,MATCH($C54,Работы!$A$2:$A$6000,0)),"") -> типовая | R54: да | T54: =IF(AND($P54>0,$R54="да"),MAX($T$1:$T53)+1,"")
A55: =IFERROR(INDEX(Работы!$D$2:$D$6000,MATCH($C55,Работы!$A$2:$A$6000,0)),"") -> Р1 | B55: =IFERROR(INDEX(Работы!$F$2:$F$6000,MATCH($C55,Работы!$A$2:$A$6000,0)),"") -> 1 | C55: =IFERROR(INDEX(Работы!$A$2:$A$6000,54),"") -> РАБ.Р1.1.054 | D55: =IFERROR(INDEX(Работы!$B$2:$B$6000,MATCH($C55,Работы!$A$2:$A$6000,0)),"") -> Рабочая документация "Система оповещения и управления эвакуацией людей при пожаре" (СОУЭ) | E55: =IFERROR(INDEX(Работы!$C$2:$C$6000,MATCH($C55,Работы!$A$2:$A$6000,0)),"") -> м2 | F55: =IFERROR(INDEX(Работы!$G$2:$G$6000,MATCH($C55,Работы!$A$2:$A$6000,0)),"") -> 0 | G55: =IFERROR(INDEX(Работы!$K$2:$K$6000,MATCH($C55,Работы!$A$2:$A$6000,0)),"") -> S_общая | J55: =IFERROR(INDEX(Материалы!$B$2:$B$9000,MATCH($I55,Материалы!$A$2:$A$9000,0)),"") | K55: =IF($I55="","",IF($F55=IFERROR(INDEX(Материалы!$G$2:$G$9000,MATCH($I55,Материалы!$A$2:$A$9000,0)),""),"OK","!! не та группа")) | L55: =IFERROR(INDEX(Работы!$H$2:$H$6000,MATCH($C55,Работы!$A$2:$A$6000,0))*(1-ДисконтТендер),0) -> 40.95 | M55: =IF($I55="",0,IFERROR(INDEX(Материалы!$I$2:$I$9000,MATCH($I55,Материалы!$A$2:$A$9000,0))*IF(INDEX(Материалы!$J$2:$J$9000,MATCH($I55,Материалы!$A$2:$A$9000,0))="USD",КурсUSD,IF(INDEX(Материалы!$J$2:$J$9000,MATCH($I55,Материалы!$A$2:$A$9000,0))="EUR",КурсEUR,1))*INDEX(Материалы!$K$2:$K$9000,MATCH($I55,Материалы!$A$2:$A$9000,0))*(1+IFERROR(INDEX(Работы!$I$2:$I$6000,MATCH($C55,Работы!$A$2:$A$6000,0))/100,0))*(1-ДисконтТендер),0)) -> 0 | N55: =IF(AND($R55="да",$H55<>""),ROUND($H55*$L55,2),0) -> 0 | O55: =IF(AND($R55="да",$H55<>""),ROUND($H55*$M55,2),0) -> 0 | P55: =$N55+$O55 -> 0 | Q55: =IFERROR(INDEX(Работы!$J$2:$J$6000,MATCH($C55,Работы!$A$2:$A$6000,0)),"") -> типовая | R55: да | T55: =IF(AND($P55>0,$R55="да"),MAX($T$1:$T54)+1,"")
A56: =IFERROR(INDEX(Работы!$D$2:$D$6000,MATCH($C56,Работы!$A$2:$A$6000,0)),"") -> Р1 | B56: =IFERROR(INDEX(Работы!$F$2:$F$6000,MATCH($C56,Работы!$A$2:$A$6000,0)),"") -> 1 | C56: =IFERROR(INDEX(Работы!$A$2:$A$6000,55),"") -> РАБ.Р1.1.055 | D56: =IFERROR(INDEX(Работы!$B$2:$B$6000,MATCH($C56,Работы!$A$2:$A$6000,0)),"") -> Рабочая документация "Автоматизация системы внутреннего противопожарного водопровода (ВПВ) | E56: =IFERROR(INDEX(Работы!$C$2:$C$6000,MATCH($C56,Работы!$A$2:$A$6000,0)),"") -> м2 | F56: =IFERROR(INDEX(Работы!$G$2:$G$6000,MATCH($C56,Работы!$A$2:$A$6000,0)),"") -> 0 | G56: =IFERROR(INDEX(Работы!$K$2:$K$6000,MATCH($C56,Работы!$A$2:$A$6000,0)),"") -> S_общая | J56: =IFERROR(INDEX(Материалы!$B$2:$B$9000,MATCH($I56,Материалы!$A$2:$A$9000,0)),"") | K56: =IF($I56="","",IF($F56=IFERROR(INDEX(Материалы!$G$2:$G$9000,MATCH($I56,Материалы!$A$2:$A$9000,0)),""),"OK","!! не та группа")) | L56: =IFERROR(INDEX(Работы!$H$2:$H$6000,MATCH($C56,Работы!$A$2:$A$6000,0))*(1-ДисконтТендер),0) -> 8.4 | M56: =IF($I56="",0,IFERROR(INDEX(Материалы!$I$2:$I$9000,MATCH($I56,Материалы!$A$2:$A$9000,0))*IF(INDEX(Материалы!$J$2:$J$9000,MATCH($I56,Материалы!$A$2:$A$9000,0))="USD",КурсUSD,IF(INDEX(Материалы!$J$2:$J$9000,MATCH($I56,Материалы!$A$2:$A$9000,0))="EUR",КурсEUR,1))*INDEX(Материалы!$K$2:$K$9000,MATCH($I56,Материалы!$A$2:$A$9000,0))*(1+IFERROR(INDEX(Работы!$I$2:$I$6000,MATCH($C56,Работы!$A$2:$A$6000,0))/100,0))*(1-ДисконтТендер),0)) -> 0 | N56: =IF(AND($R56="да",$H56<>""),ROUND($H56*$L56,2),0) -> 0 | O56: =IF(AND($R56="да",$H56<>""),ROUND($H56*$M56,2),0) -> 0 | P56: =$N56+$O56 -> 0 | Q56: =IFERROR(INDEX(Работы!$J$2:$J$6000,MATCH($C56,Работы!$A$2:$A$6000,0)),"") -> типовая | R56: да | T56: =IF(AND($P56>0,$R56="да"),MAX($T$1:$T55)+1,"")
A57: =IFERROR(INDEX(Работы!$D$2:$D$6000,MATCH($C57,Работы!$A$2:$A$6000,0)),"") -> Р1 | B57: =IFERROR(INDEX(Работы!$F$2:$F$6000,MATCH($C57,Работы!$A$2:$A$6000,0)),"") -> 1 | C57: =IFERROR(INDEX(Работы!$A$2:$A$6000,56),"") -> РАБ.Р1.1.056 | D57: =IFERROR(INDEX(Работы!$B$2:$B$6000,MATCH($C57,Работы!$A$2:$A$6000,0)),"") -> Рабочая документация "Автоматизация системы противодымной вентиляции (ПДВ")" | E57: =IFERROR(INDEX(Работы!$C$2:$C$6000,MATCH($C57,Работы!$A$2:$A$6000,0)),"") -> м2 | F57: =IFERROR(INDEX(Работы!$G$2:$G$6000,MATCH($C57,Работы!$A$2:$A$6000,0)),"") -> 0 | G57: =IFERROR(INDEX(Работы!$K$2:$K$6000,MATCH($C57,Работы!$A$2:$A$6000,0)),"") -> S_общая | J57: =IFERROR(INDEX(Материалы!$B$2:$B$9000,MATCH($I57,Материалы!$A$2:$A$9000,0)),"") | K57: =IF($I57="","",IF($F57=IFERROR(INDEX(Материалы!$G$2:$G$9000,MATCH($I57,Материалы!$A$2:$A$9000,0)),""),"OK","!! не та группа")) | L57: =IFERROR(INDEX(Работы!$H$2:$H$6000,MATCH($C57,Работы!$A$2:$A$6000,0))*(1-ДисконтТендер),0) -> 26.25 | M57: =IF($I57="",0,IFERROR(INDEX(Материалы!$I$2:$I$9000,MATCH($I57,Материалы!$A$2:$A$9000,0))*IF(INDEX(Материалы!$J$2:$J$9000,MATCH($I57,Материалы!$A$2:$A$9000,0))="USD",КурсUSD,IF(INDEX(Материалы!$J$2:$J$9000,MATCH($I57,Материалы!$A$2:$A$9000,0))="EUR",КурсEUR,1))*INDEX(Материалы!$K$2:$K$9000,MATCH($I57,Материалы!$A$2:$A$9000,0))*(1+IFERROR(INDEX(Работы!$I$2:$I$6000,MATCH($C57,Работы!$A$2:$A$6000,0))/100,0))*(1-ДисконтТендер),0)) -> 0 | N57: =IF(AND($R57="да",$H57<>""),ROUND($H57*$L57,2),0) -> 0 | O57: =IF(AND($R57="да",$H57<>""),ROUND($H57*$M57,2),0) -> 0 | P57: =$N57+$O57 -> 0 | Q57: =IFERROR(INDEX(Работы!$J$2:$J$6000,MATCH($C57,Работы!$A$2:$A$6000,0)),"") -> типовая | R57: да | T57: =IF(AND($P57>0,$R57="да"),MAX($T$1:$T56)+1,"")
A58: =IFERROR(INDEX(Работы!$D$2:$D$6000,MATCH($C58,Работы!$A$2:$A$6000,0)),"") -> Р1 | B58: =IFERROR(INDEX(Работы!$F$2:$F$6000,MATCH($C58,Работы!$A$2:$A$6000,0)),"") -> 1 | C58: =IFERROR(INDEX(Работы!$A$2:$A$6000,57),"") -> РАБ.Р1.1.057 | D58: =IFERROR(INDEX(Работы!$B$2:$B$6000,MATCH($C58,Работы!$A$2:$A$6000,0)),"") -> Рабочая документация "Автоматизация Системы отопления, вентиляции и кондиционирования (ОВиК)" | E58: =IFERROR(INDEX(Работы!$C$2:$C$6000,MATCH($C58,Работы!$A$2:$A$6000,0)),"") -> м2 | F58: =IFERROR(INDEX(Работы!$G$2:$G$6000,MATCH($C58,Работы!$A$2:$A$6000,0)),"") -> 0 | G58: =IFERROR(INDEX(Работы!$K$2:$K$6000,MATCH($C58,Работы!$A$2:$A$6000,0)),"") -> S_общая | J58: =IFERROR(INDEX(Материалы!$B$2:$B$9000,MATCH($I58,Материалы!$A$2:$A$9000,0)),"") | K58: =IF($I58="","",IF($F58=IFERROR(INDEX(Материалы!$G$2:$G$9000,MATCH($I58,Материалы!$A$2:$A$9000,0)),""),"OK","!! не та группа")) | L58: =IFERROR(INDEX(Работы!$H$2:$H$6000,MATCH($C58,Работы!$A$2:$A$6000,0))*(1-ДисконтТендер),0) -> 3.15 | M58: =IF($I58="",0,IFERROR(INDEX(Материалы!$I$2:$I$9000,MATCH($I58,Материалы!$A$2:$A$9000,0))*IF(INDEX(Материалы!$J$2:$J$9000,MATCH($I58,Материалы!$A$2:$A$9000,0))="USD",КурсUSD,IF(INDEX(Материалы!$J$2:$J$9000,MATCH($I58,Материалы!$A$2:$A$9000,0))="EUR",КурсEUR,1))*INDEX(Материалы!$K$2:$K$9000,MATCH($I58,Материалы!$A$2:$A$9000,0))*(1+IFERROR(INDEX(Работы!$I$2:$I$6000,MATCH($C58,Работы!$A$2:$A$6000,0))/100,0))*(1-ДисконтТендер),0)) -> 0 | N58: =IF(AND($R58="да",$H58<>""),ROUND($H58*$L58,2),0) -> 0 | O58: =IF(AND($R58="да",$H58<>""),ROUND($H58*$M58,2),0) -> 0 | P58: =$N58+$O58 -> 0 | Q58: =IFERROR(INDEX(Работы!$J$2:$J$6000,MATCH($C58,Работы!$A$2:$A$6000,0)),"") -> типовая | R58: да | T58: =IF(AND($P58>0,$R58="да"),MAX($T$1:$T57)+1,"")
A59: =IFERROR(INDEX(Работы!$D$2:$D$6000,MATCH($C59,Работы!$A$2:$A$6000,0)),"") -> Р1 | B59: =IFERROR(INDEX(Работы!$F$2:$F$6000,MATCH($C59,Работы!$A$2:$A$6000,0)),"") -> 1 | C59: =IFERROR(INDEX(Работы!$A$2:$A$6000,58),"") -> РАБ.Р1.1.058 | D59: =IFERROR(INDEX(Работы!$B$2:$B$6000,MATCH($C59,Работы!$A$2:$A$6000,0)),"") -> Рабочая документация "Автоматизация Системы аварийного освещения (АО)" | E59: =IFERROR(INDEX(Работы!$C$2:$C$6000,MATCH($C59,Работы!$A$2:$A$6000,0)),"") -> м2 | F59: =IFERROR(INDEX(Работы!$G$2:$G$6000,MATCH($C59,Работы!$A$2:$A$6000,0)),"") -> 0 | G59: =IFERROR(INDEX(Работы!$K$2:$K$6000,MATCH($C59,Работы!$A$2:$A$6000,0)),"") -> S_общая | J59: =IFERROR(INDEX(Материалы!$B$2:$B$9000,MATCH($I59,Материалы!$A$2:$A$9000,0)),"") | K59: =IF($I59="","",IF($F59=IFERROR(INDEX(Материалы!$G$2:$G$9000,MATCH($I59,Материалы!$A$2:$A$9000,0)),""),"OK","!! не та группа")) | L59: =IFERROR(INDEX(Работы!$H$2:$H$6000,MATCH($C59,Работы!$A$2:$A$6000,0))*(1-ДисконтТендер),0) -> 1.05 | M59: =IF($I59="",0,IFERROR(INDEX(Материалы!$I$2:$I$9000,MATCH($I59,Материалы!$A$2:$A$9000,0))*IF(INDEX(Материалы!$J$2:$J$9000,MATCH($I59,Материалы!$A$2:$A$9000,0))="USD",КурсUSD,IF(INDEX(Материалы!$J$2:$J$9000,MATCH($I59,Материалы!$A$2:$A$9000,0))="EUR",КурсEUR,1))*INDEX(Материалы!$K$2:$K$9000,MATCH($I59,Материалы!$A$2:$A$9000,0))*(1+IFERROR(INDEX(Работы!$I$2:$I$6000,MATCH($C59,Работы!$A$2:$A$6000,0))/100,0))*(1-ДисконтТендер),0)) -> 0 | N59: =IF(AND($R59="да",$H59<>""),ROUND($H59*$L59,2),0) -> 0 | O59: =IF(AND($R59="да",$H59<>""),ROUND($H59*$M59,2),0) -> 0 | P59: =$N59+$O59 -> 0 | Q59: =IFERROR(INDEX(Работы!$J$2:$J$6000,MATCH($C59,Работы!$A$2:$A$6000,0)),"") -> типовая | R59: да | T59: =IF(AND($P59>0,$R59="да"),MAX($T$1:$T58)+1,"")
A60: =IFERROR(INDEX(Работы!$D$2:$D$6000,MATCH($C60,Работы!$A$2:$A$6000,0)),"") -> Р1 | B60: =IFERROR(INDEX(Работы!$F$2:$F$6000,MATCH($C60,Работы!$A$2:$A$6000,0)),"") -> 1 | C60: =IFERROR(INDEX(Работы!$A$2:$A$6000,59),"") -> РАБ.Р1.1.059 | D60: =IFERROR(INDEX(Работы!$B$2:$B$6000,MATCH($C60,Работы!$A$2:$A$6000,0)),"") -> Рабочая документация "Автоматизации лифтовового хозяйства" | E60: =IFERROR(INDEX(Работы!$C$2:$C$6000,MATCH($C60,Работы!$A$2:$A$6000,0)),"") -> м2 | F60: =IFERROR(INDEX(Работы!$G$2:$G$6000,MATCH($C60,Работы!$A$2:$A$6000,0)),"") -> 0 | G60: =IFERROR(INDEX(Работы!$K$2:$K$6000,MATCH($C60,Работы!$A$2:$A$6000,0)),"") -> S_общая | J60: =IFERROR(INDEX(Материалы!$B$2:$B$9000,MATCH($I60,Материалы!$A$2:$A$9000,0)),"") | K60: =IF($I60="","",IF($F60=IFERROR(INDEX(Материалы!$G$2:$G$9000,MATCH($I60,Материалы!$A$2:$A$9000,0)),""),"OK","!! не та группа")) | L60: =IFERROR(INDEX(Работы!$H$2:$H$6000,MATCH($C60,Работы!$A$2:$A$6000,0))*(1-ДисконтТендер),0) -> 1.05 | M60: =IF($I60="",0,IFERROR(INDEX(Материалы!$I$2:$I$9000,MATCH($I60,Материалы!$A$2:$A$9000,0))*IF(INDEX(Материалы!$J$2:$J$9000,MATCH($I60,Материалы!$A$2:$A$9000,0))="USD",КурсUSD,IF(INDEX(Материалы!$J$2:$J$9000,MATCH($I60,Материалы!$A$2:$A$9000,0))="EUR",КурсEUR,1))*INDEX(Материалы!$K$2:$K$9000,MATCH($I60,Материалы!$A$2:$A$9000,0))*(1+IFERROR(INDEX(Работы!$I$2:$I$6000,MATCH($C60,Работы!$A$2:$A$6000,0))/100,0))*(1-ДисконтТендер),0)) -> 0 | N60: =IF(AND($R60="да",$H60<>""),ROUND($H60*$L60,2),0) -> 0 | O60: =IF(AND($R60="да",$H60<>""),ROUND($H60*$M60,2),0) -> 0 | P60: =$N60+$O60 -> 0 | Q60: =IFERROR(INDEX(Работы!$J$2:$J$6000,MATCH($C60,Работы!$A$2:$A$6000,0)),"") -> нетиповая | R60: да | T60: =IF(AND($P60>0,$R60="да"),MAX($T$1:$T59)+1,"")
A61: =IFERROR(INDEX(Работы!$D$2:$D$6000,MATCH($C61,Работы!$A$2:$A$6000,0)),"") -> Р1 | B61: =IFERROR(INDEX(Работы!$F$2:$F$6000,MATCH($C61,Работы!$A$2:$A$6000,0)),"") -> 1 | C61: =IFERROR(INDEX(Работы!$A$2:$A$6000,60),"") -> РАБ.Р1.1.060 | D61: =IFERROR(INDEX(Работы!$B$2:$B$6000,MATCH($C61,Работы!$A$2:$A$6000,0)),"") -> Рабочая документация "Автоматизации Системы контроля управления доступом (СКУД)" | E61: =IFERROR(INDEX(Работы!$C$2:$C$6000,MATCH($C61,Работы!$A$2:$A$6000,0)),"") -> м2 | F61: =IFERROR(INDEX(Работы!$G$2:$G$6000,MATCH($C61,Работы!$A$2:$A$6000,0)),"") -> 0 | G61: =IFERROR(INDEX(Работы!$K$2:$K$6000,MATCH($C61,Работы!$A$2:$A$6000,0)),"") -> S_общая | J61: =IFERROR(INDEX(Материалы!$B$2:$B$9000,MATCH($I61,Материалы!$A$2:$A$9000,0)),"") | K61: =IF($I61="","",IF($F61=IFERROR(INDEX(Материалы!$G$2:$G$9000,MATCH($I61,Материалы!$A$2:$A$9000,0)),""),"OK","!! не та группа")) | L61: =IFERROR(INDEX(Работы!$H$2:$H$6000,MATCH($C61,Работы!$A$2:$A$6000,0))*(1-ДисконтТендер),0) -> 1.05 | M61: =IF($I61="",0,IFERROR(INDEX(Материалы!$I$2:$I$9000,MATCH($I61,Материалы!$A$2:$A$9000,0))*IF(INDEX(Материалы!$J$2:$J$9000,MATCH($I61,Материалы!$A$2:$A$9000,0))="USD",КурсUSD,IF(INDEX(Материалы!$J$2:$J$9000,MATCH($I61,Материалы!$A$2:$A$9000,0))="EUR",КурсEUR,1))*INDEX(Материалы!$K$2:$K$9000,MATCH($I61,Материалы!$A$2:$A$9000,0))*(1+IFERROR(INDEX(Работы!$I$2:$I$6000,MATCH($C61,Работы!$A$2:$A$6000,0))/100,0))*(1-ДисконтТендер),0)) -> 0 | N61: =IF(AND($R61="да",$H61<>""),ROUND($H61*$L61,2),0) -> 0 | O61: =IF(AND($R61="да",$H61<>""),ROUND($H61*$M61,2),0) -> 0 | P61: =$N61+$O61 -> 0 | Q61: =IFERROR(INDEX(Работы!$J$2:$J$6000,MATCH($C61,Работы!$A$2:$A$6000,0)),"") -> типовая | R61: да | T61: =IF(AND($P61>0,$R61="да"),MAX($T$1:$T60)+1,"")
A62: =IFERROR(INDEX(Работы!$D$2:$D$6000,MATCH($C62,Работы!$A$2:$A$6000,0)),"") -> Р1 | B62: =IFERROR(INDEX(Работы!$F$2:$F$6000,MATCH($C62,Работы!$A$2:$A$6000,0)),"") -> 1 | C62: =IFERROR(INDEX(Работы!$A$2:$A$6000,61),"") -> РАБ.Р1.1.061 | D62: =IFERROR(INDEX(Работы!$B$2:$B$6000,MATCH($C62,Работы!$A$2:$A$6000,0)),"") -> Стоимость согласования проекта перепланировки/реставрации объекта культурного наследия в соответствии с нормативными актами г.______________. | E62: =IFERROR(INDEX(Работы!$C$2:$C$6000,MATCH($C62,Работы!$A$2:$A$6000,0)),"") -> м2 | F62: =IFERROR(INDEX(Работы!$G$2:$G$6000,MATCH($C62,Работы!$A$2:$A$6000,0)),"") -> 0 | G62: =IFERROR(INDEX(Работы!$K$2:$K$6000,MATCH($C62,Работы!$A$2:$A$6000,0)),"") -> S_общая | J62: =IFERROR(INDEX(Материалы!$B$2:$B$9000,MATCH($I62,Материалы!$A$2:$A$9000,0)),"") | K62: =IF($I62="","",IF($F62=IFERROR(INDEX(Материалы!$G$2:$G$9000,MATCH($I62,Материалы!$A$2:$A$9000,0)),""),"OK","!! не та группа")) | L62: =IFERROR(INDEX(Работы!$H$2:$H$6000,MATCH($C62,Работы!$A$2:$A$6000,0))*(1-ДисконтТендер),0) -> 0 | M62: =IF($I62="",0,IFERROR(INDEX(Материалы!$I$2:$I$9000,MATCH($I62,Материалы!$A$2:$A$9000,0))*IF(INDEX(Материалы!$J$2:$J$9000,MATCH($I62,Материалы!$A$2:$A$9000,0))="USD",КурсUSD,IF(INDEX(Материалы!$J$2:$J$9000,MATCH($I62,Материалы!$A$2:$A$9000,0))="EUR",КурсEUR,1))*INDEX(Материалы!$K$2:$K$9000,MATCH($I62,Материалы!$A$2:$A$9000,0))*(1+IFERROR(INDEX(Работы!$I$2:$I$6000,MATCH($C62,Работы!$A$2:$A$6000,0))/100,0))*(1-ДисконтТендер),0)) -> 0 | N62: =IF(AND($R62="да",$H62<>""),ROUND($H62*$L62,2),0) -> 0 | O62: =IF(AND($R62="да",$H62<>""),ROUND($H62*$M62,2),0) -> 0 | P62: =$N62+$O62 -> 0 | Q62: =IFERROR(INDEX(Работы!$J$2:$J$6000,MATCH($C62,Работы!$A$2:$A$6000,0)),"") -> типовая | R62: да | T62: =IF(AND($P62>0,$R62="да"),MAX($T$1:$T61)+1,"")
A63: =IFERROR(INDEX(Работы!$D$2:$D$6000,MATCH($C63,Работы!$A$2:$A$6000,0)),"") -> Р1 | B63: =IFERROR(INDEX(Работы!$F$2:$F$6000,MATCH($C63,Работы!$A$2:$A$6000,0)),"") -> 1 | C63: =IFERROR(INDEX(Работы!$A$2:$A$6000,62),"") -> РАБ.Р1.1.062 | D63: =IFERROR(INDEX(Работы!$B$2:$B$6000,MATCH($C63,Работы!$A$2:$A$6000,0)),"") -> Стоимость согласования проекта перепланировки/реконструкции объекта в соответствии с нормативными актами г.______________. | E63: =IFERROR(INDEX(Работы!$C$2:$C$6000,MATCH($C63,Работы!$A$2:$A$6000,0)),"") -> м2 | F63: =IFERROR(INDEX(Работы!$G$2:$G$6000,MATCH($C63,Работы!$A$2:$A$6000,0)),"") -> 0 | G63: =IFERROR(INDEX(Работы!$K$2:$K$6000,MATCH($C63,Работы!$A$2:$A$6000,0)),"") -> S_общая | J63: =IFERROR(INDEX(Материалы!$B$2:$B$9000,MATCH($I63,Материалы!$A$2:$A$9000,0)),"") | K63: =IF($I63="","",IF($F63=IFERROR(INDEX(Материалы!$G$2:$G$9000,MATCH($I63,Материалы!$A$2:$A$9000,0)),""),"OK","!! не та группа")) | L63: =IFERROR(INDEX(Работы!$H$2:$H$6000,MATCH($C63,Работы!$A$2:$A$6000,0))*(1-ДисконтТендер),0) -> 0 | M63: =IF($I63="",0,IFERROR(INDEX(Материалы!$I$2:$I$9000,MATCH($I63,Материалы!$A$2:$A$9000,0))*IF(INDEX(Материалы!$J$2:$J$9000,MATCH($I63,Материалы!$A$2:$A$9000,0))="USD",КурсUSD,IF(INDEX(Материалы!$J$2:$J$9000,MATCH($I63,Материалы!$A$2:$A$9000,0))="EUR",КурсEUR,1))*INDEX(Материалы!$K$2:$K$9000,MATCH($I63,Материалы!$A$2:$A$9000,0))*(1+IFERROR(INDEX(Работы!$I$2:$I$6000,MATCH($C63,Работы!$A$2:$A$6000,0))/100,0))*(1-ДисконтТендер),0)) -> 0 | N63: =IF(AND($R63="да",$H63<>""),ROUND($H63*$L63,2),0) -> 0 | O63: =IF(AND($R63="да",$H63<>""),ROUND($H63*$M63,2),0) -> 0 | P63: =$N63+$O63 -> 0 | Q63: =IFERROR(INDEX(Работы!$J$2:$J$6000,MATCH($C63,Работы!$A$2:$A$6000,0)),"") -> типовая | R63: да | T63: =IF(AND($P63>0,$R63="да"),MAX($T$1:$T62)+1,"")
A64: =IFERROR(INDEX(Работы!$D$2:$D$6000,MATCH($C64,Работы!$A$2:$A$6000,0)),"") -> Р1 | B64: =IFERROR(INDEX(Работы!$F$2:$F$6000,MATCH($C64,Работы!$A$2:$A$6000,0)),"") -> 1 | C64: =IFERROR(INDEX(Работы!$A$2:$A$6000,63),"") -> РАБ.Р1.1.063 | D64: =IFERROR(INDEX(Работы!$B$2:$B$6000,MATCH($C64,Работы!$A$2:$A$6000,0)),"") -> Получение паспорта БТИ (в черных линиях) | E64: =IFERROR(INDEX(Работы!$C$2:$C$6000,MATCH($C64,Работы!$A$2:$A$6000,0)),"") -> м2 | F64: =IFERROR(INDEX(Работы!$G$2:$G$6000,MATCH($C64,Работы!$A$2:$A$6000,0)),"") -> 0 | G64: =IFERROR(INDEX(Работы!$K$2:$K$6000,MATCH($C64,Работы!$A$2:$A$6000,0)),"") -> S_общая | J64: =IFERROR(INDEX(Материалы!$B$2:$B$9000,MATCH($I64,Материалы!$A$2:$A$9000,0)),"") | K64: =IF($I64="","",IF($F64=IFERROR(INDEX(Материалы!$G$2:$G$9000,MATCH($I64,Материалы!$A$2:$A$9000,0)),""),"OK","!! не та группа")) | L64: =IFERROR(INDEX(Работы!$H$2:$H$6000,MATCH($C64,Работы!$A$2:$A$6000,0))*(1-ДисконтТендер),0) -> 0 | M64: =IF($I64="",0,IFERROR(INDEX(Материалы!$I$2:$I$9000,MATCH($I64,Материалы!$A$2:$A$9000,0))*IF(INDEX(Материалы!$J$2:$J$9000,MATCH($I64,Материалы!$A$2:$A$9000,0))="USD",КурсUSD,IF(INDEX(Материалы!$J$2:$J$9000,MATCH($I64,Материалы!$A$2:$A$9000,0))="EUR",КурсEUR,1))*INDEX(Материалы!$K$2:$K$9000,MATCH($I64,Материалы!$A$2:$A$9000,0))*(1+IFERROR(INDEX(Работы!$I$2:$I$6000,MATCH($C64,Работы!$A$2:$A$6000,0))/100,0))*(1-ДисконтТендер),0)) -> 0 | N64: =IF(AND($R64="да",$H64<>""),ROUND($H64*$L64,2),0) -> 0 | O64: =IF(AND($R64="да",$H64<>""),ROUND($H64*$M64,2),0) -> 0 | P64: =$N64+$O64 -> 0 | Q64: =IFERROR(INDEX(Работы!$J$2:$J$6000,MATCH($C64,Работы!$A$2:$A$6000,0)),"") -> типовая | R64: да | T64: =IF(AND($P64>0,$R64="да"),MAX($T$1:$T63)+1,"")
A65: =IFERROR(INDEX(Работы!$D$2:$D$6000,MATCH($C65,Работы!$A$2:$A$6000,0)),"") -> Р1 | B65: =IFERROR(INDEX(Работы!$F$2:$F$6000,MATCH($C65,Работы!$A$2:$A$6000,0)),"") -> 1 | C65: =IFERROR(INDEX(Работы!$A$2:$A$6000,64),"") -> РАБ.Р1.1.064 | D65: =IFERROR(INDEX(Работы!$B$2:$B$6000,MATCH($C65,Работы!$A$2:$A$6000,0)),"") -> Сертификация помещения для совершения операций с ценностями, хранение ценностей по (2) классу вломостойкости и (3) классу пулестойкости | E65: =IFERROR(INDEX(Работы!$C$2:$C$6000,MATCH($C65,Работы!$A$2:$A$6000,0)),"") -> м2 | F65: =IFERROR(INDEX(Работы!$G$2:$G$6000,MATCH($C65,Работы!$A$2:$A$6000,0)),"") -> 0 | G65: =IFERROR(INDEX(Работы!$K$2:$K$6000,MATCH($C65,Работы!$A$2:$A$6000,0)),"") -> S_общая | J65: =IFERROR(INDEX(Материалы!$B$2:$B$9000,MATCH($I65,Материалы!$A$2:$A$9000,0)),"") | K65: =IF($I65="","",IF($F65=IFERROR(INDEX(Материалы!$G$2:$G$9000,MATCH($I65,Материалы!$A$2:$A$9000,0)),""),"OK","!! не та группа")) | L65: =IFERROR(INDEX(Работы!$H$2:$H$6000,MATCH($C65,Работы!$A$2:$A$6000,0))*(1-ДисконтТендер),0) -> 88.99 | M65: =IF($I65="",0,IFERROR(INDEX(Материалы!$I$2:$I$9000,MATCH($I65,Материалы!$A$2:$A$9000,0))*IF(INDEX(Материалы!$J$2:$J$9000,MATCH($I65,Материалы!$A$2:$A$9000,0))="USD",КурсUSD,IF(INDEX(Материалы!$J$2:$J$9000,MATCH($I65,Материалы!$A$2:$A$9000,0))="EUR",КурсEUR,1))*INDEX(Материалы!$K$2:$K$9000,MATCH($I65,Материалы!$A$2:$A$9000,0))*(1+IFERROR(INDEX(Работы!$I$2:$I$6000,MATCH($C65,Работы!$A$2:$A$6000,0))/100,0))*(1-ДисконтТендер),0)) -> 0 | N65: =IF(AND($R65="да",$H65<>""),ROUND($H65*$L65,2),0) -> 0 | O65: =IF(AND($R65="да",$H65<>""),ROUND($H65*$M65,2),0) -> 0 | P65: =$N65+$O65 -> 0 | Q65: =IFERROR(INDEX(Работы!$J$2:$J$6000,MATCH($C65,Работы!$A$2:$A$6000,0)),"") -> типовая | R65: да | T65: =IF(AND($P65>0,$R65="да"),MAX($T$1:$T64)+1,"")
A66: =IFERROR(INDEX(Работы!$D$2:$D$6000,MATCH($C66,Работы!$A$2:$A$6000,0)),"") -> Р1 | B66: =IFERROR(INDEX(Работы!$F$2:$F$6000,MATCH($C66,Работы!$A$2:$A$6000,0)),"") -> 1 | C66: =IFERROR(INDEX(Работы!$A$2:$A$6000,65),"") -> РАБ.Р1.1.065 | D66: =IFERROR(INDEX(Работы!$B$2:$B$6000,MATCH($C66,Работы!$A$2:$A$6000,0)),"") -> Сертификация помещения для совершения операций с ценностями, хранение ценностей по 3 классу вломостойкости и 3 классу пулестойкости | E66: =IFERROR(INDEX(Работы!$C$2:$C$6000,MATCH($C66,Работы!$A$2:$A$6000,0)),"") -> м2 | F66: =IFERROR(INDEX(Работы!$G$2:$G$6000,MATCH($C66,Работы!$A$2:$A$6000,0)),"") -> 0 | G66: =IFERROR(INDEX(Работы!$K$2:$K$6000,MATCH($C66,Работы!$A$2:$A$6000,0)),"") -> S_общая | J66: =IFERROR(INDEX(Материалы!$B$2:$B$9000,MATCH($I66,Материалы!$A$2:$A$9000,0)),"") | K66: =IF($I66="","",IF($F66=IFERROR(INDEX(Материалы!$G$2:$G$9000,MATCH($I66,Материалы!$A$2:$A$9000,0)),""),"OK","!! не та группа")) | L66: =IFERROR(INDEX(Работы!$H$2:$H$6000,MATCH($C66,Работы!$A$2:$A$6000,0))*(1-ДисконтТендер),0) -> 149.82 | M66: =IF($I66="",0,IFERROR(INDEX(Материалы!$I$2:$I$9000,MATCH($I66,Материалы!$A$2:$A$9000,0))*IF(INDEX(Материалы!$J$2:$J$9000,MATCH($I66,Материалы!$A$2:$A$9000,0))="USD",КурсUSD,IF(INDEX(Материалы!$J$2:$J$9000,MATCH($I66,Материалы!$A$2:$A$9000,0))="EUR",КурсEUR,1))*INDEX(Материалы!$K$2:$K$9000,MATCH($I66,Материалы!$A$2:$A$9000,0))*(1+IFERROR(INDEX(Работы!$I$2:$I$6000,MATCH($C66,Работы!$A$2:$A$6000,0))/100,0))*(1-ДисконтТендер),0)) -> 0 | N66: =IF(AND($R66="да",$H66<>""),ROUND($H66*$L66,2),0) -> 0 | O66: =IF(AND($R66="да",$H66<>""),ROUND($H66*$M66,2),0) -> 0 | P66: =$N66+$O66 -> 0 | Q66: =IFERROR(INDEX(Работы!$J$2:$J$6000,MATCH($C66,Работы!$A$2:$A$6000,0)),"") -> типовая | R66: да | T66: =IF(AND($P66>0,$R66="да"),MAX($T$1:$T65)+1,"")
A67: =IFERROR(INDEX(Работы!$D$2:$D$6000,MATCH($C67,Работы!$A$2:$A$6000,0)),"") -> Р1 | B67: =IFERROR(INDEX(Работы!$F$2:$F$6000,MATCH($C67,Работы!$A$2:$A$6000,0)),"") -> 1 | C67: =IFERROR(INDEX(Работы!$A$2:$A$6000,66),"") -> РАБ.Р1.1.066 | D67: =IFERROR(INDEX(Работы!$B$2:$B$6000,MATCH($C67,Работы!$A$2:$A$6000,0)),"") -> Сертификация помещения для совершения операций с ценностями, хранение ценностей по (5) классу вломостойкости | E67: =IFERROR(INDEX(Работы!$C$2:$C$6000,MATCH($C67,Работы!$A$2:$A$6000,0)),"") -> м2 | F67: =IFERROR(INDEX(Работы!$G$2:$G$6000,MATCH($C67,Работы!$A$2:$A$6000,0)),"") -> 0 | G67: =IFERROR(INDEX(Работы!$K$2:$K$6000,MATCH($C67,Работы!$A$2:$A$6000,0)),"") -> S_общая | J67: =IFERROR(INDEX(Материалы!$B$2:$B$9000,MATCH($I67,Материалы!$A$2:$A$9000,0)),"") | K67: =IF($I67="","",IF($F67=IFERROR(INDEX(Материалы!$G$2:$G$9000,MATCH($I67,Материалы!$A$2:$A$9000,0)),""),"OK","!! не та группа")) | L67: =IFERROR(INDEX(Работы!$H$2:$H$6000,MATCH($C67,Работы!$A$2:$A$6000,0))*(1-ДисконтТендер),0) -> 96.48 | M67: =IF($I67="",0,IFERROR(INDEX(Материалы!$I$2:$I$9000,MATCH($I67,Материалы!$A$2:$A$9000,0))*IF(INDEX(Материалы!$J$2:$J$9000,MATCH($I67,Материалы!$A$2:$A$9000,0))="USD",КурсUSD,IF(INDEX(Материалы!$J$2:$J$9000,MATCH($I67,Материалы!$A$2:$A$9000,0))="EUR",КурсEUR,1))*INDEX(Материалы!$K$2:$K$9000,MATCH($I67,Материалы!$A$2:$A$9000,0))*(1+IFERROR(INDEX(Работы!$I$2:$I$6000,MATCH($C67,Работы!$A$2:$A$6000,0))/100,0))*(1-ДисконтТендер),0)) -> 0 | N67: =IF(AND($R67="да",$H67<>""),ROUND($H67*$L67,2),0) -> 0 | O67: =IF(AND($R67="да",$H67<>""),ROUND($H67*$M67,2),0) -> 0 | P67: =$N67+$O67 -> 0 | Q67: =IFERROR(INDEX(Работы!$J$2:$J$6000,MATCH($C67,Работы!$A$2:$A$6000,0)),"") -> типовая | R67: да | T67: =IF(AND($P67>0,$R67="да"),MAX($T$1:$T66)+1,"")
A68: =IFERROR(INDEX(Работы!$D$2:$D$6000,MATCH($C68,Работы!$A$2:$A$6000,0)),"") -> Р1 | B68: =IFERROR(INDEX(Работы!$F$2:$F$6000,MATCH($C68,Работы!$A$2:$A$6000,0)),"") -> 1 | C68: =IFERROR(INDEX(Работы!$A$2:$A$6000,67),"") -> РАБ.Р1.1.067 | D68: =IFERROR(INDEX(Работы!$B$2:$B$6000,MATCH($C68,Работы!$A$2:$A$6000,0)),"") -> Технический отчет электролаборатории для помещений более 100 м.кв. | E68: =IFERROR(INDEX(Работы!$C$2:$C$6000,MATCH($C68,Работы!$A$2:$A$6000,0)),"") -> м2 | F68: =IFERROR(INDEX(Работы!$G$2:$G$6000,MATCH($C68,Работы!$A$2:$A$6000,0)),"") -> 0 | G68: =IFERROR(INDEX(Работы!$K$2:$K$6000,MATCH($C68,Работы!$A$2:$A$6000,0)),"") -> S_общая | J68: =IFERROR(INDEX(Материалы!$B$2:$B$9000,MATCH($I68,Материалы!$A$2:$A$9000,0)),"") | K68: =IF($I68="","",IF($F68=IFERROR(INDEX(Материалы!$G$2:$G$9000,MATCH($I68,Материалы!$A$2:$A$9000,0)),""),"OK","!! не та группа")) | L68: =IFERROR(INDEX(Работы!$H$2:$H$6000,MATCH($C68,Работы!$A$2:$A$6000,0))*(1-ДисконтТендер),0) -> 123.58 | M68: =IF($I68="",0,IFERROR(INDEX(Материалы!$I$2:$I$9000,MATCH($I68,Материалы!$A$2:$A$9000,0))*IF(INDEX(Материалы!$J$2:$J$9000,MATCH($I68,Материалы!$A$2:$A$9000,0))="USD",КурсUSD,IF(INDEX(Материалы!$J$2:$J$9000,MATCH($I68,Материалы!$A$2:$A$9000,0))="EUR",КурсEUR,1))*INDEX(Материалы!$K$2:$K$9000,MATCH($I68,Материалы!$A$2:$A$9000,0))*(1+IFERROR(INDEX(Работы!$I$2:$I$6000,MATCH($C68,Работы!$A$2:$A$6000,0))/100,0))*(1-ДисконтТендер),0)) -> 0 | N68: =IF(AND($R68="да",$H68<>""),ROUND($H68*$L68,2),0) -> 0 | O68: =IF(AND($R68="да",$H68<>""),ROUND($H68*$M68,2),0) -> 0 | P68: =$N68+$O68 -> 0 | Q68: =IFERROR(INDEX(Работы!$J$2:$J$6000,MATCH($C68,Работы!$A$2:$A$6000,0)),"") -> типовая | R68: да | T68: =IF(AND($P68>0,$R68="да"),MAX($T$1:$T67)+1,"")
A69: =IFERROR(INDEX(Работы!$D$2:$D$6000,MATCH($C69,Работы!$A$2:$A$6000,0)),"") -> Р1 | B69: =IFERROR(INDEX(Работы!$F$2:$F$6000,MATCH($C69,Работы!$A$2:$A$6000,0)),"") -> 1 | C69: =IFERROR(INDEX(Работы!$A$2:$A$6000,68),"") -> РАБ.Р1.1.068 | D69: =IFERROR(INDEX(Работы!$B$2:$B$6000,MATCH($C69,Работы!$A$2:$A$6000,0)),"") -> Технический отчет электролаборатории для помещений менее 100 м.кв. | E69: =IFERROR(INDEX(Работы!$C$2:$C$6000,MATCH($C69,Работы!$A$2:$A$6000,0)),"") -> компл. | F69: =IFERROR(INDEX(Работы!$G$2:$G$6000,MATCH($C69,Работы!$A$2:$A$6000,0)),"") -> 0 | G69: =IFERROR(INDEX(Работы!$K$2:$K$6000,MATCH($C69,Работы!$A$2:$A$6000,0)),"") -> S_общая | J69: =IFERROR(INDEX(Материалы!$B$2:$B$9000,MATCH($I69,Материалы!$A$2:$A$9000,0)),"") | K69: =IF($I69="","",IF($F69=IFERROR(INDEX(Материалы!$G$2:$G$9000,MATCH($I69,Материалы!$A$2:$A$9000,0)),""),"OK","!! не та группа")) | L69: =IFERROR(INDEX(Работы!$H$2:$H$6000,MATCH($C69,Работы!$A$2:$A$6000,0))*(1-ДисконтТендер),0) -> 13074.35 | M69: =IF($I69="",0,IFERROR(INDEX(Материалы!$I$2:$I$9000,MATCH($I69,Материалы!$A$2:$A$9000,0))*IF(INDEX(Материалы!$J$2:$J$9000,MATCH($I69,Материалы!$A$2:$A$9000,0))="USD",КурсUSD,IF(INDEX(Материалы!$J$2:$J$9000,MATCH($I69,Материалы!$A$2:$A$9000,0))="EUR",КурсEUR,1))*INDEX(Материалы!$K$2:$K$9000,MATCH($I69,Материалы!$A$2:$A$9000,0))*(1+IFERROR(INDEX(Работы!$I$2:$I$6000,MATCH($C69,Работы!$A$2:$A$6000,0))/100,0))*(1-ДисконтТендер),0)) -> 0 | N69: =IF(AND($R69="да",$H69<>""),ROUND($H69*$L69,2),0) -> 0 | O69: =IF(AND($R69="да",$H69<>""),ROUND($H69*$M69,2),0) -> 0 | P69: =$N69+$O69 -> 0 | Q69: =IFERROR(INDEX(Работы!$J$2:$J$6000,MATCH($C69,Работы!$A$2:$A$6000,0)),"") -> типовая | R69: да | T69: =IF(AND($P69>0,$R69="да"),MAX($T$1:$T68)+1,"")
A70: =IFERROR(INDEX(Работы!$D$2:$D$6000,MATCH($C70,Работы!$A$2:$A$6000,0)),"") -> Р1 | B70: =IFERROR(INDEX(Работы!$F$2:$F$6000,MATCH($C70,Работы!$A$2:$A$6000,0)),"") -> 1 | C70: =IFERROR(INDEX(Работы!$A$2:$A$6000,69),"") -> РАБ.Р1.1.069 | D70: =IFERROR(INDEX(Работы!$B$2:$B$6000,MATCH($C70,Работы!$A$2:$A$6000,0)),"") -> Стоимость согласования проекта изменения фасада согласно нормативных и законодательных актов г. ___________ и РФ. | E70: =IFERROR(INDEX(Работы!$C$2:$C$6000,MATCH($C70,Работы!$A$2:$A$6000,0)),"") -> м2 | F70: =IFERROR(INDEX(Работы!$G$2:$G$6000,MATCH($C70,Работы!$A$2:$A$6000,0)),"") -> 0 | G70: =IFERROR(INDEX(Работы!$K$2:$K$6000,MATCH($C70,Работы!$A$2:$A$6000,0)),"") -> S_общая | J70: =IFERROR(INDEX(Материалы!$B$2:$B$9000,MATCH($I70,Материалы!$A$2:$A$9000,0)),"") | K70: =IF($I70="","",IF($F70=IFERROR(INDEX(Материалы!$G$2:$G$9000,MATCH($I70,Материалы!$A$2:$A$9000,0)),""),"OK","!! не та группа")) | L70: =IFERROR(INDEX(Работы!$H$2:$H$6000,MATCH($C70,Работы!$A$2:$A$6000,0))*(1-ДисконтТендер),0) -> 190.9 | M70: =IF($I70="",0,IFERROR(INDEX(Материалы!$I$2:$I$9000,MATCH($I70,Материалы!$A$2:$A$9000,0))*IF(INDEX(Материалы!$J$2:$J$9000,MATCH($I70,Материалы!$A$2:$A$9000,0))="USD",КурсUSD,IF(INDEX(Материалы!$J$2:$J$9000,MATCH($I70,Материалы!$A$2:$A$9000,0))="EUR",КурсEUR,1))*INDEX(Материалы!$K$2:$K$9000,MATCH($I70,Материалы!$A$2:$A$9000,0))*(1+IFERROR(INDEX(Работы!$I$2:$I$6000,MATCH($C70,Работы!$A$2:$A$6000,0))/100,0))*(1-ДисконтТендер),0)) -> 0 | N70: =IF(AND($R70="да",$H70<>""),ROUND($H70*$L70,2),0) -> 0 | O70: =IF(AND($R70="да",$H70<>""),ROUND($H70*$M70,2),0) -> 0 | P70: =$N70+$O70 -> 0 | Q70: =IFERROR(INDEX(Работы!$J$2:$J$6000,MATCH($C70,Работы!$A$2:$A$6000,0)),"") -> нетиповая | R70: да | T70: =IF(AND($P70>0,$R70="да"),MAX($T$1:$T69)+1,"")
A71: =IFERROR(INDEX(Работы!$D$2:$D$6000,MATCH($C71,Работы!$A$2:$A$6000,0)),"") -> Р1 | B71: =IFERROR(INDEX(Работы!$F$2:$F$6000,MATCH($C71,Работы!$A$2:$A$6000,0)),"") -> 1 | C71: =IFERROR(INDEX(Работы!$A$2:$A$6000,70),"") -> РАБ.Р1.1.070 | D71: =IFERROR(INDEX(Работы!$B$2:$B$6000,MATCH($C71,Работы!$A$2:$A$6000,0)),"") -> Разработка дизайн-проекта интерьера | E71: =IFERROR(INDEX(Работы!$C$2:$C$6000,MATCH($C71,Работы!$A$2:$A$6000,0)),"") -> м2 | F71: =IFERROR(INDEX(Работы!$G$2:$G$6000,MATCH($C71,Работы!$A$2:$A$6000,0)),"") -> 0 | G71: =IFERROR(INDEX(Работы!$K$2:$K$6000,MATCH($C71,Работы!$A$2:$A$6000,0)),"") -> S_общая | J71: =IFERROR(INDEX(Материалы!$B$2:$B$9000,MATCH($I71,Материалы!$A$2:$A$9000,0)),"") | K71: =IF($I71="","",IF($F71=IFERROR(INDEX(Материалы!$G$2:$G$9000,MATCH($I71,Материалы!$A$2:$A$9000,0)),""),"OK","!! не та группа")) | L71: =IFERROR(INDEX(Работы!$H$2:$H$6000,MATCH($C71,Работы!$A$2:$A$6000,0))*(1-ДисконтТендер),0) -> 0 | M71: =IF($I71="",0,IFERROR(INDEX(Материалы!$I$2:$I$9000,MATCH($I71,Материалы!$A$2:$A$9000,0))*IF(INDEX(Материалы!$J$2:$J$9000,MATCH($I71,Материалы!$A$2:$A$9000,0))="USD",КурсUSD,IF(INDEX(Материалы!$J$2:$J$9000,MATCH($I71,Материалы!$A$2:$A$9000,0))="EUR",КурсEUR,1))*INDEX(Материалы!$K$2:$K$9000,MATCH($I71,Материалы!$A$2:$A$9000,0))*(1+IFERROR(INDEX(Работы!$I$2:$I$6000,MATCH($C71,Работы!$A$2:$A$6000,0))/100,0))*(1-ДисконтТендер),0)) -> 0 | N71: =IF(AND($R71="да",$H71<>""),ROUND($H71*$L71,2),0) -> 0 | O71: =IF(AND($R71="да",$H71<>""),ROUND($H71*$M71,2),0) -> 0 | P71: =$N71+$O71 -> 0 | Q71: =IFERROR(INDEX(Работы!$J$2:$J$6000,MATCH($C71,Работы!$A$2:$A$6000,0)),"") -> типовая | R71: да | T71: =IF(AND($P71>0,$R71="да"),MAX($T$1:$T70)+1,"")
A72: =IFERROR(INDEX(Работы!$D$2:$D$6000,MATCH($C72,Работы!$A$2:$A$6000,0)),"") -> Р1 | B72: =IFERROR(INDEX(Работы!$F$2:$F$6000,MATCH($C72,Работы!$A$2:$A$6000,0)),"") -> 1 | C72: =IFERROR(INDEX(Работы!$A$2:$A$6000,71),"") -> РАБ.Р1.1.071 | D72: =IFERROR(INDEX(Работы!$B$2:$B$6000,MATCH($C72,Работы!$A$2:$A$6000,0)),"") -> Экспертиза и согласование проекта ЭОМ в Ростехнадзоре | E72: =IFERROR(INDEX(Работы!$C$2:$C$6000,MATCH($C72,Работы!$A$2:$A$6000,0)),"") -> м2 | F72: =IFERROR(INDEX(Работы!$G$2:$G$6000,MATCH($C72,Работы!$A$2:$A$6000,0)),"") -> 0 | G72: =IFERROR(INDEX(Работы!$K$2:$K$6000,MATCH($C72,Работы!$A$2:$A$6000,0)),"") -> S_общая | J72: =IFERROR(INDEX(Материалы!$B$2:$B$9000,MATCH($I72,Материалы!$A$2:$A$9000,0)),"") | K72: =IF($I72="","",IF($F72=IFERROR(INDEX(Материалы!$G$2:$G$9000,MATCH($I72,Материалы!$A$2:$A$9000,0)),""),"OK","!! не та группа")) | L72: =IFERROR(INDEX(Работы!$H$2:$H$6000,MATCH($C72,Работы!$A$2:$A$6000,0))*(1-ДисконтТендер),0) -> 98.96 | M72: =IF($I72="",0,IFERROR(INDEX(Материалы!$I$2:$I$9000,MATCH($I72,Материалы!$A$2:$A$9000,0))*IF(INDEX(Материалы!$J$2:$J$9000,MATCH($I72,Материалы!$A$2:$A$9000,0))="USD",КурсUSD,IF(INDEX(Материалы!$J$2:$J$9000,MATCH($I72,Материалы!$A$2:$A$9000,0))="EUR",КурсEUR,1))*INDEX(Материалы!$K$2:$K$9000,MATCH($I72,Материалы!$A$2:$A$9000,0))*(1+IFERROR(INDEX(Работы!$I$2:$I$6000,MATCH($C72,Работы!$A$2:$A$6000,0))/100,0))*(1-ДисконтТендер),0)) -> 0 | N72: =IF(AND($R72="да",$H72<>""),ROUND($H72*$L72,2),0) -> 0 | O72: =IF(AND($R72="да",$H72<>""),ROUND($H72*$M72,2),0) -> 0 | P72: =$N72+$O72 -> 0 | Q72: =IFERROR(INDEX(Работы!$J$2:$J$6000,MATCH($C72,Работы!$A$2:$A$6000,0)),"") -> типовая | R72: да | T72: =IF(AND($P72>0,$R72="да"),MAX($T$1:$T71)+1,"")
A73: =IFERROR(INDEX(Работы!$D$2:$D$6000,MATCH($C73,Работы!$A$2:$A$6000,0)),"") -> Р1 | B73: =IFERROR(INDEX(Работы!$F$2:$F$6000,MATCH($C73,Работы!$A$2:$A$6000,0)),"") -> 1 | C73: =IFERROR(INDEX(Работы!$A$2:$A$6000,72),"") -> РАБ.Р1.1.072 | D73: =IFERROR(INDEX(Работы!$B$2:$B$6000,MATCH($C73,Работы!$A$2:$A$6000,0)),"") -> Проект системы водоотведения | E73: =IFERROR(INDEX(Работы!$C$2:$C$6000,MATCH($C73,Работы!$A$2:$A$6000,0)),"") -> м2 | F73: =IFERROR(INDEX(Работы!$G$2:$G$6000,MATCH($C73,Работы!$A$2:$A$6000,0)),"") -> 0 | G73: =IFERROR(INDEX(Работы!$K$2:$K$6000,MATCH($C73,Работы!$A$2:$A$6000,0)),"") -> S_общая | J73: =IFERROR(INDEX(Материалы!$B$2:$B$9000,MATCH($I73,Материалы!$A$2:$A$9000,0)),"") | K73: =IF($I73="","",IF($F73=IFERROR(INDEX(Материалы!$G$2:$G$9000,MATCH($I73,Материалы!$A$2:$A$9000,0)),""),"OK","!! не та группа")) | L73: =IFERROR(INDEX(Работы!$H$2:$H$6000,MATCH($C73,Работы!$A$2:$A$6000,0))*(1-ДисконтТендер),0) -> 0 | M73: =IF($I73="",0,IFERROR(INDEX(Материалы!$I$2:$I$9000,MATCH($I73,Материалы!$A$2:$A$9000,0))*IF(INDEX(Материалы!$J$2:$J$9000,MATCH($I73,Материалы!$A$2:$A$9000,0))="USD",КурсUSD,IF(INDEX(Материалы!$J$2:$J$9000,MATCH($I73,Материалы!$A$2:$A$9000,0))="EUR",КурсEUR,1))*INDEX(Материалы!$K$2:$K$9000,MATCH($I73,Материалы!$A$2:$A$9000,0))*(1+IFERROR(INDEX(Работы!$I$2:$I$6000,MATCH($C73,Работы!$A$2:$A$6000,0))/100,0))*(1-ДисконтТендер),0)) -> 0 | N73: =IF(AND($R73="да",$H73<>""),ROUND($H73*$L73,2),0) -> 0 | O73: =IF(AND($R73="да",$H73<>""),ROUND($H73*$M73,2),0) -> 0 | P73: =$N73+$O73 -> 0 | Q73: =IFERROR(INDEX(Работы!$J$2:$J$6000,MATCH($C73,Работы!$A$2:$A$6000,0)),"") -> типовая | R73: да | T73: =IF(AND($P73>0,$R73="да"),MAX($T$1:$T72)+1,"")
A74: =IFERROR(INDEX(Работы!$D$2:$D$6000,MATCH($C74,Работы!$A$2:$A$6000,0)),"") -> Р1 | B74: =IFERROR(INDEX(Работы!$F$2:$F$6000,MATCH($C74,Работы!$A$2:$A$6000,0)),"") -> 1 | C74: =IFERROR(INDEX(Работы!$A$2:$A$6000,73),"") -> РАБ.Р1.1.073 | D74: =IFERROR(INDEX(Работы!$B$2:$B$6000,MATCH($C74,Работы!$A$2:$A$6000,0)),"") -> Рабочая документация Системы ливневой канализации | E74: =IFERROR(INDEX(Работы!$C$2:$C$6000,MATCH($C74,Работы!$A$2:$A$6000,0)),"") -> м2 | F74: =IFERROR(INDEX(Работы!$G$2:$G$6000,MATCH($C74,Работы!$A$2:$A$6000,0)),"") -> 0 | G74: =IFERROR(INDEX(Работы!$K$2:$K$6000,MATCH($C74,Работы!$A$2:$A$6000,0)),"") -> S_общая | J74: =IFERROR(INDEX(Материалы!$B$2:$B$9000,MATCH($I74,Материалы!$A$2:$A$9000,0)),"") | K74: =IF($I74="","",IF($F74=IFERROR(INDEX(Материалы!$G$2:$G$9000,MATCH($I74,Материалы!$A$2:$A$9000,0)),""),"OK","!! не та группа")) | L74: =IFERROR(INDEX(Работы!$H$2:$H$6000,MATCH($C74,Работы!$A$2:$A$6000,0))*(1-ДисконтТендер),0) -> 0 | M74: =IF($I74="",0,IFERROR(INDEX(Материалы!$I$2:$I$9000,MATCH($I74,Материалы!$A$2:$A$9000,0))*IF(INDEX(Материалы!$J$2:$J$9000,MATCH($I74,Материалы!$A$2:$A$9000,0))="USD",КурсUSD,IF(INDEX(Материалы!$J$2:$J$9000,MATCH($I74,Материалы!$A$2:$A$9000,0))="EUR",КурсEUR,1))*INDEX(Материалы!$K$2:$K$9000,MATCH($I74,Материалы!$A$2:$A$9000,0))*(1+IFERROR(INDEX(Работы!$I$2:$I$6000,MATCH($C74,Работы!$A$2:$A$6000,0))/100,0))*(1-ДисконтТендер),0)) -> 0 | N74: =IF(AND($R74="да",$H74<>""),ROUND($H74*$L74,2),0) -> 0 | O74: =IF(AND($R74="да",$H74<>""),ROUND($H74*$M74,2),0) -> 0 | P74: =$N74+$O74 -> 0 | Q74: =IFERROR(INDEX(Работы!$J$2:$J$6000,MATCH($C74,Работы!$A$2:$A$6000,0)),"") -> типовая | R74: да | T74: =IF(AND($P74>0,$R74="да"),MAX($T$1:$T73)+1,"")
A75: =IFERROR(INDEX(Работы!$D$2:$D$6000,MATCH($C75,Работы!$A$2:$A$6000,0)),"") -> Р1 | B75: =IFERROR(INDEX(Работы!$F$2:$F$6000,MATCH($C75,Работы!$A$2:$A$6000,0)),"") -> 1 | C75: =IFERROR(INDEX(Работы!$A$2:$A$6000,74),"") -> РАБ.Р1.1.074 | D75: =IFERROR(INDEX(Работы!$B$2:$B$6000,MATCH($C75,Работы!$A$2:$A$6000,0)),"") -> Получение Технических условий (при необходимости) | E75: =IFERROR(INDEX(Работы!$C$2:$C$6000,MATCH($C75,Работы!$A$2:$A$6000,0)),"") -> м2 | F75: =IFERROR(INDEX(Работы!$G$2:$G$6000,MATCH($C75,Работы!$A$2:$A$6000,0)),"") -> 0 | G75: =IFERROR(INDEX(Работы!$K$2:$K$6000,MATCH($C75,Работы!$A$2:$A$6000,0)),"") -> S_общая | J75: =IFERROR(INDEX(Материалы!$B$2:$B$9000,MATCH($I75,Материалы!$A$2:$A$9000,0)),"") | K75: =IF($I75="","",IF($F75=IFERROR(INDEX(Материалы!$G$2:$G$9000,MATCH($I75,Материалы!$A$2:$A$9000,0)),""),"OK","!! не та группа")) | L75: =IFERROR(INDEX(Работы!$H$2:$H$6000,MATCH($C75,Работы!$A$2:$A$6000,0))*(1-ДисконтТендер),0) -> 0 | M75: =IF($I75="",0,IFERROR(INDEX(Материалы!$I$2:$I$9000,MATCH($I75,Материалы!$A$2:$A$9000,0))*IF(INDEX(Материалы!$J$2:$J$9000,MATCH($I75,Материалы!$A$2:$A$9000,0))="USD",КурсUSD,IF(INDEX(Материалы!$J$2:$J$9000,MATCH($I75,Материалы!$A$2:$A$9000,0))="EUR",КурсEUR,1))*INDEX(Материалы!$K$2:$K$9000,MATCH($I75,Материалы!$A$2:$A$9000,0))*(1+IFERROR(INDEX(Работы!$I$2:$I$6000,MATCH($C75,Работы!$A$2:$A$6000,0))/100,0))*(1-ДисконтТендер),0)) -> 0 | N75: =IF(AND($R75="да",$H75<>""),ROUND($H75*$L75,2),0) -> 0 | O75: =IF(AND($R75="да",$H75<>""),ROUND($H75*$M75,2),0) -> 0 | P75: =$N75+$O75 -> 0 | Q75: =IFERROR(INDEX(Работы!$J$2:$J$6000,MATCH($C75,Работы!$A$2:$A$6000,0)),"") -> типовая | R75: да | T75: =IF(AND($P75>0,$R75="да"),MAX($T$1:$T74)+1,"")
A76: =IFERROR(INDEX(Работы!$D$2:$D$6000,MATCH($C76,Работы!$A$2:$A$6000,0)),"") -> Р1 | B76: =IFERROR(INDEX(Работы!$F$2:$F$6000,MATCH($C76,Работы!$A$2:$A$6000,0)),"") -> 1 | C76: =IFERROR(INDEX(Работы!$A$2:$A$6000,75),"") -> РАБ.Р1.1.075 | D76: =IFERROR(INDEX(Работы!$B$2:$B$6000,MATCH($C76,Работы!$A$2:$A$6000,0)),"") -> Расчет категории пожарной опасности помещений | E76: =IFERROR(INDEX(Работы!$C$2:$C$6000,MATCH($C76,Работы!$A$2:$A$6000,0)),"") -> м2 | F76: =IFERROR(INDEX(Работы!$G$2:$G$6000,MATCH($C76,Работы!$A$2:$A$6000,0)),"") -> 0 | G76: =IFERROR(INDEX(Работы!$K$2:$K$6000,MATCH($C76,Работы!$A$2:$A$6000,0)),"") -> S_общая | J76: =IFERROR(INDEX(Материалы!$B$2:$B$9000,MATCH($I76,Материалы!$A$2:$A$9000,0)),"") | K76: =IF($I76="","",IF($F76=IFERROR(INDEX(Материалы!$G$2:$G$9000,MATCH($I76,Материалы!$A$2:$A$9000,0)),""),"OK","!! не та группа")) | L76: =IFERROR(INDEX(Работы!$H$2:$H$6000,MATCH($C76,Работы!$A$2:$A$6000,0))*(1-ДисконтТендер),0) -> 114.84 | M76: =IF($I76="",0,IFERROR(INDEX(Материалы!$I$2:$I$9000,MATCH($I76,Материалы!$A$2:$A$9000,0))*IF(INDEX(Материалы!$J$2:$J$9000,MATCH($I76,Материалы!$A$2:$A$9000,0))="USD",КурсUSD,IF(INDEX(Материалы!$J$2:$J$9000,MATCH($I76,Материалы!$A$2:$A$9000,0))="EUR",КурсEUR,1))*INDEX(Материалы!$K$2:$K$9000,MATCH($I76,Материалы!$A$2:$A$9000,0))*(1+IFERROR(INDEX(Работы!$I$2:$I$6000,MATCH($C76,Работы!$A$2:$A$6000,0))/100,0))*(1-ДисконтТендер),0)) -> 0 | N76: =IF(AND($R76="да",$H76<>""),ROUND($H76*$L76,2),0) -> 0 | O76: =IF(AND($R76="да",$H76<>""),ROUND($H76*$M76,2),0) -> 0 | P76: =$N76+$O76 -> 0 | Q76: =IFERROR(INDEX(Работы!$J$2:$J$6000,MATCH($C76,Работы!$A$2:$A$6000,0)),"") -> типовая | R76: да | T76: =IF(AND($P76>0,$R76="да"),MAX($T$1:$T75)+1,"")
A77: =IFERROR(INDEX(Работы!$D$2:$D$6000,MATCH($C77,Работы!$A$2:$A$6000,0)),"") -> Р1 | B77: =IFERROR(INDEX(Работы!$F$2:$F$6000,MATCH($C77,Работы!$A$2:$A$6000,0)),"") -> 1 | C77: =IFERROR(INDEX(Работы!$A$2:$A$6000,76),"") -> РАБ.Р1.1.076 | D77: =IFERROR(INDEX(Работы!$B$2:$B$6000,MATCH($C77,Работы!$A$2:$A$6000,0)),"") -> Рабочая документация Системы оповещения и управления эвакуацией в части световых указателей ("СОУЭ") | E77: =IFERROR(INDEX(Работы!$C$2:$C$6000,MATCH($C77,Работы!$A$2:$A$6000,0)),"") -> м2 | F77: =IFERROR(INDEX(Работы!$G$2:$G$6000,MATCH($C77,Работы!$A$2:$A$6000,0)),"") -> 0 | G77: =IFERROR(INDEX(Работы!$K$2:$K$6000,MATCH($C77,Работы!$A$2:$A$6000,0)),"") -> S_общая | J77: =IFERROR(INDEX(Материалы!$B$2:$B$9000,MATCH($I77,Материалы!$A$2:$A$9000,0)),"") | K77: =IF($I77="","",IF($F77=IFERROR(INDEX(Материалы!$G$2:$G$9000,MATCH($I77,Материалы!$A$2:$A$9000,0)),""),"OK","!! не та группа")) | L77: =IFERROR(INDEX(Работы!$H$2:$H$6000,MATCH($C77,Работы!$A$2:$A$6000,0))*(1-ДисконтТендер),0) -> 52.25 | M77: =IF($I77="",0,IFERROR(INDEX(Материалы!$I$2:$I$9000,MATCH($I77,Материалы!$A$2:$A$9000,0))*IF(INDEX(Материалы!$J$2:$J$9000,MATCH($I77,Материалы!$A$2:$A$9000,0))="USD",КурсUSD,IF(INDEX(Материалы!$J$2:$J$9000,MATCH($I77,Материалы!$A$2:$A$9000,0))="EUR",КурсEUR,1))*INDEX(Материалы!$K$2:$K$9000,MATCH($I77,Материалы!$A$2:$A$9000,0))*(1+IFERROR(INDEX(Работы!$I$2:$I$6000,MATCH($C77,Работы!$A$2:$A$6000,0))/100,0))*(1-ДисконтТендер),0)) -> 0 | N77: =IF(AND($R77="да",$H77<>""),ROUND($H77*$L77,2),0) -> 0 | O77: =IF(AND($R77="да",$H77<>""),ROUND($H77*$M77,2),0) -> 0 | P77: =$N77+$O77 -> 0 | Q77: =IFERROR(INDEX(Работы!$J$2:$J$6000,MATCH($C77,Работы!$A$2:$A$6000,0)),"") -> типовая | R77: да | T77: =IF(AND($P77>0,$R77="да"),MAX($T$1:$T76)+1,"")
A78: =IFERROR(INDEX(Работы!$D$2:$D$6000,MATCH($C78,Работы!$A$2:$A$6000,0)),"") -> Р1 | B78: =IFERROR(INDEX(Работы!$F$2:$F$6000,MATCH($C78,Работы!$A$2:$A$6000,0)),"") -> 1 | C78: =IFERROR(INDEX(Работы!$A$2:$A$6000,77),"") -> РАБ.Р1.1.077 | D78: =IFERROR(INDEX(Работы!$B$2:$B$6000,MATCH($C78,Работы!$A$2:$A$6000,0)),"") -> Согласование проекта Системы водоотведения и получения тех условий (при необходимости) | E78: =IFERROR(INDEX(Работы!$C$2:$C$6000,MATCH($C78,Работы!$A$2:$A$6000,0)),"") -> м2 | F78: =IFERROR(INDEX(Работы!$G$2:$G$6000,MATCH($C78,Работы!$A$2:$A$6000,0)),"") -> 0 | G78: =IFERROR(INDEX(Работы!$K$2:$K$6000,MATCH($C78,Работы!$A$2:$A$6000,0)),"") -> S_общая | J78: =IFERROR(INDEX(Материалы!$B$2:$B$9000,MATCH($I78,Материалы!$A$2:$A$9000,0)),"") | K78: =IF($I78="","",IF($F78=IFERROR(INDEX(Материалы!$G$2:$G$9000,MATCH($I78,Материалы!$A$2:$A$9000,0)),""),"OK","!! не та группа")) | L78: =IFERROR(INDEX(Работы!$H$2:$H$6000,MATCH($C78,Работы!$A$2:$A$6000,0))*(1-ДисконтТендер),0) -> 0 | M78: =IF($I78="",0,IFERROR(INDEX(Материалы!$I$2:$I$9000,MATCH($I78,Материалы!$A$2:$A$9000,0))*IF(INDEX(Материалы!$J$2:$J$9000,MATCH($I78,Материалы!$A$2:$A$9000,0))="USD",КурсUSD,IF(INDEX(Материалы!$J$2:$J$9000,MATCH($I78,Материалы!$A$2:$A$9000,0))="EUR",КурсEUR,1))*INDEX(Материалы!$K$2:$K$9000,MATCH($I78,Материалы!$A$2:$A$9000,0))*(1+IFERROR(INDEX(Работы!$I$2:$I$6000,MATCH($C78,Работы!$A$2:$A$6000,0))/100,0))*(1-ДисконтТендер),0)) -> 0 | N78: =IF(AND($R78="да",$H78<>""),ROUND($H78*$L78,2),0) -> 0 | O78: =IF(AND($R78="да",$H78<>""),ROUND($H78*$M78,2),0) -> 0 | P78: =$N78+$O78 -> 0 | Q78: =IFERROR(INDEX(Работы!$J$2:$J$6000,MATCH($C78,Работы!$A$2:$A$6000,0)),"") -> типовая | R78: да | T78: =IF(AND($P78>0,$R78="да"),MAX($T$1:$T77)+1,"")
A79: =IFERROR(INDEX(Работы!$D$2:$D$6000,MATCH($C79,Работы!$A$2:$A$6000,0)),"") -> Р1 | B79: =IFERROR(INDEX(Работы!$F$2:$F$6000,MATCH($C79,Работы!$A$2:$A$6000,0)),"") -> 1 | C79: =IFERROR(INDEX(Работы!$A$2:$A$6000,78),"") -> РАБ.Р1.1.078 | D79: =IFERROR(INDEX(Работы!$B$2:$B$6000,MATCH($C79,Работы!$A$2:$A$6000,0)),"") -> Испытание лестниц 3 типа с предоставлением актов | E79: =IFERROR(INDEX(Работы!$C$2:$C$6000,MATCH($C79,Работы!$A$2:$A$6000,0)),"") -> м2 | F79: =IFERROR(INDEX(Работы!$G$2:$G$6000,MATCH($C79,Работы!$A$2:$A$6000,0)),"") -> 0 | G79: =IFERROR(INDEX(Работы!$K$2:$K$6000,MATCH($C79,Работы!$A$2:$A$6000,0)),"") -> S_общая | J79: =IFERROR(INDEX(Материалы!$B$2:$B$9000,MATCH($I79,Материалы!$A$2:$A$9000,0)),"") | K79: =IF($I79="","",IF($F79=IFERROR(INDEX(Материалы!$G$2:$G$9000,MATCH($I79,Материалы!$A$2:$A$9000,0)),""),"OK","!! не та группа")) | L79: =IFERROR(INDEX(Работы!$H$2:$H$6000,MATCH($C79,Работы!$A$2:$A$6000,0))*(1-ДисконтТендер),0) -> 30.63 | M79: =IF($I79="",0,IFERROR(INDEX(Материалы!$I$2:$I$9000,MATCH($I79,Материалы!$A$2:$A$9000,0))*IF(INDEX(Материалы!$J$2:$J$9000,MATCH($I79,Материалы!$A$2:$A$9000,0))="USD",КурсUSD,IF(INDEX(Материалы!$J$2:$J$9000,MATCH($I79,Материалы!$A$2:$A$9000,0))="EUR",КурсEUR,1))*INDEX(Материалы!$K$2:$K$9000,MATCH($I79,Материалы!$A$2:$A$9000,0))*(1+IFERROR(INDEX(Работы!$I$2:$I$6000,MATCH($C79,Работы!$A$2:$A$6000,0))/100,0))*(1-ДисконтТендер),0)) -> 0 | N79: =IF(AND($R79="да",$H79<>""),ROUND($H79*$L79,2),0) -> 0 | O79: =IF(AND($R79="да",$H79<>""),ROUND($H79*$M79,2),0) -> 0 | P79: =$N79+$O79 -> 0 | Q79: =IFERROR(INDEX(Работы!$J$2:$J$6000,MATCH($C79,Работы!$A$2:$A$6000,0)),"") -> типовая | R79: да | T79: =IF(AND($P79>0,$R79="да"),MAX($T$1:$T78)+1,"")
A80: =IFERROR(INDEX(Работы!$D$2:$D$6000,MATCH($C80,Работы!$A$2:$A$6000,0)),"") -> Р1 | B80: =IFERROR(INDEX(Работы!$F$2:$F$6000,MATCH($C80,Работы!$A$2:$A$6000,0)),"") -> 1 | C80: =IFERROR(INDEX(Работы!$A$2:$A$6000,79),"") -> РАБ.Р1.1.079 | D80: =IFERROR(INDEX(Работы!$B$2:$B$6000,MATCH($C80,Работы!$A$2:$A$6000,0)),"") -> Испытания системы внутреннего противопожарного водопровода аккредитованной организацией (ВПВ и АУПТ). | E80: =IFERROR(INDEX(Работы!$C$2:$C$6000,MATCH($C80,Работы!$A$2:$A$6000,0)),"") -> компл. | F80: =IFERROR(INDEX(Работы!$G$2:$G$6000,MATCH($C80,Работы!$A$2:$A$6000,0)),"") -> 0 | G80: =IFERROR(INDEX(Работы!$K$2:$K$6000,MATCH($C80,Работы!$A$2:$A$6000,0)),"") -> S_общая | J80: =IFERROR(INDEX(Материалы!$B$2:$B$9000,MATCH($I80,Материалы!$A$2:$A$9000,0)),"") | K80: =IF($I80="","",IF($F80=IFERROR(INDEX(Материалы!$G$2:$G$9000,MATCH($I80,Материалы!$A$2:$A$9000,0)),""),"OK","!! не та группа")) | L80: =IFERROR(INDEX(Работы!$H$2:$H$6000,MATCH($C80,Работы!$A$2:$A$6000,0))*(1-ДисконтТендер),0) -> 10207.56 | M80: =IF($I80="",0,IFERROR(INDEX(Материалы!$I$2:$I$9000,MATCH($I80,Материалы!$A$2:$A$9000,0))*IF(INDEX(Материалы!$J$2:$J$9000,MATCH($I80,Материалы!$A$2:$A$9000,0))="USD",КурсUSD,IF(INDEX(Материалы!$J$2:$J$9000,MATCH($I80,Материалы!$A$2:$A$9000,0))="EUR",КурсEUR,1))*INDEX(Материалы!$K$2:$K$9000,MATCH($I80,Материалы!$A$2:$A$9000,0))*(1+IFERROR(INDEX(Работы!$I$2:$I$6000,MATCH($C80,Работы!$A$2:$A$6000,0))/100,0))*(1-ДисконтТендер),0)) -> 0 | N80: =IF(AND($R80="да",$H80<>""),ROUND($H80*$L80,2),0) -> 0 | O80: =IF(AND($R80="да",$H80<>""),ROUND($H80*$M80,2),0) -> 0 | P80: =$N80+$O80 -> 0 | Q80: =IFERROR(INDEX(Работы!$J$2:$J$6000,MATCH($C80,Работы!$A$2:$A$6000,0)),"") -> типовая | R80: да | T80: =IF(AND($P80>0,$R80="да"),MAX($T$1:$T79)+1,"")
A81: =IFERROR(INDEX(Работы!$D$2:$D$6000,MATCH($C81,Работы!$A$2:$A$6000,0)),"") -> Р1 | B81: =IFERROR(INDEX(Работы!$F$2:$F$6000,MATCH($C81,Работы!$A$2:$A$6000,0)),"") -> 1 | C81: =IFERROR(INDEX(Работы!$A$2:$A$6000,80),"") -> РАБ.Р1.1.080 | D81: =IFERROR(INDEX(Работы!$B$2:$B$6000,MATCH($C81,Работы!$A$2:$A$6000,0)),"") -> Мероприятия по обеспечению доступа инвалидов | E81: =IFERROR(INDEX(Работы!$C$2:$C$6000,MATCH($C81,Работы!$A$2:$A$6000,0)),"") -> м2 | F81: =IFERROR(INDEX(Работы!$G$2:$G$6000,MATCH($C81,Работы!$A$2:$A$6000,0)),"") -> 0 | G81: =IFERROR(INDEX(Работы!$K$2:$K$6000,MATCH($C81,Работы!$A$2:$A$6000,0)),"") -> S_общая | J81: =IFERROR(INDEX(Материалы!$B$2:$B$9000,MATCH($I81,Материалы!$A$2:$A$9000,0)),"") | K81: =IF($I81="","",IF($F81=IFERROR(INDEX(Материалы!$G$2:$G$9000,MATCH($I81,Материалы!$A$2:$A$9000,0)),""),"OK","!! не та группа")) | L81: =IFERROR(INDEX(Работы!$H$2:$H$6000,MATCH($C81,Работы!$A$2:$A$6000,0))*(1-ДисконтТендер),0) -> 76.52 | M81: =IF($I81="",0,IFERROR(INDEX(Материалы!$I$2:$I$9000,MATCH($I81,Материалы!$A$2:$A$9000,0))*IF(INDEX(Материалы!$J$2:$J$9000,MATCH($I81,Материалы!$A$2:$A$9000,0))="USD",КурсUSD,IF(INDEX(Материалы!$J$2:$J$9000,MATCH($I81,Материалы!$A$2:$A$9000,0))="EUR",КурсEUR,1))*INDEX(Материалы!$K$2:$K$9000,MATCH($I81,Материалы!$A$2:$A$9000,0))*(1+IFERROR(INDEX(Работы!$I$2:$I$6000,MATCH($C81,Работы!$A$2:$A$6000,0))/100,0))*(1-ДисконтТендер),0)) -> 0 | N81: =IF(AND($R81="да",$H81<>""),ROUND($H81*$L81,2),0) -> 0 | O81: =IF(AND($R81="да",$H81<>""),ROUND($H81*$M81,2),0) -> 0 | P81: =$N81+$O81 -> 0 | Q81: =IFERROR(INDEX(Работы!$J$2:$J$6000,MATCH($C81,Работы!$A$2:$A$6000,0)),"") -> типовая | R81: да | T81: =IF(AND($P81>0,$R81="да"),MAX($T$1:$T80)+1,"")
A82: =IFERROR(INDEX(Работы!$D$2:$D$6000,MATCH($C82,Работы!$A$2:$A$6000,0)),"") -> Р1 | B82: =IFERROR(INDEX(Работы!$F$2:$F$6000,MATCH($C82,Работы!$A$2:$A$6000,0)),"") -> 1 | C82: =IFERROR(INDEX(Работы!$A$2:$A$6000,81),"") -> РАБ.Р1.1.081 | D82: =IFERROR(INDEX(Работы!$B$2:$B$6000,MATCH($C82,Работы!$A$2:$A$6000,0)),"") -> Расчет пожарного риска | E82: =IFERROR(INDEX(Работы!$C$2:$C$6000,MATCH($C82,Работы!$A$2:$A$6000,0)),"") -> м2 | F82: =IFERROR(INDEX(Работы!$G$2:$G$6000,MATCH($C82,Работы!$A$2:$A$6000,0)),"") -> 0 | G82: =IFERROR(INDEX(Работы!$K$2:$K$6000,MATCH($C82,Работы!$A$2:$A$6000,0)),"") -> S_общая | J82: =IFERROR(INDEX(Материалы!$B$2:$B$9000,MATCH($I82,Материалы!$A$2:$A$9000,0)),"") | K82: =IF($I82="","",IF($F82=IFERROR(INDEX(Материалы!$G$2:$G$9000,MATCH($I82,Материалы!$A$2:$A$9000,0)),""),"OK","!! не та группа")) | L82: =IFERROR(INDEX(Работы!$H$2:$H$6000,MATCH($C82,Работы!$A$2:$A$6000,0))*(1-ДисконтТендер),0) -> 0 | M82: =IF($I82="",0,IFERROR(INDEX(Материалы!$I$2:$I$9000,MATCH($I82,Материалы!$A$2:$A$9000,0))*IF(INDEX(Материалы!$J$2:$J$9000,MATCH($I82,Материалы!$A$2:$A$9000,0))="USD",КурсUSD,IF(INDEX(Материалы!$J$2:$J$9000,MATCH($I82,Материалы!$A$2:$A$9000,0))="EUR",КурсEUR,1))*INDEX(Материалы!$K$2:$K$9000,MATCH($I82,Материалы!$A$2:$A$9000,0))*(1+IFERROR(INDEX(Работы!$I$2:$I$6000,MATCH($C82,Работы!$A$2:$A$6000,0))/100,0))*(1-ДисконтТендер),0)) -> 0 | N82: =IF(AND($R82="да",$H82<>""),ROUND($H82*$L82,2),0) -> 0 | O82: =IF(AND($R82="да",$H82<>""),ROUND($H82*$M82,2),0) -> 0 | P82: =$N82+$O82 -> 0 | Q82: =IFERROR(INDEX(Работы!$J$2:$J$6000,MATCH($C82,Работы!$A$2:$A$6000,0)),"") -> типовая | R82: да | T82: =IF(AND($P82>0,$R82="да"),MAX($T$1:$T81)+1,"")
A83: =IFERROR(INDEX(Работы!$D$2:$D$6000,MATCH($C83,Работы!$A$2:$A$6000,0)),"") -> Р1 | B83: =IFERROR(INDEX(Работы!$F$2:$F$6000,MATCH($C83,Работы!$A$2:$A$6000,0)),"") -> 1 | C83: =IFERROR(INDEX(Работы!$A$2:$A$6000,82),"") -> РАБ.Р1.1.082 | D83: =IFERROR(INDEX(Работы!$B$2:$B$6000,MATCH($C83,Работы!$A$2:$A$6000,0)),"") -> Подготовка и постановка на учет Независимой оценки пожарного риска (пожарный аудит), включая Расчет пожарного риска | E83: =IFERROR(INDEX(Работы!$C$2:$C$6000,MATCH($C83,Работы!$A$2:$A$6000,0)),"") -> м2 | F83: =IFERROR(INDEX(Работы!$G$2:$G$6000,MATCH($C83,Работы!$A$2:$A$6000,0)),"") -> 0 | G83: =IFERROR(INDEX(Работы!$K$2:$K$6000,MATCH($C83,Работы!$A$2:$A$6000,0)),"") -> S_общая | J83: =IFERROR(INDEX(Материалы!$B$2:$B$9000,MATCH($I83,Материалы!$A$2:$A$9000,0)),"") | K83: =IF($I83="","",IF($F83=IFERROR(INDEX(Материалы!$G$2:$G$9000,MATCH($I83,Материалы!$A$2:$A$9000,0)),""),"OK","!! не та группа")) | L83: =IFERROR(INDEX(Работы!$H$2:$H$6000,MATCH($C83,Работы!$A$2:$A$6000,0))*(1-ДисконтТендер),0) -> 0 | M83: =IF($I83="",0,IFERROR(INDEX(Материалы!$I$2:$I$9000,MATCH($I83,Материалы!$A$2:$A$9000,0))*IF(INDEX(Материалы!$J$2:$J$9000,MATCH($I83,Материалы!$A$2:$A$9000,0))="USD",КурсUSD,IF(INDEX(Материалы!$J$2:$J$9000,MATCH($I83,Материалы!$A$2:$A$9000,0))="EUR",КурсEUR,1))*INDEX(Материалы!$K$2:$K$9000,MATCH($I83,Материалы!$A$2:$A$9000,0))*(1+IFERROR(INDEX(Работы!$I$2:$I$6000,MATCH($C83,Работы!$A$2:$A$6000,0))/100,0))*(1-ДисконтТендер),0)) -> 0 | N83: =IF(AND($R83="да",$H83<>""),ROUND($H83*$L83,2),0) -> 0 | O83: =IF(AND($R83="да",$H83<>""),ROUND($H83*$M83,2),0) -> 0 | P83: =$N83+$O83 -> 0 | Q83: =IFERROR(INDEX(Работы!$J$2:$J$6000,MATCH($C83,Работы!$A$2:$A$6000,0)),"") -> типовая | R83: да | T83: =IF(AND($P83>0,$R83="да"),MAX($T$1:$T82)+1,"")
A84: =IFERROR(INDEX(Работы!$D$2:$D$6000,MATCH($C84,Работы!$A$2:$A$6000,0)),"") -> Р1 | B84: =IFERROR(INDEX(Работы!$F$2:$F$6000,MATCH($C84,Работы!$A$2:$A$6000,0)),"") -> 1 | C84: =IFERROR(INDEX(Работы!$A$2:$A$6000,83),"") -> РАБ.Р1.1.083 | D84: =IFERROR(INDEX(Работы!$B$2:$B$6000,MATCH($C84,Работы!$A$2:$A$6000,0)),"") -> Разработка проекта огнезащиты | E84: =IFERROR(INDEX(Работы!$C$2:$C$6000,MATCH($C84,Работы!$A$2:$A$6000,0)),"") -> шт. | F84: =IFERROR(INDEX(Работы!$G$2:$G$6000,MATCH($C84,Работы!$A$2:$A$6000,0)),"") -> 0 | G84: =IFERROR(INDEX(Работы!$K$2:$K$6000,MATCH($C84,Работы!$A$2:$A$6000,0)),"") -> S_поверхность | J84: =IFERROR(INDEX(Материалы!$B$2:$B$9000,MATCH($I84,Материалы!$A$2:$A$9000,0)),"") | K84: =IF($I84="","",IF($F84=IFERROR(INDEX(Материалы!$G$2:$G$9000,MATCH($I84,Материалы!$A$2:$A$9000,0)),""),"OK","!! не та группа")) | L84: =IFERROR(INDEX(Работы!$H$2:$H$6000,MATCH($C84,Работы!$A$2:$A$6000,0))*(1-ДисконтТендер),0) -> 16168.42 | M84: =IF($I84="",0,IFERROR(INDEX(Материалы!$I$2:$I$9000,MATCH($I84,Материалы!$A$2:$A$9000,0))*IF(INDEX(Материалы!$J$2:$J$9000,MATCH($I84,Материалы!$A$2:$A$9000,0))="USD",КурсUSD,IF(INDEX(Материалы!$J$2:$J$9000,MATCH($I84,Материалы!$A$2:$A$9000,0))="EUR",КурсEUR,1))*INDEX(Материалы!$K$2:$K$9000,MATCH($I84,Материалы!$A$2:$A$9000,0))*(1+IFERROR(INDEX(Работы!$I$2:$I$6000,MATCH($C84,Работы!$A$2:$A$6000,0))/100,0))*(1-ДисконтТендер),0)) -> 0 | N84: =IF(AND($R84="да",$H84<>""),ROUND($H84*$L84,2),0) -> 0 | O84: =IF(AND($R84="да",$H84<>""),ROUND($H84*$M84,2),0) -> 0 | P84: =$N84+$O84 -> 0 | Q84: =IFERROR(INDEX(Работы!$J$2:$J$6000,MATCH($C84,Работы!$A$2:$A$6000,0)),"") -> типовая | R84: да | T84: =IF(AND($P84>0,$R84="да"),MAX($T$1:$T83)+1,"")
A85: =IFERROR(INDEX(Работы!$D$2:$D$6000,MATCH($C85,Работы!$A$2:$A$6000,0)),"") -> Р1 | B85: =IFERROR(INDEX(Работы!$F$2:$F$6000,MATCH($C85,Работы!$A$2:$A$6000,0)),"") -> 1 | C85: =IFERROR(INDEX(Работы!$A$2:$A$6000,84),"") -> РАБ.Р1.1.084 | D85: =IFERROR(INDEX(Работы!$B$2:$B$6000,MATCH($C85,Работы!$A$2:$A$6000,0)),"") -> Предоставление заключения пожарной испытательной лаборатории для контроля качества огнезащитных работ с предоставлением заключения о соответствии (до 1000 м кв. металлоконструкций) | E85: =IFERROR(INDEX(Работы!$C$2:$C$6000,MATCH($C85,Работы!$A$2:$A$6000,0)),"") -> компл. | F85: =IFERROR(INDEX(Работы!$G$2:$G$6000,MATCH($C85,Работы!$A$2:$A$6000,0)),"") -> 0 | G85: =IFERROR(INDEX(Работы!$K$2:$K$6000,MATCH($C85,Работы!$A$2:$A$6000,0)),"") -> S_поверхность | J85: =IFERROR(INDEX(Материалы!$B$2:$B$9000,MATCH($I85,Материалы!$A$2:$A$9000,0)),"") | K85: =IF($I85="","",IF($F85=IFERROR(INDEX(Материалы!$G$2:$G$9000,MATCH($I85,Материалы!$A$2:$A$9000,0)),""),"OK","!! не та группа")) | L85: =IFERROR(INDEX(Работы!$H$2:$H$6000,MATCH($C85,Работы!$A$2:$A$6000,0))*(1-ДисконтТендер),0) -> 23438.15 | M85: =IF($I85="",0,IFERROR(INDEX(Материалы!$I$2:$I$9000,MATCH($I85,Материалы!$A$2:$A$9000,0))*IF(INDEX(Материалы!$J$2:$J$9000,MATCH($I85,Материалы!$A$2:$A$9000,0))="USD",КурсUSD,IF(INDEX(Материалы!$J$2:$J$9000,MATCH($I85,Материалы!$A$2:$A$9000,0))="EUR",КурсEUR,1))*INDEX(Материалы!$K$2:$K$9000,MATCH($I85,Материалы!$A$2:$A$9000,0))*(1+IFERROR(INDEX(Работы!$I$2:$I$6000,MATCH($C85,Работы!$A$2:$A$6000,0))/100,0))*(1-ДисконтТендер),0)) -> 0 | N85: =IF(AND($R85="да",$H85<>""),ROUND($H85*$L85,2),0) -> 0 | O85: =IF(AND($R85="да",$H85<>""),ROUND($H85*$M85,2),0) -> 0 | P85: =$N85+$O85 -> 0 | Q85: =IFERROR(INDEX(Работы!$J$2:$J$6000,MATCH($C85,Работы!$A$2:$A$6000,0)),"") -> типовая | R85: да | T85: =IF(AND($P85>0,$R85="да"),MAX($T$1:$T84)+1,"")
A86: =IFERROR(INDEX(Работы!$D$2:$D$6000,MATCH($C86,Работы!$A$2:$A$6000,0)),"") -> Р1 | B86: =IFERROR(INDEX(Работы!$F$2:$F$6000,MATCH($C86,Работы!$A$2:$A$6000,0)),"") -> 1 | C86: =IFERROR(INDEX(Работы!$A$2:$A$6000,85),"") -> РАБ.Р1.1.085 | D86: =IFERROR(INDEX(Работы!$B$2:$B$6000,MATCH($C86,Работы!$A$2:$A$6000,0)),"") -> Предоставление заключения пожарной испытательной лаборатории для контроля качества огнезащитных работ с предоставлением заключения о соответствии (более 1000 м кв. металлоконструкц… | E86: =IFERROR(INDEX(Работы!$C$2:$C$6000,MATCH($C86,Работы!$A$2:$A$6000,0)),"") -> м2 | F86: =IFERROR(INDEX(Работы!$G$2:$G$6000,MATCH($C86,Работы!$A$2:$A$6000,0)),"") -> 0 | G86: =IFERROR(INDEX(Работы!$K$2:$K$6000,MATCH($C86,Работы!$A$2:$A$6000,0)),"") -> S_поверхность | J86: =IFERROR(INDEX(Материалы!$B$2:$B$9000,MATCH($I86,Материалы!$A$2:$A$9000,0)),"") | K86: =IF($I86="","",IF($F86=IFERROR(INDEX(Материалы!$G$2:$G$9000,MATCH($I86,Материалы!$A$2:$A$9000,0)),""),"OK","!! не та группа")) | L86: =IFERROR(INDEX(Работы!$H$2:$H$6000,MATCH($C86,Работы!$A$2:$A$6000,0))*(1-ДисконтТендер),0) -> 17.8 | M86: =IF($I86="",0,IFERROR(INDEX(Материалы!$I$2:$I$9000,MATCH($I86,Материалы!$A$2:$A$9000,0))*IF(INDEX(Материалы!$J$2:$J$9000,MATCH($I86,Материалы!$A$2:$A$9000,0))="USD",КурсUSD,IF(INDEX(Материалы!$J$2:$J$9000,MATCH($I86,Материалы!$A$2:$A$9000,0))="EUR",КурсEUR,1))*INDEX(Материалы!$K$2:$K$9000,MATCH($I86,Материалы!$A$2:$A$9000,0))*(1+IFERROR(INDEX(Работы!$I$2:$I$6000,MATCH($C86,Работы!$A$2:$A$6000,0))/100,0))*(1-ДисконтТендер),0)) -> 0 | N86: =IF(AND($R86="да",$H86<>""),ROUND($H86*$L86,2),0) -> 0 | O86: =IF(AND($R86="да",$H86<>""),ROUND($H86*$M86,2),0) -> 0 | P86: =$N86+$O86 -> 0 | Q86: =IFERROR(INDEX(Работы!$J$2:$J$6000,MATCH($C86,Работы!$A$2:$A$6000,0)),"") -> типовая | R86: да | T86: =IF(AND($P86>0,$R86="да"),MAX($T$1:$T85)+1,"")
A87: =IFERROR(INDEX(Работы!$D$2:$D$6000,MATCH($C87,Работы!$A$2:$A$6000,0)),"") -> Р1 | B87: =IFERROR(INDEX(Работы!$F$2:$F$6000,MATCH($C87,Работы!$A$2:$A$6000,0)),"") -> 1 | C87: =IFERROR(INDEX(Работы!$A$2:$A$6000,86),"") -> РАБ.Р1.1.086 | D87: =IFERROR(INDEX(Работы!$B$2:$B$6000,MATCH($C87,Работы!$A$2:$A$6000,0)),"") -> Акустический расчет инженерных систем ОВиК (предоставление в Роспотребнадзор) электронный и бумажный вариант | E87: =IFERROR(INDEX(Работы!$C$2:$C$6000,MATCH($C87,Работы!$A$2:$A$6000,0)),"") -> компл. | F87: =IFERROR(INDEX(Работы!$G$2:$G$6000,MATCH($C87,Работы!$A$2:$A$6000,0)),"") -> 0 | G87: =IFERROR(INDEX(Работы!$K$2:$K$6000,MATCH($C87,Работы!$A$2:$A$6000,0)),"") -> S_общая | J87: =IFERROR(INDEX(Материалы!$B$2:$B$9000,MATCH($I87,Материалы!$A$2:$A$9000,0)),"") | K87: =IF($I87="","",IF($F87=IFERROR(INDEX(Материалы!$G$2:$G$9000,MATCH($I87,Материалы!$A$2:$A$9000,0)),""),"OK","!! не та группа")) | L87: =IFERROR(INDEX(Работы!$H$2:$H$6000,MATCH($C87,Работы!$A$2:$A$6000,0))*(1-ДисконтТендер),0) -> 132501.92 | M87: =IF($I87="",0,IFERROR(INDEX(Материалы!$I$2:$I$9000,MATCH($I87,Материалы!$A$2:$A$9000,0))*IF(INDEX(Материалы!$J$2:$J$9000,MATCH($I87,Материалы!$A$2:$A$9000,0))="USD",КурсUSD,IF(INDEX(Материалы!$J$2:$J$9000,MATCH($I87,Материалы!$A$2:$A$9000,0))="EUR",КурсEUR,1))*INDEX(Материалы!$K$2:$K$9000,MATCH($I87,Материалы!$A$2:$A$9000,0))*(1+IFERROR(INDEX(Работы!$I$2:$I$6000,MATCH($C87,Работы!$A$2:$A$6000,0))/100,0))*(1-ДисконтТендер),0)) -> 0 | N87: =IF(AND($R87="да",$H87<>""),ROUND($H87*$L87,2),0) -> 0 | O87: =IF(AND($R87="да",$H87<>""),ROUND($H87*$M87,2),0) -> 0 | P87: =$N87+$O87 -> 0 | Q87: =IFERROR(INDEX(Работы!$J$2:$J$6000,MATCH($C87,Работы!$A$2:$A$6000,0)),"") -> типовая | R87: да | T87: =IF(AND($P87>0,$R87="да"),MAX($T$1:$T86)+1,"")
A88: =IFERROR(INDEX(Работы!$D$2:$D$6000,MATCH($C88,Работы!$A$2:$A$6000,0)),"") -> Р1 | B88: =IFERROR(INDEX(Работы!$F$2:$F$6000,MATCH($C88,Работы!$A$2:$A$6000,0)),"") -> 1 | C88: =IFERROR(INDEX(Работы!$A$2:$A$6000,87),"") -> РАБ.Р1.1.087 | D88: =IFERROR(INDEX(Работы!$B$2:$B$6000,MATCH($C88,Работы!$A$2:$A$6000,0)),"") -> Стоимость согласования проекта приспособления объекта культурного наследия в соответствии с нормативными актами Министерства культуры и КГИОП г._Санкт-Петербурга_. ( включая провед… | E88: =IFERROR(INDEX(Работы!$C$2:$C$6000,MATCH($C88,Работы!$A$2:$A$6000,0)),"") -> компл. | F88: =IFERROR(INDEX(Работы!$G$2:$G$6000,MATCH($C88,Работы!$A$2:$A$6000,0)),"") -> 0 | G88: =IFERROR(INDEX(Работы!$K$2:$K$6000,MATCH($C88,Работы!$A$2:$A$6000,0)),"") -> S_общая | J88: =IFERROR(INDEX(Материалы!$B$2:$B$9000,MATCH($I88,Материалы!$A$2:$A$9000,0)),"") | K88: =IF($I88="","",IF($F88=IFERROR(INDEX(Материалы!$G$2:$G$9000,MATCH($I88,Материалы!$A$2:$A$9000,0)),""),"OK","!! не та группа")) | L88: =IFERROR(INDEX(Работы!$H$2:$H$6000,MATCH($C88,Работы!$A$2:$A$6000,0))*(1-ДисконтТендер),0) -> 134515.33 | M88: =IF($I88="",0,IFERROR(INDEX(Материалы!$I$2:$I$9000,MATCH($I88,Материалы!$A$2:$A$9000,0))*IF(INDEX(Материалы!$J$2:$J$9000,MATCH($I88,Материалы!$A$2:$A$9000,0))="USD",КурсUSD,IF(INDEX(Материалы!$J$2:$J$9000,MATCH($I88,Материалы!$A$2:$A$9000,0))="EUR",КурсEUR,1))*INDEX(Материалы!$K$2:$K$9000,MATCH($I88,Материалы!$A$2:$A$9000,0))*(1+IFERROR(INDEX(Работы!$I$2:$I$6000,MATCH($C88,Работы!$A$2:$A$6000,0))/100,0))*(1-ДисконтТендер),0)) -> 0 | N88: =IF(AND($R88="да",$H88<>""),ROUND($H88*$L88,2),0) -> 0 | O88: =IF(AND($R88="да",$H88<>""),ROUND($H88*$M88,2),0) -> 0 | P88: =$N88+$O88 -> 0 | Q88: =IFERROR(INDEX(Работы!$J$2:$J$6000,MATCH($C88,Работы!$A$2:$A$6000,0)),"") -> типовая | R88: да | T88: =IF(AND($P88>0,$R88="да"),MAX($T$1:$T87)+1,"")
A89: =IFERROR(INDEX(Работы!$D$2:$D$6000,MATCH($C89,Работы!$A$2:$A$6000,0)),"") -> Р1 | B89: =IFERROR(INDEX(Работы!$F$2:$F$6000,MATCH($C89,Работы!$A$2:$A$6000,0)),"") -> 1 | C89: =IFERROR(INDEX(Работы!$A$2:$A$6000,88),"") -> РАБ.Р1.1.088 | D89: =IFERROR(INDEX(Работы!$B$2:$B$6000,MATCH($C89,Работы!$A$2:$A$6000,0)),"") -> Стоимость согласования проекта перепланировки/реконструкции объекта в соответствии с нормативными актами г. ______________ | E89: =IFERROR(INDEX(Работы!$C$2:$C$6000,MATCH($C89,Работы!$A$2:$A$6000,0)),"") -> кв.м.площади офиса | F89: =IFERROR(INDEX(Работы!$G$2:$G$6000,MATCH($C89,Работы!$A$2:$A$6000,0)),"") -> 0 | G89: =IFERROR(INDEX(Работы!$K$2:$K$6000,MATCH($C89,Работы!$A$2:$A$6000,0)),"") -> S_общая | J89: =IFERROR(INDEX(Материалы!$B$2:$B$9000,MATCH($I89,Материалы!$A$2:$A$9000,0)),"") | K89: =IF($I89="","",IF($F89=IFERROR(INDEX(Материалы!$G$2:$G$9000,MATCH($I89,Материалы!$A$2:$A$9000,0)),""),"OK","!! не та группа")) | L89: =IFERROR(INDEX(Работы!$H$2:$H$6000,MATCH($C89,Работы!$A$2:$A$6000,0))*(1-ДисконтТендер),0) -> 137099.86 | M89: =IF($I89="",0,IFERROR(INDEX(Материалы!$I$2:$I$9000,MATCH($I89,Материалы!$A$2:$A$9000,0))*IF(INDEX(Материалы!$J$2:$J$9000,MATCH($I89,Материалы!$A$2:$A$9000,0))="USD",КурсUSD,IF(INDEX(Материалы!$J$2:$J$9000,MATCH($I89,Материалы!$A$2:$A$9000,0))="EUR",КурсEUR,1))*INDEX(Материалы!$K$2:$K$9000,MATCH($I89,Материалы!$A$2:$A$9000,0))*(1+IFERROR(INDEX(Работы!$I$2:$I$6000,MATCH($C89,Работы!$A$2:$A$6000,0))/100,0))*(1-ДисконтТендер),0)) -> 0 | N89: =IF(AND($R89="да",$H89<>""),ROUND($H89*$L89,2),0) -> 0 | O89: =IF(AND($R89="да",$H89<>""),ROUND($H89*$M89,2),0) -> 0 | P89: =$N89+$O89 -> 0 | Q89: =IFERROR(INDEX(Работы!$J$2:$J$6000,MATCH($C89,Работы!$A$2:$A$6000,0)),"") -> типовая | R89: да | T89: =IF(AND($P89>0,$R89="да"),MAX($T$1:$T88)+1,"")
A90: =IFERROR(INDEX(Работы!$D$2:$D$6000,MATCH($C90,Работы!$A$2:$A$6000,0)),"") -> Р1 | B90: =IFERROR(INDEX(Работы!$F$2:$F$6000,MATCH($C90,Работы!$A$2:$A$6000,0)),"") -> 1 | C90: =IFERROR(INDEX(Работы!$A$2:$A$6000,89),"") -> РАБ.Р1.1.089 | D90: =IFERROR(INDEX(Работы!$B$2:$B$6000,MATCH($C90,Работы!$A$2:$A$6000,0)),"") -> Получение паспорта БТИ (в черных линиях) | E90: =IFERROR(INDEX(Работы!$C$2:$C$6000,MATCH($C90,Работы!$A$2:$A$6000,0)),"") -> компл. | F90: =IFERROR(INDEX(Работы!$G$2:$G$6000,MATCH($C90,Работы!$A$2:$A$6000,0)),"") -> 0 | G90: =IFERROR(INDEX(Работы!$K$2:$K$6000,MATCH($C90,Работы!$A$2:$A$6000,0)),"") -> S_общая | J90: =IFERROR(INDEX(Материалы!$B$2:$B$9000,MATCH($I90,Материалы!$A$2:$A$9000,0)),"") | K90: =IF($I90="","",IF($F90=IFERROR(INDEX(Материалы!$G$2:$G$9000,MATCH($I90,Материалы!$A$2:$A$9000,0)),""),"OK","!! не та группа")) | L90: =IFERROR(INDEX(Работы!$H$2:$H$6000,MATCH($C90,Работы!$A$2:$A$6000,0))*(1-ДисконтТендер),0) -> 134499.93 | M90: =IF($I90="",0,IFERROR(INDEX(Материалы!$I$2:$I$9000,MATCH($I90,Материалы!$A$2:$A$9000,0))*IF(INDEX(Материалы!$J$2:$J$9000,MATCH($I90,Материалы!$A$2:$A$9000,0))="USD",КурсUSD,IF(INDEX(Материалы!$J$2:$J$9000,MATCH($I90,Материалы!$A$2:$A$9000,0))="EUR",КурсEUR,1))*INDEX(Материалы!$K$2:$K$9000,MATCH($I90,Материалы!$A$2:$A$9000,0))*(1+IFERROR(INDEX(Работы!$I$2:$I$6000,MATCH($C90,Работы!$A$2:$A$6000,0))/100,0))*(1-ДисконтТендер),0)) -> 0 | N90: =IF(AND($R90="да",$H90<>""),ROUND($H90*$L90,2),0) -> 0 | O90: =IF(AND($R90="да",$H90<>""),ROUND($H90*$M90,2),0) -> 0 | P90: =$N90+$O90 -> 0 | Q90: =IFERROR(INDEX(Работы!$J$2:$J$6000,MATCH($C90,Работы!$A$2:$A$6000,0)),"") -> типовая | R90: да | T90: =IF(AND($P90>0,$R90="да"),MAX($T$1:$T89)+1,"")
A91: =IFERROR(INDEX(Работы!$D$2:$D$6000,MATCH($C91,Работы!$A$2:$A$6000,0)),"") -> Р1 | B91: =IFERROR(INDEX(Работы!$F$2:$F$6000,MATCH($C91,Работы!$A$2:$A$6000,0)),"") -> 1 | C91: =IFERROR(INDEX(Работы!$A$2:$A$6000,90),"") -> РАБ.Р1.1.090 | D91: =IFERROR(INDEX(Работы!$B$2:$B$6000,MATCH($C91,Работы!$A$2:$A$6000,0)),"") -> Ведение авторского надзора в период проведения РСР по приспособлению объекта культурного наследия( в соответствии с условиями ТЗ) | E91: =IFERROR(INDEX(Работы!$C$2:$C$6000,MATCH($C91,Работы!$A$2:$A$6000,0)),"") -> компл. | F91: =IFERROR(INDEX(Работы!$G$2:$G$6000,MATCH($C91,Работы!$A$2:$A$6000,0)),"") -> 0 | G91: =IFERROR(INDEX(Работы!$K$2:$K$6000,MATCH($C91,Работы!$A$2:$A$6000,0)),"") -> S_общая | J91: =IFERROR(INDEX(Материалы!$B$2:$B$9000,MATCH($I91,Материалы!$A$2:$A$9000,0)),"") | K91: =IF($I91="","",IF($F91=IFERROR(INDEX(Материалы!$G$2:$G$9000,MATCH($I91,Материалы!$A$2:$A$9000,0)),""),"OK","!! не та группа")) | L91: =IFERROR(INDEX(Работы!$H$2:$H$6000,MATCH($C91,Работы!$A$2:$A$6000,0))*(1-ДисконтТендер),0) -> 135524.49 | M91: =IF($I91="",0,IFERROR(INDEX(Материалы!$I$2:$I$9000,MATCH($I91,Материалы!$A$2:$A$9000,0))*IF(INDEX(Материалы!$J$2:$J$9000,MATCH($I91,Материалы!$A$2:$A$9000,0))="USD",КурсUSD,IF(INDEX(Материалы!$J$2:$J$9000,MATCH($I91,Материалы!$A$2:$A$9000,0))="EUR",КурсEUR,1))*INDEX(Материалы!$K$2:$K$9000,MATCH($I91,Материалы!$A$2:$A$9000,0))*(1+IFERROR(INDEX(Работы!$I$2:$I$6000,MATCH($C91,Работы!$A$2:$A$6000,0))/100,0))*(1-ДисконтТендер),0)) -> 0 | N91: =IF(AND($R91="да",$H91<>""),ROUND($H91*$L91,2),0) -> 0 | O91: =IF(AND($R91="да",$H91<>""),ROUND($H91*$M91,2),0) -> 0 | P91: =$N91+$O91 -> 0 | Q91: =IFERROR(INDEX(Работы!$J$2:$J$6000,MATCH($C91,Работы!$A$2:$A$6000,0)),"") -> типовая | R91: да | T91: =IF(AND($P91>0,$R91="да"),MAX($T$1:$T90)+1,"")
A92: =IFERROR(INDEX(Работы!$D$2:$D$6000,MATCH($C92,Работы!$A$2:$A$6000,0)),"") -> Р1 | B92: =IFERROR(INDEX(Работы!$F$2:$F$6000,MATCH($C92,Работы!$A$2:$A$6000,0)),"") -> 1 | C92: =IFERROR(INDEX(Работы!$A$2:$A$6000,91),"") -> РАБ.Р1.1.091 | D92: =IFERROR(INDEX(Работы!$B$2:$B$6000,MATCH($C92,Работы!$A$2:$A$6000,0)),"") -> Подготовка и сдача в _______научного отчета | E92: =IFERROR(INDEX(Работы!$C$2:$C$6000,MATCH($C92,Работы!$A$2:$A$6000,0)),"") -> компл. | F92: =IFERROR(INDEX(Работы!$G$2:$G$6000,MATCH($C92,Работы!$A$2:$A$6000,0)),"") -> 0 | G92: =IFERROR(INDEX(Работы!$K$2:$K$6000,MATCH($C92,Работы!$A$2:$A$6000,0)),"") -> S_общая | J92: =IFERROR(INDEX(Материалы!$B$2:$B$9000,MATCH($I92,Материалы!$A$2:$A$9000,0)),"") | K92: =IF($I92="","",IF($F92=IFERROR(INDEX(Материалы!$G$2:$G$9000,MATCH($I92,Материалы!$A$2:$A$9000,0)),""),"OK","!! не та группа")) | L92: =IFERROR(INDEX(Работы!$H$2:$H$6000,MATCH($C92,Работы!$A$2:$A$6000,0))*(1-ДисконтТендер),0) -> 134002.26 | M92: =IF($I92="",0,IFERROR(INDEX(Материалы!$I$2:$I$9000,MATCH($I92,Материалы!$A$2:$A$9000,0))*IF(INDEX(Материалы!$J$2:$J$9000,MATCH($I92,Материалы!$A$2:$A$9000,0))="USD",КурсUSD,IF(INDEX(Материалы!$J$2:$J$9000,MATCH($I92,Материалы!$A$2:$A$9000,0))="EUR",КурсEUR,1))*INDEX(Материалы!$K$2:$K$9000,MATCH($I92,Материалы!$A$2:$A$9000,0))*(1+IFERROR(INDEX(Работы!$I$2:$I$6000,MATCH($C92,Работы!$A$2:$A$6000,0))/100,0))*(1-ДисконтТендер),0)) -> 0 | N92: =IF(AND($R92="да",$H92<>""),ROUND($H92*$L92,2),0) -> 0 | O92: =IF(AND($R92="да",$H92<>""),ROUND($H92*$M92,2),0) -> 0 | P92: =$N92+$O92 -> 0 | Q92: =IFERROR(INDEX(Работы!$J$2:$J$6000,MATCH($C92,Работы!$A$2:$A$6000,0)),"") -> типовая | R92: да | T92: =IF(AND($P92>0,$R92="да"),MAX($T$1:$T91)+1,"")
A93: =IFERROR(INDEX(Работы!$D$2:$D$6000,MATCH($C93,Работы!$A$2:$A$6000,0)),"") -> Р1 | B93: =IFERROR(INDEX(Работы!$F$2:$F$6000,MATCH($C93,Работы!$A$2:$A$6000,0)),"") -> 1 | C93: =IFERROR(INDEX(Работы!$A$2:$A$6000,92),"") -> РАБ.Р1.1.092 | D93: =IFERROR(INDEX(Работы!$B$2:$B$6000,MATCH($C93,Работы!$A$2:$A$6000,0)),"") -> Сопровождение проектной документации в МВК, ОГПН МЧС, ФГУЗ «ЦГиЭ», КГИОП и прочих при необходимости. Ввод объекта в эксплуатацию в КГИОП И МВК | E93: =IFERROR(INDEX(Работы!$C$2:$C$6000,MATCH($C93,Работы!$A$2:$A$6000,0)),"") -> компл. | F93: =IFERROR(INDEX(Работы!$G$2:$G$6000,MATCH($C93,Работы!$A$2:$A$6000,0)),"") -> 0 | G93: =IFERROR(INDEX(Работы!$K$2:$K$6000,MATCH($C93,Работы!$A$2:$A$6000,0)),"") -> S_общая | J93: =IFERROR(INDEX(Материалы!$B$2:$B$9000,MATCH($I93,Материалы!$A$2:$A$9000,0)),"") | K93: =IF($I93="","",IF($F93=IFERROR(INDEX(Материалы!$G$2:$G$9000,MATCH($I93,Материалы!$A$2:$A$9000,0)),""),"OK","!! не та группа")) | L93: =IFERROR(INDEX(Работы!$H$2:$H$6000,MATCH($C93,Работы!$A$2:$A$6000,0))*(1-ДисконтТендер),0) -> 852600 | M93: =IF($I93="",0,IFERROR(INDEX(Материалы!$I$2:$I$9000,MATCH($I93,Материалы!$A$2:$A$9000,0))*IF(INDEX(Материалы!$J$2:$J$9000,MATCH($I93,Материалы!$A$2:$A$9000,0))="USD",КурсUSD,IF(INDEX(Материалы!$J$2:$J$9000,MATCH($I93,Материалы!$A$2:$A$9000,0))="EUR",КурсEUR,1))*INDEX(Материалы!$K$2:$K$9000,MATCH($I93,Материалы!$A$2:$A$9000,0))*(1+IFERROR(INDEX(Работы!$I$2:$I$6000,MATCH($C93,Работы!$A$2:$A$6000,0))/100,0))*(1-ДисконтТендер),0)) -> 0 | N93: =IF(AND($R93="да",$H93<>""),ROUND($H93*$L93,2),0) -> 0 | O93: =IF(AND($R93="да",$H93<>""),ROUND($H93*$M93,2),0) -> 0 | P93: =$N93+$O93 -> 0 | Q93: =IFERROR(INDEX(Работы!$J$2:$J$6000,MATCH($C93,Работы!$A$2:$A$6000,0)),"") -> типовая | R93: да | T93: =IF(AND($P93>0,$R93="да"),MAX($T$1:$T92)+1,"")
A94: =IFERROR(INDEX(Работы!$D$2:$D$6000,MATCH($C94,Работы!$A$2:$A$6000,0)),"") -> Р2 | B94: =IFERROR(INDEX(Работы!$F$2:$F$6000,MATCH($C94,Работы!$A$2:$A$6000,0)),"") -> 1 | C94: =IFERROR(INDEX(Работы!$A$2:$A$6000,93),"") -> РАБ.Р2.1.001 | D94: =IFERROR(INDEX(Работы!$B$2:$B$6000,MATCH($C94,Работы!$A$2:$A$6000,0)),"") -> Демонтаж подвесных потолков типа "Армстронг" | E94: =IFERROR(INDEX(Работы!$C$2:$C$6000,MATCH($C94,Работы!$A$2:$A$6000,0)),"") -> м2 | F94: =IFERROR(INDEX(Работы!$G$2:$G$6000,MATCH($C94,Работы!$A$2:$A$6000,0)),"") -> 0 | G94: =IFERROR(INDEX(Работы!$K$2:$K$6000,MATCH($C94,Работы!$A$2:$A$6000,0)),"") -> Замер_демонтажа | J94: =IFERROR(INDEX(Материалы!$B$2:$B$9000,MATCH($I94,Материалы!$A$2:$A$9000,0)),"") | K94: =IF($I94="","",IF($F94=IFERROR(INDEX(Материалы!$G$2:$G$9000,MATCH($I94,Материалы!$A$2:$A$9000,0)),""),"OK","!! не та группа")) | L94: =IFERROR(INDEX(Работы!$H$2:$H$6000,MATCH($C94,Работы!$A$2:$A$6000,0))*(1-ДисконтТендер),0) -> 313.2 | M94: =IF($I94="",0,IFERROR(INDEX(Материалы!$I$2:$I$9000,MATCH($I94,Материалы!$A$2:$A$9000,0))*IF(INDEX(Материалы!$J$2:$J$9000,MATCH($I94,Материалы!$A$2:$A$9000,0))="USD",КурсUSD,IF(INDEX(Материалы!$J$2:$J$9000,MATCH($I94,Материалы!$A$2:$A$9000,0))="EUR",КурсEUR,1))*INDEX(Материалы!$K$2:$K$9000,MATCH($I94,Материалы!$A$2:$A$9000,0))*(1+IFERROR(INDEX(Работы!$I$2:$I$6000,MATCH($C94,Работы!$A$2:$A$6000,0))/100,0))*(1-ДисконтТендер),0)) -> 0 | N94: =IF(AND($R94="да",$H94<>""),ROUND($H94*$L94,2),0) -> 0 | O94: =IF(AND($R94="да",$H94<>""),ROUND($H94*$M94,2),0) -> 0 | P94: =$N94+$O94 -> 0 | Q94: =IFERROR(INDEX(Работы!$J$2:$J$6000,MATCH($C94,Работы!$A$2:$A$6000,0)),"") -> типовая | R94: да | T94: =IF(AND($P94>0,$R94="да"),MAX($T$1:$T93)+1,"")
A95: =IFERROR(INDEX(Работы!$D$2:$D$6000,MATCH($C95,Работы!$A$2:$A$6000,0)),"") -> Р2 | B95: =IFERROR(INDEX(Работы!$F$2:$F$6000,MATCH($C95,Работы!$A$2:$A$6000,0)),"") -> 1 | C95: =IFERROR(INDEX(Работы!$A$2:$A$6000,94),"") -> РАБ.Р2.1.002 | D95: =IFERROR(INDEX(Работы!$B$2:$B$6000,MATCH($C95,Работы!$A$2:$A$6000,0)),"") -> Демонтаж подвесных потолков "Армстронг" с сохранением | E95: =IFERROR(INDEX(Работы!$C$2:$C$6000,MATCH($C95,Работы!$A$2:$A$6000,0)),"") -> м2 | F95: =IFERROR(INDEX(Работы!$G$2:$G$6000,MATCH($C95,Работы!$A$2:$A$6000,0)),"") -> 0 | G95: =IFERROR(INDEX(Работы!$K$2:$K$6000,MATCH($C95,Работы!$A$2:$A$6000,0)),"") -> Замер_демонтажа | J95: =IFERROR(INDEX(Материалы!$B$2:$B$9000,MATCH($I95,Материалы!$A$2:$A$9000,0)),"") | K95: =IF($I95="","",IF($F95=IFERROR(INDEX(Материалы!$G$2:$G$9000,MATCH($I95,Материалы!$A$2:$A$9000,0)),""),"OK","!! не та группа")) | L95: =IFERROR(INDEX(Работы!$H$2:$H$6000,MATCH($C95,Работы!$A$2:$A$6000,0))*(1-ДисконтТендер),0) -> 574.75 | M95: =IF($I95="",0,IFERROR(INDEX(Материалы!$I$2:$I$9000,MATCH($I95,Материалы!$A$2:$A$9000,0))*IF(INDEX(Материалы!$J$2:$J$9000,MATCH($I95,Материалы!$A$2:$A$9000,0))="USD",КурсUSD,IF(INDEX(Материалы!$J$2:$J$9000,MATCH($I95,Материалы!$A$2:$A$9000,0))="EUR",КурсEUR,1))*INDEX(Материалы!$K$2:$K$9000,MATCH($I95,Материалы!$A$2:$A$9000,0))*(1+IFERROR(INDEX(Работы!$I$2:$I$6000,MATCH($C95,Работы!$A$2:$A$6000,0))/100,0))*(1-ДисконтТендер),0)) -> 0 | N95: =IF(AND($R95="да",$H95<>""),ROUND($H95*$L95,2),0) -> 0 | O95: =IF(AND($R95="да",$H95<>""),ROUND($H95*$M95,2),0) -> 0 | P95: =$N95+$O95 -> 0 | Q95: =IFERROR(INDEX(Работы!$J$2:$J$6000,MATCH($C95,Работы!$A$2:$A$6000,0)),"") -> типовая | R95: да | T95: =IF(AND($P95>0,$R95="да"),MAX($T$1:$T94)+1,"")
A96: =IFERROR(INDEX(Работы!$D$2:$D$6000,MATCH($C96,Работы!$A$2:$A$6000,0)),"") -> Р2 | B96: =IFERROR(INDEX(Работы!$F$2:$F$6000,MATCH($C96,Работы!$A$2:$A$6000,0)),"") -> 1 | C96: =IFERROR(INDEX(Работы!$A$2:$A$6000,95),"") -> РАБ.Р2.1.003 | D96: =IFERROR(INDEX(Работы!$B$2:$B$6000,MATCH($C96,Работы!$A$2:$A$6000,0)),"") -> Демонтаж одноуровневых потолков из ГКЛ | E96: =IFERROR(INDEX(Работы!$C$2:$C$6000,MATCH($C96,Работы!$A$2:$A$6000,0)),"") -> м2 | F96: =IFERROR(INDEX(Работы!$G$2:$G$6000,MATCH($C96,Работы!$A$2:$A$6000,0)),"") -> 0 | G96: =IFERROR(INDEX(Работы!$K$2:$K$6000,MATCH($C96,Работы!$A$2:$A$6000,0)),"") -> Замер_демонтажа | J96: =IFERROR(INDEX(Материалы!$B$2:$B$9000,MATCH($I96,Материалы!$A$2:$A$9000,0)),"") | K96: =IF($I96="","",IF($F96=IFERROR(INDEX(Материалы!$G$2:$G$9000,MATCH($I96,Материалы!$A$2:$A$9000,0)),""),"OK","!! не та группа")) | L96: =IFERROR(INDEX(Работы!$H$2:$H$6000,MATCH($C96,Работы!$A$2:$A$6000,0))*(1-ДисконтТендер),0) -> 318.72 | M96: =IF($I96="",0,IFERROR(INDEX(Материалы!$I$2:$I$9000,MATCH($I96,Материалы!$A$2:$A$9000,0))*IF(INDEX(Материалы!$J$2:$J$9000,MATCH($I96,Материалы!$A$2:$A$9000,0))="USD",КурсUSD,IF(INDEX(Материалы!$J$2:$J$9000,MATCH($I96,Материалы!$A$2:$A$9000,0))="EUR",КурсEUR,1))*INDEX(Материалы!$K$2:$K$9000,MATCH($I96,Материалы!$A$2:$A$9000,0))*(1+IFERROR(INDEX(Работы!$I$2:$I$6000,MATCH($C96,Работы!$A$2:$A$6000,0))/100,0))*(1-ДисконтТендер),0)) -> 0 | N96: =IF(AND($R96="да",$H96<>""),ROUND($H96*$L96,2),0) -> 0 | O96: =IF(AND($R96="да",$H96<>""),ROUND($H96*$M96,2),0) -> 0 | P96: =$N96+$O96 -> 0 | Q96: =IFERROR(INDEX(Работы!$J$2:$J$6000,MATCH($C96,Работы!$A$2:$A$6000,0)),"") -> типовая | R96: да | T96: =IF(AND($P96>0,$R96="да"),MAX($T$1:$T95)+1,"")
A97: =IFERROR(INDEX(Работы!$D$2:$D$6000,MATCH($C97,Работы!$A$2:$A$6000,0)),"") -> Р2 | B97: =IFERROR(INDEX(Работы!$F$2:$F$6000,MATCH($C97,Работы!$A$2:$A$6000,0)),"") -> 1 | C97: =IFERROR(INDEX(Работы!$A$2:$A$6000,96),"") -> РАБ.Р2.1.004 | D97: =IFERROR(INDEX(Работы!$B$2:$B$6000,MATCH($C97,Работы!$A$2:$A$6000,0)),"") -> Демонтаж двухуровневых потолков из ГКЛ | E97: =IFERROR(INDEX(Работы!$C$2:$C$6000,MATCH($C97,Работы!$A$2:$A$6000,0)),"") -> м2 | F97: =IFERROR(INDEX(Работы!$G$2:$G$6000,MATCH($C97,Работы!$A$2:$A$6000,0)),"") -> 0 | G97: =IFERROR(INDEX(Работы!$K$2:$K$6000,MATCH($C97,Работы!$A$2:$A$6000,0)),"") -> Замер_демонтажа | J97: =IFERROR(INDEX(Материалы!$B$2:$B$9000,MATCH($I97,Материалы!$A$2:$A$9000,0)),"") | K97: =IF($I97="","",IF($F97=IFERROR(INDEX(Материалы!$G$2:$G$9000,MATCH($I97,Материалы!$A$2:$A$9000,0)),""),"OK","!! не та группа")) | L97: =IFERROR(INDEX(Работы!$H$2:$H$6000,MATCH($C97,Работы!$A$2:$A$6000,0))*(1-ДисконтТендер),0) -> 341.73 | M97: =IF($I97="",0,IFERROR(INDEX(Материалы!$I$2:$I$9000,MATCH($I97,Материалы!$A$2:$A$9000,0))*IF(INDEX(Материалы!$J$2:$J$9000,MATCH($I97,Материалы!$A$2:$A$9000,0))="USD",КурсUSD,IF(INDEX(Материалы!$J$2:$J$9000,MATCH($I97,Материалы!$A$2:$A$9000,0))="EUR",КурсEUR,1))*INDEX(Материалы!$K$2:$K$9000,MATCH($I97,Материалы!$A$2:$A$9000,0))*(1+IFERROR(INDEX(Работы!$I$2:$I$6000,MATCH($C97,Работы!$A$2:$A$6000,0))/100,0))*(1-ДисконтТендер),0)) -> 0 | N97: =IF(AND($R97="да",$H97<>""),ROUND($H97*$L97,2),0) -> 0 | O97: =IF(AND($R97="да",$H97<>""),ROUND($H97*$M97,2),0) -> 0 | P97: =$N97+$O97 -> 0 | Q97: =IFERROR(INDEX(Работы!$J$2:$J$6000,MATCH($C97,Работы!$A$2:$A$6000,0)),"") -> типовая | R97: да | T97: =IF(AND($P97>0,$R97="да"),MAX($T$1:$T96)+1,"")
A98: =IFERROR(INDEX(Работы!$D$2:$D$6000,MATCH($C98,Работы!$A$2:$A$6000,0)),"") -> Р2 | B98: =IFERROR(INDEX(Работы!$F$2:$F$6000,MATCH($C98,Работы!$A$2:$A$6000,0)),"") -> 1 | C98: =IFERROR(INDEX(Работы!$A$2:$A$6000,97),"") -> РАБ.Р2.1.005 | D98: =IFERROR(INDEX(Работы!$B$2:$B$6000,MATCH($C98,Работы!$A$2:$A$6000,0)),"") -> Демонтаж реечного потолка | E98: =IFERROR(INDEX(Работы!$C$2:$C$6000,MATCH($C98,Работы!$A$2:$A$6000,0)),"") -> м2 | F98: =IFERROR(INDEX(Работы!$G$2:$G$6000,MATCH($C98,Работы!$A$2:$A$6000,0)),"") -> 0 | G98: =IFERROR(INDEX(Работы!$K$2:$K$6000,MATCH($C98,Работы!$A$2:$A$6000,0)),"") -> Замер_демонтажа | J98: =IFERROR(INDEX(Материалы!$B$2:$B$9000,MATCH($I98,Материалы!$A$2:$A$9000,0)),"") | K98: =IF($I98="","",IF($F98=IFERROR(INDEX(Материалы!$G$2:$G$9000,MATCH($I98,Материалы!$A$2:$A$9000,0)),""),"OK","!! не та группа")) | L98: =IFERROR(INDEX(Работы!$H$2:$H$6000,MATCH($C98,Работы!$A$2:$A$6000,0))*(1-ДисконтТендер),0) -> 260.13 | M98: =IF($I98="",0,IFERROR(INDEX(Материалы!$I$2:$I$9000,MATCH($I98,Материалы!$A$2:$A$9000,0))*IF(INDEX(Материалы!$J$2:$J$9000,MATCH($I98,Материалы!$A$2:$A$9000,0))="USD",КурсUSD,IF(INDEX(Материалы!$J$2:$J$9000,MATCH($I98,Материалы!$A$2:$A$9000,0))="EUR",КурсEUR,1))*INDEX(Материалы!$K$2:$K$9000,MATCH($I98,Материалы!$A$2:$A$9000,0))*(1+IFERROR(INDEX(Работы!$I$2:$I$6000,MATCH($C98,Работы!$A$2:$A$6000,0))/100,0))*(1-ДисконтТендер),0)) -> 0 | N98: =IF(AND($R98="да",$H98<>""),ROUND($H98*$L98,2),0) -> 0 | O98: =IF(AND($R98="да",$H98<>""),ROUND($H98*$M98,2),0) -> 0 | P98: =$N98+$O98 -> 0 | Q98: =IFERROR(INDEX(Работы!$J$2:$J$6000,MATCH($C98,Работы!$A$2:$A$6000,0)),"") -> типовая | R98: да | T98: =IF(AND($P98>0,$R98="да"),MAX($T$1:$T97)+1,"")
A99: =IFERROR(INDEX(Работы!$D$2:$D$6000,MATCH($C99,Работы!$A$2:$A$6000,0)),"") -> Р2 | B99: =IFERROR(INDEX(Работы!$F$2:$F$6000,MATCH($C99,Работы!$A$2:$A$6000,0)),"") -> 1 | C99: =IFERROR(INDEX(Работы!$A$2:$A$6000,98),"") -> РАБ.Р2.1.006 | D99: =IFERROR(INDEX(Работы!$B$2:$B$6000,MATCH($C99,Работы!$A$2:$A$6000,0)),"") -> Демонтаж плитки потолочной из экструдированного полистирола. | E99: =IFERROR(INDEX(Работы!$C$2:$C$6000,MATCH($C99,Работы!$A$2:$A$6000,0)),"") -> м2 | F99: =IFERROR(INDEX(Работы!$G$2:$G$6000,MATCH($C99,Работы!$A$2:$A$6000,0)),"") -> 0 | G99: =IFERROR(INDEX(Работы!$K$2:$K$6000,MATCH($C99,Работы!$A$2:$A$6000,0)),"") -> Замер_демонтажа | J99: =IFERROR(INDEX(Материалы!$B$2:$B$9000,MATCH($I99,Материалы!$A$2:$A$9000,0)),"") | K99: =IF($I99="","",IF($F99=IFERROR(INDEX(Материалы!$G$2:$G$9000,MATCH($I99,Материалы!$A$2:$A$9000,0)),""),"OK","!! не та группа")) | L99: =IFERROR(INDEX(Работы!$H$2:$H$6000,MATCH($C99,Работы!$A$2:$A$6000,0))*(1-ДисконтТендер),0) -> 276.02 | M99: =IF($I99="",0,IFERROR(INDEX(Материалы!$I$2:$I$9000,MATCH($I99,Материалы!$A$2:$A$9000,0))*IF(INDEX(Материалы!$J$2:$J$9000,MATCH($I99,Материалы!$A$2:$A$9000,0))="USD",КурсUSD,IF(INDEX(Материалы!$J$2:$J$9000,MATCH($I99,Материалы!$A$2:$A$9000,0))="EUR",КурсEUR,1))*INDEX(Материалы!$K$2:$K$9000,MATCH($I99,Материалы!$A$2:$A$9000,0))*(1+IFERROR(INDEX(Работы!$I$2:$I$6000,MATCH($C99,Работы!$A$2:$A$6000,0))/100,0))*(1-ДисконтТендер),0)) -> 0 | N99: =IF(AND($R99="да",$H99<>""),ROUND($H99*$L99,2),0) -> 0 | O99: =IF(AND($R99="да",$H99<>""),ROUND($H99*$M99,2),0) -> 0 | P99: =$N99+$O99 -> 0 | Q99: =IFERROR(INDEX(Работы!$J$2:$J$6000,MATCH($C99,Работы!$A$2:$A$6000,0)),"") -> типовая | R99: да | T99: =IF(AND($P99>0,$R99="да"),MAX($T$1:$T98)+1,"")
A100: =IFERROR(INDEX(Работы!$D$2:$D$6000,MATCH($C100,Работы!$A$2:$A$6000,0)),"") -> Р2 | B100: =IFERROR(INDEX(Работы!$F$2:$F$6000,MATCH($C100,Работы!$A$2:$A$6000,0)),"") -> 1 | C100: =IFERROR(INDEX(Работы!$A$2:$A$6000,99),"") -> РАБ.Р2.1.007 | D100: =IFERROR(INDEX(Работы!$B$2:$B$6000,MATCH($C100,Работы!$A$2:$A$6000,0)),"") -> Демонтаж потолков из ПВХ вагонки | E100: =IFERROR(INDEX(Работы!$C$2:$C$6000,MATCH($C100,Работы!$A$2:$A$6000,0)),"") -> м2 | F100: =IFERROR(INDEX(Работы!$G$2:$G$6000,MATCH($C100,Работы!$A$2:$A$6000,0)),"") -> 0 | G100: =IFERROR(INDEX(Работы!$K$2:$K$6000,MATCH($C100,Работы!$A$2:$A$6000,0)),"") -> Замер_демонтажа | J100: =IFERROR(INDEX(Материалы!$B$2:$B$9000,MATCH($I100,Материалы!$A$2:$A$9000,0)),"") | K100: =IF($I100="","",IF($F100=IFERROR(INDEX(Материалы!$G$2:$G$9000,MATCH($I100,Материалы!$A$2:$A$9000,0)),""),"OK","!! не та группа")) | L100: =IFERROR(INDEX(Работы!$H$2:$H$6000,MATCH($C100,Работы!$A$2:$A$6000,0))*(1-ДисконтТендер),0) -> 234.9 | M100: =IF($I100="",0,IFERROR(INDEX(Материалы!$I$2:$I$9000,MATCH($I100,Материалы!$A$2:$A$9000,0))*IF(INDEX(Материалы!$J$2:$J$9000,MATCH($I100,Материалы!$A$2:$A$9000,0))="USD",КурсUSD,IF(INDEX(Материалы!$J$2:$J$9000,MATCH($I100,Материалы!$A$2:$A$9000,0))="EUR",КурсEUR,1))*INDEX(Материалы!$K$2:$K$9000,MATCH($I100,Материалы!$A$2:$A$9000,0))*(1+IFERROR(INDEX(Работы!$I$2:$I$6000,MATCH($C100,Работы!$A$2:$A$6000,0))/100,0))*(1-ДисконтТендер),0)) -> 0 | N100: =IF(AND($R100="да",$H100<>""),ROUND($H100*$L100,2),0) -> 0 | O100: =IF(AND($R100="да",$H100<>""),ROUND($H100*$M100,2),0) -> 0 | P100: =$N100+$O100 -> 0 | Q100: =IFERROR(INDEX(Работы!$J$2:$J$6000,MATCH($C100,Работы!$A$2:$A$6000,0)),"") -> типовая | R100: да | T100: =IF(AND($P100>0,$R100="да"),MAX($T$1:$T99)+1,"")
...

Sheet Смета
A1: СМЕТА
A2: Формат объекта: | C2: =ФорматОбъекта -> ККО
A3: Адрес объекта: | C3: =Адрес -> 0
A4: Площадь объекта (м.кв.): | C4: =S_общая -> 0
A5: Срок проведения работ: | C5: =Срок -> Согласно план-графику производства работ
A6: ПОДРЯДЧИК: | C6: =Подрядчик -> 0
A7: Юридический адрес: | C7: =ЮрАдрес -> 0
A8: Электронный адрес: | C8: =ЭлАдрес -> 0
A9: Контактное лицо (Ф.И.О.): | C9: =КонтЛицо -> 0
A10: Контактный телефон: | C10: =КонтТел -> 0
A11: Реквизиты: | C11: =Реквизиты -> 0
A12: Сумма по смете, ₽: | C12: ='Свод+ТЭП'!$E$23 -> 0
A13: Цены на дату: | C13: =ДатаЦен -> 46265
A15: Курс USD: | C15: =КурсUSD -> 81
A16: Курс EUR: | C16: =КурсEUR -> 95
A17: Дисконт по тендеру, доля: | C17: =ДисконтТендер -> 0
A18: Примечание: цены с НР и СП; НДС по режиму из «Параметров».
A19: РАСШИФРОВКА РАБОТ И ЗАТРАТ (пустые строки скрыты; после ввода объёмов — Данные → Применить повторно / Ctrl+Alt+L)
A20: № | B20: Номенкл. № | C20: Наименование работ и затрат | D20: Ед. изм. | E20: Кол-во | F20: Цена ед. работ, ₽ | G20: Цена ед. материалов/оборуд., ₽ | H20: Стоимость работ, ₽ | I20: Стоимость материалов/оборуд., ₽ | J20: Всего, ₽ | K20: _кр | L20: _показать
A21: =IF($K21="","",1) | B21: =IF($K21="","",INDEX(Конструктор!$C$2:$C$1212,$K21)) | C21: =IF($K21="","",INDEX(Конструктор!$D$2:$D$1212,$K21)&IF(INDEX(Конструктор!$J$2:$J$1212,$K21)<>""," — "&INDEX(Конструктор!$J$2:$J$1212,$K21),"")) | D21: =IF($K21="","",INDEX(Конструктор!$E$2:$E$1212,$K21)) | E21: =IF($K21="","",INDEX(Конструктор!$H$2:$H$1212,$K21)) | F21: =IF($K21="","",INDEX(Конструктор!$L$2:$L$1212,$K21)) | G21: =IF($K21="","",INDEX(Конструктор!$M$2:$M$1212,$K21)) | H21: =IF($K21="","",INDEX(Конструктор!$N$2:$N$1212,$K21)) | I21: =IF($K21="","",INDEX(Конструктор!$O$2:$O$1212,$K21)) | J21: =IF($K21="","",INDEX(Конструктор!$P$2:$P$1212,$K21)) | K21: =IFERROR(MATCH(1,Конструктор!$T$2:$T$1212,0),"") | L21: =IF($K21="","","показать")
A22: =IF($K22="","",2) | B22: =IF($K22="","",INDEX(Конструктор!$C$2:$C$1212,$K22)) | C22: =IF($K22="","",INDEX(Конструктор!$D$2:$D$1212,$K22)&IF(INDEX(Конструктор!$J$2:$J$1212,$K22)<>""," — "&INDEX(Конструктор!$J$2:$J$1212,$K22),"")) | D22: =IF($K22="","",INDEX(Конструктор!$E$2:$E$1212,$K22)) | E22: =IF($K22="","",INDEX(Конструктор!$H$2:$H$1212,$K22)) | F22: =IF($K22="","",INDEX(Конструктор!$L$2:$L$1212,$K22)) | G22: =IF($K22="","",INDEX(Конструктор!$M$2:$M$1212,$K22)) | H22: =IF($K22="","",INDEX(Конструктор!$N$2:$N$1212,$K22)) | I22: =IF($K22="","",INDEX(Конструктор!$O$2:$O$1212,$K22)) | J22: =IF($K22="","",INDEX(Конструктор!$P$2:$P$1212,$K22)) | K22: =IFERROR(MATCH(2,Конструктор!$T$2:$T$1212,0),"") | L22: =IF($K22="","","показать")
A23: =IF($K23="","",3) | B23: =IF($K23="","",INDEX(Конструктор!$C$2:$C$1212,$K23)) | C23: =IF($K23="","",INDEX(Конструктор!$D$2:$D$1212,$K23)&IF(INDEX(Конструктор!$J$2:$J$1212,$K23)<>""," — "&INDEX(Конструктор!$J$2:$J$1212,$K23),"")) | D23: =IF($K23="","",INDEX(Конструктор!$E$2:$E$1212,$K23)) | E23: =IF($K23="","",INDEX(Конструктор!$H$2:$H$1212,$K23)) | F23: =IF($K23="","",INDEX(Конструктор!$L$2:$L$1212,$K23)) | G23: =IF($K23="","",INDEX(Конструктор!$M$2:$M$1212,$K23)) | H23: =IF($K23="","",INDEX(Конструктор!$N$2:$N$1212,$K23)) | I23: =IF($K23="","",INDEX(Конструктор!$O$2:$O$1212,$K23)) | J23: =IF($K23="","",INDEX(Конструктор!$P$2:$P$1212,$K23)) | K23: =IFERROR(MATCH(3,Конструктор!$T$2:$T$1212,0),"") | L23: =IF($K23="","","показать")
A24: =IF($K24="","",4) | B24: =IF($K24="","",INDEX(Конструктор!$C$2:$C$1212,$K24)) | C24: =IF($K24="","",INDEX(Конструктор!$D$2:$D$1212,$K24)&IF(INDEX(Конструктор!$J$2:$J$1212,$K24)<>""," — "&INDEX(Конструктор!$J$2:$J$1212,$K24),"")) | D24: =IF($K24="","",INDEX(Конструктор!$E$2:$E$1212,$K24)) | E24: =IF($K24="","",INDEX(Конструктор!$H$2:$H$1212,$K24)) | F24: =IF($K24="","",INDEX(Конструктор!$L$2:$L$1212,$K24)) | G24: =IF($K24="","",INDEX(Конструктор!$M$2:$M$1212,$K24)) | H24: =IF($K24="","",INDEX(Конструктор!$N$2:$N$1212,$K24)) | I24: =IF($K24="","",INDEX(Конструктор!$O$2:$O$1212,$K24)) | J24: =IF($K24="","",INDEX(Конструктор!$P$2:$P$1212,$K24)) | K24: =IFERROR(MATCH(4,Конструктор!$T$2:$T$1212,0),"") | L24: =IF($K24="","","показать")
A25: =IF($K25="","",5) | B25: =IF($K25="","",INDEX(Конструктор!$C$2:$C$1212,$K25)) | C25: =IF($K25="","",INDEX(Конструктор!$D$2:$D$1212,$K25)&IF(INDEX(Конструктор!$J$2:$J$1212,$K25)<>""," — "&INDEX(Конструктор!$J$2:$J$1212,$K25),"")) | D25: =IF($K25="","",INDEX(Конструктор!$E$2:$E$1212,$K25)) | E25: =IF($K25="","",INDEX(Конструктор!$H$2:$H$1212,$K25)) | F25: =IF($K25="","",INDEX(Конструктор!$L$2:$L$1212,$K25)) | G25: =IF($K25="","",INDEX(Конструктор!$M$2:$M$1212,$K25)) | H25: =IF($K25="","",INDEX(Конструктор!$N$2:$N$1212,$K25)) | I25: =IF($K25="","",INDEX(Конструктор!$O$2:$O$1212,$K25)) | J25: =IF($K25="","",INDEX(Конструктор!$P$2:$P$1212,$K25)) | K25: =IFERROR(MATCH(5,Конструктор!$T$2:$T$1212,0),"") | L25: =IF($K25="","","показать")
A26: =IF($K26="","",6) | B26: =IF($K26="","",INDEX(Конструктор!$C$2:$C$1212,$K26)) | C26: =IF($K26="","",INDEX(Конструктор!$D$2:$D$1212,$K26)&IF(INDEX(Конструктор!$J$2:$J$1212,$K26)<>""," — "&INDEX(Конструктор!$J$2:$J$1212,$K26),"")) | D26: =IF($K26="","",INDEX(Конструктор!$E$2:$E$1212,$K26)) | E26: =IF($K26="","",INDEX(Конструктор!$H$2:$H$1212,$K26)) | F26: =IF($K26="","",INDEX(Конструктор!$L$2:$L$1212,$K26)) | G26: =IF($K26="","",INDEX(Конструктор!$M$2:$M$1212,$K26)) | H26: =IF($K26="","",INDEX(Конструктор!$N$2:$N$1212,$K26)) | I26: =IF($K26="","",INDEX(Конструктор!$O$2:$O$1212,$K26)) | J26: =IF($K26="","",INDEX(Конструктор!$P$2:$P$1212,$K26)) | K26: =IFERROR(MATCH(6,Конструктор!$T$2:$T$1212,0),"") | L26: =IF($K26="","","показать")
A27: =IF($K27="","",7) | B27: =IF($K27="","",INDEX(Конструктор!$C$2:$C$1212,$K27)) | C27: =IF($K27="","",INDEX(Конструктор!$D$2:$D$1212,$K27)&IF(INDEX(Конструктор!$J$2:$J$1212,$K27)<>""," — "&INDEX(Конструктор!$J$2:$J$1212,$K27),"")) | D27: =IF($K27="","",INDEX(Конструктор!$E$2:$E$1212,$K27)) | E27: =IF($K27="","",INDEX(Конструктор!$H$2:$H$1212,$K27)) | F27: =IF($K27="","",INDEX(Конструктор!$L$2:$L$1212,$K27)) | G27: =IF($K27="","",INDEX(Конструктор!$M$2:$M$1212,$K27)) | H27: =IF($K27="","",INDEX(Конструктор!$N$2:$N$1212,$K27)) | I27: =IF($K27="","",INDEX(Конструктор!$O$2:$O$1212,$K27)) | J27: =IF($K27="","",INDEX(Конструктор!$P$2:$P$1212,$K27)) | K27: =IFERROR(MATCH(7,Конструктор!$T$2:$T$1212,0),"") | L27: =IF($K27="","","показать")
A28: =IF($K28="","",8) | B28: =IF($K28="","",INDEX(Конструктор!$C$2:$C$1212,$K28)) | C28: =IF($K28="","",INDEX(Конструктор!$D$2:$D$1212,$K28)&IF(INDEX(Конструктор!$J$2:$J$1212,$K28)<>""," — "&INDEX(Конструктор!$J$2:$J$1212,$K28),"")) | D28: =IF($K28="","",INDEX(Конструктор!$E$2:$E$1212,$K28)) | E28: =IF($K28="","",INDEX(Конструктор!$H$2:$H$1212,$K28)) | F28: =IF($K28="","",INDEX(Конструктор!$L$2:$L$1212,$K28)) | G28: =IF($K28="","",INDEX(Конструктор!$M$2:$M$1212,$K28)) | H28: =IF($K28="","",INDEX(Конструктор!$N$2:$N$1212,$K28)) | I28: =IF($K28="","",INDEX(Конструктор!$O$2:$O$1212,$K28)) | J28: =IF($K28="","",INDEX(Конструктор!$P$2:$P$1212,$K28)) | K28: =IFERROR(MATCH(8,Конструктор!$T$2:$T$1212,0),"") | L28: =IF($K28="","","показать")
A29: =IF($K29="","",9) | B29: =IF($K29="","",INDEX(Конструктор!$C$2:$C$1212,$K29)) | C29: =IF($K29="","",INDEX(Конструктор!$D$2:$D$1212,$K29)&IF(INDEX(Конструктор!$J$2:$J$1212,$K29)<>""," — "&INDEX(Конструктор!$J$2:$J$1212,$K29),"")) | D29: =IF($K29="","",INDEX(Конструктор!$E$2:$E$1212,$K29)) | E29: =IF($K29="","",INDEX(Конструктор!$H$2:$H$1212,$K29)) | F29: =IF($K29="","",INDEX(Конструктор!$L$2:$L$1212,$K29)) | G29: =IF($K29="","",INDEX(Конструктор!$M$2:$M$1212,$K29)) | H29: =IF($K29="","",INDEX(Конструктор!$N$2:$N$1212,$K29)) | I29: =IF($K29="","",INDEX(Конструктор!$O$2:$O$1212,$K29)) | J29: =IF($K29="","",INDEX(Конструктор!$P$2:$P$1212,$K29)) | K29: =IFERROR(MATCH(9,Конструктор!$T$2:$T$1212,0),"") | L29: =IF($K29="","","показать")
A30: =IF($K30="","",10) | B30: =IF($K30="","",INDEX(Конструктор!$C$2:$C$1212,$K30)) | C30: =IF($K30="","",INDEX(Конструктор!$D$2:$D$1212,$K30)&IF(INDEX(Конструктор!$J$2:$J$1212,$K30)<>""," — "&INDEX(Конструктор!$J$2:$J$1212,$K30),"")) | D30: =IF($K30="","",INDEX(Конструктор!$E$2:$E$1212,$K30)) | E30: =IF($K30="","",INDEX(Конструктор!$H$2:$H$1212,$K30)) | F30: =IF($K30="","",INDEX(Конструктор!$L$2:$L$1212,$K30)) | G30: =IF($K30="","",INDEX(Конструктор!$M$2:$M$1212,$K30)) | H30: =IF($K30="","",INDEX(Конструктор!$N$2:$N$1212,$K30)) | I30: =IF($K30="","",INDEX(Конструктор!$O$2:$O$1212,$K30)) | J30: =IF($K30="","",INDEX(Конструктор!$P$2:$P$1212,$K30)) | K30: =IFERROR(MATCH(10,Конструктор!$T$2:$T$1212,0),"") | L30: =IF($K30="","","показать")
A31: =IF($K31="","",11) | B31: =IF($K31="","",INDEX(Конструктор!$C$2:$C$1212,$K31)) | C31: =IF($K31="","",INDEX(Конструктор!$D$2:$D$1212,$K31)&IF(INDEX(Конструктор!$J$2:$J$1212,$K31)<>""," — "&INDEX(Конструктор!$J$2:$J$1212,$K31),"")) | D31: =IF($K31="","",INDEX(Конструктор!$E$2:$E$1212,$K31)) | E31: =IF($K31="","",INDEX(Конструктор!$H$2:$H$1212,$K31)) | F31: =IF($K31="","",INDEX(Конструктор!$L$2:$L$1212,$K31)) | G31: =IF($K31="","",INDEX(Конструктор!$M$2:$M$1212,$K31)) | H31: =IF($K31="","",INDEX(Конструктор!$N$2:$N$1212,$K31)) | I31: =IF($K31="","",INDEX(Конструктор!$O$2:$O$1212,$K31)) | J31: =IF($K31="","",INDEX(Конструктор!$P$2:$P$1212,$K31)) | K31: =IFERROR(MATCH(11,Конструктор!$T$2:$T$1212,0),"") | L31: =IF($K31="","","показать")
A32: =IF($K32="","",12) | B32: =IF($K32="","",INDEX(Конструктор!$C$2:$C$1212,$K32)) | C32: =IF($K32="","",INDEX(Конструктор!$D$2:$D$1212,$K32)&IF(INDEX(Конструктор!$J$2:$J$1212,$K32)<>""," — "&INDEX(Конструктор!$J$2:$J$1212,$K32),"")) | D32: =IF($K32="","",INDEX(Конструктор!$E$2:$E$1212,$K32)) | E32: =IF($K32="","",INDEX(Конструктор!$H$2:$H$1212,$K32)) | F32: =IF($K32="","",INDEX(Конструктор!$L$2:$L$1212,$K32)) | G32: =IF($K32="","",INDEX(Конструктор!$M$2:$M$1212,$K32)) | H32: =IF($K32="","",INDEX(Конструктор!$N$2:$N$1212,$K32)) | I32: =IF($K32="","",INDEX(Конструктор!$O$2:$O$1212,$K32)) | J32: =IF($K32="","",INDEX(Конструктор!$P$2:$P$1212,$K32)) | K32: =IFERROR(MATCH(12,Конструктор!$T$2:$T$1212,0),"") | L32: =IF($K32="","","показать")
A33: =IF($K33="","",13) | B33: =IF($K33="","",INDEX(Конструктор!$C$2:$C$1212,$K33)) | C33: =IF($K33="","",INDEX(Конструктор!$D$2:$D$1212,$K33)&IF(INDEX(Конструктор!$J$2:$J$1212,$K33)<>""," — "&INDEX(Конструктор!$J$2:$J$1212,$K33),"")) | D33: =IF($K33="","",INDEX(Конструктор!$E$2:$E$1212,$K33)) | E33: =IF($K33="","",INDEX(Конструктор!$H$2:$H$1212,$K33)) | F33: =IF($K33="","",INDEX(Конструктор!$L$2:$L$1212,$K33)) | G33: =IF($K33="","",INDEX(Конструктор!$M$2:$M$1212,$K33)) | H33: =IF($K33="","",INDEX(Конструктор!$N$2:$N$1212,$K33)) | I33: =IF($K33="","",INDEX(Конструктор!$O$2:$O$1212,$K33)) | J33: =IF($K33="","",INDEX(Конструктор!$P$2:$P$1212,$K33)) | K33: =IFERROR(MATCH(13,Конструктор!$T$2:$T$1212,0),"") | L33: =IF($K33="","","показать")
A34: =IF($K34="","",14) | B34: =IF($K34="","",INDEX(Конструктор!$C$2:$C$1212,$K34)) | C34: =IF($K34="","",INDEX(Конструктор!$D$2:$D$1212,$K34)&IF(INDEX(Конструктор!$J$2:$J$1212,$K34)<>""," — "&INDEX(Конструктор!$J$2:$J$1212,$K34),"")) | D34: =IF($K34="","",INDEX(Конструктор!$E$2:$E$1212,$K34)) | E34: =IF($K34="","",INDEX(Конструктор!$H$2:$H$1212,$K34)) | F34: =IF($K34="","",INDEX(Конструктор!$L$2:$L$1212,$K34)) | G34: =IF($K34="","",INDEX(Конструктор!$M$2:$M$1212,$K34)) | H34: =IF($K34="","",INDEX(Конструктор!$N$2:$N$1212,$K34)) | I34: =IF($K34="","",INDEX(Конструктор!$O$2:$O$1212,$K34)) | J34: =IF($K34="","",INDEX(Конструктор!$P$2:$P$1212,$K34)) | K34: =IFERROR(MATCH(14,Конструктор!$T$2:$T$1212,0),"") | L34: =IF($K34="","","показать")
A35: =IF($K35="","",15) | B35: =IF($K35="","",INDEX(Конструктор!$C$2:$C$1212,$K35)) | C35: =IF($K35="","",INDEX(Конструктор!$D$2:$D$1212,$K35)&IF(INDEX(Конструктор!$J$2:$J$1212,$K35)<>""," — "&INDEX(Конструктор!$J$2:$J$1212,$K35),"")) | D35: =IF($K35="","",INDEX(Конструктор!$E$2:$E$1212,$K35)) | E35: =IF($K35="","",INDEX(Конструктор!$H$2:$H$1212,$K35)) | F35: =IF($K35="","",INDEX(Конструктор!$L$2:$L$1212,$K35)) | G35: =IF($K35="","",INDEX(Конструктор!$M$2:$M$1212,$K35)) | H35: =IF($K35="","",INDEX(Конструктор!$N$2:$N$1212,$K35)) | I35: =IF($K35="","",INDEX(Конструктор!$O$2:$O$1212,$K35)) | J35: =IF($K35="","",INDEX(Конструктор!$P$2:$P$1212,$K35)) | K35: =IFERROR(MATCH(15,Конструктор!$T$2:$T$1212,0),"") | L35: =IF($K35="","","показать")
A36: =IF($K36="","",16) | B36: =IF($K36="","",INDEX(Конструктор!$C$2:$C$1212,$K36)) | C36: =IF($K36="","",INDEX(Конструктор!$D$2:$D$1212,$K36)&IF(INDEX(Конструктор!$J$2:$J$1212,$K36)<>""," — "&INDEX(Конструктор!$J$2:$J$1212,$K36),"")) | D36: =IF($K36="","",INDEX(Конструктор!$E$2:$E$1212,$K36)) | E36: =IF($K36="","",INDEX(Конструктор!$H$2:$H$1212,$K36)) | F36: =IF($K36="","",INDEX(Конструктор!$L$2:$L$1212,$K36)) | G36: =IF($K36="","",INDEX(Конструктор!$M$2:$M$1212,$K36)) | H36: =IF($K36="","",INDEX(Конструктор!$N$2:$N$1212,$K36)) | I36: =IF($K36="","",INDEX(Конструктор!$O$2:$O$1212,$K36)) | J36: =IF($K36="","",INDEX(Конструктор!$P$2:$P$1212,$K36)) | K36: =IFERROR(MATCH(16,Конструктор!$T$2:$T$1212,0),"") | L36: =IF($K36="","","показать")
A37: =IF($K37="","",17) | B37: =IF($K37="","",INDEX(Конструктор!$C$2:$C$1212,$K37)) | C37: =IF($K37="","",INDEX(Конструктор!$D$2:$D$1212,$K37)&IF(INDEX(Конструктор!$J$2:$J$1212,$K37)<>""," — "&INDEX(Конструктор!$J$2:$J$1212,$K37),"")) | D37: =IF($K37="","",INDEX(Конструктор!$E$2:$E$1212,$K37)) | E37: =IF($K37="","",INDEX(Конструктор!$H$2:$H$1212,$K37)) | F37: =IF($K37="","",INDEX(Конструктор!$L$2:$L$1212,$K37)) | G37: =IF($K37="","",INDEX(Конструктор!$M$2:$M$1212,$K37)) | H37: =IF($K37="","",INDEX(Конструктор!$N$2:$N$1212,$K37)) | I37: =IF($K37="","",INDEX(Конструктор!$O$2:$O$1212,$K37)) | J37: =IF($K37="","",INDEX(Конструктор!$P$2:$P$1212,$K37)) | K37: =IFERROR(MATCH(17,Конструктор!$T$2:$T$1212,0),"") | L37: =IF($K37="","","показать")
A38: =IF($K38="","",18) | B38: =IF($K38="","",INDEX(Конструктор!$C$2:$C$1212,$K38)) | C38: =IF($K38="","",INDEX(Конструктор!$D$2:$D$1212,$K38)&IF(INDEX(Конструктор!$J$2:$J$1212,$K38)<>""," — "&INDEX(Конструктор!$J$2:$J$1212,$K38),"")) | D38: =IF($K38="","",INDEX(Конструктор!$E$2:$E$1212,$K38)) | E38: =IF($K38="","",INDEX(Конструктор!$H$2:$H$1212,$K38)) | F38: =IF($K38="","",INDEX(Конструктор!$L$2:$L$1212,$K38)) | G38: =IF($K38="","",INDEX(Конструктор!$M$2:$M$1212,$K38)) | H38: =IF($K38="","",INDEX(Конструктор!$N$2:$N$1212,$K38)) | I38: =IF($K38="","",INDEX(Конструктор!$O$2:$O$1212,$K38)) | J38: =IF($K38="","",INDEX(Конструктор!$P$2:$P$1212,$K38)) | K38: =IFERROR(MATCH(18,Конструктор!$T$2:$T$1212,0),"") | L38: =IF($K38="","","показать")
A39: =IF($K39="","",19) | B39: =IF($K39="","",INDEX(Конструктор!$C$2:$C$1212,$K39)) | C39: =IF($K39="","",INDEX(Конструктор!$D$2:$D$1212,$K39)&IF(INDEX(Конструктор!$J$2:$J$1212,$K39)<>""," — "&INDEX(Конструктор!$J$2:$J$1212,$K39),"")) | D39: =IF($K39="","",INDEX(Конструктор!$E$2:$E$1212,$K39)) | E39: =IF($K39="","",INDEX(Конструктор!$H$2:$H$1212,$K39)) | F39: =IF($K39="","",INDEX(Конструктор!$L$2:$L$1212,$K39)) | G39: =IF($K39="","",INDEX(Конструктор!$M$2:$M$1212,$K39)) | H39: =IF($K39="","",INDEX(Конструктор!$N$2:$N$1212,$K39)) | I39: =IF($K39="","",INDEX(Конструктор!$O$2:$O$1212,$K39)) | J39: =IF($K39="","",INDEX(Конструктор!$P$2:$P$1212,$K39)) | K39: =IFERROR(MATCH(19,Конструктор!$T$2:$T$1212,0),"") | L39: =IF($K39="","","показать")
A40: =IF($K40="","",20) | B40: =IF($K40="","",INDEX(Конструктор!$C$2:$C$1212,$K40)) | C40: =IF($K40="","",INDEX(Конструктор!$D$2:$D$1212,$K40)&IF(INDEX(Конструктор!$J$2:$J$1212,$K40)<>""," — "&INDEX(Конструктор!$J$2:$J$1212,$K40),"")) | D40: =IF($K40="","",INDEX(Конструктор!$E$2:$E$1212,$K40)) | E40: =IF($K40="","",INDEX(Конструктор!$H$2:$H$1212,$K40)) | F40: =IF($K40="","",INDEX(Конструктор!$L$2:$L$1212,$K40)) | G40: =IF($K40="","",INDEX(Конструктор!$M$2:$M$1212,$K40)) | H40: =IF($K40="","",INDEX(Конструктор!$N$2:$N$1212,$K40)) | I40: =IF($K40="","",INDEX(Конструктор!$O$2:$O$1212,$K40)) | J40: =IF($K40="","",INDEX(Конструктор!$P$2:$P$1212,$K40)) | K40: =IFERROR(MATCH(20,Конструктор!$T$2:$T$1212,0),"") | L40: =IF($K40="","","показать")
A41: =IF($K41="","",21) | B41: =IF($K41="","",INDEX(Конструктор!$C$2:$C$1212,$K41)) | C41: =IF($K41="","",INDEX(Конструктор!$D$2:$D$1212,$K41)&IF(INDEX(Конструктор!$J$2:$J$1212,$K41)<>""," — "&INDEX(Конструктор!$J$2:$J$1212,$K41),"")) | D41: =IF($K41="","",INDEX(Конструктор!$E$2:$E$1212,$K41)) | E41: =IF($K41="","",INDEX(Конструктор!$H$2:$H$1212,$K41)) | F41: =IF($K41="","",INDEX(Конструктор!$L$2:$L$1212,$K41)) | G41: =IF($K41="","",INDEX(Конструктор!$M$2:$M$1212,$K41)) | H41: =IF($K41="","",INDEX(Конструктор!$N$2:$N$1212,$K41)) | I41: =IF($K41="","",INDEX(Конструктор!$O$2:$O$1212,$K41)) | J41: =IF($K41="","",INDEX(Конструктор!$P$2:$P$1212,$K41)) | K41: =IFERROR(MATCH(21,Конструктор!$T$2:$T$1212,0),"") | L41: =IF($K41="","","показать")
A42: =IF($K42="","",22) | B42: =IF($K42="","",INDEX(Конструктор!$C$2:$C$1212,$K42)) | C42: =IF($K42="","",INDEX(Конструктор!$D$2:$D$1212,$K42)&IF(INDEX(Конструктор!$J$2:$J$1212,$K42)<>""," — "&INDEX(Конструктор!$J$2:$J$1212,$K42),"")) | D42: =IF($K42="","",INDEX(Конструктор!$E$2:$E$1212,$K42)) | E42: =IF($K42="","",INDEX(Конструктор!$H$2:$H$1212,$K42)) | F42: =IF($K42="","",INDEX(Конструктор!$L$2:$L$1212,$K42)) | G42: =IF($K42="","",INDEX(Конструктор!$M$2:$M$1212,$K42)) | H42: =IF($K42="","",INDEX(Конструктор!$N$2:$N$1212,$K42)) | I42: =IF($K42="","",INDEX(Конструктор!$O$2:$O$1212,$K42)) | J42: =IF($K42="","",INDEX(Конструктор!$P$2:$P$1212,$K42)) | K42: =IFERROR(MATCH(22,Конструктор!$T$2:$T$1212,0),"") | L42: =IF($K42="","","показать")
A43: =IF($K43="","",23) | B43: =IF($K43="","",INDEX(Конструктор!$C$2:$C$1212,$K43)) | C43: =IF($K43="","",INDEX(Конструктор!$D$2:$D$1212,$K43)&IF(INDEX(Конструктор!$J$2:$J$1212,$K43)<>""," — "&INDEX(Конструктор!$J$2:$J$1212,$K43),"")) | D43: =IF($K43="","",INDEX(Конструктор!$E$2:$E$1212,$K43)) | E43: =IF($K43="","",INDEX(Конструктор!$H$2:$H$1212,$K43)) | F43: =IF($K43="","",INDEX(Конструктор!$L$2:$L$1212,$K43)) | G43: =IF($K43="","",INDEX(Конструктор!$M$2:$M$1212,$K43)) | H43: =IF($K43="","",INDEX(Конструктор!$N$2:$N$1212,$K43)) | I43: =IF($K43="","",INDEX(Конструктор!$O$2:$O$1212,$K43)) | J43: =IF($K43="","",INDEX(Конструктор!$P$2:$P$1212,$K43)) | K43: =IFERROR(MATCH(23,Конструктор!$T$2:$T$1212,0),"") | L43: =IF($K43="","","показать")
