Workbook
Name КодыРабот: спр_Работы!$A$2:$A$6000
Name ФорматОбъекта: Параметры!$B$5
Name Адрес: Параметры!$B$6
Name Срок: Параметры!$B$7
Name ДатаЦен: Параметры!$B$8
Name Подрядчик: Параметры!$B$11
Name ЮрАдрес: Параметры!$B$12
Name ЭлАдрес: Параметры!$B$13
Name КонтЛицо: Параметры!$B$14
Name КонтТел: Параметры!$B$15
Name Реквизиты: Параметры!$B$16
Name S_общая: Параметры!$B$19
Name S_пол: Параметры!$B$20
Name S_стены: Параметры!$B$21
Name S_потолок: Параметры!$B$22
Name S_поверхность: Параметры!$B$23
Name S_проёмы: Параметры!$B$24
Name S_фасад: Параметры!$B$25
Name Периметр_пола: Параметры!$B$26
Name РежимЦены: Параметры!$B$29
Name СтавкаНДС: Параметры!$B$30
Name ДисконтТендер: Параметры!$B$31
Name ПроцТранспорт: Параметры!$B$32
Name ПроцТакелаж: Параметры!$B$33
Name ПроцРезерв: Параметры!$B$34
Name КурсUSD: Параметры!$B$35
Name КурсEUR: Параметры!$B$36

Sheet О шаблоне
A1: Смета объекта — шаблон v0.4 (совместим с Excel 2019)
A3: ПОРЯДОК РАБОТЫ
A4: 1. «Параметры» — заполнить жёлтые ячейки: объект, подрядчик, площади, НДС, %% транспорта/такелажа/резерва, курсы.
A5: 2. «Конструктор» — предзаполнен ВСЕМИ работами справочника (колонка «Код_работы» — формула, правит сам себя).
A6: Для нужных строк: ввести «Объём» (подсказка «Драйвер»: S_пол / S_стены / спецификация / замер…),
A7: выбрать «Код_материала» (список — только материалы группы этой работы), при необходимости «Вкл.» = нет.
A8: 3. «Смета» — чистовой документ: шапка + расшифровка + итоги + сноска + подписи. Строится формулами ИНДЕКС/ПОИСКПОЗ.
A9: Изначально строки расшифровки СКРЫТЫ (данных нет). После ввода объёмов в «Конструкторе»:
A10: встать на любую ячейку таблицы расшифровки → Данные → «Применить повторно» (Ctrl+Alt+L).
A11: Заполненные позиции появятся, блок итогов встанет сразу под ними. Руками не трогать.
A12: 4. «Свод+ТЭП» — доли работ/материалов, ₽/м². «Контроль» — красное = ошибка.
A14: КАК ДОБАВЛЯТЬ НОВЫЕ РАБОТЫ И МАТЕРИАЛЫ
... A34: Сформировано: 2026-08-31. Справочники: версия 0.3. Работ предзаполнено: 911. Буфер Конструктора: 1211. Версия шаблона: 0.6.

Sheet Параметры
A1: ПАРАМЕТРЫ ОБЪЕКТА
A3: Параметр | B3: Значение | C3: Пояснение
A4: Объект
A5: Формат объекта | B5: ККО | C5: ККО / Инфраструктура
A6: Адрес объекта
A7: Срок проведения работ | B7: Согласно план-графику производства работ
A8: Дата цен | B8: 46265 | C8: на какую дату актуальны цены справочника
A10: Подрядчик
A11: ПОДРЯДЧИК (наименование)
A12: Юридический адрес
A13: Электронный адрес
A14: Контактное лицо (Ф.И.О.)
A15: Контактный телефон
A16: Реквизиты
A18: Площади, м²
A19: S_общая (площадь объекта) | B19: 0 | C19: для ТЭП и проектных расценок
A20: S_пол | B20: 0 | C20: драйвер S_пол
A21: S_стены | B21: 0 | C21: драйвер S_стены (развёртка)
A22: S_потолок | B22: 0 | C22: драйвер S_потолок
A23: S_поверхность | B23: 0 | C23: драйвер S_поверхность
A24: S_проёмы | B24: 0 | C24: драйвер S_проёмы
A25: S_фасад | B25: 0 | C25: драйвер S_фасад
A26: Периметр_пола, м.п. | B26: 0 | C26: драйвер Периметр_пола
A28: Финансы
A29: Режим цены | B29: с НДС в цене | C29: «с НДС в цене» — НДС извлекается; «без НДС» — начисляется сверху
A30: Ставка НДС, % | B30: 20 | C30: 5 / 7 / 20
A31: Дисконт по тендеру, доля | B31: 0 | C31: 0,05 = минус 5% к ЕР
A32: Транспортные, % от стоимости материалов | B32: 3
A33: Такелаж / верт. транспорт, % от (работы+материалы) | B33: 0 | C33: режим ТЦ/БЦ, ночные работы
A34: Резерв на непредвиденные, % от (работы+материалы) | B34: 0 | C34: 0 = не применять
A35: Курс USD | B35: 81 | C35: для валютных материалов
A36: Курс EUR | B36: 95

Sheet Конструктор
A1: Раздел | B1: Подраздел | C1: Код_работы | D1: Наименование работы | E1: Ед | F1: Группа_мат | G1: Драйвер | H1: Объём | I1: Код_материала | J1: Наименование материала | K1: Гр_ОK | L1: Цена работ, ₽ | M1: Цена мат, ₽ | N1: Стоим. работ, ₽ | O1: Стоим. мат, ₽ | P1: Всего, ₽ | Q1: Тип | R1: Вкл. | S1: Примечание | T1: _ранг
A2: =IFERROR(INDEX(спр_Работы!$D$2:$D$6000,MATCH($C2,спр_Работы!$A$2:$A$6000,0)),"") | B2: =IFERROR(INDEX(спр_Работы!$F$2:$F$6000,MATCH($C2,спр_Работы!$A$2:$A$6000,0)),"") | C2: =IFERROR(INDEX(спр_Работы!$A$2:$A$6000,1),"") | D2: =IFERROR(INDEX(спр_Работы!$B$2:$B$6000,MATCH($C2,спр_Работы!$A$2:$A$6000,0)),"") | E2: =IFERROR(INDEX(спр_Работы!$C$2:$C$6000,MATCH($C2,спр_Работы!$A$2:$A$6000,0)),"") | F2: =IFERROR(INDEX(спр_Работы!$G$2:$G$6000,MATCH($C2,спр_Работы!$A$2:$A$6000,0)),"") | G2: =IFERROR(INDEX(спр_Работы!$K$2:$K$6000,MATCH($C2,спр_Работы!$A$2:$A$6000,0)),"") | J2: =IFERROR(INDEX(спр_Материалы!$B$2:$B$9000,MATCH($I2,спр_Материалы!$A$2:$A$9000,0)),"") | K2: =IF($I2="","",IF($F2=IFERROR(INDEX(спр_Материалы!$G$2:$G$9000,MATCH($I2,спр_Материалы!$A$2:$A$9000,0)),""),"OK","!! не та группа")) | L2: =IFERROR(INDEX(спр_Работы!$H$2:$H$6000,MATCH($C2,спр_Работы!$A$2:$A$6000,0))*(1-ДисконтТендер),0) | M2: =IF($I2="",0,IFERROR(INDEX(спр_Материалы!$I$2:$I$9000,MATCH($I2,спр_Материалы!$A$2:$A$9000,0))*IF(INDEX(спр_Материалы!$J$2:$J$9000,MATCH($I2,спр_Материалы!$A$2:$A$9000,0))="USD",КурсUSD,IF(INDEX(спр_Материалы!$J$2:$J$9000,MATCH($I2,спр_Материалы!$A$2:$A$9000,0))="EUR",КурсEUR,1))*INDEX(спр_Материалы!$K$2:$K$9000,MATCH($I2,спр_Материалы!$A$2:$A$9000,0))*(1+IFERROR(INDEX(спр_Работы!$I$2:$I$6000,MATCH($C2,спр_Работы!$A$2:$A$6000,0))/100,0))*(1-ДисконтТендер),0)) | N2: =IF(AND($R2="да",$H2<>""),ROUND($H2*$L2,2),0) | O2: =IF(AND($R2="да",$H2<>""),ROUND($H2*$M2,2),0) | P2: =$N2+$O2 | Q2: =IFERROR(INDEX(спр_Работы!$J$2:$J$6000,MATCH($C2,спр_Работы!$A$2:$A$6000,0)),"") | R2: да | T2: =IF(AND($P2>0,$R2="да"),MAX($T$1:$T1)+1,"")
A3: =IFERROR(INDEX(спр_Работы!$D$2:$D$6000,MATCH($C3,спр_Работы!$A$2:$A$6000,0)),"") | B3: =IFERROR(INDEX(спр_Работы!$F$2:$F$6000,MATCH($C3,спр_Работы!$A$2:$A$6000,0)),"") | C3: =IFERROR(INDEX(спр_Работы!$A$2:$A$6000,2),"") | D3: =IFERROR(INDEX(спр_Работы!$B$2:$B$6000,MATCH($C3,спр_Работы!$A$2:$A$6000,0)),"") | E3: =IFERROR(INDEX(спр_Работы!$C$2:$C$6000,MATCH($C3,спр_Работы!$A$2:$A$6000,0)),"") | F3: =IFERROR(INDEX(спр_Работы!$G$2:$G$6000,MATCH($C3,спр_Работы!$A$2:$A$6000,0)),"") | G3: =IFERROR(INDEX(спр_Работы!$K$2:$K$6000,MATCH($C3,спр_Работы!$A$2:$A$6000,0)),"") | J3: =IFERROR(INDEX(спр_Материалы!$B$2:$B$9000,MATCH($I3,спр_Материалы!$A$2:$A$9000,0)),"") | K3: =IF($I3="","",IF($F3=IFERROR(INDEX(спр_Материалы!$G$2:$G$9000,MATCH($I3,спр_Материалы!$A$2:$A$9000,0)),""),"OK","!! не та группа")) | L3: =IFERROR(INDEX(спр_Работы!$H$2:$H$6000,MATCH($C3,спр_Работы!$A$2:$A$6000,0))*(1-ДисконтТендер),0) | M3: =IF($I3="",0,IFERROR(INDEX(спр_Материалы!$I$2:$I$9000,MATCH($I3,спр_Материалы!$A$2:$A$9000,0))*IF(INDEX(спр_Материалы!$J$2:$J$9000,MATCH($I3,спр_Материалы!$A$2:$A$9000,0))="USD",КурсUSD,IF(INDEX(спр_Материалы!$J$2:$J$9000,MATCH($I3,спр_Материалы!$A$2:$A$9000,0))="EUR",КурсEUR,1))*INDEX(спр_Материалы!$K$2:$K$9000,MATCH($I3,спр_Материалы!$A$2:$A$9000,0))*(1+IFERROR(INDEX(спр_Работы!$I$2:$I$6000,MATCH($C3,спр_Работы!$A$2:$A$6000,0))/100,0))*(1-ДисконтТендер),0)) | N3: =IF(AND($R3="да",$H3<>""),ROUND($H3*$L3,2),0) | O3: =IF(AND($R3="да",$H3<>""),ROUND($H3*$M3,2),0) | P3: =$N3+$O3 | Q3: =IFERROR(INDEX(спр_Работы!$J$2:$J$6000,MATCH($C3,спр_Работы!$A$2:$A$6000,0)),"") | R3: да | T3: =IF(AND($P3>0,$R3="да"),MAX($T$1:$T2)+1,"")
A4: =IFERROR(INDEX(спр_Работы!$D$2:$D$6000,MATCH($C4,спр_Работы!$A$2:$A$6000,0)),"") | B4: =IFERROR(INDEX(спр_Работы!$F$2:$F$6000,MATCH($C4,спр_Работы!$A$2:$A$6000,0)),"") | C4: =IFERROR(INDEX(спр_Работы!$A$2:$A$6000,3),"") | D4: =IFERROR(INDEX(спр_Работы!$B$2:$B$6000,MATCH($C4,спр_Работы!$A$2:$A$6000,0)),"") | E4: =IFERROR(INDEX(спр_Работы!$C$2:$C$6000,MATCH($C4,спр_Работы!$A$2:$A$6000,0)),"") | F4: =IFERROR(INDEX(спр_Работы!$G$2:$G$6000,MATCH($C4,спр_Работы!$A$2:$A$6000,0)),"") | G4: =IFERROR(INDEX(спр_Работы!$K$2:$K$6000,MATCH($C4,спр_Работы!$A$2:$A$6000,0)),"") | J4: =IFERROR(INDEX(спр_Материалы!$B$2:$B$9000,MATCH($I4,спр_Материалы!$A$2:$A$9000,0)),"") | K4: =IF($I4="","",IF($F4=IFERROR(INDEX(спр_Материалы!$G$2:$G$9000,MATCH($I4,спр_Материалы!$A$2:$A$9000,0)),""),"OK","!! не та группа")) | L4: =IFERROR(INDEX(спр_Работы!$H$2:$H$6000,MATCH($C4,спр_Работы!$A$2:$A$6000,0))*(1-ДисконтТендер),0) | M4: =IF($I4="",0,IFERROR(INDEX(спр_Материалы!$I$2:$I$9000,MATCH($I4,спр_Материалы!$A$2:$A$9000,0))*IF(INDEX(спр_Материалы!$J$2:$J$9000,MATCH($I4,спр_Материалы!$A$2:$A$9000,0))="USD",КурсUSD,IF(INDEX(спр_Материалы!$J$2:$J$9000,MATCH($I4,спр_Материалы!$A$2:$A$9000,0))="EUR",КурсEUR,1))*INDEX(спр_Материалы!$K$2:$K$9000,MATCH($I4,спр_Материалы!$A$2:$A$9000,0))*(1+IFERROR(INDEX(спр_Работы!$I$2:$I$6000,MATCH($C4,спр_Работы!$A$2:$A$6000,0))/100,0))*(1-ДисконтТендер),0)) | N4: =IF(AND($R4="да",$H4<>""),ROUND($H4*$L4,2),0) | O4: =IF(AND($R4="да",$H4<>""),ROUND($H4*$M4,2),0) | P4: =$N4+$O4 | Q4: =IFERROR(INDEX(спр_Работы!$J$2:$J$6000,MATCH($C4,спр_Работы!$A$2:$A$6000,0)),"") | R4: да | T4: =IF(AND($P4>0,$R4="да"),MAX($T$1:$T3)+1,"")
A5: =IFERROR(INDEX(спр_Работы!$D$2:$D$6000,MATCH($C5,спр_Работы!$A$2:$A$6000,0)),"") | B5: =IFERROR(INDEX(спр_Работы!$F$2:$F$6000,MATCH($C5,спр_Работы!$A$2:$A$6000,0)),"") | C5: =IFERROR(INDEX(спр_Работы!$A$2:$A$6000,4),"") | D5: =IFERROR(INDEX(спр_Работы!$B$2:$B$6000,MATCH($C5,спр_Работы!$A$2:$A$6000,0)),"") | E5: =IFERROR(INDEX(спр_Работы!$C$2:$C$6000,MATCH($C5,спр_Работы!$A$2:$A$6000,0)),"") | F5: =IFERROR(INDEX(спр_Работы!$G$2:$G$6000,MATCH($C5,спр_Работы!$A$2:$A$6000,0)),"") | G5: =IFERROR(INDEX(спр_Работы!$K$2:$K$6000,MATCH($C5,спр_Работы!$A$2:$A$6000,0)),"") | J5: =IFERROR(INDEX(спр_Материалы!$B$2:$B$9000,MATCH($I5,спр_Материалы!$A$2:$A$9000,0)),"") | K5: =IF($I5="","",IF($F5=IFERROR(INDEX(спр_Материалы!$G$2:$G$9000,MATCH($I5,спр_Материалы!$A$2:$A$9000,0)),""),"OK","!! не та группа")) | L5: =IFERROR(INDEX(спр_Работы!$H$2:$H$6000,MATCH($C5,спр_Работы!$A$2:$A$6000,0))*(1-ДисконтТендер),0) | M5: =IF($I5="",0,IFERROR(INDEX(спр_Материалы!$I$2:$I$9000,MATCH($I5,спр_Материалы!$A$2:$A$9000,0))*IF(INDEX(спр_Материалы!$J$2:$J$9000,MATCH($I5,спр_Материалы!$A$2:$A$9000,0))="USD",КурсUSD,IF(INDEX(спр_Материалы!$J$2:$J$9000,MATCH($I5,спр_Материалы!$A$2:$A$9000,0))="EUR",КурсEUR,1))*INDEX(спр_Материалы!$K$2:$K$9000,MATCH($I5,спр_Материалы!$A$2:$A$9000,0))*(1+IFERROR(INDEX(спр_Работы!$I$2:$I$6000,MATCH($C5,спр_Работы!$A$2:$A$6000,0))/100,0))*(1-ДисконтТендер),0)) | N5: =IF(AND($R5="да",$H5<>""),ROUND($H5*$L5,2),0) | O5: =IF(AND($R5="да",$H5<>""),ROUND($H5*$M5,2),0) | P5: =$N5+$O5 | Q5: =IFERROR(INDEX(спр_Работы!$J$2:$J$6000,MATCH($C5,спр_Работы!$A$2:$A$6000,0)),"") | R5: да | T5: =IF(AND($P5>0,$R5="да"),MAX($T$1:$T4)+1,"")
A6: =IFERROR(INDEX(спр_Работы!$D$2:$D$6000,MATCH($C6,спр_Работы!$A$2:$A$6000,0)),"") | B6: =IFERROR(INDEX(спр_Работы!$F$2:$F$6000,MATCH($C6,спр_Работы!$A$2:$A$6000,0)),"") | C6: =IFERROR(INDEX(спр_Работы!$A$2:$A$6000,5),"") | D6: =IFERROR(INDEX(спр_Работы!$B$2:$B$6000,MATCH($C6,спр_Работы!$A$2:$A$6000,0)),"") | E6: =IFERROR(INDEX(спр_Работы!$C$2:$C$6000,MATCH($C6,спр_Работы!$A$2:$A$6000,0)),"") | F6: =IFERROR(INDEX(спр_Работы!$G$2:$G$6000,MATCH($C6,спр_Работы!$A$2:$A$6000,0)),"") | G6: =IFERROR(INDEX(спр_Работы!$K$2:$K$6000,MATCH($C6,спр_Работы!$A$2:$A$6000,0)),"") | J6: =IFERROR(INDEX(спр_Материалы!$B$2:$B$9000,MATCH($I6,спр_Материалы!$A$2:$A$9000,0)),"") | K6: =IF($I6="","",IF($F6=IFERROR(INDEX(спр_Материалы!$G$2:$G$9000,MATCH($I6,спр_Материалы!$A$2:$A$9000,0)),""),"OK","!! не та группа")) | L6: =IFERROR(INDEX(спр_Работы!$H$2:$H$6000,MATCH($C6,спр_Работы!$A$2:$A$6000,0))*(1-ДисконтТендер),0) | M6: =IF($I6="",0,IFERROR(INDEX(спр_Материалы!$I$2:$I$9000,MATCH($I6,спр_Материалы!$A$2:$A$9000,0))*IF(INDEX(спр_Материалы!$J$2:$J$9000,MATCH($I6,спр_Материалы!$A$2:$A$9000,0))="USD",КурсUSD,IF(INDEX(спр_Материалы!$J$2:$J$9000,MATCH($I6,спр_Материалы!$A$2:$A$9000,0))="EUR",КурсEUR,1))*INDEX(спр_Материалы!$K$2:$K$9000,MATCH($I6,спр_Материалы!$A$2:$A$9000,0))*(1+IFERROR(INDEX(спр_Работы!$I$2:$I$6000,MATCH($C6,спр_Работы!$A$2:$A$6000,0))/100,0))*(1-ДисконтТендер),0)) | N6: =IF(AND($R6="да",$H6<>""),ROUND($H6*$L6,2),0) | O6: =IF(AND($R6="да",$H6<>""),ROUND($H6*$M6,2),0) | P6: =$N6+$O6 | Q6: =IFERROR(INDEX(спр_Работы!$J$2:$J$6000,MATCH($C6,спр_Работы!$A$2:$A$6000,0)),"") | R6: да | T6: =IF(AND($P6>0,$R6="да"),MAX($T$1:$T5)+1,"")
A7: =IFERROR(INDEX(спр_Работы!$D$2:$D$6000,MATCH($C7,спр_Работы!$A$2:$A$6000,0)),"") | B7: =IFERROR(INDEX(спр_Работы!$F$2:$F$6000,MATCH($C7,спр_Работы!$A$2:$A$6000,0)),"") | C7: =IFERROR(INDEX(спр_Работы!$A$2:$A$6000,6),"") | D7: =IFERROR(INDEX(спр_Работы!$B$2:$B$6000,MATCH($C7,спр_Работы!$A$2:$A$6000,0)),"") | E7: =IFERROR(INDEX(спр_Работы!$C$2:$C$6000,MATCH($C7,спр_Работы!$A$2:$A$6000,0)),"") | F7: =IFERROR(INDEX(спр_Работы!$G$2:$G$6000,MATCH($C7,спр_Работы!$A$2:$A$6000,0)),"") | G7: =IFERROR(INDEX(спр_Работы!$K$2:$K$6000,MATCH($C7,спр_Работы!$A$2:$A$6000,0)),"") | J7: =IFERROR(INDEX(спр_Материалы!$B$2:$B$9000,MATCH($I7,спр_Материалы!$A$2:$A$9000,0)),"") | K7: =IF($I7="","",IF($F7=IFERROR(INDEX(спр_Материалы!$G$2:$G$9000,MATCH($I7,спр_Материалы!$A$2:$A$9000,0)),""),"OK","!! не та группа")) | L7: =IFERROR(INDEX(спр_Работы!$H$2:$H$6000,MATCH($C7,спр_Работы!$A$2:$A$6000,0))*(1-ДисконтТендер),0) | M7: =IF($I7="",0,IFERROR(INDEX(спр_Материалы!$I$2:$I$9000,MATCH($I7,спр_Материалы!$A$2:$A$9000,0))*IF(INDEX(спр_Материалы!$J$2:$J$9000,MATCH($I7,спр_Материалы!$A$2:$A$9000,0))="USD",КурсUSD,IF(INDEX(спр_Материалы!$J$2:$J$9000,MATCH($I7,спр_Материалы!$A$2:$A$9000,0))="EUR",КурсEUR,1))*INDEX(спр_Материалы!$K$2:$K$9000,MATCH($I7,спр_Материалы!$A$2:$A$9000,0))*(1+IFERROR(INDEX(спр_Работы!$I$2:$I$6000,MATCH($C7,спр_Работы!$A$2:$A$6000,0))/100,0))*(1-ДисконтТендер),0)) | N7: =IF(AND($R7="да",$H7<>""),ROUND($H7*$L7,2),0) | O7: =IF(AND($R7="да",$H7<>""),ROUND($H7*$M7,2),0) | P7: =$N7+$O7 | Q7: =IFERROR(INDEX(спр_Работы!$J$2:$J$6000,MATCH($C7,спр_Работы!$A$2:$A$6000,0)),"") | R7: да | T7: =IF(AND($P7>0,$R7="да"),MAX($T$1:$T6)+1,"")
A8: =IFERROR(INDEX(спр_Работы!$D$2:$D$6000,MATCH($C8,спр_Работы!$A$2:$A$6000,0)),"") | B8: =IFERROR(INDEX(спр_Работы!$F$2:$F$6000,MATCH($C8,спр_Работы!$A$2:$A$6000,0)),"") | C8: =IFERROR(INDEX(спр_Работы!$A$2:$A$6000,7),"") | D8: =IFERROR(INDEX(спр_Работы!$B$2:$B$6000,MATCH($C8,спр_Работы!$A$2:$A$6000,0)),"") | E8: =IFERROR(INDEX(спр_Работы!$C$2:$C$6000,MATCH($C8,спр_Работы!$A$2:$A$6000,0)),"") | F8: =IFERROR(INDEX(спр_Работы!$G$2:$G$6000,MATCH($C8,спр_Работы!$A$2:$A$6000,0)),"") | G8: =IFERROR(INDEX(спр_Работы!$K$2:$K$6000,MATCH($C8,спр_Работы!$A$2:$A$6000,0)),"") | J8: =IFERROR(INDEX(спр_Материалы!$B$2:$B$9000,MATCH($I8,спр_Материалы!$A$2:$A$9000,0)),"") | K8: =IF($I8="","",IF($F8=IFERROR(INDEX(спр_Материалы!$G$2:$G$9000,MATCH($I8,спр_Материалы!$A$2:$A$9000,0)),""),"OK","!! не та группа")) | L8: =IFERROR(INDEX(спр_Работы!$H$2:$H$6000,MATCH($C8,спр_Работы!$A$2:$A$6000,0))*(1-ДисконтТендер),0) | M8: =IF($I8="",0,IFERROR(INDEX(спр_Материалы!$I$2:$I$9000,MATCH($I8,спр_Материалы!$A$2:$A$9000,0))*IF(INDEX(спр_Материалы!$J$2:$J$9000,MATCH($I8,спр_Материалы!$A$2:$A$9000,0))="USD",КурсUSD,IF(INDEX(спр_Материалы!$J$2:$J$9000,MATCH($I8,спр_Материалы!$A$2:$A$9000,0))="EUR",КурсEUR,1))*INDEX(спр_Материалы!$K$2:$K$9000,MATCH($I8,спр_Материалы!$A$2:$A$9000,0))*(1+IFERROR(INDEX(спр_Работы!$I$2:$I$6000,MATCH($C8,спр_Работы!$A$2:$A$6000,0))/100,0))*(1-ДисконтТендер),0)) | N8: =IF(AND($R8="да",$H8<>""),ROUND($H8*$L8,2),0) | O8: =IF(AND($R8="да",$H8<>""),ROUND($H8*$M8,2),0) | P8: =$N8+$O8 | Q8: =IFERROR(INDEX(спр_Работы!$J$2:$J$6000,MATCH($C8,спр_Работы!$A$2:$A$6000,0)),"") | R8: да | T8: =IF(AND($P8>0,$R8="да"),MAX($T$1:$T7)+1,"")
A9: =IFERROR(INDEX(спр_Работы!$D$2:$D$6000,MATCH($C9,спр_Работы!$A$2:$A$6000,0)),"") | B9: =IFERROR(INDEX(спр_Работы!$F$2:$F$6000,MATCH($C9,спр_Работы!$A$2:$A$6000,0)),"") | C9: =IFERROR(INDEX(спр_Работы!$A$2:$A$6000,8),"") | D9: =IFERROR(INDEX(спр_Работы!$B$2:$B$6000,MATCH($C9,спр_Работы!$A$2:$A$6000,0)),"") | E9: =IFERROR(INDEX(спр_Работы!$C$2:$C$6000,MATCH($C9,спр_Работы!$A$2:$A$6000,0)),"") | F9: =IFERROR(INDEX(спр_Работы!$G$2:$G$6000,MATCH($C9,спр_Работы!$A$2:$A$6000,0)),"") | G9: =IFERROR(INDEX(спр_Работы!$K$2:$K$6000,MATCH($C9,спр_Работы!$A$2:$A$6000,0)),"") | J9: =IFERROR(INDEX(спр_Материалы!$B$2:$B$9000,MATCH($I9,спр_Материалы!$A$2:$A$9000,0)),"") | K9: =IF($I9="","",IF($F9=IFERROR(INDEX(спр_Материалы!$G$2:$G$9000,MATCH($I9,спр_Материалы!$A$2:$A$9000,0)),""),"OK","!! не та группа")) | L9: =IFERROR(INDEX(спр_Работы!$H$2:$H$6000,MATCH($C9,спр_Работы!$A$2:$A$6000,0))*(1-ДисконтТендер),0) | M9: =IF($I9="",0,IFERROR(INDEX(спр_Материалы!$I$2:$I$9000,MATCH($I9,спр_Материалы!$A$2:$A$9000,0))*IF(INDEX(спр_Материалы!$J$2:$J$9000,MATCH($I9,спр_Материалы!$A$2:$A$9000,0))="USD",КурсUSD,IF(INDEX(спр_Материалы!$J$2:$J$9000,MATCH($I9,спр_Материалы!$A$2:$A$9000,0))="EUR",КурсEUR,1))*INDEX(спр_Материалы!$K$2:$K$9000,MATCH($I9,спр_Материалы!$A$2:$A$9000,0))*(1+IFERROR(INDEX(спр_Работы!$I$2:$I$6000,MATCH($C9,спр_Работы!$A$2:$A$6000,0))/100,0))*(1-ДисконтТендер),0)) | N9: =IF(AND($R9="да",$H9<>""),ROUND($H9*$L9,2),0) | O9: =IF(AND($R9="да",$H9<>""),ROUND($H9*$M9,2),0) | P9: =$N9+$O9 | Q9: =IFERROR(INDEX(спр_Работы!$J$2:$J$6000,MATCH($C9,спр_Работы!$A$2:$A$6000,0)),"") | R9: да | T9: =IF(AND($P9>0,$R9="да"),MAX($T$1:$T8)+1,"")
A10: =IFERROR(INDEX(спр_Работы!$D$2:$D$6000,MATCH($C10,спр_Работы!$A$2:$A$6000,0)),"") | B10: =IFERROR(INDEX(спр_Работы!$F$2:$F$6000,MATCH($C10,спр_Работы!$A$2:$A$6000,0)),"") | C10: =IFERROR(INDEX(спр_Работы!$A$2:$A$6000,9),"") | D10: =IFERROR(INDEX(спр_Работы!$B$2:$B$6000,MATCH($C10,спр_Работы!$A$2:$A$6000,0)),"") | E10: =IFERROR(INDEX(спр_Работы!$C$2:$C$6000,MATCH($C10,спр_Работы!$A$2:$A$6000,0)),"") | F10: =IFERROR(INDEX(спр_Работы!$G$2:$G$6000,MATCH($C10,спр_Работы!$A$2:$A$6000,0)),"") | G10: =IFERROR(INDEX(спр_Работы!$K$2:$K$6000,MATCH($C10,спр_Работы!$A$2:$A$6000,0)),"") | J10: =IFERROR(INDEX(спр_Материалы!$B$2:$B$9000,MATCH($I10,спр_Материалы!$A$2:$A$9000,0)),"") | K10: =IF($I10="","",IF($F10=IFERROR(INDEX(спр_Материалы!$G$2:$G$9000,MATCH($I10,спр_Материалы!$A$2:$A$9000,0)),""),"OK","!! не та группа")) | L10: =IFERROR(INDEX(спр_Работы!$H$2:$H$6000,MATCH($C10,спр_Работы!$A$2:$A$6000,0))*(1-ДисконтТендер),0) | M10: =IF($I10="",0,IFERROR(INDEX(спр_Материалы!$I$2:$I$9000,MATCH($I10,спр_Материалы!$A$2:$A$9000,0))*IF(INDEX(спр_Материалы!$J$2:$J$9000,MATCH($I10,спр_Материалы!$A$2:$A$9000,0))="USD",КурсUSD,IF(INDEX(спр_Материалы!$J$2:$J$9000,MATCH($I10,спр_Материалы!$A$2:$A$9000,0))="EUR",КурсEUR,1))*INDEX(спр_Материалы!$K$2:$K$9000,MATCH($I10,спр_Материалы!$A$2:$A$9000,0))*(1+IFERROR(INDEX(спр_Работы!$I$2:$I$6000,MATCH($C10,спр_Работы!$A$2:$A$6000,0))/100,0))*(1-ДисконтТендер),0)) | N10: =IF(AND($R10="да",$H10<>""),ROUND($H10*$L10,2),0) | O10: =IF(AND($R10="да",$H10<>""),ROUND($H10*$M10,2),0) | P10: =$N10+$O10 | Q10: =IFERROR(INDEX(спр_Работы!$J$2:$J$6000,MATCH($C10,спр_Работы!$A$2:$A$6000,0)),"") | R10: да | T10: =IF(AND($P10>0,$R10="да"),MAX($T$1:$T9)+1,"")
A11: =IFERROR(INDEX(спр_Работы!$D$2:$D$6000,MATCH($C11,спр_Работы!$A$2:$A$6000,0)),"") | B11: =IFERROR(INDEX(спр_Работы!$F$2:$F$6000,MATCH($C11,спр_Работы!$A$2:$A$6000,0)),"") | C11: =IFERROR(INDEX(спр_Работы!$A$2:$A$6000,10),"") | D11: =IFERROR(INDEX(спр_Работы!$B$2:$B$6000,MATCH($C11,спр_Работы!$A$2:$A$6000,0)),"") | E11: =IFERROR(INDEX(спр_Работы!$C$2:$C$6000,MATCH($C11,спр_Работы!$A$2:$A$6000,0)),"") | F11: =IFERROR(INDEX(спр_Работы!$G$2:$G$6000,MATCH($C11,спр_Работы!$A$2:$A$6000,0)),"") | G11: =IFERROR(INDEX(спр_Работы!$K$2:$K$6000,MATCH($C11,спр_Работы!$A$2:$A$6000,0)),"") | J11: =IFERROR(INDEX(спр_Материалы!$B$2:$B$9000,MATCH($I11,спр_Материалы!$A$2:$A$9000,0)),"") | K11: =IF($I11="","",IF($F11=IFERROR(INDEX(спр_Материалы!$G$2:$G$9000,MATCH($I11,спр_Материалы!$A$2:$A$9000,0)),""),"OK","!! не та группа")) | L11: =IFERROR(INDEX(спр_Работы!$H$2:$H$6000,MATCH($C11,спр_Работы!$A$2:$A$6000,0))*(1-ДисконтТендер),0) | M11: =IF($I11="",0,IFERROR(INDEX(спр_Материалы!$I$2:$I$9000,MATCH($I11,спр_Материалы!$A$2:$A$9000,0))*IF(INDEX(спр_Материалы!$J$2:$J$9000,MATCH($I11,спр_Материалы!$A$2:$A$9000,0))="USD",КурсUSD,IF(INDEX(спр_Материалы!$J$2:$J$9000,MATCH($I11,спр_Материалы!$A$2:$A$9000,0))="EUR",КурсEUR,1))*INDEX(спр_Материалы!$K$2:$K$9000,MATCH($I11,спр_Материалы!$A$2:$A$9000,0))*(1+IFERROR(INDEX(спр_Работы!$I$2:$I$6000,MATCH($C11,спр_Работы!$A$2:$A$6000,0))/100,0))*(1-ДисконтТендер),0)) | N11: =IF(AND($R11="да",$H11<>""),ROUND($H11*$L11,2),0) | O11: =IF(AND($R11="да",$H11<>""),ROUND($H11*$M11,2),0) | P11: =$N11+$O11 | Q11: =IFERROR(INDEX(спр_Работы!$J$2:$J$6000,MATCH($C11,спр_Работы!$A$2:$A$6000,0)),"") | R11: да | T11: =IF(AND($P11>0,$R11="да"),MAX($T$1:$T10)+1,"")
A12: =IFERROR(INDEX(спр_Работы!$D$2:$D$6000,MATCH($C12,спр_Работы!$A$2:$A$6000,0)),"") | B12: =IFERROR(INDEX(спр_Работы!$F$2:$F$6000,MATCH($C12,спр_Работы!$A$2:$A$6000,0)),"") | C12: =IFERROR(INDEX(спр_Работы!$A$2:$A$6000,11),"") | D12: =IFERROR(INDEX(спр_Работы!$B$2:$B$6000,MATCH($C12,спр_Работы!$A$2:$A$6000,0)),"") | E12: =IFERROR(INDEX(спр_Работы!$C$2:$C$6000,MATCH($C12,спр_Работы!$A$2:$A$6000,0)),"") | F12: =IFERROR(INDEX(спр_Работы!$G$2:$G$6000,MATCH($C12,спр_Работы!$A$2:$A$6000,0)),"") | G12: =IFERROR(INDEX(спр_Работы!$K$2:$K$6000,MATCH($C12,спр_Работы!$A$2:$A$6000,0)),"") | J12: =IFERROR(INDEX(спр_Материалы!$B$2:$B$9000,MATCH($I12,спр_Материалы!$A$2:$A$9000,0)),"") | K12: =IF($I12="","",IF($F12=IFERROR(INDEX(спр_Материалы!$G$2:$G$9000,MATCH($I12,спр_Материалы!$A$2:$A$9000,0)),""),"OK","!! не та группа")) | L12: =IFERROR(INDEX(спр_Работы!$H$2:$H$6000,MATCH($C12,спр_Работы!$A$2:$A$6000,0))*(1-ДисконтТендер),0) | M12: =IF($I12="",0,IFERROR(INDEX(спр_Материалы!$I$2:$I$9000,MATCH($I12,спр_Материалы!$A$2:$A$9000,0))*IF(INDEX(спр_Материалы!$J$2:$J$9000,MATCH($I12,спр_Материалы!$A$2:$A$9000,0))="USD",КурсUSD,IF(INDEX(спр_Материалы!$J$2:$J$9000,MATCH($I12,спр_Материалы!$A$2:$A$9000,0))="EUR",КурсEUR,1))*INDEX(спр_Материалы!$K$2:$K$9000,MATCH($I12,спр_Материалы!$A$2:$A$9000,0))*(1+IFERROR(INDEX(спр_Работы!$I$2:$I$6000,MATCH($C12,спр_Работы!$A$2:$A$6000,0))/100,0))*(1-ДисконтТендер),0)) | N12: =IF(AND($R12="да",$H12<>""),ROUND($H12*$L12,2),0) | O12: =IF(AND($R12="да",$H12<>""),ROUND($H12*$M12,2),0) | P12: =$N12+$O12 | Q12: =IFERROR(INDEX(спр_Работы!$J$2:$J$6000,MATCH($C12,спр_Работы!$A$2:$A$6000,0)),"") | R12: да | T12: =IF(AND($P12>0,$R12="да"),MAX($T$1:$T11)+1,"")
A13: =IFERROR(INDEX(спр_Работы!$D$2:$D$6000,MATCH($C13,спр_Работы!$A$2:$A$6000,0)),"") | B13: =IFERROR(INDEX(спр_Работы!$F$2:$F$6000,MATCH($C13,спр_Работы!$A$2:$A$6000,0)),"") | C13: =IFERROR(INDEX(спр_Работы!$A$2:$A$6000,12),"") | D13: =IFERROR(INDEX(спр_Работы!$B$2:$B$6000,MATCH($C13,спр_Работы!$A$2:$A$6000,0)),"") | E13: =IFERROR(INDEX(спр_Работы!$C$2:$C$6000,MATCH($C13,спр_Работы!$A$2:$A$6000,0)),"") | F13: =IFERROR(INDEX(спр_Работы!$G$2:$G$6000,MATCH($C13,спр_Работы!$A$2:$A$6000,0)),"") | G13: =IFERROR(INDEX(спр_Работы!$K$2:$K$6000,MATCH($C13,спр_Работы!$A$2:$A$6000,0)),"") | J13: =IFERROR(INDEX(спр_Материалы!$B$2:$B$9000,MATCH($I13,спр_Материалы!$A$2:$A$9000,0)),"") | K13: =IF($I13="","",IF($F13=IFERROR(INDEX(спр_Материалы!$G$2:$G$9000,MATCH($I13,спр_Материалы!$A$2:$A$9000,0)),""),"OK","!! не та группа")) | L13: =IFERROR(INDEX(спр_Работы!$H$2:$H$6000,MATCH($C13,спр_Работы!$A$2:$A$6000,0))*(1-ДисконтТендер),0) | M13: =IF($I13="",0,IFERROR(INDEX(спр_Материалы!$I$2:$I$9000,MATCH($I13,спр_Материалы!$A$2:$A$9000,0))*IF(INDEX(спр_Материалы!$J$2:$J$9000,MATCH($I13,спр_Материалы!$A$2:$A$9000,0))="USD",КурсUSD,IF(INDEX(спр_Материалы!$J$2:$J$9000,MATCH($I13,спр_Материалы!$A$2:$A$9000,0))="EUR",КурсEUR,1))*INDEX(спр_Материалы!$K$2:$K$9000,MATCH($I13,спр_Материалы!$A$2:$A$9000,0))*(1+IFERROR(INDEX(спр_Работы!$I$2:$I$6000,MATCH($C13,спр_Работы!$A$2:$A$6000,0))/100,0))*(1-ДисконтТендер),0)) | N13: =IF(AND($R13="да",$H13<>""),ROUND($H13*$L13,2),0) | O13: =IF(AND($R13="да",$H13<>""),ROUND($H13*$M13,2),0) | P13: =$N13+$O13 | Q13: =IFERROR(INDEX(спр_Работы!$J$2:$J$6000,MATCH($C13,спр_Работы!$A$2:$A$6000,0)),"") | R13: да | T13: =IF(AND($P13>0,$R13="да"),MAX($T$1:$T12)+1,"")
A14: =IFERROR(INDEX(спр_Работы!$D$2:$D$6000,MATCH($C14,спр_Работы!$A$2:$A$6000,0)),"") | B14: =IFERROR(INDEX(спр_Работы!$F$2:$F$6000,MATCH($C14,спр_Работы!$A$2:$A$6000,0)),"") | C14: =IFERROR(INDEX(спр_Работы!$A$2:$A$6000,13),"") | D14: =IFERROR(INDEX(спр_Работы!$B$2:$B$6000,MATCH($C14,спр_Работы!$A$2:$A$6000,0)),"") | E14: =IFERROR(INDEX(спр_Работы!$C$2:$C$6000,MATCH($C14,спр_Работы!$A$2:$A$6000,0)),"") | F14: =IFERROR(INDEX(спр_Работы!$G$2:$G$6000,MATCH($C14,спр_Работы!$A$2:$A$6000,0)),"") | G14: =IFERROR(INDEX(спр_Работы!$K$2:$K$6000,MATCH($C14,спр_Работы!$A$2:$A$6000,0)),"") | J14: =IFERROR(INDEX(спр_Материалы!$B$2:$B$9000,MATCH($I14,спр_Материалы!$A$2:$A$9000,0)),"") | K14: =IF($I14="","",IF($F14=IFERROR(INDEX(спр_Материалы!$G$2:$G$9000,MATCH($I14,спр_Материалы!$A$2:$A$9000,0)),""),"OK","!! не та группа")) | L14: =IFERROR(INDEX(спр_Работы!$H$2:$H$6000,MATCH($C14,спр_Работы!$A$2:$A$6000,0))*(1-ДисконтТендер),0) | M14: =IF($I14="",0,IFERROR(INDEX(спр_Материалы!$I$2:$I$9000,MATCH($I14,спр_Материалы!$A$2:$A$9000,0))*IF(INDEX(спр_Материалы!$J$2:$J$9000,MATCH($I14,спр_Материалы!$A$2:$A$9000,0))="USD",КурсUSD,IF(INDEX(спр_Материалы!$J$2:$J$9000,MATCH($I14,спр_Материалы!$A$2:$A$9000,0))="EUR",КурсEUR,1))*INDEX(спр_Материалы!$K$2:$K$9000,MATCH($I14,спр_Материалы!$A$2:$A$9000,0))*(1+IFERROR(INDEX(спр_Работы!$I$2:$I$6000,MATCH($C14,спр_Работы!$A$2:$A$6000,0))/100,0))*(1-ДисконтТендер),0)) | N14: =IF(AND($R14="да",$H14<>""),ROUND($H14*$L14,2),0) | O14: =IF(AND($R14="да",$H14<>""),ROUND($H14*$M14,2),0) | P14: =$N14+$O14 | Q14: =IFERROR(INDEX(спр_Работы!$J$2:$J$6000,MATCH($C14,спр_Работы!$A$2:$A$6000,0)),"") | R14: да | T14: =IF(AND($P14>0,$R14="да"),MAX($T$1:$T13)+1,"")
A15: =IFERROR(INDEX(спр_Работы!$D$2:$D$6000,MATCH($C15,спр_Работы!$A$2:$A$6000,0)),"") | B15: =IFERROR(INDEX(спр_Работы!$F$2:$F$6000,MATCH($C15,спр_Работы!$A$2:$A$6000,0)),"") | C15: =IFERROR(INDEX(спр_Работы!$A$2:$A$6000,14),"") | D15: =IFERROR(INDEX(спр_Работы!$B$2:$B$6000,MATCH($C15,спр_Работы!$A$2:$A$6000,0)),"") | E15: =IFERROR(INDEX(спр_Работы!$C$2:$C$6000,MATCH($C15,спр_Работы!$A$2:$A$6000,0)),"") | F15: =IFERROR(INDEX(спр_Работы!$G$2:$G$6000,MATCH($C15,спр_Работы!$A$2:$A$6000,0)),"") | G15: =IFERROR(INDEX(спр_Работы!$K$2:$K$6000,MATCH($C15,спр_Работы!$A$2:$A$6000,0)),"") | J15: =IFERROR(INDEX(спр_Материалы!$B$2:$B$9000,MATCH($I15,спр_Материалы!$A$2:$A$9000,0)),"") | K15: =IF($I15="","",IF($F15=IFERROR(INDEX(спр_Материалы!$G$2:$G$9000,MATCH($I15,спр_Материалы!$A$2:$A$9000,0)),""),"OK","!! не та группа")) | L15: =IFERROR(INDEX(спр_Работы!$H$2:$H$6000,MATCH($C15,спр_Работы!$A$2:$A$6000,0))*(1-ДисконтТендер),0) | M15: =IF($I15="",0,IFERROR(INDEX(спр_Материалы!$I$2:$I$9000,MATCH($I15,спр_Материалы!$A$2:$A$9000,0))*IF(INDEX(спр_Материалы!$J$2:$J$9000,MATCH($I15,спр_Материалы!$A$2:$A$9000,0))="USD",КурсUSD,IF(INDEX(спр_Материалы!$J$2:$J$9000,MATCH($I15,спр_Материалы!$A$2:$A$9000,0))="EUR",КурсEUR,1))*INDEX(спр_Материалы!$K$2:$K$9000,MATCH($I15,спр_Материалы!$A$2:$A$9000,0))*(1+IFERROR(INDEX(спр_Работы!$I$2:$I$6000,MATCH($C15,спр_Работы!$A$2:$A$6000,0))/100,0))*(1-ДисконтТендер),0)) | N15: =IF(AND($R15="да",$H15<>""),ROUND($H15*$L15,2),0) | O15: =IF(AND($R15="да",$H15<>""),ROUND($H15*$M15,2),0) | P15: =$N15+$O15 | Q15: =IFERROR(INDEX(спр_Работы!$J$2:$J$6000,MATCH($C15,спр_Работы!$A$2:$A$6000,0)),"") | R15: да | T15: =IF(AND($P15>0,$R15="да"),MAX($T$1:$T14)+1,"")
A16: =IFERROR(INDEX(спр_Работы!$D$2:$D$6000,MATCH($C16,спр_Работы!$A$2:$A$6000,0)),"") | B16: =IFERROR(INDEX(спр_Работы!$F$2:$F$6000,MATCH($C16,спр_Работы!$A$2:$A$6000,0)),"") | C16: =IFERROR(INDEX(спр_Работы!$A$2:$A$6000,15),"") | D16: =IFERROR(INDEX(спр_Работы!$B$2:$B$6000,MATCH($C16,спр_Работы!$A$2:$A$6000,0)),"") | E16: =IFERROR(INDEX(спр_Работы!$C$2:$C$6000,MATCH($C16,спр_Работы!$A$2:$A$6000,0)),"") | F16: =IFERROR(INDEX(спр_Работы!$G$2:$G$6000,MATCH($C16,спр_Работы!$A$2:$A$6000,0)),"") | G16: =IFERROR(INDEX(спр_Работы!$K$2:$K$6000,MATCH($C16,спр_Работы!$A$2:$A$6000,0)),"") | J16: =IFERROR(INDEX(спр_Материалы!$B$2:$B$9000,MATCH($I16,спр_Материалы!$A$2:$A$9000,0)),"") | K16: =IF($I16="","",IF($F16=IFERROR(INDEX(спр_Материалы!$G$2:$G$9000,MATCH($I16,спр_Материалы!$A$2:$A$9000,0)),""),"OK","!! не та группа")) | L16: =IFERROR(INDEX(спр_Работы!$H$2:$H$6000,MATCH($C16,спр_Работы!$A$2:$A$6000,0))*(1-ДисконтТендер),0) | M16: =IF($I16="",0,IFERROR(INDEX(спр_Материалы!$I$2:$I$9000,MATCH($I16,спр_Материалы!$A$2:$A$9000,0))*IF(INDEX(спр_Материалы!$J$2:$J$9000,MATCH($I16,спр_Материалы!$A$2:$A$9000,0))="USD",КурсUSD,IF(INDEX(спр_Материалы!$J$2:$J$9000,MATCH($I16,спр_Материалы!$A$2:$A$9000,0))="EUR",КурсEUR,1))*INDEX(спр_Материалы!$K$2:$K$9000,MATCH($I16,спр_Материалы!$A$2:$A$9000,0))*(1+IFERROR(INDEX(спр_Работы!$I$2:$I$6000,MATCH($C16,спр_Работы!$A$2:$A$6000,0))/100,0))*(1-ДисконтТендер),0)) | N16: =IF(AND($R16="да",$H16<>""),ROUND($H16*$L16,2),0) | O16: =IF(AND($R16="да",$H16<>""),ROUND($H16*$M16,2),0) | P16: =$N16+$O16 | Q16: =IFERROR(INDEX(спр_Работы!$J$2:$J$6000,MATCH($C16,спр_Работы!$A$2:$A$6000,0)),"") | R16: да | T16: =IF(AND($P16>0,$R16="да"),MAX($T$1:$T15)+1,"")
A17: =IFERROR(INDEX(спр_Работы!$D$2:$D$6000,MATCH($C17,спр_Работы!$A$2:$A$6000,0)),"") | B17: =IFERROR(INDEX(спр_Работы!$F$2:$F$6000,MATCH($C17,спр_Работы!$A$2:$A$6000,0)),"") | C17: =IFERROR(INDEX(спр_Работы!$A$2:$A$6000,16),"") | D17: =IFERROR(INDEX(спр_Работы!$B$2:$B$6000,MATCH($C17,спр_Работы!$A$2:$A$6000,0)),"") | E17: =IFERROR(INDEX(спр_Работы!$C$2:$C$6000,MATCH($C17,спр_Работы!$A$2:$A$6000,0)),"") | F17: =IFERROR(INDEX(спр_Работы!$G$2:$G$6000,MATCH($C17,спр_Работы!$A$2:$A$6000,0)),"") | G17: =IFERROR(INDEX(спр_Работы!$K$2:$K$6000,MATCH($C17,спр_Работы!$A$2:$A$6000,0)),"") | J17: =IFERROR(INDEX(спр_Материалы!$B$2:$B$9000,MATCH($I17,спр_Материалы!$A$2:$A$9000,0)),"") | K17: =IF($I17="","",IF($F17=IFERROR(INDEX(спр_Материалы!$G$2:$G$9000,MATCH($I17,спр_Материалы!$A$2:$A$9000,0)),""),"OK","!! не та группа")) | L17: =IFERROR(INDEX(спр_Работы!$H$2:$H$6000,MATCH($C17,спр_Работы!$A$2:$A$6000,0))*(1-ДисконтТендер),0) | M17: =IF($I17="",0,IFERROR(INDEX(спр_Материалы!$I$2:$I$9000,MATCH($I17,спр_Материалы!$A$2:$A$9000,0))*IF(INDEX(спр_Материалы!$J$2:$J$9000,MATCH($I17,спр_Материалы!$A$2:$A$9000,0))="USD",КурсUSD,IF(INDEX(спр_Материалы!$J$2:$J$9000,MATCH($I17,спр_Материалы!$A$2:$A$9000,0))="EUR",КурсEUR,1))*INDEX(спр_Материалы!$K$2:$K$9000,MATCH($I17,спр_Материалы!$A$2:$A$9000,0))*(1+IFERROR(INDEX(спр_Работы!$I$2:$I$6000,MATCH($C17,спр_Работы!$A$2:$A$6000,0))/100,0))*(1-ДисконтТендер),0)) | N17: =IF(AND($R17="да",$H17<>""),ROUND($H17*$L17,2),0) | O17: =IF(AND($R17="да",$H17<>""),ROUND($H17*$M17,2),0) | P17: =$N17+$O17 | Q17: =IFERROR(INDEX(спр_Работы!$J$2:$J$6000,MATCH($C17,спр_Работы!$A$2:$A$6000,0)),"") | R17: да | T17: =IF(AND($P17>0,$R17="да"),MAX($T$1:$T16)+1,"")
A18: =IFERROR(INDEX(спр_Работы!$D$2:$D$6000,MATCH($C18,спр_Работы!$A$2:$A$6000,0)),"") | B18: =IFERROR(INDEX(спр_Работы!$F$2:$F$6000,MATCH($C18,спр_Работы!$A$2:$A$6000,0)),"") | C18: =IFERROR(INDEX(спр_Работы!$A$2:$A$6000,17),"") | D18: =IFERROR(INDEX(спр_Работы!$B$2:$B$6000,MATCH($C18,спр_Работы!$A$2:$A$6000,0)),"") | E18: =IFERROR(INDEX(спр_Работы!$C$2:$C$6000,MATCH($C18,спр_Работы!$A$2:$A$6000,0)),"") | F18: =IFERROR(INDEX(спр_Работы!$G$2:$G$6000,MATCH($C18,спр_Работы!$A$2:$A$6000,0)),"") | G18: =IFERROR(INDEX(спр_Работы!$K$2:$K$6000,MATCH($C18,спр_Работы!$A$2:$A$6000,0)),"") | J18: =IFERROR(INDEX(спр_Материалы!$B$2:$B$9000,MATCH($I18,спр_Материалы!$A$2:$A$9000,0)),"") | K18: =IF($I18="","",IF($F18=IFERROR(INDEX(спр_Материалы!$G$2:$G$9000,MATCH($I18,спр_Материалы!$A$2:$A$9000,0)),""),"OK","!! не та группа")) | L18: =IFERROR(INDEX(спр_Работы!$H$2:$H$6000,MATCH($C18,спр_Работы!$A$2:$A$6000,0))*(1-ДисконтТендер),0) | M18: =IF($I18="",0,IFERROR(INDEX(спр_Материалы!$I$2:$I$9000,MATCH($I18,спр_Материалы!$A$2:$A$9000,0))*IF(INDEX(спр_Материалы!$J$2:$J$9000,MATCH($I18,спр_Материалы!$A$2:$A$9000,0))="USD",КурсUSD,IF(INDEX(спр_Материалы!$J$2:$J$9000,MATCH($I18,спр_Материалы!$A$2:$A$9000,0))="EUR",КурсEUR,1))*INDEX(спр_Материалы!$K$2:$K$9000,MATCH($I18,спр_Материалы!$A$2:$A$9000,0))*(1+IFERROR(INDEX(спр_Работы!$I$2:$I$6000,MATCH($C18,спр_Работы!$A$2:$A$6000,0))/100,0))*(1-ДисконтТендер),0)) | N18: =IF(AND($R18="да",$H18<>""),ROUND($H18*$L18,2),0) | O18: =IF(AND($R18="да",$H18<>""),ROUND($H18*$M18,2),0) | P18: =$N18+$O18 | Q18: =IFERROR(INDEX(спр_Работы!$J$2:$J$6000,MATCH($C18,спр_Работы!$A$2:$A$6000,0)),"") | R18: да | T18: =IF(AND($P18>0,$R18="да"),MAX($T$1:$T17)+1,"")
A19: =IFERROR(INDEX(спр_Работы!$D$2:$D$6000,MATCH($C19,спр_Работы!$A$2:$A$6000,0)),"") | B19: =IFERROR(INDEX(спр_Работы!$F$2:$F$6000,MATCH($C19,спр_Работы!$A$2:$A$6000,0)),"") | C19: =IFERROR(INDEX(спр_Работы!$A$2:$A$6000,18),"") | D19: =IFERROR(INDEX(спр_Работы!$B$2:$B$6000,MATCH($C19,спр_Работы!$A$2:$A$6000,0)),"") | E19: =IFERROR(INDEX(спр_Работы!$C$2:$C$6000,MATCH($C19,спр_Работы!$A$2:$A$6000,0)),"") | F19: =IFERROR(INDEX(спр_Работы!$G$2:$G$6000,MATCH($C19,спр_Работы!$A$2:$A$6000,0)),"") | G19: =IFERROR(INDEX(спр_Работы!$K$2:$K$6000,MATCH($C19,спр_Работы!$A$2:$A$6000,0)),"") | J19: =IFERROR(INDEX(спр_Материалы!$B$2:$B$9000,MATCH($I19,спр_Материалы!$A$2:$A$9000,0)),"") | K19: =IF($I19="","",IF($F19=IFERROR(INDEX(спр_Материалы!$G$2:$G$9000,MATCH($I19,спр_Материалы!$A$2:$A$9000,0)),""),"OK","!! не та группа")) | L19: =IFERROR(INDEX(спр_Работы!$H$2:$H$6000,MATCH($C19,спр_Работы!$A$2:$A$6000,0))*(1-ДисконтТендер),0) | M19: =IF($I19="",0,IFERROR(INDEX(спр_Материалы!$I$2:$I$9000,MATCH($I19,спр_Материалы!$A$2:$A$9000,0))*IF(INDEX(спр_Материалы!$J$2:$J$9000,MATCH($I19,спр_Материалы!$A$2:$A$9000,0))="USD",КурсUSD,IF(INDEX(спр_Материалы!$J$2:$J$9000,MATCH($I19,спр_Материалы!$A$2:$A$9000,0))="EUR",КурсEUR,1))*INDEX(спр_Материалы!$K$2:$K$9000,MATCH($I19,спр_Материалы!$A$2:$A$9000,0))*(1+IFERROR(INDEX(спр_Работы!$I$2:$I$6000,MATCH($C19,спр_Работы!$A$2:$A$6000,0))/100,0))*(1-ДисконтТендер),0)) | N19: =IF(AND($R19="да",$H19<>""),ROUND($H19*$L19,2),0) | O19: =IF(AND($R19="да",$H19<>""),ROUND($H19*$M19,2),0) | P19: =$N19+$O19 | Q19: =IFERROR(INDEX(спр_Работы!$J$2:$J$6000,MATCH($C19,спр_Работы!$A$2:$A$6000,0)),"") | R19: да | T19: =IF(AND($P19>0,$R19="да"),MAX($T$1:$T18)+1,"")
A20: =IFERROR(INDEX(спр_Работы!$D$2:$D$6000,MATCH($C20,спр_Работы!$A$2:$A$6000,0)),"") | B20: =IFERROR(INDEX(спр_Работы!$F$2:$F$6000,MATCH($C20,спр_Работы!$A$2:$A$6000,0)),"") | C20: =IFERROR(INDEX(спр_Работы!$A$2:$A$6000,19),"") | D20: =IFERROR(INDEX(спр_Работы!$B$2:$B$6000,MATCH($C20,спр_Работы!$A$2:$A$6000,0)),"") | E20: =IFERROR(INDEX(спр_Работы!$C$2:$C$6000,MATCH($C20,спр_Работы!$A$2:$A$6000,0)),"") | F20: =IFERROR(INDEX(спр_Работы!$G$2:$G$6000,MATCH($C20,спр_Работы!$A$2:$A$6000,0)),"") | G20: =IFERROR(INDEX(спр_Работы!$K$2:$K$6000,MATCH($C20,спр_Работы!$A$2:$A$6000,0)),"") | J20: =IFERROR(INDEX(спр_Материалы!$B$2:$B$9000,MATCH($I20,спр_Материалы!$A$2:$A$9000,0)),"") | K20: =IF($I20="","",IF($F20=IFERROR(INDEX(спр_Материалы!$G$2:$G$9000,MATCH($I20,спр_Материалы!$A$2:$A$9000,0)),""),"OK","!! не та группа")) | L20: =IFERROR(INDEX(спр_Работы!$H$2:$H$6000,MATCH($C20,спр_Работы!$A$2:$A$6000,0))*(1-ДисконтТендер),0) | M20: =IF($I20="",0,IFERROR(INDEX(спр_Материалы!$I$2:$I$9000,MATCH($I20,спр_Материалы!$A$2:$A$9000,0))*IF(INDEX(спр_Материалы!$J$2:$J$9000,MATCH($I20,спр_Материалы!$A$2:$A$9000,0))="USD",КурсUSD,IF(INDEX(спр_Материалы!$J$2:$J$9000,MATCH($I20,спр_Материалы!$A$2:$A$9000,0))="EUR",КурсEUR,1))*INDEX(спр_Материалы!$K$2:$K$9000,MATCH($I20,спр_Материалы!$A$2:$A$9000,0))*(1+IFERROR(INDEX(спр_Работы!$I$2:$I$6000,MATCH($C20,спр_Работы!$A$2:$A$6000,0))/100,0))*(1-ДисконтТендер),0)) | N20: =IF(AND($R20="да",$H20<>""),ROUND($H20*$L20,2),0) | O20: =IF(AND($R20="да",$H20<>""),ROUND($H20*$M20,2),0) | P20: =$N20+$O20 | Q20: =IFERROR(INDEX(спр_Работы!$J$2:$J$6000,MATCH($C20,спр_Работы!$A$2:$A$6000,0)),"") | R20: да | T20: =IF(AND($P20>0,$R20="да"),MAX($T$1:$T19)+1,"")
A21: =IFERROR(INDEX(спр_Работы!$D$2:$D$6000,MATCH($C21,спр_Работы!$A$2:$A$6000,0)),"") | B21: =IFERROR(INDEX(спр_Работы!$F$2:$F$6000,MATCH($C21,спр_Работы!$A$2:$A$6000,0)),"") | C21: =IFERROR(INDEX(спр_Работы!$A$2:$A$6000,20),"") | D21: =IFERROR(INDEX(спр_Работы!$B$2:$B$6000,MATCH($C21,спр_Работы!$A$2:$A$6000,0)),"") | E21: =IFERROR(INDEX(спр_Работы!$C$2:$C$6000,MATCH($C21,спр_Работы!$A$2:$A$6000,0)),"") | F21: =IFERROR(INDEX(спр_Работы!$G$2:$G$6000,MATCH($C21,спр_Работы!$A$2:$A$6000,0)),"") | G21: =IFERROR(INDEX(спр_Работы!$K$2:$K$6000,MATCH($C21,спр_Работы!$A$2:$A$6000,0)),"") | J21: =IFERROR(INDEX(спр_Материалы!$B$2:$B$9000,MATCH($I21,спр_Материалы!$A$2:$A$9000,0)),"") | K21: =IF($I21="","",IF($F21=IFERROR(INDEX(спр_Материалы!$G$2:$G$9000,MATCH($I21,спр_Материалы!$A$2:$A$9000,0)),""),"OK","!! не та группа")) | L21: =IFERROR(INDEX(спр_Работы!$H$2:$H$6000,MATCH($C21,спр_Работы!$A$2:$A$6000,0))*(1-ДисконтТендер),0) | M21: =IF($I21="",0,IFERROR(INDEX(спр_Материалы!$I$2:$I$9000,MATCH($I21,спр_Материалы!$A$2:$A$9000,0))*IF(INDEX(спр_Материалы!$J$2:$J$9000,MATCH($I21,спр_Материалы!$A$2:$A$9000,0))="USD",КурсUSD,IF(INDEX(спр_Материалы!$J$2:$J$9000,MATCH($I21,спр_Материалы!$A$2:$A$9000,0))="EUR",КурсEUR,1))*INDEX(спр_Материалы!$K$2:$K$9000,MATCH($I21,спр_Материалы!$A$2:$A$9000,0))*(1+IFERROR(INDEX(спр_Работы!$I$2:$I$6000,MATCH($C21,спр_Работы!$A$2:$A$6000,0))/100,0))*(1-ДисконтТендер),0)) | N21: =IF(AND($R21="да",$H21<>""),ROUND($H21*$L21,2),0) | O21: =IF(AND($R21="да",$H21<>""),ROUND($H21*$M21,2),0) | P21: =$N21+$O21 | Q21: =IFERROR(INDEX(спр_Работы!$J$2:$J$6000,MATCH($C21,спр_Работы!$A$2:$A$6000,0)),"") | R21: да | T21: =IF(AND($P21>0,$R21="да"),MAX($T$1:$T20)+1,"")
A22: =IFERROR(INDEX(спр_Работы!$D$2:$D$6000,MATCH($C22,спр_Работы!$A$2:$A$6000,0)),"") | B22: =IFERROR(INDEX(спр_Работы!$F$2:$F$6000,MATCH($C22,спр_Работы!$A$2:$A$6000,0)),"") | C22: =IFERROR(INDEX(спр_Работы!$A$2:$A$6000,21),"") | D22: =IFERROR(INDEX(спр_Работы!$B$2:$B$6000,MATCH($C22,спр_Работы!$A$2:$A$6000,0)),"") | E22: =IFERROR(INDEX(спр_Работы!$C$2:$C$6000,MATCH($C22,спр_Работы!$A$2:$A$6000,0)),"") | F22: =IFERROR(INDEX(спр_Работы!$G$2:$G$6000,MATCH($C22,спр_Работы!$A$2:$A$6000,0)),"") | G22: =IFERROR(INDEX(спр_Работы!$K$2:$K$6000,MATCH($C22,спр_Работы!$A$2:$A$6000,0)),"") | J22: =IFERROR(INDEX(спр_Материалы!$B$2:$B$9000,MATCH($I22,спр_Материалы!$A$2:$A$9000,0)),"") | K22: =IF($I22="","",IF($F22=IFERROR(INDEX(спр_Материалы!$G$2:$G$9000,MATCH($I22,спр_Материалы!$A$2:$A$9000,0)),""),"OK","!! не та группа")) | L22: =IFERROR(INDEX(спр_Работы!$H$2:$H$6000,MATCH($C22,спр_Работы!$A$2:$A$6000,0))*(1-ДисконтТендер),0) | M22: =IF($I22="",0,IFERROR(INDEX(спр_Материалы!$I$2:$I$9000,MATCH($I22,спр_Материалы!$A$2:$A$9000,0))*IF(INDEX(спр_Материалы!$J$2:$J$9000,MATCH($I22,спр_Материалы!$A$2:$A$9000,0))="USD",КурсUSD,IF(INDEX(спр_Материалы!$J$2:$J$9000,MATCH($I22,спр_Материалы!$A$2:$A$9000,0))="EUR",КурсEUR,1))*INDEX(спр_Материалы!$K$2:$K$9000,MATCH($I22,спр_Материалы!$A$2:$A$9000,0))*(1+IFERROR(INDEX(спр_Работы!$I$2:$I$6000,MATCH($C22,спр_Работы!$A$2:$A$6000,0))/100,0))*(1-ДисконтТендер),0)) | N22: =IF(AND($R22="да",$H22<>""),ROUND($H22*$L22,2),0) | O22: =IF(AND($R22="да",$H22<>""),ROUND($H22*$M22,2),0) | P22: =$N22+$O22 | Q22: =IFERROR(INDEX(спр_Работы!$J$2:$J$6000,MATCH($C22,спр_Работы!$A$2:$A$6000,0)),"") | R22: да | T22: =IF(AND($P22>0,$R22="да"),MAX($T$1:$T21)+1,"")
A23: =IFERROR(INDEX(спр_Работы!$D$2:$D$6000,MATCH($C23,спр_Работы!$A$2:$A$6000,0)),"") | B23: =IFERROR(INDEX(спр_Работы!$F$2:$F$6000,MATCH($C23,спр_Работы!$A$2:$A$6000,0)),"") | C23: =IFERROR(INDEX(спр_Работы!$A$2:$A$6000,22),"") | D23: =IFERROR(INDEX(спр_Работы!$B$2:$B$6000,MATCH($C23,спр_Работы!$A$2:$A$6000,0)),"") | E23: =IFERROR(INDEX(спр_Работы!$C$2:$C$6000,MATCH($C23,спр_Работы!$A$2:$A$6000,0)),"") | F23: =IFERROR(INDEX(спр_Работы!$G$2:$G$6000,MATCH($C23,спр_Работы!$A$2:$A$6000,0)),"") | G23: =IFERROR(INDEX(спр_Работы!$K$2:$K$6000,MATCH($C23,спр_Работы!$A$2:$A$6000,0)),"") | J23: =IFERROR(INDEX(спр_Материалы!$B$2:$B$9000,MATCH($I23,спр_Материалы!$A$2:$A$9000,0)),"") | K23: =IF($I23="","",IF($F23=IFERROR(INDEX(спр_Материалы!$G$2:$G$9000,MATCH($I23,спр_Материалы!$A$2:$A$9000,0)),""),"OK","!! не та группа")) | L23: =IFERROR(INDEX(спр_Работы!$H$2:$H$6000,MATCH($C23,спр_Работы!$A$2:$A$6000,0))*(1-ДисконтТендер),0) | M23: =IF($I23="",0,IFERROR(INDEX(спр_Материалы!$I$2:$I$9000,MATCH($I23,спр_Материалы!$A$2:$A$9000,0))*IF(INDEX(спр_Материалы!$J$2:$J$9000,MATCH($I23,спр_Материалы!$A$2:$A$9000,0))="USD",КурсUSD,IF(INDEX(спр_Материалы!$J$2:$J$9000,MATCH($I23,спр_Материалы!$A$2:$A$9000,0))="EUR",КурсEUR,1))*INDEX(спр_Материалы!$K$2:$K$9000,MATCH($I23,спр_Материалы!$A$2:$A$9000,0))*(1+IFERROR(INDEX(спр_Работы!$I$2:$I$6000,MATCH($C23,спр_Работы!$A$2:$A$6000,0))/100,0))*(1-ДисконтТендер),0)) | N23: =IF(AND($R23="да",$H23<>""),ROUND($H23*$L23,2),0) | O23: =IF(AND($R23="да",$H23<>""),ROUND($H23*$M23,2),0) | P23: =$N23+$O23 | Q23: =IFERROR(INDEX(спр_Работы!$J$2:$J$6000,MATCH($C23,спр_Работы!$A$2:$A$6000,0)),"") | R23: да | T23: =IF(AND($P23>0,$R23="да"),MAX($T$1:$T22)+1,"")
A24: =IFERROR(INDEX(спр_Работы!$D$2:$D$6000,MATCH($C24,спр_Работы!$A$2:$A$6000,0)),"") | B24: =IFERROR(INDEX(спр_Работы!$F$2:$F$6000,MATCH($C24,спр_Работы!$A$2:$A$6000,0)),"") | C24: =IFERROR(INDEX(спр_Работы!$A$2:$A$6000,23),"") | D24: =IFERROR(INDEX(спр_Работы!$B$2:$B$6000,MATCH($C24,спр_Работы!$A$2:$A$6000,0)),"") | E24: =IFERROR(INDEX(спр_Работы!$C$2:$C$6000,MATCH($C24,спр_Работы!$A$2:$A$6000,0)),"") | F24: =IFERROR(INDEX(спр_Работы!$G$2:$G$6000,MATCH($C24,спр_Работы!$A$2:$A$6000,0)),"") | G24: =IFERROR(INDEX(спр_Работы!$K$2:$K$6000,MATCH($C24,спр_Работы!$A$2:$A$6000,0)),"") | J24: =IFERROR(INDEX(спр_Материалы!$B$2:$B$9000,MATCH($I24,спр_Материалы!$A$2:$A$9000,0)),"") | K24: =IF($I24="","",IF($F24=IFERROR(INDEX(спр_Материалы!$G$2:$G$9000,MATCH($I24,спр_Материалы!$A$2:$A$9000,0)),""),"OK","!! не та группа")) | L24: =IFERROR(INDEX(спр_Работы!$H$2:$H$6000,MATCH($C24,спр_Работы!$A$2:$A$6000,0))*(1-ДисконтТендер),0) | M24: =IF($I24="",0,IFERROR(INDEX(спр_Материалы!$I$2:$I$9000,MATCH($I24,спр_Материалы!$A$2:$A$9000,0))*IF(INDEX(спр_Материалы!$J$2:$J$9000,MATCH($I24,спр_Материалы!$A$2:$A$9000,0))="USD",КурсUSD,IF(INDEX(спр_Материалы!$J$2:$J$9000,MATCH($I24,спр_Материалы!$A$2:$A$9000,0))="EUR",КурсEUR,1))*INDEX(спр_Материалы!$K$2:$K$9000,MATCH($I24,спр_Материалы!$A$2:$A$9000,0))*(1+IFERROR(INDEX(спр_Работы!$I$2:$I$6000,MATCH($C24,спр_Работы!$A$2:$A$6000,0))/100,0))*(1-ДисконтТендер),0)) | N24: =IF(AND($R24="да",$H24<>""),ROUND($H24*$L24,2),0) | O24: =IF(AND($R24="да",$H24<>""),ROUND($H24*$M24,2),0) | P24: =$N24+$O24 | Q24: =IFERROR(INDEX(спр_Работы!$J$2:$J$6000,MATCH($C24,спр_Работы!$A$2:$A$6000,0)),"") | R24: да | T24: =IF(AND($P24>0,$R24="да"),MAX($T$1:$T23)+1,"")
A25: =IFERROR(INDEX(спр_Работы!$D$2:$D$6000,MATCH($C25,спр_Работы!$A$2:$A$6000,0)),"") | B25: =IFERROR(INDEX(спр_Работы!$F$2:$F$6000,MATCH($C25,спр_Работы!$A$2:$A$6000,0)),"") | C25: =IFERROR(INDEX(спр_Работы!$A$2:$A$6000,24),"") | D25: =IFERROR(INDEX(спр_Работы!$B$2:$B$6000,MATCH($C25,спр_Работы!$A$2:$A$6000,0)),"") | E25: =IFERROR(INDEX(спр_Работы!$C$2:$C$6000,MATCH($C25,спр_Работы!$A$2:$A$6000,0)),"") | F25: =IFERROR(INDEX(спр_Работы!$G$2:$G$6000,MATCH($C25,спр_Работы!$A$2:$A$6000,0)),"") | G25: =IFERROR(INDEX(спр_Работы!$K$2:$K$6000,MATCH($C25,спр_Работы!$A$2:$A$6000,0)),"") | J25: =IFERROR(INDEX(спр_Материалы!$B$2:$B$9000,MATCH($I25,спр_Материалы!$A$2:$A$9000,0)),"") | K25: =IF($I25="","",IF($F25=IFERROR(INDEX(спр_Материалы!$G$2:$G$9000,MATCH($I25,спр_Материалы!$A$2:$A$9000,0)),""),"OK","!! не та группа")) | L25: =IFERROR(INDEX(спр_Работы!$H$2:$H$6000,MATCH($C25,спр_Работы!$A$2:$A$6000,0))*(1-ДисконтТендер),0) | M25: =IF($I25="",0,IFERROR(INDEX(спр_Материалы!$I$2:$I$9000,MATCH($I25,спр_Материалы!$A$2:$A$9000,0))*IF(INDEX(спр_Материалы!$J$2:$J$9000,MATCH($I25,спр_Материалы!$A$2:$A$9000,0))="USD",КурсUSD,IF(INDEX(спр_Материалы!$J$2:$J$9000,MATCH($I25,спр_Материалы!$A$2:$A$9000,0))="EUR",КурсEUR,1))*INDEX(спр_Материалы!$K$2:$K$9000,MATCH($I25,спр_Материалы!$A$2:$A$9000,0))*(1+IFERROR(INDEX(спр_Работы!$I$2:$I$6000,MATCH($C25,спр_Работы!$A$2:$A$6000,0))/100,0))*(1-ДисконтТендер),0)) | N25: =IF(AND($R25="да",$H25<>""),ROUND($H25*$L25,2),0) | O25: =IF(AND($R25="да",$H25<>""),ROUND($H25*$M25,2),0) | P25: =$N25+$O25 | Q25: =IFERROR(INDEX(спр_Работы!$J$2:$J$6000,MATCH($C25,спр_Работы!$A$2:$A$6000,0)),"") | R25: да | T25: =IF(AND($P25>0,$R25="да"),MAX($T$1:$T24)+1,"")
A26: =IFERROR(INDEX(спр_Работы!$D$2:$D$6000,MATCH($C26,спр_Работы!$A$2:$A$6000,0)),"") | B26: =IFERROR(INDEX(спр_Работы!$F$2:$F$6000,MATCH($C26,спр_Работы!$A$2:$A$6000,0)),"") | C26: =IFERROR(INDEX(спр_Работы!$A$2:$A$6000,25),"") | D26: =IFERROR(INDEX(спр_Работы!$B$2:$B$6000,MATCH($C26,спр_Работы!$A$2:$A$6000,0)),"") | E26: =IFERROR(INDEX(спр_Работы!$C$2:$C$6000,MATCH($C26,спр_Работы!$A$2:$A$6000,0)),"") | F26: =IFERROR(INDEX(спр_Работы!$G$2:$G$6000,MATCH($C26,спр_Работы!$A$2:$A$6000,0)),"") | G26: =IFERROR(INDEX(спр_Работы!$K$2:$K$6000,MATCH($C26,спр_Работы!$A$2:$A$6000,0)),"") | J26: =IFERROR(INDEX(спр_Материалы!$B$2:$B$9000,MATCH($I26,спр_Материалы!$A$2:$A$9000,0)),"") | K26: =IF($I26="","",IF($F26=IFERROR(INDEX(спр_Материалы!$G$2:$G$9000,MATCH($I26,спр_Материалы!$A$2:$A$9000,0)),""),"OK","!! не та группа")) | L26: =IFERROR(INDEX(спр_Работы!$H$2:$H$6000,MATCH($C26,спр_Работы!$A$2:$A$6000,0))*(1-ДисконтТендер),0) | M26: =IF($I26="",0,IFERROR(INDEX(спр_Материалы!$I$2:$I$9000,MATCH($I26,спр_Материалы!$A$2:$A$9000,0))*IF(INDEX(спр_Материалы!$J$2:$J$9000,MATCH($I26,спр_Материалы!$A$2:$A$9000,0))="USD",КурсUSD,IF(INDEX(спр_Материалы!$J$2:$J$9000,MATCH($I26,спр_Материалы!$A$2:$A$9000,0))="EUR",КурсEUR,1))*INDEX(спр_Материалы!$K$2:$K$9000,MATCH($I26,спр_Материалы!$A$2:$A$9000,0))*(1+IFERROR(INDEX(спр_Работы!$I$2:$I$6000,MATCH($C26,спр_Работы!$A$2:$A$6000,0))/100,0))*(1-ДисконтТендер),0)) | N26: =IF(AND($R26="да",$H26<>""),ROUND($H26*$L26,2),0) | O26: =IF(AND($R26="да",$H26<>""),ROUND($H26*$M26,2),0) | P26: =$N26+$O26 | Q26: =IFERROR(INDEX(спр_Работы!$J$2:$J$6000,MATCH($C26,спр_Работы!$A$2:$A$6000,0)),"") | R26: да | T26: =IF(AND($P26>0,$R26="да"),MAX($T$1:$T25)+1,"")
A27: =IFERROR(INDEX(спр_Работы!$D$2:$D$6000,MATCH($C27,спр_Работы!$A$2:$A$6000,0)),"") | B27: =IFERROR(INDEX(спр_Работы!$F$2:$F$6000,MATCH($C27,спр_Работы!$A$2:$A$6000,0)),"") | C27: =IFERROR(INDEX(спр_Работы!$A$2:$A$6000,26),"") | D27: =IFERROR(INDEX(спр_Работы!$B$2:$B$6000,MATCH($C27,спр_Работы!$A$2:$A$6000,0)),"") | E27: =IFERROR(INDEX(спр_Работы!$C$2:$C$6000,MATCH($C27,спр_Работы!$A$2:$A$6000,0)),"") | F27: =IFERROR(INDEX(спр_Работы!$G$2:$G$6000,MATCH($C27,спр_Работы!$A$2:$A$6000,0)),"") | G27: =IFERROR(INDEX(спр_Работы!$K$2:$K$6000,MATCH($C27,спр_Работы!$A$2:$A$6000,0)),"") | J27: =IFERROR(INDEX(спр_Материалы!$B$2:$B$9000,MATCH($I27,спр_Материалы!$A$2:$A$9000,0)),"") | K27: =IF($I27="","",IF($F27=IFERROR(INDEX(спр_Материалы!$G$2:$G$9000,MATCH($I27,спр_Материалы!$A$2:$A$9000,0)),""),"OK","!! не та группа")) | L27: =IFERROR(INDEX(спр_Работы!$H$2:$H$6000,MATCH($C27,спр_Работы!$A$2:$A$6000,0))*(1-ДисконтТендер),0) | M27: =IF($I27="",0,IFERROR(INDEX(спр_Материалы!$I$2:$I$9000,MATCH($I27,спр_Материалы!$A$2:$A$9000,0))*IF(INDEX(спр_Материалы!$J$2:$J$9000,MATCH($I27,спр_Материалы!$A$2:$A$9000,0))="USD",КурсUSD,IF(INDEX(спр_Материалы!$J$2:$J$9000,MATCH($I27,спр_Материалы!$A$2:$A$9000,0))="EUR",КурсEUR,1))*INDEX(спр_Материалы!$K$2:$K$9000,MATCH($I27,спр_Материалы!$A$2:$A$9000,0))*(1+IFERROR(INDEX(спр_Работы!$I$2:$I$6000,MATCH($C27,спр_Работы!$A$2:$A$6000,0))/100,0))*(1-ДисконтТендер),0)) | N27: =IF(AND($R27="да",$H27<>""),ROUND($H27*$L27,2),0) | O27: =IF(AND($R27="да",$H27<>""),ROUND($H27*$M27,2),0) | P27: =$N27+$O27 | Q27: =IFERROR(INDEX(спр_Работы!$J$2:$J$6000,MATCH($C27,спр_Работы!$A$2:$A$6000,0)),"") | R27: да | T27: =IF(AND($P27>0,$R27="да"),MAX($T$1:$T26)+1,"")
A28: =IFERROR(INDEX(спр_Работы!$D$2:$D$6000,MATCH($C28,спр_Работы!$A$2:$A$6000,0)),"") | B28: =IFERROR(INDEX(спр_Работы!$F$2:$F$6000,MATCH($C28,спр_Работы!$A$2:$A$6000,0)),"") | C28: =IFERROR(INDEX(спр_Работы!$A$2:$A$6000,27),"") | D28: =IFERROR(INDEX(спр_Работы!$B$2:$B$6000,MATCH($C28,спр_Работы!$A$2:$A$6000,0)),"") | E28: =IFERROR(INDEX(спр_Работы!$C$2:$C$6000,MATCH($C28,спр_Работы!$A$2:$A$6000,0)),"") | F28: =IFERROR(INDEX(спр_Работы!$G$2:$G$6000,MATCH($C28,спр_Работы!$A$2:$A$6000,0)),"") | G28: =IFERROR(INDEX(спр_Работы!$K$2:$K$6000,MATCH($C28,спр_Работы!$A$2:$A$6000,0)),"") | J28: =IFERROR(INDEX(спр_Материалы!$B$2:$B$9000,MATCH($I28,спр_Материалы!$A$2:$A$9000,0)),"") | K28: =IF($I28="","",IF($F28=IFERROR(INDEX(спр_Материалы!$G$2:$G$9000,MATCH($I28,спр_Материалы!$A$2:$A$9000,0)),""),"OK","!! не та группа")) | L28: =IFERROR(INDEX(спр_Работы!$H$2:$H$6000,MATCH($C28,спр_Работы!$A$2:$A$6000,0))*(1-ДисконтТендер),0) | M28: =IF($I28="",0,IFERROR(INDEX(спр_Материалы!$I$2:$I$9000,MATCH($I28,спр_Материалы!$A$2:$A$9000,0))*IF(INDEX(спр_Материалы!$J$2:$J$9000,MATCH($I28,спр_Материалы!$A$2:$A$9000,0))="USD",КурсUSD,IF(INDEX(спр_Материалы!$J$2:$J$9000,MATCH($I28,спр_Материалы!$A$2:$A$9000,0))="EUR",КурсEUR,1))*INDEX(спр_Материалы!$K$2:$K$9000,MATCH($I28,спр_Материалы!$A$2:$A$9000,0))*(1+IFERROR(INDEX(спр_Работы!$I$2:$I$6000,MATCH($C28,спр_Работы!$A$2:$A$6000,0))/100,0))*(1-ДисконтТендер),0)) | N28: =IF(AND($R28="да",$H28<>""),ROUND($H28*$L28,2),0) | O28: =IF(AND($R28="да",$H28<>""),ROUND($H28*$M28,2),0) | P28: =$N28+$O28 | Q28: =IFERROR(INDEX(спр_Работы!$J$2:$J$6000,MATCH($C28,спр_Работы!$A$2:$A$6000,0)),"") | R28: да | T28: =IF(AND($P28>0,$R28="да"),MAX($T$1:$T27)+1,"")
A29: =IFERROR(INDEX(спр_Работы!$D$2:$D$6000,MATCH($C29,спр_Работы!$A$2:$A$6000,0)),"") | B29: =IFERROR(INDEX(спр_Работы!$F$2:$F$6000,MATCH($C29,спр_Работы!$A$2:$A$6000,0)),"") | C29: =IFERROR(INDEX(спр_Работы!$A$2:$A$6000,28),"") | D29: =IFERROR(INDEX(спр_Работы!$B$2:$B$6000,MATCH($C29,спр_Работы!$A$2:$A$6000,0)),"") | E29: =IFERROR(INDEX(спр_Работы!$C$2:$C$6000,MATCH($C29,спр_Работы!$A$2:$A$6000,0)),"") | F29: =IFERROR(INDEX(спр_Работы!$G$2:$G$6000,MATCH($C29,спр_Работы!$A$2:$A$6000,0)),"") | G29: =IFERROR(INDEX(спр_Работы!$K$2:$K$6000,MATCH($C29,спр_Работы!$A$2:$A$6000,0)),"") | J29: =IFERROR(INDEX(спр_Материалы!$B$2:$B$9000,MATCH($I29,спр_Материалы!$A$2:$A$9000,0)),"") | K29: =IF($I29="","",IF($F29=IFERROR(INDEX(спр_Материалы!$G$2:$G$9000,MATCH($I29,спр_Материалы!$A$2:$A$9000,0)),""),"OK","!! не та группа")) | L29: =IFERROR(INDEX(спр_Работы!$H$2:$H$6000,MATCH($C29,спр_Работы!$A$2:$A$6000,0))*(1-ДисконтТендер),0) | M29: =IF($I29="",0,IFERROR(INDEX(спр_Материалы!$I$2:$I$9000,MATCH($I29,спр_Материалы!$A$2:$A$9000,0))*IF(INDEX(спр_Материалы!$J$2:$J$9000,MATCH($I29,спр_Материалы!$A$2:$A$9000,0))="USD",КурсUSD,IF(INDEX(спр_Материалы!$J$2:$J$9000,MATCH($I29,спр_Материалы!$A$2:$A$9000,0))="EUR",КурсEUR,1))*INDEX(спр_Материалы!$K$2:$K$9000,MATCH($I29,спр_Материалы!$A$2:$A$9000,0))*(1+IFERROR(INDEX(спр_Работы!$I$2:$I$6000,MATCH($C29,спр_Работы!$A$2:$A$6000,0))/100,0))*(1-ДисконтТендер),0)) | N29: =IF(AND($R29="да",$H29<>""),ROUND($H29*$L29,2),0) | O29: =IF(AND($R29="да",$H29<>""),ROUND($H29*$M29,2),0) | P29: =$N29+$O29 | Q29: =IFERROR(INDEX(спр_Работы!$J$2:$J$6000,MATCH($C29,спр_Работы!$A$2:$A$6000,0)),"") | R29: да | T29: =IF(AND($P29>0,$R29="да"),MAX($T$1:$T28)+1,"")
A30: =IFERROR(INDEX(спр_Работы!$D$2:$D$6000,MATCH($C30,спр_Работы!$A$2:$A$6000,0)),"") | B30: =IFERROR(INDEX(спр_Работы!$F$2:$F$6000,MATCH($C30,спр_Работы!$A$2:$A$6000,0)),"") | C30: =IFERROR(INDEX(спр_Работы!$A$2:$A$6000,29),"") | D30: =IFERROR(INDEX(спр_Работы!$B$2:$B$6000,MATCH($C30,спр_Работы!$A$2:$A$6000,0)),"") | E30: =IFERROR(INDEX(спр_Работы!$C$2:$C$6000,MATCH($C30,спр_Работы!$A$2:$A$6000,0)),"") | F30: =IFERROR(INDEX(спр_Работы!$G$2:$G$6000,MATCH($C30,спр_Работы!$A$2:$A$6000,0)),"") | G30: =IFERROR(INDEX(спр_Работы!$K$2:$K$6000,MATCH($C30,спр_Работы!$A$2:$A$6000,0)),"") | J30: =IFERROR(INDEX(спр_Материалы!$B$2:$B$9000,MATCH($I30,спр_Материалы!$A$2:$A$9000,0)),"") | K30: =IF($I30="","",IF($F30=IFERROR(INDEX(спр_Материалы!$G$2:$G$9000,MATCH($I30,спр_Материалы!$A$2:$A$9000,0)),""),"OK","!! не та группа")) | L30: =IFERROR(INDEX(спр_Работы!$H$2:$H$6000,MATCH($C30,спр_Работы!$A$2:$A$6000,0))*(1-ДисконтТендер),0) | M30: =IF($I30="",0,IFERROR(INDEX(спр_Материалы!$I$2:$I$9000,MATCH($I30,спр_Материалы!$A$2:$A$9000,0))*IF(INDEX(спр_Материалы!$J$2:$J$9000,MATCH($I30,спр_Материалы!$A$2:$A$9000,0))="USD",КурсUSD,IF(INDEX(спр_Материалы!$J$2:$J$9000,MATCH($I30,спр_Материалы!$A$2:$A$9000,0))="EUR",КурсEUR,1))*INDEX(спр_Материалы!$K$2:$K$9000,MATCH($I30,спр_Материалы!$A$2:$A$9000,0))*(1+IFERROR(INDEX(спр_Работы!$I$2:$I$6000,MATCH($C30,спр_Работы!$A$2:$A$6000,0))/100,0))*(1-ДисконтТендер),0)) | N30: =IF(AND($R30="да",$H30<>""),ROUND($H30*$L30,2),0) | O30: =IF(AND($R30="да",$H30<>""),ROUND($H30*$M30,2),0) | P30: =$N30+$O30 | Q30: =IFERROR(INDEX(спр_Работы!$J$2:$J$6000,MATCH($C30,спр_Работы!$A$2:$A$6000,0)),"") | R30: да | T30: =IF(AND($P30>0,$R30="да"),MAX($T$1:$T29)+1,"")
A31: =IFERROR(INDEX(спр_Работы!$D$2:$D$6000,MATCH($C31,спр_Работы!$A$2:$A$6000,0)),"") | B31: =IFERROR(INDEX(спр_Работы!$F$2:$F$6000,MATCH($C31,спр_Работы!$A$2:$A$6000,0)),"") | C31: =IFERROR(INDEX(спр_Работы!$A$2:$A$6000,30),"") | D31: =IFERROR(INDEX(спр_Работы!$B$2:$B$6000,MATCH($C31,спр_Работы!$A$2:$A$6000,0)),"") | E31: =IFERROR(INDEX(спр_Работы!$C$2:$C$6000,MATCH($C31,спр_Работы!$A$2:$A$6000,0)),"") | F31: =IFERROR(INDEX(спр_Работы!$G$2:$G$6000,MATCH($C31,спр_Работы!$A$2:$A$6000,0)),"") | G31: =IFERROR(INDEX(спр_Работы!$K$2:$K$6000,MATCH($C31,спр_Работы!$A$2:$A$6000,0)),"") | J31: =IFERROR(INDEX(спр_Материалы!$B$2:$B$9000,MATCH($I31,спр_Материалы!$A$2:$A$9000,0)),"") | K31: =IF($I31="","",IF($F31=IFERROR(INDEX(спр_Материалы!$G$2:$G$9000,MATCH($I31,спр_Материалы!$A$2:$A$9000,0)),""),"OK","!! не та группа")) | L31: =IFERROR(INDEX(спр_Работы!$H$2:$H$6000,MATCH($C31,спр_Работы!$A$2:$A$6000,0))*(1-ДисконтТендер),0) | M31: =IF($I31="",0,IFERROR(INDEX(спр_Материалы!$I$2:$I$9000,MATCH($I31,спр_Материалы!$A$2:$A$9000,0))*IF(INDEX(спр_Материалы!$J$2:$J$9000,MATCH($I31,спр_Материалы!$A$2:$A$9000,0))="USD",КурсUSD,IF(INDEX(спр_Материалы!$J$2:$J$9000,MATCH($I31,спр_Материалы!$A$2:$A$9000,0))="EUR",КурсEUR,1))*INDEX(спр_Материалы!$K$2:$K$9000,MATCH($I31,спр_Материалы!$A$2:$A$9000,0))*(1+IFERROR(INDEX(спр_Работы!$I$2:$I$6000,MATCH($C31,спр_Работы!$A$2:$A$6000,0))/100,0))*(1-ДисконтТендер),0)) | N31: =IF(AND($R31="да",$H31<>""),ROUND($H31*$L31,2),0) | O31: =IF(AND($R31="да",$H31<>""),ROUND($H31*$M31,2),0) | P31: =$N31+$O31 | Q31: =IFERROR(INDEX(спр_Работы!$J$2:$J$6000,MATCH($C31,спр_Работы!$A$2:$A$6000,0)),"") | R31: да | T31: =IF(AND($P31>0,$R31="да"),MAX($T$1:$T30)+1,"")
A32: =IFERROR(INDEX(спр_Работы!$D$2:$D$6000,MATCH($C32,спр_Работы!$A$2:$A$6000,0)),"") | B32: =IFERROR(INDEX(спр_Работы!$F$2:$F$6000,MATCH($C32,спр_Работы!$A$2:$A$6000,0)),"") | C32: =IFERROR(INDEX(спр_Работы!$A$2:$A$6000,31),"") | D32: =IFERROR(INDEX(спр_Работы!$B$2:$B$6000,MATCH($C32,спр_Работы!$A$2:$A$6000,0)),"") | E32: =IFERROR(INDEX(спр_Работы!$C$2:$C$6000,MATCH($C32,спр_Работы!$A$2:$A$6000,0)),"") | F32: =IFERROR(INDEX(спр_Работы!$G$2:$G$6000,MATCH($C32,спр_Работы!$A$2:$A$6000,0)),"") | G32: =IFERROR(INDEX(спр_Работы!$K$2:$K$6000,MATCH($C32,спр_Работы!$A$2:$A$6000,0)),"") | J32: =IFERROR(INDEX(спр_Материалы!$B$2:$B$9000,MATCH($I32,спр_Материалы!$A$2:$A$9000,0)),"") | K32: =IF($I32="","",IF($F32=IFERROR(INDEX(спр_Материалы!$G$2:$G$9000,MATCH($I32,спр_Материалы!$A$2:$A$9000,0)),""),"OK","!! не та группа")) | L32: =IFERROR(INDEX(спр_Работы!$H$2:$H$6000,MATCH($C32,спр_Работы!$A$2:$A$6000,0))*(1-ДисконтТендер),0) | M32: =IF($I32="",0,IFERROR(INDEX(спр_Материалы!$I$2:$I$9000,MATCH($I32,спр_Материалы!$A$2:$A$9000,0))*IF(INDEX(спр_Материалы!$J$2:$J$9000,MATCH($I32,спр_Материалы!$A$2:$A$9000,0))="USD",КурсUSD,IF(INDEX(спр_Материалы!$J$2:$J$9000,MATCH($I32,спр_Материалы!$A$2:$A$9000,0))="EUR",КурсEUR,1))*INDEX(спр_Материалы!$K$2:$K$9000,MATCH($I32,спр_Материалы!$A$2:$A$9000,0))*(1+IFERROR(INDEX(спр_Работы!$I$2:$I$6000,MATCH($C32,спр_Работы!$A$2:$A$6000,0))/100,0))*(1-ДисконтТендер),0)) | N32: =IF(AND($R32="да",$H32<>""),ROUND($H32*$L32,2),0) | O32: =IF(AND($R32="да",$H32<>""),ROUND($H32*$M32,2),0) | P32: =$N32+$O32 | Q32: =IFERROR(INDEX(спр_Работы!$J$2:$J$6000,MATCH($C32,спр_Работы!$A$2:$A$6000,0)),"") | R32: да | T32: =IF(AND($P32>0,$R32="да"),MAX($T$1:$T31)+1,"")
A33: =IFERROR(INDEX(спр_Работы!$D$2:$D$6000,MATCH($C33,спр_Работы!$A$2:$A$6000,0)),"") | B33: =IFERROR(INDEX(спр_Работы!$F$2:$F$6000,MATCH($C33,спр_Работы!$A$2:$A$6000,0)),"") | C33: =IFERROR(INDEX(спр_Работы!$A$2:$A$6000,32),"") | D33: =IFERROR(INDEX(спр_Работы!$B$2:$B$6000,MATCH($C33,спр_Работы!$A$2:$A$6000,0)),"") | E33: =IFERROR(INDEX(спр_Работы!$C$2:$C$6000,MATCH($C33,спр_Работы!$A$2:$A$6000,0)),"") | F33: =IFERROR(INDEX(спр_Работы!$G$2:$G$6000,MATCH($C33,спр_Работы!$A$2:$A$6000,0)),"") | G33: =IFERROR(INDEX(спр_Работы!$K$2:$K$6000,MATCH($C33,спр_Работы!$A$2:$A$6000,0)),"") | J33: =IFERROR(INDEX(спр_Материалы!$B$2:$B$9000,MATCH($I33,спр_Материалы!$A$2:$A$9000,0)),"") | K33: =IF($I33="","",IF($F33=IFERROR(INDEX(спр_Материалы!$G$2:$G$9000,MATCH($I33,спр_Материалы!$A$2:$A$9000,0)),""),"OK","!! не та группа")) | L33: =IFERROR(INDEX(спр_Работы!$H$2:$H$6000,MATCH($C33,спр_Работы!$A$2:$A$6000,0))*(1-ДисконтТендер),0) | M33: =IF($I33="",0,IFERROR(INDEX(спр_Материалы!$I$2:$I$9000,MATCH($I33,спр_Материалы!$A$2:$A$9000,0))*IF(INDEX(спр_Материалы!$J$2:$J$9000,MATCH($I33,спр_Материалы!$A$2:$A$9000,0))="USD",КурсUSD,IF(INDEX(спр_Материалы!$J$2:$J$9000,MATCH($I33,спр_Материалы!$A$2:$A$9000,0))="EUR",КурсEUR,1))*INDEX(спр_Материалы!$K$2:$K$9000,MATCH($I33,спр_Материалы!$A$2:$A$9000,0))*(1+IFERROR(INDEX(спр_Работы!$I$2:$I$6000,MATCH($C33,спр_Работы!$A$2:$A$6000,0))/100,0))*(1-ДисконтТендер),0)) | N33: =IF(AND($R33="да",$H33<>""),ROUND($H33*$L33,2),0) | O33: =IF(AND($R33="да",$H33<>""),ROUND($H33*$M33,2),0) | P33: =$N33+$O33 | Q33: =IFERROR(INDEX(спр_Работы!$J$2:$J$6000,MATCH($C33,спр_Работы!$A$2:$A$6000,0)),"") | R33: да | T33: =IF(AND($P33>0,$R33="да"),MAX($T$1:$T32)+1,"")
A34: =IFERROR(INDEX(спр_Работы!$D$2:$D$6000,MATCH($C34,спр_Работы!$A$2:$A$6000,0)),"") | B34: =IFERROR(INDEX(спр_Работы!$F$2:$F$6000,MATCH($C34,спр_Работы!$A$2:$A$6000,0)),"") | C34: =IFERROR(INDEX(спр_Работы!$A$2:$A$6000,33),"") | D34: =IFERROR(INDEX(спр_Работы!$B$2:$B$6000,MATCH($C34,спр_Работы!$A$2:$A$6000,0)),"") | E34: =IFERROR(INDEX(спр_Работы!$C$2:$C$6000,MATCH($C34,спр_Работы!$A$2:$A$6000,0)),"") | F34: =IFERROR(INDEX(спр_Работы!$G$2:$G$6000,MATCH($C34,спр_Работы!$A$2:$A$6000,0)),"") | G34: =IFERROR(INDEX(спр_Работы!$K$2:$K$6000,MATCH($C34,спр_Работы!$A$2:$A$6000,0)),"") | J34: =IFERROR(INDEX(спр_Материалы!$B$2:$B$9000,MATCH($I34,спр_Материалы!$A$2:$A$9000,0)),"") | K34: =IF($I34="","",IF($F34=IFERROR(INDEX(спр_Материалы!$G$2:$G$9000,MATCH($I34,спр_Материалы!$A$2:$A$9000,0)),""),"OK","!! не та группа")) | L34: =IFERROR(INDEX(спр_Работы!$H$2:$H$6000,MATCH($C34,спр_Работы!$A$2:$A$6000,0))*(1-ДисконтТендер),0) | M34: =IF($I34="",0,IFERROR(INDEX(спр_Материалы!$I$2:$I$9000,MATCH($I34,спр_Материалы!$A$2:$A$9000,0))*IF(INDEX(спр_Материалы!$J$2:$J$9000,MATCH($I34,спр_Материалы!$A$2:$A$9000,0))="USD",КурсUSD,IF(INDEX(спр_Материалы!$J$2:$J$9000,MATCH($I34,спр_Материалы!$A$2:$A$9000,0))="EUR",КурсEUR,1))*INDEX(спр_Материалы!$K$2:$K$9000,MATCH($I34,спр_Материалы!$A$2:$A$9000,0))*(1+IFERROR(INDEX(спр_Работы!$I$2:$I$6000,MATCH($C34,спр_Работы!$A$2:$A$6000,0))/100,0))*(1-ДисконтТендер),0)) | N34: =IF(AND($R34="да",$H34<>""),ROUND($H34*$L34,2),0) | O34: =IF(AND($R34="да",$H34<>""),ROUND($H34*$M34,2),0) | P34: =$N34+$O34 | Q34: =IFERROR(INDEX(спр_Работы!$J$2:$J$6000,MATCH($C34,спр_Работы!$A$2:$A$6000,0)),"") | R34: да | T34: =IF(AND($P34>0,$R34="да"),MAX($T$1:$T33)+1,"")
A35: =IFERROR(INDEX(спр_Работы!$D$2:$D$6000,MATCH($C35,спр_Работы!$A$2:$A$6000,0)),"") | B35: =IFERROR(INDEX(спр_Работы!$F$2:$F$6000,MATCH($C35,спр_Работы!$A$2:$A$6000,0)),"") | C35: =IFERROR(INDEX(спр_Работы!$A$2:$A$6000,34),"") | D35: =IFERROR(INDEX(спр_Работы!$B$2:$B$6000,MATCH($C35,спр_Работы!$A$2:$A$6000,0)),"") | E35: =IFERROR(INDEX(спр_Работы!$C$2:$C$6000,MATCH($C35,спр_Работы!$A$2:$A$6000,0)),"") | F35: =IFERROR(INDEX(спр_Работы!$G$2:$G$6000,MATCH($C35,спр_Работы!$A$2:$A$6000,0)),"") | G35: =IFERROR(INDEX(спр_Работы!$K$2:$K$6000,MATCH($C35,спр_Работы!$A$2:$A$6000,0)),"") | J35: =IFERROR(INDEX(спр_Материалы!$B$2:$B$9000,MATCH($I35,спр_Материалы!$A$2:$A$9000,0)),"") | K35: =IF($I35="","",IF($F35=IFERROR(INDEX(спр_Материалы!$G$2:$G$9000,MATCH($I35,спр_Материалы!$A$2:$A$9000,0)),""),"OK","!! не та группа")) | L35: =IFERROR(INDEX(спр_Работы!$H$2:$H$6000,MATCH($C35,спр_Работы!$A$2:$A$6000,0))*(1-ДисконтТендер),0) | M35: =IF($I35="",0,IFERROR(INDEX(спр_Материалы!$I$2:$I$9000,MATCH($I35,спр_Материалы!$A$2:$A$9000,0))*IF(INDEX(спр_Материалы!$J$2:$J$9000,MATCH($I35,спр_Материалы!$A$2:$A$9000,0))="USD",КурсUSD,IF(INDEX(спр_Материалы!$J$2:$J$9000,MATCH($I35,спр_Материалы!$A$2:$A$9000,0))="EUR",КурсEUR,1))*INDEX(спр_Материалы!$K$2:$K$9000,MATCH($I35,спр_Материалы!$A$2:$A$9000,0))*(1+IFERROR(INDEX(спр_Работы!$I$2:$I$6000,MATCH($C35,спр_Работы!$A$2:$A$6000,0))/100,0))*(1-ДисконтТендер),0)) | N35: =IF(AND($R35="да",$H35<>""),ROUND($H35*$L35,2),0) | O35: =IF(AND($R35="да",$H35<>""),ROUND($H35*$M35,2),0) | P35: =$N35+$O35 | Q35: =IFERROR(INDEX(спр_Работы!$J$2:$J$6000,MATCH($C35,спр_Работы!$A$2:$A$6000,0)),"") | R35: да | T35: =IF(AND($P35>0,$R35="да"),MAX($T$1:$T34)+1,"")
A36: =IFERROR(INDEX(спр_Работы!$D$2:$D$6000,MATCH($C36,спр_Работы!$A$2:$A$6000,0)),"") | B36: =IFERROR(INDEX(спр_Работы!$F$2:$F$6000,MATCH($C36,спр_Работы!$A$2:$A$6000,0)),"") | C36: =IFERROR(INDEX(спр_Работы!$A$2:$A$6000,35),"") | D36: =IFERROR(INDEX(спр_Работы!$B$2:$B$6000,MATCH($C36,спр_Работы!$A$2:$A$6000,0)),"") | E36: =IFERROR(INDEX(спр_Работы!$C$2:$C$6000,MATCH($C36,спр_Работы!$A$2:$A$6000,0)),"") | F36: =IFERROR(INDEX(спр_Работы!$G$2:$G$6000,MATCH($C36,спр_Работы!$A$2:$A$6000,0)),"") | G36: =IFERROR(INDEX(спр_Работы!$K$2:$K$6000,MATCH($C36,спр_Работы!$A$2:$A$6000,0)),"") | J36: =IFERROR(INDEX(спр_Материалы!$B$2:$B$9000,MATCH($I36,спр_Материалы!$A$2:$A$9000,0)),"") | K36: =IF($I36="","",IF($F36=IFERROR(INDEX(спр_Материалы!$G$2:$G$9000,MATCH($I36,спр_Материалы!$A$2:$A$9000,0)),""),"OK","!! не та группа")) | L36: =IFERROR(INDEX(спр_Работы!$H$2:$H$6000,MATCH($C36,спр_Работы!$A$2:$A$6000,0))*(1-ДисконтТендер),0) | M36: =IF($I36="",0,IFERROR(INDEX(спр_Материалы!$I$2:$I$9000,MATCH($I36,спр_Материалы!$A$2:$A$9000,0))*IF(INDEX(спр_Материалы!$J$2:$J$9000,MATCH($I36,спр_Материалы!$A$2:$A$9000,0))="USD",КурсUSD,IF(INDEX(спр_Материалы!$J$2:$J$9000,MATCH($I36,спр_Материалы!$A$2:$A$9000,0))="EUR",КурсEUR,1))*INDEX(спр_Материалы!$K$2:$K$9000,MATCH($I36,спр_Материалы!$A$2:$A$9000,0))*(1+IFERROR(INDEX(спр_Работы!$I$2:$I$6000,MATCH($C36,спр_Работы!$A$2:$A$6000,0))/100,0))*(1-ДисконтТендер),0)) | N36: =IF(AND($R36="да",$H36<>""),ROUND($H36*$L36,2),0) | O36: =IF(AND($R36="да",$H36<>""),ROUND($H36*$M36,2),0) | P36: =$N36+$O36 | Q36: =IFERROR(INDEX(спр_Работы!$J$2:$J$6000,MATCH($C36,спр_Работы!$A$2:$A$6000,0)),"") | R36: да | T36: =IF(AND($P36>0,$R36="да"),MAX($T$1:$T35)+1,"")
A37: =IFERROR(INDEX(спр_Работы!$D$2:$D$6000,MATCH($C37,спр_Работы!$A$2:$A$6000,0)),"") | B37: =IFERROR(INDEX(спр_Работы!$F$2:$F$6000,MATCH($C37,спр_Работы!$A$2:$A$6000,0)),"") | C37: =IFERROR(INDEX(спр_Работы!$A$2:$A$6000,36),"") | D37: =IFERROR(INDEX(спр_Работы!$B$2:$B$6000,MATCH($C37,спр_Работы!$A$2:$A$6000,0)),"") | E37: =IFERROR(INDEX(спр_Работы!$C$2:$C$6000,MATCH($C37,спр_Работы!$A$2:$A$6000,0)),"") | F37: =IFERROR(INDEX(спр_Работы!$G$2:$G$6000,MATCH($C37,спр_Работы!$A$2:$A$6000,0)),"") | G37: =IFERROR(INDEX(спр_Работы!$K$2:$K$6000,MATCH($C37,спр_Работы!$A$2:$A$6000,0)),"") | J37: =IFERROR(INDEX(спр_Материалы!$B$2:$B$9000,MATCH($I37,спр_Материалы!$A$2:$A$9000,0)),"") | K37: =IF($I37="","",IF($F37=IFERROR(INDEX(спр_Материалы!$G$2:$G$9000,MATCH($I37,спр_Материалы!$A$2:$A$9000,0)),""),"OK","!! не та группа")) | L37: =IFERROR(INDEX(спр_Работы!$H$2:$H$6000,MATCH($C37,спр_Работы!$A$2:$A$6000,0))*(1-ДисконтТендер),0) | M37: =IF($I37="",0,IFERROR(INDEX(спр_Материалы!$I$2:$I$9000,MATCH($I37,спр_Материалы!$A$2:$A$9000,0))*IF(INDEX(спр_Материалы!$J$2:$J$9000,MATCH($I37,спр_Материалы!$A$2:$A$9000,0))="USD",КурсUSD,IF(INDEX(спр_Материалы!$J$2:$J$9000,MATCH($I37,спр_Материалы!$A$2:$A$9000,0))="EUR",КурсEUR,1))*INDEX(спр_Материалы!$K$2:$K$9000,MATCH($I37,спр_Материалы!$A$2:$A$9000,0))*(1+IFERROR(INDEX(спр_Работы!$I$2:$I$6000,MATCH($C37,спр_Работы!$A$2:$A$6000,0))/100,0))*(1-ДисконтТендер),0)) | N37: =IF(AND($R37="да",$H37<>""),ROUND($H37*$L37,2),0) | O37: =IF(AND($R37="да",$H37<>""),ROUND($H37*$M37,2),0) | P37: =$N37+$O37 | Q37: =IFERROR(INDEX(спр_Работы!$J$2:$J$6000,MATCH($C37,спр_Работы!$A$2:$A$6000,0)),"") | R37: да | T37: =IF(AND($P37>0,$R37="да"),MAX($T$1:$T36)+1,"")
A38: =IFERROR(INDEX(спр_Работы!$D$2:$D$6000,MATCH($C38,спр_Работы!$A$2:$A$6000,0)),"") | B38: =IFERROR(INDEX(спр_Работы!$F$2:$F$6000,MATCH($C38,спр_Работы!$A$2:$A$6000,0)),"") | C38: =IFERROR(INDEX(спр_Работы!$A$2:$A$6000,37),"") | D38: =IFERROR(INDEX(спр_Работы!$B$2:$B$6000,MATCH($C38,спр_Работы!$A$2:$A$6000,0)),"") | E38: =IFERROR(INDEX(спр_Работы!$C$2:$C$6000,MATCH($C38,спр_Работы!$A$2:$A$6000,0)),"") | F38: =IFERROR(INDEX(спр_Работы!$G$2:$G$6000,MATCH($C38,спр_Работы!$A$2:$A$6000,0)),"") | G38: =IFERROR(INDEX(спр_Работы!$K$2:$K$6000,MATCH($C38,спр_Работы!$A$2:$A$6000,0)),"") | J38: =IFERROR(INDEX(спр_Материалы!$B$2:$B$9000,MATCH($I38,спр_Материалы!$A$2:$A$9000,0)),"") | K38: =IF($I38="","",IF($F38=IFERROR(INDEX(спр_Материалы!$G$2:$G$9000,MATCH($I38,спр_Материалы!$A$2:$A$9000,0)),""),"OK","!! не та группа")) | L38: =IFERROR(INDEX(спр_Работы!$H$2:$H$6000,MATCH($C38,спр_Работы!$A$2:$A$6000,0))*(1-ДисконтТендер),0) | M38: =IF($I38="",0,IFERROR(INDEX(спр_Материалы!$I$2:$I$9000,MATCH($I38,спр_Материалы!$A$2:$A$9000,0))*IF(INDEX(спр_Материалы!$J$2:$J$9000,MATCH($I38,спр_Материалы!$A$2:$A$9000,0))="USD",КурсUSD,IF(INDEX(спр_Материалы!$J$2:$J$9000,MATCH($I38,спр_Материалы!$A$2:$A$9000,0))="EUR",КурсEUR,1))*INDEX(спр_Материалы!$K$2:$K$9000,MATCH($I38,спр_Материалы!$A$2:$A$9000,0))*(1+IFERROR(INDEX(спр_Работы!$I$2:$I$6000,MATCH($C38,спр_Работы!$A$2:$A$6000,0))/100,0))*(1-ДисконтТендер),0)) | N38: =IF(AND($R38="да",$H38<>""),ROUND($H38*$L38,2),0) | O38: =IF(AND($R38="да",$H38<>""),ROUND($H38*$M38,2),0) | P38: =$N38+$O38 | Q38: =IFERROR(INDEX(спр_Работы!$J$2:$J$6000,MATCH($C38,спр_Работы!$A$2:$A$6000,0)),"") | R38: да | T38: =IF(AND($P38>0,$R38="да"),MAX($T$1:$T37)+1,"")
A39: =IFERROR(INDEX(спр_Работы!$D$2:$D$6000,MATCH($C39,спр_Работы!$A$2:$A$6000,0)),"") | B39: =IFERROR(INDEX(спр_Работы!$F$2:$F$6000,MATCH($C39,спр_Работы!$A$2:$A$6000,0)),"") | C39: =IFERROR(INDEX(спр_Работы!$A$2:$A$6000,38),"") | D39: =IFERROR(INDEX(спр_Работы!$B$2:$B$6000,MATCH($C39,спр_Работы!$A$2:$A$6000,0)),"") | E39: =IFERROR(INDEX(спр_Работы!$C$2:$C$6000,MATCH($C39,спр_Работы!$A$2:$A$6000,0)),"") | F39: =IFERROR(INDEX(спр_Работы!$G$2:$G$6000,MATCH($C39,спр_Работы!$A$2:$A$6000,0)),"") | G39: =IFERROR(INDEX(спр_Работы!$K$2:$K$6000,MATCH($C39,спр_Работы!$A$2:$A$6000,0)),"") | J39: =IFERROR(INDEX(спр_Материалы!$B$2:$B$9000,MATCH($I39,спр_Материалы!$A$2:$A$9000,0)),"") | K39: =IF($I39="","",IF($F39=IFERROR(INDEX(спр_Материалы!$G$2:$G$9000,MATCH($I39,спр_Материалы!$A$2:$A$9000,0)),""),"OK","!! не та группа")) | L39: =IFERROR(INDEX(спр_Работы!$H$2:$H$6000,MATCH($C39,спр_Работы!$A$2:$A$6000,0))*(1-ДисконтТендер),0) | M39: =IF($I39="",0,IFERROR(INDEX(спр_Материалы!$I$2:$I$9000,MATCH($I39,спр_Материалы!$A$2:$A$9000,0))*IF(INDEX(спр_Материалы!$J$2:$J$9000,MATCH($I39,спр_Материалы!$A$2:$A$9000,0))="USD",КурсUSD,IF(INDEX(спр_Материалы!$J$2:$J$9000,MATCH($I39,спр_Материалы!$A$2:$A$9000,0))="EUR",КурсEUR,1))*INDEX(спр_Материалы!$K$2:$K$9000,MATCH($I39,спр_Материалы!$A$2:$A$9000,0))*(1+IFERROR(INDEX(спр_Работы!$I$2:$I$6000,MATCH($C39,спр_Работы!$A$2:$A$6000,0))/100,0))*(1-ДисконтТендер),0)) | N39: =IF(AND($R39="да",$H39<>""),ROUND($H39*$L39,2),0) | O39: =IF(AND($R39="да",$H39<>""),ROUND($H39*$M39,2),0) | P39: =$N39+$O39 | Q39: =IFERROR(INDEX(спр_Работы!$J$2:$J$6000,MATCH($C39,спр_Работы!$A$2:$A$6000,0)),"") | R39: да | T39: =IF(AND($P39>0,$R39="да"),MAX($T$1:$T38)+1,"")
A40: =IFERROR(INDEX(спр_Работы!$D$2:$D$6000,MATCH($C40,спр_Работы!$A$2:$A$6000,0)),"") | B40: =IFERROR(INDEX(спр_Работы!$F$2:$F$6000,MATCH($C40,спр_Работы!$A$2:$A$6000,0)),"") | C40: =IFERROR(INDEX(спр_Работы!$A$2:$A$6000,39),"") | D40: =IFERROR(INDEX(спр_Работы!$B$2:$B$6000,MATCH($C40,спр_Работы!$A$2:$A$6000,0)),"") | E40: =IFERROR(INDEX(спр_Работы!$C$2:$C$6000,MATCH($C40,спр_Работы!$A$2:$A$6000,0)),"") | F40: =IFERROR(INDEX(спр_Работы!$G$2:$G$6000,MATCH($C40,спр_Работы!$A$2:$A$6000,0)),"") | G40: =IFERROR(INDEX(спр_Работы!$K$2:$K$6000,MATCH($C40,спр_Работы!$A$2:$A$6000,0)),"") | J40: =IFERROR(INDEX(спр_Материалы!$B$2:$B$9000,MATCH($I40,спр_Материалы!$A$2:$A$9000,0)),"") | K40: =IF($I40="","",IF($F40=IFERROR(INDEX(спр_Материалы!$G$2:$G$9000,MATCH($I40,спр_Материалы!$A$2:$A$9000,0)),""),"OK","!! не та группа")) | L40: =IFERROR(INDEX(спр_Работы!$H$2:$H$6000,MATCH($C40,спр_Работы!$A$2:$A$6000,0))*(1-ДисконтТендер),0) | M40: =IF($I40="",0,IFERROR(INDEX(спр_Материалы!$I$2:$I$9000,MATCH($I40,спр_Материалы!$A$2:$A$9000,0))*IF(INDEX(спр_Материалы!$J$2:$J$9000,MATCH($I40,спр_Материалы!$A$2:$A$9000,0))="USD",КурсUSD,IF(INDEX(спр_Материалы!$J$2:$J$9000,MATCH($I40,спр_Материалы!$A$2:$A$9000,0))="EUR",КурсEUR,1))*INDEX(спр_Материалы!$K$2:$K$9000,MATCH($I40,спр_Материалы!$A$2:$A$9000,0))*(1+IFERROR(INDEX(спр_Работы!$I$2:$I$6000,MATCH($C40,спр_Работы!$A$2:$A$6000,0))/100,0))*(1-ДисконтТендер),0)) | N40: =IF(AND($R40="да",$H40<>""),ROUND($H40*$L40,2),0) | O40: =IF(AND($R40="да",$H40<>""),ROUND($H40*$M40,2),0) | P40: =$N40+$O40 | Q40: =IFERROR(INDEX(спр_Работы!$J$2:$J$6000,MATCH($C40,спр_Работы!$A$2:$A$6000,0)),"") | R40: да | T40: =IF(AND($P40>0,$R40="да"),MAX($T$1:$T39)+1,"")
A41: =IFERROR(INDEX(спр_Работы!$D$2:$D$6000,MATCH($C41,спр_Работы!$A$2:$A$6000,0)),"") | B41: =IFERROR(INDEX(спр_Работы!$F$2:$F$6000,MATCH($C41,спр_Работы!$A$2:$A$6000,0)),"") | C41: =IFERROR(INDEX(спр_Работы!$A$2:$A$6000,40),"") | D41: =IFERROR(INDEX(спр_Работы!$B$2:$B$6000,MATCH($C41,спр_Работы!$A$2:$A$6000,0)),"") | E41: =IFERROR(INDEX(спр_Работы!$C$2:$C$6000,MATCH($C41,спр_Работы!$A$2:$A$6000,0)),"") | F41: =IFERROR(INDEX(спр_Работы!$G$2:$G$6000,MATCH($C41,спр_Работы!$A$2:$A$6000,0)),"") | G41: =IFERROR(INDEX(спр_Работы!$K$2:$K$6000,MATCH($C41,спр_Работы!$A$2:$A$6000,0)),"") | J41: =IFERROR(INDEX(спр_Материалы!$B$2:$B$9000,MATCH($I41,спр_Материалы!$A$2:$A$9000,0)),"") | K41: =IF($I41="","",IF($F41=IFERROR(INDEX(спр_Материалы!$G$2:$G$9000,MATCH($I41,спр_Материалы!$A$2:$A$9000,0)),""),"OK","!! не та группа")) | L41: =IFERROR(INDEX(спр_Работы!$H$2:$H$6000,MATCH($C41,спр_Работы!$A$2:$A$6000,0))*(1-ДисконтТендер),0) | M41: =IF($I41="",0,IFERROR(INDEX(спр_Материалы!$I$2:$I$9000,MATCH($I41,спр_Материалы!$A$2:$A$9000,0))*IF(INDEX(спр_Материалы!$J$2:$J$9000,MATCH($I41,спр_Материалы!$A$2:$A$9000,0))="USD",КурсUSD,IF(INDEX(спр_Материалы!$J$2:$J$9000,MATCH($I41,спр_Материалы!$A$2:$A$9000,0))="EUR",КурсEUR,1))*INDEX(спр_Материалы!$K$2:$K$9000,MATCH($I41,спр_Материалы!$A$2:$A$9000,0))*(1+IFERROR(INDEX(спр_Работы!$I$2:$I$6000,MATCH($C41,спр_Работы!$A$2:$A$6000,0))/100,0))*(1-ДисконтТендер),0)) | N41: =IF(AND($R41="да",$H41<>""),ROUND($H41*$L41,2),0) | O41: =IF(AND($R41="да",$H41<>""),ROUND($H41*$M41,2),0) | P41: =$N41+$O41 | Q41: =IFERROR(INDEX(спр_Работы!$J$2:$J$6000,MATCH($C41,спр_Работы!$A$2:$A$6000,0)),"") | R41: да | T41: =IF(AND($P41>0,$R41="да"),MAX($T$1:$T40)+1,"")
A42: =IFERROR(INDEX(спр_Работы!$D$2:$D$6000,MATCH($C42,спр_Работы!$A$2:$A$6000,0)),"") | B42: =IFERROR(INDEX(спр_Работы!$F$2:$F$6000,MATCH($C42,спр_Работы!$A$2:$A$6000,0)),"") | C42: =IFERROR(INDEX(спр_Работы!$A$2:$A$6000,41),"") | D42: =IFERROR(INDEX(спр_Работы!$B$2:$B$6000,MATCH($C42,спр_Работы!$A$2:$A$6000,0)),"") | E42: =IFERROR(INDEX(спр_Работы!$C$2:$C$6000,MATCH($C42,спр_Работы!$A$2:$A$6000,0)),"") | F42: =IFERROR(INDEX(спр_Работы!$G$2:$G$6000,MATCH($C42,спр_Работы!$A$2:$A$6000,0)),"") | G42: =IFERROR(INDEX(спр_Работы!$K$2:$K$6000,MATCH($C42,спр_Работы!$A$2:$A$6000,0)),"") | J42: =IFERROR(INDEX(спр_Материалы!$B$2:$B$9000,MATCH($I42,спр_Материалы!$A$2:$A$9000,0)),"") | K42: =IF($I42="","",IF($F42=IFERROR(INDEX(спр_Материалы!$G$2:$G$9000,MATCH($I42,спр_Материалы!$A$2:$A$9000,0)),""),"OK","!! не та группа")) | L42: =IFERROR(INDEX(спр_Работы!$H$2:$H$6000,MATCH($C42,спр_Работы!$A$2:$A$6000,0))*(1-ДисконтТендер),0) | M42: =IF($I42="",0,IFERROR(INDEX(спр_Материалы!$I$2:$I$9000,MATCH($I42,спр_Материалы!$A$2:$A$9000,0))*IF(INDEX(спр_Материалы!$J$2:$J$9000,MATCH($I42,спр_Материалы!$A$2:$A$9000,0))="USD",КурсUSD,IF(INDEX(спр_Материалы!$J$2:$J$9000,MATCH($I42,спр_Материалы!$A$2:$A$9000,0))="EUR",КурсEUR,1))*INDEX(спр_Материалы!$K$2:$K$9000,MATCH($I42,спр_Материалы!$A$2:$A$9000,0))*(1+IFERROR(INDEX(спр_Работы!$I$2:$I$6000,MATCH($C42,спр_Работы!$A$2:$A$6000,0))/100,0))*(1-ДисконтТендер),0)) | N42: =IF(AND($R42="да",$H42<>""),ROUND($H42*$L42,2),0) | O42: =IF(AND($R42="да",$H42<>""),ROUND($H42*$M42,2),0) | P42: =$N42+$O42 | Q42: =IFERROR(INDEX(спр_Работы!$J$2:$J$6000,MATCH($C42,спр_Работы!$A$2:$A$6000,0)),"") | R42: да | T42: =IF(AND($P42>0,$R42="да"),MAX($T$1:$T41)+1,"")
A43: =IFERROR(INDEX(спр_Работы!$D$2:$D$6000,MATCH($C43,спр_Работы!$A$2:$A$6000,0)),"") | B43: =IFERROR(INDEX(спр_Работы!$F$2:$F$6000,MATCH($C43,спр_Работы!$A$2:$A$6000,0)),"") | C43: =IFERROR(INDEX(спр_Работы!$A$2:$A$6000,42),"") | D43: =IFERROR(INDEX(спр_Работы!$B$2:$B$6000,MATCH($C43,спр_Работы!$A$2:$A$6000,0)),"") | E43: =IFERROR(INDEX(спр_Работы!$C$2:$C$6000,MATCH($C43,спр_Работы!$A$2:$A$6000,0)),"") | F43: =IFERROR(INDEX(спр_Работы!$G$2:$G$6000,MATCH($C43,спр_Работы!$A$2:$A$6000,0)),"") | G43: =IFERROR(INDEX(спр_Работы!$K$2:$K$6000,MATCH($C43,спр_Работы!$A$2:$A$6000,0)),"") | J43: =IFERROR(INDEX(спр_Материалы!$B$2:$B$9000,MATCH($I43,спр_Материалы!$A$2:$A$9000,0)),"") | K43: =IF($I43="","",IF($F43=IFERROR(INDEX(спр_Материалы!$G$2:$G$9000,MATCH($I43,спр_Материалы!$A$2:$A$9000,0)),""),"OK","!! не та группа")) | L43: =IFERROR(INDEX(спр_Работы!$H$2:$H$6000,MATCH($C43,спр_Работы!$A$2:$A$6000,0))*(1-ДисконтТендер),0) | M43: =IF($I43="",0,IFERROR(INDEX(спр_Материалы!$I$2:$I$9000,MATCH($I43,спр_Материалы!$A$2:$A$9000,0))*IF(INDEX(спр_Материалы!$J$2:$J$9000,MATCH($I43,спр_Материалы!$A$2:$A$9000,0))="USD",КурсUSD,IF(INDEX(спр_Материалы!$J$2:$J$9000,MATCH($I43,спр_Материалы!$A$2:$A$9000,0))="EUR",КурсEUR,1))*INDEX(спр_Материалы!$K$2:$K$9000,MATCH($I43,спр_Материалы!$A$2:$A$9000,0))*(1+IFERROR(INDEX(спр_Работы!$I$2:$I$6000,MATCH($C43,спр_Работы!$A$2:$A$6000,0))/100,0))*(1-ДисконтТендер),0)) | N43: =IF(AND($R43="да",$H43<>""),ROUND($H43*$L43,2),0) | O43: =IF(AND($R43="да",$H43<>""),ROUND($H43*$M43,2),0) | P43: =$N43+$O43 | Q43: =IFERROR(INDEX(спр_Работы!$J$2:$J$6000,MATCH($C43,спр_Работы!$A$2:$A$6000,0)),"") | R43: да | T43: =IF(AND($P43>0,$R43="да"),MAX($T$1:$T42)+1,"")
A44: =IFERROR(INDEX(спр_Работы!$D$2:$D$6000,MATCH($C44,спр_Работы!$A$2:$A$6000,0)),"") | B44: =IFERROR(INDEX(спр_Работы!$F$2:$F$6000,MATCH($C44,спр_Работы!$A$2:$A$6000,0)),"") | C44: =IFERROR(INDEX(спр_Работы!$A$2:$A$6000,43),"") | D44: =IFERROR(INDEX(спр_Работы!$B$2:$B$6000,MATCH($C44,спр_Работы!$A$2:$A$6000,0)),"") | E44: =IFERROR(INDEX(спр_Работы!$C$2:$C$6000,MATCH($C44,спр_Работы!$A$2:$A$6000,0)),"") | F44: =IFERROR(INDEX(спр_Работы!$G$2:$G$6000,MATCH($C44,спр_Работы!$A$2:$A$6000,0)),"") | G44: =IFERROR(INDEX(спр_Работы!$K$2:$K$6000,MATCH($C44,спр_Работы!$A$2:$A$6000,0)),"") | J44: =IFERROR(INDEX(спр_Материалы!$B$2:$B$9000,MATCH($I44,спр_Материалы!$A$2:$A$9000,0)),"") | K44: =IF($I44="","",IF($F44=IFERROR(INDEX(спр_Материалы!$G$2:$G$9000,MATCH($I44,спр_Материалы!$A$2:$A$9000,0)),""),"OK","!! не та группа")) | L44: =IFERROR(INDEX(спр_Работы!$H$2:$H$6000,MATCH($C44,спр_Работы!$A$2:$A$6000,0))*(1-ДисконтТендер),0) | M44: =IF($I44="",0,IFERROR(INDEX(спр_Материалы!$I$2:$I$9000,MATCH($I44,спр_Материалы!$A$2:$A$9000,0))*IF(INDEX(спр_Материалы!$J$2:$J$9000,MATCH($I44,спр_Материалы!$A$2:$A$9000,0))="USD",КурсUSD,IF(INDEX(спр_Материалы!$J$2:$J$9000,MATCH($I44,спр_Материалы!$A$2:$A$9000,0))="EUR",КурсEUR,1))*INDEX(спр_Материалы!$K$2:$K$9000,MATCH($I44,спр_Материалы!$A$2:$A$9000,0))*(1+IFERROR(INDEX(спр_Работы!$I$2:$I$6000,MATCH($C44,спр_Работы!$A$2:$A$6000,0))/100,0))*(1-ДисконтТендер),0)) | N44: =IF(AND($R44="да",$H44<>""),ROUND($H44*$L44,2),0) | O44: =IF(AND($R44="да",$H44<>""),ROUND($H44*$M44,2),0) | P44: =$N44+$O44 | Q44: =IFERROR(INDEX(спр_Работы!$J$2:$J$6000,MATCH($C44,спр_Работы!$A$2:$A$6000,0)),"") | R44: да | T44: =IF(AND($P44>0,$R44="да"),MAX($T$1:$T43)+1,"")
A45: =IFERROR(INDEX(спр_Работы!$D$2:$D$6000,MATCH($C45,спр_Работы!$A$2:$A$6000,0)),"") | B45: =IFERROR(INDEX(спр_Работы!$F$2:$F$6000,MATCH($C45,спр_Работы!$A$2:$A$6000,0)),"") | C45: =IFERROR(INDEX(спр_Работы!$A$2:$A$6000,44),"") | D45: =IFERROR(INDEX(спр_Работы!$B$2:$B$6000,MATCH($C45,спр_Работы!$A$2:$A$6000,0)),"") | E45: =IFERROR(INDEX(спр_Работы!$C$2:$C$6000,MATCH($C45,спр_Работы!$A$2:$A$6000,0)),"") | F45: =IFERROR(INDEX(спр_Работы!$G$2:$G$6000,MATCH($C45,спр_Работы!$A$2:$A$6000,0)),"") | G45: =IFERROR(INDEX(спр_Работы!$K$2:$K$6000,MATCH($C45,спр_Работы!$A$2:$A$6000,0)),"") | J45: =IFERROR(INDEX(спр_Материалы!$B$2:$B$9000,MATCH($I45,спр_Материалы!$A$2:$A$9000,0)),"") | K45: =IF($I45="","",IF($F45=IFERROR(INDEX(спр_Материалы!$G$2:$G$9000,MATCH($I45,спр_Материалы!$A$2:$A$9000,0)),""),"OK","!! не та группа")) | L45: =IFERROR(INDEX(спр_Работы!$H$2:$H$6000,MATCH($C45,спр_Работы!$A$2:$A$6000,0))*(1-ДисконтТендер),0) | M45: =IF($I45="",0,IFERROR(INDEX(спр_Материалы!$I$2:$I$9000,MATCH($I45,спр_Материалы!$A$2:$A$9000,0))*IF(INDEX(спр_Материалы!$J$2:$J$9000,MATCH($I45,спр_Материалы!$A$2:$A$9000,0))="USD",КурсUSD,IF(INDEX(спр_Материалы!$J$2:$J$9000,MATCH($I45,спр_Материалы!$A$2:$A$9000,0))="EUR",КурсEUR,1))*INDEX(спр_Материалы!$K$2:$K$9000,MATCH($I45,спр_Материалы!$A$2:$A$9000,0))*(1+IFERROR(INDEX(спр_Работы!$I$2:$I$6000,MATCH($C45,спр_Работы!$A$2:$A$6000,0))/100,0))*(1-ДисконтТендер),0)) | N45: =IF(AND($R45="да",$H45<>""),ROUND($H45*$L45,2),0) | O45: =IF(AND($R45="да",$H45<>""),ROUND($H45*$M45,2),0) | P45: =$N45+$O45 | Q45: =IFERROR(INDEX(спр_Работы!$J$2:$J$6000,MATCH($C45,спр_Работы!$A$2:$A$6000,0)),"") | R45: да | T45: =IF(AND($P45>0,$R45="да"),MAX($T$1:$T44)+1,"")
A46: =IFERROR(INDEX(спр_Работы!$D$2:$D$6000,MATCH($C46,спр_Работы!$A$2:$A$6000,0)),"") | B46: =IFERROR(INDEX(спр_Работы!$F$2:$F$6000,MATCH($C46,спр_Работы!$A$2:$A$6000,0)),"") | C46: =IFERROR(INDEX(спр_Работы!$A$2:$A$6000,45),"") | D46: =IFERROR(INDEX(спр_Работы!$B$2:$B$6000,MATCH($C46,спр_Работы!$A$2:$A$6000,0)),"") | E46: =IFERROR(INDEX(спр_Работы!$C$2:$C$6000,MATCH($C46,спр_Работы!$A$2:$A$6000,0)),"") | F46: =IFERROR(INDEX(спр_Работы!$G$2:$G$6000,MATCH($C46,спр_Работы!$A$2:$A$6000,0)),"") | G46: =IFERROR(INDEX(спр_Работы!$K$2:$K$6000,MATCH($C46,спр_Работы!$A$2:$A$6000,0)),"") | J46: =IFERROR(INDEX(спр_Материалы!$B$2:$B$9000,MATCH($I46,спр_Материалы!$A$2:$A$9000,0)),"") | K46: =IF($I46="","",IF($F46=IFERROR(INDEX(спр_Материалы!$G$2:$G$9000,MATCH($I46,спр_Материалы!$A$2:$A$9000,0)),""),"OK","!! не та группа")) | L46: =IFERROR(INDEX(спр_Работы!$H$2:$H$6000,MATCH($C46,спр_Работы!$A$2:$A$6000,0))*(1-ДисконтТендер),0) | M46: =IF($I46="",0,IFERROR(INDEX(спр_Материалы!$I$2:$I$9000,MATCH($I46,спр_Материалы!$A$2:$A$9000,0))*IF(INDEX(спр_Материалы!$J$2:$J$9000,MATCH($I46,спр_Материалы!$A$2:$A$9000,0))="USD",КурсUSD,IF(INDEX(спр_Материалы!$J$2:$J$9000,MATCH($I46,спр_Материалы!$A$2:$A$9000,0))="EUR",КурсEUR,1))*INDEX(спр_Материалы!$K$2:$K$9000,MATCH($I46,спр_Материалы!$A$2:$A$9000,0))*(1+IFERROR(INDEX(спр_Работы!$I$2:$I$6000,MATCH($C46,спр_Работы!$A$2:$A$6000,0))/100,0))*(1-ДисконтТендер),0)) | N46: =IF(AND($R46="да",$H46<>""),ROUND($H46*$L46,2),0) | O46: =IF(AND($R46="да",$H46<>""),ROUND($H46*$M46,2),0) | P46: =$N46+$O46 | Q46: =IFERROR(INDEX(спр_Работы!$J$2:$J$6000,MATCH($C46,спр_Работы!$A$2:$A$6000,0)),"") | R46: да | T46: =IF(AND($P46>0,$R46="да"),MAX($T$1:$T45)+1,"")
A47: =IFERROR(INDEX(спр_Работы!$D$2:$D$6000,MATCH($C47,спр_Работы!$A$2:$A$6000,0)),"") | B47: =IFERROR(INDEX(спр_Работы!$F$2:$F$6000,MATCH($C47,спр_Работы!$A$2:$A$6000,0)),"") | C47: =IFERROR(INDEX(спр_Работы!$A$2:$A$6000,46),"") | D47: =IFERROR(INDEX(спр_Работы!$B$2:$B$6000,MATCH($C47,спр_Работы!$A$2:$A$6000,0)),"") | E47: =IFERROR(INDEX(спр_Работы!$C$2:$C$6000,MATCH($C47,спр_Работы!$A$2:$A$6000,0)),"") | F47: =IFERROR(INDEX(спр_Работы!$G$2:$G$6000,MATCH($C47,спр_Работы!$A$2:$A$6000,0)),"") | G47: =IFERROR(INDEX(спр_Работы!$K$2:$K$6000,MATCH($C47,спр_Работы!$A$2:$A$6000,0)),"") | J47: =IFERROR(INDEX(спр_Материалы!$B$2:$B$9000,MATCH($I47,спр_Материалы!$A$2:$A$9000,0)),"") | K47: =IF($I47="","",IF($F47=IFERROR(INDEX(спр_Материалы!$G$2:$G$9000,MATCH($I47,спр_Материалы!$A$2:$A$9000,0)),""),"OK","!! не та группа")) | L47: =IFERROR(INDEX(спр_Работы!$H$2:$H$6000,MATCH($C47,спр_Работы!$A$2:$A$6000,0))*(1-ДисконтТендер),0) | M47: =IF($I47="",0,IFERROR(INDEX(спр_Материалы!$I$2:$I$9000,MATCH($I47,спр_Материалы!$A$2:$A$9000,0))*IF(INDEX(спр_Материалы!$J$2:$J$9000,MATCH($I47,спр_Материалы!$A$2:$A$9000,0))="USD",КурсUSD,IF(INDEX(спр_Материалы!$J$2:$J$9000,MATCH($I47,спр_Материалы!$A$2:$A$9000,0))="EUR",КурсEUR,1))*INDEX(спр_Материалы!$K$2:$K$9000,MATCH($I47,спр_Материалы!$A$2:$A$9000,0))*(1+IFERROR(INDEX(спр_Работы!$I$2:$I$6000,MATCH($C47,спр_Работы!$A$2:$A$6000,0))/100,0))*(1-ДисконтТендер),0)) | N47: =IF(AND($R47="да",$H47<>""),ROUND($H47*$L47,2),0) | O47: =IF(AND($R47="да",$H47<>""),ROUND($H47*$M47,2),0) | P47: =$N47+$O47 | Q47: =IFERROR(INDEX(спр_Работы!$J$2:$J$6000,MATCH($C47,спр_Работы!$A$2:$A$6000,0)),"") | R47: да | T47: =IF(AND($P47>0,$R47="да"),MAX($T$1:$T46)+1,"")
A48: =IFERROR(INDEX(спр_Работы!$D$2:$D$6000,MATCH($C48,спр_Работы!$A$2:$A$6000,0)),"") | B48: =IFERROR(INDEX(спр_Работы!$F$2:$F$6000,MATCH($C48,спр_Работы!$A$2:$A$6000,0)),"") | C48: =IFERROR(INDEX(спр_Работы!$A$2:$A$6000,47),"") | D48: =IFERROR(INDEX(спр_Работы!$B$2:$B$6000,MATCH($C48,спр_Работы!$A$2:$A$6000,0)),"") | E48: =IFERROR(INDEX(спр_Работы!$C$2:$C$6000,MATCH($C48,спр_Работы!$A$2:$A$6000,0)),"") | F48: =IFERROR(INDEX(спр_Работы!$G$2:$G$6000,MATCH($C48,спр_Работы!$A$2:$A$6000,0)),"") | G48: =IFERROR(INDEX(спр_Работы!$K$2:$K$6000,MATCH($C48,спр_Работы!$A$2:$A$6000,0)),"") | J48: =IFERROR(INDEX(спр_Материалы!$B$2:$B$9000,MATCH($I48,спр_Материалы!$A$2:$A$9000,0)),"") | K48: =IF($I48="","",IF($F48=IFERROR(INDEX(спр_Материалы!$G$2:$G$9000,MATCH($I48,спр_Материалы!$A$2:$A$9000,0)),""),"OK","!! не та группа")) | L48: =IFERROR(INDEX(спр_Работы!$H$2:$H$6000,MATCH($C48,спр_Работы!$A$2:$A$6000,0))*(1-ДисконтТендер),0) | M48: =IF($I48="",0,IFERROR(INDEX(спр_Материалы!$I$2:$I$9000,MATCH($I48,спр_Материалы!$A$2:$A$9000,0))*IF(INDEX(спр_Материалы!$J$2:$J$9000,MATCH($I48,спр_Материалы!$A$2:$A$9000,0))="USD",КурсUSD,IF(INDEX(спр_Материалы!$J$2:$J$9000,MATCH($I48,спр_Материалы!$A$2:$A$9000,0))="EUR",КурсEUR,1))*INDEX(спр_Материалы!$K$2:$K$9000,MATCH($I48,спр_Материалы!$A$2:$A$9000,0))*(1+IFERROR(INDEX(спр_Работы!$I$2:$I$6000,MATCH($C48,спр_Работы!$A$2:$A$6000,0))/100,0))*(1-ДисконтТендер),0)) | N48: =IF(AND($R48="да",$H48<>""),ROUND($H48*$L48,2),0) | O48: =IF(AND($R48="да",$H48<>""),ROUND($H48*$M48,2),0) | P48: =$N48+$O48 | Q48: =IFERROR(INDEX(спр_Работы!$J$2:$J$6000,MATCH($C48,спр_Работы!$A$2:$A$6000,0)),"") | R48: да | T48: =IF(AND($P48>0,$R48="да"),MAX($T$1:$T47)+1,"")
A49: =IFERROR(INDEX(спр_Работы!$D$2:$D$6000,MATCH($C49,спр_Работы!$A$2:$A$6000,0)),"") | B49: =IFERROR(INDEX(спр_Работы!$F$2:$F$6000,MATCH($C49,спр_Работы!$A$2:$A$6000,0)),"") | C49: =IFERROR(INDEX(спр_Работы!$A$2:$A$6000,48),"") | D49: =IFERROR(INDEX(спр_Работы!$B$2:$B$6000,MATCH($C49,спр_Работы!$A$2:$A$6000,0)),"") | E49: =IFERROR(INDEX(спр_Работы!$C$2:$C$6000,MATCH($C49,спр_Работы!$A$2:$A$6000,0)),"") | F49: =IFERROR(INDEX(спр_Работы!$G$2:$G$6000,MATCH($C49,спр_Работы!$A$2:$A$6000,0)),"") | G49: =IFERROR(INDEX(спр_Работы!$K$2:$K$6000,MATCH($C49,спр_Работы!$A$2:$A$6000,0)),"") | J49: =IFERROR(INDEX(спр_Материалы!$B$2:$B$9000,MATCH($I49,спр_Материалы!$A$2:$A$9000,0)),"") | K49: =IF($I49="","",IF($F49=IFERROR(INDEX(спр_Материалы!$G$2:$G$9000,MATCH($I49,спр_Материалы!$A$2:$A$9000,0)),""),"OK","!! не та группа")) | L49: =IFERROR(INDEX(спр_Работы!$H$2:$H$6000,MATCH($C49,спр_Работы!$A$2:$A$6000,0))*(1-ДисконтТендер),0) | M49: =IF($I49="",0,IFERROR(INDEX(спр_Материалы!$I$2:$I$9000,MATCH($I49,спр_Материалы!$A$2:$A$9000,0))*IF(INDEX(спр_Материалы!$J$2:$J$9000,MATCH($I49,спр_Материалы!$A$2:$A$9000,0))="USD",КурсUSD,IF(INDEX(спр_Материалы!$J$2:$J$9000,MATCH($I49,спр_Материалы!$A$2:$A$9000,0))="EUR",КурсEUR,1))*INDEX(спр_Материалы!$K$2:$K$9000,MATCH($I49,спр_Материалы!$A$2:$A$9000,0))*(1+IFERROR(INDEX(спр_Работы!$I$2:$I$6000,MATCH($C49,спр_Работы!$A$2:$A$6000,0))/100,0))*(1-ДисконтТендер),0)) | N49: =IF(AND($R49="да",$H49<>""),ROUND($H49*$L49,2),0) | O49: =IF(AND($R49="да",$H49<>""),ROUND($H49*$M49,2),0) | P49: =$N49+$O49 | Q49: =IFERROR(INDEX(спр_Работы!$J$2:$J$6000,MATCH($C49,спр_Работы!$A$2:$A$6000,0)),"") | R49: да | T49: =IF(AND($P49>0,$R49="да"),MAX($T$1:$T48)+1,"")
A50: =IFERROR(INDEX(спр_Работы!$D$2:$D$6000,MATCH($C50,спр_Работы!$A$2:$A$6000,0)),"") | B50: =IFERROR(INDEX(спр_Работы!$F$2:$F$6000,MATCH($C50,спр_Работы!$A$2:$A$6000,0)),"") | C50: =IFERROR(INDEX(спр_Работы!$A$2:$A$6000,49),"") | D50: =IFERROR(INDEX(спр_Работы!$B$2:$B$6000,MATCH($C50,спр_Работы!$A$2:$A$6000,0)),"") | E50: =IFERROR(INDEX(спр_Работы!$C$2:$C$6000,MATCH($C50,спр_Работы!$A$2:$A$6000,0)),"") | F50: =IFERROR(INDEX(спр_Работы!$G$2:$G$6000,MATCH($C50,спр_Работы!$A$2:$A$6000,0)),"") | G50: =IFERROR(INDEX(спр_Работы!$K$2:$K$6000,MATCH($C50,спр_Работы!$A$2:$A$6000,0)),"") | J50: =IFERROR(INDEX(спр_Материалы!$B$2:$B$9000,MATCH($I50,спр_Материалы!$A$2:$A$9000,0)),"") | K50: =IF($I50="","",IF($F50=IFERROR(INDEX(спр_Материалы!$G$2:$G$9000,MATCH($I50,спр_Материалы!$A$2:$A$9000,0)),""),"OK","!! не та группа")) | L50: =IFERROR(INDEX(спр_Работы!$H$2:$H$6000,MATCH($C50,спр_Работы!$A$2:$A$6000,0))*(1-ДисконтТендер),0) | M50: =IF($I50="",0,IFERROR(INDEX(спр_Материалы!$I$2:$I$9000,MATCH($I50,спр_Материалы!$A$2:$A$9000,0))*IF(INDEX(спр_Материалы!$J$2:$J$9000,MATCH($I50,спр_Материалы!$A$2:$A$9000,0))="USD",КурсUSD,IF(INDEX(спр_Материалы!$J$2:$J$9000,MATCH($I50,спр_Материалы!$A$2:$A$9000,0))="EUR",КурсEUR,1))*INDEX(спр_Материалы!$K$2:$K$9000,MATCH($I50,спр_Материалы!$A$2:$A$9000,0))*(1+IFERROR(INDEX(спр_Работы!$I$2:$I$6000,MATCH($C50,спр_Работы!$A$2:$A$6000,0))/100,0))*(1-ДисконтТендер),0)) | N50: =IF(AND($R50="да",$H50<>""),ROUND($H50*$L50,2),0) | O50: =IF(AND($R50="да",$H50<>""),ROUND($H50*$M50,2),0) | P50: =$N50+$O50 | Q50: =IFERROR(INDEX(спр_Работы!$J$2:$J$6000,MATCH($C50,спр_Работы!$A$2:$A$6000,0)),"") | R50: да | T50: =IF(AND($P50>0,$R50="да"),MAX($T$1:$T49)+1,"")
A51: =IFERROR(INDEX(спр_Работы!$D$2:$D$6000,MATCH($C51,спр_Работы!$A$2:$A$6000,0)),"") | B51: =IFERROR(INDEX(спр_Работы!$F$2:$F$6000,MATCH($C51,спр_Работы!$A$2:$A$6000,0)),"") | C51: =IFERROR(INDEX(спр_Работы!$A$2:$A$6000,50),"") | D51: =IFERROR(INDEX(спр_Работы!$B$2:$B$6000,MATCH($C51,спр_Работы!$A$2:$A$6000,0)),"") | E51: =IFERROR(INDEX(спр_Работы!$C$2:$C$6000,MATCH($C51,спр_Работы!$A$2:$A$6000,0)),"") | F51: =IFERROR(INDEX(спр_Работы!$G$2:$G$6000,MATCH($C51,спр_Работы!$A$2:$A$6000,0)),"") | G51: =IFERROR(INDEX(спр_Работы!$K$2:$K$6000,MATCH($C51,спр_Работы!$A$2:$A$6000,0)),"") | J51: =IFERROR(INDEX(спр_Материалы!$B$2:$B$9000,MATCH($I51,спр_Материалы!$A$2:$A$9000,0)),"") | K51: =IF($I51="","",IF($F51=IFERROR(INDEX(спр_Материалы!$G$2:$G$9000,MATCH($I51,спр_Материалы!$A$2:$A$9000,0)),""),"OK","!! не та группа")) | L51: =IFERROR(INDEX(спр_Работы!$H$2:$H$6000,MATCH($C51,спр_Работы!$A$2:$A$6000,0))*(1-ДисконтТендер),0) | M51: =IF($I51="",0,IFERROR(INDEX(спр_Материалы!$I$2:$I$9000,MATCH($I51,спр_Материалы!$A$2:$A$9000,0))*IF(INDEX(спр_Материалы!$J$2:$J$9000,MATCH($I51,спр_Материалы!$A$2:$A$9000,0))="USD",КурсUSD,IF(INDEX(спр_Материалы!$J$2:$J$9000,MATCH($I51,спр_Материалы!$A$2:$A$9000,0))="EUR",КурсEUR,1))*INDEX(спр_Материалы!$K$2:$K$9000,MATCH($I51,спр_Материалы!$A$2:$A$9000,0))*(1+IFERROR(INDEX(спр_Работы!$I$2:$I$6000,MATCH($C51,спр_Работы!$A$2:$A$6000,0))/100,0))*(1-ДисконтТендер),0)) | N51: =IF(AND($R51="да",$H51<>""),ROUND($H51*$L51,2),0) | O51: =IF(AND($R51="да",$H51<>""),ROUND($H51*$M51,2),0) | P51: =$N51+$O51 | Q51: =IFERROR(INDEX(спр_Работы!$J$2:$J$6000,MATCH($C51,спр_Работы!$A$2:$A$6000,0)),"") | R51: да | T51: =IF(AND($P51>0,$R51="да"),MAX($T$1:$T50)+1,"")
A52: =IFERROR(INDEX(спр_Работы!$D$2:$D$6000,MATCH($C52,спр_Работы!$A$2:$A$6000,0)),"") | B52: =IFERROR(INDEX(спр_Работы!$F$2:$F$6000,MATCH($C52,спр_Работы!$A$2:$A$6000,0)),"") | C52: =IFERROR(INDEX(спр_Работы!$A$2:$A$6000,51),"") | D52: =IFERROR(INDEX(спр_Работы!$B$2:$B$6000,MATCH($C52,спр_Работы!$A$2:$A$6000,0)),"") | E52: =IFERROR(INDEX(спр_Работы!$C$2:$C$6000,MATCH($C52,спр_Работы!$A$2:$A$6000,0)),"") | F52: =IFERROR(INDEX(спр_Работы!$G$2:$G$6000,MATCH($C52,спр_Работы!$A$2:$A$6000,0)),"") | G52: =IFERROR(INDEX(спр_Работы!$K$2:$K$6000,MATCH($C52,спр_Работы!$A$2:$A$6000,0)),"") | J52: =IFERROR(INDEX(спр_Материалы!$B$2:$B$9000,MATCH($I52,спр_Материалы!$A$2:$A$9000,0)),"") | K52: =IF($I52="","",IF($F52=IFERROR(INDEX(спр_Материалы!$G$2:$G$9000,MATCH($I52,спр_Материалы!$A$2:$A$9000,0)),""),"OK","!! не та группа")) | L52: =IFERROR(INDEX(спр_Работы!$H$2:$H$6000,MATCH($C52,спр_Работы!$A$2:$A$6000,0))*(1-ДисконтТендер),0) | M52: =IF($I52="",0,IFERROR(INDEX(спр_Материалы!$I$2:$I$9000,MATCH($I52,спр_Материалы!$A$2:$A$9000,0))*IF(INDEX(спр_Материалы!$J$2:$J$9000,MATCH($I52,спр_Материалы!$A$2:$A$9000,0))="USD",КурсUSD,IF(INDEX(спр_Материалы!$J$2:$J$9000,MATCH($I52,спр_Материалы!$A$2:$A$9000,0))="EUR",КурсEUR,1))*INDEX(спр_Материалы!$K$2:$K$9000,MATCH($I52,спр_Материалы!$A$2:$A$9000,0))*(1+IFERROR(INDEX(спр_Работы!$I$2:$I$6000,MATCH($C52,спр_Работы!$A$2:$A$6000,0))/100,0))*(1-ДисконтТендер),0)) | N52: =IF(AND($R52="да",$H52<>""),ROUND($H52*$L52,2),0) | O52: =IF(AND($R52="да",$H52<>""),ROUND($H52*$M52,2),0) | P52: =$N52+$O52 | Q52: =IFERROR(INDEX(спр_Работы!$J$2:$J$6000,MATCH($C52,спр_Работы!$A$2:$A$6000,0)),"") | R52: да | T52: =IF(AND($P52>0,$R52="да"),MAX($T$1:$T51)+1,"")
A53: =IFERROR(INDEX(спр_Работы!$D$2:$D$6000,MATCH($C53,спр_Работы!$A$2:$A$6000,0)),"") | B53: =IFERROR(INDEX(спр_Работы!$F$2:$F$6000,MATCH($C53,спр_Работы!$A$2:$A$6000,0)),"") | C53: =IFERROR(INDEX(спр_Работы!$A$2:$A$6000,52),"") | D53: =IFERROR(INDEX(спр_Работы!$B$2:$B$6000,MATCH($C53,спр_Работы!$A$2:$A$6000,0)),"") | E53: =IFERROR(INDEX(спр_Работы!$C$2:$C$6000,MATCH($C53,спр_Работы!$A$2:$A$6000,0)),"") | F53: =IFERROR(INDEX(спр_Работы!$G$2:$G$6000,MATCH($C53,спр_Работы!$A$2:$A$6000,0)),"") | G53: =IFERROR(INDEX(спр_Работы!$K$2:$K$6000,MATCH($C53,спр_Работы!$A$2:$A$6000,0)),"") | J53: =IFERROR(INDEX(спр_Материалы!$B$2:$B$9000,MATCH($I53,спр_Материалы!$A$2:$A$9000,0)),"") | K53: =IF($I53="","",IF($F53=IFERROR(INDEX(спр_Материалы!$G$2:$G$9000,MATCH($I53,спр_Материалы!$A$2:$A$9000,0)),""),"OK","!! не та группа")) | L53: =IFERROR(INDEX(спр_Работы!$H$2:$H$6000,MATCH($C53,спр_Работы!$A$2:$A$6000,0))*(1-ДисконтТендер),0) | M53: =IF($I53="",0,IFERROR(INDEX(спр_Материалы!$I$2:$I$9000,MATCH($I53,спр_Материалы!$A$2:$A$9000,0))*IF(INDEX(спр_Материалы!$J$2:$J$9000,MATCH($I53,спр_Материалы!$A$2:$A$9000,0))="USD",КурсUSD,IF(INDEX(спр_Материалы!$J$2:$J$9000,MATCH($I53,спр_Материалы!$A$2:$A$9000,0))="EUR",КурсEUR,1))*INDEX(спр_Материалы!$K$2:$K$9000,MATCH($I53,спр_Материалы!$A$2:$A$9000,0))*(1+IFERROR(INDEX(спр_Работы!$I$2:$I$6000,MATCH($C53,спр_Работы!$A$2:$A$6000,0))/100,0))*(1-ДисконтТендер),0)) | N53: =IF(AND($R53="да",$H53<>""),ROUND($H53*$L53,2),0) | O53: =IF(AND($R53="да",$H53<>""),ROUND($H53*$M53,2),0) | P53: =$N53+$O53 | Q53: =IFERROR(INDEX(спр_Работы!$J$2:$J$6000,MATCH($C53,спр_Работы!$A$2:$A$6000,0)),"") | R53: да | T53: =IF(AND($P53>0,$R53="да"),MAX($T$1:$T52)+1,"")
A54: =IFERROR(INDEX(спр_Работы!$D$2:$D$6000,MATCH($C54,спр_Работы!$A$2:$A$6000,0)),"") | B54: =IFERROR(INDEX(спр_Работы!$F$2:$F$6000,MATCH($C54,спр_Работы!$A$2:$A$6000,0)),"") | C54: =IFERROR(INDEX(спр_Работы!$A$2:$A$6000,53),"") | D54: =IFERROR(INDEX(спр_Работы!$B$2:$B$6000,MATCH($C54,спр_Работы!$A$2:$A$6000,0)),"") | E54: =IFERROR(INDEX(спр_Работы!$C$2:$C$6000,MATCH($C54,спр_Работы!$A$2:$A$6000,0)),"") | F54: =IFERROR(INDEX(спр_Работы!$G$2:$G$6000,MATCH($C54,спр_Работы!$A$2:$A$6000,0)),"") | G54: =IFERROR(INDEX(спр_Работы!$K$2:$K$6000,MATCH($C54,спр_Работы!$A$2:$A$6000,0)),"") | J54: =IFERROR(INDEX(спр_Материалы!$B$2:$B$9000,MATCH($I54,спр_Материалы!$A$2:$A$9000,0)),"") | K54: =IF($I54="","",IF($F54=IFERROR(INDEX(спр_Материалы!$G$2:$G$9000,MATCH($I54,спр_Материалы!$A$2:$A$9000,0)),""),"OK","!! не та группа")) | L54: =IFERROR(INDEX(спр_Работы!$H$2:$H$6000,MATCH($C54,спр_Работы!$A$2:$A$6000,0))*(1-ДисконтТендер),0) | M54: =IF($I54="",0,IFERROR(INDEX(спр_Материалы!$I$2:$I$9000,MATCH($I54,спр_Материалы!$A$2:$A$9000,0))*IF(INDEX(спр_Материалы!$J$2:$J$9000,MATCH($I54,спр_Материалы!$A$2:$A$9000,0))="USD",КурсUSD,IF(INDEX(спр_Материалы!$J$2:$J$9000,MATCH($I54,спр_Материалы!$A$2:$A$9000,0))="EUR",КурсEUR,1))*INDEX(спр_Материалы!$K$2:$K$9000,MATCH($I54,спр_Материалы!$A$2:$A$9000,0))*(1+IFERROR(INDEX(спр_Работы!$I$2:$I$6000,MATCH($C54,спр_Работы!$A$2:$A$6000,0))/100,0))*(1-ДисконтТендер),0)) | N54: =IF(AND($R54="да",$H54<>""),ROUND($H54*$L54,2),0) | O54: =IF(AND($R54="да",$H54<>""),ROUND($H54*$M54,2),0) | P54: =$N54+$O54 | Q54: =IFERROR(INDEX(спр_Работы!$J$2:$J$6000,MATCH($C54,спр_Работы!$A$2:$A$6000,0)),"") | R54: да | T54: =IF(AND($P54>0,$R54="да"),MAX($T$1:$T53)+1,"")
A55: =IFERROR(INDEX(спр_Работы!$D$2:$D$6000,MATCH($C55,спр_Работы!$A$2:$A$6000,0)),"") | B55: =IFERROR(INDEX(спр_Работы!$F$2:$F$6000,MATCH($C55,спр_Работы!$A$2:$A$6000,0)),"") | C55: =IFERROR(INDEX(спр_Работы!$A$2:$A$6000,54),"") | D55: =IFERROR(INDEX(спр_Работы!$B$2:$B$6000,MATCH($C55,спр_Работы!$A$2:$A$6000,0)),"") | E55: =IFERROR(INDEX(спр_Работы!$C$2:$C$6000,MATCH($C55,спр_Работы!$A$2:$A$6000,0)),"") | F55: =IFERROR(INDEX(спр_Работы!$G$2:$G$6000,MATCH($C55,спр_Работы!$A$2:$A$6000,0)),"") | G55: =IFERROR(INDEX(спр_Работы!$K$2:$K$6000,MATCH($C55,спр_Работы!$A$2:$A$6000,0)),"") | J55: =IFERROR(INDEX(спр_Материалы!$B$2:$B$9000,MATCH($I55,спр_Материалы!$A$2:$A$9000,0)),"") | K55: =IF($I55="","",IF($F55=IFERROR(INDEX(спр_Материалы!$G$2:$G$9000,MATCH($I55,спр_Материалы!$A$2:$A$9000,0)),""),"OK","!! не та группа")) | L55: =IFERROR(INDEX(спр_Работы!$H$2:$H$6000,MATCH($C55,спр_Работы!$A$2:$A$6000,0))*(1-ДисконтТендер),0) | M55: =IF($I55="",0,IFERROR(INDEX(спр_Материалы!$I$2:$I$9000,MATCH($I55,спр_Материалы!$A$2:$A$9000,0))*IF(INDEX(спр_Материалы!$J$2:$J$9000,MATCH($I55,спр_Материалы!$A$2:$A$9000,0))="USD",КурсUSD,IF(INDEX(спр_Материалы!$J$2:$J$9000,MATCH($I55,спр_Материалы!$A$2:$A$9000,0))="EUR",КурсEUR,1))*INDEX(спр_Материалы!$K$2:$K$9000,MATCH($I55,спр_Материалы!$A$2:$A$9000,0))*(1+IFERROR(INDEX(спр_Работы!$I$2:$I$6000,MATCH($C55,спр_Работы!$A$2:$A$6000,0))/100,0))*(1-ДисконтТендер),0)) | N55: =IF(AND($R55="да",$H55<>""),ROUND($H55*$L55,2),0) | O55: =IF(AND($R55="да",$H55<>""),ROUND($H55*$M55,2),0) | P55: =$N55+$O55 | Q55: =IFERROR(INDEX(спр_Работы!$J$2:$J$6000,MATCH($C55,спр_Работы!$A$2:$A$6000,0)),"") | R55: да | T55: =IF(AND($P55>0,$R55="да"),MAX($T$1:$T54)+1,"")
A56: =IFERROR(INDEX(спр_Работы!$D$2:$D$6000,MATCH($C56,спр_Работы!$A$2:$A$6000,0)),"") | B56: =IFERROR(INDEX(спр_Работы!$F$2:$F$6000,MATCH($C56,спр_Работы!$A$2:$A$6000,0)),"") | C56: =IFERROR(INDEX(спр_Работы!$A$2:$A$6000,55),"") | D56: =IFERROR(INDEX(спр_Работы!$B$2:$B$6000,MATCH($C56,спр_Работы!$A$2:$A$6000,0)),"") | E56: =IFERROR(INDEX(спр_Работы!$C$2:$C$6000,MATCH($C56,спр_Работы!$A$2:$A$6000,0)),"") | F56: =IFERROR(INDEX(спр_Работы!$G$2:$G$6000,MATCH($C56,спр_Работы!$A$2:$A$6000,0)),"") | G56: =IFERROR(INDEX(спр_Работы!$K$2:$K$6000,MATCH($C56,спр_Работы!$A$2:$A$6000,0)),"") | J56: =IFERROR(INDEX(спр_Материалы!$B$2:$B$9000,MATCH($I56,спр_Материалы!$A$2:$A$9000,0)),"") | K56: =IF($I56="","",IF($F56=IFERROR(INDEX(спр_Материалы!$G$2:$G$9000,MATCH($I56,спр_Материалы!$A$2:$A$9000,0)),""),"OK","!! не та группа")) | L56: =IFERROR(INDEX(спр_Работы!$H$2:$H$6000,MATCH($C56,спр_Работы!$A$2:$A$6000,0))*(1-ДисконтТендер),0) | M56: =IF($I56="",0,IFERROR(INDEX(спр_Материалы!$I$2:$I$9000,MATCH($I56,спр_Материалы!$A$2:$A$9000,0))*IF(INDEX(спр_Материалы!$J$2:$J$9000,MATCH($I56,спр_Материалы!$A$2:$A$9000,0))="USD",КурсUSD,IF(INDEX(спр_Материалы!$J$2:$J$9000,MATCH($I56,спр_Материалы!$A$2:$A$9000,0))="EUR",КурсEUR,1))*INDEX(спр_Материалы!$K$2:$K$9000,MATCH($I56,спр_Материалы!$A$2:$A$9000,0))*(1+IFERROR(INDEX(спр_Работы!$I$2:$I$6000,MATCH($C56,спр_Работы!$A$2:$A$6000,0))/100,0))*(1-ДисконтТендер),0)) | N56: =IF(AND($R56="да",$H56<>""),ROUND($H56*$L56,2),0) | O56: =IF(AND($R56="да",$H56<>""),ROUND($H56*$M56,2),0) | P56: =$N56+$O56 | Q56: =IFERROR(INDEX(спр_Работы!$J$2:$J$6000,MATCH($C56,спр_Работы!$A$2:$A$6000,0)),"") | R56: да | T56: =IF(AND($P56>0,$R56="да"),MAX($T$1:$T55)+1,"")
A57: =IFERROR(INDEX(спр_Работы!$D$2:$D$6000,MATCH($C57,спр_Работы!$A$2:$A$6000,0)),"") | B57: =IFERROR(INDEX(спр_Работы!$F$2:$F$6000,MATCH($C57,спр_Работы!$A$2:$A$6000,0)),"") | C57: =IFERROR(INDEX(спр_Работы!$A$2:$A$6000,56),"") | D57: =IFERROR(INDEX(спр_Работы!$B$2:$B$6000,MATCH($C57,спр_Работы!$A$2:$A$6000,0)),"") | E57: =IFERROR(INDEX(спр_Работы!$C$2:$C$6000,MATCH($C57,спр_Работы!$A$2:$A$6000,0)),"") | F57: =IFERROR(INDEX(спр_Работы!$G$2:$G$6000,MATCH($C57,спр_Работы!$A$2:$A$6000,0)),"") | G57: =IFERROR(INDEX(спр_Работы!$K$2:$K$6000,MATCH($C57,спр_Работы!$A$2:$A$6000,0)),"") | J57: =IFERROR(INDEX(спр_Материалы!$B$2:$B$9000,MATCH($I57,спр_Материалы!$A$2:$A$9000,0)),"") | K57: =IF($I57="","",IF($F57=IFERROR(INDEX(спр_Материалы!$G$2:$G$9000,MATCH($I57,спр_Материалы!$A$2:$A$9000,0)),""),"OK","!! не та группа")) | L57: =IFERROR(INDEX(спр_Работы!$H$2:$H$6000,MATCH($C57,спр_Работы!$A$2:$A$6000,0))*(1-ДисконтТендер),0) | M57: =IF($I57="",0,IFERROR(INDEX(спр_Материалы!$I$2:$I$9000,MATCH($I57,спр_Материалы!$A$2:$A$9000,0))*IF(INDEX(спр_Материалы!$J$2:$J$9000,MATCH($I57,спр_Материалы!$A$2:$A$9000,0))="USD",КурсUSD,IF(INDEX(спр_Материалы!$J$2:$J$9000,MATCH($I57,спр_Материалы!$A$2:$A$9000,0))="EUR",КурсEUR,1))*INDEX(спр_Материалы!$K$2:$K$9000,MATCH($I57,спр_Материалы!$A$2:$A$9000,0))*(1+IFERROR(INDEX(спр_Работы!$I$2:$I$6000,MATCH($C57,спр_Работы!$A$2:$A$6000,0))/100,0))*(1-ДисконтТендер),0)) | N57: =IF(AND($R57="да",$H57<>""),ROUND($H57*$L57,2),0) | O57: =IF(AND($R57="да",$H57<>""),ROUND($H57*$M57,2),0) | P57: =$N57+$O57 | Q57: =IFERROR(INDEX(спр_Работы!$J$2:$J$6000,MATCH($C57,спр_Работы!$A$2:$A$6000,0)),"") | R57: да | T57: =IF(AND($P57>0,$R57="да"),MAX($T$1:$T56)+1,"")
A58: =IFERROR(INDEX(спр_Работы!$D$2:$D$6000,MATCH($C58,спр_Работы!$A$2:$A$6000,0)),"") | B58: =IFERROR(INDEX(спр_Работы!$F$2:$F$6000,MATCH($C58,спр_Работы!$A$2:$A$6000,0)),"") | C58: =IFERROR(INDEX(спр_Работы!$A$2:$A$6000,57),"") | D58: =IFERROR(INDEX(спр_Работы!$B$2:$B$6000,MATCH($C58,спр_Работы!$A$2:$A$6000,0)),"") | E58: =IFERROR(INDEX(спр_Работы!$C$2:$C$6000,MATCH($C58,спр_Работы!$A$2:$A$6000,0)),"") | F58: =IFERROR(INDEX(спр_Работы!$G$2:$G$6000,MATCH($C58,спр_Работы!$A$2:$A$6000,0)),"") | G58: =IFERROR(INDEX(спр_Работы!$K$2:$K$6000,MATCH($C58,спр_Работы!$A$2:$A$6000,0)),"") | J58: =IFERROR(INDEX(спр_Материалы!$B$2:$B$9000,MATCH($I58,спр_Материалы!$A$2:$A$9000,0)),"") | K58: =IF($I58="","",IF($F58=IFERROR(INDEX(спр_Материалы!$G$2:$G$9000,MATCH($I58,спр_Материалы!$A$2:$A$9000,0)),""),"OK","!! не та группа")) | L58: =IFERROR(INDEX(спр_Работы!$H$2:$H$6000,MATCH($C58,спр_Работы!$A$2:$A$6000,0))*(1-ДисконтТендер),0) | M58: =IF($I58="",0,IFERROR(INDEX(спр_Материалы!$I$2:$I$9000,MATCH($I58,спр_Материалы!$A$2:$A$9000,0))*IF(INDEX(спр_Материалы!$J$2:$J$9000,MATCH($I58,спр_Материалы!$A$2:$A$9000,0))="USD",КурсUSD,IF(INDEX(спр_Материалы!$J$2:$J$9000,MATCH($I58,спр_Материалы!$A$2:$A$9000,0))="EUR",КурсEUR,1))*INDEX(спр_Материалы!$K$2:$K$9000,MATCH($I58,спр_Материалы!$A$2:$A$9000,0))*(1+IFERROR(INDEX(спр_Работы!$I$2:$I$6000,MATCH($C58,спр_Работы!$A$2:$A$6000,0))/100,0))*(1-ДисконтТендер),0)) | N58: =IF(AND($R58="да",$H58<>""),ROUND($H58*$L58,2),0) | O58: =IF(AND($R58="да",$H58<>""),ROUND($H58*$M58,2),0) | P58: =$N58+$O58 | Q58: =IFERROR(INDEX(спр_Работы!$J$2:$J$6000,MATCH($C58,спр_Работы!$A$2:$A$6000,0)),"") | R58: да | T58: =IF(AND($P58>0,$R58="да"),MAX($T$1:$T57)+1,"")
A59: =IFERROR(INDEX(спр_Работы!$D$2:$D$6000,MATCH($C59,спр_Работы!$A$2:$A$6000,0)),"") | B59: =IFERROR(INDEX(спр_Работы!$F$2:$F$6000,MATCH($C59,спр_Работы!$A$2:$A$6000,0)),"") | C59: =IFERROR(INDEX(спр_Работы!$A$2:$A$6000,58),"") | D59: =IFERROR(INDEX(спр_Работы!$B$2:$B$6000,MATCH($C59,спр_Работы!$A$2:$A$6000,0)),"") | E59: =IFERROR(INDEX(спр_Работы!$C$2:$C$6000,MATCH($C59,спр_Работы!$A$2:$A$6000,0)),"") | F59: =IFERROR(INDEX(спр_Работы!$G$2:$G$6000,MATCH($C59,спр_Работы!$A$2:$A$6000,0)),"") | G59: =IFERROR(INDEX(спр_Работы!$K$2:$K$6000,MATCH($C59,спр_Работы!$A$2:$A$6000,0)),"") | J59: =IFERROR(INDEX(спр_Материалы!$B$2:$B$9000,MATCH($I59,спр_Материалы!$A$2:$A$9000,0)),"") | K59: =IF($I59="","",IF($F59=IFERROR(INDEX(спр_Материалы!$G$2:$G$9000,MATCH($I59,спр_Материалы!$A$2:$A$9000,0)),""),"OK","!! не та группа")) | L59: =IFERROR(INDEX(спр_Работы!$H$2:$H$6000,MATCH($C59,спр_Работы!$A$2:$A$6000,0))*(1-ДисконтТендер),0) | M59: =IF($I59="",0,IFERROR(INDEX(спр_Материалы!$I$2:$I$9000,MATCH($I59,спр_Материалы!$A$2:$A$9000,0))*IF(INDEX(спр_Материалы!$J$2:$J$9000,MATCH($I59,спр_Материалы!$A$2:$A$9000,0))="USD",КурсUSD,IF(INDEX(спр_Материалы!$J$2:$J$9000,MATCH($I59,спр_Материалы!$A$2:$A$9000,0))="EUR",КурсEUR,1))*INDEX(спр_Материалы!$K$2:$K$9000,MATCH($I59,спр_Материалы!$A$2:$A$9000,0))*(1+IFERROR(INDEX(спр_Работы!$I$2:$I$6000,MATCH($C59,спр_Работы!$A$2:$A$6000,0))/100,0))*(1-ДисконтТендер),0)) | N59: =IF(AND($R59="да",$H59<>""),ROUND($H59*$L59,2),0) | O59: =IF(AND($R59="да",$H59<>""),ROUND($H59*$M59,2),0) | P59: =$N59+$O59 | Q59: =IFERROR(INDEX(спр_Работы!$J$2:$J$6000,MATCH($C59,спр_Работы!$A$2:$A$6000,0)),"") | R59: да | T59: =IF(AND($P59>0,$R59="да"),MAX($T$1:$T58)+1,"")
A60: =IFERROR(INDEX(спр_Работы!$D$2:$D$6000,MATCH($C60,спр_Работы!$A$2:$A$6000,0)),"") | B60: =IFERROR(INDEX(спр_Работы!$F$2:$F$6000,MATCH($C60,спр_Работы!$A$2:$A$6000,0)),"") | C60: =IFERROR(INDEX(спр_Работы!$A$2:$A$6000,59),"") | D60: =IFERROR(INDEX(спр_Работы!$B$2:$B$6000,MATCH($C60,спр_Работы!$A$2:$A$6000,0)),"") | E60: =IFERROR(INDEX(спр_Работы!$C$2:$C$6000,MATCH($C60,спр_Работы!$A$2:$A$6000,0)),"") | F60: =IFERROR(INDEX(спр_Работы!$G$2:$G$6000,MATCH($C60,спр_Работы!$A$2:$A$6000,0)),"") | G60: =IFERROR(INDEX(спр_Работы!$K$2:$K$6000,MATCH($C60,спр_Работы!$A$2:$A$6000,0)),"") | J60: =IFERROR(INDEX(спр_Материалы!$B$2:$B$9000,MATCH($I60,спр_Материалы!$A$2:$A$9000,0)),"") | K60: =IF($I60="","",IF($F60=IFERROR(INDEX(спр_Материалы!$G$2:$G$9000,MATCH($I60,спр_Материалы!$A$2:$A$9000,0)),""),"OK","!! не та группа")) | L60: =IFERROR(INDEX(спр_Работы!$H$2:$H$6000,MATCH($C60,спр_Работы!$A$2:$A$6000,0))*(1-ДисконтТендер),0) | M60: =IF($I60="",0,IFERROR(INDEX(спр_Материалы!$I$2:$I$9000,MATCH($I60,спр_Материалы!$A$2:$A$9000,0))*IF(INDEX(спр_Материалы!$J$2:$J$9000,MATCH($I60,спр_Материалы!$A$2:$A$9000,0))="USD",КурсUSD,IF(INDEX(спр_Материалы!$J$2:$J$9000,MATCH($I60,спр_Материалы!$A$2:$A$9000,0))="EUR",КурсEUR,1))*INDEX(спр_Материалы!$K$2:$K$9000,MATCH($I60,спр_Материалы!$A$2:$A$9000,0))*(1+IFERROR(INDEX(спр_Работы!$I$2:$I$6000,MATCH($C60,спр_Работы!$A$2:$A$6000,0))/100,0))*(1-ДисконтТендер),0)) | N60: =IF(AND($R60="да",$H60<>""),ROUND($H60*$L60,2),0) | O60: =IF(AND($R60="да",$H60<>""),ROUND($H60*$M60,2),0) | P60: =$N60+$O60 | Q60: =IFERROR(INDEX(спр_Работы!$J$2:$J$6000,MATCH($C60,спр_Работы!$A$2:$A$6000,0)),"") | R60: да | T60: =IF(AND($P60>0,$R60="да"),MAX($T$1:$T59)+1,"")
A61: =IFERROR(INDEX(спр_Работы!$D$2:$D$6000,MATCH($C61,спр_Работы!$A$2:$A$6000,0)),"") | B61: =IFERROR(INDEX(спр_Работы!$F$2:$F$6000,MATCH($C61,спр_Работы!$A$2:$A$6000,0)),"") | C61: =IFERROR(INDEX(спр_Работы!$A$2:$A$6000,60),"") | D61: =IFERROR(INDEX(спр_Работы!$B$2:$B$6000,MATCH($C61,спр_Работы!$A$2:$A$6000,0)),"") | E61: =IFERROR(INDEX(спр_Работы!$C$2:$C$6000,MATCH($C61,спр_Работы!$A$2:$A$6000,0)),"") | F61: =IFERROR(INDEX(спр_Работы!$G$2:$G$6000,MATCH($C61,спр_Работы!$A$2:$A$6000,0)),"") | G61: =IFERROR(INDEX(спр_Работы!$K$2:$K$6000,MATCH($C61,спр_Работы!$A$2:$A$6000,0)),"") | J61: =IFERROR(INDEX(спр_Материалы!$B$2:$B$9000,MATCH($I61,спр_Материалы!$A$2:$A$9000,0)),"") | K61: =IF($I61="","",IF($F61=IFERROR(INDEX(спр_Материалы!$G$2:$G$9000,MATCH($I61,спр_Материалы!$A$2:$A$9000,0)),""),"OK","!! не та группа")) | L61: =IFERROR(INDEX(спр_Работы!$H$2:$H$6000,MATCH($C61,спр_Работы!$A$2:$A$6000,0))*(1-ДисконтТендер),0) | M61: =IF($I61="",0,IFERROR(INDEX(спр_Материалы!$I$2:$I$9000,MATCH($I61,спр_Материалы!$A$2:$A$9000,0))*IF(INDEX(спр_Материалы!$J$2:$J$9000,MATCH($I61,спр_Материалы!$A$2:$A$9000,0))="USD",КурсUSD,IF(INDEX(спр_Материалы!$J$2:$J$9000,MATCH($I61,спр_Материалы!$A$2:$A$9000,0))="EUR",КурсEUR,1))*INDEX(спр_Материалы!$K$2:$K$9000,MATCH($I61,спр_Материалы!$A$2:$A$9000,0))*(1+IFERROR(INDEX(спр_Работы!$I$2:$I$6000,MATCH($C61,спр_Работы!$A$2:$A$6000,0))/100,0))*(1-ДисконтТендер),0)) | N61: =IF(AND($R61="да",$H61<>""),ROUND($H61*$L61,2),0) | O61: =IF(AND($R61="да",$H61<>""),ROUND($H61*$M61,2),0) | P61: =$N61+$O61 | Q61: =IFERROR(INDEX(спр_Работы!$J$2:$J$6000,MATCH($C61,спр_Работы!$A$2:$A$6000,0)),"") | R61: да | T61: =IF(AND($P61>0,$R61="да"),MAX($T$1:$T60)+1,"")
A62: =IFERROR(INDEX(спр_Работы!$D$2:$D$6000,MATCH($C62,спр_Работы!$A$2:$A$6000,0)),"") | B62: =IFERROR(INDEX(спр_Работы!$F$2:$F$6000,MATCH($C62,спр_Работы!$A$2:$A$6000,0)),"") | C62: =IFERROR(INDEX(спр_Работы!$A$2:$A$6000,61),"") | D62: =IFERROR(INDEX(спр_Работы!$B$2:$B$6000,MATCH($C62,спр_Работы!$A$2:$A$6000,0)),"") | E62: =IFERROR(INDEX(спр_Работы!$C$2:$C$6000,MATCH($C62,спр_Работы!$A$2:$A$6000,0)),"") | F62: =IFERROR(INDEX(спр_Работы!$G$2:$G$6000,MATCH($C62,спр_Работы!$A$2:$A$6000,0)),"") | G62: =IFERROR(INDEX(спр_Работы!$K$2:$K$6000,MATCH($C62,спр_Работы!$A$2:$A$6000,0)),"") | J62: =IFERROR(INDEX(спр_Материалы!$B$2:$B$9000,MATCH($I62,спр_Материалы!$A$2:$A$9000,0)),"") | K62: =IF($I62="","",IF($F62=IFERROR(INDEX(спр_Материалы!$G$2:$G$9000,MATCH($I62,спр_Материалы!$A$2:$A$9000,0)),""),"OK","!! не та группа")) | L62: =IFERROR(INDEX(спр_Работы!$H$2:$H$6000,MATCH($C62,спр_Работы!$A$2:$A$6000,0))*(1-ДисконтТендер),0) | M62: =IF($I62="",0,IFERROR(INDEX(спр_Материалы!$I$2:$I$9000,MATCH($I62,спр_Материалы!$A$2:$A$9000,0))*IF(INDEX(спр_Материалы!$J$2:$J$9000,MATCH($I62,спр_Материалы!$A$2:$A$9000,0))="USD",КурсUSD,IF(INDEX(спр_Материалы!$J$2:$J$9000,MATCH($I62,спр_Материалы!$A$2:$A$9000,0))="EUR",КурсEUR,1))*INDEX(спр_Материалы!$K$2:$K$9000,MATCH($I62,спр_Материалы!$A$2:$A$9000,0))*(1+IFERROR(INDEX(спр_Работы!$I$2:$I$6000,MATCH($C62,спр_Работы!$A$2:$A$6000,0))/100,0))*(1-ДисконтТендер),0)) | N62: =IF(AND($R62="да",$H62<>""),ROUND($H62*$L62,2),0) | O62: =IF(AND($R62="да",$H62<>""),ROUND($H62*$M62,2),0) | P62: =$N62+$O62 | Q62: =IFERROR(INDEX(спр_Работы!$J$2:$J$6000,MATCH($C62,спр_Работы!$A$2:$A$6000,0)),"") | R62: да | T62: =IF(AND($P62>0,$R62="да"),MAX($T$1:$T61)+1,"")
A63: =IFERROR(INDEX(спр_Работы!$D$2:$D$6000,MATCH($C63,спр_Работы!$A$2:$A$6000,0)),"") | B63: =IFERROR(INDEX(спр_Работы!$F$2:$F$6000,MATCH($C63,спр_Работы!$A$2:$A$6000,0)),"") | C63: =IFERROR(INDEX(спр_Работы!$A$2:$A$6000,62),"") | D63: =IFERROR(INDEX(спр_Работы!$B$2:$B$6000,MATCH($C63,спр_Работы!$A$2:$A$6000,0)),"") | E63: =IFERROR(INDEX(спр_Работы!$C$2:$C$6000,MATCH($C63,спр_Работы!$A$2:$A$6000,0)),"") | F63: =IFERROR(INDEX(спр_Работы!$G$2:$G$6000,MATCH($C63,спр_Работы!$A$2:$A$6000,0)),"") | G63: =IFERROR(INDEX(спр_Работы!$K$2:$K$6000,MATCH($C63,спр_Работы!$A$2:$A$6000,0)),"") | J63: =IFERROR(INDEX(спр_Материалы!$B$2:$B$9000,MATCH($I63,спр_Материалы!$A$2:$A$9000,0)),"") | K63: =IF($I63="","",IF($F63=IFERROR(INDEX(спр_Материалы!$G$2:$G$9000,MATCH($I63,спр_Материалы!$A$2:$A$9000,0)),""),"OK","!! не та группа")) | L63: =IFERROR(INDEX(спр_Работы!$H$2:$H$6000,MATCH($C63,спр_Работы!$A$2:$A$6000,0))*(1-ДисконтТендер),0) | M63: =IF($I63="",0,IFERROR(INDEX(спр_Материалы!$I$2:$I$9000,MATCH($I63,спр_Материалы!$A$2:$A$9000,0))*IF(INDEX(спр_Материалы!$J$2:$J$9000,MATCH($I63,спр_Материалы!$A$2:$A$9000,0))="USD",КурсUSD,IF(INDEX(спр_Материалы!$J$2:$J$9000,MATCH($I63,спр_Материалы!$A$2:$A$9000,0))="EUR",КурсEUR,1))*INDEX(спр_Материалы!$K$2:$K$9000,MATCH($I63,спр_Материалы!$A$2:$A$9000,0))*(1+IFERROR(INDEX(спр_Работы!$I$2:$I$6000,MATCH($C63,спр_Работы!$A$2:$A$6000,0))/100,0))*(1-ДисконтТендер),0)) | N63: =IF(AND($R63="да",$H63<>""),ROUND($H63*$L63,2),0) | O63: =IF(AND($R63="да",$H63<>""),ROUND($H63*$M63,2),0) | P63: =$N63+$O63 | Q63: =IFERROR(INDEX(спр_Работы!$J$2:$J$6000,MATCH($C63,спр_Работы!$A$2:$A$6000,0)),"") | R63: да | T63: =IF(AND($P63>0,$R63="да"),MAX($T$1:$T62)+1,"")
A64: =IFERROR(INDEX(спр_Работы!$D$2:$D$6000,MATCH($C64,спр_Работы!$A$2:$A$6000,0)),"") | B64: =IFERROR(INDEX(спр_Работы!$F$2:$F$6000,MATCH($C64,спр_Работы!$A$2:$A$6000,0)),"") | C64: =IFERROR(INDEX(спр_Работы!$A$2:$A$6000,63),"") | D64: =IFERROR(INDEX(спр_Работы!$B$2:$B$6000,MATCH($C64,спр_Работы!$A$2:$A$6000,0)),"") | E64: =IFERROR(INDEX(спр_Работы!$C$2:$C$6000,MATCH($C64,спр_Работы!$A$2:$A$6000,0)),"") | F64: =IFERROR(INDEX(спр_Работы!$G$2:$G$6000,MATCH($C64,спр_Работы!$A$2:$A$6000,0)),"") | G64: =IFERROR(INDEX(спр_Работы!$K$2:$K$6000,MATCH($C64,спр_Работы!$A$2:$A$6000,0)),"") | J64: =IFERROR(INDEX(спр_Материалы!$B$2:$B$9000,MATCH($I64,спр_Материалы!$A$2:$A$9000,0)),"") | K64: =IF($I64="","",IF($F64=IFERROR(INDEX(спр_Материалы!$G$2:$G$9000,MATCH($I64,спр_Материалы!$A$2:$A$9000,0)),""),"OK","!! не та группа")) | L64: =IFERROR(INDEX(спр_Работы!$H$2:$H$6000,MATCH($C64,спр_Работы!$A$2:$A$6000,0))*(1-ДисконтТендер),0) | M64: =IF($I64="",0,IFERROR(INDEX(спр_Материалы!$I$2:$I$9000,MATCH($I64,спр_Материалы!$A$2:$A$9000,0))*IF(INDEX(спр_Материалы!$J$2:$J$9000,MATCH($I64,спр_Материалы!$A$2:$A$9000,0))="USD",КурсUSD,IF(INDEX(спр_Материалы!$J$2:$J$9000,MATCH($I64,спр_Материалы!$A$2:$A$9000,0))="EUR",КурсEUR,1))*INDEX(спр_Материалы!$K$2:$K$9000,MATCH($I64,спр_Материалы!$A$2:$A$9000,0))*(1+IFERROR(INDEX(спр_Работы!$I$2:$I$6000,MATCH($C64,спр_Работы!$A$2:$A$6000,0))/100,0))*(1-ДисконтТендер),0)) | N64: =IF(AND($R64="да",$H64<>""),ROUND($H64*$L64,2),0) | O64: =IF(AND($R64="да",$H64<>""),ROUND($H64*$M64,2),0) | P64: =$N64+$O64 | Q64: =IFERROR(INDEX(спр_Работы!$J$2:$J$6000,MATCH($C64,спр_Работы!$A$2:$A$6000,0)),"") | R64: да | T64: =IF(AND($P64>0,$R64="да"),MAX($T$1:$T63)+1,"")
A65: =IFERROR(INDEX(спр_Работы!$D$2:$D$6000,MATCH($C65,спр_Работы!$A$2:$A$6000,0)),"") | B65: =IFERROR(INDEX(спр_Работы!$F$2:$F$6000,MATCH($C65,спр_Работы!$A$2:$A$6000,0)),"") | C65: =IFERROR(INDEX(спр_Работы!$A$2:$A$6000,64),"") | D65: =IFERROR(INDEX(спр_Работы!$B$2:$B$6000,MATCH($C65,спр_Работы!$A$2:$A$6000,0)),"") | E65: =IFERROR(INDEX(спр_Работы!$C$2:$C$6000,MATCH($C65,спр_Работы!$A$2:$A$6000,0)),"") | F65: =IFERROR(INDEX(спр_Работы!$G$2:$G$6000,MATCH($C65,спр_Работы!$A$2:$A$6000,0)),"") | G65: =IFERROR(INDEX(спр_Работы!$K$2:$K$6000,MATCH($C65,спр_Работы!$A$2:$A$6000,0)),"") | J65: =IFERROR(INDEX(спр_Материалы!$B$2:$B$9000,MATCH($I65,спр_Материалы!$A$2:$A$9000,0)),"") | K65: =IF($I65="","",IF($F65=IFERROR(INDEX(спр_Материалы!$G$2:$G$9000,MATCH($I65,спр_Материалы!$A$2:$A$9000,0)),""),"OK","!! не та группа")) | L65: =IFERROR(INDEX(спр_Работы!$H$2:$H$6000,MATCH($C65,спр_Работы!$A$2:$A$6000,0))*(1-ДисконтТендер),0) | M65: =IF($I65="",0,IFERROR(INDEX(спр_Материалы!$I$2:$I$9000,MATCH($I65,спр_Материалы!$A$2:$A$9000,0))*IF(INDEX(спр_Материалы!$J$2:$J$9000,MATCH($I65,спр_Материалы!$A$2:$A$9000,0))="USD",КурсUSD,IF(INDEX(спр_Материалы!$J$2:$J$9000,MATCH($I65,спр_Материалы!$A$2:$A$9000,0))="EUR",КурсEUR,1))*INDEX(спр_Материалы!$K$2:$K$9000,MATCH($I65,спр_Материалы!$A$2:$A$9000,0))*(1+IFERROR(INDEX(спр_Работы!$I$2:$I$6000,MATCH($C65,спр_Работы!$A$2:$A$6000,0))/100,0))*(1-ДисконтТендер),0)) | N65: =IF(AND($R65="да",$H65<>""),ROUND($H65*$L65,2),0) | O65: =IF(AND($R65="да",$H65<>""),ROUND($H65*$M65,2),0) | P65: =$N65+$O65 | Q65: =IFERROR(INDEX(спр_Работы!$J$2:$J$6000,MATCH($C65,спр_Работы!$A$2:$A$6000,0)),"") | R65: да | T65: =IF(AND($P65>0,$R65="да"),MAX($T$1:$T64)+1,"")
A66: =IFERROR(INDEX(спр_Работы!$D$2:$D$6000,MATCH($C66,спр_Работы!$A$2:$A$6000,0)),"") | B66: =IFERROR(INDEX(спр_Работы!$F$2:$F$6000,MATCH($C66,спр_Работы!$A$2:$A$6000,0)),"") | C66: =IFERROR(INDEX(спр_Работы!$A$2:$A$6000,65),"") | D66: =IFERROR(INDEX(спр_Работы!$B$2:$B$6000,MATCH($C66,спр_Работы!$A$2:$A$6000,0)),"") | E66: =IFERROR(INDEX(спр_Работы!$C$2:$C$6000,MATCH($C66,спр_Работы!$A$2:$A$6000,0)),"") | F66: =IFERROR(INDEX(спр_Работы!$G$2:$G$6000,MATCH($C66,спр_Работы!$A$2:$A$6000,0)),"") | G66: =IFERROR(INDEX(спр_Работы!$K$2:$K$6000,MATCH($C66,спр_Работы!$A$2:$A$6000,0)),"") | J66: =IFERROR(INDEX(спр_Материалы!$B$2:$B$9000,MATCH($I66,спр_Материалы!$A$2:$A$9000,0)),"") | K66: =IF($I66="","",IF($F66=IFERROR(INDEX(спр_Материалы!$G$2:$G$9000,MATCH($I66,спр_Материалы!$A$2:$A$9000,0)),""),"OK","!! не та группа")) | L66: =IFERROR(INDEX(спр_Работы!$H$2:$H$6000,MATCH($C66,спр_Работы!$A$2:$A$6000,0))*(1-ДисконтТендер),0) | M66: =IF($I66="",0,IFERROR(INDEX(спр_Материалы!$I$2:$I$9000,MATCH($I66,спр_Материалы!$A$2:$A$9000,0))*IF(INDEX(спр_Материалы!$J$2:$J$9000,MATCH($I66,спр_Материалы!$A$2:$A$9000,0))="USD",КурсUSD,IF(INDEX(спр_Материалы!$J$2:$J$9000,MATCH($I66,спр_Материалы!$A$2:$A$9000,0))="EUR",КурсEUR,1))*INDEX(спр_Материалы!$K$2:$K$9000,MATCH($I66,спр_Материалы!$A$2:$A$9000,0))*(1+IFERROR(INDEX(спр_Работы!$I$2:$I$6000,MATCH($C66,спр_Работы!$A$2:$A$6000,0))/100,0))*(1-ДисконтТендер),0)) | N66: =IF(AND($R66="да",$H66<>""),ROUND($H66*$L66,2),0) | O66: =IF(AND($R66="да",$H66<>""),ROUND($H66*$M66,2),0) | P66: =$N66+$O66 | Q66: =IFERROR(INDEX(спр_Работы!$J$2:$J$6000,MATCH($C66,спр_Работы!$A$2:$A$6000,0)),"") | R66: да | T66: =IF(AND($P66>0,$R66="да"),MAX($T$1:$T65)+1,"")
A67: =IFERROR(INDEX(спр_Работы!$D$2:$D$6000,MATCH($C67,спр_Работы!$A$2:$A$6000,0)),"") | B67: =IFERROR(INDEX(спр_Работы!$F$2:$F$6000,MATCH($C67,спр_Работы!$A$2:$A$6000,0)),"") | C67: =IFERROR(INDEX(спр_Работы!$A$2:$A$6000,66),"") | D67: =IFERROR(INDEX(спр_Работы!$B$2:$B$6000,MATCH($C67,спр_Работы!$A$2:$A$6000,0)),"") | E67: =IFERROR(INDEX(спр_Работы!$C$2:$C$6000,MATCH($C67,спр_Работы!$A$2:$A$6000,0)),"") | F67: =IFERROR(INDEX(спр_Работы!$G$2:$G$6000,MATCH($C67,спр_Работы!$A$2:$A$6000,0)),"") | G67: =IFERROR(INDEX(спр_Работы!$K$2:$K$6000,MATCH($C67,спр_Работы!$A$2:$A$6000,0)),"") | J67: =IFERROR(INDEX(спр_Материалы!$B$2:$B$9000,MATCH($I67,спр_Материалы!$A$2:$A$9000,0)),"") | K67: =IF($I67="","",IF($F67=IFERROR(INDEX(спр_Материалы!$G$2:$G$9000,MATCH($I67,спр_Материалы!$A$2:$A$9000,0)),""),"OK","!! не та группа")) | L67: =IFERROR(INDEX(спр_Работы!$H$2:$H$6000,MATCH($C67,спр_Работы!$A$2:$A$6000,0))*(1-ДисконтТендер),0) | M67: =IF($I67="",0,IFERROR(INDEX(спр_Материалы!$I$2:$I$9000,MATCH($I67,спр_Материалы!$A$2:$A$9000,0))*IF(INDEX(спр_Материалы!$J$2:$J$9000,MATCH($I67,спр_Материалы!$A$2:$A$9000,0))="USD",КурсUSD,IF(INDEX(спр_Материалы!$J$2:$J$9000,MATCH($I67,спр_Материалы!$A$2:$A$9000,0))="EUR",КурсEUR,1))*INDEX(спр_Материалы!$K$2:$K$9000,MATCH($I67,спр_Материалы!$A$2:$A$9000,0))*(1+IFERROR(INDEX(спр_Работы!$I$2:$I$6000,MATCH($C67,спр_Работы!$A$2:$A$6000,0))/100,0))*(1-ДисконтТендер),0)) | N67: =IF(AND($R67="да",$H67<>""),ROUND($H67*$L67,2),0) | O67: =IF(AND($R67="да",$H67<>""),ROUND($H67*$M67,2),0) | P67: =$N67+$O67 | Q67: =IFERROR(INDEX(спр_Работы!$J$2:$J$6000,MATCH($C67,спр_Работы!$A$2:$A$6000,0)),"") | R67: да | T67: =IF(AND($P67>0,$R67="да"),MAX($T$1:$T66)+1,"")
A68: =IFERROR(INDEX(спр_Работы!$D$2:$D$6000,MATCH($C68,спр_Работы!$A$2:$A$6000,0)),"") | B68: =IFERROR(INDEX(спр_Работы!$F$2:$F$6000,MATCH($C68,спр_Работы!$A$2:$A$6000,0)),"") | C68: =IFERROR(INDEX(спр_Работы!$A$2:$A$6000,67),"") | D68: =IFERROR(INDEX(спр_Работы!$B$2:$B$6000,MATCH($C68,спр_Работы!$A$2:$A$6000,0)),"") | E68: =IFERROR(INDEX(спр_Работы!$C$2:$C$6000,MATCH($C68,спр_Работы!$A$2:$A$6000,0)),"") | F68: =IFERROR(INDEX(спр_Работы!$G$2:$G$6000,MATCH($C68,спр_Работы!$A$2:$A$6000,0)),"") | G68: =IFERROR(INDEX(спр_Работы!$K$2:$K$6000,MATCH($C68,спр_Работы!$A$2:$A$6000,0)),"") | J68: =IFERROR(INDEX(спр_Материалы!$B$2:$B$9000,MATCH($I68,спр_Материалы!$A$2:$A$9000,0)),"") | K68: =IF($I68="","",IF($F68=IFERROR(INDEX(спр_Материалы!$G$2:$G$9000,MATCH($I68,спр_Материалы!$A$2:$A$9000,0)),""),"OK","!! не та группа")) | L68: =IFERROR(INDEX(спр_Работы!$H$2:$H$6000,MATCH($C68,спр_Работы!$A$2:$A$6000,0))*(1-ДисконтТендер),0) | M68: =IF($I68="",0,IFERROR(INDEX(спр_Материалы!$I$2:$I$9000,MATCH($I68,спр_Материалы!$A$2:$A$9000,0))*IF(INDEX(спр_Материалы!$J$2:$J$9000,MATCH($I68,спр_Материалы!$A$2:$A$9000,0))="USD",КурсUSD,IF(INDEX(спр_Материалы!$J$2:$J$9000,MATCH($I68,спр_Материалы!$A$2:$A$9000,0))="EUR",КурсEUR,1))*INDEX(спр_Материалы!$K$2:$K$9000,MATCH($I68,спр_Материалы!$A$2:$A$9000,0))*(1+IFERROR(INDEX(спр_Работы!$I$2:$I$6000,MATCH($C68,спр_Работы!$A$2:$A$6000,0))/100,0))*(1-ДисконтТендер),0)) | N68: =IF(AND($R68="да",$H68<>""),ROUND($H68*$L68,2),0) | O68: =IF(AND($R68="да",$H68<>""),ROUND($H68*$M68,2),0) | P68: =$N68+$O68 | Q68: =IFERROR(INDEX(спр_Работы!$J$2:$J$6000,MATCH($C68,спр_Работы!$A$2:$A$6000,0)),"") | R68: да | T68: =IF(AND($P68>0,$R68="да"),MAX($T$1:$T67)+1,"")
A69: =IFERROR(INDEX(спр_Работы!$D$2:$D$6000,MATCH($C69,спр_Работы!$A$2:$A$6000,0)),"") | B69: =IFERROR(INDEX(спр_Работы!$F$2:$F$6000,MATCH($C69,спр_Работы!$A$2:$A$6000,0)),"") | C69: =IFERROR(INDEX(спр_Работы!$A$2:$A$6000,68),"") | D69: =IFERROR(INDEX(спр_Работы!$B$2:$B$6000,MATCH($C69,спр_Работы!$A$2:$A$6000,0)),"") | E69: =IFERROR(INDEX(спр_Работы!$C$2:$C$6000,MATCH($C69,спр_Работы!$A$2:$A$6000,0)),"") | F69: =IFERROR(INDEX(спр_Работы!$G$2:$G$6000,MATCH($C69,спр_Работы!$A$2:$A$6000,0)),"") | G69: =IFERROR(INDEX(спр_Работы!$K$2:$K$6000,MATCH($C69,спр_Работы!$A$2:$A$6000,0)),"") | J69: =IFERROR(INDEX(спр_Материалы!$B$2:$B$9000,MATCH($I69,спр_Материалы!$A$2:$A$9000,0)),"") | K69: =IF($I69="","",IF($F69=IFERROR(INDEX(спр_Материалы!$G$2:$G$9000,MATCH($I69,спр_Материалы!$A$2:$A$9000,0)),""),"OK","!! не та группа")) | L69: =IFERROR(INDEX(спр_Работы!$H$2:$H$6000,MATCH($C69,спр_Работы!$A$2:$A$6000,0))*(1-ДисконтТендер),0) | M69: =IF($I69="",0,IFERROR(INDEX(спр_Материалы!$I$2:$I$9000,MATCH($I69,спр_Материалы!$A$2:$A$9000,0))*IF(INDEX(спр_Материалы!$J$2:$J$9000,MATCH($I69,спр_Материалы!$A$2:$A$9000,0))="USD",КурсUSD,IF(INDEX(спр_Материалы!$J$2:$J$9000,MATCH($I69,спр_Материалы!$A$2:$A$9000,0))="EUR",КурсEUR,1))*INDEX(спр_Материалы!$K$2:$K$9000,MATCH($I69,спр_Материалы!$A$2:$A$9000,0))*(1+IFERROR(INDEX(спр_Работы!$I$2:$I$6000,MATCH($C69,спр_Работы!$A$2:$A$6000,0))/100,0))*(1-ДисконтТендер),0)) | N69: =IF(AND($R69="да",$H69<>""),ROUND($H69*$L69,2),0) | O69: =IF(AND($R69="да",$H69<>""),ROUND($H69*$M69,2),0) | P69: =$N69+$O69 | Q69: =IFERROR(INDEX(спр_Работы!$J$2:$J$6000,MATCH($C69,спр_Работы!$A$2:$A$6000,0)),"") | R69: да | T69: =IF(AND($P69>0,$R69="да"),MAX($T$1:$T68)+1,"")
A70: =IFERROR(INDEX(спр_Работы!$D$2:$D$6000,MATCH($C70,спр_Работы!$A$2:$A$6000,0)),"") | B70: =IFERROR(INDEX(спр_Работы!$F$2:$F$6000,MATCH($C70,спр_Работы!$A$2:$A$6000,0)),"") | C70: =IFERROR(INDEX(спр_Работы!$A$2:$A$6000,69),"") | D70: =IFERROR(INDEX(спр_Работы!$B$2:$B$6000,MATCH($C70,спр_Работы!$A$2:$A$6000,0)),"") | E70: =IFERROR(INDEX(спр_Работы!$C$2:$C$6000,MATCH($C70,спр_Работы!$A$2:$A$6000,0)),"") | F70: =IFERROR(INDEX(спр_Работы!$G$2:$G$6000,MATCH($C70,спр_Работы!$A$2:$A$6000,0)),"") | G70: =IFERROR(INDEX(спр_Работы!$K$2:$K$6000,MATCH($C70,спр_Работы!$A$2:$A$6000,0)),"") | J70: =IFERROR(INDEX(спр_Материалы!$B$2:$B$9000,MATCH($I70,спр_Материалы!$A$2:$A$9000,0)),"") | K70: =IF($I70="","",IF($F70=IFERROR(INDEX(спр_Материалы!$G$2:$G$9000,MATCH($I70,спр_Материалы!$A$2:$A$9000,0)),""),"OK","!! не та группа")) | L70: =IFERROR(INDEX(спр_Работы!$H$2:$H$6000,MATCH($C70,спр_Работы!$A$2:$A$6000,0))*(1-ДисконтТендер),0) | M70: =IF($I70="",0,IFERROR(INDEX(спр_Материалы!$I$2:$I$9000,MATCH($I70,спр_Материалы!$A$2:$A$9000,0))*IF(INDEX(спр_Материалы!$J$2:$J$9000,MATCH($I70,спр_Материалы!$A$2:$A$9000,0))="USD",КурсUSD,IF(INDEX(спр_Материалы!$J$2:$J$9000,MATCH($I70,спр_Материалы!$A$2:$A$9000,0))="EUR",КурсEUR,1))*INDEX(спр_Материалы!$K$2:$K$9000,MATCH($I70,спр_Материалы!$A$2:$A$9000,0))*(1+IFERROR(INDEX(спр_Работы!$I$2:$I$6000,MATCH($C70,спр_Работы!$A$2:$A$6000,0))/100,0))*(1-ДисконтТендер),0)) | N70: =IF(AND($R70="да",$H70<>""),ROUND($H70*$L70,2),0) | O70: =IF(AND($R70="да",$H70<>""),ROUND($H70*$M70,2),0) | P70: =$N70+$O70 | Q70: =IFERROR(INDEX(спр_Работы!$J$2:$J$6000,MATCH($C70,спр_Работы!$A$2:$A$6000,0)),"") | R70: да | T70: =IF(AND($P70>0,$R70="да"),MAX($T$1:$T69)+1,"")
A71: =IFERROR(INDEX(спр_Работы!$D$2:$D$6000,MATCH($C71,спр_Работы!$A$2:$A$6000,0)),"") | B71: =IFERROR(INDEX(спр_Работы!$F$2:$F$6000,MATCH($C71,спр_Работы!$A$2:$A$6000,0)),"") | C71: =IFERROR(INDEX(спр_Работы!$A$2:$A$6000,70),"") | D71: =IFERROR(INDEX(спр_Работы!$B$2:$B$6000,MATCH($C71,спр_Работы!$A$2:$A$6000,0)),"") | E71: =IFERROR(INDEX(спр_Работы!$C$2:$C$6000,MATCH($C71,спр_Работы!$A$2:$A$6000,0)),"") | F71: =IFERROR(INDEX(спр_Работы!$G$2:$G$6000,MATCH($C71,спр_Работы!$A$2:$A$6000,0)),"") | G71: =IFERROR(INDEX(спр_Работы!$K$2:$K$6000,MATCH($C71,спр_Работы!$A$2:$A$6000,0)),"") | J71: =IFERROR(INDEX(спр_Материалы!$B$2:$B$9000,MATCH($I71,спр_Материалы!$A$2:$A$9000,0)),"") | K71: =IF($I71="","",IF($F71=IFERROR(INDEX(спр_Материалы!$G$2:$G$9000,MATCH($I71,спр_Материалы!$A$2:$A$9000,0)),""),"OK","!! не та группа")) | L71: =IFERROR(INDEX(спр_Работы!$H$2:$H$6000,MATCH($C71,спр_Работы!$A$2:$A$6000,0))*(1-ДисконтТендер),0) | M71: =IF($I71="",0,IFERROR(INDEX(спр_Материалы!$I$2:$I$9000,MATCH($I71,спр_Материалы!$A$2:$A$9000,0))*IF(INDEX(спр_Материалы!$J$2:$J$9000,MATCH($I71,спр_Материалы!$A$2:$A$9000,0))="USD",КурсUSD,IF(INDEX(спр_Материалы!$J$2:$J$9000,MATCH($I71,спр_Материалы!$A$2:$A$9000,0))="EUR",КурсEUR,1))*INDEX(спр_Материалы!$K$2:$K$9000,MATCH($I71,спр_Материалы!$A$2:$A$9000,0))*(1+IFERROR(INDEX(спр_Работы!$I$2:$I$6000,MATCH($C71,спр_Работы!$A$2:$A$6000,0))/100,0))*(1-ДисконтТендер),0)) | N71: =IF(AND($R71="да",$H71<>""),ROUND($H71*$L71,2),0) | O71: =IF(AND($R71="да",$H71<>""),ROUND($H71*$M71,2),0) | P71: =$N71+$O71 | Q71: =IFERROR(INDEX(спр_Работы!$J$2:$J$6000,MATCH($C71,спр_Работы!$A$2:$A$6000,0)),"") | R71: да | T71: =IF(AND($P71>0,$R71="да"),MAX($T$1:$T70)+1,"")
A72: =IFERROR(INDEX(спр_Работы!$D$2:$D$6000,MATCH($C72,спр_Работы!$A$2:$A$6000,0)),"") | B72: =IFERROR(INDEX(спр_Работы!$F$2:$F$6000,MATCH($C72,спр_Работы!$A$2:$A$6000,0)),"") | C72: =IFERROR(INDEX(спр_Работы!$A$2:$A$6000,71),"") | D72: =IFERROR(INDEX(спр_Работы!$B$2:$B$6000,MATCH($C72,спр_Работы!$A$2:$A$6000,0)),"") | E72: =IFERROR(INDEX(спр_Работы!$C$2:$C$6000,MATCH($C72,спр_Работы!$A$2:$A$6000,0)),"") | F72: =IFERROR(INDEX(спр_Работы!$G$2:$G$6000,MATCH($C72,спр_Работы!$A$2:$A$6000,0)),"") | G72: =IFERROR(INDEX(спр_Работы!$K$2:$K$6000,MATCH($C72,спр_Работы!$A$2:$A$6000,0)),"") | J72: =IFERROR(INDEX(спр_Материалы!$B$2:$B$9000,MATCH($I72,спр_Материалы!$A$2:$A$9000,0)),"") | K72: =IF($I72="","",IF($F72=IFERROR(INDEX(спр_Материалы!$G$2:$G$9000,MATCH($I72,спр_Материалы!$A$2:$A$9000,0)),""),"OK","!! не та группа")) | L72: =IFERROR(INDEX(спр_Работы!$H$2:$H$6000,MATCH($C72,спр_Работы!$A$2:$A$6000,0))*(1-ДисконтТендер),0) | M72: =IF($I72="",0,IFERROR(INDEX(спр_Материалы!$I$2:$I$9000,MATCH($I72,спр_Материалы!$A$2:$A$9000,0))*IF(INDEX(спр_Материалы!$J$2:$J$9000,MATCH($I72,спр_Материалы!$A$2:$A$9000,0))="USD",КурсUSD,IF(INDEX(спр_Материалы!$J$2:$J$9000,MATCH($I72,спр_Материалы!$A$2:$A$9000,0))="EUR",КурсEUR,1))*INDEX(спр_Материалы!$K$2:$K$9000,MATCH($I72,спр_Материалы!$A$2:$A$9000,0))*(1+IFERROR(INDEX(спр_Работы!$I$2:$I$6000,MATCH($C72,спр_Работы!$A$2:$A$6000,0))/100,0))*(1-ДисконтТендер),0)) | N72: =IF(AND($R72="да",$H72<>""),ROUND($H72*$L72,2),0) | O72: =IF(AND($R72="да",$H72<>""),ROUND($H72*$M72,2),0) | P72: =$N72+$O72 | Q72: =IFERROR(INDEX(спр_Работы!$J$2:$J$6000,MATCH($C72,спр_Работы!$A$2:$A$6000,0)),"") | R72: да | T72: =IF(AND($P72>0,$R72="да"),MAX($T$1:$T71)+1,"")
A73: =IFERROR(INDEX(спр_Работы!$D$2:$D$6000,MATCH($C73,спр_Работы!$A$2:$A$6000,0)),"") | B73: =IFERROR(INDEX(спр_Работы!$F$2:$F$6000,MATCH($C73,спр_Работы!$A$2:$A$6000,0)),"") | C73: =IFERROR(INDEX(спр_Работы!$A$2:$A$6000,72),"") | D73: =IFERROR(INDEX(спр_Работы!$B$2:$B$6000,MATCH($C73,спр_Работы!$A$2:$A$6000,0)),"") | E73: =IFERROR(INDEX(спр_Работы!$C$2:$C$6000,MATCH($C73,спр_Работы!$A$2:$A$6000,0)),"") | F73: =IFERROR(INDEX(спр_Работы!$G$2:$G$6000,MATCH($C73,спр_Работы!$A$2:$A$6000,0)),"") | G73: =IFERROR(INDEX(спр_Работы!$K$2:$K$6000,MATCH($C73,спр_Работы!$A$2:$A$6000,0)),"") | J73: =IFERROR(INDEX(спр_Материалы!$B$2:$B$9000,MATCH($I73,спр_Материалы!$A$2:$A$9000,0)),"") | K73: =IF($I73="","",IF($F73=IFERROR(INDEX(спр_Материалы!$G$2:$G$9000,MATCH($I73,спр_Материалы!$A$2:$A$9000,0)),""),"OK","!! не та группа")) | L73: =IFERROR(INDEX(спр_Работы!$H$2:$H$6000,MATCH($C73,спр_Работы!$A$2:$A$6000,0))*(1-ДисконтТендер),0) | M73: =IF($I73="",0,IFERROR(INDEX(спр_Материалы!$I$2:$I$9000,MATCH($I73,спр_Материалы!$A$2:$A$9000,0))*IF(INDEX(спр_Материалы!$J$2:$J$9000,MATCH($I73,спр_Материалы!$A$2:$A$9000,0))="USD",КурсUSD,IF(INDEX(спр_Материалы!$J$2:$J$9000,MATCH($I73,спр_Материалы!$A$2:$A$9000,0))="EUR",КурсEUR,1))*INDEX(спр_Материалы!$K$2:$K$9000,MATCH($I73,спр_Материалы!$A$2:$A$9000,0))*(1+IFERROR(INDEX(спр_Работы!$I$2:$I$6000,MATCH($C73,спр_Работы!$A$2:$A$6000,0))/100,0))*(1-ДисконтТендер),0)) | N73: =IF(AND($R73="да",$H73<>""),ROUND($H73*$L73,2),0) | O73: =IF(AND($R73="да",$H73<>""),ROUND($H73*$M73,2),0) | P73: =$N73+$O73 | Q73: =IFERROR(INDEX(спр_Работы!$J$2:$J$6000,MATCH($C73,спр_Работы!$A$2:$A$6000,0)),"") | R73: да | T73: =IF(AND($P73>0,$R73="да"),MAX($T$1:$T72)+1,"")
A74: =IFERROR(INDEX(спр_Работы!$D$2:$D$6000,MATCH($C74,спр_Работы!$A$2:$A$6000,0)),"") | B74: =IFERROR(INDEX(спр_Работы!$F$2:$F$6000,MATCH($C74,спр_Работы!$A$2:$A$6000,0)),"") | C74: =IFERROR(INDEX(спр_Работы!$A$2:$A$6000,73),"") | D74: =IFERROR(INDEX(спр_Работы!$B$2:$B$6000,MATCH($C74,спр_Работы!$A$2:$A$6000,0)),"") | E74: =IFERROR(INDEX(спр_Работы!$C$2:$C$6000,MATCH($C74,спр_Работы!$A$2:$A$6000,0)),"") | F74: =IFERROR(INDEX(спр_Работы!$G$2:$G$6000,MATCH($C74,спр_Работы!$A$2:$A$6000,0)),"") | G74: =IFERROR(INDEX(спр_Работы!$K$2:$K$6000,MATCH($C74,спр_Работы!$A$2:$A$6000,0)),"") | J74: =IFERROR(INDEX(спр_Материалы!$B$2:$B$9000,MATCH($I74,спр_Материалы!$A$2:$A$9000,0)),"") | K74: =IF($I74="","",IF($F74=IFERROR(INDEX(спр_Материалы!$G$2:$G$9000,MATCH($I74,спр_Материалы!$A$2:$A$9000,0)),""),"OK","!! не та группа")) | L74: =IFERROR(INDEX(спр_Работы!$H$2:$H$6000,MATCH($C74,спр_Работы!$A$2:$A$6000,0))*(1-ДисконтТендер),0) | M74: =IF($I74="",0,IFERROR(INDEX(спр_Материалы!$I$2:$I$9000,MATCH($I74,спр_Материалы!$A$2:$A$9000,0))*IF(INDEX(спр_Материалы!$J$2:$J$9000,MATCH($I74,спр_Материалы!$A$2:$A$9000,0))="USD",КурсUSD,IF(INDEX(спр_Материалы!$J$2:$J$9000,MATCH($I74,спр_Материалы!$A$2:$A$9000,0))="EUR",КурсEUR,1))*INDEX(спр_Материалы!$K$2:$K$9000,MATCH($I74,спр_Материалы!$A$2:$A$9000,0))*(1+IFERROR(INDEX(спр_Работы!$I$2:$I$6000,MATCH($C74,спр_Работы!$A$2:$A$6000,0))/100,0))*(1-ДисконтТендер),0)) | N74: =IF(AND($R74="да",$H74<>""),ROUND($H74*$L74,2),0) | O74: =IF(AND($R74="да",$H74<>""),ROUND($H74*$M74,2),0) | P74: =$N74+$O74 | Q74: =IFERROR(INDEX(спр_Работы!$J$2:$J$6000,MATCH($C74,спр_Работы!$A$2:$A$6000,0)),"") | R74: да | T74: =IF(AND($P74>0,$R74="да"),MAX($T$1:$T73)+1,"")
A75: =IFERROR(INDEX(спр_Работы!$D$2:$D$6000,MATCH($C75,спр_Работы!$A$2:$A$6000,0)),"") | B75: =IFERROR(INDEX(спр_Работы!$F$2:$F$6000,MATCH($C75,спр_Работы!$A$2:$A$6000,0)),"") | C75: =IFERROR(INDEX(спр_Работы!$A$2:$A$6000,74),"") | D75: =IFERROR(INDEX(спр_Работы!$B$2:$B$6000,MATCH($C75,спр_Работы!$A$2:$A$6000,0)),"") | E75: =IFERROR(INDEX(спр_Работы!$C$2:$C$6000,MATCH($C75,спр_Работы!$A$2:$A$6000,0)),"") | F75: =IFERROR(INDEX(спр_Работы!$G$2:$G$6000,MATCH($C75,спр_Работы!$A$2:$A$6000,0)),"") | G75: =IFERROR(INDEX(спр_Работы!$K$2:$K$6000,MATCH($C75,спр_Работы!$A$2:$A$6000,0)),"") | J75: =IFERROR(INDEX(спр_Материалы!$B$2:$B$9000,MATCH($I75,спр_Материалы!$A$2:$A$9000,0)),"") | K75: =IF($I75="","",IF($F75=IFERROR(INDEX(спр_Материалы!$G$2:$G$9000,MATCH($I75,спр_Материалы!$A$2:$A$9000,0)),""),"OK","!! не та группа")) | L75: =IFERROR(INDEX(спр_Работы!$H$2:$H$6000,MATCH($C75,спр_Работы!$A$2:$A$6000,0))*(1-ДисконтТендер),0) | M75: =IF($I75="",0,IFERROR(INDEX(спр_Материалы!$I$2:$I$9000,MATCH($I75,спр_Материалы!$A$2:$A$9000,0))*IF(INDEX(спр_Материалы!$J$2:$J$9000,MATCH($I75,спр_Материалы!$A$2:$A$9000,0))="USD",КурсUSD,IF(INDEX(спр_Материалы!$J$2:$J$9000,MATCH($I75,спр_Материалы!$A$2:$A$9000,0))="EUR",КурсEUR,1))*INDEX(спр_Материалы!$K$2:$K$9000,MATCH($I75,спр_Материалы!$A$2:$A$9000,0))*(1+IFERROR(INDEX(спр_Работы!$I$2:$I$6000,MATCH($C75,спр_Работы!$A$2:$A$6000,0))/100,0))*(1-ДисконтТендер),0)) | N75: =IF(AND($R75="да",$H75<>""),ROUND($H75*$L75,2),0) | O75: =IF(AND($R75="да",$H75<>""),ROUND($H75*$M75,2),0) | P75: =$N75+$O75 | Q75: =IFERROR(INDEX(спр_Работы!$J$2:$J$6000,MATCH($C75,спр_Работы!$A$2:$A$6000,0)),"") | R75: да | T75: =IF(AND($P75>0,$R75="да"),MAX($T$1:$T74)+1,"")
A76: =IFERROR(INDEX(спр_Работы!$D$2:$D$6000,MATCH($C76,спр_Работы!$A$2:$A$6000,0)),"") | B76: =IFERROR(INDEX(спр_Работы!$F$2:$F$6000,MATCH($C76,спр_Работы!$A$2:$A$6000,0)),"") | C76: =IFERROR(INDEX(спр_Работы!$A$2:$A$6000,75),"") | D76: =IFERROR(INDEX(спр_Работы!$B$2:$B$6000,MATCH($C76,спр_Работы!$A$2:$A$6000,0)),"") | E76: =IFERROR(INDEX(спр_Работы!$C$2:$C$6000,MATCH($C76,спр_Работы!$A$2:$A$6000,0)),"") | F76: =IFERROR(INDEX(спр_Работы!$G$2:$G$6000,MATCH($C76,спр_Работы!$A$2:$A$6000,0)),"") | G76: =IFERROR(INDEX(спр_Работы!$K$2:$K$6000,MATCH($C76,спр_Работы!$A$2:$A$6000,0)),"") | J76: =IFERROR(INDEX(спр_Материалы!$B$2:$B$9000,MATCH($I76,спр_Материалы!$A$2:$A$9000,0)),"") | K76: =IF($I76="","",IF($F76=IFERROR(INDEX(спр_Материалы!$G$2:$G$9000,MATCH($I76,спр_Материалы!$A$2:$A$9000,0)),""),"OK","!! не та группа")) | L76: =IFERROR(INDEX(спр_Работы!$H$2:$H$6000,MATCH($C76,спр_Работы!$A$2:$A$6000,0))*(1-ДисконтТендер),0) | M76: =IF($I76="",0,IFERROR(INDEX(спр_Материалы!$I$2:$I$9000,MATCH($I76,спр_Материалы!$A$2:$A$9000,0))*IF(INDEX(спр_Материалы!$J$2:$J$9000,MATCH($I76,спр_Материалы!$A$2:$A$9000,0))="USD",КурсUSD,IF(INDEX(спр_Материалы!$J$2:$J$9000,MATCH($I76,спр_Материалы!$A$2:$A$9000,0))="EUR",КурсEUR,1))*INDEX(спр_Материалы!$K$2:$K$9000,MATCH($I76,спр_Материалы!$A$2:$A$9000,0))*(1+IFERROR(INDEX(спр_Работы!$I$2:$I$6000,MATCH($C76,спр_Работы!$A$2:$A$6000,0))/100,0))*(1-ДисконтТендер),0)) | N76: =IF(AND($R76="да",$H76<>""),ROUND($H76*$L76,2),0) | O76: =IF(AND($R76="да",$H76<>""),ROUND($H76*$M76,2),0) | P76: =$N76+$O76 | Q76: =IFERROR(INDEX(спр_Работы!$J$2:$J$6000,MATCH($C76,спр_Работы!$A$2:$A$6000,0)),"") | R76: да | T76: =IF(AND($P76>0,$R76="да"),MAX($T$1:$T75)+1,"")
A77: =IFERROR(INDEX(спр_Работы!$D$2:$D$6000,MATCH($C77,спр_Работы!$A$2:$A$6000,0)),"") | B77: =IFERROR(INDEX(спр_Работы!$F$2:$F$6000,MATCH($C77,спр_Работы!$A$2:$A$6000,0)),"") | C77: =IFERROR(INDEX(спр_Работы!$A$2:$A$6000,76),"") | D77: =IFERROR(INDEX(спр_Работы!$B$2:$B$6000,MATCH($C77,спр_Работы!$A$2:$A$6000,0)),"") | E77: =IFERROR(INDEX(спр_Работы!$C$2:$C$6000,MATCH($C77,спр_Работы!$A$2:$A$6000,0)),"") | F77: =IFERROR(INDEX(спр_Работы!$G$2:$G$6000,MATCH($C77,спр_Работы!$A$2:$A$6000,0)),"") | G77: =IFERROR(INDEX(спр_Работы!$K$2:$K$6000,MATCH($C77,спр_Работы!$A$2:$A$6000,0)),"") | J77: =IFERROR(INDEX(спр_Материалы!$B$2:$B$9000,MATCH($I77,спр_Материалы!$A$2:$A$9000,0)),"") | K77: =IF($I77="","",IF($F77=IFERROR(INDEX(спр_Материалы!$G$2:$G$9000,MATCH($I77,спр_Материалы!$A$2:$A$9000,0)),""),"OK","!! не та группа")) | L77: =IFERROR(INDEX(спр_Работы!$H$2:$H$6000,MATCH($C77,спр_Работы!$A$2:$A$6000,0))*(1-ДисконтТендер),0) | M77: =IF($I77="",0,IFERROR(INDEX(спр_Материалы!$I$2:$I$9000,MATCH($I77,спр_Материалы!$A$2:$A$9000,0))*IF(INDEX(спр_Материалы!$J$2:$J$9000,MATCH($I77,спр_Материалы!$A$2:$A$9000,0))="USD",КурсUSD,IF(INDEX(спр_Материалы!$J$2:$J$9000,MATCH($I77,спр_Материалы!$A$2:$A$9000,0))="EUR",КурсEUR,1))*INDEX(спр_Материалы!$K$2:$K$9000,MATCH($I77,спр_Материалы!$A$2:$A$9000,0))*(1+IFERROR(INDEX(спр_Работы!$I$2:$I$6000,MATCH($C77,спр_Работы!$A$2:$A$6000,0))/100,0))*(1-ДисконтТендер),0)) | N77: =IF(AND($R77="да",$H77<>""),ROUND($H77*$L77,2),0) | O77: =IF(AND($R77="да",$H77<>""),ROUND($H77*$M77,2),0) | P77: =$N77+$O77 | Q77: =IFERROR(INDEX(спр_Работы!$J$2:$J$6000,MATCH($C77,спр_Работы!$A$2:$A$6000,0)),"") | R77: да | T77: =IF(AND($P77>0,$R77="да"),MAX($T$1:$T76)+1,"")
A78: =IFERROR(INDEX(спр_Работы!$D$2:$D$6000,MATCH($C78,спр_Работы!$A$2:$A$6000,0)),"") | B78: =IFERROR(INDEX(спр_Работы!$F$2:$F$6000,MATCH($C78,спр_Работы!$A$2:$A$6000,0)),"") | C78: =IFERROR(INDEX(спр_Работы!$A$2:$A$6000,77),"") | D78: =IFERROR(INDEX(спр_Работы!$B$2:$B$6000,MATCH($C78,спр_Работы!$A$2:$A$6000,0)),"") | E78: =IFERROR(INDEX(спр_Работы!$C$2:$C$6000,MATCH($C78,спр_Работы!$A$2:$A$6000,0)),"") | F78: =IFERROR(INDEX(спр_Работы!$G$2:$G$6000,MATCH($C78,спр_Работы!$A$2:$A$6000,0)),"") | G78: =IFERROR(INDEX(спр_Работы!$K$2:$K$6000,MATCH($C78,спр_Работы!$A$2:$A$6000,0)),"") | J78: =IFERROR(INDEX(спр_Материалы!$B$2:$B$9000,MATCH($I78,спр_Материалы!$A$2:$A$9000,0)),"") | K78: =IF($I78="","",IF($F78=IFERROR(INDEX(спр_Материалы!$G$2:$G$9000,MATCH($I78,спр_Материалы!$A$2:$A$9000,0)),""),"OK","!! не та группа")) | L78: =IFERROR(INDEX(спр_Работы!$H$2:$H$6000,MATCH($C78,спр_Работы!$A$2:$A$6000,0))*(1-ДисконтТендер),0) | M78: =IF($I78="",0,IFERROR(INDEX(спр_Материалы!$I$2:$I$9000,MATCH($I78,спр_Материалы!$A$2:$A$9000,0))*IF(INDEX(спр_Материалы!$J$2:$J$9000,MATCH($I78,спр_Материалы!$A$2:$A$9000,0))="USD",КурсUSD,IF(INDEX(спр_Материалы!$J$2:$J$9000,MATCH($I78,спр_Материалы!$A$2:$A$9000,0))="EUR",КурсEUR,1))*INDEX(спр_Материалы!$K$2:$K$9000,MATCH($I78,спр_Материалы!$A$2:$A$9000,0))*(1+IFERROR(INDEX(спр_Работы!$I$2:$I$6000,MATCH($C78,спр_Работы!$A$2:$A$6000,0))/100,0))*(1-ДисконтТендер),0)) | N78: =IF(AND($R78="да",$H78<>""),ROUND($H78*$L78,2),0) | O78: =IF(AND($R78="да",$H78<>""),ROUND($H78*$M78,2),0) | P78: =$N78+$O78 | Q78: =IFERROR(INDEX(спр_Работы!$J$2:$J$6000,MATCH($C78,спр_Работы!$A$2:$A$6000,0)),"") | R78: да | T78: =IF(AND($P78>0,$R78="да"),MAX($T$1:$T77)+1,"")
A79: =IFERROR(INDEX(спр_Работы!$D$2:$D$6000,MATCH($C79,спр_Работы!$A$2:$A$6000,0)),"") | B79: =IFERROR(INDEX(спр_Работы!$F$2:$F$6000,MATCH($C79,спр_Работы!$A$2:$A$6000,0)),"") | C79: =IFERROR(INDEX(спр_Работы!$A$2:$A$6000,78),"") | D79: =IFERROR(INDEX(спр_Работы!$B$2:$B$6000,MATCH($C79,спр_Работы!$A$2:$A$6000,0)),"") | E79: =IFERROR(INDEX(спр_Работы!$C$2:$C$6000,MATCH($C79,спр_Работы!$A$2:$A$6000,0)),"") | F79: =IFERROR(INDEX(спр_Работы!$G$2:$G$6000,MATCH($C79,спр_Работы!$A$2:$A$6000,0)),"") | G79: =IFERROR(INDEX(спр_Работы!$K$2:$K$6000,MATCH($C79,спр_Работы!$A$2:$A$6000,0)),"") | J79: =IFERROR(INDEX(спр_Материалы!$B$2:$B$9000,MATCH($I79,спр_Материалы!$A$2:$A$9000,0)),"") | K79: =IF($I79="","",IF($F79=IFERROR(INDEX(спр_Материалы!$G$2:$G$9000,MATCH($I79,спр_Материалы!$A$2:$A$9000,0)),""),"OK","!! не та группа")) | L79: =IFERROR(INDEX(спр_Работы!$H$2:$H$6000,MATCH($C79,спр_Работы!$A$2:$A$6000,0))*(1-ДисконтТендер),0) | M79: =IF($I79="",0,IFERROR(INDEX(спр_Материалы!$I$2:$I$9000,MATCH($I79,спр_Материалы!$A$2:$A$9000,0))*IF(INDEX(спр_Материалы!$J$2:$J$9000,MATCH($I79,спр_Материалы!$A$2:$A$9000,0))="USD",КурсUSD,IF(INDEX(спр_Материалы!$J$2:$J$9000,MATCH($I79,спр_Материалы!$A$2:$A$9000,0))="EUR",КурсEUR,1))*INDEX(спр_Материалы!$K$2:$K$9000,MATCH($I79,спр_Материалы!$A$2:$A$9000,0))*(1+IFERROR(INDEX(спр_Работы!$I$2:$I$6000,MATCH($C79,спр_Работы!$A$2:$A$6000,0))/100,0))*(1-ДисконтТендер),0)) | N79: =IF(AND($R79="да",$H79<>""),ROUND($H79*$L79,2),0) | O79: =IF(AND($R79="да",$H79<>""),ROUND($H79*$M79,2),0) | P79: =$N79+$O79 | Q79: =IFERROR(INDEX(спр_Работы!$J$2:$J$6000,MATCH($C79,спр_Работы!$A$2:$A$6000,0)),"") | R79: да | T79: =IF(AND($P79>0,$R79="да"),MAX($T$1:$T78)+1,"")
A80: =IFERROR(INDEX(спр_Работы!$D$2:$D$6000,MATCH($C80,спр_Работы!$A$2:$A$6000,0)),"") | B80: =IFERROR(INDEX(спр_Работы!$F$2:$F$6000,MATCH($C80,спр_Работы!$A$2:$A$6000,0)),"") | C80: =IFERROR(INDEX(спр_Работы!$A$2:$A$6000,79),"") | D80: =IFERROR(INDEX(спр_Работы!$B$2:$B$6000,MATCH($C80,спр_Работы!$A$2:$A$6000,0)),"") | E80: =IFERROR(INDEX(спр_Работы!$C$2:$C$6000,MATCH($C80,спр_Работы!$A$2:$A$6000,0)),"") | F80: =IFERROR(INDEX(спр_Работы!$G$2:$G$6000,MATCH($C80,спр_Работы!$A$2:$A$6000,0)),"") | G80: =IFERROR(INDEX(спр_Работы!$K$2:$K$6000,MATCH($C80,спр_Работы!$A$2:$A$6000,0)),"") | J80: =IFERROR(INDEX(спр_Материалы!$B$2:$B$9000,MATCH($I80,спр_Материалы!$A$2:$A$9000,0)),"") | K80: =IF($I80="","",IF($F80=IFERROR(INDEX(спр_Материалы!$G$2:$G$9000,MATCH($I80,спр_Материалы!$A$2:$A$9000,0)),""),"OK","!! не та группа")) | L80: =IFERROR(INDEX(спр_Работы!$H$2:$H$6000,MATCH($C80,спр_Работы!$A$2:$A$6000,0))*(1-ДисконтТендер),0) | M80: =IF($I80="",0,IFERROR(INDEX(спр_Материалы!$I$2:$I$9000,MATCH($I80,спр_Материалы!$A$2:$A$9000,0))*IF(INDEX(спр_Материалы!$J$2:$J$9000,MATCH($I80,спр_Материалы!$A$2:$A$9000,0))="USD",КурсUSD,IF(INDEX(спр_Материалы!$J$2:$J$9000,MATCH($I80,спр_Материалы!$A$2:$A$9000,0))="EUR",КурсEUR,1))*INDEX(спр_Материалы!$K$2:$K$9000,MATCH($I80,спр_Материалы!$A$2:$A$9000,0))*(1+IFERROR(INDEX(спр_Работы!$I$2:$I$6000,MATCH($C80,спр_Работы!$A$2:$A$6000,0))/100,0))*(1-ДисконтТендер),0)) | N80: =IF(AND($R80="да",$H80<>""),ROUND($H80*$L80,2),0) | O80: =IF(AND($R80="да",$H80<>""),ROUND($H80*$M80,2),0) | P80: =$N80+$O80 | Q80: =IFERROR(INDEX(спр_Работы!$J$2:$J$6000,MATCH($C80,спр_Работы!$A$2:$A$6000,0)),"") | R80: да | T80: =IF(AND($P80>0,$R80="да"),MAX($T$1:$T79)+1,"")
A81: =IFERROR(INDEX(спр_Работы!$D$2:$D$6000,MATCH($C81,спр_Работы!$A$2:$A$6000,0)),"") | B81: =IFERROR(INDEX(спр_Работы!$F$2:$F$6000,MATCH($C81,спр_Работы!$A$2:$A$6000,0)),"") | C81: =IFERROR(INDEX(спр_Работы!$A$2:$A$6000,80),"") | D81: =IFERROR(INDEX(спр_Работы!$B$2:$B$6000,MATCH($C81,спр_Работы!$A$2:$A$6000,0)),"") | E81: =IFERROR(INDEX(спр_Работы!$C$2:$C$6000,MATCH($C81,спр_Работы!$A$2:$A$6000,0)),"") | F81: =IFERROR(INDEX(спр_Работы!$G$2:$G$6000,MATCH($C81,спр_Работы!$A$2:$A$6000,0)),"") | G81: =IFERROR(INDEX(спр_Работы!$K$2:$K$6000,MATCH($C81,спр_Работы!$A$2:$A$6000,0)),"") | J81: =IFERROR(INDEX(спр_Материалы!$B$2:$B$9000,MATCH($I81,спр_Материалы!$A$2:$A$9000,0)),"") | K81: =IF($I81="","",IF($F81=IFERROR(INDEX(спр_Материалы!$G$2:$G$9000,MATCH($I81,спр_Материалы!$A$2:$A$9000,0)),""),"OK","!! не та группа")) | L81: =IFERROR(INDEX(спр_Работы!$H$2:$H$6000,MATCH($C81,спр_Работы!$A$2:$A$6000,0))*(1-ДисконтТендер),0) | M81: =IF($I81="",0,IFERROR(INDEX(спр_Материалы!$I$2:$I$9000,MATCH($I81,спр_Материалы!$A$2:$A$9000,0))*IF(INDEX(спр_Материалы!$J$2:$J$9000,MATCH($I81,спр_Материалы!$A$2:$A$9000,0))="USD",КурсUSD,IF(INDEX(спр_Материалы!$J$2:$J$9000,MATCH($I81,спр_Материалы!$A$2:$A$9000,0))="EUR",КурсEUR,1))*INDEX(спр_Материалы!$K$2:$K$9000,MATCH($I81,спр_Материалы!$A$2:$A$9000,0))*(1+IFERROR(INDEX(спр_Работы!$I$2:$I$6000,MATCH($C81,спр_Работы!$A$2:$A$6000,0))/100,0))*(1-ДисконтТендер),0)) | N81: =IF(AND($R81="да",$H81<>""),ROUND($H81*$L81,2),0) | O81: =IF(AND($R81="да",$H81<>""),ROUND($H81*$M81,2),0) | P81: =$N81+$O81 | Q81: =IFERROR(INDEX(спр_Работы!$J$2:$J$6000,MATCH($C81,спр_Работы!$A$2:$A$6000,0)),"") | R81: да | T81: =IF(AND($P81>0,$R81="да"),MAX($T$1:$T80)+1,"")
A82: =IFERROR(INDEX(спр_Работы!$D$2:$D$6000,MATCH($C82,спр_Работы!$A$2:$A$6000,0)),"") | B82: =IFERROR(INDEX(спр_Работы!$F$2:$F$6000,MATCH($C82,спр_Работы!$A$2:$A$6000,0)),"") | C82: =IFERROR(INDEX(спр_Работы!$A$2:$A$6000,81),"") | D82: =IFERROR(INDEX(спр_Работы!$B$2:$B$6000,MATCH($C82,спр_Работы!$A$2:$A$6000,0)),"") | E82: =IFERROR(INDEX(спр_Работы!$C$2:$C$6000,MATCH($C82,спр_Работы!$A$2:$A$6000,0)),"") | F82: =IFERROR(INDEX(спр_Работы!$G$2:$G$6000,MATCH($C82,спр_Работы!$A$2:$A$6000,0)),"") | G82: =IFERROR(INDEX(спр_Работы!$K$2:$K$6000,MATCH($C82,спр_Работы!$A$2:$A$6000,0)),"") | J82: =IFERROR(INDEX(спр_Материалы!$B$2:$B$9000,MATCH($I82,спр_Материалы!$A$2:$A$9000,0)),"") | K82: =IF($I82="","",IF($F82=IFERROR(INDEX(спр_Материалы!$G$2:$G$9000,MATCH($I82,спр_Материалы!$A$2:$A$9000,0)),""),"OK","!! не та группа")) | L82: =IFERROR(INDEX(спр_Работы!$H$2:$H$6000,MATCH($C82,спр_Работы!$A$2:$A$6000,0))*(1-ДисконтТендер),0) | M82: =IF($I82="",0,IFERROR(INDEX(спр_Материалы!$I$2:$I$9000,MATCH($I82,спр_Материалы!$A$2:$A$9000,0))*IF(INDEX(спр_Материалы!$J$2:$J$9000,MATCH($I82,спр_Материалы!$A$2:$A$9000,0))="USD",КурсUSD,IF(INDEX(спр_Материалы!$J$2:$J$9000,MATCH($I82,спр_Материалы!$A$2:$A$9000,0))="EUR",КурсEUR,1))*INDEX(спр_Материалы!$K$2:$K$9000,MATCH($I82,спр_Материалы!$A$2:$A$9000,0))*(1+IFERROR(INDEX(спр_Работы!$I$2:$I$6000,MATCH($C82,спр_Работы!$A$2:$A$6000,0))/100,0))*(1-ДисконтТендер),0)) | N82: =IF(AND($R82="да",$H82<>""),ROUND($H82*$L82,2),0) | O82: =IF(AND($R82="да",$H82<>""),ROUND($H82*$M82,2),0) | P82: =$N82+$O82 | Q82: =IFERROR(INDEX(спр_Работы!$J$2:$J$6000,MATCH($C82,спр_Работы!$A$2:$A$6000,0)),"") | R82: да | T82: =IF(AND($P82>0,$R82="да"),MAX($T$1:$T81)+1,"")
A83: =IFERROR(INDEX(спр_Работы!$D$2:$D$6000,MATCH($C83,спр_Работы!$A$2:$A$6000,0)),"") | B83: =IFERROR(INDEX(спр_Работы!$F$2:$F$6000,MATCH($C83,спр_Работы!$A$2:$A$6000,0)),"") | C83: =IFERROR(INDEX(спр_Работы!$A$2:$A$6000,82),"") | D83: =IFERROR(INDEX(спр_Работы!$B$2:$B$6000,MATCH($C83,спр_Работы!$A$2:$A$6000,0)),"") | E83: =IFERROR(INDEX(спр_Работы!$C$2:$C$6000,MATCH($C83,спр_Работы!$A$2:$A$6000,0)),"") | F83: =IFERROR(INDEX(спр_Работы!$G$2:$G$6000,MATCH($C83,спр_Работы!$A$2:$A$6000,0)),"") | G83: =IFERROR(INDEX(спр_Работы!$K$2:$K$6000,MATCH($C83,спр_Работы!$A$2:$A$6000,0)),"") | J83: =IFERROR(INDEX(спр_Материалы!$B$2:$B$9000,MATCH($I83,спр_Материалы!$A$2:$A$9000,0)),"") | K83: =IF($I83="","",IF($F83=IFERROR(INDEX(спр_Материалы!$G$2:$G$9000,MATCH($I83,спр_Материалы!$A$2:$A$9000,0)),""),"OK","!! не та группа")) | L83: =IFERROR(INDEX(спр_Работы!$H$2:$H$6000,MATCH($C83,спр_Работы!$A$2:$A$6000,0))*(1-ДисконтТендер),0) | M83: =IF($I83="",0,IFERROR(INDEX(спр_Материалы!$I$2:$I$9000,MATCH($I83,спр_Материалы!$A$2:$A$9000,0))*IF(INDEX(спр_Материалы!$J$2:$J$9000,MATCH($I83,спр_Материалы!$A$2:$A$9000,0))="USD",КурсUSD,IF(INDEX(спр_Материалы!$J$2:$J$9000,MATCH($I83,спр_Материалы!$A$2:$A$9000,0))="EUR",КурсEUR,1))*INDEX(спр_Материалы!$K$2:$K$9000,MATCH($I83,спр_Материалы!$A$2:$A$9000,0))*(1+IFERROR(INDEX(спр_Работы!$I$2:$I$6000,MATCH($C83,спр_Работы!$A$2:$A$6000,0))/100,0))*(1-ДисконтТендер),0)) | N83: =IF(AND($R83="да",$H83<>""),ROUND($H83*$L83,2),0) | O83: =IF(AND($R83="да",$H83<>""),ROUND($H83*$M83,2),0) | P83: =$N83+$O83 | Q83: =IFERROR(INDEX(спр_Работы!$J$2:$J$6000,MATCH($C83,спр_Работы!$A$2:$A$6000,0)),"") | R83: да | T83: =IF(AND($P83>0,$R83="да"),MAX($T$1:$T82)+1,"")
A84: =IFERROR(INDEX(спр_Работы!$D$2:$D$6000,MATCH($C84,спр_Работы!$A$2:$A$6000,0)),"") | B84: =IFERROR(INDEX(спр_Работы!$F$2:$F$6000,MATCH($C84,спр_Работы!$A$2:$A$6000,0)),"") | C84: =IFERROR(INDEX(спр_Работы!$A$2:$A$6000,83),"") | D84: =IFERROR(INDEX(спр_Работы!$B$2:$B$6000,MATCH($C84,спр_Работы!$A$2:$A$6000,0)),"") | E84: =IFERROR(INDEX(спр_Работы!$C$2:$C$6000,MATCH($C84,спр_Работы!$A$2:$A$6000,0)),"") | F84: =IFERROR(INDEX(спр_Работы!$G$2:$G$6000,MATCH($C84,спр_Работы!$A$2:$A$6000,0)),"") | G84: =IFERROR(INDEX(спр_Работы!$K$2:$K$6000,MATCH($C84,спр_Работы!$A$2:$A$6000,0)),"") | J84: =IFERROR(INDEX(спр_Материалы!$B$2:$B$9000,MATCH($I84,спр_Материалы!$A$2:$A$9000,0)),"") | K84: =IF($I84="","",IF($F84=IFERROR(INDEX(спр_Материалы!$G$2:$G$9000,MATCH($I84,спр_Материалы!$A$2:$A$9000,0)),""),"OK","!! не та группа")) | L84: =IFERROR(INDEX(спр_Работы!$H$2:$H$6000,MATCH($C84,спр_Работы!$A$2:$A$6000,0))*(1-ДисконтТендер),0) | M84: =IF($I84="",0,IFERROR(INDEX(спр_Материалы!$I$2:$I$9000,MATCH($I84,спр_Материалы!$A$2:$A$9000,0))*IF(INDEX(спр_Материалы!$J$2:$J$9000,MATCH($I84,спр_Материалы!$A$2:$A$9000,0))="USD",КурсUSD,IF(INDEX(спр_Материалы!$J$2:$J$9000,MATCH($I84,спр_Материалы!$A$2:$A$9000,0))="EUR",КурсEUR,1))*INDEX(спр_Материалы!$K$2:$K$9000,MATCH($I84,спр_Материалы!$A$2:$A$9000,0))*(1+IFERROR(INDEX(спр_Работы!$I$2:$I$6000,MATCH($C84,спр_Работы!$A$2:$A$6000,0))/100,0))*(1-ДисконтТендер),0)) | N84: =IF(AND($R84="да",$H84<>""),ROUND($H84*$L84,2),0) | O84: =IF(AND($R84="да",$H84<>""),ROUND($H84*$M84,2),0) | P84: =$N84+$O84 | Q84: =IFERROR(INDEX(спр_Работы!$J$2:$J$6000,MATCH($C84,спр_Работы!$A$2:$A$6000,0)),"") | R84: да | T84: =IF(AND($P84>0,$R84="да"),MAX($T$1:$T83)+1,"")
A85: =IFERROR(INDEX(спр_Работы!$D$2:$D$6000,MATCH($C85,спр_Работы!$A$2:$A$6000,0)),"") | B85: =IFERROR(INDEX(спр_Работы!$F$2:$F$6000,MATCH($C85,спр_Работы!$A$2:$A$6000,0)),"") | C85: =IFERROR(INDEX(спр_Работы!$A$2:$A$6000,84),"") | D85: =IFERROR(INDEX(спр_Работы!$B$2:$B$6000,MATCH($C85,спр_Работы!$A$2:$A$6000,0)),"") | E85: =IFERROR(INDEX(спр_Работы!$C$2:$C$6000,MATCH($C85,спр_Работы!$A$2:$A$6000,0)),"") | F85: =IFERROR(INDEX(спр_Работы!$G$2:$G$6000,MATCH($C85,спр_Работы!$A$2:$A$6000,0)),"") | G85: =IFERROR(INDEX(спр_Работы!$K$2:$K$6000,MATCH($C85,спр_Работы!$A$2:$A$6000,0)),"") | J85: =IFERROR(INDEX(спр_Материалы!$B$2:$B$9000,MATCH($I85,спр_Материалы!$A$2:$A$9000,0)),"") | K85: =IF($I85="","",IF($F85=IFERROR(INDEX(спр_Материалы!$G$2:$G$9000,MATCH($I85,спр_Материалы!$A$2:$A$9000,0)),""),"OK","!! не та группа")) | L85: =IFERROR(INDEX(спр_Работы!$H$2:$H$6000,MATCH($C85,спр_Работы!$A$2:$A$6000,0))*(1-ДисконтТендер),0) | M85: =IF($I85="",0,IFERROR(INDEX(спр_Материалы!$I$2:$I$9000,MATCH($I85,спр_Материалы!$A$2:$A$9000,0))*IF(INDEX(спр_Материалы!$J$2:$J$9000,MATCH($I85,спр_Материалы!$A$2:$A$9000,0))="USD",КурсUSD,IF(INDEX(спр_Материалы!$J$2:$J$9000,MATCH($I85,спр_Материалы!$A$2:$A$9000,0))="EUR",КурсEUR,1))*INDEX(спр_Материалы!$K$2:$K$9000,MATCH($I85,спр_Материалы!$A$2:$A$9000,0))*(1+IFERROR(INDEX(спр_Работы!$I$2:$I$6000,MATCH($C85,спр_Работы!$A$2:$A$6000,0))/100,0))*(1-ДисконтТендер),0)) | N85: =IF(AND($R85="да",$H85<>""),ROUND($H85*$L85,2),0) | O85: =IF(AND($R85="да",$H85<>""),ROUND($H85*$M85,2),0) | P85: =$N85+$O85 | Q85: =IFERROR(INDEX(спр_Работы!$J$2:$J$6000,MATCH($C85,спр_Работы!$A$2:$A$6000,0)),"") | R85: да | T85: =IF(AND($P85>0,$R85="да"),MAX($T$1:$T84)+1,"")
A86: =IFERROR(INDEX(спр_Работы!$D$2:$D$6000,MATCH($C86,спр_Работы!$A$2:$A$6000,0)),"") | B86: =IFERROR(INDEX(спр_Работы!$F$2:$F$6000,MATCH($C86,спр_Работы!$A$2:$A$6000,0)),"") | C86: =IFERROR(INDEX(спр_Работы!$A$2:$A$6000,85),"") | D86: =IFERROR(INDEX(спр_Работы!$B$2:$B$6000,MATCH($C86,спр_Работы!$A$2:$A$6000,0)),"") | E86: =IFERROR(INDEX(спр_Работы!$C$2:$C$6000,MATCH($C86,спр_Работы!$A$2:$A$6000,0)),"") | F86: =IFERROR(INDEX(спр_Работы!$G$2:$G$6000,MATCH($C86,спр_Работы!$A$2:$A$6000,0)),"") | G86: =IFERROR(INDEX(спр_Работы!$K$2:$K$6000,MATCH($C86,спр_Работы!$A$2:$A$6000,0)),"") | J86: =IFERROR(INDEX(спр_Материалы!$B$2:$B$9000,MATCH($I86,спр_Материалы!$A$2:$A$9000,0)),"") | K86: =IF($I86="","",IF($F86=IFERROR(INDEX(спр_Материалы!$G$2:$G$9000,MATCH($I86,спр_Материалы!$A$2:$A$9000,0)),""),"OK","!! не та группа")) | L86: =IFERROR(INDEX(спр_Работы!$H$2:$H$6000,MATCH($C86,спр_Работы!$A$2:$A$6000,0))*(1-ДисконтТендер),0) | M86: =IF($I86="",0,IFERROR(INDEX(спр_Материалы!$I$2:$I$9000,MATCH($I86,спр_Материалы!$A$2:$A$9000,0))*IF(INDEX(спр_Материалы!$J$2:$J$9000,MATCH($I86,спр_Материалы!$A$2:$A$9000,0))="USD",КурсUSD,IF(INDEX(спр_Материалы!$J$2:$J$9000,MATCH($I86,спр_Материалы!$A$2:$A$9000,0))="EUR",КурсEUR,1))*INDEX(спр_Материалы!$K$2:$K$9000,MATCH($I86,спр_Материалы!$A$2:$A$9000,0))*(1+IFERROR(INDEX(спр_Работы!$I$2:$I$6000,MATCH($C86,спр_Работы!$A$2:$A$6000,0))/100,0))*(1-ДисконтТендер),0)) | N86: =IF(AND($R86="да",$H86<>""),ROUND($H86*$L86,2),0) | O86: =IF(AND($R86="да",$H86<>""),ROUND($H86*$M86,2),0) | P86: =$N86+$O86 | Q86: =IFERROR(INDEX(спр_Работы!$J$2:$J$6000,MATCH($C86,спр_Работы!$A$2:$A$6000,0)),"") | R86: да | T86: =IF(AND($P86>0,$R86="да"),MAX($T$1:$T85)+1,"")
A87: =IFERROR(INDEX(спр_Работы!$D$2:$D$6000,MATCH($C87,спр_Работы!$A$2:$A$6000,0)),"") | B87: =IFERROR(INDEX(спр_Работы!$F$2:$F$6000,MATCH($C87,спр_Работы!$A$2:$A$6000,0)),"") | C87: =IFERROR(INDEX(спр_Работы!$A$2:$A$6000,86),"") | D87: =IFERROR(INDEX(спр_Работы!$B$2:$B$6000,MATCH($C87,спр_Работы!$A$2:$A$6000,0)),"") | E87: =IFERROR(INDEX(спр_Работы!$C$2:$C$6000,MATCH($C87,спр_Работы!$A$2:$A$6000,0)),"") | F87: =IFERROR(INDEX(спр_Работы!$G$2:$G$6000,MATCH($C87,спр_Работы!$A$2:$A$6000,0)),"") | G87: =IFERROR(INDEX(спр_Работы!$K$2:$K$6000,MATCH($C87,спр_Работы!$A$2:$A$6000,0)),"") | J87: =IFERROR(INDEX(спр_Материалы!$B$2:$B$9000,MATCH($I87,спр_Материалы!$A$2:$A$9000,0)),"") | K87: =IF($I87="","",IF($F87=IFERROR(INDEX(спр_Материалы!$G$2:$G$9000,MATCH($I87,спр_Материалы!$A$2:$A$9000,0)),""),"OK","!! не та группа")) | L87: =IFERROR(INDEX(спр_Работы!$H$2:$H$6000,MATCH($C87,спр_Работы!$A$2:$A$6000,0))*(1-ДисконтТендер),0) | M87: =IF($I87="",0,IFERROR(INDEX(спр_Материалы!$I$2:$I$9000,MATCH($I87,спр_Материалы!$A$2:$A$9000,0))*IF(INDEX(спр_Материалы!$J$2:$J$9000,MATCH($I87,спр_Материалы!$A$2:$A$9000,0))="USD",КурсUSD,IF(INDEX(спр_Материалы!$J$2:$J$9000,MATCH($I87,спр_Материалы!$A$2:$A$9000,0))="EUR",КурсEUR,1))*INDEX(спр_Материалы!$K$2:$K$9000,MATCH($I87,спр_Материалы!$A$2:$A$9000,0))*(1+IFERROR(INDEX(спр_Работы!$I$2:$I$6000,MATCH($C87,спр_Работы!$A$2:$A$6000,0))/100,0))*(1-ДисконтТендер),0)) | N87: =IF(AND($R87="да",$H87<>""),ROUND($H87*$L87,2),0) | O87: =IF(AND($R87="да",$H87<>""),ROUND($H87*$M87,2),0) | P87: =$N87+$O87 | Q87: =IFERROR(INDEX(спр_Работы!$J$2:$J$6000,MATCH($C87,спр_Работы!$A$2:$A$6000,0)),"") | R87: да | T87: =IF(AND($P87>0,$R87="да"),MAX($T$1:$T86)+1,"")
A88: =IFERROR(INDEX(спр_Работы!$D$2:$D$6000,MATCH($C88,спр_Работы!$A$2:$A$6000,0)),"") | B88: =IFERROR(INDEX(спр_Работы!$F$2:$F$6000,MATCH($C88,спр_Работы!$A$2:$A$6000,0)),"") | C88: =IFERROR(INDEX(спр_Работы!$A$2:$A$6000,87),"") | D88: =IFERROR(INDEX(спр_Работы!$B$2:$B$6000,MATCH($C88,спр_Работы!$A$2:$A$6000,0)),"") | E88: =IFERROR(INDEX(спр_Работы!$C$2:$C$6000,MATCH($C88,спр_Работы!$A$2:$A$6000,0)),"") | F88: =IFERROR(INDEX(спр_Работы!$G$2:$G$6000,MATCH($C88,спр_Работы!$A$2:$A$6000,0)),"") | G88: =IFERROR(INDEX(спр_Работы!$K$2:$K$6000,MATCH($C88,спр_Работы!$A$2:$A$6000,0)),"") | J88: =IFERROR(INDEX(спр_Материалы!$B$2:$B$9000,MATCH($I88,спр_Материалы!$A$2:$A$9000,0)),"") | K88: =IF($I88="","",IF($F88=IFERROR(INDEX(спр_Материалы!$G$2:$G$9000,MATCH($I88,спр_Материалы!$A$2:$A$9000,0)),""),"OK","!! не та группа")) | L88: =IFERROR(INDEX(спр_Работы!$H$2:$H$6000,MATCH($C88,спр_Работы!$A$2:$A$6000,0))*(1-ДисконтТендер),0) | M88: =IF($I88="",0,IFERROR(INDEX(спр_Материалы!$I$2:$I$9000,MATCH($I88,спр_Материалы!$A$2:$A$9000,0))*IF(INDEX(спр_Материалы!$J$2:$J$9000,MATCH($I88,спр_Материалы!$A$2:$A$9000,0))="USD",КурсUSD,IF(INDEX(спр_Материалы!$J$2:$J$9000,MATCH($I88,спр_Материалы!$A$2:$A$9000,0))="EUR",КурсEUR,1))*INDEX(спр_Материалы!$K$2:$K$9000,MATCH($I88,спр_Материалы!$A$2:$A$9000,0))*(1+IFERROR(INDEX(спр_Работы!$I$2:$I$6000,MATCH($C88,спр_Работы!$A$2:$A$6000,0))/100,0))*(1-ДисконтТендер),0)) | N88: =IF(AND($R88="да",$H88<>""),ROUND($H88*$L88,2),0) | O88: =IF(AND($R88="да",$H88<>""),ROUND($H88*$M88,2),0) | P88: =$N88+$O88 | Q88: =IFERROR(INDEX(спр_Работы!$J$2:$J$6000,MATCH($C88,спр_Работы!$A$2:$A$6000,0)),"") | R88: да | T88: =IF(AND($P88>0,$R88="да"),MAX($T$1:$T87)+1,"")
A89: =IFERROR(INDEX(спр_Работы!$D$2:$D$6000,MATCH($C89,спр_Работы!$A$2:$A$6000,0)),"") | B89: =IFERROR(INDEX(спр_Работы!$F$2:$F$6000,MATCH($C89,спр_Работы!$A$2:$A$6000,0)),"") | C89: =IFERROR(INDEX(спр_Работы!$A$2:$A$6000,88),"") | D89: =IFERROR(INDEX(спр_Работы!$B$2:$B$6000,MATCH($C89,спр_Работы!$A$2:$A$6000,0)),"") | E89: =IFERROR(INDEX(спр_Работы!$C$2:$C$6000,MATCH($C89,спр_Работы!$A$2:$A$6000,0)),"") | F89: =IFERROR(INDEX(спр_Работы!$G$2:$G$6000,MATCH($C89,спр_Работы!$A$2:$A$6000,0)),"") | G89: =IFERROR(INDEX(спр_Работы!$K$2:$K$6000,MATCH($C89,спр_Работы!$A$2:$A$6000,0)),"") | J89: =IFERROR(INDEX(спр_Материалы!$B$2:$B$9000,MATCH($I89,спр_Материалы!$A$2:$A$9000,0)),"") | K89: =IF($I89="","",IF($F89=IFERROR(INDEX(спр_Материалы!$G$2:$G$9000,MATCH($I89,спр_Материалы!$A$2:$A$9000,0)),""),"OK","!! не та группа")) | L89: =IFERROR(INDEX(спр_Работы!$H$2:$H$6000,MATCH($C89,спр_Работы!$A$2:$A$6000,0))*(1-ДисконтТендер),0) | M89: =IF($I89="",0,IFERROR(INDEX(спр_Материалы!$I$2:$I$9000,MATCH($I89,спр_Материалы!$A$2:$A$9000,0))*IF(INDEX(спр_Материалы!$J$2:$J$9000,MATCH($I89,спр_Материалы!$A$2:$A$9000,0))="USD",КурсUSD,IF(INDEX(спр_Материалы!$J$2:$J$9000,MATCH($I89,спр_Материалы!$A$2:$A$9000,0))="EUR",КурсEUR,1))*INDEX(спр_Материалы!$K$2:$K$9000,MATCH($I89,спр_Материалы!$A$2:$A$9000,0))*(1+IFERROR(INDEX(спр_Работы!$I$2:$I$6000,MATCH($C89,спр_Работы!$A$2:$A$6000,0))/100,0))*(1-ДисконтТендер),0)) | N89: =IF(AND($R89="да",$H89<>""),ROUND($H89*$L89,2),0) | O89: =IF(AND($R89="да",$H89<>""),ROUND($H89*$M89,2),0) | P89: =$N89+$O89 | Q89: =IFERROR(INDEX(спр_Работы!$J$2:$J$6000,MATCH($C89,спр_Работы!$A$2:$A$6000,0)),"") | R89: да | T89: =IF(AND($P89>0,$R89="да"),MAX($T$1:$T88)+1,"")
A90: =IFERROR(INDEX(спр_Работы!$D$2:$D$6000,MATCH($C90,спр_Работы!$A$2:$A$6000,0)),"") | B90: =IFERROR(INDEX(спр_Работы!$F$2:$F$6000,MATCH($C90,спр_Работы!$A$2:$A$6000,0)),"") | C90: =IFERROR(INDEX(спр_Работы!$A$2:$A$6000,89),"") | D90: =IFERROR(INDEX(спр_Работы!$B$2:$B$6000,MATCH($C90,спр_Работы!$A$2:$A$6000,0)),"") | E90: =IFERROR(INDEX(спр_Работы!$C$2:$C$6000,MATCH($C90,спр_Работы!$A$2:$A$6000,0)),"") | F90: =IFERROR(INDEX(спр_Работы!$G$2:$G$6000,MATCH($C90,спр_Работы!$A$2:$A$6000,0)),"") | G90: =IFERROR(INDEX(спр_Работы!$K$2:$K$6000,MATCH($C90,спр_Работы!$A$2:$A$6000,0)),"") | J90: =IFERROR(INDEX(спр_Материалы!$B$2:$B$9000,MATCH($I90,спр_Материалы!$A$2:$A$9000,0)),"") | K90: =IF($I90="","",IF($F90=IFERROR(INDEX(спр_Материалы!$G$2:$G$9000,MATCH($I90,спр_Материалы!$A$2:$A$9000,0)),""),"OK","!! не та группа")) | L90: =IFERROR(INDEX(спр_Работы!$H$2:$H$6000,MATCH($C90,спр_Работы!$A$2:$A$6000,0))*(1-ДисконтТендер),0) | M90: =IF($I90="",0,IFERROR(INDEX(спр_Материалы!$I$2:$I$9000,MATCH($I90,спр_Материалы!$A$2:$A$9000,0))*IF(INDEX(спр_Материалы!$J$2:$J$9000,MATCH($I90,спр_Материалы!$A$2:$A$9000,0))="USD",КурсUSD,IF(INDEX(спр_Материалы!$J$2:$J$9000,MATCH($I90,спр_Материалы!$A$2:$A$9000,0))="EUR",КурсEUR,1))*INDEX(спр_Материалы!$K$2:$K$9000,MATCH($I90,спр_Материалы!$A$2:$A$9000,0))*(1+IFERROR(INDEX(спр_Работы!$I$2:$I$6000,MATCH($C90,спр_Работы!$A$2:$A$6000,0))/100,0))*(1-ДисконтТендер),0)) | N90: =IF(AND($R90="да",$H90<>""),ROUND($H90*$L90,2),0) | O90: =IF(AND($R90="да",$H90<>""),ROUND($H90*$M90,2),0) | P90: =$N90+$O90 | Q90: =IFERROR(INDEX(спр_Работы!$J$2:$J$6000,MATCH($C90,спр_Работы!$A$2:$A$6000,0)),"") | R90: да | T90: =IF(AND($P90>0,$R90="да"),MAX($T$1:$T89)+1,"")
A91: =IFERROR(INDEX(спр_Работы!$D$2:$D$6000,MATCH($C91,спр_Работы!$A$2:$A$6000,0)),"") | B91: =IFERROR(INDEX(спр_Работы!$F$2:$F$6000,MATCH($C91,спр_Работы!$A$2:$A$6000,0)),"") | C91: =IFERROR(INDEX(спр_Работы!$A$2:$A$6000,90),"") | D91: =IFERROR(INDEX(спр_Работы!$B$2:$B$6000,MATCH($C91,спр_Работы!$A$2:$A$6000,0)),"") | E91: =IFERROR(INDEX(спр_Работы!$C$2:$C$6000,MATCH($C91,спр_Работы!$A$2:$A$6000,0)),"") | F91: =IFERROR(INDEX(спр_Работы!$G$2:$G$6000,MATCH($C91,спр_Работы!$A$2:$A$6000,0)),"") | G91: =IFERROR(INDEX(спр_Работы!$K$2:$K$6000,MATCH($C91,спр_Работы!$A$2:$A$6000,0)),"") | J91: =IFERROR(INDEX(спр_Материалы!$B$2:$B$9000,MATCH($I91,спр_Материалы!$A$2:$A$9000,0)),"") | K91: =IF($I91="","",IF($F91=IFERROR(INDEX(спр_Материалы!$G$2:$G$9000,MATCH($I91,спр_Материалы!$A$2:$A$9000,0)),""),"OK","!! не та группа")) | L91: =IFERROR(INDEX(спр_Работы!$H$2:$H$6000,MATCH($C91,спр_Работы!$A$2:$A$6000,0))*(1-ДисконтТендер),0) | M91: =IF($I91="",0,IFERROR(INDEX(спр_Материалы!$I$2:$I$9000,MATCH($I91,спр_Материалы!$A$2:$A$9000,0))*IF(INDEX(спр_Материалы!$J$2:$J$9000,MATCH($I91,спр_Материалы!$A$2:$A$9000,0))="USD",КурсUSD,IF(INDEX(спр_Материалы!$J$2:$J$9000,MATCH($I91,спр_Материалы!$A$2:$A$9000,0))="EUR",КурсEUR,1))*INDEX(спр_Материалы!$K$2:$K$9000,MATCH($I91,спр_Материалы!$A$2:$A$9000,0))*(1+IFERROR(INDEX(спр_Работы!$I$2:$I$6000,MATCH($C91,спр_Работы!$A$2:$A$6000,0))/100,0))*(1-ДисконтТендер),0)) | N91: =IF(AND($R91="да",$H91<>""),ROUND($H91*$L91,2),0) | O91: =IF(AND($R91="да",$H91<>""),ROUND($H91*$M91,2),0) | P91: =$N91+$O91 | Q91: =IFERROR(INDEX(спр_Работы!$J$2:$J$6000,MATCH($C91,спр_Работы!$A$2:$A$6000,0)),"") | R91: да | T91: =IF(AND($P91>0,$R91="да"),MAX($T$1:$T90)+1,"")
A92: =IFERROR(INDEX(спр_Работы!$D$2:$D$6000,MATCH($C92,спр_Работы!$A$2:$A$6000,0)),"") | B92: =IFERROR(INDEX(спр_Работы!$F$2:$F$6000,MATCH($C92,спр_Работы!$A$2:$A$6000,0)),"") | C92: =IFERROR(INDEX(спр_Работы!$A$2:$A$6000,91),"") | D92: =IFERROR(INDEX(спр_Работы!$B$2:$B$6000,MATCH($C92,спр_Работы!$A$2:$A$6000,0)),"") | E92: =IFERROR(INDEX(спр_Работы!$C$2:$C$6000,MATCH($C92,спр_Работы!$A$2:$A$6000,0)),"") | F92: =IFERROR(INDEX(спр_Работы!$G$2:$G$6000,MATCH($C92,спр_Работы!$A$2:$A$6000,0)),"") | G92: =IFERROR(INDEX(спр_Работы!$K$2:$K$6000,MATCH($C92,спр_Работы!$A$2:$A$6000,0)),"") | J92: =IFERROR(INDEX(спр_Материалы!$B$2:$B$9000,MATCH($I92,спр_Материалы!$A$2:$A$9000,0)),"") | K92: =IF($I92="","",IF($F92=IFERROR(INDEX(спр_Материалы!$G$2:$G$9000,MATCH($I92,спр_Материалы!$A$2:$A$9000,0)),""),"OK","!! не та группа")) | L92: =IFERROR(INDEX(спр_Работы!$H$2:$H$6000,MATCH($C92,спр_Работы!$A$2:$A$6000,0))*(1-ДисконтТендер),0) | M92: =IF($I92="",0,IFERROR(INDEX(спр_Материалы!$I$2:$I$9000,MATCH($I92,спр_Материалы!$A$2:$A$9000,0))*IF(INDEX(спр_Материалы!$J$2:$J$9000,MATCH($I92,спр_Материалы!$A$2:$A$9000,0))="USD",КурсUSD,IF(INDEX(спр_Материалы!$J$2:$J$9000,MATCH($I92,спр_Материалы!$A$2:$A$9000,0))="EUR",КурсEUR,1))*INDEX(спр_Материалы!$K$2:$K$9000,MATCH($I92,спр_Материалы!$A$2:$A$9000,0))*(1+IFERROR(INDEX(спр_Работы!$I$2:$I$6000,MATCH($C92,спр_Работы!$A$2:$A$6000,0))/100,0))*(1-ДисконтТендер),0)) | N92: =IF(AND($R92="да",$H92<>""),ROUND($H92*$L92,2),0) | O92: =IF(AND($R92="да",$H92<>""),ROUND($H92*$M92,2),0) | P92: =$N92+$O92 | Q92: =IFERROR(INDEX(спр_Работы!$J$2:$J$6000,MATCH($C92,спр_Работы!$A$2:$A$6000,0)),"") | R92: да | T92: =IF(AND($P92>0,$R92="да"),MAX($T$1:$T91)+1,"")
A93: =IFERROR(INDEX(спр_Работы!$D$2:$D$6000,MATCH($C93,спр_Работы!$A$2:$A$6000,0)),"") | B93: =IFERROR(INDEX(спр_Работы!$F$2:$F$6000,MATCH($C93,спр_Работы!$A$2:$A$6000,0)),"") | C93: =IFERROR(INDEX(спр_Работы!$A$2:$A$6000,92),"") | D93: =IFERROR(INDEX(спр_Работы!$B$2:$B$6000,MATCH($C93,спр_Работы!$A$2:$A$6000,0)),"") | E93: =IFERROR(INDEX(спр_Работы!$C$2:$C$6000,MATCH($C93,спр_Работы!$A$2:$A$6000,0)),"") | F93: =IFERROR(INDEX(спр_Работы!$G$2:$G$6000,MATCH($C93,спр_Работы!$A$2:$A$6000,0)),"") | G93: =IFERROR(INDEX(спр_Работы!$K$2:$K$6000,MATCH($C93,спр_Работы!$A$2:$A$6000,0)),"") | J93: =IFERROR(INDEX(спр_Материалы!$B$2:$B$9000,MATCH($I93,спр_Материалы!$A$2:$A$9000,0)),"") | K93: =IF($I93="","",IF($F93=IFERROR(INDEX(спр_Материалы!$G$2:$G$9000,MATCH($I93,спр_Материалы!$A$2:$A$9000,0)),""),"OK","!! не та группа")) | L93: =IFERROR(INDEX(спр_Работы!$H$2:$H$6000,MATCH($C93,спр_Работы!$A$2:$A$6000,0))*(1-ДисконтТендер),0) | M93: =IF($I93="",0,IFERROR(INDEX(спр_Материалы!$I$2:$I$9000,MATCH($I93,спр_Материалы!$A$2:$A$9000,0))*IF(INDEX(спр_Материалы!$J$2:$J$9000,MATCH($I93,спр_Материалы!$A$2:$A$9000,0))="USD",КурсUSD,IF(INDEX(спр_Материалы!$J$2:$J$9000,MATCH($I93,спр_Материалы!$A$2:$A$9000,0))="EUR",КурсEUR,1))*INDEX(спр_Материалы!$K$2:$K$9000,MATCH($I93,спр_Материалы!$A$2:$A$9000,0))*(1+IFERROR(INDEX(спр_Работы!$I$2:$I$6000,MATCH($C93,спр_Работы!$A$2:$A$6000,0))/100,0))*(1-ДисконтТендер),0)) | N93: =IF(AND($R93="да",$H93<>""),ROUND($H93*$L93,2),0) | O93: =IF(AND($R93="да",$H93<>""),ROUND($H93*$M93,2),0) | P93: =$N93+$O93 | Q93: =IFERROR(INDEX(спр_Работы!$J$2:$J$6000,MATCH($C93,спр_Работы!$A$2:$A$6000,0)),"") | R93: да | T93: =IF(AND($P93>0,$R93="да"),MAX($T$1:$T92)+1,"")
A94: =IFERROR(INDEX(спр_Работы!$D$2:$D$6000,MATCH($C94,спр_Работы!$A$2:$A$6000,0)),"") | B94: =IFERROR(INDEX(спр_Работы!$F$2:$F$6000,MATCH($C94,спр_Работы!$A$2:$A$6000,0)),"") | C94: =IFERROR(INDEX(спр_Работы!$A$2:$A$6000,93),"") | D94: =IFERROR(INDEX(спр_Работы!$B$2:$B$6000,MATCH($C94,спр_Работы!$A$2:$A$6000,0)),"") | E94: =IFERROR(INDEX(спр_Работы!$C$2:$C$6000,MATCH($C94,спр_Работы!$A$2:$A$6000,0)),"") | F94: =IFERROR(INDEX(спр_Работы!$G$2:$G$6000,MATCH($C94,спр_Работы!$A$2:$A$6000,0)),"") | G94: =IFERROR(INDEX(спр_Работы!$K$2:$K$6000,MATCH($C94,спр_Работы!$A$2:$A$6000,0)),"") | J94: =IFERROR(INDEX(спр_Материалы!$B$2:$B$9000,MATCH($I94,спр_Материалы!$A$2:$A$9000,0)),"") | K94: =IF($I94="","",IF($F94=IFERROR(INDEX(спр_Материалы!$G$2:$G$9000,MATCH($I94,спр_Материалы!$A$2:$A$9000,0)),""),"OK","!! не та группа")) | L94: =IFERROR(INDEX(спр_Работы!$H$2:$H$6000,MATCH($C94,спр_Работы!$A$2:$A$6000,0))*(1-ДисконтТендер),0) | M94: =IF($I94="",0,IFERROR(INDEX(спр_Материалы!$I$2:$I$9000,MATCH($I94,спр_Материалы!$A$2:$A$9000,0))*IF(INDEX(спр_Материалы!$J$2:$J$9000,MATCH($I94,спр_Материалы!$A$2:$A$9000,0))="USD",КурсUSD,IF(INDEX(спр_Материалы!$J$2:$J$9000,MATCH($I94,спр_Материалы!$A$2:$A$9000,0))="EUR",КурсEUR,1))*INDEX(спр_Материалы!$K$2:$K$9000,MATCH($I94,спр_Материалы!$A$2:$A$9000,0))*(1+IFERROR(INDEX(спр_Работы!$I$2:$I$6000,MATCH($C94,спр_Работы!$A$2:$A$6000,0))/100,0))*(1-ДисконтТендер),0)) | N94: =IF(AND($R94="да",$H94<>""),ROUND($H94*$L94,2),0) | O94: =IF(AND($R94="да",$H94<>""),ROUND($H94*$M94,2),0) | P94: =$N94+$O94 | Q94: =IFERROR(INDEX(спр_Работы!$J$2:$J$6000,MATCH($C94,спр_Работы!$A$2:$A$6000,0)),"") | R94: да | T94: =IF(AND($P94>0,$R94="да"),MAX($T$1:$T93)+1,"")
A95: =IFERROR(INDEX(спр_Работы!$D$2:$D$6000,MATCH($C95,спр_Работы!$A$2:$A$6000,0)),"") | B95: =IFERROR(INDEX(спр_Работы!$F$2:$F$6000,MATCH($C95,спр_Работы!$A$2:$A$6000,0)),"") | C95: =IFERROR(INDEX(спр_Работы!$A$2:$A$6000,94),"") | D95: =IFERROR(INDEX(спр_Работы!$B$2:$B$6000,MATCH($C95,спр_Работы!$A$2:$A$6000,0)),"") | E95: =IFERROR(INDEX(спр_Работы!$C$2:$C$6000,MATCH($C95,спр_Работы!$A$2:$A$6000,0)),"") | F95: =IFERROR(INDEX(спр_Работы!$G$2:$G$6000,MATCH($C95,спр_Работы!$A$2:$A$6000,0)),"") | G95: =IFERROR(INDEX(спр_Работы!$K$2:$K$6000,MATCH($C95,спр_Работы!$A$2:$A$6000,0)),"") | J95: =IFERROR(INDEX(спр_Материалы!$B$2:$B$9000,MATCH($I95,спр_Материалы!$A$2:$A$9000,0)),"") | K95: =IF($I95="","",IF($F95=IFERROR(INDEX(спр_Материалы!$G$2:$G$9000,MATCH($I95,спр_Материалы!$A$2:$A$9000,0)),""),"OK","!! не та группа")) | L95: =IFERROR(INDEX(спр_Работы!$H$2:$H$6000,MATCH($C95,спр_Работы!$A$2:$A$6000,0))*(1-ДисконтТендер),0) | M95: =IF($I95="",0,IFERROR(INDEX(спр_Материалы!$I$2:$I$9000,MATCH($I95,спр_Материалы!$A$2:$A$9000,0))*IF(INDEX(спр_Материалы!$J$2:$J$9000,MATCH($I95,спр_Материалы!$A$2:$A$9000,0))="USD",КурсUSD,IF(INDEX(спр_Материалы!$J$2:$J$9000,MATCH($I95,спр_Материалы!$A$2:$A$9000,0))="EUR",КурсEUR,1))*INDEX(спр_Материалы!$K$2:$K$9000,MATCH($I95,спр_Материалы!$A$2:$A$9000,0))*(1+IFERROR(INDEX(спр_Работы!$I$2:$I$6000,MATCH($C95,спр_Работы!$A$2:$A$6000,0))/100,0))*(1-ДисконтТендер),0)) | N95: =IF(AND($R95="да",$H95<>""),ROUND($H95*$L95,2),0) | O95: =IF(AND($R95="да",$H95<>""),ROUND($H95*$M95,2),0) | P95: =$N95+$O95 | Q95: =IFERROR(INDEX(спр_Работы!$J$2:$J$6000,MATCH($C95,спр_Работы!$A$2:$A$6000,0)),"") | R95: да | T95: =IF(AND($P95>0,$R95="да"),MAX($T$1:$T94)+1,"")
A96: =IFERROR(INDEX(спр_Работы!$D$2:$D$6000,MATCH($C96,спр_Работы!$A$2:$A$6000,0)),"") | B96: =IFERROR(INDEX(спр_Работы!$F$2:$F$6000,MATCH($C96,спр_Работы!$A$2:$A$6000,0)),"") | C96: =IFERROR(INDEX(спр_Работы!$A$2:$A$6000,95),"") | D96: =IFERROR(INDEX(спр_Работы!$B$2:$B$6000,MATCH($C96,спр_Работы!$A$2:$A$6000,0)),"") | E96: =IFERROR(INDEX(спр_Работы!$C$2:$C$6000,MATCH($C96,спр_Работы!$A$2:$A$6000,0)),"") | F96: =IFERROR(INDEX(спр_Работы!$G$2:$G$6000,MATCH($C96,спр_Работы!$A$2:$A$6000,0)),"") | G96: =IFERROR(INDEX(спр_Работы!$K$2:$K$6000,MATCH($C96,спр_Работы!$A$2:$A$6000,0)),"") | J96: =IFERROR(INDEX(спр_Материалы!$B$2:$B$9000,MATCH($I96,спр_Материалы!$A$2:$A$9000,0)),"") | K96: =IF($I96="","",IF($F96=IFERROR(INDEX(спр_Материалы!$G$2:$G$9000,MATCH($I96,спр_Материалы!$A$2:$A$9000,0)),""),"OK","!! не та группа")) | L96: =IFERROR(INDEX(спр_Работы!$H$2:$H$6000,MATCH($C96,спр_Работы!$A$2:$A$6000,0))*(1-ДисконтТендер),0) | M96: =IF($I96="",0,IFERROR(INDEX(спр_Материалы!$I$2:$I$9000,MATCH($I96,спр_Материалы!$A$2:$A$9000,0))*IF(INDEX(спр_Материалы!$J$2:$J$9000,MATCH($I96,спр_Материалы!$A$2:$A$9000,0))="USD",КурсUSD,IF(INDEX(спр_Материалы!$J$2:$J$9000,MATCH($I96,спр_Материалы!$A$2:$A$9000,0))="EUR",КурсEUR,1))*INDEX(спр_Материалы!$K$2:$K$9000,MATCH($I96,спр_Материалы!$A$2:$A$9000,0))*(1+IFERROR(INDEX(спр_Работы!$I$2:$I$6000,MATCH($C96,спр_Работы!$A$2:$A$6000,0))/100,0))*(1-ДисконтТендер),0)) | N96: =IF(AND($R96="да",$H96<>""),ROUND($H96*$L96,2),0) | O96: =IF(AND($R96="да",$H96<>""),ROUND($H96*$M96,2),0) | P96: =$N96+$O96 | Q96: =IFERROR(INDEX(спр_Работы!$J$2:$J$6000,MATCH($C96,спр_Работы!$A$2:$A$6000,0)),"") | R96: да | T96: =IF(AND($P96>0,$R96="да"),MAX($T$1:$T95)+1,"")
A97: =IFERROR(INDEX(спр_Работы!$D$2:$D$6000,MATCH($C97,спр_Работы!$A$2:$A$6000,0)),"") | B97: =IFERROR(INDEX(спр_Работы!$F$2:$F$6000,MATCH($C97,спр_Работы!$A$2:$A$6000,0)),"") | C97: =IFERROR(INDEX(спр_Работы!$A$2:$A$6000,96),"") | D97: =IFERROR(INDEX(спр_Работы!$B$2:$B$6000,MATCH($C97,спр_Работы!$A$2:$A$6000,0)),"") | E97: =IFERROR(INDEX(спр_Работы!$C$2:$C$6000,MATCH($C97,спр_Работы!$A$2:$A$6000,0)),"") | F97: =IFERROR(INDEX(спр_Работы!$G$2:$G$6000,MATCH($C97,спр_Работы!$A$2:$A$6000,0)),"") | G97: =IFERROR(INDEX(спр_Работы!$K$2:$K$6000,MATCH($C97,спр_Работы!$A$2:$A$6000,0)),"") | J97: =IFERROR(INDEX(спр_Материалы!$B$2:$B$9000,MATCH($I97,спр_Материалы!$A$2:$A$9000,0)),"") | K97: =IF($I97="","",IF($F97=IFERROR(INDEX(спр_Материалы!$G$2:$G$9000,MATCH($I97,спр_Материалы!$A$2:$A$9000,0)),""),"OK","!! не та группа")) | L97: =IFERROR(INDEX(спр_Работы!$H$2:$H$6000,MATCH($C97,спр_Работы!$A$2:$A$6000,0))*(1-ДисконтТендер),0) | M97: =IF($I97="",0,IFERROR(INDEX(спр_Материалы!$I$2:$I$9000,MATCH($I97,спр_Материалы!$A$2:$A$9000,0))*IF(INDEX(спр_Материалы!$J$2:$J$9000,MATCH($I97,спр_Материалы!$A$2:$A$9000,0))="USD",КурсUSD,IF(INDEX(спр_Материалы!$J$2:$J$9000,MATCH($I97,спр_Материалы!$A$2:$A$9000,0))="EUR",КурсEUR,1))*INDEX(спр_Материалы!$K$2:$K$9000,MATCH($I97,спр_Материалы!$A$2:$A$9000,0))*(1+IFERROR(INDEX(спр_Работы!$I$2:$I$6000,MATCH($C97,спр_Работы!$A$2:$A$6000,0))/100,0))*(1-ДисконтТендер),0)) | N97: =IF(AND($R97="да",$H97<>""),ROUND($H97*$L97,2),0) | O97: =IF(AND($R97="да",$H97<>""),ROUND($H97*$M97,2),0) | P97: =$N97+$O97 | Q97: =IFERROR(INDEX(спр_Работы!$J$2:$J$6000,MATCH($C97,спр_Работы!$A$2:$A$6000,0)),"") | R97: да | T97: =IF(AND($P97>0,$R97="да"),MAX($T$1:$T96)+1,"")
A98: =IFERROR(INDEX(спр_Работы!$D$2:$D$6000,MATCH($C98,спр_Работы!$A$2:$A$6000,0)),"") | B98: =IFERROR(INDEX(спр_Работы!$F$2:$F$6000,MATCH($C98,спр_Работы!$A$2:$A$6000,0)),"") | C98: =IFERROR(INDEX(спр_Работы!$A$2:$A$6000,97),"") | D98: =IFERROR(INDEX(спр_Работы!$B$2:$B$6000,MATCH($C98,спр_Работы!$A$2:$A$6000,0)),"") | E98: =IFERROR(INDEX(спр_Работы!$C$2:$C$6000,MATCH($C98,спр_Работы!$A$2:$A$6000,0)),"") | F98: =IFERROR(INDEX(спр_Работы!$G$2:$G$6000,MATCH($C98,спр_Работы!$A$2:$A$6000,0)),"") | G98: =IFERROR(INDEX(спр_Работы!$K$2:$K$6000,MATCH($C98,спр_Работы!$A$2:$A$6000,0)),"") | J98: =IFERROR(INDEX(спр_Материалы!$B$2:$B$9000,MATCH($I98,спр_Материалы!$A$2:$A$9000,0)),"") | K98: =IF($I98="","",IF($F98=IFERROR(INDEX(спр_Материалы!$G$2:$G$9000,MATCH($I98,спр_Материалы!$A$2:$A$9000,0)),""),"OK","!! не та группа")) | L98: =IFERROR(INDEX(спр_Работы!$H$2:$H$6000,MATCH($C98,спр_Работы!$A$2:$A$6000,0))*(1-ДисконтТендер),0) | M98: =IF($I98="",0,IFERROR(INDEX(спр_Материалы!$I$2:$I$9000,MATCH($I98,спр_Материалы!$A$2:$A$9000,0))*IF(INDEX(спр_Материалы!$J$2:$J$9000,MATCH($I98,спр_Материалы!$A$2:$A$9000,0))="USD",КурсUSD,IF(INDEX(спр_Материалы!$J$2:$J$9000,MATCH($I98,спр_Материалы!$A$2:$A$9000,0))="EUR",КурсEUR,1))*INDEX(спр_Материалы!$K$2:$K$9000,MATCH($I98,спр_Материалы!$A$2:$A$9000,0))*(1+IFERROR(INDEX(спр_Работы!$I$2:$I$6000,MATCH($C98,спр_Работы!$A$2:$A$6000,0))/100,0))*(1-ДисконтТендер),0)) | N98: =IF(AND($R98="да",$H98<>""),ROUND($H98*$L98,2),0) | O98: =IF(AND($R98="да",$H98<>""),ROUND($H98*$M98,2),0) | P98: =$N98+$O98 | Q98: =IFERROR(INDEX(спр_Работы!$J$2:$J$6000,MATCH($C98,спр_Работы!$A$2:$A$6000,0)),"") | R98: да | T98: =IF(AND($P98>0,$R98="да"),MAX($T$1:$T97)+1,"")
A99: =IFERROR(INDEX(спр_Работы!$D$2:$D$6000,MATCH($C99,спр_Работы!$A$2:$A$6000,0)),"") | B99: =IFERROR(INDEX(спр_Работы!$F$2:$F$6000,MATCH($C99,спр_Работы!$A$2:$A$6000,0)),"") | C99: =IFERROR(INDEX(спр_Работы!$A$2:$A$6000,98),"") | D99: =IFERROR(INDEX(спр_Работы!$B$2:$B$6000,MATCH($C99,спр_Работы!$A$2:$A$6000,0)),"") | E99: =IFERROR(INDEX(спр_Работы!$C$2:$C$6000,MATCH($C99,спр_Работы!$A$2:$A$6000,0)),"") | F99: =IFERROR(INDEX(спр_Работы!$G$2:$G$6000,MATCH($C99,спр_Работы!$A$2:$A$6000,0)),"") | G99: =IFERROR(INDEX(спр_Работы!$K$2:$K$6000,MATCH($C99,спр_Работы!$A$2:$A$6000,0)),"") | J99: =IFERROR(INDEX(спр_Материалы!$B$2:$B$9000,MATCH($I99,спр_Материалы!$A$2:$A$9000,0)),"") | K99: =IF($I99="","",IF($F99=IFERROR(INDEX(спр_Материалы!$G$2:$G$9000,MATCH($I99,спр_Материалы!$A$2:$A$9000,0)),""),"OK","!! не та группа")) | L99: =IFERROR(INDEX(спр_Работы!$H$2:$H$6000,MATCH($C99,спр_Работы!$A$2:$A$6000,0))*(1-ДисконтТендер),0) | M99: =IF($I99="",0,IFERROR(INDEX(спр_Материалы!$I$2:$I$9000,MATCH($I99,спр_Материалы!$A$2:$A$9000,0))*IF(INDEX(спр_Материалы!$J$2:$J$9000,MATCH($I99,спр_Материалы!$A$2:$A$9000,0))="USD",КурсUSD,IF(INDEX(спр_Материалы!$J$2:$J$9000,MATCH($I99,спр_Материалы!$A$2:$A$9000,0))="EUR",КурсEUR,1))*INDEX(спр_Материалы!$K$2:$K$9000,MATCH($I99,спр_Материалы!$A$2:$A$9000,0))*(1+IFERROR(INDEX(спр_Работы!$I$2:$I$6000,MATCH($C99,спр_Работы!$A$2:$A$6000,0))/100,0))*(1-ДисконтТендер),0)) | N99: =IF(AND($R99="да",$H99<>""),ROUND($H99*$L99,2),0) | O99: =IF(AND($R99="да",$H99<>""),ROUND($H99*$M99,2),0) | P99: =$N99+$O99 | Q99: =IFERROR(INDEX(спр_Работы!$J$2:$J$6000,MATCH($C99,спр_Работы!$A$2:$A$6000,0)),"") | R99: да | T99: =IF(AND($P99>0,$R99="да"),MAX($T$1:$T98)+1,"")
A100: =IFERROR(INDEX(спр_Работы!$D$2:$D$6000,MATCH($C100,спр_Работы!$A$2:$A$6000,0)),"") | B100: =IFERROR(INDEX(спр_Работы!$F$2:$F$6000,MATCH($C100,спр_Работы!$A$2:$A$6000,0)),"") | C100: =IFERROR(INDEX(спр_Работы!$A$2:$A$6000,99),"") | D100: =IFERROR(INDEX(спр_Работы!$B$2:$B$6000,MATCH($C100,спр_Работы!$A$2:$A$6000,0)),"") | E100: =IFERROR(INDEX(спр_Работы!$C$2:$C$6000,MATCH($C100,спр_Работы!$A$2:$A$6000,0)),"") | F100: =IFERROR(INDEX(спр_Работы!$G$2:$G$6000,MATCH($C100,спр_Работы!$A$2:$A$6000,0)),"") | G100: =IFERROR(INDEX(спр_Работы!$K$2:$K$6000,MATCH($C100,спр_Работы!$A$2:$A$6000,0)),"") | J100: =IFERROR(INDEX(спр_Материалы!$B$2:$B$9000,MATCH($I100,спр_Материалы!$A$2:$A$9000,0)),"") | K100: =IF($I100="","",IF($F100=IFERROR(INDEX(спр_Материалы!$G$2:$G$9000,MATCH($I100,спр_Материалы!$A$2:$A$9000,0)),""),"OK","!! не та группа")) | L100: =IFERROR(INDEX(спр_Работы!$H$2:$H$6000,MATCH($C100,спр_Работы!$A$2:$A$6000,0))*(1-ДисконтТендер),0) | M100: =IF($I100="",0,IFERROR(INDEX(спр_Материалы!$I$2:$I$9000,MATCH($I100,спр_Материалы!$A$2:$A$9000,0))*IF(INDEX(спр_Материалы!$J$2:$J$9000,MATCH($I100,спр_Материалы!$A$2:$A$9000,0))="USD",КурсUSD,IF(INDEX(спр_Материалы!$J$2:$J$9000,MATCH($I100,спр_Материалы!$A$2:$A$9000,0))="EUR",КурсEUR,1))*INDEX(спр_Материалы!$K$2:$K$9000,MATCH($I100,спр_Материалы!$A$2:$A$9000,0))*(1+IFERROR(INDEX(спр_Работы!$I$2:$I$6000,MATCH($C100,спр_Работы!$A$2:$A$6000,0))/100,0))*(1-ДисконтТендер),0)) | N100: =IF(AND($R100="да",$H100<>""),ROUND($H100*$L100,2),0) | O100: =IF(AND($R100="да",$H100<>""),ROUND($H100*$M100,2),0) | P100: =$N100+$O100 | Q100: =IFERROR(INDEX(спр_Работы!$J$2:$J$6000,MATCH($C100,спр_Работы!$A$2:$A$6000,0)),"") | R100: да | T100: =IF(AND($P100>0,$R100="да"),MAX($T$1:$T99)+1,"")
...

Sheet Смета
A1: СМЕТА
A2: Формат объекта: | C2: =ФорматОбъекта
A3: Адрес объекта: | C3: =Адрес
A4: Площадь объекта (м.кв.): | C4: =S_общая
A5: Срок проведения работ: | C5: =Срок
A6: ПОДРЯДЧИК: | C6: =Подрядчик
A7: Юридический адрес: | C7: =ЮрАдрес
A8: Электронный адрес: | C8: =ЭлАдрес
A9: Контактное лицо (Ф.И.О.): | C9: =КонтЛицо
A10: Контактный телефон: | C10: =КонтТел
A11: Реквизиты: | C11: =Реквизиты
A12: Сумма по смете, ₽: | C12: ='Свод+ТЭП'!$E$23
A13: Цены на дату: | C13: =ДатаЦен
A15: Курс USD: | C15: =КурсUSD
A16: Курс EUR: | C16: =КурсEUR
A17: Дисконт по тендеру, доля: | C17: =ДисконтТендер
A18: Примечание: цены с НР и СП; НДС по режиму из «Параметров».
A19: РАСШИФРОВКА РАБОТ И ЗАТРАТ (пустые строки скрыты; после ввода объёмов — Данные → Применить повторно / Ctrl+Alt+L)
A20: № | B20: Номенкл. № | C20: Наименование работ и затрат | D20: Ед. изм. | E20: Кол-во | F20: Цена ед. работ, ₽ | G20: Цена ед. материалов/оборуд., ₽ | H20: Стоимость работ, ₽ | I20: Стоимость материалов/оборуд., ₽ | J20: Всего, ₽ | K20: _кр | L20: _показать
A21: =IF($K21="","",1) | B21: =IF($K21="","",INDEX(Конструктор!$C$2:$C$1212,$K21)) | C21: =IF($K21="","",INDEX(Конструктор!$D$2:$D$1212,$K21)&IF(INDEX(Конструктор!$J$2:$J$1212,$K21)<>""," — "&INDEX(Конструктор!$J$2:$J$1212,$K21),"")) | D21: =IF($K21="","",INDEX(Конструктор!$E$2:$E$1212,$K21)) | E21: =IF($K21="","",INDEX(Конструктор!$H$2:$H$1212,$K21)) | F21: =IF($K21="","",INDEX(Конструктор!$L$2:$L$1212,$K21)) | G21: =IF($K21="","",INDEX(Конструктор!$M$2:$M$1212,$K21)) | H21: =IF($K21="","",INDEX(Конструктор!$N$2:$N$1212,$K21)) | I21: =IF($K21="","",INDEX(Конструктор!$O$2:$O$1212,$K21)) | J21: =IF($K21="","",INDEX(Конструктор!$P$2:$P$1212,$K21)) | K21: =IFERROR(MATCH(1,Конструктор!$T$2:$T$1212,0),"") | L21: =IF($K21="","","показать")
A22: =IF($K22="","",2) | B22: =IF($K22="","",INDEX(Конструктор!$C$2:$C$1212,$K22)) | C22: =IF($K22="","",INDEX(Конструктор!$D$2:$D$1212,$K22)&IF(INDEX(Конструктор!$J$2:$J$1212,$K22)<>""," — "&INDEX(Конструктор!$J$2:$J$1212,$K22),"")) | D22: =IF($K22="","",INDEX(Конструктор!$E$2:$E$1212,$K22)) | E22: =IF($K22="","",INDEX(Конструктор!$H$2:$H$1212,$K22)) | F22: =IF($K22="","",INDEX(Конструктор!$L$2:$L$1212,$K22)) | G22: =IF($K22="","",INDEX(Конструктор!$M$2:$M$1212,$K22)) | H22: =IF($K22="","",INDEX(Конструктор!$N$2:$N$1212,$K22)) | I22: =IF($K22="","",INDEX(Конструктор!$O$2:$O$1212,$K22)) | J22: =IF($K22="","",INDEX(Конструктор!$P$2:$P$1212,$K22)) | K22: =IFERROR(MATCH(2,Конструктор!$T$2:$T$1212,0),"") | L22: =IF($K22="","","показать")
A23: =IF($K23="","",3) | B23: =IF($K23="","",INDEX(Конструктор!$C$2:$C$1212,$K23)) | C23: =IF($K23="","",INDEX(Конструктор!$D$2:$D$1212,$K23)&IF(INDEX(Конструктор!$J$2:$J$1212,$K23)<>""," — "&INDEX(Конструктор!$J$2:$J$1212,$K23),"")) | D23: =IF($K23="","",INDEX(Конструктор!$E$2:$E$1212,$K23)) | E23: =IF($K23="","",INDEX(Конструктор!$H$2:$H$1212,$K23)) | F23: =IF($K23="","",INDEX(Конструктор!$L$2:$L$1212,$K23)) | G23: =IF($K23="","",INDEX(Конструктор!$M$2:$M$1212,$K23)) | H23: =IF($K23="","",INDEX(Конструктор!$N$2:$N$1212,$K23)) | I23: =IF($K23="","",INDEX(Конструктор!$O$2:$O$1212,$K23)) | J23: =IF($K23="","",INDEX(Конструктор!$P$2:$P$1212,$K23)) | K23: =IFERROR(MATCH(3,Конструктор!$T$2:$T$1212,0),"") | L23: =IF($K23="","","показать")
A24: =IF($K24="","",4) | B24: =IF($K24="","",INDEX(Конструктор!$C$2:$C$1212,$K24)) | C24: =IF($K24="","",INDEX(Конструктор!$D$2:$D$1212,$K24)&IF(INDEX(Конструктор!$J$2:$J$1212,$K24)<>""," — "&INDEX(Конструктор!$J$2:$J$1212,$K24),"")) | D24: =IF($K24="","",INDEX(Конструктор!$E$2:$E$1212,$K24)) | E24: =IF($K24="","",INDEX(Конструктор!$H$2:$H$1212,$K24)) | F24: =IF($K24="","",INDEX(Конструктор!$L$2:$L$1212,$K24)) | G24: =IF($K24="","",INDEX(Конструктор!$M$2:$M$1212,$K24)) | H24: =IF($K24="","",INDEX(Конструктор!$N$2:$N$1212,$K24)) | I24: =IF($K24="","",INDEX(Конструктор!$O$2:$O$1212,$K24)) | J24: =IF($K24="","",INDEX(Конструктор!$P$2:$P$1212,$K24)) | K24: =IFERROR(MATCH(4,Конструктор!$T$2:$T$1212,0),"") | L24: =IF($K24="","","показать")
A25: =IF($K25="","",5) | B25: =IF($K25="","",INDEX(Конструктор!$C$2:$C$1212,$K25)) | C25: =IF($K25="","",INDEX(Конструктор!$D$2:$D$1212,$K25)&IF(INDEX(Конструктор!$J$2:$J$1212,$K25)<>""," — "&INDEX(Конструктор!$J$2:$J$1212,$K25),"")) | D25: =IF($K25="","",INDEX(Конструктор!$E$2:$E$1212,$K25)) | E25: =IF($K25="","",INDEX(Конструктор!$H$2:$H$1212,$K25)) | F25: =IF($K25="","",INDEX(Конструктор!$L$2:$L$1212,$K25)) | G25: =IF($K25="","",INDEX(Конструктор!$M$2:$M$1212,$K25)) | H25: =IF($K25="","",INDEX(Конструктор!$N$2:$N$1212,$K25)) | I25: =IF($K25="","",INDEX(Конструктор!$O$2:$O$1212,$K25)) | J25: =IF($K25="","",INDEX(Конструктор!$P$2:$P$1212,$K25)) | K25: =IFERROR(MATCH(5,Конструктор!$T$2:$T$1212,0),"") | L25: =IF($K25="","","показать")
A26: =IF($K26="","",6) | B26: =IF($K26="","",INDEX(Конструктор!$C$2:$C$1212,$K26)) | C26: =IF($K26="","",INDEX(Конструктор!$D$2:$D$1212,$K26)&IF(INDEX(Конструктор!$J$2:$J$1212,$K26)<>""," — "&INDEX(Конструктор!$J$2:$J$1212,$K26),"")) | D26: =IF($K26="","",INDEX(Конструктор!$E$2:$E$1212,$K26)) | E26: =IF($K26="","",INDEX(Конструктор!$H$2:$H$1212,$K26)) | F26: =IF($K26="","",INDEX(Конструктор!$L$2:$L$1212,$K26)) | G26: =IF($K26="","",INDEX(Конструктор!$M$2:$M$1212,$K26)) | H26: =IF($K26="","",INDEX(Конструктор!$N$2:$N$1212,$K26)) | I26: =IF($K26="","",INDEX(Конструктор!$O$2:$O$1212,$K26)) | J26: =IF($K26="","",INDEX(Конструктор!$P$2:$P$1212,$K26)) | K26: =IFERROR(MATCH(6,Конструктор!$T$2:$T$1212,0),"") | L26: =IF($K26="","","показать")
A27: =IF($K27="","",7) | B27: =IF($K27="","",INDEX(Конструктор!$C$2:$C$1212,$K27)) | C27: =IF($K27="","",INDEX(Конструктор!$D$2:$D$1212,$K27)&IF(INDEX(Конструктор!$J$2:$J$1212,$K27)<>""," — "&INDEX(Конструктор!$J$2:$J$1212,$K27),"")) | D27: =IF($K27="","",INDEX(Конструктор!$E$2:$E$1212,$K27)) | E27: =IF($K27="","",INDEX(Конструктор!$H$2:$H$1212,$K27)) | F27: =IF($K27="","",INDEX(Конструктор!$L$2:$L$1212,$K27)) | G27: =IF($K27="","",INDEX(Конструктор!$M$2:$M$1212,$K27)) | H27: =IF($K27="","",INDEX(Конструктор!$N$2:$N$1212,$K27)) | I27: =IF($K27="","",INDEX(Конструктор!$O$2:$O$1212,$K27)) | J27: =IF($K27="","",INDEX(Конструктор!$P$2:$P$1212,$K27)) | K27: =IFERROR(MATCH(7,Конструктор!$T$2:$T$1212,0),"") | L27: =IF($K27="","","показать")
A28: =IF($K28="","",8) | B28: =IF($K28="","",INDEX(Конструктор!$C$2:$C$1212,$K28)) | C28: =IF($K28="","",INDEX(Конструктор!$D$2:$D$1212,$K28)&IF(INDEX(Конструктор!$J$2:$J$1212,$K28)<>""," — "&INDEX(Конструктор!$J$2:$J$1212,$K28),"")) | D28: =IF($K28="","",INDEX(Конструктор!$E$2:$E$1212,$K28)) | E28: =IF($K28="","",INDEX(Конструктор!$H$2:$H$1212,$K28)) | F28: =IF($K28="","",INDEX(Конструктор!$L$2:$L$1212,$K28)) | G28: =IF($K28="","",INDEX(Конструктор!$M$2:$M$1212,$K28)) | H28: =IF($K28="","",INDEX(Конструктор!$N$2:$N$1212,$K28)) | I28: =IF($K28="","",INDEX(Конструктор!$O$2:$O$1212,$K28)) | J28: =IF($K28="","",INDEX(Конструктор!$P$2:$P$1212,$K28)) | K28: =IFERROR(MATCH(8,Конструктор!$T$2:$T$1212,0),"") | L28: =IF($K28="","","показать")
A29: =IF($K29="","",9) | B29: =IF($K29="","",INDEX(Конструктор!$C$2:$C$1212,$K29)) | C29: =IF($K29="","",INDEX(Конструктор!$D$2:$D$1212,$K29)&IF(INDEX(Конструктор!$J$2:$J$1212,$K29)<>""," — "&INDEX(Конструктор!$J$2:$J$1212,$K29),"")) | D29: =IF($K29="","",INDEX(Конструктор!$E$2:$E$1212,$K29)) | E29: =IF($K29="","",INDEX(Конструктор!$H$2:$H$1212,$K29)) | F29: =IF($K29="","",INDEX(Конструктор!$L$2:$L$1212,$K29)) | G29: =IF($K29="","",INDEX(Конструктор!$M$2:$M$1212,$K29)) | H29: =IF($K29="","",INDEX(Конструктор!$N$2:$N$1212,$K29)) | I29: =IF($K29="","",INDEX(Конструктор!$O$2:$O$1212,$K29)) | J29: =IF($K29="","",INDEX(Конструктор!$P$2:$P$1212,$K29)) | K29: =IFERROR(MATCH(9,Конструктор!$T$2:$T$1212,0),"") | L29: =IF($K29="","","показать")
A30: =IF($K30="","",10) | B30: =IF($K30="","",INDEX(Конструктор!$C$2:$C$1212,$K30)) | C30: =IF($K30="","",INDEX(Конструктор!$D$2:$D$1212,$K30)&IF(INDEX(Конструктор!$J$2:$J$1212,$K30)<>""," — "&INDEX(Конструктор!$J$2:$J$1212,$K30),"")) | D30: =IF($K30="","",INDEX(Конструктор!$E$2:$E$1212,$K30)) | E30: =IF($K30="","",INDEX(Конструктор!$H$2:$H$1212,$K30)) | F30: =IF($K30="","",INDEX(Конструктор!$L$2:$L$1212,$K30)) | G30: =IF($K30="","",INDEX(Конструктор!$M$2:$M$1212,$K30)) | H30: =IF($K30="","",INDEX(Конструктор!$N$2:$N$1212,$K30)) | I30: =IF($K30="","",INDEX(Конструктор!$O$2:$O$1212,$K30)) | J30: =IF($K30="","",INDEX(Конструктор!$P$2:$P$1212,$K30)) | K30: =IFERROR(MATCH(10,Конструктор!$T$2:$T$1212,0),"") | L30: =IF($K30="","","показать")
A31: =IF($K31="","",11) | B31: =IF($K31="","",INDEX(Конструктор!$C$2:$C$1212,$K31)) | C31: =IF($K31="","",INDEX(Конструктор!$D$2:$D$1212,$K31)&IF(INDEX(Конструктор!$J$2:$J$1212,$K31)<>""," — "&INDEX(Конструктор!$J$2:$J$1212,$K31),"")) | D31: =IF($K31="","",INDEX(Конструктор!$E$2:$E$1212,$K31)) | E31: =IF($K31="","",INDEX(Конструктор!$H$2:$H$1212,$K31)) | F31: =IF($K31="","",INDEX(Конструктор!$L$2:$L$1212,$K31)) | G31: =IF($K31="","",INDEX(Конструктор!$M$2:$M$1212,$K31)) | H31: =IF($K31="","",INDEX(Конструктор!$N$2:$N$1212,$K31)) | I31: =IF($K31="","",INDEX(Конструктор!$O$2:$O$1212,$K31)) | J31: =IF($K31="","",INDEX(Конструктор!$P$2:$P$1212,$K31)) | K31: =IFERROR(MATCH(11,Конструктор!$T$2:$T$1212,0),"") | L31: =IF($K31="","","показать")
A32: =IF($K32="","",12) | B32: =IF($K32="","",INDEX(Конструктор!$C$2:$C$1212,$K32)) | C32: =IF($K32="","",INDEX(Конструктор!$D$2:$D$1212,$K32)&IF(INDEX(Конструктор!$J$2:$J$1212,$K32)<>""," — "&INDEX(Конструктор!$J$2:$J$1212,$K32),"")) | D32: =IF($K32="","",INDEX(Конструктор!$E$2:$E$1212,$K32)) | E32: =IF($K32="","",INDEX(Конструктор!$H$2:$H$1212,$K32)) | F32: =IF($K32="","",INDEX(Конструктор!$L$2:$L$1212,$K32)) | G32: =IF($K32="","",INDEX(Конструктор!$M$2:$M$1212,$K32)) | H32: =IF($K32="","",INDEX(Конструктор!$N$2:$N$1212,$K32)) | I32: =IF($K32="","",INDEX(Конструктор!$O$2:$O$1212,$K32)) | J32: =IF($K32="","",INDEX(Конструктор!$P$2:$P$1212,$K32)) | K32: =IFERROR(MATCH(12,Конструктор!$T$2:$T$1212,0),"") | L32: =IF($K32="","","показать")
A33: =IF($K33="","",13) | B33: =IF($K33="","",INDEX(Конструктор!$C$2:$C$1212,$K33)) | C33: =IF($K33="","",INDEX(Конструктор!$D$2:$D$1212,$K33)&IF(INDEX(Конструктор!$J$2:$J$1212,$K33)<>""," — "&INDEX(Конструктор!$J$2:$J$1212,$K33),"")) | D33: =IF($K33="","",INDEX(Конструктор!$E$2:$E$1212,$K33)) | E33: =IF($K33="","",INDEX(Конструктор!$H$2:$H$1212,$K33)) | F33: =IF($K33="","",INDEX(Конструктор!$L$2:$L$1212,$K33)) | G33: =IF($K33="","",INDEX(Конструктор!$M$2:$M$1212,$K33)) | H33: =IF($K33="","",INDEX(Конструктор!$N$2:$N$1212,$K33)) | I33: =IF($K33="","",INDEX(Конструктор!$O$2:$O$1212,$K33)) | J33: =IF($K33="","",INDEX(Конструктор!$P$2:$P$1212,$K33)) | K33: =IFERROR(MATCH(13,Конструктор!$T$2:$T$1212,0),"") | L33: =IF($K33="","","показать")
A34: =IF($K34="","",14) | B34: =IF($K34="","",INDEX(Конструктор!$C$2:$C$1212,$K34)) | C34: =IF($K34="","",INDEX(Конструктор!$D$2:$D$1212,$K34)&IF(INDEX(Конструктор!$J$2:$J$1212,$K34)<>""," — "&INDEX(Конструктор!$J$2:$J$1212,$K34),"")) | D34: =IF($K34="","",INDEX(Конструктор!$E$2:$E$1212,$K34)) | E34: =IF($K34="","",INDEX(Конструктор!$H$2:$H$1212,$K34)) | F34: =IF($K34="","",INDEX(Конструктор!$L$2:$L$1212,$K34)) | G34: =IF($K34="","",INDEX(Конструктор!$M$2:$M$1212,$K34)) | H34: =IF($K34="","",INDEX(Конструктор!$N$2:$N$1212,$K34)) | I34: =IF($K34="","",INDEX(Конструктор!$O$2:$O$1212,$K34)) | J34: =IF($K34="","",INDEX(Конструктор!$P$2:$P$1212,$K34)) | K34: =IFERROR(MATCH(14,Конструктор!$T$2:$T$1212,0),"") | L34: =IF($K34="","","показать")
A35: =IF($K35="","",15) | B35: =IF($K35="","",INDEX(Конструктор!$C$2:$C$1212,$K35)) | C35: =IF($K35="","",INDEX(Конструктор!$D$2:$D$1212,$K35)&IF(INDEX(Конструктор!$J$2:$J$1212,$K35)<>""," — "&INDEX(Конструктор!$J$2:$J$1212,$K35),"")) | D35: =IF($K35="","",INDEX(Конструктор!$E$2:$E$1212,$K35)) | E35: =IF($K35="","",INDEX(Конструктор!$H$2:$H$1212,$K35)) | F35: =IF($K35="","",INDEX(Конструктор!$L$2:$L$1212,$K35)) | G35: =IF($K35="","",INDEX(Конструктор!$M$2:$M$1212,$K35)) | H35: =IF($K35="","",INDEX(Конструктор!$N$2:$N$1212,$K35)) | I35: =IF($K35="","",INDEX(Конструктор!$O$2:$O$1212,$K35)) | J35: =IF($K35="","",INDEX(Конструктор!$P$2:$P$1212,$K35)) | K35: =IFERROR(MATCH(15,Конструктор!$T$2:$T$1212,0),"") | L35: =IF($K35="","","показать")
A36: =IF($K36="","",16) | B36: =IF($K36="","",INDEX(Конструктор!$C$2:$C$1212,$K36)) | C36: =IF($K36="","",INDEX(Конструктор!$D$2:$D$1212,$K36)&IF(INDEX(Конструктор!$J$2:$J$1212,$K36)<>""," — "&INDEX(Конструктор!$J$2:$J$1212,$K36),"")) | D36: =IF($K36="","",INDEX(Конструктор!$E$2:$E$1212,$K36)) | E36: =IF($K36="","",INDEX(Конструктор!$H$2:$H$1212,$K36)) | F36: =IF($K36="","",INDEX(Конструктор!$L$2:$L$1212,$K36)) | G36: =IF($K36="","",INDEX(Конструктор!$M$2:$M$1212,$K36)) | H36: =IF($K36="","",INDEX(Конструктор!$N$2:$N$1212,$K36)) | I36: =IF($K36="","",INDEX(Конструктор!$O$2:$O$1212,$K36)) | J36: =IF($K36="","",INDEX(Конструктор!$P$2:$P$1212,$K36)) | K36: =IFERROR(MATCH(16,Конструктор!$T$2:$T$1212,0),"") | L36: =IF($K36="","","показать")
A37: =IF($K37="","",17) | B37: =IF($K37="","",INDEX(Конструктор!$C$2:$C$1212,$K37)) | C37: =IF($K37="","",INDEX(Конструктор!$D$2:$D$1212,$K37)&IF(INDEX(Конструктор!$J$2:$J$1212,$K37)<>""," — "&INDEX(Конструктор!$J$2:$J$1212,$K37),"")) | D37: =IF($K37="","",INDEX(Конструктор!$E$2:$E$1212,$K37)) | E37: =IF($K37="","",INDEX(Конструктор!$H$2:$H$1212,$K37)) | F37: =IF($K37="","",INDEX(Конструктор!$L$2:$L$1212,$K37)) | G37: =IF($K37="","",INDEX(Конструктор!$M$2:$M$1212,$K37)) | H37: =IF($K37="","",INDEX(Конструктор!$N$2:$N$1212,$K37)) | I37: =IF($K37="","",INDEX(Конструктор!$O$2:$O$1212,$K37)) | J37: =IF($K37="","",INDEX(Конструктор!$P$2:$P$1212,$K37)) | K37: =IFERROR(MATCH(17,Конструктор!$T$2:$T$1212,0),"") | L37: =IF($K37="","","показать")
A38: =IF($K38="","",18) | B38: =IF($K38="","",INDEX(Конструктор!$C$2:$C$1212,$K38)) | C38: =IF($K38="","",INDEX(Конструктор!$D$2:$D$1212,$K38)&IF(INDEX(Конструктор!$J$2:$J$1212,$K38)<>""," — "&INDEX(Конструктор!$J$2:$J$1212,$K38),"")) | D38: =IF($K38="","",INDEX(Конструктор!$E$2:$E$1212,$K38)) | E38: =IF($K38="","",INDEX(Конструктор!$H$2:$H$1212,$K38)) | F38: =IF($K38="","",INDEX(Конструктор!$L$2:$L$1212,$K38)) | G38: =IF($K38="","",INDEX(Конструктор!$M$2:$M$1212,$K38)) | H38: =IF($K38="","",INDEX(Конструктор!$N$2:$N$1212,$K38)) | I38: =IF($K38="","",INDEX(Конструктор!$O$2:$O$1212,$K38)) | J38: =IF($K38="","",INDEX(Конструктор!$P$2:$P$1212,$K38)) | K38: =IFERROR(MATCH(18,Конструктор!$T$2:$T$1212,0),"") | L38: =IF($K38="","","показать")
A39: =IF($K39="","",19) | B39: =IF($K39="","",INDEX(Конструктор!$C$2:$C$1212,$K39)) | C39: =IF($K39="","",INDEX(Конструктор!$D$2:$D$1212,$K39)&IF(INDEX(Конструктор!$J$2:$J$1212,$K39)<>""," — "&INDEX(Конструктор!$J$2:$J$1212,$K39),"")) | D39: =IF($K39="","",INDEX(Конструктор!$E$2:$E$1212,$K39)) | E39: =IF($K39="","",INDEX(Конструктор!$H$2:$H$1212,$K39)) | F39: =IF($K39="","",INDEX(Конструктор!$L$2:$L$1212,$K39)) | G39: =IF($K39="","",INDEX(Конструктор!$M$2:$M$1212,$K39)) | H39: =IF($K39="","",INDEX(Конструктор!$N$2:$N$1212,$K39)) | I39: =IF($K39="","",INDEX(Конструктор!$O$2:$O$1212,$K39)) | J39: =IF($K39="","",INDEX(Конструктор!$P$2:$P$1212,$K39)) | K39: =IFERROR(MATCH(19,Конструктор!$T$2:$T$1212,0),"") | L39: =IF($K39="","","показать")
A40: =IF($K40="","",20) | B40: =IF($K40="","",INDEX(Конструктор!$C$2:$C$1212,$K40)) | C40: =IF($K40="","",INDEX(Конструктор!$D$2:$D$1212,$K40)&IF(INDEX(Конструктор!$J$2:$J$1212,$K40)<>""," — "&INDEX(Конструктор!$J$2:$J$1212,$K40),"")) | D40: =IF($K40="","",INDEX(Конструктор!$E$2:$E$1212,$K40)) | E40: =IF($K40="","",INDEX(Конструктор!$H$2:$H$1212,$K40)) | F40: =IF($K40="","",INDEX(Конструктор!$L$2:$L$1212,$K40)) | G40: =IF($K40="","",INDEX(Конструктор!$M$2:$M$1212,$K40)) | H40: =IF($K40="","",INDEX(Конструктор!$N$2:$N$1212,$K40)) | I40: =IF($K40="","",INDEX(Конструктор!$O$2:$O$1212,$K40)) | J40: =IF($K40="","",INDEX(Конструктор!$P$2:$P$1212,$K40)) | K40: =IFERROR(MATCH(20,Конструктор!$T$2:$T$1212,0),"") | L40: =IF($K40="","","показать")
A41: =IF($K41="","",21) | B41: =IF($K41="","",INDEX(Конструктор!$C$2:$C$1212,$K41)) | C41: =IF($K41="","",INDEX(Конструктор!$D$2:$D$1212,$K41)&IF(INDEX(Конструктор!$J$2:$J$1212,$K41)<>""," — "&INDEX(Конструктор!$J$2:$J$1212,$K41),"")) | D41: =IF($K41="","",INDEX(Конструктор!$E$2:$E$1212,$K41)) | E41: =IF($K41="","",INDEX(Конструктор!$H$2:$H$1212,$K41)) | F41: =IF($K41="","",INDEX(Конструктор!$L$2:$L$1212,$K41)) | G41: =IF($K41="","",INDEX(Конструктор!$M$2:$M$1212,$K41)) | H41: =IF($K41="","",INDEX(Конструктор!$N$2:$N$1212,$K41)) | I41: =IF($K41="","",INDEX(Конструктор!$O$2:$O$1212,$K41)) | J41: =IF($K41="","",INDEX(Конструктор!$P$2:$P$1212,$K41)) | K41: =IFERROR(MATCH(21,Конструктор!$T$2:$T$1212,0),"") | L41: =IF($K41="","","показать")
A42: =IF($K42="","",22) | B42: =IF($K42="","",INDEX(Конструктор!$C$2:$C$1212,$K42)) | C42: =IF($K42="","",INDEX(Конструктор!$D$2:$D$1212,$K42)&IF(INDEX(Конструктор!$J$2:$J$1212,$K42)<>""," — "&INDEX(Конструктор!$J$2:$J$1212,$K42),"")) | D42: =IF($K42="","",INDEX(Конструктор!$E$2:$E$1212,$K42)) | E42: =IF($K42="","",INDEX(Конструктор!$H$2:$H$1212,$K42)) | F42: =IF($K42="","",INDEX(Конструктор!$L$2:$L$1212,$K42)) | G42: =IF($K42="","",INDEX(Конструктор!$M$2:$M$1212,$K42)) | H42: =IF($K42="","",INDEX(Конструктор!$N$2:$N$1212,$K42)) | I42: =IF($K42="","",INDEX(Конструктор!$O$2:$O$1212,$K42)) | J42: =IF($K42="","",INDEX(Конструктор!$P$2:$P$1212,$K42)) | K42: =IFERROR(MATCH(22,Конструктор!$T$2:$T$1212,0),"") | L42: =IF($K42="","","показать")
A43: =IF($K43="","",23) | B43: =IF($K43="","",INDEX(Конструктор!$C$2:$C$1212,$K43)) | C43: =IF($K43="","",INDEX(Конструктор!$D$2:$D$1212,$K43)&IF(INDEX(Конструктор!$J$2:$J$1212,$K43)<>""," — "&INDEX(Конструктор!$J$2:$J$1212,$K43),"")) | D43: =IF($K43="","",INDEX(Конструктор!$E$2:$E$1212,$K43)) | E43: =IF($K43="","",INDEX(Конструктор!$H$2:$H$1212,$K43)) | F43: =IF($K43="","",INDEX(Конструктор!$L$2:$L$1212,$K43)) | G43: =IF($K43="","",INDEX(Конструктор!$M$2:$M$1212,$K43)) | H43: =IF($K43="","",INDEX(Конструктор!$N$2:$N$1212,$K43)) | I43: =IF($K43="","",INDEX(Конструктор!$O$2:$O$1212,$K43)) | J43: =IF($K43="","",INDEX(Конструктор!$P$2:$P$1212,$K43)) | K43: =IFERROR(MATCH(23,Конструктор!$T$2:$T$1212,0),"") | L43: =IF($K43="","","показать")
A44: =IF($K44="","",24) | B44: =IF($K44="","",INDEX(Конструктор!$C$2:$C$1212,$K44)) | C44: =IF($K44="","",INDEX(Конструктор!$D$2:$D$1212,$K44)&IF(INDEX(Конструктор!$J$2:$J$1212,$K44)<>""," — "&INDEX(Конструктор!$J$2:$J$1212,$K44),"")) | D44: =IF($K44="","",INDEX(Конструктор!$E$2:$E$1212,$K44)) | E44: =IF($K44="","",INDEX(Конструктор!$H$2:$H$1212,$K44)) | F44: =IF($K44="","",INDEX(Конструктор!$L$2:$L$1212,$K44)) | G44: =IF($K44="","",INDEX(Конструктор!$M$2:$M$1212,$K44)) | H44: =IF($K44="","",INDEX(Конструктор!$N$2:$N$1212,$K44)) | I44: =IF($K44="","",INDEX(Конструктор!$O$2:$O$1212,$K44)) | J44: =IF($K44="","",INDEX(Конструктор!$P$2:$P$1212,$K44)) | K44: =IFERROR(MATCH(24,Конструктор!$T$2:$T$1212,0),"") | L44: =IF($K44="","","показать")
A45: =IF($K45="","",25) | B45: =IF($K45="","",INDEX(Конструктор!$C$2:$C$1212,$K45)) | C45: =IF($K45="","",INDEX(Конструктор!$D$2:$D$1212,$K45)&IF(INDEX(Конструктор!$J$2:$J$1212,$K45)<>""," — "&INDEX(Конструктор!$J$2:$J$1212,$K45),"")) | D45: =IF($K45="","",INDEX(Конструктор!$E$2:$E$1212,$K45)) | E45: =IF($K45="","",INDEX(Конструктор!$H$2:$H$1212,$K45)) | F45: =IF($K45="","",INDEX(Конструктор!$L$2:$L$1212,$K45)) | G45: =IF($K45="","",INDEX(Конструктор!$M$2:$M$1212,$K45)) | H45: =IF($K45="","",INDEX(Конструктор!$N$2:$N$1212,$K45)) | I45: =IF($K45="","",INDEX(Конструктор!$O$2:$O$1212,$K45)) | J45: =IF($K45="","",INDEX(Конструктор!$P$2:$P$1212,$K45)) | K45: =IFERROR(MATCH(25,Конструктор!$T$2:$T$1212,0),"") | L45: =IF($K45="","","показать")
A46: =IF($K46="","",26) | B46: =IF($K46="","",INDEX(Конструктор!$C$2:$C$1212,$K46)) | C46: =IF($K46="","",INDEX(Конструктор!$D$2:$D$1212,$K46)&IF(INDEX(Конструктор!$J$2:$J$1212,$K46)<>""," — "&INDEX(Конструктор!$J$2:$J$1212,$K46),"")) | D46: =IF($K46="","",INDEX(Конструктор!$E$2:$E$1212,$K46)) | E46: =IF($K46="","",INDEX(Конструктор!$H$2:$H$1212,$K46)) | F46: =IF($K46="","",INDEX(Конструктор!$L$2:$L$1212,$K46)) | G46: =IF($K46="","",INDEX(Конструктор!$M$2:$M$1212,$K46)) | H46: =IF($K46="","",INDEX(Конструктор!$N$2:$N$1212,$K46)) | I46: =IF($K46="","",INDEX(Конструктор!$O$2:$O$1212,$K46)) | J46: =IF($K46="","",INDEX(Конструктор!$P$2:$P$1212,$K46)) | K46: =IFERROR(MATCH(26,Конструктор!$T$2:$T$1212,0),"") | L46: =IF($K46="","","показать")
A47: =IF($K47="","",27) | B47: =IF($K47="","",INDEX(Конструктор!$C$2:$C$1212,$K47)) | C47: =IF($K47="","",INDEX(Конструктор!$D$2:$D$1212,$K47)&IF(INDEX(Конструктор!$J$2:$J$1212,$K47)<>""," — "&INDEX(Конструктор!$J$2:$J$1212,$K47),"")) | D47: =IF($K47="","",INDEX(Конструктор!$E$2:$E$1212,$K47)) | E47: =IF($K47="","",INDEX(Конструктор!$H$2:$H$1212,$K47)) | F47: =IF($K47="","",INDEX(Конструктор!$L$2:$L$1212,$K47)) | G47: =IF($K47="","",INDEX(Конструктор!$M$2:$M$1212,$K47)) | H47: =IF($K47="","",INDEX(Конструктор!$N$2:$N$1212,$K47)) | I47: =IF($K47="","",INDEX(Конструктор!$O$2:$O$1212,$K47)) | J47: =IF($K47="","",INDEX(Конструктор!$P$2:$P$1212,$K47)) | K47: =IFERROR(MATCH(27,Конструктор!$T$2:$T$1212,0),"") | L47: =IF($K47="","","показать")
A48: =IF($K48="","",28) | B48: =IF($K48="","",INDEX(Конструктор!$C$2:$C$1212,$K48)) | C48: =IF($K48="","",INDEX(Конструктор!$D$2:$D$1212,$K48)&IF(INDEX(Конструктор!$J$2:$J$1212,$K48)<>""," — "&INDEX(Конструктор!$J$2:$J$1212,$K48),"")) | D48: =IF($K48="","",INDEX(Конструктор!$E$2:$E$1212,$K48)) | E48: =IF($K48="","",INDEX(Конструктор!$H$2:$H$1212,$K48)) | F48: =IF($K48="","",INDEX(Конструктор!$L$2:$L$1212,$K48)) | G48: =IF($K48="","",INDEX(Конструктор!$M$2:$M$1212,$K48)) | H48: =IF($K48="","",INDEX(Конструктор!$N$2:$N$1212,$K48)) | I48: =IF($K48="","",INDEX(Конструктор!$O$2:$O$1212,$K48)) | J48: =IF($K48="","",INDEX(Конструктор!$P$2:$P$1212,$K48)) | K48: =IFERROR(MATCH(28,Конструктор!$T$2:$T$1212,0),"") | L48: =IF($K48="","","показать")
A49: =IF($K49="","",29) | B49: =IF($K49="","",INDEX(Конструктор!$C$2:$C$1212,$K49)) | C49: =IF($K49="","",INDEX(Конструктор!$D$2:$D$1212,$K49)&IF(INDEX(Конструктор!$J$2:$J$1212,$K49)<>""," — "&INDEX(Конструктор!$J$2:$J$1212,$K49),"")) | D49: =IF($K49="","",INDEX(Конструктор!$E$2:$E$1212,$K49)) | E49: =IF($K49="","",INDEX(Конструктор!$H$2:$H$1212,$K49)) | F49: =IF($K49="","",INDEX(Конструктор!$L$2:$L$1212,$K49)) | G49: =IF($K49="","",INDEX(Конструктор!$M$2:$M$1212,$K49)) | H49: =IF($K49="","",INDEX(Конструктор!$N$2:$N$1212,$K49)) | I49: =IF($K49="","",INDEX(Конструктор!$O$2:$O$1212,$K49)) | J49: =IF($K49="","",INDEX(Конструктор!$P$2:$P$1212,$K49)) | K49: =IFERROR(MATCH(29,Конструктор!$T$2:$T$1212,0),"") | L49: =IF($K49="","","показать")
A50: =IF($K50="","",30) | B50: =IF($K50="","",INDEX(Конструктор!$C$2:$C$1212,$K50)) | C50: =IF($K50="","",INDEX(Конструктор!$D$2:$D$1212,$K50)&IF(INDEX(Конструктор!$J$2:$J$1212,$K50)<>""," — "&INDEX(Конструктор!$J$2:$J$1212,$K50),"")) | D50: =IF($K50="","",INDEX(Конструктор!$E$2:$E$1212,$K50)) | E50: =IF($K50="","",INDEX(Конструктор!$H$2:$H$1212,$K50)) | F50: =IF($K50="","",INDEX(Конструктор!$L$2:$L$1212,$K50)) | G50: =IF($K50="","",INDEX(Конструктор!$M$2:$M$1212,$K50)) | H50: =IF($K50="","",INDEX(Конструктор!$N$2:$N$1212,$K50)) | I50: =IF($K50="","",INDEX(Конструктор!$O$2:$O$1212,$K50)) | J50: =IF($K50="","",INDEX(Конструктор!$P$2:$P$1212,$K50)) | K50: =IFERROR(MATCH(30,Конструктор!$T$2:$T$1212,0),"") | L50: =IF($K50="","","показать")
A51: =IF($K51="","",31) | B51: =IF($K51="","",INDEX(Конструктор!$C$2:$C$1212,$K51)) | C51: =IF($K51="","",INDEX(Конструктор!$D$2:$D$1212,$K51)&IF(INDEX(Конструктор!$J$2:$J$1212,$K51)<>""," — "&INDEX(Конструктор!$J$2:$J$1212,$K51),"")) | D51: =IF($K51="","",INDEX(Конструктор!$E$2:$E$1212,$K51)) | E51: =IF($K51="","",INDEX(Конструктор!$H$2:$H$1212,$K51)) | F51: =IF($K51="","",INDEX(Конструктор!$L$2:$L$1212,$K51)) | G51: =IF($K51="","",INDEX(Конструктор!$M$2:$M$1212,$K51)) | H51: =IF($K51="","",INDEX(Конструктор!$N$2:$N$1212,$K51)) | I51: =IF($K51="","",INDEX(Конструктор!$O$2:$O$1212,$K51)) | J51: =IF($K51="","",INDEX(Конструктор!$P$2:$P$1212,$K51)) | K51: =IFERROR(MATCH(31,Конструктор!$T$2:$T$1212,0),"") | L51: =IF($K51="","","показать")
A52: =IF($K52="","",32) | B52: =IF($K52="","",INDEX(Конструктор!$C$2:$C$1212,$K52)) | C52: =IF($K52="","",INDEX(Конструктор!$D$2:$D$1212,$K52)&IF(INDEX(Конструктор!$J$2:$J$1212,$K52)<>""," — "&INDEX(Конструктор!$J$2:$J$1212,$K52),"")) | D52: =IF($K52="","",INDEX(Конструктор!$E$2:$E$1212,$K52)) | E52: =IF($K52="","",INDEX(Конструктор!$H$2:$H$1212,$K52)) | F52: =IF($K52="","",INDEX(Конструктор!$L$2:$L$1212,$K52)) | G52: =IF($K52="","",INDEX(Конструктор!$M$2:$M$1212,$K52)) | H52: =IF($K52="","",INDEX(Конструктор!$N$2:$N$1212,$K52)) | I52: =IF($K52="","",INDEX(Конструктор!$O$2:$O$1212,$K52)) | J52: =IF($K52="","",INDEX(Конструктор!$P$2:$P$1212,$K52)) | K52: =IFERROR(MATCH(32,Конструктор!$T$2:$T$1212,0),"") | L52: =IF($K52="","","показать")
A53: =IF($K53="","",33) | B53: =IF($K53="","",INDEX(Конструктор!$C$2:$C$1212,$K53)) | C53: =IF($K53="","",INDEX(Конструктор!$D$2:$D$1212,$K53)&IF(INDEX(Конструктор!$J$2:$J$1212,$K53)<>""," — "&INDEX(Конструктор!$J$2:$J$1212,$K53),"")) | D53: =IF($K53="","",INDEX(Конструктор!$E$2:$E$1212,$K53)) | E53: =IF($K53="","",INDEX(Конструктор!$H$2:$H$1212,$K53)) | F53: =IF($K53="","",INDEX(Конструктор!$L$2:$L$1212,$K53)) | G53: =IF($K53="","",INDEX(Конструктор!$M$2:$M$1212,$K53)) | H53: =IF($K53="","",INDEX(Конструктор!$N$2:$N$1212,$K53)) | I53: =IF($K53="","",INDEX(Конструктор!$O$2:$O$1212,$K53)) | J53: =IF($K53="","",INDEX(Конструктор!$P$2:$P$1212,$K53)) | K53: =IFERROR(MATCH(33,Конструктор!$T$2:$T$1212,0),"") | L53: =IF($K53="","","показать")
A54: =IF($K54="","",34) | B54: =IF($K54="","",INDEX(Конструктор!$C$2:$C$1212,$K54)) | C54: =IF($K54="","",INDEX(Конструктор!$D$2:$D$1212,$K54)&IF(INDEX(Конструктор!$J$2:$J$1212,$K54)<>""," — "&INDEX(Конструктор!$J$2:$J$1212,$K54),"")) | D54: =IF($K54="","",INDEX(Конструктор!$E$2:$E$1212,$K54)) | E54: =IF($K54="","",INDEX(Конструктор!$H$2:$H$1212,$K54)) | F54: =IF($K54="","",INDEX(Конструктор!$L$2:$L$1212,$K54)) | G54: =IF($K54="","",INDEX(Конструктор!$M$2:$M$1212,$K54)) | H54: =IF($K54="","",INDEX(Конструктор!$N$2:$N$1212,$K54)) | I54: =IF($K54="","",INDEX(Конструктор!$O$2:$O$1212,$K54)) | J54: =IF($K54="","",INDEX(Конструктор!$P$2:$P$1212,$K54)) | K54: =IFERROR(MATCH(34,Конструктор!$T$2:$T$1212,0),"") | L54: =IF($K54="","","показать")
A55: =IF($K55="","",35) | B55: =IF($K55="","",INDEX(Конструктор!$C$2:$C$1212,$K55)) | C55: =IF($K55="","",INDEX(Конструктор!$D$2:$D$1212,$K55)&IF(INDEX(Конструктор!$J$2:$J$1212,$K55)<>""," — "&INDEX(Конструктор!$J$2:$J$1212,$K55),"")) | D55: =IF($K55="","",INDEX(Конструктор!$E$2:$E$1212,$K55)) | E55: =IF($K55="","",INDEX(Конструктор!$H$2:$H$1212,$K55)) | F55: =IF($K55="","",INDEX(Конструктор!$L$2:$L$1212,$K55)) | G55: =IF($K55="","",INDEX(Конструктор!$M$2:$M$1212,$K55)) | H55: =IF($K55="","",INDEX(Конструктор!$N$2:$N$1212,$K55)) | I55: =IF($K55="","",INDEX(Конструктор!$O$2:$O$1212,$K55)) | J55: =IF($K55="","",INDEX(Конструктор!$P$2:$P$1212,$K55)) | K55: =IFERROR(MATCH(35,Конструктор!$T$2:$T$1212,0),"") | L55: =IF($K55="","","показать")
A56: =IF($K56="","",36) | B56: =IF($K56="","",INDEX(Конструктор!$C$2:$C$1212,$K56)) | C56: =IF($K56="","",INDEX(Конструктор!$D$2:$D$1212,$K56)&IF(INDEX(Конструктор!$J$2:$J$1212,$K56)<>""," — "&INDEX(Конструктор!$J$2:$J$1212,$K56),"")) | D56: =IF($K56="","",INDEX(Конструктор!$E$2:$E$1212,$K56)) | E56: =IF($K56="","",INDEX(Конструктор!$H$2:$H$1212,$K56)) | F56: =IF($K56="","",INDEX(Конструктор!$L$2:$L$1212,$K56)) | G56: =IF($K56="","",INDEX(Конструктор!$M$2:$M$1212,$K56)) | H56: =IF($K56="","",INDEX(Конструктор!$N$2:$N$1212,$K56)) | I56: =IF($K56="","",INDEX(Конструктор!$O$2:$O$1212,$K56)) | J56: =IF($K56="","",INDEX(Конструктор!$P$2:$P$1212,$K56)) | K56: =IFERROR(MATCH(36,Конструктор!$T$2:$T$1212,0),"") | L56: =IF($K56="","","показать")
A57: =IF($K57="","",37) | B57: =IF($K57="","",INDEX(Конструктор!$C$2:$C$1212,$K57)) | C57: =IF($K57="","",INDEX(Конструктор!$D$2:$D$1212,$K57)&IF(INDEX(Конструктор!$J$2:$J$1212,$K57)<>""," — "&INDEX(Конструктор!$J$2:$J$1212,$K57),"")) | D57: =IF($K57="","",INDEX(Конструктор!$E$2:$E$1212,$K57)) | E57: =IF($K57="","",INDEX(Конструктор!$H$2:$H$1212,$K57)) | F57: =IF($K57="","",INDEX(Конструктор!$L$2:$L$1212,$K57)) | G57: =IF($K57="","",INDEX(Конструктор!$M$2:$M$1212,$K57)) | H57: =IF($K57="","",INDEX(Конструктор!$N$2:$N$1212,$K57)) | I57: =IF($K57="","",INDEX(Конструктор!$O$2:$O$1212,$K57)) | J57: =IF($K57="","",INDEX(Конструктор!$P$2:$P$1212,$K57)) | K57: =IFERROR(MATCH(37,Конструктор!$T$2:$T$1212,0),"") | L57: =IF($K57="","","показать")
