Workbook
Name ДисконтТендер: Смета!$C$18
Name КурсCNY: Смета!$C$17
Name КурсEUR: Смета!$C$16
Name КурсUSD: Смета!$C$15
Name мат_VRF_ВНУТ: МАТЕРИАЛЫ!$L$2:$L$259
Name мат_VRF_НАР: МАТЕРИАЛЫ!$L$260:$L$360
Name мат_БРОНЯ: МАТЕРИАЛЫ!$L$361:$L$382
Name мат_ДВ: МАТЕРИАЛЫ!$L$383:$L$393
Name мат_ДВ_АЛ: МАТЕРИАЛЫ!$L$394:$L$399
Name мат_ДВ_ДЕР: МАТЕРИАЛЫ!$L$400:$L$405
Name мат_ДВ_СТ: МАТЕРИАЛЫ!$L$406:$L$410
Name мат_ДОК_ИД: Документация!$F$38:$F$57
Name мат_ДОК_РД: Документация!$F$2:$F$37
Name мат_ЗАВЕСА: МАТЕРИАЛЫ!$L$411:$L$414
Name мат_ЛЮЧОК: МАТЕРИАЛЫ!$L$415:$L$415
Name мат_ПВУ: МАТЕРИАЛЫ!$L$416:$L$431
Name мат_ПЕРЕГ_СТ: МАТЕРИАЛЫ!$L$432:$L$432
Name мат_ПЕРЕГ_ТР: МАТЕРИАЛЫ!$L$433:$L$442
Name мат_ПОЛ_КГ: МАТЕРИАЛЫ!$L$443:$L$450
Name мат_ПОЛ_МОД: МАТЕРИАЛЫ!$L$451:$L$455
Name мат_ПОТОЛОК: МАТЕРИАЛЫ!$L$456:$L$460
Name мат_РАД: МАТЕРИАЛЫ!$L$461:$L$597
Name мат_РАД_КОМПЛ: МАТЕРИАЛЫ!$L$598:$L$612
Name мат_СВЕТ: МАТЕРИАЛЫ!$L$613:$L$925
Name мат_СВЕТ_АВАР: МАТЕРИАЛЫ!$L$926:$L$1035
Name мат_СПЛИТ: МАТЕРИАЛЫ!$L$1036:$L$1151
Name мат_СТЕН_ПЛ: МАТЕРИАЛЫ!$L$1152:$L$1154
Name мат_СТП_РАК: МАТЕРИАЛЫ!$L$1155:$L$1167
Name мат_СТП_СМЕС: МАТЕРИАЛЫ!$L$1168:$L$1180
Name мат_СТП_УНИТ: МАТЕРИАЛЫ!$L$1181:$L$1188
Name мат_ФАЛЬШПОЛ: МАТЕРИАЛЫ!$L$1189:$L$1197
Name мат_ЭУИ_ВЫКЛ: МАТЕРИАЛЫ!$L$1198:$L$1199
Name мат_ЭУИ_РОЗ: МАТЕРИАЛЫ!$L$1200:$L$1208
Name мат_ЭЩ: МАТЕРИАЛЫ!$L$1209:$L$1219
Name спрРазделы: Разделы!$A$2:$B$13

Sheet О файле
A1: ТС ЕР — раздельно. Справочник расценок + сборка смет (Excel 2019+)
A3: КАК РАБОТАТЬ
A4: Этот файл — МАСТЕР (справочник). Смету на объект делай в КОПИИ:
A5: 1. Файл → Сохранить как → «Смета <объект> <дата>.xlsx».
A6: 2. Лист РАБОТЫ. По нужным работам поставь «в смету» = да, впиши «Объём».
A7: Если работа с материалом — выбери «Материал» из списка (список = материалы группы работы).
A8: Нет списка или своего материала — впиши «Цена мат (ручн.), ₽».
A9: Строки «Рабочая/Исполнительная документация» (раздел 1): в «Материал» выбери раздел проекта —
A10: цена подставится с листа «Документация». Для нескольких разделов — вставь копию строки.
A11: Розовая ячейка объёма = работа отмечена, а объём не введён.
A12: 3. Лист «Смета» — печатная форма. Данные → «Применить повторно» (Ctrl+Alt+L): останутся
A13: только отмеченные строки, по разделам, с итогом. Заполни шапку объекта.
... A25: Сформировано: 2026-09-01. Работ: 857. Материалов: 1218. Вариантов документации: 56. Запас строк РАБОТЫ: 1057.

Sheet РАБОТЫ
A1: Код | B1: Раздел | C1: Подраздел | D1: Наименование работы | E1: Ед | F1: Цена работы, ₽ | G1: Группа мат. | H1: Вспом. мат., % | I1: Источник | J1: Дата изм. цены | K1: Кто изменил | L1: в смету | M1: Объём | N1: Материал | O1: Цена мат (ручн.), ₽ | P1: Стоим. работ, ₽ | Q1: Стоим. мат, ₽ | R1: Всего, ₽ | S1: _цр | T1: _цм | U1: _ранг | V1: _рзд | W1: _перв | X1: _строка | Y1: _имя | Z1: _разд_имя
A2: РАБ.Р1.1.001 | B2: Р1 | C2: 1 | D2: Техническое обследование состояния несущих конструкций помещения с подготовкой рекомендаций по усилению (Техничесекое заключение о конструктиве - "ТЗК") (для помещений от 100 до 45… | E2: м2 | F2: 3675 | H2: 0 | I2: ТС ЕР | P2: =IF($L2="да",ROUND(N($M2)*$S2,2),"") | Q2: =IF($L2="да",ROUND(N($M2)*$T2,2),"") | R2: =IF($L2="да",N($P2)+N($Q2),"") | S2: =IF($A2="","",IF(AND(LEFT($G2,3)="ДОК",$N2<>""),IFERROR(INDEX(Документация!$E$2:$E$57,MATCH($N2,Документация!$F$2:$F$57,0)),0),N($F2))*(1-MEDIAN(0,N(ДисконтТендер),1))) -> 3675 | T2: =IF($A2="","",IF(AND(LEFT($G2,3)="ДОК",$N2<>""),0,IF(AND(LEFT($G2,3)<>"ДОК",$N2<>""),IFERROR(INDEX(МАТЕРИАЛЫ!$H$2:$H$9000,MATCH($N2,МАТЕРИАЛЫ!$L$2:$L$9000,0))*IF(INDEX(МАТЕРИАЛЫ!$I$2:$I$9000,MATCH($N2,МАТЕРИАЛЫ!$L$2:$L$9000,0))="USD",КурсUSD,IF(INDEX(МАТЕРИАЛЫ!$I$2:$I$9000,MATCH($N2,МАТЕРИАЛЫ!$L$2:$L$9000,0))="EUR",КурсEUR,IF(INDEX(МАТЕРИАЛЫ!$I$2:$I$9000,MATCH($N2,МАТЕРИАЛЫ!$L$2:$L$9000,0))="CNY",КурсCNY,1)))*(1+N($H2)/100),0),N($O2))*(1-MEDIAN(0,N(ДисконтТендер),1)))) -> 0 | U2: =IF($L2="да",MAX($U$1:$U1)+1,"") | V2: =IF($A2="","",$B2) -> Р1 | W2: =IF($U2="","",IF($U2=1,1,IF($V2<>IFERROR(INDEX($V$2:$V$1058,MATCH($U2-1,$U$2:$U$1058,0)),"~"),1,0))) | X2: =IF($U2="","",$U2+SUMIFS($W$2:$W$1058,$U$2:$U$1058,"<="&$U2)) | Y2: =IF($A2="","",IF(AND(LEFT($G2,3)="ДОК",$N2<>""),IFERROR(INDEX(Документация!$G$2:$G$57,MATCH($N2,Документация!$F$2:$F$57,0)),$D2),$D2&IF(AND(LEFT($G2,3)<>"ДОК",$N2<>"")," — "&IFERROR(INDEX(МАТЕРИАЛЫ!$C$2:$C$9000,MATCH($N2,МАТЕРИАЛЫ!$L$2:$L$9000,0)),""),""))) -> Техническое обследование состояния несущих конструкций помещения с подготовкой рекомендаций по усилению (Техничесекое заключение о конструктиве - "ТЗК") (для помещений от 100 до 45… | Z2: =IF($B2="","",$B2&" · "&IFERROR(VLOOKUP($B2,спрРазделы,2,0),"")) -> Р1 · Проектные работы и согласования
A3: РАБ.Р1.1.002 | B3: Р1 | C3: 1 | D3: Эскизный проект фасада и Колористический паспорт с указанием ведомости отделки и проектным решением со спецификацией элементов (крыльцо, пандус, навесы, колонны и т.д.)(для фасадов… | E3: м2 | F3: 7822.5 | H3: 0 | I3: ТС ЕР | P3: =IF($L3="да",ROUND(N($M3)*$S3,2),"") | Q3: =IF($L3="да",ROUND(N($M3)*$T3,2),"") | R3: =IF($L3="да",N($P3)+N($Q3),"") | S3: =IF($A3="","",IF(AND(LEFT($G3,3)="ДОК",$N3<>""),IFERROR(INDEX(Документация!$E$2:$E$57,MATCH($N3,Документация!$F$2:$F$57,0)),0),N($F3))*(1-MEDIAN(0,N(ДисконтТендер),1))) -> 7822.5 | T3: =IF($A3="","",IF(AND(LEFT($G3,3)="ДОК",$N3<>""),0,IF(AND(LEFT($G3,3)<>"ДОК",$N3<>""),IFERROR(INDEX(МАТЕРИАЛЫ!$H$2:$H$9000,MATCH($N3,МАТЕРИАЛЫ!$L$2:$L$9000,0))*IF(INDEX(МАТЕРИАЛЫ!$I$2:$I$9000,MATCH($N3,МАТЕРИАЛЫ!$L$2:$L$9000,0))="USD",КурсUSD,IF(INDEX(МАТЕРИАЛЫ!$I$2:$I$9000,MATCH($N3,МАТЕРИАЛЫ!$L$2:$L$9000,0))="EUR",КурсEUR,IF(INDEX(МАТЕРИАЛЫ!$I$2:$I$9000,MATCH($N3,МАТЕРИАЛЫ!$L$2:$L$9000,0))="CNY",КурсCNY,1)))*(1+N($H3)/100),0),N($O3))*(1-MEDIAN(0,N(ДисконтТендер),1)))) -> 0 | U3: =IF($L3="да",MAX($U$1:$U2)+1,"") | V3: =IF($A3="","",$B3) -> Р1 | W3: =IF($U3="","",IF($U3=1,1,IF($V3<>IFERROR(INDEX($V$2:$V$1058,MATCH($U3-1,$U$2:$U$1058,0)),"~"),1,0))) | X3: =IF($U3="","",$U3+SUMIFS($W$2:$W$1058,$U$2:$U$1058,"<="&$U3)) | Y3: =IF($A3="","",IF(AND(LEFT($G3,3)="ДОК",$N3<>""),IFERROR(INDEX(Документация!$G$2:$G$57,MATCH($N3,Документация!$F$2:$F$57,0)),$D3),$D3&IF(AND(LEFT($G3,3)<>"ДОК",$N3<>"")," — "&IFERROR(INDEX(МАТЕРИАЛЫ!$C$2:$C$9000,MATCH($N3,МАТЕРИАЛЫ!$L$2:$L$9000,0)),""),""))) -> Эскизный проект фасада и Колористический паспорт с указанием ведомости отделки и проектным решением со спецификацией элементов (крыльцо, пандус, навесы, колонны и т.д.)(для фасадов… | Z3: =IF($B3="","",$B3&" · "&IFERROR(VLOOKUP($B3,спрРазделы,2,0),"")) -> Р1 · Проектные работы и согласования
A4: РАБ.Р1.1.901 | B4: Р1 | C4: 1 | D4: Рабочая документация (раздел проекта — выбрать) | E4: =IF($N4="","—",IFERROR(INDEX(Документация!$D$2:$D$57,MATCH($N4,Документация!$F$2:$F$57,0)),"—")) -> — | F4: 0 | G4: ДОК.РД | H4: 0 | I4: ТС ЕР | P4: =IF($L4="да",ROUND(N($M4)*$S4,2),"") | Q4: =IF($L4="да",ROUND(N($M4)*$T4,2),"") | R4: =IF($L4="да",N($P4)+N($Q4),"") | S4: =IF($A4="","",IF(AND(LEFT($G4,3)="ДОК",$N4<>""),IFERROR(INDEX(Документация!$E$2:$E$57,MATCH($N4,Документация!$F$2:$F$57,0)),0),N($F4))*(1-MEDIAN(0,N(ДисконтТендер),1))) -> 0 | T4: =IF($A4="","",IF(AND(LEFT($G4,3)="ДОК",$N4<>""),0,IF(AND(LEFT($G4,3)<>"ДОК",$N4<>""),IFERROR(INDEX(МАТЕРИАЛЫ!$H$2:$H$9000,MATCH($N4,МАТЕРИАЛЫ!$L$2:$L$9000,0))*IF(INDEX(МАТЕРИАЛЫ!$I$2:$I$9000,MATCH($N4,МАТЕРИАЛЫ!$L$2:$L$9000,0))="USD",КурсUSD,IF(INDEX(МАТЕРИАЛЫ!$I$2:$I$9000,MATCH($N4,МАТЕРИАЛЫ!$L$2:$L$9000,0))="EUR",КурсEUR,IF(INDEX(МАТЕРИАЛЫ!$I$2:$I$9000,MATCH($N4,МАТЕРИАЛЫ!$L$2:$L$9000,0))="CNY",КурсCNY,1)))*(1+N($H4)/100),0),N($O4))*(1-MEDIAN(0,N(ДисконтТендер),1)))) -> 0 | U4: =IF($L4="да",MAX($U$1:$U3)+1,"") | V4: =IF($A4="","",$B4) -> Р1 | W4: =IF($U4="","",IF($U4=1,1,IF($V4<>IFERROR(INDEX($V$2:$V$1058,MATCH($U4-1,$U$2:$U$1058,0)),"~"),1,0))) | X4: =IF($U4="","",$U4+SUMIFS($W$2:$W$1058,$U$2:$U$1058,"<="&$U4)) | Y4: =IF($A4="","",IF(AND(LEFT($G4,3)="ДОК",$N4<>""),IFERROR(INDEX(Документация!$G$2:$G$57,MATCH($N4,Документация!$F$2:$F$57,0)),$D4),$D4&IF(AND(LEFT($G4,3)<>"ДОК",$N4<>"")," — "&IFERROR(INDEX(МАТЕРИАЛЫ!$C$2:$C$9000,MATCH($N4,МАТЕРИАЛЫ!$L$2:$L$9000,0)),""),""))) -> Рабочая документация (раздел проекта — выбрать) | Z4: =IF($B4="","",$B4&" · "&IFERROR(VLOOKUP($B4,спрРазделы,2,0),"")) -> Р1 · Проектные работы и согласования
A5: РАБ.Р1.1.961 | B5: Р1 | C5: 1 | D5: Исполнительная документация (раздел проекта — выбрать) | E5: =IF($N5="","—",IFERROR(INDEX(Документация!$D$2:$D$57,MATCH($N5,Документация!$F$2:$F$57,0)),"—")) -> — | F5: 0 | G5: ДОК.ИД | H5: 0 | I5: ТС ЕР | P5: =IF($L5="да",ROUND(N($M5)*$S5,2),"") | Q5: =IF($L5="да",ROUND(N($M5)*$T5,2),"") | R5: =IF($L5="да",N($P5)+N($Q5),"") | S5: =IF($A5="","",IF(AND(LEFT($G5,3)="ДОК",$N5<>""),IFERROR(INDEX(Документация!$E$2:$E$57,MATCH($N5,Документация!$F$2:$F$57,0)),0),N($F5))*(1-MEDIAN(0,N(ДисконтТендер),1))) -> 0 | T5: =IF($A5="","",IF(AND(LEFT($G5,3)="ДОК",$N5<>""),0,IF(AND(LEFT($G5,3)<>"ДОК",$N5<>""),IFERROR(INDEX(МАТЕРИАЛЫ!$H$2:$H$9000,MATCH($N5,МАТЕРИАЛЫ!$L$2:$L$9000,0))*IF(INDEX(МАТЕРИАЛЫ!$I$2:$I$9000,MATCH($N5,МАТЕРИАЛЫ!$L$2:$L$9000,0))="USD",КурсUSD,IF(INDEX(МАТЕРИАЛЫ!$I$2:$I$9000,MATCH($N5,МАТЕРИАЛЫ!$L$2:$L$9000,0))="EUR",КурсEUR,IF(INDEX(МАТЕРИАЛЫ!$I$2:$I$9000,MATCH($N5,МАТЕРИАЛЫ!$L$2:$L$9000,0))="CNY",КурсCNY,1)))*(1+N($H5)/100),0),N($O5))*(1-MEDIAN(0,N(ДисконтТендер),1)))) -> 0 | U5: =IF($L5="да",MAX($U$1:$U4)+1,"") | V5: =IF($A5="","",$B5) -> Р1 | W5: =IF($U5="","",IF($U5=1,1,IF($V5<>IFERROR(INDEX($V$2:$V$1058,MATCH($U5-1,$U$2:$U$1058,0)),"~"),1,0))) | X5: =IF($U5="","",$U5+SUMIFS($W$2:$W$1058,$U$2:$U$1058,"<="&$U5)) | Y5: =IF($A5="","",IF(AND(LEFT($G5,3)="ДОК",$N5<>""),IFERROR(INDEX(Документация!$G$2:$G$57,MATCH($N5,Документация!$F$2:$F$57,0)),$D5),$D5&IF(AND(LEFT($G5,3)<>"ДОК",$N5<>"")," — "&IFERROR(INDEX(МАТЕРИАЛЫ!$C$2:$C$9000,MATCH($N5,МАТЕРИАЛЫ!$L$2:$L$9000,0)),""),""))) -> Исполнительная документация (раздел проекта — выбрать) | Z5: =IF($B5="","",$B5&" · "&IFERROR(VLOOKUP($B5,спрРазделы,2,0),"")) -> Р1 · Проектные работы и согласования
A6: РАБ.Р1.1.021 | B6: Р1 | C6: 1 | D6: Техническое обследование состояния несущих конструкций помещения с подготовкой рекомендаций по усилению в зоне расположения депозитария, кассового узла и банкоматов (Техничесекое з… | E6: м2 | F6: 3675 | H6: 0 | I6: ТС ЕР | P6: =IF($L6="да",ROUND(N($M6)*$S6,2),"") | Q6: =IF($L6="да",ROUND(N($M6)*$T6,2),"") | R6: =IF($L6="да",N($P6)+N($Q6),"") | S6: =IF($A6="","",IF(AND(LEFT($G6,3)="ДОК",$N6<>""),IFERROR(INDEX(Документация!$E$2:$E$57,MATCH($N6,Документация!$F$2:$F$57,0)),0),N($F6))*(1-MEDIAN(0,N(ДисконтТендер),1))) -> 3675 | T6: =IF($A6="","",IF(AND(LEFT($G6,3)="ДОК",$N6<>""),0,IF(AND(LEFT($G6,3)<>"ДОК",$N6<>""),IFERROR(INDEX(МАТЕРИАЛЫ!$H$2:$H$9000,MATCH($N6,МАТЕРИАЛЫ!$L$2:$L$9000,0))*IF(INDEX(МАТЕРИАЛЫ!$I$2:$I$9000,MATCH($N6,МАТЕРИАЛЫ!$L$2:$L$9000,0))="USD",КурсUSD,IF(INDEX(МАТЕРИАЛЫ!$I$2:$I$9000,MATCH($N6,МАТЕРИАЛЫ!$L$2:$L$9000,0))="EUR",КурсEUR,IF(INDEX(МАТЕРИАЛЫ!$I$2:$I$9000,MATCH($N6,МАТЕРИАЛЫ!$L$2:$L$9000,0))="CNY",КурсCNY,1)))*(1+N($H6)/100),0),N($O6))*(1-MEDIAN(0,N(ДисконтТендер),1)))) -> 0 | U6: =IF($L6="да",MAX($U$1:$U5)+1,"") | V6: =IF($A6="","",$B6) -> Р1 | W6: =IF($U6="","",IF($U6=1,1,IF($V6<>IFERROR(INDEX($V$2:$V$1058,MATCH($U6-1,$U$2:$U$1058,0)),"~"),1,0))) | X6: =IF($U6="","",$U6+SUMIFS($W$2:$W$1058,$U$2:$U$1058,"<="&$U6)) | Y6: =IF($A6="","",IF(AND(LEFT($G6,3)="ДОК",$N6<>""),IFERROR(INDEX(Документация!$G$2:$G$57,MATCH($N6,Документация!$F$2:$F$57,0)),$D6),$D6&IF(AND(LEFT($G6,3)<>"ДОК",$N6<>"")," — "&IFERROR(INDEX(МАТЕРИАЛЫ!$C$2:$C$9000,MATCH($N6,МАТЕРИАЛЫ!$L$2:$L$9000,0)),""),""))) -> Техническое обследование состояния несущих конструкций помещения с подготовкой рекомендаций по усилению в зоне расположения депозитария, кассового узла и банкоматов (Техничесекое з… | Z6: =IF($B6="","",$B6&" · "&IFERROR(VLOOKUP($B6,спрРазделы,2,0),"")) -> Р1 · Проектные работы и согласования
A7: РАБ.Р1.1.022 | B7: Р1 | C7: 1 | D7: Эскизный проект фасада и колористический паспорт с указанием ведомости отделки и проектным решением со спецификацией элементов (крыльцо, пандус, навесы, колонны и т.д.)(для фасадов… | E7: кв.м.площади фасада | F7: 7822.5 | H7: 0 | I7: ТС ЕР | P7: =IF($L7="да",ROUND(N($M7)*$S7,2),"") | Q7: =IF($L7="да",ROUND(N($M7)*$T7,2),"") | R7: =IF($L7="да",N($P7)+N($Q7),"") | S7: =IF($A7="","",IF(AND(LEFT($G7,3)="ДОК",$N7<>""),IFERROR(INDEX(Документация!$E$2:$E$57,MATCH($N7,Документация!$F$2:$F$57,0)),0),N($F7))*(1-MEDIAN(0,N(ДисконтТендер),1))) -> 7822.5 | T7: =IF($A7="","",IF(AND(LEFT($G7,3)="ДОК",$N7<>""),0,IF(AND(LEFT($G7,3)<>"ДОК",$N7<>""),IFERROR(INDEX(МАТЕРИАЛЫ!$H$2:$H$9000,MATCH($N7,МАТЕРИАЛЫ!$L$2:$L$9000,0))*IF(INDEX(МАТЕРИАЛЫ!$I$2:$I$9000,MATCH($N7,МАТЕРИАЛЫ!$L$2:$L$9000,0))="USD",КурсUSD,IF(INDEX(МАТЕРИАЛЫ!$I$2:$I$9000,MATCH($N7,МАТЕРИАЛЫ!$L$2:$L$9000,0))="EUR",КурсEUR,IF(INDEX(МАТЕРИАЛЫ!$I$2:$I$9000,MATCH($N7,МАТЕРИАЛЫ!$L$2:$L$9000,0))="CNY",КурсCNY,1)))*(1+N($H7)/100),0),N($O7))*(1-MEDIAN(0,N(ДисконтТендер),1)))) -> 0 | U7: =IF($L7="да",MAX($U$1:$U6)+1,"") | V7: =IF($A7="","",$B7) -> Р1 | W7: =IF($U7="","",IF($U7=1,1,IF($V7<>IFERROR(INDEX($V$2:$V$1058,MATCH($U7-1,$U$2:$U$1058,0)),"~"),1,0))) | X7: =IF($U7="","",$U7+SUMIFS($W$2:$W$1058,$U$2:$U$1058,"<="&$U7)) | Y7: =IF($A7="","",IF(AND(LEFT($G7,3)="ДОК",$N7<>""),IFERROR(INDEX(Документация!$G$2:$G$57,MATCH($N7,Документация!$F$2:$F$57,0)),$D7),$D7&IF(AND(LEFT($G7,3)<>"ДОК",$N7<>"")," — "&IFERROR(INDEX(МАТЕРИАЛЫ!$C$2:$C$9000,MATCH($N7,МАТЕРИАЛЫ!$L$2:$L$9000,0)),""),""))) -> Эскизный проект фасада и колористический паспорт с указанием ведомости отделки и проектным решением со спецификацией элементов (крыльцо, пандус, навесы, колонны и т.д.)(для фасадов… | Z7: =IF($B7="","",$B7&" · "&IFERROR(VLOOKUP($B7,спрРазделы,2,0),"")) -> Р1 · Проектные работы и согласования
A8: РАБ.Р1.1.061 | B8: Р1 | C8: 1 | D8: Стоимость согласования проекта перепланировки/реставрации объекта культурного наследия в соответствии с нормативными актами г.______________. | E8: м2 | F8: 0 | H8: 0 | I8: ТС ЕР | P8: =IF($L8="да",ROUND(N($M8)*$S8,2),"") | Q8: =IF($L8="да",ROUND(N($M8)*$T8,2),"") | R8: =IF($L8="да",N($P8)+N($Q8),"") | S8: =IF($A8="","",IF(AND(LEFT($G8,3)="ДОК",$N8<>""),IFERROR(INDEX(Документация!$E$2:$E$57,MATCH($N8,Документация!$F$2:$F$57,0)),0),N($F8))*(1-MEDIAN(0,N(ДисконтТендер),1))) -> 0 | T8: =IF($A8="","",IF(AND(LEFT($G8,3)="ДОК",$N8<>""),0,IF(AND(LEFT($G8,3)<>"ДОК",$N8<>""),IFERROR(INDEX(МАТЕРИАЛЫ!$H$2:$H$9000,MATCH($N8,МАТЕРИАЛЫ!$L$2:$L$9000,0))*IF(INDEX(МАТЕРИАЛЫ!$I$2:$I$9000,MATCH($N8,МАТЕРИАЛЫ!$L$2:$L$9000,0))="USD",КурсUSD,IF(INDEX(МАТЕРИАЛЫ!$I$2:$I$9000,MATCH($N8,МАТЕРИАЛЫ!$L$2:$L$9000,0))="EUR",КурсEUR,IF(INDEX(МАТЕРИАЛЫ!$I$2:$I$9000,MATCH($N8,МАТЕРИАЛЫ!$L$2:$L$9000,0))="CNY",КурсCNY,1)))*(1+N($H8)/100),0),N($O8))*(1-MEDIAN(0,N(ДисконтТендер),1)))) -> 0 | U8: =IF($L8="да",MAX($U$1:$U7)+1,"") | V8: =IF($A8="","",$B8) -> Р1 | W8: =IF($U8="","",IF($U8=1,1,IF($V8<>IFERROR(INDEX($V$2:$V$1058,MATCH($U8-1,$U$2:$U$1058,0)),"~"),1,0))) | X8: =IF($U8="","",$U8+SUMIFS($W$2:$W$1058,$U$2:$U$1058,"<="&$U8)) | Y8: =IF($A8="","",IF(AND(LEFT($G8,3)="ДОК",$N8<>""),IFERROR(INDEX(Документация!$G$2:$G$57,MATCH($N8,Документация!$F$2:$F$57,0)),$D8),$D8&IF(AND(LEFT($G8,3)<>"ДОК",$N8<>"")," — "&IFERROR(INDEX(МАТЕРИАЛЫ!$C$2:$C$9000,MATCH($N8,МАТЕРИАЛЫ!$L$2:$L$9000,0)),""),""))) -> Стоимость согласования проекта перепланировки/реставрации объекта культурного наследия в соответствии с нормативными актами г.______________. | Z8: =IF($B8="","",$B8&" · "&IFERROR(VLOOKUP($B8,спрРазделы,2,0),"")) -> Р1 · Проектные работы и согласования
A9: РАБ.Р1.1.062 | B9: Р1 | C9: 1 | D9: Стоимость согласования проекта перепланировки/реконструкции объекта в соответствии с нормативными актами г.______________. | E9: м2 | F9: 0 | H9: 0 | I9: ТС ЕР | P9: =IF($L9="да",ROUND(N($M9)*$S9,2),"") | Q9: =IF($L9="да",ROUND(N($M9)*$T9,2),"") | R9: =IF($L9="да",N($P9)+N($Q9),"") | S9: =IF($A9="","",IF(AND(LEFT($G9,3)="ДОК",$N9<>""),IFERROR(INDEX(Документация!$E$2:$E$57,MATCH($N9,Документация!$F$2:$F$57,0)),0),N($F9))*(1-MEDIAN(0,N(ДисконтТендер),1))) -> 0 | T9: =IF($A9="","",IF(AND(LEFT($G9,3)="ДОК",$N9<>""),0,IF(AND(LEFT($G9,3)<>"ДОК",$N9<>""),IFERROR(INDEX(МАТЕРИАЛЫ!$H$2:$H$9000,MATCH($N9,МАТЕРИАЛЫ!$L$2:$L$9000,0))*IF(INDEX(МАТЕРИАЛЫ!$I$2:$I$9000,MATCH($N9,МАТЕРИАЛЫ!$L$2:$L$9000,0))="USD",КурсUSD,IF(INDEX(МАТЕРИАЛЫ!$I$2:$I$9000,MATCH($N9,МАТЕРИАЛЫ!$L$2:$L$9000,0))="EUR",КурсEUR,IF(INDEX(МАТЕРИАЛЫ!$I$2:$I$9000,MATCH($N9,МАТЕРИАЛЫ!$L$2:$L$9000,0))="CNY",КурсCNY,1)))*(1+N($H9)/100),0),N($O9))*(1-MEDIAN(0,N(ДисконтТендер),1)))) -> 0 | U9: =IF($L9="да",MAX($U$1:$U8)+1,"") | V9: =IF($A9="","",$B9) -> Р1 | W9: =IF($U9="","",IF($U9=1,1,IF($V9<>IFERROR(INDEX($V$2:$V$1058,MATCH($U9-1,$U$2:$U$1058,0)),"~"),1,0))) | X9: =IF($U9="","",$U9+SUMIFS($W$2:$W$1058,$U$2:$U$1058,"<="&$U9)) | Y9: =IF($A9="","",IF(AND(LEFT($G9,3)="ДОК",$N9<>""),IFERROR(INDEX(Документация!$G$2:$G$57,MATCH($N9,Документация!$F$2:$F$57,0)),$D9),$D9&IF(AND(LEFT($G9,3)<>"ДОК",$N9<>"")," — "&IFERROR(INDEX(МАТЕРИАЛЫ!$C$2:$C$9000,MATCH($N9,МАТЕРИАЛЫ!$L$2:$L$9000,0)),""),""))) -> Стоимость согласования проекта перепланировки/реконструкции объекта в соответствии с нормативными актами г.______________. | Z9: =IF($B9="","",$B9&" · "&IFERROR(VLOOKUP($B9,спрРазделы,2,0),"")) -> Р1 · Проектные работы и согласования
A10: РАБ.Р1.1.063 | B10: Р1 | C10: 1 | D10: Получение паспорта БТИ (в черных линиях) | E10: м2 | F10: 0 | H10: 0 | I10: ТС ЕР | P10: =IF($L10="да",ROUND(N($M10)*$S10,2),"") | Q10: =IF($L10="да",ROUND(N($M10)*$T10,2),"") | R10: =IF($L10="да",N($P10)+N($Q10),"") | S10: =IF($A10="","",IF(AND(LEFT($G10,3)="ДОК",$N10<>""),IFERROR(INDEX(Документация!$E$2:$E$57,MATCH($N10,Документация!$F$2:$F$57,0)),0),N($F10))*(1-MEDIAN(0,N(ДисконтТендер),1))) -> 0 | T10: =IF($A10="","",IF(AND(LEFT($G10,3)="ДОК",$N10<>""),0,IF(AND(LEFT($G10,3)<>"ДОК",$N10<>""),IFERROR(INDEX(МАТЕРИАЛЫ!$H$2:$H$9000,MATCH($N10,МАТЕРИАЛЫ!$L$2:$L$9000,0))*IF(INDEX(МАТЕРИАЛЫ!$I$2:$I$9000,MATCH($N10,МАТЕРИАЛЫ!$L$2:$L$9000,0))="USD",КурсUSD,IF(INDEX(МАТЕРИАЛЫ!$I$2:$I$9000,MATCH($N10,МАТЕРИАЛЫ!$L$2:$L$9000,0))="EUR",КурсEUR,IF(INDEX(МАТЕРИАЛЫ!$I$2:$I$9000,MATCH($N10,МАТЕРИАЛЫ!$L$2:$L$9000,0))="CNY",КурсCNY,1)))*(1+N($H10)/100),0),N($O10))*(1-MEDIAN(0,N(ДисконтТендер),1)))) -> 0 | U10: =IF($L10="да",MAX($U$1:$U9)+1,"") | V10: =IF($A10="","",$B10) -> Р1 | W10: =IF($U10="","",IF($U10=1,1,IF($V10<>IFERROR(INDEX($V$2:$V$1058,MATCH($U10-1,$U$2:$U$1058,0)),"~"),1,0))) | X10: =IF($U10="","",$U10+SUMIFS($W$2:$W$1058,$U$2:$U$1058,"<="&$U10)) | Y10: =IF($A10="","",IF(AND(LEFT($G10,3)="ДОК",$N10<>""),IFERROR(INDEX(Документация!$G$2:$G$57,MATCH($N10,Документация!$F$2:$F$57,0)),$D10),$D10&IF(AND(LEFT($G10,3)<>"ДОК",$N10<>"")," — "&IFERROR(INDEX(МАТЕРИАЛЫ!$C$2:$C$9000,MATCH($N10,МАТЕРИАЛЫ!$L$2:$L$9000,0)),""),""))) -> Получение паспорта БТИ (в черных линиях) | Z10: =IF($B10="","",$B10&" · "&IFERROR(VLOOKUP($B10,спрРазделы,2,0),"")) -> Р1 · Проектные работы и согласования
A11: РАБ.Р1.1.064 | B11: Р1 | C11: 1 | D11: Сертификация помещения для совершения операций с ценностями, хранение ценностей по (2) классу вломостойкости и (3) классу пулестойкости | E11: м2 | F11: 88.99 | H11: 0 | I11: ТС ЕР | P11: =IF($L11="да",ROUND(N($M11)*$S11,2),"") | Q11: =IF($L11="да",ROUND(N($M11)*$T11,2),"") | R11: =IF($L11="да",N($P11)+N($Q11),"") | S11: =IF($A11="","",IF(AND(LEFT($G11,3)="ДОК",$N11<>""),IFERROR(INDEX(Документация!$E$2:$E$57,MATCH($N11,Документация!$F$2:$F$57,0)),0),N($F11))*(1-MEDIAN(0,N(ДисконтТендер),1))) -> 88.99 | T11: =IF($A11="","",IF(AND(LEFT($G11,3)="ДОК",$N11<>""),0,IF(AND(LEFT($G11,3)<>"ДОК",$N11<>""),IFERROR(INDEX(МАТЕРИАЛЫ!$H$2:$H$9000,MATCH($N11,МАТЕРИАЛЫ!$L$2:$L$9000,0))*IF(INDEX(МАТЕРИАЛЫ!$I$2:$I$9000,MATCH($N11,МАТЕРИАЛЫ!$L$2:$L$9000,0))="USD",КурсUSD,IF(INDEX(МАТЕРИАЛЫ!$I$2:$I$9000,MATCH($N11,МАТЕРИАЛЫ!$L$2:$L$9000,0))="EUR",КурсEUR,IF(INDEX(МАТЕРИАЛЫ!$I$2:$I$9000,MATCH($N11,МАТЕРИАЛЫ!$L$2:$L$9000,0))="CNY",КурсCNY,1)))*(1+N($H11)/100),0),N($O11))*(1-MEDIAN(0,N(ДисконтТендер),1)))) -> 0 | U11: =IF($L11="да",MAX($U$1:$U10)+1,"") | V11: =IF($A11="","",$B11) -> Р1 | W11: =IF($U11="","",IF($U11=1,1,IF($V11<>IFERROR(INDEX($V$2:$V$1058,MATCH($U11-1,$U$2:$U$1058,0)),"~"),1,0))) | X11: =IF($U11="","",$U11+SUMIFS($W$2:$W$1058,$U$2:$U$1058,"<="&$U11)) | Y11: =IF($A11="","",IF(AND(LEFT($G11,3)="ДОК",$N11<>""),IFERROR(INDEX(Документация!$G$2:$G$57,MATCH($N11,Документация!$F$2:$F$57,0)),$D11),$D11&IF(AND(LEFT($G11,3)<>"ДОК",$N11<>"")," — "&IFERROR(INDEX(МАТЕРИАЛЫ!$C$2:$C$9000,MATCH($N11,МАТЕРИАЛЫ!$L$2:$L$9000,0)),""),""))) -> Сертификация помещения для совершения операций с ценностями, хранение ценностей по (2) классу вломостойкости и (3) классу пулестойкости | Z11: =IF($B11="","",$B11&" · "&IFERROR(VLOOKUP($B11,спрРазделы,2,0),"")) -> Р1 · Проектные работы и согласования
A12: РАБ.Р1.1.065 | B12: Р1 | C12: 1 | D12: Сертификация помещения для совершения операций с ценностями, хранение ценностей по 3 классу вломостойкости и 3 классу пулестойкости | E12: м2 | F12: 149.82 | H12: 0 | I12: ТС ЕР | P12: =IF($L12="да",ROUND(N($M12)*$S12,2),"") | Q12: =IF($L12="да",ROUND(N($M12)*$T12,2),"") | R12: =IF($L12="да",N($P12)+N($Q12),"") | S12: =IF($A12="","",IF(AND(LEFT($G12,3)="ДОК",$N12<>""),IFERROR(INDEX(Документация!$E$2:$E$57,MATCH($N12,Документация!$F$2:$F$57,0)),0),N($F12))*(1-MEDIAN(0,N(ДисконтТендер),1))) -> 149.82 | T12: =IF($A12="","",IF(AND(LEFT($G12,3)="ДОК",$N12<>""),0,IF(AND(LEFT($G12,3)<>"ДОК",$N12<>""),IFERROR(INDEX(МАТЕРИАЛЫ!$H$2:$H$9000,MATCH($N12,МАТЕРИАЛЫ!$L$2:$L$9000,0))*IF(INDEX(МАТЕРИАЛЫ!$I$2:$I$9000,MATCH($N12,МАТЕРИАЛЫ!$L$2:$L$9000,0))="USD",КурсUSD,IF(INDEX(МАТЕРИАЛЫ!$I$2:$I$9000,MATCH($N12,МАТЕРИАЛЫ!$L$2:$L$9000,0))="EUR",КурсEUR,IF(INDEX(МАТЕРИАЛЫ!$I$2:$I$9000,MATCH($N12,МАТЕРИАЛЫ!$L$2:$L$9000,0))="CNY",КурсCNY,1)))*(1+N($H12)/100),0),N($O12))*(1-MEDIAN(0,N(ДисконтТендер),1)))) -> 0 | U12: =IF($L12="да",MAX($U$1:$U11)+1,"") | V12: =IF($A12="","",$B12) -> Р1 | W12: =IF($U12="","",IF($U12=1,1,IF($V12<>IFERROR(INDEX($V$2:$V$1058,MATCH($U12-1,$U$2:$U$1058,0)),"~"),1,0))) | X12: =IF($U12="","",$U12+SUMIFS($W$2:$W$1058,$U$2:$U$1058,"<="&$U12)) | Y12: =IF($A12="","",IF(AND(LEFT($G12,3)="ДОК",$N12<>""),IFERROR(INDEX(Документация!$G$2:$G$57,MATCH($N12,Документация!$F$2:$F$57,0)),$D12),$D12&IF(AND(LEFT($G12,3)<>"ДОК",$N12<>"")," — "&IFERROR(INDEX(МАТЕРИАЛЫ!$C$2:$C$9000,MATCH($N12,МАТЕРИАЛЫ!$L$2:$L$9000,0)),""),""))) -> Сертификация помещения для совершения операций с ценностями, хранение ценностей по 3 классу вломостойкости и 3 классу пулестойкости | Z12: =IF($B12="","",$B12&" · "&IFERROR(VLOOKUP($B12,спрРазделы,2,0),"")) -> Р1 · Проектные работы и согласования
A13: РАБ.Р1.1.066 | B13: Р1 | C13: 1 | D13: Сертификация помещения для совершения операций с ценностями, хранение ценностей по (5) классу вломостойкости | E13: м2 | F13: 96.48 | H13: 0 | I13: ТС ЕР | P13: =IF($L13="да",ROUND(N($M13)*$S13,2),"") | Q13: =IF($L13="да",ROUND(N($M13)*$T13,2),"") | R13: =IF($L13="да",N($P13)+N($Q13),"") | S13: =IF($A13="","",IF(AND(LEFT($G13,3)="ДОК",$N13<>""),IFERROR(INDEX(Документация!$E$2:$E$57,MATCH($N13,Документация!$F$2:$F$57,0)),0),N($F13))*(1-MEDIAN(0,N(ДисконтТендер),1))) -> 96.48 | T13: =IF($A13="","",IF(AND(LEFT($G13,3)="ДОК",$N13<>""),0,IF(AND(LEFT($G13,3)<>"ДОК",$N13<>""),IFERROR(INDEX(МАТЕРИАЛЫ!$H$2:$H$9000,MATCH($N13,МАТЕРИАЛЫ!$L$2:$L$9000,0))*IF(INDEX(МАТЕРИАЛЫ!$I$2:$I$9000,MATCH($N13,МАТЕРИАЛЫ!$L$2:$L$9000,0))="USD",КурсUSD,IF(INDEX(МАТЕРИАЛЫ!$I$2:$I$9000,MATCH($N13,МАТЕРИАЛЫ!$L$2:$L$9000,0))="EUR",КурсEUR,IF(INDEX(МАТЕРИАЛЫ!$I$2:$I$9000,MATCH($N13,МАТЕРИАЛЫ!$L$2:$L$9000,0))="CNY",КурсCNY,1)))*(1+N($H13)/100),0),N($O13))*(1-MEDIAN(0,N(ДисконтТендер),1)))) -> 0 | U13: =IF($L13="да",MAX($U$1:$U12)+1,"") | V13: =IF($A13="","",$B13) -> Р1 | W13: =IF($U13="","",IF($U13=1,1,IF($V13<>IFERROR(INDEX($V$2:$V$1058,MATCH($U13-1,$U$2:$U$1058,0)),"~"),1,0))) | X13: =IF($U13="","",$U13+SUMIFS($W$2:$W$1058,$U$2:$U$1058,"<="&$U13)) | Y13: =IF($A13="","",IF(AND(LEFT($G13,3)="ДОК",$N13<>""),IFERROR(INDEX(Документация!$G$2:$G$57,MATCH($N13,Документация!$F$2:$F$57,0)),$D13),$D13&IF(AND(LEFT($G13,3)<>"ДОК",$N13<>"")," — "&IFERROR(INDEX(МАТЕРИАЛЫ!$C$2:$C$9000,MATCH($N13,МАТЕРИАЛЫ!$L$2:$L$9000,0)),""),""))) -> Сертификация помещения для совершения операций с ценностями, хранение ценностей по (5) классу вломостойкости | Z13: =IF($B13="","",$B13&" · "&IFERROR(VLOOKUP($B13,спрРазделы,2,0),"")) -> Р1 · Проектные работы и согласования
A14: РАБ.Р1.1.067 | B14: Р1 | C14: 1 | D14: Технический отчет электролаборатории для помещений более 100 м.кв. | E14: м2 | F14: 123.58 | H14: 0 | I14: ТС ЕР | P14: =IF($L14="да",ROUND(N($M14)*$S14,2),"") | Q14: =IF($L14="да",ROUND(N($M14)*$T14,2),"") | R14: =IF($L14="да",N($P14)+N($Q14),"") | S14: =IF($A14="","",IF(AND(LEFT($G14,3)="ДОК",$N14<>""),IFERROR(INDEX(Документация!$E$2:$E$57,MATCH($N14,Документация!$F$2:$F$57,0)),0),N($F14))*(1-MEDIAN(0,N(ДисконтТендер),1))) -> 123.58 | T14: =IF($A14="","",IF(AND(LEFT($G14,3)="ДОК",$N14<>""),0,IF(AND(LEFT($G14,3)<>"ДОК",$N14<>""),IFERROR(INDEX(МАТЕРИАЛЫ!$H$2:$H$9000,MATCH($N14,МАТЕРИАЛЫ!$L$2:$L$9000,0))*IF(INDEX(МАТЕРИАЛЫ!$I$2:$I$9000,MATCH($N14,МАТЕРИАЛЫ!$L$2:$L$9000,0))="USD",КурсUSD,IF(INDEX(МАТЕРИАЛЫ!$I$2:$I$9000,MATCH($N14,МАТЕРИАЛЫ!$L$2:$L$9000,0))="EUR",КурсEUR,IF(INDEX(МАТЕРИАЛЫ!$I$2:$I$9000,MATCH($N14,МАТЕРИАЛЫ!$L$2:$L$9000,0))="CNY",КурсCNY,1)))*(1+N($H14)/100),0),N($O14))*(1-MEDIAN(0,N(ДисконтТендер),1)))) -> 0 | U14: =IF($L14="да",MAX($U$1:$U13)+1,"") | V14: =IF($A14="","",$B14) -> Р1 | W14: =IF($U14="","",IF($U14=1,1,IF($V14<>IFERROR(INDEX($V$2:$V$1058,MATCH($U14-1,$U$2:$U$1058,0)),"~"),1,0))) | X14: =IF($U14="","",$U14+SUMIFS($W$2:$W$1058,$U$2:$U$1058,"<="&$U14)) | Y14: =IF($A14="","",IF(AND(LEFT($G14,3)="ДОК",$N14<>""),IFERROR(INDEX(Документация!$G$2:$G$57,MATCH($N14,Документация!$F$2:$F$57,0)),$D14),$D14&IF(AND(LEFT($G14,3)<>"ДОК",$N14<>"")," — "&IFERROR(INDEX(МАТЕРИАЛЫ!$C$2:$C$9000,MATCH($N14,МАТЕРИАЛЫ!$L$2:$L$9000,0)),""),""))) -> Технический отчет электролаборатории для помещений более 100 м.кв. | Z14: =IF($B14="","",$B14&" · "&IFERROR(VLOOKUP($B14,спрРазделы,2,0),"")) -> Р1 · Проектные работы и согласования
A15: РАБ.Р1.1.068 | B15: Р1 | C15: 1 | D15: Технический отчет электролаборатории для помещений менее 100 м.кв. | E15: компл. | F15: 13074.35 | H15: 0 | I15: ТС ЕР | P15: =IF($L15="да",ROUND(N($M15)*$S15,2),"") | Q15: =IF($L15="да",ROUND(N($M15)*$T15,2),"") | R15: =IF($L15="да",N($P15)+N($Q15),"") | S15: =IF($A15="","",IF(AND(LEFT($G15,3)="ДОК",$N15<>""),IFERROR(INDEX(Документация!$E$2:$E$57,MATCH($N15,Документация!$F$2:$F$57,0)),0),N($F15))*(1-MEDIAN(0,N(ДисконтТендер),1))) -> 13074.35 | T15: =IF($A15="","",IF(AND(LEFT($G15,3)="ДОК",$N15<>""),0,IF(AND(LEFT($G15,3)<>"ДОК",$N15<>""),IFERROR(INDEX(МАТЕРИАЛЫ!$H$2:$H$9000,MATCH($N15,МАТЕРИАЛЫ!$L$2:$L$9000,0))*IF(INDEX(МАТЕРИАЛЫ!$I$2:$I$9000,MATCH($N15,МАТЕРИАЛЫ!$L$2:$L$9000,0))="USD",КурсUSD,IF(INDEX(МАТЕРИАЛЫ!$I$2:$I$9000,MATCH($N15,МАТЕРИАЛЫ!$L$2:$L$9000,0))="EUR",КурсEUR,IF(INDEX(МАТЕРИАЛЫ!$I$2:$I$9000,MATCH($N15,МАТЕРИАЛЫ!$L$2:$L$9000,0))="CNY",КурсCNY,1)))*(1+N($H15)/100),0),N($O15))*(1-MEDIAN(0,N(ДисконтТендер),1)))) -> 0 | U15: =IF($L15="да",MAX($U$1:$U14)+1,"") | V15: =IF($A15="","",$B15) -> Р1 | W15: =IF($U15="","",IF($U15=1,1,IF($V15<>IFERROR(INDEX($V$2:$V$1058,MATCH($U15-1,$U$2:$U$1058,0)),"~"),1,0))) | X15: =IF($U15="","",$U15+SUMIFS($W$2:$W$1058,$U$2:$U$1058,"<="&$U15)) | Y15: =IF($A15="","",IF(AND(LEFT($G15,3)="ДОК",$N15<>""),IFERROR(INDEX(Документация!$G$2:$G$57,MATCH($N15,Документация!$F$2:$F$57,0)),$D15),$D15&IF(AND(LEFT($G15,3)<>"ДОК",$N15<>"")," — "&IFERROR(INDEX(МАТЕРИАЛЫ!$C$2:$C$9000,MATCH($N15,МАТЕРИАЛЫ!$L$2:$L$9000,0)),""),""))) -> Технический отчет электролаборатории для помещений менее 100 м.кв. | Z15: =IF($B15="","",$B15&" · "&IFERROR(VLOOKUP($B15,спрРазделы,2,0),"")) -> Р1 · Проектные работы и согласования
A16: РАБ.Р1.1.069 | B16: Р1 | C16: 1 | D16: Стоимость согласования проекта изменения фасада согласно нормативных и законодательных актов г. ___________ и РФ. | E16: м2 | F16: 190.9 | H16: 0 | I16: ТС ЕР | P16: =IF($L16="да",ROUND(N($M16)*$S16,2),"") | Q16: =IF($L16="да",ROUND(N($M16)*$T16,2),"") | R16: =IF($L16="да",N($P16)+N($Q16),"") | S16: =IF($A16="","",IF(AND(LEFT($G16,3)="ДОК",$N16<>""),IFERROR(INDEX(Документация!$E$2:$E$57,MATCH($N16,Документация!$F$2:$F$57,0)),0),N($F16))*(1-MEDIAN(0,N(ДисконтТендер),1))) -> 190.9 | T16: =IF($A16="","",IF(AND(LEFT($G16,3)="ДОК",$N16<>""),0,IF(AND(LEFT($G16,3)<>"ДОК",$N16<>""),IFERROR(INDEX(МАТЕРИАЛЫ!$H$2:$H$9000,MATCH($N16,МАТЕРИАЛЫ!$L$2:$L$9000,0))*IF(INDEX(МАТЕРИАЛЫ!$I$2:$I$9000,MATCH($N16,МАТЕРИАЛЫ!$L$2:$L$9000,0))="USD",КурсUSD,IF(INDEX(МАТЕРИАЛЫ!$I$2:$I$9000,MATCH($N16,МАТЕРИАЛЫ!$L$2:$L$9000,0))="EUR",КурсEUR,IF(INDEX(МАТЕРИАЛЫ!$I$2:$I$9000,MATCH($N16,МАТЕРИАЛЫ!$L$2:$L$9000,0))="CNY",КурсCNY,1)))*(1+N($H16)/100),0),N($O16))*(1-MEDIAN(0,N(ДисконтТендер),1)))) -> 0 | U16: =IF($L16="да",MAX($U$1:$U15)+1,"") | V16: =IF($A16="","",$B16) -> Р1 | W16: =IF($U16="","",IF($U16=1,1,IF($V16<>IFERROR(INDEX($V$2:$V$1058,MATCH($U16-1,$U$2:$U$1058,0)),"~"),1,0))) | X16: =IF($U16="","",$U16+SUMIFS($W$2:$W$1058,$U$2:$U$1058,"<="&$U16)) | Y16: =IF($A16="","",IF(AND(LEFT($G16,3)="ДОК",$N16<>""),IFERROR(INDEX(Документация!$G$2:$G$57,MATCH($N16,Документация!$F$2:$F$57,0)),$D16),$D16&IF(AND(LEFT($G16,3)<>"ДОК",$N16<>"")," — "&IFERROR(INDEX(МАТЕРИАЛЫ!$C$2:$C$9000,MATCH($N16,МАТЕРИАЛЫ!$L$2:$L$9000,0)),""),""))) -> Стоимость согласования проекта изменения фасада согласно нормативных и законодательных актов г. ___________ и РФ. | Z16: =IF($B16="","",$B16&" · "&IFERROR(VLOOKUP($B16,спрРазделы,2,0),"")) -> Р1 · Проектные работы и согласования
A17: РАБ.Р1.1.070 | B17: Р1 | C17: 1 | D17: Разработка дизайн-проекта интерьера | E17: м2 | F17: 0 | H17: 0 | I17: ТС ЕР | P17: =IF($L17="да",ROUND(N($M17)*$S17,2),"") | Q17: =IF($L17="да",ROUND(N($M17)*$T17,2),"") | R17: =IF($L17="да",N($P17)+N($Q17),"") | S17: =IF($A17="","",IF(AND(LEFT($G17,3)="ДОК",$N17<>""),IFERROR(INDEX(Документация!$E$2:$E$57,MATCH($N17,Документация!$F$2:$F$57,0)),0),N($F17))*(1-MEDIAN(0,N(ДисконтТендер),1))) -> 0 | T17: =IF($A17="","",IF(AND(LEFT($G17,3)="ДОК",$N17<>""),0,IF(AND(LEFT($G17,3)<>"ДОК",$N17<>""),IFERROR(INDEX(МАТЕРИАЛЫ!$H$2:$H$9000,MATCH($N17,МАТЕРИАЛЫ!$L$2:$L$9000,0))*IF(INDEX(МАТЕРИАЛЫ!$I$2:$I$9000,MATCH($N17,МАТЕРИАЛЫ!$L$2:$L$9000,0))="USD",КурсUSD,IF(INDEX(МАТЕРИАЛЫ!$I$2:$I$9000,MATCH($N17,МАТЕРИАЛЫ!$L$2:$L$9000,0))="EUR",КурсEUR,IF(INDEX(МАТЕРИАЛЫ!$I$2:$I$9000,MATCH($N17,МАТЕРИАЛЫ!$L$2:$L$9000,0))="CNY",КурсCNY,1)))*(1+N($H17)/100),0),N($O17))*(1-MEDIAN(0,N(ДисконтТендер),1)))) -> 0 | U17: =IF($L17="да",MAX($U$1:$U16)+1,"") | V17: =IF($A17="","",$B17) -> Р1 | W17: =IF($U17="","",IF($U17=1,1,IF($V17<>IFERROR(INDEX($V$2:$V$1058,MATCH($U17-1,$U$2:$U$1058,0)),"~"),1,0))) | X17: =IF($U17="","",$U17+SUMIFS($W$2:$W$1058,$U$2:$U$1058,"<="&$U17)) | Y17: =IF($A17="","",IF(AND(LEFT($G17,3)="ДОК",$N17<>""),IFERROR(INDEX(Документация!$G$2:$G$57,MATCH($N17,Документация!$F$2:$F$57,0)),$D17),$D17&IF(AND(LEFT($G17,3)<>"ДОК",$N17<>"")," — "&IFERROR(INDEX(МАТЕРИАЛЫ!$C$2:$C$9000,MATCH($N17,МАТЕРИАЛЫ!$L$2:$L$9000,0)),""),""))) -> Разработка дизайн-проекта интерьера | Z17: =IF($B17="","",$B17&" · "&IFERROR(VLOOKUP($B17,спрРазделы,2,0),"")) -> Р1 · Проектные работы и согласования
... A161: РАБ.Р2.13.001 | B161: Р2 | C161: 13 | D161: Демонтажные работы до состояния shell-and-core | E161: м2 | F161: 2133.33 | H161: 0 | I161: ТС ЕР | P161: =IF($L161="да",ROUND(N($M161)*$S161,2),"") | Q161: =IF($L161="да",ROUND(N($M161)*$T161,2),"") | R161: =IF($L161="да",N($P161)+N($Q161),"") | S161: =IF($A161="","",IF(AND(LEFT($G161,3)="ДОК",$N161<>""),IFERROR(INDEX(Документация!$E$2:$E$57,MATCH($N161,Документация!$F$2:$F$57,0)),0),N($F161))*(1-MEDIAN(0,N(ДисконтТендер),1))) -> 2133.33 | T161: =IF($A161="","",IF(AND(LEFT($G161,3)="ДОК",$N161<>""),0,IF(AND(LEFT($G161,3)<>"ДОК",$N161<>""),IFERROR(INDEX(МАТЕРИАЛЫ!$H$2:$H$9000,MATCH($N161,МАТЕРИАЛЫ!$L$2:$L$9000,0))*IF(INDEX(МАТЕРИАЛЫ!$I$2:$I$9000,MATCH($N161,МАТЕРИАЛЫ!$L$2:$L$9000,0))="USD",КурсUSD,IF(INDEX(МАТЕРИАЛЫ!$I$2:$I$9000,MATCH($N161,МАТЕРИАЛЫ!$L$2:$L$9000,0))="EUR",КурсEUR,IF(INDEX(МАТЕРИАЛЫ!$I$2:$I$9000,MATCH($N161,МАТЕРИАЛЫ!$L$2:$L$9000,0))="CNY",КурсCNY,1)))*(1+N($H161)/100),0),N($O161))*(1-MEDIAN(0,N(ДисконтТендер),1)))) -> 0 | U161: =IF($L161="да",MAX($U$1:$U160)+1,"") | V161: =IF($A161="","",$B161) -> Р2 | W161: =IF($U161="","",IF($U161=1,1,IF($V161<>IFERROR(INDEX($V$2:$V$1058,MATCH($U161-1,$U$2:$U$1058,0)),"~"),1,0))) | X161: =IF($U161="","",$U161+SUMIFS($W$2:$W$1058,$U$2:$U$1058,"<="&$U161)) | Y161: =IF($A161="","",IF(AND(LEFT($G161,3)="ДОК",$N161<>""),IFERROR(INDEX(Документация!$G$2:$G$57,MATCH($N161,Документация!$F$2:$F$57,0)),$D161),$D161&IF(AND(LEFT($G161,3)<>"ДОК",$N161<>"")," — "&IFERROR(INDEX(МАТЕРИАЛЫ!$C$2:$C$9000,MATCH($N161,МАТЕРИАЛЫ!$L$2:$L$9000,0)),""),""))) -> Демонтажные работы до состояния shell-and-core | Z161: =IF($B161="","",$B161&" · "&IFERROR(VLOOKUP($B161,спрРазделы,2,0),"")) -> Р2 · Демонтажные работы
A162: РАБ.Р3.1.001 | B162: Р3 | C162: 1 | D162: Кладка перегородок толщиной в 1/2 кирпича | E162: м2 | F162: 2392.5 | G162: КЛАДКА | H162: 5 | I162: ТС ЕР | P162: =IF($L162="да",ROUND(N($M162)*$S162,2),"") | Q162: =IF($L162="да",ROUND(N($M162)*$T162,2),"") | R162: =IF($L162="да",N($P162)+N($Q162),"") | S162: =IF($A162="","",IF(AND(LEFT($G162,3)="ДОК",$N162<>""),IFERROR(INDEX(Документация!$E$2:$E$57,MATCH($N162,Документация!$F$2:$F$57,0)),0),N($F162))*(1-MEDIAN(0,N(ДисконтТендер),1))) -> 2392.5 | T162: =IF($A162="","",IF(AND(LEFT($G162,3)="ДОК",$N162<>""),0,IF(AND(LEFT($G162,3)<>"ДОК",$N162<>""),IFERROR(INDEX(МАТЕРИАЛЫ!$H$2:$H$9000,MATCH($N162,МАТЕРИАЛЫ!$L$2:$L$9000,0))*IF(INDEX(МАТЕРИАЛЫ!$I$2:$I$9000,MATCH($N162,МАТЕРИАЛЫ!$L$2:$L$9000,0))="USD",КурсUSD,IF(INDEX(МАТЕРИАЛЫ!$I$2:$I$9000,MATCH($N162,МАТЕРИАЛЫ!$L$2:$L$9000,0))="EUR",КурсEUR,IF(INDEX(МАТЕРИАЛЫ!$I$2:$I$9000,MATCH($N162,МАТЕРИАЛЫ!$L$2:$L$9000,0))="CNY",КурсCNY,1)))*(1+N($H162)/100),0),N($O162))*(1-MEDIAN(0,N(ДисконтТендер),1)))) -> 0 | U162: =IF($L162="да",MAX($U$1:$U161)+1,"") | V162: =IF($A162="","",$B162) -> Р3 | W162: =IF($U162="","",IF($U162=1,1,IF($V162<>IFERROR(INDEX($V$2:$V$1058,MATCH($U162-1,$U$2:$U$1058,0)),"~"),1,0))) | X162: =IF($U162="","",$U162+SUMIFS($W$2:$W$1058,$U$2:$U$1058,"<="&$U162)) | Y162: =IF($A162="","",IF(AND(LEFT($G162,3)="ДОК",$N162<>""),IFERROR(INDEX(Документация!$G$2:$G$57,MATCH($N162,Документация!$F$2:$F$57,0)),$D162),$D162&IF(AND(LEFT($G162,3)<>"ДОК",$N162<>"")," — "&IFERROR(INDEX(МАТЕРИАЛЫ!$C$2:$C$9000,MATCH($N162,МАТЕРИАЛЫ!$L$2:$L$9000,0)),""),""))) -> Кладка перегородок толщиной в 1/2 кирпича | Z162: =IF($B162="","",$B162&" · "&IFERROR(VLOOKUP($B162,спрРазделы,2,0),"")) -> Р3 · Внутренние строительные работы
A163: РАБ.Р3.1.002 | B163: Р3 | C163: 1 | D163: Кладка перегородок армированных толщиной в 1 кирпич | E163: м2 | F163: 2704.48 | G163: КЛАДКА | H163: 5 | I163: ТС ЕР | P163: =IF($L163="да",ROUND(N($M163)*$S163,2),"") | Q163: =IF($L163="да",ROUND(N($M163)*$T163,2),"") | R163: =IF($L163="да",N($P163)+N($Q163),"") | S163: =IF($A163="","",IF(AND(LEFT($G163,3)="ДОК",$N163<>""),IFERROR(INDEX(Документация!$E$2:$E$57,MATCH($N163,Документация!$F$2:$F$57,0)),0),N($F163))*(1-MEDIAN(0,N(ДисконтТендер),1))) -> 2704.48 | T163: =IF($A163="","",IF(AND(LEFT($G163,3)="ДОК",$N163<>""),0,IF(AND(LEFT($G163,3)<>"ДОК",$N163<>""),IFERROR(INDEX(МАТЕРИАЛЫ!$H$2:$H$9000,MATCH($N163,МАТЕРИАЛЫ!$L$2:$L$9000,0))*IF(INDEX(МАТЕРИАЛЫ!$I$2:$I$9000,MATCH($N163,МАТЕРИАЛЫ!$L$2:$L$9000,0))="USD",КурсUSD,IF(INDEX(МАТЕРИАЛЫ!$I$2:$I$9000,MATCH($N163,МАТЕРИАЛЫ!$L$2:$L$9000,0))="EUR",КурсEUR,IF(INDEX(МАТЕРИАЛЫ!$I$2:$I$9000,MATCH($N163,МАТЕРИАЛЫ!$L$2:$L$9000,0))="CNY",КурсCNY,1)))*(1+N($H163)/100),0),N($O163))*(1-MEDIAN(0,N(ДисконтТендер),1)))) -> 0 | U163: =IF($L163="да",MAX($U$1:$U162)+1,"") | V163: =IF($A163="","",$B163) -> Р3 | W163: =IF($U163="","",IF($U163=1,1,IF($V163<>IFERROR(INDEX($V$2:$V$1058,MATCH($U163-1,$U$2:$U$1058,0)),"~"),1,0))) | X163: =IF($U163="","",$U163+SUMIFS($W$2:$W$1058,$U$2:$U$1058,"<="&$U163)) | Y163: =IF($A163="","",IF(AND(LEFT($G163,3)="ДОК",$N163<>""),IFERROR(INDEX(Документация!$G$2:$G$57,MATCH($N163,Документация!$F$2:$F$57,0)),$D163),$D163&IF(AND(LEFT($G163,3)<>"ДОК",$N163<>"")," — "&IFERROR(INDEX(МАТЕРИАЛЫ!$C$2:$C$9000,MATCH($N163,МАТЕРИАЛЫ!$L$2:$L$9000,0)),""),""))) -> Кладка перегородок армированных толщиной в 1 кирпич | Z163: =IF($B163="","",$B163&" · "&IFERROR(VLOOKUP($B163,спрРазделы,2,0),"")) -> Р3 · Внутренние строительные работы
A164: РАБ.Р3.1.003 | B164: Р3 | C164: 1 | D164: Кладка перегородок из пеноблоков (600*300*200) | E164: м2 | F164: 2035.8 | G164: КЛАДКА | H164: 5 | I164: ТС ЕР | P164: =IF($L164="да",ROUND(N($M164)*$S164,2),"") | Q164: =IF($L164="да",ROUND(N($M164)*$T164,2),"") | R164: =IF($L164="да",N($P164)+N($Q164),"") | S164: =IF($A164="","",IF(AND(LEFT($G164,3)="ДОК",$N164<>""),IFERROR(INDEX(Документация!$E$2:$E$57,MATCH($N164,Документация!$F$2:$F$57,0)),0),N($F164))*(1-MEDIAN(0,N(ДисконтТендер),1))) -> 2035.8 | T164: =IF($A164="","",IF(AND(LEFT($G164,3)="ДОК",$N164<>""),0,IF(AND(LEFT($G164,3)<>"ДОК",$N164<>""),IFERROR(INDEX(МАТЕРИАЛЫ!$H$2:$H$9000,MATCH($N164,МАТЕРИАЛЫ!$L$2:$L$9000,0))*IF(INDEX(МАТЕРИАЛЫ!$I$2:$I$9000,MATCH($N164,МАТЕРИАЛЫ!$L$2:$L$9000,0))="USD",КурсUSD,IF(INDEX(МАТЕРИАЛЫ!$I$2:$I$9000,MATCH($N164,МАТЕРИАЛЫ!$L$2:$L$9000,0))="EUR",КурсEUR,IF(INDEX(МАТЕРИАЛЫ!$I$2:$I$9000,MATCH($N164,МАТЕРИАЛЫ!$L$2:$L$9000,0))="CNY",КурсCNY,1)))*(1+N($H164)/100),0),N($O164))*(1-MEDIAN(0,N(ДисконтТендер),1)))) -> 0 | U164: =IF($L164="да",MAX($U$1:$U163)+1,"") | V164: =IF($A164="","",$B164) -> Р3 | W164: =IF($U164="","",IF($U164=1,1,IF($V164<>IFERROR(INDEX($V$2:$V$1058,MATCH($U164-1,$U$2:$U$1058,0)),"~"),1,0))) | X164: =IF($U164="","",$U164+SUMIFS($W$2:$W$1058,$U$2:$U$1058,"<="&$U164)) | Y164: =IF($A164="","",IF(AND(LEFT($G164,3)="ДОК",$N164<>""),IFERROR(INDEX(Документация!$G$2:$G$57,MATCH($N164,Документация!$F$2:$F$57,0)),$D164),$D164&IF(AND(LEFT($G164,3)<>"ДОК",$N164<>"")," — "&IFERROR(INDEX(МАТЕРИАЛЫ!$C$2:$C$9000,MATCH($N164,МАТЕРИАЛЫ!$L$2:$L$9000,0)),""),""))) -> Кладка перегородок из пеноблоков (600*300*200) | Z164: =IF($B164="","",$B164&" · "&IFERROR(VLOOKUP($B164,спрРазделы,2,0),"")) -> Р3 · Внутренние строительные работы
A165: РАБ.Р3.1.004 | B165: Р3 | C165: 1 | D165: Заделка проемов в кирпичных стенах | E165: м3 | F165: 9787.5 | G165: КЛАДКА | H165: 5 | I165: ТС ЕР | P165: =IF($L165="да",ROUND(N($M165)*$S165,2),"") | Q165: =IF($L165="да",ROUND(N($M165)*$T165,2),"") | R165: =IF($L165="да",N($P165)+N($Q165),"") | S165: =IF($A165="","",IF(AND(LEFT($G165,3)="ДОК",$N165<>""),IFERROR(INDEX(Документация!$E$2:$E$57,MATCH($N165,Документация!$F$2:$F$57,0)),0),N($F165))*(1-MEDIAN(0,N(ДисконтТендер),1))) -> 9787.5 | T165: =IF($A165="","",IF(AND(LEFT($G165,3)="ДОК",$N165<>""),0,IF(AND(LEFT($G165,3)<>"ДОК",$N165<>""),IFERROR(INDEX(МАТЕРИАЛЫ!$H$2:$H$9000,MATCH($N165,МАТЕРИАЛЫ!$L$2:$L$9000,0))*IF(INDEX(МАТЕРИАЛЫ!$I$2:$I$9000,MATCH($N165,МАТЕРИАЛЫ!$L$2:$L$9000,0))="USD",КурсUSD,IF(INDEX(МАТЕРИАЛЫ!$I$2:$I$9000,MATCH($N165,МАТЕРИАЛЫ!$L$2:$L$9000,0))="EUR",КурсEUR,IF(INDEX(МАТЕРИАЛЫ!$I$2:$I$9000,MATCH($N165,МАТЕРИАЛЫ!$L$2:$L$9000,0))="CNY",КурсCNY,1)))*(1+N($H165)/100),0),N($O165))*(1-MEDIAN(0,N(ДисконтТендер),1)))) -> 0 | U165: =IF($L165="да",MAX($U$1:$U164)+1,"") | V165: =IF($A165="","",$B165) -> Р3 | W165: =IF($U165="","",IF($U165=1,1,IF($V165<>IFERROR(INDEX($V$2:$V$1058,MATCH($U165-1,$U$2:$U$1058,0)),"~"),1,0))) | X165: =IF($U165="","",$U165+SUMIFS($W$2:$W$1058,$U$2:$U$1058,"<="&$U165)) | Y165: =IF($A165="","",IF(AND(LEFT($G165,3)="ДОК",$N165<>""),IFERROR(INDEX(Документация!$G$2:$G$57,MATCH($N165,Документация!$F$2:$F$57,0)),$D165),$D165&IF(AND(LEFT($G165,3)<>"ДОК",$N165<>"")," — "&IFERROR(INDEX(МАТЕРИАЛЫ!$C$2:$C$9000,MATCH($N165,МАТЕРИАЛЫ!$L$2:$L$9000,0)),""),""))) -> Заделка проемов в кирпичных стенах | Z165: =IF($B165="","",$B165&" · "&IFERROR(VLOOKUP($B165,спрРазделы,2,0),"")) -> Р3 · Внутренние строительные работы
A166: РАБ.Р3.1.005 | B166: Р3 | C166: 1 | D166: Усиление проемов металлическим профилем из уголка 50*3 | E166: м.п. | F166: 1045 | H166: 0 | I166: ТС ЕР | P166: =IF($L166="да",ROUND(N($M166)*$S166,2),"") | Q166: =IF($L166="да",ROUND(N($M166)*$T166,2),"") | R166: =IF($L166="да",N($P166)+N($Q166),"") | S166: =IF($A166="","",IF(AND(LEFT($G166,3)="ДОК",$N166<>""),IFERROR(INDEX(Документация!$E$2:$E$57,MATCH($N166,Документация!$F$2:$F$57,0)),0),N($F166))*(1-MEDIAN(0,N(ДисконтТендер),1))) -> 1045 | T166: =IF($A166="","",IF(AND(LEFT($G166,3)="ДОК",$N166<>""),0,IF(AND(LEFT($G166,3)<>"ДОК",$N166<>""),IFERROR(INDEX(МАТЕРИАЛЫ!$H$2:$H$9000,MATCH($N166,МАТЕРИАЛЫ!$L$2:$L$9000,0))*IF(INDEX(МАТЕРИАЛЫ!$I$2:$I$9000,MATCH($N166,МАТЕРИАЛЫ!$L$2:$L$9000,0))="USD",КурсUSD,IF(INDEX(МАТЕРИАЛЫ!$I$2:$I$9000,MATCH($N166,МАТЕРИАЛЫ!$L$2:$L$9000,0))="EUR",КурсEUR,IF(INDEX(МАТЕРИАЛЫ!$I$2:$I$9000,MATCH($N166,МАТЕРИАЛЫ!$L$2:$L$9000,0))="CNY",КурсCNY,1)))*(1+N($H166)/100),0),N($O166))*(1-MEDIAN(0,N(ДисконтТендер),1)))) -> 0 | U166: =IF($L166="да",MAX($U$1:$U165)+1,"") | V166: =IF($A166="","",$B166) -> Р3 | W166: =IF($U166="","",IF($U166=1,1,IF($V166<>IFERROR(INDEX($V$2:$V$1058,MATCH($U166-1,$U$2:$U$1058,0)),"~"),1,0))) | X166: =IF($U166="","",$U166+SUMIFS($W$2:$W$1058,$U$2:$U$1058,"<="&$U166)) | Y166: =IF($A166="","",IF(AND(LEFT($G166,3)="ДОК",$N166<>""),IFERROR(INDEX(Документация!$G$2:$G$57,MATCH($N166,Документация!$F$2:$F$57,0)),$D166),$D166&IF(AND(LEFT($G166,3)<>"ДОК",$N166<>"")," — "&IFERROR(INDEX(МАТЕРИАЛЫ!$C$2:$C$9000,MATCH($N166,МАТЕРИАЛЫ!$L$2:$L$9000,0)),""),""))) -> Усиление проемов металлическим профилем из уголка 50*3 | Z166: =IF($B166="","",$B166&" · "&IFERROR(VLOOKUP($B166,спрРазделы,2,0),"")) -> Р3 · Внутренние строительные работы
A167: РАБ.Р3.1.006 | B167: Р3 | C167: 1 | D167: Усиление проемов металлическим профилем из уголка 100*100*10 | E167: м.п. | F167: 2090 | H167: 0 | I167: ТС ЕР | P167: =IF($L167="да",ROUND(N($M167)*$S167,2),"") | Q167: =IF($L167="да",ROUND(N($M167)*$T167,2),"") | R167: =IF($L167="да",N($P167)+N($Q167),"") | S167: =IF($A167="","",IF(AND(LEFT($G167,3)="ДОК",$N167<>""),IFERROR(INDEX(Документация!$E$2:$E$57,MATCH($N167,Документация!$F$2:$F$57,0)),0),N($F167))*(1-MEDIAN(0,N(ДисконтТендер),1))) -> 2090 | T167: =IF($A167="","",IF(AND(LEFT($G167,3)="ДОК",$N167<>""),0,IF(AND(LEFT($G167,3)<>"ДОК",$N167<>""),IFERROR(INDEX(МАТЕРИАЛЫ!$H$2:$H$9000,MATCH($N167,МАТЕРИАЛЫ!$L$2:$L$9000,0))*IF(INDEX(МАТЕРИАЛЫ!$I$2:$I$9000,MATCH($N167,МАТЕРИАЛЫ!$L$2:$L$9000,0))="USD",КурсUSD,IF(INDEX(МАТЕРИАЛЫ!$I$2:$I$9000,MATCH($N167,МАТЕРИАЛЫ!$L$2:$L$9000,0))="EUR",КурсEUR,IF(INDEX(МАТЕРИАЛЫ!$I$2:$I$9000,MATCH($N167,МАТЕРИАЛЫ!$L$2:$L$9000,0))="CNY",КурсCNY,1)))*(1+N($H167)/100),0),N($O167))*(1-MEDIAN(0,N(ДисконтТендер),1)))) -> 0 | U167: =IF($L167="да",MAX($U$1:$U166)+1,"") | V167: =IF($A167="","",$B167) -> Р3 | W167: =IF($U167="","",IF($U167=1,1,IF($V167<>IFERROR(INDEX($V$2:$V$1058,MATCH($U167-1,$U$2:$U$1058,0)),"~"),1,0))) | X167: =IF($U167="","",$U167+SUMIFS($W$2:$W$1058,$U$2:$U$1058,"<="&$U167)) | Y167: =IF($A167="","",IF(AND(LEFT($G167,3)="ДОК",$N167<>""),IFERROR(INDEX(Документация!$G$2:$G$57,MATCH($N167,Документация!$F$2:$F$57,0)),$D167),$D167&IF(AND(LEFT($G167,3)<>"ДОК",$N167<>"")," — "&IFERROR(INDEX(МАТЕРИАЛЫ!$C$2:$C$9000,MATCH($N167,МАТЕРИАЛЫ!$L$2:$L$9000,0)),""),""))) -> Усиление проемов металлическим профилем из уголка 100*100*10 | Z167: =IF($B167="","",$B167&" · "&IFERROR(VLOOKUP($B167,спрРазделы,2,0),"")) -> Р3 · Внутренние строительные работы
A168: РАБ.Р3.1.007 | B168: Р3 | C168: 1 | D168: Устройство перегородок из ГКЛ толщ. 12 мм. "Кнауф" с одинарным металлическим каркасом и однослойной обшивкой с обеих сторон (включая перфорированные уголки на внешние углы) | E168: м2 | F168: 1722.6 | G168: ГКЛ | H168: 5 | I168: ТС ЕР | P168: =IF($L168="да",ROUND(N($M168)*$S168,2),"") | Q168: =IF($L168="да",ROUND(N($M168)*$T168,2),"") | R168: =IF($L168="да",N($P168)+N($Q168),"") | S168: =IF($A168="","",IF(AND(LEFT($G168,3)="ДОК",$N168<>""),IFERROR(INDEX(Документация!$E$2:$E$57,MATCH($N168,Документация!$F$2:$F$57,0)),0),N($F168))*(1-MEDIAN(0,N(ДисконтТендер),1))) -> 1722.6 | T168: =IF($A168="","",IF(AND(LEFT($G168,3)="ДОК",$N168<>""),0,IF(AND(LEFT($G168,3)<>"ДОК",$N168<>""),IFERROR(INDEX(МАТЕРИАЛЫ!$H$2:$H$9000,MATCH($N168,МАТЕРИАЛЫ!$L$2:$L$9000,0))*IF(INDEX(МАТЕРИАЛЫ!$I$2:$I$9000,MATCH($N168,МАТЕРИАЛЫ!$L$2:$L$9000,0))="USD",КурсUSD,IF(INDEX(МАТЕРИАЛЫ!$I$2:$I$9000,MATCH($N168,МАТЕРИАЛЫ!$L$2:$L$9000,0))="EUR",КурсEUR,IF(INDEX(МАТЕРИАЛЫ!$I$2:$I$9000,MATCH($N168,МАТЕРИАЛЫ!$L$2:$L$9000,0))="CNY",КурсCNY,1)))*(1+N($H168)/100),0),N($O168))*(1-MEDIAN(0,N(ДисконтТендер),1)))) -> 0 | U168: =IF($L168="да",MAX($U$1:$U167)+1,"") | V168: =IF($A168="","",$B168) -> Р3 | W168: =IF($U168="","",IF($U168=1,1,IF($V168<>IFERROR(INDEX($V$2:$V$1058,MATCH($U168-1,$U$2:$U$1058,0)),"~"),1,0))) | X168: =IF($U168="","",$U168+SUMIFS($W$2:$W$1058,$U$2:$U$1058,"<="&$U168)) | Y168: =IF($A168="","",IF(AND(LEFT($G168,3)="ДОК",$N168<>""),IFERROR(INDEX(Документация!$G$2:$G$57,MATCH($N168,Документация!$F$2:$F$57,0)),$D168),$D168&IF(AND(LEFT($G168,3)<>"ДОК",$N168<>"")," — "&IFERROR(INDEX(МАТЕРИАЛЫ!$C$2:$C$9000,MATCH($N168,МАТЕРИАЛЫ!$L$2:$L$9000,0)),""),""))) -> Устройство перегородок из ГКЛ толщ. 12 мм. "Кнауф" с одинарным металлическим каркасом и однослойной обшивкой с обеих сторон (включая перфорированные уголки на внешние углы) | Z168: =IF($B168="","",$B168&" · "&IFERROR(VLOOKUP($B168,спрРазделы,2,0),"")) -> Р3 · Внутренние строительные работы
A169: РАБ.Р3.1.008 | B169: Р3 | C169: 1 | D169: Устройство перегородок из ГКЛ толщ. 12 мм. "Кнауф" с одинарным металлическим каркасом и двухслойной обшивкой с обеих сторон (включая перфорированные уголки на внешние углы) | E169: м2 | F169: 1894.86 | G169: ГКЛ | H169: 5 | I169: ТС ЕР | P169: =IF($L169="да",ROUND(N($M169)*$S169,2),"") | Q169: =IF($L169="да",ROUND(N($M169)*$T169,2),"") | R169: =IF($L169="да",N($P169)+N($Q169),"") | S169: =IF($A169="","",IF(AND(LEFT($G169,3)="ДОК",$N169<>""),IFERROR(INDEX(Документация!$E$2:$E$57,MATCH($N169,Документация!$F$2:$F$57,0)),0),N($F169))*(1-MEDIAN(0,N(ДисконтТендер),1))) -> 1894.86 | T169: =IF($A169="","",IF(AND(LEFT($G169,3)="ДОК",$N169<>""),0,IF(AND(LEFT($G169,3)<>"ДОК",$N169<>""),IFERROR(INDEX(МАТЕРИАЛЫ!$H$2:$H$9000,MATCH($N169,МАТЕРИАЛЫ!$L$2:$L$9000,0))*IF(INDEX(МАТЕРИАЛЫ!$I$2:$I$9000,MATCH($N169,МАТЕРИАЛЫ!$L$2:$L$9000,0))="USD",КурсUSD,IF(INDEX(МАТЕРИАЛЫ!$I$2:$I$9000,MATCH($N169,МАТЕРИАЛЫ!$L$2:$L$9000,0))="EUR",КурсEUR,IF(INDEX(МАТЕРИАЛЫ!$I$2:$I$9000,MATCH($N169,МАТЕРИАЛЫ!$L$2:$L$9000,0))="CNY",КурсCNY,1)))*(1+N($H169)/100),0),N($O169))*(1-MEDIAN(0,N(ДисконтТендер),1)))) -> 0 | U169: =IF($L169="да",MAX($U$1:$U168)+1,"") | V169: =IF($A169="","",$B169) -> Р3 | W169: =IF($U169="","",IF($U169=1,1,IF($V169<>IFERROR(INDEX($V$2:$V$1058,MATCH($U169-1,$U$2:$U$1058,0)),"~"),1,0))) | X169: =IF($U169="","",$U169+SUMIFS($W$2:$W$1058,$U$2:$U$1058,"<="&$U169)) | Y169: =IF($A169="","",IF(AND(LEFT($G169,3)="ДОК",$N169<>""),IFERROR(INDEX(Документация!$G$2:$G$57,MATCH($N169,Документация!$F$2:$F$57,0)),$D169),$D169&IF(AND(LEFT($G169,3)<>"ДОК",$N169<>"")," — "&IFERROR(INDEX(МАТЕРИАЛЫ!$C$2:$C$9000,MATCH($N169,МАТЕРИАЛЫ!$L$2:$L$9000,0)),""),""))) -> Устройство перегородок из ГКЛ толщ. 12 мм. "Кнауф" с одинарным металлическим каркасом и двухслойной обшивкой с обеих сторон (включая перфорированные уголки на внешние углы) | Z169: =IF($B169="","",$B169&" · "&IFERROR(VLOOKUP($B169,спрРазделы,2,0),"")) -> Р3 · Внутренние строительные работы
A170: РАБ.Р3.1.009 | B170: Р3 | C170: 1 | D170: Устройство перегородки / облицовки из ГКЛ | E170: м2 | F170: 1305.22 | G170: ГКЛ | H170: 5 | I170: ТС ЕР | P170: =IF($L170="да",ROUND(N($M170)*$S170,2),"") | Q170: =IF($L170="да",ROUND(N($M170)*$T170,2),"") | R170: =IF($L170="да",N($P170)+N($Q170),"") | S170: =IF($A170="","",IF(AND(LEFT($G170,3)="ДОК",$N170<>""),IFERROR(INDEX(Документация!$E$2:$E$57,MATCH($N170,Документация!$F$2:$F$57,0)),0),N($F170))*(1-MEDIAN(0,N(ДисконтТендер),1))) -> 1305.22 | T170: =IF($A170="","",IF(AND(LEFT($G170,3)="ДОК",$N170<>""),0,IF(AND(LEFT($G170,3)<>"ДОК",$N170<>""),IFERROR(INDEX(МАТЕРИАЛЫ!$H$2:$H$9000,MATCH($N170,МАТЕРИАЛЫ!$L$2:$L$9000,0))*IF(INDEX(МАТЕРИАЛЫ!$I$2:$I$9000,MATCH($N170,МАТЕРИАЛЫ!$L$2:$L$9000,0))="USD",КурсUSD,IF(INDEX(МАТЕРИАЛЫ!$I$2:$I$9000,MATCH($N170,МАТЕРИАЛЫ!$L$2:$L$9000,0))="EUR",КурсEUR,IF(INDEX(МАТЕРИАЛЫ!$I$2:$I$9000,MATCH($N170,МАТЕРИАЛЫ!$L$2:$L$9000,0))="CNY",КурсCNY,1)))*(1+N($H170)/100),0),N($O170))*(1-MEDIAN(0,N(ДисконтТендер),1)))) -> 0 | U170: =IF($L170="да",MAX($U$1:$U169)+1,"") | V170: =IF($A170="","",$B170) -> Р3 | W170: =IF($U170="","",IF($U170=1,1,IF($V170<>IFERROR(INDEX($V$2:$V$1058,MATCH($U170-1,$U$2:$U$1058,0)),"~"),1,0))) | X170: =IF($U170="","",$U170+SUMIFS($W$2:$W$1058,$U$2:$U$1058,"<="&$U170)) | Y170: =IF($A170="","",IF(AND(LEFT($G170,3)="ДОК",$N170<>""),IFERROR(INDEX(Документация!$G$2:$G$57,MATCH($N170,Документация!$F$2:$F$57,0)),$D170),$D170&IF(AND(LEFT($G170,3)<>"ДОК",$N170<>"")," — "&IFERROR(INDEX(МАТЕРИАЛЫ!$C$2:$C$9000,MATCH($N170,МАТЕРИАЛЫ!$L$2:$L$9000,0)),""),""))) -> Устройство перегородки / облицовки из ГКЛ | Z170: =IF($B170="","",$B170&" · "&IFERROR(VLOOKUP($B170,спрРазделы,2,0),"")) -> Р3 · Внутренние строительные работы
A171: РАБ.Р3.1.010 | B171: Р3 | C171: 1 | D171: Устройство перегородки / облицовки из ГКЛ | E171: м2 | F171: 1515.98 | G171: ГКЛ | H171: 5 | I171: ТС ЕР | P171: =IF($L171="да",ROUND(N($M171)*$S171,2),"") | Q171: =IF($L171="да",ROUND(N($M171)*$T171,2),"") | R171: =IF($L171="да",N($P171)+N($Q171),"") | S171: =IF($A171="","",IF(AND(LEFT($G171,3)="ДОК",$N171<>""),IFERROR(INDEX(Документация!$E$2:$E$57,MATCH($N171,Документация!$F$2:$F$57,0)),0),N($F171))*(1-MEDIAN(0,N(ДисконтТендер),1))) -> 1515.98 | T171: =IF($A171="","",IF(AND(LEFT($G171,3)="ДОК",$N171<>""),0,IF(AND(LEFT($G171,3)<>"ДОК",$N171<>""),IFERROR(INDEX(МАТЕРИАЛЫ!$H$2:$H$9000,MATCH($N171,МАТЕРИАЛЫ!$L$2:$L$9000,0))*IF(INDEX(МАТЕРИАЛЫ!$I$2:$I$9000,MATCH($N171,МАТЕРИАЛЫ!$L$2:$L$9000,0))="USD",КурсUSD,IF(INDEX(МАТЕРИАЛЫ!$I$2:$I$9000,MATCH($N171,МАТЕРИАЛЫ!$L$2:$L$9000,0))="EUR",КурсEUR,IF(INDEX(МАТЕРИАЛЫ!$I$2:$I$9000,MATCH($N171,МАТЕРИАЛЫ!$L$2:$L$9000,0))="CNY",КурсCNY,1)))*(1+N($H171)/100),0),N($O171))*(1-MEDIAN(0,N(ДисконтТендер),1)))) -> 0 | U171: =IF($L171="да",MAX($U$1:$U170)+1,"") | V171: =IF($A171="","",$B171) -> Р3 | W171: =IF($U171="","",IF($U171=1,1,IF($V171<>IFERROR(INDEX($V$2:$V$1058,MATCH($U171-1,$U$2:$U$1058,0)),"~"),1,0))) | X171: =IF($U171="","",$U171+SUMIFS($W$2:$W$1058,$U$2:$U$1058,"<="&$U171)) | Y171: =IF($A171="","",IF(AND(LEFT($G171,3)="ДОК",$N171<>""),IFERROR(INDEX(Документация!$G$2:$G$57,MATCH($N171,Документация!$F$2:$F$57,0)),$D171),$D171&IF(AND(LEFT($G171,3)<>"ДОК",$N171<>"")," — "&IFERROR(INDEX(МАТЕРИАЛЫ!$C$2:$C$9000,MATCH($N171,МАТЕРИАЛЫ!$L$2:$L$9000,0)),""),""))) -> Устройство перегородки / облицовки из ГКЛ | Z171: =IF($B171="","",$B171&" · "&IFERROR(VLOOKUP($B171,спрРазделы,2,0),"")) -> Р3 · Внутренние строительные работы
A172: РАБ.Р3.1.011 | B172: Р3 | C172: 1 | D172: Облицовка стен гипсокартонными листами (ГКЛ) "Кнауф" в один слой на клее (включая перфорированные уголки на внешние углы) | E172: м2 | F172: 1357.2 | G172: ГКЛ | H172: 5 | I172: ТС ЕР | P172: =IF($L172="да",ROUND(N($M172)*$S172,2),"") | Q172: =IF($L172="да",ROUND(N($M172)*$T172,2),"") | R172: =IF($L172="да",N($P172)+N($Q172),"") | S172: =IF($A172="","",IF(AND(LEFT($G172,3)="ДОК",$N172<>""),IFERROR(INDEX(Документация!$E$2:$E$57,MATCH($N172,Документация!$F$2:$F$57,0)),0),N($F172))*(1-MEDIAN(0,N(ДисконтТендер),1))) -> 1357.2 | T172: =IF($A172="","",IF(AND(LEFT($G172,3)="ДОК",$N172<>""),0,IF(AND(LEFT($G172,3)<>"ДОК",$N172<>""),IFERROR(INDEX(МАТЕРИАЛЫ!$H$2:$H$9000,MATCH($N172,МАТЕРИАЛЫ!$L$2:$L$9000,0))*IF(INDEX(МАТЕРИАЛЫ!$I$2:$I$9000,MATCH($N172,МАТЕРИАЛЫ!$L$2:$L$9000,0))="USD",КурсUSD,IF(INDEX(МАТЕРИАЛЫ!$I$2:$I$9000,MATCH($N172,МАТЕРИАЛЫ!$L$2:$L$9000,0))="EUR",КурсEUR,IF(INDEX(МАТЕРИАЛЫ!$I$2:$I$9000,MATCH($N172,МАТЕРИАЛЫ!$L$2:$L$9000,0))="CNY",КурсCNY,1)))*(1+N($H172)/100),0),N($O172))*(1-MEDIAN(0,N(ДисконтТендер),1)))) -> 0 | U172: =IF($L172="да",MAX($U$1:$U171)+1,"") | V172: =IF($A172="","",$B172) -> Р3 | W172: =IF($U172="","",IF($U172=1,1,IF($V172<>IFERROR(INDEX($V$2:$V$1058,MATCH($U172-1,$U$2:$U$1058,0)),"~"),1,0))) | X172: =IF($U172="","",$U172+SUMIFS($W$2:$W$1058,$U$2:$U$1058,"<="&$U172)) | Y172: =IF($A172="","",IF(AND(LEFT($G172,3)="ДОК",$N172<>""),IFERROR(INDEX(Документация!$G$2:$G$57,MATCH($N172,Документация!$F$2:$F$57,0)),$D172),$D172&IF(AND(LEFT($G172,3)<>"ДОК",$N172<>"")," — "&IFERROR(INDEX(МАТЕРИАЛЫ!$C$2:$C$9000,MATCH($N172,МАТЕРИАЛЫ!$L$2:$L$9000,0)),""),""))) -> Облицовка стен гипсокартонными листами (ГКЛ) "Кнауф" в один слой на клее (включая перфорированные уголки на внешние углы) | Z172: =IF($B172="","",$B172&" · "&IFERROR(VLOOKUP($B172,спрРазделы,2,0),"")) -> Р3 · Внутренние строительные работы
A173: РАБ.Р3.1.012 | B173: Р3 | C173: 1 | D173: Устройство оконных откосов из ГКЛВ толщ. 12 мм. | E173: м2 | F173: 1305 | G173: ГКЛ | H173: 5 | I173: ТС ЕР | P173: =IF($L173="да",ROUND(N($M173)*$S173,2),"") | Q173: =IF($L173="да",ROUND(N($M173)*$T173,2),"") | R173: =IF($L173="да",N($P173)+N($Q173),"") | S173: =IF($A173="","",IF(AND(LEFT($G173,3)="ДОК",$N173<>""),IFERROR(INDEX(Документация!$E$2:$E$57,MATCH($N173,Документация!$F$2:$F$57,0)),0),N($F173))*(1-MEDIAN(0,N(ДисконтТендер),1))) -> 1305 | T173: =IF($A173="","",IF(AND(LEFT($G173,3)="ДОК",$N173<>""),0,IF(AND(LEFT($G173,3)<>"ДОК",$N173<>""),IFERROR(INDEX(МАТЕРИАЛЫ!$H$2:$H$9000,MATCH($N173,МАТЕРИАЛЫ!$L$2:$L$9000,0))*IF(INDEX(МАТЕРИАЛЫ!$I$2:$I$9000,MATCH($N173,МАТЕРИАЛЫ!$L$2:$L$9000,0))="USD",КурсUSD,IF(INDEX(МАТЕРИАЛЫ!$I$2:$I$9000,MATCH($N173,МАТЕРИАЛЫ!$L$2:$L$9000,0))="EUR",КурсEUR,IF(INDEX(МАТЕРИАЛЫ!$I$2:$I$9000,MATCH($N173,МАТЕРИАЛЫ!$L$2:$L$9000,0))="CNY",КурсCNY,1)))*(1+N($H173)/100),0),N($O173))*(1-MEDIAN(0,N(ДисконтТендер),1)))) -> 0 | U173: =IF($L173="да",MAX($U$1:$U172)+1,"") | V173: =IF($A173="","",$B173) -> Р3 | W173: =IF($U173="","",IF($U173=1,1,IF($V173<>IFERROR(INDEX($V$2:$V$1058,MATCH($U173-1,$U$2:$U$1058,0)),"~"),1,0))) | X173: =IF($U173="","",$U173+SUMIFS($W$2:$W$1058,$U$2:$U$1058,"<="&$U173)) | Y173: =IF($A173="","",IF(AND(LEFT($G173,3)="ДОК",$N173<>""),IFERROR(INDEX(Документация!$G$2:$G$57,MATCH($N173,Документация!$F$2:$F$57,0)),$D173),$D173&IF(AND(LEFT($G173,3)<>"ДОК",$N173<>"")," — "&IFERROR(INDEX(МАТЕРИАЛЫ!$C$2:$C$9000,MATCH($N173,МАТЕРИАЛЫ!$L$2:$L$9000,0)),""),""))) -> Устройство оконных откосов из ГКЛВ толщ. 12 мм. | Z173: =IF($B173="","",$B173&" · "&IFERROR(VLOOKUP($B173,спрРазделы,2,0),"")) -> Р3 · Внутренние строительные работы
A174: РАБ.Р3.1.013 | B174: Р3 | C174: 1 | D174: Тепло- и звукоизоляция стен из минеральных материалов | E174: м2 | F174: 106.14 | G174: ИЗОЛ | H174: 5 | I174: ТС ЕР | P174: =IF($L174="да",ROUND(N($M174)*$S174,2),"") | Q174: =IF($L174="да",ROUND(N($M174)*$T174,2),"") | R174: =IF($L174="да",N($P174)+N($Q174),"") | S174: =IF($A174="","",IF(AND(LEFT($G174,3)="ДОК",$N174<>""),IFERROR(INDEX(Документация!$E$2:$E$57,MATCH($N174,Документация!$F$2:$F$57,0)),0),N($F174))*(1-MEDIAN(0,N(ДисконтТендер),1))) -> 106.14 | T174: =IF($A174="","",IF(AND(LEFT($G174,3)="ДОК",$N174<>""),0,IF(AND(LEFT($G174,3)<>"ДОК",$N174<>""),IFERROR(INDEX(МАТЕРИАЛЫ!$H$2:$H$9000,MATCH($N174,МАТЕРИАЛЫ!$L$2:$L$9000,0))*IF(INDEX(МАТЕРИАЛЫ!$I$2:$I$9000,MATCH($N174,МАТЕРИАЛЫ!$L$2:$L$9000,0))="USD",КурсUSD,IF(INDEX(МАТЕРИАЛЫ!$I$2:$I$9000,MATCH($N174,МАТЕРИАЛЫ!$L$2:$L$9000,0))="EUR",КурсEUR,IF(INDEX(МАТЕРИАЛЫ!$I$2:$I$9000,MATCH($N174,МАТЕРИАЛЫ!$L$2:$L$9000,0))="CNY",КурсCNY,1)))*(1+N($H174)/100),0),N($O174))*(1-MEDIAN(0,N(ДисконтТендер),1)))) -> 0 | U174: =IF($L174="да",MAX($U$1:$U173)+1,"") | V174: =IF($A174="","",$B174) -> Р3 | W174: =IF($U174="","",IF($U174=1,1,IF($V174<>IFERROR(INDEX($V$2:$V$1058,MATCH($U174-1,$U$2:$U$1058,0)),"~"),1,0))) | X174: =IF($U174="","",$U174+SUMIFS($W$2:$W$1058,$U$2:$U$1058,"<="&$U174)) | Y174: =IF($A174="","",IF(AND(LEFT($G174,3)="ДОК",$N174<>""),IFERROR(INDEX(Документация!$G$2:$G$57,MATCH($N174,Документация!$F$2:$F$57,0)),$D174),$D174&IF(AND(LEFT($G174,3)<>"ДОК",$N174<>"")," — "&IFERROR(INDEX(МАТЕРИАЛЫ!$C$2:$C$9000,MATCH($N174,МАТЕРИАЛЫ!$L$2:$L$9000,0)),""),""))) -> Тепло- и звукоизоляция стен из минеральных материалов | Z174: =IF($B174="","",$B174&" · "&IFERROR(VLOOKUP($B174,спрРазделы,2,0),"")) -> Р3 · Внутренние строительные работы
A175: РАБ.Р3.1.014 | B175: Р3 | C175: 1 | D175: Штукатурка стен | E175: м2 | F175: 977.08 | H175: 0 | I175: ТС ЕР | P175: =IF($L175="да",ROUND(N($M175)*$S175,2),"") | Q175: =IF($L175="да",ROUND(N($M175)*$T175,2),"") | R175: =IF($L175="да",N($P175)+N($Q175),"") | S175: =IF($A175="","",IF(AND(LEFT($G175,3)="ДОК",$N175<>""),IFERROR(INDEX(Документация!$E$2:$E$57,MATCH($N175,Документация!$F$2:$F$57,0)),0),N($F175))*(1-MEDIAN(0,N(ДисконтТендер),1))) -> 977.08 | T175: =IF($A175="","",IF(AND(LEFT($G175,3)="ДОК",$N175<>""),0,IF(AND(LEFT($G175,3)<>"ДОК",$N175<>""),IFERROR(INDEX(МАТЕРИАЛЫ!$H$2:$H$9000,MATCH($N175,МАТЕРИАЛЫ!$L$2:$L$9000,0))*IF(INDEX(МАТЕРИАЛЫ!$I$2:$I$9000,MATCH($N175,МАТЕРИАЛЫ!$L$2:$L$9000,0))="USD",КурсUSD,IF(INDEX(МАТЕРИАЛЫ!$I$2:$I$9000,MATCH($N175,МАТЕРИАЛЫ!$L$2:$L$9000,0))="EUR",КурсEUR,IF(INDEX(МАТЕРИАЛЫ!$I$2:$I$9000,MATCH($N175,МАТЕРИАЛЫ!$L$2:$L$9000,0))="CNY",КурсCNY,1)))*(1+N($H175)/100),0),N($O175))*(1-MEDIAN(0,N(ДисконтТендер),1)))) -> 0 | U175: =IF($L175="да",MAX($U$1:$U174)+1,"") | V175: =IF($A175="","",$B175) -> Р3 | W175: =IF($U175="","",IF($U175=1,1,IF($V175<>IFERROR(INDEX($V$2:$V$1058,MATCH($U175-1,$U$2:$U$1058,0)),"~"),1,0))) | X175: =IF($U175="","",$U175+SUMIFS($W$2:$W$1058,$U$2:$U$1058,"<="&$U175)) | Y175: =IF($A175="","",IF(AND(LEFT($G175,3)="ДОК",$N175<>""),IFERROR(INDEX(Документация!$G$2:$G$57,MATCH($N175,Документация!$F$2:$F$57,0)),$D175),$D175&IF(AND(LEFT($G175,3)<>"ДОК",$N175<>"")," — "&IFERROR(INDEX(МАТЕРИАЛЫ!$C$2:$C$9000,MATCH($N175,МАТЕРИАЛЫ!$L$2:$L$9000,0)),""),""))) -> Штукатурка стен | Z175: =IF($B175="","",$B175&" · "&IFERROR(VLOOKUP($B175,спрРазделы,2,0),"")) -> Р3 · Внутренние строительные работы
A176: РАБ.Р3.1.015 | B176: Р3 | C176: 1 | D176: Устройство штроб в кирпичных стенах | E176: м.п. | F176: 616.1 | G176: КЛАДКА | H176: 5 | I176: ТС ЕР | P176: =IF($L176="да",ROUND(N($M176)*$S176,2),"") | Q176: =IF($L176="да",ROUND(N($M176)*$T176,2),"") | R176: =IF($L176="да",N($P176)+N($Q176),"") | S176: =IF($A176="","",IF(AND(LEFT($G176,3)="ДОК",$N176<>""),IFERROR(INDEX(Документация!$E$2:$E$57,MATCH($N176,Документация!$F$2:$F$57,0)),0),N($F176))*(1-MEDIAN(0,N(ДисконтТендер),1))) -> 616.1 | T176: =IF($A176="","",IF(AND(LEFT($G176,3)="ДОК",$N176<>""),0,IF(AND(LEFT($G176,3)<>"ДОК",$N176<>""),IFERROR(INDEX(МАТЕРИАЛЫ!$H$2:$H$9000,MATCH($N176,МАТЕРИАЛЫ!$L$2:$L$9000,0))*IF(INDEX(МАТЕРИАЛЫ!$I$2:$I$9000,MATCH($N176,МАТЕРИАЛЫ!$L$2:$L$9000,0))="USD",КурсUSD,IF(INDEX(МАТЕРИАЛЫ!$I$2:$I$9000,MATCH($N176,МАТЕРИАЛЫ!$L$2:$L$9000,0))="EUR",КурсEUR,IF(INDEX(МАТЕРИАЛЫ!$I$2:$I$9000,MATCH($N176,МАТЕРИАЛЫ!$L$2:$L$9000,0))="CNY",КурсCNY,1)))*(1+N($H176)/100),0),N($O176))*(1-MEDIAN(0,N(ДисконтТендер),1)))) -> 0 | U176: =IF($L176="да",MAX($U$1:$U175)+1,"") | V176: =IF($A176="","",$B176) -> Р3 | W176: =IF($U176="","",IF($U176=1,1,IF($V176<>IFERROR(INDEX($V$2:$V$1058,MATCH($U176-1,$U$2:$U$1058,0)),"~"),1,0))) | X176: =IF($U176="","",$U176+SUMIFS($W$2:$W$1058,$U$2:$U$1058,"<="&$U176)) | Y176: =IF($A176="","",IF(AND(LEFT($G176,3)="ДОК",$N176<>""),IFERROR(INDEX(Документация!$G$2:$G$57,MATCH($N176,Документация!$F$2:$F$57,0)),$D176),$D176&IF(AND(LEFT($G176,3)<>"ДОК",$N176<>"")," — "&IFERROR(INDEX(МАТЕРИАЛЫ!$C$2:$C$9000,MATCH($N176,МАТЕРИАЛЫ!$L$2:$L$9000,0)),""),""))) -> Устройство штроб в кирпичных стенах | Z176: =IF($B176="","",$B176&" · "&IFERROR(VLOOKUP($B176,спрРазделы,2,0),"")) -> Р3 · Внутренние строительные работы
A177: РАБ.Р3.1.016 | B177: Р3 | C177: 1 | D177: Устройство штроб в конструкциях газосиликатных, керамзитобетонных, шлакобетонных, пенобетонных. | E177: м.п. | F177: 585.2 | H177: 0 | I177: ТС ЕР | P177: =IF($L177="да",ROUND(N($M177)*$S177,2),"") | Q177: =IF($L177="да",ROUND(N($M177)*$T177,2),"") | R177: =IF($L177="да",N($P177)+N($Q177),"") | S177: =IF($A177="","",IF(AND(LEFT($G177,3)="ДОК",$N177<>""),IFERROR(INDEX(Документация!$E$2:$E$57,MATCH($N177,Документация!$F$2:$F$57,0)),0),N($F177))*(1-MEDIAN(0,N(ДисконтТендер),1))) -> 585.2 | T177: =IF($A177="","",IF(AND(LEFT($G177,3)="ДОК",$N177<>""),0,IF(AND(LEFT($G177,3)<>"ДОК",$N177<>""),IFERROR(INDEX(МАТЕРИАЛЫ!$H$2:$H$9000,MATCH($N177,МАТЕРИАЛЫ!$L$2:$L$9000,0))*IF(INDEX(МАТЕРИАЛЫ!$I$2:$I$9000,MATCH($N177,МАТЕРИАЛЫ!$L$2:$L$9000,0))="USD",КурсUSD,IF(INDEX(МАТЕРИАЛЫ!$I$2:$I$9000,MATCH($N177,МАТЕРИАЛЫ!$L$2:$L$9000,0))="EUR",КурсEUR,IF(INDEX(МАТЕРИАЛЫ!$I$2:$I$9000,MATCH($N177,МАТЕРИАЛЫ!$L$2:$L$9000,0))="CNY",КурсCNY,1)))*(1+N($H177)/100),0),N($O177))*(1-MEDIAN(0,N(ДисконтТендер),1)))) -> 0 | U177: =IF($L177="да",MAX($U$1:$U176)+1,"") | V177: =IF($A177="","",$B177) -> Р3 | W177: =IF($U177="","",IF($U177=1,1,IF($V177<>IFERROR(INDEX($V$2:$V$1058,MATCH($U177-1,$U$2:$U$1058,0)),"~"),1,0))) | X177: =IF($U177="","",$U177+SUMIFS($W$2:$W$1058,$U$2:$U$1058,"<="&$U177)) | Y177: =IF($A177="","",IF(AND(LEFT($G177,3)="ДОК",$N177<>""),IFERROR(INDEX(Документация!$G$2:$G$57,MATCH($N177,Документация!$F$2:$F$57,0)),$D177),$D177&IF(AND(LEFT($G177,3)<>"ДОК",$N177<>"")," — "&IFERROR(INDEX(МАТЕРИАЛЫ!$C$2:$C$9000,MATCH($N177,МАТЕРИАЛЫ!$L$2:$L$9000,0)),""),""))) -> Устройство штроб в конструкциях газосиликатных, керамзитобетонных, шлакобетонных, пенобетонных. | Z177: =IF($B177="","",$B177&" · "&IFERROR(VLOOKUP($B177,спрРазделы,2,0),"")) -> Р3 · Внутренние строительные работы
A178: РАБ.Р3.1.017 | B178: Р3 | C178: 1 | D178: Пробивка отверстий в кирпичных стенах фасада, внутренних перегородках под прокладку труб ОВиК, электролотков, | E178: м3 | F178: 25414.48 | G178: КЛАДКА | H178: 5 | I178: ТС ЕР | P178: =IF($L178="да",ROUND(N($M178)*$S178,2),"") | Q178: =IF($L178="да",ROUND(N($M178)*$T178,2),"") | R178: =IF($L178="да",N($P178)+N($Q178),"") | S178: =IF($A178="","",IF(AND(LEFT($G178,3)="ДОК",$N178<>""),IFERROR(INDEX(Документация!$E$2:$E$57,MATCH($N178,Документация!$F$2:$F$57,0)),0),N($F178))*(1-MEDIAN(0,N(ДисконтТендер),1))) -> 25414.48 | T178: =IF($A178="","",IF(AND(LEFT($G178,3)="ДОК",$N178<>""),0,IF(AND(LEFT($G178,3)<>"ДОК",$N178<>""),IFERROR(INDEX(МАТЕРИАЛЫ!$H$2:$H$9000,MATCH($N178,МАТЕРИАЛЫ!$L$2:$L$9000,0))*IF(INDEX(МАТЕРИАЛЫ!$I$2:$I$9000,MATCH($N178,МАТЕРИАЛЫ!$L$2:$L$9000,0))="USD",КурсUSD,IF(INDEX(МАТЕРИАЛЫ!$I$2:$I$9000,MATCH($N178,МАТЕРИАЛЫ!$L$2:$L$9000,0))="EUR",КурсEUR,IF(INDEX(МАТЕРИАЛЫ!$I$2:$I$9000,MATCH($N178,МАТЕРИАЛЫ!$L$2:$L$9000,0))="CNY",КурсCNY,1)))*(1+N($H178)/100),0),N($O178))*(1-MEDIAN(0,N(ДисконтТендер),1)))) -> 0 | U178: =IF($L178="да",MAX($U$1:$U177)+1,"") | V178: =IF($A178="","",$B178) -> Р3 | W178: =IF($U178="","",IF($U178=1,1,IF($V178<>IFERROR(INDEX($V$2:$V$1058,MATCH($U178-1,$U$2:$U$1058,0)),"~"),1,0))) | X178: =IF($U178="","",$U178+SUMIFS($W$2:$W$1058,$U$2:$U$1058,"<="&$U178)) | Y178: =IF($A178="","",IF(AND(LEFT($G178,3)="ДОК",$N178<>""),IFERROR(INDEX(Документация!$G$2:$G$57,MATCH($N178,Документация!$F$2:$F$57,0)),$D178),$D178&IF(AND(LEFT($G178,3)<>"ДОК",$N178<>"")," — "&IFERROR(INDEX(МАТЕРИАЛЫ!$C$2:$C$9000,MATCH($N178,МАТЕРИАЛЫ!$L$2:$L$9000,0)),""),""))) -> Пробивка отверстий в кирпичных стенах фасада, внутренних перегородках под прокладку труб ОВиК, электролотков, | Z178: =IF($B178="","",$B178&" · "&IFERROR(VLOOKUP($B178,спрРазделы,2,0),"")) -> Р3 · Внутренние строительные работы
A179: РАБ.Р3.1.018 | B179: Р3 | C179: 1 | D179: Пробивка отверстий в бетоных стенах фасада, внутренних перегородках под прокладку труб ОВиК, электролотков. | E179: м3 | F179: 31115.45 | H179: 0 | I179: ТС ЕР | P179: =IF($L179="да",ROUND(N($M179)*$S179,2),"") | Q179: =IF($L179="да",ROUND(N($M179)*$T179,2),"") | R179: =IF($L179="да",N($P179)+N($Q179),"") | S179: =IF($A179="","",IF(AND(LEFT($G179,3)="ДОК",$N179<>""),IFERROR(INDEX(Документация!$E$2:$E$57,MATCH($N179,Документация!$F$2:$F$57,0)),0),N($F179))*(1-MEDIAN(0,N(ДисконтТендер),1))) -> 31115.45 | T179: =IF($A179="","",IF(AND(LEFT($G179,3)="ДОК",$N179<>""),0,IF(AND(LEFT($G179,3)<>"ДОК",$N179<>""),IFERROR(INDEX(МАТЕРИАЛЫ!$H$2:$H$9000,MATCH($N179,МАТЕРИАЛЫ!$L$2:$L$9000,0))*IF(INDEX(МАТЕРИАЛЫ!$I$2:$I$9000,MATCH($N179,МАТЕРИАЛЫ!$L$2:$L$9000,0))="USD",КурсUSD,IF(INDEX(МАТЕРИАЛЫ!$I$2:$I$9000,MATCH($N179,МАТЕРИАЛЫ!$L$2:$L$9000,0))="EUR",КурсEUR,IF(INDEX(МАТЕРИАЛЫ!$I$2:$I$9000,MATCH($N179,МАТЕРИАЛЫ!$L$2:$L$9000,0))="CNY",КурсCNY,1)))*(1+N($H179)/100),0),N($O179))*(1-MEDIAN(0,N(ДисконтТендер),1)))) -> 0 | U179: =IF($L179="да",MAX($U$1:$U178)+1,"") | V179: =IF($A179="","",$B179) -> Р3 | W179: =IF($U179="","",IF($U179=1,1,IF($V179<>IFERROR(INDEX($V$2:$V$1058,MATCH($U179-1,$U$2:$U$1058,0)),"~"),1,0))) | X179: =IF($U179="","",$U179+SUMIFS($W$2:$W$1058,$U$2:$U$1058,"<="&$U179)) | Y179: =IF($A179="","",IF(AND(LEFT($G179,3)="ДОК",$N179<>""),IFERROR(INDEX(Документация!$G$2:$G$57,MATCH($N179,Документация!$F$2:$F$57,0)),$D179),$D179&IF(AND(LEFT($G179,3)<>"ДОК",$N179<>"")," — "&IFERROR(INDEX(МАТЕРИАЛЫ!$C$2:$C$9000,MATCH($N179,МАТЕРИАЛЫ!$L$2:$L$9000,0)),""),""))) -> Пробивка отверстий в бетоных стенах фасада, внутренних перегородках под прокладку труб ОВиК, электролотков. | Z179: =IF($B179="","",$B179&" · "&IFERROR(VLOOKUP($B179,спрРазделы,2,0),"")) -> Р3 · Внутренние строительные работы
A180: РАБ.Р3.1.019 | B180: Р3 | C180: 1 | D180: Запенивание противопожарной пеной тех. отверстий прохода транзитных коммуникаций | E180: м2 | F180: 500.21 | H180: 0 | I180: ТС ЕР | P180: =IF($L180="да",ROUND(N($M180)*$S180,2),"") | Q180: =IF($L180="да",ROUND(N($M180)*$T180,2),"") | R180: =IF($L180="да",N($P180)+N($Q180),"") | S180: =IF($A180="","",IF(AND(LEFT($G180,3)="ДОК",$N180<>""),IFERROR(INDEX(Документация!$E$2:$E$57,MATCH($N180,Документация!$F$2:$F$57,0)),0),N($F180))*(1-MEDIAN(0,N(ДисконтТендер),1))) -> 500.21 | T180: =IF($A180="","",IF(AND(LEFT($G180,3)="ДОК",$N180<>""),0,IF(AND(LEFT($G180,3)<>"ДОК",$N180<>""),IFERROR(INDEX(МАТЕРИАЛЫ!$H$2:$H$9000,MATCH($N180,МАТЕРИАЛЫ!$L$2:$L$9000,0))*IF(INDEX(МАТЕРИАЛЫ!$I$2:$I$9000,MATCH($N180,МАТЕРИАЛЫ!$L$2:$L$9000,0))="USD",КурсUSD,IF(INDEX(МАТЕРИАЛЫ!$I$2:$I$9000,MATCH($N180,МАТЕРИАЛЫ!$L$2:$L$9000,0))="EUR",КурсEUR,IF(INDEX(МАТЕРИАЛЫ!$I$2:$I$9000,MATCH($N180,МАТЕРИАЛЫ!$L$2:$L$9000,0))="CNY",КурсCNY,1)))*(1+N($H180)/100),0),N($O180))*(1-MEDIAN(0,N(ДисконтТендер),1)))) -> 0 | U180: =IF($L180="да",MAX($U$1:$U179)+1,"") | V180: =IF($A180="","",$B180) -> Р3 | W180: =IF($U180="","",IF($U180=1,1,IF($V180<>IFERROR(INDEX($V$2:$V$1058,MATCH($U180-1,$U$2:$U$1058,0)),"~"),1,0))) | X180: =IF($U180="","",$U180+SUMIFS($W$2:$W$1058,$U$2:$U$1058,"<="&$U180)) | Y180: =IF($A180="","",IF(AND(LEFT($G180,3)="ДОК",$N180<>""),IFERROR(INDEX(Документация!$G$2:$G$57,MATCH($N180,Документация!$F$2:$F$57,0)),$D180),$D180&IF(AND(LEFT($G180,3)<>"ДОК",$N180<>"")," — "&IFERROR(INDEX(МАТЕРИАЛЫ!$C$2:$C$9000,MATCH($N180,МАТЕРИАЛЫ!$L$2:$L$9000,0)),""),""))) -> Запенивание противопожарной пеной тех. отверстий прохода транзитных коммуникаций | Z180: =IF($B180="","",$B180&" · "&IFERROR(VLOOKUP($B180,спрРазделы,2,0),"")) -> Р3 · Внутренние строительные работы
A181: РАБ.Р3.1.020 | B181: Р3 | C181: 1 | D181: Пробивка проемов в стенах из пенобетонных блоков | E181: м3 | F181: 12214.8 | H181: 0 | I181: ТС ЕР | P181: =IF($L181="да",ROUND(N($M181)*$S181,2),"") | Q181: =IF($L181="да",ROUND(N($M181)*$T181,2),"") | R181: =IF($L181="да",N($P181)+N($Q181),"") | S181: =IF($A181="","",IF(AND(LEFT($G181,3)="ДОК",$N181<>""),IFERROR(INDEX(Документация!$E$2:$E$57,MATCH($N181,Документация!$F$2:$F$57,0)),0),N($F181))*(1-MEDIAN(0,N(ДисконтТендер),1))) -> 12214.8 | T181: =IF($A181="","",IF(AND(LEFT($G181,3)="ДОК",$N181<>""),0,IF(AND(LEFT($G181,3)<>"ДОК",$N181<>""),IFERROR(INDEX(МАТЕРИАЛЫ!$H$2:$H$9000,MATCH($N181,МАТЕРИАЛЫ!$L$2:$L$9000,0))*IF(INDEX(МАТЕРИАЛЫ!$I$2:$I$9000,MATCH($N181,МАТЕРИАЛЫ!$L$2:$L$9000,0))="USD",КурсUSD,IF(INDEX(МАТЕРИАЛЫ!$I$2:$I$9000,MATCH($N181,МАТЕРИАЛЫ!$L$2:$L$9000,0))="EUR",КурсEUR,IF(INDEX(МАТЕРИАЛЫ!$I$2:$I$9000,MATCH($N181,МАТЕРИАЛЫ!$L$2:$L$9000,0))="CNY",КурсCNY,1)))*(1+N($H181)/100),0),N($O181))*(1-MEDIAN(0,N(ДисконтТендер),1)))) -> 0 | U181: =IF($L181="да",MAX($U$1:$U180)+1,"") | V181: =IF($A181="","",$B181) -> Р3 | W181: =IF($U181="","",IF($U181=1,1,IF($V181<>IFERROR(INDEX($V$2:$V$1058,MATCH($U181-1,$U$2:$U$1058,0)),"~"),1,0))) | X181: =IF($U181="","",$U181+SUMIFS($W$2:$W$1058,$U$2:$U$1058,"<="&$U181)) | Y181: =IF($A181="","",IF(AND(LEFT($G181,3)="ДОК",$N181<>""),IFERROR(INDEX(Документация!$G$2:$G$57,MATCH($N181,Документация!$F$2:$F$57,0)),$D181),$D181&IF(AND(LEFT($G181,3)<>"ДОК",$N181<>"")," — "&IFERROR(INDEX(МАТЕРИАЛЫ!$C$2:$C$9000,MATCH($N181,МАТЕРИАЛЫ!$L$2:$L$9000,0)),""),""))) -> Пробивка проемов в стенах из пенобетонных блоков | Z181: =IF($B181="","",$B181&" · "&IFERROR(VLOOKUP($B181,спрРазделы,2,0),"")) -> Р3 · Внутренние строительные работы
A182: РАБ.Р3.1.021 | B182: Р3 | C182: 1 | D182: Пробивка проемов в стенах из кирпича | E182: м3 | F182: 10521.32 | G182: КЛАДКА | H182: 5 | I182: ТС ЕР | P182: =IF($L182="да",ROUND(N($M182)*$S182,2),"") | Q182: =IF($L182="да",ROUND(N($M182)*$T182,2),"") | R182: =IF($L182="да",N($P182)+N($Q182),"") | S182: =IF($A182="","",IF(AND(LEFT($G182,3)="ДОК",$N182<>""),IFERROR(INDEX(Документация!$E$2:$E$57,MATCH($N182,Документация!$F$2:$F$57,0)),0),N($F182))*(1-MEDIAN(0,N(ДисконтТендер),1))) -> 10521.32 | T182: =IF($A182="","",IF(AND(LEFT($G182,3)="ДОК",$N182<>""),0,IF(AND(LEFT($G182,3)<>"ДОК",$N182<>""),IFERROR(INDEX(МАТЕРИАЛЫ!$H$2:$H$9000,MATCH($N182,МАТЕРИАЛЫ!$L$2:$L$9000,0))*IF(INDEX(МАТЕРИАЛЫ!$I$2:$I$9000,MATCH($N182,МАТЕРИАЛЫ!$L$2:$L$9000,0))="USD",КурсUSD,IF(INDEX(МАТЕРИАЛЫ!$I$2:$I$9000,MATCH($N182,МАТЕРИАЛЫ!$L$2:$L$9000,0))="EUR",КурсEUR,IF(INDEX(МАТЕРИАЛЫ!$I$2:$I$9000,MATCH($N182,МАТЕРИАЛЫ!$L$2:$L$9000,0))="CNY",КурсCNY,1)))*(1+N($H182)/100),0),N($O182))*(1-MEDIAN(0,N(ДисконтТендер),1)))) -> 0 | U182: =IF($L182="да",MAX($U$1:$U181)+1,"") | V182: =IF($A182="","",$B182) -> Р3 | W182: =IF($U182="","",IF($U182=1,1,IF($V182<>IFERROR(INDEX($V$2:$V$1058,MATCH($U182-1,$U$2:$U$1058,0)),"~"),1,0))) | X182: =IF($U182="","",$U182+SUMIFS($W$2:$W$1058,$U$2:$U$1058,"<="&$U182)) | Y182: =IF($A182="","",IF(AND(LEFT($G182,3)="ДОК",$N182<>""),IFERROR(INDEX(Документация!$G$2:$G$57,MATCH($N182,Документация!$F$2:$F$57,0)),$D182),$D182&IF(AND(LEFT($G182,3)<>"ДОК",$N182<>"")," — "&IFERROR(INDEX(МАТЕРИАЛЫ!$C$2:$C$9000,MATCH($N182,МАТЕРИАЛЫ!$L$2:$L$9000,0)),""),""))) -> Пробивка проемов в стенах из кирпича | Z182: =IF($B182="","",$B182&" · "&IFERROR(VLOOKUP($B182,спрРазделы,2,0),"")) -> Р3 · Внутренние строительные работы
A183: РАБ.Р3.1.022 | B183: Р3 | C183: 1 | D183: Алмазное сверление отверстий в стенах Ø50-100 мм | E183: см. | F183: 76.37 | H183: 0 | I183: ТС ЕР | P183: =IF($L183="да",ROUND(N($M183)*$S183,2),"") | Q183: =IF($L183="да",ROUND(N($M183)*$T183,2),"") | R183: =IF($L183="да",N($P183)+N($Q183),"") | S183: =IF($A183="","",IF(AND(LEFT($G183,3)="ДОК",$N183<>""),IFERROR(INDEX(Документация!$E$2:$E$57,MATCH($N183,Документация!$F$2:$F$57,0)),0),N($F183))*(1-MEDIAN(0,N(ДисконтТендер),1))) -> 76.37 | T183: =IF($A183="","",IF(AND(LEFT($G183,3)="ДОК",$N183<>""),0,IF(AND(LEFT($G183,3)<>"ДОК",$N183<>""),IFERROR(INDEX(МАТЕРИАЛЫ!$H$2:$H$9000,MATCH($N183,МАТЕРИАЛЫ!$L$2:$L$9000,0))*IF(INDEX(МАТЕРИАЛЫ!$I$2:$I$9000,MATCH($N183,МАТЕРИАЛЫ!$L$2:$L$9000,0))="USD",КурсUSD,IF(INDEX(МАТЕРИАЛЫ!$I$2:$I$9000,MATCH($N183,МАТЕРИАЛЫ!$L$2:$L$9000,0))="EUR",КурсEUR,IF(INDEX(МАТЕРИАЛЫ!$I$2:$I$9000,MATCH($N183,МАТЕРИАЛЫ!$L$2:$L$9000,0))="CNY",КурсCNY,1)))*(1+N($H183)/100),0),N($O183))*(1-MEDIAN(0,N(ДисконтТендер),1)))) -> 0 | U183: =IF($L183="да",MAX($U$1:$U182)+1,"") | V183: =IF($A183="","",$B183) -> Р3 | W183: =IF($U183="","",IF($U183=1,1,IF($V183<>IFERROR(INDEX($V$2:$V$1058,MATCH($U183-1,$U$2:$U$1058,0)),"~"),1,0))) | X183: =IF($U183="","",$U183+SUMIFS($W$2:$W$1058,$U$2:$U$1058,"<="&$U183)) | Y183: =IF($A183="","",IF(AND(LEFT($G183,3)="ДОК",$N183<>""),IFERROR(INDEX(Документация!$G$2:$G$57,MATCH($N183,Документация!$F$2:$F$57,0)),$D183),$D183&IF(AND(LEFT($G183,3)<>"ДОК",$N183<>"")," — "&IFERROR(INDEX(МАТЕРИАЛЫ!$C$2:$C$9000,MATCH($N183,МАТЕРИАЛЫ!$L$2:$L$9000,0)),""),""))) -> Алмазное сверление отверстий в стенах Ø50-100 мм | Z183: =IF($B183="","",$B183&" · "&IFERROR(VLOOKUP($B183,спрРазделы,2,0),"")) -> Р3 · Внутренние строительные работы
A184: РАБ.Р3.1.023 | B184: Р3 | C184: 1 | D184: Алмазное сверление отверстий в стенах Ø101-200 мм | E184: см. | F184: 78.96 | H184: 0 | I184: ТС ЕР | P184: =IF($L184="да",ROUND(N($M184)*$S184,2),"") | Q184: =IF($L184="да",ROUND(N($M184)*$T184,2),"") | R184: =IF($L184="да",N($P184)+N($Q184),"") | S184: =IF($A184="","",IF(AND(LEFT($G184,3)="ДОК",$N184<>""),IFERROR(INDEX(Документация!$E$2:$E$57,MATCH($N184,Документация!$F$2:$F$57,0)),0),N($F184))*(1-MEDIAN(0,N(ДисконтТендер),1))) -> 78.96 | T184: =IF($A184="","",IF(AND(LEFT($G184,3)="ДОК",$N184<>""),0,IF(AND(LEFT($G184,3)<>"ДОК",$N184<>""),IFERROR(INDEX(МАТЕРИАЛЫ!$H$2:$H$9000,MATCH($N184,МАТЕРИАЛЫ!$L$2:$L$9000,0))*IF(INDEX(МАТЕРИАЛЫ!$I$2:$I$9000,MATCH($N184,МАТЕРИАЛЫ!$L$2:$L$9000,0))="USD",КурсUSD,IF(INDEX(МАТЕРИАЛЫ!$I$2:$I$9000,MATCH($N184,МАТЕРИАЛЫ!$L$2:$L$9000,0))="EUR",КурсEUR,IF(INDEX(МАТЕРИАЛЫ!$I$2:$I$9000,MATCH($N184,МАТЕРИАЛЫ!$L$2:$L$9000,0))="CNY",КурсCNY,1)))*(1+N($H184)/100),0),N($O184))*(1-MEDIAN(0,N(ДисконтТендер),1)))) -> 0 | U184: =IF($L184="да",MAX($U$1:$U183)+1,"") | V184: =IF($A184="","",$B184) -> Р3 | W184: =IF($U184="","",IF($U184=1,1,IF($V184<>IFERROR(INDEX($V$2:$V$1058,MATCH($U184-1,$U$2:$U$1058,0)),"~"),1,0))) | X184: =IF($U184="","",$U184+SUMIFS($W$2:$W$1058,$U$2:$U$1058,"<="&$U184)) | Y184: =IF($A184="","",IF(AND(LEFT($G184,3)="ДОК",$N184<>""),IFERROR(INDEX(Документация!$G$2:$G$57,MATCH($N184,Документация!$F$2:$F$57,0)),$D184),$D184&IF(AND(LEFT($G184,3)<>"ДОК",$N184<>"")," — "&IFERROR(INDEX(МАТЕРИАЛЫ!$C$2:$C$9000,MATCH($N184,МАТЕРИАЛЫ!$L$2:$L$9000,0)),""),""))) -> Алмазное сверление отверстий в стенах Ø101-200 мм | Z184: =IF($B184="","",$B184&" · "&IFERROR(VLOOKUP($B184,спрРазделы,2,0),"")) -> Р3 · Внутренние строительные работы
A185: РАБ.Р3.1.024 | B185: Р3 | C185: 1 | D185: Алмазное сверление отверстий в стенах Ø201-300 мм | E185: см. | F185: 134.85 | H185: 0 | I185: ТС ЕР | P185: =IF($L185="да",ROUND(N($M185)*$S185,2),"") | Q185: =IF($L185="да",ROUND(N($M185)*$T185,2),"") | R185: =IF($L185="да",N($P185)+N($Q185),"") | S185: =IF($A185="","",IF(AND(LEFT($G185,3)="ДОК",$N185<>""),IFERROR(INDEX(Документация!$E$2:$E$57,MATCH($N185,Документация!$F$2:$F$57,0)),0),N($F185))*(1-MEDIAN(0,N(ДисконтТендер),1))) -> 134.85 | T185: =IF($A185="","",IF(AND(LEFT($G185,3)="ДОК",$N185<>""),0,IF(AND(LEFT($G185,3)<>"ДОК",$N185<>""),IFERROR(INDEX(МАТЕРИАЛЫ!$H$2:$H$9000,MATCH($N185,МАТЕРИАЛЫ!$L$2:$L$9000,0))*IF(INDEX(МАТЕРИАЛЫ!$I$2:$I$9000,MATCH($N185,МАТЕРИАЛЫ!$L$2:$L$9000,0))="USD",КурсUSD,IF(INDEX(МАТЕРИАЛЫ!$I$2:$I$9000,MATCH($N185,МАТЕРИАЛЫ!$L$2:$L$9000,0))="EUR",КурсEUR,IF(INDEX(МАТЕРИАЛЫ!$I$2:$I$9000,MATCH($N185,МАТЕРИАЛЫ!$L$2:$L$9000,0))="CNY",КурсCNY,1)))*(1+N($H185)/100),0),N($O185))*(1-MEDIAN(0,N(ДисконтТендер),1)))) -> 0 | U185: =IF($L185="да",MAX($U$1:$U184)+1,"") | V185: =IF($A185="","",$B185) -> Р3 | W185: =IF($U185="","",IF($U185=1,1,IF($V185<>IFERROR(INDEX($V$2:$V$1058,MATCH($U185-1,$U$2:$U$1058,0)),"~"),1,0))) | X185: =IF($U185="","",$U185+SUMIFS($W$2:$W$1058,$U$2:$U$1058,"<="&$U185)) | Y185: =IF($A185="","",IF(AND(LEFT($G185,3)="ДОК",$N185<>""),IFERROR(INDEX(Документация!$G$2:$G$57,MATCH($N185,Документация!$F$2:$F$57,0)),$D185),$D185&IF(AND(LEFT($G185,3)<>"ДОК",$N185<>"")," — "&IFERROR(INDEX(МАТЕРИАЛЫ!$C$2:$C$9000,MATCH($N185,МАТЕРИАЛЫ!$L$2:$L$9000,0)),""),""))) -> Алмазное сверление отверстий в стенах Ø201-300 мм | Z185: =IF($B185="","",$B185&" · "&IFERROR(VLOOKUP($B185,спрРазделы,2,0),"")) -> Р3 · Внутренние строительные работы
A186: РАБ.Р3.1.025 | B186: Р3 | C186: 1 | D186: Алмазное сверление отверстий в стенах Ø301-400 мм | E186: см. | F186: 174 | H186: 0 | I186: ТС ЕР | P186: =IF($L186="да",ROUND(N($M186)*$S186,2),"") | Q186: =IF($L186="да",ROUND(N($M186)*$T186,2),"") | R186: =IF($L186="да",N($P186)+N($Q186),"") | S186: =IF($A186="","",IF(AND(LEFT($G186,3)="ДОК",$N186<>""),IFERROR(INDEX(Документация!$E$2:$E$57,MATCH($N186,Документация!$F$2:$F$57,0)),0),N($F186))*(1-MEDIAN(0,N(ДисконтТендер),1))) -> 174 | T186: =IF($A186="","",IF(AND(LEFT($G186,3)="ДОК",$N186<>""),0,IF(AND(LEFT($G186,3)<>"ДОК",$N186<>""),IFERROR(INDEX(МАТЕРИАЛЫ!$H$2:$H$9000,MATCH($N186,МАТЕРИАЛЫ!$L$2:$L$9000,0))*IF(INDEX(МАТЕРИАЛЫ!$I$2:$I$9000,MATCH($N186,МАТЕРИАЛЫ!$L$2:$L$9000,0))="USD",КурсUSD,IF(INDEX(МАТЕРИАЛЫ!$I$2:$I$9000,MATCH($N186,МАТЕРИАЛЫ!$L$2:$L$9000,0))="EUR",КурсEUR,IF(INDEX(МАТЕРИАЛЫ!$I$2:$I$9000,MATCH($N186,МАТЕРИАЛЫ!$L$2:$L$9000,0))="CNY",КурсCNY,1)))*(1+N($H186)/100),0),N($O186))*(1-MEDIAN(0,N(ДисконтТендер),1)))) -> 0 | U186: =IF($L186="да",MAX($U$1:$U185)+1,"") | V186: =IF($A186="","",$B186) -> Р3 | W186: =IF($U186="","",IF($U186=1,1,IF($V186<>IFERROR(INDEX($V$2:$V$1058,MATCH($U186-1,$U$2:$U$1058,0)),"~"),1,0))) | X186: =IF($U186="","",$U186+SUMIFS($W$2:$W$1058,$U$2:$U$1058,"<="&$U186)) | Y186: =IF($A186="","",IF(AND(LEFT($G186,3)="ДОК",$N186<>""),IFERROR(INDEX(Документация!$G$2:$G$57,MATCH($N186,Документация!$F$2:$F$57,0)),$D186),$D186&IF(AND(LEFT($G186,3)<>"ДОК",$N186<>"")," — "&IFERROR(INDEX(МАТЕРИАЛЫ!$C$2:$C$9000,MATCH($N186,МАТЕРИАЛЫ!$L$2:$L$9000,0)),""),""))) -> Алмазное сверление отверстий в стенах Ø301-400 мм | Z186: =IF($B186="","",$B186&" · "&IFERROR(VLOOKUP($B186,спрРазделы,2,0),"")) -> Р3 · Внутренние строительные работы
A187: РАБ.Р3.1.026 | B187: Р3 | C187: 1 | D187: Монтаж закладных из фанеры 12мм под шкафы обработанная составом "NEOMID 450-1". | E187: м2 | F187: 560 | H187: 0 | I187: ТС ЕР | P187: =IF($L187="да",ROUND(N($M187)*$S187,2),"") | Q187: =IF($L187="да",ROUND(N($M187)*$T187,2),"") | R187: =IF($L187="да",N($P187)+N($Q187),"") | S187: =IF($A187="","",IF(AND(LEFT($G187,3)="ДОК",$N187<>""),IFERROR(INDEX(Документация!$E$2:$E$57,MATCH($N187,Документация!$F$2:$F$57,0)),0),N($F187))*(1-MEDIAN(0,N(ДисконтТендер),1))) -> 560 | T187: =IF($A187="","",IF(AND(LEFT($G187,3)="ДОК",$N187<>""),0,IF(AND(LEFT($G187,3)<>"ДОК",$N187<>""),IFERROR(INDEX(МАТЕРИАЛЫ!$H$2:$H$9000,MATCH($N187,МАТЕРИАЛЫ!$L$2:$L$9000,0))*IF(INDEX(МАТЕРИАЛЫ!$I$2:$I$9000,MATCH($N187,МАТЕРИАЛЫ!$L$2:$L$9000,0))="USD",КурсUSD,IF(INDEX(МАТЕРИАЛЫ!$I$2:$I$9000,MATCH($N187,МАТЕРИАЛЫ!$L$2:$L$9000,0))="EUR",КурсEUR,IF(INDEX(МАТЕРИАЛЫ!$I$2:$I$9000,MATCH($N187,МАТЕРИАЛЫ!$L$2:$L$9000,0))="CNY",КурсCNY,1)))*(1+N($H187)/100),0),N($O187))*(1-MEDIAN(0,N(ДисконтТендер),1)))) -> 0 | U187: =IF($L187="да",MAX($U$1:$U186)+1,"") | V187: =IF($A187="","",$B187) -> Р3 | W187: =IF($U187="","",IF($U187=1,1,IF($V187<>IFERROR(INDEX($V$2:$V$1058,MATCH($U187-1,$U$2:$U$1058,0)),"~"),1,0))) | X187: =IF($U187="","",$U187+SUMIFS($W$2:$W$1058,$U$2:$U$1058,"<="&$U187)) | Y187: =IF($A187="","",IF(AND(LEFT($G187,3)="ДОК",$N187<>""),IFERROR(INDEX(Документация!$G$2:$G$57,MATCH($N187,Документация!$F$2:$F$57,0)),$D187),$D187&IF(AND(LEFT($G187,3)<>"ДОК",$N187<>"")," — "&IFERROR(INDEX(МАТЕРИАЛЫ!$C$2:$C$9000,MATCH($N187,МАТЕРИАЛЫ!$L$2:$L$9000,0)),""),""))) -> Монтаж закладных из фанеры 12мм под шкафы обработанная составом "NEOMID 450-1". | Z187: =IF($B187="","",$B187&" · "&IFERROR(VLOOKUP($B187,спрРазделы,2,0),"")) -> Р3 · Внутренние строительные работы
A188: РАБ.Р3.1.027 | B188: Р3 | C188: 1 | D188: Устройство ниши ГКЛ по м/к под монтаж приборов отопления | E188: шт. | F188: 3063.98 | G188: ГКЛ | H188: 5 | I188: ТС ЕР | P188: =IF($L188="да",ROUND(N($M188)*$S188,2),"") | Q188: =IF($L188="да",ROUND(N($M188)*$T188,2),"") | R188: =IF($L188="да",N($P188)+N($Q188),"") | S188: =IF($A188="","",IF(AND(LEFT($G188,3)="ДОК",$N188<>""),IFERROR(INDEX(Документация!$E$2:$E$57,MATCH($N188,Документация!$F$2:$F$57,0)),0),N($F188))*(1-MEDIAN(0,N(ДисконтТендер),1))) -> 3063.98 | T188: =IF($A188="","",IF(AND(LEFT($G188,3)="ДОК",$N188<>""),0,IF(AND(LEFT($G188,3)<>"ДОК",$N188<>""),IFERROR(INDEX(МАТЕРИАЛЫ!$H$2:$H$9000,MATCH($N188,МАТЕРИАЛЫ!$L$2:$L$9000,0))*IF(INDEX(МАТЕРИАЛЫ!$I$2:$I$9000,MATCH($N188,МАТЕРИАЛЫ!$L$2:$L$9000,0))="USD",КурсUSD,IF(INDEX(МАТЕРИАЛЫ!$I$2:$I$9000,MATCH($N188,МАТЕРИАЛЫ!$L$2:$L$9000,0))="EUR",КурсEUR,IF(INDEX(МАТЕРИАЛЫ!$I$2:$I$9000,MATCH($N188,МАТЕРИАЛЫ!$L$2:$L$9000,0))="CNY",КурсCNY,1)))*(1+N($H188)/100),0),N($O188))*(1-MEDIAN(0,N(ДисконтТендер),1)))) -> 0 | U188: =IF($L188="да",MAX($U$1:$U187)+1,"") | V188: =IF($A188="","",$B188) -> Р3 | W188: =IF($U188="","",IF($U188=1,1,IF($V188<>IFERROR(INDEX($V$2:$V$1058,MATCH($U188-1,$U$2:$U$1058,0)),"~"),1,0))) | X188: =IF($U188="","",$U188+SUMIFS($W$2:$W$1058,$U$2:$U$1058,"<="&$U188)) | Y188: =IF($A188="","",IF(AND(LEFT($G188,3)="ДОК",$N188<>""),IFERROR(INDEX(Документация!$G$2:$G$57,MATCH($N188,Документация!$F$2:$F$57,0)),$D188),$D188&IF(AND(LEFT($G188,3)<>"ДОК",$N188<>"")," — "&IFERROR(INDEX(МАТЕРИАЛЫ!$C$2:$C$9000,MATCH($N188,МАТЕРИАЛЫ!$L$2:$L$9000,0)),""),""))) -> Устройство ниши ГКЛ по м/к под монтаж приборов отопления | Z188: =IF($B188="","",$B188&" · "&IFERROR(VLOOKUP($B188,спрРазделы,2,0),"")) -> Р3 · Внутренние строительные работы
A189: РАБ.Р3.1.028 | B189: Р3 | C189: 1 | D189: Устройство пароизоляции из полиэтиленовой пленки до 100 мкр. | E189: м2 | F189: 115.13 | H189: 0 | I189: ТС ЕР | P189: =IF($L189="да",ROUND(N($M189)*$S189,2),"") | Q189: =IF($L189="да",ROUND(N($M189)*$T189,2),"") | R189: =IF($L189="да",N($P189)+N($Q189),"") | S189: =IF($A189="","",IF(AND(LEFT($G189,3)="ДОК",$N189<>""),IFERROR(INDEX(Документация!$E$2:$E$57,MATCH($N189,Документация!$F$2:$F$57,0)),0),N($F189))*(1-MEDIAN(0,N(ДисконтТендер),1))) -> 115.13 | T189: =IF($A189="","",IF(AND(LEFT($G189,3)="ДОК",$N189<>""),0,IF(AND(LEFT($G189,3)<>"ДОК",$N189<>""),IFERROR(INDEX(МАТЕРИАЛЫ!$H$2:$H$9000,MATCH($N189,МАТЕРИАЛЫ!$L$2:$L$9000,0))*IF(INDEX(МАТЕРИАЛЫ!$I$2:$I$9000,MATCH($N189,МАТЕРИАЛЫ!$L$2:$L$9000,0))="USD",КурсUSD,IF(INDEX(МАТЕРИАЛЫ!$I$2:$I$9000,MATCH($N189,МАТЕРИАЛЫ!$L$2:$L$9000,0))="EUR",КурсEUR,IF(INDEX(МАТЕРИАЛЫ!$I$2:$I$9000,MATCH($N189,МАТЕРИАЛЫ!$L$2:$L$9000,0))="CNY",КурсCNY,1)))*(1+N($H189)/100),0),N($O189))*(1-MEDIAN(0,N(ДисконтТендер),1)))) -> 0 | U189: =IF($L189="да",MAX($U$1:$U188)+1,"") | V189: =IF($A189="","",$B189) -> Р3 | W189: =IF($U189="","",IF($U189=1,1,IF($V189<>IFERROR(INDEX($V$2:$V$1058,MATCH($U189-1,$U$2:$U$1058,0)),"~"),1,0))) | X189: =IF($U189="","",$U189+SUMIFS($W$2:$W$1058,$U$2:$U$1058,"<="&$U189)) | Y189: =IF($A189="","",IF(AND(LEFT($G189,3)="ДОК",$N189<>""),IFERROR(INDEX(Документация!$G$2:$G$57,MATCH($N189,Документация!$F$2:$F$57,0)),$D189),$D189&IF(AND(LEFT($G189,3)<>"ДОК",$N189<>"")," — "&IFERROR(INDEX(МАТЕРИАЛЫ!$C$2:$C$9000,MATCH($N189,МАТЕРИАЛЫ!$L$2:$L$9000,0)),""),""))) -> Устройство пароизоляции из полиэтиленовой пленки до 100 мкр. | Z189: =IF($B189="","",$B189&" · "&IFERROR(VLOOKUP($B189,спрРазделы,2,0),"")) -> Р3 · Внутренние строительные работы
A190: РАБ.Р3.1.029 | B190: Р3 | C190: 1 | D190: Усиление проемов деревянным антисептированным бруском 50*50 | E190: м.п. | F190: 490.94 | H190: 0 | I190: ТС ЕР | P190: =IF($L190="да",ROUND(N($M190)*$S190,2),"") | Q190: =IF($L190="да",ROUND(N($M190)*$T190,2),"") | R190: =IF($L190="да",N($P190)+N($Q190),"") | S190: =IF($A190="","",IF(AND(LEFT($G190,3)="ДОК",$N190<>""),IFERROR(INDEX(Документация!$E$2:$E$57,MATCH($N190,Документация!$F$2:$F$57,0)),0),N($F190))*(1-MEDIAN(0,N(ДисконтТендер),1))) -> 490.94 | T190: =IF($A190="","",IF(AND(LEFT($G190,3)="ДОК",$N190<>""),0,IF(AND(LEFT($G190,3)<>"ДОК",$N190<>""),IFERROR(INDEX(МАТЕРИАЛЫ!$H$2:$H$9000,MATCH($N190,МАТЕРИАЛЫ!$L$2:$L$9000,0))*IF(INDEX(МАТЕРИАЛЫ!$I$2:$I$9000,MATCH($N190,МАТЕРИАЛЫ!$L$2:$L$9000,0))="USD",КурсUSD,IF(INDEX(МАТЕРИАЛЫ!$I$2:$I$9000,MATCH($N190,МАТЕРИАЛЫ!$L$2:$L$9000,0))="EUR",КурсEUR,IF(INDEX(МАТЕРИАЛЫ!$I$2:$I$9000,MATCH($N190,МАТЕРИАЛЫ!$L$2:$L$9000,0))="CNY",КурсCNY,1)))*(1+N($H190)/100),0),N($O190))*(1-MEDIAN(0,N(ДисконтТендер),1)))) -> 0 | U190: =IF($L190="да",MAX($U$1:$U189)+1,"") | V190: =IF($A190="","",$B190) -> Р3 | W190: =IF($U190="","",IF($U190=1,1,IF($V190<>IFERROR(INDEX($V$2:$V$1058,MATCH($U190-1,$U$2:$U$1058,0)),"~"),1,0))) | X190: =IF($U190="","",$U190+SUMIFS($W$2:$W$1058,$U$2:$U$1058,"<="&$U190)) | Y190: =IF($A190="","",IF(AND(LEFT($G190,3)="ДОК",$N190<>""),IFERROR(INDEX(Документация!$G$2:$G$57,MATCH($N190,Документация!$F$2:$F$57,0)),$D190),$D190&IF(AND(LEFT($G190,3)<>"ДОК",$N190<>"")," — "&IFERROR(INDEX(МАТЕРИАЛЫ!$C$2:$C$9000,MATCH($N190,МАТЕРИАЛЫ!$L$2:$L$9000,0)),""),""))) -> Усиление проемов деревянным антисептированным бруском 50*50 | Z190: =IF($B190="","",$B190&" · "&IFERROR(VLOOKUP($B190,спрРазделы,2,0),"")) -> Р3 · Внутренние строительные работы
A191: РАБ.Р3.1.030 | B191: Р3 | C191: 1 | D191: Люк скрытый нажимной 300*300 | E191: шт. | F191: 1788.72 | H191: 0 | I191: ТС ЕР | P191: =IF($L191="да",ROUND(N($M191)*$S191,2),"") | Q191: =IF($L191="да",ROUND(N($M191)*$T191,2),"") | R191: =IF($L191="да",N($P191)+N($Q191),"") | S191: =IF($A191="","",IF(AND(LEFT($G191,3)="ДОК",$N191<>""),IFERROR(INDEX(Документация!$E$2:$E$57,MATCH($N191,Документация!$F$2:$F$57,0)),0),N($F191))*(1-MEDIAN(0,N(ДисконтТендер),1))) -> 1788.72 | T191: =IF($A191="","",IF(AND(LEFT($G191,3)="ДОК",$N191<>""),0,IF(AND(LEFT($G191,3)<>"ДОК",$N191<>""),IFERROR(INDEX(МАТЕРИАЛЫ!$H$2:$H$9000,MATCH($N191,МАТЕРИАЛЫ!$L$2:$L$9000,0))*IF(INDEX(МАТЕРИАЛЫ!$I$2:$I$9000,MATCH($N191,МАТЕРИАЛЫ!$L$2:$L$9000,0))="USD",КурсUSD,IF(INDEX(МАТЕРИАЛЫ!$I$2:$I$9000,MATCH($N191,МАТЕРИАЛЫ!$L$2:$L$9000,0))="EUR",КурсEUR,IF(INDEX(МАТЕРИАЛЫ!$I$2:$I$9000,MATCH($N191,МАТЕРИАЛЫ!$L$2:$L$9000,0))="CNY",КурсCNY,1)))*(1+N($H191)/100),0),N($O191))*(1-MEDIAN(0,N(ДисконтТендер),1)))) -> 0 | U191: =IF($L191="да",MAX($U$1:$U190)+1,"") | V191: =IF($A191="","",$B191) -> Р3 | W191: =IF($U191="","",IF($U191=1,1,IF($V191<>IFERROR(INDEX($V$2:$V$1058,MATCH($U191-1,$U$2:$U$1058,0)),"~"),1,0))) | X191: =IF($U191="","",$U191+SUMIFS($W$2:$W$1058,$U$2:$U$1058,"<="&$U191)) | Y191: =IF($A191="","",IF(AND(LEFT($G191,3)="ДОК",$N191<>""),IFERROR(INDEX(Документация!$G$2:$G$57,MATCH($N191,Документация!$F$2:$F$57,0)),$D191),$D191&IF(AND(LEFT($G191,3)<>"ДОК",$N191<>"")," — "&IFERROR(INDEX(МАТЕРИАЛЫ!$C$2:$C$9000,MATCH($N191,МАТЕРИАЛЫ!$L$2:$L$9000,0)),""),""))) -> Люк скрытый нажимной 300*300 | Z191: =IF($B191="","",$B191&" · "&IFERROR(VLOOKUP($B191,спрРазделы,2,0),"")) -> Р3 · Внутренние строительные работы
A192: РАБ.Р3.1.031 | B192: Р3 | C192: 1 | D192: Люк скрытый нажимной 400*600 | E192: шт. | F192: 2401.2 | H192: 0 | I192: ТС ЕР | P192: =IF($L192="да",ROUND(N($M192)*$S192,2),"") | Q192: =IF($L192="да",ROUND(N($M192)*$T192,2),"") | R192: =IF($L192="да",N($P192)+N($Q192),"") | S192: =IF($A192="","",IF(AND(LEFT($G192,3)="ДОК",$N192<>""),IFERROR(INDEX(Документация!$E$2:$E$57,MATCH($N192,Документация!$F$2:$F$57,0)),0),N($F192))*(1-MEDIAN(0,N(ДисконтТендер),1))) -> 2401.2 | T192: =IF($A192="","",IF(AND(LEFT($G192,3)="ДОК",$N192<>""),0,IF(AND(LEFT($G192,3)<>"ДОК",$N192<>""),IFERROR(INDEX(МАТЕРИАЛЫ!$H$2:$H$9000,MATCH($N192,МАТЕРИАЛЫ!$L$2:$L$9000,0))*IF(INDEX(МАТЕРИАЛЫ!$I$2:$I$9000,MATCH($N192,МАТЕРИАЛЫ!$L$2:$L$9000,0))="USD",КурсUSD,IF(INDEX(МАТЕРИАЛЫ!$I$2:$I$9000,MATCH($N192,МАТЕРИАЛЫ!$L$2:$L$9000,0))="EUR",КурсEUR,IF(INDEX(МАТЕРИАЛЫ!$I$2:$I$9000,MATCH($N192,МАТЕРИАЛЫ!$L$2:$L$9000,0))="CNY",КурсCNY,1)))*(1+N($H192)/100),0),N($O192))*(1-MEDIAN(0,N(ДисконтТендер),1)))) -> 0 | U192: =IF($L192="да",MAX($U$1:$U191)+1,"") | V192: =IF($A192="","",$B192) -> Р3 | W192: =IF($U192="","",IF($U192=1,1,IF($V192<>IFERROR(INDEX($V$2:$V$1058,MATCH($U192-1,$U$2:$U$1058,0)),"~"),1,0))) | X192: =IF($U192="","",$U192+SUMIFS($W$2:$W$1058,$U$2:$U$1058,"<="&$U192)) | Y192: =IF($A192="","",IF(AND(LEFT($G192,3)="ДОК",$N192<>""),IFERROR(INDEX(Документация!$G$2:$G$57,MATCH($N192,Документация!$F$2:$F$57,0)),$D192),$D192&IF(AND(LEFT($G192,3)<>"ДОК",$N192<>"")," — "&IFERROR(INDEX(МАТЕРИАЛЫ!$C$2:$C$9000,MATCH($N192,МАТЕРИАЛЫ!$L$2:$L$9000,0)),""),""))) -> Люк скрытый нажимной 400*600 | Z192: =IF($B192="","",$B192&" · "&IFERROR(VLOOKUP($B192,спрРазделы,2,0),"")) -> Р3 · Внутренние строительные работы
A193: РАБ.Р3.1.032 | B193: Р3 | C193: 1 | D193: Люк скрытый нажимной 500*600 | E193: шт. | F193: 2554.32 | H193: 0 | I193: ТС ЕР | P193: =IF($L193="да",ROUND(N($M193)*$S193,2),"") | Q193: =IF($L193="да",ROUND(N($M193)*$T193,2),"") | R193: =IF($L193="да",N($P193)+N($Q193),"") | S193: =IF($A193="","",IF(AND(LEFT($G193,3)="ДОК",$N193<>""),IFERROR(INDEX(Документация!$E$2:$E$57,MATCH($N193,Документация!$F$2:$F$57,0)),0),N($F193))*(1-MEDIAN(0,N(ДисконтТендер),1))) -> 2554.32 | T193: =IF($A193="","",IF(AND(LEFT($G193,3)="ДОК",$N193<>""),0,IF(AND(LEFT($G193,3)<>"ДОК",$N193<>""),IFERROR(INDEX(МАТЕРИАЛЫ!$H$2:$H$9000,MATCH($N193,МАТЕРИАЛЫ!$L$2:$L$9000,0))*IF(INDEX(МАТЕРИАЛЫ!$I$2:$I$9000,MATCH($N193,МАТЕРИАЛЫ!$L$2:$L$9000,0))="USD",КурсUSD,IF(INDEX(МАТЕРИАЛЫ!$I$2:$I$9000,MATCH($N193,МАТЕРИАЛЫ!$L$2:$L$9000,0))="EUR",КурсEUR,IF(INDEX(МАТЕРИАЛЫ!$I$2:$I$9000,MATCH($N193,МАТЕРИАЛЫ!$L$2:$L$9000,0))="CNY",КурсCNY,1)))*(1+N($H193)/100),0),N($O193))*(1-MEDIAN(0,N(ДисконтТендер),1)))) -> 0 | U193: =IF($L193="да",MAX($U$1:$U192)+1,"") | V193: =IF($A193="","",$B193) -> Р3 | W193: =IF($U193="","",IF($U193=1,1,IF($V193<>IFERROR(INDEX($V$2:$V$1058,MATCH($U193-1,$U$2:$U$1058,0)),"~"),1,0))) | X193: =IF($U193="","",$U193+SUMIFS($W$2:$W$1058,$U$2:$U$1058,"<="&$U193)) | Y193: =IF($A193="","",IF(AND(LEFT($G193,3)="ДОК",$N193<>""),IFERROR(INDEX(Документация!$G$2:$G$57,MATCH($N193,Документация!$F$2:$F$57,0)),$D193),$D193&IF(AND(LEFT($G193,3)<>"ДОК",$N193<>"")," — "&IFERROR(INDEX(МАТЕРИАЛЫ!$C$2:$C$9000,MATCH($N193,МАТЕРИАЛЫ!$L$2:$L$9000,0)),""),""))) -> Люк скрытый нажимной 500*600 | Z193: =IF($B193="","",$B193&" · "&IFERROR(VLOOKUP($B193,спрРазделы,2,0),"")) -> Р3 · Внутренние строительные работы
A194: РАБ.Р3.1.033 | B194: Р3 | C194: 1 | D194: Люк скрытый нажимной 600*600 | E194: шт. | F194: 2924.94 | H194: 0 | I194: ТС ЕР | P194: =IF($L194="да",ROUND(N($M194)*$S194,2),"") | Q194: =IF($L194="да",ROUND(N($M194)*$T194,2),"") | R194: =IF($L194="да",N($P194)+N($Q194),"") | S194: =IF($A194="","",IF(AND(LEFT($G194,3)="ДОК",$N194<>""),IFERROR(INDEX(Документация!$E$2:$E$57,MATCH($N194,Документация!$F$2:$F$57,0)),0),N($F194))*(1-MEDIAN(0,N(ДисконтТендер),1))) -> 2924.94 | T194: =IF($A194="","",IF(AND(LEFT($G194,3)="ДОК",$N194<>""),0,IF(AND(LEFT($G194,3)<>"ДОК",$N194<>""),IFERROR(INDEX(МАТЕРИАЛЫ!$H$2:$H$9000,MATCH($N194,МАТЕРИАЛЫ!$L$2:$L$9000,0))*IF(INDEX(МАТЕРИАЛЫ!$I$2:$I$9000,MATCH($N194,МАТЕРИАЛЫ!$L$2:$L$9000,0))="USD",КурсUSD,IF(INDEX(МАТЕРИАЛЫ!$I$2:$I$9000,MATCH($N194,МАТЕРИАЛЫ!$L$2:$L$9000,0))="EUR",КурсEUR,IF(INDEX(МАТЕРИАЛЫ!$I$2:$I$9000,MATCH($N194,МАТЕРИАЛЫ!$L$2:$L$9000,0))="CNY",КурсCNY,1)))*(1+N($H194)/100),0),N($O194))*(1-MEDIAN(0,N(ДисконтТендер),1)))) -> 0 | U194: =IF($L194="да",MAX($U$1:$U193)+1,"") | V194: =IF($A194="","",$B194) -> Р3 | W194: =IF($U194="","",IF($U194=1,1,IF($V194<>IFERROR(INDEX($V$2:$V$1058,MATCH($U194-1,$U$2:$U$1058,0)),"~"),1,0))) | X194: =IF($U194="","",$U194+SUMIFS($W$2:$W$1058,$U$2:$U$1058,"<="&$U194)) | Y194: =IF($A194="","",IF(AND(LEFT($G194,3)="ДОК",$N194<>""),IFERROR(INDEX(Документация!$G$2:$G$57,MATCH($N194,Документация!$F$2:$F$57,0)),$D194),$D194&IF(AND(LEFT($G194,3)<>"ДОК",$N194<>"")," — "&IFERROR(INDEX(МАТЕРИАЛЫ!$C$2:$C$9000,MATCH($N194,МАТЕРИАЛЫ!$L$2:$L$9000,0)),""),""))) -> Люк скрытый нажимной 600*600 | Z194: =IF($B194="","",$B194&" · "&IFERROR(VLOOKUP($B194,спрРазделы,2,0),"")) -> Р3 · Внутренние строительные работы
A195: РАБ.Р3.1.034 | B195: Р3 | C195: 1 | D195: Устройство коробов из ГКЛ до 600 мм шириной (для обшивки ригелей, балок колонн и т.д.) | E195: м.п. | F195: 1733.48 | G195: ГКЛ | H195: 5 | I195: ТС ЕР | P195: =IF($L195="да",ROUND(N($M195)*$S195,2),"") | Q195: =IF($L195="да",ROUND(N($M195)*$T195,2),"") | R195: =IF($L195="да",N($P195)+N($Q195),"") | S195: =IF($A195="","",IF(AND(LEFT($G195,3)="ДОК",$N195<>""),IFERROR(INDEX(Документация!$E$2:$E$57,MATCH($N195,Документация!$F$2:$F$57,0)),0),N($F195))*(1-MEDIAN(0,N(ДисконтТендер),1))) -> 1733.48 | T195: =IF($A195="","",IF(AND(LEFT($G195,3)="ДОК",$N195<>""),0,IF(AND(LEFT($G195,3)<>"ДОК",$N195<>""),IFERROR(INDEX(МАТЕРИАЛЫ!$H$2:$H$9000,MATCH($N195,МАТЕРИАЛЫ!$L$2:$L$9000,0))*IF(INDEX(МАТЕРИАЛЫ!$I$2:$I$9000,MATCH($N195,МАТЕРИАЛЫ!$L$2:$L$9000,0))="USD",КурсUSD,IF(INDEX(МАТЕРИАЛЫ!$I$2:$I$9000,MATCH($N195,МАТЕРИАЛЫ!$L$2:$L$9000,0))="EUR",КурсEUR,IF(INDEX(МАТЕРИАЛЫ!$I$2:$I$9000,MATCH($N195,МАТЕРИАЛЫ!$L$2:$L$9000,0))="CNY",КурсCNY,1)))*(1+N($H195)/100),0),N($O195))*(1-MEDIAN(0,N(ДисконтТендер),1)))) -> 0 | U195: =IF($L195="да",MAX($U$1:$U194)+1,"") | V195: =IF($A195="","",$B195) -> Р3 | W195: =IF($U195="","",IF($U195=1,1,IF($V195<>IFERROR(INDEX($V$2:$V$1058,MATCH($U195-1,$U$2:$U$1058,0)),"~"),1,0))) | X195: =IF($U195="","",$U195+SUMIFS($W$2:$W$1058,$U$2:$U$1058,"<="&$U195)) | Y195: =IF($A195="","",IF(AND(LEFT($G195,3)="ДОК",$N195<>""),IFERROR(INDEX(Документация!$G$2:$G$57,MATCH($N195,Документация!$F$2:$F$57,0)),$D195),$D195&IF(AND(LEFT($G195,3)<>"ДОК",$N195<>"")," — "&IFERROR(INDEX(МАТЕРИАЛЫ!$C$2:$C$9000,MATCH($N195,МАТЕРИАЛЫ!$L$2:$L$9000,0)),""),""))) -> Устройство коробов из ГКЛ до 600 мм шириной (для обшивки ригелей, балок колонн и т.д.) | Z195: =IF($B195="","",$B195&" · "&IFERROR(VLOOKUP($B195,спрРазделы,2,0),"")) -> Р3 · Внутренние строительные работы
A196: РАБ.Р3.2.001 | B196: Р3 | C196: 2 | D196: Монтаж стеклянных бескаркасных перегородок , стекло 10 мм, закаленное с фурнитурой цвета матовая нержавеющая сталь | E196: м2 | F196: 3065.04 | H196: 0 | I196: ТС ЕР | P196: =IF($L196="да",ROUND(N($M196)*$S196,2),"") | Q196: =IF($L196="да",ROUND(N($M196)*$T196,2),"") | R196: =IF($L196="да",N($P196)+N($Q196),"") | S196: =IF($A196="","",IF(AND(LEFT($G196,3)="ДОК",$N196<>""),IFERROR(INDEX(Документация!$E$2:$E$57,MATCH($N196,Документация!$F$2:$F$57,0)),0),N($F196))*(1-MEDIAN(0,N(ДисконтТендер),1))) -> 3065.04 | T196: =IF($A196="","",IF(AND(LEFT($G196,3)="ДОК",$N196<>""),0,IF(AND(LEFT($G196,3)<>"ДОК",$N196<>""),IFERROR(INDEX(МАТЕРИАЛЫ!$H$2:$H$9000,MATCH($N196,МАТЕРИАЛЫ!$L$2:$L$9000,0))*IF(INDEX(МАТЕРИАЛЫ!$I$2:$I$9000,MATCH($N196,МАТЕРИАЛЫ!$L$2:$L$9000,0))="USD",КурсUSD,IF(INDEX(МАТЕРИАЛЫ!$I$2:$I$9000,MATCH($N196,МАТЕРИАЛЫ!$L$2:$L$9000,0))="EUR",КурсEUR,IF(INDEX(МАТЕРИАЛЫ!$I$2:$I$9000,MATCH($N196,МАТЕРИАЛЫ!$L$2:$L$9000,0))="CNY",КурсCNY,1)))*(1+N($H196)/100),0),N($O196))*(1-MEDIAN(0,N(ДисконтТендер),1)))) -> 0 | U196: =IF($L196="да",MAX($U$1:$U195)+1,"") | V196: =IF($A196="","",$B196) -> Р3 | W196: =IF($U196="","",IF($U196=1,1,IF($V196<>IFERROR(INDEX($V$2:$V$1058,MATCH($U196-1,$U$2:$U$1058,0)),"~"),1,0))) | X196: =IF($U196="","",$U196+SUMIFS($W$2:$W$1058,$U$2:$U$1058,"<="&$U196)) | Y196: =IF($A196="","",IF(AND(LEFT($G196,3)="ДОК",$N196<>""),IFERROR(INDEX(Документация!$G$2:$G$57,MATCH($N196,Документация!$F$2:$F$57,0)),$D196),$D196&IF(AND(LEFT($G196,3)<>"ДОК",$N196<>"")," — "&IFERROR(INDEX(МАТЕРИАЛЫ!$C$2:$C$9000,MATCH($N196,МАТЕРИАЛЫ!$L$2:$L$9000,0)),""),""))) -> Монтаж стеклянных бескаркасных перегородок , стекло 10 мм, закаленное с фурнитурой цвета матовая нержавеющая сталь | Z196: =IF($B196="","",$B196&" · "&IFERROR(VLOOKUP($B196,спрРазделы,2,0),"")) -> Р3 · Внутренние строительные работы
A197: РАБ.Р3.2.002 | B197: Р3 | C197: 2 | D197: Устройство стеклянной перегородки в алюминиевом профиле по RAL. Стекло закаленное 6 мм. | E197: м2 | F197: 2210.33 | G197: ПЕРЕГ.СТ | H197: 5 | I197: ТС ЕР | P197: =IF($L197="да",ROUND(N($M197)*$S197,2),"") | Q197: =IF($L197="да",ROUND(N($M197)*$T197,2),"") | R197: =IF($L197="да",N($P197)+N($Q197),"") | S197: =IF($A197="","",IF(AND(LEFT($G197,3)="ДОК",$N197<>""),IFERROR(INDEX(Документация!$E$2:$E$57,MATCH($N197,Документация!$F$2:$F$57,0)),0),N($F197))*(1-MEDIAN(0,N(ДисконтТендер),1))) -> 2210.33 | T197: =IF($A197="","",IF(AND(LEFT($G197,3)="ДОК",$N197<>""),0,IF(AND(LEFT($G197,3)<>"ДОК",$N197<>""),IFERROR(INDEX(МАТЕРИАЛЫ!$H$2:$H$9000,MATCH($N197,МАТЕРИАЛЫ!$L$2:$L$9000,0))*IF(INDEX(МАТЕРИАЛЫ!$I$2:$I$9000,MATCH($N197,МАТЕРИАЛЫ!$L$2:$L$9000,0))="USD",КурсUSD,IF(INDEX(МАТЕРИАЛЫ!$I$2:$I$9000,MATCH($N197,МАТЕРИАЛЫ!$L$2:$L$9000,0))="EUR",КурсEUR,IF(INDEX(МАТЕРИАЛЫ!$I$2:$I$9000,MATCH($N197,МАТЕРИАЛЫ!$L$2:$L$9000,0))="CNY",КурсCNY,1)))*(1+N($H197)/100),0),N($O197))*(1-MEDIAN(0,N(ДисконтТендер),1)))) -> 0 | U197: =IF($L197="да",MAX($U$1:$U196)+1,"") | V197: =IF($A197="","",$B197) -> Р3 | W197: =IF($U197="","",IF($U197=1,1,IF($V197<>IFERROR(INDEX($V$2:$V$1058,MATCH($U197-1,$U$2:$U$1058,0)),"~"),1,0))) | X197: =IF($U197="","",$U197+SUMIFS($W$2:$W$1058,$U$2:$U$1058,"<="&$U197)) | Y197: =IF($A197="","",IF(AND(LEFT($G197,3)="ДОК",$N197<>""),IFERROR(INDEX(Документация!$G$2:$G$57,MATCH($N197,Документация!$F$2:$F$57,0)),$D197),$D197&IF(AND(LEFT($G197,3)<>"ДОК",$N197<>"")," — "&IFERROR(INDEX(МАТЕРИАЛЫ!$C$2:$C$9000,MATCH($N197,МАТЕРИАЛЫ!$L$2:$L$9000,0)),""),""))) -> Устройство стеклянной перегородки в алюминиевом профиле по RAL. Стекло закаленное 6 мм. | Z197: =IF($B197="","",$B197&" · "&IFERROR(VLOOKUP($B197,спрРазделы,2,0),"")) -> Р3 · Внутренние строительные работы
A198: РАБ.Р3.2.003 | B198: Р3 | C198: 2 | D198: Устройство стеклянной перегородки в пластиковом профиле. Стекло закаленное 6 мм. | E198: м2 | F198: 2197.32 | G198: ПЕРЕГ.СТ | H198: 5 | I198: ТС ЕР | P198: =IF($L198="да",ROUND(N($M198)*$S198,2),"") | Q198: =IF($L198="да",ROUND(N($M198)*$T198,2),"") | R198: =IF($L198="да",N($P198)+N($Q198),"") | S198: =IF($A198="","",IF(AND(LEFT($G198,3)="ДОК",$N198<>""),IFERROR(INDEX(Документация!$E$2:$E$57,MATCH($N198,Документация!$F$2:$F$57,0)),0),N($F198))*(1-MEDIAN(0,N(ДисконтТендер),1))) -> 2197.32 | T198: =IF($A198="","",IF(AND(LEFT($G198,3)="ДОК",$N198<>""),0,IF(AND(LEFT($G198,3)<>"ДОК",$N198<>""),IFERROR(INDEX(МАТЕРИАЛЫ!$H$2:$H$9000,MATCH($N198,МАТЕРИАЛЫ!$L$2:$L$9000,0))*IF(INDEX(МАТЕРИАЛЫ!$I$2:$I$9000,MATCH($N198,МАТЕРИАЛЫ!$L$2:$L$9000,0))="USD",КурсUSD,IF(INDEX(МАТЕРИАЛЫ!$I$2:$I$9000,MATCH($N198,МАТЕРИАЛЫ!$L$2:$L$9000,0))="EUR",КурсEUR,IF(INDEX(МАТЕРИАЛЫ!$I$2:$I$9000,MATCH($N198,МАТЕРИАЛЫ!$L$2:$L$9000,0))="CNY",КурсCNY,1)))*(1+N($H198)/100),0),N($O198))*(1-MEDIAN(0,N(ДисконтТендер),1)))) -> 0 | U198: =IF($L198="да",MAX($U$1:$U197)+1,"") | V198: =IF($A198="","",$B198) -> Р3 | W198: =IF($U198="","",IF($U198=1,1,IF($V198<>IFERROR(INDEX($V$2:$V$1058,MATCH($U198-1,$U$2:$U$1058,0)),"~"),1,0))) | X198: =IF($U198="","",$U198+SUMIFS($W$2:$W$1058,$U$2:$U$1058,"<="&$U198)) | Y198: =IF($A198="","",IF(AND(LEFT($G198,3)="ДОК",$N198<>""),IFERROR(INDEX(Документация!$G$2:$G$57,MATCH($N198,Документация!$F$2:$F$57,0)),$D198),$D198&IF(AND(LEFT($G198,3)<>"ДОК",$N198<>"")," — "&IFERROR(INDEX(МАТЕРИАЛЫ!$C$2:$C$9000,MATCH($N198,МАТЕРИАЛЫ!$L$2:$L$9000,0)),""),""))) -> Устройство стеклянной перегородки в пластиковом профиле. Стекло закаленное 6 мм. | Z198: =IF($B198="","",$B198&" · "&IFERROR(VLOOKUP($B198,спрРазделы,2,0),"")) -> Р3 · Внутренние строительные работы
A199: РАБ.Р3.2.004 | B199: Р3 | C199: 2 | D199: Оклейка стеклянных перегородок декоративной пленкой (перфорированной) с фоторисунком | E199: м2 | F199: 1650 | H199: 0 | I199: ТС ЕР | P199: =IF($L199="да",ROUND(N($M199)*$S199,2),"") | Q199: =IF($L199="да",ROUND(N($M199)*$T199,2),"") | R199: =IF($L199="да",N($P199)+N($Q199),"") | S199: =IF($A199="","",IF(AND(LEFT($G199,3)="ДОК",$N199<>""),IFERROR(INDEX(Документация!$E$2:$E$57,MATCH($N199,Документация!$F$2:$F$57,0)),0),N($F199))*(1-MEDIAN(0,N(ДисконтТендер),1))) -> 1650 | T199: =IF($A199="","",IF(AND(LEFT($G199,3)="ДОК",$N199<>""),0,IF(AND(LEFT($G199,3)<>"ДОК",$N199<>""),IFERROR(INDEX(МАТЕРИАЛЫ!$H$2:$H$9000,MATCH($N199,МАТЕРИАЛЫ!$L$2:$L$9000,0))*IF(INDEX(МАТЕРИАЛЫ!$I$2:$I$9000,MATCH($N199,МАТЕРИАЛЫ!$L$2:$L$9000,0))="USD",КурсUSD,IF(INDEX(МАТЕРИАЛЫ!$I$2:$I$9000,MATCH($N199,МАТЕРИАЛЫ!$L$2:$L$9000,0))="EUR",КурсEUR,IF(INDEX(МАТЕРИАЛЫ!$I$2:$I$9000,MATCH($N199,МАТЕРИАЛЫ!$L$2:$L$9000,0))="CNY",КурсCNY,1)))*(1+N($H199)/100),0),N($O199))*(1-MEDIAN(0,N(ДисконтТендер),1)))) -> 0 | U199: =IF($L199="да",MAX($U$1:$U198)+1,"") | V199: =IF($A199="","",$B199) -> Р3 | W199: =IF($U199="","",IF($U199=1,1,IF($V199<>IFERROR(INDEX($V$2:$V$1058,MATCH($U199-1,$U$2:$U$1058,0)),"~"),1,0))) | X199: =IF($U199="","",$U199+SUMIFS($W$2:$W$1058,$U$2:$U$1058,"<="&$U199)) | Y199: =IF($A199="","",IF(AND(LEFT($G199,3)="ДОК",$N199<>""),IFERROR(INDEX(Документация!$G$2:$G$57,MATCH($N199,Документация!$F$2:$F$57,0)),$D199),$D199&IF(AND(LEFT($G199,3)<>"ДОК",$N199<>"")," — "&IFERROR(INDEX(МАТЕРИАЛЫ!$C$2:$C$9000,MATCH($N199,МАТЕРИАЛЫ!$L$2:$L$9000,0)),""),""))) -> Оклейка стеклянных перегородок декоративной пленкой (перфорированной) с фоторисунком | Z199: =IF($B199="","",$B199&" · "&IFERROR(VLOOKUP($B199,спрРазделы,2,0),"")) -> Р3 · Внутренние строительные работы
A200: РАБ.Р3.2.005 | B200: Р3 | C200: 2 | D200: Монтаж стеклянной перегородки | E200: м2 | F200: 5637.6 | G200: ПЕРЕГ.СТ | H200: 5 | I200: ТС ЕР | P200: =IF($L200="да",ROUND(N($M200)*$S200,2),"") | Q200: =IF($L200="да",ROUND(N($M200)*$T200,2),"") | R200: =IF($L200="да",N($P200)+N($Q200),"") | S200: =IF($A200="","",IF(AND(LEFT($G200,3)="ДОК",$N200<>""),IFERROR(INDEX(Документация!$E$2:$E$57,MATCH($N200,Документация!$F$2:$F$57,0)),0),N($F200))*(1-MEDIAN(0,N(ДисконтТендер),1))) -> 5637.6 | T200: =IF($A200="","",IF(AND(LEFT($G200,3)="ДОК",$N200<>""),0,IF(AND(LEFT($G200,3)<>"ДОК",$N200<>""),IFERROR(INDEX(МАТЕРИАЛЫ!$H$2:$H$9000,MATCH($N200,МАТЕРИАЛЫ!$L$2:$L$9000,0))*IF(INDEX(МАТЕРИАЛЫ!$I$2:$I$9000,MATCH($N200,МАТЕРИАЛЫ!$L$2:$L$9000,0))="USD",КурсUSD,IF(INDEX(МАТЕРИАЛЫ!$I$2:$I$9000,MATCH($N200,МАТЕРИАЛЫ!$L$2:$L$9000,0))="EUR",КурсEUR,IF(INDEX(МАТЕРИАЛЫ!$I$2:$I$9000,MATCH($N200,МАТЕРИАЛЫ!$L$2:$L$9000,0))="CNY",КурсCNY,1)))*(1+N($H200)/100),0),N($O200))*(1-MEDIAN(0,N(ДисконтТендер),1)))) -> 0 | U200: =IF($L200="да",MAX($U$1:$U199)+1,"") | V200: =IF($A200="","",$B200) -> Р3 | W200: =IF($U200="","",IF($U200=1,1,IF($V200<>IFERROR(INDEX($V$2:$V$1058,MATCH($U200-1,$U$2:$U$1058,0)),"~"),1,0))) | X200: =IF($U200="","",$U200+SUMIFS($W$2:$W$1058,$U$2:$U$1058,"<="&$U200)) | Y200: =IF($A200="","",IF(AND(LEFT($G200,3)="ДОК",$N200<>""),IFERROR(INDEX(Документация!$G$2:$G$57,MATCH($N200,Документация!$F$2:$F$57,0)),$D200),$D200&IF(AND(LEFT($G200,3)<>"ДОК",$N200<>"")," — "&IFERROR(INDEX(МАТЕРИАЛЫ!$C$2:$C$9000,MATCH($N200,МАТЕРИАЛЫ!$L$2:$L$9000,0)),""),""))) -> Монтаж стеклянной перегородки | Z200: =IF($B200="","",$B200&" · "&IFERROR(VLOOKUP($B200,спрРазделы,2,0),"")) -> Р3 · Внутренние строительные работы
A201: РАБ.Р3.2.006 | B201: Р3 | C201: 2 | D201: Устройство фальшпола | E201: м2 | F201: 8143.2 | G201: ФАЛЬШПОЛ | H201: 5 | I201: ТС ЕР | P201: =IF($L201="да",ROUND(N($M201)*$S201,2),"") | Q201: =IF($L201="да",ROUND(N($M201)*$T201,2),"") | R201: =IF($L201="да",N($P201)+N($Q201),"") | S201: =IF($A201="","",IF(AND(LEFT($G201,3)="ДОК",$N201<>""),IFERROR(INDEX(Документация!$E$2:$E$57,MATCH($N201,Документация!$F$2:$F$57,0)),0),N($F201))*(1-MEDIAN(0,N(ДисконтТендер),1))) -> 8143.2 | T201: =IF($A201="","",IF(AND(LEFT($G201,3)="ДОК",$N201<>""),0,IF(AND(LEFT($G201,3)<>"ДОК",$N201<>""),IFERROR(INDEX(МАТЕРИАЛЫ!$H$2:$H$9000,MATCH($N201,МАТЕРИАЛЫ!$L$2:$L$9000,0))*IF(INDEX(МАТЕРИАЛЫ!$I$2:$I$9000,MATCH($N201,МАТЕРИАЛЫ!$L$2:$L$9000,0))="USD",КурсUSD,IF(INDEX(МАТЕРИАЛЫ!$I$2:$I$9000,MATCH($N201,МАТЕРИАЛЫ!$L$2:$L$9000,0))="EUR",КурсEUR,IF(INDEX(МАТЕРИАЛЫ!$I$2:$I$9000,MATCH($N201,МАТЕРИАЛЫ!$L$2:$L$9000,0))="CNY",КурсCNY,1)))*(1+N($H201)/100),0),N($O201))*(1-MEDIAN(0,N(ДисконтТендер),1)))) -> 0 | U201: =IF($L201="да",MAX($U$1:$U200)+1,"") | V201: =IF($A201="","",$B201) -> Р3 | W201: =IF($U201="","",IF($U201=1,1,IF($V201<>IFERROR(INDEX($V$2:$V$1058,MATCH($U201-1,$U$2:$U$1058,0)),"~"),1,0))) | X201: =IF($U201="","",$U201+SUMIFS($W$2:$W$1058,$U$2:$U$1058,"<="&$U201)) | Y201: =IF($A201="","",IF(AND(LEFT($G201,3)="ДОК",$N201<>""),IFERROR(INDEX(Документация!$G$2:$G$57,MATCH($N201,Документация!$F$2:$F$57,0)),$D201),$D201&IF(AND(LEFT($G201,3)<>"ДОК",$N201<>"")," — "&IFERROR(INDEX(МАТЕРИАЛЫ!$C$2:$C$9000,MATCH($N201,МАТЕРИАЛЫ!$L$2:$L$9000,0)),""),""))) -> Устройство фальшпола | Z201: =IF($B201="","",$B201&" · "&IFERROR(VLOOKUP($B201,спрРазделы,2,0),"")) -> Р3 · Внутренние строительные работы
A202: РАБ.Р3.2.007 | B202: Р3 | C202: 2 | D202: Замок для трансформируемой перегородки типа «Т-009 PSS» | E202: шт. | F202: 720.36 | G202: ПЕРЕГ.ТР | H202: 5 | I202: ТС ЕР | P202: =IF($L202="да",ROUND(N($M202)*$S202,2),"") | Q202: =IF($L202="да",ROUND(N($M202)*$T202,2),"") | R202: =IF($L202="да",N($P202)+N($Q202),"") | S202: =IF($A202="","",IF(AND(LEFT($G202,3)="ДОК",$N202<>""),IFERROR(INDEX(Документация!$E$2:$E$57,MATCH($N202,Документация!$F$2:$F$57,0)),0),N($F202))*(1-MEDIAN(0,N(ДисконтТендер),1))) -> 720.36 | T202: =IF($A202="","",IF(AND(LEFT($G202,3)="ДОК",$N202<>""),0,IF(AND(LEFT($G202,3)<>"ДОК",$N202<>""),IFERROR(INDEX(МАТЕРИАЛЫ!$H$2:$H$9000,MATCH($N202,МАТЕРИАЛЫ!$L$2:$L$9000,0))*IF(INDEX(МАТЕРИАЛЫ!$I$2:$I$9000,MATCH($N202,МАТЕРИАЛЫ!$L$2:$L$9000,0))="USD",КурсUSD,IF(INDEX(МАТЕРИАЛЫ!$I$2:$I$9000,MATCH($N202,МАТЕРИАЛЫ!$L$2:$L$9000,0))="EUR",КурсEUR,IF(INDEX(МАТЕРИАЛЫ!$I$2:$I$9000,MATCH($N202,МАТЕРИАЛЫ!$L$2:$L$9000,0))="CNY",КурсCNY,1)))*(1+N($H202)/100),0),N($O202))*(1-MEDIAN(0,N(ДисконтТендер),1)))) -> 0 | U202: =IF($L202="да",MAX($U$1:$U201)+1,"") | V202: =IF($A202="","",$B202) -> Р3 | W202: =IF($U202="","",IF($U202=1,1,IF($V202<>IFERROR(INDEX($V$2:$V$1058,MATCH($U202-1,$U$2:$U$1058,0)),"~"),1,0))) | X202: =IF($U202="","",$U202+SUMIFS($W$2:$W$1058,$U$2:$U$1058,"<="&$U202)) | Y202: =IF($A202="","",IF(AND(LEFT($G202,3)="ДОК",$N202<>""),IFERROR(INDEX(Документация!$G$2:$G$57,MATCH($N202,Документация!$F$2:$F$57,0)),$D202),$D202&IF(AND(LEFT($G202,3)<>"ДОК",$N202<>"")," — "&IFERROR(INDEX(МАТЕРИАЛЫ!$C$2:$C$9000,MATCH($N202,МАТЕРИАЛЫ!$L$2:$L$9000,0)),""),""))) -> Замок для трансформируемой перегородки типа «Т-009 PSS» | Z202: =IF($B202="","",$B202&" · "&IFERROR(VLOOKUP($B202,спрРазделы,2,0),"")) -> Р3 · Внутренние строительные работы
A203: РАБ.Р3.2.008 | B203: Р3 | C203: 2 | D203: Цилиндр с заверткой для нижнего замка | E203: шт. | F203: 250.56 | H203: 0 | I203: ТС ЕР | P203: =IF($L203="да",ROUND(N($M203)*$S203,2),"") | Q203: =IF($L203="да",ROUND(N($M203)*$T203,2),"") | R203: =IF($L203="да",N($P203)+N($Q203),"") | S203: =IF($A203="","",IF(AND(LEFT($G203,3)="ДОК",$N203<>""),IFERROR(INDEX(Документация!$E$2:$E$57,MATCH($N203,Документация!$F$2:$F$57,0)),0),N($F203))*(1-MEDIAN(0,N(ДисконтТендер),1))) -> 250.56 | T203: =IF($A203="","",IF(AND(LEFT($G203,3)="ДОК",$N203<>""),0,IF(AND(LEFT($G203,3)<>"ДОК",$N203<>""),IFERROR(INDEX(МАТЕРИАЛЫ!$H$2:$H$9000,MATCH($N203,МАТЕРИАЛЫ!$L$2:$L$9000,0))*IF(INDEX(МАТЕРИАЛЫ!$I$2:$I$9000,MATCH($N203,МАТЕРИАЛЫ!$L$2:$L$9000,0))="USD",КурсUSD,IF(INDEX(МАТЕРИАЛЫ!$I$2:$I$9000,MATCH($N203,МАТЕРИАЛЫ!$L$2:$L$9000,0))="EUR",КурсEUR,IF(INDEX(МАТЕРИАЛЫ!$I$2:$I$9000,MATCH($N203,МАТЕРИАЛЫ!$L$2:$L$9000,0))="CNY",КурсCNY,1)))*(1+N($H203)/100),0),N($O203))*(1-MEDIAN(0,N(ДисконтТендер),1)))) -> 0 | U203: =IF($L203="да",MAX($U$1:$U202)+1,"") | V203: =IF($A203="","",$B203) -> Р3 | W203: =IF($U203="","",IF($U203=1,1,IF($V203<>IFERROR(INDEX($V$2:$V$1058,MATCH($U203-1,$U$2:$U$1058,0)),"~"),1,0))) | X203: =IF($U203="","",$U203+SUMIFS($W$2:$W$1058,$U$2:$U$1058,"<="&$U203)) | Y203: =IF($A203="","",IF(AND(LEFT($G203,3)="ДОК",$N203<>""),IFERROR(INDEX(Документация!$G$2:$G$57,MATCH($N203,Документация!$F$2:$F$57,0)),$D203),$D203&IF(AND(LEFT($G203,3)<>"ДОК",$N203<>"")," — "&IFERROR(INDEX(МАТЕРИАЛЫ!$C$2:$C$9000,MATCH($N203,МАТЕРИАЛЫ!$L$2:$L$9000,0)),""),""))) -> Цилиндр с заверткой для нижнего замка | Z203: =IF($B203="","",$B203&" · "&IFERROR(VLOOKUP($B203,спрРазделы,2,0),"")) -> Р3 · Внутренние строительные работы
A204: РАБ.Р3.3.001 | B204: Р3 | C204: 3 | D204: Обработка стен, поврежденных грибком антисептическим раствором за 2 раза | E204: м2 | F204: 87 | H204: 0 | I204: ТС ЕР | P204: =IF($L204="да",ROUND(N($M204)*$S204,2),"") | Q204: =IF($L204="да",ROUND(N($M204)*$T204,2),"") | R204: =IF($L204="да",N($P204)+N($Q204),"") | S204: =IF($A204="","",IF(AND(LEFT($G204,3)="ДОК",$N204<>""),IFERROR(INDEX(Документация!$E$2:$E$57,MATCH($N204,Документация!$F$2:$F$57,0)),0),N($F204))*(1-MEDIAN(0,N(ДисконтТендер),1))) -> 87 | T204: =IF($A204="","",IF(AND(LEFT($G204,3)="ДОК",$N204<>""),0,IF(AND(LEFT($G204,3)<>"ДОК",$N204<>""),IFERROR(INDEX(МАТЕРИАЛЫ!$H$2:$H$9000,MATCH($N204,МАТЕРИАЛЫ!$L$2:$L$9000,0))*IF(INDEX(МАТЕРИАЛЫ!$I$2:$I$9000,MATCH($N204,МАТЕРИАЛЫ!$L$2:$L$9000,0))="USD",КурсUSD,IF(INDEX(МАТЕРИАЛЫ!$I$2:$I$9000,MATCH($N204,МАТЕРИАЛЫ!$L$2:$L$9000,0))="EUR",КурсEUR,IF(INDEX(МАТЕРИАЛЫ!$I$2:$I$9000,MATCH($N204,МАТЕРИАЛЫ!$L$2:$L$9000,0))="CNY",КурсCNY,1)))*(1+N($H204)/100),0),N($O204))*(1-MEDIAN(0,N(ДисконтТендер),1)))) -> 0 | U204: =IF($L204="да",MAX($U$1:$U203)+1,"") | V204: =IF($A204="","",$B204) -> Р3 | W204: =IF($U204="","",IF($U204=1,1,IF($V204<>IFERROR(INDEX($V$2:$V$1058,MATCH($U204-1,$U$2:$U$1058,0)),"~"),1,0))) | X204: =IF($U204="","",$U204+SUMIFS($W$2:$W$1058,$U$2:$U$1058,"<="&$U204)) | Y204: =IF($A204="","",IF(AND(LEFT($G204,3)="ДОК",$N204<>""),IFERROR(INDEX(Документация!$G$2:$G$57,MATCH($N204,Документация!$F$2:$F$57,0)),$D204),$D204&IF(AND(LEFT($G204,3)<>"ДОК",$N204<>"")," — "&IFERROR(INDEX(МАТЕРИАЛЫ!$C$2:$C$9000,MATCH($N204,МАТЕРИАЛЫ!$L$2:$L$9000,0)),""),""))) -> Обработка стен, поврежденных грибком антисептическим раствором за 2 раза | Z204: =IF($B204="","",$B204&" · "&IFERROR(VLOOKUP($B204,спрРазделы,2,0),"")) -> Р3 · Внутренние строительные работы
A205: РАБ.Р3.3.002 | B205: Р3 | C205: 3 | D205: Шпатлевка швов, саморезов и примыканий стен и перегородок из ГКЛ | E205: м2 | F205: 143.55 | H205: 0 | I205: ТС ЕР | P205: =IF($L205="да",ROUND(N($M205)*$S205,2),"") | Q205: =IF($L205="да",ROUND(N($M205)*$T205,2),"") | R205: =IF($L205="да",N($P205)+N($Q205),"") | S205: =IF($A205="","",IF(AND(LEFT($G205,3)="ДОК",$N205<>""),IFERROR(INDEX(Документация!$E$2:$E$57,MATCH($N205,Документация!$F$2:$F$57,0)),0),N($F205))*(1-MEDIAN(0,N(ДисконтТендер),1))) -> 143.55 | T205: =IF($A205="","",IF(AND(LEFT($G205,3)="ДОК",$N205<>""),0,IF(AND(LEFT($G205,3)<>"ДОК",$N205<>""),IFERROR(INDEX(МАТЕРИАЛЫ!$H$2:$H$9000,MATCH($N205,МАТЕРИАЛЫ!$L$2:$L$9000,0))*IF(INDEX(МАТЕРИАЛЫ!$I$2:$I$9000,MATCH($N205,МАТЕРИАЛЫ!$L$2:$L$9000,0))="USD",КурсUSD,IF(INDEX(МАТЕРИАЛЫ!$I$2:$I$9000,MATCH($N205,МАТЕРИАЛЫ!$L$2:$L$9000,0))="EUR",КурсEUR,IF(INDEX(МАТЕРИАЛЫ!$I$2:$I$9000,MATCH($N205,МАТЕРИАЛЫ!$L$2:$L$9000,0))="CNY",КурсCNY,1)))*(1+N($H205)/100),0),N($O205))*(1-MEDIAN(0,N(ДисконтТендер),1)))) -> 0 | U205: =IF($L205="да",MAX($U$1:$U204)+1,"") | V205: =IF($A205="","",$B205) -> Р3 | W205: =IF($U205="","",IF($U205=1,1,IF($V205<>IFERROR(INDEX($V$2:$V$1058,MATCH($U205-1,$U$2:$U$1058,0)),"~"),1,0))) | X205: =IF($U205="","",$U205+SUMIFS($W$2:$W$1058,$U$2:$U$1058,"<="&$U205)) | Y205: =IF($A205="","",IF(AND(LEFT($G205,3)="ДОК",$N205<>""),IFERROR(INDEX(Документация!$G$2:$G$57,MATCH($N205,Документация!$F$2:$F$57,0)),$D205),$D205&IF(AND(LEFT($G205,3)<>"ДОК",$N205<>"")," — "&IFERROR(INDEX(МАТЕРИАЛЫ!$C$2:$C$9000,MATCH($N205,МАТЕРИАЛЫ!$L$2:$L$9000,0)),""),""))) -> Шпатлевка швов, саморезов и примыканий стен и перегородок из ГКЛ | Z205: =IF($B205="","",$B205&" · "&IFERROR(VLOOKUP($B205,спрРазделы,2,0),"")) -> Р3 · Внутренние строительные работы
A206: РАБ.Р3.3.003 | B206: Р3 | C206: 3 | D206: Шпатлевка стен | E206: м2 | F206: 530.66 | H206: 0 | I206: ТС ЕР | P206: =IF($L206="да",ROUND(N($M206)*$S206,2),"") | Q206: =IF($L206="да",ROUND(N($M206)*$T206,2),"") | R206: =IF($L206="да",N($P206)+N($Q206),"") | S206: =IF($A206="","",IF(AND(LEFT($G206,3)="ДОК",$N206<>""),IFERROR(INDEX(Документация!$E$2:$E$57,MATCH($N206,Документация!$F$2:$F$57,0)),0),N($F206))*(1-MEDIAN(0,N(ДисконтТендер),1))) -> 530.66 | T206: =IF($A206="","",IF(AND(LEFT($G206,3)="ДОК",$N206<>""),0,IF(AND(LEFT($G206,3)<>"ДОК",$N206<>""),IFERROR(INDEX(МАТЕРИАЛЫ!$H$2:$H$9000,MATCH($N206,МАТЕРИАЛЫ!$L$2:$L$9000,0))*IF(INDEX(МАТЕРИАЛЫ!$I$2:$I$9000,MATCH($N206,МАТЕРИАЛЫ!$L$2:$L$9000,0))="USD",КурсUSD,IF(INDEX(МАТЕРИАЛЫ!$I$2:$I$9000,MATCH($N206,МАТЕРИАЛЫ!$L$2:$L$9000,0))="EUR",КурсEUR,IF(INDEX(МАТЕРИАЛЫ!$I$2:$I$9000,MATCH($N206,МАТЕРИАЛЫ!$L$2:$L$9000,0))="CNY",КурсCNY,1)))*(1+N($H206)/100),0),N($O206))*(1-MEDIAN(0,N(ДисконтТендер),1)))) -> 0 | U206: =IF($L206="да",MAX($U$1:$U205)+1,"") | V206: =IF($A206="","",$B206) -> Р3 | W206: =IF($U206="","",IF($U206=1,1,IF($V206<>IFERROR(INDEX($V$2:$V$1058,MATCH($U206-1,$U$2:$U$1058,0)),"~"),1,0))) | X206: =IF($U206="","",$U206+SUMIFS($W$2:$W$1058,$U$2:$U$1058,"<="&$U206)) | Y206: =IF($A206="","",IF(AND(LEFT($G206,3)="ДОК",$N206<>""),IFERROR(INDEX(Документация!$G$2:$G$57,MATCH($N206,Документация!$F$2:$F$57,0)),$D206),$D206&IF(AND(LEFT($G206,3)<>"ДОК",$N206<>"")," — "&IFERROR(INDEX(МАТЕРИАЛЫ!$C$2:$C$9000,MATCH($N206,МАТЕРИАЛЫ!$L$2:$L$9000,0)),""),""))) -> Шпатлевка стен | Z206: =IF($B206="","",$B206&" · "&IFERROR(VLOOKUP($B206,спрРазделы,2,0),"")) -> Р3 · Внутренние строительные работы
A207: РАБ.Р3.3.004 | B207: Р3 | C207: 3 | D207: Шпатлевка стен по стеклохолсту | E207: м2 | F207: 531.53 | H207: 0 | I207: ТС ЕР | P207: =IF($L207="да",ROUND(N($M207)*$S207,2),"") | Q207: =IF($L207="да",ROUND(N($M207)*$T207,2),"") | R207: =IF($L207="да",N($P207)+N($Q207),"") | S207: =IF($A207="","",IF(AND(LEFT($G207,3)="ДОК",$N207<>""),IFERROR(INDEX(Документация!$E$2:$E$57,MATCH($N207,Документация!$F$2:$F$57,0)),0),N($F207))*(1-MEDIAN(0,N(ДисконтТендер),1))) -> 531.53 | T207: =IF($A207="","",IF(AND(LEFT($G207,3)="ДОК",$N207<>""),0,IF(AND(LEFT($G207,3)<>"ДОК",$N207<>""),IFERROR(INDEX(МАТЕРИАЛЫ!$H$2:$H$9000,MATCH($N207,МАТЕРИАЛЫ!$L$2:$L$9000,0))*IF(INDEX(МАТЕРИАЛЫ!$I$2:$I$9000,MATCH($N207,МАТЕРИАЛЫ!$L$2:$L$9000,0))="USD",КурсUSD,IF(INDEX(МАТЕРИАЛЫ!$I$2:$I$9000,MATCH($N207,МАТЕРИАЛЫ!$L$2:$L$9000,0))="EUR",КурсEUR,IF(INDEX(МАТЕРИАЛЫ!$I$2:$I$9000,MATCH($N207,МАТЕРИАЛЫ!$L$2:$L$9000,0))="CNY",КурсCNY,1)))*(1+N($H207)/100),0),N($O207))*(1-MEDIAN(0,N(ДисконтТендер),1)))) -> 0 | U207: =IF($L207="да",MAX($U$1:$U206)+1,"") | V207: =IF($A207="","",$B207) -> Р3 | W207: =IF($U207="","",IF($U207=1,1,IF($V207<>IFERROR(INDEX($V$2:$V$1058,MATCH($U207-1,$U$2:$U$1058,0)),"~"),1,0))) | X207: =IF($U207="","",$U207+SUMIFS($W$2:$W$1058,$U$2:$U$1058,"<="&$U207)) | Y207: =IF($A207="","",IF(AND(LEFT($G207,3)="ДОК",$N207<>""),IFERROR(INDEX(Документация!$G$2:$G$57,MATCH($N207,Документация!$F$2:$F$57,0)),$D207),$D207&IF(AND(LEFT($G207,3)<>"ДОК",$N207<>"")," — "&IFERROR(INDEX(МАТЕРИАЛЫ!$C$2:$C$9000,MATCH($N207,МАТЕРИАЛЫ!$L$2:$L$9000,0)),""),""))) -> Шпатлевка стен по стеклохолсту | Z207: =IF($B207="","",$B207&" · "&IFERROR(VLOOKUP($B207,спрРазделы,2,0),"")) -> Р3 · Внутренние строительные работы
A208: РАБ.Р3.3.005 | B208: Р3 | C208: 3 | D208: Сплошное выравние стен составами "Ветонит" толщиной до 10 мм | E208: м2 | F208: 532.4 | H208: 0 | I208: ТС ЕР | P208: =IF($L208="да",ROUND(N($M208)*$S208,2),"") | Q208: =IF($L208="да",ROUND(N($M208)*$T208,2),"") | R208: =IF($L208="да",N($P208)+N($Q208),"") | S208: =IF($A208="","",IF(AND(LEFT($G208,3)="ДОК",$N208<>""),IFERROR(INDEX(Документация!$E$2:$E$57,MATCH($N208,Документация!$F$2:$F$57,0)),0),N($F208))*(1-MEDIAN(0,N(ДисконтТендер),1))) -> 532.4 | T208: =IF($A208="","",IF(AND(LEFT($G208,3)="ДОК",$N208<>""),0,IF(AND(LEFT($G208,3)<>"ДОК",$N208<>""),IFERROR(INDEX(МАТЕРИАЛЫ!$H$2:$H$9000,MATCH($N208,МАТЕРИАЛЫ!$L$2:$L$9000,0))*IF(INDEX(МАТЕРИАЛЫ!$I$2:$I$9000,MATCH($N208,МАТЕРИАЛЫ!$L$2:$L$9000,0))="USD",КурсUSD,IF(INDEX(МАТЕРИАЛЫ!$I$2:$I$9000,MATCH($N208,МАТЕРИАЛЫ!$L$2:$L$9000,0))="EUR",КурсEUR,IF(INDEX(МАТЕРИАЛЫ!$I$2:$I$9000,MATCH($N208,МАТЕРИАЛЫ!$L$2:$L$9000,0))="CNY",КурсCNY,1)))*(1+N($H208)/100),0),N($O208))*(1-MEDIAN(0,N(ДисконтТендер),1)))) -> 0 | U208: =IF($L208="да",MAX($U$1:$U207)+1,"") | V208: =IF($A208="","",$B208) -> Р3 | W208: =IF($U208="","",IF($U208=1,1,IF($V208<>IFERROR(INDEX($V$2:$V$1058,MATCH($U208-1,$U$2:$U$1058,0)),"~"),1,0))) | X208: =IF($U208="","",$U208+SUMIFS($W$2:$W$1058,$U$2:$U$1058,"<="&$U208)) | Y208: =IF($A208="","",IF(AND(LEFT($G208,3)="ДОК",$N208<>""),IFERROR(INDEX(Документация!$G$2:$G$57,MATCH($N208,Документация!$F$2:$F$57,0)),$D208),$D208&IF(AND(LEFT($G208,3)<>"ДОК",$N208<>"")," — "&IFERROR(INDEX(МАТЕРИАЛЫ!$C$2:$C$9000,MATCH($N208,МАТЕРИАЛЫ!$L$2:$L$9000,0)),""),""))) -> Сплошное выравние стен составами "Ветонит" толщиной до 10 мм | Z208: =IF($B208="","",$B208&" · "&IFERROR(VLOOKUP($B208,спрРазделы,2,0),"")) -> Р3 · Внутренние строительные работы
A209: РАБ.Р3.3.006 | B209: Р3 | C209: 3 | D209: Грунтовка поверхности стен и перегородок за 2 раза | E209: м2 | F209: 75.2 | H209: 0 | I209: ТС ЕР | P209: =IF($L209="да",ROUND(N($M209)*$S209,2),"") | Q209: =IF($L209="да",ROUND(N($M209)*$T209,2),"") | R209: =IF($L209="да",N($P209)+N($Q209),"") | S209: =IF($A209="","",IF(AND(LEFT($G209,3)="ДОК",$N209<>""),IFERROR(INDEX(Документация!$E$2:$E$57,MATCH($N209,Документация!$F$2:$F$57,0)),0),N($F209))*(1-MEDIAN(0,N(ДисконтТендер),1))) -> 75.2 | T209: =IF($A209="","",IF(AND(LEFT($G209,3)="ДОК",$N209<>""),0,IF(AND(LEFT($G209,3)<>"ДОК",$N209<>""),IFERROR(INDEX(МАТЕРИАЛЫ!$H$2:$H$9000,MATCH($N209,МАТЕРИАЛЫ!$L$2:$L$9000,0))*IF(INDEX(МАТЕРИАЛЫ!$I$2:$I$9000,MATCH($N209,МАТЕРИАЛЫ!$L$2:$L$9000,0))="USD",КурсUSD,IF(INDEX(МАТЕРИАЛЫ!$I$2:$I$9000,MATCH($N209,МАТЕРИАЛЫ!$L$2:$L$9000,0))="EUR",КурсEUR,IF(INDEX(МАТЕРИАЛЫ!$I$2:$I$9000,MATCH($N209,МАТЕРИАЛЫ!$L$2:$L$9000,0))="CNY",КурсCNY,1)))*(1+N($H209)/100),0),N($O209))*(1-MEDIAN(0,N(ДисконтТендер),1)))) -> 0 | U209: =IF($L209="да",MAX($U$1:$U208)+1,"") | V209: =IF($A209="","",$B209) -> Р3 | W209: =IF($U209="","",IF($U209=1,1,IF($V209<>IFERROR(INDEX($V$2:$V$1058,MATCH($U209-1,$U$2:$U$1058,0)),"~"),1,0))) | X209: =IF($U209="","",$U209+SUMIFS($W$2:$W$1058,$U$2:$U$1058,"<="&$U209)) | Y209: =IF($A209="","",IF(AND(LEFT($G209,3)="ДОК",$N209<>""),IFERROR(INDEX(Документация!$G$2:$G$57,MATCH($N209,Документация!$F$2:$F$57,0)),$D209),$D209&IF(AND(LEFT($G209,3)<>"ДОК",$N209<>"")," — "&IFERROR(INDEX(МАТЕРИАЛЫ!$C$2:$C$9000,MATCH($N209,МАТЕРИАЛЫ!$L$2:$L$9000,0)),""),""))) -> Грунтовка поверхности стен и перегородок за 2 раза | Z209: =IF($B209="","",$B209&" · "&IFERROR(VLOOKUP($B209,спрРазделы,2,0),"")) -> Р3 · Внутренние строительные работы
A210: РАБ.Р3.3.007 | B210: Р3 | C210: 3 | D210: Окраска стен за 2 раза краской Tikkurila EURO 7 (колерованная) | E210: м2 | F210: 350 | G210: КРАСКА | H210: 5 | I210: ТС ЕР | P210: =IF($L210="да",ROUND(N($M210)*$S210,2),"") | Q210: =IF($L210="да",ROUND(N($M210)*$T210,2),"") | R210: =IF($L210="да",N($P210)+N($Q210),"") | S210: =IF($A210="","",IF(AND(LEFT($G210,3)="ДОК",$N210<>""),IFERROR(INDEX(Документация!$E$2:$E$57,MATCH($N210,Документация!$F$2:$F$57,0)),0),N($F210))*(1-MEDIAN(0,N(ДисконтТендер),1))) -> 350 | T210: =IF($A210="","",IF(AND(LEFT($G210,3)="ДОК",$N210<>""),0,IF(AND(LEFT($G210,3)<>"ДОК",$N210<>""),IFERROR(INDEX(МАТЕРИАЛЫ!$H$2:$H$9000,MATCH($N210,МАТЕРИАЛЫ!$L$2:$L$9000,0))*IF(INDEX(МАТЕРИАЛЫ!$I$2:$I$9000,MATCH($N210,МАТЕРИАЛЫ!$L$2:$L$9000,0))="USD",КурсUSD,IF(INDEX(МАТЕРИАЛЫ!$I$2:$I$9000,MATCH($N210,МАТЕРИАЛЫ!$L$2:$L$9000,0))="EUR",КурсEUR,IF(INDEX(МАТЕРИАЛЫ!$I$2:$I$9000,MATCH($N210,МАТЕРИАЛЫ!$L$2:$L$9000,0))="CNY",КурсCNY,1)))*(1+N($H210)/100),0),N($O210))*(1-MEDIAN(0,N(ДисконтТендер),1)))) -> 0 | U210: =IF($L210="да",MAX($U$1:$U209)+1,"") | V210: =IF($A210="","",$B210) -> Р3 | W210: =IF($U210="","",IF($U210=1,1,IF($V210<>IFERROR(INDEX($V$2:$V$1058,MATCH($U210-1,$U$2:$U$1058,0)),"~"),1,0))) | X210: =IF($U210="","",$U210+SUMIFS($W$2:$W$1058,$U$2:$U$1058,"<="&$U210)) | Y210: =IF($A210="","",IF(AND(LEFT($G210,3)="ДОК",$N210<>""),IFERROR(INDEX(Документация!$G$2:$G$57,MATCH($N210,Документация!$F$2:$F$57,0)),$D210),$D210&IF(AND(LEFT($G210,3)<>"ДОК",$N210<>"")," — "&IFERROR(INDEX(МАТЕРИАЛЫ!$C$2:$C$9000,MATCH($N210,МАТЕРИАЛЫ!$L$2:$L$9000,0)),""),""))) -> Окраска стен за 2 раза краской Tikkurila EURO 7 (колерованная) | Z210: =IF($B210="","",$B210&" · "&IFERROR(VLOOKUP($B210,спрРазделы,2,0),"")) -> Р3 · Внутренние строительные работы
A211: РАБ.Р3.3.008 | B211: Р3 | C211: 3 | D211: Оклейка стен стеклообоями типа "Паутинка" (нефактурными) | E211: м2 | F211: 220 | G211: ОБОИ | H211: 5 | I211: ТС ЕР | P211: =IF($L211="да",ROUND(N($M211)*$S211,2),"") | Q211: =IF($L211="да",ROUND(N($M211)*$T211,2),"") | R211: =IF($L211="да",N($P211)+N($Q211),"") | S211: =IF($A211="","",IF(AND(LEFT($G211,3)="ДОК",$N211<>""),IFERROR(INDEX(Документация!$E$2:$E$57,MATCH($N211,Документация!$F$2:$F$57,0)),0),N($F211))*(1-MEDIAN(0,N(ДисконтТендер),1))) -> 220 | T211: =IF($A211="","",IF(AND(LEFT($G211,3)="ДОК",$N211<>""),0,IF(AND(LEFT($G211,3)<>"ДОК",$N211<>""),IFERROR(INDEX(МАТЕРИАЛЫ!$H$2:$H$9000,MATCH($N211,МАТЕРИАЛЫ!$L$2:$L$9000,0))*IF(INDEX(МАТЕРИАЛЫ!$I$2:$I$9000,MATCH($N211,МАТЕРИАЛЫ!$L$2:$L$9000,0))="USD",КурсUSD,IF(INDEX(МАТЕРИАЛЫ!$I$2:$I$9000,MATCH($N211,МАТЕРИАЛЫ!$L$2:$L$9000,0))="EUR",КурсEUR,IF(INDEX(МАТЕРИАЛЫ!$I$2:$I$9000,MATCH($N211,МАТЕРИАЛЫ!$L$2:$L$9000,0))="CNY",КурсCNY,1)))*(1+N($H211)/100),0),N($O211))*(1-MEDIAN(0,N(ДисконтТендер),1)))) -> 0 | U211: =IF($L211="да",MAX($U$1:$U210)+1,"") | V211: =IF($A211="","",$B211) -> Р3 | W211: =IF($U211="","",IF($U211=1,1,IF($V211<>IFERROR(INDEX($V$2:$V$1058,MATCH($U211-1,$U$2:$U$1058,0)),"~"),1,0))) | X211: =IF($U211="","",$U211+SUMIFS($W$2:$W$1058,$U$2:$U$1058,"<="&$U211)) | Y211: =IF($A211="","",IF(AND(LEFT($G211,3)="ДОК",$N211<>""),IFERROR(INDEX(Документация!$G$2:$G$57,MATCH($N211,Документация!$F$2:$F$57,0)),$D211),$D211&IF(AND(LEFT($G211,3)<>"ДОК",$N211<>"")," — "&IFERROR(INDEX(МАТЕРИАЛЫ!$C$2:$C$9000,MATCH($N211,МАТЕРИАЛЫ!$L$2:$L$9000,0)),""),""))) -> Оклейка стен стеклообоями типа "Паутинка" (нефактурными) | Z211: =IF($B211="","",$B211&" · "&IFERROR(VLOOKUP($B211,спрРазделы,2,0),"")) -> Р3 · Внутренние строительные работы
A212: РАБ.Р3.3.009 | B212: Р3 | C212: 3 | D212: Ремонт штукатурки стен с расшивкой швов, отдельными местами до 1 м.кв. | E212: м2 | F212: 977.08 | H212: 0 | I212: ТС ЕР | P212: =IF($L212="да",ROUND(N($M212)*$S212,2),"") | Q212: =IF($L212="да",ROUND(N($M212)*$T212,2),"") | R212: =IF($L212="да",N($P212)+N($Q212),"") | S212: =IF($A212="","",IF(AND(LEFT($G212,3)="ДОК",$N212<>""),IFERROR(INDEX(Документация!$E$2:$E$57,MATCH($N212,Документация!$F$2:$F$57,0)),0),N($F212))*(1-MEDIAN(0,N(ДисконтТендер),1))) -> 977.08 | T212: =IF($A212="","",IF(AND(LEFT($G212,3)="ДОК",$N212<>""),0,IF(AND(LEFT($G212,3)<>"ДОК",$N212<>""),IFERROR(INDEX(МАТЕРИАЛЫ!$H$2:$H$9000,MATCH($N212,МАТЕРИАЛЫ!$L$2:$L$9000,0))*IF(INDEX(МАТЕРИАЛЫ!$I$2:$I$9000,MATCH($N212,МАТЕРИАЛЫ!$L$2:$L$9000,0))="USD",КурсUSD,IF(INDEX(МАТЕРИАЛЫ!$I$2:$I$9000,MATCH($N212,МАТЕРИАЛЫ!$L$2:$L$9000,0))="EUR",КурсEUR,IF(INDEX(МАТЕРИАЛЫ!$I$2:$I$9000,MATCH($N212,МАТЕРИАЛЫ!$L$2:$L$9000,0))="CNY",КурсCNY,1)))*(1+N($H212)/100),0),N($O212))*(1-MEDIAN(0,N(ДисконтТендер),1)))) -> 0 | U212: =IF($L212="да",MAX($U$1:$U211)+1,"") | V212: =IF($A212="","",$B212) -> Р3 | W212: =IF($U212="","",IF($U212=1,1,IF($V212<>IFERROR(INDEX($V$2:$V$1058,MATCH($U212-1,$U$2:$U$1058,0)),"~"),1,0))) | X212: =IF($U212="","",$U212+SUMIFS($W$2:$W$1058,$U$2:$U$1058,"<="&$U212)) | Y212: =IF($A212="","",IF(AND(LEFT($G212,3)="ДОК",$N212<>""),IFERROR(INDEX(Документация!$G$2:$G$57,MATCH($N212,Документация!$F$2:$F$57,0)),$D212),$D212&IF(AND(LEFT($G212,3)<>"ДОК",$N212<>"")," — "&IFERROR(INDEX(МАТЕРИАЛЫ!$C$2:$C$9000,MATCH($N212,МАТЕРИАЛЫ!$L$2:$L$9000,0)),""),""))) -> Ремонт штукатурки стен с расшивкой швов, отдельными местами до 1 м.кв. | Z212: =IF($B212="","",$B212&" · "&IFERROR(VLOOKUP($B212,спрРазделы,2,0),"")) -> Р3 · Внутренние строительные работы
A213: РАБ.Р3.3.010 | B213: Р3 | C213: 3 | D213: Облицовка стен керамической плиткой с затиркой швов. | E213: м2 | F213: 2307.71 | G213: СТЕН.ПЛ | H213: 5 | I213: ТС ЕР | P213: =IF($L213="да",ROUND(N($M213)*$S213,2),"") | Q213: =IF($L213="да",ROUND(N($M213)*$T213,2),"") | R213: =IF($L213="да",N($P213)+N($Q213),"") | S213: =IF($A213="","",IF(AND(LEFT($G213,3)="ДОК",$N213<>""),IFERROR(INDEX(Документация!$E$2:$E$57,MATCH($N213,Документация!$F$2:$F$57,0)),0),N($F213))*(1-MEDIAN(0,N(ДисконтТендер),1))) -> 2307.71 | T213: =IF($A213="","",IF(AND(LEFT($G213,3)="ДОК",$N213<>""),0,IF(AND(LEFT($G213,3)<>"ДОК",$N213<>""),IFERROR(INDEX(МАТЕРИАЛЫ!$H$2:$H$9000,MATCH($N213,МАТЕРИАЛЫ!$L$2:$L$9000,0))*IF(INDEX(МАТЕРИАЛЫ!$I$2:$I$9000,MATCH($N213,МАТЕРИАЛЫ!$L$2:$L$9000,0))="USD",КурсUSD,IF(INDEX(МАТЕРИАЛЫ!$I$2:$I$9000,MATCH($N213,МАТЕРИАЛЫ!$L$2:$L$9000,0))="EUR",КурсEUR,IF(INDEX(МАТЕРИАЛЫ!$I$2:$I$9000,MATCH($N213,МАТЕРИАЛЫ!$L$2:$L$9000,0))="CNY",КурсCNY,1)))*(1+N($H213)/100),0),N($O213))*(1-MEDIAN(0,N(ДисконтТендер),1)))) -> 0 | U213: =IF($L213="да",MAX($U$1:$U212)+1,"") | V213: =IF($A213="","",$B213) -> Р3 | W213: =IF($U213="","",IF($U213=1,1,IF($V213<>IFERROR(INDEX($V$2:$V$1058,MATCH($U213-1,$U$2:$U$1058,0)),"~"),1,0))) | X213: =IF($U213="","",$U213+SUMIFS($W$2:$W$1058,$U$2:$U$1058,"<="&$U213)) | Y213: =IF($A213="","",IF(AND(LEFT($G213,3)="ДОК",$N213<>""),IFERROR(INDEX(Документация!$G$2:$G$57,MATCH($N213,Документация!$F$2:$F$57,0)),$D213),$D213&IF(AND(LEFT($G213,3)<>"ДОК",$N213<>"")," — "&IFERROR(INDEX(МАТЕРИАЛЫ!$C$2:$C$9000,MATCH($N213,МАТЕРИАЛЫ!$L$2:$L$9000,0)),""),""))) -> Облицовка стен керамической плиткой с затиркой швов. | Z213: =IF($B213="","",$B213&" · "&IFERROR(VLOOKUP($B213,спрРазделы,2,0),"")) -> Р3 · Внутренние строительные работы
A214: РАБ.Р3.3.011 | B214: Р3 | C214: 3 | D214: Облицовка стен керамической плиткой | E214: м2 | F214: 3048.05 | G214: СТЕН.ПЛ | H214: 5 | I214: ТС ЕР | P214: =IF($L214="да",ROUND(N($M214)*$S214,2),"") | Q214: =IF($L214="да",ROUND(N($M214)*$T214,2),"") | R214: =IF($L214="да",N($P214)+N($Q214),"") | S214: =IF($A214="","",IF(AND(LEFT($G214,3)="ДОК",$N214<>""),IFERROR(INDEX(Документация!$E$2:$E$57,MATCH($N214,Документация!$F$2:$F$57,0)),0),N($F214))*(1-MEDIAN(0,N(ДисконтТендер),1))) -> 3048.05 | T214: =IF($A214="","",IF(AND(LEFT($G214,3)="ДОК",$N214<>""),0,IF(AND(LEFT($G214,3)<>"ДОК",$N214<>""),IFERROR(INDEX(МАТЕРИАЛЫ!$H$2:$H$9000,MATCH($N214,МАТЕРИАЛЫ!$L$2:$L$9000,0))*IF(INDEX(МАТЕРИАЛЫ!$I$2:$I$9000,MATCH($N214,МАТЕРИАЛЫ!$L$2:$L$9000,0))="USD",КурсUSD,IF(INDEX(МАТЕРИАЛЫ!$I$2:$I$9000,MATCH($N214,МАТЕРИАЛЫ!$L$2:$L$9000,0))="EUR",КурсEUR,IF(INDEX(МАТЕРИАЛЫ!$I$2:$I$9000,MATCH($N214,МАТЕРИАЛЫ!$L$2:$L$9000,0))="CNY",КурсCNY,1)))*(1+N($H214)/100),0),N($O214))*(1-MEDIAN(0,N(ДисконтТендер),1)))) -> 0 | U214: =IF($L214="да",MAX($U$1:$U213)+1,"") | V214: =IF($A214="","",$B214) -> Р3 | W214: =IF($U214="","",IF($U214=1,1,IF($V214<>IFERROR(INDEX($V$2:$V$1058,MATCH($U214-1,$U$2:$U$1058,0)),"~"),1,0))) | X214: =IF($U214="","",$U214+SUMIFS($W$2:$W$1058,$U$2:$U$1058,"<="&$U214)) | Y214: =IF($A214="","",IF(AND(LEFT($G214,3)="ДОК",$N214<>""),IFERROR(INDEX(Документация!$G$2:$G$57,MATCH($N214,Документация!$F$2:$F$57,0)),$D214),$D214&IF(AND(LEFT($G214,3)<>"ДОК",$N214<>"")," — "&IFERROR(INDEX(МАТЕРИАЛЫ!$C$2:$C$9000,MATCH($N214,МАТЕРИАЛЫ!$L$2:$L$9000,0)),""),""))) -> Облицовка стен керамической плиткой | Z214: =IF($B214="","",$B214&" · "&IFERROR(VLOOKUP($B214,спрРазделы,2,0),"")) -> Р3 · Внутренние строительные работы
A215: РАБ.Р3.3.012 | B215: Р3 | C215: 3 | D215: Бордюр 500*15 "Szklana T40" коллекциии "Oxford" " Ctramica Konskie" с затиркой швов. | E215: шт. | F215: 339.3 | H215: 0 | I215: ТС ЕР | P215: =IF($L215="да",ROUND(N($M215)*$S215,2),"") | Q215: =IF($L215="да",ROUND(N($M215)*$T215,2),"") | R215: =IF($L215="да",N($P215)+N($Q215),"") | S215: =IF($A215="","",IF(AND(LEFT($G215,3)="ДОК",$N215<>""),IFERROR(INDEX(Документация!$E$2:$E$57,MATCH($N215,Документация!$F$2:$F$57,0)),0),N($F215))*(1-MEDIAN(0,N(ДисконтТендер),1))) -> 339.3 | T215: =IF($A215="","",IF(AND(LEFT($G215,3)="ДОК",$N215<>""),0,IF(AND(LEFT($G215,3)<>"ДОК",$N215<>""),IFERROR(INDEX(МАТЕРИАЛЫ!$H$2:$H$9000,MATCH($N215,МАТЕРИАЛЫ!$L$2:$L$9000,0))*IF(INDEX(МАТЕРИАЛЫ!$I$2:$I$9000,MATCH($N215,МАТЕРИАЛЫ!$L$2:$L$9000,0))="USD",КурсUSD,IF(INDEX(МАТЕРИАЛЫ!$I$2:$I$9000,MATCH($N215,МАТЕРИАЛЫ!$L$2:$L$9000,0))="EUR",КурсEUR,IF(INDEX(МАТЕРИАЛЫ!$I$2:$I$9000,MATCH($N215,МАТЕРИАЛЫ!$L$2:$L$9000,0))="CNY",КурсCNY,1)))*(1+N($H215)/100),0),N($O215))*(1-MEDIAN(0,N(ДисконтТендер),1)))) -> 0 | U215: =IF($L215="да",MAX($U$1:$U214)+1,"") | V215: =IF($A215="","",$B215) -> Р3 | W215: =IF($U215="","",IF($U215=1,1,IF($V215<>IFERROR(INDEX($V$2:$V$1058,MATCH($U215-1,$U$2:$U$1058,0)),"~"),1,0))) | X215: =IF($U215="","",$U215+SUMIFS($W$2:$W$1058,$U$2:$U$1058,"<="&$U215)) | Y215: =IF($A215="","",IF(AND(LEFT($G215,3)="ДОК",$N215<>""),IFERROR(INDEX(Документация!$G$2:$G$57,MATCH($N215,Документация!$F$2:$F$57,0)),$D215),$D215&IF(AND(LEFT($G215,3)<>"ДОК",$N215<>"")," — "&IFERROR(INDEX(МАТЕРИАЛЫ!$C$2:$C$9000,MATCH($N215,МАТЕРИАЛЫ!$L$2:$L$9000,0)),""),""))) -> Бордюр 500*15 "Szklana T40" коллекциии "Oxford" " Ctramica Konskie" с затиркой швов. | Z215: =IF($B215="","",$B215&" · "&IFERROR(VLOOKUP($B215,спрРазделы,2,0),"")) -> Р3 · Внутренние строительные работы
A216: РАБ.Р3.3.013 | B216: Р3 | C216: 3 | D216: Установка пластиковых уголков на наружные углы колонн и стен | E216: м.п. | F216: 297.58 | H216: 0 | I216: ТС ЕР | P216: =IF($L216="да",ROUND(N($M216)*$S216,2),"") | Q216: =IF($L216="да",ROUND(N($M216)*$T216,2),"") | R216: =IF($L216="да",N($P216)+N($Q216),"") | S216: =IF($A216="","",IF(AND(LEFT($G216,3)="ДОК",$N216<>""),IFERROR(INDEX(Документация!$E$2:$E$57,MATCH($N216,Документация!$F$2:$F$57,0)),0),N($F216))*(1-MEDIAN(0,N(ДисконтТендер),1))) -> 297.58 | T216: =IF($A216="","",IF(AND(LEFT($G216,3)="ДОК",$N216<>""),0,IF(AND(LEFT($G216,3)<>"ДОК",$N216<>""),IFERROR(INDEX(МАТЕРИАЛЫ!$H$2:$H$9000,MATCH($N216,МАТЕРИАЛЫ!$L$2:$L$9000,0))*IF(INDEX(МАТЕРИАЛЫ!$I$2:$I$9000,MATCH($N216,МАТЕРИАЛЫ!$L$2:$L$9000,0))="USD",КурсUSD,IF(INDEX(МАТЕРИАЛЫ!$I$2:$I$9000,MATCH($N216,МАТЕРИАЛЫ!$L$2:$L$9000,0))="EUR",КурсEUR,IF(INDEX(МАТЕРИАЛЫ!$I$2:$I$9000,MATCH($N216,МАТЕРИАЛЫ!$L$2:$L$9000,0))="CNY",КурсCNY,1)))*(1+N($H216)/100),0),N($O216))*(1-MEDIAN(0,N(ДисконтТендер),1)))) -> 0 | U216: =IF($L216="да",MAX($U$1:$U215)+1,"") | V216: =IF($A216="","",$B216) -> Р3 | W216: =IF($U216="","",IF($U216=1,1,IF($V216<>IFERROR(INDEX($V$2:$V$1058,MATCH($U216-1,$U$2:$U$1058,0)),"~"),1,0))) | X216: =IF($U216="","",$U216+SUMIFS($W$2:$W$1058,$U$2:$U$1058,"<="&$U216)) | Y216: =IF($A216="","",IF(AND(LEFT($G216,3)="ДОК",$N216<>""),IFERROR(INDEX(Документация!$G$2:$G$57,MATCH($N216,Документация!$F$2:$F$57,0)),$D216),$D216&IF(AND(LEFT($G216,3)<>"ДОК",$N216<>"")," — "&IFERROR(INDEX(МАТЕРИАЛЫ!$C$2:$C$9000,MATCH($N216,МАТЕРИАЛЫ!$L$2:$L$9000,0)),""),""))) -> Установка пластиковых уголков на наружные углы колонн и стен | Z216: =IF($B216="","",$B216&" · "&IFERROR(VLOOKUP($B216,спрРазделы,2,0),"")) -> Р3 · Внутренние строительные работы
A217: РАБ.Р3.3.014 | B217: Р3 | C217: 3 | D217: Штукатурка поверхности | E217: м2 | F217: 2926 | H217: 0 | I217: ТС ЕР | P217: =IF($L217="да",ROUND(N($M217)*$S217,2),"") | Q217: =IF($L217="да",ROUND(N($M217)*$T217,2),"") | R217: =IF($L217="да",N($P217)+N($Q217),"") | S217: =IF($A217="","",IF(AND(LEFT($G217,3)="ДОК",$N217<>""),IFERROR(INDEX(Документация!$E$2:$E$57,MATCH($N217,Документация!$F$2:$F$57,0)),0),N($F217))*(1-MEDIAN(0,N(ДисконтТендер),1))) -> 2926 | T217: =IF($A217="","",IF(AND(LEFT($G217,3)="ДОК",$N217<>""),0,IF(AND(LEFT($G217,3)<>"ДОК",$N217<>""),IFERROR(INDEX(МАТЕРИАЛЫ!$H$2:$H$9000,MATCH($N217,МАТЕРИАЛЫ!$L$2:$L$9000,0))*IF(INDEX(МАТЕРИАЛЫ!$I$2:$I$9000,MATCH($N217,МАТЕРИАЛЫ!$L$2:$L$9000,0))="USD",КурсUSD,IF(INDEX(МАТЕРИАЛЫ!$I$2:$I$9000,MATCH($N217,МАТЕРИАЛЫ!$L$2:$L$9000,0))="EUR",КурсEUR,IF(INDEX(МАТЕРИАЛЫ!$I$2:$I$9000,MATCH($N217,МАТЕРИАЛЫ!$L$2:$L$9000,0))="CNY",КурсCNY,1)))*(1+N($H217)/100),0),N($O217))*(1-MEDIAN(0,N(ДисконтТендер),1)))) -> 0 | U217: =IF($L217="да",MAX($U$1:$U216)+1,"") | V217: =IF($A217="","",$B217) -> Р3 | W217: =IF($U217="","",IF($U217=1,1,IF($V217<>IFERROR(INDEX($V$2:$V$1058,MATCH($U217-1,$U$2:$U$1058,0)),"~"),1,0))) | X217: =IF($U217="","",$U217+SUMIFS($W$2:$W$1058,$U$2:$U$1058,"<="&$U217)) | Y217: =IF($A217="","",IF(AND(LEFT($G217,3)="ДОК",$N217<>""),IFERROR(INDEX(Документация!$G$2:$G$57,MATCH($N217,Документация!$F$2:$F$57,0)),$D217),$D217&IF(AND(LEFT($G217,3)<>"ДОК",$N217<>"")," — "&IFERROR(INDEX(МАТЕРИАЛЫ!$C$2:$C$9000,MATCH($N217,МАТЕРИАЛЫ!$L$2:$L$9000,0)),""),""))) -> Штукатурка поверхности | Z217: =IF($B217="","",$B217&" · "&IFERROR(VLOOKUP($B217,спрРазделы,2,0),"")) -> Р3 · Внутренние строительные работы
A218: РАБ.Р3.3.015 | B218: Р3 | C218: 3 | D218: Оклейка стен стеклообоями типа "Рогожка" | E218: м2 | F218: 475.02 | G218: ОБОИ | H218: 5 | I218: ТС ЕР | P218: =IF($L218="да",ROUND(N($M218)*$S218,2),"") | Q218: =IF($L218="да",ROUND(N($M218)*$T218,2),"") | R218: =IF($L218="да",N($P218)+N($Q218),"") | S218: =IF($A218="","",IF(AND(LEFT($G218,3)="ДОК",$N218<>""),IFERROR(INDEX(Документация!$E$2:$E$57,MATCH($N218,Документация!$F$2:$F$57,0)),0),N($F218))*(1-MEDIAN(0,N(ДисконтТендер),1))) -> 475.02 | T218: =IF($A218="","",IF(AND(LEFT($G218,3)="ДОК",$N218<>""),0,IF(AND(LEFT($G218,3)<>"ДОК",$N218<>""),IFERROR(INDEX(МАТЕРИАЛЫ!$H$2:$H$9000,MATCH($N218,МАТЕРИАЛЫ!$L$2:$L$9000,0))*IF(INDEX(МАТЕРИАЛЫ!$I$2:$I$9000,MATCH($N218,МАТЕРИАЛЫ!$L$2:$L$9000,0))="USD",КурсUSD,IF(INDEX(МАТЕРИАЛЫ!$I$2:$I$9000,MATCH($N218,МАТЕРИАЛЫ!$L$2:$L$9000,0))="EUR",КурсEUR,IF(INDEX(МАТЕРИАЛЫ!$I$2:$I$9000,MATCH($N218,МАТЕРИАЛЫ!$L$2:$L$9000,0))="CNY",КурсCNY,1)))*(1+N($H218)/100),0),N($O218))*(1-MEDIAN(0,N(ДисконтТендер),1)))) -> 0 | U218: =IF($L218="да",MAX($U$1:$U217)+1,"") | V218: =IF($A218="","",$B218) -> Р3 | W218: =IF($U218="","",IF($U218=1,1,IF($V218<>IFERROR(INDEX($V$2:$V$1058,MATCH($U218-1,$U$2:$U$1058,0)),"~"),1,0))) | X218: =IF($U218="","",$U218+SUMIFS($W$2:$W$1058,$U$2:$U$1058,"<="&$U218)) | Y218: =IF($A218="","",IF(AND(LEFT($G218,3)="ДОК",$N218<>""),IFERROR(INDEX(Документация!$G$2:$G$57,MATCH($N218,Документация!$F$2:$F$57,0)),$D218),$D218&IF(AND(LEFT($G218,3)<>"ДОК",$N218<>"")," — "&IFERROR(INDEX(МАТЕРИАЛЫ!$C$2:$C$9000,MATCH($N218,МАТЕРИАЛЫ!$L$2:$L$9000,0)),""),""))) -> Оклейка стен стеклообоями типа "Рогожка" | Z218: =IF($B218="","",$B218&" · "&IFERROR(VLOOKUP($B218,спрРазделы,2,0),"")) -> Р3 · Внутренние строительные работы
A219: РАБ.Р3.3.016 | B219: Р3 | C219: 3 | D219: Декоративные крашенные МДФ ПАНЕЛИ 20ММ, ЦВЕТ RAL 7040, Швы - черный, П-образный профиль 10мм | E219: м2 | F219: 1289.34 | H219: 0 | I219: ТС ЕР | P219: =IF($L219="да",ROUND(N($M219)*$S219,2),"") | Q219: =IF($L219="да",ROUND(N($M219)*$T219,2),"") | R219: =IF($L219="да",N($P219)+N($Q219),"") | S219: =IF($A219="","",IF(AND(LEFT($G219,3)="ДОК",$N219<>""),IFERROR(INDEX(Документация!$E$2:$E$57,MATCH($N219,Документация!$F$2:$F$57,0)),0),N($F219))*(1-MEDIAN(0,N(ДисконтТендер),1))) -> 1289.34 | T219: =IF($A219="","",IF(AND(LEFT($G219,3)="ДОК",$N219<>""),0,IF(AND(LEFT($G219,3)<>"ДОК",$N219<>""),IFERROR(INDEX(МАТЕРИАЛЫ!$H$2:$H$9000,MATCH($N219,МАТЕРИАЛЫ!$L$2:$L$9000,0))*IF(INDEX(МАТЕРИАЛЫ!$I$2:$I$9000,MATCH($N219,МАТЕРИАЛЫ!$L$2:$L$9000,0))="USD",КурсUSD,IF(INDEX(МАТЕРИАЛЫ!$I$2:$I$9000,MATCH($N219,МАТЕРИАЛЫ!$L$2:$L$9000,0))="EUR",КурсEUR,IF(INDEX(МАТЕРИАЛЫ!$I$2:$I$9000,MATCH($N219,МАТЕРИАЛЫ!$L$2:$L$9000,0))="CNY",КурсCNY,1)))*(1+N($H219)/100),0),N($O219))*(1-MEDIAN(0,N(ДисконтТендер),1)))) -> 0 | U219: =IF($L219="да",MAX($U$1:$U218)+1,"") | V219: =IF($A219="","",$B219) -> Р3 | W219: =IF($U219="","",IF($U219=1,1,IF($V219<>IFERROR(INDEX($V$2:$V$1058,MATCH($U219-1,$U$2:$U$1058,0)),"~"),1,0))) | X219: =IF($U219="","",$U219+SUMIFS($W$2:$W$1058,$U$2:$U$1058,"<="&$U219)) | Y219: =IF($A219="","",IF(AND(LEFT($G219,3)="ДОК",$N219<>""),IFERROR(INDEX(Документация!$G$2:$G$57,MATCH($N219,Документация!$F$2:$F$57,0)),$D219),$D219&IF(AND(LEFT($G219,3)<>"ДОК",$N219<>"")," — "&IFERROR(INDEX(МАТЕРИАЛЫ!$C$2:$C$9000,MATCH($N219,МАТЕРИАЛЫ!$L$2:$L$9000,0)),""),""))) -> Декоративные крашенные МДФ ПАНЕЛИ 20ММ, ЦВЕТ RAL 7040, Швы - черный, П-образный профиль 10мм | Z219: =IF($B219="","",$B219&" · "&IFERROR(VLOOKUP($B219,спрРазделы,2,0),"")) -> Р3 · Внутренние строительные работы
A220: РАБ.Р3.3.017 | B220: Р3 | C220: 3 | D220: Аккустическая панель из Войлока, максимальные размери 1200X2400см, клеиться на стену | E220: м2 | F220: 548.06 | H220: 0 | I220: ТС ЕР | P220: =IF($L220="да",ROUND(N($M220)*$S220,2),"") | Q220: =IF($L220="да",ROUND(N($M220)*$T220,2),"") | R220: =IF($L220="да",N($P220)+N($Q220),"") | S220: =IF($A220="","",IF(AND(LEFT($G220,3)="ДОК",$N220<>""),IFERROR(INDEX(Документация!$E$2:$E$57,MATCH($N220,Документация!$F$2:$F$57,0)),0),N($F220))*(1-MEDIAN(0,N(ДисконтТендер),1))) -> 548.06 | T220: =IF($A220="","",IF(AND(LEFT($G220,3)="ДОК",$N220<>""),0,IF(AND(LEFT($G220,3)<>"ДОК",$N220<>""),IFERROR(INDEX(МАТЕРИАЛЫ!$H$2:$H$9000,MATCH($N220,МАТЕРИАЛЫ!$L$2:$L$9000,0))*IF(INDEX(МАТЕРИАЛЫ!$I$2:$I$9000,MATCH($N220,МАТЕРИАЛЫ!$L$2:$L$9000,0))="USD",КурсUSD,IF(INDEX(МАТЕРИАЛЫ!$I$2:$I$9000,MATCH($N220,МАТЕРИАЛЫ!$L$2:$L$9000,0))="EUR",КурсEUR,IF(INDEX(МАТЕРИАЛЫ!$I$2:$I$9000,MATCH($N220,МАТЕРИАЛЫ!$L$2:$L$9000,0))="CNY",КурсCNY,1)))*(1+N($H220)/100),0),N($O220))*(1-MEDIAN(0,N(ДисконтТендер),1)))) -> 0 | U220: =IF($L220="да",MAX($U$1:$U219)+1,"") | V220: =IF($A220="","",$B220) -> Р3 | W220: =IF($U220="","",IF($U220=1,1,IF($V220<>IFERROR(INDEX($V$2:$V$1058,MATCH($U220-1,$U$2:$U$1058,0)),"~"),1,0))) | X220: =IF($U220="","",$U220+SUMIFS($W$2:$W$1058,$U$2:$U$1058,"<="&$U220)) | Y220: =IF($A220="","",IF(AND(LEFT($G220,3)="ДОК",$N220<>""),IFERROR(INDEX(Документация!$G$2:$G$57,MATCH($N220,Документация!$F$2:$F$57,0)),$D220),$D220&IF(AND(LEFT($G220,3)<>"ДОК",$N220<>"")," — "&IFERROR(INDEX(МАТЕРИАЛЫ!$C$2:$C$9000,MATCH($N220,МАТЕРИАЛЫ!$L$2:$L$9000,0)),""),""))) -> Аккустическая панель из Войлока, максимальные размери 1200X2400см, клеиться на стену | Z220: =IF($B220="","",$B220&" · "&IFERROR(VLOOKUP($B220,спрРазделы,2,0),"")) -> Р3 · Внутренние строительные работы
A221: РАБ.Р3.3.018 | B221: Р3 | C221: 3 | D221: Оклейка обоями / стеклохолстом | E221: м2 | F221: 1628.64 | G221: ОБОИ | H221: 5 | I221: ТС ЕР | P221: =IF($L221="да",ROUND(N($M221)*$S221,2),"") | Q221: =IF($L221="да",ROUND(N($M221)*$T221,2),"") | R221: =IF($L221="да",N($P221)+N($Q221),"") | S221: =IF($A221="","",IF(AND(LEFT($G221,3)="ДОК",$N221<>""),IFERROR(INDEX(Документация!$E$2:$E$57,MATCH($N221,Документация!$F$2:$F$57,0)),0),N($F221))*(1-MEDIAN(0,N(ДисконтТендер),1))) -> 1628.64 | T221: =IF($A221="","",IF(AND(LEFT($G221,3)="ДОК",$N221<>""),0,IF(AND(LEFT($G221,3)<>"ДОК",$N221<>""),IFERROR(INDEX(МАТЕРИАЛЫ!$H$2:$H$9000,MATCH($N221,МАТЕРИАЛЫ!$L$2:$L$9000,0))*IF(INDEX(МАТЕРИАЛЫ!$I$2:$I$9000,MATCH($N221,МАТЕРИАЛЫ!$L$2:$L$9000,0))="USD",КурсUSD,IF(INDEX(МАТЕРИАЛЫ!$I$2:$I$9000,MATCH($N221,МАТЕРИАЛЫ!$L$2:$L$9000,0))="EUR",КурсEUR,IF(INDEX(МАТЕРИАЛЫ!$I$2:$I$9000,MATCH($N221,МАТЕРИАЛЫ!$L$2:$L$9000,0))="CNY",КурсCNY,1)))*(1+N($H221)/100),0),N($O221))*(1-MEDIAN(0,N(ДисконтТендер),1)))) -> 0 | U221: =IF($L221="да",MAX($U$1:$U220)+1,"") | V221: =IF($A221="","",$B221) -> Р3 | W221: =IF($U221="","",IF($U221=1,1,IF($V221<>IFERROR(INDEX($V$2:$V$1058,MATCH($U221-1,$U$2:$U$1058,0)),"~"),1,0))) | X221: =IF($U221="","",$U221+SUMIFS($W$2:$W$1058,$U$2:$U$1058,"<="&$U221)) | Y221: =IF($A221="","",IF(AND(LEFT($G221,3)="ДОК",$N221<>""),IFERROR(INDEX(Документация!$G$2:$G$57,MATCH($N221,Документация!$F$2:$F$57,0)),$D221),$D221&IF(AND(LEFT($G221,3)<>"ДОК",$N221<>"")," — "&IFERROR(INDEX(МАТЕРИАЛЫ!$C$2:$C$9000,MATCH($N221,МАТЕРИАЛЫ!$L$2:$L$9000,0)),""),""))) -> Оклейка обоями / стеклохолстом | Z221: =IF($B221="","",$B221&" · "&IFERROR(VLOOKUP($B221,спрРазделы,2,0),"")) -> Р3 · Внутренние строительные работы
A222: РАБ.Р3.3.019 | B222: Р3 | C222: 3 | D222: Оклейка поверхностей стен и перегородок Обои Голландские обои Eijffinger, коллекция Ibiza, артикул 330203 | E222: м2 | F222: 474.15 | G222: ОБОИ | H222: 5 | I222: ТС ЕР | P222: =IF($L222="да",ROUND(N($M222)*$S222,2),"") | Q222: =IF($L222="да",ROUND(N($M222)*$T222,2),"") | R222: =IF($L222="да",N($P222)+N($Q222),"") | S222: =IF($A222="","",IF(AND(LEFT($G222,3)="ДОК",$N222<>""),IFERROR(INDEX(Документация!$E$2:$E$57,MATCH($N222,Документация!$F$2:$F$57,0)),0),N($F222))*(1-MEDIAN(0,N(ДисконтТендер),1))) -> 474.15 | T222: =IF($A222="","",IF(AND(LEFT($G222,3)="ДОК",$N222<>""),0,IF(AND(LEFT($G222,3)<>"ДОК",$N222<>""),IFERROR(INDEX(МАТЕРИАЛЫ!$H$2:$H$9000,MATCH($N222,МАТЕРИАЛЫ!$L$2:$L$9000,0))*IF(INDEX(МАТЕРИАЛЫ!$I$2:$I$9000,MATCH($N222,МАТЕРИАЛЫ!$L$2:$L$9000,0))="USD",КурсUSD,IF(INDEX(МАТЕРИАЛЫ!$I$2:$I$9000,MATCH($N222,МАТЕРИАЛЫ!$L$2:$L$9000,0))="EUR",КурсEUR,IF(INDEX(МАТЕРИАЛЫ!$I$2:$I$9000,MATCH($N222,МАТЕРИАЛЫ!$L$2:$L$9000,0))="CNY",КурсCNY,1)))*(1+N($H222)/100),0),N($O222))*(1-MEDIAN(0,N(ДисконтТендер),1)))) -> 0 | U222: =IF($L222="да",MAX($U$1:$U221)+1,"") | V222: =IF($A222="","",$B222) -> Р3 | W222: =IF($U222="","",IF($U222=1,1,IF($V222<>IFERROR(INDEX($V$2:$V$1058,MATCH($U222-1,$U$2:$U$1058,0)),"~"),1,0))) | X222: =IF($U222="","",$U222+SUMIFS($W$2:$W$1058,$U$2:$U$1058,"<="&$U222)) | Y222: =IF($A222="","",IF(AND(LEFT($G222,3)="ДОК",$N222<>""),IFERROR(INDEX(Документация!$G$2:$G$57,MATCH($N222,Документация!$F$2:$F$57,0)),$D222),$D222&IF(AND(LEFT($G222,3)<>"ДОК",$N222<>"")," — "&IFERROR(INDEX(МАТЕРИАЛЫ!$C$2:$C$9000,MATCH($N222,МАТЕРИАЛЫ!$L$2:$L$9000,0)),""),""))) -> Оклейка поверхностей стен и перегородок Обои Голландские обои Eijffinger, коллекция Ibiza, артикул 330203 | Z222: =IF($B222="","",$B222&" · "&IFERROR(VLOOKUP($B222,спрРазделы,2,0),"")) -> Р3 · Внутренние строительные работы
A223: РАБ.Р3.3.020 | B223: Р3 | C223: 3 | D223: Оклейка поверхностей стен и перегородок бумажными обоями (рисунок обоев выполняется "на заказ") | E223: м2 | F223: 652.5 | G223: ОБОИ | H223: 5 | I223: ТС ЕР | P223: =IF($L223="да",ROUND(N($M223)*$S223,2),"") | Q223: =IF($L223="да",ROUND(N($M223)*$T223,2),"") | R223: =IF($L223="да",N($P223)+N($Q223),"") | S223: =IF($A223="","",IF(AND(LEFT($G223,3)="ДОК",$N223<>""),IFERROR(INDEX(Документация!$E$2:$E$57,MATCH($N223,Документация!$F$2:$F$57,0)),0),N($F223))*(1-MEDIAN(0,N(ДисконтТендер),1))) -> 652.5 | T223: =IF($A223="","",IF(AND(LEFT($G223,3)="ДОК",$N223<>""),0,IF(AND(LEFT($G223,3)<>"ДОК",$N223<>""),IFERROR(INDEX(МАТЕРИАЛЫ!$H$2:$H$9000,MATCH($N223,МАТЕРИАЛЫ!$L$2:$L$9000,0))*IF(INDEX(МАТЕРИАЛЫ!$I$2:$I$9000,MATCH($N223,МАТЕРИАЛЫ!$L$2:$L$9000,0))="USD",КурсUSD,IF(INDEX(МАТЕРИАЛЫ!$I$2:$I$9000,MATCH($N223,МАТЕРИАЛЫ!$L$2:$L$9000,0))="EUR",КурсEUR,IF(INDEX(МАТЕРИАЛЫ!$I$2:$I$9000,MATCH($N223,МАТЕРИАЛЫ!$L$2:$L$9000,0))="CNY",КурсCNY,1)))*(1+N($H223)/100),0),N($O223))*(1-MEDIAN(0,N(ДисконтТендер),1)))) -> 0 | U223: =IF($L223="да",MAX($U$1:$U222)+1,"") | V223: =IF($A223="","",$B223) -> Р3 | W223: =IF($U223="","",IF($U223=1,1,IF($V223<>IFERROR(INDEX($V$2:$V$1058,MATCH($U223-1,$U$2:$U$1058,0)),"~"),1,0))) | X223: =IF($U223="","",$U223+SUMIFS($W$2:$W$1058,$U$2:$U$1058,"<="&$U223)) | Y223: =IF($A223="","",IF(AND(LEFT($G223,3)="ДОК",$N223<>""),IFERROR(INDEX(Документация!$G$2:$G$57,MATCH($N223,Документация!$F$2:$F$57,0)),$D223),$D223&IF(AND(LEFT($G223,3)<>"ДОК",$N223<>"")," — "&IFERROR(INDEX(МАТЕРИАЛЫ!$C$2:$C$9000,MATCH($N223,МАТЕРИАЛЫ!$L$2:$L$9000,0)),""),""))) -> Оклейка поверхностей стен и перегородок бумажными обоями (рисунок обоев выполняется "на заказ") | Z223: =IF($B223="","",$B223&" · "&IFERROR(VLOOKUP($B223,спрРазделы,2,0),"")) -> Р3 · Внутренние строительные работы
A224: РАБ.Р3.4.001 | B224: Р3 | C224: 4 | D224: Монтаж однопольного дверного блока (алюминиевый теплый профиль 3 петли, два врезных замка сувального типа (количество ключей не менее 4 шт.) без защелки , ручка из нержавеющей стал… | E224: шт. | F224: 5781.74 | G224: ДВ.АЛ | H224: 5 | I224: ТС ЕР | P224: =IF($L224="да",ROUND(N($M224)*$S224,2),"") | Q224: =IF($L224="да",ROUND(N($M224)*$T224,2),"") | R224: =IF($L224="да",N($P224)+N($Q224),"") | S224: =IF($A224="","",IF(AND(LEFT($G224,3)="ДОК",$N224<>""),IFERROR(INDEX(Документация!$E$2:$E$57,MATCH($N224,Документация!$F$2:$F$57,0)),0),N($F224))*(1-MEDIAN(0,N(ДисконтТендер),1))) -> 5781.74 | T224: =IF($A224="","",IF(AND(LEFT($G224,3)="ДОК",$N224<>""),0,IF(AND(LEFT($G224,3)<>"ДОК",$N224<>""),IFERROR(INDEX(МАТЕРИАЛЫ!$H$2:$H$9000,MATCH($N224,МАТЕРИАЛЫ!$L$2:$L$9000,0))*IF(INDEX(МАТЕРИАЛЫ!$I$2:$I$9000,MATCH($N224,МАТЕРИАЛЫ!$L$2:$L$9000,0))="USD",КурсUSD,IF(INDEX(МАТЕРИАЛЫ!$I$2:$I$9000,MATCH($N224,МАТЕРИАЛЫ!$L$2:$L$9000,0))="EUR",КурсEUR,IF(INDEX(МАТЕРИАЛЫ!$I$2:$I$9000,MATCH($N224,МАТЕРИАЛЫ!$L$2:$L$9000,0))="CNY",КурсCNY,1)))*(1+N($H224)/100),0),N($O224))*(1-MEDIAN(0,N(ДисконтТендер),1)))) -> 0 | U224: =IF($L224="да",MAX($U$1:$U223)+1,"") | V224: =IF($A224="","",$B224) -> Р3 | W224: =IF($U224="","",IF($U224=1,1,IF($V224<>IFERROR(INDEX($V$2:$V$1058,MATCH($U224-1,$U$2:$U$1058,0)),"~"),1,0))) | X224: =IF($U224="","",$U224+SUMIFS($W$2:$W$1058,$U$2:$U$1058,"<="&$U224)) | Y224: =IF($A224="","",IF(AND(LEFT($G224,3)="ДОК",$N224<>""),IFERROR(INDEX(Документация!$G$2:$G$57,MATCH($N224,Документация!$F$2:$F$57,0)),$D224),$D224&IF(AND(LEFT($G224,3)<>"ДОК",$N224<>"")," — "&IFERROR(INDEX(МАТЕРИАЛЫ!$C$2:$C$9000,MATCH($N224,МАТЕРИАЛЫ!$L$2:$L$9000,0)),""),""))) -> Монтаж однопольного дверного блока (алюминиевый теплый профиль 3 петли, два врезных замка сувального типа (количество ключей не менее 4 шт.) без защелки , ручка из нержавеющей стал… | Z224: =IF($B224="","",$B224&" · "&IFERROR(VLOOKUP($B224,спрРазделы,2,0),"")) -> Р3 · Внутренние строительные работы
A225: РАБ.Р3.4.002 | B225: Р3 | C225: 4 | D225: Монтаж полуторапольного дверного блока (алюминиевый теплый профиль 3 петли, два врезных замка сувального типа (количество ключей не менее 4 шт.) без защелки , ручка из нержавеющей … | E225: шт. | F225: 7892.64 | G225: ДВ.АЛ | H225: 5 | I225: ТС ЕР | P225: =IF($L225="да",ROUND(N($M225)*$S225,2),"") | Q225: =IF($L225="да",ROUND(N($M225)*$T225,2),"") | R225: =IF($L225="да",N($P225)+N($Q225),"") | S225: =IF($A225="","",IF(AND(LEFT($G225,3)="ДОК",$N225<>""),IFERROR(INDEX(Документация!$E$2:$E$57,MATCH($N225,Документация!$F$2:$F$57,0)),0),N($F225))*(1-MEDIAN(0,N(ДисконтТендер),1))) -> 7892.64 | T225: =IF($A225="","",IF(AND(LEFT($G225,3)="ДОК",$N225<>""),0,IF(AND(LEFT($G225,3)<>"ДОК",$N225<>""),IFERROR(INDEX(МАТЕРИАЛЫ!$H$2:$H$9000,MATCH($N225,МАТЕРИАЛЫ!$L$2:$L$9000,0))*IF(INDEX(МАТЕРИАЛЫ!$I$2:$I$9000,MATCH($N225,МАТЕРИАЛЫ!$L$2:$L$9000,0))="USD",КурсUSD,IF(INDEX(МАТЕРИАЛЫ!$I$2:$I$9000,MATCH($N225,МАТЕРИАЛЫ!$L$2:$L$9000,0))="EUR",КурсEUR,IF(INDEX(МАТЕРИАЛЫ!$I$2:$I$9000,MATCH($N225,МАТЕРИАЛЫ!$L$2:$L$9000,0))="CNY",КурсCNY,1)))*(1+N($H225)/100),0),N($O225))*(1-MEDIAN(0,N(ДисконтТендер),1)))) -> 0 | U225: =IF($L225="да",MAX($U$1:$U224)+1,"") | V225: =IF($A225="","",$B225) -> Р3 | W225: =IF($U225="","",IF($U225=1,1,IF($V225<>IFERROR(INDEX($V$2:$V$1058,MATCH($U225-1,$U$2:$U$1058,0)),"~"),1,0))) | X225: =IF($U225="","",$U225+SUMIFS($W$2:$W$1058,$U$2:$U$1058,"<="&$U225)) | Y225: =IF($A225="","",IF(AND(LEFT($G225,3)="ДОК",$N225<>""),IFERROR(INDEX(Документация!$G$2:$G$57,MATCH($N225,Документация!$F$2:$F$57,0)),$D225),$D225&IF(AND(LEFT($G225,3)<>"ДОК",$N225<>"")," — "&IFERROR(INDEX(МАТЕРИАЛЫ!$C$2:$C$9000,MATCH($N225,МАТЕРИАЛЫ!$L$2:$L$9000,0)),""),""))) -> Монтаж полуторапольного дверного блока (алюминиевый теплый профиль 3 петли, два врезных замка сувального типа (количество ключей не менее 4 шт.) без защелки , ручка из нержавеющей … | Z225: =IF($B225="","",$B225&" · "&IFERROR(VLOOKUP($B225,спрРазделы,2,0),"")) -> Р3 · Внутренние строительные работы
A226: РАБ.Р3.4.003 | B226: Р3 | C226: 4 | D226: Монтаж двупольного дверного блока (алюминиевый теплый профиль 3 петли, два врезных замка сувального типа (количество ключей не менее 4 шт.) без защелки , ручка из нержавеющей стали… | E226: шт. | F226: 9900 | G226: ДВ.АЛ | H226: 5 | I226: ТС ЕР | P226: =IF($L226="да",ROUND(N($M226)*$S226,2),"") | Q226: =IF($L226="да",ROUND(N($M226)*$T226,2),"") | R226: =IF($L226="да",N($P226)+N($Q226),"") | S226: =IF($A226="","",IF(AND(LEFT($G226,3)="ДОК",$N226<>""),IFERROR(INDEX(Документация!$E$2:$E$57,MATCH($N226,Документация!$F$2:$F$57,0)),0),N($F226))*(1-MEDIAN(0,N(ДисконтТендер),1))) -> 9900 | T226: =IF($A226="","",IF(AND(LEFT($G226,3)="ДОК",$N226<>""),0,IF(AND(LEFT($G226,3)<>"ДОК",$N226<>""),IFERROR(INDEX(МАТЕРИАЛЫ!$H$2:$H$9000,MATCH($N226,МАТЕРИАЛЫ!$L$2:$L$9000,0))*IF(INDEX(МАТЕРИАЛЫ!$I$2:$I$9000,MATCH($N226,МАТЕРИАЛЫ!$L$2:$L$9000,0))="USD",КурсUSD,IF(INDEX(МАТЕРИАЛЫ!$I$2:$I$9000,MATCH($N226,МАТЕРИАЛЫ!$L$2:$L$9000,0))="EUR",КурсEUR,IF(INDEX(МАТЕРИАЛЫ!$I$2:$I$9000,MATCH($N226,МАТЕРИАЛЫ!$L$2:$L$9000,0))="CNY",КурсCNY,1)))*(1+N($H226)/100),0),N($O226))*(1-MEDIAN(0,N(ДисконтТендер),1)))) -> 0 | U226: =IF($L226="да",MAX($U$1:$U225)+1,"") | V226: =IF($A226="","",$B226) -> Р3 | W226: =IF($U226="","",IF($U226=1,1,IF($V226<>IFERROR(INDEX($V$2:$V$1058,MATCH($U226-1,$U$2:$U$1058,0)),"~"),1,0))) | X226: =IF($U226="","",$U226+SUMIFS($W$2:$W$1058,$U$2:$U$1058,"<="&$U226)) | Y226: =IF($A226="","",IF(AND(LEFT($G226,3)="ДОК",$N226<>""),IFERROR(INDEX(Документация!$G$2:$G$57,MATCH($N226,Документация!$F$2:$F$57,0)),$D226),$D226&IF(AND(LEFT($G226,3)<>"ДОК",$N226<>"")," — "&IFERROR(INDEX(МАТЕРИАЛЫ!$C$2:$C$9000,MATCH($N226,МАТЕРИАЛЫ!$L$2:$L$9000,0)),""),""))) -> Монтаж двупольного дверного блока (алюминиевый теплый профиль 3 петли, два врезных замка сувального типа (количество ключей не менее 4 шт.) без защелки , ручка из нержавеющей стали… | Z226: =IF($B226="","",$B226&" · "&IFERROR(VLOOKUP($B226,спрРазделы,2,0),"")) -> Р3 · Внутренние строительные работы
A227: РАБ.Р3.4.004 | B227: Р3 | C227: 4 | D227: Монтаж дверного блока / дверных приборов | E227: шт. | F227: 1280.13 | G227: ДВ | H227: 5 | I227: ТС ЕР | P227: =IF($L227="да",ROUND(N($M227)*$S227,2),"") | Q227: =IF($L227="да",ROUND(N($M227)*$T227,2),"") | R227: =IF($L227="да",N($P227)+N($Q227),"") | S227: =IF($A227="","",IF(AND(LEFT($G227,3)="ДОК",$N227<>""),IFERROR(INDEX(Документация!$E$2:$E$57,MATCH($N227,Документация!$F$2:$F$57,0)),0),N($F227))*(1-MEDIAN(0,N(ДисконтТендер),1))) -> 1280.13 | T227: =IF($A227="","",IF(AND(LEFT($G227,3)="ДОК",$N227<>""),0,IF(AND(LEFT($G227,3)<>"ДОК",$N227<>""),IFERROR(INDEX(МАТЕРИАЛЫ!$H$2:$H$9000,MATCH($N227,МАТЕРИАЛЫ!$L$2:$L$9000,0))*IF(INDEX(МАТЕРИАЛЫ!$I$2:$I$9000,MATCH($N227,МАТЕРИАЛЫ!$L$2:$L$9000,0))="USD",КурсUSD,IF(INDEX(МАТЕРИАЛЫ!$I$2:$I$9000,MATCH($N227,МАТЕРИАЛЫ!$L$2:$L$9000,0))="EUR",КурсEUR,IF(INDEX(МАТЕРИАЛЫ!$I$2:$I$9000,MATCH($N227,МАТЕРИАЛЫ!$L$2:$L$9000,0))="CNY",КурсCNY,1)))*(1+N($H227)/100),0),N($O227))*(1-MEDIAN(0,N(ДисконтТендер),1)))) -> 0 | U227: =IF($L227="да",MAX($U$1:$U226)+1,"") | V227: =IF($A227="","",$B227) -> Р3 | W227: =IF($U227="","",IF($U227=1,1,IF($V227<>IFERROR(INDEX($V$2:$V$1058,MATCH($U227-1,$U$2:$U$1058,0)),"~"),1,0))) | X227: =IF($U227="","",$U227+SUMIFS($W$2:$W$1058,$U$2:$U$1058,"<="&$U227)) | Y227: =IF($A227="","",IF(AND(LEFT($G227,3)="ДОК",$N227<>""),IFERROR(INDEX(Документация!$G$2:$G$57,MATCH($N227,Документация!$F$2:$F$57,0)),$D227),$D227&IF(AND(LEFT($G227,3)<>"ДОК",$N227<>"")," — "&IFERROR(INDEX(МАТЕРИАЛЫ!$C$2:$C$9000,MATCH($N227,МАТЕРИАЛЫ!$L$2:$L$9000,0)),""),""))) -> Монтаж дверного блока / дверных приборов | Z227: =IF($B227="","",$B227&" · "&IFERROR(VLOOKUP($B227,спрРазделы,2,0),"")) -> Р3 · Внутренние строительные работы
A228: РАБ.Р3.4.005 | B228: Р3 | C228: 4 | D228: Монтаж дверного блока / дверных приборов | E228: шт. | F228: 10648.8 | G228: ДВ | H228: 5 | I228: ТС ЕР | P228: =IF($L228="да",ROUND(N($M228)*$S228,2),"") | Q228: =IF($L228="да",ROUND(N($M228)*$T228,2),"") | R228: =IF($L228="да",N($P228)+N($Q228),"") | S228: =IF($A228="","",IF(AND(LEFT($G228,3)="ДОК",$N228<>""),IFERROR(INDEX(Документация!$E$2:$E$57,MATCH($N228,Документация!$F$2:$F$57,0)),0),N($F228))*(1-MEDIAN(0,N(ДисконтТендер),1))) -> 10648.8 | T228: =IF($A228="","",IF(AND(LEFT($G228,3)="ДОК",$N228<>""),0,IF(AND(LEFT($G228,3)<>"ДОК",$N228<>""),IFERROR(INDEX(МАТЕРИАЛЫ!$H$2:$H$9000,MATCH($N228,МАТЕРИАЛЫ!$L$2:$L$9000,0))*IF(INDEX(МАТЕРИАЛЫ!$I$2:$I$9000,MATCH($N228,МАТЕРИАЛЫ!$L$2:$L$9000,0))="USD",КурсUSD,IF(INDEX(МАТЕРИАЛЫ!$I$2:$I$9000,MATCH($N228,МАТЕРИАЛЫ!$L$2:$L$9000,0))="EUR",КурсEUR,IF(INDEX(МАТЕРИАЛЫ!$I$2:$I$9000,MATCH($N228,МАТЕРИАЛЫ!$L$2:$L$9000,0))="CNY",КурсCNY,1)))*(1+N($H228)/100),0),N($O228))*(1-MEDIAN(0,N(ДисконтТендер),1)))) -> 0 | U228: =IF($L228="да",MAX($U$1:$U227)+1,"") | V228: =IF($A228="","",$B228) -> Р3 | W228: =IF($U228="","",IF($U228=1,1,IF($V228<>IFERROR(INDEX($V$2:$V$1058,MATCH($U228-1,$U$2:$U$1058,0)),"~"),1,0))) | X228: =IF($U228="","",$U228+SUMIFS($W$2:$W$1058,$U$2:$U$1058,"<="&$U228)) | Y228: =IF($A228="","",IF(AND(LEFT($G228,3)="ДОК",$N228<>""),IFERROR(INDEX(Документация!$G$2:$G$57,MATCH($N228,Документация!$F$2:$F$57,0)),$D228),$D228&IF(AND(LEFT($G228,3)<>"ДОК",$N228<>"")," — "&IFERROR(INDEX(МАТЕРИАЛЫ!$C$2:$C$9000,MATCH($N228,МАТЕРИАЛЫ!$L$2:$L$9000,0)),""),""))) -> Монтаж дверного блока / дверных приборов | Z228: =IF($B228="","",$B228&" · "&IFERROR(VLOOKUP($B228,спрРазделы,2,0),"")) -> Р3 · Внутренние строительные работы
A229: РАБ.Р3.4.006 | B229: Р3 | C229: 4 | D229: Дверной блок утепленый, полуторастворчатый размером по раме 2100Нх1400 мм (размер двери в свету 2000Нх1200 мм), полотна из листов металла 2+2 мм (наружный и внутренние листы). Рабо… | E229: шт. | F229: 13154.4 | G229: КРАСКА | H229: 5 | I229: ТС ЕР | P229: =IF($L229="да",ROUND(N($M229)*$S229,2),"") | Q229: =IF($L229="да",ROUND(N($M229)*$T229,2),"") | R229: =IF($L229="да",N($P229)+N($Q229),"") | S229: =IF($A229="","",IF(AND(LEFT($G229,3)="ДОК",$N229<>""),IFERROR(INDEX(Документация!$E$2:$E$57,MATCH($N229,Документация!$F$2:$F$57,0)),0),N($F229))*(1-MEDIAN(0,N(ДисконтТендер),1))) -> 13154.4 | T229: =IF($A229="","",IF(AND(LEFT($G229,3)="ДОК",$N229<>""),0,IF(AND(LEFT($G229,3)<>"ДОК",$N229<>""),IFERROR(INDEX(МАТЕРИАЛЫ!$H$2:$H$9000,MATCH($N229,МАТЕРИАЛЫ!$L$2:$L$9000,0))*IF(INDEX(МАТЕРИАЛЫ!$I$2:$I$9000,MATCH($N229,МАТЕРИАЛЫ!$L$2:$L$9000,0))="USD",КурсUSD,IF(INDEX(МАТЕРИАЛЫ!$I$2:$I$9000,MATCH($N229,МАТЕРИАЛЫ!$L$2:$L$9000,0))="EUR",КурсEUR,IF(INDEX(МАТЕРИАЛЫ!$I$2:$I$9000,MATCH($N229,МАТЕРИАЛЫ!$L$2:$L$9000,0))="CNY",КурсCNY,1)))*(1+N($H229)/100),0),N($O229))*(1-MEDIAN(0,N(ДисконтТендер),1)))) -> 0 | U229: =IF($L229="да",MAX($U$1:$U228)+1,"") | V229: =IF($A229="","",$B229) -> Р3 | W229: =IF($U229="","",IF($U229=1,1,IF($V229<>IFERROR(INDEX($V$2:$V$1058,MATCH($U229-1,$U$2:$U$1058,0)),"~"),1,0))) | X229: =IF($U229="","",$U229+SUMIFS($W$2:$W$1058,$U$2:$U$1058,"<="&$U229)) | Y229: =IF($A229="","",IF(AND(LEFT($G229,3)="ДОК",$N229<>""),IFERROR(INDEX(Документация!$G$2:$G$57,MATCH($N229,Документация!$F$2:$F$57,0)),$D229),$D229&IF(AND(LEFT($G229,3)<>"ДОК",$N229<>"")," — "&IFERROR(INDEX(МАТЕРИАЛЫ!$C$2:$C$9000,MATCH($N229,МАТЕРИАЛЫ!$L$2:$L$9000,0)),""),""))) -> Дверной блок утепленый, полуторастворчатый размером по раме 2100Нх1400 мм (размер двери в свету 2000Нх1200 мм), полотна из листов металла 2+2 мм (наружный и внутренние листы). Рабо… | Z229: =IF($B229="","",$B229&" · "&IFERROR(VLOOKUP($B229,спрРазделы,2,0),"")) -> Р3 · Внутренние строительные работы
A230: РАБ.Р3.4.007 | B230: Р3 | C230: 4 | D230: Доводчик на рабочую створку NOTEDO DC-025-095 (со скользящим каналом). Доводчик на паразитную створку NOTEDO DC-070 (паук) | E230: шт. | F230: 1315.44 | G230: ДВ | H230: 5 | I230: ТС ЕР | P230: =IF($L230="да",ROUND(N($M230)*$S230,2),"") | Q230: =IF($L230="да",ROUND(N($M230)*$T230,2),"") | R230: =IF($L230="да",N($P230)+N($Q230),"") | S230: =IF($A230="","",IF(AND(LEFT($G230,3)="ДОК",$N230<>""),IFERROR(INDEX(Документация!$E$2:$E$57,MATCH($N230,Документация!$F$2:$F$57,0)),0),N($F230))*(1-MEDIAN(0,N(ДисконтТендер),1))) -> 1315.44 | T230: =IF($A230="","",IF(AND(LEFT($G230,3)="ДОК",$N230<>""),0,IF(AND(LEFT($G230,3)<>"ДОК",$N230<>""),IFERROR(INDEX(МАТЕРИАЛЫ!$H$2:$H$9000,MATCH($N230,МАТЕРИАЛЫ!$L$2:$L$9000,0))*IF(INDEX(МАТЕРИАЛЫ!$I$2:$I$9000,MATCH($N230,МАТЕРИАЛЫ!$L$2:$L$9000,0))="USD",КурсUSD,IF(INDEX(МАТЕРИАЛЫ!$I$2:$I$9000,MATCH($N230,МАТЕРИАЛЫ!$L$2:$L$9000,0))="EUR",КурсEUR,IF(INDEX(МАТЕРИАЛЫ!$I$2:$I$9000,MATCH($N230,МАТЕРИАЛЫ!$L$2:$L$9000,0))="CNY",КурсCNY,1)))*(1+N($H230)/100),0),N($O230))*(1-MEDIAN(0,N(ДисконтТендер),1)))) -> 0 | U230: =IF($L230="да",MAX($U$1:$U229)+1,"") | V230: =IF($A230="","",$B230) -> Р3 | W230: =IF($U230="","",IF($U230=1,1,IF($V230<>IFERROR(INDEX($V$2:$V$1058,MATCH($U230-1,$U$2:$U$1058,0)),"~"),1,0))) | X230: =IF($U230="","",$U230+SUMIFS($W$2:$W$1058,$U$2:$U$1058,"<="&$U230)) | Y230: =IF($A230="","",IF(AND(LEFT($G230,3)="ДОК",$N230<>""),IFERROR(INDEX(Документация!$G$2:$G$57,MATCH($N230,Документация!$F$2:$F$57,0)),$D230),$D230&IF(AND(LEFT($G230,3)<>"ДОК",$N230<>"")," — "&IFERROR(INDEX(МАТЕРИАЛЫ!$C$2:$C$9000,MATCH($N230,МАТЕРИАЛЫ!$L$2:$L$9000,0)),""),""))) -> Доводчик на рабочую створку NOTEDO DC-025-095 (со скользящим каналом). Доводчик на паразитную створку NOTEDO DC-070 (паук) | Z230: =IF($B230="","",$B230&" · "&IFERROR(VLOOKUP($B230,спрРазделы,2,0),"")) -> Р3 · Внутренние строительные работы
A231: РАБ.Р3.4.008 | B231: Р3 | C231: 4 | D231: Установка металлической двери-решетчатой гармошки с замком 900х2100 мм (запасной выход) | E231: шт. | F231: 11901.6 | G231: ДВ.БР | H231: 5 | I231: ТС ЕР | P231: =IF($L231="да",ROUND(N($M231)*$S231,2),"") | Q231: =IF($L231="да",ROUND(N($M231)*$T231,2),"") | R231: =IF($L231="да",N($P231)+N($Q231),"") | S231: =IF($A231="","",IF(AND(LEFT($G231,3)="ДОК",$N231<>""),IFERROR(INDEX(Документация!$E$2:$E$57,MATCH($N231,Документация!$F$2:$F$57,0)),0),N($F231))*(1-MEDIAN(0,N(ДисконтТендер),1))) -> 11901.6 | T231: =IF($A231="","",IF(AND(LEFT($G231,3)="ДОК",$N231<>""),0,IF(AND(LEFT($G231,3)<>"ДОК",$N231<>""),IFERROR(INDEX(МАТЕРИАЛЫ!$H$2:$H$9000,MATCH($N231,МАТЕРИАЛЫ!$L$2:$L$9000,0))*IF(INDEX(МАТЕРИАЛЫ!$I$2:$I$9000,MATCH($N231,МАТЕРИАЛЫ!$L$2:$L$9000,0))="USD",КурсUSD,IF(INDEX(МАТЕРИАЛЫ!$I$2:$I$9000,MATCH($N231,МАТЕРИАЛЫ!$L$2:$L$9000,0))="EUR",КурсEUR,IF(INDEX(МАТЕРИАЛЫ!$I$2:$I$9000,MATCH($N231,МАТЕРИАЛЫ!$L$2:$L$9000,0))="CNY",КурсCNY,1)))*(1+N($H231)/100),0),N($O231))*(1-MEDIAN(0,N(ДисконтТендер),1)))) -> 0 | U231: =IF($L231="да",MAX($U$1:$U230)+1,"") | V231: =IF($A231="","",$B231) -> Р3 | W231: =IF($U231="","",IF($U231=1,1,IF($V231<>IFERROR(INDEX($V$2:$V$1058,MATCH($U231-1,$U$2:$U$1058,0)),"~"),1,0))) | X231: =IF($U231="","",$U231+SUMIFS($W$2:$W$1058,$U$2:$U$1058,"<="&$U231)) | Y231: =IF($A231="","",IF(AND(LEFT($G231,3)="ДОК",$N231<>""),IFERROR(INDEX(Документация!$G$2:$G$57,MATCH($N231,Документация!$F$2:$F$57,0)),$D231),$D231&IF(AND(LEFT($G231,3)<>"ДОК",$N231<>"")," — "&IFERROR(INDEX(МАТЕРИАЛЫ!$C$2:$C$9000,MATCH($N231,МАТЕРИАЛЫ!$L$2:$L$9000,0)),""),""))) -> Установка металлической двери-решетчатой гармошки с замком 900х2100 мм (запасной выход) | Z231: =IF($B231="","",$B231&" · "&IFERROR(VLOOKUP($B231,спрРазделы,2,0),"")) -> Р3 · Внутренние строительные работы
A232: РАБ.Р3.4.009 | B232: Р3 | C232: 4 | D232: Монтаж дверного блока стеклянного | E232: шт. | F232: 9350 | G232: ДВ.СТ | H232: 5 | I232: ТС ЕР | P232: =IF($L232="да",ROUND(N($M232)*$S232,2),"") | Q232: =IF($L232="да",ROUND(N($M232)*$T232,2),"") | R232: =IF($L232="да",N($P232)+N($Q232),"") | S232: =IF($A232="","",IF(AND(LEFT($G232,3)="ДОК",$N232<>""),IFERROR(INDEX(Документация!$E$2:$E$57,MATCH($N232,Документация!$F$2:$F$57,0)),0),N($F232))*(1-MEDIAN(0,N(ДисконтТендер),1))) -> 9350 | T232: =IF($A232="","",IF(AND(LEFT($G232,3)="ДОК",$N232<>""),0,IF(AND(LEFT($G232,3)<>"ДОК",$N232<>""),IFERROR(INDEX(МАТЕРИАЛЫ!$H$2:$H$9000,MATCH($N232,МАТЕРИАЛЫ!$L$2:$L$9000,0))*IF(INDEX(МАТЕРИАЛЫ!$I$2:$I$9000,MATCH($N232,МАТЕРИАЛЫ!$L$2:$L$9000,0))="USD",КурсUSD,IF(INDEX(МАТЕРИАЛЫ!$I$2:$I$9000,MATCH($N232,МАТЕРИАЛЫ!$L$2:$L$9000,0))="EUR",КурсEUR,IF(INDEX(МАТЕРИАЛЫ!$I$2:$I$9000,MATCH($N232,МАТЕРИАЛЫ!$L$2:$L$9000,0))="CNY",КурсCNY,1)))*(1+N($H232)/100),0),N($O232))*(1-MEDIAN(0,N(ДисконтТендер),1)))) -> 0 | U232: =IF($L232="да",MAX($U$1:$U231)+1,"") | V232: =IF($A232="","",$B232) -> Р3 | W232: =IF($U232="","",IF($U232=1,1,IF($V232<>IFERROR(INDEX($V$2:$V$1058,MATCH($U232-1,$U$2:$U$1058,0)),"~"),1,0))) | X232: =IF($U232="","",$U232+SUMIFS($W$2:$W$1058,$U$2:$U$1058,"<="&$U232)) | Y232: =IF($A232="","",IF(AND(LEFT($G232,3)="ДОК",$N232<>""),IFERROR(INDEX(Документация!$G$2:$G$57,MATCH($N232,Документация!$F$2:$F$57,0)),$D232),$D232&IF(AND(LEFT($G232,3)<>"ДОК",$N232<>"")," — "&IFERROR(INDEX(МАТЕРИАЛЫ!$C$2:$C$9000,MATCH($N232,МАТЕРИАЛЫ!$L$2:$L$9000,0)),""),""))) -> Монтаж дверного блока стеклянного | Z232: =IF($B232="","",$B232&" · "&IFERROR(VLOOKUP($B232,спрРазделы,2,0),"")) -> Р3 · Внутренние строительные работы
... A237: РАБ.Р3.4.014 | B237: Р3 | C237: 4 | D237: фрезеровка под Eff-Eff 34 12 V DC (34-E91) с длинными планками Eff-Eff HZ (021 35) (-------02135-01) (предоставляет заказчик), защищенный стальной гибкий переход для кабеля, прокла… | E237: шт. | F237: 1503.36 | G237: ДВ | H237: 5 | I237: ТС ЕР | P237: =IF($L237="да",ROUND(N($M237)*$S237,2),"") | Q237: =IF($L237="да",ROUND(N($M237)*$T237,2),"") | R237: =IF($L237="да",N($P237)+N($Q237),"") | S237: =IF($A237="","",IF(AND(LEFT($G237,3)="ДОК",$N237<>""),IFERROR(INDEX(Документация!$E$2:$E$57,MATCH($N237,Документация!$F$2:$F$57,0)),0),N($F237))*(1-MEDIAN(0,N(ДисконтТендер),1))) -> 1503.36 | T237: =IF($A237="","",IF(AND(LEFT($G237,3)="ДОК",$N237<>""),0,IF(AND(LEFT($G237,3)<>"ДОК",$N237<>""),IFERROR(INDEX(МАТЕРИАЛЫ!$H$2:$H$9000,MATCH($N237,МАТЕРИАЛЫ!$L$2:$L$9000,0))*IF(INDEX(МАТЕРИАЛЫ!$I$2:$I$9000,MATCH($N237,МАТЕРИАЛЫ!$L$2:$L$9000,0))="USD",КурсUSD,IF(INDEX(МАТЕРИАЛЫ!$I$2:$I$9000,MATCH($N237,МАТЕРИАЛЫ!$L$2:$L$9000,0))="EUR",КурсEUR,IF(INDEX(МАТЕРИАЛЫ!$I$2:$I$9000,MATCH($N237,МАТЕРИАЛЫ!$L$2:$L$9000,0))="CNY",КурсCNY,1)))*(1+N($H237)/100),0),N($O237))*(1-MEDIAN(0,N(ДисконтТендер),1)))) -> 0 | U237: =IF($L237="да",MAX($U$1:$U236)+1,"") | V237: =IF($A237="","",$B237) -> Р3 | W237: =IF($U237="","",IF($U237=1,1,IF($V237<>IFERROR(INDEX($V$2:$V$1058,MATCH($U237-1,$U$2:$U$1058,0)),"~"),1,0))) | X237: =IF($U237="","",$U237+SUMIFS($W$2:$W$1058,$U$2:$U$1058,"<="&$U237)) | Y237: =IF($A237="","",IF(AND(LEFT($G237,3)="ДОК",$N237<>""),IFERROR(INDEX(Документация!$G$2:$G$57,MATCH($N237,Документация!$F$2:$F$57,0)),$D237),$D237&IF(AND(LEFT($G237,3)<>"ДОК",$N237<>"")," — "&IFERROR(INDEX(МАТЕРИАЛЫ!$C$2:$C$9000,MATCH($N237,МАТЕРИАЛЫ!$L$2:$L$9000,0)),""),""))) -> фрезеровка под Eff-Eff 34 12 V DC (34-E91) с длинными планками Eff-Eff HZ (021 35) (-------02135-01) (предоставляет заказчик), защищенный стальной гибкий переход для кабеля, прокла… | Z237: =IF($B237="","",$B237&" · "&IFERROR(VLOOKUP($B237,спрРазделы,2,0),"")) -> Р3 · Внутренние строительные работы
A238: РАБ.Р3.4.015 | B238: Р3 | C238: 4 | D238: Комплект антипаника Doorlock на активную створку DL PD800FR-BAR (или аналог по согласованию заказчика) | E238: шт. | F238: 2192.4 | H238: 0 | I238: ТС ЕР | P238: =IF($L238="да",ROUND(N($M238)*$S238,2),"") | Q238: =IF($L238="да",ROUND(N($M238)*$T238,2),"") | R238: =IF($L238="да",N($P238)+N($Q238),"") | S238: =IF($A238="","",IF(AND(LEFT($G238,3)="ДОК",$N238<>""),IFERROR(INDEX(Документация!$E$2:$E$57,MATCH($N238,Документация!$F$2:$F$57,0)),0),N($F238))*(1-MEDIAN(0,N(ДисконтТендер),1))) -> 2192.4 | T238: =IF($A238="","",IF(AND(LEFT($G238,3)="ДОК",$N238<>""),0,IF(AND(LEFT($G238,3)<>"ДОК",$N238<>""),IFERROR(INDEX(МАТЕРИАЛЫ!$H$2:$H$9000,MATCH($N238,МАТЕРИАЛЫ!$L$2:$L$9000,0))*IF(INDEX(МАТЕРИАЛЫ!$I$2:$I$9000,MATCH($N238,МАТЕРИАЛЫ!$L$2:$L$9000,0))="USD",КурсUSD,IF(INDEX(МАТЕРИАЛЫ!$I$2:$I$9000,MATCH($N238,МАТЕРИАЛЫ!$L$2:$L$9000,0))="EUR",КурсEUR,IF(INDEX(МАТЕРИАЛЫ!$I$2:$I$9000,MATCH($N238,МАТЕРИАЛЫ!$L$2:$L$9000,0))="CNY",КурсCNY,1)))*(1+N($H238)/100),0),N($O238))*(1-MEDIAN(0,N(ДисконтТендер),1)))) -> 0 | U238: =IF($L238="да",MAX($U$1:$U237)+1,"") | V238: =IF($A238="","",$B238) -> Р3 | W238: =IF($U238="","",IF($U238=1,1,IF($V238<>IFERROR(INDEX($V$2:$V$1058,MATCH($U238-1,$U$2:$U$1058,0)),"~"),1,0))) | X238: =IF($U238="","",$U238+SUMIFS($W$2:$W$1058,$U$2:$U$1058,"<="&$U238)) | Y238: =IF($A238="","",IF(AND(LEFT($G238,3)="ДОК",$N238<>""),IFERROR(INDEX(Документация!$G$2:$G$57,MATCH($N238,Документация!$F$2:$F$57,0)),$D238),$D238&IF(AND(LEFT($G238,3)<>"ДОК",$N238<>"")," — "&IFERROR(INDEX(МАТЕРИАЛЫ!$C$2:$C$9000,MATCH($N238,МАТЕРИАЛЫ!$L$2:$L$9000,0)),""),""))) -> Комплект антипаника Doorlock на активную створку DL PD800FR-BAR (или аналог по согласованию заказчика) | Z238: =IF($B238="","",$B238&" · "&IFERROR(VLOOKUP($B238,спрРазделы,2,0),"")) -> Р3 · Внутренние строительные работы
A239: РАБ.Р3.4.016 | B239: Р3 | C239: 4 | D239: Монтаж дверного блока деревянного | E239: шт. | F239: 7297.56 | G239: ДВ.ДЕР | H239: 5 | I239: ТС ЕР | P239: =IF($L239="да",ROUND(N($M239)*$S239,2),"") | Q239: =IF($L239="да",ROUND(N($M239)*$T239,2),"") | R239: =IF($L239="да",N($P239)+N($Q239),"") | S239: =IF($A239="","",IF(AND(LEFT($G239,3)="ДОК",$N239<>""),IFERROR(INDEX(Документация!$E$2:$E$57,MATCH($N239,Документация!$F$2:$F$57,0)),0),N($F239))*(1-MEDIAN(0,N(ДисконтТендер),1))) -> 7297.56 | T239: =IF($A239="","",IF(AND(LEFT($G239,3)="ДОК",$N239<>""),0,IF(AND(LEFT($G239,3)<>"ДОК",$N239<>""),IFERROR(INDEX(МАТЕРИАЛЫ!$H$2:$H$9000,MATCH($N239,МАТЕРИАЛЫ!$L$2:$L$9000,0))*IF(INDEX(МАТЕРИАЛЫ!$I$2:$I$9000,MATCH($N239,МАТЕРИАЛЫ!$L$2:$L$9000,0))="USD",КурсUSD,IF(INDEX(МАТЕРИАЛЫ!$I$2:$I$9000,MATCH($N239,МАТЕРИАЛЫ!$L$2:$L$9000,0))="EUR",КурсEUR,IF(INDEX(МАТЕРИАЛЫ!$I$2:$I$9000,MATCH($N239,МАТЕРИАЛЫ!$L$2:$L$9000,0))="CNY",КурсCNY,1)))*(1+N($H239)/100),0),N($O239))*(1-MEDIAN(0,N(ДисконтТендер),1)))) -> 0 | U239: =IF($L239="да",MAX($U$1:$U238)+1,"") | V239: =IF($A239="","",$B239) -> Р3 | W239: =IF($U239="","",IF($U239=1,1,IF($V239<>IFERROR(INDEX($V$2:$V$1058,MATCH($U239-1,$U$2:$U$1058,0)),"~"),1,0))) | X239: =IF($U239="","",$U239+SUMIFS($W$2:$W$1058,$U$2:$U$1058,"<="&$U239)) | Y239: =IF($A239="","",IF(AND(LEFT($G239,3)="ДОК",$N239<>""),IFERROR(INDEX(Документация!$G$2:$G$57,MATCH($N239,Документация!$F$2:$F$57,0)),$D239),$D239&IF(AND(LEFT($G239,3)<>"ДОК",$N239<>"")," — "&IFERROR(INDEX(МАТЕРИАЛЫ!$C$2:$C$9000,MATCH($N239,МАТЕРИАЛЫ!$L$2:$L$9000,0)),""),""))) -> Монтаж дверного блока деревянного | Z239: =IF($B239="","",$B239&" · "&IFERROR(VLOOKUP($B239,спрРазделы,2,0),"")) -> Р3 · Внутренние строительные работы
A240: РАБ.Р3.4.017 | B240: Р3 | C240: 4 | D240: Установка стопора дверного Standers, 3.5х3.2 см, нержавеющая сталь | E240: шт. | F240: 224.46 | G240: ДВ | H240: 5 | I240: ТС ЕР | P240: =IF($L240="да",ROUND(N($M240)*$S240,2),"") | Q240: =IF($L240="да",ROUND(N($M240)*$T240,2),"") | R240: =IF($L240="да",N($P240)+N($Q240),"") | S240: =IF($A240="","",IF(AND(LEFT($G240,3)="ДОК",$N240<>""),IFERROR(INDEX(Документация!$E$2:$E$57,MATCH($N240,Документация!$F$2:$F$57,0)),0),N($F240))*(1-MEDIAN(0,N(ДисконтТендер),1))) -> 224.46 | T240: =IF($A240="","",IF(AND(LEFT($G240,3)="ДОК",$N240<>""),0,IF(AND(LEFT($G240,3)<>"ДОК",$N240<>""),IFERROR(INDEX(МАТЕРИАЛЫ!$H$2:$H$9000,MATCH($N240,МАТЕРИАЛЫ!$L$2:$L$9000,0))*IF(INDEX(МАТЕРИАЛЫ!$I$2:$I$9000,MATCH($N240,МАТЕРИАЛЫ!$L$2:$L$9000,0))="USD",КурсUSD,IF(INDEX(МАТЕРИАЛЫ!$I$2:$I$9000,MATCH($N240,МАТЕРИАЛЫ!$L$2:$L$9000,0))="EUR",КурсEUR,IF(INDEX(МАТЕРИАЛЫ!$I$2:$I$9000,MATCH($N240,МАТЕРИАЛЫ!$L$2:$L$9000,0))="CNY",КурсCNY,1)))*(1+N($H240)/100),0),N($O240))*(1-MEDIAN(0,N(ДисконтТендер),1)))) -> 0 | U240: =IF($L240="да",MAX($U$1:$U239)+1,"") | V240: =IF($A240="","",$B240) -> Р3 | W240: =IF($U240="","",IF($U240=1,1,IF($V240<>IFERROR(INDEX($V$2:$V$1058,MATCH($U240-1,$U$2:$U$1058,0)),"~"),1,0))) | X240: =IF($U240="","",$U240+SUMIFS($W$2:$W$1058,$U$2:$U$1058,"<="&$U240)) | Y240: =IF($A240="","",IF(AND(LEFT($G240,3)="ДОК",$N240<>""),IFERROR(INDEX(Документация!$G$2:$G$57,MATCH($N240,Документация!$F$2:$F$57,0)),$D240),$D240&IF(AND(LEFT($G240,3)<>"ДОК",$N240<>"")," — "&IFERROR(INDEX(МАТЕРИАЛЫ!$C$2:$C$9000,MATCH($N240,МАТЕРИАЛЫ!$L$2:$L$9000,0)),""),""))) -> Установка стопора дверного Standers, 3.5х3.2 см, нержавеющая сталь | Z240: =IF($B240="","",$B240&" · "&IFERROR(VLOOKUP($B240,спрРазделы,2,0),"")) -> Р3 · Внутренние строительные работы
A241: РАБ.Р3.4.018 | B241: Р3 | C241: 4 | D241: Монтаж оконного блока / светопрозрачной конструкции | E241: м2 | F241: 2750 | G241: ОКНО | H241: 5 | I241: ТС ЕР | P241: =IF($L241="да",ROUND(N($M241)*$S241,2),"") | Q241: =IF($L241="да",ROUND(N($M241)*$T241,2),"") | R241: =IF($L241="да",N($P241)+N($Q241),"") | S241: =IF($A241="","",IF(AND(LEFT($G241,3)="ДОК",$N241<>""),IFERROR(INDEX(Документация!$E$2:$E$57,MATCH($N241,Документация!$F$2:$F$57,0)),0),N($F241))*(1-MEDIAN(0,N(ДисконтТендер),1))) -> 2750 | T241: =IF($A241="","",IF(AND(LEFT($G241,3)="ДОК",$N241<>""),0,IF(AND(LEFT($G241,3)<>"ДОК",$N241<>""),IFERROR(INDEX(МАТЕРИАЛЫ!$H$2:$H$9000,MATCH($N241,МАТЕРИАЛЫ!$L$2:$L$9000,0))*IF(INDEX(МАТЕРИАЛЫ!$I$2:$I$9000,MATCH($N241,МАТЕРИАЛЫ!$L$2:$L$9000,0))="USD",КурсUSD,IF(INDEX(МАТЕРИАЛЫ!$I$2:$I$9000,MATCH($N241,МАТЕРИАЛЫ!$L$2:$L$9000,0))="EUR",КурсEUR,IF(INDEX(МАТЕРИАЛЫ!$I$2:$I$9000,MATCH($N241,МАТЕРИАЛЫ!$L$2:$L$9000,0))="CNY",КурсCNY,1)))*(1+N($H241)/100),0),N($O241))*(1-MEDIAN(0,N(ДисконтТендер),1)))) -> 0 | U241: =IF($L241="да",MAX($U$1:$U240)+1,"") | V241: =IF($A241="","",$B241) -> Р3 | W241: =IF($U241="","",IF($U241=1,1,IF($V241<>IFERROR(INDEX($V$2:$V$1058,MATCH($U241-1,$U$2:$U$1058,0)),"~"),1,0))) | X241: =IF($U241="","",$U241+SUMIFS($W$2:$W$1058,$U$2:$U$1058,"<="&$U241)) | Y241: =IF($A241="","",IF(AND(LEFT($G241,3)="ДОК",$N241<>""),IFERROR(INDEX(Документация!$G$2:$G$57,MATCH($N241,Документация!$F$2:$F$57,0)),$D241),$D241&IF(AND(LEFT($G241,3)<>"ДОК",$N241<>"")," — "&IFERROR(INDEX(МАТЕРИАЛЫ!$C$2:$C$9000,MATCH($N241,МАТЕРИАЛЫ!$L$2:$L$9000,0)),""),""))) -> Монтаж оконного блока / светопрозрачной конструкции | Z241: =IF($B241="","",$B241&" · "&IFERROR(VLOOKUP($B241,спрРазделы,2,0),"")) -> Р3 · Внутренние строительные работы
A242: РАБ.Р3.4.019 | B242: Р3 | C242: 4 | D242: Окраска поверхности | E242: м2 | F242: 1252.8 | G242: КРАСКА | H242: 5 | I242: ТС ЕР | P242: =IF($L242="да",ROUND(N($M242)*$S242,2),"") | Q242: =IF($L242="да",ROUND(N($M242)*$T242,2),"") | R242: =IF($L242="да",N($P242)+N($Q242),"") | S242: =IF($A242="","",IF(AND(LEFT($G242,3)="ДОК",$N242<>""),IFERROR(INDEX(Документация!$E$2:$E$57,MATCH($N242,Документация!$F$2:$F$57,0)),0),N($F242))*(1-MEDIAN(0,N(ДисконтТендер),1))) -> 1252.8 | T242: =IF($A242="","",IF(AND(LEFT($G242,3)="ДОК",$N242<>""),0,IF(AND(LEFT($G242,3)<>"ДОК",$N242<>""),IFERROR(INDEX(МАТЕРИАЛЫ!$H$2:$H$9000,MATCH($N242,МАТЕРИАЛЫ!$L$2:$L$9000,0))*IF(INDEX(МАТЕРИАЛЫ!$I$2:$I$9000,MATCH($N242,МАТЕРИАЛЫ!$L$2:$L$9000,0))="USD",КурсUSD,IF(INDEX(МАТЕРИАЛЫ!$I$2:$I$9000,MATCH($N242,МАТЕРИАЛЫ!$L$2:$L$9000,0))="EUR",КурсEUR,IF(INDEX(МАТЕРИАЛЫ!$I$2:$I$9000,MATCH($N242,МАТЕРИАЛЫ!$L$2:$L$9000,0))="CNY",КурсCNY,1)))*(1+N($H242)/100),0),N($O242))*(1-MEDIAN(0,N(ДисконтТендер),1)))) -> 0 | U242: =IF($L242="да",MAX($U$1:$U241)+1,"") | V242: =IF($A242="","",$B242) -> Р3 | W242: =IF($U242="","",IF($U242=1,1,IF($V242<>IFERROR(INDEX($V$2:$V$1058,MATCH($U242-1,$U$2:$U$1058,0)),"~"),1,0))) | X242: =IF($U242="","",$U242+SUMIFS($W$2:$W$1058,$U$2:$U$1058,"<="&$U242)) | Y242: =IF($A242="","",IF(AND(LEFT($G242,3)="ДОК",$N242<>""),IFERROR(INDEX(Документация!$G$2:$G$57,MATCH($N242,Документация!$F$2:$F$57,0)),$D242),$D242&IF(AND(LEFT($G242,3)<>"ДОК",$N242<>"")," — "&IFERROR(INDEX(МАТЕРИАЛЫ!$C$2:$C$9000,MATCH($N242,МАТЕРИАЛЫ!$L$2:$L$9000,0)),""),""))) -> Окраска поверхности | Z242: =IF($B242="","",$B242&" · "&IFERROR(VLOOKUP($B242,спрРазделы,2,0),"")) -> Р3 · Внутренние строительные работы
A243: РАБ.Р3.4.020 | B243: Р3 | C243: 4 | D243: Установка рулонных штор | E243: м2 | F243: 220 | G243: ЖАЛЮЗИ | H243: 5 | I243: ТС ЕР | P243: =IF($L243="да",ROUND(N($M243)*$S243,2),"") | Q243: =IF($L243="да",ROUND(N($M243)*$T243,2),"") | R243: =IF($L243="да",N($P243)+N($Q243),"") | S243: =IF($A243="","",IF(AND(LEFT($G243,3)="ДОК",$N243<>""),IFERROR(INDEX(Документация!$E$2:$E$57,MATCH($N243,Документация!$F$2:$F$57,0)),0),N($F243))*(1-MEDIAN(0,N(ДисконтТендер),1))) -> 220 | T243: =IF($A243="","",IF(AND(LEFT($G243,3)="ДОК",$N243<>""),0,IF(AND(LEFT($G243,3)<>"ДОК",$N243<>""),IFERROR(INDEX(МАТЕРИАЛЫ!$H$2:$H$9000,MATCH($N243,МАТЕРИАЛЫ!$L$2:$L$9000,0))*IF(INDEX(МАТЕРИАЛЫ!$I$2:$I$9000,MATCH($N243,МАТЕРИАЛЫ!$L$2:$L$9000,0))="USD",КурсUSD,IF(INDEX(МАТЕРИАЛЫ!$I$2:$I$9000,MATCH($N243,МАТЕРИАЛЫ!$L$2:$L$9000,0))="EUR",КурсEUR,IF(INDEX(МАТЕРИАЛЫ!$I$2:$I$9000,MATCH($N243,МАТЕРИАЛЫ!$L$2:$L$9000,0))="CNY",КурсCNY,1)))*(1+N($H243)/100),0),N($O243))*(1-MEDIAN(0,N(ДисконтТендер),1)))) -> 0 | U243: =IF($L243="да",MAX($U$1:$U242)+1,"") | V243: =IF($A243="","",$B243) -> Р3 | W243: =IF($U243="","",IF($U243=1,1,IF($V243<>IFERROR(INDEX($V$2:$V$1058,MATCH($U243-1,$U$2:$U$1058,0)),"~"),1,0))) | X243: =IF($U243="","",$U243+SUMIFS($W$2:$W$1058,$U$2:$U$1058,"<="&$U243)) | Y243: =IF($A243="","",IF(AND(LEFT($G243,3)="ДОК",$N243<>""),IFERROR(INDEX(Документация!$G$2:$G$57,MATCH($N243,Документация!$F$2:$F$57,0)),$D243),$D243&IF(AND(LEFT($G243,3)<>"ДОК",$N243<>"")," — "&IFERROR(INDEX(МАТЕРИАЛЫ!$C$2:$C$9000,MATCH($N243,МАТЕРИАЛЫ!$L$2:$L$9000,0)),""),""))) -> Установка рулонных штор | Z243: =IF($B243="","",$B243&" · "&IFERROR(VLOOKUP($B243,спрРазделы,2,0),"")) -> Р3 · Внутренние строительные работы
A244: РАБ.Р3.4.021 | B244: Р3 | C244: 4 | D244: Установка жалюзи вертикальных серии Line | E244: м2 | F244: 330 | G244: ЖАЛЮЗИ | H244: 5 | I244: ТС ЕР | P244: =IF($L244="да",ROUND(N($M244)*$S244,2),"") | Q244: =IF($L244="да",ROUND(N($M244)*$T244,2),"") | R244: =IF($L244="да",N($P244)+N($Q244),"") | S244: =IF($A244="","",IF(AND(LEFT($G244,3)="ДОК",$N244<>""),IFERROR(INDEX(Документация!$E$2:$E$57,MATCH($N244,Документация!$F$2:$F$57,0)),0),N($F244))*(1-MEDIAN(0,N(ДисконтТендер),1))) -> 330 | T244: =IF($A244="","",IF(AND(LEFT($G244,3)="ДОК",$N244<>""),0,IF(AND(LEFT($G244,3)<>"ДОК",$N244<>""),IFERROR(INDEX(МАТЕРИАЛЫ!$H$2:$H$9000,MATCH($N244,МАТЕРИАЛЫ!$L$2:$L$9000,0))*IF(INDEX(МАТЕРИАЛЫ!$I$2:$I$9000,MATCH($N244,МАТЕРИАЛЫ!$L$2:$L$9000,0))="USD",КурсUSD,IF(INDEX(МАТЕРИАЛЫ!$I$2:$I$9000,MATCH($N244,МАТЕРИАЛЫ!$L$2:$L$9000,0))="EUR",КурсEUR,IF(INDEX(МАТЕРИАЛЫ!$I$2:$I$9000,MATCH($N244,МАТЕРИАЛЫ!$L$2:$L$9000,0))="CNY",КурсCNY,1)))*(1+N($H244)/100),0),N($O244))*(1-MEDIAN(0,N(ДисконтТендер),1)))) -> 0 | U244: =IF($L244="да",MAX($U$1:$U243)+1,"") | V244: =IF($A244="","",$B244) -> Р3 | W244: =IF($U244="","",IF($U244=1,1,IF($V244<>IFERROR(INDEX($V$2:$V$1058,MATCH($U244-1,$U$2:$U$1058,0)),"~"),1,0))) | X244: =IF($U244="","",$U244+SUMIFS($W$2:$W$1058,$U$2:$U$1058,"<="&$U244)) | Y244: =IF($A244="","",IF(AND(LEFT($G244,3)="ДОК",$N244<>""),IFERROR(INDEX(Документация!$G$2:$G$57,MATCH($N244,Документация!$F$2:$F$57,0)),$D244),$D244&IF(AND(LEFT($G244,3)<>"ДОК",$N244<>"")," — "&IFERROR(INDEX(МАТЕРИАЛЫ!$C$2:$C$9000,MATCH($N244,МАТЕРИАЛЫ!$L$2:$L$9000,0)),""),""))) -> Установка жалюзи вертикальных серии Line | Z244: =IF($B244="","",$B244&" · "&IFERROR(VLOOKUP($B244,спрРазделы,2,0),"")) -> Р3 · Внутренние строительные работы
A245: РАБ.Р3.4.022 | B245: Р3 | C245: 4 | D245: Установка подоконной доски | E245: м.п. | F245: 888.25 | G245: ПОДОК | H245: 5 | I245: ТС ЕР | P245: =IF($L245="да",ROUND(N($M245)*$S245,2),"") | Q245: =IF($L245="да",ROUND(N($M245)*$T245,2),"") | R245: =IF($L245="да",N($P245)+N($Q245),"") | S245: =IF($A245="","",IF(AND(LEFT($G245,3)="ДОК",$N245<>""),IFERROR(INDEX(Документация!$E$2:$E$57,MATCH($N245,Документация!$F$2:$F$57,0)),0),N($F245))*(1-MEDIAN(0,N(ДисконтТендер),1))) -> 888.25 | T245: =IF($A245="","",IF(AND(LEFT($G245,3)="ДОК",$N245<>""),0,IF(AND(LEFT($G245,3)<>"ДОК",$N245<>""),IFERROR(INDEX(МАТЕРИАЛЫ!$H$2:$H$9000,MATCH($N245,МАТЕРИАЛЫ!$L$2:$L$9000,0))*IF(INDEX(МАТЕРИАЛЫ!$I$2:$I$9000,MATCH($N245,МАТЕРИАЛЫ!$L$2:$L$9000,0))="USD",КурсUSD,IF(INDEX(МАТЕРИАЛЫ!$I$2:$I$9000,MATCH($N245,МАТЕРИАЛЫ!$L$2:$L$9000,0))="EUR",КурсEUR,IF(INDEX(МАТЕРИАЛЫ!$I$2:$I$9000,MATCH($N245,МАТЕРИАЛЫ!$L$2:$L$9000,0))="CNY",КурсCNY,1)))*(1+N($H245)/100),0),N($O245))*(1-MEDIAN(0,N(ДисконтТендер),1)))) -> 0 | U245: =IF($L245="да",MAX($U$1:$U244)+1,"") | V245: =IF($A245="","",$B245) -> Р3 | W245: =IF($U245="","",IF($U245=1,1,IF($V245<>IFERROR(INDEX($V$2:$V$1058,MATCH($U245-1,$U$2:$U$1058,0)),"~"),1,0))) | X245: =IF($U245="","",$U245+SUMIFS($W$2:$W$1058,$U$2:$U$1058,"<="&$U245)) | Y245: =IF($A245="","",IF(AND(LEFT($G245,3)="ДОК",$N245<>""),IFERROR(INDEX(Документация!$G$2:$G$57,MATCH($N245,Документация!$F$2:$F$57,0)),$D245),$D245&IF(AND(LEFT($G245,3)<>"ДОК",$N245<>"")," — "&IFERROR(INDEX(МАТЕРИАЛЫ!$C$2:$C$9000,MATCH($N245,МАТЕРИАЛЫ!$L$2:$L$9000,0)),""),""))) -> Установка подоконной доски | Z245: =IF($B245="","",$B245&" · "&IFERROR(VLOOKUP($B245,спрРазделы,2,0),"")) -> Р3 · Внутренние строительные работы
A246: РАБ.Р3.4.023 | B246: Р3 | C246: 4 | D246: Установка оконных отливов с окраской по RAL | E246: м.п. | F246: 599.39 | G246: КРАСКА | H246: 5 | I246: ТС ЕР | P246: =IF($L246="да",ROUND(N($M246)*$S246,2),"") | Q246: =IF($L246="да",ROUND(N($M246)*$T246,2),"") | R246: =IF($L246="да",N($P246)+N($Q246),"") | S246: =IF($A246="","",IF(AND(LEFT($G246,3)="ДОК",$N246<>""),IFERROR(INDEX(Документация!$E$2:$E$57,MATCH($N246,Документация!$F$2:$F$57,0)),0),N($F246))*(1-MEDIAN(0,N(ДисконтТендер),1))) -> 599.39 | T246: =IF($A246="","",IF(AND(LEFT($G246,3)="ДОК",$N246<>""),0,IF(AND(LEFT($G246,3)<>"ДОК",$N246<>""),IFERROR(INDEX(МАТЕРИАЛЫ!$H$2:$H$9000,MATCH($N246,МАТЕРИАЛЫ!$L$2:$L$9000,0))*IF(INDEX(МАТЕРИАЛЫ!$I$2:$I$9000,MATCH($N246,МАТЕРИАЛЫ!$L$2:$L$9000,0))="USD",КурсUSD,IF(INDEX(МАТЕРИАЛЫ!$I$2:$I$9000,MATCH($N246,МАТЕРИАЛЫ!$L$2:$L$9000,0))="EUR",КурсEUR,IF(INDEX(МАТЕРИАЛЫ!$I$2:$I$9000,MATCH($N246,МАТЕРИАЛЫ!$L$2:$L$9000,0))="CNY",КурсCNY,1)))*(1+N($H246)/100),0),N($O246))*(1-MEDIAN(0,N(ДисконтТендер),1)))) -> 0 | U246: =IF($L246="да",MAX($U$1:$U245)+1,"") | V246: =IF($A246="","",$B246) -> Р3 | W246: =IF($U246="","",IF($U246=1,1,IF($V246<>IFERROR(INDEX($V$2:$V$1058,MATCH($U246-1,$U$2:$U$1058,0)),"~"),1,0))) | X246: =IF($U246="","",$U246+SUMIFS($W$2:$W$1058,$U$2:$U$1058,"<="&$U246)) | Y246: =IF($A246="","",IF(AND(LEFT($G246,3)="ДОК",$N246<>""),IFERROR(INDEX(Документация!$G$2:$G$57,MATCH($N246,Документация!$F$2:$F$57,0)),$D246),$D246&IF(AND(LEFT($G246,3)<>"ДОК",$N246<>"")," — "&IFERROR(INDEX(МАТЕРИАЛЫ!$C$2:$C$9000,MATCH($N246,МАТЕРИАЛЫ!$L$2:$L$9000,0)),""),""))) -> Установка оконных отливов с окраской по RAL | Z246: =IF($B246="","",$B246&" · "&IFERROR(VLOOKUP($B246,спрРазделы,2,0),"")) -> Р3 · Внутренние строительные работы
A247: РАБ.Р3.4.024 | B247: Р3 | C247: 4 | D247: Оклейка окон, стеклянных поверхностей дверных полотен пленкой класса защиты А3 | E247: м2 | F247: 2000 | G247: ПЛЁНКА | H247: 5 | I247: ТС ЕР | P247: =IF($L247="да",ROUND(N($M247)*$S247,2),"") | Q247: =IF($L247="да",ROUND(N($M247)*$T247,2),"") | R247: =IF($L247="да",N($P247)+N($Q247),"") | S247: =IF($A247="","",IF(AND(LEFT($G247,3)="ДОК",$N247<>""),IFERROR(INDEX(Документация!$E$2:$E$57,MATCH($N247,Документация!$F$2:$F$57,0)),0),N($F247))*(1-MEDIAN(0,N(ДисконтТендер),1))) -> 2000 | T247: =IF($A247="","",IF(AND(LEFT($G247,3)="ДОК",$N247<>""),0,IF(AND(LEFT($G247,3)<>"ДОК",$N247<>""),IFERROR(INDEX(МАТЕРИАЛЫ!$H$2:$H$9000,MATCH($N247,МАТЕРИАЛЫ!$L$2:$L$9000,0))*IF(INDEX(МАТЕРИАЛЫ!$I$2:$I$9000,MATCH($N247,МАТЕРИАЛЫ!$L$2:$L$9000,0))="USD",КурсUSD,IF(INDEX(МАТЕРИАЛЫ!$I$2:$I$9000,MATCH($N247,МАТЕРИАЛЫ!$L$2:$L$9000,0))="EUR",КурсEUR,IF(INDEX(МАТЕРИАЛЫ!$I$2:$I$9000,MATCH($N247,МАТЕРИАЛЫ!$L$2:$L$9000,0))="CNY",КурсCNY,1)))*(1+N($H247)/100),0),N($O247))*(1-MEDIAN(0,N(ДисконтТендер),1)))) -> 0 | U247: =IF($L247="да",MAX($U$1:$U246)+1,"") | V247: =IF($A247="","",$B247) -> Р3 | W247: =IF($U247="","",IF($U247=1,1,IF($V247<>IFERROR(INDEX($V$2:$V$1058,MATCH($U247-1,$U$2:$U$1058,0)),"~"),1,0))) | X247: =IF($U247="","",$U247+SUMIFS($W$2:$W$1058,$U$2:$U$1058,"<="&$U247)) | Y247: =IF($A247="","",IF(AND(LEFT($G247,3)="ДОК",$N247<>""),IFERROR(INDEX(Документация!$G$2:$G$57,MATCH($N247,Документация!$F$2:$F$57,0)),$D247),$D247&IF(AND(LEFT($G247,3)<>"ДОК",$N247<>"")," — "&IFERROR(INDEX(МАТЕРИАЛЫ!$C$2:$C$9000,MATCH($N247,МАТЕРИАЛЫ!$L$2:$L$9000,0)),""),""))) -> Оклейка окон, стеклянных поверхностей дверных полотен пленкой класса защиты А3 | Z247: =IF($B247="","",$B247&" · "&IFERROR(VLOOKUP($B247,спрРазделы,2,0),"")) -> Р3 · Внутренние строительные работы
...

Sheet МАТЕРИАЛЫ
A1: Код_материала | B1: Группа | C1: Наименование | D1: Артикул | E1: Производитель | F1: Поставщик | G1: Ед_изм | H1: Цена | I1: Валюта | J1: Дата изм. цены | K1: Кто изменил | L1: КОД — Наименование (служебный)
A2: МАТ.VRF.ВНУТ.001 | B2: VRF.ВНУТ | C2: BMS interface HCM-04 | D2: HCM-04 | E2: Haier | F2: Хайер | G2: шт | H2: 1791.3 | I2: USD | L2: МАТ.VRF.ВНУТ.001 — BMS interface HCM-04
A3: МАТ.VRF.ВНУТ.002 | B3: VRF.ВНУТ | C3: Inverter Protocol Adapter IGU02 | D3: IGU02 | E3: Haier | F3: Хайер | G3: шт | H3: 294 | I3: USD | L3: МАТ.VRF.ВНУТ.002 — Inverter Protocol Adapter IGU02
A4: МАТ.VRF.ВНУТ.003 | B4: VRF.ВНУТ | C4: MDVI3-100C4VR12D | E4: MDV | F4: Дженерал-Трейд (АЯК) | G4: шт | H4: 1014.13 | I4: USD | L4: МАТ.VRF.ВНУТ.003 — MDVI3-100C4VR12D
A5: МАТ.VRF.ВНУТ.004 | B5: VRF.ВНУТ | C5: MDVI3-100CFVR12D | E5: MDV | F5: Дженерал-Трейд (АЯК) | G5: шт | H5: 1135.82 | I5: USD | L5: МАТ.VRF.ВНУТ.004 — MDVI3-100CFVR12D
A6: МАТ.VRF.ВНУТ.005 | B6: VRF.ВНУТ | C6: MDVI3-112C4VR12D | E6: MDV | F6: Дженерал-Трейд (АЯК) | G6: шт | H6: 1182.36 | I6: USD | L6: МАТ.VRF.ВНУТ.005 — MDVI3-112C4VR12D
A7: МАТ.VRF.ВНУТ.006 | B7: VRF.ВНУТ | C7: MDVI3-112CFVR12D | E7: MDV | F7: Дженерал-Трейд (АЯК) | G7: шт | H7: 1166.14 | I7: USD | L7: МАТ.VRF.ВНУТ.006 — MDVI3-112CFVR12D
A8: МАТ.VRF.ВНУТ.007 | B8: VRF.ВНУТ | C8: MDVI3-112D1VR12D | E8: MDV | F8: Дженерал-Трейд (АЯК) | G8: шт | H8: 877.49 | I8: USD | L8: МАТ.VRF.ВНУТ.007 — MDVI3-112D1VR12D
A9: МАТ.VRF.ВНУТ.008 | B9: VRF.ВНУТ | C9: MDVI3-112D2VR12D | E9: MDV | F9: Дженерал-Трейд (АЯК) | G9: шт | H9: 802.76 | I9: USD | L9: МАТ.VRF.ВНУТ.008 — MDVI3-112D2VR12D
A10: МАТ.VRF.ВНУТ.009 | B10: VRF.ВНУТ | C10: MDVI3-112D3VR12D | E10: MDV | F10: Дженерал-Трейд (АЯК) | G10: шт | H10: 1099.95 | I10: USD | L10: МАТ.VRF.ВНУТ.009 — MDVI3-112D3VR12D
A11: МАТ.VRF.ВНУТ.010 | B11: VRF.ВНУТ | C11: MDVI3-125CFVR12D | E11: MDV | F11: Дженерал-Трейд (АЯК) | G11: шт | H11: 1221.22 | I11: USD | L11: МАТ.VRF.ВНУТ.010 — MDVI3-125CFVR12D
A12: МАТ.VRF.ВНУТ.011 | B12: VRF.ВНУТ | C12: MDVI3-125D2VR12D | E12: MDV | F12: Дженерал-Трейд (АЯК) | G12: шт | H12: 821.12 | I12: USD | L12: МАТ.VRF.ВНУТ.011 — MDVI3-125D2VR12D
A13: МАТ.VRF.ВНУТ.012 | B13: VRF.ВНУТ | C13: MDVI3-125D3VR12D | E13: MDV | F13: Дженерал-Трейд (АЯК) | G13: шт | H13: 1133.26 | I13: USD | L13: МАТ.VRF.ВНУТ.012 — MDVI3-125D3VR12D
A14: МАТ.VRF.ВНУТ.013 | B14: VRF.ВНУТ | C14: MDVI3-140C4VR12D | E14: MDV | F14: Дженерал-Трейд (АЯК) | G14: шт | H14: 1228.91 | I14: USD | L14: МАТ.VRF.ВНУТ.013 — MDVI3-140C4VR12D
A15: МАТ.VRF.ВНУТ.014 | B15: VRF.ВНУТ | C15: MDVI3-140CFVR12D | E15: MDV | F15: Дженерал-Трейд (АЯК) | G15: шт | H15: 1233.6 | I15: USD | L15: МАТ.VRF.ВНУТ.014 — MDVI3-140CFVR12D
... A134: МАТ.VRF.ВНУТ.133 | B134: VRF.ВНУТ | C134: MDVI3-90OAVR12D(A) | E134: MDV | F134: Дженерал-Трейд (АЯК) | G134: шт | H134: 1026.08 | I134: USD | L134: МАТ.VRF.ВНУТ.133 — MDVI3-90OAVR12D(A)
A135: МАТ.VRF.ВНУТ.134 | B135: VRF.ВНУТ | C135: WI-FI модуль для управления центральным пультом HC-SA164DBT HI-WA164DBI | D135: HI-WA164DBI | E135: Haier | F135: Хайер | G135: шт | H135: 39.9 | I135: USD | L135: МАТ.VRF.ВНУТ.134 — WI-FI модуль для управления центральным пультом HC-SA164DBT HI-WA164DBI
A136: МАТ.VRF.ВНУТ.135 | B136: VRF.ВНУТ | C136: Жалюзи к канальным блокам серии AD…MSERA P1B-1210IA | D136: P1B-1210IA | E136: Haier | F136: Хайер | G136: шт | H136: 61.95 | I136: USD | L136: МАТ.VRF.ВНУТ.135 — Жалюзи к канальным блокам серии AD…MSERA P1B-1210IA
A137: МАТ.VRF.ВНУТ.136 | B137: VRF.ВНУТ | C137: Жалюзи к канальным блокам серии AD…MSERA P1B-1210IA(D) с дисплеем | D137: P1B-1210IA(D) с дисплеем | E137: Haier | F137: Хайер | G137: шт | H137: 88.2 | I137: USD | L137: МАТ.VRF.ВНУТ.136 — Жалюзи к канальным блокам серии AD…MSERA P1B-1210IA(D) с дисплеем
A138: МАТ.VRF.ВНУТ.137 | B138: VRF.ВНУТ | C138: Жалюзи к канальным блокам серии AD…MSERA P1B-890IA | D138: P1B-890IA | E138: Haier | F138: Хайер | G138: шт | H138: 51.45 | I138: USD | L138: МАТ.VRF.ВНУТ.137 — Жалюзи к канальным блокам серии AD…MSERA P1B-890IA
A139: МАТ.VRF.ВНУТ.138 | B139: VRF.ВНУТ | C139: Жалюзи к канальным блокам серии AD…MSERA P1B-890IA(D) с дисплеем | D139: P1B-890IA(D) с дисплеем | E139: Haier | F139: Хайер | G139: шт | H139: 72.45 | I139: USD | L139: МАТ.VRF.ВНУТ.138 — Жалюзи к канальным блокам серии AD…MSERA P1B-890IA(D) с дисплеем
A140: МАТ.VRF.ВНУТ.139 | B140: VRF.ВНУТ | C140: ИК-пульт YR-HQS01 | D140: YR-HQS01 | E140: Haier | F140: Хайер | G140: шт | H140: 27.3 | I140: USD | L140: МАТ.VRF.ВНУТ.139 — ИК-пульт YR-HQS01
A141: МАТ.VRF.ВНУТ.140 | B141: VRF.ВНУТ | C141: ИК-пульт YR-HRS01 | D141: YR-HRS01 | E141: Haier | F141: Хайер | G141: шт | H141: 13.65 | I141: USD | L141: МАТ.VRF.ВНУТ.140 — ИК-пульт YR-HRS01
A142: МАТ.VRF.ВНУТ.141 | B142: VRF.ВНУТ | C142: Канальный 12K AD122MJERA | D142: AD122MJERA | E142: Haier | F142: Хайер | G142: шт | H142: 567 | I142: USD | L142: МАТ.VRF.ВНУТ.141 — Канальный 12K AD122MJERA
A143: МАТ.VRF.ВНУТ.142 | B143: VRF.ВНУТ | C143: Канальный 12K AD122MJERAD | D143: AD122MJERAD | E143: Haier | F143: Хайер | G143: шт | H143: 748.65 | I143: USD | L143: МАТ.VRF.ВНУТ.142 — Канальный 12K AD122MJERAD
A144: МАТ.VRF.ВНУТ.143 | B144: VRF.ВНУТ | C144: Канальный 12K AD122MSERA | D144: AD122MSERA | E144: Haier | F144: Хайер | G144: шт | H144: 340.2 | I144: USD | L144: МАТ.VRF.ВНУТ.143 — Канальный 12K AD122MSERA
A145: МАТ.VRF.ВНУТ.144 | B145: VRF.ВНУТ | C145: Канальный 12K AD122MSERA (D) | D145: AD122MSERA (D) | E145: Haier | F145: Хайер | G145: шт | H145: 442.05 | I145: USD | L145: МАТ.VRF.ВНУТ.144 — Канальный 12K AD122MSERA (D)
A146: МАТ.VRF.ВНУТ.145 | B146: VRF.ВНУТ | C146: Канальный 16K AD162MJERA | D146: AD162MJERA | E146: Haier | F146: Хайер | G146: шт | H146: 590.1 | I146: USD | L146: МАТ.VRF.ВНУТ.145 — Канальный 16K AD162MJERA
... A259: МАТ.VRF.ВНУТ.258 | B259: VRF.ВНУТ | C259: Шлюз для интеграции с Modbus new HA-MA164ADB | D259: HA-MA164ADB | E259: Haier | F259: Хайер | G259: шт | H259: 328.65 | I259: USD | L259: МАТ.VRF.ВНУТ.258 — Шлюз для интеграции с Modbus new HA-MA164ADB
A260: МАТ.VRF.НАР.001 | B260: VRF.НАР | C260: MDV-V81010V2R1A(MA) | E260: MDV | F260: Дженерал-Трейд (АЯК) | G260: шт | H260: 20867.92 | I260: USD | L260: МАТ.VRF.НАР.001 — MDV-V81010V2R1A(MA)
A261: МАТ.VRF.НАР.002 | B261: VRF.НАР | C261: MDV-V81060V2R1A(MA) | E261: MDV | F261: Дженерал-Трейд (АЯК) | G261: шт | H261: 22505.46 | I261: USD | L261: МАТ.VRF.НАР.002 — MDV-V81060V2R1A(MA)
A262: МАТ.VRF.НАР.003 | B262: VRF.НАР | C262: MDV-V81120V2R1A(MA) | E262: MDV | F262: Дженерал-Трейд (АЯК) | G262: шт | H262: 23020 | I262: USD | L262: МАТ.VRF.НАР.003 — MDV-V81120V2R1A(MA)
A263: МАТ.VRF.НАР.004 | B263: VRF.НАР | C263: MDV-V8252V2R1A(MA) | E263: MDV | F263: Дженерал-Трейд (АЯК) | G263: шт | H263: 7779.94 | I263: USD | L263: МАТ.VRF.НАР.004 — MDV-V8252V2R1A(MA)
A264: МАТ.VRF.НАР.005 | B264: VRF.НАР | C264: MDV-V8280V2R1A(MA) | E264: MDV | F264: Дженерал-Трейд (АЯК) | G264: шт | H264: 8384.57 | I264: USD | L264: МАТ.VRF.НАР.005 — MDV-V8280V2R1A(MA)
A265: МАТ.VRF.НАР.006 | B265: VRF.НАР | C265: MDV-V8335V2R1A(MA) | E265: MDV | F265: Дженерал-Трейд (АЯК) | G265: шт | H265: 8922.59 | I265: USD | L265: МАТ.VRF.НАР.006 — MDV-V8335V2R1A(MA)
A266: МАТ.VRF.НАР.007 | B266: VRF.НАР | C266: MDV-V8400V2R1A(MA) | E266: MDV | F266: Дженерал-Трейд (АЯК) | G266: шт | H266: 10215.12 | I266: USD | L266: МАТ.VRF.НАР.007 — MDV-V8400V2R1A(MA)
A267: МАТ.VRF.НАР.008 | B267: VRF.НАР | C267: MDV-V8450V2R1A(MA) | E267: MDV | F267: Дженерал-Трейд (АЯК) | G267: шт | H267: 10720.26 | I267: USD | L267: МАТ.VRF.НАР.008 — MDV-V8450V2R1A(MA)
A268: МАТ.VRF.НАР.009 | B268: VRF.НАР | C268: MDV-V8500V2R1A(MA) | E268: MDV | F268: Дженерал-Трейд (АЯК) | G268: шт | H268: 12516.65 | I268: USD | L268: МАТ.VRF.НАР.009 — MDV-V8500V2R1A(MA)
A269: МАТ.VRF.НАР.010 | B269: VRF.НАР | C269: MDV-V8560V2R1A(MA) | E269: MDV | F269: Дженерал-Трейд (АЯК) | G269: шт | H269: 13211.81 | I269: USD | L269: МАТ.VRF.НАР.010 — MDV-V8560V2R1A(MA)
A270: МАТ.VRF.НАР.011 | B270: VRF.НАР | C270: MDV-V8615V2R1A(MA) | E270: MDV | F270: Дженерал-Трейд (АЯК) | G270: шт | H270: 14202.45 | I270: USD | L270: МАТ.VRF.НАР.011 — MDV-V8615V2R1A(MA)
A271: МАТ.VRF.НАР.012 | B271: VRF.НАР | C271: MDV-V8670V2R1A(MA) | E271: MDV | F271: Дженерал-Трейд (АЯК) | G271: шт | H271: 16027.87 | I271: USD | L271: МАТ.VRF.НАР.012 — MDV-V8670V2R1A(MA)
... A332: МАТ.VRF.НАР.073 | B332: VRF.НАР | C332: MDVO-VCM850V2R1A | E332: MDV | F332: Дженерал-Трейд (АЯК) | G332: шт | H332: 10031.08 | I332: USD | L332: МАТ.VRF.НАР.073 — MDVO-VCM850V2R1A
A333: МАТ.VRF.НАР.074 | B333: VRF.НАР | C333: MRV III - S Внешний блок 10HP AU10NFKERA | D333: AU10NFKERA | E333: Haier | F333: Хайер | G333: шт | H333: 3265.5 | I333: USD | L333: МАТ.VRF.НАР.074 — MRV III - S Внешний блок 10HP AU10NFKERA
A334: МАТ.VRF.НАР.075 | B334: VRF.НАР | C334: MRV III - S Внешний блок 12HP AU12NFKERA | D334: AU12NFKERA | E334: Haier | F334: Хайер | G334: шт | H334: 3378.9 | I334: USD | L334: МАТ.VRF.НАР.075 — MRV III - S Внешний блок 12HP AU12NFKERA
A335: МАТ.VRF.НАР.076 | B335: VRF.НАР | C335: MRV III - S Внешний блок 3HP AU032FSEUA | D335: AU032FSEUA | E335: Haier | F335: Хайер | G335: шт | H335: 1304.1 | I335: USD | L335: МАТ.VRF.НАР.076 — MRV III - S Внешний блок 3HP AU032FSEUA
A336: МАТ.VRF.НАР.077 | B336: VRF.НАР | C336: MRV III - S Внешний блок 4HP AU042FNERA | D336: AU042FNERA | E336: Haier | F336: Хайер | G336: шт | H336: 2064.3 | I336: USD | L336: МАТ.VRF.НАР.077 — MRV III - S Внешний блок 4HP AU042FNERA
A337: МАТ.VRF.НАР.078 | B337: VRF.НАР | C337: MRV III - S Внешний блок 4HP AU042FPERA | D337: AU042FPERA | E337: Haier | F337: Хайер | G337: шт | H337: 2313.15 | I337: USD | L337: МАТ.VRF.НАР.078 — MRV III - S Внешний блок 4HP AU042FPERA
A338: МАТ.VRF.НАР.079 | B338: VRF.НАР | C338: MRV III - S Внешний блок 4HP AU04IFPERA | D338: AU04IFPERA | E338: Haier | F338: Хайер | G338: шт | H338: 2313.15 | I338: USD | L338: МАТ.VRF.НАР.079 — MRV III - S Внешний блок 4HP AU04IFPERA
A339: МАТ.VRF.НАР.080 | B339: VRF.НАР | C339: MRV III - S Внешний блок 5HP AU052FNERA | D339: AU052FNERA | E339: Haier | F339: Хайер | G339: шт | H339: 2074.8 | I339: USD | L339: МАТ.VRF.НАР.080 — MRV III - S Внешний блок 5HP AU052FNERA
A340: МАТ.VRF.НАР.081 | B340: VRF.НАР | C340: MRV III - S Внешний блок 5HP AU052FPERA | D340: AU052FPERA | E340: Haier | F340: Хайер | G340: шт | H340: 2324.7 | I340: USD | L340: МАТ.VRF.НАР.081 — MRV III - S Внешний блок 5HP AU052FPERA
A341: МАТ.VRF.НАР.082 | B341: VRF.НАР | C341: MRV III - S Внешний блок 5HP AU052FPEUA | D341: AU052FPEUA | E341: Haier | F341: Хайер | G341: шт | H341: 2256.45 | I341: USD | L341: МАТ.VRF.НАР.082 — MRV III - S Внешний блок 5HP AU052FPEUA
A342: МАТ.VRF.НАР.083 | B342: VRF.НАР | C342: MRV III - S Внешний блок 5HP AU05IFPERA | D342: AU05IFPERA | E342: Haier | F342: Хайер | G342: шт | H342: 2324.7 | I342: USD | L342: МАТ.VRF.НАР.083 — MRV III - S Внешний блок 5HP AU05IFPERA
A343: МАТ.VRF.НАР.084 | B343: VRF.НАР | C343: MRV III - S Внешний блок 6HP AU062FPERA | D343: AU062FPERA | E343: Haier | F343: Хайер | G343: шт | H343: 2336.25 | I343: USD | L343: МАТ.VRF.НАР.084 — MRV III - S Внешний блок 6HP AU062FPERA
A344: МАТ.VRF.НАР.085 | B344: VRF.НАР | C344: MRV III - S Внешний блок 6HP AU06IFPERA | D344: AU06IFPERA | E344: Haier | F344: Хайер | G344: шт | H344: 2336.25 | I344: USD | L344: МАТ.VRF.НАР.085 — MRV III - S Внешний блок 6HP AU06IFPERA
... A360: МАТ.VRF.НАР.101 | B360: VRF.НАР | C360: Рефнет для наружных блоков MRV V HZG-30B | D360: HZG-30B | E360: Haier | F360: Хайер | G360: шт | H360: 277.2 | I360: USD | L360: МАТ.VRF.НАР.101 — Рефнет для наружных блоков MRV V HZG-30B
A361: МАТ.БРОНЯ.001 | B361: БРОНЯ | C361: Бронестекло ПУз-Бр3 (1000*1000 мм. Видимая часть). По раме 1090х1090 мм без учета лотка. ЛИСТ 2. | F361: СПЕЦ Прожект групп | G361: шт. | H361: 52500 | I361: RUB | L361: МАТ.БРОНЯ.001 — Бронестекло ПУз-Бр3 (1000*1000 мм. Видимая часть). По раме 1090х1090 мм без учета лотка. ЛИСТ 2.
A362: МАТ.БРОНЯ.002 | B362: БРОНЯ | C362: Бронестекло ПУз-Бр3 (1090*1335 мм. ). С учетом лотка. ЛИСТ 1. | F362: СПЕЦ Прожект групп | G362: шт. | H362: 105000 | I362: RUB | L362: МАТ.БРОНЯ.002 — Бронестекло ПУз-Бр3 (1090*1335 мм. ). С учетом лотка. ЛИСТ 1.
A363: МАТ.БРОНЯ.003 | B363: БРОНЯ | C363: Дверной блок 2-го класса устойчивости к взлому (дверное полотно 758*2010). Размер по раме 850х2100 мм. Цилиндровый механизм с перекодировкой со штоком Securemme K2. Гардиан сувальдный ЗВ 71.14 Т (К-К). Без наличников. ЛИСТ 11. RAL7047. Упаковка изоло | F363: СПЕЦ Прожект групп | G363: шт. | H363: 87150 | I363: RUB | L363: МАТ.БРОНЯ.003 — Дверной блок 2-го класса устойчивости к взлому (дверное полотно 758*2010). Размер по раме 850х2100 мм. Цилиндровый механизм с перекодировкой со штоком Securemme K2. Гардиан сувальдный ЗВ 71.14 Т (К-К). Без наличников. ЛИСТ 11. RAL7047. Упаковка изоло
A364: МАТ.БРОНЯ.004 | B364: БРОНЯ | C364: Дверной блок 2-го класса устойчивости к взлому (дверное полотно 858*2110). Размер по раме 950х2200 мм. Цилиндровый механизм с перекодировкой со штоком Securemme K2. Гардиан сувальдный ЗВ 71.14 Т (К-К). Без наличников. ЛИСТ 10. RAL7047. Упаковка изоло | F364: СПЕЦ Прожект групп | G364: шт. | H364: 88725 | I364: RUB | L364: МАТ.БРОНЯ.004 — Дверной блок 2-го класса устойчивости к взлому (дверное полотно 858*2110). Размер по раме 950х2200 мм. Цилиндровый механизм с перекодировкой со штоком Securemme K2. Гардиан сувальдный ЗВ 71.14 Т (К-К). Без наличников. ЛИСТ 10. RAL7047. Упаковка изоло
A365: МАТ.БРОНЯ.005 | B365: БРОНЯ | C365: Дверной блок 3-го класса устойчивости к взлому с решетчатой дверью (дверное полотно 908*2110). Размер по раме 1000х2200 мм. Размер по раме 1000х2200 мм. Два замка Гардиан 71.14Т сувальдного типа на расстоянии не менее 350 мм друг от друга по замочным | F365: СПЕЦ Прожект групп | G365: шт. | H365: 148575 | I365: RUB | L365: МАТ.БРОНЯ.005 — Дверной блок 3-го класса устойчивости к взлому с решетчатой дверью (дверное полотно 908*2110). Размер по раме 1000х2200 мм. Размер по раме 1000х2200 мм. Два замка Гардиан 71.14Т сувальдного типа на расстоянии не менее 350 мм друг от друга по замочным
A366: МАТ.БРОНЯ.006 | B366: БРОНЯ | C366: Дверной блок 5-го класса устойчивости к взлому с решетчатой дверью . 2 замка СИ600 (дверное полотно 898*1970), 1030х2100 мм по раме. ЛИСТ 13. | F366: СПЕЦ Прожект групп | G366: шт. | H366: 223650 | I366: RUB | L366: МАТ.БРОНЯ.006 — Дверной блок 5-го класса устойчивости к взлому с решетчатой дверью . 2 замка СИ600 (дверное полотно 898*1970), 1030х2100 мм по раме. ЛИСТ 13.
A367: МАТ.БРОНЯ.007 | B367: БРОНЯ | C367: Дверной блок утепленый, полуторастворчатый размером по раме 2100Нх1400 мм (размер двери в свету 2000Нх1200 мм), полотна из листов металла 2+2 мм (наружный и внутренние листы). Рабочая створка-________, шириной 900 мм, на раб створке 2 замка: оба цили | F367: СПЕЦ Прожект групп | G367: шт. | H367: 110250 | I367: RUB | L367: МАТ.БРОНЯ.007 — Дверной блок утепленый, полуторастворчатый размером по раме 2100Нх1400 мм (размер двери в свету 2000Нх1200 мм), полотна из листов металла 2+2 мм (наружный и внутренние листы). Рабочая створка-________, шириной 900 мм, на раб створке 2 замка: оба цили
A368: МАТ.БРОНЯ.008 | B368: БРОНЯ | C368: Доводчик на рабочую створку NOTEDO DC-025-095 (со скользящим каналом). Доводчик на паразитную створку NOTEDO DC-070 (паук) | F368: СПЕЦ Прожект групп | G368: шт. | H368: 8400 | I368: RUB | L368: МАТ.БРОНЯ.008 — Доводчик на рабочую створку NOTEDO DC-025-095 (со скользящим каналом). Доводчик на паразитную створку NOTEDO DC-070 (паук)
A369: МАТ.БРОНЯ.009 | B369: БРОНЯ | C369: Панели защитные, стеновые V класс взломостойкости, сварное соединение, бетонно-заливная. Покраска грунт | F369: СПЕЦ Прожект групп | G369: м2 | H369: 15750 | I369: RUB | L369: МАТ.БРОНЯ.009 — Панели защитные, стеновые V класс взломостойкости, сварное соединение, бетонно-заливная. Покраска грунт
A370: МАТ.БРОНЯ.010 | B370: БРОНЯ | C370: Панели защитные, стеновые кл. Бр-2 по пулестойкости и II класс взломостойкости, болтовое соединение, облегченные, Покраска грунт | F370: СПЕЦ Прожект групп | G370: м2 | H370: 15225 | I370: RUB | L370: МАТ.БРОНЯ.010 — Панели защитные, стеновые кл. Бр-2 по пулестойкости и II класс взломостойкости, болтовое соединение, облегченные, Покраска грунт
A371: МАТ.БРОНЯ.011 | B371: БРОНЯ | C371: Панели защитные, стеновые кл. Бр-2 по пулестойкости и II класс взломостойкости, сварное соединение, облегченные, Покраска грунт | F371: СПЕЦ Прожект групп | G371: м2 | H371: 14700 | I371: RUB | L371: МАТ.БРОНЯ.011 — Панели защитные, стеновые кл. Бр-2 по пулестойкости и II класс взломостойкости, сварное соединение, облегченные, Покраска грунт
A372: МАТ.БРОНЯ.012 | B372: БРОНЯ | C372: Панели защитные, стеновые кл. Бр-3 по пулестойкости и III класс взломостойкости, болтовое соединение, облегченные, Покраска грунт | F372: СПЕЦ Прожект групп | G372: м2 | H372: 18060 | I372: RUB | L372: МАТ.БРОНЯ.012 — Панели защитные, стеновые кл. Бр-3 по пулестойкости и III класс взломостойкости, болтовое соединение, облегченные, Покраска грунт
... A382: МАТ.БРОНЯ.022 | B382: БРОНЯ | C382: Шлюз инкассаторский кл. Бр-3 по пулестойкости, электромеханический со стеклом СЗМ-Бр3, габаритные размеры 750х540х615 мм, ВШхД. внутренние размеры 652х250х471 мм.Открывание кассира левое, инкассатора правое. Способ крепления - на монтажные уголки при | F382: СПЕЦ Прожект групп | G382: шт. | H382: 93450 | I382: RUB | L382: МАТ.БРОНЯ.022 — Шлюз инкассаторский кл. Бр-3 по пулестойкости, электромеханический со стеклом СЗМ-Бр3, габаритные размеры 750х540х615 мм, ВШхД. внутренние размеры 652х250х471 мм.Открывание кассира левое, инкассатора правое. Способ крепления - на монтажные уголки при
A383: МАТ.ДВ.001 | B383: ДВ | C383: Добор для F-наличника серый 7035 (5х100х2070мм) | E383: Kapelli | F383: Фабрика дверей KAPELLI | G383: шт | H383: 460 | I383: RUB | L383: МАТ.ДВ.001 — Добор для F-наличника серый 7035 (5х100х2070мм)
A384: МАТ.ДВ.002 | B384: ДВ | C384: Добор для F-наличника серый 7035 (5х150х2070мм) | E384: Kapelli | F384: Фабрика дверей KAPELLI | G384: шт | H384: 690 | I384: RUB | L384: МАТ.ДВ.002 — Добор для F-наличника серый 7035 (5х150х2070мм)
A385: МАТ.ДВ.003 | B385: ДВ | C385: Завертка WC | E385: Kapelli | F385: Фабрика дверей KAPELLI | G385: шт | H385: 270 | I385: RUB | L385: МАТ.ДВ.003 — Завертка WC
A386: МАТ.ДВ.004 | B386: ДВ | C386: Замок магнитный (под цилиндр / под фиксатор) | E386: Kapelli | F386: Фабрика дверей KAPELLI | G386: шт | H386: 390 | I386: RUB | L386: МАТ.ДВ.004 — Замок магнитный (под цилиндр / под фиксатор)
A387: МАТ.ДВ.005 | B387: ДВ | C387: Замок механический (под цилиндр / под фиксатор) | E387: Kapelli | F387: Фабрика дверей KAPELLI | G387: шт | H387: 410 | I387: RUB | L387: МАТ.ДВ.005 — Замок механический (под цилиндр / под фиксатор)
A388: МАТ.ДВ.006 | B388: ДВ | C388: Накладка под цилиндр | E388: Kapelli | F388: Фабрика дверей KAPELLI | G388: шт | H388: 121 | I388: RUB | L388: МАТ.ДВ.006 — Накладка под цилиндр
A389: МАТ.ДВ.007 | B389: ДВ | C389: Наличник F ПВХ 2,17м серый 7035 телескопический | E389: Kapelli | F389: Фабрика дверей KAPELLI | G389: шт | H389: 510 | I389: RUB | L389: МАТ.ДВ.007 — Наличник F ПВХ 2,17м серый 7035 телескопический
A390: МАТ.ДВ.008 | B390: ДВ | C390: Петля накладная | E390: Kapelli | F390: Фабрика дверей KAPELLI | G390: шт | H390: 75 | I390: RUB | L390: МАТ.ДВ.008 — Петля накладная
A391: МАТ.ДВ.009 | B391: ДВ | C391: Установка дверного доводчика штанга рычажная на входные двери (210 кг) | E391: ФАСАДСТРОЙ | F391: ФАСАДСТРОЙ | G391: шт. | H391: 5775 | I391: RUB | L391: МАТ.ДВ.009 — Установка дверного доводчика штанга рычажная на входные двери (210 кг)
A392: МАТ.ДВ.010 | B392: ДВ | C392: Цилиндр (клю-ключ) | E392: Kapelli | F392: Фабрика дверей KAPELLI | G392: шт | H392: 245 | I392: RUB | L392: МАТ.ДВ.010 — Цилиндр (клю-ключ)
A393: МАТ.ДВ.011 | B393: ДВ | C393: Цилиндр (ключ-фиксатор) | E393: Kapelli | F393: Фабрика дверей KAPELLI | G393: шт | H393: 276 | I393: RUB | L393: МАТ.ДВ.011 — Цилиндр (ключ-фиксатор)
A394: МАТ.ДВ.АЛ.001 | B394: ДВ.АЛ | C394: двупольноый дверной блок (алюминиевый теплый профиль 3 петли, два врезных замка цилиндрического типа, имеющих с внутренней стороны запорные устройства типа «вертушок» без защелки , ручка из нержавеющей стали типа «труба» со смещением креплений диамет | E394: ФАСАДСТРОЙ | F394: ФАСАДСТРОЙ | G394: шт. | H394: 89201.7 | I394: RUB | L394: МАТ.ДВ.АЛ.001 — двупольноый дверной блок (алюминиевый теплый профиль 3 петли, два врезных замка цилиндрического типа, имеющих с внутренней стороны запорные устройства типа «вертушок» без защелки , ручка из нержавеющей стали типа «труба» со смещением креплений диамет
... A403: МАТ.ДВ.ДЕР.004 | B403: ДВ.ДЕР | C403: ДГ 21-9 КАПЕЛЬ Гладкая МС7035 (полотно 2000*800, ДКТ80) УД | E403: Kapelli | F403: Фабрика дверей KAPELLI | G403: компл | H403: 11655 | I403: RUB | L403: МАТ.ДВ.ДЕР.004 — ДГ 21-9 КАПЕЛЬ Гладкая МС7035 (полотно 2000*800, ДКТ80) УД
A404: МАТ.ДВ.ДЕР.005 | B404: ДВ.ДЕР | C404: Дверь глухая в проем. Способ открывания: распашная. Число полотен: одностворчатая. Полотно со звукоизоляционным заполнением (62,5 мм). Отделка полотна - ЛДСП 16 мм. Цвет: EGGER. Алюминиевая кромка слева/справа/сверху полотна. Цвет: RAL 9005 муар. Кор | F404: Вертикальный транспорт | G404: шт | H404: 93350 | I404: RUB | L404: МАТ.ДВ.ДЕР.005 — Дверь глухая в проем. Способ открывания: распашная. Число полотен: одностворчатая. Полотно со звукоизоляционным заполнением (62,5 мм). Отделка полотна - ЛДСП 16 мм. Цвет: EGGER. Алюминиевая кромка слева/справа/сверху полотна. Цвет: RAL 9005 муар. Кор
