Workbook

Sheet Смета ЕР (общ) 
F1: Формат объекта | M1: ККО | U1: курс $ | V1: 81
F2: дверной | L2: Адрес объекта: | M2: СПб, улюЛьва Толстого д..9 | U2: курс Евро | V2: 95
F3: Плoщадь объекта (м.кв.): | L3: Плащадь объекта: | M3: 1900 | U3: Дисконт по тендеру | V3: 0
F4: Срок проведения работ | L4: Срок проведения работ | M4: Согласно план-графику производства работ | U4: курс Юань | V4: 10.94
F5: ПОДРЯДЧИК: | L5: ПОДРЯДЧИК:
F6: Юридический адрес: | L6: Юридический адрес:
F7: Электронный адрес: | L7: Электронный адрес:
F8: Контактное лицо (Ф.И.О.) : | L8: Контактное лицо (Ф.И.О.) :
F9: Контактный телефон: | L9: Контактный телефон:
F10: Реквизиты: | L10: Реквизиты:
F11: Сумма по смете: | L11: Сумма по смете:
A14: Раздел | B14: Подраздел | C14: Подраздел подраздела | D14: Пункт подраздела | E14: Новый номенклатурный номер | F14: № | L14: Наименование работ и затрат | M14: Един. изм. | N14: Кол - во. (объем) | O14: ЕР цена работ, руб.* | P14: ЕР цена материалов и оборудования, руб.* | Q14: Цена работ, руб. * | R14: Цена материалов и оборудования, руб. * | S14: Стоимость работ, руб. * | T14: Стоимость материалов и оборудования руб. * | U14: Примечание | Y14: Кол - во. (объем)
A15: Р1 | B15: 0 | D15: 0 | E15: =CONCATENATE('Смета ЕР (общ) '!$A15,".",'Смета ЕР (общ) '!$B15,".",'Смета ЕР (общ) '!$D15) -> Р1.0.0 | F15: 1 | L15: Раздел №1. Проектные работы и согласования | N15: =N16 -> 0 | S15: =ROUND(S16,2) -> 0 | T15: =ROUND(T16,2) -> 0 | Y15: 1498
A16: Р1 | B16: 1 | D16: 0 | E16: =CONCATENATE('Смета ЕР (общ) '!$A16,".",'Смета ЕР (общ) '!$B16,".",'Смета ЕР (общ) '!$D16) -> Р1.1.0 | F16: =IF(N16>0,F15+1,F15) -> 1 | G16: Раздел №1. Проектные работы и согласования | H16: 1.1.0 Проектные работы и согласования | L16: 1.1.0 Проектные работы и согласования | N16: =SUM(N17:N108) -> 0 | S16: =SUM(S17:S108) -> 0 | T16: =SUM(T17:T108) -> 0 | Y16: 1498
A17: Р1 | B17: 1 | D17: 1 | E17: =CONCATENATE('Смета ЕР (общ) '!$A17,".",'Смета ЕР (общ) '!$B17,".",'Смета ЕР (общ) '!$D17) -> Р1.1.1 | F17: =IF(N17>0,F16+1,F16) -> 1 | G17: Раздел №1. Проектные работы и согласования | H17: 1.1.0 Проектные работы и согласования | J17: Техническое обследование состояния несущих конструкций помещения с подготовкой рекомендаций по усилению (Техничесекое заключение о конструктиве - "ТЗК") | K17: (для помещений от 100 до 450 м.кв) | L17: Техническое обследование состояния несущих конструкций помещения с подготовкой рекомендаций по усилению (Техничесекое заключение о конструктиве - "ТЗК") (для помещений от 100 до 450 м.кв) | M17: м2 | O17: ='[1]Проектирование 100-450'!E36*1.05 -> 3675 | P17: 0 | Q17: =ROUND(O17-O17*$V$3,2) -> 3675 | R17: =ROUND(P17-P17*$V$3,2) -> 0 | S17: =ROUND('Смета ЕР (общ) '!$N17*'Смета ЕР (общ) '!$Q17,2) -> 0 | T17: =ROUND('Смета ЕР (общ) '!$N17*'Смета ЕР (общ) '!$R17,2) -> 0
A18: Р1 | B18: 1 | D18: 44 | E18: =CONCATENATE('Смета ЕР (общ) '!$A18,".",'Смета ЕР (общ) '!$B18,".",'Смета ЕР (общ) '!$D18) -> Р1.1.44 | F18: =IF(N18>0,F17+1,F17) -> 1 | G18: Раздел №1. Проектные работы и согласования | H18: 1.1.0 Проектные работы и согласования | J18: Эскизный проект фасада и Колористический паспорт с указанием ведомости отделки и проектным решением со спецификацией элементов (крыльцо, пандус, навесы, колонны и т.д.) | K18: (для фасадов от 100 до 450 м.кв) | L18: Эскизный проект фасада и Колористический паспорт с указанием ведомости отделки и проектным решением со спецификацией элементов (крыльцо, пандус, навесы, колонны и т.д.)(для фасадов от 100 до 450 м.кв) | M18: м2 | O18: ='[1]Проектирование 100-450'!E37*1.05 -> 7822.5 | P18: 0 | Q18: =ROUND(O18-O18*$V$3,2) -> 7822.5 | R18: =ROUND(P18-P18*$V$3,2) -> 0 | S18: =ROUND('Смета ЕР (общ) '!$N18*'Смета ЕР (общ) '!$Q18,2) -> 0 | T18: =ROUND('Смета ЕР (общ) '!$N18*'Смета ЕР (общ) '!$R18,2) -> 0
A19: Р1 | B19: 1 | D19: 2 | E19: =CONCATENATE('Смета ЕР (общ) '!$A19,".",'Смета ЕР (общ) '!$B19,".",'Смета ЕР (общ) '!$D19) -> Р1.1.2 | F19: =IF(N19>0,F18+1,F18) -> 1 | G19: Раздел №1. Проектные работы и согласования | H19: 1.1.0 Проектные работы и согласования | I19: Рабочая документация | J19: Рабочая документация по усилению/устройству несущих конструкций ("КР"), включая пояснительную записку | K19: (для помещений от 100 до 450 м.кв) | L19: Рабочая документация по усилению/устройству несущих конструкций ("КР"), включая пояснительную записку (для помещений от 100 до 450 м.кв) | M19: м2 | O19: ='[1]Проектирование 100-450'!E18*1.05 -> 135.45 | P19: 0 | Q19: =ROUND(O19-O19*$V$3,2) -> 135.45 | R19: =ROUND(P19-P19*$V$3,2) -> 0 | S19: =ROUND('Смета ЕР (общ) '!$N19*'Смета ЕР (общ) '!$Q19,2) -> 0 | T19: =ROUND('Смета ЕР (общ) '!$N19*'Смета ЕР (общ) '!$R19,2) -> 0
A20: Р1 | B20: 1 | D20: 3 | E20: =CONCATENATE('Смета ЕР (общ) '!$A20,".",'Смета ЕР (общ) '!$B20,".",'Смета ЕР (общ) '!$D20) -> Р1.1.3 | F20: =IF(N20>0,F19+1,F19) -> 1 | G20: Раздел №1. Проектные работы и согласования | H20: 1.1.0 Проектные работы и согласования | I20: Рабочая документация | J20: Рабочая документация "Архитектурные решения" ("АР"), включая пояснительную записку | K20: (для помещений от 100 до 450 м.кв) | L20: Рабочая документация "Архитектурные решения" ("АР"), включая пояснительную записку (для помещений от 100 до 450 м.кв) | M20: м2 | O20: ='[1]Проектирование 100-450'!E19*1.05 -> 389.55 | P20: 0 | Q20: =ROUND(O20-O20*$V$3,2) -> 389.55 | R20: =ROUND(P20-P20*$V$3,2) -> 0 | S20: =ROUND('Смета ЕР (общ) '!$N20*'Смета ЕР (общ) '!$Q20,2) -> 0 | T20: =ROUND('Смета ЕР (общ) '!$N20*'Смета ЕР (общ) '!$R20,2) -> 0 | Y20: 214
A21: Р1 | B21: 1 | D21: 4 | E21: =CONCATENATE('Смета ЕР (общ) '!$A21,".",'Смета ЕР (общ) '!$B21,".",'Смета ЕР (общ) '!$D21) -> Р1.1.4 | F21: =IF(N21>0,F20+1,F20) -> 1 | G21: Раздел №1. Проектные работы и согласования | H21: 1.1.0 Проектные работы и согласования | I21: Рабочая документация | J21: Рабочая документация по электроснабжению и электроосвещению ("ЭОМ"), включая пояснительную записку | K21: (для помещений от 100 до 450 м.кв) | L21: Рабочая документация по электроснабжению и электроосвещению ("ЭОМ"), включая пояснительную записку (для помещений от 100 до 450 м.кв) | M21: м2 | O21: ='[1]Проектирование 100-450'!E20*1.05 -> 258.3 | P21: 0 | Q21: =ROUND(O21-O21*$V$3,2) -> 258.3 | R21: =ROUND(P21-P21*$V$3,2) -> 0 | S21: =ROUND('Смета ЕР (общ) '!$N21*'Смета ЕР (общ) '!$Q21,2) -> 0 | T21: =ROUND('Смета ЕР (общ) '!$N21*'Смета ЕР (общ) '!$R21,2) -> 0 | Y21: 214
A22: Р1 | B22: 1 | D22: 5 | E22: =CONCATENATE('Смета ЕР (общ) '!$A22,".",'Смета ЕР (общ) '!$B22,".",'Смета ЕР (общ) '!$D22) -> Р1.1.5 | F22: =IF(N22>0,F21+1,F21) -> 1 | G22: Раздел №1. Проектные работы и согласования | H22: 1.1.0 Проектные работы и согласования | I22: Рабочая документация | J22: Рабочая документация Системы вентиляции ("ОВиК-В"), включая пояснительную записку | K22: (для помещений от 100 до 450 м.кв) | L22: Рабочая документация Системы вентиляции ("ОВиК-В"), включая пояснительную записку (для помещений от 100 до 450 м.кв) | M22: м2 | O22: ='[1]Проектирование 100-450'!E21*1.05 -> 202.65 | P22: 0 | Q22: =ROUND(O22-O22*$V$3,2) -> 202.65 | R22: =ROUND(P22-P22*$V$3,2) -> 0 | S22: =ROUND('Смета ЕР (общ) '!$N22*'Смета ЕР (общ) '!$Q22,2) -> 0 | T22: =ROUND('Смета ЕР (общ) '!$N22*'Смета ЕР (общ) '!$R22,2) -> 0 | Y22: 214
A23: Р1 | B23: 1 | D23: 6 | E23: =CONCATENATE('Смета ЕР (общ) '!$A23,".",'Смета ЕР (общ) '!$B23,".",'Смета ЕР (общ) '!$D23) -> Р1.1.6 | F23: =IF(N23>0,F22+1,F22) -> 1 | G23: Раздел №1. Проектные работы и согласования | H23: 1.1.0 Проектные работы и согласования | I23: Рабочая документация | J23: Рабочая документация Системы кондиционирования ("ОВиК-К"), включая пояснительную записку | K23: (для помещений от 100 до 450 м.кв) | L23: Рабочая документация Системы кондиционирования ("ОВиК-К"), включая пояснительную записку (для помещений от 100 до 450 м.кв) | M23: м2 | O23: ='[1]Проектирование 100-450'!E22*1.05 -> 159.4845 | P23: 0 | Q23: =ROUND(O23-O23*$V$3,2) -> 159.48 | R23: =ROUND(P23-P23*$V$3,2) -> 0 | S23: =ROUND('Смета ЕР (общ) '!$N23*'Смета ЕР (общ) '!$Q23,2) -> 0 | T23: =ROUND('Смета ЕР (общ) '!$N23*'Смета ЕР (общ) '!$R23,2) -> 0 | Y23: 214
A24: Р1 | B24: 1 | D24: 7 | E24: =CONCATENATE('Смета ЕР (общ) '!$A24,".",'Смета ЕР (общ) '!$B24,".",'Смета ЕР (общ) '!$D24) -> Р1.1.7 | F24: =IF(N24>0,F23+1,F23) -> 1 | G24: Раздел №1. Проектные работы и согласования | H24: 1.1.0 Проектные работы и согласования | I24: Рабочая документация | J24: Рабочая документация Системы отопления ("ОВиК-О"), включая Пояснительную записку и Теплотехнический расчет | K24: (для помещений от 100 до 450 м.кв) | L24: Рабочая документация Системы отопления ("ОВиК-О"), включая Пояснительную записку и Теплотехнический расчет (для помещений от 100 до 450 м.кв) | M24: м2 | O24: ='[1]Проектирование 100-450'!E23*1.05 -> 123.9 | P24: 0 | Q24: =ROUND(O24-O24*$V$3,2) -> 123.9 | R24: =ROUND(P24-P24*$V$3,2) -> 0 | S24: =ROUND('Смета ЕР (общ) '!$N24*'Смета ЕР (общ) '!$Q24,2) -> 0 | T24: =ROUND('Смета ЕР (общ) '!$N24*'Смета ЕР (общ) '!$R24,2) -> 0 | Y24: 214
A25: Р1 | B25: 1 | D25: 8 | E25: =CONCATENATE('Смета ЕР (общ) '!$A25,".",'Смета ЕР (общ) '!$B25,".",'Смета ЕР (общ) '!$D25) -> Р1.1.8 | F25: =IF(N25>0,F24+1,F24) -> 1 | G25: Раздел №1. Проектные работы и согласования | H25: 1.1.0 Проектные работы и согласования | I25: Рабочая документация | J25: Рабочая документация Системы водоснабжения и канализации ("ВК"), включая пояснительную записку | K25: (для помещений от 100 до 450 м.кв) | L25: Рабочая документация Системы водоснабжения и канализации ("ВК"), включая пояснительную записку (для помещений от 100 до 450 м.кв) | M25: м2 | O25: ='[1]Проектирование 100-450'!E24*1.05 -> 130.2 | P25: 0 | Q25: =ROUND(O25-O25*$V$3,2) -> 130.2 | R25: =ROUND(P25-P25*$V$3,2) -> 0 | S25: =ROUND('Смета ЕР (общ) '!$N25*'Смета ЕР (общ) '!$Q25,2) -> 0 | T25: =ROUND('Смета ЕР (общ) '!$N25*'Смета ЕР (общ) '!$R25,2) -> 0 | Y25: 214
A26: Р1 | B26: 1 | D26: 9 | E26: =CONCATENATE('Смета ЕР (общ) '!$A26,".",'Смета ЕР (общ) '!$B26,".",'Смета ЕР (общ) '!$D26) -> Р1.1.9 | F26: =IF(N26>0,F25+1,F25) -> 1 | G26: Раздел №1. Проектные работы и согласования | H26: 1.1.0 Проектные работы и согласования | I26: Рабочая документация | J26: Рабочая документация Системы автоматической установки водяного пожаротушения ("АУВПТ"), (спринкерная, дренчерная, модульная система), включая пояснительную записку | K26: (для помещений от 100 до 450 м.кв) | L26: Рабочая документация Системы автоматической установки водяного пожаротушения ("АУВПТ"), (спринкерная, дренчерная, модульная система), включая пояснительную записку (для помещений от 100 до 450 м.кв) | M26: м2 | O26: ='[1]Проектирование 100-450'!E25*1.05 -> 91.6755 | P26: 0 | Q26: =ROUND(O26-O26*$V$3,2) -> 91.68 | R26: =ROUND(P26-P26*$V$3,2) -> 0 | S26: =ROUND('Смета ЕР (общ) '!$N26*'Смета ЕР (общ) '!$Q26,2) -> 0 | T26: =ROUND('Смета ЕР (общ) '!$N26*'Смета ЕР (общ) '!$R26,2) -> 0
A27: Р1 | B27: 1 | D27: 43 | E27: =CONCATENATE('Смета ЕР (общ) '!$A27,".",'Смета ЕР (общ) '!$B27,".",'Смета ЕР (общ) '!$D27) -> Р1.1.43 | F27: =IF(N27>0,F26+1,F26) -> 1 | G27: Раздел №1. Проектные работы и согласования | H27: 1.1.0 Проектные работы и согласования | I27: Рабочая документация | J27: Рабочая документация Системы Внутреннего противопожарного водопровода ("ВПВ"), включая пояснительную записку | K27: (для помещений от 100 до 450 м.кв) | L27: Рабочая документация Системы Внутреннего противопожарного водопровода ("ВПВ"), включая пояснительную записку (для помещений от 100 до 450 м.кв) | M27: м2 | O27: ='[1]Проектирование 100-450'!E26*1.05 -> 91.6755 | P27: 0 | Q27: =ROUND(O27-O27*$V$3,2) -> 91.68 | R27: =ROUND(P27-P27*$V$3,2) -> 0 | S27: =ROUND('Смета ЕР (общ) '!$N27*'Смета ЕР (общ) '!$Q27,2) -> 0 | T27: =ROUND('Смета ЕР (общ) '!$N27*'Смета ЕР (общ) '!$R27,2) -> 0
A28: Р1 | B28: 1 | D28: 10 | E28: =CONCATENATE('Смета ЕР (общ) '!$A28,".",'Смета ЕР (общ) '!$B28,".",'Смета ЕР (общ) '!$D28) -> Р1.1.10 | F28: =IF(N28>0,F27+1,F27) -> 1 | G28: Раздел №1. Проектные работы и согласования | H28: 1.1.0 Проектные работы и согласования | I28: Рабочая документация | J28: Рабочая документация Системы дымоудаления ("ДУ"), включая пояснительную записку | K28: (для помещений от 100 до 450 м.кв) | L28: Рабочая документация Системы дымоудаления ("ДУ"), включая пояснительную записку (для помещений от 100 до 450 м.кв) | M28: м2 | O28: ='[1]Проектирование 100-450'!E27*1.05 -> 103.95 | P28: 0 | Q28: =ROUND(O28-O28*$V$3,2) -> 103.95 | R28: =ROUND(P28-P28*$V$3,2) -> 0 | S28: =ROUND('Смета ЕР (общ) '!$N28*'Смета ЕР (общ) '!$Q28,2) -> 0 | T28: =ROUND('Смета ЕР (общ) '!$N28*'Смета ЕР (общ) '!$R28,2) -> 0
A29: Р1 | B29: 1 | D29: 11 | E29: =CONCATENATE('Смета ЕР (общ) '!$A29,".",'Смета ЕР (общ) '!$B29,".",'Смета ЕР (общ) '!$D29) -> Р1.1.11 | F29: =IF(N29>0,F28+1,F28) -> 1 | G29: Раздел №1. Проектные работы и согласования | H29: 1.1.0 Проектные работы и согласования | I29: Рабочая документация | J29: Рабочая документация "Автоматическая пожарная сигнализация" (АПС) | L29: Рабочая документация "Автоматическая пожарная сигнализация" (АПС) | M29: м2 | O29: ='[1]АПС, СОУЭ, ППА'!F13*1.05*0.1 -> 7.035 | P29: 0 | Q29: =ROUND(O29-O29*$V$3,2) -> 7.04 | R29: =ROUND(P29-P29*$V$3,2) -> 0 | S29: =ROUND('Смета ЕР (общ) '!$N29*'Смета ЕР (общ) '!$Q29,2) -> 0 | T29: =ROUND('Смета ЕР (общ) '!$N29*'Смета ЕР (общ) '!$R29,2) -> 0
A30: Р1 | B30: 1 | D30: 25 | E30: =CONCATENATE('Смета ЕР (общ) '!$A30,".",'Смета ЕР (общ) '!$B30,".",'Смета ЕР (общ) '!$D30) -> Р1.1.25 | F30: =IF(N30>0,F29+1,F29) -> 1 | G30: Раздел №1. Проектные работы и согласования | H30: 1.1.0 Проектные работы и согласования | I30: Рабочая документация | J30: Рабочая документация "Система оповещения и управления эвакуацией людей при пожаре" (СОУЭ) | L30: Рабочая документация "Система оповещения и управления эвакуацией людей при пожаре" (СОУЭ) | M30: м2 | O30: ='[1]АПС, СОУЭ, ППА'!F14*1.05*0.1 -> 4.095 | P30: 0 | Q30: =ROUND(O30-O30*$V$3,2) -> 4.1 | R30: =ROUND(P30-P30*$V$3,2) -> 0 | S30: =ROUND('Смета ЕР (общ) '!$N30*'Смета ЕР (общ) '!$Q30,2) -> 0 | T30: =ROUND('Смета ЕР (общ) '!$N30*'Смета ЕР (общ) '!$R30,2) -> 0
A31: Р1 | B31: 1 | D31: 26 | E31: =CONCATENATE('Смета ЕР (общ) '!$A31,".",'Смета ЕР (общ) '!$B31,".",'Смета ЕР (общ) '!$D31) -> Р1.1.26 | F31: =IF(N31>0,F30+1,F30) -> 1 | G31: Раздел №1. Проектные работы и согласования | H31: 1.1.0 Проектные работы и согласования | I31: Рабочая документация | J31: Рабочая документация "Автоматизация системы внутреннего противопожарного водопровода (ВПВ) | L31: Рабочая документация "Автоматизация системы внутреннего противопожарного водопровода (ВПВ) | M31: м2 | O31: ='[1]АПС, СОУЭ, ППА'!F16*1.05*0.1 -> 0.84 | P31: 0 | Q31: =ROUND(O31-O31*$V$3,2) -> 0.84 | R31: =ROUND(P31-P31*$V$3,2) -> 0 | S31: =ROUND('Смета ЕР (общ) '!$N31*'Смета ЕР (общ) '!$Q31,2) -> 0 | T31: =ROUND('Смета ЕР (общ) '!$N31*'Смета ЕР (общ) '!$R31,2) -> 0
A32: Р1 | B32: 1 | D32: 29 | E32: =CONCATENATE('Смета ЕР (общ) '!$A32,".",'Смета ЕР (общ) '!$B32,".",'Смета ЕР (общ) '!$D32) -> Р1.1.29 | F32: =IF(N32>0,F31+1,F31) -> 1 | G32: Раздел №1. Проектные работы и согласования | H32: 1.1.0 Проектные работы и согласования | I32: Рабочая документация | J32: Рабочая документация "Автоматизация системы противодымной вентиляции (ПДВ")" | L32: Рабочая документация "Автоматизация системы противодымной вентиляции (ПДВ")" | M32: м2 | O32: ='[1]АПС, СОУЭ, ППА'!F17*1.05*0.1 -> 2.625 | P32: 0 | Q32: =ROUND(O32-O32*$V$3,2) -> 2.63 | R32: =ROUND(P32-P32*$V$3,2) -> 0 | S32: =ROUND('Смета ЕР (общ) '!$N32*'Смета ЕР (общ) '!$Q32,2) -> 0 | T32: =ROUND('Смета ЕР (общ) '!$N32*'Смета ЕР (общ) '!$R32,2) -> 0
A33: Р1 | B33: 1 | D33: 30 | E33: =CONCATENATE('Смета ЕР (общ) '!$A33,".",'Смета ЕР (общ) '!$B33,".",'Смета ЕР (общ) '!$D33) -> Р1.1.30 | F33: =IF(N33>0,F32+1,F32) -> 1 | G33: Раздел №1. Проектные работы и согласования | H33: 1.1.0 Проектные работы и согласования | I33: Рабочая документация | J33: Рабочая документация "Автоматизация Системы отопления, вентиляции и кондиционирования (ОВиК)" | L33: Рабочая документация "Автоматизация Системы отопления, вентиляции и кондиционирования (ОВиК)" | M33: м2 | O33: ='[1]АПС, СОУЭ, ППА'!F18*1.05*0.1 -> 0.315 | P33: 0 | Q33: =ROUND(O33-O33*$V$3,2) -> 0.32 | R33: =ROUND(P33-P33*$V$3,2) -> 0 | S33: =ROUND('Смета ЕР (общ) '!$N33*'Смета ЕР (общ) '!$Q33,2) -> 0 | T33: =ROUND('Смета ЕР (общ) '!$N33*'Смета ЕР (общ) '!$R33,2) -> 0
A34: Р1 | B34: 1 | D34: 31 | E34: =CONCATENATE('Смета ЕР (общ) '!$A34,".",'Смета ЕР (общ) '!$B34,".",'Смета ЕР (общ) '!$D34) -> Р1.1.31 | F34: =IF(N34>0,F33+1,F33) -> 1 | G34: Раздел №1. Проектные работы и согласования | H34: 1.1.0 Проектные работы и согласования | I34: Рабочая документация | J34: Рабочая документация "Автоматизация Системы аварийного освещения (АО)" | L34: Рабочая документация "Автоматизация Системы аварийного освещения (АО)" | M34: м2 | O34: ='[1]АПС, СОУЭ, ППА'!F19*1.05*0.1 -> 0.105 | P34: 0 | Q34: =ROUND(O34-O34*$V$3,2) -> 0.11 | R34: =ROUND(P34-P34*$V$3,2) -> 0 | S34: =ROUND('Смета ЕР (общ) '!$N34*'Смета ЕР (общ) '!$Q34,2) -> 0 | T34: =ROUND('Смета ЕР (общ) '!$N34*'Смета ЕР (общ) '!$R34,2) -> 0
A35: Р1 | B35: 1 | D35: 33 | E35: =CONCATENATE('Смета ЕР (общ) '!$A35,".",'Смета ЕР (общ) '!$B35,".",'Смета ЕР (общ) '!$D35) -> Р1.1.33 | F35: =IF(N35>0,F34+1,F34) -> 1 | G35: Раздел №1. Проектные работы и согласования | H35: 1.1.0 Проектные работы и согласования | I35: Рабочая документация | J35: Рабочая документация "Автоматизации лифтовового хозяйства" | L35: Рабочая документация "Автоматизации лифтовового хозяйства" | M35: м2 | O35: ='[1]АПС, СОУЭ, ППА'!F20*1.05*0.1 -> 0.105 | P35: 0 | Q35: =ROUND(O35-O35*$V$3,2) -> 0.11 | R35: =ROUND(P35-P35*$V$3,2) -> 0 | S35: =ROUND('Смета ЕР (общ) '!$N35*'Смета ЕР (общ) '!$Q35,2) -> 0 | T35: =ROUND('Смета ЕР (общ) '!$N35*'Смета ЕР (общ) '!$R35,2) -> 0
A36: Р1 | B36: 1 | D36: 36 | E36: =CONCATENATE('Смета ЕР (общ) '!$A36,".",'Смета ЕР (общ) '!$B36,".",'Смета ЕР (общ) '!$D36) -> Р1.1.36 | F36: =IF(N36>0,F35+1,F35) -> 1 | G36: Раздел №1. Проектные работы и согласования | H36: 1.1.0 Проектные работы и согласования | I36: Рабочая документация | J36: Рабочая документация "Автоматизации Системы контроля управления доступом (СКУД)" | L36: Рабочая документация "Автоматизации Системы контроля управления доступом (СКУД)" | M36: м2 | O36: ='[1]АПС, СОУЭ, ППА'!F21*1.05*0.1 -> 0.105 | P36: 0 | Q36: =ROUND(O36-O36*$V$3,2) -> 0.11 | R36: =ROUND(P36-P36*$V$3,2) -> 0 | S36: =ROUND('Смета ЕР (общ) '!$N36*'Смета ЕР (общ) '!$Q36,2) -> 0 | T36: =ROUND('Смета ЕР (общ) '!$N36*'Смета ЕР (общ) '!$R36,2) -> 0
A37: Р1 | B37: 1 | D37: 37 | E37: =CONCATENATE('Смета ЕР (общ) '!$A37,".",'Смета ЕР (общ) '!$B37,".",'Смета ЕР (общ) '!$D37) -> Р1.1.37 | F37: =IF(N37>0,F36+1,F36) -> 1 | G37: Раздел №1. Проектные работы и согласования | H37: 1.1.0 Проектные работы и согласования | J37: Техническое обследование состояния несущих конструкций помещения с подготовкой рекомендаций по усилению в зоне расположения депозитария, кассового узла и банкоматов (Техничесекое заключение о конструктиве - "ТЗК") | K37: (для помещений менее 100 м.кв) | L37: Техническое обследование состояния несущих конструкций помещения с подготовкой рекомендаций по усилению в зоне расположения депозитария, кассового узла и банкоматов (Техничесекое заключение о конструктиве - "ТЗК")(для помещений менее 100 м.кв) | M37: м2 | O37: ='[1]Проектирование до 100'!E35*1.05 -> 3675 | P37: 0 | Q37: =ROUND(O37-O37*$V$3,2) -> 3675 | R37: =ROUND(P37-P37*$V$3,2) -> 0 | S37: =ROUND('Смета ЕР (общ) '!$N37*'Смета ЕР (общ) '!$Q37,2) -> 0 | T37: =ROUND('Смета ЕР (общ) '!$N37*'Смета ЕР (общ) '!$R37,2) -> 0
A38: Р1 | B38: 1 | D38: 45 | E38: =CONCATENATE('Смета ЕР (общ) '!$A38,".",'Смета ЕР (общ) '!$B38,".",'Смета ЕР (общ) '!$D38) -> Р1.1.45 | F38: =IF(N38>0,F37+1,F37) -> 1 | G38: Раздел №1. Проектные работы и согласования | H38: 1.1.0 Проектные работы и согласования | J38: Эскизный проект фасада и колористический паспорт с указанием ведомости отделки и проектным решением со спецификацией элементов (крыльцо, пандус, навесы, колонны и т.д.) | K38: (для фасадов менее 100 м.кв) | L38: Эскизный проект фасада и колористический паспорт с указанием ведомости отделки и проектным решением со спецификацией элементов (крыльцо, пандус, навесы, колонны и т.д.)(для фасадов менее 100 м.кв) | M38: кв.м.площади фасада | O38: ='[1]Проектирование до 100'!E36*1.05 -> 7822.5 | P38: 0 | Q38: =ROUND(O38-O38*$V$3,2) -> 7822.5 | R38: =ROUND(P38-P38*$V$3,2) -> 0 | S38: =ROUND('Смета ЕР (общ) '!$N38*'Смета ЕР (общ) '!$Q38,2) -> 0 | T38: =ROUND('Смета ЕР (общ) '!$N38*'Смета ЕР (общ) '!$R38,2) -> 0
A39: Р1 | B39: 1 | D39: 46 | E39: =CONCATENATE('Смета ЕР (общ) '!$A39,".",'Смета ЕР (общ) '!$B39,".",'Смета ЕР (общ) '!$D39) -> Р1.1.46 | F39: =IF(N39>0,F38+1,F38) -> 1 | G39: Раздел №1. Проектные работы и согласования | H39: 1.1.0 Проектные работы и согласования | I39: Рабочая документация | J39: Рабочая документация по усилению/устройству несущих конструкций ("КР"), включая пояснительную записку | K39: (для помещений менее 100 м.кв) | L39: Рабочая документация по усилению/устройству несущих конструкций ("КР"), включая пояснительную записку (для помещений менее 100 м.кв) | M39: компл. | O39: ='[1]Проектирование до 100'!E17*1.05 -> 10500 | P39: 0 | Q39: =ROUND(O39-O39*$V$3,2) -> 10500 | R39: =ROUND(P39-P39*$V$3,2) -> 0 | S39: =ROUND('Смета ЕР (общ) '!$N39*'Смета ЕР (общ) '!$Q39,2) -> 0 | T39: =ROUND('Смета ЕР (общ) '!$N39*'Смета ЕР (общ) '!$R39,2) -> 0
A40: Р1 | B40: 1 | D40: 47 | E40: =CONCATENATE('Смета ЕР (общ) '!$A40,".",'Смета ЕР (общ) '!$B40,".",'Смета ЕР (общ) '!$D40) -> Р1.1.47 | F40: =IF(N40>0,F39+1,F39) -> 1 | G40: Раздел №1. Проектные работы и согласования | H40: 1.1.0 Проектные работы и согласования | I40: Рабочая документация | J40: Рабочая документация "Архитектурные решения" ("АР"), включая пояснительную записку | K40: (для помещений менее 100 м.кв) | L40: Рабочая документация "Архитектурные решения" ("АР"), включая пояснительную записку (для помещений менее 100 м.кв) | M40: компл. | O40: ='[1]Проектирование до 100'!E18*1.05 -> 20737.5 | P40: 0 | Q40: =ROUND(O40-O40*$V$3,2) -> 20737.5 | R40: =ROUND(P40-P40*$V$3,2) -> 0 | S40: =ROUND('Смета ЕР (общ) '!$N40*'Смета ЕР (общ) '!$Q40,2) -> 0 | T40: =ROUND('Смета ЕР (общ) '!$N40*'Смета ЕР (общ) '!$R40,2) -> 0
A41: Р1 | B41: 1 | D41: 48 | E41: =CONCATENATE('Смета ЕР (общ) '!$A41,".",'Смета ЕР (общ) '!$B41,".",'Смета ЕР (общ) '!$D41) -> Р1.1.48 | F41: =IF(N41>0,F40+1,F40) -> 1 | G41: Раздел №1. Проектные работы и согласования | H41: 1.1.0 Проектные работы и согласования | I41: Рабочая документация | J41: Рабочая документация по электроснабжению и электроосвещению ("ЭОМ"), включая пояснительную записку | K41: (для помещений менее 100 м.кв) | L41: Рабочая документация по электроснабжению и электроосвещению ("ЭОМ"), включая пояснительную записку (для помещений менее 100 м.кв) | M41: компл. | O41: ='[1]Проектирование до 100'!E19*1.05 -> 20737.5 | P41: 0 | Q41: =ROUND(O41-O41*$V$3,2) -> 20737.5 | R41: =ROUND(P41-P41*$V$3,2) -> 0 | S41: =ROUND('Смета ЕР (общ) '!$N41*'Смета ЕР (общ) '!$Q41,2) -> 0 | T41: =ROUND('Смета ЕР (общ) '!$N41*'Смета ЕР (общ) '!$R41,2) -> 0
A42: Р1 | B42: 1 | D42: 49 | E42: =CONCATENATE('Смета ЕР (общ) '!$A42,".",'Смета ЕР (общ) '!$B42,".",'Смета ЕР (общ) '!$D42) -> Р1.1.49 | F42: =IF(N42>0,F41+1,F41) -> 1 | G42: Раздел №1. Проектные работы и согласования | H42: 1.1.0 Проектные работы и согласования | I42: Рабочая документация | J42: Рабочая документация Системы вентиляции ("ОВиК-В"), включая пояснительную записку | K42: (для помещений менее 100 м.кв) | L42: Рабочая документация Системы вентиляции ("ОВиК-В"), включая пояснительную записку (для помещений менее 100 м.кв) | M42: компл. | O42: ='[1]Проектирование до 100'!E20*1.05 -> 15592.5 | P42: 0 | Q42: =ROUND(O42-O42*$V$3,2) -> 15592.5 | R42: =ROUND(P42-P42*$V$3,2) -> 0 | S42: =ROUND('Смета ЕР (общ) '!$N42*'Смета ЕР (общ) '!$Q42,2) -> 0 | T42: =ROUND('Смета ЕР (общ) '!$N42*'Смета ЕР (общ) '!$R42,2) -> 0
A43: Р1 | B43: 1 | D43: 50 | E43: =CONCATENATE('Смета ЕР (общ) '!$A43,".",'Смета ЕР (общ) '!$B43,".",'Смета ЕР (общ) '!$D43) -> Р1.1.50 | F43: =IF(N43>0,F42+1,F42) -> 1 | G43: Раздел №1. Проектные работы и согласования | H43: 1.1.0 Проектные работы и согласования | I43: Рабочая документация | J43: Рабочая документация Системы кондиционирования ("ОВиК-К"), включая пояснительную записку | K43: (для помещений менее 100 м.кв) | L43: Рабочая документация Системы кондиционирования ("ОВиК-К"), включая пояснительную записку (для помещений менее 100 м.кв) | M43: компл. | O43: ='[1]Проектирование до 100'!E21*1.05 -> 10395 | P43: 0 | Q43: =ROUND(O43-O43*$V$3,2) -> 10395 | R43: =ROUND(P43-P43*$V$3,2) -> 0 | S43: =ROUND('Смета ЕР (общ) '!$N43*'Смета ЕР (общ) '!$Q43,2) -> 0 | T43: =ROUND('Смета ЕР (общ) '!$N43*'Смета ЕР (общ) '!$R43,2) -> 0
A44: Р1 | B44: 1 | D44: 51 | E44: =CONCATENATE('Смета ЕР (общ) '!$A44,".",'Смета ЕР (общ) '!$B44,".",'Смета ЕР (общ) '!$D44) -> Р1.1.51 | F44: =IF(N44>0,F43+1,F43) -> 1 | G44: Раздел №1. Проектные работы и согласования | H44: 1.1.0 Проектные работы и согласования | I44: Рабочая документация | J44: Рабочая документация Системы отопления ("ОВиК-О"), включая Пояснительную записку и Теплотехнический расчет | K44: (для помещений менее 100 м.кв) | L44: Рабочая документация Системы отопления ("ОВиК-О"), включая Пояснительную записку и Теплотехнический расчет (для помещений менее 100 м.кв) | M44: компл. | O44: ='[1]Проектирование до 100'!E22*1.05 -> 10395 | P44: 0 | Q44: =ROUND(O44-O44*$V$3,2) -> 10395 | R44: =ROUND(P44-P44*$V$3,2) -> 0 | S44: =ROUND('Смета ЕР (общ) '!$N44*'Смета ЕР (общ) '!$Q44,2) -> 0 | T44: =ROUND('Смета ЕР (общ) '!$N44*'Смета ЕР (общ) '!$R44,2) -> 0
A45: Р1 | B45: 1 | D45: 52 | E45: =CONCATENATE('Смета ЕР (общ) '!$A45,".",'Смета ЕР (общ) '!$B45,".",'Смета ЕР (общ) '!$D45) -> Р1.1.52 | F45: =IF(N45>0,F44+1,F44) -> 1 | G45: Раздел №1. Проектные работы и согласования | H45: 1.1.0 Проектные работы и согласования | I45: Рабочая документация | J45: Рабочая документация Системы водоснабжения и канализации ("ВК"), включая пояснительную записку | K45: (для помещений менее 100 м.кв) | L45: Рабочая документация Системы водоснабжения и канализации ("ВК"), включая пояснительную записку (для помещений менее 100 м.кв) | M45: компл. | O45: ='[1]Проектирование до 100'!E23*1.05 -> 10395 | P45: 0 | Q45: =ROUND(O45-O45*$V$3,2) -> 10395 | R45: =ROUND(P45-P45*$V$3,2) -> 0 | S45: =ROUND('Смета ЕР (общ) '!$N45*'Смета ЕР (общ) '!$Q45,2) -> 0 | T45: =ROUND('Смета ЕР (общ) '!$N45*'Смета ЕР (общ) '!$R45,2) -> 0
A46: Р1 | B46: 1 | D46: 53 | E46: =CONCATENATE('Смета ЕР (общ) '!$A46,".",'Смета ЕР (общ) '!$B46,".",'Смета ЕР (общ) '!$D46) -> Р1.1.53 | F46: =IF(N46>0,F45+1,F45) -> 1 | G46: Раздел №1. Проектные работы и согласования | H46: 1.1.0 Проектные работы и согласования | I46: Рабочая документация | J46: Рабочая документация Системы автоматической установки водяного пожаротушения ("АУВПТ"), (спринкерная, дренчерная, модульная система), включая пояснительную записку | K46: (для помещений менее 100 м.кв) | L46: Рабочая документация Системы автоматической установки водяного пожаротушения ("АУВПТ"), (спринкерная, дренчерная, модульная система), включая пояснительную записку (для помещений менее 100 м.кв) | M46: компл. | O46: ='[1]Проектирование до 100'!E24*1.05 -> 15592.5 | P46: 0 | Q46: =ROUND(O46-O46*$V$3,2) -> 15592.5 | R46: =ROUND(P46-P46*$V$3,2) -> 0 | S46: =ROUND('Смета ЕР (общ) '!$N46*'Смета ЕР (общ) '!$Q46,2) -> 0 | T46: =ROUND('Смета ЕР (общ) '!$N46*'Смета ЕР (общ) '!$R46,2) -> 0
A47: Р1 | B47: 1 | D47: 54 | E47: =CONCATENATE('Смета ЕР (общ) '!$A47,".",'Смета ЕР (общ) '!$B47,".",'Смета ЕР (общ) '!$D47) -> Р1.1.54 | F47: =IF(N47>0,F46+1,F46) -> 1 | G47: Раздел №1. Проектные работы и согласования | H47: 1.1.0 Проектные работы и согласования | I47: Рабочая документация | J47: Рабочая документация Системы Внутреннего противопожарного водопровода ("ВПВ"), включая пояснительную записку | K47: (для помещений менее 100 м.кв) | L47: Рабочая документация Системы Внутреннего противопожарного водопровода ("ВПВ"), включая пояснительную записку (для помещений менее 100 м.кв) | M47: компл. | O47: ='[1]Проектирование до 100'!E25*1.05 -> 10395 | P47: 0 | Q47: =ROUND(O47-O47*$V$3,2) -> 10395 | R47: =ROUND(P47-P47*$V$3,2) -> 0 | S47: =ROUND('Смета ЕР (общ) '!$N47*'Смета ЕР (общ) '!$Q47,2) -> 0 | T47: =ROUND('Смета ЕР (общ) '!$N47*'Смета ЕР (общ) '!$R47,2) -> 0
A48: Р1 | B48: 1 | D48: 55 | E48: =CONCATENATE('Смета ЕР (общ) '!$A48,".",'Смета ЕР (общ) '!$B48,".",'Смета ЕР (общ) '!$D48) -> Р1.1.55 | F48: =IF(N48>0,F47+1,F47) -> 1 | G48: Раздел №1. Проектные работы и согласования | H48: 1.1.0 Проектные работы и согласования | I48: Рабочая документация | J48: Рабочая документация Системы дымоудаления ("ДУ"), включая пояснительную записку | K48: (для помещений менее 100 м.кв) | L48: Рабочая документация Системы дымоудаления ("ДУ"), включая пояснительную записку (для помещений менее 100 м.кв) | M48: компл. | O48: ='[1]Проектирование до 100'!E26*1.05 -> 15592.5 | P48: 0 | Q48: =ROUND(O48-O48*$V$3,2) -> 15592.5 | R48: =ROUND(P48-P48*$V$3,2) -> 0 | S48: =ROUND('Смета ЕР (общ) '!$N48*'Смета ЕР (общ) '!$Q48,2) -> 0 | T48: =ROUND('Смета ЕР (общ) '!$N48*'Смета ЕР (общ) '!$R48,2) -> 0
A49: Р1 | B49: 1 | D49: 56 | E49: =CONCATENATE('Смета ЕР (общ) '!$A49,".",'Смета ЕР (общ) '!$B49,".",'Смета ЕР (общ) '!$D49) -> Р1.1.56 | F49: =IF(N49>0,F48+1,F48) -> 1 | G49: Раздел №1. Проектные работы и согласования | H49: 1.1.0 Проектные работы и согласования | I49: Исполнительная документация | J49: Исполнительная документация по усилению/устройству несущих конструкций ("КР"), включая пояснительную записку | K49: (для объектов более 100 кв.м.) | L49: Исполнительная документация по усилению/устройству несущих конструкций ("КР"), включая пояснительную записку (для объектов более 100 кв.м.) | M49: м2 | O49: ='[1]Проектирование 100-450'!E18*1.05*0.1 -> 13.545 | P49: 0 | Q49: =ROUND(O49-O49*$V$3,2) -> 13.55 | R49: =ROUND(P49-P49*$V$3,2) -> 0 | S49: =ROUND('Смета ЕР (общ) '!$N49*'Смета ЕР (общ) '!$Q49,2) -> 0 | T49: =ROUND('Смета ЕР (общ) '!$N49*'Смета ЕР (общ) '!$R49,2) -> 0
A50: Р1 | B50: 1 | D50: 57 | E50: =CONCATENATE('Смета ЕР (общ) '!$A50,".",'Смета ЕР (общ) '!$B50,".",'Смета ЕР (общ) '!$D50) -> Р1.1.57 | F50: =IF(N50>0,F49+1,F49) -> 1 | G50: Раздел №1. Проектные работы и согласования | H50: 1.1.0 Проектные работы и согласования | I50: Исполнительная документация | J50: Исполнительная документация "Архитектурные решения" ("АР"), включая пояснительную записку | K50: (для объектов более 100 кв.м.) | L50: Исполнительная документация "Архитектурные решения" ("АР"), включая пояснительную записку (для объектов более 100 кв.м.) | M50: м2 | O50: ='[1]Проектирование 100-450'!E19*1.05*0.1 -> 38.955 | P50: 0 | Q50: =ROUND(O50-O50*$V$3,2) -> 38.96 | R50: =ROUND(P50-P50*$V$3,2) -> 0 | S50: =ROUND('Смета ЕР (общ) '!$N50*'Смета ЕР (общ) '!$Q50,2) -> 0 | T50: =ROUND('Смета ЕР (общ) '!$N50*'Смета ЕР (общ) '!$R50,2) -> 0
A51: Р1 | B51: 1 | D51: 58 | E51: =CONCATENATE('Смета ЕР (общ) '!$A51,".",'Смета ЕР (общ) '!$B51,".",'Смета ЕР (общ) '!$D51) -> Р1.1.58 | F51: =IF(N51>0,F50+1,F50) -> 1 | G51: Раздел №1. Проектные работы и согласования | H51: 1.1.0 Проектные работы и согласования | I51: Исполнительная документация | J51: Исполнительная документация по электроснабжению и электроосвещению ("ЭОМ"), включая пояснительную записку | K51: (для объектов более 100 кв.м.) | L51: Исполнительная документация по электроснабжению и электроосвещению ("ЭОМ"), включая пояснительную записку (для объектов более 100 кв.м.) | M51: м2 | O51: ='[1]Проектирование 100-450'!E20*1.05*0.1 -> 25.83 | P51: 0 | Q51: =ROUND(O51-O51*$V$3,2) -> 25.83 | R51: =ROUND(P51-P51*$V$3,2) -> 0 | S51: =ROUND('Смета ЕР (общ) '!$N51*'Смета ЕР (общ) '!$Q51,2) -> 0 | T51: =ROUND('Смета ЕР (общ) '!$N51*'Смета ЕР (общ) '!$R51,2) -> 0
A52: Р1 | B52: 1 | D52: 59 | E52: =CONCATENATE('Смета ЕР (общ) '!$A52,".",'Смета ЕР (общ) '!$B52,".",'Смета ЕР (общ) '!$D52) -> Р1.1.59 | F52: =IF(N52>0,F51+1,F51) -> 1 | G52: Раздел №1. Проектные работы и согласования | H52: 1.1.0 Проектные работы и согласования | I52: Исполнительная документация | J52: Исполнительная документация Системы вентиляции ("ОВиК-В"), включая пояснительную записку | K52: (для объектов более 100 кв.м.) | L52: Исполнительная документация Системы вентиляции ("ОВиК-В"), включая пояснительную записку (для объектов более 100 кв.м.) | M52: м2 | O52: ='[1]Проектирование 100-450'!E21*1.05*0.1 -> 20.265 | P52: 0 | Q52: =ROUND(O52-O52*$V$3,2) -> 20.27 | R52: =ROUND(P52-P52*$V$3,2) -> 0 | S52: =ROUND('Смета ЕР (общ) '!$N52*'Смета ЕР (общ) '!$Q52,2) -> 0 | T52: =ROUND('Смета ЕР (общ) '!$N52*'Смета ЕР (общ) '!$R52,2) -> 0
A53: Р1 | B53: 1 | D53: 60 | E53: =CONCATENATE('Смета ЕР (общ) '!$A53,".",'Смета ЕР (общ) '!$B53,".",'Смета ЕР (общ) '!$D53) -> Р1.1.60 | F53: =IF(N53>0,F52+1,F52) -> 1 | G53: Раздел №1. Проектные работы и согласования | H53: 1.1.0 Проектные работы и согласования | I53: Исполнительная документация | J53: Исполнительная документация Системы кондиционирования ("ОВиК-К"), включая пояснительную записку | K53: (для объектов более 100 кв.м.) | L53: Исполнительная документация Системы кондиционирования ("ОВиК-К"), включая пояснительную записку (для объектов более 100 кв.м.) | M53: м2 | O53: ='[1]Проектирование 100-450'!E22*1.05*0.1 -> 15.94845 | P53: 0 | Q53: =ROUND(O53-O53*$V$3,2) -> 15.95 | R53: =ROUND(P53-P53*$V$3,2) -> 0 | S53: =ROUND('Смета ЕР (общ) '!$N53*'Смета ЕР (общ) '!$Q53,2) -> 0 | T53: =ROUND('Смета ЕР (общ) '!$N53*'Смета ЕР (общ) '!$R53,2) -> 0
A54: Р1 | B54: 1 | D54: 61 | E54: =CONCATENATE('Смета ЕР (общ) '!$A54,".",'Смета ЕР (общ) '!$B54,".",'Смета ЕР (общ) '!$D54) -> Р1.1.61 | F54: =IF(N54>0,F53+1,F53) -> 1 | G54: Раздел №1. Проектные работы и согласования | H54: 1.1.0 Проектные работы и согласования | I54: Исполнительная документация | J54: Исполнительная документация Системы отопления ("ОВиК-О"), включая Пояснительную записку и Теплотехнический расчет | K54: (для объектов более 100 кв.м.) | L54: Исполнительная документация Системы отопления ("ОВиК-О"), включая Пояснительную записку и Теплотехнический расчет (для объектов более 100 кв.м.) | M54: м2 | O54: ='[1]Проектирование 100-450'!E23*1.05*0.1 -> 12.39 | P54: 0 | Q54: =ROUND(O54-O54*$V$3,2) -> 12.39 | R54: =ROUND(P54-P54*$V$3,2) -> 0 | S54: =ROUND('Смета ЕР (общ) '!$N54*'Смета ЕР (общ) '!$Q54,2) -> 0 | T54: =ROUND('Смета ЕР (общ) '!$N54*'Смета ЕР (общ) '!$R54,2) -> 0
A55: Р1 | B55: 1 | D55: 62 | E55: =CONCATENATE('Смета ЕР (общ) '!$A55,".",'Смета ЕР (общ) '!$B55,".",'Смета ЕР (общ) '!$D55) -> Р1.1.62 | F55: =IF(N55>0,F54+1,F54) -> 1 | G55: Раздел №1. Проектные работы и согласования | H55: 1.1.0 Проектные работы и согласования | I55: Исполнительная документация | J55: Исполнительная документация Системы водоснабжения и канализации ("ВК"), включая пояснительную записку | K55: (для объектов более 100 кв.м.) | L55: Исполнительная документация Системы водоснабжения и канализации ("ВК"), включая пояснительную записку (для объектов более 100 кв.м.) | M55: м2 | O55: ='[1]Проектирование 100-450'!E24*1.05*0.1 -> 13.02 | P55: 0 | Q55: =ROUND(O55-O55*$V$3,2) -> 13.02 | R55: =ROUND(P55-P55*$V$3,2) -> 0 | S55: =ROUND('Смета ЕР (общ) '!$N55*'Смета ЕР (общ) '!$Q55,2) -> 0 | T55: =ROUND('Смета ЕР (общ) '!$N55*'Смета ЕР (общ) '!$R55,2) -> 0
A56: Р1 | B56: 1 | D56: 63 | E56: =CONCATENATE('Смета ЕР (общ) '!$A56,".",'Смета ЕР (общ) '!$B56,".",'Смета ЕР (общ) '!$D56) -> Р1.1.63 | F56: =IF(N56>0,F55+1,F55) -> 1 | G56: Раздел №1. Проектные работы и согласования | H56: 1.1.0 Проектные работы и согласования | I56: Исполнительная документация | J56: Исполнительная документация Системы автматической установки водяного пожаротушения ("АУВПТ"), (спринкерная, дренчерная, модульная система), включая пояснительную записку | K56: (для объектов более 100 кв.м.) | L56: Исполнительная документация Системы автматической установки водяного пожаротушения ("АУВПТ"), (спринкерная, дренчерная, модульная система), включая пояснительную записку (для объектов более 100 кв.м.) | M56: м2 | O56: ='[1]Проектирование 100-450'!E25*1.05*0.1 -> 9.16755 | P56: 0 | Q56: =ROUND(O56-O56*$V$3,2) -> 9.17 | R56: =ROUND(P56-P56*$V$3,2) -> 0 | S56: =ROUND('Смета ЕР (общ) '!$N56*'Смета ЕР (общ) '!$Q56,2) -> 0 | T56: =ROUND('Смета ЕР (общ) '!$N56*'Смета ЕР (общ) '!$R56,2) -> 0
A57: Р1 | B57: 1 | D57: 64 | E57: =CONCATENATE('Смета ЕР (общ) '!$A57,".",'Смета ЕР (общ) '!$B57,".",'Смета ЕР (общ) '!$D57) -> Р1.1.64 | F57: =IF(N57>0,F56+1,F56) -> 1 | G57: Раздел №1. Проектные работы и согласования | H57: 1.1.0 Проектные работы и согласования | I57: Исполнительная документация | J57: Исполнительная документация Системы Внутреннего противопожарного водопровода ("ВПВ"), включая пояснительную записку | K57: (для объектов более 100 кв.м.) | L57: Исполнительная документация Системы Внутреннего противопожарного водопровода ("ВПВ"), включая пояснительную записку (для объектов более 100 кв.м.) | M57: м2 | O57: ='[1]Проектирование 100-450'!E26*1.05*0.1 -> 9.16755 | P57: 0 | Q57: =ROUND(O57-O57*$V$3,2) -> 9.17 | R57: =ROUND(P57-P57*$V$3,2) -> 0 | S57: =ROUND('Смета ЕР (общ) '!$N57*'Смета ЕР (общ) '!$Q57,2) -> 0 | T57: =ROUND('Смета ЕР (общ) '!$N57*'Смета ЕР (общ) '!$R57,2) -> 0
A58: Р1 | B58: 1 | D58: 65 | E58: =CONCATENATE('Смета ЕР (общ) '!$A58,".",'Смета ЕР (общ) '!$B58,".",'Смета ЕР (общ) '!$D58) -> Р1.1.65 | F58: =IF(N58>0,F57+1,F57) -> 1 | G58: Раздел №1. Проектные работы и согласования | H58: 1.1.0 Проектные работы и согласования | I58: Исполнительная документация | J58: Исполнительная документация Системы дымоудаления ("ДУ"), включая пояснительную записку | K58: (для объектов более 100 кв.м.) | L58: Исполнительная документация Системы дымоудаления ("ДУ"), включая пояснительную записку (для объектов более 100 кв.м.) | M58: м2 | O58: ='[1]Проектирование 100-450'!E27*1.05*0.1 -> 10.395 | P58: 0 | Q58: =ROUND(O58-O58*$V$3,2) -> 10.4 | R58: =ROUND(P58-P58*$V$3,2) -> 0 | S58: =ROUND('Смета ЕР (общ) '!$N58*'Смета ЕР (общ) '!$Q58,2) -> 0 | T58: =ROUND('Смета ЕР (общ) '!$N58*'Смета ЕР (общ) '!$R58,2) -> 0
A59: Р1 | B59: 1 | D59: 66 | E59: =CONCATENATE('Смета ЕР (общ) '!$A59,".",'Смета ЕР (общ) '!$B59,".",'Смета ЕР (общ) '!$D59) -> Р1.1.66 | F59: =IF(N59>0,F58+1,F58) -> 1 | G59: Раздел №1. Проектные работы и согласования | H59: 1.1.0 Проектные работы и согласования | I59: Исполнительная документация | J59: Исполнительная документация по усилению/устройству несущих конструкций ("КР"), включая пояснительную записку | K59: (для объектов более 100 кв.м.) | L59: Исполнительная документация по усилению/устройству несущих конструкций ("КР"), включая пояснительную записку (для объектов менее 100 кв.м.) | M59: компл. | O59: ='[1]Проектирование до 100'!E17*1.05*0.1 -> 1050 | P59: 0 | Q59: =ROUND(O59-O59*$V$3,2) -> 1050 | R59: =ROUND(P59-P59*$V$3,2) -> 0 | S59: =ROUND('Смета ЕР (общ) '!$N59*'Смета ЕР (общ) '!$Q59,2) -> 0 | T59: =ROUND('Смета ЕР (общ) '!$N59*'Смета ЕР (общ) '!$R59,2) -> 0
A60: Р1 | B60: 1 | D60: 67 | E60: =CONCATENATE('Смета ЕР (общ) '!$A60,".",'Смета ЕР (общ) '!$B60,".",'Смета ЕР (общ) '!$D60) -> Р1.1.67 | F60: =IF(N60>0,F59+1,F59) -> 1 | G60: Раздел №1. Проектные работы и согласования | H60: 1.1.0 Проектные работы и согласования | I60: Исполнительная документация | J60: Исполнительная документация "Архитектурные решения" ("АР"), включая пояснительную записку | K60: (для объектов более 100 кв.м.) | L60: Исполнительная документация "Архитектурные решения" ("АР"), включая пояснительную записку (для объектов менее 100 кв.м.) | M60: компл. | O60: ='[1]Проектирование до 100'!E18*1.05*0.1 -> 2073.75 | P60: 0 | Q60: =ROUND(O60-O60*$V$3,2) -> 2073.75 | R60: =ROUND(P60-P60*$V$3,2) -> 0 | S60: =ROUND('Смета ЕР (общ) '!$N60*'Смета ЕР (общ) '!$Q60,2) -> 0 | T60: =ROUND('Смета ЕР (общ) '!$N60*'Смета ЕР (общ) '!$R60,2) -> 0
A61: Р1 | B61: 1 | D61: 68 | E61: =CONCATENATE('Смета ЕР (общ) '!$A61,".",'Смета ЕР (общ) '!$B61,".",'Смета ЕР (общ) '!$D61) -> Р1.1.68 | F61: =IF(N61>0,F60+1,F60) -> 1 | G61: Раздел №1. Проектные работы и согласования | H61: 1.1.0 Проектные работы и согласования | I61: Исполнительная документация | J61: Исполнительная документация по электроснабжению и электроосвещению ("ЭОМ"), включая пояснительную записку | K61: (для объектов более 100 кв.м.) | L61: Исполнительная документация по электроснабжению и электроосвещению ("ЭОМ"), включая пояснительную записку (для объектов менее 100 кв.м.) | M61: компл. | O61: ='[1]Проектирование до 100'!E19*1.05*0.1 -> 2073.75 | P61: 0 | Q61: =ROUND(O61-O61*$V$3,2) -> 2073.75 | R61: =ROUND(P61-P61*$V$3,2) -> 0 | S61: =ROUND('Смета ЕР (общ) '!$N61*'Смета ЕР (общ) '!$Q61,2) -> 0 | T61: =ROUND('Смета ЕР (общ) '!$N61*'Смета ЕР (общ) '!$R61,2) -> 0
A62: Р1 | B62: 1 | D62: 69 | E62: =CONCATENATE('Смета ЕР (общ) '!$A62,".",'Смета ЕР (общ) '!$B62,".",'Смета ЕР (общ) '!$D62) -> Р1.1.69 | F62: =IF(N62>0,F61+1,F61) -> 1 | G62: Раздел №1. Проектные работы и согласования | H62: 1.1.0 Проектные работы и согласования | I62: Исполнительная документация | J62: Исполнительная документация Системы вентиляции ("ОВиК-В"), включая пояснительную записку | K62: (для объектов более 100 кв.м.) | L62: Исполнительная документация Системы вентиляции ("ОВиК-В"), включая пояснительную записку (для объектов менее 100 кв.м.) | M62: компл. | O62: ='[1]Проектирование до 100'!E20*1.05*0.1 -> 1559.25 | P62: 0 | Q62: =ROUND(O62-O62*$V$3,2) -> 1559.25 | R62: =ROUND(P62-P62*$V$3,2) -> 0 | S62: =ROUND('Смета ЕР (общ) '!$N62*'Смета ЕР (общ) '!$Q62,2) -> 0 | T62: =ROUND('Смета ЕР (общ) '!$N62*'Смета ЕР (общ) '!$R62,2) -> 0
A63: Р1 | B63: 1 | D63: 70 | E63: =CONCATENATE('Смета ЕР (общ) '!$A63,".",'Смета ЕР (общ) '!$B63,".",'Смета ЕР (общ) '!$D63) -> Р1.1.70 | F63: =IF(N63>0,F62+1,F62) -> 1 | G63: Раздел №1. Проектные работы и согласования | H63: 1.1.0 Проектные работы и согласования | I63: Исполнительная документация | J63: Исполнительная документация Системы кондиционирования ("ОВиК-К"), включая пояснительную записку | K63: (для объектов более 100 кв.м.) | L63: Исполнительная документация Системы кондиционирования ("ОВиК-К"), включая пояснительную записку (для объектов менее 100 кв.м.) | M63: компл. | O63: ='[1]Проектирование до 100'!E21*1.05*0.1 -> 1039.5 | P63: 0 | Q63: =ROUND(O63-O63*$V$3,2) -> 1039.5 | R63: =ROUND(P63-P63*$V$3,2) -> 0 | S63: =ROUND('Смета ЕР (общ) '!$N63*'Смета ЕР (общ) '!$Q63,2) -> 0 | T63: =ROUND('Смета ЕР (общ) '!$N63*'Смета ЕР (общ) '!$R63,2) -> 0
A64: Р1 | B64: 1 | D64: 71 | E64: =CONCATENATE('Смета ЕР (общ) '!$A64,".",'Смета ЕР (общ) '!$B64,".",'Смета ЕР (общ) '!$D64) -> Р1.1.71 | F64: =IF(N64>0,F63+1,F63) -> 1 | G64: Раздел №1. Проектные работы и согласования | H64: 1.1.0 Проектные работы и согласования | I64: Исполнительная документация | J64: Исполнительная документация Системы отопления ("ОВиК-О"), включая Пояснительную записку и Теплотехнический расчет | K64: (для объектов более 100 кв.м.) | L64: Исполнительная документация Системы отопления ("ОВиК-О"), включая Пояснительную записку и Теплотехнический расчет (для объектов менее 100 кв.м.) | M64: компл. | O64: ='[1]Проектирование до 100'!E22*1.05*0.1 -> 1039.5 | P64: 0 | Q64: =ROUND(O64-O64*$V$3,2) -> 1039.5 | R64: =ROUND(P64-P64*$V$3,2) -> 0 | S64: =ROUND('Смета ЕР (общ) '!$N64*'Смета ЕР (общ) '!$Q64,2) -> 0 | T64: =ROUND('Смета ЕР (общ) '!$N64*'Смета ЕР (общ) '!$R64,2) -> 0
A65: Р1 | B65: 1 | D65: 72 | E65: =CONCATENATE('Смета ЕР (общ) '!$A65,".",'Смета ЕР (общ) '!$B65,".",'Смета ЕР (общ) '!$D65) -> Р1.1.72 | F65: =IF(N65>0,F64+1,F64) -> 1 | G65: Раздел №1. Проектные работы и согласования | H65: 1.1.0 Проектные работы и согласования | I65: Исполнительная документация | J65: Исполнительная документация Системы водоснабжения и канализации ("ВК"), включая пояснительную записку | K65: (для объектов более 100 кв.м.) | L65: Исполнительная документация Системы водоснабжения и канализации ("ВК"), включая пояснительную записку (для объектов менее 100 кв.м.) | M65: компл. | O65: ='[1]Проектирование до 100'!E23*1.05*0.1 -> 1039.5 | P65: 0 | Q65: =ROUND(O65-O65*$V$3,2) -> 1039.5 | R65: =ROUND(P65-P65*$V$3,2) -> 0 | S65: =ROUND('Смета ЕР (общ) '!$N65*'Смета ЕР (общ) '!$Q65,2) -> 0 | T65: =ROUND('Смета ЕР (общ) '!$N65*'Смета ЕР (общ) '!$R65,2) -> 0
A66: Р1 | B66: 1 | D66: 73 | E66: =CONCATENATE('Смета ЕР (общ) '!$A66,".",'Смета ЕР (общ) '!$B66,".",'Смета ЕР (общ) '!$D66) -> Р1.1.73 | F66: =IF(N66>0,F65+1,F65) -> 1 | G66: Раздел №1. Проектные работы и согласования | H66: 1.1.0 Проектные работы и согласования | I66: Исполнительная документация | J66: Исполнительная документация Системы автматической установки водяного пожаротушения ("АУВПТ"), (спринкерная, дренчерная, модульная система), включая пояснительную записку | K66: (для объектов более 100 кв.м.) | L66: Исполнительная документация Системы автматической установки водяного пожаротушения ("АУВПТ"), (спринкерная, дренчерная, модульная система), включая пояснительную записку (для объектов менее 100 кв.м.) | M66: компл. | O66: ='[1]Проектирование до 100'!E24*1.05*0.1 -> 1559.25 | P66: 0 | Q66: =ROUND(O66-O66*$V$3,2) -> 1559.25 | R66: =ROUND(P66-P66*$V$3,2) -> 0 | S66: =ROUND('Смета ЕР (общ) '!$N66*'Смета ЕР (общ) '!$Q66,2) -> 0 | T66: =ROUND('Смета ЕР (общ) '!$N66*'Смета ЕР (общ) '!$R66,2) -> 0
A67: Р1 | B67: 1 | D67: 74 | E67: =CONCATENATE('Смета ЕР (общ) '!$A67,".",'Смета ЕР (общ) '!$B67,".",'Смета ЕР (общ) '!$D67) -> Р1.1.74 | F67: =IF(N67>0,F66+1,F66) -> 1 | G67: Раздел №1. Проектные работы и согласования | H67: 1.1.0 Проектные работы и согласования | I67: Исполнительная документация | J67: Исполнительная документация Системы Внутреннего противопожарного водопровода ("ВПВ"), включая пояснительную записку | K67: (для объектов более 100 кв.м.) | L67: Исполнительная документация Системы Внутреннего противопожарного водопровода ("ВПВ"), включая пояснительную записку (для объектов менее 100 кв.м.) | M67: компл. | O67: ='[1]Проектирование до 100'!E25*1.05*0.1 -> 1039.5 | P67: 0 | Q67: =ROUND(O67-O67*$V$3,2) -> 1039.5 | R67: =ROUND(P67-P67*$V$3,2) -> 0 | S67: =ROUND('Смета ЕР (общ) '!$N67*'Смета ЕР (общ) '!$Q67,2) -> 0 | T67: =ROUND('Смета ЕР (общ) '!$N67*'Смета ЕР (общ) '!$R67,2) -> 0
A68: Р1 | B68: 1 | D68: 75 | E68: =CONCATENATE('Смета ЕР (общ) '!$A68,".",'Смета ЕР (общ) '!$B68,".",'Смета ЕР (общ) '!$D68) -> Р1.1.75 | F68: =IF(N68>0,F67+1,F67) -> 1 | G68: Раздел №1. Проектные работы и согласования | H68: 1.1.0 Проектные работы и согласования | I68: Исполнительная документация | J68: Исполнительная документация Системы дымоудаления ("ДУ"), включая пояснительную записку | K68: (для объектов более 100 кв.м.) | L68: Исполнительная документация Системы дымоудаления ("ДУ"), включая пояснительную записку (для объектов менее 100 кв.м.) | M68: компл. | O68: ='[1]Проектирование до 100'!E26*1.05*0.1 -> 1559.25 | P68: 0 | Q68: =ROUND(O68-O68*$V$3,2) -> 1559.25 | R68: =ROUND(P68-P68*$V$3,2) -> 0 | S68: =ROUND('Смета ЕР (общ) '!$N68*'Смета ЕР (общ) '!$Q68,2) -> 0 | T68: =ROUND('Смета ЕР (общ) '!$N68*'Смета ЕР (общ) '!$R68,2) -> 0
A69: Р1 | B69: 1 | D69: 76 | E69: =CONCATENATE('Смета ЕР (общ) '!$A69,".",'Смета ЕР (общ) '!$B69,".",'Смета ЕР (общ) '!$D69) -> Р1.1.76 | F69: =IF(N69>0,F68+1,F68) -> 1 | G69: Раздел №1. Проектные работы и согласования | H69: 1.1.0 Проектные работы и согласования | I69: Рабочая документация | J69: Рабочая документация "Автоматическая пожарная сигнализация" (АПС) | L69: Рабочая документация "Автоматическая пожарная сигнализация" (АПС) | M69: м2 | O69: ='[1]АПС, СОУЭ, ППА'!F13*1.05 -> 70.35 | P69: 1 | Q69: =ROUND(O69-O69*$V$3,2) -> 70.35 | R69: =ROUND(P69-P69*$V$3,2) -> 1 | S69: =ROUND('Смета ЕР (общ) '!$N69*'Смета ЕР (общ) '!$Q69,2) -> 0 | T69: =ROUND('Смета ЕР (общ) '!$N69*'Смета ЕР (общ) '!$R69,2) -> 0
A70: Р1 | B70: 1 | D70: 77 | E70: =CONCATENATE('Смета ЕР (общ) '!$A70,".",'Смета ЕР (общ) '!$B70,".",'Смета ЕР (общ) '!$D70) -> Р1.1.77 | F70: =IF(N70>0,F69+1,F69) -> 1 | G70: Раздел №1. Проектные работы и согласования | H70: 1.1.0 Проектные работы и согласования | I70: Рабочая документация | J70: Рабочая документация "Система оповещения и управления эвакуацией людей при пожаре" (СОУЭ) | L70: Рабочая документация "Система оповещения и управления эвакуацией людей при пожаре" (СОУЭ) | M70: м2 | O70: ='[1]АПС, СОУЭ, ППА'!F14*1.05 -> 40.95 | P70: 2 | Q70: =ROUND(O70-O70*$V$3,2) -> 40.95 | R70: =ROUND(P70-P70*$V$3,2) -> 2 | S70: =ROUND('Смета ЕР (общ) '!$N70*'Смета ЕР (общ) '!$Q70,2) -> 0 | T70: =ROUND('Смета ЕР (общ) '!$N70*'Смета ЕР (общ) '!$R70,2) -> 0
A71: Р1 | B71: 1 | D71: 78 | E71: =CONCATENATE('Смета ЕР (общ) '!$A71,".",'Смета ЕР (общ) '!$B71,".",'Смета ЕР (общ) '!$D71) -> Р1.1.78 | F71: =IF(N71>0,F70+1,F70) -> 1 | G71: Раздел №1. Проектные работы и согласования | H71: 1.1.0 Проектные работы и согласования | I71: Рабочая документация | J71: Рабочая документация "Автоматизация системы внутреннего противопожарного водопровода (ВПВ) | L71: Рабочая документация "Автоматизация системы внутреннего противопожарного водопровода (ВПВ) | M71: м2 | O71: ='[1]АПС, СОУЭ, ППА'!F16*1.05 -> 8.4 | P71: 3 | Q71: =ROUND(O71-O71*$V$3,2) -> 8.4 | R71: =ROUND(P71-P71*$V$3,2) -> 3 | S71: =ROUND('Смета ЕР (общ) '!$N71*'Смета ЕР (общ) '!$Q71,2) -> 0 | T71: =ROUND('Смета ЕР (общ) '!$N71*'Смета ЕР (общ) '!$R71,2) -> 0
A72: Р1 | B72: 1 | D72: 79 | E72: =CONCATENATE('Смета ЕР (общ) '!$A72,".",'Смета ЕР (общ) '!$B72,".",'Смета ЕР (общ) '!$D72) -> Р1.1.79 | F72: =IF(N72>0,F71+1,F71) -> 1 | G72: Раздел №1. Проектные работы и согласования | H72: 1.1.0 Проектные работы и согласования | I72: Рабочая документация | J72: Рабочая документация "Автоматизация системы противодымной вентиляции (ПДВ")" | L72: Рабочая документация "Автоматизация системы противодымной вентиляции (ПДВ")" | M72: м2 | O72: ='[1]АПС, СОУЭ, ППА'!F17*1.05 -> 26.25 | P72: 4 | Q72: =ROUND(O72-O72*$V$3,2) -> 26.25 | R72: =ROUND(P72-P72*$V$3,2) -> 4 | S72: =ROUND('Смета ЕР (общ) '!$N72*'Смета ЕР (общ) '!$Q72,2) -> 0 | T72: =ROUND('Смета ЕР (общ) '!$N72*'Смета ЕР (общ) '!$R72,2) -> 0
A73: Р1 | B73: 1 | D73: 80 | E73: =CONCATENATE('Смета ЕР (общ) '!$A73,".",'Смета ЕР (общ) '!$B73,".",'Смета ЕР (общ) '!$D73) -> Р1.1.80 | F73: =IF(N73>0,F72+1,F72) -> 1 | G73: Раздел №1. Проектные работы и согласования | H73: 1.1.0 Проектные работы и согласования | I73: Рабочая документация | J73: Рабочая документация "Автоматизация Системы отопления, вентиляции и кондиционирования (ОВиК)" | L73: Рабочая документация "Автоматизация Системы отопления, вентиляции и кондиционирования (ОВиК)" | M73: м2 | O73: ='[1]АПС, СОУЭ, ППА'!F18*1.05 -> 3.15 | P73: 5 | Q73: =ROUND(O73-O73*$V$3,2) -> 3.15 | R73: =ROUND(P73-P73*$V$3,2) -> 5 | S73: =ROUND('Смета ЕР (общ) '!$N73*'Смета ЕР (общ) '!$Q73,2) -> 0 | T73: =ROUND('Смета ЕР (общ) '!$N73*'Смета ЕР (общ) '!$R73,2) -> 0
A74: Р1 | B74: 1 | D74: 81 | E74: =CONCATENATE('Смета ЕР (общ) '!$A74,".",'Смета ЕР (общ) '!$B74,".",'Смета ЕР (общ) '!$D74) -> Р1.1.81 | F74: =IF(N74>0,F73+1,F73) -> 1 | G74: Раздел №1. Проектные работы и согласования | H74: 1.1.0 Проектные работы и согласования | I74: Рабочая документация | J74: Рабочая документация "Автоматизация Системы аварийного освещения (АО)" | L74: Рабочая документация "Автоматизация Системы аварийного освещения (АО)" | M74: м2 | O74: ='[1]АПС, СОУЭ, ППА'!F19*1.05 -> 1.05 | P74: 6 | Q74: =ROUND(O74-O74*$V$3,2) -> 1.05 | R74: =ROUND(P74-P74*$V$3,2) -> 6 | S74: =ROUND('Смета ЕР (общ) '!$N74*'Смета ЕР (общ) '!$Q74,2) -> 0 | T74: =ROUND('Смета ЕР (общ) '!$N74*'Смета ЕР (общ) '!$R74,2) -> 0
A75: Р1 | B75: 1 | D75: 82 | E75: =CONCATENATE('Смета ЕР (общ) '!$A75,".",'Смета ЕР (общ) '!$B75,".",'Смета ЕР (общ) '!$D75) -> Р1.1.82 | F75: =IF(N75>0,F74+1,F74) -> 1 | G75: Раздел №1. Проектные работы и согласования | H75: 1.1.0 Проектные работы и согласования | I75: Рабочая документация | J75: Рабочая документация "Автоматизации лифтовового хозяйства" | L75: Рабочая документация "Автоматизации лифтовового хозяйства" | M75: м2 | O75: ='[1]АПС, СОУЭ, ППА'!F20*1.05 -> 1.05 | P75: 7 | Q75: =ROUND(O75-O75*$V$3,2) -> 1.05 | R75: =ROUND(P75-P75*$V$3,2) -> 7 | S75: =ROUND('Смета ЕР (общ) '!$N75*'Смета ЕР (общ) '!$Q75,2) -> 0 | T75: =ROUND('Смета ЕР (общ) '!$N75*'Смета ЕР (общ) '!$R75,2) -> 0
A76: Р1 | B76: 1 | D76: 83 | E76: =CONCATENATE('Смета ЕР (общ) '!$A76,".",'Смета ЕР (общ) '!$B76,".",'Смета ЕР (общ) '!$D76) -> Р1.1.83 | F76: =IF(N76>0,F75+1,F75) -> 1 | G76: Раздел №1. Проектные работы и согласования | H76: 1.1.0 Проектные работы и согласования | I76: Рабочая документация | J76: Рабочая документация "Автоматизации Системы контроля управления доступом (СКУД)" | L76: Рабочая документация "Автоматизации Системы контроля управления доступом (СКУД)" | M76: м2 | O76: ='[1]АПС, СОУЭ, ППА'!F21*1.05 -> 1.05 | P76: 8 | Q76: =ROUND(O76-O76*$V$3,2) -> 1.05 | R76: =ROUND(P76-P76*$V$3,2) -> 8 | S76: =ROUND('Смета ЕР (общ) '!$N76*'Смета ЕР (общ) '!$Q76,2) -> 0 | T76: =ROUND('Смета ЕР (общ) '!$N76*'Смета ЕР (общ) '!$R76,2) -> 0
A77: Р1 | B77: 1 | D77: 12 | E77: =CONCATENATE('Смета ЕР (общ) '!$A77,".",'Смета ЕР (общ) '!$B77,".",'Смета ЕР (общ) '!$D77) -> Р1.1.12 | F77: =IF(N77>0,F76+1,F76) -> 1 | G77: Раздел №1. Проектные работы и согласования | H77: 1.1.0 Проектные работы и согласования | L77: Стоимость согласования проекта перепланировки/реставрации объекта культурного наследия в соответствии с нормативными актами г.______________. | M77: м2 | O77: 0 | P77: 0 | Q77: =ROUND(O77-O77*$V$3,2) -> 0 | R77: =ROUND(P77-P77*$V$3,2) -> 0 | S77: =ROUND('Смета ЕР (общ) '!$N77*'Смета ЕР (общ) '!$Q77,2) -> 0 | T77: =ROUND('Смета ЕР (общ) '!$N77*'Смета ЕР (общ) '!$R77,2) -> 0 | U77: цена по КП
A78: Р1 | B78: 1 | D78: 13 | E78: =CONCATENATE('Смета ЕР (общ) '!$A78,".",'Смета ЕР (общ) '!$B78,".",'Смета ЕР (общ) '!$D78) -> Р1.1.13 | F78: =IF(N78>0,F77+1,F77) -> 1 | G78: Раздел №1. Проектные работы и согласования | H78: 1.1.0 Проектные работы и согласования | L78: Стоимость согласования проекта перепланировки/реконструкции объекта в соответствии с нормативными актами г.______________. | M78: м2 | O78: 0 | P78: 0 | Q78: =ROUND(O78-O78*$V$3,2) -> 0 | R78: =ROUND(P78-P78*$V$3,2) -> 0 | S78: =ROUND('Смета ЕР (общ) '!$N78*'Смета ЕР (общ) '!$Q78,2) -> 0 | T78: =ROUND('Смета ЕР (общ) '!$N78*'Смета ЕР (общ) '!$R78,2) -> 0 | U78: цена по КП
A79: Р1 | B79: 1 | D79: 14 | E79: =CONCATENATE('Смета ЕР (общ) '!$A79,".",'Смета ЕР (общ) '!$B79,".",'Смета ЕР (общ) '!$D79) -> Р1.1.14 | F79: =IF(N79>0,F78+1,F78) -> 1 | G79: Раздел №1. Проектные работы и согласования | H79: 1.1.0 Проектные работы и согласования | L79: Получение паспорта БТИ (в черных линиях) | M79: м2 | O79: 0 | P79: 0 | Q79: =ROUND(O79-O79*$V$3,2) -> 0 | R79: =ROUND(P79-P79*$V$3,2) -> 0 | S79: =ROUND('Смета ЕР (общ) '!$N79*'Смета ЕР (общ) '!$Q79,2) -> 0 | T79: =ROUND('Смета ЕР (общ) '!$N79*'Смета ЕР (общ) '!$R79,2) -> 0 | U79: цена по КП
A80: Р1 | B80: 1 | D80: 15 | E80: =CONCATENATE('Смета ЕР (общ) '!$A80,".",'Смета ЕР (общ) '!$B80,".",'Смета ЕР (общ) '!$D80) -> Р1.1.15 | F80: =IF(N80>0,F79+1,F79) -> 1 | G80: Раздел №1. Проектные работы и согласования | H80: 1.1.0 Проектные работы и согласования | L80: Сертификация помещения для совершения операций с ценностями, хранение ценностей по (2) классу вломостойкости и (3) классу пулестойкости | M80: м2 | O80: 88.99 | P80: 0 | Q80: =ROUND(O80-O80*$V$3,2) -> 88.99 | R80: =ROUND(P80-P80*$V$3,2) -> 0 | S80: =ROUND('Смета ЕР (общ) '!$N80*'Смета ЕР (общ) '!$Q80,2) -> 0 | T80: =ROUND('Смета ЕР (общ) '!$N80*'Смета ЕР (общ) '!$R80,2) -> 0
A81: Р1 | B81: 1 | D81: 16 | E81: =CONCATENATE('Смета ЕР (общ) '!$A81,".",'Смета ЕР (общ) '!$B81,".",'Смета ЕР (общ) '!$D81) -> Р1.1.16 | F81: =IF(N81>0,F80+1,F80) -> 1 | G81: Раздел №1. Проектные работы и согласования | H81: 1.1.0 Проектные работы и согласования | L81: Сертификация помещения для совершения операций с ценностями, хранение ценностей по 3 классу вломостойкости и 3 классу пулестойкости | M81: м2 | O81: 149.82 | P81: 0 | Q81: =ROUND(O81-O81*$V$3,2) -> 149.82 | R81: =ROUND(P81-P81*$V$3,2) -> 0 | S81: =ROUND('Смета ЕР (общ) '!$N81*'Смета ЕР (общ) '!$Q81,2) -> 0 | T81: =ROUND('Смета ЕР (общ) '!$N81*'Смета ЕР (общ) '!$R81,2) -> 0
A82: Р1 | B82: 1 | D82: 17 | E82: =CONCATENATE('Смета ЕР (общ) '!$A82,".",'Смета ЕР (общ) '!$B82,".",'Смета ЕР (общ) '!$D82) -> Р1.1.17 | F82: =IF(N82>0,F81+1,F81) -> 1 | G82: Раздел №1. Проектные работы и согласования | H82: 1.1.0 Проектные работы и согласования | L82: Сертификация помещения для совершения операций с ценностями, хранение ценностей по (5) классу вломостойкости | M82: м2 | O82: 96.48 | P82: 0 | Q82: =ROUND(O82-O82*$V$3,2) -> 96.48 | R82: =ROUND(P82-P82*$V$3,2) -> 0 | S82: =ROUND('Смета ЕР (общ) '!$N82*'Смета ЕР (общ) '!$Q82,2) -> 0 | T82: =ROUND('Смета ЕР (общ) '!$N82*'Смета ЕР (общ) '!$R82,2) -> 0
A83: Р1 | B83: 1 | D83: 18 | E83: =CONCATENATE('Смета ЕР (общ) '!$A83,".",'Смета ЕР (общ) '!$B83,".",'Смета ЕР (общ) '!$D83) -> Р1.1.18 | F83: =IF(N83>0,F82+1,F82) -> 1 | G83: Раздел №1. Проектные работы и согласования | H83: 1.1.0 Проектные работы и согласования | L83: Технический отчет электролаборатории для помещений более 100 м.кв. | M83: м2 | O83: 123.58 | P83: 0 | Q83: =ROUND(O83-O83*$V$3,2) -> 123.58 | R83: =ROUND(P83-P83*$V$3,2) -> 0 | S83: =ROUND('Смета ЕР (общ) '!$N83*'Смета ЕР (общ) '!$Q83,2) -> 0 | T83: =ROUND('Смета ЕР (общ) '!$N83*'Смета ЕР (общ) '!$R83,2) -> 0 | Y83: 214
A84: Р1 | B84: 1 | D84: 84 | E84: =CONCATENATE('Смета ЕР (общ) '!$A84,".",'Смета ЕР (общ) '!$B84,".",'Смета ЕР (общ) '!$D84) -> Р1.1.84 | F84: =IF(N84>0,F83+1,F83) -> 1 | G84: Раздел №1. Проектные работы и согласования | H84: 1.1.0 Проектные работы и согласования | L84: Технический отчет электролаборатории для помещений менее 100 м.кв. | M84: компл. | O84: 13074.35 | P84: 0 | Q84: =ROUND(O84-O84*$V$3,2) -> 13074.35 | R84: =ROUND(P84-P84*$V$3,2) -> 0 | S84: =ROUND('Смета ЕР (общ) '!$N84*'Смета ЕР (общ) '!$Q84,2) -> 0 | T84: =ROUND('Смета ЕР (общ) '!$N84*'Смета ЕР (общ) '!$R84,2) -> 0
A85: Р1 | B85: 1 | D85: 19 | E85: =CONCATENATE('Смета ЕР (общ) '!$A85,".",'Смета ЕР (общ) '!$B85,".",'Смета ЕР (общ) '!$D85) -> Р1.1.19 | F85: =IF(N85>0,F84+1,F84) -> 1 | G85: Раздел №1. Проектные работы и согласования | H85: 1.1.0 Проектные работы и согласования | L85: Стоимость согласования проекта изменения фасада согласно нормативных и законодательных актов г. ___________ и РФ. | M85: м2 | O85: 190.9 | P85: 0 | Q85: =ROUND(O85-O85*$V$3,2) -> 190.9 | R85: =ROUND(P85-P85*$V$3,2) -> 0 | S85: =ROUND('Смета ЕР (общ) '!$N85*'Смета ЕР (общ) '!$Q85,2) -> 0 | T85: =ROUND('Смета ЕР (общ) '!$N85*'Смета ЕР (общ) '!$R85,2) -> 0
A86: Р1 | B86: 1 | D86: 20 | E86: =CONCATENATE('Смета ЕР (общ) '!$A86,".",'Смета ЕР (общ) '!$B86,".",'Смета ЕР (общ) '!$D86) -> Р1.1.20 | F86: =IF(N86>0,F85+1,F85) -> 1 | G86: Раздел №1. Проектные работы и согласования | H86: 1.1.0 Проектные работы и согласования | L86: Разработка дизайн-проекта интерьера | M86: м2 | O86: 0 | P86: 0 | Q86: =ROUND(O86-O86*$V$3,2) -> 0 | R86: =ROUND(P86-P86*$V$3,2) -> 0 | S86: =ROUND('Смета ЕР (общ) '!$N86*'Смета ЕР (общ) '!$Q86,2) -> 0 | T86: =ROUND('Смета ЕР (общ) '!$N86*'Смета ЕР (общ) '!$R86,2) -> 0 | U86: цена по КП
A87: Р1 | B87: 1 | D87: 21 | E87: =CONCATENATE('Смета ЕР (общ) '!$A87,".",'Смета ЕР (общ) '!$B87,".",'Смета ЕР (общ) '!$D87) -> Р1.1.21 | F87: =IF(N87>0,F86+1,F86) -> 1 | G87: Раздел №1. Проектные работы и согласования | H87: 1.1.0 Проектные работы и согласования | L87: Экспертиза и согласование проекта ЭОМ в Ростехнадзоре | M87: м2 | O87: 98.96 | P87: 0 | Q87: =ROUND(O87-O87*$V$3,2) -> 98.96 | R87: =ROUND(P87-P87*$V$3,2) -> 0 | S87: =ROUND('Смета ЕР (общ) '!$N87*'Смета ЕР (общ) '!$Q87,2) -> 0 | T87: =ROUND('Смета ЕР (общ) '!$N87*'Смета ЕР (общ) '!$R87,2) -> 0
A88: Р1 | B88: 1 | D88: 22 | E88: =CONCATENATE('Смета ЕР (общ) '!$A88,".",'Смета ЕР (общ) '!$B88,".",'Смета ЕР (общ) '!$D88) -> Р1.1.22 | F88: =IF(N88>0,F87+1,F87) -> 1 | G88: Раздел №1. Проектные работы и согласования | H88: 1.1.0 Проектные работы и согласования | L88: Проект системы водоотведения | M88: м2 | O88: 0 | P88: 0 | Q88: =ROUND(O88-O88*$V$3,2) -> 0 | R88: =ROUND(P88-P88*$V$3,2) -> 0 | S88: =ROUND('Смета ЕР (общ) '!$N88*'Смета ЕР (общ) '!$Q88,2) -> 0 | T88: =ROUND('Смета ЕР (общ) '!$N88*'Смета ЕР (общ) '!$R88,2) -> 0 | U88: цена по КП
A89: Р1 | B89: 1 | D89: 23 | E89: =CONCATENATE('Смета ЕР (общ) '!$A89,".",'Смета ЕР (общ) '!$B89,".",'Смета ЕР (общ) '!$D89) -> Р1.1.23 | F89: =IF(N89>0,F88+1,F88) -> 1 | G89: Раздел №1. Проектные работы и согласования | H89: 1.1.0 Проектные работы и согласования | L89: Рабочая документация Системы ливневой канализации | M89: м2 | O89: 0 | P89: 0 | Q89: =ROUND(O89-O89*$V$3,2) -> 0 | R89: =ROUND(P89-P89*$V$3,2) -> 0 | S89: =ROUND('Смета ЕР (общ) '!$N89*'Смета ЕР (общ) '!$Q89,2) -> 0 | T89: =ROUND('Смета ЕР (общ) '!$N89*'Смета ЕР (общ) '!$R89,2) -> 0 | U89: цена по КП
A90: Р1 | B90: 1 | D90: 24 | E90: =CONCATENATE('Смета ЕР (общ) '!$A90,".",'Смета ЕР (общ) '!$B90,".",'Смета ЕР (общ) '!$D90) -> Р1.1.24 | F90: =IF(N90>0,F89+1,F89) -> 1 | G90: Раздел №1. Проектные работы и согласования | H90: 1.1.0 Проектные работы и согласования | L90: Получение Технических условий (при необходимости) | M90: м2 | O90: 0 | P90: 0 | Q90: =ROUND(O90-O90*$V$3,2) -> 0 | R90: =ROUND(P90-P90*$V$3,2) -> 0 | S90: =ROUND('Смета ЕР (общ) '!$N90*'Смета ЕР (общ) '!$Q90,2) -> 0 | T90: =ROUND('Смета ЕР (общ) '!$N90*'Смета ЕР (общ) '!$R90,2) -> 0 | U90: цена по КП
A91: Р1 | B91: 1 | D91: 27 | E91: =CONCATENATE('Смета ЕР (общ) '!$A91,".",'Смета ЕР (общ) '!$B91,".",'Смета ЕР (общ) '!$D91) -> Р1.1.27 | F91: =IF(N91>0,F90+1,F90) -> 1 | G91: Раздел №1. Проектные работы и согласования | H91: 1.1.0 Проектные работы и согласования | L91: Расчет категории пожарной опасности помещений | M91: м2 | O91: 114.84 | P91: 0 | Q91: =ROUND(O91-O91*$V$3,2) -> 114.84 | R91: =ROUND(P91-P91*$V$3,2) -> 0 | S91: =ROUND('Смета ЕР (общ) '!$N91*'Смета ЕР (общ) '!$Q91,2) -> 0 | T91: =ROUND('Смета ЕР (общ) '!$N91*'Смета ЕР (общ) '!$R91,2) -> 0
A92: Р1 | B92: 1 | D92: 28 | E92: =CONCATENATE('Смета ЕР (общ) '!$A92,".",'Смета ЕР (общ) '!$B92,".",'Смета ЕР (общ) '!$D92) -> Р1.1.28 | F92: =IF(N92>0,F91+1,F91) -> 1 | G92: Раздел №1. Проектные работы и согласования | H92: 1.1.0 Проектные работы и согласования | L92: Рабочая документация Системы оповещения и управления эвакуацией в части световых указателей ("СОУЭ") | M92: м2 | O92: 52.25 | P92: 0 | Q92: =ROUND(O92-O92*$V$3,2) -> 52.25 | R92: =ROUND(P92-P92*$V$3,2) -> 0 | S92: =ROUND('Смета ЕР (общ) '!$N92*'Смета ЕР (общ) '!$Q92,2) -> 0 | T92: =ROUND('Смета ЕР (общ) '!$N92*'Смета ЕР (общ) '!$R92,2) -> 0
A93: Р1 | B93: 1 | D93: 32 | E93: =CONCATENATE('Смета ЕР (общ) '!$A93,".",'Смета ЕР (общ) '!$B93,".",'Смета ЕР (общ) '!$D93) -> Р1.1.32 | F93: =IF(N93>0,F92+1,F92) -> 1 | G93: Раздел №1. Проектные работы и согласования | H93: 1.1.0 Проектные работы и согласования | L93: Согласование проекта Системы водоотведения и получения тех условий (при необходимости) | M93: м2 | O93: 0 | P93: 0 | Q93: =ROUND(O93-O93*$V$3,2) -> 0 | R93: =ROUND(P93-P93*$V$3,2) -> 0 | S93: =ROUND('Смета ЕР (общ) '!$N93*'Смета ЕР (общ) '!$Q93,2) -> 0 | T93: =ROUND('Смета ЕР (общ) '!$N93*'Смета ЕР (общ) '!$R93,2) -> 0 | U93: цена по КП
A94: Р1 | B94: 1 | D94: 34 | E94: =CONCATENATE('Смета ЕР (общ) '!$A94,".",'Смета ЕР (общ) '!$B94,".",'Смета ЕР (общ) '!$D94) -> Р1.1.34 | F94: =IF(N94>0,F93+1,F93) -> 1 | G94: Раздел №1. Проектные работы и согласования | H94: 1.1.0 Проектные работы и согласования | L94: Испытание лестниц 3 типа с предоставлением актов | M94: м2 | O94: 30.63 | P94: 0 | Q94: =ROUND(O94-O94*$V$3,2) -> 30.63 | R94: =ROUND(P94-P94*$V$3,2) -> 0 | S94: =ROUND('Смета ЕР (общ) '!$N94*'Смета ЕР (общ) '!$Q94,2) -> 0 | T94: =ROUND('Смета ЕР (общ) '!$N94*'Смета ЕР (общ) '!$R94,2) -> 0
A95: Р1 | B95: 1 | D95: 92 | E95: =CONCATENATE('Смета ЕР (общ) '!$A95,".",'Смета ЕР (общ) '!$B95,".",'Смета ЕР (общ) '!$D95) -> Р1.1.92 | F95: =IF(N95>0,F94+1,F94) -> 1 | G95: Раздел №1. Проектные работы и согласования | H95: 1.1.0 Проектные работы и согласования | L95: Испытания системы внутреннего противопожарного водопровода аккредитованной организацией (ВПВ и АУПТ). | M95: компл. | O95: 10207.56 | P95: 0 | Q95: =ROUND(O95-O95*$V$3,2) -> 10207.56 | R95: =ROUND(P95-P95*$V$3,2) -> 0 | S95: =ROUND('Смета ЕР (общ) '!$N95*'Смета ЕР (общ) '!$Q95,2) -> 0 | T95: =ROUND('Смета ЕР (общ) '!$N95*'Смета ЕР (общ) '!$R95,2) -> 0
A96: Р1 | B96: 1 | D96: 35 | E96: =CONCATENATE('Смета ЕР (общ) '!$A96,".",'Смета ЕР (общ) '!$B96,".",'Смета ЕР (общ) '!$D96) -> Р1.1.35 | F96: =IF(N96>0,F94+1,F94) -> 1 | G96: Раздел №1. Проектные работы и согласования | H96: 1.1.0 Проектные работы и согласования | L96: Мероприятия по обеспечению доступа инвалидов | M96: м2 | O96: 76.52 | P96: 0 | Q96: =ROUND(O96-O96*$V$3,2) -> 76.52 | R96: =ROUND(P96-P96*$V$3,2) -> 0 | S96: =ROUND('Смета ЕР (общ) '!$N96*'Смета ЕР (общ) '!$Q96,2) -> 0 | T96: =ROUND('Смета ЕР (общ) '!$N96*'Смета ЕР (общ) '!$R96,2) -> 0
A97: Р1 | B97: 1 | D97: 38 | E97: =CONCATENATE('Смета ЕР (общ) '!$A97,".",'Смета ЕР (общ) '!$B97,".",'Смета ЕР (общ) '!$D97) -> Р1.1.38 | F97: =IF(N97>0,F96+1,F96) -> 1 | G97: Раздел №1. Проектные работы и согласования | H97: 1.1.0 Проектные работы и согласования | L97: Расчет пожарного риска | M97: м2 | O97: 0 | P97: 0 | Q97: =ROUND(O97-O97*$V$3,2) -> 0 | R97: =ROUND(P97-P97*$V$3,2) -> 0 | S97: =ROUND('Смета ЕР (общ) '!$N97*'Смета ЕР (общ) '!$Q97,2) -> 0 | T97: =ROUND('Смета ЕР (общ) '!$N97*'Смета ЕР (общ) '!$R97,2) -> 0 | U97: цена по КП
A98: Р1 | B98: 1 | D98: 39 | E98: =CONCATENATE('Смета ЕР (общ) '!$A98,".",'Смета ЕР (общ) '!$B98,".",'Смета ЕР (общ) '!$D98) -> Р1.1.39 | F98: =IF(N98>0,F97+1,F97) -> 1 | G98: Раздел №1. Проектные работы и согласования | H98: 1.1.0 Проектные работы и согласования | L98: Подготовка и постановка на учет Независимой оценки пожарного риска (пожарный аудит), включая Расчет пожарного риска | M98: м2 | O98: 0 | P98: 0 | Q98: =ROUND(O98-O98*$V$3,2) -> 0 | R98: =ROUND(P98-P98*$V$3,2) -> 0 | S98: =ROUND('Смета ЕР (общ) '!$N98*'Смета ЕР (общ) '!$Q98,2) -> 0 | T98: =ROUND('Смета ЕР (общ) '!$N98*'Смета ЕР (общ) '!$R98,2) -> 0 | U98: цена по КП
A99: Р1 | B99: 1 | D99: 40 | E99: =CONCATENATE('Смета ЕР (общ) '!$A99,".",'Смета ЕР (общ) '!$B99,".",'Смета ЕР (общ) '!$D99) -> Р1.1.40 | F99: =IF(N99>0,F98+1,F98) -> 1 | G99: Раздел №1. Проектные работы и согласования | H99: 1.1.0 Проектные работы и согласования | L99: Разработка проекта огнезащиты | M99: шт. | O99: 16168.42 | P99: 0 | Q99: =ROUND(O99-O99*$V$3,2) -> 16168.42 | R99: =ROUND(P99-P99*$V$3,2) -> 0 | S99: =ROUND('Смета ЕР (общ) '!$N99*'Смета ЕР (общ) '!$Q99,2) -> 0 | T99: =ROUND('Смета ЕР (общ) '!$N99*'Смета ЕР (общ) '!$R99,2) -> 0
A100: Р1 | B100: 1 | D100: 41 | E100: =CONCATENATE('Смета ЕР (общ) '!$A100,".",'Смета ЕР (общ) '!$B100,".",'Смета ЕР (общ) '!$D100) -> Р1.1.41 | F100: =IF(N100>0,F99+1,F99) -> 1 | G100: Раздел №1. Проектные работы и согласования | H100: 1.1.0 Проектные работы и согласования | L100: Предоставление заключения пожарной испытательной лаборатории для контроля качества огнезащитных работ с предоставлением заключения о соответствии (до 1000 м кв. металлоконструкций) | M100: компл. | O100: 23438.15 | P100: 0 | Q100: =ROUND(O100-O100*$V$3,2) -> 23438.15 | R100: =ROUND(P100-P100*$V$3,2) -> 0 | S100: =ROUND('Смета ЕР (общ) '!$N100*'Смета ЕР (общ) '!$Q100,2) -> 0 | T100: =ROUND('Смета ЕР (общ) '!$N100*'Смета ЕР (общ) '!$R100,2) -> 0
A101: Р1 | B101: 1 | D101: 85 | E101: =CONCATENATE('Смета ЕР (общ) '!$A101,".",'Смета ЕР (общ) '!$B101,".",'Смета ЕР (общ) '!$D101) -> Р1.1.85 | F101: =IF(N101>0,F100+1,F100) -> 1 | G101: Раздел №1. Проектные работы и согласования | H101: 1.1.0 Проектные работы и согласования | L101: Предоставление заключения пожарной испытательной лаборатории для контроля качества огнезащитных работ с предоставлением заключения о соответствии (более 1000 м кв. металлоконструкций) | M101: м2 | O101: 17.8 | P101: 0 | Q101: =ROUND(O101-O101*$V$3,2) -> 17.8 | R101: =ROUND(P101-P101*$V$3,2) -> 0 | S101: =ROUND('Смета ЕР (общ) '!$N101*'Смета ЕР (общ) '!$Q101,2) -> 0 | T101: =ROUND('Смета ЕР (общ) '!$N101*'Смета ЕР (общ) '!$R101,2) -> 0
A102: Р1 | B102: 1 | D102: 86 | E102: =CONCATENATE('Смета ЕР (общ) '!$A102,".",'Смета ЕР (общ) '!$B102,".",'Смета ЕР (общ) '!$D102) -> Р1.1.86 | F102: =IF(N102>0,F101+1,F101) -> 1 | G102: Раздел №1. Проектные работы и согласования | H102: 1.1.0 Проектные работы и согласования | L102: Акустический расчет инженерных систем ОВиК (предоставление в Роспотребнадзор) электронный и бумажный вариант | M102: компл. | O102: 132501.92 | P102: 0 | Q102: =ROUND(O102-O102*$V$3,2) -> 132501.92 | R102: =ROUND(P102-P102*$V$3,2) -> 0 | S102: =ROUND('Смета ЕР (общ) '!$N102*'Смета ЕР (общ) '!$Q102,2) -> 0 | T102: =ROUND('Смета ЕР (общ) '!$N102*'Смета ЕР (общ) '!$R102,2) -> 0 | U102: согласование памятников архитектуры
...
