Workbook
Name ДисконтТендер: Смета!$C$17
Name КурсEUR: Смета!$C$16
Name КурсUSD: Смета!$C$15
Name мат_VRF_ВНУТ: Материалы!$M$2:$M$259
Name мат_VRF_НАР: Материалы!$M$260:$M$360
Name мат_БРОНЯ: Материалы!$M$361:$M$382
Name мат_ДВ: Материалы!$M$383:$M$393
Name мат_ДВ_АЛ: Материалы!$M$394:$M$399
Name мат_ДВ_ДЕР: Материалы!$M$400:$M$405
Name мат_ДВ_СТ: Материалы!$M$406:$M$410
Name мат_ДОК_ИД: Документация!$F$38:$F$57
Name мат_ДОК_РД: Документация!$F$2:$F$37
Name мат_ЗАВЕСА: Материалы!$M$411:$M$414
Name мат_ЛЮЧОК: Материалы!$M$415:$M$415
Name мат_ПВУ: Материалы!$M$416:$M$431
Name мат_ПЕРЕГ_СТ: Материалы!$M$432:$M$432
Name мат_ПЕРЕГ_ТР: Материалы!$M$433:$M$442
Name мат_ПОЛ_КГ: Материалы!$M$443:$M$450
Name мат_ПОЛ_МОД: Материалы!$M$451:$M$455
Name мат_ПОТОЛОК: Материалы!$M$456:$M$460
Name мат_РАД: Материалы!$M$461:$M$597
Name мат_РАД_КОМПЛ: Материалы!$M$598:$M$612
Name мат_СВЕТ: Материалы!$M$613:$M$925
Name мат_СВЕТ_АВАР: Материалы!$M$926:$M$1035
Name мат_СПЛИТ: Материалы!$M$1036:$M$1151
Name мат_СТЕН_ПЛ: Материалы!$M$1152:$M$1154
Name мат_СТП_РАК: Материалы!$M$1155:$M$1167
Name мат_СТП_СМЕС: Материалы!$M$1168:$M$1180
Name мат_СТП_УНИТ: Материалы!$M$1181:$M$1188
Name мат_ФАЛЬШПОЛ: Материалы!$M$1189:$M$1197
Name мат_ЭУИ_ВЫКЛ: Материалы!$M$1198:$M$1199
Name мат_ЭУИ_РОЗ: Материалы!$M$1200:$M$1208
Name мат_ЭЩ: Материалы!$M$1209:$M$1219
Name раб_Р1: Работы!$N$2:$N$39
Name раб_Р10: Работы!$N$821:$N$832
Name раб_Р11: Работы!$N$833:$N$841
Name раб_Р12: Работы!$N$842:$N$858
Name раб_Р2: Работы!$N$40:$N$161
Name раб_Р3: Работы!$N$162:$N$371
Name раб_Р4: Работы!$N$372:$N$429
Name раб_Р5: Работы!$N$430:$N$475
Name раб_Р6: Работы!$N$476:$N$522
Name раб_Р7: Работы!$N$523:$N$556
Name раб_Р8: Работы!$N$557:$N$581
Name раб_Р9: Работы!$N$582:$N$820

Sheet О шаблоне
A1: Шаблон сметы — РУЧНАЯ СБОРКА перечня (Excel 2019+)
A3: КАК РАБОТАТЬ
A4: 1. Лист «Сборка» — пустой. Для каждой нужной работы заполни строку:
A5: • Раздел — выбери Р1…Р12 из списка;
A6: • Работа (Код — Наименование) — выбери из списка (в нём только работы этого раздела);
A7: • Объём — впиши число;
A8: • Материал / раздел документации — если работа с материалом, выбери из списка;
A9: для строк «Рабочая/Исполнительная документация» (раздел 1) в этом же столбце выбирается
A10: раздел проекта — цена подставится с листа «Документация».
A11: Наименование, ед. изм. и цены подставляются сами. Порядок строк — любой.
A12: 2. Лист «Смета» — готовый документ. После сборки встань на таблицу расшифровки и нажми
A13: Ctrl+Alt+L (Данные → «Применить повторно»): останутся только строки с объёмом, разбитые
... A21: Сформировано: 2026-09-01. Работ в справочнике: 857. Материалов: 1218. Вариантов документации: 56. Пустых строк «Сборки»: 500.

Sheet Сборка
A1: Раздел | B1: Работа (Код — Наименование) | C1: _код | D1: Наименование работы | E1: Ед | F1: Группа_мат | G1: Объём | H1: Материал / раздел документации | I1: Наим. материала | J1: Цена работ, ₽ | K1: Цена мат, ₽ | L1: Стоим. работ, ₽ | M1: Стоим. мат, ₽ | N1: Всего, ₽ | O1: _ранг | P1: _рзд | Q1: _перв | R1: _строка | S1: _разд_имя
C2: =IF($B2="","",IFERROR(LEFT($B2,FIND(" — ",$B2)-1),$B2)) | D2: =IF($C2="","",IF(AND(LEFT($F2,3)="ДОК",$H2<>""),IFERROR(INDEX(Документация!$G$2:$G$57,MATCH($H2,Документация!$F$2:$F$57,0)),"— вариант не найден —"),IFERROR(INDEX(Работы!$B$2:$B$6000,MATCH($C2,Работы!$A$2:$A$6000,0)),"— нет такого кода —"))) | E2: =IF($C2="","",IF(AND(LEFT($F2,3)="ДОК",$H2<>""),IFERROR(INDEX(Документация!$D$2:$D$57,MATCH($H2,Документация!$F$2:$F$57,0)),""),IFERROR(INDEX(Работы!$C$2:$C$6000,MATCH($C2,Работы!$A$2:$A$6000,0)),""))) | F2: =IF($C2="","",IFERROR(INDEX(Работы!$G$2:$G$6000,MATCH($C2,Работы!$A$2:$A$6000,0))&"","")) | I2: =IF((LEFT($F2,3)="ДОК"),"",IF($H2="","",IFERROR(INDEX(Материалы!$B$2:$B$9000,MATCH($H2,Материалы!$M$2:$M$9000,0)),""))) | J2: =IF(AND(LEFT($F2,3)="ДОК",$H2<>""),IFERROR(INDEX(Документация!$E$2:$E$57,MATCH($H2,Документация!$F$2:$F$57,0)),0),IFERROR(INDEX(Работы!$H$2:$H$6000,MATCH($C2,Работы!$A$2:$A$6000,0)),0))*(1-MEDIAN(0,N(ДисконтТендер),1)) -> 0 | K2: =IF(OR((LEFT($F2,3)="ДОК"),$H2=""),0,IFERROR(INDEX(Материалы!$H$2:$H$9000,MATCH($H2,Материалы!$M$2:$M$9000,0))*IF(INDEX(Материалы!$I$2:$I$9000,MATCH($H2,Материалы!$M$2:$M$9000,0))="USD",КурсUSD,IF(INDEX(Материалы!$I$2:$I$9000,MATCH($H2,Материалы!$M$2:$M$9000,0))="EUR",КурсEUR,1))*(1+IFERROR(INDEX(Работы!$I$2:$I$6000,MATCH($C2,Работы!$A$2:$A$6000,0))/100,0))*(1-MEDIAN(0,N(ДисконтТендер),1)),0)) -> 0 | L2: =IF($G2<>"",ROUND($G2*$J2,2),0) -> 0 | M2: =IF($G2<>"",ROUND($G2*$K2,2),0) -> 0 | N2: =$L2+$M2 -> 0 | O2: =IF($N2>0,MAX($O$1:$O1)+1,"") | P2: =IF($C2="","",IFERROR(INDEX(Работы!$D$2:$D$6000,MATCH($C2,Работы!$A$2:$A$6000,0)),"")) | Q2: =IF($O2="","",IF($O2=1,1,IF($P2<>IFERROR(INDEX($P$2:$P$501,MATCH($O2-1,$O$2:$O$501,0)),"~"),1,0))) | R2: =IF($O2="","",$O2+SUMIFS($Q$2:$Q$501,$O$2:$O$501,"<="&$O2)) | S2: =IF($P2="","",$P2&" · "&IFERROR(INDEX(Работы!$E$2:$E$6000,MATCH($C2,Работы!$A$2:$A$6000,0)),""))
C3: =IF($B3="","",IFERROR(LEFT($B3,FIND(" — ",$B3)-1),$B3)) | D3: =IF($C3="","",IF(AND(LEFT($F3,3)="ДОК",$H3<>""),IFERROR(INDEX(Документация!$G$2:$G$57,MATCH($H3,Документация!$F$2:$F$57,0)),"— вариант не найден —"),IFERROR(INDEX(Работы!$B$2:$B$6000,MATCH($C3,Работы!$A$2:$A$6000,0)),"— нет такого кода —"))) | E3: =IF($C3="","",IF(AND(LEFT($F3,3)="ДОК",$H3<>""),IFERROR(INDEX(Документация!$D$2:$D$57,MATCH($H3,Документация!$F$2:$F$57,0)),""),IFERROR(INDEX(Работы!$C$2:$C$6000,MATCH($C3,Работы!$A$2:$A$6000,0)),""))) | F3: =IF($C3="","",IFERROR(INDEX(Работы!$G$2:$G$6000,MATCH($C3,Работы!$A$2:$A$6000,0))&"","")) | I3: =IF((LEFT($F3,3)="ДОК"),"",IF($H3="","",IFERROR(INDEX(Материалы!$B$2:$B$9000,MATCH($H3,Материалы!$M$2:$M$9000,0)),""))) | J3: =IF(AND(LEFT($F3,3)="ДОК",$H3<>""),IFERROR(INDEX(Документация!$E$2:$E$57,MATCH($H3,Документация!$F$2:$F$57,0)),0),IFERROR(INDEX(Работы!$H$2:$H$6000,MATCH($C3,Работы!$A$2:$A$6000,0)),0))*(1-MEDIAN(0,N(ДисконтТендер),1)) -> 0 | K3: =IF(OR((LEFT($F3,3)="ДОК"),$H3=""),0,IFERROR(INDEX(Материалы!$H$2:$H$9000,MATCH($H3,Материалы!$M$2:$M$9000,0))*IF(INDEX(Материалы!$I$2:$I$9000,MATCH($H3,Материалы!$M$2:$M$9000,0))="USD",КурсUSD,IF(INDEX(Материалы!$I$2:$I$9000,MATCH($H3,Материалы!$M$2:$M$9000,0))="EUR",КурсEUR,1))*(1+IFERROR(INDEX(Работы!$I$2:$I$6000,MATCH($C3,Работы!$A$2:$A$6000,0))/100,0))*(1-MEDIAN(0,N(ДисконтТендер),1)),0)) -> 0 | L3: =IF($G3<>"",ROUND($G3*$J3,2),0) -> 0 | M3: =IF($G3<>"",ROUND($G3*$K3,2),0) -> 0 | N3: =$L3+$M3 -> 0 | O3: =IF($N3>0,MAX($O$1:$O2)+1,"") | P3: =IF($C3="","",IFERROR(INDEX(Работы!$D$2:$D$6000,MATCH($C3,Работы!$A$2:$A$6000,0)),"")) | Q3: =IF($O3="","",IF($O3=1,1,IF($P3<>IFERROR(INDEX($P$2:$P$501,MATCH($O3-1,$O$2:$O$501,0)),"~"),1,0))) | R3: =IF($O3="","",$O3+SUMIFS($Q$2:$Q$501,$O$2:$O$501,"<="&$O3)) | S3: =IF($P3="","",$P3&" · "&IFERROR(INDEX(Работы!$E$2:$E$6000,MATCH($C3,Работы!$A$2:$A$6000,0)),""))
C4: =IF($B4="","",IFERROR(LEFT($B4,FIND(" — ",$B4)-1),$B4)) | D4: =IF($C4="","",IF(AND(LEFT($F4,3)="ДОК",$H4<>""),IFERROR(INDEX(Документация!$G$2:$G$57,MATCH($H4,Документация!$F$2:$F$57,0)),"— вариант не найден —"),IFERROR(INDEX(Работы!$B$2:$B$6000,MATCH($C4,Работы!$A$2:$A$6000,0)),"— нет такого кода —"))) | E4: =IF($C4="","",IF(AND(LEFT($F4,3)="ДОК",$H4<>""),IFERROR(INDEX(Документация!$D$2:$D$57,MATCH($H4,Документация!$F$2:$F$57,0)),""),IFERROR(INDEX(Работы!$C$2:$C$6000,MATCH($C4,Работы!$A$2:$A$6000,0)),""))) | F4: =IF($C4="","",IFERROR(INDEX(Работы!$G$2:$G$6000,MATCH($C4,Работы!$A$2:$A$6000,0))&"","")) | I4: =IF((LEFT($F4,3)="ДОК"),"",IF($H4="","",IFERROR(INDEX(Материалы!$B$2:$B$9000,MATCH($H4,Материалы!$M$2:$M$9000,0)),""))) | J4: =IF(AND(LEFT($F4,3)="ДОК",$H4<>""),IFERROR(INDEX(Документация!$E$2:$E$57,MATCH($H4,Документация!$F$2:$F$57,0)),0),IFERROR(INDEX(Работы!$H$2:$H$6000,MATCH($C4,Работы!$A$2:$A$6000,0)),0))*(1-MEDIAN(0,N(ДисконтТендер),1)) -> 0 | K4: =IF(OR((LEFT($F4,3)="ДОК"),$H4=""),0,IFERROR(INDEX(Материалы!$H$2:$H$9000,MATCH($H4,Материалы!$M$2:$M$9000,0))*IF(INDEX(Материалы!$I$2:$I$9000,MATCH($H4,Материалы!$M$2:$M$9000,0))="USD",КурсUSD,IF(INDEX(Материалы!$I$2:$I$9000,MATCH($H4,Материалы!$M$2:$M$9000,0))="EUR",КурсEUR,1))*(1+IFERROR(INDEX(Работы!$I$2:$I$6000,MATCH($C4,Работы!$A$2:$A$6000,0))/100,0))*(1-MEDIAN(0,N(ДисконтТендер),1)),0)) -> 0 | L4: =IF($G4<>"",ROUND($G4*$J4,2),0) -> 0 | M4: =IF($G4<>"",ROUND($G4*$K4,2),0) -> 0 | N4: =$L4+$M4 -> 0 | O4: =IF($N4>0,MAX($O$1:$O3)+1,"") | P4: =IF($C4="","",IFERROR(INDEX(Работы!$D$2:$D$6000,MATCH($C4,Работы!$A$2:$A$6000,0)),"")) | Q4: =IF($O4="","",IF($O4=1,1,IF($P4<>IFERROR(INDEX($P$2:$P$501,MATCH($O4-1,$O$2:$O$501,0)),"~"),1,0))) | R4: =IF($O4="","",$O4+SUMIFS($Q$2:$Q$501,$O$2:$O$501,"<="&$O4)) | S4: =IF($P4="","",$P4&" · "&IFERROR(INDEX(Работы!$E$2:$E$6000,MATCH($C4,Работы!$A$2:$A$6000,0)),""))
C5: =IF($B5="","",IFERROR(LEFT($B5,FIND(" — ",$B5)-1),$B5)) | D5: =IF($C5="","",IF(AND(LEFT($F5,3)="ДОК",$H5<>""),IFERROR(INDEX(Документация!$G$2:$G$57,MATCH($H5,Документация!$F$2:$F$57,0)),"— вариант не найден —"),IFERROR(INDEX(Работы!$B$2:$B$6000,MATCH($C5,Работы!$A$2:$A$6000,0)),"— нет такого кода —"))) | E5: =IF($C5="","",IF(AND(LEFT($F5,3)="ДОК",$H5<>""),IFERROR(INDEX(Документация!$D$2:$D$57,MATCH($H5,Документация!$F$2:$F$57,0)),""),IFERROR(INDEX(Работы!$C$2:$C$6000,MATCH($C5,Работы!$A$2:$A$6000,0)),""))) | F5: =IF($C5="","",IFERROR(INDEX(Работы!$G$2:$G$6000,MATCH($C5,Работы!$A$2:$A$6000,0))&"","")) | I5: =IF((LEFT($F5,3)="ДОК"),"",IF($H5="","",IFERROR(INDEX(Материалы!$B$2:$B$9000,MATCH($H5,Материалы!$M$2:$M$9000,0)),""))) | J5: =IF(AND(LEFT($F5,3)="ДОК",$H5<>""),IFERROR(INDEX(Документация!$E$2:$E$57,MATCH($H5,Документация!$F$2:$F$57,0)),0),IFERROR(INDEX(Работы!$H$2:$H$6000,MATCH($C5,Работы!$A$2:$A$6000,0)),0))*(1-MEDIAN(0,N(ДисконтТендер),1)) -> 0 | K5: =IF(OR((LEFT($F5,3)="ДОК"),$H5=""),0,IFERROR(INDEX(Материалы!$H$2:$H$9000,MATCH($H5,Материалы!$M$2:$M$9000,0))*IF(INDEX(Материалы!$I$2:$I$9000,MATCH($H5,Материалы!$M$2:$M$9000,0))="USD",КурсUSD,IF(INDEX(Материалы!$I$2:$I$9000,MATCH($H5,Материалы!$M$2:$M$9000,0))="EUR",КурсEUR,1))*(1+IFERROR(INDEX(Работы!$I$2:$I$6000,MATCH($C5,Работы!$A$2:$A$6000,0))/100,0))*(1-MEDIAN(0,N(ДисконтТендер),1)),0)) -> 0 | L5: =IF($G5<>"",ROUND($G5*$J5,2),0) -> 0 | M5: =IF($G5<>"",ROUND($G5*$K5,2),0) -> 0 | N5: =$L5+$M5 -> 0 | O5: =IF($N5>0,MAX($O$1:$O4)+1,"") | P5: =IF($C5="","",IFERROR(INDEX(Работы!$D$2:$D$6000,MATCH($C5,Работы!$A$2:$A$6000,0)),"")) | Q5: =IF($O5="","",IF($O5=1,1,IF($P5<>IFERROR(INDEX($P$2:$P$501,MATCH($O5-1,$O$2:$O$501,0)),"~"),1,0))) | R5: =IF($O5="","",$O5+SUMIFS($Q$2:$Q$501,$O$2:$O$501,"<="&$O5)) | S5: =IF($P5="","",$P5&" · "&IFERROR(INDEX(Работы!$E$2:$E$6000,MATCH($C5,Работы!$A$2:$A$6000,0)),""))
C6: =IF($B6="","",IFERROR(LEFT($B6,FIND(" — ",$B6)-1),$B6)) | D6: =IF($C6="","",IF(AND(LEFT($F6,3)="ДОК",$H6<>""),IFERROR(INDEX(Документация!$G$2:$G$57,MATCH($H6,Документация!$F$2:$F$57,0)),"— вариант не найден —"),IFERROR(INDEX(Работы!$B$2:$B$6000,MATCH($C6,Работы!$A$2:$A$6000,0)),"— нет такого кода —"))) | E6: =IF($C6="","",IF(AND(LEFT($F6,3)="ДОК",$H6<>""),IFERROR(INDEX(Документация!$D$2:$D$57,MATCH($H6,Документация!$F$2:$F$57,0)),""),IFERROR(INDEX(Работы!$C$2:$C$6000,MATCH($C6,Работы!$A$2:$A$6000,0)),""))) | F6: =IF($C6="","",IFERROR(INDEX(Работы!$G$2:$G$6000,MATCH($C6,Работы!$A$2:$A$6000,0))&"","")) | I6: =IF((LEFT($F6,3)="ДОК"),"",IF($H6="","",IFERROR(INDEX(Материалы!$B$2:$B$9000,MATCH($H6,Материалы!$M$2:$M$9000,0)),""))) | J6: =IF(AND(LEFT($F6,3)="ДОК",$H6<>""),IFERROR(INDEX(Документация!$E$2:$E$57,MATCH($H6,Документация!$F$2:$F$57,0)),0),IFERROR(INDEX(Работы!$H$2:$H$6000,MATCH($C6,Работы!$A$2:$A$6000,0)),0))*(1-MEDIAN(0,N(ДисконтТендер),1)) -> 0 | K6: =IF(OR((LEFT($F6,3)="ДОК"),$H6=""),0,IFERROR(INDEX(Материалы!$H$2:$H$9000,MATCH($H6,Материалы!$M$2:$M$9000,0))*IF(INDEX(Материалы!$I$2:$I$9000,MATCH($H6,Материалы!$M$2:$M$9000,0))="USD",КурсUSD,IF(INDEX(Материалы!$I$2:$I$9000,MATCH($H6,Материалы!$M$2:$M$9000,0))="EUR",КурсEUR,1))*(1+IFERROR(INDEX(Работы!$I$2:$I$6000,MATCH($C6,Работы!$A$2:$A$6000,0))/100,0))*(1-MEDIAN(0,N(ДисконтТендер),1)),0)) -> 0 | L6: =IF($G6<>"",ROUND($G6*$J6,2),0) -> 0 | M6: =IF($G6<>"",ROUND($G6*$K6,2),0) -> 0 | N6: =$L6+$M6 -> 0 | O6: =IF($N6>0,MAX($O$1:$O5)+1,"") | P6: =IF($C6="","",IFERROR(INDEX(Работы!$D$2:$D$6000,MATCH($C6,Работы!$A$2:$A$6000,0)),"")) | Q6: =IF($O6="","",IF($O6=1,1,IF($P6<>IFERROR(INDEX($P$2:$P$501,MATCH($O6-1,$O$2:$O$501,0)),"~"),1,0))) | R6: =IF($O6="","",$O6+SUMIFS($Q$2:$Q$501,$O$2:$O$501,"<="&$O6)) | S6: =IF($P6="","",$P6&" · "&IFERROR(INDEX(Работы!$E$2:$E$6000,MATCH($C6,Работы!$A$2:$A$6000,0)),""))
C7: =IF($B7="","",IFERROR(LEFT($B7,FIND(" — ",$B7)-1),$B7)) | D7: =IF($C7="","",IF(AND(LEFT($F7,3)="ДОК",$H7<>""),IFERROR(INDEX(Документация!$G$2:$G$57,MATCH($H7,Документация!$F$2:$F$57,0)),"— вариант не найден —"),IFERROR(INDEX(Работы!$B$2:$B$6000,MATCH($C7,Работы!$A$2:$A$6000,0)),"— нет такого кода —"))) | E7: =IF($C7="","",IF(AND(LEFT($F7,3)="ДОК",$H7<>""),IFERROR(INDEX(Документация!$D$2:$D$57,MATCH($H7,Документация!$F$2:$F$57,0)),""),IFERROR(INDEX(Работы!$C$2:$C$6000,MATCH($C7,Работы!$A$2:$A$6000,0)),""))) | F7: =IF($C7="","",IFERROR(INDEX(Работы!$G$2:$G$6000,MATCH($C7,Работы!$A$2:$A$6000,0))&"","")) | I7: =IF((LEFT($F7,3)="ДОК"),"",IF($H7="","",IFERROR(INDEX(Материалы!$B$2:$B$9000,MATCH($H7,Материалы!$M$2:$M$9000,0)),""))) | J7: =IF(AND(LEFT($F7,3)="ДОК",$H7<>""),IFERROR(INDEX(Документация!$E$2:$E$57,MATCH($H7,Документация!$F$2:$F$57,0)),0),IFERROR(INDEX(Работы!$H$2:$H$6000,MATCH($C7,Работы!$A$2:$A$6000,0)),0))*(1-MEDIAN(0,N(ДисконтТендер),1)) -> 0 | K7: =IF(OR((LEFT($F7,3)="ДОК"),$H7=""),0,IFERROR(INDEX(Материалы!$H$2:$H$9000,MATCH($H7,Материалы!$M$2:$M$9000,0))*IF(INDEX(Материалы!$I$2:$I$9000,MATCH($H7,Материалы!$M$2:$M$9000,0))="USD",КурсUSD,IF(INDEX(Материалы!$I$2:$I$9000,MATCH($H7,Материалы!$M$2:$M$9000,0))="EUR",КурсEUR,1))*(1+IFERROR(INDEX(Работы!$I$2:$I$6000,MATCH($C7,Работы!$A$2:$A$6000,0))/100,0))*(1-MEDIAN(0,N(ДисконтТендер),1)),0)) -> 0 | L7: =IF($G7<>"",ROUND($G7*$J7,2),0) -> 0 | M7: =IF($G7<>"",ROUND($G7*$K7,2),0) -> 0 | N7: =$L7+$M7 -> 0 | O7: =IF($N7>0,MAX($O$1:$O6)+1,"") | P7: =IF($C7="","",IFERROR(INDEX(Работы!$D$2:$D$6000,MATCH($C7,Работы!$A$2:$A$6000,0)),"")) | Q7: =IF($O7="","",IF($O7=1,1,IF($P7<>IFERROR(INDEX($P$2:$P$501,MATCH($O7-1,$O$2:$O$501,0)),"~"),1,0))) | R7: =IF($O7="","",$O7+SUMIFS($Q$2:$Q$501,$O$2:$O$501,"<="&$O7)) | S7: =IF($P7="","",$P7&" · "&IFERROR(INDEX(Работы!$E$2:$E$6000,MATCH($C7,Работы!$A$2:$A$6000,0)),""))
C8: =IF($B8="","",IFERROR(LEFT($B8,FIND(" — ",$B8)-1),$B8)) | D8: =IF($C8="","",IF(AND(LEFT($F8,3)="ДОК",$H8<>""),IFERROR(INDEX(Документация!$G$2:$G$57,MATCH($H8,Документация!$F$2:$F$57,0)),"— вариант не найден —"),IFERROR(INDEX(Работы!$B$2:$B$6000,MATCH($C8,Работы!$A$2:$A$6000,0)),"— нет такого кода —"))) | E8: =IF($C8="","",IF(AND(LEFT($F8,3)="ДОК",$H8<>""),IFERROR(INDEX(Документация!$D$2:$D$57,MATCH($H8,Документация!$F$2:$F$57,0)),""),IFERROR(INDEX(Работы!$C$2:$C$6000,MATCH($C8,Работы!$A$2:$A$6000,0)),""))) | F8: =IF($C8="","",IFERROR(INDEX(Работы!$G$2:$G$6000,MATCH($C8,Работы!$A$2:$A$6000,0))&"","")) | I8: =IF((LEFT($F8,3)="ДОК"),"",IF($H8="","",IFERROR(INDEX(Материалы!$B$2:$B$9000,MATCH($H8,Материалы!$M$2:$M$9000,0)),""))) | J8: =IF(AND(LEFT($F8,3)="ДОК",$H8<>""),IFERROR(INDEX(Документация!$E$2:$E$57,MATCH($H8,Документация!$F$2:$F$57,0)),0),IFERROR(INDEX(Работы!$H$2:$H$6000,MATCH($C8,Работы!$A$2:$A$6000,0)),0))*(1-MEDIAN(0,N(ДисконтТендер),1)) -> 0 | K8: =IF(OR((LEFT($F8,3)="ДОК"),$H8=""),0,IFERROR(INDEX(Материалы!$H$2:$H$9000,MATCH($H8,Материалы!$M$2:$M$9000,0))*IF(INDEX(Материалы!$I$2:$I$9000,MATCH($H8,Материалы!$M$2:$M$9000,0))="USD",КурсUSD,IF(INDEX(Материалы!$I$2:$I$9000,MATCH($H8,Материалы!$M$2:$M$9000,0))="EUR",КурсEUR,1))*(1+IFERROR(INDEX(Работы!$I$2:$I$6000,MATCH($C8,Работы!$A$2:$A$6000,0))/100,0))*(1-MEDIAN(0,N(ДисконтТендер),1)),0)) -> 0 | L8: =IF($G8<>"",ROUND($G8*$J8,2),0) -> 0 | M8: =IF($G8<>"",ROUND($G8*$K8,2),0) -> 0 | N8: =$L8+$M8 -> 0 | O8: =IF($N8>0,MAX($O$1:$O7)+1,"") | P8: =IF($C8="","",IFERROR(INDEX(Работы!$D$2:$D$6000,MATCH($C8,Работы!$A$2:$A$6000,0)),"")) | Q8: =IF($O8="","",IF($O8=1,1,IF($P8<>IFERROR(INDEX($P$2:$P$501,MATCH($O8-1,$O$2:$O$501,0)),"~"),1,0))) | R8: =IF($O8="","",$O8+SUMIFS($Q$2:$Q$501,$O$2:$O$501,"<="&$O8)) | S8: =IF($P8="","",$P8&" · "&IFERROR(INDEX(Работы!$E$2:$E$6000,MATCH($C8,Работы!$A$2:$A$6000,0)),""))
C9: =IF($B9="","",IFERROR(LEFT($B9,FIND(" — ",$B9)-1),$B9)) | D9: =IF($C9="","",IF(AND(LEFT($F9,3)="ДОК",$H9<>""),IFERROR(INDEX(Документация!$G$2:$G$57,MATCH($H9,Документация!$F$2:$F$57,0)),"— вариант не найден —"),IFERROR(INDEX(Работы!$B$2:$B$6000,MATCH($C9,Работы!$A$2:$A$6000,0)),"— нет такого кода —"))) | E9: =IF($C9="","",IF(AND(LEFT($F9,3)="ДОК",$H9<>""),IFERROR(INDEX(Документация!$D$2:$D$57,MATCH($H9,Документация!$F$2:$F$57,0)),""),IFERROR(INDEX(Работы!$C$2:$C$6000,MATCH($C9,Работы!$A$2:$A$6000,0)),""))) | F9: =IF($C9="","",IFERROR(INDEX(Работы!$G$2:$G$6000,MATCH($C9,Работы!$A$2:$A$6000,0))&"","")) | I9: =IF((LEFT($F9,3)="ДОК"),"",IF($H9="","",IFERROR(INDEX(Материалы!$B$2:$B$9000,MATCH($H9,Материалы!$M$2:$M$9000,0)),""))) | J9: =IF(AND(LEFT($F9,3)="ДОК",$H9<>""),IFERROR(INDEX(Документация!$E$2:$E$57,MATCH($H9,Документация!$F$2:$F$57,0)),0),IFERROR(INDEX(Работы!$H$2:$H$6000,MATCH($C9,Работы!$A$2:$A$6000,0)),0))*(1-MEDIAN(0,N(ДисконтТендер),1)) -> 0 | K9: =IF(OR((LEFT($F9,3)="ДОК"),$H9=""),0,IFERROR(INDEX(Материалы!$H$2:$H$9000,MATCH($H9,Материалы!$M$2:$M$9000,0))*IF(INDEX(Материалы!$I$2:$I$9000,MATCH($H9,Материалы!$M$2:$M$9000,0))="USD",КурсUSD,IF(INDEX(Материалы!$I$2:$I$9000,MATCH($H9,Материалы!$M$2:$M$9000,0))="EUR",КурсEUR,1))*(1+IFERROR(INDEX(Работы!$I$2:$I$6000,MATCH($C9,Работы!$A$2:$A$6000,0))/100,0))*(1-MEDIAN(0,N(ДисконтТендер),1)),0)) -> 0 | L9: =IF($G9<>"",ROUND($G9*$J9,2),0) -> 0 | M9: =IF($G9<>"",ROUND($G9*$K9,2),0) -> 0 | N9: =$L9+$M9 -> 0 | O9: =IF($N9>0,MAX($O$1:$O8)+1,"") | P9: =IF($C9="","",IFERROR(INDEX(Работы!$D$2:$D$6000,MATCH($C9,Работы!$A$2:$A$6000,0)),"")) | Q9: =IF($O9="","",IF($O9=1,1,IF($P9<>IFERROR(INDEX($P$2:$P$501,MATCH($O9-1,$O$2:$O$501,0)),"~"),1,0))) | R9: =IF($O9="","",$O9+SUMIFS($Q$2:$Q$501,$O$2:$O$501,"<="&$O9)) | S9: =IF($P9="","",$P9&" · "&IFERROR(INDEX(Работы!$E$2:$E$6000,MATCH($C9,Работы!$A$2:$A$6000,0)),""))
C10: =IF($B10="","",IFERROR(LEFT($B10,FIND(" — ",$B10)-1),$B10)) | D10: =IF($C10="","",IF(AND(LEFT($F10,3)="ДОК",$H10<>""),IFERROR(INDEX(Документация!$G$2:$G$57,MATCH($H10,Документация!$F$2:$F$57,0)),"— вариант не найден —"),IFERROR(INDEX(Работы!$B$2:$B$6000,MATCH($C10,Работы!$A$2:$A$6000,0)),"— нет такого кода —"))) | E10: =IF($C10="","",IF(AND(LEFT($F10,3)="ДОК",$H10<>""),IFERROR(INDEX(Документация!$D$2:$D$57,MATCH($H10,Документация!$F$2:$F$57,0)),""),IFERROR(INDEX(Работы!$C$2:$C$6000,MATCH($C10,Работы!$A$2:$A$6000,0)),""))) | F10: =IF($C10="","",IFERROR(INDEX(Работы!$G$2:$G$6000,MATCH($C10,Работы!$A$2:$A$6000,0))&"","")) | I10: =IF((LEFT($F10,3)="ДОК"),"",IF($H10="","",IFERROR(INDEX(Материалы!$B$2:$B$9000,MATCH($H10,Материалы!$M$2:$M$9000,0)),""))) | J10: =IF(AND(LEFT($F10,3)="ДОК",$H10<>""),IFERROR(INDEX(Документация!$E$2:$E$57,MATCH($H10,Документация!$F$2:$F$57,0)),0),IFERROR(INDEX(Работы!$H$2:$H$6000,MATCH($C10,Работы!$A$2:$A$6000,0)),0))*(1-MEDIAN(0,N(ДисконтТендер),1)) -> 0 | K10: =IF(OR((LEFT($F10,3)="ДОК"),$H10=""),0,IFERROR(INDEX(Материалы!$H$2:$H$9000,MATCH($H10,Материалы!$M$2:$M$9000,0))*IF(INDEX(Материалы!$I$2:$I$9000,MATCH($H10,Материалы!$M$2:$M$9000,0))="USD",КурсUSD,IF(INDEX(Материалы!$I$2:$I$9000,MATCH($H10,Материалы!$M$2:$M$9000,0))="EUR",КурсEUR,1))*(1+IFERROR(INDEX(Работы!$I$2:$I$6000,MATCH($C10,Работы!$A$2:$A$6000,0))/100,0))*(1-MEDIAN(0,N(ДисконтТендер),1)),0)) -> 0 | L10: =IF($G10<>"",ROUND($G10*$J10,2),0) -> 0 | M10: =IF($G10<>"",ROUND($G10*$K10,2),0) -> 0 | N10: =$L10+$M10 -> 0 | O10: =IF($N10>0,MAX($O$1:$O9)+1,"") | P10: =IF($C10="","",IFERROR(INDEX(Работы!$D$2:$D$6000,MATCH($C10,Работы!$A$2:$A$6000,0)),"")) | Q10: =IF($O10="","",IF($O10=1,1,IF($P10<>IFERROR(INDEX($P$2:$P$501,MATCH($O10-1,$O$2:$O$501,0)),"~"),1,0))) | R10: =IF($O10="","",$O10+SUMIFS($Q$2:$Q$501,$O$2:$O$501,"<="&$O10)) | S10: =IF($P10="","",$P10&" · "&IFERROR(INDEX(Работы!$E$2:$E$6000,MATCH($C10,Работы!$A$2:$A$6000,0)),""))
C11: =IF($B11="","",IFERROR(LEFT($B11,FIND(" — ",$B11)-1),$B11)) | D11: =IF($C11="","",IF(AND(LEFT($F11,3)="ДОК",$H11<>""),IFERROR(INDEX(Документация!$G$2:$G$57,MATCH($H11,Документация!$F$2:$F$57,0)),"— вариант не найден —"),IFERROR(INDEX(Работы!$B$2:$B$6000,MATCH($C11,Работы!$A$2:$A$6000,0)),"— нет такого кода —"))) | E11: =IF($C11="","",IF(AND(LEFT($F11,3)="ДОК",$H11<>""),IFERROR(INDEX(Документация!$D$2:$D$57,MATCH($H11,Документация!$F$2:$F$57,0)),""),IFERROR(INDEX(Работы!$C$2:$C$6000,MATCH($C11,Работы!$A$2:$A$6000,0)),""))) | F11: =IF($C11="","",IFERROR(INDEX(Работы!$G$2:$G$6000,MATCH($C11,Работы!$A$2:$A$6000,0))&"","")) | I11: =IF((LEFT($F11,3)="ДОК"),"",IF($H11="","",IFERROR(INDEX(Материалы!$B$2:$B$9000,MATCH($H11,Материалы!$M$2:$M$9000,0)),""))) | J11: =IF(AND(LEFT($F11,3)="ДОК",$H11<>""),IFERROR(INDEX(Документация!$E$2:$E$57,MATCH($H11,Документация!$F$2:$F$57,0)),0),IFERROR(INDEX(Работы!$H$2:$H$6000,MATCH($C11,Работы!$A$2:$A$6000,0)),0))*(1-MEDIAN(0,N(ДисконтТендер),1)) -> 0 | K11: =IF(OR((LEFT($F11,3)="ДОК"),$H11=""),0,IFERROR(INDEX(Материалы!$H$2:$H$9000,MATCH($H11,Материалы!$M$2:$M$9000,0))*IF(INDEX(Материалы!$I$2:$I$9000,MATCH($H11,Материалы!$M$2:$M$9000,0))="USD",КурсUSD,IF(INDEX(Материалы!$I$2:$I$9000,MATCH($H11,Материалы!$M$2:$M$9000,0))="EUR",КурсEUR,1))*(1+IFERROR(INDEX(Работы!$I$2:$I$6000,MATCH($C11,Работы!$A$2:$A$6000,0))/100,0))*(1-MEDIAN(0,N(ДисконтТендер),1)),0)) -> 0 | L11: =IF($G11<>"",ROUND($G11*$J11,2),0) -> 0 | M11: =IF($G11<>"",ROUND($G11*$K11,2),0) -> 0 | N11: =$L11+$M11 -> 0 | O11: =IF($N11>0,MAX($O$1:$O10)+1,"") | P11: =IF($C11="","",IFERROR(INDEX(Работы!$D$2:$D$6000,MATCH($C11,Работы!$A$2:$A$6000,0)),"")) | Q11: =IF($O11="","",IF($O11=1,1,IF($P11<>IFERROR(INDEX($P$2:$P$501,MATCH($O11-1,$O$2:$O$501,0)),"~"),1,0))) | R11: =IF($O11="","",$O11+SUMIFS($Q$2:$Q$501,$O$2:$O$501,"<="&$O11)) | S11: =IF($P11="","",$P11&" · "&IFERROR(INDEX(Работы!$E$2:$E$6000,MATCH($C11,Работы!$A$2:$A$6000,0)),""))
C12: =IF($B12="","",IFERROR(LEFT($B12,FIND(" — ",$B12)-1),$B12)) | D12: =IF($C12="","",IF(AND(LEFT($F12,3)="ДОК",$H12<>""),IFERROR(INDEX(Документация!$G$2:$G$57,MATCH($H12,Документация!$F$2:$F$57,0)),"— вариант не найден —"),IFERROR(INDEX(Работы!$B$2:$B$6000,MATCH($C12,Работы!$A$2:$A$6000,0)),"— нет такого кода —"))) | E12: =IF($C12="","",IF(AND(LEFT($F12,3)="ДОК",$H12<>""),IFERROR(INDEX(Документация!$D$2:$D$57,MATCH($H12,Документация!$F$2:$F$57,0)),""),IFERROR(INDEX(Работы!$C$2:$C$6000,MATCH($C12,Работы!$A$2:$A$6000,0)),""))) | F12: =IF($C12="","",IFERROR(INDEX(Работы!$G$2:$G$6000,MATCH($C12,Работы!$A$2:$A$6000,0))&"","")) | I12: =IF((LEFT($F12,3)="ДОК"),"",IF($H12="","",IFERROR(INDEX(Материалы!$B$2:$B$9000,MATCH($H12,Материалы!$M$2:$M$9000,0)),""))) | J12: =IF(AND(LEFT($F12,3)="ДОК",$H12<>""),IFERROR(INDEX(Документация!$E$2:$E$57,MATCH($H12,Документация!$F$2:$F$57,0)),0),IFERROR(INDEX(Работы!$H$2:$H$6000,MATCH($C12,Работы!$A$2:$A$6000,0)),0))*(1-MEDIAN(0,N(ДисконтТендер),1)) -> 0 | K12: =IF(OR((LEFT($F12,3)="ДОК"),$H12=""),0,IFERROR(INDEX(Материалы!$H$2:$H$9000,MATCH($H12,Материалы!$M$2:$M$9000,0))*IF(INDEX(Материалы!$I$2:$I$9000,MATCH($H12,Материалы!$M$2:$M$9000,0))="USD",КурсUSD,IF(INDEX(Материалы!$I$2:$I$9000,MATCH($H12,Материалы!$M$2:$M$9000,0))="EUR",КурсEUR,1))*(1+IFERROR(INDEX(Работы!$I$2:$I$6000,MATCH($C12,Работы!$A$2:$A$6000,0))/100,0))*(1-MEDIAN(0,N(ДисконтТендер),1)),0)) -> 0 | L12: =IF($G12<>"",ROUND($G12*$J12,2),0) -> 0 | M12: =IF($G12<>"",ROUND($G12*$K12,2),0) -> 0 | N12: =$L12+$M12 -> 0 | O12: =IF($N12>0,MAX($O$1:$O11)+1,"") | P12: =IF($C12="","",IFERROR(INDEX(Работы!$D$2:$D$6000,MATCH($C12,Работы!$A$2:$A$6000,0)),"")) | Q12: =IF($O12="","",IF($O12=1,1,IF($P12<>IFERROR(INDEX($P$2:$P$501,MATCH($O12-1,$O$2:$O$501,0)),"~"),1,0))) | R12: =IF($O12="","",$O12+SUMIFS($Q$2:$Q$501,$O$2:$O$501,"<="&$O12)) | S12: =IF($P12="","",$P12&" · "&IFERROR(INDEX(Работы!$E$2:$E$6000,MATCH($C12,Работы!$A$2:$A$6000,0)),""))
C13: =IF($B13="","",IFERROR(LEFT($B13,FIND(" — ",$B13)-1),$B13)) | D13: =IF($C13="","",IF(AND(LEFT($F13,3)="ДОК",$H13<>""),IFERROR(INDEX(Документация!$G$2:$G$57,MATCH($H13,Документация!$F$2:$F$57,0)),"— вариант не найден —"),IFERROR(INDEX(Работы!$B$2:$B$6000,MATCH($C13,Работы!$A$2:$A$6000,0)),"— нет такого кода —"))) | E13: =IF($C13="","",IF(AND(LEFT($F13,3)="ДОК",$H13<>""),IFERROR(INDEX(Документация!$D$2:$D$57,MATCH($H13,Документация!$F$2:$F$57,0)),""),IFERROR(INDEX(Работы!$C$2:$C$6000,MATCH($C13,Работы!$A$2:$A$6000,0)),""))) | F13: =IF($C13="","",IFERROR(INDEX(Работы!$G$2:$G$6000,MATCH($C13,Работы!$A$2:$A$6000,0))&"","")) | I13: =IF((LEFT($F13,3)="ДОК"),"",IF($H13="","",IFERROR(INDEX(Материалы!$B$2:$B$9000,MATCH($H13,Материалы!$M$2:$M$9000,0)),""))) | J13: =IF(AND(LEFT($F13,3)="ДОК",$H13<>""),IFERROR(INDEX(Документация!$E$2:$E$57,MATCH($H13,Документация!$F$2:$F$57,0)),0),IFERROR(INDEX(Работы!$H$2:$H$6000,MATCH($C13,Работы!$A$2:$A$6000,0)),0))*(1-MEDIAN(0,N(ДисконтТендер),1)) -> 0 | K13: =IF(OR((LEFT($F13,3)="ДОК"),$H13=""),0,IFERROR(INDEX(Материалы!$H$2:$H$9000,MATCH($H13,Материалы!$M$2:$M$9000,0))*IF(INDEX(Материалы!$I$2:$I$9000,MATCH($H13,Материалы!$M$2:$M$9000,0))="USD",КурсUSD,IF(INDEX(Материалы!$I$2:$I$9000,MATCH($H13,Материалы!$M$2:$M$9000,0))="EUR",КурсEUR,1))*(1+IFERROR(INDEX(Работы!$I$2:$I$6000,MATCH($C13,Работы!$A$2:$A$6000,0))/100,0))*(1-MEDIAN(0,N(ДисконтТендер),1)),0)) -> 0 | L13: =IF($G13<>"",ROUND($G13*$J13,2),0) -> 0 | M13: =IF($G13<>"",ROUND($G13*$K13,2),0) -> 0 | N13: =$L13+$M13 -> 0 | O13: =IF($N13>0,MAX($O$1:$O12)+1,"") | P13: =IF($C13="","",IFERROR(INDEX(Работы!$D$2:$D$6000,MATCH($C13,Работы!$A$2:$A$6000,0)),"")) | Q13: =IF($O13="","",IF($O13=1,1,IF($P13<>IFERROR(INDEX($P$2:$P$501,MATCH($O13-1,$O$2:$O$501,0)),"~"),1,0))) | R13: =IF($O13="","",$O13+SUMIFS($Q$2:$Q$501,$O$2:$O$501,"<="&$O13)) | S13: =IF($P13="","",$P13&" · "&IFERROR(INDEX(Работы!$E$2:$E$6000,MATCH($C13,Работы!$A$2:$A$6000,0)),""))
... C501: =IF($B501="","",IFERROR(LEFT($B501,FIND(" — ",$B501)-1),$B501)) | D501: =IF($C501="","",IF(AND(LEFT($F501,3)="ДОК",$H501<>""),IFERROR(INDEX(Документация!$G$2:$G$57,MATCH($H501,Документация!$F$2:$F$57,0)),"— вариант не найден —"),IFERROR(INDEX(Работы!$B$2:$B$6000,MATCH($C501,Работы!$A$2:$A$6000,0)),"— нет такого кода —"))) | E501: =IF($C501="","",IF(AND(LEFT($F501,3)="ДОК",$H501<>""),IFERROR(INDEX(Документация!$D$2:$D$57,MATCH($H501,Документация!$F$2:$F$57,0)),""),IFERROR(INDEX(Работы!$C$2:$C$6000,MATCH($C501,Работы!$A$2:$A$6000,0)),""))) | F501: =IF($C501="","",IFERROR(INDEX(Работы!$G$2:$G$6000,MATCH($C501,Работы!$A$2:$A$6000,0))&"","")) | I501: =IF((LEFT($F501,3)="ДОК"),"",IF($H501="","",IFERROR(INDEX(Материалы!$B$2:$B$9000,MATCH($H501,Материалы!$M$2:$M$9000,0)),""))) | J501: =IF(AND(LEFT($F501,3)="ДОК",$H501<>""),IFERROR(INDEX(Документация!$E$2:$E$57,MATCH($H501,Документация!$F$2:$F$57,0)),0),IFERROR(INDEX(Работы!$H$2:$H$6000,MATCH($C501,Работы!$A$2:$A$6000,0)),0))*(1-MEDIAN(0,N(ДисконтТендер),1)) -> 0 | K501: =IF(OR((LEFT($F501,3)="ДОК"),$H501=""),0,IFERROR(INDEX(Материалы!$H$2:$H$9000,MATCH($H501,Материалы!$M$2:$M$9000,0))*IF(INDEX(Материалы!$I$2:$I$9000,MATCH($H501,Материалы!$M$2:$M$9000,0))="USD",КурсUSD,IF(INDEX(Материалы!$I$2:$I$9000,MATCH($H501,Материалы!$M$2:$M$9000,0))="EUR",КурсEUR,1))*(1+IFERROR(INDEX(Работы!$I$2:$I$6000,MATCH($C501,Работы!$A$2:$A$6000,0))/100,0))*(1-MEDIAN(0,N(ДисконтТендер),1)),0)) -> 0 | L501: =IF($G501<>"",ROUND($G501*$J501,2),0) -> 0 | M501: =IF($G501<>"",ROUND($G501*$K501,2),0) -> 0 | N501: =$L501+$M501 -> 0 | O501: =IF($N501>0,MAX($O$1:$O500)+1,"") | P501: =IF($C501="","",IFERROR(INDEX(Работы!$D$2:$D$6000,MATCH($C501,Работы!$A$2:$A$6000,0)),"")) | Q501: =IF($O501="","",IF($O501=1,1,IF($P501<>IFERROR(INDEX($P$2:$P$501,MATCH($O501-1,$O$2:$O$501,0)),"~"),1,0))) | R501: =IF($O501="","",$O501+SUMIFS($Q$2:$Q$501,$O$2:$O$501,"<="&$O501)) | S501: =IF($P501="","",$P501&" · "&IFERROR(INDEX(Работы!$E$2:$E$6000,MATCH($C501,Работы!$A$2:$A$6000,0)),""))

Sheet Смета
A1: СМЕТА
A2: Формат объекта:
A3: Адрес объекта:
A4: Площадь объекта (м.кв.):
A5: Срок проведения работ:
A6: ПОДРЯДЧИК:
A7: Юридический адрес:
A8: Электронный адрес:
A9: Контактное лицо (Ф.И.О.):
A10: Контактный телефон:
A11: Реквизиты:
A12: Сумма по смете, ₽: | C12: =$J$541 -> 0
A13: Цены на дату:
A15: Курс USD: | C15: 81
A16: Курс EUR: | C16: 95
A17: Дисконт по тендеру, доля: | C17: 0
A19: РАСШИФРОВКА РАБОТ И ЗАТРАТ. После сборки перечня: встать на таблицу → Данные → «Применить повторно» (Ctrl+Alt+L). Перед отправкой фильтровать по «Кол-ву».
A20: № | B20: Код | C20: Наименование работ и затрат | D20: Ед. изм. | E20: Кол-во | F20: Цена ед. работ, ₽ | G20: Цена ед. материалов/оборуд., ₽ | H20: Стоимость работ, ₽ | I20: Стоимость материалов/оборуд., ₽ | J20: Всего, ₽ | K20: _w | L20: _hdr | M20: _показать
A21: =IF(ISNUMBER($K21),INDEX(Сборка!$O$2:$O$501,$K21),"") | B21: =IF(ISNUMBER($K21),INDEX(Сборка!$C$2:$C$501,$K21),"") | C21: =IF($L21<>"",INDEX(Сборка!$S$2:$S$501,MATCH($L21,Сборка!$P$2:$P$501,0)),IF(ISNUMBER($K21),INDEX(Сборка!$D$2:$D$501,$K21)&IF(INDEX(Сборка!$I$2:$I$501,$K21)<>""," — "&INDEX(Сборка!$I$2:$I$501,$K21),""),"")) | D21: =IF(ISNUMBER($K21),INDEX(Сборка!$E$2:$E$501,$K21),"") | E21: =IF(ISNUMBER($K21),INDEX(Сборка!$G$2:$G$501,$K21),"") | F21: =IF(ISNUMBER($K21),INDEX(Сборка!$J$2:$J$501,$K21),"") | G21: =IF(ISNUMBER($K21),INDEX(Сборка!$K$2:$K$501,$K21),"") | H21: =IF(ISNUMBER($K21),ROUND($E21*$F21,2),"") | I21: =IF(ISNUMBER($K21),ROUND($E21*$G21,2),"") | J21: =IF(ISNUMBER($K21),$H21+$I21,"") | K21: =IFERROR(MATCH(1,Сборка!$R$2:$R$501,0),"") | L21: =IFERROR(IF(INDEX(Сборка!$Q$2:$Q$501,MATCH(1+1,Сборка!$R$2:$R$501,0))=1,INDEX(Сборка!$P$2:$P$501,MATCH(1+1,Сборка!$R$2:$R$501,0)),""),"") | M21: =IF(OR(ISNUMBER($K21),$L21<>""),"показать","")
A22: =IF(ISNUMBER($K22),INDEX(Сборка!$O$2:$O$501,$K22),"") | B22: =IF(ISNUMBER($K22),INDEX(Сборка!$C$2:$C$501,$K22),"") | C22: =IF($L22<>"",INDEX(Сборка!$S$2:$S$501,MATCH($L22,Сборка!$P$2:$P$501,0)),IF(ISNUMBER($K22),INDEX(Сборка!$D$2:$D$501,$K22)&IF(INDEX(Сборка!$I$2:$I$501,$K22)<>""," — "&INDEX(Сборка!$I$2:$I$501,$K22),""),"")) | D22: =IF(ISNUMBER($K22),INDEX(Сборка!$E$2:$E$501,$K22),"") | E22: =IF(ISNUMBER($K22),INDEX(Сборка!$G$2:$G$501,$K22),"") | F22: =IF(ISNUMBER($K22),INDEX(Сборка!$J$2:$J$501,$K22),"") | G22: =IF(ISNUMBER($K22),INDEX(Сборка!$K$2:$K$501,$K22),"") | H22: =IF(ISNUMBER($K22),ROUND($E22*$F22,2),"") | I22: =IF(ISNUMBER($K22),ROUND($E22*$G22,2),"") | J22: =IF(ISNUMBER($K22),$H22+$I22,"") | K22: =IFERROR(MATCH(2,Сборка!$R$2:$R$501,0),"") | L22: =IFERROR(IF(INDEX(Сборка!$Q$2:$Q$501,MATCH(2+1,Сборка!$R$2:$R$501,0))=1,INDEX(Сборка!$P$2:$P$501,MATCH(2+1,Сборка!$R$2:$R$501,0)),""),"") | M22: =IF(OR(ISNUMBER($K22),$L22<>""),"показать","")
A23: =IF(ISNUMBER($K23),INDEX(Сборка!$O$2:$O$501,$K23),"") | B23: =IF(ISNUMBER($K23),INDEX(Сборка!$C$2:$C$501,$K23),"") | C23: =IF($L23<>"",INDEX(Сборка!$S$2:$S$501,MATCH($L23,Сборка!$P$2:$P$501,0)),IF(ISNUMBER($K23),INDEX(Сборка!$D$2:$D$501,$K23)&IF(INDEX(Сборка!$I$2:$I$501,$K23)<>""," — "&INDEX(Сборка!$I$2:$I$501,$K23),""),"")) | D23: =IF(ISNUMBER($K23),INDEX(Сборка!$E$2:$E$501,$K23),"") | E23: =IF(ISNUMBER($K23),INDEX(Сборка!$G$2:$G$501,$K23),"") | F23: =IF(ISNUMBER($K23),INDEX(Сборка!$J$2:$J$501,$K23),"") | G23: =IF(ISNUMBER($K23),INDEX(Сборка!$K$2:$K$501,$K23),"") | H23: =IF(ISNUMBER($K23),ROUND($E23*$F23,2),"") | I23: =IF(ISNUMBER($K23),ROUND($E23*$G23,2),"") | J23: =IF(ISNUMBER($K23),$H23+$I23,"") | K23: =IFERROR(MATCH(3,Сборка!$R$2:$R$501,0),"") | L23: =IFERROR(IF(INDEX(Сборка!$Q$2:$Q$501,MATCH(3+1,Сборка!$R$2:$R$501,0))=1,INDEX(Сборка!$P$2:$P$501,MATCH(3+1,Сборка!$R$2:$R$501,0)),""),"") | M23: =IF(OR(ISNUMBER($K23),$L23<>""),"показать","")
A24: =IF(ISNUMBER($K24),INDEX(Сборка!$O$2:$O$501,$K24),"") | B24: =IF(ISNUMBER($K24),INDEX(Сборка!$C$2:$C$501,$K24),"") | C24: =IF($L24<>"",INDEX(Сборка!$S$2:$S$501,MATCH($L24,Сборка!$P$2:$P$501,0)),IF(ISNUMBER($K24),INDEX(Сборка!$D$2:$D$501,$K24)&IF(INDEX(Сборка!$I$2:$I$501,$K24)<>""," — "&INDEX(Сборка!$I$2:$I$501,$K24),""),"")) | D24: =IF(ISNUMBER($K24),INDEX(Сборка!$E$2:$E$501,$K24),"") | E24: =IF(ISNUMBER($K24),INDEX(Сборка!$G$2:$G$501,$K24),"") | F24: =IF(ISNUMBER($K24),INDEX(Сборка!$J$2:$J$501,$K24),"") | G24: =IF(ISNUMBER($K24),INDEX(Сборка!$K$2:$K$501,$K24),"") | H24: =IF(ISNUMBER($K24),ROUND($E24*$F24,2),"") | I24: =IF(ISNUMBER($K24),ROUND($E24*$G24,2),"") | J24: =IF(ISNUMBER($K24),$H24+$I24,"") | K24: =IFERROR(MATCH(4,Сборка!$R$2:$R$501,0),"") | L24: =IFERROR(IF(INDEX(Сборка!$Q$2:$Q$501,MATCH(4+1,Сборка!$R$2:$R$501,0))=1,INDEX(Сборка!$P$2:$P$501,MATCH(4+1,Сборка!$R$2:$R$501,0)),""),"") | M24: =IF(OR(ISNUMBER($K24),$L24<>""),"показать","")
A25: =IF(ISNUMBER($K25),INDEX(Сборка!$O$2:$O$501,$K25),"") | B25: =IF(ISNUMBER($K25),INDEX(Сборка!$C$2:$C$501,$K25),"") | C25: =IF($L25<>"",INDEX(Сборка!$S$2:$S$501,MATCH($L25,Сборка!$P$2:$P$501,0)),IF(ISNUMBER($K25),INDEX(Сборка!$D$2:$D$501,$K25)&IF(INDEX(Сборка!$I$2:$I$501,$K25)<>""," — "&INDEX(Сборка!$I$2:$I$501,$K25),""),"")) | D25: =IF(ISNUMBER($K25),INDEX(Сборка!$E$2:$E$501,$K25),"") | E25: =IF(ISNUMBER($K25),INDEX(Сборка!$G$2:$G$501,$K25),"") | F25: =IF(ISNUMBER($K25),INDEX(Сборка!$J$2:$J$501,$K25),"") | G25: =IF(ISNUMBER($K25),INDEX(Сборка!$K$2:$K$501,$K25),"") | H25: =IF(ISNUMBER($K25),ROUND($E25*$F25,2),"") | I25: =IF(ISNUMBER($K25),ROUND($E25*$G25,2),"") | J25: =IF(ISNUMBER($K25),$H25+$I25,"") | K25: =IFERROR(MATCH(5,Сборка!$R$2:$R$501,0),"") | L25: =IFERROR(IF(INDEX(Сборка!$Q$2:$Q$501,MATCH(5+1,Сборка!$R$2:$R$501,0))=1,INDEX(Сборка!$P$2:$P$501,MATCH(5+1,Сборка!$R$2:$R$501,0)),""),"") | M25: =IF(OR(ISNUMBER($K25),$L25<>""),"показать","")
A26: =IF(ISNUMBER($K26),INDEX(Сборка!$O$2:$O$501,$K26),"") | B26: =IF(ISNUMBER($K26),INDEX(Сборка!$C$2:$C$501,$K26),"") | C26: =IF($L26<>"",INDEX(Сборка!$S$2:$S$501,MATCH($L26,Сборка!$P$2:$P$501,0)),IF(ISNUMBER($K26),INDEX(Сборка!$D$2:$D$501,$K26)&IF(INDEX(Сборка!$I$2:$I$501,$K26)<>""," — "&INDEX(Сборка!$I$2:$I$501,$K26),""),"")) | D26: =IF(ISNUMBER($K26),INDEX(Сборка!$E$2:$E$501,$K26),"") | E26: =IF(ISNUMBER($K26),INDEX(Сборка!$G$2:$G$501,$K26),"") | F26: =IF(ISNUMBER($K26),INDEX(Сборка!$J$2:$J$501,$K26),"") | G26: =IF(ISNUMBER($K26),INDEX(Сборка!$K$2:$K$501,$K26),"") | H26: =IF(ISNUMBER($K26),ROUND($E26*$F26,2),"") | I26: =IF(ISNUMBER($K26),ROUND($E26*$G26,2),"") | J26: =IF(ISNUMBER($K26),$H26+$I26,"") | K26: =IFERROR(MATCH(6,Сборка!$R$2:$R$501,0),"") | L26: =IFERROR(IF(INDEX(Сборка!$Q$2:$Q$501,MATCH(6+1,Сборка!$R$2:$R$501,0))=1,INDEX(Сборка!$P$2:$P$501,MATCH(6+1,Сборка!$R$2:$R$501,0)),""),"") | M26: =IF(OR(ISNUMBER($K26),$L26<>""),"показать","")
A27: =IF(ISNUMBER($K27),INDEX(Сборка!$O$2:$O$501,$K27),"") | B27: =IF(ISNUMBER($K27),INDEX(Сборка!$C$2:$C$501,$K27),"") | C27: =IF($L27<>"",INDEX(Сборка!$S$2:$S$501,MATCH($L27,Сборка!$P$2:$P$501,0)),IF(ISNUMBER($K27),INDEX(Сборка!$D$2:$D$501,$K27)&IF(INDEX(Сборка!$I$2:$I$501,$K27)<>""," — "&INDEX(Сборка!$I$2:$I$501,$K27),""),"")) | D27: =IF(ISNUMBER($K27),INDEX(Сборка!$E$2:$E$501,$K27),"") | E27: =IF(ISNUMBER($K27),INDEX(Сборка!$G$2:$G$501,$K27),"") | F27: =IF(ISNUMBER($K27),INDEX(Сборка!$J$2:$J$501,$K27),"") | G27: =IF(ISNUMBER($K27),INDEX(Сборка!$K$2:$K$501,$K27),"") | H27: =IF(ISNUMBER($K27),ROUND($E27*$F27,2),"") | I27: =IF(ISNUMBER($K27),ROUND($E27*$G27,2),"") | J27: =IF(ISNUMBER($K27),$H27+$I27,"") | K27: =IFERROR(MATCH(7,Сборка!$R$2:$R$501,0),"") | L27: =IFERROR(IF(INDEX(Сборка!$Q$2:$Q$501,MATCH(7+1,Сборка!$R$2:$R$501,0))=1,INDEX(Сборка!$P$2:$P$501,MATCH(7+1,Сборка!$R$2:$R$501,0)),""),"") | M27: =IF(OR(ISNUMBER($K27),$L27<>""),"показать","")
A28: =IF(ISNUMBER($K28),INDEX(Сборка!$O$2:$O$501,$K28),"") | B28: =IF(ISNUMBER($K28),INDEX(Сборка!$C$2:$C$501,$K28),"") | C28: =IF($L28<>"",INDEX(Сборка!$S$2:$S$501,MATCH($L28,Сборка!$P$2:$P$501,0)),IF(ISNUMBER($K28),INDEX(Сборка!$D$2:$D$501,$K28)&IF(INDEX(Сборка!$I$2:$I$501,$K28)<>""," — "&INDEX(Сборка!$I$2:$I$501,$K28),""),"")) | D28: =IF(ISNUMBER($K28),INDEX(Сборка!$E$2:$E$501,$K28),"") | E28: =IF(ISNUMBER($K28),INDEX(Сборка!$G$2:$G$501,$K28),"") | F28: =IF(ISNUMBER($K28),INDEX(Сборка!$J$2:$J$501,$K28),"") | G28: =IF(ISNUMBER($K28),INDEX(Сборка!$K$2:$K$501,$K28),"") | H28: =IF(ISNUMBER($K28),ROUND($E28*$F28,2),"") | I28: =IF(ISNUMBER($K28),ROUND($E28*$G28,2),"") | J28: =IF(ISNUMBER($K28),$H28+$I28,"") | K28: =IFERROR(MATCH(8,Сборка!$R$2:$R$501,0),"") | L28: =IFERROR(IF(INDEX(Сборка!$Q$2:$Q$501,MATCH(8+1,Сборка!$R$2:$R$501,0))=1,INDEX(Сборка!$P$2:$P$501,MATCH(8+1,Сборка!$R$2:$R$501,0)),""),"") | M28: =IF(OR(ISNUMBER($K28),$L28<>""),"показать","")
A29: =IF(ISNUMBER($K29),INDEX(Сборка!$O$2:$O$501,$K29),"") | B29: =IF(ISNUMBER($K29),INDEX(Сборка!$C$2:$C$501,$K29),"") | C29: =IF($L29<>"",INDEX(Сборка!$S$2:$S$501,MATCH($L29,Сборка!$P$2:$P$501,0)),IF(ISNUMBER($K29),INDEX(Сборка!$D$2:$D$501,$K29)&IF(INDEX(Сборка!$I$2:$I$501,$K29)<>""," — "&INDEX(Сборка!$I$2:$I$501,$K29),""),"")) | D29: =IF(ISNUMBER($K29),INDEX(Сборка!$E$2:$E$501,$K29),"") | E29: =IF(ISNUMBER($K29),INDEX(Сборка!$G$2:$G$501,$K29),"") | F29: =IF(ISNUMBER($K29),INDEX(Сборка!$J$2:$J$501,$K29),"") | G29: =IF(ISNUMBER($K29),INDEX(Сборка!$K$2:$K$501,$K29),"") | H29: =IF(ISNUMBER($K29),ROUND($E29*$F29,2),"") | I29: =IF(ISNUMBER($K29),ROUND($E29*$G29,2),"") | J29: =IF(ISNUMBER($K29),$H29+$I29,"") | K29: =IFERROR(MATCH(9,Сборка!$R$2:$R$501,0),"") | L29: =IFERROR(IF(INDEX(Сборка!$Q$2:$Q$501,MATCH(9+1,Сборка!$R$2:$R$501,0))=1,INDEX(Сборка!$P$2:$P$501,MATCH(9+1,Сборка!$R$2:$R$501,0)),""),"") | M29: =IF(OR(ISNUMBER($K29),$L29<>""),"показать","")
A30: =IF(ISNUMBER($K30),INDEX(Сборка!$O$2:$O$501,$K30),"") | B30: =IF(ISNUMBER($K30),INDEX(Сборка!$C$2:$C$501,$K30),"") | C30: =IF($L30<>"",INDEX(Сборка!$S$2:$S$501,MATCH($L30,Сборка!$P$2:$P$501,0)),IF(ISNUMBER($K30),INDEX(Сборка!$D$2:$D$501,$K30)&IF(INDEX(Сборка!$I$2:$I$501,$K30)<>""," — "&INDEX(Сборка!$I$2:$I$501,$K30),""),"")) | D30: =IF(ISNUMBER($K30),INDEX(Сборка!$E$2:$E$501,$K30),"") | E30: =IF(ISNUMBER($K30),INDEX(Сборка!$G$2:$G$501,$K30),"") | F30: =IF(ISNUMBER($K30),INDEX(Сборка!$J$2:$J$501,$K30),"") | G30: =IF(ISNUMBER($K30),INDEX(Сборка!$K$2:$K$501,$K30),"") | H30: =IF(ISNUMBER($K30),ROUND($E30*$F30,2),"") | I30: =IF(ISNUMBER($K30),ROUND($E30*$G30,2),"") | J30: =IF(ISNUMBER($K30),$H30+$I30,"") | K30: =IFERROR(MATCH(10,Сборка!$R$2:$R$501,0),"") | L30: =IFERROR(IF(INDEX(Сборка!$Q$2:$Q$501,MATCH(10+1,Сборка!$R$2:$R$501,0))=1,INDEX(Сборка!$P$2:$P$501,MATCH(10+1,Сборка!$R$2:$R$501,0)),""),"") | M30: =IF(OR(ISNUMBER($K30),$L30<>""),"показать","")
A31: =IF(ISNUMBER($K31),INDEX(Сборка!$O$2:$O$501,$K31),"") | B31: =IF(ISNUMBER($K31),INDEX(Сборка!$C$2:$C$501,$K31),"") | C31: =IF($L31<>"",INDEX(Сборка!$S$2:$S$501,MATCH($L31,Сборка!$P$2:$P$501,0)),IF(ISNUMBER($K31),INDEX(Сборка!$D$2:$D$501,$K31)&IF(INDEX(Сборка!$I$2:$I$501,$K31)<>""," — "&INDEX(Сборка!$I$2:$I$501,$K31),""),"")) | D31: =IF(ISNUMBER($K31),INDEX(Сборка!$E$2:$E$501,$K31),"") | E31: =IF(ISNUMBER($K31),INDEX(Сборка!$G$2:$G$501,$K31),"") | F31: =IF(ISNUMBER($K31),INDEX(Сборка!$J$2:$J$501,$K31),"") | G31: =IF(ISNUMBER($K31),INDEX(Сборка!$K$2:$K$501,$K31),"") | H31: =IF(ISNUMBER($K31),ROUND($E31*$F31,2),"") | I31: =IF(ISNUMBER($K31),ROUND($E31*$G31,2),"") | J31: =IF(ISNUMBER($K31),$H31+$I31,"") | K31: =IFERROR(MATCH(11,Сборка!$R$2:$R$501,0),"") | L31: =IFERROR(IF(INDEX(Сборка!$Q$2:$Q$501,MATCH(11+1,Сборка!$R$2:$R$501,0))=1,INDEX(Сборка!$P$2:$P$501,MATCH(11+1,Сборка!$R$2:$R$501,0)),""),"") | M31: =IF(OR(ISNUMBER($K31),$L31<>""),"показать","")
A32: =IF(ISNUMBER($K32),INDEX(Сборка!$O$2:$O$501,$K32),"") | B32: =IF(ISNUMBER($K32),INDEX(Сборка!$C$2:$C$501,$K32),"") | C32: =IF($L32<>"",INDEX(Сборка!$S$2:$S$501,MATCH($L32,Сборка!$P$2:$P$501,0)),IF(ISNUMBER($K32),INDEX(Сборка!$D$2:$D$501,$K32)&IF(INDEX(Сборка!$I$2:$I$501,$K32)<>""," — "&INDEX(Сборка!$I$2:$I$501,$K32),""),"")) | D32: =IF(ISNUMBER($K32),INDEX(Сборка!$E$2:$E$501,$K32),"") | E32: =IF(ISNUMBER($K32),INDEX(Сборка!$G$2:$G$501,$K32),"") | F32: =IF(ISNUMBER($K32),INDEX(Сборка!$J$2:$J$501,$K32),"") | G32: =IF(ISNUMBER($K32),INDEX(Сборка!$K$2:$K$501,$K32),"") | H32: =IF(ISNUMBER($K32),ROUND($E32*$F32,2),"") | I32: =IF(ISNUMBER($K32),ROUND($E32*$G32,2),"") | J32: =IF(ISNUMBER($K32),$H32+$I32,"") | K32: =IFERROR(MATCH(12,Сборка!$R$2:$R$501,0),"") | L32: =IFERROR(IF(INDEX(Сборка!$Q$2:$Q$501,MATCH(12+1,Сборка!$R$2:$R$501,0))=1,INDEX(Сборка!$P$2:$P$501,MATCH(12+1,Сборка!$R$2:$R$501,0)),""),"") | M32: =IF(OR(ISNUMBER($K32),$L32<>""),"показать","")
A33: =IF(ISNUMBER($K33),INDEX(Сборка!$O$2:$O$501,$K33),"") | B33: =IF(ISNUMBER($K33),INDEX(Сборка!$C$2:$C$501,$K33),"") | C33: =IF($L33<>"",INDEX(Сборка!$S$2:$S$501,MATCH($L33,Сборка!$P$2:$P$501,0)),IF(ISNUMBER($K33),INDEX(Сборка!$D$2:$D$501,$K33)&IF(INDEX(Сборка!$I$2:$I$501,$K33)<>""," — "&INDEX(Сборка!$I$2:$I$501,$K33),""),"")) | D33: =IF(ISNUMBER($K33),INDEX(Сборка!$E$2:$E$501,$K33),"") | E33: =IF(ISNUMBER($K33),INDEX(Сборка!$G$2:$G$501,$K33),"") | F33: =IF(ISNUMBER($K33),INDEX(Сборка!$J$2:$J$501,$K33),"") | G33: =IF(ISNUMBER($K33),INDEX(Сборка!$K$2:$K$501,$K33),"") | H33: =IF(ISNUMBER($K33),ROUND($E33*$F33,2),"") | I33: =IF(ISNUMBER($K33),ROUND($E33*$G33,2),"") | J33: =IF(ISNUMBER($K33),$H33+$I33,"") | K33: =IFERROR(MATCH(13,Сборка!$R$2:$R$501,0),"") | L33: =IFERROR(IF(INDEX(Сборка!$Q$2:$Q$501,MATCH(13+1,Сборка!$R$2:$R$501,0))=1,INDEX(Сборка!$P$2:$P$501,MATCH(13+1,Сборка!$R$2:$R$501,0)),""),"") | M33: =IF(OR(ISNUMBER($K33),$L33<>""),"показать","")
A34: =IF(ISNUMBER($K34),INDEX(Сборка!$O$2:$O$501,$K34),"") | B34: =IF(ISNUMBER($K34),INDEX(Сборка!$C$2:$C$501,$K34),"") | C34: =IF($L34<>"",INDEX(Сборка!$S$2:$S$501,MATCH($L34,Сборка!$P$2:$P$501,0)),IF(ISNUMBER($K34),INDEX(Сборка!$D$2:$D$501,$K34)&IF(INDEX(Сборка!$I$2:$I$501,$K34)<>""," — "&INDEX(Сборка!$I$2:$I$501,$K34),""),"")) | D34: =IF(ISNUMBER($K34),INDEX(Сборка!$E$2:$E$501,$K34),"") | E34: =IF(ISNUMBER($K34),INDEX(Сборка!$G$2:$G$501,$K34),"") | F34: =IF(ISNUMBER($K34),INDEX(Сборка!$J$2:$J$501,$K34),"") | G34: =IF(ISNUMBER($K34),INDEX(Сборка!$K$2:$K$501,$K34),"") | H34: =IF(ISNUMBER($K34),ROUND($E34*$F34,2),"") | I34: =IF(ISNUMBER($K34),ROUND($E34*$G34,2),"") | J34: =IF(ISNUMBER($K34),$H34+$I34,"") | K34: =IFERROR(MATCH(14,Сборка!$R$2:$R$501,0),"") | L34: =IFERROR(IF(INDEX(Сборка!$Q$2:$Q$501,MATCH(14+1,Сборка!$R$2:$R$501,0))=1,INDEX(Сборка!$P$2:$P$501,MATCH(14+1,Сборка!$R$2:$R$501,0)),""),"") | M34: =IF(OR(ISNUMBER($K34),$L34<>""),"показать","")
A35: =IF(ISNUMBER($K35),INDEX(Сборка!$O$2:$O$501,$K35),"") | B35: =IF(ISNUMBER($K35),INDEX(Сборка!$C$2:$C$501,$K35),"") | C35: =IF($L35<>"",INDEX(Сборка!$S$2:$S$501,MATCH($L35,Сборка!$P$2:$P$501,0)),IF(ISNUMBER($K35),INDEX(Сборка!$D$2:$D$501,$K35)&IF(INDEX(Сборка!$I$2:$I$501,$K35)<>""," — "&INDEX(Сборка!$I$2:$I$501,$K35),""),"")) | D35: =IF(ISNUMBER($K35),INDEX(Сборка!$E$2:$E$501,$K35),"") | E35: =IF(ISNUMBER($K35),INDEX(Сборка!$G$2:$G$501,$K35),"") | F35: =IF(ISNUMBER($K35),INDEX(Сборка!$J$2:$J$501,$K35),"") | G35: =IF(ISNUMBER($K35),INDEX(Сборка!$K$2:$K$501,$K35),"") | H35: =IF(ISNUMBER($K35),ROUND($E35*$F35,2),"") | I35: =IF(ISNUMBER($K35),ROUND($E35*$G35,2),"") | J35: =IF(ISNUMBER($K35),$H35+$I35,"") | K35: =IFERROR(MATCH(15,Сборка!$R$2:$R$501,0),"") | L35: =IFERROR(IF(INDEX(Сборка!$Q$2:$Q$501,MATCH(15+1,Сборка!$R$2:$R$501,0))=1,INDEX(Сборка!$P$2:$P$501,MATCH(15+1,Сборка!$R$2:$R$501,0)),""),"") | M35: =IF(OR(ISNUMBER($K35),$L35<>""),"показать","")
A36: =IF(ISNUMBER($K36),INDEX(Сборка!$O$2:$O$501,$K36),"") | B36: =IF(ISNUMBER($K36),INDEX(Сборка!$C$2:$C$501,$K36),"") | C36: =IF($L36<>"",INDEX(Сборка!$S$2:$S$501,MATCH($L36,Сборка!$P$2:$P$501,0)),IF(ISNUMBER($K36),INDEX(Сборка!$D$2:$D$501,$K36)&IF(INDEX(Сборка!$I$2:$I$501,$K36)<>""," — "&INDEX(Сборка!$I$2:$I$501,$K36),""),"")) | D36: =IF(ISNUMBER($K36),INDEX(Сборка!$E$2:$E$501,$K36),"") | E36: =IF(ISNUMBER($K36),INDEX(Сборка!$G$2:$G$501,$K36),"") | F36: =IF(ISNUMBER($K36),INDEX(Сборка!$J$2:$J$501,$K36),"") | G36: =IF(ISNUMBER($K36),INDEX(Сборка!$K$2:$K$501,$K36),"") | H36: =IF(ISNUMBER($K36),ROUND($E36*$F36,2),"") | I36: =IF(ISNUMBER($K36),ROUND($E36*$G36,2),"") | J36: =IF(ISNUMBER($K36),$H36+$I36,"") | K36: =IFERROR(MATCH(16,Сборка!$R$2:$R$501,0),"") | L36: =IFERROR(IF(INDEX(Сборка!$Q$2:$Q$501,MATCH(16+1,Сборка!$R$2:$R$501,0))=1,INDEX(Сборка!$P$2:$P$501,MATCH(16+1,Сборка!$R$2:$R$501,0)),""),"") | M36: =IF(OR(ISNUMBER($K36),$L36<>""),"показать","")
A37: =IF(ISNUMBER($K37),INDEX(Сборка!$O$2:$O$501,$K37),"") | B37: =IF(ISNUMBER($K37),INDEX(Сборка!$C$2:$C$501,$K37),"") | C37: =IF($L37<>"",INDEX(Сборка!$S$2:$S$501,MATCH($L37,Сборка!$P$2:$P$501,0)),IF(ISNUMBER($K37),INDEX(Сборка!$D$2:$D$501,$K37)&IF(INDEX(Сборка!$I$2:$I$501,$K37)<>""," — "&INDEX(Сборка!$I$2:$I$501,$K37),""),"")) | D37: =IF(ISNUMBER($K37),INDEX(Сборка!$E$2:$E$501,$K37),"") | E37: =IF(ISNUMBER($K37),INDEX(Сборка!$G$2:$G$501,$K37),"") | F37: =IF(ISNUMBER($K37),INDEX(Сборка!$J$2:$J$501,$K37),"") | G37: =IF(ISNUMBER($K37),INDEX(Сборка!$K$2:$K$501,$K37),"") | H37: =IF(ISNUMBER($K37),ROUND($E37*$F37,2),"") | I37: =IF(ISNUMBER($K37),ROUND($E37*$G37,2),"") | J37: =IF(ISNUMBER($K37),$H37+$I37,"") | K37: =IFERROR(MATCH(17,Сборка!$R$2:$R$501,0),"") | L37: =IFERROR(IF(INDEX(Сборка!$Q$2:$Q$501,MATCH(17+1,Сборка!$R$2:$R$501,0))=1,INDEX(Сборка!$P$2:$P$501,MATCH(17+1,Сборка!$R$2:$R$501,0)),""),"") | M37: =IF(OR(ISNUMBER($K37),$L37<>""),"показать","")
A38: =IF(ISNUMBER($K38),INDEX(Сборка!$O$2:$O$501,$K38),"") | B38: =IF(ISNUMBER($K38),INDEX(Сборка!$C$2:$C$501,$K38),"") | C38: =IF($L38<>"",INDEX(Сборка!$S$2:$S$501,MATCH($L38,Сборка!$P$2:$P$501,0)),IF(ISNUMBER($K38),INDEX(Сборка!$D$2:$D$501,$K38)&IF(INDEX(Сборка!$I$2:$I$501,$K38)<>""," — "&INDEX(Сборка!$I$2:$I$501,$K38),""),"")) | D38: =IF(ISNUMBER($K38),INDEX(Сборка!$E$2:$E$501,$K38),"") | E38: =IF(ISNUMBER($K38),INDEX(Сборка!$G$2:$G$501,$K38),"") | F38: =IF(ISNUMBER($K38),INDEX(Сборка!$J$2:$J$501,$K38),"") | G38: =IF(ISNUMBER($K38),INDEX(Сборка!$K$2:$K$501,$K38),"") | H38: =IF(ISNUMBER($K38),ROUND($E38*$F38,2),"") | I38: =IF(ISNUMBER($K38),ROUND($E38*$G38,2),"") | J38: =IF(ISNUMBER($K38),$H38+$I38,"") | K38: =IFERROR(MATCH(18,Сборка!$R$2:$R$501,0),"") | L38: =IFERROR(IF(INDEX(Сборка!$Q$2:$Q$501,MATCH(18+1,Сборка!$R$2:$R$501,0))=1,INDEX(Сборка!$P$2:$P$501,MATCH(18+1,Сборка!$R$2:$R$501,0)),""),"") | M38: =IF(OR(ISNUMBER($K38),$L38<>""),"показать","")
A39: =IF(ISNUMBER($K39),INDEX(Сборка!$O$2:$O$501,$K39),"") | B39: =IF(ISNUMBER($K39),INDEX(Сборка!$C$2:$C$501,$K39),"") | C39: =IF($L39<>"",INDEX(Сборка!$S$2:$S$501,MATCH($L39,Сборка!$P$2:$P$501,0)),IF(ISNUMBER($K39),INDEX(Сборка!$D$2:$D$501,$K39)&IF(INDEX(Сборка!$I$2:$I$501,$K39)<>""," — "&INDEX(Сборка!$I$2:$I$501,$K39),""),"")) | D39: =IF(ISNUMBER($K39),INDEX(Сборка!$E$2:$E$501,$K39),"") | E39: =IF(ISNUMBER($K39),INDEX(Сборка!$G$2:$G$501,$K39),"") | F39: =IF(ISNUMBER($K39),INDEX(Сборка!$J$2:$J$501,$K39),"") | G39: =IF(ISNUMBER($K39),INDEX(Сборка!$K$2:$K$501,$K39),"") | H39: =IF(ISNUMBER($K39),ROUND($E39*$F39,2),"") | I39: =IF(ISNUMBER($K39),ROUND($E39*$G39,2),"") | J39: =IF(ISNUMBER($K39),$H39+$I39,"") | K39: =IFERROR(MATCH(19,Сборка!$R$2:$R$501,0),"") | L39: =IFERROR(IF(INDEX(Сборка!$Q$2:$Q$501,MATCH(19+1,Сборка!$R$2:$R$501,0))=1,INDEX(Сборка!$P$2:$P$501,MATCH(19+1,Сборка!$R$2:$R$501,0)),""),"") | M39: =IF(OR(ISNUMBER($K39),$L39<>""),"показать","")
A40: =IF(ISNUMBER($K40),INDEX(Сборка!$O$2:$O$501,$K40),"") | B40: =IF(ISNUMBER($K40),INDEX(Сборка!$C$2:$C$501,$K40),"") | C40: =IF($L40<>"",INDEX(Сборка!$S$2:$S$501,MATCH($L40,Сборка!$P$2:$P$501,0)),IF(ISNUMBER($K40),INDEX(Сборка!$D$2:$D$501,$K40)&IF(INDEX(Сборка!$I$2:$I$501,$K40)<>""," — "&INDEX(Сборка!$I$2:$I$501,$K40),""),"")) | D40: =IF(ISNUMBER($K40),INDEX(Сборка!$E$2:$E$501,$K40),"") | E40: =IF(ISNUMBER($K40),INDEX(Сборка!$G$2:$G$501,$K40),"") | F40: =IF(ISNUMBER($K40),INDEX(Сборка!$J$2:$J$501,$K40),"") | G40: =IF(ISNUMBER($K40),INDEX(Сборка!$K$2:$K$501,$K40),"") | H40: =IF(ISNUMBER($K40),ROUND($E40*$F40,2),"") | I40: =IF(ISNUMBER($K40),ROUND($E40*$G40,2),"") | J40: =IF(ISNUMBER($K40),$H40+$I40,"") | K40: =IFERROR(MATCH(20,Сборка!$R$2:$R$501,0),"") | L40: =IFERROR(IF(INDEX(Сборка!$Q$2:$Q$501,MATCH(20+1,Сборка!$R$2:$R$501,0))=1,INDEX(Сборка!$P$2:$P$501,MATCH(20+1,Сборка!$R$2:$R$501,0)),""),"") | M40: =IF(OR(ISNUMBER($K40),$L40<>""),"показать","")
A41: =IF(ISNUMBER($K41),INDEX(Сборка!$O$2:$O$501,$K41),"") | B41: =IF(ISNUMBER($K41),INDEX(Сборка!$C$2:$C$501,$K41),"") | C41: =IF($L41<>"",INDEX(Сборка!$S$2:$S$501,MATCH($L41,Сборка!$P$2:$P$501,0)),IF(ISNUMBER($K41),INDEX(Сборка!$D$2:$D$501,$K41)&IF(INDEX(Сборка!$I$2:$I$501,$K41)<>""," — "&INDEX(Сборка!$I$2:$I$501,$K41),""),"")) | D41: =IF(ISNUMBER($K41),INDEX(Сборка!$E$2:$E$501,$K41),"") | E41: =IF(ISNUMBER($K41),INDEX(Сборка!$G$2:$G$501,$K41),"") | F41: =IF(ISNUMBER($K41),INDEX(Сборка!$J$2:$J$501,$K41),"") | G41: =IF(ISNUMBER($K41),INDEX(Сборка!$K$2:$K$501,$K41),"") | H41: =IF(ISNUMBER($K41),ROUND($E41*$F41,2),"") | I41: =IF(ISNUMBER($K41),ROUND($E41*$G41,2),"") | J41: =IF(ISNUMBER($K41),$H41+$I41,"") | K41: =IFERROR(MATCH(21,Сборка!$R$2:$R$501,0),"") | L41: =IFERROR(IF(INDEX(Сборка!$Q$2:$Q$501,MATCH(21+1,Сборка!$R$2:$R$501,0))=1,INDEX(Сборка!$P$2:$P$501,MATCH(21+1,Сборка!$R$2:$R$501,0)),""),"") | M41: =IF(OR(ISNUMBER($K41),$L41<>""),"показать","")
A42: =IF(ISNUMBER($K42),INDEX(Сборка!$O$2:$O$501,$K42),"") | B42: =IF(ISNUMBER($K42),INDEX(Сборка!$C$2:$C$501,$K42),"") | C42: =IF($L42<>"",INDEX(Сборка!$S$2:$S$501,MATCH($L42,Сборка!$P$2:$P$501,0)),IF(ISNUMBER($K42),INDEX(Сборка!$D$2:$D$501,$K42)&IF(INDEX(Сборка!$I$2:$I$501,$K42)<>""," — "&INDEX(Сборка!$I$2:$I$501,$K42),""),"")) | D42: =IF(ISNUMBER($K42),INDEX(Сборка!$E$2:$E$501,$K42),"") | E42: =IF(ISNUMBER($K42),INDEX(Сборка!$G$2:$G$501,$K42),"") | F42: =IF(ISNUMBER($K42),INDEX(Сборка!$J$2:$J$501,$K42),"") | G42: =IF(ISNUMBER($K42),INDEX(Сборка!$K$2:$K$501,$K42),"") | H42: =IF(ISNUMBER($K42),ROUND($E42*$F42,2),"") | I42: =IF(ISNUMBER($K42),ROUND($E42*$G42,2),"") | J42: =IF(ISNUMBER($K42),$H42+$I42,"") | K42: =IFERROR(MATCH(22,Сборка!$R$2:$R$501,0),"") | L42: =IFERROR(IF(INDEX(Сборка!$Q$2:$Q$501,MATCH(22+1,Сборка!$R$2:$R$501,0))=1,INDEX(Сборка!$P$2:$P$501,MATCH(22+1,Сборка!$R$2:$R$501,0)),""),"") | M42: =IF(OR(ISNUMBER($K42),$L42<>""),"показать","")
A43: =IF(ISNUMBER($K43),INDEX(Сборка!$O$2:$O$501,$K43),"") | B43: =IF(ISNUMBER($K43),INDEX(Сборка!$C$2:$C$501,$K43),"") | C43: =IF($L43<>"",INDEX(Сборка!$S$2:$S$501,MATCH($L43,Сборка!$P$2:$P$501,0)),IF(ISNUMBER($K43),INDEX(Сборка!$D$2:$D$501,$K43)&IF(INDEX(Сборка!$I$2:$I$501,$K43)<>""," — "&INDEX(Сборка!$I$2:$I$501,$K43),""),"")) | D43: =IF(ISNUMBER($K43),INDEX(Сборка!$E$2:$E$501,$K43),"") | E43: =IF(ISNUMBER($K43),INDEX(Сборка!$G$2:$G$501,$K43),"") | F43: =IF(ISNUMBER($K43),INDEX(Сборка!$J$2:$J$501,$K43),"") | G43: =IF(ISNUMBER($K43),INDEX(Сборка!$K$2:$K$501,$K43),"") | H43: =IF(ISNUMBER($K43),ROUND($E43*$F43,2),"") | I43: =IF(ISNUMBER($K43),ROUND($E43*$G43,2),"") | J43: =IF(ISNUMBER($K43),$H43+$I43,"") | K43: =IFERROR(MATCH(23,Сборка!$R$2:$R$501,0),"") | L43: =IFERROR(IF(INDEX(Сборка!$Q$2:$Q$501,MATCH(23+1,Сборка!$R$2:$R$501,0))=1,INDEX(Сборка!$P$2:$P$501,MATCH(23+1,Сборка!$R$2:$R$501,0)),""),"") | M43: =IF(OR(ISNUMBER($K43),$L43<>""),"показать","")
A44: =IF(ISNUMBER($K44),INDEX(Сборка!$O$2:$O$501,$K44),"") | B44: =IF(ISNUMBER($K44),INDEX(Сборка!$C$2:$C$501,$K44),"") | C44: =IF($L44<>"",INDEX(Сборка!$S$2:$S$501,MATCH($L44,Сборка!$P$2:$P$501,0)),IF(ISNUMBER($K44),INDEX(Сборка!$D$2:$D$501,$K44)&IF(INDEX(Сборка!$I$2:$I$501,$K44)<>""," — "&INDEX(Сборка!$I$2:$I$501,$K44),""),"")) | D44: =IF(ISNUMBER($K44),INDEX(Сборка!$E$2:$E$501,$K44),"") | E44: =IF(ISNUMBER($K44),INDEX(Сборка!$G$2:$G$501,$K44),"") | F44: =IF(ISNUMBER($K44),INDEX(Сборка!$J$2:$J$501,$K44),"") | G44: =IF(ISNUMBER($K44),INDEX(Сборка!$K$2:$K$501,$K44),"") | H44: =IF(ISNUMBER($K44),ROUND($E44*$F44,2),"") | I44: =IF(ISNUMBER($K44),ROUND($E44*$G44,2),"") | J44: =IF(ISNUMBER($K44),$H44+$I44,"") | K44: =IFERROR(MATCH(24,Сборка!$R$2:$R$501,0),"") | L44: =IFERROR(IF(INDEX(Сборка!$Q$2:$Q$501,MATCH(24+1,Сборка!$R$2:$R$501,0))=1,INDEX(Сборка!$P$2:$P$501,MATCH(24+1,Сборка!$R$2:$R$501,0)),""),"") | M44: =IF(OR(ISNUMBER($K44),$L44<>""),"показать","")
A45: =IF(ISNUMBER($K45),INDEX(Сборка!$O$2:$O$501,$K45),"") | B45: =IF(ISNUMBER($K45),INDEX(Сборка!$C$2:$C$501,$K45),"") | C45: =IF($L45<>"",INDEX(Сборка!$S$2:$S$501,MATCH($L45,Сборка!$P$2:$P$501,0)),IF(ISNUMBER($K45),INDEX(Сборка!$D$2:$D$501,$K45)&IF(INDEX(Сборка!$I$2:$I$501,$K45)<>""," — "&INDEX(Сборка!$I$2:$I$501,$K45),""),"")) | D45: =IF(ISNUMBER($K45),INDEX(Сборка!$E$2:$E$501,$K45),"") | E45: =IF(ISNUMBER($K45),INDEX(Сборка!$G$2:$G$501,$K45),"") | F45: =IF(ISNUMBER($K45),INDEX(Сборка!$J$2:$J$501,$K45),"") | G45: =IF(ISNUMBER($K45),INDEX(Сборка!$K$2:$K$501,$K45),"") | H45: =IF(ISNUMBER($K45),ROUND($E45*$F45,2),"") | I45: =IF(ISNUMBER($K45),ROUND($E45*$G45,2),"") | J45: =IF(ISNUMBER($K45),$H45+$I45,"") | K45: =IFERROR(MATCH(25,Сборка!$R$2:$R$501,0),"") | L45: =IFERROR(IF(INDEX(Сборка!$Q$2:$Q$501,MATCH(25+1,Сборка!$R$2:$R$501,0))=1,INDEX(Сборка!$P$2:$P$501,MATCH(25+1,Сборка!$R$2:$R$501,0)),""),"") | M45: =IF(OR(ISNUMBER($K45),$L45<>""),"показать","")
A46: =IF(ISNUMBER($K46),INDEX(Сборка!$O$2:$O$501,$K46),"") | B46: =IF(ISNUMBER($K46),INDEX(Сборка!$C$2:$C$501,$K46),"") | C46: =IF($L46<>"",INDEX(Сборка!$S$2:$S$501,MATCH($L46,Сборка!$P$2:$P$501,0)),IF(ISNUMBER($K46),INDEX(Сборка!$D$2:$D$501,$K46)&IF(INDEX(Сборка!$I$2:$I$501,$K46)<>""," — "&INDEX(Сборка!$I$2:$I$501,$K46),""),"")) | D46: =IF(ISNUMBER($K46),INDEX(Сборка!$E$2:$E$501,$K46),"") | E46: =IF(ISNUMBER($K46),INDEX(Сборка!$G$2:$G$501,$K46),"") | F46: =IF(ISNUMBER($K46),INDEX(Сборка!$J$2:$J$501,$K46),"") | G46: =IF(ISNUMBER($K46),INDEX(Сборка!$K$2:$K$501,$K46),"") | H46: =IF(ISNUMBER($K46),ROUND($E46*$F46,2),"") | I46: =IF(ISNUMBER($K46),ROUND($E46*$G46,2),"") | J46: =IF(ISNUMBER($K46),$H46+$I46,"") | K46: =IFERROR(MATCH(26,Сборка!$R$2:$R$501,0),"") | L46: =IFERROR(IF(INDEX(Сборка!$Q$2:$Q$501,MATCH(26+1,Сборка!$R$2:$R$501,0))=1,INDEX(Сборка!$P$2:$P$501,MATCH(26+1,Сборка!$R$2:$R$501,0)),""),"") | M46: =IF(OR(ISNUMBER($K46),$L46<>""),"показать","")
A47: =IF(ISNUMBER($K47),INDEX(Сборка!$O$2:$O$501,$K47),"") | B47: =IF(ISNUMBER($K47),INDEX(Сборка!$C$2:$C$501,$K47),"") | C47: =IF($L47<>"",INDEX(Сборка!$S$2:$S$501,MATCH($L47,Сборка!$P$2:$P$501,0)),IF(ISNUMBER($K47),INDEX(Сборка!$D$2:$D$501,$K47)&IF(INDEX(Сборка!$I$2:$I$501,$K47)<>""," — "&INDEX(Сборка!$I$2:$I$501,$K47),""),"")) | D47: =IF(ISNUMBER($K47),INDEX(Сборка!$E$2:$E$501,$K47),"") | E47: =IF(ISNUMBER($K47),INDEX(Сборка!$G$2:$G$501,$K47),"") | F47: =IF(ISNUMBER($K47),INDEX(Сборка!$J$2:$J$501,$K47),"") | G47: =IF(ISNUMBER($K47),INDEX(Сборка!$K$2:$K$501,$K47),"") | H47: =IF(ISNUMBER($K47),ROUND($E47*$F47,2),"") | I47: =IF(ISNUMBER($K47),ROUND($E47*$G47,2),"") | J47: =IF(ISNUMBER($K47),$H47+$I47,"") | K47: =IFERROR(MATCH(27,Сборка!$R$2:$R$501,0),"") | L47: =IFERROR(IF(INDEX(Сборка!$Q$2:$Q$501,MATCH(27+1,Сборка!$R$2:$R$501,0))=1,INDEX(Сборка!$P$2:$P$501,MATCH(27+1,Сборка!$R$2:$R$501,0)),""),"") | M47: =IF(OR(ISNUMBER($K47),$L47<>""),"показать","")
A48: =IF(ISNUMBER($K48),INDEX(Сборка!$O$2:$O$501,$K48),"") | B48: =IF(ISNUMBER($K48),INDEX(Сборка!$C$2:$C$501,$K48),"") | C48: =IF($L48<>"",INDEX(Сборка!$S$2:$S$501,MATCH($L48,Сборка!$P$2:$P$501,0)),IF(ISNUMBER($K48),INDEX(Сборка!$D$2:$D$501,$K48)&IF(INDEX(Сборка!$I$2:$I$501,$K48)<>""," — "&INDEX(Сборка!$I$2:$I$501,$K48),""),"")) | D48: =IF(ISNUMBER($K48),INDEX(Сборка!$E$2:$E$501,$K48),"") | E48: =IF(ISNUMBER($K48),INDEX(Сборка!$G$2:$G$501,$K48),"") | F48: =IF(ISNUMBER($K48),INDEX(Сборка!$J$2:$J$501,$K48),"") | G48: =IF(ISNUMBER($K48),INDEX(Сборка!$K$2:$K$501,$K48),"") | H48: =IF(ISNUMBER($K48),ROUND($E48*$F48,2),"") | I48: =IF(ISNUMBER($K48),ROUND($E48*$G48,2),"") | J48: =IF(ISNUMBER($K48),$H48+$I48,"") | K48: =IFERROR(MATCH(28,Сборка!$R$2:$R$501,0),"") | L48: =IFERROR(IF(INDEX(Сборка!$Q$2:$Q$501,MATCH(28+1,Сборка!$R$2:$R$501,0))=1,INDEX(Сборка!$P$2:$P$501,MATCH(28+1,Сборка!$R$2:$R$501,0)),""),"") | M48: =IF(OR(ISNUMBER($K48),$L48<>""),"показать","")
A49: =IF(ISNUMBER($K49),INDEX(Сборка!$O$2:$O$501,$K49),"") | B49: =IF(ISNUMBER($K49),INDEX(Сборка!$C$2:$C$501,$K49),"") | C49: =IF($L49<>"",INDEX(Сборка!$S$2:$S$501,MATCH($L49,Сборка!$P$2:$P$501,0)),IF(ISNUMBER($K49),INDEX(Сборка!$D$2:$D$501,$K49)&IF(INDEX(Сборка!$I$2:$I$501,$K49)<>""," — "&INDEX(Сборка!$I$2:$I$501,$K49),""),"")) | D49: =IF(ISNUMBER($K49),INDEX(Сборка!$E$2:$E$501,$K49),"") | E49: =IF(ISNUMBER($K49),INDEX(Сборка!$G$2:$G$501,$K49),"") | F49: =IF(ISNUMBER($K49),INDEX(Сборка!$J$2:$J$501,$K49),"") | G49: =IF(ISNUMBER($K49),INDEX(Сборка!$K$2:$K$501,$K49),"") | H49: =IF(ISNUMBER($K49),ROUND($E49*$F49,2),"") | I49: =IF(ISNUMBER($K49),ROUND($E49*$G49,2),"") | J49: =IF(ISNUMBER($K49),$H49+$I49,"") | K49: =IFERROR(MATCH(29,Сборка!$R$2:$R$501,0),"") | L49: =IFERROR(IF(INDEX(Сборка!$Q$2:$Q$501,MATCH(29+1,Сборка!$R$2:$R$501,0))=1,INDEX(Сборка!$P$2:$P$501,MATCH(29+1,Сборка!$R$2:$R$501,0)),""),"") | M49: =IF(OR(ISNUMBER($K49),$L49<>""),"показать","")
A50: =IF(ISNUMBER($K50),INDEX(Сборка!$O$2:$O$501,$K50),"") | B50: =IF(ISNUMBER($K50),INDEX(Сборка!$C$2:$C$501,$K50),"") | C50: =IF($L50<>"",INDEX(Сборка!$S$2:$S$501,MATCH($L50,Сборка!$P$2:$P$501,0)),IF(ISNUMBER($K50),INDEX(Сборка!$D$2:$D$501,$K50)&IF(INDEX(Сборка!$I$2:$I$501,$K50)<>""," — "&INDEX(Сборка!$I$2:$I$501,$K50),""),"")) | D50: =IF(ISNUMBER($K50),INDEX(Сборка!$E$2:$E$501,$K50),"") | E50: =IF(ISNUMBER($K50),INDEX(Сборка!$G$2:$G$501,$K50),"") | F50: =IF(ISNUMBER($K50),INDEX(Сборка!$J$2:$J$501,$K50),"") | G50: =IF(ISNUMBER($K50),INDEX(Сборка!$K$2:$K$501,$K50),"") | H50: =IF(ISNUMBER($K50),ROUND($E50*$F50,2),"") | I50: =IF(ISNUMBER($K50),ROUND($E50*$G50,2),"") | J50: =IF(ISNUMBER($K50),$H50+$I50,"") | K50: =IFERROR(MATCH(30,Сборка!$R$2:$R$501,0),"") | L50: =IFERROR(IF(INDEX(Сборка!$Q$2:$Q$501,MATCH(30+1,Сборка!$R$2:$R$501,0))=1,INDEX(Сборка!$P$2:$P$501,MATCH(30+1,Сборка!$R$2:$R$501,0)),""),"") | M50: =IF(OR(ISNUMBER($K50),$L50<>""),"показать","")
A51: =IF(ISNUMBER($K51),INDEX(Сборка!$O$2:$O$501,$K51),"") | B51: =IF(ISNUMBER($K51),INDEX(Сборка!$C$2:$C$501,$K51),"") | C51: =IF($L51<>"",INDEX(Сборка!$S$2:$S$501,MATCH($L51,Сборка!$P$2:$P$501,0)),IF(ISNUMBER($K51),INDEX(Сборка!$D$2:$D$501,$K51)&IF(INDEX(Сборка!$I$2:$I$501,$K51)<>""," — "&INDEX(Сборка!$I$2:$I$501,$K51),""),"")) | D51: =IF(ISNUMBER($K51),INDEX(Сборка!$E$2:$E$501,$K51),"") | E51: =IF(ISNUMBER($K51),INDEX(Сборка!$G$2:$G$501,$K51),"") | F51: =IF(ISNUMBER($K51),INDEX(Сборка!$J$2:$J$501,$K51),"") | G51: =IF(ISNUMBER($K51),INDEX(Сборка!$K$2:$K$501,$K51),"") | H51: =IF(ISNUMBER($K51),ROUND($E51*$F51,2),"") | I51: =IF(ISNUMBER($K51),ROUND($E51*$G51,2),"") | J51: =IF(ISNUMBER($K51),$H51+$I51,"") | K51: =IFERROR(MATCH(31,Сборка!$R$2:$R$501,0),"") | L51: =IFERROR(IF(INDEX(Сборка!$Q$2:$Q$501,MATCH(31+1,Сборка!$R$2:$R$501,0))=1,INDEX(Сборка!$P$2:$P$501,MATCH(31+1,Сборка!$R$2:$R$501,0)),""),"") | M51: =IF(OR(ISNUMBER($K51),$L51<>""),"показать","")
A52: =IF(ISNUMBER($K52),INDEX(Сборка!$O$2:$O$501,$K52),"") | B52: =IF(ISNUMBER($K52),INDEX(Сборка!$C$2:$C$501,$K52),"") | C52: =IF($L52<>"",INDEX(Сборка!$S$2:$S$501,MATCH($L52,Сборка!$P$2:$P$501,0)),IF(ISNUMBER($K52),INDEX(Сборка!$D$2:$D$501,$K52)&IF(INDEX(Сборка!$I$2:$I$501,$K52)<>""," — "&INDEX(Сборка!$I$2:$I$501,$K52),""),"")) | D52: =IF(ISNUMBER($K52),INDEX(Сборка!$E$2:$E$501,$K52),"") | E52: =IF(ISNUMBER($K52),INDEX(Сборка!$G$2:$G$501,$K52),"") | F52: =IF(ISNUMBER($K52),INDEX(Сборка!$J$2:$J$501,$K52),"") | G52: =IF(ISNUMBER($K52),INDEX(Сборка!$K$2:$K$501,$K52),"") | H52: =IF(ISNUMBER($K52),ROUND($E52*$F52,2),"") | I52: =IF(ISNUMBER($K52),ROUND($E52*$G52,2),"") | J52: =IF(ISNUMBER($K52),$H52+$I52,"") | K52: =IFERROR(MATCH(32,Сборка!$R$2:$R$501,0),"") | L52: =IFERROR(IF(INDEX(Сборка!$Q$2:$Q$501,MATCH(32+1,Сборка!$R$2:$R$501,0))=1,INDEX(Сборка!$P$2:$P$501,MATCH(32+1,Сборка!$R$2:$R$501,0)),""),"") | M52: =IF(OR(ISNUMBER($K52),$L52<>""),"показать","")
A53: =IF(ISNUMBER($K53),INDEX(Сборка!$O$2:$O$501,$K53),"") | B53: =IF(ISNUMBER($K53),INDEX(Сборка!$C$2:$C$501,$K53),"") | C53: =IF($L53<>"",INDEX(Сборка!$S$2:$S$501,MATCH($L53,Сборка!$P$2:$P$501,0)),IF(ISNUMBER($K53),INDEX(Сборка!$D$2:$D$501,$K53)&IF(INDEX(Сборка!$I$2:$I$501,$K53)<>""," — "&INDEX(Сборка!$I$2:$I$501,$K53),""),"")) | D53: =IF(ISNUMBER($K53),INDEX(Сборка!$E$2:$E$501,$K53),"") | E53: =IF(ISNUMBER($K53),INDEX(Сборка!$G$2:$G$501,$K53),"") | F53: =IF(ISNUMBER($K53),INDEX(Сборка!$J$2:$J$501,$K53),"") | G53: =IF(ISNUMBER($K53),INDEX(Сборка!$K$2:$K$501,$K53),"") | H53: =IF(ISNUMBER($K53),ROUND($E53*$F53,2),"") | I53: =IF(ISNUMBER($K53),ROUND($E53*$G53,2),"") | J53: =IF(ISNUMBER($K53),$H53+$I53,"") | K53: =IFERROR(MATCH(33,Сборка!$R$2:$R$501,0),"") | L53: =IFERROR(IF(INDEX(Сборка!$Q$2:$Q$501,MATCH(33+1,Сборка!$R$2:$R$501,0))=1,INDEX(Сборка!$P$2:$P$501,MATCH(33+1,Сборка!$R$2:$R$501,0)),""),"") | M53: =IF(OR(ISNUMBER($K53),$L53<>""),"показать","")
A54: =IF(ISNUMBER($K54),INDEX(Сборка!$O$2:$O$501,$K54),"") | B54: =IF(ISNUMBER($K54),INDEX(Сборка!$C$2:$C$501,$K54),"") | C54: =IF($L54<>"",INDEX(Сборка!$S$2:$S$501,MATCH($L54,Сборка!$P$2:$P$501,0)),IF(ISNUMBER($K54),INDEX(Сборка!$D$2:$D$501,$K54)&IF(INDEX(Сборка!$I$2:$I$501,$K54)<>""," — "&INDEX(Сборка!$I$2:$I$501,$K54),""),"")) | D54: =IF(ISNUMBER($K54),INDEX(Сборка!$E$2:$E$501,$K54),"") | E54: =IF(ISNUMBER($K54),INDEX(Сборка!$G$2:$G$501,$K54),"") | F54: =IF(ISNUMBER($K54),INDEX(Сборка!$J$2:$J$501,$K54),"") | G54: =IF(ISNUMBER($K54),INDEX(Сборка!$K$2:$K$501,$K54),"") | H54: =IF(ISNUMBER($K54),ROUND($E54*$F54,2),"") | I54: =IF(ISNUMBER($K54),ROUND($E54*$G54,2),"") | J54: =IF(ISNUMBER($K54),$H54+$I54,"") | K54: =IFERROR(MATCH(34,Сборка!$R$2:$R$501,0),"") | L54: =IFERROR(IF(INDEX(Сборка!$Q$2:$Q$501,MATCH(34+1,Сборка!$R$2:$R$501,0))=1,INDEX(Сборка!$P$2:$P$501,MATCH(34+1,Сборка!$R$2:$R$501,0)),""),"") | M54: =IF(OR(ISNUMBER($K54),$L54<>""),"показать","")
A55: =IF(ISNUMBER($K55),INDEX(Сборка!$O$2:$O$501,$K55),"") | B55: =IF(ISNUMBER($K55),INDEX(Сборка!$C$2:$C$501,$K55),"") | C55: =IF($L55<>"",INDEX(Сборка!$S$2:$S$501,MATCH($L55,Сборка!$P$2:$P$501,0)),IF(ISNUMBER($K55),INDEX(Сборка!$D$2:$D$501,$K55)&IF(INDEX(Сборка!$I$2:$I$501,$K55)<>""," — "&INDEX(Сборка!$I$2:$I$501,$K55),""),"")) | D55: =IF(ISNUMBER($K55),INDEX(Сборка!$E$2:$E$501,$K55),"") | E55: =IF(ISNUMBER($K55),INDEX(Сборка!$G$2:$G$501,$K55),"") | F55: =IF(ISNUMBER($K55),INDEX(Сборка!$J$2:$J$501,$K55),"") | G55: =IF(ISNUMBER($K55),INDEX(Сборка!$K$2:$K$501,$K55),"") | H55: =IF(ISNUMBER($K55),ROUND($E55*$F55,2),"") | I55: =IF(ISNUMBER($K55),ROUND($E55*$G55,2),"") | J55: =IF(ISNUMBER($K55),$H55+$I55,"") | K55: =IFERROR(MATCH(35,Сборка!$R$2:$R$501,0),"") | L55: =IFERROR(IF(INDEX(Сборка!$Q$2:$Q$501,MATCH(35+1,Сборка!$R$2:$R$501,0))=1,INDEX(Сборка!$P$2:$P$501,MATCH(35+1,Сборка!$R$2:$R$501,0)),""),"") | M55: =IF(OR(ISNUMBER($K55),$L55<>""),"показать","")
A56: =IF(ISNUMBER($K56),INDEX(Сборка!$O$2:$O$501,$K56),"") | B56: =IF(ISNUMBER($K56),INDEX(Сборка!$C$2:$C$501,$K56),"") | C56: =IF($L56<>"",INDEX(Сборка!$S$2:$S$501,MATCH($L56,Сборка!$P$2:$P$501,0)),IF(ISNUMBER($K56),INDEX(Сборка!$D$2:$D$501,$K56)&IF(INDEX(Сборка!$I$2:$I$501,$K56)<>""," — "&INDEX(Сборка!$I$2:$I$501,$K56),""),"")) | D56: =IF(ISNUMBER($K56),INDEX(Сборка!$E$2:$E$501,$K56),"") | E56: =IF(ISNUMBER($K56),INDEX(Сборка!$G$2:$G$501,$K56),"") | F56: =IF(ISNUMBER($K56),INDEX(Сборка!$J$2:$J$501,$K56),"") | G56: =IF(ISNUMBER($K56),INDEX(Сборка!$K$2:$K$501,$K56),"") | H56: =IF(ISNUMBER($K56),ROUND($E56*$F56,2),"") | I56: =IF(ISNUMBER($K56),ROUND($E56*$G56,2),"") | J56: =IF(ISNUMBER($K56),$H56+$I56,"") | K56: =IFERROR(MATCH(36,Сборка!$R$2:$R$501,0),"") | L56: =IFERROR(IF(INDEX(Сборка!$Q$2:$Q$501,MATCH(36+1,Сборка!$R$2:$R$501,0))=1,INDEX(Сборка!$P$2:$P$501,MATCH(36+1,Сборка!$R$2:$R$501,0)),""),"") | M56: =IF(OR(ISNUMBER($K56),$L56<>""),"показать","")
A57: =IF(ISNUMBER($K57),INDEX(Сборка!$O$2:$O$501,$K57),"") | B57: =IF(ISNUMBER($K57),INDEX(Сборка!$C$2:$C$501,$K57),"") | C57: =IF($L57<>"",INDEX(Сборка!$S$2:$S$501,MATCH($L57,Сборка!$P$2:$P$501,0)),IF(ISNUMBER($K57),INDEX(Сборка!$D$2:$D$501,$K57)&IF(INDEX(Сборка!$I$2:$I$501,$K57)<>""," — "&INDEX(Сборка!$I$2:$I$501,$K57),""),"")) | D57: =IF(ISNUMBER($K57),INDEX(Сборка!$E$2:$E$501,$K57),"") | E57: =IF(ISNUMBER($K57),INDEX(Сборка!$G$2:$G$501,$K57),"") | F57: =IF(ISNUMBER($K57),INDEX(Сборка!$J$2:$J$501,$K57),"") | G57: =IF(ISNUMBER($K57),INDEX(Сборка!$K$2:$K$501,$K57),"") | H57: =IF(ISNUMBER($K57),ROUND($E57*$F57,2),"") | I57: =IF(ISNUMBER($K57),ROUND($E57*$G57,2),"") | J57: =IF(ISNUMBER($K57),$H57+$I57,"") | K57: =IFERROR(MATCH(37,Сборка!$R$2:$R$501,0),"") | L57: =IFERROR(IF(INDEX(Сборка!$Q$2:$Q$501,MATCH(37+1,Сборка!$R$2:$R$501,0))=1,INDEX(Сборка!$P$2:$P$501,MATCH(37+1,Сборка!$R$2:$R$501,0)),""),"") | M57: =IF(OR(ISNUMBER($K57),$L57<>""),"показать","")
A58: =IF(ISNUMBER($K58),INDEX(Сборка!$O$2:$O$501,$K58),"") | B58: =IF(ISNUMBER($K58),INDEX(Сборка!$C$2:$C$501,$K58),"") | C58: =IF($L58<>"",INDEX(Сборка!$S$2:$S$501,MATCH($L58,Сборка!$P$2:$P$501,0)),IF(ISNUMBER($K58),INDEX(Сборка!$D$2:$D$501,$K58)&IF(INDEX(Сборка!$I$2:$I$501,$K58)<>""," — "&INDEX(Сборка!$I$2:$I$501,$K58),""),"")) | D58: =IF(ISNUMBER($K58),INDEX(Сборка!$E$2:$E$501,$K58),"") | E58: =IF(ISNUMBER($K58),INDEX(Сборка!$G$2:$G$501,$K58),"") | F58: =IF(ISNUMBER($K58),INDEX(Сборка!$J$2:$J$501,$K58),"") | G58: =IF(ISNUMBER($K58),INDEX(Сборка!$K$2:$K$501,$K58),"") | H58: =IF(ISNUMBER($K58),ROUND($E58*$F58,2),"") | I58: =IF(ISNUMBER($K58),ROUND($E58*$G58,2),"") | J58: =IF(ISNUMBER($K58),$H58+$I58,"") | K58: =IFERROR(MATCH(38,Сборка!$R$2:$R$501,0),"") | L58: =IFERROR(IF(INDEX(Сборка!$Q$2:$Q$501,MATCH(38+1,Сборка!$R$2:$R$501,0))=1,INDEX(Сборка!$P$2:$P$501,MATCH(38+1,Сборка!$R$2:$R$501,0)),""),"") | M58: =IF(OR(ISNUMBER($K58),$L58<>""),"показать","")
A59: =IF(ISNUMBER($K59),INDEX(Сборка!$O$2:$O$501,$K59),"") | B59: =IF(ISNUMBER($K59),INDEX(Сборка!$C$2:$C$501,$K59),"") | C59: =IF($L59<>"",INDEX(Сборка!$S$2:$S$501,MATCH($L59,Сборка!$P$2:$P$501,0)),IF(ISNUMBER($K59),INDEX(Сборка!$D$2:$D$501,$K59)&IF(INDEX(Сборка!$I$2:$I$501,$K59)<>""," — "&INDEX(Сборка!$I$2:$I$501,$K59),""),"")) | D59: =IF(ISNUMBER($K59),INDEX(Сборка!$E$2:$E$501,$K59),"") | E59: =IF(ISNUMBER($K59),INDEX(Сборка!$G$2:$G$501,$K59),"") | F59: =IF(ISNUMBER($K59),INDEX(Сборка!$J$2:$J$501,$K59),"") | G59: =IF(ISNUMBER($K59),INDEX(Сборка!$K$2:$K$501,$K59),"") | H59: =IF(ISNUMBER($K59),ROUND($E59*$F59,2),"") | I59: =IF(ISNUMBER($K59),ROUND($E59*$G59,2),"") | J59: =IF(ISNUMBER($K59),$H59+$I59,"") | K59: =IFERROR(MATCH(39,Сборка!$R$2:$R$501,0),"") | L59: =IFERROR(IF(INDEX(Сборка!$Q$2:$Q$501,MATCH(39+1,Сборка!$R$2:$R$501,0))=1,INDEX(Сборка!$P$2:$P$501,MATCH(39+1,Сборка!$R$2:$R$501,0)),""),"") | M59: =IF(OR(ISNUMBER($K59),$L59<>""),"показать","")
A60: =IF(ISNUMBER($K60),INDEX(Сборка!$O$2:$O$501,$K60),"") | B60: =IF(ISNUMBER($K60),INDEX(Сборка!$C$2:$C$501,$K60),"") | C60: =IF($L60<>"",INDEX(Сборка!$S$2:$S$501,MATCH($L60,Сборка!$P$2:$P$501,0)),IF(ISNUMBER($K60),INDEX(Сборка!$D$2:$D$501,$K60)&IF(INDEX(Сборка!$I$2:$I$501,$K60)<>""," — "&INDEX(Сборка!$I$2:$I$501,$K60),""),"")) | D60: =IF(ISNUMBER($K60),INDEX(Сборка!$E$2:$E$501,$K60),"") | E60: =IF(ISNUMBER($K60),INDEX(Сборка!$G$2:$G$501,$K60),"") | F60: =IF(ISNUMBER($K60),INDEX(Сборка!$J$2:$J$501,$K60),"") | G60: =IF(ISNUMBER($K60),INDEX(Сборка!$K$2:$K$501,$K60),"") | H60: =IF(ISNUMBER($K60),ROUND($E60*$F60,2),"") | I60: =IF(ISNUMBER($K60),ROUND($E60*$G60,2),"") | J60: =IF(ISNUMBER($K60),$H60+$I60,"") | K60: =IFERROR(MATCH(40,Сборка!$R$2:$R$501,0),"") | L60: =IFERROR(IF(INDEX(Сборка!$Q$2:$Q$501,MATCH(40+1,Сборка!$R$2:$R$501,0))=1,INDEX(Сборка!$P$2:$P$501,MATCH(40+1,Сборка!$R$2:$R$501,0)),""),"") | M60: =IF(OR(ISNUMBER($K60),$L60<>""),"показать","")
A61: =IF(ISNUMBER($K61),INDEX(Сборка!$O$2:$O$501,$K61),"") | B61: =IF(ISNUMBER($K61),INDEX(Сборка!$C$2:$C$501,$K61),"") | C61: =IF($L61<>"",INDEX(Сборка!$S$2:$S$501,MATCH($L61,Сборка!$P$2:$P$501,0)),IF(ISNUMBER($K61),INDEX(Сборка!$D$2:$D$501,$K61)&IF(INDEX(Сборка!$I$2:$I$501,$K61)<>""," — "&INDEX(Сборка!$I$2:$I$501,$K61),""),"")) | D61: =IF(ISNUMBER($K61),INDEX(Сборка!$E$2:$E$501,$K61),"") | E61: =IF(ISNUMBER($K61),INDEX(Сборка!$G$2:$G$501,$K61),"") | F61: =IF(ISNUMBER($K61),INDEX(Сборка!$J$2:$J$501,$K61),"") | G61: =IF(ISNUMBER($K61),INDEX(Сборка!$K$2:$K$501,$K61),"") | H61: =IF(ISNUMBER($K61),ROUND($E61*$F61,2),"") | I61: =IF(ISNUMBER($K61),ROUND($E61*$G61,2),"") | J61: =IF(ISNUMBER($K61),$H61+$I61,"") | K61: =IFERROR(MATCH(41,Сборка!$R$2:$R$501,0),"") | L61: =IFERROR(IF(INDEX(Сборка!$Q$2:$Q$501,MATCH(41+1,Сборка!$R$2:$R$501,0))=1,INDEX(Сборка!$P$2:$P$501,MATCH(41+1,Сборка!$R$2:$R$501,0)),""),"") | M61: =IF(OR(ISNUMBER($K61),$L61<>""),"показать","")
A62: =IF(ISNUMBER($K62),INDEX(Сборка!$O$2:$O$501,$K62),"") | B62: =IF(ISNUMBER($K62),INDEX(Сборка!$C$2:$C$501,$K62),"") | C62: =IF($L62<>"",INDEX(Сборка!$S$2:$S$501,MATCH($L62,Сборка!$P$2:$P$501,0)),IF(ISNUMBER($K62),INDEX(Сборка!$D$2:$D$501,$K62)&IF(INDEX(Сборка!$I$2:$I$501,$K62)<>""," — "&INDEX(Сборка!$I$2:$I$501,$K62),""),"")) | D62: =IF(ISNUMBER($K62),INDEX(Сборка!$E$2:$E$501,$K62),"") | E62: =IF(ISNUMBER($K62),INDEX(Сборка!$G$2:$G$501,$K62),"") | F62: =IF(ISNUMBER($K62),INDEX(Сборка!$J$2:$J$501,$K62),"") | G62: =IF(ISNUMBER($K62),INDEX(Сборка!$K$2:$K$501,$K62),"") | H62: =IF(ISNUMBER($K62),ROUND($E62*$F62,2),"") | I62: =IF(ISNUMBER($K62),ROUND($E62*$G62,2),"") | J62: =IF(ISNUMBER($K62),$H62+$I62,"") | K62: =IFERROR(MATCH(42,Сборка!$R$2:$R$501,0),"") | L62: =IFERROR(IF(INDEX(Сборка!$Q$2:$Q$501,MATCH(42+1,Сборка!$R$2:$R$501,0))=1,INDEX(Сборка!$P$2:$P$501,MATCH(42+1,Сборка!$R$2:$R$501,0)),""),"") | M62: =IF(OR(ISNUMBER($K62),$L62<>""),"показать","")
A63: =IF(ISNUMBER($K63),INDEX(Сборка!$O$2:$O$501,$K63),"") | B63: =IF(ISNUMBER($K63),INDEX(Сборка!$C$2:$C$501,$K63),"") | C63: =IF($L63<>"",INDEX(Сборка!$S$2:$S$501,MATCH($L63,Сборка!$P$2:$P$501,0)),IF(ISNUMBER($K63),INDEX(Сборка!$D$2:$D$501,$K63)&IF(INDEX(Сборка!$I$2:$I$501,$K63)<>""," — "&INDEX(Сборка!$I$2:$I$501,$K63),""),"")) | D63: =IF(ISNUMBER($K63),INDEX(Сборка!$E$2:$E$501,$K63),"") | E63: =IF(ISNUMBER($K63),INDEX(Сборка!$G$2:$G$501,$K63),"") | F63: =IF(ISNUMBER($K63),INDEX(Сборка!$J$2:$J$501,$K63),"") | G63: =IF(ISNUMBER($K63),INDEX(Сборка!$K$2:$K$501,$K63),"") | H63: =IF(ISNUMBER($K63),ROUND($E63*$F63,2),"") | I63: =IF(ISNUMBER($K63),ROUND($E63*$G63,2),"") | J63: =IF(ISNUMBER($K63),$H63+$I63,"") | K63: =IFERROR(MATCH(43,Сборка!$R$2:$R$501,0),"") | L63: =IFERROR(IF(INDEX(Сборка!$Q$2:$Q$501,MATCH(43+1,Сборка!$R$2:$R$501,0))=1,INDEX(Сборка!$P$2:$P$501,MATCH(43+1,Сборка!$R$2:$R$501,0)),""),"") | M63: =IF(OR(ISNUMBER($K63),$L63<>""),"показать","")
A64: =IF(ISNUMBER($K64),INDEX(Сборка!$O$2:$O$501,$K64),"") | B64: =IF(ISNUMBER($K64),INDEX(Сборка!$C$2:$C$501,$K64),"") | C64: =IF($L64<>"",INDEX(Сборка!$S$2:$S$501,MATCH($L64,Сборка!$P$2:$P$501,0)),IF(ISNUMBER($K64),INDEX(Сборка!$D$2:$D$501,$K64)&IF(INDEX(Сборка!$I$2:$I$501,$K64)<>""," — "&INDEX(Сборка!$I$2:$I$501,$K64),""),"")) | D64: =IF(ISNUMBER($K64),INDEX(Сборка!$E$2:$E$501,$K64),"") | E64: =IF(ISNUMBER($K64),INDEX(Сборка!$G$2:$G$501,$K64),"") | F64: =IF(ISNUMBER($K64),INDEX(Сборка!$J$2:$J$501,$K64),"") | G64: =IF(ISNUMBER($K64),INDEX(Сборка!$K$2:$K$501,$K64),"") | H64: =IF(ISNUMBER($K64),ROUND($E64*$F64,2),"") | I64: =IF(ISNUMBER($K64),ROUND($E64*$G64,2),"") | J64: =IF(ISNUMBER($K64),$H64+$I64,"") | K64: =IFERROR(MATCH(44,Сборка!$R$2:$R$501,0),"") | L64: =IFERROR(IF(INDEX(Сборка!$Q$2:$Q$501,MATCH(44+1,Сборка!$R$2:$R$501,0))=1,INDEX(Сборка!$P$2:$P$501,MATCH(44+1,Сборка!$R$2:$R$501,0)),""),"") | M64: =IF(OR(ISNUMBER($K64),$L64<>""),"показать","")
A65: =IF(ISNUMBER($K65),INDEX(Сборка!$O$2:$O$501,$K65),"") | B65: =IF(ISNUMBER($K65),INDEX(Сборка!$C$2:$C$501,$K65),"") | C65: =IF($L65<>"",INDEX(Сборка!$S$2:$S$501,MATCH($L65,Сборка!$P$2:$P$501,0)),IF(ISNUMBER($K65),INDEX(Сборка!$D$2:$D$501,$K65)&IF(INDEX(Сборка!$I$2:$I$501,$K65)<>""," — "&INDEX(Сборка!$I$2:$I$501,$K65),""),"")) | D65: =IF(ISNUMBER($K65),INDEX(Сборка!$E$2:$E$501,$K65),"") | E65: =IF(ISNUMBER($K65),INDEX(Сборка!$G$2:$G$501,$K65),"") | F65: =IF(ISNUMBER($K65),INDEX(Сборка!$J$2:$J$501,$K65),"") | G65: =IF(ISNUMBER($K65),INDEX(Сборка!$K$2:$K$501,$K65),"") | H65: =IF(ISNUMBER($K65),ROUND($E65*$F65,2),"") | I65: =IF(ISNUMBER($K65),ROUND($E65*$G65,2),"") | J65: =IF(ISNUMBER($K65),$H65+$I65,"") | K65: =IFERROR(MATCH(45,Сборка!$R$2:$R$501,0),"") | L65: =IFERROR(IF(INDEX(Сборка!$Q$2:$Q$501,MATCH(45+1,Сборка!$R$2:$R$501,0))=1,INDEX(Сборка!$P$2:$P$501,MATCH(45+1,Сборка!$R$2:$R$501,0)),""),"") | M65: =IF(OR(ISNUMBER($K65),$L65<>""),"показать","")
A66: =IF(ISNUMBER($K66),INDEX(Сборка!$O$2:$O$501,$K66),"") | B66: =IF(ISNUMBER($K66),INDEX(Сборка!$C$2:$C$501,$K66),"") | C66: =IF($L66<>"",INDEX(Сборка!$S$2:$S$501,MATCH($L66,Сборка!$P$2:$P$501,0)),IF(ISNUMBER($K66),INDEX(Сборка!$D$2:$D$501,$K66)&IF(INDEX(Сборка!$I$2:$I$501,$K66)<>""," — "&INDEX(Сборка!$I$2:$I$501,$K66),""),"")) | D66: =IF(ISNUMBER($K66),INDEX(Сборка!$E$2:$E$501,$K66),"") | E66: =IF(ISNUMBER($K66),INDEX(Сборка!$G$2:$G$501,$K66),"") | F66: =IF(ISNUMBER($K66),INDEX(Сборка!$J$2:$J$501,$K66),"") | G66: =IF(ISNUMBER($K66),INDEX(Сборка!$K$2:$K$501,$K66),"") | H66: =IF(ISNUMBER($K66),ROUND($E66*$F66,2),"") | I66: =IF(ISNUMBER($K66),ROUND($E66*$G66,2),"") | J66: =IF(ISNUMBER($K66),$H66+$I66,"") | K66: =IFERROR(MATCH(46,Сборка!$R$2:$R$501,0),"") | L66: =IFERROR(IF(INDEX(Сборка!$Q$2:$Q$501,MATCH(46+1,Сборка!$R$2:$R$501,0))=1,INDEX(Сборка!$P$2:$P$501,MATCH(46+1,Сборка!$R$2:$R$501,0)),""),"") | M66: =IF(OR(ISNUMBER($K66),$L66<>""),"показать","")
A67: =IF(ISNUMBER($K67),INDEX(Сборка!$O$2:$O$501,$K67),"") | B67: =IF(ISNUMBER($K67),INDEX(Сборка!$C$2:$C$501,$K67),"") | C67: =IF($L67<>"",INDEX(Сборка!$S$2:$S$501,MATCH($L67,Сборка!$P$2:$P$501,0)),IF(ISNUMBER($K67),INDEX(Сборка!$D$2:$D$501,$K67)&IF(INDEX(Сборка!$I$2:$I$501,$K67)<>""," — "&INDEX(Сборка!$I$2:$I$501,$K67),""),"")) | D67: =IF(ISNUMBER($K67),INDEX(Сборка!$E$2:$E$501,$K67),"") | E67: =IF(ISNUMBER($K67),INDEX(Сборка!$G$2:$G$501,$K67),"") | F67: =IF(ISNUMBER($K67),INDEX(Сборка!$J$2:$J$501,$K67),"") | G67: =IF(ISNUMBER($K67),INDEX(Сборка!$K$2:$K$501,$K67),"") | H67: =IF(ISNUMBER($K67),ROUND($E67*$F67,2),"") | I67: =IF(ISNUMBER($K67),ROUND($E67*$G67,2),"") | J67: =IF(ISNUMBER($K67),$H67+$I67,"") | K67: =IFERROR(MATCH(47,Сборка!$R$2:$R$501,0),"") | L67: =IFERROR(IF(INDEX(Сборка!$Q$2:$Q$501,MATCH(47+1,Сборка!$R$2:$R$501,0))=1,INDEX(Сборка!$P$2:$P$501,MATCH(47+1,Сборка!$R$2:$R$501,0)),""),"") | M67: =IF(OR(ISNUMBER($K67),$L67<>""),"показать","")
A68: =IF(ISNUMBER($K68),INDEX(Сборка!$O$2:$O$501,$K68),"") | B68: =IF(ISNUMBER($K68),INDEX(Сборка!$C$2:$C$501,$K68),"") | C68: =IF($L68<>"",INDEX(Сборка!$S$2:$S$501,MATCH($L68,Сборка!$P$2:$P$501,0)),IF(ISNUMBER($K68),INDEX(Сборка!$D$2:$D$501,$K68)&IF(INDEX(Сборка!$I$2:$I$501,$K68)<>""," — "&INDEX(Сборка!$I$2:$I$501,$K68),""),"")) | D68: =IF(ISNUMBER($K68),INDEX(Сборка!$E$2:$E$501,$K68),"") | E68: =IF(ISNUMBER($K68),INDEX(Сборка!$G$2:$G$501,$K68),"") | F68: =IF(ISNUMBER($K68),INDEX(Сборка!$J$2:$J$501,$K68),"") | G68: =IF(ISNUMBER($K68),INDEX(Сборка!$K$2:$K$501,$K68),"") | H68: =IF(ISNUMBER($K68),ROUND($E68*$F68,2),"") | I68: =IF(ISNUMBER($K68),ROUND($E68*$G68,2),"") | J68: =IF(ISNUMBER($K68),$H68+$I68,"") | K68: =IFERROR(MATCH(48,Сборка!$R$2:$R$501,0),"") | L68: =IFERROR(IF(INDEX(Сборка!$Q$2:$Q$501,MATCH(48+1,Сборка!$R$2:$R$501,0))=1,INDEX(Сборка!$P$2:$P$501,MATCH(48+1,Сборка!$R$2:$R$501,0)),""),"") | M68: =IF(OR(ISNUMBER($K68),$L68<>""),"показать","")
A69: =IF(ISNUMBER($K69),INDEX(Сборка!$O$2:$O$501,$K69),"") | B69: =IF(ISNUMBER($K69),INDEX(Сборка!$C$2:$C$501,$K69),"") | C69: =IF($L69<>"",INDEX(Сборка!$S$2:$S$501,MATCH($L69,Сборка!$P$2:$P$501,0)),IF(ISNUMBER($K69),INDEX(Сборка!$D$2:$D$501,$K69)&IF(INDEX(Сборка!$I$2:$I$501,$K69)<>""," — "&INDEX(Сборка!$I$2:$I$501,$K69),""),"")) | D69: =IF(ISNUMBER($K69),INDEX(Сборка!$E$2:$E$501,$K69),"") | E69: =IF(ISNUMBER($K69),INDEX(Сборка!$G$2:$G$501,$K69),"") | F69: =IF(ISNUMBER($K69),INDEX(Сборка!$J$2:$J$501,$K69),"") | G69: =IF(ISNUMBER($K69),INDEX(Сборка!$K$2:$K$501,$K69),"") | H69: =IF(ISNUMBER($K69),ROUND($E69*$F69,2),"") | I69: =IF(ISNUMBER($K69),ROUND($E69*$G69,2),"") | J69: =IF(ISNUMBER($K69),$H69+$I69,"") | K69: =IFERROR(MATCH(49,Сборка!$R$2:$R$501,0),"") | L69: =IFERROR(IF(INDEX(Сборка!$Q$2:$Q$501,MATCH(49+1,Сборка!$R$2:$R$501,0))=1,INDEX(Сборка!$P$2:$P$501,MATCH(49+1,Сборка!$R$2:$R$501,0)),""),"") | M69: =IF(OR(ISNUMBER($K69),$L69<>""),"показать","")
A70: =IF(ISNUMBER($K70),INDEX(Сборка!$O$2:$O$501,$K70),"") | B70: =IF(ISNUMBER($K70),INDEX(Сборка!$C$2:$C$501,$K70),"") | C70: =IF($L70<>"",INDEX(Сборка!$S$2:$S$501,MATCH($L70,Сборка!$P$2:$P$501,0)),IF(ISNUMBER($K70),INDEX(Сборка!$D$2:$D$501,$K70)&IF(INDEX(Сборка!$I$2:$I$501,$K70)<>""," — "&INDEX(Сборка!$I$2:$I$501,$K70),""),"")) | D70: =IF(ISNUMBER($K70),INDEX(Сборка!$E$2:$E$501,$K70),"") | E70: =IF(ISNUMBER($K70),INDEX(Сборка!$G$2:$G$501,$K70),"") | F70: =IF(ISNUMBER($K70),INDEX(Сборка!$J$2:$J$501,$K70),"") | G70: =IF(ISNUMBER($K70),INDEX(Сборка!$K$2:$K$501,$K70),"") | H70: =IF(ISNUMBER($K70),ROUND($E70*$F70,2),"") | I70: =IF(ISNUMBER($K70),ROUND($E70*$G70,2),"") | J70: =IF(ISNUMBER($K70),$H70+$I70,"") | K70: =IFERROR(MATCH(50,Сборка!$R$2:$R$501,0),"") | L70: =IFERROR(IF(INDEX(Сборка!$Q$2:$Q$501,MATCH(50+1,Сборка!$R$2:$R$501,0))=1,INDEX(Сборка!$P$2:$P$501,MATCH(50+1,Сборка!$R$2:$R$501,0)),""),"") | M70: =IF(OR(ISNUMBER($K70),$L70<>""),"показать","")
A71: =IF(ISNUMBER($K71),INDEX(Сборка!$O$2:$O$501,$K71),"") | B71: =IF(ISNUMBER($K71),INDEX(Сборка!$C$2:$C$501,$K71),"") | C71: =IF($L71<>"",INDEX(Сборка!$S$2:$S$501,MATCH($L71,Сборка!$P$2:$P$501,0)),IF(ISNUMBER($K71),INDEX(Сборка!$D$2:$D$501,$K71)&IF(INDEX(Сборка!$I$2:$I$501,$K71)<>""," — "&INDEX(Сборка!$I$2:$I$501,$K71),""),"")) | D71: =IF(ISNUMBER($K71),INDEX(Сборка!$E$2:$E$501,$K71),"") | E71: =IF(ISNUMBER($K71),INDEX(Сборка!$G$2:$G$501,$K71),"") | F71: =IF(ISNUMBER($K71),INDEX(Сборка!$J$2:$J$501,$K71),"") | G71: =IF(ISNUMBER($K71),INDEX(Сборка!$K$2:$K$501,$K71),"") | H71: =IF(ISNUMBER($K71),ROUND($E71*$F71,2),"") | I71: =IF(ISNUMBER($K71),ROUND($E71*$G71,2),"") | J71: =IF(ISNUMBER($K71),$H71+$I71,"") | K71: =IFERROR(MATCH(51,Сборка!$R$2:$R$501,0),"") | L71: =IFERROR(IF(INDEX(Сборка!$Q$2:$Q$501,MATCH(51+1,Сборка!$R$2:$R$501,0))=1,INDEX(Сборка!$P$2:$P$501,MATCH(51+1,Сборка!$R$2:$R$501,0)),""),"") | M71: =IF(OR(ISNUMBER($K71),$L71<>""),"показать","")
A72: =IF(ISNUMBER($K72),INDEX(Сборка!$O$2:$O$501,$K72),"") | B72: =IF(ISNUMBER($K72),INDEX(Сборка!$C$2:$C$501,$K72),"") | C72: =IF($L72<>"",INDEX(Сборка!$S$2:$S$501,MATCH($L72,Сборка!$P$2:$P$501,0)),IF(ISNUMBER($K72),INDEX(Сборка!$D$2:$D$501,$K72)&IF(INDEX(Сборка!$I$2:$I$501,$K72)<>""," — "&INDEX(Сборка!$I$2:$I$501,$K72),""),"")) | D72: =IF(ISNUMBER($K72),INDEX(Сборка!$E$2:$E$501,$K72),"") | E72: =IF(ISNUMBER($K72),INDEX(Сборка!$G$2:$G$501,$K72),"") | F72: =IF(ISNUMBER($K72),INDEX(Сборка!$J$2:$J$501,$K72),"") | G72: =IF(ISNUMBER($K72),INDEX(Сборка!$K$2:$K$501,$K72),"") | H72: =IF(ISNUMBER($K72),ROUND($E72*$F72,2),"") | I72: =IF(ISNUMBER($K72),ROUND($E72*$G72,2),"") | J72: =IF(ISNUMBER($K72),$H72+$I72,"") | K72: =IFERROR(MATCH(52,Сборка!$R$2:$R$501,0),"") | L72: =IFERROR(IF(INDEX(Сборка!$Q$2:$Q$501,MATCH(52+1,Сборка!$R$2:$R$501,0))=1,INDEX(Сборка!$P$2:$P$501,MATCH(52+1,Сборка!$R$2:$R$501,0)),""),"") | M72: =IF(OR(ISNUMBER($K72),$L72<>""),"показать","")
A73: =IF(ISNUMBER($K73),INDEX(Сборка!$O$2:$O$501,$K73),"") | B73: =IF(ISNUMBER($K73),INDEX(Сборка!$C$2:$C$501,$K73),"") | C73: =IF($L73<>"",INDEX(Сборка!$S$2:$S$501,MATCH($L73,Сборка!$P$2:$P$501,0)),IF(ISNUMBER($K73),INDEX(Сборка!$D$2:$D$501,$K73)&IF(INDEX(Сборка!$I$2:$I$501,$K73)<>""," — "&INDEX(Сборка!$I$2:$I$501,$K73),""),"")) | D73: =IF(ISNUMBER($K73),INDEX(Сборка!$E$2:$E$501,$K73),"") | E73: =IF(ISNUMBER($K73),INDEX(Сборка!$G$2:$G$501,$K73),"") | F73: =IF(ISNUMBER($K73),INDEX(Сборка!$J$2:$J$501,$K73),"") | G73: =IF(ISNUMBER($K73),INDEX(Сборка!$K$2:$K$501,$K73),"") | H73: =IF(ISNUMBER($K73),ROUND($E73*$F73,2),"") | I73: =IF(ISNUMBER($K73),ROUND($E73*$G73,2),"") | J73: =IF(ISNUMBER($K73),$H73+$I73,"") | K73: =IFERROR(MATCH(53,Сборка!$R$2:$R$501,0),"") | L73: =IFERROR(IF(INDEX(Сборка!$Q$2:$Q$501,MATCH(53+1,Сборка!$R$2:$R$501,0))=1,INDEX(Сборка!$P$2:$P$501,MATCH(53+1,Сборка!$R$2:$R$501,0)),""),"") | M73: =IF(OR(ISNUMBER($K73),$L73<>""),"показать","")
A74: =IF(ISNUMBER($K74),INDEX(Сборка!$O$2:$O$501,$K74),"") | B74: =IF(ISNUMBER($K74),INDEX(Сборка!$C$2:$C$501,$K74),"") | C74: =IF($L74<>"",INDEX(Сборка!$S$2:$S$501,MATCH($L74,Сборка!$P$2:$P$501,0)),IF(ISNUMBER($K74),INDEX(Сборка!$D$2:$D$501,$K74)&IF(INDEX(Сборка!$I$2:$I$501,$K74)<>""," — "&INDEX(Сборка!$I$2:$I$501,$K74),""),"")) | D74: =IF(ISNUMBER($K74),INDEX(Сборка!$E$2:$E$501,$K74),"") | E74: =IF(ISNUMBER($K74),INDEX(Сборка!$G$2:$G$501,$K74),"") | F74: =IF(ISNUMBER($K74),INDEX(Сборка!$J$2:$J$501,$K74),"") | G74: =IF(ISNUMBER($K74),INDEX(Сборка!$K$2:$K$501,$K74),"") | H74: =IF(ISNUMBER($K74),ROUND($E74*$F74,2),"") | I74: =IF(ISNUMBER($K74),ROUND($E74*$G74,2),"") | J74: =IF(ISNUMBER($K74),$H74+$I74,"") | K74: =IFERROR(MATCH(54,Сборка!$R$2:$R$501,0),"") | L74: =IFERROR(IF(INDEX(Сборка!$Q$2:$Q$501,MATCH(54+1,Сборка!$R$2:$R$501,0))=1,INDEX(Сборка!$P$2:$P$501,MATCH(54+1,Сборка!$R$2:$R$501,0)),""),"") | M74: =IF(OR(ISNUMBER($K74),$L74<>""),"показать","")
A75: =IF(ISNUMBER($K75),INDEX(Сборка!$O$2:$O$501,$K75),"") | B75: =IF(ISNUMBER($K75),INDEX(Сборка!$C$2:$C$501,$K75),"") | C75: =IF($L75<>"",INDEX(Сборка!$S$2:$S$501,MATCH($L75,Сборка!$P$2:$P$501,0)),IF(ISNUMBER($K75),INDEX(Сборка!$D$2:$D$501,$K75)&IF(INDEX(Сборка!$I$2:$I$501,$K75)<>""," — "&INDEX(Сборка!$I$2:$I$501,$K75),""),"")) | D75: =IF(ISNUMBER($K75),INDEX(Сборка!$E$2:$E$501,$K75),"") | E75: =IF(ISNUMBER($K75),INDEX(Сборка!$G$2:$G$501,$K75),"") | F75: =IF(ISNUMBER($K75),INDEX(Сборка!$J$2:$J$501,$K75),"") | G75: =IF(ISNUMBER($K75),INDEX(Сборка!$K$2:$K$501,$K75),"") | H75: =IF(ISNUMBER($K75),ROUND($E75*$F75,2),"") | I75: =IF(ISNUMBER($K75),ROUND($E75*$G75,2),"") | J75: =IF(ISNUMBER($K75),$H75+$I75,"") | K75: =IFERROR(MATCH(55,Сборка!$R$2:$R$501,0),"") | L75: =IFERROR(IF(INDEX(Сборка!$Q$2:$Q$501,MATCH(55+1,Сборка!$R$2:$R$501,0))=1,INDEX(Сборка!$P$2:$P$501,MATCH(55+1,Сборка!$R$2:$R$501,0)),""),"") | M75: =IF(OR(ISNUMBER($K75),$L75<>""),"показать","")
A76: =IF(ISNUMBER($K76),INDEX(Сборка!$O$2:$O$501,$K76),"") | B76: =IF(ISNUMBER($K76),INDEX(Сборка!$C$2:$C$501,$K76),"") | C76: =IF($L76<>"",INDEX(Сборка!$S$2:$S$501,MATCH($L76,Сборка!$P$2:$P$501,0)),IF(ISNUMBER($K76),INDEX(Сборка!$D$2:$D$501,$K76)&IF(INDEX(Сборка!$I$2:$I$501,$K76)<>""," — "&INDEX(Сборка!$I$2:$I$501,$K76),""),"")) | D76: =IF(ISNUMBER($K76),INDEX(Сборка!$E$2:$E$501,$K76),"") | E76: =IF(ISNUMBER($K76),INDEX(Сборка!$G$2:$G$501,$K76),"") | F76: =IF(ISNUMBER($K76),INDEX(Сборка!$J$2:$J$501,$K76),"") | G76: =IF(ISNUMBER($K76),INDEX(Сборка!$K$2:$K$501,$K76),"") | H76: =IF(ISNUMBER($K76),ROUND($E76*$F76,2),"") | I76: =IF(ISNUMBER($K76),ROUND($E76*$G76,2),"") | J76: =IF(ISNUMBER($K76),$H76+$I76,"") | K76: =IFERROR(MATCH(56,Сборка!$R$2:$R$501,0),"") | L76: =IFERROR(IF(INDEX(Сборка!$Q$2:$Q$501,MATCH(56+1,Сборка!$R$2:$R$501,0))=1,INDEX(Сборка!$P$2:$P$501,MATCH(56+1,Сборка!$R$2:$R$501,0)),""),"") | M76: =IF(OR(ISNUMBER($K76),$L76<>""),"показать","")
A77: =IF(ISNUMBER($K77),INDEX(Сборка!$O$2:$O$501,$K77),"") | B77: =IF(ISNUMBER($K77),INDEX(Сборка!$C$2:$C$501,$K77),"") | C77: =IF($L77<>"",INDEX(Сборка!$S$2:$S$501,MATCH($L77,Сборка!$P$2:$P$501,0)),IF(ISNUMBER($K77),INDEX(Сборка!$D$2:$D$501,$K77)&IF(INDEX(Сборка!$I$2:$I$501,$K77)<>""," — "&INDEX(Сборка!$I$2:$I$501,$K77),""),"")) | D77: =IF(ISNUMBER($K77),INDEX(Сборка!$E$2:$E$501,$K77),"") | E77: =IF(ISNUMBER($K77),INDEX(Сборка!$G$2:$G$501,$K77),"") | F77: =IF(ISNUMBER($K77),INDEX(Сборка!$J$2:$J$501,$K77),"") | G77: =IF(ISNUMBER($K77),INDEX(Сборка!$K$2:$K$501,$K77),"") | H77: =IF(ISNUMBER($K77),ROUND($E77*$F77,2),"") | I77: =IF(ISNUMBER($K77),ROUND($E77*$G77,2),"") | J77: =IF(ISNUMBER($K77),$H77+$I77,"") | K77: =IFERROR(MATCH(57,Сборка!$R$2:$R$501,0),"") | L77: =IFERROR(IF(INDEX(Сборка!$Q$2:$Q$501,MATCH(57+1,Сборка!$R$2:$R$501,0))=1,INDEX(Сборка!$P$2:$P$501,MATCH(57+1,Сборка!$R$2:$R$501,0)),""),"") | M77: =IF(OR(ISNUMBER($K77),$L77<>""),"показать","")
A78: =IF(ISNUMBER($K78),INDEX(Сборка!$O$2:$O$501,$K78),"") | B78: =IF(ISNUMBER($K78),INDEX(Сборка!$C$2:$C$501,$K78),"") | C78: =IF($L78<>"",INDEX(Сборка!$S$2:$S$501,MATCH($L78,Сборка!$P$2:$P$501,0)),IF(ISNUMBER($K78),INDEX(Сборка!$D$2:$D$501,$K78)&IF(INDEX(Сборка!$I$2:$I$501,$K78)<>""," — "&INDEX(Сборка!$I$2:$I$501,$K78),""),"")) | D78: =IF(ISNUMBER($K78),INDEX(Сборка!$E$2:$E$501,$K78),"") | E78: =IF(ISNUMBER($K78),INDEX(Сборка!$G$2:$G$501,$K78),"") | F78: =IF(ISNUMBER($K78),INDEX(Сборка!$J$2:$J$501,$K78),"") | G78: =IF(ISNUMBER($K78),INDEX(Сборка!$K$2:$K$501,$K78),"") | H78: =IF(ISNUMBER($K78),ROUND($E78*$F78,2),"") | I78: =IF(ISNUMBER($K78),ROUND($E78*$G78,2),"") | J78: =IF(ISNUMBER($K78),$H78+$I78,"") | K78: =IFERROR(MATCH(58,Сборка!$R$2:$R$501,0),"") | L78: =IFERROR(IF(INDEX(Сборка!$Q$2:$Q$501,MATCH(58+1,Сборка!$R$2:$R$501,0))=1,INDEX(Сборка!$P$2:$P$501,MATCH(58+1,Сборка!$R$2:$R$501,0)),""),"") | M78: =IF(OR(ISNUMBER($K78),$L78<>""),"показать","")
A79: =IF(ISNUMBER($K79),INDEX(Сборка!$O$2:$O$501,$K79),"") | B79: =IF(ISNUMBER($K79),INDEX(Сборка!$C$2:$C$501,$K79),"") | C79: =IF($L79<>"",INDEX(Сборка!$S$2:$S$501,MATCH($L79,Сборка!$P$2:$P$501,0)),IF(ISNUMBER($K79),INDEX(Сборка!$D$2:$D$501,$K79)&IF(INDEX(Сборка!$I$2:$I$501,$K79)<>""," — "&INDEX(Сборка!$I$2:$I$501,$K79),""),"")) | D79: =IF(ISNUMBER($K79),INDEX(Сборка!$E$2:$E$501,$K79),"") | E79: =IF(ISNUMBER($K79),INDEX(Сборка!$G$2:$G$501,$K79),"") | F79: =IF(ISNUMBER($K79),INDEX(Сборка!$J$2:$J$501,$K79),"") | G79: =IF(ISNUMBER($K79),INDEX(Сборка!$K$2:$K$501,$K79),"") | H79: =IF(ISNUMBER($K79),ROUND($E79*$F79,2),"") | I79: =IF(ISNUMBER($K79),ROUND($E79*$G79,2),"") | J79: =IF(ISNUMBER($K79),$H79+$I79,"") | K79: =IFERROR(MATCH(59,Сборка!$R$2:$R$501,0),"") | L79: =IFERROR(IF(INDEX(Сборка!$Q$2:$Q$501,MATCH(59+1,Сборка!$R$2:$R$501,0))=1,INDEX(Сборка!$P$2:$P$501,MATCH(59+1,Сборка!$R$2:$R$501,0)),""),"") | M79: =IF(OR(ISNUMBER($K79),$L79<>""),"показать","")
A80: =IF(ISNUMBER($K80),INDEX(Сборка!$O$2:$O$501,$K80),"") | B80: =IF(ISNUMBER($K80),INDEX(Сборка!$C$2:$C$501,$K80),"") | C80: =IF($L80<>"",INDEX(Сборка!$S$2:$S$501,MATCH($L80,Сборка!$P$2:$P$501,0)),IF(ISNUMBER($K80),INDEX(Сборка!$D$2:$D$501,$K80)&IF(INDEX(Сборка!$I$2:$I$501,$K80)<>""," — "&INDEX(Сборка!$I$2:$I$501,$K80),""),"")) | D80: =IF(ISNUMBER($K80),INDEX(Сборка!$E$2:$E$501,$K80),"") | E80: =IF(ISNUMBER($K80),INDEX(Сборка!$G$2:$G$501,$K80),"") | F80: =IF(ISNUMBER($K80),INDEX(Сборка!$J$2:$J$501,$K80),"") | G80: =IF(ISNUMBER($K80),INDEX(Сборка!$K$2:$K$501,$K80),"") | H80: =IF(ISNUMBER($K80),ROUND($E80*$F80,2),"") | I80: =IF(ISNUMBER($K80),ROUND($E80*$G80,2),"") | J80: =IF(ISNUMBER($K80),$H80+$I80,"") | K80: =IFERROR(MATCH(60,Сборка!$R$2:$R$501,0),"") | L80: =IFERROR(IF(INDEX(Сборка!$Q$2:$Q$501,MATCH(60+1,Сборка!$R$2:$R$501,0))=1,INDEX(Сборка!$P$2:$P$501,MATCH(60+1,Сборка!$R$2:$R$501,0)),""),"") | M80: =IF(OR(ISNUMBER($K80),$L80<>""),"показать","")
A81: =IF(ISNUMBER($K81),INDEX(Сборка!$O$2:$O$501,$K81),"") | B81: =IF(ISNUMBER($K81),INDEX(Сборка!$C$2:$C$501,$K81),"") | C81: =IF($L81<>"",INDEX(Сборка!$S$2:$S$501,MATCH($L81,Сборка!$P$2:$P$501,0)),IF(ISNUMBER($K81),INDEX(Сборка!$D$2:$D$501,$K81)&IF(INDEX(Сборка!$I$2:$I$501,$K81)<>""," — "&INDEX(Сборка!$I$2:$I$501,$K81),""),"")) | D81: =IF(ISNUMBER($K81),INDEX(Сборка!$E$2:$E$501,$K81),"") | E81: =IF(ISNUMBER($K81),INDEX(Сборка!$G$2:$G$501,$K81),"") | F81: =IF(ISNUMBER($K81),INDEX(Сборка!$J$2:$J$501,$K81),"") | G81: =IF(ISNUMBER($K81),INDEX(Сборка!$K$2:$K$501,$K81),"") | H81: =IF(ISNUMBER($K81),ROUND($E81*$F81,2),"") | I81: =IF(ISNUMBER($K81),ROUND($E81*$G81,2),"") | J81: =IF(ISNUMBER($K81),$H81+$I81,"") | K81: =IFERROR(MATCH(61,Сборка!$R$2:$R$501,0),"") | L81: =IFERROR(IF(INDEX(Сборка!$Q$2:$Q$501,MATCH(61+1,Сборка!$R$2:$R$501,0))=1,INDEX(Сборка!$P$2:$P$501,MATCH(61+1,Сборка!$R$2:$R$501,0)),""),"") | M81: =IF(OR(ISNUMBER($K81),$L81<>""),"показать","")
A82: =IF(ISNUMBER($K82),INDEX(Сборка!$O$2:$O$501,$K82),"") | B82: =IF(ISNUMBER($K82),INDEX(Сборка!$C$2:$C$501,$K82),"") | C82: =IF($L82<>"",INDEX(Сборка!$S$2:$S$501,MATCH($L82,Сборка!$P$2:$P$501,0)),IF(ISNUMBER($K82),INDEX(Сборка!$D$2:$D$501,$K82)&IF(INDEX(Сборка!$I$2:$I$501,$K82)<>""," — "&INDEX(Сборка!$I$2:$I$501,$K82),""),"")) | D82: =IF(ISNUMBER($K82),INDEX(Сборка!$E$2:$E$501,$K82),"") | E82: =IF(ISNUMBER($K82),INDEX(Сборка!$G$2:$G$501,$K82),"") | F82: =IF(ISNUMBER($K82),INDEX(Сборка!$J$2:$J$501,$K82),"") | G82: =IF(ISNUMBER($K82),INDEX(Сборка!$K$2:$K$501,$K82),"") | H82: =IF(ISNUMBER($K82),ROUND($E82*$F82,2),"") | I82: =IF(ISNUMBER($K82),ROUND($E82*$G82,2),"") | J82: =IF(ISNUMBER($K82),$H82+$I82,"") | K82: =IFERROR(MATCH(62,Сборка!$R$2:$R$501,0),"") | L82: =IFERROR(IF(INDEX(Сборка!$Q$2:$Q$501,MATCH(62+1,Сборка!$R$2:$R$501,0))=1,INDEX(Сборка!$P$2:$P$501,MATCH(62+1,Сборка!$R$2:$R$501,0)),""),"") | M82: =IF(OR(ISNUMBER($K82),$L82<>""),"показать","")
A83: =IF(ISNUMBER($K83),INDEX(Сборка!$O$2:$O$501,$K83),"") | B83: =IF(ISNUMBER($K83),INDEX(Сборка!$C$2:$C$501,$K83),"") | C83: =IF($L83<>"",INDEX(Сборка!$S$2:$S$501,MATCH($L83,Сборка!$P$2:$P$501,0)),IF(ISNUMBER($K83),INDEX(Сборка!$D$2:$D$501,$K83)&IF(INDEX(Сборка!$I$2:$I$501,$K83)<>""," — "&INDEX(Сборка!$I$2:$I$501,$K83),""),"")) | D83: =IF(ISNUMBER($K83),INDEX(Сборка!$E$2:$E$501,$K83),"") | E83: =IF(ISNUMBER($K83),INDEX(Сборка!$G$2:$G$501,$K83),"") | F83: =IF(ISNUMBER($K83),INDEX(Сборка!$J$2:$J$501,$K83),"") | G83: =IF(ISNUMBER($K83),INDEX(Сборка!$K$2:$K$501,$K83),"") | H83: =IF(ISNUMBER($K83),ROUND($E83*$F83,2),"") | I83: =IF(ISNUMBER($K83),ROUND($E83*$G83,2),"") | J83: =IF(ISNUMBER($K83),$H83+$I83,"") | K83: =IFERROR(MATCH(63,Сборка!$R$2:$R$501,0),"") | L83: =IFERROR(IF(INDEX(Сборка!$Q$2:$Q$501,MATCH(63+1,Сборка!$R$2:$R$501,0))=1,INDEX(Сборка!$P$2:$P$501,MATCH(63+1,Сборка!$R$2:$R$501,0)),""),"") | M83: =IF(OR(ISNUMBER($K83),$L83<>""),"показать","")
A84: =IF(ISNUMBER($K84),INDEX(Сборка!$O$2:$O$501,$K84),"") | B84: =IF(ISNUMBER($K84),INDEX(Сборка!$C$2:$C$501,$K84),"") | C84: =IF($L84<>"",INDEX(Сборка!$S$2:$S$501,MATCH($L84,Сборка!$P$2:$P$501,0)),IF(ISNUMBER($K84),INDEX(Сборка!$D$2:$D$501,$K84)&IF(INDEX(Сборка!$I$2:$I$501,$K84)<>""," — "&INDEX(Сборка!$I$2:$I$501,$K84),""),"")) | D84: =IF(ISNUMBER($K84),INDEX(Сборка!$E$2:$E$501,$K84),"") | E84: =IF(ISNUMBER($K84),INDEX(Сборка!$G$2:$G$501,$K84),"") | F84: =IF(ISNUMBER($K84),INDEX(Сборка!$J$2:$J$501,$K84),"") | G84: =IF(ISNUMBER($K84),INDEX(Сборка!$K$2:$K$501,$K84),"") | H84: =IF(ISNUMBER($K84),ROUND($E84*$F84,2),"") | I84: =IF(ISNUMBER($K84),ROUND($E84*$G84,2),"") | J84: =IF(ISNUMBER($K84),$H84+$I84,"") | K84: =IFERROR(MATCH(64,Сборка!$R$2:$R$501,0),"") | L84: =IFERROR(IF(INDEX(Сборка!$Q$2:$Q$501,MATCH(64+1,Сборка!$R$2:$R$501,0))=1,INDEX(Сборка!$P$2:$P$501,MATCH(64+1,Сборка!$R$2:$R$501,0)),""),"") | M84: =IF(OR(ISNUMBER($K84),$L84<>""),"показать","")
A85: =IF(ISNUMBER($K85),INDEX(Сборка!$O$2:$O$501,$K85),"") | B85: =IF(ISNUMBER($K85),INDEX(Сборка!$C$2:$C$501,$K85),"") | C85: =IF($L85<>"",INDEX(Сборка!$S$2:$S$501,MATCH($L85,Сборка!$P$2:$P$501,0)),IF(ISNUMBER($K85),INDEX(Сборка!$D$2:$D$501,$K85)&IF(INDEX(Сборка!$I$2:$I$501,$K85)<>""," — "&INDEX(Сборка!$I$2:$I$501,$K85),""),"")) | D85: =IF(ISNUMBER($K85),INDEX(Сборка!$E$2:$E$501,$K85),"") | E85: =IF(ISNUMBER($K85),INDEX(Сборка!$G$2:$G$501,$K85),"") | F85: =IF(ISNUMBER($K85),INDEX(Сборка!$J$2:$J$501,$K85),"") | G85: =IF(ISNUMBER($K85),INDEX(Сборка!$K$2:$K$501,$K85),"") | H85: =IF(ISNUMBER($K85),ROUND($E85*$F85,2),"") | I85: =IF(ISNUMBER($K85),ROUND($E85*$G85,2),"") | J85: =IF(ISNUMBER($K85),$H85+$I85,"") | K85: =IFERROR(MATCH(65,Сборка!$R$2:$R$501,0),"") | L85: =IFERROR(IF(INDEX(Сборка!$Q$2:$Q$501,MATCH(65+1,Сборка!$R$2:$R$501,0))=1,INDEX(Сборка!$P$2:$P$501,MATCH(65+1,Сборка!$R$2:$R$501,0)),""),"") | M85: =IF(OR(ISNUMBER($K85),$L85<>""),"показать","")
A86: =IF(ISNUMBER($K86),INDEX(Сборка!$O$2:$O$501,$K86),"") | B86: =IF(ISNUMBER($K86),INDEX(Сборка!$C$2:$C$501,$K86),"") | C86: =IF($L86<>"",INDEX(Сборка!$S$2:$S$501,MATCH($L86,Сборка!$P$2:$P$501,0)),IF(ISNUMBER($K86),INDEX(Сборка!$D$2:$D$501,$K86)&IF(INDEX(Сборка!$I$2:$I$501,$K86)<>""," — "&INDEX(Сборка!$I$2:$I$501,$K86),""),"")) | D86: =IF(ISNUMBER($K86),INDEX(Сборка!$E$2:$E$501,$K86),"") | E86: =IF(ISNUMBER($K86),INDEX(Сборка!$G$2:$G$501,$K86),"") | F86: =IF(ISNUMBER($K86),INDEX(Сборка!$J$2:$J$501,$K86),"") | G86: =IF(ISNUMBER($K86),INDEX(Сборка!$K$2:$K$501,$K86),"") | H86: =IF(ISNUMBER($K86),ROUND($E86*$F86,2),"") | I86: =IF(ISNUMBER($K86),ROUND($E86*$G86,2),"") | J86: =IF(ISNUMBER($K86),$H86+$I86,"") | K86: =IFERROR(MATCH(66,Сборка!$R$2:$R$501,0),"") | L86: =IFERROR(IF(INDEX(Сборка!$Q$2:$Q$501,MATCH(66+1,Сборка!$R$2:$R$501,0))=1,INDEX(Сборка!$P$2:$P$501,MATCH(66+1,Сборка!$R$2:$R$501,0)),""),"") | M86: =IF(OR(ISNUMBER($K86),$L86<>""),"показать","")
A87: =IF(ISNUMBER($K87),INDEX(Сборка!$O$2:$O$501,$K87),"") | B87: =IF(ISNUMBER($K87),INDEX(Сборка!$C$2:$C$501,$K87),"") | C87: =IF($L87<>"",INDEX(Сборка!$S$2:$S$501,MATCH($L87,Сборка!$P$2:$P$501,0)),IF(ISNUMBER($K87),INDEX(Сборка!$D$2:$D$501,$K87)&IF(INDEX(Сборка!$I$2:$I$501,$K87)<>""," — "&INDEX(Сборка!$I$2:$I$501,$K87),""),"")) | D87: =IF(ISNUMBER($K87),INDEX(Сборка!$E$2:$E$501,$K87),"") | E87: =IF(ISNUMBER($K87),INDEX(Сборка!$G$2:$G$501,$K87),"") | F87: =IF(ISNUMBER($K87),INDEX(Сборка!$J$2:$J$501,$K87),"") | G87: =IF(ISNUMBER($K87),INDEX(Сборка!$K$2:$K$501,$K87),"") | H87: =IF(ISNUMBER($K87),ROUND($E87*$F87,2),"") | I87: =IF(ISNUMBER($K87),ROUND($E87*$G87,2),"") | J87: =IF(ISNUMBER($K87),$H87+$I87,"") | K87: =IFERROR(MATCH(67,Сборка!$R$2:$R$501,0),"") | L87: =IFERROR(IF(INDEX(Сборка!$Q$2:$Q$501,MATCH(67+1,Сборка!$R$2:$R$501,0))=1,INDEX(Сборка!$P$2:$P$501,MATCH(67+1,Сборка!$R$2:$R$501,0)),""),"") | M87: =IF(OR(ISNUMBER($K87),$L87<>""),"показать","")
A88: =IF(ISNUMBER($K88),INDEX(Сборка!$O$2:$O$501,$K88),"") | B88: =IF(ISNUMBER($K88),INDEX(Сборка!$C$2:$C$501,$K88),"") | C88: =IF($L88<>"",INDEX(Сборка!$S$2:$S$501,MATCH($L88,Сборка!$P$2:$P$501,0)),IF(ISNUMBER($K88),INDEX(Сборка!$D$2:$D$501,$K88)&IF(INDEX(Сборка!$I$2:$I$501,$K88)<>""," — "&INDEX(Сборка!$I$2:$I$501,$K88),""),"")) | D88: =IF(ISNUMBER($K88),INDEX(Сборка!$E$2:$E$501,$K88),"") | E88: =IF(ISNUMBER($K88),INDEX(Сборка!$G$2:$G$501,$K88),"") | F88: =IF(ISNUMBER($K88),INDEX(Сборка!$J$2:$J$501,$K88),"") | G88: =IF(ISNUMBER($K88),INDEX(Сборка!$K$2:$K$501,$K88),"") | H88: =IF(ISNUMBER($K88),ROUND($E88*$F88,2),"") | I88: =IF(ISNUMBER($K88),ROUND($E88*$G88,2),"") | J88: =IF(ISNUMBER($K88),$H88+$I88,"") | K88: =IFERROR(MATCH(68,Сборка!$R$2:$R$501,0),"") | L88: =IFERROR(IF(INDEX(Сборка!$Q$2:$Q$501,MATCH(68+1,Сборка!$R$2:$R$501,0))=1,INDEX(Сборка!$P$2:$P$501,MATCH(68+1,Сборка!$R$2:$R$501,0)),""),"") | M88: =IF(OR(ISNUMBER($K88),$L88<>""),"показать","")
A89: =IF(ISNUMBER($K89),INDEX(Сборка!$O$2:$O$501,$K89),"") | B89: =IF(ISNUMBER($K89),INDEX(Сборка!$C$2:$C$501,$K89),"") | C89: =IF($L89<>"",INDEX(Сборка!$S$2:$S$501,MATCH($L89,Сборка!$P$2:$P$501,0)),IF(ISNUMBER($K89),INDEX(Сборка!$D$2:$D$501,$K89)&IF(INDEX(Сборка!$I$2:$I$501,$K89)<>""," — "&INDEX(Сборка!$I$2:$I$501,$K89),""),"")) | D89: =IF(ISNUMBER($K89),INDEX(Сборка!$E$2:$E$501,$K89),"") | E89: =IF(ISNUMBER($K89),INDEX(Сборка!$G$2:$G$501,$K89),"") | F89: =IF(ISNUMBER($K89),INDEX(Сборка!$J$2:$J$501,$K89),"") | G89: =IF(ISNUMBER($K89),INDEX(Сборка!$K$2:$K$501,$K89),"") | H89: =IF(ISNUMBER($K89),ROUND($E89*$F89,2),"") | I89: =IF(ISNUMBER($K89),ROUND($E89*$G89,2),"") | J89: =IF(ISNUMBER($K89),$H89+$I89,"") | K89: =IFERROR(MATCH(69,Сборка!$R$2:$R$501,0),"") | L89: =IFERROR(IF(INDEX(Сборка!$Q$2:$Q$501,MATCH(69+1,Сборка!$R$2:$R$501,0))=1,INDEX(Сборка!$P$2:$P$501,MATCH(69+1,Сборка!$R$2:$R$501,0)),""),"") | M89: =IF(OR(ISNUMBER($K89),$L89<>""),"показать","")
A90: =IF(ISNUMBER($K90),INDEX(Сборка!$O$2:$O$501,$K90),"") | B90: =IF(ISNUMBER($K90),INDEX(Сборка!$C$2:$C$501,$K90),"") | C90: =IF($L90<>"",INDEX(Сборка!$S$2:$S$501,MATCH($L90,Сборка!$P$2:$P$501,0)),IF(ISNUMBER($K90),INDEX(Сборка!$D$2:$D$501,$K90)&IF(INDEX(Сборка!$I$2:$I$501,$K90)<>""," — "&INDEX(Сборка!$I$2:$I$501,$K90),""),"")) | D90: =IF(ISNUMBER($K90),INDEX(Сборка!$E$2:$E$501,$K90),"") | E90: =IF(ISNUMBER($K90),INDEX(Сборка!$G$2:$G$501,$K90),"") | F90: =IF(ISNUMBER($K90),INDEX(Сборка!$J$2:$J$501,$K90),"") | G90: =IF(ISNUMBER($K90),INDEX(Сборка!$K$2:$K$501,$K90),"") | H90: =IF(ISNUMBER($K90),ROUND($E90*$F90,2),"") | I90: =IF(ISNUMBER($K90),ROUND($E90*$G90,2),"") | J90: =IF(ISNUMBER($K90),$H90+$I90,"") | K90: =IFERROR(MATCH(70,Сборка!$R$2:$R$501,0),"") | L90: =IFERROR(IF(INDEX(Сборка!$Q$2:$Q$501,MATCH(70+1,Сборка!$R$2:$R$501,0))=1,INDEX(Сборка!$P$2:$P$501,MATCH(70+1,Сборка!$R$2:$R$501,0)),""),"") | M90: =IF(OR(ISNUMBER($K90),$L90<>""),"показать","")
A91: =IF(ISNUMBER($K91),INDEX(Сборка!$O$2:$O$501,$K91),"") | B91: =IF(ISNUMBER($K91),INDEX(Сборка!$C$2:$C$501,$K91),"") | C91: =IF($L91<>"",INDEX(Сборка!$S$2:$S$501,MATCH($L91,Сборка!$P$2:$P$501,0)),IF(ISNUMBER($K91),INDEX(Сборка!$D$2:$D$501,$K91)&IF(INDEX(Сборка!$I$2:$I$501,$K91)<>""," — "&INDEX(Сборка!$I$2:$I$501,$K91),""),"")) | D91: =IF(ISNUMBER($K91),INDEX(Сборка!$E$2:$E$501,$K91),"") | E91: =IF(ISNUMBER($K91),INDEX(Сборка!$G$2:$G$501,$K91),"") | F91: =IF(ISNUMBER($K91),INDEX(Сборка!$J$2:$J$501,$K91),"") | G91: =IF(ISNUMBER($K91),INDEX(Сборка!$K$2:$K$501,$K91),"") | H91: =IF(ISNUMBER($K91),ROUND($E91*$F91,2),"") | I91: =IF(ISNUMBER($K91),ROUND($E91*$G91,2),"") | J91: =IF(ISNUMBER($K91),$H91+$I91,"") | K91: =IFERROR(MATCH(71,Сборка!$R$2:$R$501,0),"") | L91: =IFERROR(IF(INDEX(Сборка!$Q$2:$Q$501,MATCH(71+1,Сборка!$R$2:$R$501,0))=1,INDEX(Сборка!$P$2:$P$501,MATCH(71+1,Сборка!$R$2:$R$501,0)),""),"") | M91: =IF(OR(ISNUMBER($K91),$L91<>""),"показать","")
A92: =IF(ISNUMBER($K92),INDEX(Сборка!$O$2:$O$501,$K92),"") | B92: =IF(ISNUMBER($K92),INDEX(Сборка!$C$2:$C$501,$K92),"") | C92: =IF($L92<>"",INDEX(Сборка!$S$2:$S$501,MATCH($L92,Сборка!$P$2:$P$501,0)),IF(ISNUMBER($K92),INDEX(Сборка!$D$2:$D$501,$K92)&IF(INDEX(Сборка!$I$2:$I$501,$K92)<>""," — "&INDEX(Сборка!$I$2:$I$501,$K92),""),"")) | D92: =IF(ISNUMBER($K92),INDEX(Сборка!$E$2:$E$501,$K92),"") | E92: =IF(ISNUMBER($K92),INDEX(Сборка!$G$2:$G$501,$K92),"") | F92: =IF(ISNUMBER($K92),INDEX(Сборка!$J$2:$J$501,$K92),"") | G92: =IF(ISNUMBER($K92),INDEX(Сборка!$K$2:$K$501,$K92),"") | H92: =IF(ISNUMBER($K92),ROUND($E92*$F92,2),"") | I92: =IF(ISNUMBER($K92),ROUND($E92*$G92,2),"") | J92: =IF(ISNUMBER($K92),$H92+$I92,"") | K92: =IFERROR(MATCH(72,Сборка!$R$2:$R$501,0),"") | L92: =IFERROR(IF(INDEX(Сборка!$Q$2:$Q$501,MATCH(72+1,Сборка!$R$2:$R$501,0))=1,INDEX(Сборка!$P$2:$P$501,MATCH(72+1,Сборка!$R$2:$R$501,0)),""),"") | M92: =IF(OR(ISNUMBER($K92),$L92<>""),"показать","")
A93: =IF(ISNUMBER($K93),INDEX(Сборка!$O$2:$O$501,$K93),"") | B93: =IF(ISNUMBER($K93),INDEX(Сборка!$C$2:$C$501,$K93),"") | C93: =IF($L93<>"",INDEX(Сборка!$S$2:$S$501,MATCH($L93,Сборка!$P$2:$P$501,0)),IF(ISNUMBER($K93),INDEX(Сборка!$D$2:$D$501,$K93)&IF(INDEX(Сборка!$I$2:$I$501,$K93)<>""," — "&INDEX(Сборка!$I$2:$I$501,$K93),""),"")) | D93: =IF(ISNUMBER($K93),INDEX(Сборка!$E$2:$E$501,$K93),"") | E93: =IF(ISNUMBER($K93),INDEX(Сборка!$G$2:$G$501,$K93),"") | F93: =IF(ISNUMBER($K93),INDEX(Сборка!$J$2:$J$501,$K93),"") | G93: =IF(ISNUMBER($K93),INDEX(Сборка!$K$2:$K$501,$K93),"") | H93: =IF(ISNUMBER($K93),ROUND($E93*$F93,2),"") | I93: =IF(ISNUMBER($K93),ROUND($E93*$G93,2),"") | J93: =IF(ISNUMBER($K93),$H93+$I93,"") | K93: =IFERROR(MATCH(73,Сборка!$R$2:$R$501,0),"") | L93: =IFERROR(IF(INDEX(Сборка!$Q$2:$Q$501,MATCH(73+1,Сборка!$R$2:$R$501,0))=1,INDEX(Сборка!$P$2:$P$501,MATCH(73+1,Сборка!$R$2:$R$501,0)),""),"") | M93: =IF(OR(ISNUMBER($K93),$L93<>""),"показать","")
A94: =IF(ISNUMBER($K94),INDEX(Сборка!$O$2:$O$501,$K94),"") | B94: =IF(ISNUMBER($K94),INDEX(Сборка!$C$2:$C$501,$K94),"") | C94: =IF($L94<>"",INDEX(Сборка!$S$2:$S$501,MATCH($L94,Сборка!$P$2:$P$501,0)),IF(ISNUMBER($K94),INDEX(Сборка!$D$2:$D$501,$K94)&IF(INDEX(Сборка!$I$2:$I$501,$K94)<>""," — "&INDEX(Сборка!$I$2:$I$501,$K94),""),"")) | D94: =IF(ISNUMBER($K94),INDEX(Сборка!$E$2:$E$501,$K94),"") | E94: =IF(ISNUMBER($K94),INDEX(Сборка!$G$2:$G$501,$K94),"") | F94: =IF(ISNUMBER($K94),INDEX(Сборка!$J$2:$J$501,$K94),"") | G94: =IF(ISNUMBER($K94),INDEX(Сборка!$K$2:$K$501,$K94),"") | H94: =IF(ISNUMBER($K94),ROUND($E94*$F94,2),"") | I94: =IF(ISNUMBER($K94),ROUND($E94*$G94,2),"") | J94: =IF(ISNUMBER($K94),$H94+$I94,"") | K94: =IFERROR(MATCH(74,Сборка!$R$2:$R$501,0),"") | L94: =IFERROR(IF(INDEX(Сборка!$Q$2:$Q$501,MATCH(74+1,Сборка!$R$2:$R$501,0))=1,INDEX(Сборка!$P$2:$P$501,MATCH(74+1,Сборка!$R$2:$R$501,0)),""),"") | M94: =IF(OR(ISNUMBER($K94),$L94<>""),"показать","")
A95: =IF(ISNUMBER($K95),INDEX(Сборка!$O$2:$O$501,$K95),"") | B95: =IF(ISNUMBER($K95),INDEX(Сборка!$C$2:$C$501,$K95),"") | C95: =IF($L95<>"",INDEX(Сборка!$S$2:$S$501,MATCH($L95,Сборка!$P$2:$P$501,0)),IF(ISNUMBER($K95),INDEX(Сборка!$D$2:$D$501,$K95)&IF(INDEX(Сборка!$I$2:$I$501,$K95)<>""," — "&INDEX(Сборка!$I$2:$I$501,$K95),""),"")) | D95: =IF(ISNUMBER($K95),INDEX(Сборка!$E$2:$E$501,$K95),"") | E95: =IF(ISNUMBER($K95),INDEX(Сборка!$G$2:$G$501,$K95),"") | F95: =IF(ISNUMBER($K95),INDEX(Сборка!$J$2:$J$501,$K95),"") | G95: =IF(ISNUMBER($K95),INDEX(Сборка!$K$2:$K$501,$K95),"") | H95: =IF(ISNUMBER($K95),ROUND($E95*$F95,2),"") | I95: =IF(ISNUMBER($K95),ROUND($E95*$G95,2),"") | J95: =IF(ISNUMBER($K95),$H95+$I95,"") | K95: =IFERROR(MATCH(75,Сборка!$R$2:$R$501,0),"") | L95: =IFERROR(IF(INDEX(Сборка!$Q$2:$Q$501,MATCH(75+1,Сборка!$R$2:$R$501,0))=1,INDEX(Сборка!$P$2:$P$501,MATCH(75+1,Сборка!$R$2:$R$501,0)),""),"") | M95: =IF(OR(ISNUMBER($K95),$L95<>""),"показать","")
A96: =IF(ISNUMBER($K96),INDEX(Сборка!$O$2:$O$501,$K96),"") | B96: =IF(ISNUMBER($K96),INDEX(Сборка!$C$2:$C$501,$K96),"") | C96: =IF($L96<>"",INDEX(Сборка!$S$2:$S$501,MATCH($L96,Сборка!$P$2:$P$501,0)),IF(ISNUMBER($K96),INDEX(Сборка!$D$2:$D$501,$K96)&IF(INDEX(Сборка!$I$2:$I$501,$K96)<>""," — "&INDEX(Сборка!$I$2:$I$501,$K96),""),"")) | D96: =IF(ISNUMBER($K96),INDEX(Сборка!$E$2:$E$501,$K96),"") | E96: =IF(ISNUMBER($K96),INDEX(Сборка!$G$2:$G$501,$K96),"") | F96: =IF(ISNUMBER($K96),INDEX(Сборка!$J$2:$J$501,$K96),"") | G96: =IF(ISNUMBER($K96),INDEX(Сборка!$K$2:$K$501,$K96),"") | H96: =IF(ISNUMBER($K96),ROUND($E96*$F96,2),"") | I96: =IF(ISNUMBER($K96),ROUND($E96*$G96,2),"") | J96: =IF(ISNUMBER($K96),$H96+$I96,"") | K96: =IFERROR(MATCH(76,Сборка!$R$2:$R$501,0),"") | L96: =IFERROR(IF(INDEX(Сборка!$Q$2:$Q$501,MATCH(76+1,Сборка!$R$2:$R$501,0))=1,INDEX(Сборка!$P$2:$P$501,MATCH(76+1,Сборка!$R$2:$R$501,0)),""),"") | M96: =IF(OR(ISNUMBER($K96),$L96<>""),"показать","")
A97: =IF(ISNUMBER($K97),INDEX(Сборка!$O$2:$O$501,$K97),"") | B97: =IF(ISNUMBER($K97),INDEX(Сборка!$C$2:$C$501,$K97),"") | C97: =IF($L97<>"",INDEX(Сборка!$S$2:$S$501,MATCH($L97,Сборка!$P$2:$P$501,0)),IF(ISNUMBER($K97),INDEX(Сборка!$D$2:$D$501,$K97)&IF(INDEX(Сборка!$I$2:$I$501,$K97)<>""," — "&INDEX(Сборка!$I$2:$I$501,$K97),""),"")) | D97: =IF(ISNUMBER($K97),INDEX(Сборка!$E$2:$E$501,$K97),"") | E97: =IF(ISNUMBER($K97),INDEX(Сборка!$G$2:$G$501,$K97),"") | F97: =IF(ISNUMBER($K97),INDEX(Сборка!$J$2:$J$501,$K97),"") | G97: =IF(ISNUMBER($K97),INDEX(Сборка!$K$2:$K$501,$K97),"") | H97: =IF(ISNUMBER($K97),ROUND($E97*$F97,2),"") | I97: =IF(ISNUMBER($K97),ROUND($E97*$G97,2),"") | J97: =IF(ISNUMBER($K97),$H97+$I97,"") | K97: =IFERROR(MATCH(77,Сборка!$R$2:$R$501,0),"") | L97: =IFERROR(IF(INDEX(Сборка!$Q$2:$Q$501,MATCH(77+1,Сборка!$R$2:$R$501,0))=1,INDEX(Сборка!$P$2:$P$501,MATCH(77+1,Сборка!$R$2:$R$501,0)),""),"") | M97: =IF(OR(ISNUMBER($K97),$L97<>""),"показать","")
A98: =IF(ISNUMBER($K98),INDEX(Сборка!$O$2:$O$501,$K98),"") | B98: =IF(ISNUMBER($K98),INDEX(Сборка!$C$2:$C$501,$K98),"") | C98: =IF($L98<>"",INDEX(Сборка!$S$2:$S$501,MATCH($L98,Сборка!$P$2:$P$501,0)),IF(ISNUMBER($K98),INDEX(Сборка!$D$2:$D$501,$K98)&IF(INDEX(Сборка!$I$2:$I$501,$K98)<>""," — "&INDEX(Сборка!$I$2:$I$501,$K98),""),"")) | D98: =IF(ISNUMBER($K98),INDEX(Сборка!$E$2:$E$501,$K98),"") | E98: =IF(ISNUMBER($K98),INDEX(Сборка!$G$2:$G$501,$K98),"") | F98: =IF(ISNUMBER($K98),INDEX(Сборка!$J$2:$J$501,$K98),"") | G98: =IF(ISNUMBER($K98),INDEX(Сборка!$K$2:$K$501,$K98),"") | H98: =IF(ISNUMBER($K98),ROUND($E98*$F98,2),"") | I98: =IF(ISNUMBER($K98),ROUND($E98*$G98,2),"") | J98: =IF(ISNUMBER($K98),$H98+$I98,"") | K98: =IFERROR(MATCH(78,Сборка!$R$2:$R$501,0),"") | L98: =IFERROR(IF(INDEX(Сборка!$Q$2:$Q$501,MATCH(78+1,Сборка!$R$2:$R$501,0))=1,INDEX(Сборка!$P$2:$P$501,MATCH(78+1,Сборка!$R$2:$R$501,0)),""),"") | M98: =IF(OR(ISNUMBER($K98),$L98<>""),"показать","")
A99: =IF(ISNUMBER($K99),INDEX(Сборка!$O$2:$O$501,$K99),"") | B99: =IF(ISNUMBER($K99),INDEX(Сборка!$C$2:$C$501,$K99),"") | C99: =IF($L99<>"",INDEX(Сборка!$S$2:$S$501,MATCH($L99,Сборка!$P$2:$P$501,0)),IF(ISNUMBER($K99),INDEX(Сборка!$D$2:$D$501,$K99)&IF(INDEX(Сборка!$I$2:$I$501,$K99)<>""," — "&INDEX(Сборка!$I$2:$I$501,$K99),""),"")) | D99: =IF(ISNUMBER($K99),INDEX(Сборка!$E$2:$E$501,$K99),"") | E99: =IF(ISNUMBER($K99),INDEX(Сборка!$G$2:$G$501,$K99),"") | F99: =IF(ISNUMBER($K99),INDEX(Сборка!$J$2:$J$501,$K99),"") | G99: =IF(ISNUMBER($K99),INDEX(Сборка!$K$2:$K$501,$K99),"") | H99: =IF(ISNUMBER($K99),ROUND($E99*$F99,2),"") | I99: =IF(ISNUMBER($K99),ROUND($E99*$G99,2),"") | J99: =IF(ISNUMBER($K99),$H99+$I99,"") | K99: =IFERROR(MATCH(79,Сборка!$R$2:$R$501,0),"") | L99: =IFERROR(IF(INDEX(Сборка!$Q$2:$Q$501,MATCH(79+1,Сборка!$R$2:$R$501,0))=1,INDEX(Сборка!$P$2:$P$501,MATCH(79+1,Сборка!$R$2:$R$501,0)),""),"") | M99: =IF(OR(ISNUMBER($K99),$L99<>""),"показать","")
A100: =IF(ISNUMBER($K100),INDEX(Сборка!$O$2:$O$501,$K100),"") | B100: =IF(ISNUMBER($K100),INDEX(Сборка!$C$2:$C$501,$K100),"") | C100: =IF($L100<>"",INDEX(Сборка!$S$2:$S$501,MATCH($L100,Сборка!$P$2:$P$501,0)),IF(ISNUMBER($K100),INDEX(Сборка!$D$2:$D$501,$K100)&IF(INDEX(Сборка!$I$2:$I$501,$K100)<>""," — "&INDEX(Сборка!$I$2:$I$501,$K100),""),"")) | D100: =IF(ISNUMBER($K100),INDEX(Сборка!$E$2:$E$501,$K100),"") | E100: =IF(ISNUMBER($K100),INDEX(Сборка!$G$2:$G$501,$K100),"") | F100: =IF(ISNUMBER($K100),INDEX(Сборка!$J$2:$J$501,$K100),"") | G100: =IF(ISNUMBER($K100),INDEX(Сборка!$K$2:$K$501,$K100),"") | H100: =IF(ISNUMBER($K100),ROUND($E100*$F100,2),"") | I100: =IF(ISNUMBER($K100),ROUND($E100*$G100,2),"") | J100: =IF(ISNUMBER($K100),$H100+$I100,"") | K100: =IFERROR(MATCH(80,Сборка!$R$2:$R$501,0),"") | L100: =IFERROR(IF(INDEX(Сборка!$Q$2:$Q$501,MATCH(80+1,Сборка!$R$2:$R$501,0))=1,INDEX(Сборка!$P$2:$P$501,MATCH(80+1,Сборка!$R$2:$R$501,0)),""),"") | M100: =IF(OR(ISNUMBER($K100),$L100<>""),"показать","")
A101: =IF(ISNUMBER($K101),INDEX(Сборка!$O$2:$O$501,$K101),"") | B101: =IF(ISNUMBER($K101),INDEX(Сборка!$C$2:$C$501,$K101),"") | C101: =IF($L101<>"",INDEX(Сборка!$S$2:$S$501,MATCH($L101,Сборка!$P$2:$P$501,0)),IF(ISNUMBER($K101),INDEX(Сборка!$D$2:$D$501,$K101)&IF(INDEX(Сборка!$I$2:$I$501,$K101)<>""," — "&INDEX(Сборка!$I$2:$I$501,$K101),""),"")) | D101: =IF(ISNUMBER($K101),INDEX(Сборка!$E$2:$E$501,$K101),"") | E101: =IF(ISNUMBER($K101),INDEX(Сборка!$G$2:$G$501,$K101),"") | F101: =IF(ISNUMBER($K101),INDEX(Сборка!$J$2:$J$501,$K101),"") | G101: =IF(ISNUMBER($K101),INDEX(Сборка!$K$2:$K$501,$K101),"") | H101: =IF(ISNUMBER($K101),ROUND($E101*$F101,2),"") | I101: =IF(ISNUMBER($K101),ROUND($E101*$G101,2),"") | J101: =IF(ISNUMBER($K101),$H101+$I101,"") | K101: =IFERROR(MATCH(81,Сборка!$R$2:$R$501,0),"") | L101: =IFERROR(IF(INDEX(Сборка!$Q$2:$Q$501,MATCH(81+1,Сборка!$R$2:$R$501,0))=1,INDEX(Сборка!$P$2:$P$501,MATCH(81+1,Сборка!$R$2:$R$501,0)),""),"") | M101: =IF(OR(ISNUMBER($K101),$L101<>""),"показать","")
A102: =IF(ISNUMBER($K102),INDEX(Сборка!$O$2:$O$501,$K102),"") | B102: =IF(ISNUMBER($K102),INDEX(Сборка!$C$2:$C$501,$K102),"") | C102: =IF($L102<>"",INDEX(Сборка!$S$2:$S$501,MATCH($L102,Сборка!$P$2:$P$501,0)),IF(ISNUMBER($K102),INDEX(Сборка!$D$2:$D$501,$K102)&IF(INDEX(Сборка!$I$2:$I$501,$K102)<>""," — "&INDEX(Сборка!$I$2:$I$501,$K102),""),"")) | D102: =IF(ISNUMBER($K102),INDEX(Сборка!$E$2:$E$501,$K102),"") | E102: =IF(ISNUMBER($K102),INDEX(Сборка!$G$2:$G$501,$K102),"") | F102: =IF(ISNUMBER($K102),INDEX(Сборка!$J$2:$J$501,$K102),"") | G102: =IF(ISNUMBER($K102),INDEX(Сборка!$K$2:$K$501,$K102),"") | H102: =IF(ISNUMBER($K102),ROUND($E102*$F102,2),"") | I102: =IF(ISNUMBER($K102),ROUND($E102*$G102,2),"") | J102: =IF(ISNUMBER($K102),$H102+$I102,"") | K102: =IFERROR(MATCH(82,Сборка!$R$2:$R$501,0),"") | L102: =IFERROR(IF(INDEX(Сборка!$Q$2:$Q$501,MATCH(82+1,Сборка!$R$2:$R$501,0))=1,INDEX(Сборка!$P$2:$P$501,MATCH(82+1,Сборка!$R$2:$R$501,0)),""),"") | M102: =IF(OR(ISNUMBER($K102),$L102<>""),"показать","")
...

Sheet Работы
A1: Код_работы | B1: Наименование_работы | C1: Ед_изм | D1: Раздел | E1: Раздел_наимен | F1: Подраздел | G1: Группа_материалов | H1: Цена_работ_ЕР | I1: Вспом_материалы_% | J1: Тип | K1: Примечание | L1: Дата изм. цены | M1: Кто изменил / обоснование | N1: Код — Наименование (для списка)
A2: РАБ.Р1.1.001 | B2: Техническое обследование состояния несущих конструкций помещения с подготовкой рекомендаций по усилению (Техничесекое заключение о конструктиве - "ТЗК") (для помещений от 100 до 45… | C2: м2 | D2: Р1 | E2: Проектные работы и согласования | F2: 1 | H2: 3675 | I2: 0 | J2: нетиповая | N2: РАБ.Р1.1.001 — Техническое обследование состояния несущих конструкций помещения с подготовкой рекомендаций по усилению (Техничесекое заключение о конструктиве - "ТЗК") (для помещений от 100 до 45…
A3: РАБ.Р1.1.002 | B3: Эскизный проект фасада и Колористический паспорт с указанием ведомости отделки и проектным решением со спецификацией элементов (крыльцо, пандус, навесы, колонны и т.д.)(для фасадов… | C3: м2 | D3: Р1 | E3: Проектные работы и согласования | F3: 1 | H3: 7822.5 | I3: 0 | J3: нетиповая | N3: РАБ.Р1.1.002 — Эскизный проект фасада и Колористический паспорт с указанием ведомости отделки и проектным решением со спецификацией элементов (крыльцо, пандус, навесы, колонны и т.д.)(для фасадов…
A4: РАБ.Р1.1.901 | B4: Рабочая документация (раздел проекта — выбрать в «Сборке») | C4: — | D4: Р1 | E4: Проектные работы и согласования | F4: 1 | G4: ДОК.РД | H4: 0 | I4: 0 | J4: нетиповая | N4: РАБ.Р1.1.901 — Рабочая документация (раздел проекта — выбрать в «Сборке»)
A5: РАБ.Р1.1.961 | B5: Исполнительная документация (раздел проекта — выбрать в «Сборке») | C5: — | D5: Р1 | E5: Проектные работы и согласования | F5: 1 | G5: ДОК.ИД | H5: 0 | I5: 0 | J5: нетиповая | N5: РАБ.Р1.1.961 — Исполнительная документация (раздел проекта — выбрать в «Сборке»)
A6: РАБ.Р1.1.021 | B6: Техническое обследование состояния несущих конструкций помещения с подготовкой рекомендаций по усилению в зоне расположения депозитария, кассового узла и банкоматов (Техничесекое з… | C6: м2 | D6: Р1 | E6: Проектные работы и согласования | F6: 1 | H6: 3675 | I6: 0 | J6: нетиповая | N6: РАБ.Р1.1.021 — Техническое обследование состояния несущих конструкций помещения с подготовкой рекомендаций по усилению в зоне расположения депозитария, кассового узла и банкоматов (Техничесекое з…
A7: РАБ.Р1.1.022 | B7: Эскизный проект фасада и колористический паспорт с указанием ведомости отделки и проектным решением со спецификацией элементов (крыльцо, пандус, навесы, колонны и т.д.)(для фасадов… | C7: кв.м.площади фасада | D7: Р1 | E7: Проектные работы и согласования | F7: 1 | H7: 7822.5 | I7: 0 | J7: нетиповая | N7: РАБ.Р1.1.022 — Эскизный проект фасада и колористический паспорт с указанием ведомости отделки и проектным решением со спецификацией элементов (крыльцо, пандус, навесы, колонны и т.д.)(для фасадов…
A8: РАБ.Р1.1.061 | B8: Стоимость согласования проекта перепланировки/реставрации объекта культурного наследия в соответствии с нормативными актами г.______________. | C8: м2 | D8: Р1 | E8: Проектные работы и согласования | F8: 1 | H8: 0 | I8: 0 | J8: типовая | N8: РАБ.Р1.1.061 — Стоимость согласования проекта перепланировки/реставрации объекта культурного наследия в соответствии с нормативными актами г.______________.
A9: РАБ.Р1.1.062 | B9: Стоимость согласования проекта перепланировки/реконструкции объекта в соответствии с нормативными актами г.______________. | C9: м2 | D9: Р1 | E9: Проектные работы и согласования | F9: 1 | H9: 0 | I9: 0 | J9: типовая | N9: РАБ.Р1.1.062 — Стоимость согласования проекта перепланировки/реконструкции объекта в соответствии с нормативными актами г.______________.
A10: РАБ.Р1.1.063 | B10: Получение паспорта БТИ (в черных линиях) | C10: м2 | D10: Р1 | E10: Проектные работы и согласования | F10: 1 | H10: 0 | I10: 0 | J10: типовая | N10: РАБ.Р1.1.063 — Получение паспорта БТИ (в черных линиях)
A11: РАБ.Р1.1.064 | B11: Сертификация помещения для совершения операций с ценностями, хранение ценностей по (2) классу вломостойкости и (3) классу пулестойкости | C11: м2 | D11: Р1 | E11: Проектные работы и согласования | F11: 1 | H11: 88.99 | I11: 0 | J11: типовая | N11: РАБ.Р1.1.064 — Сертификация помещения для совершения операций с ценностями, хранение ценностей по (2) классу вломостойкости и (3) классу пулестойкости
A12: РАБ.Р1.1.065 | B12: Сертификация помещения для совершения операций с ценностями, хранение ценностей по 3 классу вломостойкости и 3 классу пулестойкости | C12: м2 | D12: Р1 | E12: Проектные работы и согласования | F12: 1 | H12: 149.82 | I12: 0 | J12: типовая | N12: РАБ.Р1.1.065 — Сертификация помещения для совершения операций с ценностями, хранение ценностей по 3 классу вломостойкости и 3 классу пулестойкости
A13: РАБ.Р1.1.066 | B13: Сертификация помещения для совершения операций с ценностями, хранение ценностей по (5) классу вломостойкости | C13: м2 | D13: Р1 | E13: Проектные работы и согласования | F13: 1 | H13: 96.48 | I13: 0 | J13: типовая | N13: РАБ.Р1.1.066 — Сертификация помещения для совершения операций с ценностями, хранение ценностей по (5) классу вломостойкости
A14: РАБ.Р1.1.067 | B14: Технический отчет электролаборатории для помещений более 100 м.кв. | C14: м2 | D14: Р1 | E14: Проектные работы и согласования | F14: 1 | H14: 123.58 | I14: 0 | J14: типовая | N14: РАБ.Р1.1.067 — Технический отчет электролаборатории для помещений более 100 м.кв.
A15: РАБ.Р1.1.068 | B15: Технический отчет электролаборатории для помещений менее 100 м.кв. | C15: компл. | D15: Р1 | E15: Проектные работы и согласования | F15: 1 | H15: 13074.35 | I15: 0 | J15: типовая | N15: РАБ.Р1.1.068 — Технический отчет электролаборатории для помещений менее 100 м.кв.
A16: РАБ.Р1.1.069 | B16: Стоимость согласования проекта изменения фасада согласно нормативных и законодательных актов г. ___________ и РФ. | C16: м2 | D16: Р1 | E16: Проектные работы и согласования | F16: 1 | H16: 190.9 | I16: 0 | J16: нетиповая | N16: РАБ.Р1.1.069 — Стоимость согласования проекта изменения фасада согласно нормативных и законодательных актов г. ___________ и РФ.
A17: РАБ.Р1.1.070 | B17: Разработка дизайн-проекта интерьера | C17: м2 | D17: Р1 | E17: Проектные работы и согласования | F17: 1 | H17: 0 | I17: 0 | J17: типовая | N17: РАБ.Р1.1.070 — Разработка дизайн-проекта интерьера
... A161: РАБ.Р2.13.001 | B161: Демонтажные работы до состояния shell-and-core | C161: м2 | D161: Р2 | E161: Демонтажные работы | F161: 13 | H161: 2133.33 | I161: 0 | J161: типовая | N161: РАБ.Р2.13.001 — Демонтажные работы до состояния shell-and-core
A162: РАБ.Р3.1.001 | B162: Кладка перегородок толщиной в 1/2 кирпича | C162: м2 | D162: Р3 | E162: Внутренние строительные работы | F162: 1 | G162: КЛАДКА | H162: 2392.5 | I162: 5 | J162: типовая | N162: РАБ.Р3.1.001 — Кладка перегородок толщиной в 1/2 кирпича
A163: РАБ.Р3.1.002 | B163: Кладка перегородок армированных толщиной в 1 кирпич | C163: м2 | D163: Р3 | E163: Внутренние строительные работы | F163: 1 | G163: КЛАДКА | H163: 2704.48 | I163: 5 | J163: типовая | N163: РАБ.Р3.1.002 — Кладка перегородок армированных толщиной в 1 кирпич
A164: РАБ.Р3.1.003 | B164: Кладка перегородок из пеноблоков (600*300*200) | C164: м2 | D164: Р3 | E164: Внутренние строительные работы | F164: 1 | G164: КЛАДКА | H164: 2035.8 | I164: 5 | J164: типовая | N164: РАБ.Р3.1.003 — Кладка перегородок из пеноблоков (600*300*200)
A165: РАБ.Р3.1.004 | B165: Заделка проемов в кирпичных стенах | C165: м3 | D165: Р3 | E165: Внутренние строительные работы | F165: 1 | G165: КЛАДКА | H165: 9787.5 | I165: 5 | J165: типовая | N165: РАБ.Р3.1.004 — Заделка проемов в кирпичных стенах
A166: РАБ.Р3.1.005 | B166: Усиление проемов металлическим профилем из уголка 50*3 | C166: м.п. | D166: Р3 | E166: Внутренние строительные работы | F166: 1 | H166: 1045 | I166: 0 | J166: нетиповая | N166: РАБ.Р3.1.005 — Усиление проемов металлическим профилем из уголка 50*3
A167: РАБ.Р3.1.006 | B167: Усиление проемов металлическим профилем из уголка 100*100*10 | C167: м.п. | D167: Р3 | E167: Внутренние строительные работы | F167: 1 | H167: 2090 | I167: 0 | J167: нетиповая | N167: РАБ.Р3.1.006 — Усиление проемов металлическим профилем из уголка 100*100*10
A168: РАБ.Р3.1.007 | B168: Устройство перегородок из ГКЛ толщ. 12 мм. "Кнауф" с одинарным металлическим каркасом и однослойной обшивкой с обеих сторон (включая перфорированные уголки на внешние углы) | C168: м2 | D168: Р3 | E168: Внутренние строительные работы | F168: 1 | G168: ГКЛ | H168: 1722.6 | I168: 5 | J168: типовая | N168: РАБ.Р3.1.007 — Устройство перегородок из ГКЛ толщ. 12 мм. "Кнауф" с одинарным металлическим каркасом и однослойной обшивкой с обеих сторон (включая перфорированные уголки на внешние углы)
A169: РАБ.Р3.1.008 | B169: Устройство перегородок из ГКЛ толщ. 12 мм. "Кнауф" с одинарным металлическим каркасом и двухслойной обшивкой с обеих сторон (включая перфорированные уголки на внешние углы) | C169: м2 | D169: Р3 | E169: Внутренние строительные работы | F169: 1 | G169: ГКЛ | H169: 1894.86 | I169: 5 | J169: типовая | N169: РАБ.Р3.1.008 — Устройство перегородок из ГКЛ толщ. 12 мм. "Кнауф" с одинарным металлическим каркасом и двухслойной обшивкой с обеих сторон (включая перфорированные уголки на внешние углы)
A170: РАБ.Р3.1.009 | B170: Устройство перегородки / облицовки из ГКЛ | C170: м2 | D170: Р3 | E170: Внутренние строительные работы | F170: 1 | G170: ГКЛ | H170: 1305.22 | I170: 5 | J170: типовая | N170: РАБ.Р3.1.009 — Устройство перегородки / облицовки из ГКЛ
A171: РАБ.Р3.1.010 | B171: Устройство перегородки / облицовки из ГКЛ | C171: м2 | D171: Р3 | E171: Внутренние строительные работы | F171: 1 | G171: ГКЛ | H171: 1515.98 | I171: 5 | J171: типовая | N171: РАБ.Р3.1.010 — Устройство перегородки / облицовки из ГКЛ
A172: РАБ.Р3.1.011 | B172: Облицовка стен гипсокартонными листами (ГКЛ) "Кнауф" в один слой на клее (включая перфорированные уголки на внешние углы) | C172: м2 | D172: Р3 | E172: Внутренние строительные работы | F172: 1 | G172: ГКЛ | H172: 1357.2 | I172: 5 | J172: типовая | N172: РАБ.Р3.1.011 — Облицовка стен гипсокартонными листами (ГКЛ) "Кнауф" в один слой на клее (включая перфорированные уголки на внешние углы)
A173: РАБ.Р3.1.012 | B173: Устройство оконных откосов из ГКЛВ толщ. 12 мм. | C173: м2 | D173: Р3 | E173: Внутренние строительные работы | F173: 1 | G173: ГКЛ | H173: 1305 | I173: 5 | J173: типовая | N173: РАБ.Р3.1.012 — Устройство оконных откосов из ГКЛВ толщ. 12 мм.
A174: РАБ.Р3.1.013 | B174: Тепло- и звукоизоляция стен из минеральных материалов | C174: м2 | D174: Р3 | E174: Внутренние строительные работы | F174: 1 | G174: ИЗОЛ | H174: 106.14 | I174: 5 | J174: типовая | N174: РАБ.Р3.1.013 — Тепло- и звукоизоляция стен из минеральных материалов
A175: РАБ.Р3.1.014 | B175: Штукатурка стен | C175: м2 | D175: Р3 | E175: Внутренние строительные работы | F175: 1 | H175: 977.08 | I175: 0 | J175: типовая | N175: РАБ.Р3.1.014 — Штукатурка стен
A176: РАБ.Р3.1.015 | B176: Устройство штроб в кирпичных стенах | C176: м.п. | D176: Р3 | E176: Внутренние строительные работы | F176: 1 | G176: КЛАДКА | H176: 616.1 | I176: 5 | J176: типовая | N176: РАБ.Р3.1.015 — Устройство штроб в кирпичных стенах
A177: РАБ.Р3.1.016 | B177: Устройство штроб в конструкциях газосиликатных, керамзитобетонных, шлакобетонных, пенобетонных. | C177: м.п. | D177: Р3 | E177: Внутренние строительные работы | F177: 1 | H177: 585.2 | I177: 0 | J177: типовая | N177: РАБ.Р3.1.016 — Устройство штроб в конструкциях газосиликатных, керамзитобетонных, шлакобетонных, пенобетонных.
A178: РАБ.Р3.1.017 | B178: Пробивка отверстий в кирпичных стенах фасада, внутренних перегородках под прокладку труб ОВиК, электролотков, | C178: м3 | D178: Р3 | E178: Внутренние строительные работы | F178: 1 | G178: КЛАДКА | H178: 25414.48 | I178: 5 | J178: нетиповая | N178: РАБ.Р3.1.017 — Пробивка отверстий в кирпичных стенах фасада, внутренних перегородках под прокладку труб ОВиК, электролотков,
A179: РАБ.Р3.1.018 | B179: Пробивка отверстий в бетоных стенах фасада, внутренних перегородках под прокладку труб ОВиК, электролотков. | C179: м3 | D179: Р3 | E179: Внутренние строительные работы | F179: 1 | H179: 31115.45 | I179: 0 | J179: нетиповая | N179: РАБ.Р3.1.018 — Пробивка отверстий в бетоных стенах фасада, внутренних перегородках под прокладку труб ОВиК, электролотков.
A180: РАБ.Р3.1.019 | B180: Запенивание противопожарной пеной тех. отверстий прохода транзитных коммуникаций | C180: м2 | D180: Р3 | E180: Внутренние строительные работы | F180: 1 | H180: 500.21 | I180: 0 | J180: типовая | N180: РАБ.Р3.1.019 — Запенивание противопожарной пеной тех. отверстий прохода транзитных коммуникаций
A181: РАБ.Р3.1.020 | B181: Пробивка проемов в стенах из пенобетонных блоков | C181: м3 | D181: Р3 | E181: Внутренние строительные работы | F181: 1 | H181: 12214.8 | I181: 0 | J181: типовая | N181: РАБ.Р3.1.020 — Пробивка проемов в стенах из пенобетонных блоков
A182: РАБ.Р3.1.021 | B182: Пробивка проемов в стенах из кирпича | C182: м3 | D182: Р3 | E182: Внутренние строительные работы | F182: 1 | G182: КЛАДКА | H182: 10521.32 | I182: 5 | J182: типовая | N182: РАБ.Р3.1.021 — Пробивка проемов в стенах из кирпича
A183: РАБ.Р3.1.022 | B183: Алмазное сверление отверстий в стенах Ø50-100 мм | C183: см. | D183: Р3 | E183: Внутренние строительные работы | F183: 1 | H183: 76.37 | I183: 0 | J183: типовая | N183: РАБ.Р3.1.022 — Алмазное сверление отверстий в стенах Ø50-100 мм
A184: РАБ.Р3.1.023 | B184: Алмазное сверление отверстий в стенах Ø101-200 мм | C184: см. | D184: Р3 | E184: Внутренние строительные работы | F184: 1 | H184: 78.96 | I184: 0 | J184: типовая | N184: РАБ.Р3.1.023 — Алмазное сверление отверстий в стенах Ø101-200 мм
A185: РАБ.Р3.1.024 | B185: Алмазное сверление отверстий в стенах Ø201-300 мм | C185: см. | D185: Р3 | E185: Внутренние строительные работы | F185: 1 | H185: 134.85 | I185: 0 | J185: типовая | N185: РАБ.Р3.1.024 — Алмазное сверление отверстий в стенах Ø201-300 мм
A186: РАБ.Р3.1.025 | B186: Алмазное сверление отверстий в стенах Ø301-400 мм | C186: см. | D186: Р3 | E186: Внутренние строительные работы | F186: 1 | H186: 174 | I186: 0 | J186: типовая | N186: РАБ.Р3.1.025 — Алмазное сверление отверстий в стенах Ø301-400 мм
A187: РАБ.Р3.1.026 | B187: Монтаж закладных из фанеры 12мм под шкафы обработанная составом "NEOMID 450-1". | C187: м2 | D187: Р3 | E187: Внутренние строительные работы | F187: 1 | H187: 560 | I187: 0 | J187: типовая | N187: РАБ.Р3.1.026 — Монтаж закладных из фанеры 12мм под шкафы обработанная составом "NEOMID 450-1".
A188: РАБ.Р3.1.027 | B188: Устройство ниши ГКЛ по м/к под монтаж приборов отопления | C188: шт. | D188: Р3 | E188: Внутренние строительные работы | F188: 1 | G188: ГКЛ | H188: 3063.98 | I188: 5 | J188: типовая | N188: РАБ.Р3.1.027 — Устройство ниши ГКЛ по м/к под монтаж приборов отопления
A189: РАБ.Р3.1.028 | B189: Устройство пароизоляции из полиэтиленовой пленки до 100 мкр. | C189: м2 | D189: Р3 | E189: Внутренние строительные работы | F189: 1 | H189: 115.13 | I189: 0 | J189: типовая | N189: РАБ.Р3.1.028 — Устройство пароизоляции из полиэтиленовой пленки до 100 мкр.
A190: РАБ.Р3.1.029 | B190: Усиление проемов деревянным антисептированным бруском 50*50 | C190: м.п. | D190: Р3 | E190: Внутренние строительные работы | F190: 1 | H190: 490.94 | I190: 0 | J190: нетиповая | N190: РАБ.Р3.1.029 — Усиление проемов деревянным антисептированным бруском 50*50
A191: РАБ.Р3.1.030 | B191: Люк скрытый нажимной 300*300 | C191: шт. | D191: Р3 | E191: Внутренние строительные работы | F191: 1 | H191: 1788.72 | I191: 0 | J191: типовая | N191: РАБ.Р3.1.030 — Люк скрытый нажимной 300*300
A192: РАБ.Р3.1.031 | B192: Люк скрытый нажимной 400*600 | C192: шт. | D192: Р3 | E192: Внутренние строительные работы | F192: 1 | H192: 2401.2 | I192: 0 | J192: типовая | N192: РАБ.Р3.1.031 — Люк скрытый нажимной 400*600
A193: РАБ.Р3.1.032 | B193: Люк скрытый нажимной 500*600 | C193: шт. | D193: Р3 | E193: Внутренние строительные работы | F193: 1 | H193: 2554.32 | I193: 0 | J193: типовая | N193: РАБ.Р3.1.032 — Люк скрытый нажимной 500*600
A194: РАБ.Р3.1.033 | B194: Люк скрытый нажимной 600*600 | C194: шт. | D194: Р3 | E194: Внутренние строительные работы | F194: 1 | H194: 2924.94 | I194: 0 | J194: типовая | N194: РАБ.Р3.1.033 — Люк скрытый нажимной 600*600
A195: РАБ.Р3.1.034 | B195: Устройство коробов из ГКЛ до 600 мм шириной (для обшивки ригелей, балок колонн и т.д.) | C195: м.п. | D195: Р3 | E195: Внутренние строительные работы | F195: 1 | G195: ГКЛ | H195: 1733.48 | I195: 5 | J195: типовая | N195: РАБ.Р3.1.034 — Устройство коробов из ГКЛ до 600 мм шириной (для обшивки ригелей, балок колонн и т.д.)
A196: РАБ.Р3.2.001 | B196: Монтаж стеклянных бескаркасных перегородок , стекло 10 мм, закаленное с фурнитурой цвета матовая нержавеющая сталь | C196: м2 | D196: Р3 | E196: Внутренние строительные работы | F196: 2 | H196: 3065.04 | I196: 0 | J196: типовая | N196: РАБ.Р3.2.001 — Монтаж стеклянных бескаркасных перегородок , стекло 10 мм, закаленное с фурнитурой цвета матовая нержавеющая сталь
A197: РАБ.Р3.2.002 | B197: Устройство стеклянной перегородки в алюминиевом профиле по RAL. Стекло закаленное 6 мм. | C197: м2 | D197: Р3 | E197: Внутренние строительные работы | F197: 2 | G197: ПЕРЕГ.СТ | H197: 2210.33 | I197: 5 | J197: типовая | N197: РАБ.Р3.2.002 — Устройство стеклянной перегородки в алюминиевом профиле по RAL. Стекло закаленное 6 мм.
A198: РАБ.Р3.2.003 | B198: Устройство стеклянной перегородки в пластиковом профиле. Стекло закаленное 6 мм. | C198: м2 | D198: Р3 | E198: Внутренние строительные работы | F198: 2 | G198: ПЕРЕГ.СТ | H198: 2197.32 | I198: 5 | J198: типовая | N198: РАБ.Р3.2.003 — Устройство стеклянной перегородки в пластиковом профиле. Стекло закаленное 6 мм.
A199: РАБ.Р3.2.004 | B199: Оклейка стеклянных перегородок декоративной пленкой (перфорированной) с фоторисунком | C199: м2 | D199: Р3 | E199: Внутренние строительные работы | F199: 2 | H199: 1650 | I199: 0 | J199: типовая | N199: РАБ.Р3.2.004 — Оклейка стеклянных перегородок декоративной пленкой (перфорированной) с фоторисунком
A200: РАБ.Р3.2.005 | B200: Монтаж стеклянной перегородки | C200: м2 | D200: Р3 | E200: Внутренние строительные работы | F200: 2 | G200: ПЕРЕГ.СТ | H200: 5637.6 | I200: 5 | J200: типовая | N200: РАБ.Р3.2.005 — Монтаж стеклянной перегородки
A201: РАБ.Р3.2.006 | B201: Устройство фальшпола | C201: м2 | D201: Р3 | E201: Внутренние строительные работы | F201: 2 | G201: ФАЛЬШПОЛ | H201: 8143.2 | I201: 5 | J201: типовая | N201: РАБ.Р3.2.006 — Устройство фальшпола
A202: РАБ.Р3.2.007 | B202: Замок для трансформируемой перегородки типа «Т-009 PSS» | C202: шт. | D202: Р3 | E202: Внутренние строительные работы | F202: 2 | G202: ПЕРЕГ.ТР | H202: 720.36 | I202: 5 | J202: типовая | N202: РАБ.Р3.2.007 — Замок для трансформируемой перегородки типа «Т-009 PSS»
A203: РАБ.Р3.2.008 | B203: Цилиндр с заверткой для нижнего замка | C203: шт. | D203: Р3 | E203: Внутренние строительные работы | F203: 2 | H203: 250.56 | I203: 0 | J203: типовая | N203: РАБ.Р3.2.008 — Цилиндр с заверткой для нижнего замка
A204: РАБ.Р3.3.001 | B204: Обработка стен, поврежденных грибком антисептическим раствором за 2 раза | C204: м2 | D204: Р3 | E204: Внутренние строительные работы | F204: 3 | H204: 87 | I204: 0 | J204: типовая | N204: РАБ.Р3.3.001 — Обработка стен, поврежденных грибком антисептическим раствором за 2 раза
A205: РАБ.Р3.3.002 | B205: Шпатлевка швов, саморезов и примыканий стен и перегородок из ГКЛ | C205: м2 | D205: Р3 | E205: Внутренние строительные работы | F205: 3 | H205: 143.55 | I205: 0 | J205: типовая | N205: РАБ.Р3.3.002 — Шпатлевка швов, саморезов и примыканий стен и перегородок из ГКЛ
A206: РАБ.Р3.3.003 | B206: Шпатлевка стен | C206: м2 | D206: Р3 | E206: Внутренние строительные работы | F206: 3 | H206: 530.66 | I206: 0 | J206: типовая | N206: РАБ.Р3.3.003 — Шпатлевка стен
A207: РАБ.Р3.3.004 | B207: Шпатлевка стен по стеклохолсту | C207: м2 | D207: Р3 | E207: Внутренние строительные работы | F207: 3 | H207: 531.53 | I207: 0 | J207: типовая | N207: РАБ.Р3.3.004 — Шпатлевка стен по стеклохолсту
A208: РАБ.Р3.3.005 | B208: Сплошное выравние стен составами "Ветонит" толщиной до 10 мм | C208: м2 | D208: Р3 | E208: Внутренние строительные работы | F208: 3 | H208: 532.4 | I208: 0 | J208: типовая | N208: РАБ.Р3.3.005 — Сплошное выравние стен составами "Ветонит" толщиной до 10 мм
A209: РАБ.Р3.3.006 | B209: Грунтовка поверхности стен и перегородок за 2 раза | C209: м2 | D209: Р3 | E209: Внутренние строительные работы | F209: 3 | H209: 75.2 | I209: 0 | J209: типовая | N209: РАБ.Р3.3.006 — Грунтовка поверхности стен и перегородок за 2 раза
A210: РАБ.Р3.3.007 | B210: Окраска стен за 2 раза краской Tikkurila EURO 7 (колерованная) | C210: м2 | D210: Р3 | E210: Внутренние строительные работы | F210: 3 | G210: КРАСКА | H210: 350 | I210: 5 | J210: типовая | N210: РАБ.Р3.3.007 — Окраска стен за 2 раза краской Tikkurila EURO 7 (колерованная)
A211: РАБ.Р3.3.008 | B211: Оклейка стен стеклообоями типа "Паутинка" (нефактурными) | C211: м2 | D211: Р3 | E211: Внутренние строительные работы | F211: 3 | G211: ОБОИ | H211: 220 | I211: 5 | J211: типовая | N211: РАБ.Р3.3.008 — Оклейка стен стеклообоями типа "Паутинка" (нефактурными)
A212: РАБ.Р3.3.009 | B212: Ремонт штукатурки стен с расшивкой швов, отдельными местами до 1 м.кв. | C212: м2 | D212: Р3 | E212: Внутренние строительные работы | F212: 3 | H212: 977.08 | I212: 0 | J212: типовая | N212: РАБ.Р3.3.009 — Ремонт штукатурки стен с расшивкой швов, отдельными местами до 1 м.кв.
A213: РАБ.Р3.3.010 | B213: Облицовка стен керамической плиткой с затиркой швов. | C213: м2 | D213: Р3 | E213: Внутренние строительные работы | F213: 3 | G213: СТЕН.ПЛ | H213: 2307.71 | I213: 5 | J213: типовая | N213: РАБ.Р3.3.010 — Облицовка стен керамической плиткой с затиркой швов.
A214: РАБ.Р3.3.011 | B214: Облицовка стен керамической плиткой | C214: м2 | D214: Р3 | E214: Внутренние строительные работы | F214: 3 | G214: СТЕН.ПЛ | H214: 3048.05 | I214: 5 | J214: типовая | N214: РАБ.Р3.3.011 — Облицовка стен керамической плиткой
A215: РАБ.Р3.3.012 | B215: Бордюр 500*15 "Szklana T40" коллекциии "Oxford" " Ctramica Konskie" с затиркой швов. | C215: шт. | D215: Р3 | E215: Внутренние строительные работы | F215: 3 | H215: 339.3 | I215: 0 | J215: типовая | N215: РАБ.Р3.3.012 — Бордюр 500*15 "Szklana T40" коллекциии "Oxford" " Ctramica Konskie" с затиркой швов.
A216: РАБ.Р3.3.013 | B216: Установка пластиковых уголков на наружные углы колонн и стен | C216: м.п. | D216: Р3 | E216: Внутренние строительные работы | F216: 3 | H216: 297.58 | I216: 0 | J216: типовая | N216: РАБ.Р3.3.013 — Установка пластиковых уголков на наружные углы колонн и стен
A217: РАБ.Р3.3.014 | B217: Штукатурка поверхности | C217: м2 | D217: Р3 | E217: Внутренние строительные работы | F217: 3 | H217: 2926 | I217: 0 | J217: типовая | N217: РАБ.Р3.3.014 — Штукатурка поверхности
A218: РАБ.Р3.3.015 | B218: Оклейка стен стеклообоями типа "Рогожка" | C218: м2 | D218: Р3 | E218: Внутренние строительные работы | F218: 3 | G218: ОБОИ | H218: 475.02 | I218: 5 | J218: типовая | N218: РАБ.Р3.3.015 — Оклейка стен стеклообоями типа "Рогожка"
A219: РАБ.Р3.3.016 | B219: Декоративные крашенные МДФ ПАНЕЛИ 20ММ, ЦВЕТ RAL 7040, Швы - черный, П-образный профиль 10мм | C219: м2 | D219: Р3 | E219: Внутренние строительные работы | F219: 3 | H219: 1289.34 | I219: 0 | J219: типовая | N219: РАБ.Р3.3.016 — Декоративные крашенные МДФ ПАНЕЛИ 20ММ, ЦВЕТ RAL 7040, Швы - черный, П-образный профиль 10мм
A220: РАБ.Р3.3.017 | B220: Аккустическая панель из Войлока, максимальные размери 1200X2400см, клеиться на стену | C220: м2 | D220: Р3 | E220: Внутренние строительные работы | F220: 3 | H220: 548.06 | I220: 0 | J220: типовая | N220: РАБ.Р3.3.017 — Аккустическая панель из Войлока, максимальные размери 1200X2400см, клеиться на стену
A221: РАБ.Р3.3.018 | B221: Оклейка обоями / стеклохолстом | C221: м2 | D221: Р3 | E221: Внутренние строительные работы | F221: 3 | G221: ОБОИ | H221: 1628.64 | I221: 5 | J221: типовая | N221: РАБ.Р3.3.018 — Оклейка обоями / стеклохолстом
A222: РАБ.Р3.3.019 | B222: Оклейка поверхностей стен и перегородок Обои Голландские обои Eijffinger, коллекция Ibiza, артикул 330203 | C222: м2 | D222: Р3 | E222: Внутренние строительные работы | F222: 3 | G222: ОБОИ | H222: 474.15 | I222: 5 | J222: типовая | N222: РАБ.Р3.3.019 — Оклейка поверхностей стен и перегородок Обои Голландские обои Eijffinger, коллекция Ibiza, артикул 330203
A223: РАБ.Р3.3.020 | B223: Оклейка поверхностей стен и перегородок бумажными обоями (рисунок обоев выполняется "на заказ") | C223: м2 | D223: Р3 | E223: Внутренние строительные работы | F223: 3 | G223: ОБОИ | H223: 652.5 | I223: 5 | J223: типовая | N223: РАБ.Р3.3.020 — Оклейка поверхностей стен и перегородок бумажными обоями (рисунок обоев выполняется "на заказ")
A224: РАБ.Р3.4.001 | B224: Монтаж однопольного дверного блока (алюминиевый теплый профиль 3 петли, два врезных замка сувального типа (количество ключей не менее 4 шт.) без защелки , ручка из нержавеющей стал… | C224: шт. | D224: Р3 | E224: Внутренние строительные работы | F224: 4 | G224: ДВ.АЛ | H224: 5781.74 | I224: 5 | J224: типовая | N224: РАБ.Р3.4.001 — Монтаж однопольного дверного блока (алюминиевый теплый профиль 3 петли, два врезных замка сувального типа (количество ключей не менее 4 шт.) без защелки , ручка из нержавеющей стал…
A225: РАБ.Р3.4.002 | B225: Монтаж полуторапольного дверного блока (алюминиевый теплый профиль 3 петли, два врезных замка сувального типа (количество ключей не менее 4 шт.) без защелки , ручка из нержавеющей … | C225: шт. | D225: Р3 | E225: Внутренние строительные работы | F225: 4 | G225: ДВ.АЛ | H225: 7892.64 | I225: 5 | J225: типовая | N225: РАБ.Р3.4.002 — Монтаж полуторапольного дверного блока (алюминиевый теплый профиль 3 петли, два врезных замка сувального типа (количество ключей не менее 4 шт.) без защелки , ручка из нержавеющей …
A226: РАБ.Р3.4.003 | B226: Монтаж двупольного дверного блока (алюминиевый теплый профиль 3 петли, два врезных замка сувального типа (количество ключей не менее 4 шт.) без защелки , ручка из нержавеющей стали… | C226: шт. | D226: Р3 | E226: Внутренние строительные работы | F226: 4 | G226: ДВ.АЛ | H226: 9900 | I226: 5 | J226: типовая | N226: РАБ.Р3.4.003 — Монтаж двупольного дверного блока (алюминиевый теплый профиль 3 петли, два врезных замка сувального типа (количество ключей не менее 4 шт.) без защелки , ручка из нержавеющей стали…
A227: РАБ.Р3.4.004 | B227: Монтаж дверного блока / дверных приборов | C227: шт. | D227: Р3 | E227: Внутренние строительные работы | F227: 4 | G227: ДВ | H227: 1280.13 | I227: 5 | J227: типовая | N227: РАБ.Р3.4.004 — Монтаж дверного блока / дверных приборов
A228: РАБ.Р3.4.005 | B228: Монтаж дверного блока / дверных приборов | C228: шт. | D228: Р3 | E228: Внутренние строительные работы | F228: 4 | G228: ДВ | H228: 10648.8 | I228: 5 | J228: типовая | N228: РАБ.Р3.4.005 — Монтаж дверного блока / дверных приборов
A229: РАБ.Р3.4.006 | B229: Дверной блок утепленый, полуторастворчатый размером по раме 2100Нх1400 мм (размер двери в свету 2000Нх1200 мм), полотна из листов металла 2+2 мм (наружный и внутренние листы). Рабо… | C229: шт. | D229: Р3 | E229: Внутренние строительные работы | F229: 4 | G229: КРАСКА | H229: 13154.4 | I229: 5 | J229: типовая | N229: РАБ.Р3.4.006 — Дверной блок утепленый, полуторастворчатый размером по раме 2100Нх1400 мм (размер двери в свету 2000Нх1200 мм), полотна из листов металла 2+2 мм (наружный и внутренние листы). Рабо…
A230: РАБ.Р3.4.007 | B230: Доводчик на рабочую створку NOTEDO DC-025-095 (со скользящим каналом). Доводчик на паразитную створку NOTEDO DC-070 (паук) | C230: шт. | D230: Р3 | E230: Внутренние строительные работы | F230: 4 | G230: ДВ | H230: 1315.44 | I230: 5 | J230: типовая | N230: РАБ.Р3.4.007 — Доводчик на рабочую створку NOTEDO DC-025-095 (со скользящим каналом). Доводчик на паразитную створку NOTEDO DC-070 (паук)
A231: РАБ.Р3.4.008 | B231: Установка металлической двери-решетчатой гармошки с замком 900х2100 мм (запасной выход) | C231: шт. | D231: Р3 | E231: Внутренние строительные работы | F231: 4 | G231: ДВ.БР | H231: 11901.6 | I231: 5 | J231: нетиповая | N231: РАБ.Р3.4.008 — Установка металлической двери-решетчатой гармошки с замком 900х2100 мм (запасной выход)
A232: РАБ.Р3.4.009 | B232: Монтаж дверного блока стеклянного | C232: шт. | D232: Р3 | E232: Внутренние строительные работы | F232: 4 | G232: ДВ.СТ | H232: 9350 | I232: 5 | J232: типовая | N232: РАБ.Р3.4.009 — Монтаж дверного блока стеклянного
... A237: РАБ.Р3.4.014 | B237: фрезеровка под Eff-Eff 34 12 V DC (34-E91) с длинными планками Eff-Eff HZ (021 35) (-------02135-01) (предоставляет заказчик), защищенный стальной гибкий переход для кабеля, прокла… | C237: шт. | D237: Р3 | E237: Внутренние строительные работы | F237: 4 | G237: ДВ | H237: 1503.36 | I237: 5 | J237: типовая | N237: РАБ.Р3.4.014 — фрезеровка под Eff-Eff 34 12 V DC (34-E91) с длинными планками Eff-Eff HZ (021 35) (-------02135-01) (предоставляет заказчик), защищенный стальной гибкий переход для кабеля, прокла…
A238: РАБ.Р3.4.015 | B238: Комплект антипаника Doorlock на активную створку DL PD800FR-BAR (или аналог по согласованию заказчика) | C238: шт. | D238: Р3 | E238: Внутренние строительные работы | F238: 4 | H238: 2192.4 | I238: 0 | J238: типовая | N238: РАБ.Р3.4.015 — Комплект антипаника Doorlock на активную створку DL PD800FR-BAR (или аналог по согласованию заказчика)
A239: РАБ.Р3.4.016 | B239: Монтаж дверного блока деревянного | C239: шт. | D239: Р3 | E239: Внутренние строительные работы | F239: 4 | G239: ДВ.ДЕР | H239: 7297.56 | I239: 5 | J239: типовая | N239: РАБ.Р3.4.016 — Монтаж дверного блока деревянного
A240: РАБ.Р3.4.017 | B240: Установка стопора дверного Standers, 3.5х3.2 см, нержавеющая сталь | C240: шт. | D240: Р3 | E240: Внутренние строительные работы | F240: 4 | G240: ДВ | H240: 224.46 | I240: 5 | J240: типовая | N240: РАБ.Р3.4.017 — Установка стопора дверного Standers, 3.5х3.2 см, нержавеющая сталь
A241: РАБ.Р3.4.018 | B241: Монтаж оконного блока / светопрозрачной конструкции | C241: м2 | D241: Р3 | E241: Внутренние строительные работы | F241: 4 | G241: ОКНО | H241: 2750 | I241: 5 | J241: типовая | N241: РАБ.Р3.4.018 — Монтаж оконного блока / светопрозрачной конструкции
A242: РАБ.Р3.4.019 | B242: Окраска поверхности | C242: м2 | D242: Р3 | E242: Внутренние строительные работы | F242: 4 | G242: КРАСКА | H242: 1252.8 | I242: 5 | J242: типовая | N242: РАБ.Р3.4.019 — Окраска поверхности
A243: РАБ.Р3.4.020 | B243: Установка рулонных штор | C243: м2 | D243: Р3 | E243: Внутренние строительные работы | F243: 4 | G243: ЖАЛЮЗИ | H243: 220 | I243: 5 | J243: типовая | N243: РАБ.Р3.4.020 — Установка рулонных штор
A244: РАБ.Р3.4.021 | B244: Установка жалюзи вертикальных серии Line | C244: м2 | D244: Р3 | E244: Внутренние строительные работы | F244: 4 | G244: ЖАЛЮЗИ | H244: 330 | I244: 5 | J244: типовая | N244: РАБ.Р3.4.021 — Установка жалюзи вертикальных серии Line
A245: РАБ.Р3.4.022 | B245: Установка подоконной доски | C245: м.п. | D245: Р3 | E245: Внутренние строительные работы | F245: 4 | G245: ПОДОК | H245: 888.25 | I245: 5 | J245: типовая | N245: РАБ.Р3.4.022 — Установка подоконной доски
A246: РАБ.Р3.4.023 | B246: Установка оконных отливов с окраской по RAL | C246: м.п. | D246: Р3 | E246: Внутренние строительные работы | F246: 4 | G246: КРАСКА | H246: 599.39 | I246: 5 | J246: типовая | N246: РАБ.Р3.4.023 — Установка оконных отливов с окраской по RAL
A247: РАБ.Р3.4.024 | B247: Оклейка окон, стеклянных поверхностей дверных полотен пленкой класса защиты А3 | C247: м2 | D247: Р3 | E247: Внутренние строительные работы | F247: 4 | G247: ПЛЁНКА | H247: 2000 | I247: 5 | J247: типовая | N247: РАБ.Р3.4.024 — Оклейка окон, стеклянных поверхностей дверных полотен пленкой класса защиты А3
...

Sheet Материалы
A1: Код_материала | B1: Наименование | C1: Артикул | D1: Производитель | E1: Поставщик | F1: Ед_изм | G1: Группа_материалов | H1: Цена | I1: Валюта | J1: Примечание | K1: Дата изм. цены | L1: Кто изменил / обоснование | M1: КОД — Наименование (служебный)
A2: МАТ.VRF.ВНУТ.001 | B2: BMS interface HCM-04 | C2: HCM-04 | D2: Haier | E2: Хайер | F2: шт | G2: VRF.ВНУТ | H2: 1791.3 | I2: USD | M2: МАТ.VRF.ВНУТ.001 — BMS interface HCM-04
A3: МАТ.VRF.ВНУТ.002 | B3: Inverter Protocol Adapter IGU02 | C3: IGU02 | D3: Haier | E3: Хайер | F3: шт | G3: VRF.ВНУТ | H3: 294 | I3: USD | M3: МАТ.VRF.ВНУТ.002 — Inverter Protocol Adapter IGU02
A4: МАТ.VRF.ВНУТ.003 | B4: MDVI3-100C4VR12D | D4: MDV | E4: Дженерал-Трейд (АЯК) | F4: шт | G4: VRF.ВНУТ | H4: 1014.13 | I4: USD | J4: 10.0 кВт охл. | M4: МАТ.VRF.ВНУТ.003 — MDVI3-100C4VR12D
A5: МАТ.VRF.ВНУТ.004 | B5: MDVI3-100CFVR12D | D5: MDV | E5: Дженерал-Трейд (АЯК) | F5: шт | G5: VRF.ВНУТ | H5: 1135.82 | I5: USD | J5: 10.0 кВт охл. | M5: МАТ.VRF.ВНУТ.004 — MDVI3-100CFVR12D
A6: МАТ.VRF.ВНУТ.005 | B6: MDVI3-112C4VR12D | D6: MDV | E6: Дженерал-Трейд (АЯК) | F6: шт | G6: VRF.ВНУТ | H6: 1182.36 | I6: USD | J6: 11.2 кВт охл. | M6: МАТ.VRF.ВНУТ.005 — MDVI3-112C4VR12D
A7: МАТ.VRF.ВНУТ.006 | B7: MDVI3-112CFVR12D | D7: MDV | E7: Дженерал-Трейд (АЯК) | F7: шт | G7: VRF.ВНУТ | H7: 1166.14 | I7: USD | J7: 11.2 кВт охл. | M7: МАТ.VRF.ВНУТ.006 — MDVI3-112CFVR12D
A8: МАТ.VRF.ВНУТ.007 | B8: MDVI3-112D1VR12D | D8: MDV | E8: Дженерал-Трейд (АЯК) | F8: шт | G8: VRF.ВНУТ | H8: 877.49 | I8: USD | J8: 11.2 кВт охл. | M8: МАТ.VRF.ВНУТ.007 — MDVI3-112D1VR12D
A9: МАТ.VRF.ВНУТ.008 | B9: MDVI3-112D2VR12D | D9: MDV | E9: Дженерал-Трейд (АЯК) | F9: шт | G9: VRF.ВНУТ | H9: 802.76 | I9: USD | J9: 11.2 кВт охл. | M9: МАТ.VRF.ВНУТ.008 — MDVI3-112D2VR12D
A10: МАТ.VRF.ВНУТ.009 | B10: MDVI3-112D3VR12D | D10: MDV | E10: Дженерал-Трейд (АЯК) | F10: шт | G10: VRF.ВНУТ | H10: 1099.95 | I10: USD | J10: 11.2 кВт охл. | M10: МАТ.VRF.ВНУТ.009 — MDVI3-112D3VR12D
A11: МАТ.VRF.ВНУТ.010 | B11: MDVI3-125CFVR12D | D11: MDV | E11: Дженерал-Трейд (АЯК) | F11: шт | G11: VRF.ВНУТ | H11: 1221.22 | I11: USD | J11: 12.5 кВт охл. | M11: МАТ.VRF.ВНУТ.010 — MDVI3-125CFVR12D
A12: МАТ.VRF.ВНУТ.011 | B12: MDVI3-125D2VR12D | D12: MDV | E12: Дженерал-Трейд (АЯК) | F12: шт | G12: VRF.ВНУТ | H12: 821.12 | I12: USD | J12: 12.5 кВт охл. | M12: МАТ.VRF.ВНУТ.011 — MDVI3-125D2VR12D
A13: МАТ.VRF.ВНУТ.012 | B13: MDVI3-125D3VR12D | D13: MDV | E13: Дженерал-Трейд (АЯК) | F13: шт | G13: VRF.ВНУТ | H13: 1133.26 | I13: USD | J13: 12.5 кВт охл. | M13: МАТ.VRF.ВНУТ.012 — MDVI3-125D3VR12D
A14: МАТ.VRF.ВНУТ.013 | B14: MDVI3-140C4VR12D | D14: MDV | E14: Дженерал-Трейд (АЯК) | F14: шт | G14: VRF.ВНУТ | H14: 1228.91 | I14: USD | J14: 14.0 кВт охл. | M14: МАТ.VRF.ВНУТ.013 — MDVI3-140C4VR12D
A15: МАТ.VRF.ВНУТ.014 | B15: MDVI3-140CFVR12D | D15: MDV | E15: Дженерал-Трейд (АЯК) | F15: шт | G15: VRF.ВНУТ | H15: 1233.6 | I15: USD | J15: 14.0 кВт охл. | M15: МАТ.VRF.ВНУТ.014 — MDVI3-140CFVR12D
... A134: МАТ.VRF.ВНУТ.133 | B134: MDVI3-90OAVR12D(A) | D134: MDV | E134: Дженерал-Трейд (АЯК) | F134: шт | G134: VRF.ВНУТ | H134: 1026.08 | I134: USD | J134: 9.0 кВт охл. | M134: МАТ.VRF.ВНУТ.133 — MDVI3-90OAVR12D(A)
A135: МАТ.VRF.ВНУТ.134 | B135: WI-FI модуль для управления центральным пультом HC-SA164DBT HI-WA164DBI | C135: HI-WA164DBI | D135: Haier | E135: Хайер | F135: шт | G135: VRF.ВНУТ | H135: 39.9 | I135: USD | M135: МАТ.VRF.ВНУТ.134 — WI-FI модуль для управления центральным пультом HC-SA164DBT HI-WA164DBI
A136: МАТ.VRF.ВНУТ.135 | B136: Жалюзи к канальным блокам серии AD…MSERA P1B-1210IA | C136: P1B-1210IA | D136: Haier | E136: Хайер | F136: шт | G136: VRF.ВНУТ | H136: 61.95 | I136: USD | M136: МАТ.VRF.ВНУТ.135 — Жалюзи к канальным блокам серии AD…MSERA P1B-1210IA
A137: МАТ.VRF.ВНУТ.136 | B137: Жалюзи к канальным блокам серии AD…MSERA P1B-1210IA(D) с дисплеем | C137: P1B-1210IA(D) с дисплеем | D137: Haier | E137: Хайер | F137: шт | G137: VRF.ВНУТ | H137: 88.2 | I137: USD | M137: МАТ.VRF.ВНУТ.136 — Жалюзи к канальным блокам серии AD…MSERA P1B-1210IA(D) с дисплеем
A138: МАТ.VRF.ВНУТ.137 | B138: Жалюзи к канальным блокам серии AD…MSERA P1B-890IA | C138: P1B-890IA | D138: Haier | E138: Хайер | F138: шт | G138: VRF.ВНУТ | H138: 51.45 | I138: USD | M138: МАТ.VRF.ВНУТ.137 — Жалюзи к канальным блокам серии AD…MSERA P1B-890IA
A139: МАТ.VRF.ВНУТ.138 | B139: Жалюзи к канальным блокам серии AD…MSERA P1B-890IA(D) с дисплеем | C139: P1B-890IA(D) с дисплеем | D139: Haier | E139: Хайер | F139: шт | G139: VRF.ВНУТ | H139: 72.45 | I139: USD | M139: МАТ.VRF.ВНУТ.138 — Жалюзи к канальным блокам серии AD…MSERA P1B-890IA(D) с дисплеем
A140: МАТ.VRF.ВНУТ.139 | B140: ИК-пульт YR-HQS01 | C140: YR-HQS01 | D140: Haier | E140: Хайер | F140: шт | G140: VRF.ВНУТ | H140: 27.3 | I140: USD | M140: МАТ.VRF.ВНУТ.139 — ИК-пульт YR-HQS01
A141: МАТ.VRF.ВНУТ.140 | B141: ИК-пульт YR-HRS01 | C141: YR-HRS01 | D141: Haier | E141: Хайер | F141: шт | G141: VRF.ВНУТ | H141: 13.65 | I141: USD | M141: МАТ.VRF.ВНУТ.140 — ИК-пульт YR-HRS01
A142: МАТ.VRF.ВНУТ.141 | B142: Канальный 12K AD122MJERA | C142: AD122MJERA | D142: Haier | E142: Хайер | F142: шт | G142: VRF.ВНУТ | H142: 567 | I142: USD | M142: МАТ.VRF.ВНУТ.141 — Канальный 12K AD122MJERA
A143: МАТ.VRF.ВНУТ.142 | B143: Канальный 12K AD122MJERAD | C143: AD122MJERAD | D143: Haier | E143: Хайер | F143: шт | G143: VRF.ВНУТ | H143: 748.65 | I143: USD | M143: МАТ.VRF.ВНУТ.142 — Канальный 12K AD122MJERAD
A144: МАТ.VRF.ВНУТ.143 | B144: Канальный 12K AD122MSERA | C144: AD122MSERA | D144: Haier | E144: Хайер | F144: шт | G144: VRF.ВНУТ | H144: 340.2 | I144: USD | M144: МАТ.VRF.ВНУТ.143 — Канальный 12K AD122MSERA
A145: МАТ.VRF.ВНУТ.144 | B145: Канальный 12K AD122MSERA (D) | C145: AD122MSERA (D) | D145: Haier | E145: Хайер | F145: шт | G145: VRF.ВНУТ | H145: 442.05 | I145: USD | M145: МАТ.VRF.ВНУТ.144 — Канальный 12K AD122MSERA (D)
A146: МАТ.VRF.ВНУТ.145 | B146: Канальный 16K AD162MJERA | C146: AD162MJERA | D146: Haier | E146: Хайер | F146: шт | G146: VRF.ВНУТ | H146: 590.1 | I146: USD | M146: МАТ.VRF.ВНУТ.145 — Канальный 16K AD162MJERA
... A259: МАТ.VRF.ВНУТ.258 | B259: Шлюз для интеграции с Modbus new HA-MA164ADB | C259: HA-MA164ADB | D259: Haier | E259: Хайер | F259: шт | G259: VRF.ВНУТ | H259: 328.65 | I259: USD | M259: МАТ.VRF.ВНУТ.258 — Шлюз для интеграции с Modbus new HA-MA164ADB
A260: МАТ.VRF.НАР.001 | B260: MDV-V81010V2R1A(MA) | D260: MDV | E260: Дженерал-Трейд (АЯК) | F260: шт | G260: VRF.НАР | H260: 20867.92 | I260: USD | J260: 101.0 кВт охл. | M260: МАТ.VRF.НАР.001 — MDV-V81010V2R1A(MA)
A261: МАТ.VRF.НАР.002 | B261: MDV-V81060V2R1A(MA) | D261: MDV | E261: Дженерал-Трейд (АЯК) | F261: шт | G261: VRF.НАР | H261: 22505.46 | I261: USD | J261: 106.0 кВт охл. | M261: МАТ.VRF.НАР.002 — MDV-V81060V2R1A(MA)
A262: МАТ.VRF.НАР.003 | B262: MDV-V81120V2R1A(MA) | D262: MDV | E262: Дженерал-Трейд (АЯК) | F262: шт | G262: VRF.НАР | H262: 23020 | I262: USD | J262: 112.0 кВт охл. | M262: МАТ.VRF.НАР.003 — MDV-V81120V2R1A(MA)
A263: МАТ.VRF.НАР.004 | B263: MDV-V8252V2R1A(MA) | D263: MDV | E263: Дженерал-Трейд (АЯК) | F263: шт | G263: VRF.НАР | H263: 7779.94 | I263: USD | J263: 25.2 кВт охл. | M263: МАТ.VRF.НАР.004 — MDV-V8252V2R1A(MA)
A264: МАТ.VRF.НАР.005 | B264: MDV-V8280V2R1A(MA) | D264: MDV | E264: Дженерал-Трейд (АЯК) | F264: шт | G264: VRF.НАР | H264: 8384.57 | I264: USD | J264: 28.0 кВт охл. | M264: МАТ.VRF.НАР.005 — MDV-V8280V2R1A(MA)
A265: МАТ.VRF.НАР.006 | B265: MDV-V8335V2R1A(MA) | D265: MDV | E265: Дженерал-Трейд (АЯК) | F265: шт | G265: VRF.НАР | H265: 8922.59 | I265: USD | J265: 33.5 кВт охл. | M265: МАТ.VRF.НАР.006 — MDV-V8335V2R1A(MA)
A266: МАТ.VRF.НАР.007 | B266: MDV-V8400V2R1A(MA) | D266: MDV | E266: Дженерал-Трейд (АЯК) | F266: шт | G266: VRF.НАР | H266: 10215.12 | I266: USD | J266: 40.0 кВт охл. | M266: МАТ.VRF.НАР.007 — MDV-V8400V2R1A(MA)
A267: МАТ.VRF.НАР.008 | B267: MDV-V8450V2R1A(MA) | D267: MDV | E267: Дженерал-Трейд (АЯК) | F267: шт | G267: VRF.НАР | H267: 10720.26 | I267: USD | J267: 45.0 кВт охл. | M267: МАТ.VRF.НАР.008 — MDV-V8450V2R1A(MA)
A268: МАТ.VRF.НАР.009 | B268: MDV-V8500V2R1A(MA) | D268: MDV | E268: Дженерал-Трейд (АЯК) | F268: шт | G268: VRF.НАР | H268: 12516.65 | I268: USD | J268: 50.0 кВт охл. | M268: МАТ.VRF.НАР.009 — MDV-V8500V2R1A(MA)
A269: МАТ.VRF.НАР.010 | B269: MDV-V8560V2R1A(MA) | D269: MDV | E269: Дженерал-Трейд (АЯК) | F269: шт | G269: VRF.НАР | H269: 13211.81 | I269: USD | J269: 56.0 кВт охл. | M269: МАТ.VRF.НАР.010 — MDV-V8560V2R1A(MA)
A270: МАТ.VRF.НАР.011 | B270: MDV-V8615V2R1A(MA) | D270: MDV | E270: Дженерал-Трейд (АЯК) | F270: шт | G270: VRF.НАР | H270: 14202.45 | I270: USD | J270: 61.5 кВт охл. | M270: МАТ.VRF.НАР.011 — MDV-V8615V2R1A(MA)
A271: МАТ.VRF.НАР.012 | B271: MDV-V8670V2R1A(MA) | D271: MDV | E271: Дженерал-Трейд (АЯК) | F271: шт | G271: VRF.НАР | H271: 16027.87 | I271: USD | J271: 67.0 кВт охл. | M271: МАТ.VRF.НАР.012 — MDV-V8670V2R1A(MA)
... A332: МАТ.VRF.НАР.073 | B332: MDVO-VCM850V2R1A | D332: MDV | E332: Дженерал-Трейд (АЯК) | F332: шт | G332: VRF.НАР | H332: 10031.08 | I332: USD | J332: 85.0 кВт охл. | M332: МАТ.VRF.НАР.073 — MDVO-VCM850V2R1A
A333: МАТ.VRF.НАР.074 | B333: MRV III - S Внешний блок 10HP AU10NFKERA | C333: AU10NFKERA | D333: Haier | E333: Хайер | F333: шт | G333: VRF.НАР | H333: 3265.5 | I333: USD | M333: МАТ.VRF.НАР.074 — MRV III - S Внешний блок 10HP AU10NFKERA
A334: МАТ.VRF.НАР.075 | B334: MRV III - S Внешний блок 12HP AU12NFKERA | C334: AU12NFKERA | D334: Haier | E334: Хайер | F334: шт | G334: VRF.НАР | H334: 3378.9 | I334: USD | M334: МАТ.VRF.НАР.075 — MRV III - S Внешний блок 12HP AU12NFKERA
A335: МАТ.VRF.НАР.076 | B335: MRV III - S Внешний блок 3HP AU032FSEUA | C335: AU032FSEUA | D335: Haier | E335: Хайер | F335: шт | G335: VRF.НАР | H335: 1304.1 | I335: USD | M335: МАТ.VRF.НАР.076 — MRV III - S Внешний блок 3HP AU032FSEUA
A336: МАТ.VRF.НАР.077 | B336: MRV III - S Внешний блок 4HP AU042FNERA | C336: AU042FNERA | D336: Haier | E336: Хайер | F336: шт | G336: VRF.НАР | H336: 2064.3 | I336: USD | M336: МАТ.VRF.НАР.077 — MRV III - S Внешний блок 4HP AU042FNERA
A337: МАТ.VRF.НАР.078 | B337: MRV III - S Внешний блок 4HP AU042FPERA | C337: AU042FPERA | D337: Haier | E337: Хайер | F337: шт | G337: VRF.НАР | H337: 2313.15 | I337: USD | M337: МАТ.VRF.НАР.078 — MRV III - S Внешний блок 4HP AU042FPERA
A338: МАТ.VRF.НАР.079 | B338: MRV III - S Внешний блок 4HP AU04IFPERA | C338: AU04IFPERA | D338: Haier | E338: Хайер | F338: шт | G338: VRF.НАР | H338: 2313.15 | I338: USD | M338: МАТ.VRF.НАР.079 — MRV III - S Внешний блок 4HP AU04IFPERA
A339: МАТ.VRF.НАР.080 | B339: MRV III - S Внешний блок 5HP AU052FNERA | C339: AU052FNERA | D339: Haier | E339: Хайер | F339: шт | G339: VRF.НАР | H339: 2074.8 | I339: USD | M339: МАТ.VRF.НАР.080 — MRV III - S Внешний блок 5HP AU052FNERA
A340: МАТ.VRF.НАР.081 | B340: MRV III - S Внешний блок 5HP AU052FPERA | C340: AU052FPERA | D340: Haier | E340: Хайер | F340: шт | G340: VRF.НАР | H340: 2324.7 | I340: USD | M340: МАТ.VRF.НАР.081 — MRV III - S Внешний блок 5HP AU052FPERA
A341: МАТ.VRF.НАР.082 | B341: MRV III - S Внешний блок 5HP AU052FPEUA | C341: AU052FPEUA | D341: Haier | E341: Хайер | F341: шт | G341: VRF.НАР | H341: 2256.45 | I341: USD | M341: МАТ.VRF.НАР.082 — MRV III - S Внешний блок 5HP AU052FPEUA
A342: МАТ.VRF.НАР.083 | B342: MRV III - S Внешний блок 5HP AU05IFPERA | C342: AU05IFPERA | D342: Haier | E342: Хайер | F342: шт | G342: VRF.НАР | H342: 2324.7 | I342: USD | M342: МАТ.VRF.НАР.083 — MRV III - S Внешний блок 5HP AU05IFPERA
A343: МАТ.VRF.НАР.084 | B343: MRV III - S Внешний блок 6HP AU062FPERA | C343: AU062FPERA | D343: Haier | E343: Хайер | F343: шт | G343: VRF.НАР | H343: 2336.25 | I343: USD | M343: МАТ.VRF.НАР.084 — MRV III - S Внешний блок 6HP AU062FPERA
A344: МАТ.VRF.НАР.085 | B344: MRV III - S Внешний блок 6HP AU06IFPERA | C344: AU06IFPERA | D344: Haier | E344: Хайер | F344: шт | G344: VRF.НАР | H344: 2336.25 | I344: USD | M344: МАТ.VRF.НАР.085 — MRV III - S Внешний блок 6HP AU06IFPERA
... A360: МАТ.VRF.НАР.101 | B360: Рефнет для наружных блоков MRV V HZG-30B | C360: HZG-30B | D360: Haier | E360: Хайер | F360: шт | G360: VRF.НАР | H360: 277.2 | I360: USD | M360: МАТ.VRF.НАР.101 — Рефнет для наружных блоков MRV V HZG-30B
A361: МАТ.БРОНЯ.001 | B361: Бронестекло ПУз-Бр3 (1000*1000 мм. Видимая часть). По раме 1090х1090 мм без учета лотка. ЛИСТ 2. | E361: СПЕЦ Прожект групп | F361: шт. | G361: БРОНЯ | H361: 52500 | I361: RUB | M361: МАТ.БРОНЯ.001 — Бронестекло ПУз-Бр3 (1000*1000 мм. Видимая часть). По раме 1090х1090 мм без учета лотка. ЛИСТ 2.
A362: МАТ.БРОНЯ.002 | B362: Бронестекло ПУз-Бр3 (1090*1335 мм. ). С учетом лотка. ЛИСТ 1. | E362: СПЕЦ Прожект групп | F362: шт. | G362: БРОНЯ | H362: 105000 | I362: RUB | M362: МАТ.БРОНЯ.002 — Бронестекло ПУз-Бр3 (1090*1335 мм. ). С учетом лотка. ЛИСТ 1.
A363: МАТ.БРОНЯ.003 | B363: Дверной блок 2-го класса устойчивости к взлому (дверное полотно 758*2010). Размер по раме 850х2100 мм. Цилиндровый механизм с перекодировкой со штоком Securemme K2. Гардиан сувальдный ЗВ 71.14 Т (К-К). Без наличников. ЛИСТ 11. RAL7047. Упаковка изоло | E363: СПЕЦ Прожект групп | F363: шт. | G363: БРОНЯ | H363: 87150 | I363: RUB | J363: См. ТЗ "Двери 2 кл" | M363: МАТ.БРОНЯ.003 — Дверной блок 2-го класса устойчивости к взлому (дверное полотно 758*2010). Размер по раме 850х2100 мм. Цилиндровый механизм с перекодировкой со штоком Securemme K2. Гардиан сувальдный ЗВ 71.14 Т (К-К). Без наличников. ЛИСТ 11. RAL7047. Упаковка изоло
A364: МАТ.БРОНЯ.004 | B364: Дверной блок 2-го класса устойчивости к взлому (дверное полотно 858*2110). Размер по раме 950х2200 мм. Цилиндровый механизм с перекодировкой со штоком Securemme K2. Гардиан сувальдный ЗВ 71.14 Т (К-К). Без наличников. ЛИСТ 10. RAL7047. Упаковка изоло | E364: СПЕЦ Прожект групп | F364: шт. | G364: БРОНЯ | H364: 88725 | I364: RUB | J364: См. ТЗ "Двери 2 кл" | M364: МАТ.БРОНЯ.004 — Дверной блок 2-го класса устойчивости к взлому (дверное полотно 858*2110). Размер по раме 950х2200 мм. Цилиндровый механизм с перекодировкой со штоком Securemme K2. Гардиан сувальдный ЗВ 71.14 Т (К-К). Без наличников. ЛИСТ 10. RAL7047. Упаковка изоло
A365: МАТ.БРОНЯ.005 | B365: Дверной блок 3-го класса устойчивости к взлому с решетчатой дверью (дверное полотно 908*2110). Размер по раме 1000х2200 мм. Размер по раме 1000х2200 мм. Два замка Гардиан 71.14Т сувальдного типа на расстоянии не менее 350 мм друг от друга по замочным | E365: СПЕЦ Прожект групп | F365: шт. | G365: БРОНЯ | H365: 148575 | I365: RUB | J365: См. ТЗ "Двери 3 кл" | M365: МАТ.БРОНЯ.005 — Дверной блок 3-го класса устойчивости к взлому с решетчатой дверью (дверное полотно 908*2110). Размер по раме 1000х2200 мм. Размер по раме 1000х2200 мм. Два замка Гардиан 71.14Т сувальдного типа на расстоянии не менее 350 мм друг от друга по замочным
A366: МАТ.БРОНЯ.006 | B366: Дверной блок 5-го класса устойчивости к взлому с решетчатой дверью . 2 замка СИ600 (дверное полотно 898*1970), 1030х2100 мм по раме. ЛИСТ 13. | E366: СПЕЦ Прожект групп | F366: шт. | G366: БРОНЯ | H366: 223650 | I366: RUB | J366: См. ТЗ "Двери 5 кл." | M366: МАТ.БРОНЯ.006 — Дверной блок 5-го класса устойчивости к взлому с решетчатой дверью . 2 замка СИ600 (дверное полотно 898*1970), 1030х2100 мм по раме. ЛИСТ 13.
A367: МАТ.БРОНЯ.007 | B367: Дверной блок утепленый, полуторастворчатый размером по раме 2100Нх1400 мм (размер двери в свету 2000Нх1200 мм), полотна из листов металла 2+2 мм (наружный и внутренние листы). Рабочая створка-________, шириной 900 мм, на раб створке 2 замка: оба цили | E367: СПЕЦ Прожект групп | F367: шт. | G367: БРОНЯ | H367: 110250 | I367: RUB | J367: См. ТЗ "Двери запасного выхода" | M367: МАТ.БРОНЯ.007 — Дверной блок утепленый, полуторастворчатый размером по раме 2100Нх1400 мм (размер двери в свету 2000Нх1200 мм), полотна из листов металла 2+2 мм (наружный и внутренние листы). Рабочая створка-________, шириной 900 мм, на раб створке 2 замка: оба цили
A368: МАТ.БРОНЯ.008 | B368: Доводчик на рабочую створку NOTEDO DC-025-095 (со скользящим каналом). Доводчик на паразитную створку NOTEDO DC-070 (паук) | E368: СПЕЦ Прожект групп | F368: шт. | G368: БРОНЯ | H368: 8400 | I368: RUB | M368: МАТ.БРОНЯ.008 — Доводчик на рабочую створку NOTEDO DC-025-095 (со скользящим каналом). Доводчик на паразитную створку NOTEDO DC-070 (паук)
A369: МАТ.БРОНЯ.009 | B369: Панели защитные, стеновые V класс взломостойкости, сварное соединение, бетонно-заливная. Покраска грунт | E369: СПЕЦ Прожект групп | F369: м2 | G369: БРОНЯ | H369: 15750 | I369: RUB | M369: МАТ.БРОНЯ.009 — Панели защитные, стеновые V класс взломостойкости, сварное соединение, бетонно-заливная. Покраска грунт
A370: МАТ.БРОНЯ.010 | B370: Панели защитные, стеновые кл. Бр-2 по пулестойкости и II класс взломостойкости, болтовое соединение, облегченные, Покраска грунт | E370: СПЕЦ Прожект групп | F370: м2 | G370: БРОНЯ | H370: 15225 | I370: RUB | M370: МАТ.БРОНЯ.010 — Панели защитные, стеновые кл. Бр-2 по пулестойкости и II класс взломостойкости, болтовое соединение, облегченные, Покраска грунт
A371: МАТ.БРОНЯ.011 | B371: Панели защитные, стеновые кл. Бр-2 по пулестойкости и II класс взломостойкости, сварное соединение, облегченные, Покраска грунт | E371: СПЕЦ Прожект групп | F371: м2 | G371: БРОНЯ | H371: 14700 | I371: RUB | M371: МАТ.БРОНЯ.011 — Панели защитные, стеновые кл. Бр-2 по пулестойкости и II класс взломостойкости, сварное соединение, облегченные, Покраска грунт
A372: МАТ.БРОНЯ.012 | B372: Панели защитные, стеновые кл. Бр-3 по пулестойкости и III класс взломостойкости, болтовое соединение, облегченные, Покраска грунт | E372: СПЕЦ Прожект групп | F372: м2 | G372: БРОНЯ | H372: 18060 | I372: RUB | M372: МАТ.БРОНЯ.012 — Панели защитные, стеновые кл. Бр-3 по пулестойкости и III класс взломостойкости, болтовое соединение, облегченные, Покраска грунт
A373: МАТ.БРОНЯ.013 | B373: Панели защитные, стеновые кл. Бр-3 по пулестойкости и III класс взломостойкости, сварное соединение, облегченные, Покраска грунт | E373: СПЕЦ Прожект групп | F373: м2 | G373: БРОНЯ | H373: 17535 | I373: RUB | M373: МАТ.БРОНЯ.013 — Панели защитные, стеновые кл. Бр-3 по пулестойкости и III класс взломостойкости, сварное соединение, облегченные, Покраска грунт
A374: МАТ.БРОНЯ.014 | B374: Передаточный (подвижный, двухуровневый) лоток для передачи 5-ти банковских упаковок по 1000 листов Габаритные размеры 415х610х232 мм Ш*В*Д, внутри нижнего лотка 300х160х260 мм Ш*В*Д, внутри верхнего лотка 300х20-185 мм Ш*В*Д . Отделка лотка : лотковы | E374: СПЕЦ Прожект групп | F374: шт. | G374: БРОНЯ | H374: 39900 | I374: RUB | M374: МАТ.БРОНЯ.014 — Передаточный (подвижный, двухуровневый) лоток для передачи 5-ти банковских упаковок по 1000 листов Габаритные размеры 415х610х232 мм Ш*В*Д, внутри нижнего лотка 300х160х260 мм Ш*В*Д, внутри верхнего лотка 300х20-185 мм Ш*В*Д . Отделка лотка : лотковы
A375: МАТ.БРОНЯ.015 | B375: Противопожарный однопольный дверной блок , min EI60 с фурнитурой 1000х2100мм по раме | E375: СПЕЦ Прожект групп | F375: шт. | G375: БРОНЯ | H375: 110250 | I375: RUB | M375: МАТ.БРОНЯ.015 — Противопожарный однопольный дверной блок , min EI60 с фурнитурой 1000х2100мм по раме
A376: МАТ.БРОНЯ.016 | B376: Установка противопожарного однопольного дверного блока, min EI60 с фурнитурой 1200х2100мм | E376: СПЕЦ Прожект групп | F376: шт | G376: БРОНЯ | H376: 8000 | I376: RUB | M376: МАТ.БРОНЯ.016 — Установка противопожарного однопольного дверного блока, min EI60 с фурнитурой 1200х2100мм
A377: МАТ.БРОНЯ.017 | B377: Шлюз инкассаторский кл. Бр-2 по пулестойкости, механический со стеклом СЗМ-Бр3, габаритные размеры 750х540х615 мм, ВШхД. внутренние размеры 652х250х471 мм.Открывание кассира левое, инкассатора правое. Способ крепления - на монтажные уголки приваренны | E377: СПЕЦ Прожект групп | F377: шт. | G377: БРОНЯ | H377: 78120 | I377: RUB | M377: МАТ.БРОНЯ.017 — Шлюз инкассаторский кл. Бр-2 по пулестойкости, механический со стеклом СЗМ-Бр3, габаритные размеры 750х540х615 мм, ВШхД. внутренние размеры 652х250х471 мм.Открывание кассира левое, инкассатора правое. Способ крепления - на монтажные уголки приваренны
A378: МАТ.БРОНЯ.018 | B378: Шлюз инкассаторский кл. Бр-2 по пулестойкости, механический со стеклом, габаритные размеры 910х820х870 мм, ВШхД. внутренние размеры 710х670х750 мм. Открывание кассира левое, инкассатора правое. Порошковая окрас. RAL7047. ЛИСТ 6. | E378: СПЕЦ Прожект групп | F378: шт. | G378: БРОНЯ | H378: 102585 | I378: RUB | M378: МАТ.БРОНЯ.018 — Шлюз инкассаторский кл. Бр-2 по пулестойкости, механический со стеклом, габаритные размеры 910х820х870 мм, ВШхД. внутренние размеры 710х670х750 мм. Открывание кассира левое, инкассатора правое. Порошковая окрас. RAL7047. ЛИСТ 6.
A379: МАТ.БРОНЯ.019 | B379: Шлюз инкассаторский кл. Бр-3 по пулестойкости, механический со стеклом СЗМ-Бр3, габаритные размеры 750х540х615 мм, ВШхД. внутренние размеры 652х250х471 мм.Открывание кассира левое, инкассатора правое. Способ крепления - на монтажные уголки приваренны | E379: СПЕЦ Прожект групп | F379: шт. | G379: БРОНЯ | H379: 78750 | I379: RUB | M379: МАТ.БРОНЯ.019 — Шлюз инкассаторский кл. Бр-3 по пулестойкости, механический со стеклом СЗМ-Бр3, габаритные размеры 750х540х615 мм, ВШхД. внутренние размеры 652х250х471 мм.Открывание кассира левое, инкассатора правое. Способ крепления - на монтажные уголки приваренны
... A382: МАТ.БРОНЯ.022 | B382: Шлюз инкассаторский кл. Бр-3 по пулестойкости, электромеханический со стеклом СЗМ-Бр3, габаритные размеры 750х540х615 мм, ВШхД. внутренние размеры 652х250х471 мм.Открывание кассира левое, инкассатора правое. Способ крепления - на монтажные уголки при | E382: СПЕЦ Прожект групп | F382: шт. | G382: БРОНЯ | H382: 93450 | I382: RUB | M382: МАТ.БРОНЯ.022 — Шлюз инкассаторский кл. Бр-3 по пулестойкости, электромеханический со стеклом СЗМ-Бр3, габаритные размеры 750х540х615 мм, ВШхД. внутренние размеры 652х250х471 мм.Открывание кассира левое, инкассатора правое. Способ крепления - на монтажные уголки при
A383: МАТ.ДВ.001 | B383: Добор для F-наличника серый 7035 (5х100х2070мм) | D383: Kapelli | E383: Фабрика дверей KAPELLI | F383: шт | G383: ДВ | H383: 460 | I383: RUB | M383: МАТ.ДВ.001 — Добор для F-наличника серый 7035 (5х100х2070мм)
A384: МАТ.ДВ.002 | B384: Добор для F-наличника серый 7035 (5х150х2070мм) | D384: Kapelli | E384: Фабрика дверей KAPELLI | F384: шт | G384: ДВ | H384: 690 | I384: RUB | M384: МАТ.ДВ.002 — Добор для F-наличника серый 7035 (5х150х2070мм)
A385: МАТ.ДВ.003 | B385: Завертка WC | D385: Kapelli | E385: Фабрика дверей KAPELLI | F385: шт | G385: ДВ | H385: 270 | I385: RUB | M385: МАТ.ДВ.003 — Завертка WC
A386: МАТ.ДВ.004 | B386: Замок магнитный (под цилиндр / под фиксатор) | D386: Kapelli | E386: Фабрика дверей KAPELLI | F386: шт | G386: ДВ | H386: 390 | I386: RUB | M386: МАТ.ДВ.004 — Замок магнитный (под цилиндр / под фиксатор)
A387: МАТ.ДВ.005 | B387: Замок механический (под цилиндр / под фиксатор) | D387: Kapelli | E387: Фабрика дверей KAPELLI | F387: шт | G387: ДВ | H387: 410 | I387: RUB | M387: МАТ.ДВ.005 — Замок механический (под цилиндр / под фиксатор)
A388: МАТ.ДВ.006 | B388: Накладка под цилиндр | D388: Kapelli | E388: Фабрика дверей KAPELLI | F388: шт | G388: ДВ | H388: 121 | I388: RUB | M388: МАТ.ДВ.006 — Накладка под цилиндр
A389: МАТ.ДВ.007 | B389: Наличник F ПВХ 2,17м серый 7035 телескопический | D389: Kapelli | E389: Фабрика дверей KAPELLI | F389: шт | G389: ДВ | H389: 510 | I389: RUB | M389: МАТ.ДВ.007 — Наличник F ПВХ 2,17м серый 7035 телескопический
A390: МАТ.ДВ.008 | B390: Петля накладная | D390: Kapelli | E390: Фабрика дверей KAPELLI | F390: шт | G390: ДВ | H390: 75 | I390: RUB | M390: МАТ.ДВ.008 — Петля накладная
A391: МАТ.ДВ.009 | B391: Установка дверного доводчика штанга рычажная на входные двери (210 кг) | D391: ФАСАДСТРОЙ | E391: ФАСАДСТРОЙ | F391: шт. | G391: ДВ | H391: 5775 | I391: RUB | M391: МАТ.ДВ.009 — Установка дверного доводчика штанга рычажная на входные двери (210 кг)
A392: МАТ.ДВ.010 | B392: Цилиндр (клю-ключ) | D392: Kapelli | E392: Фабрика дверей KAPELLI | F392: шт | G392: ДВ | H392: 245 | I392: RUB | M392: МАТ.ДВ.010 — Цилиндр (клю-ключ)
A393: МАТ.ДВ.011 | B393: Цилиндр (ключ-фиксатор) | D393: Kapelli | E393: Фабрика дверей KAPELLI | F393: шт | G393: ДВ | H393: 276 | I393: RUB | M393: МАТ.ДВ.011 — Цилиндр (ключ-фиксатор)
A394: МАТ.ДВ.АЛ.001 | B394: двупольноый дверной блок (алюминиевый теплый профиль 3 петли, два врезных замка цилиндрического типа, имеющих с внутренней стороны запорные устройства типа «вертушок» без защелки , ручка из нержавеющей стали типа «труба» со смещением креплений диамет | D394: ФАСАДСТРОЙ | E394: ФАСАДСТРОЙ | F394: шт. | G394: ДВ.АЛ | H394: 89201.7 | I394: RUB | M394: МАТ.ДВ.АЛ.001 — двупольноый дверной блок (алюминиевый теплый профиль 3 петли, два врезных замка цилиндрического типа, имеющих с внутренней стороны запорные устройства типа «вертушок» без защелки , ручка из нержавеющей стали типа «труба» со смещением креплений диамет
... A403: МАТ.ДВ.ДЕР.004 | B403: ДГ 21-9 КАПЕЛЬ Гладкая МС7035 (полотно 2000*800, ДКТ80) УД | D403: Kapelli | E403: Фабрика дверей KAPELLI | F403: компл | G403: ДВ.ДЕР | H403: 11655 | I403: RUB | M403: МАТ.ДВ.ДЕР.004 — ДГ 21-9 КАПЕЛЬ Гладкая МС7035 (полотно 2000*800, ДКТ80) УД
A404: МАТ.ДВ.ДЕР.005 | B404: Дверь глухая в проем. Способ открывания: распашная. Число полотен: одностворчатая. Полотно со звукоизоляционным заполнением (62,5 мм). Отделка полотна - ЛДСП 16 мм. Цвет: EGGER. Алюминиевая кромка слева/справа/сверху полотна. Цвет: RAL 9005 муар. Кор | E404: Вертикальный транспорт | F404: шт | G404: ДВ.ДЕР | H404: 93350 | I404: RUB | M404: МАТ.ДВ.ДЕР.005 — Дверь глухая в проем. Способ открывания: распашная. Число полотен: одностворчатая. Полотно со звукоизоляционным заполнением (62,5 мм). Отделка полотна - ЛДСП 16 мм. Цвет: EGGER. Алюминиевая кромка слева/справа/сверху полотна. Цвет: RAL 9005 муар. Кор
A405: МАТ.ДВ.ДЕР.006 | B405: Дверь глухая в проем. Способ открывания: распашная. Число полотен: одностворчатая. Полотно со звукоизоляционным заполнением (63 мм), ламинированное. Цвет: Egger U999 ST19, направление: вертикальное. Алюминиевый профиль скрытой установки. Цвет: RAL 90 | E405: Вертикальный транспорт | F405: шт | G405: ДВ.ДЕР | H405: 88300 | I405: RUB | M405: МАТ.ДВ.ДЕР.006 — Дверь глухая в проем. Способ открывания: распашная. Число полотен: одностворчатая. Полотно со звукоизоляционным заполнением (63 мм), ламинированное. Цвет: Egger U999 ST19, направление: вертикальное. Алюминиевый профиль скрытой установки. Цвет: RAL 90
A406: МАТ.ДВ.СТ.001 | B406: Дверь светопрозрачная в алюминиевом профиле в перегородку, одностворчатая, размер по раме 2100х950мм. Остекление: двойное 4 мм закаленное, Pilkington. Алюминиевый профиль по периметру 72/93 мм. Коробка: алюминиевая торцевая. Ширина рабочей створки 90 | E406: Вертикальный транспорт | F406: шт | G406: ДВ.СТ | H406: 95950 | I406: RUB | M406: МАТ.ДВ.СТ.001 — Дверь светопрозрачная в алюминиевом профиле в перегородку, одностворчатая, размер по раме 2100х950мм. Остекление: двойное 4 мм закаленное, Pilkington. Алюминиевый профиль по периметру 72/93 мм. Коробка: алюминиевая торцевая. Ширина рабочей створки 90
A407: МАТ.ДВ.СТ.002 | B407: Дверь светопрозрачная в алюминиевом профиле в проем, полуторная, размер по раме 2130х1420мм. Остекление: двойное 4 мм закаленное. Алюминиевый профиль по периметру 71/93 мм. Коробка: алюминиевая телескопическая, наличник. Цвет: RAL 9005 муар. Добор: Л | E407: Вертикальный транспорт | F407: шт | G407: ДВ.СТ | H407: 161350 | I407: RUB | M407: МАТ.ДВ.СТ.002 — Дверь светопрозрачная в алюминиевом профиле в проем, полуторная, размер по раме 2130х1420мм. Остекление: двойное 4 мм закаленное. Алюминиевый профиль по периметру 71/93 мм. Коробка: алюминиевая телескопическая, наличник. Цвет: RAL 9005 муар. Добор: Л
A408: МАТ.ДВ.СТ.003 | B408: Стеклянный двупольный дверной блок 1800х2400 мм Стекло 10мм закалённое. Фурнитура цвета матовая нержавеющая сталь Dorma в Universal Light. Кромка стекла полированная. Доводчик Tinan N87D SSS с фиксацией 90* вар.№ 1 Запирающаяся ручка-скоба двусторонн | E408: Вертикальный транспорт | F408: шт. | G408: ДВ.СТ | H408: 106310.4 | I408: RUB | M408: МАТ.ДВ.СТ.003 — Стеклянный двупольный дверной блок 1800х2400 мм Стекло 10мм закалённое. Фурнитура цвета матовая нержавеющая сталь Dorma в Universal Light. Кромка стекла полированная. Доводчик Tinan N87D SSS с фиксацией 90* вар.№ 1 Запирающаяся ручка-скоба двусторонн
A409: МАТ.ДВ.СТ.004 | B409: Стеклянный однопольный дверной блок 900х2100 мм Стекло 10мм закалённое. Фурнитура цвета матовая нержавеющая сталь Dorma в Universal Light. Кромка стекла полированная. Доводчик Titan N87D SSS с фиксацией 90* вар.№ 1 Запирающаяся ручка-скоба двусторонн | E409: Вертикальный транспорт | F409: шт. | G409: ДВ.СТ | H409: 46510.8 | I409: RUB | M409: МАТ.ДВ.СТ.004 — Стеклянный однопольный дверной блок 900х2100 мм Стекло 10мм закалённое. Фурнитура цвета матовая нержавеющая сталь Dorma в Universal Light. Кромка стекла полированная. Доводчик Titan N87D SSS с фиксацией 90* вар.№ 1 Запирающаяся ручка-скоба двусторонн
A410: МАТ.ДВ.СТ.005 | B410: Стеклянный полуторапольный дверной блок 1400х2100 мм Стекло 10мм закалённое. Фурнитура цвета матовая нержавеющая сталь Dorma в Universal Light. Кромка стекла полированная. Доводчик Tinan N87D SSS с фиксацией 90* вар.№ 1 Запирающаяся ручка-скоба двуст | E410: Вертикальный транспорт | F410: шт. | G410: ДВ.СТ | H410: 72350.25 | I410: RUB | M410: МАТ.ДВ.СТ.005 — Стеклянный полуторапольный дверной блок 1400х2100 мм Стекло 10мм закалённое. Фурнитура цвета матовая нержавеющая сталь Dorma в Universal Light. Кромка стекла полированная. Доводчик Tinan N87D SSS с фиксацией 90* вар.№ 1 Запирающаяся ручка-скоба двуст
A411: МАТ.ЗАВЕСА.001 | B411: Компактная воздушно-тепловая завеса КЭВ-12П3042E | C411: 123040 | D411: Тепломаш | E411: Тепломаш | F411: шт | G411: ЗАВЕСА | H411: 49888.13 | I411: RUB | M411: МАТ.ЗАВЕСА.001 — Компактная воздушно-тепловая завеса КЭВ-12П3042E
A412: МАТ.ЗАВЕСА.002 | B412: Компактная воздушно-тепловая завеса КЭВ-3П1154Е | C412: 121021 | D412: Тепломаш | E412: Тепломаш | F412: шт | G412: ЗАВЕСА | H412: 12056.63 | I412: RUB | M412: МАТ.ЗАВЕСА.002 — Компактная воздушно-тепловая завеса КЭВ-3П1154Е
A413: МАТ.ЗАВЕСА.003 | B413: Компактная воздушно-тепловая завеса КЭВ-6П2212E | C413: 122002 | D413: Тепломаш | E413: Тепломаш | F413: шт | G413: ЗАВЕСА | H413: 25452 | I413: RUB | M413: МАТ.ЗАВЕСА.003 — Компактная воздушно-тепловая завеса КЭВ-6П2212E
A414: МАТ.ЗАВЕСА.004 | B414: Компактная воздушно-тепловая завеса КЭВ-9П3012E | C414: 123037 | D414: Тепломаш | E414: Тепломаш | F414: шт | G414: ЗАВЕСА | H414: 44730 | I414: RUB | M414: МАТ.ЗАВЕСА.004 — Компактная воздушно-тепловая завеса КЭВ-9П3012E
A415: МАТ.ЛЮЧОК.001 | B415: Лючок напольный SEG-Lux 250x250x100мм на 16 модуля арт. ALFB16M с розетками 2К+3 красного(Legrand Mozaic 077218) 4 шт. и белого(Legrand Mozaic 077211) 2 шт. цвета | C415: ALFB16M | D415: SEG-Lux | E415: РусТрэйд | F415: шт | G415: ЛЮЧОК | H415: 9303.87 | I415: RUB | M415: МАТ.ЛЮЧОК.001 — Лючок напольный SEG-Lux 250x250x100мм на 16 модуля арт. ALFB16M с розетками 2К+3 красного(Legrand Mozaic 077218) 4 шт. и белого(Legrand Mozaic 077211) 2 шт. цвета
...

Sheet Группы
A1: ГРУППЫ МАТЕРИАЛОВ — что означают коды
A2: У работы стоит код группы, у материала — тот же код. Список материала в «Сборке» показывает только материалы группы выбранной работы. Пустая группа = чистая работа.
A4: Код группы | B4: Наименование | C4: Область | D4: Что входит | E4: Пример операции
A5: VRF.ВНУТ | B5: Внутренние блоки VRF / мультисплит | C5: Кондиционирование | D5: Внутренние блоки мультизональных систем + пульты, декоративные панели | E5: Монтаж внутреннего блока VRF / мультисплит
A6: VRF.НАР | B6: Наружные блоки VRF / ККБ | C6: Кондиционирование | D6: Наружные блоки мультизональных систем, компрессорно-конденсаторные блоки | E6: Монтаж наружного блока / ККБ
A7: АРМ.ОВ | B7: Арматура и фасонные части ВК / отопления | C7: Отопление / ВК | D7: Краны шаровые, вентили, фильтры, обратные клапаны, балансировочные клапаны, фланцы, отводы, гильзы | E7: Монтаж арматуры и фасонных частей (ВК / отопление)
A8: АРМ.УКР | B8: Арматура для укрепления конструкций | C8: Безопасность (ККО) | D8: Армосетка / пруток по классу взломостойкости, анкерный крепёж | E8: Укрепление конструкций арматурой
A9: БРОНЯ | B9: Элементы технической укреплённости | C9: Безопасность (ККО) | D9: Бронестекло, бронепанели, передаточные лотки, шлюзы инкассаторские, переговорные устройства | E9: Монтаж элемента технической укреплённости (броня)
A10: ВЕНТ | B10: Вентиляторы | C10: Вентиляция | D10: Вентиляторы канальные, крышные, осевые, вытяжные бытовые; с регуляторами | E10: Монтаж вентилятора
A11: ВОЗД | B11: Воздуховоды и фасонные части | C11: Вентиляция | D11: Воздуховоды круглые и прямоугольные, отводы, переходы, врезки, гибкие воздуховоды, изоляция | E11: Монтаж воздуховода
A12: ВР | B12: Воздухораспределители | C12: Вентиляция | D12: Решётки приточные и вытяжные, диффузоры, анемостаты, регуляторы расхода | E12: Монтаж воздухораспределителя (решётка / диффузор)
A13: ГКЛ | B13: Комплект ГКЛ — перегородки и облицовки | C13: Отделка стен | D13: ГКЛ / ГКЛВ / ГКЛО, профиль, крепёж, лента, серпянка | E13: Устройство перегородки / облицовки из ГКЛ
A14: ДВ | B14: Дверные блоки (общая группа) и дверные приборы | C14: Двери | D14: Дверные блоки без чёткого подтипа, доводчики, упоры, ручки, замки | E14: Монтаж дверного блока / дверных приборов
A15: ДВ.АЛ | B15: Двери алюминиевые | C15: Двери | D15: Дверные блоки в алюминиевом тёплом/холодном профиле, с заполнением | E15: Монтаж дверного блока алюминиевого
... A64: ЭЩ | B64: Щиты, боксы, шкафы распределительные | C64: Электрика | D64: ГРЩ, этажные и групповые щиты, ППУ, боксы модульные, шкафы распределительные (корпус + начинка) | E64: Монтаж щита / бокса

Sheet Документация
A1: Вид | B1: Раздел проекта | C1: База расчёта | D1: Ед | E1: Цена ЕР, ₽ | F1: Ключ (текст выбора) | G1: Наименование для сметы
A2: РД | B2: КР — усиление/устройство несущих конструкций | C2: за м² · объект 100–450 м² | D2: м2 | E2: 135.45 | F2: РД · КР — усиление/устройство несущих конструкций · за м² · объект 100–450 м² | G2: Рабочая документация: КР — усиление/устройство несущих конструкций (за м² · объект 100–450 м²)
A3: РД | B3: КР — усиление/устройство несущих конструкций | C3: комплексом · объект < 100 м² | D3: компл. | E3: 10500 | F3: РД · КР — усиление/устройство несущих конструкций · комплексом · объект < 100 м² | G3: Рабочая документация: КР — усиление/устройство несущих конструкций (комплексом · объект < 100 м²)
A4: РД | B4: АР — архитектурные решения | C4: за м² · объект 100–450 м² | D4: м2 | E4: 389.55 | F4: РД · АР — архитектурные решения · за м² · объект 100–450 м² | G4: Рабочая документация: АР — архитектурные решения (за м² · объект 100–450 м²)
A5: РД | B5: АР — архитектурные решения | C5: комплексом · объект < 100 м² | D5: компл. | E5: 20737.5 | F5: РД · АР — архитектурные решения · комплексом · объект < 100 м² | G5: Рабочая документация: АР — архитектурные решения (комплексом · объект < 100 м²)
A6: РД | B6: ЭОМ — электроснабжение и электроосвещение | C6: за м² · объект 100–450 м² | D6: м2 | E6: 258.3 | F6: РД · ЭОМ — электроснабжение и электроосвещение · за м² · объект 100–450 м² | G6: Рабочая документация: ЭОМ — электроснабжение и электроосвещение (за м² · объект 100–450 м²)
A7: РД | B7: ЭОМ — электроснабжение и электроосвещение | C7: комплексом · объект < 100 м² | D7: компл. | E7: 20737.5 | F7: РД · ЭОМ — электроснабжение и электроосвещение · комплексом · объект < 100 м² | G7: Рабочая документация: ЭОМ — электроснабжение и электроосвещение (комплексом · объект < 100 м²)
A8: РД | B8: ОВиК-В — вентиляция | C8: за м² · объект 100–450 м² | D8: м2 | E8: 202.65 | F8: РД · ОВиК-В — вентиляция · за м² · объект 100–450 м² | G8: Рабочая документация: ОВиК-В — вентиляция (за м² · объект 100–450 м²)
A9: РД | B9: ОВиК-В — вентиляция | C9: комплексом · объект < 100 м² | D9: компл. | E9: 15592.5 | F9: РД · ОВиК-В — вентиляция · комплексом · объект < 100 м² | G9: Рабочая документация: ОВиК-В — вентиляция (комплексом · объект < 100 м²)
A10: РД | B10: ОВиК-К — кондиционирование | C10: за м² · объект 100–450 м² | D10: м2 | E10: 159.48 | F10: РД · ОВиК-К — кондиционирование · за м² · объект 100–450 м² | G10: Рабочая документация: ОВиК-К — кондиционирование (за м² · объект 100–450 м²)
A11: РД | B11: ОВиК-К — кондиционирование | C11: комплексом · объект < 100 м² | D11: компл. | E11: 10395 | F11: РД · ОВиК-К — кондиционирование · комплексом · объект < 100 м² | G11: Рабочая документация: ОВиК-К — кондиционирование (комплексом · объект < 100 м²)
A12: РД | B12: ОВиК-О — отопление | C12: за м² · объект 100–450 м² | D12: м2 | E12: 123.9 | F12: РД · ОВиК-О — отопление · за м² · объект 100–450 м² | G12: Рабочая документация: ОВиК-О — отопление (за м² · объект 100–450 м²)
A13: РД | B13: ОВиК-О — отопление | C13: комплексом · объект < 100 м² | D13: компл. | E13: 10395 | F13: РД · ОВиК-О — отопление · комплексом · объект < 100 м² | G13: Рабочая документация: ОВиК-О — отопление (комплексом · объект < 100 м²)
... A57: ИД | B57: ДУ — дымоудаление | C57: комплексом · объект < 100 м² | D57: компл. | E57: 1559.25 | F57: ИД · ДУ — дымоудаление · комплексом · объект < 100 м² | G57: Исполнительная документация: ДУ — дымоудаление (комплексом · объект < 100 м²)
